{
  "type": "Feature",
  "properties": {
    "addr:full":"16697 Bruhl Rd Folsom LA 70437",
    "addr:housenumber":"16697",
    "addr:postcode":"70437",
    "addr:street":"Bruhl Rd",
    "iso:country":"US",
    "sg:address":"16697 Bruhl Rd",
    "sg:city":"Folsom",
    "sg:classifiers":[
        {
            "category":"Building & Trades",
            "subcategory":"Plumbing",
            "type":"Services"
        }
    ],
    "sg:phone":"+1 985 807 4279",
    "sg:postcode":"70437",
    "sg:province":"LA",
    "sg:tags":[
        "septic"
    ],
    "wof:name":"Gary's Septic Tank & Backhoe",
    "wof:placetype":"venue"
},
  "geometry": {"coordinates":[-90.13503,30.586448],"type":"Point"}
}