{
  "type": "Feature",
  "properties": {
    "iso:country":"US",
    "sg:address":"2222 E Bert Kouns Industrial Loop",
    "sg:city":"Shreveport",
    "sg:classifiers":[
        {
            "category":"Social Services",
            "subcategory":"Adult Care",
            "type":"Services"
        },
        {
            "category":"Health Services",
            "subcategory":"Nursing And Care Facility",
            "type":"Services"
        }
    ],
    "sg:phone":"+1 318 524 3300",
    "sg:postcode":"71105",
    "sg:province":"LA",
    "sg:tags":[
        "home",
        "retirement",
        "community",
        "residential"
    ],
    "wof:name":"Waterford At Shreveport",
    "wof:placetype":"venue"
},
  "geometry": {"coordinates":[-93.703413,32.442822],"type":"Point"}
}