{
  "type": "Feature",
  "properties": {
    "addr:full":"648 Corporate Dr Houma LA 70360",
    "addr:housenumber":"648",
    "addr:postcode":"70360",
    "addr:street":"Corporate Dr",
    "iso:country":"US",
    "sg:address":"648 Corporate Dr",
    "sg:city":"Houma",
    "sg:classifiers":[
        {
            "category":"Shopping",
            "subcategory":"Books",
            "type":"Retail Goods"
        }
    ],
    "sg:phone":"+1 985 876 1283",
    "sg:postcode":"70360",
    "sg:province":"LA",
    "sg:tags":[
        "dealer"
    ],
    "wof:name":"God's Promises Books & Gifts",
    "wof:placetype":"venue"
},
  "geometry": {"coordinates":[-90.757476,29.608957],"type":"Point"}
}