{
  "type": "Feature",
  "properties": {
    "iso:country":"US",
    "sg:address":"901 Derbigny St",
    "sg:city":"Gretna",
    "sg:classifiers":[
        {
            "category":"Professional",
            "subcategory":"Lawyer & Legal Services",
            "type":"Services"
        }
    ],
    "sg:phone":"+1 504 362 9961",
    "sg:postcode":"70053",
    "sg:province":"LA",
    "sg:tags":[
        "attorney"
    ],
    "wof:name":"Melvin Ripp",
    "wof:placetype":"venue"
},
  "geometry": {"coordinates":[-90.062866,29.909816],"type":"Point"}
}