{
  "type": "Feature",
  "properties": {
    "iso:country":"US",
    "sg:address":"132 Broad St",
    "sg:city":"Lake Charles",
    "sg:classifiers":[
        {
            "category":"Professional",
            "subcategory":"Management & Consulting",
            "type":"Services"
        }
    ],
    "sg:phone":"+1 337 436 2434",
    "sg:postcode":"70601",
    "sg:province":"LA",
    "sg:tags":[
        "food"
    ],
    "wof:name":"W & R Food Svc",
    "wof:placetype":"venue"
},
  "geometry": {"coordinates":[-93.217348,30.229401],"type":"Point"}
}