{
  "type": "Feature",
  "properties": {
    "addr:full":"4010 W Lakeshore Dr Baton Rouge LA 70808",
    "addr:housenumber":"4010",
    "addr:postcode":"70808",
    "addr:street":"W Lakeshore Dr",
    "iso:country":"US",
    "sg:address":"4010 W Lakeshore Dr",
    "sg:city":"Baton Rouge",
    "sg:classifiers":[
        {
            "category":"Organizations",
            "subcategory":"Community Association",
            "type":"Services"
        }
    ],
    "sg:phone":"+1 225 344 7511",
    "sg:postcode":"70808",
    "sg:province":"LA",
    "sg:tags":[
        "club"
    ],
    "wof:name":"Zeta Tau Alpha Sorority",
    "wof:placetype":"venue"
},
  "geometry": {"coordinates":[-91.17029599999999,30.408956],"type":"Point"}
}