{
  "type": "Feature",
  "properties": {
    "iso:country":"US",
    "sg:address":"1313 Monroe St",
    "sg:city":"Mandeville",
    "sg:classifiers":[
        {
            "category":"Real Estate",
            "subcategory":"Real Estate Agent",
            "type":"Services"
        }
    ],
    "sg:phone":"+1 985 674 0326",
    "sg:postcode":"70448",
    "sg:province":"LA",
    "wof:name":"Sleeping Millionaire LLC",
    "wof:placetype":"venue"
},
  "geometry": {"coordinates":[-90.054962,30.353112],"type":"Point"}
}