{
  "type": "Feature",
  "properties": {
    "addr:full":"15618 Greenwell Springs Rd Greenwell Spgs LA 70739",
    "addr:housenumber":"15618",
    "addr:postcode":"70739",
    "addr:street":"Greenwell Springs Rd;Spgs",
    "iso:country":"US",
    "sg:address":"15618 Greenwell Springs Rd",
    "sg:city":"Greenwell Spgs",
    "sg:classifiers":[
        {
            "category":"Farming",
            "subcategory":"Livestock Farm",
            "type":"Manufacturing & Wholesale Goods"
        }
    ],
    "sg:phone":"+1 225 262 1510",
    "sg:postcode":"70739",
    "sg:province":"LA",
    "sg:tags":[
        "feeding"
    ],
    "wof:name":"Swift Horse General Store",
    "wof:placetype":"venue"
},
  "geometry": {"coordinates":[-91.017377,30.517804],"type":"Point"}
}