{
  "type": "Feature",
  "properties": {
    "addr:full":"1112 Sulphur Ave Westlake LA 70669",
    "addr:housenumber":"1112",
    "addr:postcode":"70669",
    "addr:street":"Sulphur Ave",
    "iso:country":"US",
    "sg:address":"1112 Sulphur Ave",
    "sg:city":"Westlake",
    "sg:classifiers":[
        {
            "category":"Building & Trades",
            "subcategory":"Construction",
            "type":"Services"
        }
    ],
    "sg:phone":"+1 337 433 2963",
    "sg:postcode":"70669",
    "sg:province":"LA",
    "sg:tags":[
        "general",
        "contractor"
    ],
    "wof:name":"Cypress General Contractors",
    "wof:placetype":"venue"
},
  "geometry": {"coordinates":[-93.260336,30.242408],"type":"Point"}
}