{
  "type": "Feature",
  "properties": {
    "addr:full":"221 Gunther Ln Belle Chasse LA 70037",
    "addr:housenumber":"221",
    "addr:postcode":"70037",
    "addr:street":"Gunther Ln",
    "iso:country":"US",
    "sg:address":"221 Gunther Ln",
    "sg:city":"Belle Chasse",
    "sg:classifiers":[
        {
            "category":"Professional",
            "subcategory":"Business Services",
            "type":"Services"
        }
    ],
    "sg:phone":"+1 504 392 3700",
    "sg:postcode":"70037",
    "sg:province":"LA",
    "sg:tags":[
        "diver"
    ],
    "sg:website":"www.superiordiving.com",
    "wof:name":"Superior Diving Co Inc",
    "wof:placetype":"venue"
},
  "geometry": {"coordinates":[-90.051715,29.8358],"type":"Point"}
}