{
  "type": "Feature",
  "properties": {
    "addr:full":"1644 Plaza Dr Marrero LA 70072",
    "addr:housenumber":"1644",
    "addr:postcode":"70072",
    "addr:street":"Plaza Dr Marrero",
    "iso:country":"US",
    "sg:address":"1644 Plaza Dr",
    "sg:city":"Marrero",
    "sg:classifiers":[
        {
            "category":"Building & Trades",
            "subcategory":"Construction",
            "type":"Services"
        }
    ],
    "sg:phone":"+1 504 341 8874",
    "sg:postcode":"70072",
    "sg:province":"LA",
    "sg:tags":[
        "fence",
        "contractor"
    ],
    "wof:name":"Quality Fence",
    "wof:placetype":"venue"
},
  "geometry": {"coordinates":[-90.116303,29.884714],"type":"Point"}
}