{
  "type": "Feature",
  "properties": {
    "addr:full":"165 N 6th St Ponchatoula LA 70454",
    "addr:housenumber":"165",
    "addr:postcode":"70454",
    "addr:street":"N 6Th St",
    "iso:country":"US",
    "sg:address":"165 N 6th St",
    "sg:city":"Ponchatoula",
    "sg:classifiers":[
        {
            "category":"Freight",
            "type":"Transportation"
        }
    ],
    "sg:phone":"+1 985 370 7900",
    "sg:postcode":"70454",
    "sg:province":"LA",
    "sg:tags":[
        "trucking"
    ],
    "wof:name":"Citation Investments Inc",
    "wof:placetype":"venue"
},
  "geometry": {"coordinates":[-90.44319400000001,30.438873],"type":"Point"}
}