{
  "type": "Feature",
  "properties": {
    "iso:country":"US",
    "sg:address":"826 Perdido St",
    "sg:city":"New Orleans",
    "sg:classifiers":[
        {
            "category":"Professional",
            "type":"Services"
        }
    ],
    "sg:phone":"+1 504 587 9099",
    "sg:postcode":"70112",
    "sg:province":"LA",
    "sg:tags":[
        "establishment"
    ],
    "wof:name":"Bowne Management Systems",
    "wof:placetype":"venue"
},
  "geometry": {"coordinates":[-90.071753,29.950852],"type":"Point"}
}