{
  "type": "Feature",
  "properties": {
    "iso:country":"US",
    "sg:address":"501 Edgewood Dr",
    "sg:city":"Pineville",
    "sg:classifiers":[
        {
            "category":"Education",
            "subcategory":"School",
            "type":"Public Place"
        }
    ],
    "sg:phone":"+1 318 640 0512",
    "sg:postcode":"71360",
    "sg:province":"LA",
    "wof:name":"Pineville Junior High School",
    "wof:placetype":"venue"
},
  "geometry": {"coordinates":[-92.400723,31.344477],"type":"Point"}
}