{
  "type": "Feature",
  "properties": {
    "addr:full":"1414 Belair Blvd Slidell LA 70460",
    "addr:housenumber":"1414",
    "addr:postcode":"70460",
    "addr:street":"Belair Blvd",
    "iso:country":"US",
    "sg:address":"1414 Belair Blvd",
    "sg:city":"Slidell",
    "sg:classifiers":[
        {
            "category":"Building & Trades",
            "subcategory":"Construction",
            "type":"Services"
        }
    ],
    "sg:phone":"+1 985 781 0856",
    "sg:postcode":"70460",
    "sg:province":"LA",
    "sg:tags":[
        "restoration",
        "cleaning",
        "patio",
        "deck"
    ],
    "wof:name":"Absolute Pressure Washing",
    "wof:placetype":"venue"
},
  "geometry": {"coordinates":[-89.838493,30.33646],"type":"Point"}
}