{
  "type": "Feature",
  "properties": {
    "addr:full":"301 Aimee Dr Carencro LA 70520",
    "addr:housenumber":"301",
    "addr:postcode":"70520",
    "addr:street":"Aimee Dr",
    "iso:country":"US",
    "sg:address":"301 Aimee Dr",
    "sg:city":"Carencro",
    "sg:classifiers":[
        {
            "category":"Social Services",
            "subcategory":"Child Care",
            "type":"Services"
        }
    ],
    "sg:phone":"+1 337 896 3265",
    "sg:postcode":"70520",
    "sg:province":"LA",
    "sg:tags":[
        "elementary",
        "school"
    ],
    "wof:name":"Hollie Hobby Day Care Center",
    "wof:placetype":"venue"
},
  "geometry": {"coordinates":[-92.043999,30.312099],"type":"Point"}
}