{
  "type": "Feature",
  "properties": {
    "iso:country":"US",
    "sg:address":"1011 N Causeway Blvd",
    "sg:city":"Mandeville",
    "sg:classifiers":[
        {
            "category":"Banks & Credit Unions",
            "subcategory":"Bank",
            "type":"Services"
        }
    ],
    "sg:phone":"+1 985 727 3034",
    "sg:postcode":"70471",
    "sg:province":"LA",
    "sg:tags":[
        "loan",
        "real estate"
    ],
    "wof:name":"Prime Source Mortgage",
    "wof:placetype":"venue"
},
  "geometry": {"coordinates":[-90.090924,30.380479],"type":"Point"}
}