{
  "type": "Feature",
  "properties": {
    "iso:country":"US",
    "sg:address":"2608 State Rte 14",
    "sg:city":"Lake Charles",
    "sg:classifiers":[
        {
            "category":"Retail",
            "subcategory":"Car Wash",
            "type":"Services"
        }
    ],
    "sg:phone":"+1 337 479 0630",
    "sg:postcode":"70607",
    "sg:province":"LA",
    "sg:tags":[
        "polishing",
        "washing"
    ],
    "wof:name":"Lake Charles Spray & Wash",
    "wof:placetype":"venue"
},
  "geometry": {"coordinates":[-93.173698,30.158078],"type":"Point"}
}