{
  "type": "Feature",
  "properties": {
    "iso:country":"US",
    "sg:address":"3609 Cameron St",
    "sg:city":"Lafayette",
    "sg:classifiers":[
        {
            "category":"Banks & Credit Unions",
            "subcategory":"Bank",
            "type":"Services"
        }
    ],
    "sg:phone":"+1 337 289 0818",
    "sg:postcode":"70506",
    "sg:province":"LA",
    "sg:tags":[
        "loan"
    ],
    "wof:name":"Coach's Payday Loan",
    "wof:placetype":"venue"
},
  "geometry": {"coordinates":[-92.058819,30.23251],"type":"Point"}
}