{
  "type": "Feature",
  "properties": {
    "addr:full":"16055 Chickamauga Ave Baton Rouge LA 70817",
    "addr:housenumber":"16055",
    "addr:postcode":"70817",
    "addr:street":"Chickamauga Ave",
    "iso:country":"US",
    "sg:address":"16055 Chickamauga Ave",
    "sg:city":"Baton Rouge",
    "sg:classifiers":[
        {
            "category":"Real Estate",
            "subcategory":"Real Estate Agent",
            "type":"Services"
        }
    ],
    "sg:phone":"+1 225 752 8458",
    "sg:postcode":"70817",
    "sg:province":"LA",
    "wof:name":"RSD Realty",
    "wof:placetype":"venue"
},
  "geometry": {"coordinates":[-91.004335,30.3993],"type":"Point"}
}