{
  "type": "Feature",
  "properties": {
    "addr:full":"123 Washington St St Martinville LA 70582",
    "addr:housenumber":"123",
    "addr:postcode":"70582",
    "addr:street":"Washington St St",
    "iso:country":"US",
    "sg:address":"123 Washington St",
    "sg:city":"St Martinville",
    "sg:classifiers":[
        {
            "category":"Organizations",
            "subcategory":"Non-profit Organization",
            "type":"Services"
        }
    ],
    "sg:phone":"+1 337 394 8515",
    "sg:postcode":"70582",
    "sg:province":"LA",
    "sg:tags":[
        "info",
        "addiction",
        "abuse",
        "treatment",
        "drug"
    ],
    "wof:name":"CDJ Consultation",
    "wof:placetype":"venue"
},
  "geometry": {"coordinates":[-91.830051,30.123911],"type":"Point"}
}