{
  "type": "Feature",
  "properties": {
    "iso:country":"US",
    "sg:address":"1518 Doctors Dr",
    "sg:city":"Bossier City",
    "sg:classifiers":[
        {
            "category":"Health Services",
            "subcategory":"Doctor",
            "type":"Services"
        }
    ],
    "sg:phone":"+1 318 746 1094",
    "sg:postcode":"71111",
    "sg:province":"LA",
    "sg:tags":[
        "physician",
        "surgeon"
    ],
    "wof:name":"Boyd Family Practice",
    "wof:placetype":"venue"
},
  "geometry": {"coordinates":[-93.71019699999999,32.536152],"type":"Point"}
}