{
  "type": "Feature",
  "properties": {
    "iso:country":"US",
    "sg:address":"14358 Lilac St",
    "sg:city":"Baton Rouge",
    "sg:classifiers":[
        {
            "category":"Personal",
            "type":"Services"
        }
    ],
    "sg:phone":"+1 225 274 3823",
    "sg:postcode":"70819",
    "sg:province":"LA",
    "sg:tags":[
        "hair",
        "replacement"
    ],
    "wof:name":"P H Group Of Louisiana Inc",
    "wof:placetype":"venue"
},
  "geometry": {"coordinates":[-91.02565,30.46175],"type":"Point"}
}