{
  "type": "Feature",
  "properties": {
    "addr:full":"1515 Pauger St New Orleans LA 70116",
    "addr:housenumber":"1515",
    "addr:postcode":"70116",
    "addr:street":"Pauger St",
    "iso:country":"US",
    "sg:address":"1515 Pauger St",
    "sg:city":"New Orleans",
    "sg:classifiers":[
        {
            "category":"Museum",
            "type":"Entertainment"
        }
    ],
    "sg:phone":"+1 504 947 7673",
    "sg:postcode":"70116",
    "sg:province":"LA",
    "wof:name":"Musee Rochon-Don Richmond",
    "wof:placetype":"venue"
},
  "geometry": {"coordinates":[-90.060303,29.965799],"type":"Point"}
}