{
  "type": "Feature",
  "properties": {
    "iso:country":"US",
    "sg:address":"4545 Veterans Memorial Blvd",
    "sg:city":"Metairie",
    "sg:classifiers":[
        {
            "category":"Freight",
            "type":"Transportation"
        }
    ],
    "sg:phone":"+1 504 455 2245",
    "sg:postcode":"70006",
    "sg:province":"LA",
    "sg:tags":[
        "commercial",
        "storage"
    ],
    "wof:name":"Horizon Self Storage & Vault",
    "wof:placetype":"venue"
},
  "geometry": {"coordinates":[-90.18436699999999,30.005411],"type":"Point"}
}