{
  "type": "Feature",
  "properties": {
    "addr:full":"2208 Ormond Blvd Destrehan LA 70047",
    "addr:housenumber":"2208",
    "addr:postcode":"70047",
    "addr:street":"Ormond Blvd Destrehan",
    "iso:country":"US",
    "sg:address":"2208 Ormond Blvd",
    "sg:city":"Destrehan",
    "sg:classifiers":[
        {
            "category":"Marine",
            "type":"Transportation"
        }
    ],
    "sg:phone":"+1 985 764 1723",
    "sg:postcode":"70047",
    "sg:province":"LA",
    "sg:tags":[
        "towing"
    ],
    "wof:name":"Johnson Marine Svc",
    "wof:placetype":"venue"
},
  "geometry": {"coordinates":[-90.364986,29.974555],"type":"Point"}
}