{
  "type": "Feature",
  "properties": {
    "addr:full":"524 Main Project Rd Schriever LA 70395",
    "addr:housenumber":"524",
    "addr:postcode":"70395",
    "addr:street":"Project Rd",
    "iso:country":"US",
    "sg:address":"524 Main Project Rd",
    "sg:city":"Schriever",
    "sg:classifiers":[
        {
            "category":"Professional",
            "subcategory":"Management & Consulting",
            "type":"Services"
        }
    ],
    "sg:phone":"+1 985 447 7739",
    "sg:postcode":"70395",
    "sg:province":"LA",
    "sg:tags":[
        "business"
    ],
    "wof:name":"E R Consultant Services",
    "wof:placetype":"venue"
},
  "geometry": {"coordinates":[-90.81841900000001,29.725653],"type":"Point"}
}