{
  "type": "Feature",
  "properties": {
    "iso:country":"US",
    "sg:address":"306 Church St",
    "sg:city":"Logansport",
    "sg:classifiers":[
        {
            "category":"Organizations",
            "subcategory":"Religious Organization",
            "type":"Services"
        }
    ],
    "sg:phone":"+1 318 697 5229",
    "sg:postcode":"71064",
    "sg:province":"LA",
    "sg:tags":[
        "church"
    ],
    "wof:name":"Saint Luke Baptist Church",
    "wof:placetype":"venue"
},
  "geometry": {"coordinates":[-93.69929,32.902644],"type":"Point"}
}