{
  "type": "Feature",
  "properties": {
    "iso:country":"US",
    "sg:address":"2418 Powers St",
    "sg:city":"Opelousas",
    "sg:classifiers":[
        {
            "category":"Restaurant",
            "type":"Food & Drink"
        }
    ],
    "sg:phone":"+1 337 594 8794",
    "sg:postcode":"70570",
    "sg:province":"LA",
    "sg:tags":[
        "caterer"
    ],
    "wof:name":"John L Soileau Inc",
    "wof:placetype":"venue"
},
  "geometry": {"coordinates":[-92.11224,30.547445],"type":"Point"}
}