{
  "type": "Feature",
  "properties": {
    "iso:country":"US",
    "sg:address":"10641 Hillary Ct",
    "sg:city":"Baton Rouge",
    "sg:classifiers":[
        {
            "category":"Professional",
            "subcategory":"Lawyer & Legal Services",
            "type":"Services"
        }
    ],
    "sg:phone":"+1 225 819 9673",
    "sg:postcode":"70810",
    "sg:province":"LA",
    "sg:tags":[
        "attorney"
    ],
    "wof:name":"Leo J D'Aubin",
    "wof:placetype":"venue"
},
  "geometry": {"coordinates":[-91.103921,30.365079],"type":"Point"}
}