{
  "type": "Feature",
  "properties": {
    "iso:country":"US",
    "sg:address":"5252 Mancuso Ln",
    "sg:city":"Baton Rouge",
    "sg:classifiers":[
        {
            "category":"Freight",
            "type":"Transportation"
        }
    ],
    "sg:phone":"+1 225 767 0063",
    "sg:postcode":"70809",
    "sg:province":"LA",
    "sg:tags":[
        "commercial",
        "storage"
    ],
    "wof:name":"Climastor",
    "wof:placetype":"venue"
},
  "geometry": {"coordinates":[-91.10110299999999,30.398508],"type":"Point"}
}