{
  "type": "Feature",
  "properties": {
    "addr:full":"540 9th St Gretna LA 70053",
    "addr:housenumber":"540",
    "addr:postcode":"70053",
    "addr:street":"9Th St",
    "iso:country":"US",
    "sg:address":"540 9th St",
    "sg:city":"Gretna",
    "sg:classifiers":[
        {
            "category":"Building & Trades",
            "subcategory":"Plumbing",
            "type":"Services"
        }
    ],
    "sg:phone":"+1 504 366 9548",
    "sg:postcode":"70053",
    "sg:province":"LA",
    "sg:tags":[
        "conditioning",
        "air",
        "system",
        "contractor"
    ],
    "wof:name":"Fred's Air Conditioning",
    "wof:placetype":"venue"
},
  "geometry": {"coordinates":[-90.060186,29.912559],"type":"Point"}
}