{
  "type": "Feature",
  "properties": {
    "iso:country":"US",
    "sg:address":"1531 N Claiborne Ave",
    "sg:city":"New Orleans",
    "sg:classifiers":[
        {
            "category":"Health Services",
            "subcategory":"Doctor",
            "type":"Services"
        }
    ],
    "sg:phone":"+1 504 944 0170",
    "sg:postcode":"70116",
    "sg:province":"LA",
    "sg:tags":[
        "dentist"
    ],
    "wof:name":"Smiles Family Dentistry",
    "wof:placetype":"venue"
},
  "geometry": {"coordinates":[-90.06707,29.971392],"type":"Point"}
}