{
  "type": "Feature",
  "properties": {
    "addr:full":"1100 Hwy 662 Morgan City LA 70380",
    "addr:housenumber":"1100",
    "addr:postcode":"70380",
    "addr:street":"Hwy 662 Morgan",
    "iso:country":"US",
    "sg:address":"1100 Hwy 662",
    "sg:city":"Morgan City",
    "sg:classifiers":[
        {
            "category":"Food & Beverages",
            "subcategory":"Groceries & Convenience Stores",
            "type":"Retail Goods"
        }
    ],
    "sg:phone":"+1 985 631 0849",
    "sg:postcode":"70380",
    "sg:province":"LA",
    "sg:tags":[
        "grocer"
    ],
    "wof:name":"Bayou L'Ourse Supermarket",
    "wof:placetype":"venue"
},
  "geometry": {"coordinates":[-91.09224500000001,29.69438],"type":"Point"}
}