{
  "type": "Feature",
  "properties": {
    "iso:country":"US",
    "sg:address":"382 Robert Blvd",
    "sg:city":"Slidell",
    "sg:classifiers":[
        {
            "category":"Professional",
            "subcategory":"Advertising",
            "type":"Services"
        }
    ],
    "sg:phone":"+1 985 726 9001",
    "sg:postcode":"70458",
    "sg:province":"LA",
    "wof:name":"Press'Cision",
    "wof:placetype":"venue"
},
  "geometry": {"coordinates":[-89.753501,30.300812],"type":"Point"}
}