{
  "type": "Feature",
  "properties": {
    "iso:country":"US",
    "sg:address":"81458 Hwy 21",
    "sg:city":"Bush",
    "sg:classifiers":[
        {
            "category":"Health Services",
            "subcategory":"Doctor",
            "type":"Services"
        }
    ],
    "sg:phone":"+1 985 886 6777",
    "sg:postcode":"70431",
    "sg:province":"LA",
    "sg:tags":[
        "physician",
        "surgeon"
    ],
    "wof:name":"Purnachandr Yerneni MD",
    "wof:placetype":"venue"
},
  "geometry": {"coordinates":[-89.918611,30.615844],"type":"Point"}
}