{
  "type": "Feature",
  "properties": {
    "iso:country":"US",
    "sg:address":"111 Christian Rd",
    "sg:city":"Rayville",
    "sg:classifiers":[
        {
            "category":"Health Services",
            "subcategory":"Doctor",
            "type":"Services"
        }
    ],
    "sg:phone":"+1 318 728 3263",
    "sg:postcode":"71270",
    "sg:province":"LA",
    "sg:tags":[
        "physician",
        "surgeon"
    ],
    "wof:name":"Gordon B Massengale MD",
    "wof:placetype":"venue"
},
  "geometry": {"coordinates":[-92.691018,32.464879],"type":"Point"}
}