{
  "type": "Feature",
  "properties": {
    "iso:country":"US",
    "sg:address":"3966 Lakeshore Dr",
    "sg:city":"Shreveport",
    "sg:classifiers":[
        {
            "category":"Home & Garden",
            "subcategory":"Furniture",
            "type":"Retail Goods"
        }
    ],
    "sg:phone":"+1 318 631 6370",
    "sg:postcode":"71109",
    "sg:province":"LA",
    "wof:name":"Then Is Now Home Consignment",
    "wof:placetype":"venue"
},
  "geometry": {"coordinates":[-93.8032,32.490196],"type":"Point"}
}