{
  "type": "Feature",
  "properties": {
    "addr:full":"400 S Roadway St New Orleans LA 70124",
    "addr:housenumber":"400",
    "addr:postcode":"70124",
    "addr:street":"S Roadway St",
    "iso:country":"US",
    "sg:address":"400 S Roadway St",
    "sg:city":"New Orleans",
    "sg:classifiers":[
        {
            "category":"Manufacturing",
            "subcategory":"Apparel",
            "type":"Manufacturing & Wholesale Goods"
        }
    ],
    "sg:phone":"+1 504 283 3135",
    "sg:postcode":"70124",
    "sg:province":"LA",
    "wof:name":"U K New Orleans",
    "wof:placetype":"venue"
},
  "geometry": {"coordinates":[-90.11934599999999,30.023679],"type":"Point"}
}