{
  "type": "Feature",
  "properties": {
    "addr:full":"16227 River Rd Hahnville LA 70057",
    "addr:housenumber":"16227",
    "addr:postcode":"70057",
    "addr:street":"River Rd",
    "iso:country":"US",
    "sg:address":"16227 River Rd",
    "sg:city":"Hahnville",
    "sg:classifiers":[
        {
            "category":"Organizations",
            "subcategory":"Religious Organization",
            "type":"Services"
        }
    ],
    "sg:phone":"+1 985 783 9105",
    "sg:postcode":"70057",
    "sg:province":"LA",
    "sg:tags":[
        "church"
    ],
    "wof:name":"Faith Praise & Deliverance",
    "wof:placetype":"venue"
},
  "geometry": {"coordinates":[-90.41660299999999,29.988612],"type":"Point"}
}