{
  "type": "Feature",
  "properties": {
    "iso:country":"US",
    "sg:address":"4415 Thornhill Ave",
    "sg:city":"Shreveport",
    "sg:classifiers":[
        {
            "category":"Professional",
            "subcategory":"Lawyer & Legal Services",
            "type":"Services"
        }
    ],
    "sg:phone":"+1 318 869 3900",
    "sg:postcode":"71106",
    "sg:province":"LA",
    "sg:tags":[
        "attorney"
    ],
    "wof:name":"Byram & Mc Carthy",
    "wof:placetype":"venue"
},
  "geometry": {"coordinates":[-93.748137,32.462324],"type":"Point"}
}