{
  "type": "Feature",
  "properties": {
    "addr:full":"79110 Pat Obrien Rd Covington LA 70435",
    "addr:postcode":"79110;70435",
    "addr:street":"Obrien Rd",
    "iso:country":"US",
    "sg:address":"79110 Pat Obrien Rd",
    "sg:city":"Covington",
    "sg:classifiers":[
        {
            "category":"Building & Trades",
            "subcategory":"Landscaping Services",
            "type":"Services"
        }
    ],
    "sg:phone":"+1 985 898 0278",
    "sg:postcode":"70435",
    "sg:province":"LA",
    "sg:tags":[
        "tree"
    ],
    "wof:name":"Mc Craney's Tree Svc",
    "wof:placetype":"venue"
},
  "geometry": {"coordinates":[-90.05393100000001,30.57732],"type":"Point"}
}