{
  "type": "Feature",
  "properties": {
    "addr:full":"228 Hidalgo Dr Houma LA 70363",
    "addr:housenumber":"228",
    "addr:postcode":"70363",
    "addr:street":"Hidalgo Dr",
    "iso:country":"US",
    "sg:address":"228 Hidalgo Dr",
    "sg:city":"Houma",
    "sg:classifiers":[
        {
            "category":"Building & Trades",
            "subcategory":"Construction",
            "type":"Services"
        }
    ],
    "sg:phone":"+1 985 868 8355",
    "sg:postcode":"70363",
    "sg:province":"LA",
    "sg:tags":[
        "house"
    ],
    "wof:name":"Frisellas Crpntry Vinyl Siding",
    "wof:placetype":"venue"
},
  "geometry": {"coordinates":[-90.716511,29.537033],"type":"Point"}
}