{
  "type": "Feature",
  "properties": {
    "iso:country":"US",
    "sg:address":"239 Oak Park Blvd",
    "sg:city":"Garyville",
    "sg:classifiers":[
        {
            "category":"Building & Trades",
            "subcategory":"Plumbing",
            "type":"Services"
        }
    ],
    "sg:phone":"+1 504 417 2370",
    "sg:postcode":"70051",
    "sg:province":"LA",
    "sg:tags":[
        "contractor"
    ],
    "wof:name":"Zacks Plumbing & Heating",
    "wof:placetype":"venue"
},
  "geometry": {"coordinates":[-90.62833500000001,30.064345],"type":"Point"}
}