{
  "type": "Feature",
  "properties": {
    "addr:full":"3000 Kilpatrick Blvd Monroe LA 71201",
    "addr:housenumber":"3000",
    "addr:postcode":"71201",
    "addr:street":"Kilpatrick Blvd",
    "iso:country":"US",
    "sg:address":"3000 Kilpatrick Blvd",
    "sg:city":"Monroe",
    "sg:classifiers":[
        {
            "category":"Professional",
            "subcategory":"Lawyer & Legal Services",
            "type":"Services"
        }
    ],
    "sg:phone":"+1 318 323 3800",
    "sg:postcode":"71201",
    "sg:province":"LA",
    "sg:tags":[
        "attorney"
    ],
    "wof:name":"John L Luffey Jr",
    "wof:placetype":"venue"
},
  "geometry": {"coordinates":[-92.09138,32.52639],"type":"Point"}
}