{
  "type": "Feature",
  "properties": {
    "iso:country":"US",
    "sg:address":"3873 Choctaw Dr",
    "sg:city":"Baton Rouge",
    "sg:classifiers":[
        {
            "category":"Professional",
            "subcategory":"Business Services",
            "type":"Services"
        }
    ],
    "sg:phone":"+1 225 357 9870",
    "sg:postcode":"70805",
    "sg:province":"LA",
    "sg:tags":[
        "notary"
    ],
    "wof:name":"Piggly Wiggly Notary Public",
    "wof:placetype":"venue"
},
  "geometry": {"coordinates":[-91.150378,30.470402],"type":"Point"}
}