{
  "type": "Feature",
  "properties": {
    "iso:country":"US",
    "sg:address":"3547 18th St",
    "sg:city":"Metairie",
    "sg:classifiers":[
        {
            "category":"Restaurant",
            "type":"Food & Drink"
        }
    ],
    "sg:phone":"+1 504 888 0654",
    "sg:postcode":"70002",
    "sg:province":"LA",
    "wof:name":"Korea House Restaurant & Club",
    "wof:placetype":"venue"
},
  "geometry": {"coordinates":[-90.161536,30.008747],"type":"Point"}
}