{
  "type": "Feature",
  "properties": {
    "addr:full":"600 Live Oak St Metairie LA 70005",
    "addr:housenumber":"600",
    "addr:postcode":"70005",
    "addr:street":"Live Oak St",
    "iso:country":"US",
    "sg:address":"600 Live Oak St",
    "sg:city":"Metairie",
    "sg:classifiers":[
        {
            "category":"Local Transit",
            "type":"Transportation"
        }
    ],
    "sg:phone":"+1 504 828 3550",
    "sg:postcode":"70005",
    "sg:province":"LA",
    "sg:tags":[
        "passenger"
    ],
    "wof:name":"Ace Limosine Service",
    "wof:placetype":"venue"
},
  "geometry": {"coordinates":[-90.12944,30.018182],"type":"Point"}
}