{
  "type": "Feature",
  "properties": {
    "iso:country":"US",
    "sg:address":"2009 Hwy 190 Byp",
    "sg:city":"Covington",
    "sg:classifiers":[
        {
            "category":"Building & Trades",
            "subcategory":"Construction",
            "type":"Services"
        }
    ],
    "sg:phone":"+1 985 892 2546",
    "sg:postcode":"70433",
    "sg:province":"LA",
    "sg:tags":[
        "coping",
        "plastering",
        "tiling",
        "pool",
        "swimming"
    ],
    "wof:name":"All Clear Pool Svc",
    "wof:placetype":"venue"
},
  "geometry": {"coordinates":[-90.114294,30.496927],"type":"Point"}
}