{
  "type": "Feature",
  "properties": {
    "iso:country":"US",
    "sg:address":"520 Lincoln Rd",
    "sg:city":"Monroe",
    "sg:classifiers":[
        {
            "category":"Restaurant",
            "type":"Food & Drink"
        }
    ],
    "sg:menulink":"http://www.allmenus.com/la/swartz/201519-sonic/menu/",
    "sg:phone":"+1 318 343 5738",
    "sg:postcode":"71203",
    "sg:province":"LA",
    "sg:tags":[
        "burger",
        "american"
    ],
    "wof:name":"Sonic",
    "wof:placetype":"venue"
},
  "geometry": {"coordinates":[-92.016882,32.542815],"type":"Point"}
}