{
  "type": "Feature",
  "properties": {
    "addr:full":"377 State Rte 522 Mansfield LA 71052",
    "addr:housenumber":"377",
    "addr:postcode":"71052",
    "addr:street":"State Rte 522",
    "iso:country":"US",
    "sg:address":"377 State Rte 522",
    "sg:city":"Mansfield",
    "sg:classifiers":[
        {
            "category":"Mining & Drilling",
            "type":"Manufacturing & Wholesale Goods"
        }
    ],
    "sg:phone":"+1 318 872 6333",
    "sg:postcode":"71052",
    "sg:province":"LA",
    "sg:tags":[
        "company"
    ],
    "wof:name":"Dolet Hills Lignite Co",
    "wof:placetype":"venue"
},
  "geometry": {"coordinates":[-93.567142,32.048011],"type":"Point"}
}