{
  "type": "Feature",
  "properties": {
    "addr:full":"346 Philo St Marksville LA 71351",
    "addr:housenumber":"346",
    "addr:postcode":"71351",
    "addr:street":"Philo St",
    "iso:country":"US",
    "sg:address":"346 Philo St",
    "sg:city":"Marksville",
    "sg:classifiers":[
        {
            "category":"Retail",
            "subcategory":"Portrait Studio",
            "type":"Services"
        }
    ],
    "sg:phone":"+1 318 253 9863",
    "sg:postcode":"71351",
    "sg:province":"LA",
    "sg:tags":[
        "photographer"
    ],
    "wof:name":"Dick Crawford Photography Inc",
    "wof:placetype":"venue"
},
  "geometry": {"coordinates":[-92.075784,31.125437],"type":"Point"}
}