{
  "type": "Feature",
  "properties": {
    "addr:full":"749 Goodson Dr Gretna LA 70056",
    "addr:housenumber":"749",
    "addr:postcode":"70056",
    "addr:street":"Goodson Dr",
    "iso:country":"US",
    "sg:address":"749 Goodson Dr",
    "sg:city":"Gretna",
    "sg:classifiers":[
        {
            "category":"Communications",
            "type":"Services"
        }
    ],
    "sg:phone":"+1 504 393 8668",
    "sg:postcode":"70056",
    "sg:province":"LA",
    "wof:name":"Dauterive Communications",
    "wof:placetype":"venue"
},
  "geometry": {"coordinates":[-90.023675,29.89722],"type":"Point"}
}