{
  "type": "Feature",
  "properties": {
    "addr:full":"207 Gerald Dr Lafayette LA 70503",
    "addr:housenumber":"207",
    "addr:postcode":"70503",
    "addr:street":"Gerald Dr",
    "iso:country":"US",
    "sg:address":"207 Gerald Dr",
    "sg:city":"Lafayette",
    "sg:classifiers":[
        {
            "category":"Professional",
            "subcategory":"Management & Consulting",
            "type":"Services"
        }
    ],
    "sg:phone":"+1 337 984 5839",
    "sg:postcode":"70503",
    "sg:province":"LA",
    "sg:tags":[
        "business"
    ],
    "wof:name":"Lejeune Consulting",
    "wof:placetype":"venue"
},
  "geometry": {"coordinates":[-92.06652099999999,30.181642],"type":"Point"}
}