{
  "type": "Feature",
  "properties": {
    "iso:country":"US",
    "sg:address":"5824 McCann Dr",
    "sg:city":"Baton Rouge",
    "sg:classifiers":[
        {
            "category":"Professional",
            "type":"Services"
        }
    ],
    "sg:phone":"+1 225 755 0504",
    "sg:postcode":"70809",
    "sg:province":"LA",
    "sg:tags":[
        "establishment"
    ],
    "wof:name":"AVSI",
    "wof:placetype":"venue"
},
  "geometry": {"coordinates":[-91.054446,30.394713],"type":"Point"}
}