{
  "type": "Feature",
  "properties": {
    "iso:country":"US",
    "sg:address":"1027 Martin",
    "sg:city":"Saint Martinville",
    "sg:classifiers":[
        {
            "category":"Health Services",
            "subcategory":"Doctor",
            "type":"Services"
        }
    ],
    "sg:phone":"+1 337 845 4900",
    "sg:postcode":"70582",
    "sg:province":"LA",
    "sg:tags":[
        "medicine",
        "internal"
    ],
    "wof:name":"Durham Debra A MD",
    "wof:placetype":"venue"
},
  "geometry": {"coordinates":[-91.825798,30.1367],"type":"Point"}
}