{
  "type": "Feature",
  "properties": {
    "addr:full":"325 Enterprise Blvd Lake Charles LA 70601",
    "addr:housenumber":"325",
    "addr:postcode":"70601",
    "addr:street":"Enterprise Blvd",
    "iso:country":"US",
    "sg:address":"325 Enterprise Blvd",
    "sg:city":"Lake Charles",
    "sg:classifiers":[
        {
            "category":"Manufacturing",
            "subcategory":"Printing",
            "type":"Manufacturing & Wholesale Goods"
        }
    ],
    "sg:phone":"+1 337 436 0062",
    "sg:postcode":"70601",
    "sg:province":"LA",
    "sg:tags":[
        "screen"
    ],
    "wof:name":"Aubrey's Graphic Designs",
    "wof:placetype":"venue"
},
  "geometry": {"coordinates":[-93.20424800000001,30.234543],"type":"Point"}
}