{
  "type": "Feature",
  "properties": {
    "iso:country":"US",
    "sg:address":"2304 N Parkerson Ave",
    "sg:city":"Crowley",
    "sg:classifiers":[
        {
            "category":"Cinema",
            "subcategory":"Movie Theater",
            "type":"Entertainment"
        }
    ],
    "sg:phone":"+1 337 788 0808",
    "sg:postcode":"70526",
    "sg:province":"LA",
    "wof:name":"Crowley Cinema Iv",
    "wof:placetype":"venue"
},
  "geometry": {"coordinates":[-92.384866,30.234275],"type":"Point"}
}