{
  "type": "Feature",
  "properties": {
    "iso:country":"US",
    "sg:address":"2701 Johnston St",
    "sg:city":"Lafayette",
    "sg:classifiers":[
        {
            "category":"Banks & Credit Unions",
            "subcategory":"Bank",
            "type":"Services"
        }
    ],
    "sg:phone":"+1 337 234 2301",
    "sg:postcode":"70503",
    "sg:province":"LA",
    "sg:tags":[
        "financing"
    ],
    "wof:name":"Aegis Lending",
    "wof:placetype":"venue"
},
  "geometry": {"coordinates":[-92.03918400000001,30.206774],"type":"Point"}
}