{
  "type": "Feature",
  "properties": {
    "addr:full":"119 Rees St Breaux Bridge LA 70517",
    "addr:housenumber":"119",
    "addr:postcode":"70517",
    "addr:street":"Rees St;Bridge",
    "iso:country":"US",
    "sg:address":"119 Rees St",
    "sg:city":"Breaux Bridge",
    "sg:classifiers":[
        {
            "category":"Retail",
            "subcategory":"Repair Shop",
            "type":"Services"
        }
    ],
    "sg:phone":"+1 337 332 1422",
    "sg:postcode":"70517",
    "sg:province":"LA",
    "sg:tags":[
        "repairing",
        "lawn",
        "mower"
    ],
    "wof:name":"Z Tec Small Engine Repair",
    "wof:placetype":"venue"
},
  "geometry": {"coordinates":[-91.897814,30.277115],"type":"Point"}
}