{
  "type": "Feature",
  "properties": {
    "addr:full":"208 Gunther Ln Belle Chasse LA 70037",
    "addr:housenumber":"208",
    "addr:postcode":"70037",
    "addr:street":"Gunther Ln",
    "iso:country":"US",
    "sg:address":"208 Gunther Ln",
    "sg:city":"Belle Chasse",
    "sg:classifiers":[
        {
            "category":"Wholesale",
            "subcategory":"Machinery & Supplies",
            "type":"Manufacturing & Wholesale Goods"
        }
    ],
    "sg:phone":"+1 504 394 4600",
    "sg:postcode":"70037",
    "sg:province":"LA",
    "sg:tags":[
        "crane",
        "derrick"
    ],
    "wof:name":"Seatrax Marine Cranes",
    "wof:placetype":"venue"
},
  "geometry": {"coordinates":[-90.05189900000001,29.836176],"type":"Point"}
}