{
  "type": "Feature",
  "properties": {
    "addr:full":"2540 Deutsch Rd Marrero LA 70072",
    "addr:housenumber":"2540",
    "addr:postcode":"70072",
    "addr:street":"Deutsch Rd Marrero",
    "iso:country":"US",
    "sg:address":"2540 Deutsch Rd",
    "sg:city":"Marrero",
    "sg:classifiers":[
        {
            "category":"Building & Trades",
            "subcategory":"Construction",
            "type":"Services"
        }
    ],
    "sg:phone":"+1 504 340 1960",
    "sg:postcode":"70072",
    "sg:province":"LA",
    "sg:tags":[
        "commercial"
    ],
    "wof:name":"Hennessy Construction Corp",
    "wof:placetype":"venue"
},
  "geometry": {"coordinates":[-90.102378,29.852991],"type":"Point"}
}