{
  "type": "Feature",
  "properties": {
    "iso:country":"US",
    "sg:address":"1657 Pleasure St",
    "sg:city":"New Orleans",
    "sg:classifiers":[
        {
            "category":"Personal",
            "subcategory":"Barber",
            "type":"Services"
        }
    ],
    "sg:phone":"+1 504 283 9403",
    "sg:postcode":"70122",
    "sg:province":"LA",
    "wof:name":"Irvin's Barber Shop",
    "wof:placetype":"venue"
},
  "geometry": {"coordinates":[-90.07097899999999,29.992213],"type":"Point"}
}