{
  "type": "Feature",
  "properties": {
    "iso:country":"US",
    "sg:address":"2801 Marty Ln",
    "sg:city":"Shreveport",
    "sg:classifiers":[
        {
            "category":"Manufacturing",
            "subcategory":"Tools & Machinery",
            "type":"Manufacturing & Wholesale Goods"
        }
    ],
    "sg:phone":"+1 318 688 1800",
    "sg:postcode":"71119",
    "sg:province":"LA",
    "sg:tags":[
        "machine",
        "shop"
    ],
    "wof:name":"Walker-Wheland Inc",
    "wof:placetype":"venue"
},
  "geometry": {"coordinates":[-93.871647,32.504335],"type":"Point"}
}