{
  "type": "Feature",
  "properties": {
    "iso:country":"US",
    "sg:address":"6226 Jefferson Hwy",
    "sg:city":"Harahan",
    "sg:classifiers":[
        {
            "category":"Shopping",
            "subcategory":"Pharmacy",
            "type":"Retail Goods"
        }
    ],
    "sg:phone":"+1 504 737 4007",
    "sg:postcode":"70123",
    "sg:province":"LA",
    "wof:name":"Avita Drugs LLC",
    "wof:placetype":"venue"
},
  "geometry": {"coordinates":[-90.19087,29.938228],"type":"Point"}
}