{
  "type": "Feature",
  "properties": {
    "addr:full":"3829 Lake Huron Dr Harvey LA 70058",
    "addr:housenumber":"3829",
    "addr:postcode":"70058",
    "addr:street":"Lake Huron Dr",
    "iso:country":"US",
    "sg:address":"3829 Lake Huron Dr",
    "sg:city":"Harvey",
    "sg:classifiers":[
        {
            "category":"Building & Trades",
            "subcategory":"Plumbing",
            "type":"Services"
        }
    ],
    "sg:phone":"+1 504 392 9737",
    "sg:postcode":"70058",
    "sg:province":"LA",
    "sg:tags":[
        "conditioning",
        "air",
        "system",
        "contractor"
    ],
    "wof:name":"Bayou Services",
    "wof:placetype":"venue"
},
  "geometry": {"coordinates":[-90.038315,29.853129],"type":"Point"}
}