{
  "type": "Feature",
  "properties": {
    "addr:full":"1160 Cypress St Sulphur LA 70663",
    "addr:housenumber":"1160",
    "addr:postcode":"70663",
    "addr:street":"Cypress St",
    "iso:country":"US",
    "sg:address":"1160 Cypress St",
    "sg:city":"Sulphur",
    "sg:classifiers":[
        {
            "category":"Education",
            "subcategory":"Library",
            "type":"Public Place"
        }
    ],
    "sg:phone":"+1 337 527 7200",
    "sg:postcode":"70663",
    "sg:province":"LA",
    "wof:name":"Sulphur Library",
    "wof:placetype":"venue"
},
  "geometry": {"coordinates":[-93.363636,30.231146],"type":"Point"}
}