{
  "type": "Feature",
  "properties": {
    "addr:full":"1304 N 18th St Monroe LA 71201",
    "addr:housenumber":"1304",
    "addr:postcode":"71201",
    "addr:street":"N 18Th St",
    "iso:country":"US",
    "sg:address":"1304 N 18th St",
    "sg:city":"Monroe",
    "sg:classifiers":[
        {
            "category":"Real Estate",
            "subcategory":"Real Estate Agent",
            "type":"Services"
        }
    ],
    "sg:phone":"+1 318 388 2412",
    "sg:postcode":"71201",
    "sg:province":"LA",
    "wof:name":"Richard K Moore & Assoc",
    "wof:placetype":"venue"
},
  "geometry": {"coordinates":[-92.11181500000001,32.522825],"type":"Point"}
}