{
  "type": "Feature",
  "properties": {
    "addr:full":"3407 Metairie Rd Metairie LA 70001",
    "addr:housenumber":"3407",
    "addr:postcode":"70001",
    "addr:street":"Metairie Rd",
    "iso:country":"US",
    "sg:address":"3407 Metairie Rd",
    "sg:city":"Metairie",
    "sg:classifiers":[
        {
            "category":"Autos & Motor Vehicles",
            "subcategory":"Automobile Sales",
            "type":"Retail Goods"
        }
    ],
    "sg:phone":"+1 504 837 0850",
    "sg:postcode":"70001",
    "sg:province":"LA",
    "sg:tags":[
        "car",
        "dealer"
    ],
    "wof:name":"S V Inc",
    "wof:placetype":"venue"
},
  "geometry": {"coordinates":[-90.16061999999999,29.975293],"type":"Point"}
}