{
  "type": "Feature",
  "properties": {
    "iso:country":"US",
    "sg:address":"2423 Bainbridge St",
    "sg:city":"Kenner",
    "sg:classifiers":[
        {
            "category":"Professional",
            "subcategory":"Business Services",
            "type":"Services"
        }
    ],
    "sg:phone":"+1 504 472 9300",
    "sg:postcode":"70062",
    "sg:province":"LA",
    "wof:name":"Star Answers",
    "wof:placetype":"venue"
},
  "geometry": {"coordinates":[-90.250029,30.00072],"type":"Point"}
}