{
  "type": "Feature",
  "properties": {
    "iso:country":"US",
    "sg:address":"12812 Coursey Blvd",
    "sg:city":"Baton Rouge",
    "sg:classifiers":[
        {
            "category":"Professional",
            "subcategory":"Lawyer & Legal Services",
            "type":"Services"
        }
    ],
    "sg:phone":"+1 225 752 2688",
    "sg:postcode":"70816",
    "sg:province":"LA",
    "sg:tags":[
        "attorney"
    ],
    "wof:name":"Steve Irving LLC",
    "wof:placetype":"venue"
},
  "geometry": {"coordinates":[-91.03615600000001,30.410181],"type":"Point"}
}