{
  "type": "Feature",
  "properties": {
    "iso:country":"US",
    "sg:address":"2805 Armand St",
    "sg:city":"Monroe",
    "sg:classifiers":[
        {
            "category":"Professional",
            "subcategory":"Lawyer & Legal Services",
            "type":"Services"
        }
    ],
    "sg:phone":"+1 318 323 7141",
    "sg:postcode":"71201",
    "sg:province":"LA",
    "sg:tags":[
        "attorney"
    ],
    "wof:name":"Ronald K Cook",
    "wof:placetype":"venue"
},
  "geometry": {"coordinates":[-92.092759,32.529182],"type":"Point"}
}