{
  "type": "Feature",
  "properties": {
    "iso:country":"US",
    "sg:address":"812 Sampson St",
    "sg:city":"Westlake",
    "sg:classifiers":[
        {
            "category":"Autos & Motor Vehicles",
            "subcategory":"Auto Supplies",
            "type":"Retail Goods"
        }
    ],
    "sg:phone":"+1 337 436 9620",
    "sg:postcode":"70669",
    "sg:province":"LA",
    "sg:tags":[
        "automobile",
        "parts"
    ],
    "wof:name":"Dimmick's All Pro Auto Parts",
    "wof:placetype":"venue"
},
  "geometry": {"coordinates":[-93.25804599999999,30.242536],"type":"Point"}
}