{
  "type": "Feature",
  "properties": {
    "iso:country":"US",
    "sg:address":"1569 Sabine St",
    "sg:city":"Natchitoches",
    "sg:classifiers":[
        {
            "category":"Social Services",
            "subcategory":"Child Care",
            "type":"Services"
        }
    ],
    "sg:phone":"+1 318 352 2940",
    "sg:postcode":"71457",
    "sg:province":"LA",
    "wof:name":"Daddy's Day Care & Learning",
    "wof:placetype":"venue"
},
  "geometry": {"coordinates":[-93.100841,31.774267],"type":"Point"}
}