{
  "type": "Feature",
  "properties": {
    "iso:country":"US",
    "sg:address":"2900 Westfork Dr",
    "sg:city":"Baton Rouge",
    "sg:classifiers":[
        {
            "category":"Professional",
            "subcategory":"Detective & Security Services",
            "type":"Services"
        }
    ],
    "sg:phone":"+1 225 295 5616",
    "sg:postcode":"70816",
    "sg:province":"LA",
    "sg:tags":[
        "investigator"
    ],
    "wof:name":"Legal Investigative Svc",
    "wof:placetype":"venue"
},
  "geometry": {"coordinates":[-91.05489,30.423432],"type":"Point"}
}