{
  "type": "Feature",
  "properties": {
    "addr:full":"202 E Thompson St New Iberia LA 70560",
    "addr:housenumber":"202",
    "addr:postcode":"70560",
    "addr:street":"E Thompson St",
    "iso:country":"US",
    "sg:address":"202 E Thompson St",
    "sg:city":"New Iberia",
    "sg:classifiers":[
        {
            "category":"Social Services",
            "subcategory":"Child Care",
            "type":"Services"
        }
    ],
    "sg:phone":"+1 337 367 2770",
    "sg:postcode":"70560",
    "sg:province":"LA",
    "wof:name":"St Anne's Child Care Ctr",
    "wof:placetype":"venue"
},
  "geometry": {"coordinates":[-91.836658,29.990779],"type":"Point"}
}