{
  "type": "Feature",
  "properties": {
    "iso:country":"US",
    "sg:address":"318 Venture Blvd",
    "sg:city":"Houma",
    "sg:classifiers":[
        {
            "category":"Building & Trades",
            "subcategory":"Plumbing",
            "type":"Services"
        }
    ],
    "sg:phone":"+1 985 876 6187",
    "sg:postcode":"70360",
    "sg:province":"LA",
    "sg:tags":[
        "heating",
        "contractor"
    ],
    "wof:name":"Coastal Mechanical Contrs Inc",
    "wof:placetype":"venue"
},
  "geometry": {"coordinates":[-90.76387200000001,29.597057],"type":"Point"}
}