{
  "type": "Feature",
  "properties": {
    "addr:full":"3207 Lavey Ln Baker LA 70714",
    "addr:postcode":"3207;70714",
    "addr:street":"Lavey Ln",
    "iso:country":"US",
    "sg:address":"3207 Lavey Ln",
    "sg:city":"Baker",
    "sg:classifiers":[
        {
            "category":"Home & Garden",
            "subcategory":"Furniture",
            "type":"Retail Goods"
        }
    ],
    "sg:phone":"+1 225 774 0707",
    "sg:postcode":"70714",
    "sg:province":"LA",
    "sg:tags":[
        "top",
        "counter"
    ],
    "wof:name":"First In Counters",
    "wof:placetype":"venue"
},
  "geometry": {"coordinates":[-91.16718899999999,30.575399],"type":"Point"}
}