{
  "type": "Feature",
  "properties": {
    "addr:full":"135 Enterprise Gretna LA 70056",
    "addr:housenumber":"135",
    "addr:postcode":"70056",
    "addr:street":"Enterprise",
    "iso:country":"US",
    "sg:address":"135 Enterprise",
    "sg:city":"Gretna",
    "sg:classifiers":[
        {
            "category":"Home & Garden",
            "subcategory":"Building Materials",
            "type":"Retail Goods"
        }
    ],
    "sg:phone":"+1 504 277 4476",
    "sg:postcode":"70056",
    "sg:province":"LA",
    "sg:tags":[
        "glass",
        "window",
        "plate"
    ],
    "wof:name":"Access Lips Door & Glass Co",
    "wof:placetype":"venue"
},
  "geometry": {"coordinates":[-90.043115,29.896713],"type":"Point"}
}