{
  "type": "Feature",
  "properties": {
    "addr:full":"10180 State Rte 17 Oak Grove LA 71263",
    "addr:housenumber":"10180",
    "addr:postcode":"71263",
    "addr:street":"State Rte 17;Grove",
    "iso:country":"US",
    "sg:address":"10180 State Rte 17",
    "sg:city":"Oak Grove",
    "sg:classifiers":[
        {
            "category":"Autos & Motor Vehicles",
            "subcategory":"Automobile Sales",
            "type":"Retail Goods"
        }
    ],
    "sg:phone":"+1 318 428 1099",
    "sg:postcode":"71263",
    "sg:province":"LA",
    "sg:tags":[
        "car",
        "dealer"
    ],
    "wof:name":"Ken's Kustom Used & Trucks",
    "wof:placetype":"venue"
},
  "geometry": {"coordinates":[-91.394863,32.847142],"type":"Point"}
}