{
  "type": "Feature",
  "properties": {
    "addr:full":"3895 Holifield Dr Bastrop LA 71220",
    "addr:postcode":"3895;71220",
    "addr:street":"Holifield Dr",
    "iso:country":"US",
    "sg:address":"3895 Holifield Dr",
    "sg:city":"Bastrop",
    "sg:classifiers":[
        {
            "category":"Building & Trades",
            "subcategory":"Construction",
            "type":"Services"
        }
    ],
    "sg:phone":"+1 318 281 0800",
    "sg:postcode":"71220",
    "sg:province":"LA",
    "wof:name":"Diamond Utility Inc",
    "wof:placetype":"venue"
},
  "geometry": {"coordinates":[-91.961895,32.756599],"type":"Point"}
}