{
  "type": "Feature",
  "properties": {
    "iso:country":"US",
    "sg:address":"4448 Lake St",
    "sg:city":"Lake Charles",
    "sg:classifiers":[
        {
            "category":"Real Estate",
            "subcategory":"Real Estate Agent",
            "type":"Services"
        }
    ],
    "sg:phone":"+1 337 474 0592",
    "sg:postcode":"70605",
    "sg:province":"LA",
    "sg:tags":[
        "appraiser"
    ],
    "wof:name":"Advanced Appraisals",
    "wof:placetype":"venue"
},
  "geometry": {"coordinates":[-93.23245,30.180339],"type":"Point"}
}