{
  "type": "Feature",
  "properties": {
    "addr:full":"815 King Pl Shreveport LA 71115",
    "addr:housenumber":"815",
    "addr:postcode":"71115",
    "addr:street":"King Pl",
    "iso:country":"US",
    "sg:address":"815 King Pl",
    "sg:city":"Shreveport",
    "sg:classifiers":[
        {
            "category":"Home & Garden",
            "subcategory":"Building Materials",
            "type":"Retail Goods"
        }
    ],
    "sg:phone":"+1 318 798 6736",
    "sg:postcode":"71115",
    "sg:province":"LA",
    "sg:tags":[
        "door"
    ],
    "sg:website":"www.avallone.com",
    "wof:name":"Avallone Architectural Specs",
    "wof:placetype":"venue"
},
  "geometry": {"coordinates":[-93.69909800000001,32.405317],"type":"Point"}
}