{
  "type": "Feature",
  "properties": {
    "addr:full":"8201 Peach St New Orleans LA 70118",
    "addr:housenumber":"8201",
    "addr:postcode":"70118",
    "addr:street":"Peach St",
    "iso:country":"US",
    "sg:address":"8201 Peach St",
    "sg:city":"New Orleans",
    "sg:classifiers":[
        {
            "category":"Wholesale",
            "subcategory":"Machinery & Supplies",
            "type":"Manufacturing & Wholesale Goods"
        }
    ],
    "sg:phone":"+1 504 488 1212",
    "sg:postcode":"70118",
    "sg:province":"LA",
    "sg:tags":[
        "sprinkler"
    ],
    "wof:name":"Coastal Fire Protection",
    "wof:placetype":"venue"
},
  "geometry": {"coordinates":[-90.11072799999999,29.969547],"type":"Point"}
}