{
  "type": "Feature",
  "properties": {
    "iso:country":"US",
    "sg:address":"58038 Fort St",
    "sg:city":"Plaquemine",
    "sg:classifiers":[
        {
            "category":"Government",
            "subcategory":"Office",
            "type":"Public Place"
        }
    ],
    "sg:phone":"+1 225 687 8555",
    "sg:postcode":"70764",
    "sg:province":"LA",
    "wof:name":"Iberville Parish Coroner Ofc",
    "wof:placetype":"venue"
},
  "geometry": {"coordinates":[-91.23383699999999,30.283692],"type":"Point"}
}