{
  "type": "Feature",
  "properties": {
    "iso:country":"US",
    "sg:address":"2905 Loreauville Rd",
    "sg:city":"New Iberia",
    "sg:classifiers":[
        {
            "category":"Restaurant",
            "type":"Food & Drink"
        }
    ],
    "sg:phone":"+1 337 367 0094",
    "sg:postcode":"70563",
    "sg:province":"LA",
    "wof:name":"Caribbean Ice Co",
    "wof:placetype":"venue"
},
  "geometry": {"coordinates":[-91.76494099999999,30.012073],"type":"Point"}
}