{
  "type": "Feature",
  "properties": {
    "addr:full":"2508 20th St Kenner LA 70062",
    "addr:housenumber":"2508",
    "addr:postcode":"70062",
    "addr:street":"20Th St",
    "iso:country":"US",
    "sg:address":"2508 20th St",
    "sg:city":"Kenner",
    "sg:classifiers":[
        {
            "category":"Education",
            "subcategory":"Special Training",
            "type":"Public Place"
        }
    ],
    "sg:phone":"+1 504 468 7593",
    "sg:postcode":"70062",
    "sg:province":"LA",
    "sg:tags":[
        "ceramics"
    ],
    "wof:name":"Ceramics Studio",
    "wof:placetype":"venue"
},
  "geometry": {"coordinates":[-90.23685399999999,29.992045],"type":"Point"}
}