{
  "type": "Feature",
  "properties": {
    "addr:full":"719 Common St New Orleans LA 70130",
    "addr:housenumber":"719",
    "addr:postcode":"70130",
    "addr:street":"Common St",
    "iso:country":"US",
    "sg:address":"719 Common St",
    "sg:city":"New Orleans",
    "sg:classifiers":[
        {
            "category":"Wholesale",
            "subcategory":"Machinery & Supplies",
            "type":"Manufacturing & Wholesale Goods"
        }
    ],
    "sg:phone":"+1 504 525 8247",
    "sg:postcode":"70130",
    "sg:province":"LA",
    "sg:tags":[
        "salon",
        "beauty"
    ],
    "wof:name":"Sally Beauty Supply",
    "wof:placetype":"venue"
},
  "geometry": {"coordinates":[-90.07064800000001,29.952779],"type":"Point"}
}