{
  "type": "Feature",
  "properties": {
    "iso:country":"US",
    "sg:address":"4709 Lee St",
    "sg:city":"Alexandria",
    "sg:classifiers":[
        {
            "category":"Manufacturing",
            "subcategory":"Printing",
            "type":"Manufacturing & Wholesale Goods"
        }
    ],
    "sg:phone":"+1 318 473 8052",
    "sg:postcode":"71302",
    "sg:province":"LA",
    "sg:tags":[
        "printer"
    ],
    "wof:name":"Business Publisher & Notary",
    "wof:placetype":"venue"
},
  "geometry": {"coordinates":[-92.447382,31.263694],"type":"Point"}
}