{
  "type": "Feature",
  "properties": {
    "iso:country":"US",
    "sg:address":"64367 Hwy 41",
    "sg:city":"Pearl River",
    "sg:classifiers":[
        {
            "category":"Farming",
            "subcategory":"Dairy Farm",
            "type":"Manufacturing & Wholesale Goods"
        }
    ],
    "sg:phone":"+1 985 863 8475",
    "sg:postcode":"70452",
    "sg:province":"LA",
    "wof:name":"Lafleur Dairy Products Inc",
    "wof:placetype":"venue"
},
  "geometry": {"coordinates":[-89.758503,30.366379],"type":"Point"}
}