{
  "type": "Feature",
  "properties": {
    "addr:full":"1068 Pearl Dr Bossier City LA 71111",
    "addr:housenumber":"1068",
    "addr:postcode":"71111",
    "addr:street":"Pearl Dr",
    "iso:country":"US",
    "sg:address":"1068 Pearl Dr",
    "sg:city":"Bossier City",
    "sg:classifiers":[
        {
            "category":"Wholesale",
            "subcategory":"Electrical",
            "type":"Manufacturing & Wholesale Goods"
        }
    ],
    "sg:phone":"+1 318 747 7265",
    "sg:postcode":"71111",
    "sg:province":"LA",
    "sg:tags":[
        "fire",
        "equipment",
        "protection"
    ],
    "wof:name":"JEI Alliance Fire Control",
    "wof:placetype":"venue"
},
  "geometry": {"coordinates":[-93.676068,32.5333],"type":"Point"}
}