{
  "type": "Feature",
  "properties": {
    "iso:country":"US",
    "sg:address":"822 Perdido St",
    "sg:city":"New Orleans",
    "sg:classifiers":[
        {
            "category":"Food & Beverages",
            "subcategory":"Specialty",
            "type":"Retail Goods"
        }
    ],
    "sg:phone":"+1 504 525 0082",
    "sg:postcode":"70112",
    "sg:province":"LA",
    "sg:tags":[
        "tea",
        "coffee"
    ],
    "wof:name":"Cafe Lobo",
    "wof:placetype":"venue"
},
  "geometry": {"coordinates":[-90.071834,29.950864],"type":"Point"}
}