{
  "type": "Feature",
  "properties": {
    "iso:country":"US",
    "sg:address":"558 Front St",
    "sg:city":"Natchitoches",
    "sg:classifiers":[
        {
            "category":"Shopping",
            "subcategory":"Gifts & Souvenirs",
            "type":"Retail Goods"
        }
    ],
    "sg:phone":"+1 318 354 8800",
    "sg:postcode":"71457",
    "sg:province":"LA",
    "sg:tags":[
        "shop"
    ],
    "wof:name":"Arc En Ciel",
    "wof:placetype":"venue"
},
  "geometry": {"coordinates":[-93.086203,31.760755],"type":"Point"}
}