{
  "type": "Feature",
  "properties": {
    "iso:country":"US",
    "sg:address":"101 N Trenton St",
    "sg:city":"Ruston",
    "sg:classifiers":[
        {
            "category":"Restaurant",
            "type":"Food & Drink"
        }
    ],
    "sg:phone":"+1 318 251 2222",
    "sg:postcode":"71270",
    "sg:province":"LA",
    "wof:name":"Monjuni's Italian Cafe & Grcry",
    "wof:placetype":"venue"
},
  "geometry": {"coordinates":[-92.63928,32.529035],"type":"Point"}
}