{
  "type": "Feature",
  "properties": {
    "iso:country":"US",
    "sg:address":"3043 Old Forge Dr",
    "sg:city":"Baton Rouge",
    "sg:classifiers":[
        {
            "category":"Professional",
            "subcategory":"Art Services",
            "type":"Services"
        }
    ],
    "sg:phone":"+1 225 216 0078",
    "sg:postcode":"70808",
    "sg:province":"LA",
    "sg:tags":[
        "graphic",
        "designer"
    ],
    "wof:name":"Moonlight Graphics",
    "wof:placetype":"venue"
},
  "geometry": {"coordinates":[-91.136628,30.416992],"type":"Point"}
}