{
  "type": "Feature",
  "properties": {
    "iso:country":"US",
    "sg:address":"3419 Curtis Ln",
    "sg:city":"New Iberia",
    "sg:classifiers":[
        {
            "category":"Building & Trades",
            "subcategory":"Equipment Rental",
            "type":"Services"
        }
    ],
    "sg:phone":"+1 337 367 2520",
    "sg:postcode":"70560",
    "sg:province":"LA",
    "sg:tags":[
        "yard"
    ],
    "wof:name":"Rental Equipment Xchange Inc",
    "wof:placetype":"venue"
},
  "geometry": {"coordinates":[-91.84478900000001,29.968792],"type":"Point"}
}