{
  "type": "Feature",
  "properties": {
    "addr:full":"1114 Church St Houma LA 70360",
    "addr:housenumber":"1114",
    "addr:postcode":"70360",
    "addr:street":"Church St",
    "iso:country":"US",
    "sg:address":"1114 Church St",
    "sg:city":"Houma",
    "sg:classifiers":[
        {
            "category":"Organizations",
            "subcategory":"Religious Organization",
            "type":"Services"
        }
    ],
    "sg:phone":"+1 985 876 1430",
    "sg:postcode":"70360",
    "sg:province":"LA",
    "sg:tags":[
        "church"
    ],
    "wof:name":"First Corinthian Baptst Church",
    "wof:placetype":"venue"
},
  "geometry": {"coordinates":[-90.723687,29.589574],"type":"Point"}
}