{
  "type": "Feature",
  "properties": {
    "iso:country":"US",
    "sg:address":"1135 Hwy 55",
    "sg:city":"Montegut",
    "sg:classifiers":[
        {
            "category":"Education",
            "subcategory":"Library",
            "type":"Public Place"
        }
    ],
    "sg:phone":"+1 985 594 4390",
    "sg:postcode":"70377",
    "sg:province":"LA",
    "wof:name":"Terrebonne Parish Library",
    "wof:placetype":"venue"
},
  "geometry": {"coordinates":[-90.55584,29.477805],"type":"Point"}
}