{
  "type": "Feature",
  "properties": {
    "iso:country":"US",
    "sg:address":"1298 Hwy 15",
    "sg:city":"West Monroe",
    "sg:classifiers":[
        {
            "category":"Shopping",
            "type":"Retail Goods"
        }
    ],
    "sg:phone":"+1 318 396 2441",
    "sg:postcode":"71291",
    "sg:province":"LA",
    "sg:tags":[
        "candle"
    ],
    "wof:name":"Mary's Candles",
    "wof:placetype":"venue"
},
  "geometry": {"coordinates":[-92.244952,32.546003],"type":"Point"}
}