{
  "type": "Feature",
  "properties": {
    "addr:full":"8010 Burr Oak Drive Greenwood LA 71033",
    "addr:housenumber":"8010",
    "addr:postcode":"71033",
    "addr:street":"Burr Oak Drive",
    "iso:country":"US",
    "sg:address":"8010 Burr Oak Drive",
    "sg:city":"Greenwood",
    "sg:classifiers":[
        {
            "category":"Professional",
            "subcategory":"Computer Services",
            "type":"Services"
        }
    ],
    "sg:postcode":"71033",
    "sg:province":"LA",
    "sg:tags":[
        "advice-research-homework-help-assistance-answers-expert"
    ],
    "sg:website":"http://www.answerway.com",
    "wof:name":"Answerway.com",
    "wof:placetype":"venue"
},
  "geometry": {"coordinates":[-93.936015,32.434912],"type":"Point"}
}