{
  "type": "Feature",
  "properties": {
    "iso:country":"US",
    "sg:address":"501 Government St",
    "sg:city":"Baton Rouge",
    "sg:classifiers":[
        {
            "category":"Shopping",
            "subcategory":"Used Merchandise",
            "type":"Retail Goods"
        }
    ],
    "sg:phone":"+1 225 343 3421",
    "sg:postcode":"70802",
    "sg:province":"LA",
    "sg:tags":[
        "antique"
    ],
    "wof:name":"I M Causey & Co Inc",
    "wof:placetype":"venue"
},
  "geometry": {"coordinates":[-91.183742,30.44342],"type":"Point"}
}