{
  "type": "Feature",
  "properties": {
    "addr:full":"1101 E 5th St Natchitoches LA 71457",
    "addr:housenumber":"1101",
    "addr:postcode":"71457",
    "addr:street":"E 5Th St",
    "iso:country":"US",
    "sg:address":"1101 E 5th St",
    "sg:city":"Natchitoches",
    "sg:classifiers":[
        {
            "category":"Education",
            "subcategory":"School",
            "type":"Public Place"
        }
    ],
    "sg:phone":"+1 318 352 8394",
    "sg:postcode":"71457",
    "sg:province":"LA",
    "wof:name":"St Mary's School",
    "wof:placetype":"venue"
},
  "geometry": {"coordinates":[-93.077664,31.772446],"type":"Point"}
}