{
  "type": "Feature",
  "properties": {
    "iso:country":"US",
    "sg:address":"8550 United Plaza Blvd",
    "sg:city":"Baton Rouge",
    "sg:classifiers":[
        {
            "category":"Wholesale",
            "subcategory":"Medical Equipment & Supplies",
            "type":"Manufacturing & Wholesale Goods"
        }
    ],
    "sg:phone":"+1 225 935 2259",
    "sg:postcode":"70809",
    "sg:province":"LA",
    "sg:tags":[
        "physician",
        "surgeon"
    ],
    "wof:name":"Medtronic Sofamor Danek",
    "wof:placetype":"venue"
},
  "geometry": {"coordinates":[-91.095983,30.409447],"type":"Point"}
}