{
  "type": "Feature",
  "properties": {
    "iso:country":"US",
    "sg:address":"1505 Federal Rd",
    "sg:city":"Opelousas",
    "sg:classifiers":[
        {
            "category":"Organizations",
            "subcategory":"Religious Organization",
            "type":"Services"
        }
    ],
    "sg:phone":"+1 337 407 0086",
    "sg:postcode":"70570",
    "sg:province":"LA",
    "sg:tags":[
        "church"
    ],
    "wof:name":"Living Water Christian Ctr",
    "wof:placetype":"venue"
},
  "geometry": {"coordinates":[-92.10628199999999,30.551488],"type":"Point"}
}