{
  "type": "Feature",
  "properties": {
    "iso:country":"US",
    "sg:address":"125 Mackey Ln",
    "sg:city":"Port Sulphur",
    "sg:classifiers":[
        {
            "category":"Organizations",
            "subcategory":"Religious Organization",
            "type":"Services"
        }
    ],
    "sg:phone":"+1 985 564 2339",
    "sg:postcode":"70083",
    "sg:province":"LA",
    "sg:tags":[
        "church"
    ],
    "wof:name":"Greater Mt Sinai Baptist Chr",
    "wof:placetype":"venue"
},
  "geometry": {"coordinates":[-89.615627,29.427891],"type":"Point"}
}