{
  "type": "Feature",
  "properties": {
    "iso:country":"US",
    "sg:address":"150 Fisher Rd",
    "sg:city":"Many",
    "sg:classifiers":[
        {
            "category":"Restaurant",
            "type":"Food & Drink"
        }
    ],
    "sg:phone":"+1 318 256 5999",
    "sg:postcode":"71449",
    "sg:province":"LA",
    "wof:name":"Los Gallos",
    "wof:placetype":"venue"
},
  "geometry": {"coordinates":[-93.475403,31.56231],"type":"Point"}
}