{
  "type": "Feature",
  "properties": {
    "addr:full":"2911 Centenary Blvd Shreveport LA 71104",
    "addr:housenumber":"2911",
    "addr:postcode":"71104",
    "addr:street":"Centenary Blvd",
    "iso:country":"US",
    "sg:address":"2911 Centenary Blvd",
    "sg:city":"Shreveport",
    "sg:classifiers":[
        {
            "category":"Arts & Performance",
            "subcategory":"Theater",
            "type":"Entertainment"
        }
    ],
    "sg:phone":"+1 318 869 5242",
    "sg:postcode":"71104",
    "sg:province":"LA",
    "sg:website":"www.centenary.edu",
    "wof:name":"Marjorie Lyons Playhouse",
    "wof:placetype":"venue"
},
  "geometry": {"coordinates":[-93.733054,32.485659],"type":"Point"}
}