{
  "type": "Feature",
  "properties": {
    "iso:country":"US",
    "sg:address":"366 Webb Smith",
    "sg:city":"Colfax",
    "sg:classifiers":[
        {
            "category":"Health Services",
            "subcategory":"Nursing And Care Facility",
            "type":"Services"
        }
    ],
    "sg:phone":"+1 318 448 0604",
    "sg:postcode":"71417",
    "sg:province":"LA",
    "sg:tags":[
        "home",
        "convalescent"
    ],
    "wof:name":"Grant Manor Nursing Home",
    "wof:placetype":"venue"
},
  "geometry": {"coordinates":[-92.690091,31.524249],"type":"Point"}
}