{
  "type": "Feature",
  "properties": {
    "addr:full":"1220 Winder Rd E Thibodaux LA 70301",
    "addr:housenumber":"1220",
    "addr:postcode":"70301",
    "addr:street":"Winder Rd E",
    "iso:country":"US",
    "sg:address":"1220 Winder Rd E",
    "sg:city":"Thibodaux",
    "sg:classifiers":[
        {
            "category":"Real Estate",
            "subcategory":"Real Estate Operator",
            "type":"Services"
        }
    ],
    "sg:phone":"+1 985 446 9103",
    "sg:postcode":"70301",
    "sg:province":"LA",
    "sg:tags":[
        "home",
        "park",
        "mobil"
    ],
    "wof:name":"Solars Mobile Home Park",
    "wof:placetype":"venue"
},
  "geometry": {"coordinates":[-90.872784,29.786182],"type":"Point"}
}