{
  "type": "Feature",
  "properties": {
    "iso:country":"US",
    "sg:address":"914 North Rampart Street",
    "sg:city":"New Orleans",
    "sg:classifiers":[
        {
            "category":"Personal",
            "subcategory":"Day Spa",
            "type":"Services"
        }
    ],
    "sg:phone":"+1 504 522 7288",
    "sg:postcode":"70116",
    "sg:province":"LA",
    "sg:website":"www.spaorleans.com",
    "wof:name":"Miss Celie's Spa Orleans",
    "wof:placetype":"venue"
},
  "geometry": {"coordinates":[-90.066597,29.9622],"type":"Point"}
}