{
  "type": "Feature",
  "properties": {
    "iso:country":"US",
    "sg:address":"132 Scopena Cir",
    "sg:city":"Bossier City",
    "sg:classifiers":[
        {
            "category":"Professional",
            "subcategory":"Business Services",
            "type":"Services"
        }
    ],
    "sg:phone":"+1 318 746 8210",
    "sg:postcode":"71112",
    "sg:province":"LA",
    "wof:name":"Horizon Services Inc",
    "wof:placetype":"venue"
},
  "geometry": {"coordinates":[-93.62334799999999,32.408803],"type":"Point"}
}