{
  "type": "Feature",
  "properties": {
    "addr:full":"1023 Common St Lake Charles LA 70601",
    "addr:housenumber":"1023",
    "addr:postcode":"70601",
    "addr:street":"Common St",
    "iso:country":"US",
    "sg:address":"1023 Common St",
    "sg:city":"Lake Charles",
    "sg:classifiers":[
        {
            "category":"Social Services",
            "type":"Services"
        }
    ],
    "sg:phone":"+1 337 439 6109",
    "sg:postcode":"70601",
    "sg:province":"LA",
    "sg:tags":[
        "organization",
        "welfare"
    ],
    "sg:website":"www.310info.org",
    "wof:name":"Volunteer Center",
    "wof:placetype":"venue"
},
  "geometry": {"coordinates":[-93.214004,30.225739],"type":"Point"}
}