{
  "type": "Feature",
  "properties": {
    "iso:country":"US",
    "sg:address":"831 Robert Blvd",
    "sg:city":"Slidell",
    "sg:classifiers":[
        {
            "category":"Shopping",
            "subcategory":"Musical Instruments",
            "type":"Retail Goods"
        }
    ],
    "sg:phone":"+1 985 641 6175",
    "sg:postcode":"70458",
    "sg:province":"LA",
    "wof:name":"Christy Music",
    "wof:placetype":"venue"
},
  "geometry": {"coordinates":[-89.766244,30.29401],"type":"Point"}
}