{
  "type": "Feature",
  "properties": {
    "iso:country":"US",
    "sg:address":"17283 Candies Rd",
    "sg:city":"Covington",
    "sg:classifiers":[
        {
            "category":"Building & Trades",
            "subcategory":"Construction",
            "type":"Services"
        }
    ],
    "sg:phone":"+1 985 892 8447",
    "sg:postcode":"70435",
    "sg:province":"LA",
    "sg:tags":[
        "excavating",
        "contractor"
    ],
    "wof:name":"Candies Excavation Inc",
    "wof:placetype":"venue"
},
  "geometry": {"coordinates":[-90.117891,30.604382],"type":"Point"}
}