{
  "type": "Feature",
  "properties": {
    "iso:country":"US",
    "sg:address":"503 Front St",
    "sg:city":"Jonesville",
    "sg:classifiers":[
        {
            "category":"Building & Trades",
            "subcategory":"Construction",
            "type":"Services"
        }
    ],
    "sg:phone":"+1 318 339 4707",
    "sg:postcode":"71343",
    "sg:province":"LA",
    "wof:name":"Johnson Brothers Construction",
    "wof:placetype":"venue"
},
  "geometry": {"coordinates":[-91.81422499999999,31.624178],"type":"Point"}
}