{
  "type": "Feature",
  "properties": {
    "iso:country":"US",
    "sg:address":"1508 Dehart Dr",
    "sg:city":"New Iberia",
    "sg:classifiers":[
        {
            "category":"Real Estate",
            "subcategory":"Real Estate Agent",
            "type":"Services"
        }
    ],
    "sg:phone":"+1 337 365 1461",
    "sg:postcode":"70560",
    "sg:province":"LA",
    "sg:tags":[
        "finding",
        "apartment",
        "rental"
    ],
    "wof:name":"Wayne Trahan Rentals",
    "wof:placetype":"venue"
},
  "geometry": {"coordinates":[-91.811162,29.974132],"type":"Point"}
}