{
  "type": "Feature",
  "properties": {
    "iso:country":"US",
    "sg:address":"732 Canal St",
    "sg:city":"New Orleans",
    "sg:classifiers":[
        {
            "category":"Shopping",
            "subcategory":"Shoes",
            "type":"Retail Goods"
        }
    ],
    "sg:phone":"+1 504 561 0807",
    "sg:postcode":"70130",
    "sg:province":"LA",
    "wof:name":"Kids Foot Locker",
    "wof:placetype":"venue"
},
  "geometry": {"coordinates":[-90.069588,29.953751],"type":"Point"}
}