{
  "type": "Feature",
  "properties": {
    "iso:country":"US",
    "sg:address":"707 N Coreil St",
    "sg:city":"Ville Platte",
    "sg:classifiers":[
        {
            "category":"Personal",
            "subcategory":"Beauty Salon",
            "type":"Services"
        }
    ],
    "sg:phone":"+1 337 363 1853",
    "sg:postcode":"70586",
    "sg:province":"LA",
    "wof:name":"None Callesia's Hair Salon",
    "wof:placetype":"venue"
},
  "geometry": {"coordinates":[-92.273608,30.69506],"type":"Point"}
}