{
  "type": "Feature",
  "properties": {
    "iso:country":"US",
    "sg:address":"3019 Breard St",
    "sg:city":"Monroe",
    "sg:classifiers":[
        {
            "category":"Home & Garden",
            "subcategory":"Carpets & Floor Coverings",
            "type":"Retail Goods"
        }
    ],
    "sg:phone":"+1 318 322 5655",
    "sg:postcode":"71201",
    "sg:province":"LA",
    "sg:tags":[
        "dealer",
        "rug"
    ],
    "wof:name":"Keith Young's Inc",
    "wof:placetype":"venue"
},
  "geometry": {"coordinates":[-92.08605,32.52525],"type":"Point"}
}