{
  "type": "Feature",
  "properties": {
    "iso:country":"US",
    "sg:address":"330 Feu Follet Rd",
    "sg:city":"Lafayette",
    "sg:classifiers":[
        {
            "category":"Real Estate",
            "subcategory":"Real Estate Operator",
            "type":"Services"
        }
    ],
    "sg:phone":"+1 337 237 8348",
    "sg:postcode":"70508",
    "sg:province":"LA",
    "sg:tags":[
        "apartment"
    ],
    "wof:name":"Bayou Oaks Apartments",
    "wof:placetype":"venue"
},
  "geometry": {"coordinates":[-92.01246500000001,30.179708],"type":"Point"}
}