{
  "type": "Feature",
  "properties": {
    "iso:country":"US",
    "sg:address":"2004 J Marvin Magee Dr",
    "sg:city":"Franklinton",
    "sg:classifiers":[
        {
            "category":"Health Services",
            "subcategory":"Doctor",
            "type":"Services"
        }
    ],
    "sg:phone":"+1 985 839 3555",
    "sg:postcode":"70438",
    "sg:province":"LA",
    "sg:tags":[
        "physician",
        "surgeon"
    ],
    "wof:name":"Franklinton Rural Health Clnc",
    "wof:placetype":"venue"
},
  "geometry": {"coordinates":[-90.153333,30.832455],"type":"Point"}
}