{
  "type": "Feature",
  "properties": {
    "addr:full":"224 Finks Hideaway Rd Monroe LA 71203",
    "addr:housenumber":"224",
    "addr:postcode":"71203",
    "addr:street":"Finks Hideaway Rd",
    "iso:country":"US",
    "sg:address":"224 Finks Hideaway Rd",
    "sg:city":"Monroe",
    "sg:classifiers":[
        {
            "category":"Real Estate",
            "subcategory":"Real Estate Operator",
            "type":"Services"
        }
    ],
    "sg:phone":"+1 318 343 7929",
    "sg:postcode":"71203",
    "sg:province":"LA",
    "sg:tags":[
        "apartment"
    ],
    "wof:name":"Pinnacle",
    "wof:placetype":"venue"
},
  "geometry": {"coordinates":[-92.07153,32.568385],"type":"Point"}
}