{
  "type": "Feature",
  "properties": {
    "iso:country":"US",
    "sg:address":"9000 Airline Hwy",
    "sg:city":"Baton Rouge",
    "sg:classifiers":[
        {
            "category":"Organizations",
            "subcategory":"Non-profit Organization",
            "type":"Services"
        }
    ],
    "sg:phone":"+1 225 231 5578",
    "sg:postcode":"70815",
    "sg:province":"LA",
    "sg:tags":[
        "breastfeeding",
        "information",
        "supply"
    ],
    "wof:name":"Woman's Touch Boutique",
    "wof:placetype":"venue"
},
  "geometry": {"coordinates":[-91.090615,30.445606],"type":"Point"}
}