{
  "type": "Feature",
  "properties": {
    "iso:country":"US",
    "sg:address":"1757 N River Rd",
    "sg:city":"Port Allen",
    "sg:classifiers":[
        {
            "category":"Mining & Drilling",
            "type":"Manufacturing & Wholesale Goods"
        }
    ],
    "sg:phone":"+1 225 383 1680",
    "sg:postcode":"70767",
    "sg:province":"LA",
    "sg:tags":[
        "limestone"
    ],
    "wof:name":"Construction Aggregate Supply",
    "wof:placetype":"venue"
},
  "geometry": {"coordinates":[-91.202146,30.473158],"type":"Point"}
}