{
  "type": "Feature",
  "properties": {
    "addr:full":"1428 Seabord Dr Baton Rouge LA 70810",
    "addr:housenumber":"1428",
    "addr:postcode":"70810",
    "addr:street":"Seabord Dr",
    "iso:country":"US",
    "sg:address":"1428 Seabord Dr",
    "sg:city":"Baton Rouge",
    "sg:classifiers":[
        {
            "category":"Building & Trades",
            "subcategory":"Construction",
            "type":"Services"
        }
    ],
    "sg:phone":"+1 225 766 7714",
    "sg:postcode":"70810",
    "sg:province":"LA",
    "sg:tags":[
        "general",
        "contractor"
    ],
    "wof:name":"H & K Construction Co",
    "wof:placetype":"venue"
},
  "geometry": {"coordinates":[-91.12465899999999,30.357041],"type":"Point"}
}