{
  "type": "Feature",
  "properties": {
    "iso:country":"US",
    "sg:address":"1221 Gardere Ln",
    "sg:city":"Baton Rouge",
    "sg:classifiers":[
        {
            "category":"Personal",
            "subcategory":"Barber",
            "type":"Services"
        }
    ],
    "sg:phone":"+1 225 765 7575",
    "sg:postcode":"70820",
    "sg:province":"LA",
    "wof:name":"Shelvin's Barber Shop",
    "wof:placetype":"venue"
},
  "geometry": {"coordinates":[-91.126869,30.35547],"type":"Point"}
}