{
  "type": "Feature",
  "properties": {
    "addr:full":"4002 Johnston St Lafayette LA 70503",
    "addr:housenumber":"4002",
    "addr:postcode":"70503",
    "addr:street":"Johnston St",
    "iso:country":"US",
    "sg:address":"4002 Johnston St",
    "sg:city":"Lafayette",
    "sg:classifiers":[
        {
            "category":"Shopping",
            "subcategory":"Clothing, Apparel, & Fashions",
            "type":"Retail Goods"
        }
    ],
    "sg:phone":"+1 337 984 4308",
    "sg:postcode":"70503",
    "sg:province":"LA",
    "sg:tags":[
        "western"
    ],
    "wof:name":"Cal's Western Store",
    "wof:placetype":"venue"
},
  "geometry": {"coordinates":[-92.05616999999999,30.19803],"type":"Point"}
}