{
  "type": "Feature",
  "properties": {
    "iso:country":"US",
    "sg:address":"1500 Veterans Memorial Blvd",
    "sg:city":"Kenner",
    "sg:classifiers":[
        {
            "category":"Shopping",
            "subcategory":"Pharmacy",
            "type":"Retail Goods"
        }
    ],
    "sg:phone":"+1 504 712 9272",
    "sg:postcode":"70062",
    "sg:province":"LA",
    "wof:name":"First Call Pharmacy",
    "wof:placetype":"venue"
},
  "geometry": {"coordinates":[-90.24786400000001,30.007083],"type":"Point"}
}