{
  "type": "Feature",
  "properties": {
    "addr:full":"100 Thomas St Abbeville LA 70510",
    "addr:housenumber":"100",
    "addr:postcode":"70510",
    "addr:street":"Thomas St",
    "iso:country":"US",
    "sg:address":"100 Thomas St",
    "sg:city":"Abbeville",
    "sg:classifiers":[
        {
            "category":"Sports & Exercise",
            "subcategory":"Gym",
            "type":"Entertainment"
        }
    ],
    "sg:phone":"+1 337 893 8199",
    "sg:postcode":"70510",
    "sg:province":"LA",
    "sg:tags":[
        "club",
        "health",
        "studio",
        "gymnasium"
    ],
    "wof:name":"Curves For Women",
    "wof:placetype":"venue"
},
  "geometry": {"coordinates":[-92.145011,29.978102],"type":"Point"}
}