{
  "type": "Feature",
  "properties": {
    "iso:country":"US",
    "sg:address":"4253 Odell St",
    "sg:city":"Baton Rouge",
    "sg:classifiers":[
        {
            "category":"Organizations",
            "subcategory":"Religious Organization",
            "type":"Services"
        }
    ],
    "sg:phone":"+1 225 387 0292",
    "sg:postcode":"70802",
    "sg:province":"LA",
    "wof:name":"Christian Faith Church of God",
    "wof:placetype":"venue"
},
  "geometry": {"coordinates":[-91.147347,30.459662],"type":"Point"}
}