{
  "type": "Feature",
  "properties": {
    "iso:country":"US",
    "sg:address":"320 Duson Ave",
    "sg:city":"Iota",
    "sg:classifiers":[
        {
            "category":"Professional",
            "subcategory":"Lawyer & Legal Services",
            "type":"Services"
        }
    ],
    "sg:phone":"+1 337 779 3661",
    "sg:postcode":"70543",
    "sg:province":"LA",
    "sg:tags":[
        "attorney"
    ],
    "wof:name":"Robert K Guillory & Assoc",
    "wof:placetype":"venue"
},
  "geometry": {"coordinates":[-92.493289,30.330311],"type":"Point"}
}