{
  "type": "Feature",
  "properties": {
    "iso:country":"US",
    "sg:address":"4118 Magazine St",
    "sg:city":"New Orleans",
    "sg:classifiers":[
        {
            "category":"Shopping",
            "subcategory":"Used Merchandise",
            "type":"Retail Goods"
        }
    ],
    "sg:phone":"+1 504 891 5600",
    "sg:postcode":"70115",
    "sg:province":"LA",
    "sg:tags":[
        "antique"
    ],
    "wof:name":"Royal Crescent Antiques",
    "wof:placetype":"venue"
},
  "geometry": {"coordinates":[-90.098902,29.920931],"type":"Point"}
}