{
  "type": "Feature",
  "properties": {
    "iso:country":"US",
    "sg:address":"2375 Tchoupitoulas St",
    "sg:city":"New Orleans",
    "sg:classifiers":[
        {
            "category":"Retail",
            "subcategory":"Repair Shop",
            "type":"Services"
        }
    ],
    "sg:phone":"+1 504 525 1018",
    "sg:postcode":"70130",
    "sg:province":"LA",
    "sg:tags":[
        "refinishing",
        "furniture"
    ],
    "wof:name":"European Restorations",
    "wof:placetype":"venue"
},
  "geometry": {"coordinates":[-90.073986,29.922145],"type":"Point"}
}