{
  "type": "Feature",
  "properties": {
    "iso:country":"US",
    "sg:address":"635 E Admiral Doyle Dr",
    "sg:city":"New Iberia",
    "sg:classifiers":[
        {
            "category":"Restaurant",
            "type":"Food & Drink"
        }
    ],
    "sg:menulink":"http://www.allmenus.com/la/new-iberia/72969-pizza-hut/menu/",
    "sg:phone":"+1 337 364 1176",
    "sg:postcode":"70560",
    "sg:province":"LA",
    "sg:tags":[
        "american",
        "pizza"
    ],
    "wof:name":"Pizza Hut",
    "wof:placetype":"venue"
},
  "geometry": {"coordinates":[-91.829313,29.989539],"type":"Point"}
}