{
  "type": "Feature",
  "properties": {
    "iso:country":"US",
    "sg:address":"5937 Marigny St",
    "sg:city":"New Orleans",
    "sg:classifiers":[
        {
            "category":"Building & Trades",
            "subcategory":"Electrical",
            "type":"Services"
        }
    ],
    "sg:phone":"+1 504 891 0353",
    "sg:postcode":"70122",
    "sg:province":"LA",
    "sg:tags":[
        "electrical",
        "contractor"
    ],
    "wof:name":"Excel Electric Inc",
    "wof:placetype":"venue"
},
  "geometry": {"coordinates":[-90.059505,30.019609],"type":"Point"}
}