{
  "type": "Feature",
  "properties": {
    "iso:country":"US",
    "sg:address":"1601 Royal Ave",
    "sg:city":"Monroe",
    "sg:classifiers":[
        {
            "category":"Health Services",
            "subcategory":"Doctor",
            "type":"Services"
        }
    ],
    "sg:phone":"+1 318 361 0898",
    "sg:postcode":"71201",
    "sg:province":"LA",
    "sg:tags":[
        "dentist"
    ],
    "wof:name":"Cascio & Cascio",
    "wof:placetype":"venue"
},
  "geometry": {"coordinates":[-92.11189899999999,32.519097],"type":"Point"}
}