{
  "type": "Feature",
  "properties": {
    "addr:full":"1247 Jaycee Dr Slidell LA 70460",
    "addr:housenumber":"1247",
    "addr:postcode":"70460",
    "addr:street":"Jaycee Dr",
    "iso:country":"US",
    "sg:address":"1247 Jaycee Dr",
    "sg:city":"Slidell",
    "sg:classifiers":[
        {
            "category":"Organizations",
            "subcategory":"Religious Organization",
            "type":"Services"
        }
    ],
    "sg:phone":"+1 985 649 4973",
    "sg:postcode":"70460",
    "sg:province":"LA",
    "sg:tags":[
        "church"
    ],
    "wof:name":"New Life Missionary Baptist",
    "wof:placetype":"venue"
},
  "geometry": {"coordinates":[-89.801107,30.285701],"type":"Point"}
}