{
  "type": "Feature",
  "properties": {
    "iso:country":"US",
    "sg:address":"1345 W Willow St",
    "sg:city":"Lafayette",
    "sg:classifiers":[
        {
            "category":"Real Estate",
            "subcategory":"Real Estate Operator",
            "type":"Services"
        }
    ],
    "sg:phone":"+1 337 269 4050",
    "sg:postcode":"70506",
    "sg:province":"LA",
    "sg:tags":[
        "apartment"
    ],
    "wof:name":"Maison De Lemairie",
    "wof:placetype":"venue"
},
  "geometry": {"coordinates":[-92.037999,30.244415],"type":"Point"}
}