{
  "type": "Feature",
  "properties": {
    "addr:full":"807 S Lewis St New Iberia LA 70560",
    "addr:housenumber":"807",
    "addr:postcode":"70560",
    "addr:street":"S Lewis St",
    "iso:country":"US",
    "sg:address":"807 S Lewis St",
    "sg:city":"New Iberia",
    "sg:classifiers":[
        {
            "category":"Shopping",
            "subcategory":"Tobacco",
            "type":"Retail Goods"
        }
    ],
    "sg:phone":"+1 337 367 5017",
    "sg:postcode":"70560",
    "sg:province":"LA",
    "sg:tags":[
        "cigarette",
        "cigar",
        "dealer"
    ],
    "wof:name":"Tobacco Time",
    "wof:placetype":"venue"
},
  "geometry": {"coordinates":[-91.810259,29.993173],"type":"Point"}
}