{
  "type": "Feature",
  "properties": {
    "addr:full":"1500 N Hwy 190 Covington LA 70433",
    "addr:housenumber":"1500",
    "addr:postcode":"70433",
    "addr:street":"N Hwy 190",
    "iso:country":"US",
    "sg:address":"1500 N Hwy 190",
    "sg:city":"Covington",
    "sg:classifiers":[
        {
            "category":"Personal",
            "subcategory":"Beauty Salon",
            "type":"Services"
        }
    ],
    "sg:phone":"+1 985 809 7805",
    "sg:postcode":"70433",
    "sg:province":"LA",
    "sg:website":"www.supercuts.com",
    "wof:name":"Supercuts",
    "wof:placetype":"venue"
},
  "geometry": {"coordinates":[-90.08203399999999,30.453409],"type":"Point"}
}