{
  "type": "Feature",
  "properties": {
    "addr:full":"3636 S Sherwood Forest Blvd Baton Rouge LA 70816",
    "addr:housenumber":"3636",
    "addr:postcode":"70816",
    "addr:street":"S Sherwood Forest Blvd",
    "iso:country":"US",
    "sg:address":"3636 S Sherwood Forest Blvd",
    "sg:city":"Baton Rouge",
    "sg:classifiers":[
        {
            "category":"Professional",
            "subcategory":"Lawyer & Legal Services",
            "type":"Services"
        }
    ],
    "sg:phone":"+1 225 291 3798",
    "sg:postcode":"70816",
    "sg:province":"LA",
    "sg:tags":[
        "attorney"
    ],
    "wof:name":"Pelican State Title Co Inc",
    "wof:placetype":"venue"
},
  "geometry": {"coordinates":[-91.05157199999999,30.419582],"type":"Point"}
}