{
  "type": "Feature",
  "properties": {
    "iso:country":"US",
    "sg:address":"1127 Highland Ave",
    "sg:city":"Shreveport",
    "sg:classifiers":[
        {
            "category":"Professional",
            "subcategory":"Business Services",
            "type":"Services"
        }
    ],
    "sg:phone":"+1 318 221 7536",
    "sg:postcode":"71101",
    "sg:province":"LA",
    "sg:tags":[
        "foreground",
        "music"
    ],
    "wof:name":"Specialty Service Company",
    "wof:placetype":"venue"
},
  "geometry": {"coordinates":[-93.73954500000001,32.501116],"type":"Point"}
}