{
  "type": "Feature",
  "properties": {
    "iso:country":"US",
    "sg:address":"76 Christine Dr",
    "sg:city":"Boyce",
    "sg:classifiers":[
        {
            "category":"Retail",
            "subcategory":"Auto Repair",
            "type":"Services"
        }
    ],
    "sg:phone":"+1 318 448 8468",
    "sg:postcode":"71409",
    "sg:province":"LA",
    "sg:tags":[
        "glass",
        "coating",
        "tinting"
    ],
    "wof:name":"Ace Glass Tinting",
    "wof:placetype":"venue"
},
  "geometry": {"coordinates":[-92.580945,31.349887],"type":"Point"}
}