{
  "type": "Feature",
  "properties": {
    "addr:full":"2609 Veterans Memorial Blvd Kenner LA 70062",
    "addr:housenumber":"2609",
    "addr:postcode":"70062",
    "addr:street":"Veterans Memorial Blvd",
    "iso:country":"US",
    "sg:address":"2609 Veterans Memorial Blvd",
    "sg:city":"Kenner",
    "sg:classifiers":[
        {
            "category":"Banks & Credit Unions",
            "subcategory":"Bank",
            "type":"Services"
        }
    ],
    "sg:phone":"+1 504 207 4167",
    "sg:postcode":"70062",
    "sg:province":"LA",
    "wof:name":"Parish National Bank",
    "wof:placetype":"venue"
},
  "geometry": {"coordinates":[-90.231863,30.005895],"type":"Point"}
}