{
  "type": "Feature",
  "properties": {
    "iso:country":"US",
    "sg:address":"4909 Cameron St",
    "sg:city":"Lafayette",
    "sg:classifiers":[
        {
            "category":"Shopping",
            "subcategory":"Party Supplies",
            "type":"Retail Goods"
        }
    ],
    "sg:phone":"+1 337 769 8034",
    "sg:postcode":"70506",
    "sg:province":"LA",
    "sg:website":"www.beadsgalore.net",
    "wof:name":"Beads Galore",
    "wof:placetype":"venue"
},
  "geometry": {"coordinates":[-92.079777,30.231969],"type":"Point"}
}