{
  "type": "Feature",
  "properties": {
    "addr:full":"1080 Westview St Abbeville LA 70510",
    "addr:housenumber":"1080",
    "addr:postcode":"70510",
    "addr:street":"Westview St",
    "iso:country":"US",
    "sg:address":"1080 Westview St",
    "sg:city":"Abbeville",
    "sg:classifiers":[
        {
            "category":"Wholesale",
            "subcategory":"Electrical",
            "type":"Manufacturing & Wholesale Goods"
        }
    ],
    "sg:phone":"+1 337 893 4720",
    "sg:postcode":"70510",
    "sg:province":"LA",
    "sg:tags":[
        "electric",
        "motor"
    ],
    "wof:name":"Cormier Electric Motor Shop",
    "wof:placetype":"venue"
},
  "geometry": {"coordinates":[-92.15418099999999,29.966094],"type":"Point"}
}