{
  "type": "Feature",
  "properties": {
    "iso:country":"US",
    "sg:address":"116 Dugas St",
    "sg:city":"Morgan City",
    "sg:classifiers":[
        {
            "category":"Professional",
            "type":"Services"
        }
    ],
    "sg:phone":"+1 985 385 2041",
    "sg:postcode":"70380",
    "sg:province":"LA",
    "sg:tags":[
        "establishment"
    ],
    "wof:name":"Ed Bell & Assoc",
    "wof:placetype":"venue"
},
  "geometry": {"coordinates":[-91.21258400000001,29.701123],"type":"Point"}
}