{
  "type": "Feature",
  "properties": {
    "addr:full":"1000 Jackson St Monroe LA 71201",
    "addr:housenumber":"1000",
    "addr:postcode":"71201",
    "addr:street":"Jackson St",
    "iso:country":"US",
    "sg:address":"1000 Jackson St",
    "sg:city":"Monroe",
    "sg:classifiers":[
        {
            "category":"Food & Beverages",
            "subcategory":"Groceries & Convenience Stores",
            "type":"Retail Goods"
        }
    ],
    "sg:phone":"+1 318 388 1184",
    "sg:postcode":"71201",
    "sg:province":"LA",
    "wof:name":"Jackson Street Citgo",
    "wof:placetype":"venue"
},
  "geometry": {"coordinates":[-92.11179,32.492759],"type":"Point"}
}