{
  "type": "Feature",
  "properties": {
    "addr:full":"6326 State Hwy 996 Lp Belle Rose LA 70341",
    "addr:housenumber":"6326",
    "addr:postcode":"70341",
    "addr:street":"State Hwy 996 Lp Belle Rose",
    "iso:country":"US",
    "sg:address":"6326 State Hwy 996 Lp",
    "sg:city":"Belle Rose",
    "sg:classifiers":[
        {
            "category":"Wholesale",
            "subcategory":"Chemicals & Plastics",
            "type":"Manufacturing & Wholesale Goods"
        }
    ],
    "sg:phone":"+1 985 369 6045",
    "sg:postcode":"70341",
    "sg:province":"LA",
    "wof:name":"Acadian Gas Pipeline",
    "wof:placetype":"venue"
},
  "geometry": {"coordinates":[-91.114086,30.05481],"type":"Point"}
}