{
  "type": "Feature",
  "properties": {
    "addr:full":"808 Main St Pineville LA 71360",
    "addr:housenumber":"808",
    "addr:postcode":"71360",
    "addr:street":"Main St",
    "iso:country":"US",
    "sg:address":"808 Main St",
    "sg:city":"Pineville",
    "sg:classifiers":[
        {
            "category":"Insurance",
            "subcategory":"Insurance Agent",
            "type":"Services"
        }
    ],
    "sg:phone":"+1 318 442 3276",
    "sg:postcode":"71360",
    "sg:province":"LA",
    "wof:name":"Shelter Insurance",
    "wof:placetype":"venue"
},
  "geometry": {"coordinates":[-92.432878,31.323785],"type":"Point"}
}