{
  "type": "Feature",
  "properties": {
    "addr:full":"2179 Denley Rd Houma LA 70363",
    "addr:housenumber":"2179",
    "addr:postcode":"70363",
    "addr:street":"Denley Rd",
    "iso:country":"US",
    "sg:address":"2179 Denley Rd",
    "sg:city":"Houma",
    "sg:classifiers":[
        {
            "category":"Building & Trades",
            "subcategory":"Construction",
            "type":"Services"
        }
    ],
    "sg:phone":"+1 985 879 2171",
    "sg:postcode":"70363",
    "sg:province":"LA",
    "sg:tags":[
        "general",
        "contractor"
    ],
    "wof:name":"MMT LLC",
    "wof:placetype":"venue"
},
  "geometry": {"coordinates":[-90.68359700000001,29.550713],"type":"Point"}
}