{
  "type": "Feature",
  "properties": {
    "addr:full":"814 N Howard Ave Metairie LA 70003",
    "addr:housenumber":"814",
    "addr:postcode":"70003",
    "addr:street":"N Howard Ave",
    "iso:country":"US",
    "sg:address":"814 N Howard Ave",
    "sg:city":"Metairie",
    "sg:classifiers":[
        {
            "category":"Bars & Pubs",
            "type":"Food & Drink"
        }
    ],
    "sg:phone":"+1 504 737 9045",
    "sg:postcode":"70003",
    "sg:province":"LA",
    "wof:name":"Uncle Joe's Bar",
    "wof:placetype":"venue"
},
  "geometry": {"coordinates":[-90.220072,29.984283],"type":"Point"}
}