{
  "type": "Feature",
  "properties": {
    "iso:country":"US",
    "sg:address":"15155 Garden Park Ave",
    "sg:city":"Baton Rouge",
    "sg:classifiers":[
        {
            "category":"Professional",
            "subcategory":"Accounting & Tax Preparation",
            "type":"Services"
        }
    ],
    "sg:phone":"+1 225 755 2666",
    "sg:postcode":"70817",
    "sg:province":"LA",
    "sg:tags":[
        "return"
    ],
    "wof:name":"Shirley Pourciau",
    "wof:placetype":"venue"
},
  "geometry": {"coordinates":[-91.018073,30.403448],"type":"Point"}
}