{
  "type": "Feature",
  "properties": {
    "addr:full":"610 1st St Jonesville LA 71343",
    "addr:housenumber":"610",
    "addr:postcode":"71343",
    "addr:street":"1St St",
    "iso:country":"US",
    "sg:address":"610 1st St",
    "sg:city":"Jonesville",
    "sg:classifiers":[
        {
            "category":"Professional",
            "subcategory":"Lawyer & Legal Services",
            "type":"Services"
        }
    ],
    "sg:phone":"+1 318 339 7238",
    "sg:postcode":"71343",
    "sg:province":"LA",
    "sg:tags":[
        "attorney"
    ],
    "wof:name":"H James Lossin Sr Law Office",
    "wof:placetype":"venue"
},
  "geometry": {"coordinates":[-91.817573,31.630076],"type":"Point"}
}