{
  "type": "Feature",
  "properties": {
    "iso:country":"US",
    "sg:address":"415 Wood St",
    "sg:city":"Monroe",
    "sg:classifiers":[
        {
            "category":"Health Services",
            "subcategory":"Doctor",
            "type":"Services"
        }
    ],
    "sg:phone":"+1 318 388 0193",
    "sg:postcode":"71201",
    "sg:province":"LA",
    "sg:tags":[
        "physician",
        "surgeon"
    ],
    "wof:name":"Pathology",
    "wof:placetype":"venue"
},
  "geometry": {"coordinates":[-92.11275000000001,32.50108],"type":"Point"}
}