{
  "type": "Feature",
  "properties": {
    "iso:country":"US",
    "sg:address":"1804 Center St",
    "sg:city":"New Iberia",
    "sg:classifiers":[
        {
            "category":"Retail",
            "subcategory":"Auto Repair",
            "type":"Services"
        }
    ],
    "sg:phone":"+1 337 365 6055",
    "sg:postcode":"70560",
    "sg:province":"LA",
    "sg:tags":[
        "wrecker"
    ],
    "wof:name":"Maricle's Body & Paint Shop",
    "wof:placetype":"venue"
},
  "geometry": {"coordinates":[-91.839738,29.986228],"type":"Point"}
}