{
  "type": "Feature",
  "properties": {
    "iso:country":"US",
    "sg:address":"721 Booth Dr",
    "sg:city":"Shreveport",
    "sg:classifiers":[
        {
            "category":"Insurance",
            "subcategory":"Insurance Agent",
            "type":"Services"
        }
    ],
    "sg:phone":"+1 318 425 4765",
    "sg:postcode":"71107",
    "sg:province":"LA",
    "wof:name":"Church Insurance Specialists",
    "wof:placetype":"venue"
},
  "geometry": {"coordinates":[-93.782449,32.566343],"type":"Point"}
}