{
  "type": "Feature",
  "properties": {
    "iso:country":"US",
    "sg:address":"12090 S Harrells Ferry Rd",
    "sg:city":"Baton Rouge",
    "sg:classifiers":[
        {
            "category":"Home & Garden",
            "subcategory":"Building Materials",
            "type":"Retail Goods"
        }
    ],
    "sg:phone":"+1 225 298 3223",
    "sg:postcode":"70816",
    "sg:province":"LA",
    "sg:tags":[
        "glass",
        "window",
        "plate"
    ],
    "wof:name":"Max Toler Glass",
    "wof:placetype":"venue"
},
  "geometry": {"coordinates":[-91.045164,30.432127],"type":"Point"}
}