{
  "type": "Feature",
  "properties": {
    "addr:full":"250 Main St Baker LA 70714",
    "addr:housenumber":"250",
    "addr:postcode":"70714",
    "addr:street":"Main St",
    "iso:country":"US",
    "sg:address":"250 Main St",
    "sg:city":"Baker",
    "sg:classifiers":[
        {
            "category":"Shopping",
            "subcategory":"Department Store",
            "type":"Retail Goods"
        }
    ],
    "sg:phone":"+1 225 774 8116",
    "sg:postcode":"70714",
    "sg:province":"LA",
    "sg:tags":[
        "shop"
    ],
    "wof:name":"Big Lots",
    "wof:placetype":"venue"
},
  "geometry": {"coordinates":[-91.169464,30.580508],"type":"Point"}
}