{
  "type": "Feature",
  "properties": {
    "iso:country":"US",
    "sg:address":"4227 Canal St",
    "sg:city":"New Orleans",
    "sg:classifiers":[
        {
            "category":"Professional",
            "subcategory":"Accounting & Tax Preparation",
            "type":"Services"
        }
    ],
    "sg:phone":"+1 504 486 7275",
    "sg:postcode":"70119",
    "sg:province":"LA",
    "sg:tags":[
        "accountant"
    ],
    "sg:website":"www.ericksenkrentel.com",
    "wof:name":"EKCL Financial Advisors",
    "wof:placetype":"venue"
},
  "geometry": {"coordinates":[-90.102869,29.976261],"type":"Point"}
}