{
  "type": "Feature",
  "properties": {
    "addr:full":"3467 New Monroe Rd Bastrop LA 71220",
    "addr:housenumber":"3467",
    "addr:postcode":"71220",
    "addr:street":"New Monroe Rd",
    "iso:country":"US",
    "sg:address":"3467 New Monroe Rd",
    "sg:city":"Bastrop",
    "sg:classifiers":[
        {
            "category":"Autos & Motor Vehicles",
            "subcategory":"Fuel & Gas Station",
            "type":"Retail Goods"
        }
    ],
    "sg:phone":"+1 318 283 6188",
    "sg:postcode":"71220",
    "sg:province":"LA",
    "sg:tags":[
        "oil"
    ],
    "wof:name":"Point Texaco",
    "wof:placetype":"venue"
},
  "geometry": {"coordinates":[-91.952613,32.772249],"type":"Point"}
}