{
  "type": "Feature",
  "properties": {
    "iso:country":"US",
    "sg:address":"4212 W Congress St",
    "sg:city":"Lafayette",
    "sg:classifiers":[
        {
            "category":"Health Services",
            "subcategory":"Clinic",
            "type":"Services"
        }
    ],
    "sg:phone":"+1 337 991 9290",
    "sg:postcode":"70506",
    "sg:province":"LA",
    "wof:name":"United Health Care Group",
    "wof:placetype":"venue"
},
  "geometry": {"coordinates":[-92.075205,30.195991],"type":"Point"}
}