{
  "type": "Feature",
  "properties": {
    "addr:full":"2014 S Burnside Ave Gonzales LA 70737",
    "addr:housenumber":"2014",
    "addr:postcode":"70737",
    "addr:street":"S Burnside Ave",
    "iso:country":"US",
    "sg:address":"2014 S Burnside Ave",
    "sg:city":"Gonzales",
    "sg:classifiers":[
        {
            "category":"Real Estate",
            "subcategory":"Real Estate Agent",
            "type":"Services"
        }
    ],
    "sg:phone":"+1 225 647 5337",
    "sg:postcode":"70737",
    "sg:province":"LA",
    "sg:website":"www.eastbankrealty.com",
    "wof:name":"East Bank Realty Inc",
    "wof:placetype":"venue"
},
  "geometry": {"coordinates":[-90.920514,30.216969],"type":"Point"}
}