{
  "type": "Feature",
  "properties": {
    "iso:country":"US",
    "sg:address":"101 State Rte 14",
    "sg:city":"Delcambre",
    "sg:classifiers":[
        {
            "category":"Professional",
            "type":"Services"
        }
    ],
    "sg:phone":"+1 337 685 3041",
    "sg:postcode":"70528",
    "sg:province":"LA",
    "sg:tags":[
        "establishment"
    ],
    "wof:name":"Saunier J A Enterprise Inc",
    "wof:placetype":"venue"
},
  "geometry": {"coordinates":[-91.98791799999999,29.951621],"type":"Point"}
}