{
  "type": "Feature",
  "properties": {
    "iso:country":"US",
    "sg:address":"3001 17th St",
    "sg:city":"Metairie",
    "sg:classifiers":[
        {
            "category":"Building & Trades",
            "subcategory":"Construction",
            "type":"Services"
        }
    ],
    "sg:phone":"+1 504 833 8291",
    "sg:postcode":"70002",
    "sg:province":"LA",
    "sg:tags":[
        "contractor"
    ],
    "wof:name":"Mechanical Construction Co",
    "wof:placetype":"venue"
},
  "geometry": {"coordinates":[-90.15334900000001,30.009096],"type":"Point"}
}