{
  "type": "Feature",
  "properties": {
    "iso:country":"US",
    "sg:address":"5167 Greenwell Springs Rd",
    "sg:city":"Baton Rouge",
    "sg:classifiers":[
        {
            "category":"Building & Trades",
            "subcategory":"Plumbing",
            "type":"Services"
        }
    ],
    "sg:phone":"+1 225 926 5255",
    "sg:postcode":"70806",
    "sg:province":"LA",
    "sg:tags":[
        "conditioning",
        "air",
        "system",
        "contractor"
    ],
    "wof:name":"Hinton Heating-Air Cond Inc",
    "wof:placetype":"venue"
},
  "geometry": {"coordinates":[-91.134417,30.465263],"type":"Point"}
}