{
  "type": "Feature",
  "properties": {
    "iso:country":"US",
    "sg:address":"1104 Frankel Ave",
    "sg:city":"Metairie",
    "sg:classifiers":[
        {
            "category":"Real Estate",
            "subcategory":"Real Estate Operator",
            "type":"Services"
        }
    ],
    "sg:phone":"+1 504 733 2373",
    "sg:postcode":"70003",
    "sg:province":"LA",
    "sg:tags":[
        "property",
        "rental"
    ],
    "wof:name":"Cain Properties",
    "wof:placetype":"venue"
},
  "geometry": {"coordinates":[-90.213179,29.986895],"type":"Point"}
}