{
  "type": "Feature",
  "properties": {
    "iso:country":"US",
    "sg:address":"5202 Old Jeanerette Rd",
    "sg:city":"New Iberia",
    "sg:classifiers":[
        {
            "category":"Building & Trades",
            "subcategory":"Construction",
            "type":"Services"
        }
    ],
    "sg:phone":"+1 337 365 0256",
    "sg:postcode":"70563",
    "sg:province":"LA",
    "sg:tags":[
        "house"
    ],
    "wof:name":"Richards Construction",
    "wof:placetype":"venue"
},
  "geometry": {"coordinates":[-91.746132,29.977226],"type":"Point"}
}