{
  "type": "Feature",
  "properties": {
    "iso:country":"US",
    "sg:address":"3842 Independence Dr",
    "sg:city":"Alexandria",
    "sg:classifiers":[
        {
            "category":"Wholesale",
            "subcategory":"Medical Equipment & Supplies",
            "type":"Manufacturing & Wholesale Goods"
        }
    ],
    "sg:phone":"+1 318 487 8891",
    "sg:postcode":"71303",
    "sg:province":"LA",
    "sg:tags":[
        "physician",
        "surgeon"
    ],
    "wof:name":"Louisiana Nursing Supply",
    "wof:placetype":"venue"
},
  "geometry": {"coordinates":[-92.485702,31.299784],"type":"Point"}
}