{
  "type": "Feature",
  "properties": {
    "iso:country":"US",
    "sg:address":"1718 N University Ave",
    "sg:city":"Lafayette",
    "sg:classifiers":[
        {
            "category":"Travel",
            "subcategory":"Hotels & Motels",
            "type":"Entertainment"
        }
    ],
    "sg:phone":"+1 337 233 3339",
    "sg:postcode":"70507",
    "sg:province":"LA",
    "sg:website":"www.redroof.com",
    "wof:name":"Red Roof Inns",
    "wof:placetype":"venue"
},
  "geometry": {"coordinates":[-92.036697,30.2526],"type":"Point"}
}