{
  "type": "Feature",
  "properties": {
    "addr:full":"1413 Louisiana Ave New Orleans LA 70115",
    "addr:housenumber":"1413",
    "addr:postcode":"70115",
    "addr:street":"Louisiana Ave",
    "iso:country":"US",
    "sg:address":"1413 Louisiana Ave",
    "sg:city":"New Orleans",
    "sg:classifiers":[
        {
            "category":"Organizations",
            "subcategory":"Non-profit Organization",
            "type":"Services"
        }
    ],
    "sg:phone":"+1 504 897 3745",
    "sg:postcode":"70115",
    "sg:province":"LA",
    "wof:name":"NSCDA In Louisiana",
    "wof:placetype":"venue"
},
  "geometry": {"coordinates":[-90.090559,29.926805],"type":"Point"}
}