{
  "type": "Feature",
  "properties": {
    "iso:country":"US",
    "sg:address":"716 E 4th Ave",
    "sg:city":"Covington",
    "sg:classifiers":[
        {
            "category":"Professional",
            "subcategory":"Engineering",
            "type":"Services"
        }
    ],
    "sg:phone":"+1 985 892 4720",
    "sg:postcode":"70433",
    "sg:province":"LA",
    "sg:tags":[
        "environmental",
        "consulting"
    ],
    "wof:name":"Norman Murray & Associates",
    "wof:placetype":"venue"
},
  "geometry": {"coordinates":[-90.106003,30.457086],"type":"Point"}
}