{
  "type": "Feature",
  "properties": {
    "iso:country":"US",
    "sg:address":"2909 Division St",
    "sg:city":"Metairie",
    "sg:classifiers":[
        {
            "category":"Organizations",
            "subcategory":"Religious Organization",
            "type":"Services"
        }
    ],
    "sg:phone":"+1 504 454 0477",
    "sg:postcode":"70002",
    "sg:province":"LA",
    "wof:name":"Louisiana Sastang Society Inc",
    "wof:placetype":"venue"
},
  "geometry": {"coordinates":[-90.16443700000001,30.000652],"type":"Point"}
}