{
  "type": "Feature",
  "properties": {
    "iso:country":"US",
    "sg:address":"125 Pecan St",
    "sg:city":"Choudrant",
    "sg:classifiers":[
        {
            "category":"Organizations",
            "subcategory":"Religious Organization",
            "type":"Services"
        }
    ],
    "sg:phone":"+1 318 768 4388",
    "sg:postcode":"71227",
    "sg:province":"LA",
    "sg:tags":[
        "church"
    ],
    "wof:name":"Choudrant United Methodist Chr",
    "wof:placetype":"venue"
},
  "geometry": {"coordinates":[-92.516418,32.529521],"type":"Point"}
}