{
  "type": "Feature",
  "properties": {
    "iso:country":"US",
    "sg:address":"2901 Maplewood Dr",
    "sg:city":"Sulphur",
    "sg:classifiers":[
        {
            "category":"Manufacturing",
            "subcategory":"Printing",
            "type":"Manufacturing & Wholesale Goods"
        }
    ],
    "sg:phone":"+1 337 625 2075",
    "sg:postcode":"70663",
    "sg:province":"LA",
    "sg:tags":[
        "screen"
    ],
    "wof:name":"Precision Prints",
    "wof:placetype":"venue"
},
  "geometry": {"coordinates":[-93.344037,30.227444],"type":"Point"}
}