{
  "type": "Feature",
  "properties": {
    "iso:country":"US",
    "sg:address":"3635 Prytania St",
    "sg:city":"New Orleans",
    "sg:classifiers":[
        {
            "category":"Restaurant",
            "type":"Food & Drink"
        }
    ],
    "sg:menulink":"http://www.allmenus.com/la/new-orleans/221494-august-moon/menu/",
    "sg:phone":"+1 504 899 5129",
    "sg:postcode":"70115",
    "sg:province":"LA",
    "sg:tags":[
        "asian",
        "vietnamese"
    ],
    "wof:name":"August Moon",
    "wof:placetype":"venue"
},
  "geometry": {"coordinates":[-90.094128,29.925845],"type":"Point"}
}