{
  "type": "Feature",
  "properties": {
    "addr:full":"3600 General Degaulle Dr New Orleans LA 70114",
    "addr:housenumber":"3600",
    "addr:postcode":"70114",
    "addr:street":"General Degaulle Dr",
    "iso:country":"US",
    "sg:address":"3600 General Degaulle Dr",
    "sg:city":"New Orleans",
    "sg:classifiers":[
        {
            "category":"Shopping",
            "subcategory":"Florist",
            "type":"Retail Goods"
        }
    ],
    "sg:phone":"+1 504 523 1144",
    "sg:postcode":"70114",
    "sg:province":"LA",
    "wof:name":"John David Flowers",
    "wof:placetype":"venue"
},
  "geometry": {"coordinates":[-90.02222999999999,29.92567],"type":"Point"}
}