{
  "type": "Feature",
  "properties": {
    "iso:country":"US",
    "sg:address":"1622 Midway St",
    "sg:city":"Shreveport",
    "sg:classifiers":[
        {
            "category":"Organizations",
            "subcategory":"Religious Organization",
            "type":"Services"
        }
    ],
    "sg:phone":"+1 318 631 4467",
    "sg:postcode":"71108",
    "sg:province":"LA",
    "sg:tags":[
        "church"
    ],
    "wof:name":"Linwood Baptist Church",
    "wof:placetype":"venue"
},
  "geometry": {"coordinates":[-93.76474899999999,32.471011],"type":"Point"}
}