{
  "type": "Feature",
  "properties": {
    "addr:full":"1858 Forsythe Ave Monroe LA 71201",
    "addr:housenumber":"1858",
    "addr:postcode":"71201",
    "addr:street":"Forsythe Ave",
    "iso:country":"US",
    "sg:address":"1858 Forsythe Ave",
    "sg:city":"Monroe",
    "sg:classifiers":[
        {
            "category":"Restaurant",
            "type":"Food & Drink"
        }
    ],
    "sg:menulink":"http://www.allmenus.com/la/brownsville-bawcomville/132161-subway/menu/",
    "sg:phone":"+1 318 322 1387",
    "sg:postcode":"71201",
    "sg:province":"LA",
    "sg:tags":[
        "american",
        "sandwich"
    ],
    "wof:name":"Subway",
    "wof:placetype":"venue"
},
  "geometry": {"coordinates":[-92.11563099999999,32.530012],"type":"Point"}
}