{
  "type": "Feature",
  "properties": {
    "addr:full":"1100 C M Fagan Dr Hammond LA 70403",
    "addr:housenumber":"1100 c m",
    "addr:postcode":"70403",
    "addr:street":"Fagan Dr",
    "iso:country":"US",
    "sg:address":"1100 C M Fagan Dr",
    "sg:city":"Hammond",
    "sg:classifiers":[
        {
            "category":"Health Services",
            "subcategory":"Health Practitioner",
            "type":"Services"
        }
    ],
    "sg:phone":"+1 985 542 6664",
    "sg:postcode":"70403",
    "sg:province":"LA",
    "sg:tags":[
        "therapist",
        "physical"
    ],
    "wof:name":"Anatomix Physical Therapy",
    "wof:placetype":"venue"
},
  "geometry": {"coordinates":[-90.467623,30.48282],"type":"Point"}
}