{
  "type": "Feature",
  "properties": {
    "iso:country":"US",
    "sg:address":"1037 Bickham St",
    "sg:city":"Franklinton",
    "sg:classifiers":[
        {
            "category":"Professional",
            "subcategory":"Accounting & Tax Preparation",
            "type":"Services"
        }
    ],
    "sg:phone":"+1 985 839 4303",
    "sg:postcode":"70438",
    "sg:province":"LA",
    "sg:tags":[
        "accountant"
    ],
    "wof:name":"Tom R Richardson CPA",
    "wof:placetype":"venue"
},
  "geometry": {"coordinates":[-90.151948,30.846352],"type":"Point"}
}