{
  "type": "Feature",
  "properties": {
    "addr:full":"1539 River Oaks Rd E Harahan LA 70123",
    "addr:housenumber":"1539",
    "addr:postcode":"70123",
    "addr:street":"River Oaks Rd E Harahan",
    "iso:country":"US",
    "sg:address":"1539 River Oaks Rd E",
    "sg:city":"Harahan",
    "sg:classifiers":[
        {
            "category":"Building & Trades",
            "subcategory":"Electrical",
            "type":"Services"
        },
        {
            "category":"Utilities",
            "subcategory":"Telephone",
            "type":"Services"
        }
    ],
    "sg:phone":"+1 504 736 9455",
    "sg:postcode":"70123",
    "sg:province":"LA",
    "sg:tags":[
        "equipment",
        "telecommunication",
        "communications"
    ],
    "wof:name":"Universal Solutions LLC",
    "wof:placetype":"venue"
},
  "geometry": {"coordinates":[-90.20129300000001,29.963848],"type":"Point"}
}