{
  "type": "Feature",
  "properties": {
    "iso:country":"US",
    "sg:address":"16198 State Rte 23",
    "sg:city":"Belle Chasse",
    "sg:classifiers":[
        {
            "category":"Wholesale",
            "subcategory":"Fruits & Vegetables",
            "type":"Manufacturing & Wholesale Goods"
        }
    ],
    "sg:phone":"+1 504 656 2326",
    "sg:postcode":"70037",
    "sg:province":"LA",
    "sg:tags":[
        "shipper"
    ],
    "wof:name":"Ben Becnel Citrus Farm",
    "wof:placetype":"venue"
},
  "geometry": {"coordinates":[-89.97578,29.664551],"type":"Point"}
}