{
  "type": "Feature",
  "properties": {
    "iso:country":"US",
    "sg:address":"2300 N University Ave",
    "sg:city":"Lafayette",
    "sg:classifiers":[
        {
            "category":"Banks & Credit Unions",
            "subcategory":"Bank",
            "type":"Services"
        }
    ],
    "sg:phone":"+1 337 234 4586",
    "sg:postcode":"70507",
    "sg:province":"LA",
    "sg:tags":[
        "financing"
    ],
    "wof:name":"Morgan Discount Corp",
    "wof:placetype":"venue"
},
  "geometry": {"coordinates":[-92.042823,30.263519],"type":"Point"}
}