{
  "type": "Feature",
  "properties": {
    "iso:country":"US",
    "sg:address":"615 Morris Rd",
    "sg:city":"Deridder",
    "sg:classifiers":[
        {
            "category":"Manufacturing",
            "subcategory":"Furniture",
            "type":"Manufacturing & Wholesale Goods"
        }
    ],
    "sg:phone":"+1 337 463 8586",
    "sg:postcode":"70634",
    "sg:province":"LA",
    "sg:tags":[
        "remodeling",
        "cabinet"
    ],
    "wof:name":"Quality Custom Furnishing",
    "wof:placetype":"venue"
},
  "geometry": {"coordinates":[-93.27593899999999,30.815083],"type":"Point"}
}