{
  "type": "Feature",
  "properties": {
    "iso:country":"US",
    "sg:address":"1734 N Tallowood Dr",
    "sg:city":"Lake Charles",
    "sg:classifiers":[
        {
            "category":"Professional",
            "subcategory":"Management & Consulting",
            "type":"Services"
        }
    ],
    "sg:phone":"+1 337 478 5058",
    "sg:postcode":"70605",
    "sg:province":"LA",
    "sg:tags":[
        "business"
    ],
    "wof:name":"Canning Consulting Inc",
    "wof:placetype":"venue"
},
  "geometry": {"coordinates":[-93.245779,30.166778],"type":"Point"}
}