{
  "type": "Feature",
  "properties": {
    "iso:country":"US",
    "sg:address":"2131 Quail Run Dr",
    "sg:city":"Baton Rouge",
    "sg:classifiers":[
        {
            "category":"Building & Trades",
            "subcategory":"Construction",
            "type":"Services"
        }
    ],
    "sg:phone":"+1 225 766 1966",
    "sg:postcode":"70808",
    "sg:province":"LA",
    "sg:tags":[
        "general",
        "contractor"
    ],
    "wof:name":"Joffrion & Stuart Co LLC",
    "wof:placetype":"venue"
},
  "geometry": {"coordinates":[-91.126807,30.405265],"type":"Point"}
}