{
  "type": "Feature",
  "properties": {
    "addr:full":"218 Sepulvado Ln Belmont LA 71450",
    "addr:housenumber":"218",
    "addr:postcode":"71450",
    "addr:street":"Sepulvado Ln",
    "iso:country":"US",
    "sg:address":"218 Sepulvado Ln",
    "sg:city":"Belmont",
    "sg:classifiers":[
        {
            "category":"Professional",
            "subcategory":"Management & Consulting",
            "type":"Services"
        }
    ],
    "sg:phone":"+1 318 256 3519",
    "sg:postcode":"71450",
    "sg:province":"LA",
    "sg:tags":[
        "field",
        "oil",
        "consultant"
    ],
    "wof:name":"Tim Sepulvado's Consultant Svc",
    "wof:placetype":"venue"
},
  "geometry": {"coordinates":[-93.496565,31.71886],"type":"Point"}
}