{
  "type": "Feature",
  "properties": {
    "iso:country":"US",
    "sg:address":"270 Kennison Rd",
    "sg:city":"Port Barre",
    "sg:classifiers":[
        {
            "category":"Building & Trades",
            "subcategory":"Construction",
            "type":"Services"
        }
    ],
    "sg:phone":"+1 337 585 2624",
    "sg:postcode":"70577",
    "sg:province":"LA",
    "sg:tags":[
        "carpentry",
        "contractor"
    ],
    "wof:name":"Oren Reed Carpentry",
    "wof:placetype":"venue"
},
  "geometry": {"coordinates":[-91.91415499999999,30.551137],"type":"Point"}
}