{
  "type": "Feature",
  "properties": {
    "iso:country":"US",
    "sg:address":"4901 E Texas St",
    "sg:city":"Bossier City",
    "sg:classifiers":[
        {
            "category":"Freight",
            "type":"Transportation"
        }
    ],
    "sg:phone":"+1 318 747 0083",
    "sg:postcode":"71111",
    "sg:province":"LA",
    "sg:tags":[
        "special",
        "general"
    ],
    "wof:name":"Bossier Self Storage",
    "wof:placetype":"venue"
},
  "geometry": {"coordinates":[-93.667028,32.535345],"type":"Point"}
}