{
  "type": "Feature",
  "properties": {
    "iso:country":"US",
    "sg:address":"1711 Kegleman Blvd",
    "sg:city":"Alexandria",
    "sg:classifiers":[
        {
            "category":"Sports & Exercise",
            "subcategory":"Bowling",
            "type":"Entertainment"
        }
    ],
    "sg:phone":"+1 318 443 0557",
    "sg:postcode":"71303",
    "sg:province":"LA",
    "sg:tags":[
        "center"
    ],
    "wof:name":"Tiger Lanes",
    "wof:placetype":"venue"
},
  "geometry": {"coordinates":[-92.53603,31.327308],"type":"Point"}
}