{
  "type": "Feature",
  "properties": {
    "iso:country":"US",
    "sg:address":"706 Kirby St",
    "sg:city":"Lake Charles",
    "sg:classifiers":[
        {
            "category":"Professional",
            "subcategory":"Lawyer & Legal Services",
            "type":"Services"
        }
    ],
    "sg:phone":"+1 337 433 3726",
    "sg:postcode":"70601",
    "sg:province":"LA",
    "sg:tags":[
        "attorney"
    ],
    "wof:name":"Michael R Cagle",
    "wof:placetype":"venue"
},
  "geometry": {"coordinates":[-93.212154,30.225748],"type":"Point"}
}