{
  "type": "Feature",
  "properties": {
    "addr:full":"103 Oak Park Cir Lafayette LA 70506",
    "addr:housenumber":"103",
    "addr:postcode":"70506",
    "addr:street":"Oak Park Cir",
    "iso:country":"US",
    "sg:address":"103 Oak Park Cir",
    "sg:city":"Lafayette",
    "sg:classifiers":[
        {
            "category":"Building & Trades",
            "subcategory":"Plumbing",
            "type":"Services"
        }
    ],
    "sg:phone":"+1 337 988 4647",
    "sg:postcode":"70506",
    "sg:province":"LA",
    "sg:tags":[
        "plumbing",
        "contractor"
    ],
    "wof:name":"B & B Jet-A-Rooter",
    "wof:placetype":"venue"
},
  "geometry": {"coordinates":[-92.08645799999999,30.196633],"type":"Point"}
}