{
  "type": "Feature",
  "properties": {
    "iso:country":"US",
    "sg:address":"4814 Sullivan St",
    "sg:city":"Bossier City",
    "sg:classifiers":[
        {
            "category":"Shopping",
            "type":"Retail Goods"
        }
    ],
    "sg:phone":"+1 318 746 1323",
    "sg:postcode":"71111",
    "sg:province":"LA",
    "sg:tags":[
        "pet",
        "shop"
    ],
    "wof:name":"Tropical Paradise",
    "wof:placetype":"venue"
},
  "geometry": {"coordinates":[-93.667244,32.540637],"type":"Point"}
}