{
  "type": "Feature",
  "properties": {
    "iso:country":"US",
    "sg:address":"190 Plantation Rd",
    "sg:city":"Scott",
    "sg:classifiers":[
        {
            "category":"Travel",
            "subcategory":"Hotels & Motels",
            "type":"Entertainment"
        }
    ],
    "sg:phone":"+1 337 873 4517",
    "sg:postcode":"70508",
    "sg:province":"LA",
    "sg:tags":[
        "breakfast",
        "accommodation",
        "bed"
    ],
    "wof:name":"Acadian Oaks Bed & Breakfast",
    "wof:placetype":"venue"
},
  "geometry": {"coordinates":[-92.00198399999999,30.207176],"type":"Point"}
}