{
  "type": "Feature",
  "properties": {
    "iso:country":"US",
    "sg:address":"103 Carolyn Ave",
    "sg:city":"Houma",
    "sg:classifiers":[
        {
            "category":"Personal",
            "subcategory":"Beauty Salon",
            "type":"Services"
        }
    ],
    "sg:phone":"+1 985 853 1921",
    "sg:postcode":"70363",
    "sg:province":"LA",
    "sg:tags":[
        "shop"
    ],
    "wof:name":"Golden Locks Salon",
    "wof:placetype":"venue"
},
  "geometry": {"coordinates":[-90.68714300000001,29.581368],"type":"Point"}
}