{
  "type": "Feature",
  "properties": {
    "addr:full":"556 NE Court Cir Crowley LA 70526",
    "addr:housenumber":"556",
    "addr:postcode":"70526",
    "addr:street":"Ne Court Cir",
    "iso:country":"US",
    "sg:address":"556 NE Court Cir",
    "sg:city":"Crowley",
    "sg:classifiers":[
        {
            "category":"Food & Beverages",
            "subcategory":"Bakery",
            "type":"Retail Goods"
        }
    ],
    "sg:phone":"+1 337 783 2962",
    "sg:postcode":"70526",
    "sg:province":"LA",
    "sg:tags":[
        "baker"
    ],
    "wof:name":"Ruddock Bakery",
    "wof:placetype":"venue"
},
  "geometry": {"coordinates":[-92.37320099999999,30.21472],"type":"Point"}
}