{
  "type": "Feature",
  "properties": {
    "iso:country":"US",
    "sg:address":"829 Derbigny St",
    "sg:city":"Gretna",
    "sg:classifiers":[
        {
            "category":"Insurance",
            "subcategory":"Hazard Insurance",
            "type":"Services"
        }
    ],
    "sg:phone":"+1 504 263 2663",
    "sg:postcode":"70053",
    "sg:province":"LA",
    "sg:tags":[
        "bond"
    ],
    "wof:name":"Steve's Bail Bonds",
    "wof:placetype":"venue"
},
  "geometry": {"coordinates":[-90.063486,29.910905],"type":"Point"}
}