{
  "type": "Feature",
  "properties": {
    "iso:country":"US",
    "sg:address":"6441 Jones Creek Rd",
    "sg:city":"Baton Rouge",
    "sg:classifiers":[
        {
            "category":"Retail",
            "subcategory":"Auto Repair",
            "type":"Services"
        }
    ],
    "sg:phone":"+1 225 753 2886",
    "sg:postcode":"70817",
    "sg:province":"LA",
    "sg:tags":[
        "glass",
        "coating",
        "tinting"
    ],
    "wof:name":"Auto Evolution",
    "wof:placetype":"venue"
},
  "geometry": {"coordinates":[-91.018427,30.391548],"type":"Point"}
}