{
  "type": "Feature",
  "properties": {
    "addr:full":"977 N 48th St Baton Rouge LA 70802",
    "addr:housenumber":"977",
    "addr:postcode":"70802",
    "addr:street":"N 48Th St",
    "iso:country":"US",
    "sg:address":"977 N 48th St",
    "sg:city":"Baton Rouge",
    "sg:classifiers":[
        {
            "category":"Organizations",
            "subcategory":"Religious Organization",
            "type":"Services"
        }
    ],
    "sg:phone":"+1 225 922 9925",
    "sg:postcode":"70802",
    "sg:province":"LA",
    "sg:tags":[
        "reach",
        "ministry"
    ],
    "wof:name":"United Ministries House",
    "wof:placetype":"venue"
},
  "geometry": {"coordinates":[-91.14200599999999,30.458827],"type":"Point"}
}