{
  "type": "Feature",
  "properties": {
    "addr:full":"1017 Sharron Dr Benton LA 71006",
    "addr:housenumber":"1017",
    "addr:postcode":"71006",
    "addr:street":"Sharron Dr",
    "iso:country":"US",
    "sg:address":"1017 Sharron Dr",
    "sg:city":"Benton",
    "sg:classifiers":[
        {
            "category":"Manufacturing",
            "subcategory":"Pottery",
            "type":"Manufacturing & Wholesale Goods"
        }
    ],
    "sg:phone":"+1 318 965 0290",
    "sg:postcode":"71006",
    "sg:province":"LA",
    "sg:tags":[
        "product",
        "mfg"
    ],
    "wof:name":"Fullwinds Trading",
    "wof:placetype":"venue"
},
  "geometry": {"coordinates":[-93.746027,32.687363],"type":"Point"}
}