{
  "type": "Feature",
  "properties": {
    "addr:full":"22007 White St Abita Springs LA 70420",
    "addr:housenumber":"22007",
    "addr:postcode":"70420",
    "addr:street":"White St",
    "iso:country":"US",
    "sg:address":"22007 White St",
    "sg:city":"Abita Springs",
    "sg:classifiers":[
        {
            "category":"Shopping",
            "subcategory":"Computers & Home Electronics",
            "type":"Retail Goods"
        }
    ],
    "sg:phone":"+1 985 893 1814",
    "sg:postcode":"70420",
    "sg:province":"LA",
    "sg:tags":[
        "equipment",
        "dealer"
    ],
    "wof:name":"Tammany Computer Consulting",
    "wof:placetype":"venue"
},
  "geometry": {"coordinates":[-90.04053,30.465223],"type":"Point"}
}