{
  "type": "Feature",
  "properties": {
    "iso:country":"US",
    "sg:address":"14572 Bluff Rd",
    "sg:city":"Prairieville",
    "sg:classifiers":[
        {
            "category":"Restaurant",
            "type":"Food & Drink"
        }
    ],
    "sg:phone":"+1 225 677 7272",
    "sg:postcode":"70769",
    "sg:province":"LA",
    "sg:tags":[
        "caterer"
    ],
    "wof:name":"Noble's Catering",
    "wof:placetype":"venue"
},
  "geometry": {"coordinates":[-90.99398600000001,30.286339],"type":"Point"}
}