{
  "type": "Feature",
  "properties": {
    "addr:full":"2721 Athania Pkwy Metairie LA 70002",
    "addr:housenumber":"2721",
    "addr:postcode":"70002",
    "addr:street":"Athania Pkwy",
    "iso:country":"US",
    "sg:address":"2721 Athania Pkwy",
    "sg:city":"Metairie",
    "sg:classifiers":[
        {
            "category":"Health Services",
            "subcategory":"Doctor",
            "type":"Services"
        }
    ],
    "sg:phone":"+1 504 838 8183",
    "sg:postcode":"70002",
    "sg:province":"LA",
    "sg:tags":[
        "dentist"
    ],
    "wof:name":"Professional Dental Corp",
    "wof:placetype":"venue"
},
  "geometry": {"coordinates":[-90.157196,30.001219],"type":"Point"}
}