{
  "type": "Feature",
  "properties": {
    "addr:full":"18014 Autumn View Dr Prairieville LA 70769",
    "addr:housenumber":"18014",
    "addr:postcode":"70769",
    "addr:street":"Autumn View Dr Prairieville",
    "iso:country":"US",
    "sg:address":"18014 Autumn View Dr",
    "sg:city":"Prairieville",
    "sg:classifiers":[
        {
            "category":"Real Estate",
            "subcategory":"Real Estate Operator",
            "type":"Services"
        }
    ],
    "sg:phone":"+1 225 622 7507",
    "sg:postcode":"70769",
    "sg:province":"LA",
    "sg:tags":[
        "building",
        "apartment"
    ],
    "wof:name":"Autumn View Aprtmnts Ktchnttes",
    "wof:placetype":"venue"
},
  "geometry": {"coordinates":[-90.9256,30.324676],"type":"Point"}
}