{
  "type": "Feature",
  "properties": {
    "iso:country":"US",
    "sg:address":"650 Jean St",
    "sg:city":"Denham Springs",
    "sg:classifiers":[
        {
            "category":"Building & Trades",
            "subcategory":"Cleaning & Sanitation",
            "type":"Services"
        }
    ],
    "sg:phone":"+1 225 664 7257",
    "sg:postcode":"70726",
    "sg:province":"LA",
    "wof:name":"Rick's Kitchen Ventilation Svc",
    "wof:placetype":"venue"
},
  "geometry": {"coordinates":[-90.966392,30.463255],"type":"Point"}
}