{
  "type": "Feature",
  "properties": {
    "iso:country":"US",
    "sg:address":"1201 W Esplanade Ave",
    "sg:city":"Kenner",
    "sg:classifiers":[
        {
            "category":"Manufacturing",
            "subcategory":"Food",
            "type":"Manufacturing & Wholesale Goods"
        }
    ],
    "sg:phone":"+1 504 712 1971",
    "sg:postcode":"70065",
    "sg:province":"LA",
    "sg:tags":[
        "mfg"
    ],
    "wof:name":"Connoisseur Edition Inc",
    "wof:placetype":"venue"
},
  "geometry": {"coordinates":[-90.25299699999999,30.020654],"type":"Point"}
}