{
  "type": "Feature",
  "properties": {
    "iso:country":"US",
    "sg:address":"518 S Thompson St",
    "sg:city":"Ville Platte",
    "sg:classifiers":[
        {
            "category":"Organizations",
            "subcategory":"Religious Organization",
            "type":"Services"
        }
    ],
    "sg:phone":"+1 337 363 2336",
    "sg:postcode":"70586",
    "sg:province":"LA",
    "sg:tags":[
        "church"
    ],
    "wof:name":"St Paul Baptist Church",
    "wof:placetype":"venue"
},
  "geometry": {"coordinates":[-92.28680300000001,30.68849],"type":"Point"}
}