{
  "type": "Feature",
  "properties": {
    "iso:country":"US",
    "sg:address":"201 Southland St",
    "sg:city":"Abbeville",
    "sg:classifiers":[
        {
            "category":"Building & Trades",
            "subcategory":"Equipment Rental",
            "type":"Services"
        }
    ],
    "sg:phone":"+1 337 898 6686",
    "sg:postcode":"70510",
    "sg:province":"LA",
    "sg:tags":[
        "aircraft",
        "leasing",
        "charter"
    ],
    "wof:name":"Tex-Air Helicopters",
    "wof:placetype":"venue"
},
  "geometry": {"coordinates":[-92.09858199999999,29.976598],"type":"Point"}
}