{
  "type": "Feature",
  "properties": {
    "iso:country":"US",
    "sg:address":"122 N Cate St",
    "sg:city":"Hammond",
    "sg:classifiers":[
        {
            "category":"Personal",
            "subcategory":"Beauty Salon",
            "type":"Services"
        }
    ],
    "sg:phone":"+1 985 345 7888",
    "sg:postcode":"70401",
    "sg:province":"LA",
    "wof:name":"Rafe's Hair Studio",
    "wof:placetype":"venue"
},
  "geometry": {"coordinates":[-90.46079400000001,30.504379],"type":"Point"}
}