{
  "type": "Feature",
  "properties": {
    "iso:country":"US",
    "sg:address":"8550 United Plaza Blvd",
    "sg:city":"Baton Rouge",
    "sg:classifiers":[
        {
            "category":"Personal",
            "type":"Services"
        }
    ],
    "sg:phone":"+1 225 922 4535",
    "sg:postcode":"70809",
    "sg:province":"LA",
    "sg:tags":[
        "consultant",
        "image"
    ],
    "sg:website":"www.it-group.com",
    "wof:name":"I T Group Inc",
    "wof:placetype":"venue"
},
  "geometry": {"coordinates":[-91.095983,30.409447],"type":"Point"}
}