{
  "type": "Feature",
  "properties": {
    "addr:full":"210 Magnate Dr Lafayette LA 70508",
    "addr:housenumber":"210",
    "addr:postcode":"70508",
    "addr:street":"Magnate Dr",
    "iso:country":"US",
    "sg:address":"210 Magnate Dr",
    "sg:city":"Lafayette",
    "sg:classifiers":[
        {
            "category":"Health Services",
            "subcategory":"Clinic",
            "type":"Services"
        }
    ],
    "sg:phone":"+1 337 235 9741",
    "sg:postcode":"70508",
    "sg:province":"LA",
    "sg:tags":[
        "home"
    ],
    "wof:name":"First Option Home Health",
    "wof:placetype":"venue"
},
  "geometry": {"coordinates":[-92.010166,30.182687],"type":"Point"}
}