{
  "type": "Feature",
  "properties": {
    "addr:full":"5213 Horseshoe Lake Rd Monroe LA 71203",
    "addr:housenumber":"5213",
    "addr:postcode":"71203",
    "addr:street":"Horseshoe Lake Rd",
    "iso:country":"US",
    "sg:address":"5213 Horseshoe Lake Rd",
    "sg:city":"Monroe",
    "sg:classifiers":[
        {
            "category":"Building & Trades",
            "subcategory":"Plumbing",
            "type":"Services"
        }
    ],
    "sg:phone":"+1 318 388 3400",
    "sg:postcode":"71203",
    "sg:province":"LA",
    "sg:tags":[
        "conditioning",
        "air",
        "system",
        "contractor"
    ],
    "wof:name":"Pruitt's Air Cond & Heating Co",
    "wof:placetype":"venue"
},
  "geometry": {"coordinates":[-92.11486499999999,32.671269],"type":"Point"}
}