{
  "type": "Feature",
  "properties": {
    "iso:country":"US",
    "sg:address":"1026 N 2nd St",
    "sg:city":"Eunice",
    "sg:classifiers":[
        {
            "category":"Autos & Motor Vehicles",
            "subcategory":"Automobile Sales",
            "type":"Retail Goods"
        }
    ],
    "sg:phone":"+1 337 457 9221",
    "sg:postcode":"70535",
    "sg:province":"LA",
    "sg:tags":[
        "car",
        "dealer"
    ],
    "wof:name":"Red's Auto Sales & Repair",
    "wof:placetype":"venue"
},
  "geometry": {"coordinates":[-92.416375,30.503383],"type":"Point"}
}