{
  "type": "Feature",
  "properties": {
    "iso:country":"US",
    "sg:address":"10917 Hilltree Dr",
    "sg:city":"Baton Rouge",
    "sg:classifiers":[
        {
            "category":"Shopping",
            "subcategory":"Used Merchandise",
            "type":"Retail Goods"
        }
    ],
    "sg:phone":"+1 225 761 4955",
    "sg:postcode":"70810",
    "sg:province":"LA",
    "sg:tags":[
        "antique"
    ],
    "wof:name":"Carolami Fine Antiques",
    "wof:placetype":"venue"
},
  "geometry": {"coordinates":[-91.10748100000001,30.347454],"type":"Point"}
}