{
  "type": "Feature",
  "properties": {
    "addr:full":"916 Francis St Marrero LA 70072",
    "addr:housenumber":"916",
    "addr:postcode":"70072",
    "addr:street":"Francis St Marrero",
    "iso:country":"US",
    "sg:address":"916 Francis St",
    "sg:city":"Marrero",
    "sg:classifiers":[
        {
            "category":"Professional",
            "subcategory":"Management & Consulting",
            "type":"Services"
        }
    ],
    "sg:phone":"+1 504 421 5588",
    "sg:postcode":"70072",
    "sg:province":"LA",
    "sg:tags":[
        "consultant",
        "educational"
    ],
    "wof:name":"NTS LTD",
    "wof:placetype":"venue"
},
  "geometry": {"coordinates":[-90.12233500000001,29.891246],"type":"Point"}
}