{
  "type": "Feature",
  "properties": {
    "addr:full":"900 N Villere St New Orleans LA 70116",
    "addr:housenumber":"900",
    "addr:postcode":"70116",
    "addr:street":"N Villere St",
    "iso:country":"US",
    "sg:address":"900 N Villere St",
    "sg:city":"New Orleans",
    "sg:classifiers":[
        {
            "category":"Government",
            "subcategory":"Office",
            "type":"Public Place"
        }
    ],
    "sg:phone":"+1 504 565 7290",
    "sg:postcode":"70116",
    "sg:province":"LA",
    "sg:tags":[
        "village"
    ],
    "wof:name":"New Orleans Treme Ctr",
    "wof:placetype":"venue"
},
  "geometry": {"coordinates":[-90.069541,29.965266],"type":"Point"}
}