{
  "type": "Feature",
  "properties": {
    "addr:full":"806 Homer Rd Minden LA 71055",
    "addr:housenumber":"806",
    "addr:postcode":"71055",
    "addr:street":"Homer Rd",
    "iso:country":"US",
    "sg:address":"806 Homer Rd",
    "sg:city":"Minden",
    "sg:classifiers":[
        {
            "category":"Communications",
            "type":"Services"
        }
    ],
    "sg:phone":"+1 318 382 8600",
    "sg:postcode":"71055",
    "sg:province":"LA",
    "wof:name":"Now Communications",
    "wof:placetype":"venue"
},
  "geometry": {"coordinates":[-93.262721,32.622547],"type":"Point"}
}