{
  "type": "Feature",
  "properties": {
    "iso:country":"US",
    "sg:address":"6658 Youree Dr",
    "sg:city":"Shreveport",
    "sg:classifiers":[
        {
            "category":"Retail",
            "subcategory":"Laundry & Dry Cleaning",
            "type":"Services"
        }
    ],
    "sg:phone":"+1 318 797 6007",
    "sg:postcode":"71105",
    "sg:province":"LA",
    "wof:name":"Imperial Dry Cleaners",
    "wof:placetype":"venue"
},
  "geometry": {"coordinates":[-93.719435,32.444723],"type":"Point"}
}