{
  "type": "Feature",
  "properties": {
    "iso:country":"US",
    "sg:address":"331 Bailey St",
    "sg:city":"Minden",
    "sg:classifiers":[
        {
            "category":"Organizations",
            "subcategory":"Religious Organization",
            "type":"Services"
        }
    ],
    "sg:phone":"+1 318 377 1780",
    "sg:postcode":"71055",
    "sg:province":"LA",
    "sg:tags":[
        "church"
    ],
    "wof:name":"Mt Calm Baptist Church",
    "wof:placetype":"venue"
},
  "geometry": {"coordinates":[-93.282049,32.605443],"type":"Point"}
}