{
  "type": "Feature",
  "properties": {
    "iso:country":"US",
    "sg:address":"8680 Frontage Rd",
    "sg:city":"Monroe",
    "sg:classifiers":[
        {
            "category":"Wholesale",
            "subcategory":"Petroleum",
            "type":"Manufacturing & Wholesale Goods"
        }
    ],
    "sg:phone":"+1 318 342 9065",
    "sg:postcode":"71202",
    "sg:province":"LA",
    "sg:tags":[
        "pipe",
        "line",
        "company"
    ],
    "wof:name":"Tennessee Gas Pipeline Co",
    "wof:placetype":"venue"
},
  "geometry": {"coordinates":[-92.014353,32.490603],"type":"Point"}
}