{
  "type": "Feature",
  "properties": {
    "iso:country":"US",
    "sg:address":"1129 S 1st",
    "sg:city":"Gibsland",
    "sg:classifiers":[
        {
            "category":"Autos & Motor Vehicles",
            "subcategory":"Fuel & Gas Station",
            "type":"Retail Goods"
        }
    ],
    "sg:phone":"+1 318 843 6202",
    "sg:postcode":"71028",
    "sg:province":"LA",
    "sg:tags":[
        "oil"
    ],
    "wof:name":"Durham's Shell Station",
    "wof:placetype":"venue"
},
  "geometry": {"coordinates":[-93.055003,32.545345],"type":"Point"}
}