{
  "type": "Feature",
  "properties": {
    "iso:country":"US",
    "sg:address":"54296 Hwy 445",
    "sg:city":"Loranger",
    "sg:classifiers":[
        {
            "category":"Professional",
            "type":"Services"
        }
    ],
    "sg:phone":"+1 985 748 6634",
    "sg:postcode":"70446",
    "sg:province":"LA",
    "sg:tags":[
        "establishment"
    ],
    "wof:name":"Solomon Episcopal Conference",
    "wof:placetype":"venue"
},
  "geometry": {"coordinates":[-90.311798,30.6444],"type":"Point"}
}