{
  "type": "Feature",
  "properties": {
    "addr:full":"1097 Hwy 151 S Calhoun LA 71225",
    "addr:housenumber":"1097",
    "addr:postcode":"71225",
    "addr:street":"Hwy 151 S",
    "iso:country":"US",
    "sg:address":"1097 Hwy 151 S",
    "sg:city":"Calhoun",
    "sg:classifiers":[
        {
            "category":"Recreation",
            "subcategory":"Amusement Park",
            "type":"Entertainment"
        }
    ],
    "sg:phone":"+1 318 644 4433",
    "sg:postcode":"71225",
    "sg:province":"LA",
    "sg:website":"www.edgeofmadness.com",
    "wof:name":"Edge Of Madness Scream Park",
    "wof:placetype":"venue"
},
  "geometry": {"coordinates":[-92.354956,32.484737],"type":"Point"}
}