{
  "type": "Feature",
  "properties": {
    "addr:full":"2202 Peniston St New Orleans LA 70115",
    "addr:housenumber":"2202",
    "addr:postcode":"70115",
    "addr:street":"Peniston St",
    "iso:country":"US",
    "sg:address":"2202 Peniston St",
    "sg:city":"New Orleans",
    "sg:classifiers":[
        {
            "category":"Professional",
            "type":"Services"
        }
    ],
    "sg:phone":"+1 504 895 0184",
    "sg:postcode":"70115",
    "sg:province":"LA",
    "wof:name":"Darrell L Brown",
    "wof:placetype":"venue"
},
  "geometry": {"coordinates":[-90.09746800000001,29.933789],"type":"Point"}
}