{
  "type": "Feature",
  "properties": {
    "addr:full":"1442 Huron Ave Metairie LA 70005",
    "addr:housenumber":"1442",
    "addr:postcode":"70005",
    "addr:street":"Huron Ave",
    "iso:country":"US",
    "sg:address":"1442 Huron Ave",
    "sg:city":"Metairie",
    "sg:classifiers":[
        {
            "category":"Shopping",
            "subcategory":"Hobbies, Toys, & Games",
            "type":"Retail Goods"
        }
    ],
    "sg:phone":"+1 504 831 4600",
    "sg:postcode":"70005",
    "sg:province":"LA",
    "sg:tags":[
        "model",
        "supply"
    ],
    "wof:name":"Black Hawk Hobbies",
    "wof:placetype":"venue"
},
  "geometry": {"coordinates":[-90.12841,30.017309],"type":"Point"}
}