{
  "type": "Feature",
  "properties": {
    "iso:country":"US",
    "sg:address":"1526 N Ave I",
    "sg:city":"Crowley",
    "sg:classifiers":[
        {
            "category":"Health Services",
            "subcategory":"Nursing And Care Facility",
            "type":"Services"
        }
    ],
    "sg:phone":"+1 337 783 2363",
    "sg:postcode":"70526",
    "sg:province":"LA",
    "sg:tags":[
        "home",
        "convalescent"
    ],
    "wof:name":"Crowley Guest House North",
    "wof:placetype":"venue"
},
  "geometry": {"coordinates":[-92.376007,30.22602],"type":"Point"}
}