{
  "type": "Feature",
  "properties": {
    "addr:full":"6445 Prescott Rd Baton Rouge LA 70805",
    "addr:housenumber":"6445",
    "addr:postcode":"70805",
    "addr:street":"Prescott Rd",
    "iso:country":"US",
    "sg:address":"6445 Prescott Rd",
    "sg:city":"Baton Rouge",
    "sg:classifiers":[
        {
            "category":"Home & Garden",
            "subcategory":"Building Materials",
            "type":"Retail Goods"
        }
    ],
    "sg:phone":"+1 225 355 5433",
    "sg:postcode":"70805",
    "sg:province":"LA",
    "sg:tags":[
        "glass",
        "window",
        "plate"
    ],
    "wof:name":"Paul's Auto Glass Upholstery",
    "wof:placetype":"venue"
},
  "geometry": {"coordinates":[-91.12169799999999,30.488559],"type":"Point"}
}