{
  "type": "Feature",
  "properties": {
    "iso:country":"US",
    "sg:address":"15514 State Rte 44",
    "sg:city":"Gonzales",
    "sg:classifiers":[
        {
            "category":"Retail",
            "subcategory":"Laundry & Dry Cleaning",
            "type":"Services"
        }
    ],
    "sg:phone":"+1 225 622 0918",
    "sg:postcode":"70737",
    "sg:province":"LA",
    "wof:name":"Sud's & Tub's Laundry",
    "wof:placetype":"venue"
},
  "geometry": {"coordinates":[-90.921548,30.296475],"type":"Point"}
}