{
  "type": "Feature",
  "properties": {
    "addr:full":"6308 Nora St Metairie LA 70003",
    "addr:housenumber":"6308",
    "addr:postcode":"70003",
    "addr:street":"Nora St",
    "iso:country":"US",
    "sg:address":"6308 Nora St",
    "sg:city":"Metairie",
    "sg:classifiers":[
        {
            "category":"Arts & Performance",
            "subcategory":"Theater",
            "type":"Entertainment"
        }
    ],
    "sg:phone":"+1 504 733 4628",
    "sg:postcode":"70003",
    "sg:province":"LA",
    "sg:tags":[
        "band",
        "orchestra"
    ],
    "wof:name":"Fardella Enterprises Inc",
    "wof:placetype":"venue"
},
  "geometry": {"coordinates":[-90.20624599999999,29.988015],"type":"Point"}
}