{
  "type": "Feature",
  "properties": {
    "iso:country":"US",
    "sg:address":"328 Hunters Hollow Dr",
    "sg:city":"Bossier City",
    "sg:classifiers":[
        {
            "category":"Retail",
            "subcategory":"Portrait Studio",
            "type":"Services"
        }
    ],
    "sg:phone":"+1 318 747 2932",
    "sg:postcode":"71111",
    "sg:province":"LA",
    "sg:tags":[
        "photographer"
    ],
    "wof:name":"Bill Jones Photography",
    "wof:placetype":"venue"
},
  "geometry": {"coordinates":[-93.69885600000001,32.590636],"type":"Point"}
}