{
  "type": "Feature",
  "properties": {
    "iso:country":"US",
    "sg:address":"3201 E Judge Perez Dr",
    "sg:city":"Meraux",
    "sg:classifiers":[
        {
            "category":"Personal",
            "subcategory":"Beauty Salon",
            "type":"Services"
        }
    ],
    "sg:phone":"+1 504 279 0071",
    "sg:postcode":"70075",
    "sg:province":"LA",
    "sg:tags":[
        "shop",
        "manicuring"
    ],
    "wof:name":"Artistic Nails",
    "wof:placetype":"venue"
},
  "geometry": {"coordinates":[-89.928623,29.937314],"type":"Point"}
}