{
  "type": "Feature",
  "properties": {
    "iso:country":"US",
    "sg:address":"2024 Bayou Rd",
    "sg:city":"New Orleans",
    "sg:classifiers":[
        {
            "category":"Wholesale",
            "subcategory":"Construction Materials",
            "type":"Manufacturing & Wholesale Goods"
        }
    ],
    "sg:phone":"+1 504 822 1678",
    "sg:postcode":"70116",
    "sg:province":"LA",
    "sg:tags":[
        "fence"
    ],
    "wof:name":"EBE Fence Co Inc",
    "wof:placetype":"venue"
},
  "geometry": {"coordinates":[-90.07234,29.971273],"type":"Point"}
}