{
  "type": "Feature",
  "properties": {
    "iso:country":"US",
    "sg:address":"111 Deerwood Ln",
    "sg:city":"Arcadia",
    "sg:classifiers":[
        {
            "category":"Building & Trades",
            "subcategory":"Construction",
            "type":"Services"
        }
    ],
    "sg:phone":"+1 318 263 9861",
    "sg:postcode":"71037",
    "sg:province":"LA",
    "sg:tags":[
        "general",
        "contractor"
    ],
    "wof:name":"Steven Towns Construction Svc",
    "wof:placetype":"venue"
},
  "geometry": {"coordinates":[-93.604304,32.566552],"type":"Point"}
}