{
  "type": "Feature",
  "properties": {
    "iso:country":"US",
    "sg:address":"1221 Elmwood Park Blvd",
    "sg:city":"New Orleans",
    "sg:classifiers":[
        {
            "category":"Government",
            "subcategory":"Court House",
            "type":"Public Place"
        }
    ],
    "sg:phone":"+1 504 736 6390",
    "sg:postcode":"70123",
    "sg:province":"LA",
    "wof:name":"Clerk of Court Satellite",
    "wof:placetype":"venue"
},
  "geometry": {"coordinates":[-90.18916900000001,29.96237],"type":"Point"}
}