{
  "type": "Feature",
  "properties": {
    "addr:full":"5220 Flanders Dr Baton Rouge LA 70808",
    "addr:housenumber":"5220",
    "addr:postcode":"70808",
    "addr:street":"Flanders Dr",
    "iso:country":"US",
    "sg:address":"5220 Flanders Dr",
    "sg:city":"Baton Rouge",
    "sg:classifiers":[
        {
            "category":"Health Services",
            "subcategory":"Doctor",
            "type":"Services"
        }
    ],
    "sg:phone":"+1 225 766 5151",
    "sg:postcode":"70808",
    "sg:province":"LA",
    "sg:tags":[
        "physician",
        "surgeon"
    ],
    "wof:name":"Calais Dermatology Assoc",
    "wof:placetype":"venue"
},
  "geometry": {"coordinates":[-91.108586,30.399898],"type":"Point"}
}