{
  "type": "Feature",
  "properties": {
    "iso:country":"US",
    "sg:address":"3011 Pontchartrain Dr",
    "sg:city":"Slidell",
    "sg:classifiers":[
        {
            "category":"Wholesale",
            "subcategory":"Tobacco Products",
            "type":"Manufacturing & Wholesale Goods"
        }
    ],
    "sg:phone":"+1 985 781 7060",
    "sg:postcode":"70458",
    "sg:province":"LA",
    "sg:tags":[
        "cigarette",
        "cigar",
        "dealer"
    ],
    "wof:name":"Jack's Beverages",
    "wof:placetype":"venue"
},
  "geometry": {"coordinates":[-89.784909,30.263072],"type":"Point"}
}