{
  "type": "Feature",
  "properties": {
    "addr:full":"7300 Read Blvd New Orleans LA 70127",
    "addr:housenumber":"7300",
    "addr:postcode":"70127",
    "addr:street":"Read Blvd",
    "iso:country":"US",
    "sg:address":"7300 Read Blvd",
    "sg:city":"New Orleans",
    "sg:classifiers":[
        {
            "category":"Cinema",
            "subcategory":"Movie Rental",
            "type":"Entertainment"
        }
    ],
    "sg:phone":"+1 504 241 6078",
    "sg:postcode":"70127",
    "sg:province":"LA",
    "sg:tags":[
        "leasing",
        "video",
        "disc",
        "tape"
    ],
    "wof:name":"Blockbuster Video",
    "wof:placetype":"venue"
},
  "geometry": {"coordinates":[-89.978951,30.040528],"type":"Point"}
}