{
  "type": "Feature",
  "properties": {
    "addr:full":"835 Bourbon St New Orleans LA 70116",
    "addr:housenumber":"835",
    "addr:postcode":"70116",
    "addr:street":"Bourbon St",
    "iso:country":"US",
    "sg:address":"835 Bourbon St",
    "sg:city":"New Orleans",
    "sg:classifiers":[
        {
            "category":"Travel",
            "subcategory":"Hotels & Motels",
            "type":"Entertainment"
        }
    ],
    "sg:phone":"+1 504 561 8498",
    "sg:postcode":"70116",
    "sg:province":"LA",
    "sg:website":"www.bonmaison.com/",
    "wof:name":"Bon Maison Guest House",
    "wof:placetype":"venue"
},
  "geometry": {"coordinates":[-90.064499,29.9601],"type":"Point"}
}