{
  "type": "Feature",
  "properties": {
    "iso:country":"US",
    "sg:address":"6213 Linwood Ave",
    "sg:city":"Shreveport",
    "sg:classifiers":[
        {
            "category":"Shopping",
            "type":"Retail Goods"
        }
    ],
    "sg:phone":"+1 318 688 0392",
    "sg:postcode":"71106",
    "sg:province":"LA",
    "sg:tags":[
        "merchandise"
    ],
    "wof:name":"Page Me Communications",
    "wof:placetype":"venue"
},
  "geometry": {"coordinates":[-93.762912,32.448684],"type":"Point"}
}