{
  "type": "Feature",
  "properties": {
    "iso:country":"US",
    "sg:address":"316 Calcasieu Ave",
    "sg:city":"Jennings",
    "sg:classifiers":[
        {
            "category":"Professional",
            "type":"Services"
        }
    ],
    "sg:phone":"+1 337 774 2444",
    "sg:postcode":"70549",
    "sg:province":"LA",
    "sg:tags":[
        "establishment"
    ],
    "wof:name":"Cruise'n Joe's",
    "wof:placetype":"venue"
},
  "geometry": {"coordinates":[-92.671319,30.08085],"type":"Point"}
}