{
  "type": "Feature",
  "properties": {
    "iso:country":"US",
    "sg:address":"105 S Railroad Ave",
    "sg:city":"Opelousas",
    "sg:classifiers":[
        {
            "category":"Personal",
            "subcategory":"Beauty Salon",
            "type":"Services"
        }
    ],
    "sg:phone":"+1 337 948 1786",
    "sg:postcode":"70570",
    "sg:province":"LA",
    "sg:tags":[
        "shop"
    ],
    "wof:name":"Mary's Beauty Salon",
    "wof:placetype":"venue"
},
  "geometry": {"coordinates":[-92.08807,30.534768],"type":"Point"}
}