{
  "type": "Feature",
  "properties": {
    "addr:full":"13823 Hwy 113 Reeves LA 70658",
    "addr:housenumber":"13823",
    "addr:postcode":"70658",
    "addr:street":"Hwy 113 Reeves",
    "iso:country":"US",
    "sg:address":"13823 Hwy 113",
    "sg:city":"Reeves",
    "sg:classifiers":[
        {
            "category":"Wholesale",
            "subcategory":"Farm Supplies",
            "type":"Manufacturing & Wholesale Goods"
        }
    ],
    "sg:phone":"+1 337 666 2205",
    "sg:postcode":"70658",
    "sg:province":"LA",
    "sg:tags":[
        "feed"
    ],
    "wof:name":"Perkins Feed & Farm",
    "wof:placetype":"venue"
},
  "geometry": {"coordinates":[-93.048382,30.522823],"type":"Point"}
}