{
  "type": "Feature",
  "properties": {
    "iso:country":"US",
    "sg:address":"5304 Jewella Ave",
    "sg:city":"Shreveport",
    "sg:classifiers":[
        {
            "category":"Organizations",
            "subcategory":"Religious Organization",
            "type":"Services"
        }
    ],
    "sg:phone":"+1 318 631 1154",
    "sg:postcode":"71109",
    "sg:province":"LA",
    "sg:tags":[
        "church"
    ],
    "wof:name":"North Star Baptist Church",
    "wof:placetype":"venue"
},
  "geometry": {"coordinates":[-93.797389,32.461575],"type":"Point"}
}