{
  "type": "Feature",
  "properties": {
    "iso:country":"US",
    "sg:address":"1460 Hawn Ave",
    "sg:city":"Shreveport",
    "sg:classifiers":[
        {
            "category":"Professional",
            "subcategory":"Lawyer & Legal Services",
            "type":"Services"
        }
    ],
    "sg:phone":"+1 318 425 8600",
    "sg:postcode":"71107",
    "sg:province":"LA",
    "sg:tags":[
        "attorney"
    ],
    "wof:name":"James E Franklin",
    "wof:placetype":"venue"
},
  "geometry": {"coordinates":[-93.763741,32.536417],"type":"Point"}
}