{
  "type": "Feature",
  "properties": {
    "addr:full":"1404 Garden Rd Marrero LA 70072",
    "addr:housenumber":"1404",
    "addr:postcode":"70072",
    "addr:street":"Garden Rd Marrero",
    "iso:country":"US",
    "sg:address":"1404 Garden Rd",
    "sg:city":"Marrero",
    "sg:classifiers":[
        {
            "category":"Shopping",
            "subcategory":"Gifts & Souvenirs",
            "type":"Retail Goods"
        }
    ],
    "sg:phone":"+1 504 341 0502",
    "sg:postcode":"70072",
    "sg:province":"LA",
    "sg:tags":[
        "shop"
    ],
    "wof:name":"Young's Creation",
    "wof:placetype":"venue"
},
  "geometry": {"coordinates":[-90.12046599999999,29.887085],"type":"Point"}
}