{
  "type": "Feature",
  "properties": {
    "iso:country":"US",
    "sg:address":"605 Evergreen St",
    "sg:city":"Bunkie",
    "sg:classifiers":[
        {
            "category":"Food & Beverages",
            "subcategory":"Groceries & Convenience Stores",
            "type":"Retail Goods"
        }
    ],
    "sg:phone":"+1 318 346 8111",
    "sg:postcode":"71322",
    "sg:province":"LA",
    "wof:name":"Short Stop Discount Tobacco",
    "wof:placetype":"venue"
},
  "geometry": {"coordinates":[-92.17425900000001,30.9517],"type":"Point"}
}