{
  "type": "Feature",
  "properties": {
    "iso:country":"US",
    "sg:address":"2931 Hwy 1",
    "sg:city":"Grand Isle",
    "sg:classifiers":[
        {
            "category":"Real Estate",
            "subcategory":"Real Estate Agent",
            "type":"Services"
        }
    ],
    "sg:phone":"+1 985 787 3200",
    "sg:postcode":"70358",
    "sg:province":"LA",
    "wof:name":"Nicole Lombas & Assoc",
    "wof:placetype":"venue"
},
  "geometry": {"coordinates":[-89.998718,29.230432],"type":"Point"}
}