{
  "type": "Feature",
  "properties": {
    "iso:country":"US",
    "sg:address":"841 Carondelet St",
    "sg:city":"New Orleans",
    "sg:classifiers":[
        {
            "category":"Shopping",
            "type":"Retail Goods"
        }
    ],
    "sg:phone":"+1 504 522 5471",
    "sg:postcode":"70130",
    "sg:province":"LA",
    "sg:tags":[
        "art",
        "gallery",
        "dealer"
    ],
    "wof:name":"Jonathan Ferrara Gallery",
    "wof:placetype":"venue"
},
  "geometry": {"coordinates":[-90.07328,29.945307],"type":"Point"}
}