{
  "type": "Feature",
  "properties": {
    "iso:country":"US",
    "sg:address":"8312 Jefferson Hwy",
    "sg:city":"Baton Rouge",
    "sg:classifiers":[
        {
            "category":"Shopping",
            "subcategory":"Bicycles & Sporting Goods",
            "type":"Retail Goods"
        }
    ],
    "sg:phone":"+1 225 927 0171",
    "sg:postcode":"70809",
    "sg:province":"LA",
    "wof:name":"Third Coast Soccer",
    "wof:placetype":"venue"
},
  "geometry": {"coordinates":[-91.09894,30.419763],"type":"Point"}
}