{
  "type": "Feature",
  "properties": {
    "iso:country":"US",
    "sg:address":"112 E Pine Ave",
    "sg:city":"Bastrop",
    "sg:classifiers":[
        {
            "category":"Manufacturing",
            "subcategory":"Printing",
            "type":"Manufacturing & Wholesale Goods"
        }
    ],
    "sg:phone":"+1 318 281 5466",
    "sg:postcode":"71220",
    "sg:province":"LA",
    "sg:tags":[
        "commercial"
    ],
    "wof:name":"Bastrop Printing & Office",
    "wof:placetype":"venue"
},
  "geometry": {"coordinates":[-91.91432399999999,32.779316],"type":"Point"}
}