{
  "type": "Feature",
  "properties": {
    "iso:country":"US",
    "sg:address":"11129 Jefferson Hwy",
    "sg:city":"New Orleans",
    "sg:classifiers":[
        {
            "category":"Travel",
            "subcategory":"Campground",
            "type":"Entertainment"
        }
    ],
    "sg:phone":"+1 504 467 1792",
    "sg:postcode":"70123",
    "sg:province":"LA",
    "sg:website":"www.koa.com",
    "wof:name":"KOA Kampgrounds",
    "wof:placetype":"venue"
},
  "geometry": {"coordinates":[-90.23452,29.970008],"type":"Point"}
}