{
  "type": "Feature",
  "properties": {
    "iso:country":"US",
    "sg:address":"2007 Cedardale Ave",
    "sg:city":"Baton Rouge",
    "sg:classifiers":[
        {
            "category":"Professional",
            "subcategory":"Lawyer & Legal Services",
            "type":"Services"
        }
    ],
    "sg:phone":"+1 225 343 9868",
    "sg:postcode":"70808",
    "sg:province":"LA",
    "sg:tags":[
        "attorney"
    ],
    "wof:name":"Ben L Guelfo",
    "wof:placetype":"venue"
},
  "geometry": {"coordinates":[-91.15885,30.419621],"type":"Point"}
}