{
  "type": "Feature",
  "properties": {
    "iso:country":"US",
    "sg:address":"2850 Hwy 90 W",
    "sg:city":"Avondale",
    "sg:classifiers":[
        {
            "category":"Restaurant",
            "type":"Food & Drink"
        }
    ],
    "sg:phone":"+1 504 436 3228",
    "sg:postcode":"70094",
    "sg:province":"LA",
    "wof:name":"Burger King",
    "wof:placetype":"venue"
},
  "geometry": {"coordinates":[-90.200952,29.909939],"type":"Point"}
}