{
  "type": "Feature",
  "properties": {
    "addr:full":"3181 Press St New Orleans LA 70126",
    "addr:housenumber":"3181",
    "addr:postcode":"70126",
    "addr:street":"Press St",
    "iso:country":"US",
    "sg:address":"3181 Press St",
    "sg:city":"New Orleans",
    "sg:classifiers":[
        {
            "category":"Recreation",
            "type":"Entertainment"
        }
    ],
    "sg:phone":"+1 504 940 1951",
    "sg:postcode":"70126",
    "sg:province":"LA",
    "sg:tags":[
        "hall",
        "auditorium"
    ],
    "wof:name":"Press Community Ctr",
    "wof:placetype":"venue"
},
  "geometry": {"coordinates":[-90.040007,29.988945],"type":"Point"}
}