{
  "type": "Feature",
  "properties": {
    "iso:country":"US",
    "sg:address":"926 Crescent Blvd",
    "sg:city":"Houma",
    "sg:classifiers":[
        {
            "category":"Personal",
            "type":"Services"
        }
    ],
    "sg:phone":"+1 985 872 2287",
    "sg:postcode":"70360",
    "sg:province":"LA",
    "sg:tags":[
        "therapist",
        "massage"
    ],
    "wof:name":"Alternative Health & Massage",
    "wof:placetype":"venue"
},
  "geometry": {"coordinates":[-90.71898,29.580715],"type":"Point"}
}