{
  "type": "Feature",
  "properties": {
    "iso:country":"US",
    "sg:address":"2209 Legion St",
    "sg:city":"Lake Charles",
    "sg:classifiers":[
        {
            "category":"Professional",
            "type":"Services"
        }
    ],
    "sg:phone":"+1 337 436 5187",
    "sg:postcode":"70601",
    "sg:province":"LA",
    "wof:name":"Cannon Meter Reading Service",
    "wof:placetype":"venue"
},
  "geometry": {"coordinates":[-93.18617999999999,30.216578],"type":"Point"}
}