{
  "type": "Feature",
  "properties": {
    "addr:full":"1100 W Willow St Lafayette LA 70501",
    "addr:housenumber":"1100",
    "addr:postcode":"70501",
    "addr:street":"W Willow St",
    "iso:country":"US",
    "sg:address":"1100 W Willow St",
    "sg:city":"Lafayette",
    "sg:classifiers":[
        {
            "category":"Shopping",
            "subcategory":"Department Store",
            "type":"Retail Goods"
        }
    ],
    "sg:phone":"+1 337 593 0997",
    "sg:postcode":"70501",
    "sg:province":"LA",
    "sg:website":"www.familydollar.com",
    "wof:name":"Family Dollar Store",
    "wof:placetype":"venue"
},
  "geometry": {"coordinates":[-92.02770200000001,30.245899],"type":"Point"}
}