{
  "type": "Feature",
  "properties": {
    "iso:country":"US",
    "sg:address":"220 Greenbrier Ln",
    "sg:city":"Many",
    "sg:classifiers":[
        {
            "category":"Shopping",
            "subcategory":"Hobbies, Toys, & Games",
            "type":"Retail Goods"
        }
    ],
    "sg:phone":"+1 318 256 5353",
    "sg:postcode":"71449",
    "sg:province":"LA",
    "sg:tags":[
        "craft",
        "supply"
    ],
    "wof:name":"Karen's Scrapbook Korner",
    "wof:placetype":"venue"
},
  "geometry": {"coordinates":[-93.403964,31.607605],"type":"Point"}
}