{
  "type": "Feature",
  "properties": {
    "iso:country":"US",
    "sg:address":"2740 Hwy 563",
    "sg:city":"Simsboro",
    "sg:classifiers":[
        {
            "category":"Real Estate",
            "subcategory":"Real Estate Agent",
            "type":"Services"
        }
    ],
    "sg:phone":"+1 318 247 0053",
    "sg:postcode":"71275",
    "sg:province":"LA",
    "sg:tags":[
        "inspection"
    ],
    "wof:name":"Leone Property Inspections",
    "wof:placetype":"venue"
},
  "geometry": {"coordinates":[-92.755925,32.595826],"type":"Point"}
}