{
  "type": "Feature",
  "properties": {
    "addr:full":"2066 Woodmere Blvd Harvey LA 70058",
    "addr:housenumber":"2066",
    "addr:postcode":"70058",
    "addr:street":"Woodmere Blvd",
    "iso:country":"US",
    "sg:address":"2066 Woodmere Blvd",
    "sg:city":"Harvey",
    "sg:classifiers":[
        {
            "category":"Travel",
            "subcategory":"Travel Agent",
            "type":"Entertainment"
        }
    ],
    "sg:phone":"+1 504 347 5551",
    "sg:postcode":"70058",
    "sg:province":"LA",
    "sg:tags":[
        "agency",
        "bureau"
    ],
    "wof:name":"Fastravel",
    "wof:placetype":"venue"
},
  "geometry": {"coordinates":[-90.082415,29.871689],"type":"Point"}
}