{
  "type": "Feature",
  "properties": {
    "iso:country":"US",
    "sg:address":"1004 N Reed St",
    "sg:city":"Ville Platte",
    "sg:classifiers":[
        {
            "category":"Health Services",
            "subcategory":"Clinic",
            "type":"Services"
        }
    ],
    "sg:phone":"+1 337 363 7949",
    "sg:postcode":"70586",
    "sg:province":"LA",
    "sg:tags":[
        "home"
    ],
    "wof:name":"Medsource Home Care",
    "wof:placetype":"venue"
},
  "geometry": {"coordinates":[-92.27511699999999,30.698053],"type":"Point"}
}