{
  "type": "Feature",
  "properties": {
    "iso:country":"US",
    "sg:address":"2123 Forsythe Ave",
    "sg:city":"Monroe",
    "sg:classifiers":[
        {
            "category":"Restaurant",
            "type":"Food & Drink"
        }
    ],
    "sg:menulink":"http://www.allmenus.com/la/brownsville-bawcomville/136672-smoothie-king/menu/",
    "sg:phone":"+1 318 325 7878",
    "sg:postcode":"71201",
    "sg:province":"LA",
    "sg:tags":[
        "smoothy",
        "juice",
        "american"
    ],
    "wof:name":"Smoothie King",
    "wof:placetype":"venue"
},
  "geometry": {"coordinates":[-92.10982300000001,32.533674],"type":"Point"}
}