{
  "type": "Feature",
  "properties": {
    "addr:full":"450 E Main St New Iberia LA 70560",
    "addr:housenumber":"450",
    "addr:postcode":"70560",
    "addr:street":"E Main St",
    "iso:country":"US",
    "sg:address":"450 E Main St",
    "sg:city":"New Iberia",
    "sg:classifiers":[
        {
            "category":"Professional",
            "subcategory":"Accounting & Tax Preparation",
            "type":"Services"
        }
    ],
    "sg:phone":"+1 337 367 9204",
    "sg:postcode":"70560",
    "sg:province":"LA",
    "sg:tags":[
        "accountant"
    ],
    "wof:name":"Mixon T E Jr CPA",
    "wof:placetype":"venue"
},
  "geometry": {"coordinates":[-91.81410200000001,30.002899],"type":"Point"}
}