{
  "type": "Feature",
  "properties": {
    "addr:full":"211 Wyche St Bossier City LA 71111",
    "addr:housenumber":"211",
    "addr:postcode":"71111",
    "addr:street":"Wyche St",
    "iso:country":"US",
    "sg:address":"211 Wyche St",
    "sg:city":"Bossier City",
    "sg:classifiers":[
        {
            "category":"Personal",
            "subcategory":"Beauty Salon",
            "type":"Services"
        }
    ],
    "sg:phone":"+1 318 746 1228",
    "sg:postcode":"71111",
    "sg:province":"LA",
    "wof:name":"Shealett Hall Hair Salon",
    "wof:placetype":"venue"
},
  "geometry": {"coordinates":[-93.73822800000001,32.523973],"type":"Point"}
}