{
  "type": "Feature",
  "properties": {
    "addr:full":"306 W Prien Lake Rd Lake Charles LA 70601",
    "addr:housenumber":"306",
    "addr:postcode":"70601",
    "addr:street":"W Prien Lake Rd",
    "iso:country":"US",
    "sg:address":"306 W Prien Lake Rd",
    "sg:city":"Lake Charles",
    "sg:classifiers":[
        {
            "category":"Restaurant",
            "type":"Food & Drink"
        }
    ],
    "sg:menulink":"http://www.allmenus.com/la/lake-charles/176137-kfc---kentucky-fried-chicken/menu/",
    "sg:phone":"+1 318 478 8843",
    "sg:postcode":"70601",
    "sg:province":"LA",
    "sg:tags":[
        "american",
        "chicken"
    ],
    "wof:name":"KFC - Kentucky Fried Chicken",
    "wof:placetype":"venue"
},
  "geometry": {"coordinates":[-93.223343,30.19827],"type":"Point"}
}