{
  "type": "Feature",
  "properties": {
    "addr:full":"318 N Canal Blvd Thibodaux LA 70301",
    "addr:housenumber":"318",
    "addr:postcode":"70301",
    "addr:street":"N Canal Blvd",
    "iso:country":"US",
    "sg:address":"318 N Canal Blvd",
    "sg:city":"Thibodaux",
    "sg:classifiers":[
        {
            "category":"Health Services",
            "subcategory":"Optometrist",
            "type":"Services"
        }
    ],
    "sg:phone":"+1 985 446 3276",
    "sg:postcode":"70301",
    "sg:province":"LA",
    "wof:name":"Chiasson Eye Care Ctr",
    "wof:placetype":"venue"
},
  "geometry": {"coordinates":[-90.816637,29.804429],"type":"Point"}
}