{
  "type": "Feature",
  "properties": {
    "iso:country":"US",
    "sg:address":"507 Clifton Dr",
    "sg:city":"Ball",
    "sg:classifiers":[
        {
            "category":"Shopping",
            "subcategory":"Bicycles & Sporting Goods",
            "type":"Retail Goods"
        }
    ],
    "sg:phone":"+1 318 640 4315",
    "sg:postcode":"71405",
    "sg:province":"LA",
    "sg:tags":[
        "gun",
        "gunsmith"
    ],
    "wof:name":"Hutchinson's Firearms & Acces",
    "wof:placetype":"venue"
},
  "geometry": {"coordinates":[-92.41877100000001,31.392129],"type":"Point"}
}