{
  "type": "Feature",
  "properties": {
    "iso:country":"US",
    "sg:address":"26464 Hwy 16",
    "sg:city":"Amite",
    "sg:classifiers":[
        {
            "category":"Real Estate",
            "subcategory":"Real Estate Agent",
            "type":"Services"
        }
    ],
    "sg:phone":"+1 985 748 7774",
    "sg:postcode":"70422",
    "sg:province":"LA",
    "wof:name":"Jenkins Real Estate",
    "wof:placetype":"venue"
},
  "geometry": {"coordinates":[-90.273713,30.757102],"type":"Point"}
}