{
  "type": "Feature",
  "properties": {
    "iso:country":"US",
    "sg:address":"3000 Old Minden Rd",
    "sg:city":"Bossier City",
    "sg:classifiers":[
        {
            "category":"Recreation",
            "type":"Entertainment"
        }
    ],
    "sg:phone":"+1 318 747 5095",
    "sg:postcode":"71112",
    "sg:province":"LA",
    "sg:tags":[
        "skating",
        "rink"
    ],
    "wof:name":"Hot Wheels Skating Palace",
    "wof:placetype":"venue"
},
  "geometry": {"coordinates":[-93.69562500000001,32.521402],"type":"Point"}
}