{
  "type": "Feature",
  "properties": {
    "iso:country":"US",
    "sg:address":"7100 Glenleaf Rd",
    "sg:city":"Shreveport",
    "sg:classifiers":[
        {
            "category":"Organizations",
            "subcategory":"Religious Organization",
            "type":"Services"
        }
    ],
    "sg:phone":"+1 318 688 7710",
    "sg:postcode":"71129",
    "sg:province":"LA",
    "sg:tags":[
        "church"
    ],
    "wof:name":"Bible Missionary Church Prsnge",
    "wof:placetype":"venue"
},
  "geometry": {"coordinates":[-93.883005,32.43929],"type":"Point"}
}