{
  "type": "Feature",
  "properties": {
    "addr:full":"3224 26th St Metairie LA 70002",
    "addr:housenumber":"3224",
    "addr:postcode":"70002",
    "addr:street":"26Th St",
    "iso:country":"US",
    "sg:address":"3224 26th St",
    "sg:city":"Metairie",
    "sg:classifiers":[
        {
            "category":"Professional",
            "subcategory":"Credit Reporting & Collection",
            "type":"Services"
        }
    ],
    "sg:phone":"+1 504 887 8406",
    "sg:postcode":"70002",
    "sg:province":"LA",
    "sg:tags":[
        "agency"
    ],
    "sg:website":"www.cibservice.com",
    "wof:name":"Corporate Investigation",
    "wof:placetype":"venue"
},
  "geometry": {"coordinates":[-90.156904,30.001153],"type":"Point"}
}