{
  "type": "Feature",
  "properties": {
    "iso:country":"US",
    "sg:address":"6760 W Main St",
    "sg:city":"Houma",
    "sg:classifiers":[
        {
            "category":"Retail",
            "subcategory":"Repair Shop",
            "type":"Services"
        },
        {
            "category":"Arts & Performance",
            "subcategory":"Theater",
            "type":"Entertainment"
        }
    ],
    "sg:phone":"+1 985 879 1024",
    "sg:postcode":"70360",
    "sg:province":"LA",
    "sg:tags":[
        "musician"
    ],
    "wof:name":"Haddad Music Co",
    "wof:placetype":"venue"
},
  "geometry": {"coordinates":[-90.745773,29.613201],"type":"Point"}
}