{
  "type": "Feature",
  "properties": {
    "iso:country":"US",
    "sg:address":"985 Robert Blvd",
    "sg:city":"Slidell",
    "sg:classifiers":[
        {
            "category":"Health Services",
            "subcategory":"Health Practitioner",
            "type":"Services"
        }
    ],
    "sg:phone":"+1 985 690 8293",
    "sg:postcode":"70458",
    "sg:province":"LA",
    "sg:tags":[
        "nurse",
        "registry"
    ],
    "wof:name":"Nursing Services",
    "wof:placetype":"venue"
},
  "geometry": {"coordinates":[-89.768748,30.291435],"type":"Point"}
}