{
  "type": "Feature",
  "properties": {
    "iso:country":"US",
    "sg:address":"800 Johnson St",
    "sg:city":"Tallulah",
    "sg:classifiers":[
        {
            "category":"Health Services",
            "subcategory":"Doctor",
            "type":"Services"
        }
    ],
    "sg:phone":"+1 318 574 4731",
    "sg:postcode":"71282",
    "sg:province":"LA",
    "sg:tags":[
        "physician",
        "surgeon"
    ],
    "wof:name":"Rural Health Clinic",
    "wof:placetype":"venue"
},
  "geometry": {"coordinates":[-91.18593300000001,32.404617],"type":"Point"}
}