{
  "type": "Feature",
  "properties": {
    "iso:country":"US",
    "sg:address":"6100 S Lakeshore Dr",
    "sg:city":"Shreveport",
    "sg:classifiers":[
        {
            "category":"Restaurant",
            "type":"Food & Drink"
        }
    ],
    "sg:phone":"+1 318 865 5084",
    "sg:postcode":"71119",
    "sg:province":"LA",
    "sg:tags":[
        "caterer"
    ],
    "wof:name":"A Taster's Choice Catering",
    "wof:placetype":"venue"
},
  "geometry": {"coordinates":[-93.86967799999999,32.4983],"type":"Point"}
}