{
  "type": "Feature",
  "properties": {
    "iso:country":"US",
    "sg:address":"125 E Lafayette Dr",
    "sg:city":"West Monroe",
    "sg:classifiers":[
        {
            "category":"Insurance",
            "subcategory":"Insurance Agent",
            "type":"Services"
        }
    ],
    "sg:phone":"+1 318 396 5135",
    "sg:postcode":"71291",
    "sg:province":"LA",
    "wof:name":"Horace Mann Insurance Co",
    "wof:placetype":"venue"
},
  "geometry": {"coordinates":[-92.17106099999999,32.560616],"type":"Point"}
}