{
  "type": "Feature",
  "properties": {
    "iso:country":"US",
    "sg:address":"524 Brook Ave",
    "sg:city":"Lafayette",
    "sg:classifiers":[
        {
            "category":"Government",
            "subcategory":"Office",
            "type":"Public Place"
        }
    ],
    "sg:phone":"+1 337 262 5900",
    "sg:postcode":"70506",
    "sg:province":"LA",
    "sg:tags":[
        "program",
        "state",
        "adm"
    ],
    "wof:name":"Culture Recreation & Tourism",
    "wof:placetype":"venue"
},
  "geometry": {"coordinates":[-92.02492700000001,30.214201],"type":"Point"}
}