{
  "type": "Feature",
  "properties": {
    "addr:full":"1502 N Pine St Deridder LA 70634",
    "addr:housenumber":"1502",
    "addr:postcode":"70634",
    "addr:street":"N Pine St",
    "iso:country":"US",
    "sg:address":"1502 N Pine St",
    "sg:city":"Deridder",
    "sg:classifiers":[
        {
            "category":"Freight",
            "type":"Transportation"
        }
    ],
    "sg:phone":"+1 337 463 4140",
    "sg:postcode":"70634",
    "sg:province":"LA",
    "sg:tags":[
        "commercial",
        "storage"
    ],
    "wof:name":"Mohawk Storage",
    "wof:placetype":"venue"
},
  "geometry": {"coordinates":[-93.284846,30.873787],"type":"Point"}
}