{
  "type": "Feature",
  "properties": {
    "iso:country":"US",
    "sg:address":"11689 Crossett Rd",
    "sg:city":"Bastrop",
    "sg:classifiers":[
        {
            "category":"Restaurant",
            "type":"Food & Drink"
        }
    ],
    "sg:phone":"+1 318 281 6940",
    "sg:postcode":"71220",
    "sg:province":"LA",
    "wof:name":"Arnold's Kgin Kooking",
    "wof:placetype":"venue"
},
  "geometry": {"coordinates":[-91.878409,32.831043],"type":"Point"}
}