{
  "type": "Feature",
  "properties": {
    "iso:country":"US",
    "sg:address":"405 S Gatehouse Dr",
    "sg:city":"Metairie",
    "sg:classifiers":[
        {
            "category":"Government",
            "subcategory":"Office",
            "type":"Public Place"
        }
    ],
    "sg:phone":"+1 504 813 5775",
    "sg:postcode":"70001",
    "sg:province":"LA",
    "sg:tags":[
        "general"
    ],
    "wof:name":"Gaap Outsource & Co",
    "wof:placetype":"venue"
},
  "geometry": {"coordinates":[-90.150882,29.992134],"type":"Point"}
}