{
  "type": "Feature",
  "properties": {
    "addr:full":"5701 Aspen St Lake Charles LA 70605",
    "addr:housenumber":"5701",
    "addr:postcode":"70605",
    "addr:street":"Aspen St",
    "iso:country":"US",
    "sg:address":"5701 Aspen St",
    "sg:city":"Lake Charles",
    "sg:classifiers":[
        {
            "category":"Personal",
            "subcategory":"Beauty Salon",
            "type":"Services"
        }
    ],
    "sg:phone":"+1 337 474 3658",
    "sg:postcode":"70605",
    "sg:province":"LA",
    "wof:name":"Patsy's",
    "wof:placetype":"venue"
},
  "geometry": {"coordinates":[-93.26011099999999,30.147029],"type":"Point"}
}