{
  "type": "Feature",
  "properties": {
    "iso:country":"US",
    "sg:address":"930 Nashville Ave",
    "sg:city":"New Orleans",
    "sg:classifiers":[
        {
            "category":"Professional",
            "subcategory":"Lawyer & Legal Services",
            "type":"Services"
        }
    ],
    "sg:phone":"+1 504 899 1129",
    "sg:postcode":"70115",
    "sg:province":"LA",
    "sg:tags":[
        "attorney"
    ],
    "wof:name":"Benjamin Hatfield",
    "wof:placetype":"venue"
},
  "geometry": {"coordinates":[-90.11857000000001,29.923135],"type":"Point"}
}