{
  "type": "Feature",
  "properties": {
    "addr:full":"9042 Meadowood St Baton Rouge LA 70815",
    "addr:housenumber":"9042",
    "addr:postcode":"70815",
    "addr:street":"Meadowood St",
    "iso:country":"US",
    "sg:address":"9042 Meadowood St",
    "sg:city":"Baton Rouge",
    "sg:classifiers":[
        {
            "category":"Food & Beverages",
            "subcategory":"Specialty",
            "type":"Retail Goods"
        }
    ],
    "sg:phone":"+1 225 767 6740",
    "sg:postcode":"70815",
    "sg:province":"LA",
    "sg:tags":[
        "health",
        "diet"
    ],
    "wof:name":"Vitality Food Shoppe",
    "wof:placetype":"venue"
},
  "geometry": {"coordinates":[-91.089996,30.452131],"type":"Point"}
}