{
  "type": "Feature",
  "properties": {
    "addr:full":"1819 Touchet Dr Abbeville LA 70510",
    "addr:housenumber":"1819",
    "addr:postcode":"70510",
    "addr:street":"Touchet Dr",
    "iso:country":"US",
    "sg:address":"1819 Touchet Dr",
    "sg:city":"Abbeville",
    "sg:classifiers":[
        {
            "category":"Mining & Drilling",
            "type":"Manufacturing & Wholesale Goods"
        }
    ],
    "sg:phone":"+1 337 898 2466",
    "sg:postcode":"70510",
    "sg:province":"LA",
    "sg:tags":[
        "field"
    ],
    "wof:name":"Daneger Production Co",
    "wof:placetype":"venue"
},
  "geometry": {"coordinates":[-92.09846,29.955601],"type":"Point"}
}