{
  "type": "Feature",
  "properties": {
    "iso:country":"US",
    "sg:address":"805 N 30th St",
    "sg:city":"Monroe",
    "sg:classifiers":[
        {
            "category":"Utilities",
            "subcategory":"Mobile Phone",
            "type":"Services"
        }
    ],
    "sg:phone":"+1 318 998 5276",
    "sg:postcode":"71201",
    "sg:province":"LA",
    "sg:tags":[
        "telephone",
        "cellular"
    ],
    "wof:name":"Utilcom USA",
    "wof:placetype":"venue"
},
  "geometry": {"coordinates":[-92.090613,32.531898],"type":"Point"}
}