{
  "type": "Feature",
  "properties": {
    "addr:full":"377 Belle Terre Blvd La Place LA 70068",
    "addr:housenumber":"377",
    "addr:postcode":"70068",
    "addr:street":"Belle Terre Blvd La Place",
    "iso:country":"US",
    "sg:address":"377 Belle Terre Blvd",
    "sg:city":"La Place",
    "sg:classifiers":[
        {
            "category":"Banks & Credit Unions",
            "subcategory":"Bank",
            "type":"Services"
        }
    ],
    "sg:phone":"+1 985 651 0781",
    "sg:postcode":"70068",
    "sg:province":"LA",
    "sg:website":"www.fnbusa.com",
    "wof:name":"First National Bank USA",
    "wof:placetype":"venue"
},
  "geometry": {"coordinates":[-90.502836,30.084615],"type":"Point"}
}