{
  "type": "Feature",
  "properties": {
    "iso:country":"US",
    "sg:address":"507 Levert Dr",
    "sg:city":"Thibodaux",
    "sg:classifiers":[
        {
            "category":"Personal",
            "type":"Services"
        }
    ],
    "sg:phone":"+1 985 447 2659",
    "sg:postcode":"70301",
    "sg:province":"LA",
    "wof:name":"Grand Court Heroines of Jews",
    "wof:placetype":"venue"
},
  "geometry": {"coordinates":[-90.78531700000001,29.78203],"type":"Point"}
}