{
  "type": "Feature",
  "properties": {
    "addr:full":"8033 Barringer Rd Baton Rouge LA 70817",
    "addr:housenumber":"8033",
    "addr:postcode":"70817",
    "addr:street":"Barringer Rd",
    "iso:country":"US",
    "sg:address":"8033 Barringer Rd",
    "sg:city":"Baton Rouge",
    "sg:classifiers":[
        {
            "category":"Education",
            "subcategory":"School",
            "type":"Public Place"
        }
    ],
    "sg:phone":"+1 225 751 0273",
    "sg:postcode":"70817",
    "sg:province":"LA",
    "sg:website":"www.mbsbr.org",
    "wof:name":"Most Blessed Sacrament School",
    "wof:placetype":"venue"
},
  "geometry": {"coordinates":[-91.015435,30.378099],"type":"Point"}
}