{
  "type": "Feature",
  "properties": {
    "iso:country":"US",
    "sg:address":"1024 N Rampart St",
    "sg:city":"New Orleans",
    "sg:classifiers":[
        {
            "category":"Communications",
            "subcategory":"Television Station",
            "type":"Services"
        }
    ],
    "sg:phone":"+1 504 529 6298",
    "sg:postcode":"70116",
    "sg:province":"LA",
    "wof:name":"Eyewitness News",
    "wof:placetype":"venue"
},
  "geometry": {"coordinates":[-90.065547,29.963485],"type":"Point"}
}