{
  "type": "Feature",
  "properties": {
    "iso:country":"US",
    "sg:address":"901 Airline Dr",
    "sg:city":"Kenner",
    "sg:classifiers":[
        {
            "category":"Travel",
            "subcategory":"Hotels & Motels",
            "type":"Entertainment"
        }
    ],
    "sg:phone":"+1 504 469 5000",
    "sg:postcode":"70062",
    "sg:province":"LA",
    "wof:name":"Hilton",
    "wof:placetype":"venue"
},
  "geometry": {"coordinates":[-90.258032,29.982381],"type":"Point"}
}