{
  "type": "Feature",
  "properties": {
    "iso:country":"US",
    "sg:address":"11062 Cloverland Ave",
    "sg:city":"Baton Rouge",
    "sg:classifiers":[
        {
            "category":"Retail",
            "subcategory":"Auto Repair",
            "type":"Services"
        }
    ],
    "sg:phone":"+1 225 292 9270",
    "sg:postcode":"70809",
    "sg:province":"LA",
    "sg:tags":[
        "automobile",
        "customizing"
    ],
    "wof:name":"Rouse Custom Fabrication",
    "wof:placetype":"venue"
},
  "geometry": {"coordinates":[-91.057074,30.394688],"type":"Point"}
}