{
  "type": "Feature",
  "properties": {
    "addr:full":"528 Country Estates Dr Houma LA 70364",
    "addr:housenumber":"528",
    "addr:postcode":"70364",
    "addr:street":"Country Estates Dr",
    "iso:country":"US",
    "sg:address":"528 Country Estates Dr",
    "sg:city":"Houma",
    "sg:classifiers":[
        {
            "category":"Building & Trades",
            "subcategory":"Plumbing",
            "type":"Services"
        }
    ],
    "sg:phone":"+1 985 876 1105",
    "sg:postcode":"70364",
    "sg:province":"LA",
    "sg:tags":[
        "plumbing",
        "contractor"
    ],
    "wof:name":"Stan's Plumbing & Heating Inc",
    "wof:placetype":"venue"
},
  "geometry": {"coordinates":[-90.74263999999999,29.664387],"type":"Point"}
}