{
  "type": "Feature",
  "properties": {
    "iso:country":"US",
    "sg:address":"2514 Bayou Rd",
    "sg:city":"New Orleans",
    "sg:classifiers":[
        {
            "category":"Food & Beverages",
            "subcategory":"Groceries & Convenience Stores",
            "type":"Retail Goods"
        }
    ],
    "sg:phone":"+1 504 945 8373",
    "sg:postcode":"70119",
    "sg:province":"LA",
    "sg:tags":[
        "grocer"
    ],
    "wof:name":"Kwick Stop & Save",
    "wof:placetype":"venue"
},
  "geometry": {"coordinates":[-90.076944,29.977088],"type":"Point"}
}