{
  "type": "Feature",
  "properties": {
    "iso:country":"US",
    "sg:address":"292 Lee Rd",
    "sg:city":"Anacoco",
    "sg:classifiers":[
        {
            "category":"Travel",
            "subcategory":"Campground",
            "type":"Entertainment"
        }
    ],
    "sg:phone":"+1 337 239 6567",
    "sg:postcode":"71403",
    "sg:province":"LA",
    "sg:tags":[
        "camp"
    ],
    "sg:website":"www.lionscamp.org",
    "wof:name":"Louisiana Lion's Camp",
    "wof:placetype":"venue"
},
  "geometry": {"coordinates":[-93.392849,31.226568],"type":"Point"}
}