{
  "type": "Feature",
  "properties": {
    "iso:country":"US",
    "sg:address":"220 W Church St",
    "sg:city":"Opelousas",
    "sg:classifiers":[
        {
            "category":"Retail",
            "subcategory":"Repair Shop",
            "type":"Services"
        }
    ],
    "sg:phone":"+1 337 942 9900",
    "sg:postcode":"70570",
    "sg:province":"LA",
    "sg:tags":[
        "lock",
        "locksmith"
    ],
    "wof:name":"Ron's Locksmith & Ornamental",
    "wof:placetype":"venue"
},
  "geometry": {"coordinates":[-92.083403,30.543482],"type":"Point"}
}