{
  "type": "Feature",
  "properties": {
    "addr:full":"100 W Elm Ave Eunice LA 70535",
    "addr:housenumber":"100",
    "addr:postcode":"70535",
    "addr:street":"W Elm Ave",
    "iso:country":"US",
    "sg:address":"100 W Elm Ave",
    "sg:city":"Eunice",
    "sg:classifiers":[
        {
            "category":"Autos & Motor Vehicles",
            "subcategory":"Auto Supplies",
            "type":"Retail Goods"
        }
    ],
    "sg:phone":"+1 337 457 0552",
    "sg:postcode":"70535",
    "sg:province":"LA",
    "sg:tags":[
        "automotive",
        "tire"
    ],
    "wof:name":"Troy's Tire & Etc",
    "wof:placetype":"venue"
},
  "geometry": {"coordinates":[-92.41632799999999,30.488581],"type":"Point"}
}