{
  "type": "Feature",
  "properties": {
    "iso:country":"US",
    "sg:address":"318 N Court St",
    "sg:city":"Opelousas",
    "sg:classifiers":[
        {
            "category":"Government",
            "subcategory":"Office",
            "type":"Public Place"
        }
    ],
    "sg:phone":"+1 337 948 2533",
    "sg:postcode":"70570",
    "sg:province":"LA",
    "sg:tags":[
        "village"
    ],
    "wof:name":"Opelousas Building Inspector",
    "wof:placetype":"venue"
},
  "geometry": {"coordinates":[-92.082245,30.536889],"type":"Point"}
}