{
  "type": "Feature",
  "properties": {
    "addr:full":"1543 Delplaza Dr Baton Rouge LA 70815",
    "addr:housenumber":"1543",
    "addr:postcode":"70815",
    "addr:street":"Delplaza Dr",
    "iso:country":"US",
    "sg:address":"1543 Delplaza Dr",
    "sg:city":"Baton Rouge",
    "sg:classifiers":[
        {
            "category":"Cinema",
            "subcategory":"Movie Theater",
            "type":"Entertainment"
        }
    ],
    "sg:phone":"+1 225 928 8310",
    "sg:postcode":"70815",
    "sg:province":"LA",
    "wof:name":"Theatre The Co Of Louisiana",
    "wof:placetype":"venue"
},
  "geometry": {"coordinates":[-91.08256,30.437923],"type":"Point"}
}