{
  "type": "Feature",
  "properties": {
    "iso:country":"US",
    "sg:address":"9187 Huntington Ave",
    "sg:city":"Denham Springs",
    "sg:classifiers":[
        {
            "category":"Freight",
            "type":"Transportation"
        }
    ],
    "sg:phone":"+1 225 664 9776",
    "sg:postcode":"70726",
    "sg:province":"LA",
    "sg:tags":[
        "operator",
        "local",
        "trucking"
    ],
    "wof:name":"Lm Express Inc",
    "wof:placetype":"venue"
},
  "geometry": {"coordinates":[-90.933617,30.506204],"type":"Point"}
}