{
  "type": "Feature",
  "properties": {
    "addr:full":"2632 E Napoleon St Sulphur LA 70663",
    "addr:housenumber":"2632",
    "addr:postcode":"70663",
    "addr:street":"E Napoleon St",
    "iso:country":"US",
    "sg:address":"2632 E Napoleon St",
    "sg:city":"Sulphur",
    "sg:classifiers":[
        {
            "category":"Travel",
            "subcategory":"Hotels & Motels",
            "type":"Entertainment"
        }
    ],
    "sg:phone":"+1 337 625 3411",
    "sg:postcode":"70663",
    "sg:province":"LA",
    "sg:tags":[
        "operation"
    ],
    "wof:name":"Pelican Motel",
    "wof:placetype":"venue"
},
  "geometry": {"coordinates":[-93.34572900000001,30.236856],"type":"Point"}
}