{
  "type": "Feature",
  "properties": {
    "iso:country":"US",
    "sg:address":"4334 Christina St",
    "sg:city":"Lake Charles",
    "sg:classifiers":[
        {
            "category":"Banks & Credit Unions",
            "subcategory":"Investment Brokerage",
            "type":"Services"
        },
        {
            "category":"Banks & Credit Unions",
            "subcategory":"Financial Services",
            "type":"Services"
        }
    ],
    "sg:phone":"+1 337 479 1049",
    "sg:postcode":"70605",
    "sg:province":"LA",
    "sg:tags":[
        "stock",
        "closed",
        "bond"
    ],
    "wof:name":"Quest Capital Investments Lake",
    "wof:placetype":"venue"
},
  "geometry": {"coordinates":[-93.241392,30.17661],"type":"Point"}
}