{
  "type": "Feature",
  "properties": {
    "iso:country":"US",
    "sg:address":"563 Hickory Ave",
    "sg:city":"New Orleans",
    "sg:classifiers":[
        {
            "category":"Building & Trades",
            "subcategory":"Plumbing",
            "type":"Services"
        }
    ],
    "sg:phone":"+1 504 738 6763",
    "sg:postcode":"70123",
    "sg:province":"LA",
    "sg:tags":[
        "contractor"
    ],
    "wof:name":"Efrain S Lugo",
    "wof:placetype":"venue"
},
  "geometry": {"coordinates":[-90.198599,29.944805],"type":"Point"}
}