{
  "type": "Feature",
  "properties": {
    "addr:full":"819 Napoleon Ave Sunset LA 70584",
    "addr:housenumber":"819",
    "addr:postcode":"70584",
    "addr:street":"Napoleon Ave",
    "iso:country":"US",
    "sg:address":"819 Napoleon Ave",
    "sg:city":"Sunset",
    "sg:classifiers":[
        {
            "category":"Banks & Credit Unions",
            "subcategory":"Investment Brokerage",
            "type":"Services"
        }
    ],
    "sg:phone":"+1 337 662 6655",
    "sg:postcode":"70584",
    "sg:province":"LA",
    "sg:tags":[
        "security"
    ],
    "wof:name":"Edward Jones Co",
    "wof:placetype":"venue"
},
  "geometry": {"coordinates":[-92.065152,30.411756],"type":"Point"}
}