{
  "type": "Feature",
  "properties": {
    "iso:country":"US",
    "sg:address":"42241 S Morrison Blvd",
    "sg:city":"Hammond",
    "sg:classifiers":[
        {
            "category":"Retail",
            "subcategory":"Auto Repair",
            "type":"Services"
        }
    ],
    "sg:phone":"+1 985 542 1902",
    "sg:postcode":"70403",
    "sg:province":"LA",
    "sg:tags":[
        "truck"
    ],
    "wof:name":"Big Wheel Diesel Repair Shop",
    "wof:placetype":"venue"
},
  "geometry": {"coordinates":[-90.48260399999999,30.46951],"type":"Point"}
}