{
  "type": "Feature",
  "properties": {
    "addr:full":"118 Iroquois Dr Abita Springs LA 70420",
    "addr:housenumber":"118",
    "addr:postcode":"70420",
    "addr:street":"Iroquois Dr",
    "iso:country":"US",
    "sg:address":"118 Iroquois Dr",
    "sg:city":"Abita Springs",
    "sg:classifiers":[
        {
            "category":"Shopping",
            "subcategory":"Computers & Home Electronics",
            "type":"Retail Goods"
        }
    ],
    "sg:phone":"+1 985 871 7101",
    "sg:postcode":"70420",
    "sg:province":"LA",
    "sg:tags":[
        "software"
    ],
    "wof:name":"Stratagem Software Intl Inc",
    "wof:placetype":"venue"
},
  "geometry": {"coordinates":[-90.05362,30.460471],"type":"Point"}
}