{
  "type": "Feature",
  "properties": {
    "iso:country":"US",
    "sg:address":"601 Pleasant Dr",
    "sg:city":"Bastrop",
    "sg:classifiers":[
        {
            "category":"Real Estate",
            "subcategory":"Real Estate Operator",
            "type":"Services"
        }
    ],
    "sg:phone":"+1 318 281 6029",
    "sg:postcode":"71220",
    "sg:province":"LA",
    "sg:tags":[
        "apartment"
    ],
    "wof:name":"Morehouse Gardens Apartments",
    "wof:placetype":"venue"
},
  "geometry": {"coordinates":[-91.93183999999999,32.783139],"type":"Point"}
}