{
  "type": "Feature",
  "properties": {
    "iso:country":"US",
    "sg:address":"2233 Canal St",
    "sg:city":"New Orleans",
    "sg:classifiers":[
        {
            "category":"Insurance",
            "subcategory":"Insurance Agent",
            "type":"Services"
        }
    ],
    "sg:phone":"+1 504 821 7001",
    "sg:postcode":"70119",
    "sg:province":"LA",
    "wof:name":"State Farm Acceptance Corp",
    "wof:placetype":"venue"
},
  "geometry": {"coordinates":[-90.082787,29.962652],"type":"Point"}
}