{
  "type": "Feature",
  "properties": {
    "iso:country":"US",
    "sg:address":"5604 Jennifer Ln",
    "sg:city":"Bossier City",
    "sg:classifiers":[
        {
            "category":"Banks & Credit Unions",
            "subcategory":"Bank",
            "type":"Services"
        }
    ],
    "sg:phone":"+1 318 841 0165",
    "sg:postcode":"71112",
    "sg:province":"LA",
    "sg:tags":[
        "loan",
        "real estate"
    ],
    "wof:name":"Prosource Funding Ruby",
    "wof:placetype":"venue"
},
  "geometry": {"coordinates":[-93.64483199999999,32.451854],"type":"Point"}
}