{
  "type": "Feature",
  "properties": {
    "iso:country":"US",
    "sg:address":"109 Chamale Cove",
    "sg:city":"Slidell",
    "sg:classifiers":[
        {
            "category":"Home & Garden",
            "subcategory":"Home Furnishings",
            "type":"Retail Goods"
        }
    ],
    "sg:phone":"+1 985 645 0914",
    "sg:postcode":"70460",
    "sg:province":"LA",
    "sg:tags":[
        "curtain",
        "made",
        "drapery"
    ],
    "wof:name":"Godwin's Draperies & Shutters",
    "wof:placetype":"venue"
},
  "geometry": {"coordinates":[-89.787178,30.277384],"type":"Point"}
}