{
  "type": "Feature",
  "properties": {
    "addr:full":"8130 Kelwood Ave Baton Rouge LA 70806",
    "addr:postcode":"8130;70806",
    "addr:street":"Kelwood Ave",
    "iso:country":"US",
    "sg:address":"8130 Kelwood Ave",
    "sg:city":"Baton Rouge",
    "sg:classifiers":[
        {
            "category":"Professional",
            "subcategory":"Management & Consulting",
            "type":"Services"
        }
    ],
    "sg:phone":"+1 225 216 0668",
    "sg:postcode":"70806",
    "sg:province":"LA",
    "sg:tags":[
        "fuel"
    ],
    "wof:name":"Horizon Management & Conslntg",
    "wof:placetype":"venue"
},
  "geometry": {"coordinates":[-91.099446,30.447515],"type":"Point"}
}