{
  "type": "Feature",
  "properties": {
    "addr:full":"7809 Airline Dr Metairie LA 70003",
    "addr:housenumber":"7809",
    "addr:postcode":"70003",
    "addr:street":"Airline Dr",
    "iso:country":"US",
    "sg:address":"7809 Airline Dr",
    "sg:city":"Metairie",
    "sg:classifiers":[
        {
            "category":"Professional",
            "subcategory":"Detective & Security Services",
            "type":"Services"
        }
    ],
    "sg:phone":"+1 504 739 1011",
    "sg:postcode":"70003",
    "sg:province":"LA",
    "wof:name":"Risk Control Investigative Svc",
    "wof:placetype":"venue"
},
  "geometry": {"coordinates":[-90.220603,29.978518],"type":"Point"}
}