{
  "type": "Feature",
  "properties": {
    "iso:country":"US",
    "sg:address":"3450 Hwy 190",
    "sg:city":"Mandeville",
    "sg:classifiers":[
        {
            "category":"Shopping",
            "subcategory":"Clothing, Apparel, & Fashions",
            "type":"Retail Goods"
        }
    ],
    "sg:phone":"+1 985 674 9225",
    "sg:postcode":"70471",
    "sg:province":"LA",
    "sg:website":"www.oldnavy.com",
    "wof:name":"Old Navy",
    "wof:placetype":"venue"
},
  "geometry": {"coordinates":[-90.083564,30.392002],"type":"Point"}
}