{
  "type": "Feature",
  "properties": {
    "addr:full":"235 N Live Oak St Simmesport LA 71369",
    "addr:housenumber":"235",
    "addr:postcode":"71369",
    "addr:street":"N Live Oak St",
    "iso:country":"US",
    "sg:address":"235 N Live Oak St",
    "sg:city":"Simmesport",
    "sg:classifiers":[
        {
            "category":"Personal",
            "subcategory":"Beauty Salon",
            "type":"Services"
        }
    ],
    "sg:phone":"+1 318 941 2994",
    "sg:postcode":"71369",
    "sg:province":"LA",
    "wof:name":"Patsy's Beauty Shop",
    "wof:placetype":"venue"
},
  "geometry": {"coordinates":[-91.82371999999999,30.98948],"type":"Point"}
}