{
  "type": "Feature",
  "properties": {
    "addr:full":"919 Main St Elton LA 70532",
    "addr:housenumber":"919",
    "addr:postcode":"70532",
    "addr:street":"Main St",
    "iso:country":"US",
    "sg:address":"919 Main St",
    "sg:city":"Elton",
    "sg:classifiers":[
        {
            "category":"Banks & Credit Unions",
            "subcategory":"Bank",
            "type":"Services"
        }
    ],
    "sg:phone":"+1 337 584 2224",
    "sg:postcode":"70532",
    "sg:province":"LA",
    "wof:name":"Hibernia National Bank",
    "wof:placetype":"venue"
},
  "geometry": {"coordinates":[-92.694558,30.481254],"type":"Point"}
}