{
  "type": "Feature",
  "properties": {
    "addr:full":"619 Cypress St Gibson LA 70356",
    "addr:housenumber":"619",
    "addr:postcode":"70356",
    "addr:street":"Cypress St",
    "iso:country":"US",
    "sg:address":"619 Cypress St",
    "sg:city":"Gibson",
    "sg:classifiers":[
        {
            "category":"Retail",
            "subcategory":"Repair Shop",
            "type":"Services"
        }
    ],
    "sg:phone":"+1 985 575 2103",
    "sg:postcode":"70356",
    "sg:province":"LA",
    "sg:tags":[
        "welding"
    ],
    "wof:name":"John Le Blanc Welding Svc",
    "wof:placetype":"venue"
},
  "geometry": {"coordinates":[-90.9975,29.700902],"type":"Point"}
}