{
  "type": "Feature",
  "properties": {
    "addr:full":"3000 18th St Metairie LA 70002",
    "addr:housenumber":"3000",
    "addr:postcode":"70002",
    "addr:street":"18Th St",
    "iso:country":"US",
    "sg:address":"3000 18th St",
    "sg:city":"Metairie",
    "sg:classifiers":[
        {
            "category":"Professional",
            "subcategory":"Lawyer & Legal Services",
            "type":"Services"
        }
    ],
    "sg:phone":"+1 504 835 1200",
    "sg:postcode":"70002",
    "sg:province":"LA",
    "sg:tags":[
        "attorney"
    ],
    "wof:name":"Holahan John M Jr Law Offices",
    "wof:placetype":"venue"
},
  "geometry": {"coordinates":[-90.153387,30.008308],"type":"Point"}
}