{
  "type": "Feature",
  "properties": {
    "addr:full":"1207 Defee Lankford Rd Marion LA 71260",
    "addr:housenumber":"1207",
    "addr:postcode":"71260",
    "addr:street":"Defee Lankford Rd",
    "iso:country":"US",
    "sg:address":"1207 Defee Lankford Rd",
    "sg:city":"Marion",
    "sg:classifiers":[
        {
            "category":"Shopping",
            "subcategory":"Gifts & Souvenirs",
            "type":"Retail Goods"
        }
    ],
    "sg:phone":"+1 318 292 5128",
    "sg:postcode":"71260",
    "sg:province":"LA",
    "wof:name":"Country At Heart",
    "wof:placetype":"venue"
},
  "geometry": {"coordinates":[-92.217822,32.8532],"type":"Point"}
}