{
  "type": "Feature",
  "properties": {
    "addr:full":"16149 State Bank Dr Prairieville LA 70769",
    "addr:housenumber":"16149",
    "addr:postcode":"70769",
    "addr:street":"State Bank Dr Prairieville",
    "iso:country":"US",
    "sg:address":"16149 State Bank Dr",
    "sg:city":"Prairieville",
    "sg:classifiers":[
        {
            "category":"Professional",
            "subcategory":"Research",
            "type":"Services"
        }
    ],
    "sg:phone":"+1 225 677 9873",
    "sg:postcode":"70769",
    "sg:province":"LA",
    "sg:tags":[
        "laboratory"
    ],
    "wof:name":"A B Labs",
    "wof:placetype":"venue"
},
  "geometry": {"coordinates":[-90.97315,30.302199],"type":"Point"}
}