{
  "type": "Feature",
  "properties": {
    "iso:country":"US",
    "sg:address":"337 Caples Rd",
    "sg:city":"West Monroe",
    "sg:classifiers":[
        {
            "category":"Retail",
            "subcategory":"Repair Shop",
            "type":"Services"
        }
    ],
    "sg:phone":"+1 318 387 5359",
    "sg:postcode":"71292",
    "sg:province":"LA",
    "sg:tags":[
        "welding"
    ],
    "wof:name":"Swenk & Co Inc",
    "wof:placetype":"venue"
},
  "geometry": {"coordinates":[-92.22177600000001,32.43721],"type":"Point"}
}