{
  "type": "Feature",
  "properties": {
    "addr:full":"7225 Scenic Hwy Baton Rouge LA 70807",
    "addr:housenumber":"7225",
    "addr:postcode":"70807",
    "addr:street":"Scenic Hwy",
    "iso:country":"US",
    "sg:address":"7225 Scenic Hwy",
    "sg:city":"Baton Rouge",
    "sg:classifiers":[
        {
            "category":"Retail",
            "subcategory":"Auto Repair",
            "type":"Services"
        }
    ],
    "sg:phone":"+1 225 357 4888",
    "sg:postcode":"70807",
    "sg:province":"LA",
    "sg:tags":[
        "repairing",
        "automobile"
    ],
    "wof:name":"Veal's Automotive",
    "wof:placetype":"venue"
},
  "geometry": {"coordinates":[-91.175781,30.514648],"type":"Point"}
}