{
  "type": "Feature",
  "properties": {
    "iso:country":"US",
    "sg:address":"2200 Westbank Expy",
    "sg:city":"Harvey",
    "sg:classifiers":[
        {
            "category":"Restaurant",
            "type":"Food & Drink"
        }
    ],
    "sg:phone":"+1 504 227 0270",
    "sg:postcode":"70058",
    "sg:province":"LA",
    "sg:tags":[
        "eating"
    ],
    "wof:name":"Macs & Co",
    "wof:placetype":"venue"
},
  "geometry": {"coordinates":[-90.071489,29.90108],"type":"Point"}
}