{
  "type": "Feature",
  "properties": {
    "iso:country":"US",
    "sg:address":"2 Canal St",
    "sg:city":"New Orleans",
    "sg:classifiers":[
        {
            "category":"Government",
            "subcategory":"Office",
            "type":"Public Place"
        }
    ],
    "sg:phone":"+1 504 565 7230",
    "sg:postcode":"70130",
    "sg:province":"LA",
    "sg:tags":[
        "administrative",
        "program",
        "economic",
        "general"
    ],
    "wof:name":"Economic Development",
    "wof:placetype":"venue"
},
  "geometry": {"coordinates":[-90.064413,29.950375],"type":"Point"}
}