{
  "type": "Feature",
  "properties": {
    "addr:full":"2701 Louisville Ave Monroe LA 71201",
    "addr:housenumber":"2701",
    "addr:postcode":"71201",
    "addr:street":"Louisville Ave",
    "iso:country":"US",
    "sg:address":"2701 Louisville Ave",
    "sg:city":"Monroe",
    "sg:classifiers":[
        {
            "category":"Retail",
            "subcategory":"Portrait Studio",
            "type":"Services"
        }
    ],
    "sg:phone":"+1 318 387 6990",
    "sg:postcode":"71201",
    "sg:province":"LA",
    "sg:tags":[
        "photo"
    ],
    "wof:name":"PCA International LLC",
    "wof:placetype":"venue"
},
  "geometry": {"coordinates":[-92.09347200000001,32.524803],"type":"Point"}
}