{
  "type": "Feature",
  "properties": {
    "iso:country":"US",
    "sg:address":"7240 Crowder Blvd",
    "sg:city":"New Orleans",
    "sg:classifiers":[
        {
            "category":"Retail",
            "subcategory":"Laundry & Dry Cleaning",
            "type":"Services"
        }
    ],
    "sg:phone":"+1 504 246 5980",
    "sg:postcode":"70127",
    "sg:province":"LA",
    "sg:tags":[
        "cleaners"
    ],
    "wof:name":"Sun Tailor Cleaners",
    "wof:placetype":"venue"
},
  "geometry": {"coordinates":[-89.996509,30.034731],"type":"Point"}
}