{
  "type": "Feature",
  "properties": {
    "iso:country":"US",
    "sg:address":"3021 Pontchartrain Dr",
    "sg:city":"Slidell",
    "sg:classifiers":[
        {
            "category":"Home & Garden",
            "subcategory":"Hardware",
            "type":"Retail Goods"
        }
    ],
    "sg:phone":"+1 985 643 2468",
    "sg:postcode":"70458",
    "sg:province":"LA",
    "wof:name":"Slidell Hardware",
    "wof:placetype":"venue"
},
  "geometry": {"coordinates":[-89.78496699999999,30.262951],"type":"Point"}
}