{
  "type": "Feature",
  "properties": {
    "addr:full":"19370 Hwy 36 Covington LA 70433",
    "addr:housenumber":"19370",
    "addr:postcode":"70433",
    "addr:street":"Hwy 36",
    "iso:country":"US",
    "sg:address":"19370 Hwy 36",
    "sg:city":"Covington",
    "sg:classifiers":[
        {
            "category":"Professional",
            "subcategory":"Lawyer & Legal Services",
            "type":"Services"
        }
    ],
    "sg:phone":"+1 985 875 0275",
    "sg:postcode":"70433",
    "sg:province":"LA",
    "sg:tags":[
        "attorney"
    ],
    "wof:name":"Brooks Law Firm",
    "wof:placetype":"venue"
},
  "geometry": {"coordinates":[-90.08255,30.479424],"type":"Point"}
}