{
  "type": "Feature",
  "properties": {
    "iso:country":"US",
    "sg:address":"31575 Hwy 16 S",
    "sg:city":"Denham Springs",
    "sg:classifiers":[
        {
            "category":"Personal",
            "subcategory":"Beauty Salon",
            "type":"Services"
        }
    ],
    "sg:phone":"+1 225 791 7949",
    "sg:postcode":"70726",
    "sg:province":"LA",
    "wof:name":"Shear Xpressions",
    "wof:placetype":"venue"
},
  "geometry": {"coordinates":[-90.86408900000001,30.37925],"type":"Point"}
}