{
  "type": "Feature",
  "properties": {
    "iso:country":"US",
    "sg:address":"3329 Houston River Rd",
    "sg:city":"Westlake",
    "sg:classifiers":[
        {
            "category":"Travel",
            "subcategory":"Campground",
            "type":"Entertainment"
        }
    ],
    "sg:phone":"+1 337 433 2038",
    "sg:postcode":"70669",
    "sg:province":"LA",
    "wof:name":"Tall Pines Rv Park",
    "wof:placetype":"venue"
},
  "geometry": {"coordinates":[-93.296257,30.27068],"type":"Point"}
}