{
  "type": "Feature",
  "properties": {
    "iso:country":"US",
    "sg:address":"12568 Bonne Idee Rd",
    "sg:city":"Bonita",
    "sg:classifiers":[
        {
            "category":"Manufacturing",
            "subcategory":"Food",
            "type":"Manufacturing & Wholesale Goods"
        }
    ],
    "sg:phone":"+1 318 823 2488",
    "sg:postcode":"71223",
    "sg:province":"LA",
    "sg:tags":[
        "product"
    ],
    "wof:name":"Spencer Herrington",
    "wof:placetype":"venue"
},
  "geometry": {"coordinates":[-91.711223,32.864044],"type":"Point"}
}