{
  "type": "Feature",
  "properties": {
    "iso:country":"US",
    "sg:address":"2000 Florida St",
    "sg:city":"Mandeville",
    "sg:classifiers":[
        {
            "category":"Autos & Motor Vehicles",
            "subcategory":"Fuel & Gas Station",
            "type":"Retail Goods"
        }
    ],
    "sg:phone":"+1 985 727 1141",
    "sg:postcode":"70448",
    "sg:province":"LA",
    "sg:tags":[
        "oil"
    ],
    "wof:name":"Minnie's BP",
    "wof:placetype":"venue"
},
  "geometry": {"coordinates":[-90.06209800000001,30.363754],"type":"Point"}
}