{
  "type": "Feature",
  "properties": {
    "addr:full":"1312 Fulton St Kenner LA 70062",
    "addr:housenumber":"1312",
    "addr:postcode":"70062",
    "addr:street":"Fulton St",
    "iso:country":"US",
    "sg:address":"1312 Fulton St",
    "sg:city":"Kenner",
    "sg:classifiers":[
        {
            "category":"Retail",
            "subcategory":"Auto Repair",
            "type":"Services"
        }
    ],
    "sg:phone":"+1 504 466 3963",
    "sg:postcode":"70062",
    "sg:province":"LA",
    "sg:tags":[
        "automobile",
        "top",
        "upholstery"
    ],
    "wof:name":"Knight's Auto Trim",
    "wof:placetype":"venue"
},
  "geometry": {"coordinates":[-90.250737,30.00354],"type":"Point"}
}