{
  "type": "Feature",
  "properties": {
    "addr:full":"1650 Cameron Ave Baton Rouge LA 70806",
    "addr:housenumber":"1650",
    "addr:postcode":"70806",
    "addr:street":"Cameron Ave",
    "iso:country":"US",
    "sg:address":"1650 Cameron Ave",
    "sg:city":"Baton Rouge",
    "sg:classifiers":[
        {
            "category":"Real Estate",
            "subcategory":"Developer",
            "type":"Services"
        }
    ],
    "sg:phone":"+1 225 928 6042",
    "sg:postcode":"70806",
    "sg:province":"LA",
    "wof:name":"M B Washauer",
    "wof:placetype":"venue"
},
  "geometry": {"coordinates":[-91.12128199999999,30.435742],"type":"Point"}
}