{
  "type": "Feature",
  "properties": {
    "iso:country":"US",
    "sg:address":"1752 Center St",
    "sg:city":"New Iberia",
    "sg:classifiers":[
        {
            "category":"Recreation",
            "type":"Entertainment"
        }
    ],
    "sg:phone":"+1 337 364 7573",
    "sg:postcode":"70560",
    "sg:province":"LA",
    "sg:tags":[
        "center"
    ],
    "wof:name":"Gator Tracks",
    "wof:placetype":"venue"
},
  "geometry": {"coordinates":[-91.837709,29.987512],"type":"Point"}
}