{
  "type": "Feature",
  "properties": {
    "iso:country":"US",
    "sg:address":"304 E Front St",
    "sg:city":"Crowley",
    "sg:classifiers":[
        {
            "category":"Professional",
            "type":"Services"
        }
    ],
    "sg:phone":"+1 337 783 0300",
    "sg:postcode":"70526",
    "sg:province":"LA",
    "sg:tags":[
        "establishment"
    ],
    "wof:name":"Southwest Ambulatory Bhvrl",
    "wof:placetype":"venue"
},
  "geometry": {"coordinates":[-92.367622,30.210878],"type":"Point"}
}