{
  "type": "Feature",
  "properties": {
    "iso:country":"US",
    "sg:address":"17425 Airline Hwy",
    "sg:city":"Prairieville",
    "sg:classifiers":[
        {
            "category":"Restaurant",
            "type":"Food & Drink"
        }
    ],
    "sg:phone":"+1 225 673 8876",
    "sg:postcode":"70769",
    "sg:province":"LA",
    "wof:name":"Frank's Restaurant & Catering",
    "wof:placetype":"venue"
},
  "geometry": {"coordinates":[-90.980856,30.324809],"type":"Point"}
}