{
  "type": "Feature",
  "properties": {
    "iso:country":"US",
    "sg:address":"2400 Cypress St",
    "sg:city":"West Monroe",
    "sg:classifiers":[
        {
            "category":"Shopping",
            "subcategory":"Hobbies, Toys, & Games",
            "type":"Retail Goods"
        }
    ],
    "sg:phone":"+1 318 325 6519",
    "sg:postcode":"71291",
    "sg:province":"LA",
    "sg:tags":[
        "craft",
        "supply"
    ],
    "sg:website":"www.bayoucraftersmall.com",
    "wof:name":"Bayou Crafters Mall",
    "wof:placetype":"venue"
},
  "geometry": {"coordinates":[-92.14317200000001,32.518191],"type":"Point"}
}