{
  "type": "Feature",
  "properties": {
    "addr:full":"635 St. Peter St. New Orleans LA 70130",
    "addr:housenumber":"635",
    "addr:postcode":"70130",
    "addr:street":"St. Peter St.",
    "iso:country":"US",
    "sg:address":"635 St. Peter St.",
    "sg:city":"New Orleans",
    "sg:classifiers":[
        {
            "category":"Shopping",
            "subcategory":"Jewelry",
            "type":"Retail Goods"
        }
    ],
    "sg:phone":"+1 866 432 4568",
    "sg:postcode":"70130",
    "sg:province":"LA",
    "sg:website":"www.bijounola.com/index.html",
    "wof:name":"Bijounola Jewelry",
    "wof:placetype":"venue"
},
  "geometry": {"coordinates":[-90.06435399999999,29.957757],"type":"Point"}
}