{
  "type": "Feature",
  "properties": {
    "iso:country":"US",
    "sg:address":"2330 Lapalco Blvd Ste 10",
    "sg:city":"Harvey",
    "sg:classifiers":[
        {
            "category":"Health Services",
            "subcategory":"Doctor",
            "type":"Services"
        }
    ],
    "sg:phone":"+1 504 366 3302",
    "sg:postcode":"70058",
    "sg:province":"LA",
    "sg:tags":[
        "medicine",
        "sport"
    ],
    "wof:name":"Professional Therapy Services Inc",
    "wof:placetype":"venue"
},
  "geometry": {"coordinates":[-90.058098,29.873199],"type":"Point"}
}