{
  "type": "Feature",
  "properties": {
    "iso:country":"US",
    "sg:address":"5607 Cameron St Ste 4",
    "sg:city":"Scott",
    "sg:classifiers":[
        {
            "category":"Communications",
            "type":"Services"
        }
    ],
    "sg:phone":"+1 337 205 2541",
    "sg:postcode":"70583",
    "sg:province":"LA",
    "sg:tags":[
        "web",
        "design"
    ],
    "sg:website":"www.kalidust.com/",
    "wof:name":"Kalidust Internet Advertising",
    "wof:placetype":"venue"
},
  "geometry": {"coordinates":[-92.09056099999999,30.233051],"type":"Point"}
}