{
  "type": "Feature",
  "properties": {
    "iso:country":"US",
    "sg:address":"1455 Hwy 456",
    "sg:city":"Lecompte",
    "sg:classifiers":[
        {
            "category":"Real Estate",
            "subcategory":"Real Estate Operator",
            "type":"Services"
        }
    ],
    "sg:phone":"+1 318 776 5525",
    "sg:postcode":"71346",
    "sg:province":"LA",
    "sg:tags":[
        "cane",
        "lessor",
        "mfg",
        "sugar",
        "raw",
        "property"
    ],
    "wof:name":"E Boniol Farm",
    "wof:placetype":"venue"
},
  "geometry": {"coordinates":[-92.38028,31.056406],"type":"Point"}
}