{
  "type": "Feature",
  "properties": {
    "addr:full":"411 N Magnolia St Hammond LA 70401",
    "addr:housenumber":"411",
    "addr:postcode":"70401",
    "addr:street":"N Magnolia St",
    "iso:country":"US",
    "sg:address":"411 N Magnolia St",
    "sg:city":"Hammond",
    "sg:classifiers":[
        {
            "category":"Building & Trades",
            "subcategory":"Construction",
            "type":"Services"
        }
    ],
    "sg:phone":"+1 985 345 3517",
    "sg:postcode":"70401",
    "sg:province":"LA",
    "sg:tags":[
        "resurfacing",
        "laying",
        "refinishing",
        "floor"
    ],
    "wof:name":"Pulliam Floor Sanding",
    "wof:placetype":"venue"
},
  "geometry": {"coordinates":[-90.46465499999999,30.507483],"type":"Point"}
}