{
  "type": "Feature",
  "properties": {
    "iso:country":"US",
    "sg:address":"20744 Old Scenic Hwy",
    "sg:city":"Zachary",
    "sg:classifiers":[
        {
            "category":"Retail",
            "subcategory":"Veterinary Services",
            "type":"Services"
        }
    ],
    "sg:phone":"+1 225 658 2242",
    "sg:postcode":"70791",
    "sg:province":"LA",
    "sg:tags":[
        "veterinarian"
    ],
    "wof:name":"Plains Veterinary Hospital",
    "wof:placetype":"venue"
},
  "geometry": {"coordinates":[-91.192279,30.659822],"type":"Point"}
}