{
  "type": "Feature",
  "properties": {
    "iso:country":"US",
    "sg:address":"141 Aspen Sq",
    "sg:city":"Denham Springs",
    "sg:classifiers":[
        {
            "category":"Recreation",
            "type":"Entertainment"
        }
    ],
    "sg:phone":"+1 225 665 3301",
    "sg:postcode":"70726",
    "sg:province":"LA",
    "sg:tags":[
        "martial",
        "arts",
        "instruction"
    ],
    "wof:name":"Ata Black Belt Academy",
    "wof:placetype":"venue"
},
  "geometry": {"coordinates":[-90.95573,30.460259],"type":"Point"}
}