{
  "type": "Feature",
  "properties": {
    "addr:full":"42019 Betty St Gonzales LA 70737",
    "addr:housenumber":"42019",
    "addr:postcode":"70737",
    "addr:street":"Betty St",
    "iso:country":"US",
    "sg:address":"42019 Betty St",
    "sg:city":"Gonzales",
    "sg:classifiers":[
        {
            "category":"Building & Trades",
            "subcategory":"Construction",
            "type":"Services"
        }
    ],
    "sg:phone":"+1 225 622 5501",
    "sg:postcode":"70737",
    "sg:province":"LA",
    "sg:tags":[
        "residential",
        "designer"
    ],
    "wof:name":"Affordable Design Svc",
    "wof:placetype":"venue"
},
  "geometry": {"coordinates":[-90.90308,30.281103],"type":"Point"}
}