{
  "type": "Feature",
  "properties": {
    "iso:country":"US",
    "sg:address":"127 Lake Powell Dr",
    "sg:city":"West Monroe",
    "sg:classifiers":[
        {
            "category":"Manufacturing",
            "subcategory":"Printing",
            "type":"Manufacturing & Wholesale Goods"
        }
    ],
    "sg:phone":"+1 318 397 0250",
    "sg:postcode":"71292",
    "sg:province":"LA",
    "sg:tags":[
        "screen"
    ],
    "wof:name":"First Impression Graphics",
    "wof:placetype":"venue"
},
  "geometry": {"coordinates":[-92.225786,32.505036],"type":"Point"}
}