{
  "type": "Feature",
  "properties": {
    "iso:country":"US",
    "sg:address":"8320 Line Ave",
    "sg:city":"Shreveport",
    "sg:classifiers":[
        {
            "category":"Retail",
            "subcategory":"Repair Shop",
            "type":"Services"
        }
    ],
    "sg:phone":"+1 318 868 2914",
    "sg:postcode":"71106",
    "sg:province":"LA",
    "sg:tags":[
        "lock",
        "locksmith"
    ],
    "wof:name":"A-Line Avenue Locksmith",
    "wof:placetype":"venue"
},
  "geometry": {"coordinates":[-93.743584,32.429154],"type":"Point"}
}