{
  "type": "Feature",
  "properties": {
    "addr:full":"1605 N University Ave Lafayette LA 70506",
    "addr:housenumber":"1605",
    "addr:postcode":"70506",
    "addr:street":"N University Ave",
    "iso:country":"US",
    "sg:address":"1605 N University Ave",
    "sg:city":"Lafayette",
    "sg:classifiers":[
        {
            "category":"Travel",
            "subcategory":"Hotels & Motels",
            "type":"Entertainment"
        }
    ],
    "sg:phone":"+1 337 232 6131",
    "sg:postcode":"70506",
    "sg:province":"LA",
    "wof:name":"Calloway's Inn",
    "wof:placetype":"venue"
},
  "geometry": {"coordinates":[-92.035599,30.249599],"type":"Point"}
}