{
  "type": "Feature",
  "properties": {
    "addr:full":"299 Mill St Campti LA 71411",
    "addr:housenumber":"299",
    "addr:postcode":"71411",
    "addr:street":"Mill St",
    "iso:country":"US",
    "sg:address":"299 Mill St",
    "sg:city":"Campti",
    "sg:classifiers":[
        {
            "category":"Organizations",
            "subcategory":"Religious Organization",
            "type":"Services"
        }
    ],
    "sg:phone":"+1 318 476 3739",
    "sg:postcode":"71411",
    "sg:province":"LA",
    "sg:tags":[
        "church"
    ],
    "wof:name":"Campti Baptist Church",
    "wof:placetype":"venue"
},
  "geometry": {"coordinates":[-93.118347,31.893672],"type":"Point"}
}