{
  "type": "Feature",
  "properties": {
    "iso:country":"US",
    "sg:address":"1421 Doctor Beatrous Rd",
    "sg:city":"Theriot",
    "sg:classifiers":[
        {
            "category":"Personal",
            "subcategory":"Beauty Salon",
            "type":"Services"
        }
    ],
    "sg:phone":"+1 985 873 8917",
    "sg:postcode":"70397",
    "sg:province":"LA",
    "sg:tags":[
        "shop"
    ],
    "wof:name":"Patrice Hair Salon",
    "wof:placetype":"venue"
},
  "geometry": {"coordinates":[-90.750529,29.451516],"type":"Point"}
}