{
  "type": "Feature",
  "properties": {
    "iso:country":"US",
    "sg:address":"36365 State Rte 38",
    "sg:city":"Mt Hermon",
    "sg:classifiers":[
        {
            "category":"Government",
            "subcategory":"Fire Station",
            "type":"Public Place"
        }
    ],
    "sg:phone":"+1 985 877 5029",
    "sg:postcode":"70450",
    "sg:province":"LA",
    "sg:tags":[
        "department"
    ],
    "wof:name":"Volunteer Fire Dept",
    "wof:placetype":"venue"
},
  "geometry": {"coordinates":[-90.29307300000001,30.950898],"type":"Point"}
}