{
  "type": "Feature",
  "properties": {
    "iso:country":"US",
    "sg:address":"30038 Industrial Park Dr",
    "sg:city":"Walker",
    "sg:classifiers":[
        {
            "category":"Professional",
            "subcategory":"Research",
            "type":"Services"
        }
    ],
    "sg:phone":"+1 225 664 1383",
    "sg:postcode":"70785",
    "sg:province":"LA",
    "sg:tags":[
        "environmental",
        "ecological"
    ],
    "sg:website":"www.laticoenvironmental.com",
    "wof:name":"Latico Intl Inc",
    "wof:placetype":"venue"
},
  "geometry": {"coordinates":[-90.828047,30.504026],"type":"Point"}
}