{
  "type": "Feature",
  "properties": {
    "addr:full":"4118 Curtis Ln Shreveport LA 71109",
    "addr:housenumber":"4118",
    "addr:postcode":"71109",
    "addr:street":"Curtis Ln",
    "iso:country":"US",
    "sg:address":"4118 Curtis Ln",
    "sg:city":"Shreveport",
    "sg:classifiers":[
        {
            "category":"Autos & Motor Vehicles",
            "subcategory":"Auto Supplies",
            "type":"Retail Goods"
        }
    ],
    "sg:phone":"+1 318 632 9111",
    "sg:postcode":"71109",
    "sg:province":"LA",
    "sg:tags":[
        "battery"
    ],
    "wof:name":"Louisiana Industrial Batteries",
    "wof:placetype":"venue"
},
  "geometry": {"coordinates":[-93.81430400000001,32.470013],"type":"Point"}
}