{
  "type": "Feature",
  "properties": {
    "iso:country":"US",
    "sg:address":"101 Sicily St",
    "sg:city":"Sicily Island",
    "sg:classifiers":[
        {
            "category":"Organizations",
            "subcategory":"Non-profit Organization",
            "type":"Services"
        }
    ],
    "sg:phone":"+1 318 389 4465",
    "sg:postcode":"71340",
    "sg:province":"LA",
    "wof:name":"Catahoula Council On Aging",
    "wof:placetype":"venue"
},
  "geometry": {"coordinates":[-91.819878,31.771948],"type":"Point"}
}