{
  "type": "Feature",
  "properties": {
    "addr:full":"303 Cedar Grove Rd Houma LA 70363",
    "addr:housenumber":"303",
    "addr:postcode":"70363",
    "addr:street":"Cedar Grove Rd",
    "iso:country":"US",
    "sg:address":"303 Cedar Grove Rd",
    "sg:city":"Houma",
    "sg:classifiers":[
        {
            "category":"Professional",
            "type":"Services"
        }
    ],
    "sg:phone":"+1 985 868 0204",
    "sg:postcode":"70363",
    "sg:province":"LA",
    "wof:name":"Lirette Airboat Service",
    "wof:placetype":"venue"
},
  "geometry": {"coordinates":[-90.686818,29.498887],"type":"Point"}
}