{
  "type": "Feature",
  "properties": {
    "iso:country":"US",
    "sg:address":"2901 Municipal Pier Rd",
    "sg:city":"Shreveport",
    "sg:classifiers":[
        {
            "category":"Manufacturing",
            "subcategory":"Printing",
            "type":"Manufacturing & Wholesale Goods"
        }
    ],
    "sg:phone":"+1 318 226 0741",
    "sg:postcode":"71119",
    "sg:province":"LA",
    "sg:tags":[
        "periodical"
    ],
    "sg:website":"www.citylightsmag.com",
    "wof:name":"City Lights Magazine",
    "wof:placetype":"venue"
},
  "geometry": {"coordinates":[-93.84551999999999,32.492404],"type":"Point"}
}