{
  "type": "Feature",
  "properties": {
    "addr:full":"1705 Old Minden Rd Bossier City LA 71111",
    "addr:housenumber":"1705",
    "addr:postcode":"71111",
    "addr:street":"Old Minden Rd",
    "iso:country":"US",
    "sg:address":"1705 Old Minden Rd",
    "sg:city":"Bossier City",
    "sg:classifiers":[
        {
            "category":"Restaurant",
            "type":"Food & Drink"
        }
    ],
    "sg:menulink":"http://www.allmenus.com/la/bossier-city/197539-burger-king/menu/",
    "sg:phone":"+1 318 746 6641",
    "sg:postcode":"71111",
    "sg:province":"LA",
    "sg:tags":[
        "burger",
        "american"
    ],
    "wof:name":"Burger King",
    "wof:placetype":"venue"
},
  "geometry": {"coordinates":[-93.716313,32.516124],"type":"Point"}
}