{
  "type": "Feature",
  "properties": {
    "iso:country":"US",
    "sg:address":"1917 Olive St",
    "sg:city":"Monroe",
    "sg:classifiers":[
        {
            "category":"Building & Trades",
            "subcategory":"Cleaning & Sanitation",
            "type":"Services"
        }
    ],
    "sg:phone":"+1 318 322 7585",
    "sg:postcode":"71201",
    "sg:province":"LA",
    "sg:tags":[
        "janitor"
    ],
    "wof:name":"Burgoyne Janitor Svc",
    "wof:placetype":"venue"
},
  "geometry": {"coordinates":[-92.103572,32.516053],"type":"Point"}
}