{
  "type": "Feature",
  "properties": {
    "iso:country":"US",
    "sg:address":"984 Topaz St",
    "sg:city":"New Orleans",
    "sg:classifiers":[
        {
            "category":"Shopping",
            "subcategory":"Bicycles & Sporting Goods",
            "type":"Retail Goods"
        }
    ],
    "sg:phone":"+1 504 288 8228",
    "sg:postcode":"70124",
    "sg:province":"LA",
    "wof:name":"Bike New Orleans",
    "wof:placetype":"venue"
},
  "geometry": {"coordinates":[-90.100447,30.025356],"type":"Point"}
}