{
  "type": "Feature",
  "properties": {
    "iso:country":"US",
    "sg:address":"5630 Crowder Blvd",
    "sg:city":"New Orleans",
    "sg:classifiers":[
        {
            "category":"Building & Trades",
            "subcategory":"Cleaning & Sanitation",
            "type":"Services"
        }
    ],
    "sg:phone":"+1 504 304 3267",
    "sg:postcode":"70127",
    "sg:province":"LA",
    "sg:tags":[
        "janitor"
    ],
    "wof:name":"Benagee Services",
    "wof:placetype":"venue"
},
  "geometry": {"coordinates":[-89.99247200000001,30.027494],"type":"Point"}
}