{
  "type": "Feature",
  "properties": {
    "iso:country":"US",
    "sg:address":"3200 Magazine St",
    "sg:city":"New Orleans",
    "sg:classifiers":[
        {
            "category":"Banks & Credit Unions",
            "subcategory":"Bank",
            "type":"Services"
        }
    ],
    "sg:phone":"+1 504 240 5147",
    "sg:postcode":"70115",
    "sg:province":"LA",
    "wof:name":"Liberty Bank & Trust Co",
    "wof:placetype":"venue"
},
  "geometry": {"coordinates":[-90.087238,29.923629],"type":"Point"}
}