{
  "type": "Feature",
  "properties": {
    "addr:full":"2609 N River Rd Port Allen LA 70767",
    "addr:housenumber":"2609",
    "addr:postcode":"70767",
    "addr:street":"N River Rd",
    "iso:country":"US",
    "sg:address":"2609 N River Rd",
    "sg:city":"Port Allen",
    "sg:classifiers":[
        {
            "category":"Professional",
            "subcategory":"Research",
            "type":"Services"
        }
    ],
    "sg:phone":"+1 225 381 2991",
    "sg:postcode":"70767",
    "sg:province":"LA",
    "sg:tags":[
        "environmental",
        "ecological"
    ],
    "sg:website":"www.amrad.com",
    "wof:name":"American Radiation Svc Inc",
    "wof:placetype":"venue"
},
  "geometry": {"coordinates":[-91.20252000000001,30.488053],"type":"Point"}
}