{
  "type": "Feature",
  "properties": {
    "addr:full":"1102 2nd Ave Lake Charles LA 70601",
    "addr:housenumber":"1102",
    "addr:postcode":"70601",
    "addr:street":"2Nd Ave",
    "iso:country":"US",
    "sg:address":"1102 2nd Ave",
    "sg:city":"Lake Charles",
    "sg:classifiers":[
        {
            "category":"Recreation",
            "type":"Entertainment"
        }
    ],
    "sg:phone":"+1 337 491 1269",
    "sg:postcode":"70601",
    "sg:province":"LA",
    "sg:tags":[
        "pool",
        "swimming"
    ],
    "wof:name":"Second Avenue Swimming Pool",
    "wof:placetype":"venue"
},
  "geometry": {"coordinates":[-93.198807,30.222711],"type":"Point"}
}