{
  "type": "Feature",
  "properties": {
    "addr:full":"21160 Plank Rd Zachary LA 70791",
    "addr:housenumber":"21160",
    "addr:postcode":"70791",
    "addr:street":"Plank Rd",
    "iso:country":"US",
    "sg:address":"21160 Plank Rd",
    "sg:city":"Zachary",
    "sg:classifiers":[
        {
            "category":"Wholesale",
            "subcategory":"Farm Supplies",
            "type":"Manufacturing & Wholesale Goods"
        }
    ],
    "sg:phone":"+1 225 654 6653",
    "sg:postcode":"70791",
    "sg:province":"LA",
    "sg:tags":[
        "feed"
    ],
    "wof:name":"Bowman's Ole Blue Mill",
    "wof:placetype":"venue"
},
  "geometry": {"coordinates":[-91.100201,30.665044],"type":"Point"}
}