{
  "type": "Feature",
  "properties": {
    "iso:country":"US",
    "sg:address":"130 Stoner Ave",
    "sg:city":"Shreveport",
    "sg:classifiers":[
        {
            "category":"Government",
            "subcategory":"Office",
            "type":"Public Place"
        }
    ],
    "sg:phone":"+1 318 673 7712",
    "sg:postcode":"71101",
    "sg:province":"LA",
    "sg:tags":[
        "village"
    ],
    "wof:name":"Greenwood Cemetery",
    "wof:placetype":"venue"
},
  "geometry": {"coordinates":[-93.731589,32.50005],"type":"Point"}
}