{
  "type": "Feature",
  "properties": {
    "addr:full":"154 Jesse James Rd Atlanta LA 71404",
    "addr:housenumber":"154",
    "addr:postcode":"71404",
    "addr:street":"Jesse James Rd",
    "iso:country":"US",
    "sg:address":"154 Jesse James Rd",
    "sg:city":"Atlanta",
    "sg:classifiers":[
        {
            "category":"Organizations",
            "subcategory":"Religious Organization",
            "type":"Services"
        }
    ],
    "sg:phone":"+1 318 646 2790",
    "sg:postcode":"71404",
    "sg:province":"LA",
    "wof:name":"Iatt Baptist Church",
    "wof:placetype":"venue"
},
  "geometry": {"coordinates":[-92.761565,31.712806],"type":"Point"}
}