{
  "type": "Feature",
  "properties": {
    "iso:country":"US",
    "sg:address":"309 Highway Ave",
    "sg:city":"Franklin",
    "sg:classifiers":[
        {
            "category":"Food & Beverages",
            "subcategory":"Groceries & Convenience Stores",
            "type":"Retail Goods"
        }
    ],
    "sg:phone":"+1 337 828 1908",
    "sg:postcode":"70538",
    "sg:province":"LA",
    "sg:tags":[
        "grocer"
    ],
    "wof:name":"Friends",
    "wof:placetype":"venue"
},
  "geometry": {"coordinates":[-91.505781,29.805443],"type":"Point"}
}