{
  "type": "Feature",
  "properties": {
    "iso:country":"US",
    "sg:address":"805 Court St",
    "sg:city":"Port Allen",
    "sg:classifiers":[
        {
            "category":"Retail",
            "subcategory":"Auto Repair",
            "type":"Services"
        }
    ],
    "sg:phone":"+1 225 344 5384",
    "sg:postcode":"70767",
    "sg:province":"LA",
    "sg:tags":[
        "repairing",
        "automobile"
    ],
    "wof:name":"G & G Auto",
    "wof:placetype":"venue"
},
  "geometry": {"coordinates":[-91.21003,30.452218],"type":"Point"}
}