{
  "type": "Feature",
  "properties": {
    "iso:country":"US",
    "sg:address":"210 Bayside Dr",
    "sg:city":"West Monroe",
    "sg:classifiers":[
        {
            "category":"Shopping",
            "subcategory":"Gifts & Souvenirs",
            "type":"Retail Goods"
        }
    ],
    "sg:phone":"+1 318 340 6200",
    "sg:postcode":"71291",
    "sg:province":"LA",
    "sg:tags":[
        "shop"
    ],
    "wof:name":"Harmony Gifts",
    "wof:placetype":"venue"
},
  "geometry": {"coordinates":[-92.19510699999999,32.555394],"type":"Point"}
}