{
  "type": "Feature",
  "properties": {
    "addr:full":"4525 Westbank Expy Marrero LA 70072",
    "addr:housenumber":"4525",
    "addr:postcode":"70072",
    "addr:street":"Westbank Expy Marrero",
    "iso:country":"US",
    "sg:address":"4525 Westbank Expy",
    "sg:city":"Marrero",
    "sg:classifiers":[
        {
            "category":"Building & Trades",
            "subcategory":"Construction",
            "type":"Services"
        }
    ],
    "sg:phone":"+1 504 341 3777",
    "sg:postcode":"70072",
    "sg:province":"LA",
    "sg:tags":[
        "general",
        "contractor"
    ],
    "wof:name":"Metro Construction",
    "wof:placetype":"venue"
},
  "geometry": {"coordinates":[-90.09588599999999,29.894724],"type":"Point"}
}