{
  "type": "Feature",
  "properties": {
    "iso:country":"US",
    "sg:address":"1050 Peters Rd",
    "sg:city":"Harvey",
    "sg:classifiers":[
        {
            "category":"Wholesale",
            "subcategory":"Machinery & Supplies",
            "type":"Manufacturing & Wholesale Goods"
        }
    ],
    "sg:phone":"+1 504 361 9002",
    "sg:postcode":"70058",
    "sg:province":"LA",
    "sg:tags":[
        "field",
        "oil"
    ],
    "wof:name":"Sooner Pipe",
    "wof:placetype":"venue"
},
  "geometry": {"coordinates":[-90.077522,29.897155],"type":"Point"}
}