{
  "type": "Feature",
  "properties": {
    "addr:full":"420 Bourbon St New Orleans LA 70130",
    "addr:housenumber":"420",
    "addr:postcode":"70130",
    "addr:street":"Bourbon St",
    "iso:country":"US",
    "sg:address":"420 Bourbon St",
    "sg:city":"New Orleans",
    "sg:classifiers":[
        {
            "category":"Shopping",
            "subcategory":"Gifts & Souvenirs",
            "type":"Retail Goods"
        }
    ],
    "sg:phone":"+1 504 523 4300",
    "sg:postcode":"70130",
    "sg:province":"LA",
    "wof:name":"Crawdaddy & Co",
    "wof:placetype":"venue"
},
  "geometry": {"coordinates":[-90.06771999999999,29.956255],"type":"Point"}
}