{
  "type": "Feature",
  "properties": {
    "iso:country":"US",
    "sg:address":"3924 Greenwood Rd",
    "sg:city":"Shreveport",
    "sg:classifiers":[
        {
            "category":"Organizations",
            "subcategory":"Labor Organization",
            "type":"Services"
        }
    ],
    "sg:phone":"+1 318 631 0581",
    "sg:postcode":"71109",
    "sg:province":"LA",
    "wof:name":"Paper Allied-Ind Chemical WRKR",
    "wof:placetype":"venue"
},
  "geometry": {"coordinates":[-93.809258,32.471204],"type":"Point"}
}