{
  "type": "Feature",
  "properties": {
    "addr:full":"1204 Cleveland St Thibodaux LA 70301",
    "addr:housenumber":"1204",
    "addr:postcode":"70301",
    "addr:street":"Cleveland St",
    "iso:country":"US",
    "sg:address":"1204 Cleveland St",
    "sg:city":"Thibodaux",
    "sg:classifiers":[
        {
            "category":"Professional",
            "subcategory":"Business Services",
            "type":"Services"
        }
    ],
    "sg:phone":"+1 985 447 2513",
    "sg:postcode":"70301",
    "sg:province":"LA",
    "sg:tags":[
        "legal"
    ],
    "wof:name":"Southall Bonding Service",
    "wof:placetype":"venue"
},
  "geometry": {"coordinates":[-90.817106,29.785929],"type":"Point"}
}