{
  "type": "Feature",
  "properties": {
    "addr:full":"1030 Old Metairie Pl Metairie LA 70001",
    "addr:housenumber":"1030",
    "addr:postcode":"70001",
    "addr:street":"Old Metairie Pl",
    "iso:country":"US",
    "sg:address":"1030 Old Metairie Pl",
    "sg:city":"Metairie",
    "sg:classifiers":[
        {
            "category":"Wholesale",
            "subcategory":"Medical Equipment & Supplies",
            "type":"Manufacturing & Wholesale Goods"
        }
    ],
    "sg:phone":"+1 504 834 1344",
    "sg:postcode":"70001",
    "sg:province":"LA",
    "wof:name":"Medical Inovations Inc",
    "wof:placetype":"venue"
},
  "geometry": {"coordinates":[-90.14441100000001,29.975712],"type":"Point"}
}