{
  "type": "Feature",
  "properties": {
    "iso:country":"US",
    "sg:address":"3030 General Degaulle Dr",
    "sg:city":"New Orleans",
    "sg:classifiers":[
        {
            "category":"Building & Trades",
            "subcategory":"Landscaping Services",
            "type":"Services"
        }
    ],
    "sg:phone":"+1 504 392 0717",
    "sg:postcode":"70114",
    "sg:province":"LA",
    "sg:tags":[
        "landscape",
        "contractor"
    ],
    "sg:website":"www.gardensmith.com",
    "wof:name":"Garden Smith Inc",
    "wof:placetype":"venue"
},
  "geometry": {"coordinates":[-90.027953,29.927456],"type":"Point"}
}