{
  "type": "Feature",
  "properties": {
    "iso:country":"US",
    "sg:address":"1326 6th St",
    "sg:city":"Mamou",
    "sg:classifiers":[
        {
            "category":"Restaurant",
            "type":"Food & Drink"
        }
    ],
    "sg:phone":"+1 337 468 2856",
    "sg:postcode":"70554",
    "sg:province":"LA",
    "sg:tags":[
        "eating"
    ],
    "wof:name":"Pizza Inn",
    "wof:placetype":"venue"
},
  "geometry": {"coordinates":[-92.41957499999999,30.640743],"type":"Point"}
}