{
  "type": "Feature",
  "properties": {
    "addr:full":"2700 Paris Rd Chalmette LA 70043",
    "addr:housenumber":"2700",
    "addr:postcode":"70043",
    "addr:street":"Paris Rd",
    "iso:country":"US",
    "sg:address":"2700 Paris Rd",
    "sg:city":"Chalmette",
    "sg:classifiers":[
        {
            "category":"Health Services",
            "subcategory":"Doctor",
            "type":"Services"
        }
    ],
    "sg:phone":"+1 504 271 0667",
    "sg:postcode":"70043",
    "sg:province":"LA",
    "sg:tags":[
        "physician",
        "surgeon"
    ],
    "wof:name":"St Bernard Clinic Svc",
    "wof:placetype":"venue"
},
  "geometry": {"coordinates":[-89.962712,29.944391],"type":"Point"}
}