{
  "type": "Feature",
  "properties": {
    "iso:country":"US",
    "sg:address":"1957 Stuart Ave",
    "sg:city":"Baton Rouge",
    "sg:classifiers":[
        {
            "category":"Social Services",
            "subcategory":"Child Care",
            "type":"Services"
        }
    ],
    "sg:phone":"+1 225 343 1338",
    "sg:postcode":"70808",
    "sg:province":"LA",
    "wof:name":"St Aloysius Child Care Ctr",
    "wof:placetype":"venue"
},
  "geometry": {"coordinates":[-91.149191,30.414269],"type":"Point"}
}