{
  "type": "Feature",
  "properties": {
    "addr:full":"104 P St Belle Chasse LA 70037",
    "addr:housenumber":"104",
    "addr:postcode":"70037",
    "addr:street":"P St",
    "iso:country":"US",
    "sg:address":"104 P St",
    "sg:city":"Belle Chasse",
    "sg:classifiers":[
        {
            "category":"Home & Garden",
            "subcategory":"Building Materials",
            "type":"Retail Goods"
        }
    ],
    "sg:phone":"+1 504 394 4132",
    "sg:postcode":"70037",
    "sg:province":"LA",
    "sg:tags":[
        "equipment",
        "fixture",
        "lighting"
    ],
    "wof:name":"X-Pert Electric Supply",
    "wof:placetype":"venue"
},
  "geometry": {"coordinates":[-90.005798,29.8689],"type":"Point"}
}