{
  "type": "Feature",
  "properties": {
    "addr:full":"6602 Main St Winnsboro LA 71295",
    "addr:housenumber":"6602",
    "addr:postcode":"71295",
    "addr:street":"Main St",
    "iso:country":"US",
    "sg:address":"6602 Main St",
    "sg:city":"Winnsboro",
    "sg:classifiers":[
        {
            "category":"Banks & Credit Unions",
            "subcategory":"Investment Brokerage",
            "type":"Services"
        }
    ],
    "sg:phone":"+1 318 435 8244",
    "sg:postcode":"71295",
    "sg:province":"LA",
    "sg:tags":[
        "stock",
        "bond"
    ],
    "wof:name":"Edward Jones Co",
    "wof:placetype":"venue"
},
  "geometry": {"coordinates":[-91.71601699999999,32.16553],"type":"Point"}
}