{
  "type": "Feature",
  "properties": {
    "iso:country":"US",
    "sg:address":"619 Brothers Rd",
    "sg:city":"Lafayette",
    "sg:classifiers":[
        {
            "category":"Retail",
            "subcategory":"Animal Services",
            "type":"Services"
        }
    ],
    "sg:phone":"+1 337 237 2271",
    "sg:postcode":"70507",
    "sg:province":"LA",
    "wof:name":"Oak Alley Stallion Station",
    "wof:placetype":"venue"
},
  "geometry": {"coordinates":[-92.05754399999999,30.270555],"type":"Point"}
}