{
  "type": "Feature",
  "properties": {
    "addr:full":"111 E Mississippi Ave Ruston LA 71270",
    "addr:housenumber":"111",
    "addr:postcode":"71270",
    "addr:street":"E Mississippi Ave",
    "iso:country":"US",
    "sg:address":"111 E Mississippi Ave",
    "sg:city":"Ruston",
    "sg:classifiers":[
        {
            "category":"Manufacturing",
            "subcategory":"Printing",
            "type":"Manufacturing & Wholesale Goods"
        }
    ],
    "sg:phone":"+1 318 255 3747",
    "sg:postcode":"71270",
    "sg:province":"LA",
    "sg:tags":[
        "newspaper"
    ],
    "wof:name":"Morning Paper",
    "wof:placetype":"venue"
},
  "geometry": {"coordinates":[-92.637024,32.529741],"type":"Point"}
}