{
  "type": "Feature",
  "properties": {
    "iso:country":"US",
    "sg:address":"4902 Canal St",
    "sg:city":"New Orleans",
    "sg:classifiers":[
        {
            "category":"Professional",
            "subcategory":"Lawyer & Legal Services",
            "type":"Services"
        }
    ],
    "sg:phone":"+1 504 484 6855",
    "sg:postcode":"70119",
    "sg:province":"LA",
    "sg:tags":[
        "attorney"
    ],
    "wof:name":"Riguer J Silva Law Corp",
    "wof:placetype":"venue"
},
  "geometry": {"coordinates":[-90.109863,29.980632],"type":"Point"}
}