{
  "type": "Feature",
  "properties": {
    "iso:country":"US",
    "sg:address":"119 Fairview Dr",
    "sg:city":"Madisonville",
    "sg:classifiers":[
        {
            "category":"Recreation",
            "type":"Entertainment"
        }
    ],
    "sg:phone":"+1 985 845 3318",
    "sg:postcode":"70447",
    "sg:province":"LA",
    "sg:tags":[
        "parks"
    ],
    "wof:name":"Fairview-Riverside Park",
    "wof:placetype":"venue"
},
  "geometry": {"coordinates":[-90.134721,30.409674],"type":"Point"}
}