{
  "type": "Feature",
  "properties": {
    "iso:country":"US",
    "sg:address":"982 Government St",
    "sg:city":"Baton Rouge",
    "sg:classifiers":[
        {
            "category":"Professional",
            "subcategory":"Advertising",
            "type":"Services"
        }
    ],
    "sg:phone":"+1 225 381 7266",
    "sg:postcode":"70802",
    "sg:province":"LA",
    "sg:tags":[
        "counselor"
    ],
    "wof:name":"Stun Design & Advertising",
    "wof:placetype":"venue"
},
  "geometry": {"coordinates":[-91.179875,30.443505],"type":"Point"}
}