{
  "type": "Feature",
  "properties": {
    "addr:full":"789 Grand Caillou Rd Houma LA 70363",
    "addr:housenumber":"789",
    "addr:postcode":"70363",
    "addr:street":"Grand Caillou Rd",
    "iso:country":"US",
    "sg:address":"789 Grand Caillou Rd",
    "sg:city":"Houma",
    "sg:classifiers":[
        {
            "category":"Insurance",
            "subcategory":"Insurance Agent",
            "type":"Services"
        }
    ],
    "sg:phone":"+1 985 876 4410",
    "sg:postcode":"70363",
    "sg:province":"LA",
    "wof:name":"Dalton A Le Blanc Insurance",
    "wof:placetype":"venue"
},
  "geometry": {"coordinates":[-90.69773600000001,29.584742],"type":"Point"}
}