{
  "type": "Feature",
  "properties": {
    "iso:country":"US",
    "sg:address":"10001 Lake Forest Blvd",
    "sg:city":"New Orleans",
    "sg:classifiers":[
        {
            "category":"Professional",
            "subcategory":"Management & Consulting",
            "type":"Services"
        }
    ],
    "sg:phone":"+1 504 243 3033",
    "sg:postcode":"70127",
    "sg:province":"LA",
    "sg:tags":[
        "business"
    ],
    "wof:name":"Fore Wall Success Pubg Co",
    "wof:placetype":"venue"
},
  "geometry": {"coordinates":[-89.975769,30.031112],"type":"Point"}
}