{
  "type": "Feature",
  "properties": {
    "addr:full":"6892 Preston Rd Keithville LA 71047",
    "addr:housenumber":"6892",
    "addr:postcode":"71047",
    "addr:street":"Preston Rd",
    "iso:country":"US",
    "sg:address":"6892 Preston Rd",
    "sg:city":"Keithville",
    "sg:classifiers":[
        {
            "category":"Retail",
            "subcategory":"Repair Shop",
            "type":"Services"
        }
    ],
    "sg:phone":"+1 318 933 5723",
    "sg:postcode":"71047",
    "sg:province":"LA",
    "wof:name":"Datex Ohmeda",
    "wof:placetype":"venue"
},
  "geometry": {"coordinates":[-93.896807,32.252178],"type":"Point"}
}