{
  "type": "Feature",
  "properties": {
    "addr:full":"629 E Admiral Doyle Dr New Iberia LA 70560",
    "addr:housenumber":"629",
    "addr:postcode":"70560",
    "addr:street":"E Admiral Doyle Dr",
    "iso:country":"US",
    "sg:address":"629 E Admiral Doyle Dr",
    "sg:city":"New Iberia",
    "sg:classifiers":[
        {
            "category":"Restaurant",
            "type":"Food & Drink"
        }
    ],
    "sg:phone":"+1 337 365 8069",
    "sg:postcode":"70560",
    "sg:province":"LA",
    "wof:name":"KFC",
    "wof:placetype":"venue"
},
  "geometry": {"coordinates":[-91.82421600000001,29.987226],"type":"Point"}
}