{
  "type": "Feature",
  "properties": {
    "iso:country":"US",
    "sg:address":"306 E Oak St",
    "sg:city":"Amite",
    "sg:classifiers":[
        {
            "category":"Organizations",
            "subcategory":"Non-profit Organization",
            "type":"Services"
        }
    ],
    "sg:phone":"+1 985 747 6766",
    "sg:postcode":"70422",
    "sg:province":"LA",
    "sg:tags":[
        "info",
        "addiction",
        "abuse",
        "treatment",
        "drug"
    ],
    "wof:name":"Juvenile Drug Court",
    "wof:placetype":"venue"
},
  "geometry": {"coordinates":[-90.505216,30.726626],"type":"Point"}
}