{
  "type": "Feature",
  "properties": {
    "iso:country":"US",
    "sg:address":"1110 W 70th St",
    "sg:city":"Shreveport",
    "sg:classifiers":[
        {
            "category":"Home & Garden",
            "subcategory":"Furniture",
            "type":"Retail Goods"
        }
    ],
    "sg:phone":"+1 318 865 8794",
    "sg:postcode":"71106",
    "sg:province":"LA",
    "wof:name":"Ivan Smith Furniture Outlet",
    "wof:placetype":"venue"
},
  "geometry": {"coordinates":[-93.777372,32.441974],"type":"Point"}
}