{
  "type": "Feature",
  "properties": {
    "iso:country":"US",
    "sg:address":"401 Whitney Ave",
    "sg:city":"Gretna",
    "sg:classifiers":[
        {
            "category":"Real Estate",
            "subcategory":"Real Estate Services",
            "type":"Services"
        }
    ],
    "sg:phone":"+1 504 362 7774",
    "sg:postcode":"70056",
    "sg:province":"LA",
    "sg:tags":[
        "company",
        "title"
    ],
    "wof:name":"Winters Title Agency Inc",
    "wof:placetype":"venue"
},
  "geometry": {"coordinates":[-90.042304,29.919904],"type":"Point"}
}