{
  "type": "Feature",
  "properties": {
    "iso:country":"US",
    "sg:address":"6649 Sullivan Rd",
    "sg:city":"Greenwell Spgs",
    "sg:classifiers":[
        {
            "category":"Personal",
            "subcategory":"Beauty Salon",
            "type":"Services"
        }
    ],
    "sg:phone":"+1 225 261 3131",
    "sg:postcode":"70739",
    "sg:province":"LA",
    "wof:name":"Fantastic Sam's",
    "wof:placetype":"venue"
},
  "geometry": {"coordinates":[-91.029849,30.51407],"type":"Point"}
}