{
  "type": "Feature",
  "properties": {
    "iso:country":"US",
    "sg:address":"3025 Lamas Rd",
    "sg:city":"Erath",
    "sg:classifiers":[
        {
            "category":"Building & Trades",
            "subcategory":"Construction",
            "type":"Services"
        }
    ],
    "sg:phone":"+1 337 937 5410",
    "sg:postcode":"70533",
    "sg:province":"LA",
    "sg:tags":[
        "house"
    ],
    "wof:name":"Cajun Covers",
    "wof:placetype":"venue"
},
  "geometry": {"coordinates":[-92.022802,29.943403],"type":"Point"}
}