{
  "type": "Feature",
  "properties": {
    "addr:full":"6011 Fairfield Ave Shreveport LA 71106",
    "addr:housenumber":"6011",
    "addr:postcode":"71106",
    "addr:street":"Fairfield Ave",
    "iso:country":"US",
    "sg:address":"6011 Fairfield Ave",
    "sg:city":"Shreveport",
    "sg:classifiers":[
        {
            "category":"Organizations",
            "subcategory":"Religious Organization",
            "type":"Services"
        }
    ],
    "sg:phone":"+1 318 865 0468",
    "sg:postcode":"71106",
    "sg:province":"LA",
    "wof:name":"Gospel Light Baptist Church",
    "wof:placetype":"venue"
},
  "geometry": {"coordinates":[-93.750184,32.451121],"type":"Point"}
}