{
  "type": "Feature",
  "properties": {
    "addr:full":"8417 Kelwood Ave Baton Rouge LA 70806",
    "addr:housenumber":"8417",
    "addr:postcode":"70806",
    "addr:street":"Kelwood Ave",
    "iso:country":"US",
    "sg:address":"8417 Kelwood Ave",
    "sg:city":"Baton Rouge",
    "sg:classifiers":[
        {
            "category":"Professional",
            "subcategory":"Engineering",
            "type":"Services"
        }
    ],
    "sg:phone":"+1 225 926 5600",
    "sg:postcode":"70806",
    "sg:province":"LA",
    "sg:tags":[
        "engineer"
    ],
    "wof:name":"Assaf Semioneaux Tauzin",
    "wof:placetype":"venue"
},
  "geometry": {"coordinates":[-91.09610000000001,30.446618],"type":"Point"}
}