{
  "type": "Feature",
  "properties": {
    "addr:full":"1001 Victory Dr Westwego LA 70094",
    "addr:housenumber":"1001",
    "addr:postcode":"70094",
    "addr:street":"Victory Dr Westwego",
    "iso:country":"US",
    "sg:address":"1001 Victory Dr",
    "sg:city":"Westwego",
    "sg:classifiers":[
        {
            "category":"Organizations",
            "subcategory":"Religious Organization",
            "type":"Services"
        }
    ],
    "sg:phone":"+1 504 347 6209",
    "sg:postcode":"70094",
    "sg:province":"LA",
    "wof:name":"Jehovahs Wtnesses Kingdom Hall",
    "wof:placetype":"venue"
},
  "geometry": {"coordinates":[-90.135604,29.891559],"type":"Point"}
}