{
  "type": "Feature",
  "properties": {
    "iso:country":"US",
    "sg:address":"15958 Old Hammond Hwy",
    "sg:city":"Baton Rouge",
    "sg:classifiers":[
        {
            "category":"Food & Beverages",
            "subcategory":"Groceries & Convenience Stores",
            "type":"Retail Goods"
        }
    ],
    "sg:phone":"+1 225 275 7731",
    "sg:postcode":"70816",
    "sg:province":"LA",
    "wof:name":"Circle K",
    "wof:placetype":"venue"
},
  "geometry": {"coordinates":[-91.009573,30.459406],"type":"Point"}
}