{
  "type": "Feature",
  "properties": {
    "addr:full":"2621 Ruth St Sulphur LA 70665",
    "addr:housenumber":"2621",
    "addr:postcode":"70665",
    "addr:street":"Ruth St",
    "iso:country":"US",
    "sg:address":"2621 Ruth St",
    "sg:city":"Sulphur",
    "sg:classifiers":[
        {
            "category":"Restaurant",
            "type":"Food & Drink"
        }
    ],
    "sg:menulink":"http://www.allmenus.com/la/sulphur/136412-waffle-house/menu/",
    "sg:phone":"+1 337 527 6641",
    "sg:postcode":"70665",
    "sg:province":"LA",
    "sg:tags":[
        "american"
    ],
    "wof:name":"Waffle House",
    "wof:placetype":"venue"
},
  "geometry": {"coordinates":[-93.37629,30.212884],"type":"Point"}
}