{
  "type": "Feature",
  "properties": {
    "addr:full":"614 Georgia Ave Bogalusa LA 70427",
    "addr:housenumber":"614",
    "addr:postcode":"70427",
    "addr:street":"Georgia Ave",
    "iso:country":"US",
    "sg:address":"614 Georgia Ave",
    "sg:city":"Bogalusa",
    "sg:classifiers":[
        {
            "category":"Building & Trades",
            "subcategory":"Construction",
            "type":"Services"
        }
    ],
    "sg:phone":"+1 985 516 9264",
    "sg:postcode":"70427",
    "sg:province":"LA",
    "sg:tags":[
        "house"
    ],
    "wof:name":"Foreman Building LLC",
    "wof:placetype":"venue"
},
  "geometry": {"coordinates":[-89.855363,30.786467],"type":"Point"}
}