{
  "type": "Feature",
  "properties": {
    "iso:country":"US",
    "sg:address":"4819 Downman Rd",
    "sg:city":"New Orleans",
    "sg:classifiers":[
        {
            "category":"Home & Garden",
            "subcategory":"Building Materials",
            "type":"Retail Goods"
        }
    ],
    "sg:phone":"+1 504 246 4111",
    "sg:postcode":"70126",
    "sg:province":"LA",
    "sg:tags":[
        "glass",
        "window",
        "plate"
    ],
    "wof:name":"Ray Authement Glass Co",
    "wof:placetype":"venue"
},
  "geometry": {"coordinates":[-90.021565,30.017933],"type":"Point"}
}