{
  "type": "Feature",
  "properties": {
    "iso:country":"US",
    "sg:address":"200 Douglas Ln",
    "sg:city":"Marrero",
    "sg:classifiers":[
        {
            "category":"Wholesale",
            "subcategory":"Petroleum",
            "type":"Manufacturing & Wholesale Goods"
        }
    ],
    "sg:phone":"+1 504 371 3900",
    "sg:postcode":"70072",
    "sg:province":"LA",
    "sg:tags":[
        "pipe",
        "line",
        "company"
    ],
    "wof:name":"Magellan Midstream Partners LP",
    "wof:placetype":"venue"
},
  "geometry": {"coordinates":[-90.105407,29.90251],"type":"Point"}
}