{
  "type": "Feature",
  "properties": {
    "iso:country":"US",
    "sg:address":"1404 Murray St",
    "sg:city":"Alexandria",
    "sg:classifiers":[
        {
            "category":"Social Services",
            "type":"Services"
        }
    ],
    "sg:phone":"+1 318 445 2022",
    "sg:postcode":"71309",
    "sg:province":"LA",
    "sg:tags":[
        "victim",
        "crime"
    ],
    "wof:name":"Rape Crisis Program",
    "wof:placetype":"venue"
},
  "geometry": {"coordinates":[-92.45260500000001,31.304417],"type":"Point"}
}