{
  "type": "Feature",
  "properties": {
    "iso:country":"US",
    "sg:address":"2000 4th St",
    "sg:city":"Harvey",
    "sg:classifiers":[
        {
            "category":"Organizations",
            "subcategory":"Community Association",
            "type":"Services"
        }
    ],
    "sg:phone":"+1 504 367 1464",
    "sg:postcode":"70058",
    "sg:province":"LA",
    "sg:tags":[
        "fraternal"
    ],
    "wof:name":"Loyal Order Of Moose",
    "wof:placetype":"venue"
},
  "geometry": {"coordinates":[-90.07528499999999,29.909822],"type":"Point"}
}