{
  "type": "Feature",
  "properties": {
    "iso:country":"US",
    "sg:address":"33095 Bowie St Ofc",
    "sg:city":"White Castle",
    "sg:classifiers":[
        {
            "category":"Real Estate",
            "subcategory":"Real Estate Operator",
            "type":"Services"
        }
    ],
    "sg:phone":"+1 225 545 2357",
    "sg:postcode":"70788",
    "sg:province":"LA",
    "sg:tags":[
        "apartment"
    ],
    "wof:name":"White Castle Senior Citizens Apts",
    "wof:placetype":"venue"
},
  "geometry": {"coordinates":[-91.15070299999999,30.159],"type":"Point"}
}