{
  "type": "Feature",
  "properties": {
    "addr:full":"2025 Whitney Ave Gretna LA 70056",
    "addr:housenumber":"2025",
    "addr:postcode":"70056",
    "addr:street":"Whitney Ave",
    "iso:country":"US",
    "sg:address":"2025 Whitney Ave",
    "sg:city":"Gretna",
    "sg:classifiers":[
        {
            "category":"Retail",
            "subcategory":"Repair Shop",
            "type":"Services"
        }
    ],
    "sg:phone":"+1 504 366 2559",
    "sg:postcode":"70056",
    "sg:province":"LA",
    "wof:name":"Bob Garretts In Mint Cond",
    "wof:placetype":"venue"
},
  "geometry": {"coordinates":[-90.042722,29.918051],"type":"Point"}
}