{
  "type": "Feature",
  "properties": {
    "addr:full":"1003 E Illinois Ave Hammond LA 70403",
    "addr:housenumber":"1003",
    "addr:postcode":"70403",
    "addr:street":"E Illinois Ave",
    "iso:country":"US",
    "sg:address":"1003 E Illinois Ave",
    "sg:city":"Hammond",
    "sg:classifiers":[
        {
            "category":"Social Services",
            "subcategory":"Child Care",
            "type":"Services"
        }
    ],
    "sg:phone":"+1 985 429 1181",
    "sg:postcode":"70403",
    "sg:province":"LA",
    "sg:tags":[
        "day"
    ],
    "wof:name":"Child Care Provider",
    "wof:placetype":"venue"
},
  "geometry": {"coordinates":[-90.44922,30.499618],"type":"Point"}
}