{
  "type": "Feature",
  "properties": {
    "addr:full":"4225 Rollins Rd Zachary LA 70791",
    "addr:housenumber":"4225",
    "addr:postcode":"70791",
    "addr:street":"Rollins Rd",
    "iso:country":"US",
    "sg:address":"4225 Rollins Rd",
    "sg:city":"Zachary",
    "sg:classifiers":[
        {
            "category":"Organizations",
            "subcategory":"Religious Organization",
            "type":"Services"
        }
    ],
    "sg:phone":"+1 225 654 0221",
    "sg:postcode":"70791",
    "sg:province":"LA",
    "wof:name":"Union Antioch Baptist Church",
    "wof:placetype":"venue"
},
  "geometry": {"coordinates":[-91.162784,30.669058],"type":"Point"}
}