{
  "type": "Feature",
  "properties": {
    "addr:full":"1316 Corporate Square Dr Slidell LA 70458",
    "addr:housenumber":"1316",
    "addr:postcode":"70458",
    "addr:street":"Corporate Square Dr",
    "iso:country":"US",
    "sg:address":"1316 Corporate Square Dr",
    "sg:city":"Slidell",
    "sg:classifiers":[
        {
            "category":"Building & Trades",
            "subcategory":"Pest Control",
            "type":"Services"
        }
    ],
    "sg:phone":"+1 985 645 0767",
    "sg:postcode":"70458",
    "sg:province":"LA",
    "wof:name":"Pest Stop",
    "wof:placetype":"venue"
},
  "geometry": {"coordinates":[-89.756272,30.282798],"type":"Point"}
}