{
  "type": "Feature",
  "properties": {
    "iso:country":"US",
    "sg:address":"32558 Fisher Rd",
    "sg:city":"Denham Springs",
    "sg:classifiers":[
        {
            "category":"Professional",
            "subcategory":"Advertising",
            "type":"Services"
        }
    ],
    "sg:phone":"+1 225 665 0836",
    "sg:postcode":"70706",
    "sg:province":"LA",
    "wof:name":"Ad Ceaux Promotional Products",
    "wof:placetype":"venue"
},
  "geometry": {"coordinates":[-90.932676,30.541839],"type":"Point"}
}