{
  "type": "Feature",
  "properties": {
    "addr:full":"120 Odessa Rd Duson LA 70529",
    "addr:housenumber":"120",
    "addr:postcode":"70529",
    "addr:street":"Odessa Rd",
    "iso:country":"US",
    "sg:address":"120 Odessa Rd",
    "sg:city":"Duson",
    "sg:classifiers":[
        {
            "category":"Freight",
            "type":"Transportation"
        }
    ],
    "sg:phone":"+1 337 873 0179",
    "sg:postcode":"70529",
    "sg:province":"LA",
    "sg:tags":[
        "courier"
    ],
    "wof:name":"Acadiana Courier",
    "wof:placetype":"venue"
},
  "geometry": {"coordinates":[-92.15020199999999,30.13652],"type":"Point"}
}