{
  "type": "Feature",
  "properties": {
    "iso:country":"US",
    "sg:address":"101 Mahlon St",
    "sg:city":"Deridder",
    "sg:classifiers":[
        {
            "category":"Home & Garden",
            "subcategory":"Furniture",
            "type":"Retail Goods"
        }
    ],
    "sg:phone":"+1 337 462 1145",
    "sg:postcode":"70634",
    "sg:province":"LA",
    "wof:name":"De Ridder Vac & Sew Gifts",
    "wof:placetype":"venue"
},
  "geometry": {"coordinates":[-93.2855,30.847906],"type":"Point"}
}