{
  "type": "Feature",
  "properties": {
    "iso:country":"US",
    "sg:address":"8094 Highway 23",
    "sg:city":"Belle Chasse",
    "sg:classifiers":[
        {
            "category":"Shopping",
            "subcategory":"Clothing, Apparel, & Fashions",
            "type":"Retail Goods"
        }
    ],
    "sg:phone":"+1 504 398 3033",
    "sg:postcode":"70037",
    "sg:province":"LA",
    "sg:tags":[
        "children's",
        "clothing"
    ],
    "wof:name":"Finders Keepers",
    "wof:placetype":"venue"
},
  "geometry": {"coordinates":[-89.990233,29.858834],"type":"Point"}
}