{
  "type": "Feature",
  "properties": {
    "iso:country":"US",
    "sg:address":"7250 Perkins Rd",
    "sg:city":"Baton Rouge",
    "sg:classifiers":[
        {
            "category":"Professional",
            "subcategory":"Management & Consulting",
            "type":"Services"
        }
    ],
    "sg:phone":"+1 225 769 0529",
    "sg:postcode":"70808",
    "sg:province":"LA",
    "sg:tags":[
        "business"
    ],
    "wof:name":"Capital City Consultant Inc",
    "wof:placetype":"venue"
},
  "geometry": {"coordinates":[-91.11479199999999,30.398286],"type":"Point"}
}