{
  "type": "Feature",
  "properties": {
    "iso:country":"US",
    "sg:address":"3800 Florida Blvd",
    "sg:city":"Baton Rouge",
    "sg:classifiers":[
        {
            "category":"Autos & Motor Vehicles",
            "subcategory":"Automobile Sales",
            "type":"Retail Goods"
        }
    ],
    "sg:phone":"+1 225 383 1080",
    "sg:postcode":"70806",
    "sg:province":"LA",
    "sg:tags":[
        "car",
        "dealer"
    ],
    "wof:name":"Best Price Auto Sales",
    "wof:placetype":"venue"
},
  "geometry": {"coordinates":[-91.15066299999999,30.450469],"type":"Point"}
}