{
  "type": "Feature",
  "properties": {
    "iso:country":"US",
    "sg:address":"4430 Hwy 24",
    "sg:city":"Bourg",
    "sg:classifiers":[
        {
            "category":"Organizations",
            "subcategory":"Religious Organization",
            "type":"Services"
        }
    ],
    "sg:phone":"+1 985 594 7757",
    "sg:postcode":"70343",
    "sg:province":"LA",
    "sg:tags":[
        "church"
    ],
    "wof:name":"New Life Fellowship",
    "wof:placetype":"venue"
},
  "geometry": {"coordinates":[-90.602407,29.553462],"type":"Point"}
}