{
  "type": "Feature",
  "properties": {
    "addr:full":"152 Zimmer Rd Gibson LA 70356",
    "addr:housenumber":"152",
    "addr:postcode":"70356",
    "addr:street":"Zimmer Rd",
    "iso:country":"US",
    "sg:address":"152 Zimmer Rd",
    "sg:city":"Gibson",
    "sg:classifiers":[
        {
            "category":"Professional",
            "subcategory":"Management & Consulting",
            "type":"Services"
        }
    ],
    "sg:phone":"+1 985 631 3278",
    "sg:postcode":"70356",
    "sg:province":"LA",
    "sg:tags":[
        "field",
        "oil",
        "consultant"
    ],
    "wof:name":"Eagle Consulting",
    "wof:placetype":"venue"
},
  "geometry": {"coordinates":[-91.011927,29.668027],"type":"Point"}
}