{
  "type": "Feature",
  "properties": {
    "iso:country":"US",
    "sg:address":"1205 S Pointe Pkwy",
    "sg:city":"Shreveport",
    "sg:classifiers":[
        {
            "category":"Shopping",
            "subcategory":"Bicycles & Sporting Goods",
            "type":"Retail Goods"
        }
    ],
    "sg:phone":"+1 318 869 1293",
    "sg:postcode":"71105",
    "sg:province":"LA",
    "wof:name":"Racing Research Distributing",
    "wof:placetype":"venue"
},
  "geometry": {"coordinates":[-93.70305,32.483491],"type":"Point"}
}