{
  "type": "Feature",
  "properties": {
    "iso:country":"US",
    "sg:address":"187 Beechwood Ln",
    "sg:city":"Natchitoches",
    "sg:classifiers":[
        {
            "category":"Wholesale",
            "subcategory":"Apparel",
            "type":"Manufacturing & Wholesale Goods"
        }
    ],
    "sg:phone":"+1 318 352 5866",
    "sg:postcode":"71457",
    "sg:province":"LA",
    "sg:tags":[
        "clothing"
    ],
    "wof:name":"Parrish Sales Inc",
    "wof:placetype":"venue"
},
  "geometry": {"coordinates":[-93.13119399999999,31.750452],"type":"Point"}
}