{
  "type": "Feature",
  "properties": {
    "addr:full":"1512 Polk St Houma LA 70360",
    "addr:housenumber":"1512",
    "addr:postcode":"70360",
    "addr:street":"Polk St",
    "iso:country":"US",
    "sg:address":"1512 Polk St",
    "sg:city":"Houma",
    "sg:classifiers":[
        {
            "category":"Personal",
            "subcategory":"Barber",
            "type":"Services"
        }
    ],
    "sg:phone":"+1 985 868 3344",
    "sg:postcode":"70360",
    "sg:province":"LA",
    "wof:name":"Perceptions For Hair",
    "wof:placetype":"venue"
},
  "geometry": {"coordinates":[-90.734539,29.592125],"type":"Point"}
}