{
  "type": "Feature",
  "properties": {
    "addr:full":"606 E College Homer LA 71040",
    "addr:housenumber":"606",
    "addr:postcode":"71040",
    "addr:street":"E College",
    "iso:country":"US",
    "sg:address":"606 E College",
    "sg:city":"Homer",
    "sg:classifiers":[
        {
            "category":"Local Transit",
            "type":"Transportation"
        }
    ],
    "sg:phone":"+1 318 927 4141",
    "sg:postcode":"71040",
    "sg:province":"LA",
    "sg:tags":[
        "ambulance"
    ],
    "wof:name":"Clairborne Ambulance Inc",
    "wof:placetype":"venue"
},
  "geometry": {"coordinates":[-93.062365,32.792251],"type":"Point"}
}