{
  "type": "Feature",
  "properties": {
    "addr:full":"11822 Coursey Blvd Baton Rouge LA 70816",
    "addr:housenumber":"11822",
    "addr:postcode":"70816",
    "addr:street":"Coursey Blvd",
    "iso:country":"US",
    "sg:address":"11822 Coursey Blvd",
    "sg:city":"Baton Rouge",
    "sg:classifiers":[
        {
            "category":"Restaurant",
            "type":"Food & Drink"
        }
    ],
    "sg:phone":"+1 225 292 4513",
    "sg:postcode":"70816",
    "sg:province":"LA",
    "wof:name":"China Express",
    "wof:placetype":"venue"
},
  "geometry": {"coordinates":[-91.04781199999999,30.411204],"type":"Point"}
}