{
  "type": "Feature",
  "properties": {
    "addr:full":"1100 N Peters St New Orleans LA 70116",
    "addr:housenumber":"1100",
    "addr:postcode":"70116",
    "addr:street":"N Peters St",
    "iso:country":"US",
    "sg:address":"1100 N Peters St",
    "sg:city":"New Orleans",
    "sg:classifiers":[
        {
            "category":"Food & Beverages",
            "subcategory":"Fruits & Vegetables",
            "type":"Retail Goods"
        }
    ],
    "sg:phone":"+1 504 558 9600",
    "sg:postcode":"70116",
    "sg:province":"LA",
    "sg:tags":[
        "produce"
    ],
    "wof:name":"Mama San Produce",
    "wof:placetype":"venue"
},
  "geometry": {"coordinates":[-90.05852899999999,29.960213],"type":"Point"}
}