{
  "type": "Feature",
  "properties": {
    "addr:full":"103 Vernon Dr West Monroe LA 71292",
    "addr:housenumber":"103",
    "addr:postcode":"71292",
    "addr:street":"Vernon Dr West",
    "iso:country":"US",
    "sg:address":"103 Vernon Dr",
    "sg:city":"West Monroe",
    "sg:classifiers":[
        {
            "category":"Retail",
            "subcategory":"Repair Shop",
            "type":"Services"
        }
    ],
    "sg:phone":"+1 318 322 6511",
    "sg:postcode":"71292",
    "sg:province":"LA",
    "sg:tags":[
        "welding"
    ],
    "wof:name":"Linders Welding Fabricati",
    "wof:placetype":"venue"
},
  "geometry": {"coordinates":[-92.18005100000001,32.476916],"type":"Point"}
}