{
  "type": "Feature",
  "properties": {
    "addr:full":"1617 Federal Ave Morgan City LA 70380",
    "addr:housenumber":"1617",
    "addr:postcode":"70380",
    "addr:street":"Federal Ave",
    "iso:country":"US",
    "sg:address":"1617 Federal Ave",
    "sg:city":"Morgan City",
    "sg:classifiers":[
        {
            "category":"Government",
            "subcategory":"Fire Station",
            "type":"Public Place"
        }
    ],
    "sg:phone":"+1 985 380 4619",
    "sg:postcode":"70380",
    "sg:province":"LA",
    "sg:tags":[
        "department"
    ],
    "wof:name":"Morgan City Fire Dept",
    "wof:placetype":"venue"
},
  "geometry": {"coordinates":[-91.212586,29.709217],"type":"Point"}
}