{
  "type": "Feature",
  "properties": {
    "addr:full":"118 C Moon Ln Houma LA 70301",
    "addr:housenumber":"118 c",
    "addr:postcode":"70301",
    "addr:street":"Moon Ln",
    "iso:country":"US",
    "sg:address":"118 C Moon Ln",
    "sg:city":"Houma",
    "sg:classifiers":[
        {
            "category":"Professional",
            "subcategory":"Research",
            "type":"Services"
        }
    ],
    "sg:phone":"+1 985 851 6060",
    "sg:postcode":"70301",
    "sg:province":"LA",
    "sg:tags":[
        "environmental",
        "ecological"
    ],
    "wof:name":"B B Chemical Inc",
    "wof:placetype":"venue"
},
  "geometry": {"coordinates":[-90.759473,29.905795],"type":"Point"}
}