{
  "type": "Feature",
  "properties": {
    "addr:full":"3750 Veterans Memorial Blvd Metairie LA 70006",
    "addr:housenumber":"3750",
    "addr:postcode":"70006",
    "addr:street":"Veterans Memorial Blvd",
    "iso:country":"US",
    "sg:address":"3750 Veterans Memorial Blvd",
    "sg:city":"Metairie",
    "sg:classifiers":[
        {
            "category":"Banks & Credit Unions",
            "subcategory":"Bank",
            "type":"Services"
        }
    ],
    "sg:phone":"+1 504 887 6867",
    "sg:postcode":"70006",
    "sg:province":"LA",
    "sg:tags":[
        "cashing",
        "check"
    ],
    "wof:name":"Advance America",
    "wof:placetype":"venue"
},
  "geometry": {"coordinates":[-90.16766699999999,30.004326],"type":"Point"}
}