{
  "type": "Feature",
  "properties": {
    "iso:country":"US",
    "sg:address":"9301 Lake Forest Blvd",
    "sg:city":"New Orleans",
    "sg:classifiers":[
        {
            "category":"Shopping",
            "subcategory":"Clothing, Apparel, & Fashions",
            "type":"Retail Goods"
        }
    ],
    "sg:phone":"+1 504 244 9972",
    "sg:postcode":"70127",
    "sg:province":"LA",
    "sg:tags":[
        "furnishing"
    ],
    "wof:name":"Designers Touch",
    "wof:placetype":"venue"
},
  "geometry": {"coordinates":[-89.984104,30.028956],"type":"Point"}
}