{
  "type": "Feature",
  "properties": {
    "addr:full":"201 Gemini Ct Houma LA 70360",
    "addr:housenumber":"201",
    "addr:postcode":"70360",
    "addr:street":"Gemini Ct",
    "iso:country":"US",
    "sg:address":"201 Gemini Ct",
    "sg:city":"Houma",
    "sg:classifiers":[
        {
            "category":"Social Services",
            "subcategory":"Child Care",
            "type":"Services"
        }
    ],
    "sg:phone":"+1 985 876 7213",
    "sg:postcode":"70360",
    "sg:province":"LA",
    "wof:name":"Feed My Lambs Daycare-Pre-Schl",
    "wof:placetype":"venue"
},
  "geometry": {"coordinates":[-90.740983,29.590525],"type":"Point"}
}