{
  "type": "Feature",
  "properties": {
    "iso:country":"US",
    "sg:address":"2364 Thomas H Delpit Dr",
    "sg:city":"Baton Rouge",
    "sg:classifiers":[
        {
            "category":"Organizations",
            "subcategory":"Religious Organization",
            "type":"Services"
        }
    ],
    "sg:phone":"+1 225 383 0937",
    "sg:postcode":"70802",
    "sg:province":"LA",
    "sg:tags":[
        "church"
    ],
    "wof:name":"Faith AME Zion Church",
    "wof:placetype":"venue"
},
  "geometry": {"coordinates":[-91.17683,30.425147],"type":"Point"}
}