{
  "type": "Feature",
  "properties": {
    "iso:country":"US",
    "sg:address":"2001 42nd St",
    "sg:city":"Kenner",
    "sg:classifiers":[
        {
            "category":"Freight",
            "type":"Transportation"
        }
    ],
    "sg:phone":"+1 504 463 3005",
    "sg:postcode":"70065",
    "sg:province":"LA",
    "sg:tags":[
        "trucking"
    ],
    "wof:name":"ALS Transport Inc",
    "wof:placetype":"venue"
},
  "geometry": {"coordinates":[-90.23889,30.032572],"type":"Point"}
}