{
  "type": "Feature",
  "properties": {
    "addr:full":"1205 Seabord Dr Baton Rouge LA 70810",
    "addr:housenumber":"1205",
    "addr:postcode":"70810",
    "addr:street":"Seabord Dr",
    "iso:country":"US",
    "sg:address":"1205 Seabord Dr",
    "sg:city":"Baton Rouge",
    "sg:classifiers":[
        {
            "category":"Food & Beverages",
            "subcategory":"Liquor & Beverages",
            "type":"Retail Goods"
        }
    ],
    "sg:phone":"+1 225 766 5226",
    "sg:postcode":"70810",
    "sg:province":"LA",
    "sg:tags":[
        "beer",
        "ale"
    ],
    "wof:name":"Catering Kegs",
    "wof:placetype":"venue"
},
  "geometry": {"coordinates":[-91.12578600000001,30.354853],"type":"Point"}
}