{
  "type": "Feature",
  "properties": {
    "iso:country":"US",
    "sg:address":"119 C Moon Ln",
    "sg:city":"Houma",
    "sg:classifiers":[
        {
            "category":"Building & Trades",
            "subcategory":"Construction",
            "type":"Services"
        }
    ],
    "sg:phone":"+1 985 868 5990",
    "sg:postcode":"70301",
    "sg:province":"LA",
    "sg:tags":[
        "general",
        "contractor"
    ],
    "wof:name":"Calongne Inc",
    "wof:placetype":"venue"
},
  "geometry": {"coordinates":[-90.75932299999999,29.905797],"type":"Point"}
}