{
  "type": "Feature",
  "properties": {
    "iso:country":"US",
    "sg:address":"4213 E Judge Perez Dr",
    "sg:city":"Meraux",
    "sg:classifiers":[
        {
            "category":"Restaurant",
            "type":"Food & Drink"
        }
    ],
    "sg:phone":"+1 504 281 2265",
    "sg:postcode":"70075",
    "sg:province":"LA",
    "sg:tags":[
        "parlor",
        "ice",
        "cream"
    ],
    "wof:name":"Sweet Spot",
    "wof:placetype":"venue"
},
  "geometry": {"coordinates":[-89.921307,29.934697],"type":"Point"}
}