{
  "type": "Feature",
  "properties": {
    "iso:country":"US",
    "sg:address":"560 N Main St",
    "sg:city":"Church Point",
    "sg:classifiers":[
        {
            "category":"Bars & Pubs",
            "type":"Food & Drink"
        }
    ],
    "sg:phone":"+1 337 684 1315",
    "sg:postcode":"70525",
    "sg:province":"LA",
    "sg:tags":[
        "lounge",
        "cocktail"
    ],
    "wof:name":"Oasis",
    "wof:placetype":"venue"
},
  "geometry": {"coordinates":[-92.222961,30.41209],"type":"Point"}
}