{
  "type": "Feature",
  "properties": {
    "iso:country":"US",
    "sg:address":"3655 W Main St",
    "sg:city":"Gray",
    "sg:classifiers":[
        {
            "category":"Wholesale",
            "subcategory":"Groceries",
            "type":"Manufacturing & Wholesale Goods"
        }
    ],
    "sg:phone":"+1 985 879 1645",
    "sg:postcode":"70359",
    "sg:province":"LA",
    "sg:tags":[
        "baker"
    ],
    "wof:name":"Sunbeam Bakeries",
    "wof:placetype":"venue"
},
  "geometry": {"coordinates":[-90.785811,29.686918],"type":"Point"}
}