{
  "type": "Feature",
  "properties": {
    "iso:country":"US",
    "sg:address":"3201 Edenborn Ave",
    "sg:city":"Metairie",
    "sg:classifiers":[
        {
            "category":"Bars & Pubs",
            "type":"Food & Drink"
        }
    ],
    "sg:phone":"+1 504 885 0070",
    "sg:postcode":"70002",
    "sg:province":"LA",
    "wof:name":"Que Pasa",
    "wof:placetype":"venue"
},
  "geometry": {"coordinates":[-90.161878,30.007827],"type":"Point"}
}