{
  "type": "Feature",
  "properties": {
    "iso:country":"US",
    "sg:address":"201 Napoleon St",
    "sg:city":"Baton Rouge",
    "sg:classifiers":[
        {
            "category":"Professional",
            "subcategory":"Lawyer & Legal Services",
            "type":"Services"
        }
    ],
    "sg:phone":"+1 225 383 3545",
    "sg:postcode":"70802",
    "sg:province":"LA",
    "sg:tags":[
        "attorney"
    ],
    "wof:name":"David M Lefeve Law Office",
    "wof:placetype":"venue"
},
  "geometry": {"coordinates":[-91.18379400000001,30.444968],"type":"Point"}
}