{
  "type": "Feature",
  "properties": {
    "iso:country":"US",
    "sg:address":"8819 W Judge Perez Dr",
    "sg:city":"Chalmette",
    "sg:classifiers":[
        {
            "category":"Shopping",
            "subcategory":"Tobacco",
            "type":"Retail Goods"
        }
    ],
    "sg:phone":"+1 504 277 8340",
    "sg:postcode":"70043",
    "sg:province":"LA",
    "sg:tags":[
        "shop"
    ],
    "wof:name":"Smokes For Less",
    "wof:placetype":"venue"
},
  "geometry": {"coordinates":[-89.977699,29.9531],"type":"Point"}
}