{
  "type": "Feature",
  "properties": {
    "addr:full":"1347 Lakeshore Ave Metairie LA 70005",
    "addr:housenumber":"1347",
    "addr:postcode":"70005",
    "addr:street":"Lakeshore Ave",
    "iso:country":"US",
    "sg:address":"1347 Lakeshore Ave",
    "sg:city":"Metairie",
    "sg:classifiers":[
        {
            "category":"Building & Trades",
            "subcategory":"Construction",
            "type":"Services"
        }
    ],
    "sg:phone":"+1 504 837 3464",
    "sg:postcode":"70005",
    "sg:province":"LA",
    "sg:tags":[
        "house"
    ],
    "wof:name":"Ginther Constr",
    "wof:placetype":"venue"
},
  "geometry": {"coordinates":[-90.136162,30.015007],"type":"Point"}
}