{
  "type": "Feature",
  "properties": {
    "iso:country":"US",
    "sg:address":"317 Ayres Loop",
    "sg:city":"Jonesboro",
    "sg:classifiers":[
        {
            "category":"Organizations",
            "subcategory":"Religious Organization",
            "type":"Services"
        }
    ],
    "sg:phone":"+1 318 259 9351",
    "sg:postcode":"71251",
    "sg:province":"LA",
    "wof:name":"Bill Weeks & Christ",
    "wof:placetype":"venue"
},
  "geometry": {"coordinates":[-92.667991,32.249408],"type":"Point"}
}