{
  "type": "Feature",
  "properties": {
    "addr:full":"428 Jefferson Hwy Jefferson LA 70121",
    "addr:housenumber":"428",
    "addr:postcode":"70121",
    "addr:street":"Jefferson Hwy Jefferson",
    "iso:country":"US",
    "sg:address":"428 Jefferson Hwy",
    "sg:city":"Jefferson",
    "sg:classifiers":[
        {
            "category":"Wholesale",
            "subcategory":"Seafood",
            "type":"Manufacturing & Wholesale Goods"
        }
    ],
    "sg:phone":"+1 504 834 9393",
    "sg:postcode":"70121",
    "sg:province":"LA",
    "wof:name":"Louisiana Seafood Exchange Inc",
    "wof:placetype":"venue"
},
  "geometry": {"coordinates":[-90.13596200000001,29.96499],"type":"Point"}
}