{
  "type": "Feature",
  "properties": {
    "addr:full":"1623 N Parkerson Ave Crowley LA 70526",
    "addr:housenumber":"1623",
    "addr:postcode":"70526",
    "addr:street":"N Parkerson Ave",
    "iso:country":"US",
    "sg:address":"1623 N Parkerson Ave",
    "sg:city":"Crowley",
    "sg:classifiers":[
        {
            "category":"Retail",
            "subcategory":"Auto Repair",
            "type":"Services"
        }
    ],
    "sg:phone":"+1 337 783 4600",
    "sg:postcode":"70526",
    "sg:province":"LA",
    "sg:tags":[
        "repairing",
        "automobile"
    ],
    "sg:website":"www.shetlercorleyford.com",
    "wof:name":"Shelter-Corley Motors",
    "wof:placetype":"venue"
},
  "geometry": {"coordinates":[-92.37924,30.224098],"type":"Point"}
}