{
  "type": "Feature",
  "properties": {
    "addr:full":"2444 Woodland Ridge Blvd Baton Rouge LA 70816",
    "addr:housenumber":"2444",
    "addr:postcode":"70816",
    "addr:street":"Woodland Ridge Blvd",
    "iso:country":"US",
    "sg:address":"2444 Woodland Ridge Blvd",
    "sg:city":"Baton Rouge",
    "sg:classifiers":[
        {
            "category":"Home & Garden",
            "subcategory":"Building Materials",
            "type":"Retail Goods"
        }
    ],
    "sg:phone":"+1 225 291 2314",
    "sg:postcode":"70816",
    "sg:province":"LA",
    "sg:tags":[
        "equipment",
        "electric",
        "supply"
    ],
    "sg:website":"www.hvsales.com",
    "wof:name":"H V Sales Co",
    "wof:placetype":"venue"
},
  "geometry": {"coordinates":[-91.04154699999999,30.429086],"type":"Point"}
}