{
  "type": "Feature",
  "properties": {
    "iso:country":"US",
    "sg:address":"4027 US Hwy 90",
    "sg:city":"Broussard",
    "sg:classifiers":[
        {
            "category":"Health Services",
            "subcategory":"Chiropractor",
            "type":"Services"
        }
    ],
    "sg:phone":"+1 337 837 7174",
    "sg:postcode":"70518",
    "sg:province":"LA",
    "wof:name":"Bryant Chiropractic Broussard",
    "wof:placetype":"venue"
},
  "geometry": {"coordinates":[-91.96672599999999,30.156944],"type":"Point"}
}