{
  "type": "Feature",
  "properties": {
    "addr:full":"4801 Chef Menteur Hwy New Orleans LA 70126",
    "addr:housenumber":"4801",
    "addr:postcode":"70126",
    "addr:street":"Chef Menteur Hwy",
    "iso:country":"US",
    "sg:address":"4801 Chef Menteur Hwy",
    "sg:city":"New Orleans",
    "sg:classifiers":[
        {
            "category":"Shopping",
            "subcategory":"Clothing, Apparel, & Fashions",
            "type":"Retail Goods"
        }
    ],
    "sg:phone":"+1 504 288 8141",
    "sg:postcode":"70126",
    "sg:province":"LA",
    "sg:tags":[
        "furnishing"
    ],
    "wof:name":"Soul Train Fashions",
    "wof:placetype":"venue"
},
  "geometry": {"coordinates":[-90.032955,30.006719],"type":"Point"}
}