{
  "type": "Feature",
  "properties": {
    "iso:country":"US",
    "sg:address":"2100 Woodmere Blvd",
    "sg:city":"Harvey",
    "sg:classifiers":[
        {
            "category":"Professional",
            "subcategory":"Accounting & Tax Preparation",
            "type":"Services"
        }
    ],
    "sg:phone":"+1 504 341 8881",
    "sg:postcode":"70058",
    "sg:province":"LA",
    "sg:tags":[
        "return",
        "filing"
    ],
    "wof:name":"Total Tax Time",
    "wof:placetype":"venue"
},
  "geometry": {"coordinates":[-90.081169,29.867238],"type":"Point"}
}