{
  "type": "Feature",
  "properties": {
    "addr:full":"1011 Lowerline St New Orleans LA 70118",
    "addr:housenumber":"1011",
    "addr:postcode":"70118",
    "addr:street":"Lowerline St",
    "iso:country":"US",
    "sg:address":"1011 Lowerline St",
    "sg:city":"New Orleans",
    "sg:classifiers":[
        {
            "category":"Real Estate",
            "subcategory":"Real Estate Agent",
            "type":"Services"
        }
    ],
    "sg:phone":"+1 504 861 4583",
    "sg:postcode":"70118",
    "sg:province":"LA",
    "wof:name":"Ferchaud Realty",
    "wof:placetype":"venue"
},
  "geometry": {"coordinates":[-90.125072,29.942243],"type":"Point"}
}