{
  "type": "Feature",
  "properties": {
    "iso:country":"US",
    "sg:address":"3000 S Macarthur Dr",
    "sg:city":"Alexandria",
    "sg:classifiers":[
        {
            "category":"Real Estate",
            "subcategory":"Real Estate Agent",
            "type":"Services"
        }
    ],
    "sg:phone":"+1 318 473 0082",
    "sg:postcode":"71301",
    "sg:province":"LA",
    "sg:tags":[
        "agency",
        "rental"
    ],
    "wof:name":"South Circle Trailer Rentals",
    "wof:placetype":"venue"
},
  "geometry": {"coordinates":[-92.45508100000001,31.265599],"type":"Point"}
}