{
  "type": "Feature",
  "properties": {
    "iso:country":"US",
    "sg:address":"6045 Magazine St",
    "sg:city":"New Orleans",
    "sg:classifiers":[
        {
            "category":"Utilities",
            "subcategory":"Mobile Phone",
            "type":"Services"
        }
    ],
    "sg:phone":"+1 504 895 4765",
    "sg:postcode":"70118",
    "sg:province":"LA",
    "sg:tags":[
        "telephone",
        "cellular"
    ],
    "wof:name":"Radio Shack",
    "wof:placetype":"venue"
},
  "geometry": {"coordinates":[-90.122602,29.922554],"type":"Point"}
}