{
  "type": "Feature",
  "properties": {
    "iso:country":"US",
    "sg:address":"100 Robert E Lee Blvd",
    "sg:city":"New Orleans",
    "sg:classifiers":[
        {
            "category":"Health Services",
            "subcategory":"Doctor",
            "type":"Services"
        }
    ],
    "sg:phone":"+1 504 282 7700",
    "sg:postcode":"70124",
    "sg:province":"LA",
    "sg:tags":[
        "dentist"
    ],
    "wof:name":"Deborah E Lesem DDS",
    "wof:placetype":"venue"
},
  "geometry": {"coordinates":[-90.113551,30.020114],"type":"Point"}
}