{
  "type": "Feature",
  "properties": {
    "iso:country":"US",
    "sg:address":"3107 Maplewood Dr",
    "sg:city":"Sulphur",
    "sg:classifiers":[
        {
            "category":"Health Services",
            "subcategory":"Doctor",
            "type":"Services"
        }
    ],
    "sg:phone":"+1 337 625 9911",
    "sg:postcode":"70663",
    "sg:province":"LA",
    "sg:tags":[
        "dentist"
    ],
    "wof:name":"E Suzanne Mc Crory DDS",
    "wof:placetype":"venue"
},
  "geometry": {"coordinates":[-93.341911,30.227449],"type":"Point"}
}