{
  "type": "Feature",
  "properties": {
    "addr:full":"17487 Meadow Ridge Cir Prairieville LA 70769",
    "addr:housenumber":"17487",
    "addr:postcode":"70769",
    "addr:street":"Meadow Ridge Cir Prairieville",
    "iso:country":"US",
    "sg:address":"17487 Meadow Ridge Cir",
    "sg:city":"Prairieville",
    "sg:classifiers":[
        {
            "category":"Retail",
            "subcategory":"Repair Shop",
            "type":"Services"
        }
    ],
    "sg:phone":"+1 225 622 2700",
    "sg:postcode":"70769",
    "sg:province":"LA",
    "wof:name":"D&S Vehicle Unlocking Service",
    "wof:placetype":"venue"
},
  "geometry": {"coordinates":[-90.954042,30.32593],"type":"Point"}
}