{
  "type": "Feature",
  "properties": {
    "iso:country":"US",
    "sg:address":"16324 Black Dr",
    "sg:city":"Ponchatoula",
    "sg:classifiers":[
        {
            "category":"Professional",
            "subcategory":"Secretarial Services",
            "type":"Services"
        }
    ],
    "sg:phone":"+1 985 370 0768",
    "sg:postcode":"70454",
    "sg:province":"LA",
    "sg:tags":[
        "reporting"
    ],
    "wof:name":"Geromanos Colette C Ccr",
    "wof:placetype":"venue"
},
  "geometry": {"coordinates":[-90.447513,30.464161],"type":"Point"}
}