{
  "type": "Feature",
  "properties": {
    "iso:country":"US",
    "sg:address":"4425 Shores Dr",
    "sg:city":"Metairie",
    "sg:classifiers":[
        {
            "category":"Personal",
            "subcategory":"Beauty Salon",
            "type":"Services"
        }
    ],
    "sg:phone":"+1 504 780 8000",
    "sg:postcode":"70006",
    "sg:province":"LA",
    "wof:name":"J Christopher's",
    "wof:placetype":"venue"
},
  "geometry": {"coordinates":[-90.18936600000001,30.018733],"type":"Point"}
}