{
  "type": "Feature",
  "properties": {
    "iso:country":"US",
    "sg:address":"777 N Washington St",
    "sg:city":"Bastrop",
    "sg:classifiers":[
        {
            "category":"Professional",
            "subcategory":"Business Services",
            "type":"Services"
        }
    ],
    "sg:phone":"+1 318 281 7774",
    "sg:postcode":"71220",
    "sg:province":"LA",
    "wof:name":"Hammerhead Graphics",
    "wof:placetype":"venue"
},
  "geometry": {"coordinates":[-91.91385699999999,32.785173],"type":"Point"}
}