{
  "type": "Feature",
  "properties": {
    "iso:country":"US",
    "sg:address":"3524 Canal St",
    "sg:city":"New Orleans",
    "sg:classifiers":[
        {
            "category":"Professional",
            "subcategory":"Art Services",
            "type":"Services"
        }
    ],
    "sg:phone":"+1 504 488 8000",
    "sg:postcode":"70119",
    "sg:province":"LA",
    "sg:tags":[
        "photographer"
    ],
    "sg:website":"www.posey-images.com",
    "wof:name":"Mike Posey Photography & Video",
    "wof:placetype":"venue"
},
  "geometry": {"coordinates":[-90.095872,29.971152],"type":"Point"}
}