{
  "type": "Feature",
  "properties": {
    "addr:full":"306 Dr Parrot Ave Branch LA 70516",
    "addr:housenumber":"306",
    "addr:postcode":"70516",
    "addr:street":"Dr Parrot Ave Branch La",
    "iso:country":"US",
    "sg:address":"306 Dr Parrot Ave",
    "sg:city":"Branch",
    "sg:classifiers":[
        {
            "category":"Building & Trades",
            "subcategory":"Plumbing",
            "type":"Services"
        }
    ],
    "sg:phone":"+1 337 334 3627",
    "sg:postcode":"70516",
    "sg:province":"LA",
    "sg:tags":[
        "contractor"
    ],
    "wof:name":"Pipe Doctor LLC",
    "wof:placetype":"venue"
},
  "geometry": {"coordinates":[-92.26906200000001,30.340607],"type":"Point"}
}