{
  "type": "Feature",
  "properties": {
    "iso:country":"US",
    "sg:address":"421 State Rte 306",
    "sg:city":"Paradis",
    "sg:classifiers":[
        {
            "category":"Organizations",
            "subcategory":"Religious Organization",
            "type":"Services"
        }
    ],
    "sg:phone":"+1 985 758 2668",
    "sg:postcode":"70080",
    "sg:province":"LA",
    "sg:tags":[
        "church"
    ],
    "wof:name":"St John The Baptist",
    "wof:placetype":"venue"
},
  "geometry": {"coordinates":[-90.43897200000001,29.872765],"type":"Point"}
}