{
  "type": "Feature",
  "properties": {
    "iso:country":"US",
    "sg:address":"5914 Delacroix Hwy",
    "sg:city":"St Bernard",
    "sg:classifiers":[
        {
            "category":"Mining & Drilling",
            "type":"Manufacturing & Wholesale Goods"
        }
    ],
    "sg:phone":"+1 504 676 4524",
    "sg:postcode":"70085",
    "sg:province":"LA",
    "sg:tags":[
        "oil",
        "gas",
        "producer"
    ],
    "wof:name":"Apache Corp",
    "wof:placetype":"venue"
},
  "geometry": {"coordinates":[-89.78139299999999,29.776525],"type":"Point"}
}