{
  "type": "Feature",
  "properties": {
    "addr:full":"4041 Williams Blvd Kenner LA 70065",
    "addr:housenumber":"4041",
    "addr:postcode":"70065",
    "addr:street":"Williams Blvd",
    "iso:country":"US",
    "sg:address":"4041 Williams Blvd",
    "sg:city":"Kenner",
    "sg:classifiers":[
        {
            "category":"Professional",
            "subcategory":"Management & Consulting",
            "type":"Services"
        }
    ],
    "sg:phone":"+1 504 468 2350",
    "sg:postcode":"70065",
    "sg:province":"LA",
    "sg:tags":[
        "consultant",
        "safety"
    ],
    "wof:name":"Child Recovery System",
    "wof:placetype":"venue"
},
  "geometry": {"coordinates":[-90.238845,30.027513],"type":"Point"}
}