{
  "type": "Feature",
  "properties": {
    "iso:country":"US",
    "sg:address":"100 Tivoli St",
    "sg:city":"Abbeville",
    "sg:classifiers":[
        {
            "category":"Government",
            "subcategory":"Police Station",
            "type":"Public Place"
        }
    ],
    "sg:phone":"+1 337 898 4300",
    "sg:postcode":"70510",
    "sg:province":"LA",
    "sg:tags":[
        "sheriff"
    ],
    "wof:name":"Vermilion Parish Police Jury",
    "wof:placetype":"venue"
},
  "geometry": {"coordinates":[-92.134485,29.97412],"type":"Point"}
}