{
  "type": "Feature",
  "properties": {
    "iso:country":"US",
    "sg:address":"3321 Jefferson Hwy",
    "sg:city":"New Orleans",
    "sg:classifiers":[
        {
            "category":"Travel",
            "subcategory":"Hotels & Motels",
            "type":"Entertainment"
        }
    ],
    "sg:phone":"+1 504 831 0654",
    "sg:postcode":"70121",
    "sg:province":"LA",
    "sg:tags":[
        "operation"
    ],
    "wof:name":"Labella Motel Inc",
    "wof:placetype":"venue"
},
  "geometry": {"coordinates":[-90.159347,29.963252],"type":"Point"}
}