{
  "type": "Feature",
  "properties": {
    "addr:full":"252 S Preston St Marksville LA 71351",
    "addr:housenumber":"252",
    "addr:postcode":"71351",
    "addr:street":"S Preston St",
    "iso:country":"US",
    "sg:address":"252 S Preston St",
    "sg:city":"Marksville",
    "sg:classifiers":[
        {
            "category":"Autos & Motor Vehicles",
            "subcategory":"Fuel & Gas Station",
            "type":"Retail Goods"
        }
    ],
    "sg:phone":"+1 318 253 9662",
    "sg:postcode":"71351",
    "sg:province":"LA",
    "sg:tags":[
        "oil"
    ],
    "wof:name":"Leroy's Full Svc Station",
    "wof:placetype":"venue"
},
  "geometry": {"coordinates":[-92.06323,31.122525],"type":"Point"}
}