{
  "type": "Feature",
  "properties": {
    "iso:country":"US",
    "sg:address":"12939 Hooper Rd",
    "sg:city":"Baton Rouge",
    "sg:classifiers":[
        {
            "category":"Retail",
            "subcategory":"Auto Repair",
            "type":"Services"
        }
    ],
    "sg:phone":"+1 225 261 1111",
    "sg:postcode":"70818",
    "sg:province":"LA",
    "sg:tags":[
        "automobile",
        "inspection"
    ],
    "wof:name":"Central State",
    "wof:placetype":"venue"
},
  "geometry": {"coordinates":[-91.043409,30.551551],"type":"Point"}
}