{
  "type": "Feature",
  "properties": {
    "addr:full":"1400 N 19th St Monroe LA 71201",
    "addr:housenumber":"1400",
    "addr:postcode":"71201",
    "addr:street":"N 19Th St",
    "iso:country":"US",
    "sg:address":"1400 N 19th St",
    "sg:city":"Monroe",
    "sg:classifiers":[
        {
            "category":"Government",
            "subcategory":"Office",
            "type":"Public Place"
        }
    ],
    "sg:phone":"+1 318 362 3435",
    "sg:postcode":"71201",
    "sg:province":"LA",
    "wof:name":"Employees Group Benefits Prog",
    "wof:placetype":"venue"
},
  "geometry": {"coordinates":[-92.11069999999999,32.525169],"type":"Point"}
}