{
  "type": "Feature",
  "properties": {
    "addr:full":"2250 W Thomas St Hammond LA 70401",
    "addr:housenumber":"2250",
    "addr:postcode":"70401",
    "addr:street":"W Thomas St",
    "iso:country":"US",
    "sg:address":"2250 W Thomas St",
    "sg:city":"Hammond",
    "sg:classifiers":[
        {
            "category":"Shopping",
            "subcategory":"Clothing, Apparel, & Fashions",
            "type":"Retail Goods"
        }
    ],
    "sg:phone":"+1 985 549 1910",
    "sg:postcode":"70401",
    "sg:province":"LA",
    "sg:tags":[
        "furnishing"
    ],
    "wof:name":"Broadway's Men's Fashions Inc",
    "wof:placetype":"venue"
},
  "geometry": {"coordinates":[-90.483103,30.500985],"type":"Point"}
}