{
  "type": "Feature",
  "properties": {
    "iso:country":"US",
    "sg:address":"714 St Louis Street",
    "sg:city":"New Orleans",
    "sg:classifiers":[
        {
            "category":"Food & Beverages",
            "subcategory":"Candy",
            "type":"Retail Goods"
        }
    ],
    "sg:phone":"+1 504 523 5662",
    "sg:postcode":"70130",
    "sg:province":"LA",
    "sg:tags":[
        "store"
    ],
    "sg:website":"www.leahspralines.com",
    "wof:name":"Leah's Pralines",
    "wof:placetype":"venue"
},
  "geometry": {"coordinates":[-90.066289,29.956482],"type":"Point"}
}