{
  "type": "Feature",
  "properties": {
    "iso:country":"US",
    "sg:address":"617 W Main",
    "sg:city":"Homer",
    "sg:classifiers":[
        {
            "category":"Banks & Credit Unions",
            "subcategory":"Bank",
            "type":"Services"
        }
    ],
    "sg:phone":"+1 318 927 9666",
    "sg:postcode":"71040",
    "sg:province":"LA",
    "wof:name":"Hibernia National Bank",
    "wof:placetype":"venue"
},
  "geometry": {"coordinates":[-93.073554,32.793677],"type":"Point"}
}