{
  "type": "Feature",
  "properties": {
    "addr:full":"150 Belle Terre Blvd La Place LA 70068",
    "addr:housenumber":"150",
    "addr:postcode":"70068",
    "addr:street":"Belle Terre Blvd La Place",
    "iso:country":"US",
    "sg:address":"150 Belle Terre Blvd",
    "sg:city":"La Place",
    "sg:classifiers":[
        {
            "category":"Shopping",
            "subcategory":"Computers & Home Electronics",
            "type":"Retail Goods"
        }
    ],
    "sg:phone":"+1 985 652 7468",
    "sg:postcode":"70068",
    "sg:province":"LA",
    "sg:tags":[
        "game",
        "video"
    ],
    "wof:name":"Gamestop",
    "wof:placetype":"venue"
},
  "geometry": {"coordinates":[-90.500934,30.075685],"type":"Point"}
}