{
  "type": "Feature",
  "properties": {
    "iso:country":"US",
    "sg:address":"5875 N Market St",
    "sg:city":"Shreveport",
    "sg:classifiers":[
        {
            "category":"Food & Beverages",
            "subcategory":"Groceries & Convenience Stores",
            "type":"Retail Goods"
        }
    ],
    "sg:phone":"+1 318 929 4798",
    "sg:postcode":"71107",
    "sg:province":"LA",
    "wof:name":"Fast Food Convenience Store",
    "wof:placetype":"venue"
},
  "geometry": {"coordinates":[-93.845158,32.602517],"type":"Point"}
}