{
  "type": "Feature",
  "properties": {
    "addr:full":"1116 Saizan Ave Port Barre LA 70577",
    "addr:housenumber":"1116",
    "addr:postcode":"70577",
    "addr:street":"Saizan Ave",
    "iso:country":"US",
    "sg:address":"1116 Saizan Ave",
    "sg:city":"Port Barre",
    "sg:classifiers":[
        {
            "category":"Food & Beverages",
            "subcategory":"Groceries & Convenience Stores",
            "type":"Retail Goods"
        }
    ],
    "sg:phone":"+1 337 585 7477",
    "sg:postcode":"70577",
    "sg:province":"LA",
    "sg:tags":[
        "grocer"
    ],
    "wof:name":"Burghgoff's Grocery",
    "wof:placetype":"venue"
},
  "geometry": {"coordinates":[-91.9534,30.566115],"type":"Point"}
}