{
  "type": "Feature",
  "properties": {
    "addr:full":"247 S Robertson St New Orleans LA 70112",
    "addr:housenumber":"247",
    "addr:postcode":"70112",
    "addr:street":"S Robertson St",
    "iso:country":"US",
    "sg:address":"247 S Robertson St",
    "sg:city":"New Orleans",
    "sg:classifiers":[
        {
            "category":"Restaurant",
            "type":"Food & Drink"
        }
    ],
    "sg:phone":"+1 504 524 9012",
    "sg:postcode":"70112",
    "sg:province":"LA",
    "wof:name":"Mandarin Chinese Restaurant",
    "wof:placetype":"venue"
},
  "geometry": {"coordinates":[-90.078339,29.956978],"type":"Point"}
}