{
  "type": "Feature",
  "properties": {
    "iso:country":"US",
    "sg:address":"2245 Peters Rd",
    "sg:city":"Harvey",
    "sg:classifiers":[
        {
            "category":"Building & Trades",
            "subcategory":"Construction",
            "type":"Services"
        }
    ],
    "sg:phone":"+1 504 263 0214",
    "sg:postcode":"70058",
    "sg:province":"LA",
    "sg:tags":[
        "general",
        "contractor"
    ],
    "sg:website":"www.gootee.com",
    "wof:name":"Gootee Fabrication",
    "wof:placetype":"venue"
},
  "geometry": {"coordinates":[-90.069221,29.87389],"type":"Point"}
}