{
  "type": "Feature",
  "properties": {
    "addr:full":"4266 Hwy 665 Montegut LA 70377",
    "addr:housenumber":"4266",
    "addr:postcode":"70377",
    "addr:street":"Hwy 665 Montegut",
    "iso:country":"US",
    "sg:address":"4266 Hwy 665",
    "sg:city":"Montegut",
    "sg:classifiers":[
        {
            "category":"Recreation",
            "subcategory":"Marina",
            "type":"Entertainment"
        }
    ],
    "sg:phone":"+1 985 594 4654",
    "sg:postcode":"70377",
    "sg:province":"LA",
    "wof:name":"Pointe Aux Chene Marina Inc",
    "wof:placetype":"venue"
},
  "geometry": {"coordinates":[-90.447754,29.416998],"type":"Point"}
}