{
  "type": "Feature",
  "properties": {
    "addr:full":"11848 Hooper Rd Baton Rouge LA 70818",
    "addr:housenumber":"11848",
    "addr:postcode":"70818",
    "addr:street":"Hooper Rd",
    "iso:country":"US",
    "sg:address":"11848 Hooper Rd",
    "sg:city":"Baton Rouge",
    "sg:classifiers":[
        {
            "category":"Organizations",
            "subcategory":"Religious Organization",
            "type":"Services"
        }
    ],
    "sg:phone":"+1 225 261 3434",
    "sg:postcode":"70818",
    "sg:province":"LA",
    "sg:tags":[
        "church"
    ],
    "sg:website":"www.zoarbaptist.org",
    "wof:name":"Zoar Baptist Church",
    "wof:placetype":"venue"
},
  "geometry": {"coordinates":[-91.057276,30.545458],"type":"Point"}
}