{
  "type": "Feature",
  "properties": {
    "addr:full":"30163 Walker Rd N Walker LA 70785",
    "addr:housenumber":"30163",
    "addr:postcode":"70785",
    "addr:street":"Walker Rd N",
    "iso:country":"US",
    "sg:address":"30163 Walker Rd N",
    "sg:city":"Walker",
    "sg:classifiers":[
        {
            "category":"Professional",
            "subcategory":"Management & Consulting",
            "type":"Services"
        }
    ],
    "sg:phone":"+1 225 664 9329",
    "sg:postcode":"70785",
    "sg:province":"LA",
    "sg:tags":[
        "party",
        "planning"
    ],
    "wof:name":"Walker Game Room",
    "wof:placetype":"venue"
},
  "geometry": {"coordinates":[-90.86244600000001,30.490727],"type":"Point"}
}