{
  "type": "Feature",
  "properties": {
    "iso:country":"US",
    "sg:address":"2627 Ryan St",
    "sg:city":"Lake Charles",
    "sg:classifiers":[
        {
            "category":"Restaurant",
            "type":"Food & Drink"
        }
    ],
    "sg:phone":"+1 337 436 2813",
    "sg:postcode":"70601",
    "sg:province":"LA",
    "wof:name":"Pappy's Deli & Pub",
    "wof:placetype":"venue"
},
  "geometry": {"coordinates":[-93.21865699999999,30.206909],"type":"Point"}
}