{
  "type": "Feature",
  "properties": {
    "iso:country":"US",
    "sg:address":"621 Beatrice St",
    "sg:city":"Houma",
    "sg:classifiers":[
        {
            "category":"Retail",
            "subcategory":"Repair Shop",
            "type":"Services"
        }
    ],
    "sg:phone":"+1 985 872 1562",
    "sg:postcode":"70363",
    "sg:province":"LA",
    "sg:tags":[
        "upholsterer"
    ],
    "wof:name":"Darcey's Upholstery & Glass",
    "wof:placetype":"venue"
},
  "geometry": {"coordinates":[-90.70717399999999,29.588341],"type":"Point"}
}