{
  "type": "Feature",
  "properties": {
    "addr:full":"2314 Kentucky Ave Kenner LA 70062",
    "addr:housenumber":"2314",
    "addr:postcode":"70062",
    "addr:street":"Kentucky Ave",
    "iso:country":"US",
    "sg:address":"2314 Kentucky Ave",
    "sg:city":"Kenner",
    "sg:classifiers":[
        {
            "category":"Professional",
            "subcategory":"Art Services",
            "type":"Services"
        }
    ],
    "sg:phone":"+1 504 469 3581",
    "sg:postcode":"70062",
    "sg:province":"LA",
    "sg:tags":[
        "photography",
        "commercial"
    ],
    "wof:name":"Fineart Photography",
    "wof:placetype":"venue"
},
  "geometry": {"coordinates":[-90.234172,29.99898],"type":"Point"}
}