{
  "type": "Feature",
  "properties": {
    "iso:country":"US",
    "sg:address":"139 Robicheaux Rd",
    "sg:city":"Broussard",
    "sg:classifiers":[
        {
            "category":"Shopping",
            "subcategory":"Pets & Pet Supplies",
            "type":"Retail Goods"
        }
    ],
    "sg:phone":"+1 337 837 2519",
    "sg:postcode":"70518",
    "sg:province":"LA",
    "sg:tags":[
        "training"
    ],
    "wof:name":"K-9 Concepts Inc Dog Training",
    "wof:placetype":"venue"
},
  "geometry": {"coordinates":[-91.971703,30.127199],"type":"Point"}
}