{
  "type": "Feature",
  "properties": {
    "addr:full":"1020 Canal St New Orleans LA 70112",
    "addr:housenumber":"1020",
    "addr:postcode":"70112",
    "addr:street":"Canal St",
    "iso:country":"US",
    "sg:address":"1020 Canal St",
    "sg:city":"New Orleans",
    "sg:classifiers":[
        {
            "category":"Shopping",
            "subcategory":"Clothing, Apparel, & Fashions",
            "type":"Retail Goods"
        }
    ],
    "sg:phone":"+1 504 412 8382",
    "sg:postcode":"70112",
    "sg:province":"LA",
    "wof:name":"New York Connections",
    "wof:placetype":"venue"
},
  "geometry": {"coordinates":[-90.072647,29.955357],"type":"Point"}
}