{
  "type": "Feature",
  "properties": {
    "iso:country":"US",
    "sg:address":"3656 Government St",
    "sg:city":"Alexandria",
    "sg:classifiers":[
        {
            "category":"Home & Garden",
            "subcategory":"Building Materials",
            "type":"Retail Goods"
        }
    ],
    "sg:phone":"+1 318 484 9175",
    "sg:postcode":"71302",
    "sg:province":"LA",
    "sg:tags":[
        "door"
    ],
    "wof:name":"Younger Enterprises",
    "wof:placetype":"venue"
},
  "geometry": {"coordinates":[-92.44653599999999,31.266155],"type":"Point"}
}