{
  "type": "Feature",
  "properties": {
    "addr:full":"6000 Cleveland Pl Metairie LA 70003",
    "addr:housenumber":"6000",
    "addr:postcode":"70003",
    "addr:street":"Cleveland Pl",
    "iso:country":"US",
    "sg:address":"6000 Cleveland Pl",
    "sg:city":"Metairie",
    "sg:classifiers":[
        {
            "category":"Recreation",
            "type":"Entertainment"
        }
    ],
    "sg:phone":"+1 504 885 4738",
    "sg:postcode":"70003",
    "sg:province":"LA",
    "sg:tags":[
        "tennis",
        "court"
    ],
    "wof:name":"Beach Club Tennis & Fitness",
    "wof:placetype":"venue"
},
  "geometry": {"coordinates":[-90.214676,30.030558],"type":"Point"}
}