{
  "type": "Feature",
  "properties": {
    "iso:country":"US",
    "sg:address":"5810 Main St",
    "sg:city":"Zachary",
    "sg:classifiers":[
        {
            "category":"Professional",
            "subcategory":"Accounting & Tax Preparation",
            "type":"Services"
        }
    ],
    "sg:phone":"+1 225 658 8821",
    "sg:postcode":"70791",
    "sg:province":"LA",
    "sg:tags":[
        "return",
        "filing"
    ],
    "wof:name":"H & R Block Tax Svc",
    "wof:placetype":"venue"
},
  "geometry": {"coordinates":[-91.141139,30.649187],"type":"Point"}
}