{
  "type": "Feature",
  "properties": {
    "iso:country":"US",
    "sg:address":"3209 Cleary Ave",
    "sg:city":"Metairie",
    "sg:classifiers":[
        {
            "category":"Personal",
            "subcategory":"Beauty Salon",
            "type":"Services"
        }
    ],
    "sg:phone":"+1 504 888 4955",
    "sg:postcode":"70002",
    "sg:province":"LA",
    "sg:tags":[
        "shop",
        "manicuring"
    ],
    "wof:name":"Nails By Tina",
    "wof:placetype":"venue"
},
  "geometry": {"coordinates":[-90.172337,30.004001],"type":"Point"}
}