{
  "type": "Feature",
  "properties": {
    "addr:full":"2475 Canal St New Orleans LA 70119",
    "addr:housenumber":"2475",
    "addr:postcode":"70119",
    "addr:street":"Canal St",
    "iso:country":"US",
    "sg:address":"2475 Canal St",
    "sg:city":"New Orleans",
    "sg:classifiers":[
        {
            "category":"Organizations",
            "subcategory":"Labor Organization",
            "type":"Services"
        }
    ],
    "sg:phone":"+1 504 822 3500",
    "sg:postcode":"70119",
    "sg:province":"LA",
    "wof:name":"Communications Workers-America",
    "wof:placetype":"venue"
},
  "geometry": {"coordinates":[-90.08420599999999,29.963543],"type":"Point"}
}