{
  "type": "Feature",
  "properties": {
    "addr:full":"233 Industrial Pkwy Lafayette LA 70508",
    "addr:housenumber":"233",
    "addr:postcode":"70508",
    "addr:street":"Industrial Pkwy",
    "iso:country":"US",
    "sg:address":"233 Industrial Pkwy",
    "sg:city":"Lafayette",
    "sg:classifiers":[
        {
            "category":"Wholesale",
            "subcategory":"Machinery & Supplies",
            "type":"Manufacturing & Wholesale Goods"
        }
    ],
    "sg:phone":"+1 337 593 9999",
    "sg:postcode":"70508",
    "sg:province":"LA",
    "sg:tags":[
        "equipment",
        "industrial"
    ],
    "wof:name":"M M Industries",
    "wof:placetype":"venue"
},
  "geometry": {"coordinates":[-92.002464,30.186695],"type":"Point"}
}