{
  "type": "Feature",
  "properties": {
    "iso:country":"US",
    "sg:address":"973 Brannon Rd",
    "sg:city":"Pineville",
    "sg:classifiers":[
        {
            "category":"Building & Trades",
            "subcategory":"Construction",
            "type":"Services"
        }
    ],
    "sg:phone":"+1 318 443 1946",
    "sg:postcode":"71360",
    "sg:province":"LA",
    "sg:tags":[
        "hanging",
        "contractor"
    ],
    "wof:name":"Allstar Painting",
    "wof:placetype":"venue"
},
  "geometry": {"coordinates":[-92.32521300000001,31.25666],"type":"Point"}
}