{
  "type": "Feature",
  "properties": {
    "iso:country":"US",
    "sg:address":"309 S Shattuck St",
    "sg:city":"Lake Charles",
    "sg:classifiers":[
        {
            "category":"Organizations",
            "subcategory":"Community Association",
            "type":"Services"
        }
    ],
    "sg:phone":"+1 337 436 0270",
    "sg:postcode":"70601",
    "sg:province":"LA",
    "sg:tags":[
        "club"
    ],
    "wof:name":"Bear's Social Club",
    "wof:placetype":"venue"
},
  "geometry": {"coordinates":[-93.197068,30.23529],"type":"Point"}
}