{
  "type": "Feature",
  "properties": {
    "iso:country":"US",
    "sg:address":"3723 Veterans Memorial Blvd",
    "sg:city":"Metairie",
    "sg:classifiers":[
        {
            "category":"Autos & Motor Vehicles",
            "subcategory":"Automobile Sales",
            "type":"Retail Goods"
        }
    ],
    "sg:phone":"+1 504 456 3723",
    "sg:postcode":"70006",
    "sg:province":"LA",
    "sg:tags":[
        "car",
        "dealer"
    ],
    "wof:name":"Porsche Audi Of New Orleans",
    "wof:placetype":"venue"
},
  "geometry": {"coordinates":[-90.16703699999999,30.004216],"type":"Point"}
}