{
  "type": "Feature",
  "properties": {
    "iso:country":"US",
    "sg:address":"507 Washington St",
    "sg:city":"West Monroe",
    "sg:classifiers":[
        {
            "category":"Bars & Pubs",
            "type":"Food & Drink"
        }
    ],
    "sg:phone":"+1 318 699 0433",
    "sg:postcode":"71292",
    "sg:province":"LA",
    "sg:tags":[
        "lounge",
        "cocktail"
    ],
    "wof:name":"J & B Lounge",
    "wof:placetype":"venue"
},
  "geometry": {"coordinates":[-92.175636,32.4772],"type":"Point"}
}