{
  "type": "Feature",
  "properties": {
    "addr:full":"424 N Columbia St Covington LA 70433",
    "addr:housenumber":"424",
    "addr:postcode":"70433",
    "addr:street":"N",
    "iso:country":"US",
    "sg:address":"424 N Columbia St",
    "sg:city":"Covington",
    "sg:classifiers":[
        {
            "category":"Personal",
            "subcategory":"Tattoo Parlor",
            "type":"Services"
        }
    ],
    "sg:phone":"+1 985 871 1077",
    "sg:postcode":"70433",
    "sg:province":"LA",
    "sg:tags":[
        "tattooing"
    ],
    "wof:name":"Covington Ink",
    "wof:placetype":"venue"
},
  "geometry": {"coordinates":[-90.094578,30.477051],"type":"Point"}
}