{
  "type": "Feature",
  "properties": {
    "iso:country":"US",
    "sg:address":"3036 Brakley Dr",
    "sg:city":"Baton Rouge",
    "sg:classifiers":[
        {
            "category":"Professional",
            "subcategory":"Business Services",
            "type":"Services"
        }
    ],
    "sg:phone":"+1 225 295 1684",
    "sg:postcode":"70816",
    "sg:province":"LA",
    "sg:tags":[
        "program",
        "incentive"
    ],
    "wof:name":"O C Tanner Co",
    "wof:placetype":"venue"
},
  "geometry": {"coordinates":[-91.05023799999999,30.424734],"type":"Point"}
}