{
  "type": "Feature",
  "properties": {
    "addr:full":"2801 Loyola Dr Kenner LA 70062",
    "addr:housenumber":"2801",
    "addr:postcode":"70062",
    "addr:street":"Loyola Dr",
    "iso:country":"US",
    "sg:address":"2801 Loyola Dr",
    "sg:city":"Kenner",
    "sg:classifiers":[
        {
            "category":"Banks & Credit Unions",
            "subcategory":"Bank",
            "type":"Services"
        }
    ],
    "sg:phone":"+1 504 466 1100",
    "sg:postcode":"70062",
    "sg:province":"LA",
    "sg:tags":[
        "financing"
    ],
    "wof:name":"Sun Finance Co",
    "wof:placetype":"venue"
},
  "geometry": {"coordinates":[-90.26602800000001,30.007368],"type":"Point"}
}