{
  "type": "Feature",
  "properties": {
    "iso:country":"US",
    "sg:address":"3428 Greenwood Rd",
    "sg:city":"Shreveport",
    "sg:classifiers":[
        {
            "category":"Autos & Motor Vehicles",
            "subcategory":"Auto Supplies",
            "type":"Retail Goods"
        }
    ],
    "sg:phone":"+1 318 635 5849",
    "sg:postcode":"71109",
    "sg:province":"LA",
    "sg:tags":[
        "automobile",
        "parts"
    ],
    "sg:website":"www.autozone.com",
    "wof:name":"Autozone",
    "wof:placetype":"venue"
},
  "geometry": {"coordinates":[-93.79382699999999,32.476963],"type":"Point"}
}