{
  "type": "Feature",
  "properties": {
    "iso:country":"US",
    "sg:address":"13826 Marlin Ave",
    "sg:city":"Baton Rouge",
    "sg:classifiers":[
        {
            "category":"Wholesale",
            "subcategory":"Motor Vehicles",
            "type":"Manufacturing & Wholesale Goods"
        }
    ],
    "sg:phone":"+1 225 261 5143",
    "sg:postcode":"70818",
    "sg:province":"LA",
    "wof:name":"Gill Communications",
    "wof:placetype":"venue"
},
  "geometry": {"coordinates":[-91.037609,30.545075],"type":"Point"}
}