{
  "type": "Feature",
  "properties": {
    "iso:country":"US",
    "sg:address":"4625 Main St",
    "sg:city":"Zachary",
    "sg:classifiers":[
        {
            "category":"Shopping",
            "subcategory":"Florist",
            "type":"Retail Goods"
        },
        {
            "category":"Home & Garden",
            "subcategory":"Garden Supply",
            "type":"Retail Goods"
        }
    ],
    "sg:phone":"+1 225 654 3969",
    "sg:postcode":"70791",
    "sg:province":"LA",
    "sg:tags":[
        "nurseryman"
    ],
    "wof:name":"Kim's Potted Plants",
    "wof:placetype":"venue"
},
  "geometry": {"coordinates":[-91.15512099999999,30.648422],"type":"Point"}
}