{
  "type": "Feature",
  "properties": {
    "iso:country":"US",
    "sg:address":"285 W Esplanade Ave",
    "sg:city":"Kenner",
    "sg:classifiers":[
        {
            "category":"Mining & Drilling",
            "type":"Manufacturing & Wholesale Goods"
        }
    ],
    "sg:phone":"+1 504 467 5100",
    "sg:postcode":"70065",
    "sg:province":"LA",
    "sg:tags":[
        "field",
        "oil"
    ],
    "sg:website":"www.crescentdrilling.com",
    "wof:name":"Crescent Drilling & Production",
    "wof:placetype":"venue"
},
  "geometry": {"coordinates":[-90.270084,30.022819],"type":"Point"}
}