{
  "type": "Feature",
  "properties": {
    "iso:country":"US",
    "sg:address":"311 Barrow St",
    "sg:city":"Morgan City",
    "sg:classifiers":[
        {
            "category":"Government",
            "subcategory":"Office",
            "type":"Public Place"
        }
    ],
    "sg:phone":"+1 985 385 2600",
    "sg:postcode":"70380",
    "sg:province":"LA",
    "wof:name":"St Mary Civilian Defense Ofc",
    "wof:placetype":"venue"
},
  "geometry": {"coordinates":[-91.205196,29.692519],"type":"Point"}
}