{
  "type": "Feature",
  "properties": {
    "iso:country":"US",
    "sg:address":"510 N Washington St",
    "sg:city":"Bastrop",
    "sg:classifiers":[
        {
            "category":"Government",
            "subcategory":"Office",
            "type":"Public Place"
        }
    ],
    "sg:phone":"+1 318 283 0842",
    "sg:postcode":"71220",
    "sg:province":"LA",
    "sg:tags":[
        "state",
        "program"
    ],
    "wof:name":"Public Safety Dept",
    "wof:placetype":"venue"
},
  "geometry": {"coordinates":[-91.914098,32.782555],"type":"Point"}
}