{
  "type": "Feature",
  "properties": {
    "iso:country":"US",
    "sg:address":"22325 Greenwell Springs Rd",
    "sg:city":"Greenwell Spgs",
    "sg:classifiers":[
        {
            "category":"Organizations",
            "subcategory":"Religious Organization",
            "type":"Services"
        }
    ],
    "sg:phone":"+1 225 261 3088",
    "sg:postcode":"70739",
    "sg:province":"LA",
    "sg:tags":[
        "church"
    ],
    "wof:name":"Covenant Community Church",
    "wof:placetype":"venue"
},
  "geometry": {"coordinates":[-90.98976399999999,30.569615],"type":"Point"}
}