{
  "type": "Feature",
  "properties": {
    "addr:full":"37292 State Rte 942 Darrow LA 70725",
    "addr:housenumber":"37292",
    "addr:postcode":"70725",
    "addr:street":"State Rte 942 Darrow",
    "iso:country":"US",
    "sg:address":"37292 State Rte 942",
    "sg:city":"Darrow",
    "sg:classifiers":[
        {
            "category":"Freight",
            "type":"Transportation"
        },
        {
            "category":"Building & Trades",
            "subcategory":"Construction",
            "type":"Services"
        }
    ],
    "sg:phone":"+1 225 473 0740",
    "sg:postcode":"70725",
    "sg:province":"LA",
    "sg:tags":[
        "house",
        "ship",
        "line",
        "mooring"
    ],
    "wof:name":"Cooper T Smith Mooring",
    "wof:placetype":"venue"
},
  "geometry": {"coordinates":[-90.973963,30.115971],"type":"Point"}
}