{
  "type": "Feature",
  "properties": {
    "iso:country":"US",
    "sg:address":"1305 Lemaire St",
    "sg:city":"New Iberia",
    "sg:classifiers":[
        {
            "category":"Retail",
            "subcategory":"Auto Repair",
            "type":"Services"
        }
    ],
    "sg:phone":"+1 337 364 6977",
    "sg:postcode":"70560",
    "sg:province":"LA",
    "sg:tags":[
        "repairing",
        "automobile"
    ],
    "wof:name":"Master Mechanics",
    "wof:placetype":"venue"
},
  "geometry": {"coordinates":[-91.804778,29.993089],"type":"Point"}
}