{
  "type": "Feature",
  "properties": {
    "iso:country":"US",
    "sg:address":"518 Mockingbird Ln",
    "sg:city":"Shreveport",
    "sg:classifiers":[
        {
            "category":"Travel",
            "subcategory":"Travel Agent",
            "type":"Entertainment"
        }
    ],
    "sg:phone":"+1 318 868 9097",
    "sg:postcode":"71105",
    "sg:province":"LA",
    "sg:tags":[
        "agency",
        "bureau"
    ],
    "wof:name":"Affordable Escapes",
    "wof:placetype":"venue"
},
  "geometry": {"coordinates":[-93.701972,32.455288],"type":"Point"}
}