{
  "type": "Feature",
  "properties": {
    "iso:country":"US",
    "sg:address":"110 Smith Ave",
    "sg:city":"Monroe",
    "sg:classifiers":[
        {
            "category":"Personal",
            "subcategory":"Beauty Salon",
            "type":"Services"
        }
    ],
    "sg:phone":"+1 318 343 9905",
    "sg:postcode":"71203",
    "sg:province":"LA",
    "wof:name":"Creatove Images",
    "wof:placetype":"venue"
},
  "geometry": {"coordinates":[-92.078579,32.521875],"type":"Point"}
}