{
  "type": "Feature",
  "properties": {
    "addr:full":"9310 Normandie Dr Ste 2 Shreveport LA 71118",
    "addr:housenumber":"9310",
    "addr:postcode":"71118",
    "addr:street":"Normandie Dr Ste 2",
    "iso:country":"US",
    "sg:address":"9310 Normandie Dr Ste 2",
    "sg:city":"Shreveport",
    "sg:classifiers":[
        {
            "category":"Government",
            "subcategory":"Office",
            "type":"Public Place"
        }
    ],
    "sg:phone":"+1 318 676 5857",
    "sg:postcode":"71118",
    "sg:province":"LA",
    "sg:tags":[
        "government-united",
        "state"
    ],
    "sg:website":"http://www.fpjdc.org",
    "wof:name":"Motor Vehicle Office",
    "wof:placetype":"venue"
},
  "geometry": {"coordinates":[-93.806574,32.396281],"type":"Point"}
}