{
  "type": "Feature",
  "properties": {
    "addr:full":"128 Breckenridge Loop Lafayette LA 70506",
    "addr:housenumber":"128",
    "addr:postcode":"70506",
    "addr:street":"Breckenridge Loop",
    "iso:country":"US",
    "sg:address":"128 Breckenridge Loop",
    "sg:city":"Lafayette",
    "sg:classifiers":[
        {
            "category":"Shopping",
            "subcategory":"Florist",
            "type":"Retail Goods"
        }
    ],
    "sg:phone":"+1 337 837 2807",
    "sg:postcode":"70506",
    "sg:province":"LA",
    "wof:name":"Beautiful Blooms",
    "wof:placetype":"venue"
},
  "geometry": {"coordinates":[-92.098499,30.213116],"type":"Point"}
}