{
  "type": "Feature",
  "properties": {
    "iso:country":"US",
    "sg:address":"1241 Tricou St",
    "sg:city":"New Orleans",
    "sg:classifiers":[
        {
            "category":"Shopping",
            "subcategory":"Clothing, Apparel, & Fashions",
            "type":"Retail Goods"
        }
    ],
    "sg:phone":"+1 504 277 9130",
    "sg:postcode":"70117",
    "sg:province":"LA",
    "wof:name":"Deszirees Portable Boutique",
    "wof:placetype":"venue"
},
  "geometry": {"coordinates":[-90.008353,29.96058],"type":"Point"}
}