{
  "type": "Feature",
  "properties": {
    "iso:country":"US",
    "sg:address":"1494 S Cities Service Hwy",
    "sg:city":"Sulphur",
    "sg:classifiers":[
        {
            "category":"Building & Trades",
            "subcategory":"Construction",
            "type":"Services"
        }
    ],
    "sg:phone":"+1 337 625 3855",
    "sg:postcode":"70663",
    "sg:province":"LA",
    "sg:tags":[
        "general",
        "contractor"
    ],
    "wof:name":"F D Shay Contractor Inc",
    "wof:placetype":"venue"
},
  "geometry": {"coordinates":[-93.32542599999999,30.225832],"type":"Point"}
}