{
  "type": "Feature",
  "properties": {
    "iso:country":"US",
    "sg:address":"307 Polly Ln",
    "sg:city":"Lafayette",
    "sg:classifiers":[
        {
            "category":"Building & Trades",
            "subcategory":"Construction",
            "type":"Services"
        }
    ],
    "sg:phone":"+1 337 988 6949",
    "sg:postcode":"70508",
    "sg:province":"LA",
    "sg:tags":[
        "contractor"
    ],
    "wof:name":"Citadel Builders LLC",
    "wof:placetype":"venue"
},
  "geometry": {"coordinates":[-92.021964,30.172297],"type":"Point"}
}