{
  "type": "Feature",
  "properties": {
    "iso:country":"US",
    "sg:address":"203 Rue Louis Xiv",
    "sg:city":"Lafayette",
    "sg:classifiers":[
        {
            "category":"Health Services",
            "subcategory":"Doctor",
            "type":"Services"
        }
    ],
    "sg:phone":"+1 337 981 8294",
    "sg:postcode":"70508",
    "sg:province":"LA",
    "sg:tags":[
        "physician",
        "surgeon"
    ],
    "wof:name":"Ricardo Leoni MD",
    "wof:placetype":"venue"
},
  "geometry": {"coordinates":[-92.024854,30.168611],"type":"Point"}
}