{
  "type": "Feature",
  "properties": {
    "addr:full":"224 Saint Landry St Lafayette LA 70506",
    "addr:housenumber":"224",
    "addr:postcode":"70506",
    "addr:street":"Saint Landry St",
    "iso:country":"US",
    "sg:address":"224 Saint Landry St",
    "sg:city":"Lafayette",
    "sg:classifiers":[
        {
            "category":"Health Services",
            "subcategory":"Doctor",
            "type":"Services"
        }
    ],
    "sg:phone":"+1 337 235 4554",
    "sg:postcode":"70506",
    "sg:province":"LA",
    "sg:tags":[
        "physician",
        "surgeon"
    ],
    "wof:name":"Comprehensive Neurologic Ctr",
    "wof:placetype":"venue"
},
  "geometry": {"coordinates":[-92.025412,30.218797],"type":"Point"}
}