{
  "type": "Feature",
  "properties": {
    "addr:full":"431 Gravier St New Orleans LA 70130",
    "addr:housenumber":"431",
    "addr:postcode":"70130",
    "addr:street":"Gravier St",
    "iso:country":"US",
    "sg:address":"431 Gravier St",
    "sg:city":"New Orleans",
    "sg:classifiers":[
        {
            "category":"Professional",
            "subcategory":"Lawyer & Legal Services",
            "type":"Services"
        }
    ],
    "sg:phone":"+1 504 595 5000",
    "sg:postcode":"70130",
    "sg:province":"LA",
    "sg:tags":[
        "attorney",
        "bureau"
    ],
    "wof:name":"Evidence Management",
    "wof:placetype":"venue"
},
  "geometry": {"coordinates":[-90.06751800000001,29.950661],"type":"Point"}
}