{
  "type": "Feature",
  "properties": {
    "addr:full":"3609 Louisiana Ave Lake Charles LA 70607",
    "addr:housenumber":"3609",
    "addr:postcode":"70607",
    "addr:street":"Louisiana Ave",
    "iso:country":"US",
    "sg:address":"3609 Louisiana Ave",
    "sg:city":"Lake Charles",
    "sg:classifiers":[
        {
            "category":"Wholesale",
            "subcategory":"Machinery & Supplies",
            "type":"Manufacturing & Wholesale Goods"
        }
    ],
    "sg:phone":"+1 337 480 4009",
    "sg:postcode":"70607",
    "sg:province":"LA",
    "sg:tags":[
        "farm",
        "implement",
        "tractor"
    ],
    "wof:name":"Trinity Tractor Company LLC",
    "wof:placetype":"venue"
},
  "geometry": {"coordinates":[-93.205443,30.191308],"type":"Point"}
}