{
  "type": "Feature",
  "properties": {
    "addr:full":"1500 Prytania St New Orleans LA 70130",
    "addr:housenumber":"1500",
    "addr:postcode":"70130",
    "addr:street":"Prytania St",
    "iso:country":"US",
    "sg:address":"1500 Prytania St",
    "sg:city":"New Orleans",
    "sg:classifiers":[
        {
            "category":"Real Estate",
            "subcategory":"Real Estate Services",
            "type":"Services"
        }
    ],
    "sg:phone":"+1 504 581 9123",
    "sg:postcode":"70130",
    "sg:province":"LA",
    "sg:tags":[
        "company",
        "title"
    ],
    "wof:name":"A Automobile Title Change Svc",
    "wof:placetype":"venue"
},
  "geometry": {"coordinates":[-90.074578,29.937655],"type":"Point"}
}