{
  "type": "Feature",
  "properties": {
    "iso:country":"US",
    "sg:address":"2 Canal St",
    "sg:city":"New Orleans",
    "sg:classifiers":[
        {
            "category":"Professional",
            "subcategory":"Employment Agencies",
            "type":"Services"
        }
    ],
    "sg:phone":"+1 504 524 8574",
    "sg:postcode":"70130",
    "sg:province":"LA",
    "sg:tags":[
        "opportunity"
    ],
    "wof:name":"Topp Knotch Personnel Inc",
    "wof:placetype":"venue"
},
  "geometry": {"coordinates":[-90.064413,29.950375],"type":"Point"}
}