{
  "type": "Feature",
  "properties": {
    "iso:country":"US",
    "sg:address":"2626 Charles Dr",
    "sg:city":"Chalmette",
    "sg:classifiers":[
        {
            "category":"Manufacturing",
            "subcategory":"Jewelry",
            "type":"Manufacturing & Wholesale Goods"
        }
    ],
    "sg:phone":"+1 504 277 9221",
    "sg:postcode":"70043",
    "sg:province":"LA",
    "sg:tags":[
        "engraving",
        "on",
        "precious",
        "metal",
        "manufacturer"
    ],
    "wof:name":"Fine Line Engravers & Jewelers",
    "wof:placetype":"venue"
},
  "geometry": {"coordinates":[-89.94710000000001,29.938507],"type":"Point"}
}