{
  "type": "Feature",
  "properties": {
    "iso:country":"US",
    "sg:address":"4733 Chastant St",
    "sg:city":"Metairie",
    "sg:classifiers":[
        {
            "category":"Real Estate",
            "subcategory":"Real Estate Agent",
            "type":"Services"
        }
    ],
    "sg:phone":"+1 504 885 6043",
    "sg:postcode":"70006",
    "sg:province":"LA",
    "wof:name":"Olivier Family",
    "wof:placetype":"venue"
},
  "geometry": {"coordinates":[-90.201148,30.023844],"type":"Point"}
}