{
  "type": "Feature",
  "properties": {
    "iso:country":"US",
    "sg:address":"310 Ingleside Dr",
    "sg:city":"Baton Rouge",
    "sg:classifiers":[
        {
            "category":"Restaurant",
            "type":"Food & Drink"
        }
    ],
    "sg:phone":"+1 225 344 8797",
    "sg:postcode":"70806",
    "sg:province":"LA",
    "sg:tags":[
        "eating"
    ],
    "wof:name":"Affairs Catering",
    "wof:placetype":"venue"
},
  "geometry": {"coordinates":[-91.145478,30.44584],"type":"Point"}
}