{
  "type": "Feature",
  "properties": {
    "iso:country":"US",
    "sg:address":"4317 N University Ave",
    "sg:city":"Carencro",
    "sg:classifiers":[
        {
            "category":"Retail",
            "subcategory":"Auto Repair",
            "type":"Services"
        }
    ],
    "sg:phone":"+1 337 886 9509",
    "sg:postcode":"70520",
    "sg:province":"LA",
    "sg:tags":[
        "repairing",
        "automobile"
    ],
    "wof:name":"Carencro Automotive Ctr",
    "wof:placetype":"venue"
},
  "geometry": {"coordinates":[-92.049575,30.316455],"type":"Point"}
}