{
  "type": "Feature",
  "properties": {
    "addr:full":"104 13th St Forest Hill LA 71430",
    "addr:housenumber":"104",
    "addr:postcode":"71430",
    "addr:street":"13Th St",
    "iso:country":"US",
    "sg:address":"104 13th St",
    "sg:city":"Forest Hill",
    "sg:classifiers":[
        {
            "category":"Home & Garden",
            "subcategory":"Garden Supply",
            "type":"Retail Goods"
        }
    ],
    "sg:phone":"+1 318 748 6275",
    "sg:postcode":"71430",
    "sg:province":"LA",
    "sg:tags":[
        "nurseryman"
    ],
    "wof:name":"Forest Hill Nursery Farm",
    "wof:placetype":"venue"
},
  "geometry": {"coordinates":[-92.527964,31.040636],"type":"Point"}
}