{
  "type": "Feature",
  "properties": {
    "addr:full":"1720 W Prien Lake Rd Lake Charles LA 70601",
    "addr:housenumber":"1720",
    "addr:postcode":"70601",
    "addr:street":"W Prien Lake Rd",
    "iso:country":"US",
    "sg:address":"1720 W Prien Lake Rd",
    "sg:city":"Lake Charles",
    "sg:classifiers":[
        {
            "category":"Shopping",
            "subcategory":"Department Store",
            "type":"Retail Goods"
        }
    ],
    "sg:phone":"+1 337 474 2391",
    "sg:postcode":"70601",
    "sg:province":"LA",
    "wof:name":"Target",
    "wof:placetype":"venue"
},
  "geometry": {"coordinates":[-93.24677699999999,30.197665],"type":"Point"}
}