{
  "type": "Feature",
  "properties": {
    "iso:country":"US",
    "sg:address":"15730 River Rd",
    "sg:city":"Hahnville",
    "sg:classifiers":[
        {
            "category":"Freight",
            "type":"Transportation"
        }
    ],
    "sg:phone":"+1 985 783 6403",
    "sg:postcode":"70057",
    "sg:province":"LA",
    "sg:tags":[
        "terminal",
        "line",
        "barge"
    ],
    "wof:name":"Bayou Fleet Inc",
    "wof:placetype":"venue"
},
  "geometry": {"coordinates":[-90.41698599999999,29.988707],"type":"Point"}
}