{
  "type": "Feature",
  "properties": {
    "iso:country":"US",
    "sg:address":"8550 E Park Ave",
    "sg:city":"Houma",
    "sg:classifiers":[
        {
            "category":"Wholesale",
            "subcategory":"Electrical",
            "type":"Manufacturing & Wholesale Goods"
        }
    ],
    "sg:phone":"+1 985 872 0486",
    "sg:postcode":"70363",
    "sg:province":"LA",
    "sg:tags":[
        "electric",
        "motor"
    ],
    "wof:name":"Gulf South Armature Inc",
    "wof:placetype":"venue"
},
  "geometry": {"coordinates":[-90.648368,29.568294],"type":"Point"}
}