{
  "type": "Feature",
  "properties": {
    "iso:country":"US",
    "sg:address":"201 Frost Ln",
    "sg:city":"Mandeville",
    "sg:classifiers":[
        {
            "category":"Banks & Credit Unions",
            "subcategory":"Bank",
            "type":"Services"
        }
    ],
    "sg:phone":"+1 985 674 2589",
    "sg:postcode":"70448",
    "sg:province":"LA",
    "wof:name":"Resource Bank",
    "wof:placetype":"venue"
},
  "geometry": {"coordinates":[-90.061286,30.384718],"type":"Point"}
}