{
  "type": "Feature",
  "properties": {
    "iso:country":"US",
    "sg:address":"1435 E Laurel Ave",
    "sg:city":"Eunice",
    "sg:classifiers":[
        {
            "category":"Retail",
            "subcategory":"Auto Repair",
            "type":"Services"
        }
    ],
    "sg:phone":"+1 337 457 5315",
    "sg:postcode":"70535",
    "sg:province":"LA",
    "sg:tags":[
        "body",
        "automobile",
        "painting"
    ],
    "wof:name":"Mark's Paint & Body Shop",
    "wof:placetype":"venue"
},
  "geometry": {"coordinates":[-92.39621099999999,30.494838],"type":"Point"}
}