{
  "type": "Feature",
  "properties": {
    "iso:country":"US",
    "sg:address":"23010 US Hwy 190",
    "sg:city":"Robert",
    "sg:classifiers":[
        {
            "category":"Shopping",
            "subcategory":"Discount & Variety Stores",
            "type":"Retail Goods"
        }
    ],
    "sg:phone":"+1 985 345 3307",
    "sg:postcode":"70455",
    "sg:province":"LA",
    "sg:tags":[
        "merchandise",
        "general"
    ],
    "wof:name":"Robert Trade Mart Inc",
    "wof:placetype":"venue"
},
  "geometry": {"coordinates":[-90.34136700000001,30.505734],"type":"Point"}
}