{
  "type": "Feature",
  "properties": {
    "iso:country":"US",
    "sg:address":"500 N Cortez St",
    "sg:city":"New Orleans",
    "sg:classifiers":[
        {
            "category":"Wholesale",
            "subcategory":"Machinery & Supplies",
            "type":"Manufacturing & Wholesale Goods"
        }
    ],
    "sg:phone":"+1 504 486 6263",
    "sg:postcode":"70119",
    "sg:province":"LA",
    "sg:tags":[
        "ship",
        "chandler"
    ],
    "sg:website":"www.davestreiffer.com",
    "wof:name":"Dave Streiffer Co",
    "wof:placetype":"venue"
},
  "geometry": {"coordinates":[-90.09410699999999,29.976419],"type":"Point"}
}