{
  "type": "Feature",
  "properties": {
    "iso:country":"US",
    "sg:address":"110 Terry Pkwy",
    "sg:city":"Terrytown",
    "sg:classifiers":[
        {
            "category":"Home & Garden",
            "subcategory":"Furniture",
            "type":"Retail Goods"
        }
    ],
    "sg:phone":"+1 504 227 8332",
    "sg:postcode":"70056",
    "sg:province":"LA",
    "sg:tags":[
        "bedding",
        "store"
    ],
    "sg:website":"www.beddingplusmattress.com",
    "wof:name":"Bedding Plus",
    "wof:placetype":"venue"
},
  "geometry": {"coordinates":[-90.03531599999999,29.921696],"type":"Point"}
}