{
  "type": "Feature",
  "properties": {
    "iso:country":"US",
    "sg:address":"110 E Saint Peter St",
    "sg:city":"Carencro",
    "sg:classifiers":[
        {
            "category":"Cinema",
            "subcategory":"Movie Rental",
            "type":"Entertainment"
        }
    ],
    "sg:phone":"+1 337 896 8273",
    "sg:postcode":"70520",
    "sg:province":"LA",
    "sg:tags":[
        "game",
        "video"
    ],
    "sg:website":"www.moviegallery.com",
    "wof:name":"Movie Gallery",
    "wof:placetype":"venue"
},
  "geometry": {"coordinates":[-92.049408,30.317535],"type":"Point"}
}