{
  "type": "Feature",
  "properties": {
    "addr:full":"3112 State Rte 315 Theriot LA 70397",
    "addr:housenumber":"3112",
    "addr:postcode":"70397",
    "addr:street":"State Rte 315 Theriot",
    "iso:country":"US",
    "sg:address":"3112 State Rte 315",
    "sg:city":"Theriot",
    "sg:classifiers":[
        {
            "category":"Shopping",
            "subcategory":"Department Store",
            "type":"Retail Goods"
        }
    ],
    "sg:phone":"+1 985 223 5778",
    "sg:postcode":"70397",
    "sg:province":"LA",
    "sg:tags":[
        "shop"
    ],
    "wof:name":"Dollar General",
    "wof:placetype":"venue"
},
  "geometry": {"coordinates":[-90.834733,29.343163],"type":"Point"}
}