{
  "type": "Feature",
  "properties": {
    "iso:country":"US",
    "sg:address":"1800 Irving Pl",
    "sg:city":"Shreveport",
    "sg:classifiers":[
        {
            "category":"Wholesale",
            "subcategory":"Durable Goods & Equipment",
            "type":"Manufacturing & Wholesale Goods"
        }
    ],
    "sg:phone":"+1 318 425 4096",
    "sg:postcode":"71101",
    "sg:province":"LA",
    "sg:tags":[
        "exporter"
    ],
    "wof:name":"Promise Specialty Hospital",
    "wof:placetype":"venue"
},
  "geometry": {"coordinates":[-93.74449799999999,32.493592],"type":"Point"}
}