{
  "type": "Feature",
  "properties": {
    "iso:country":"US",
    "sg:address":"2926 Jackson Ave",
    "sg:city":"New Orleans",
    "sg:classifiers":[
        {
            "category":"Organizations",
            "subcategory":"Religious Organization",
            "type":"Services"
        }
    ],
    "sg:phone":"+1 504 524 5976",
    "sg:postcode":"70125",
    "sg:province":"LA",
    "sg:tags":[
        "church"
    ],
    "wof:name":"St Thomas Missionary Bapt Chr",
    "wof:placetype":"venue"
},
  "geometry": {"coordinates":[-90.090727,29.945729],"type":"Point"}
}