{
  "type": "Feature",
  "properties": {
    "iso:country":"US",
    "sg:address":"4004 S Bamboo Dr",
    "sg:city":"Harvey",
    "sg:classifiers":[
        {
            "category":"Retail",
            "subcategory":"Repair Shop",
            "type":"Services"
        }
    ],
    "sg:phone":"+1 504 263 8552",
    "sg:postcode":"70058",
    "sg:province":"LA",
    "sg:tags":[
        "welding"
    ],
    "wof:name":"Kenneth Smith Welding Svc",
    "wof:placetype":"venue"
},
  "geometry": {"coordinates":[-90.04471700000001,29.849347],"type":"Point"}
}