{
  "type": "Feature",
  "properties": {
    "addr:full":"3180 Watts Rd Lake Charles LA 70611",
    "addr:housenumber":"3180",
    "addr:postcode":"70611",
    "addr:street":"Watts Rd",
    "iso:country":"US",
    "sg:address":"3180 Watts Rd",
    "sg:city":"Lake Charles",
    "sg:classifiers":[
        {
            "category":"Retail",
            "subcategory":"Repair Shop",
            "type":"Services"
        }
    ],
    "sg:phone":"+1 337 855 1218",
    "sg:postcode":"70611",
    "sg:province":"LA",
    "wof:name":"Kiln Repair",
    "wof:placetype":"venue"
},
  "geometry": {"coordinates":[-93.278785,30.355149],"type":"Point"}
}