{
  "type": "Feature",
  "properties": {
    "addr:full":"160 Grambling Ct Westwego LA 70094",
    "addr:housenumber":"160",
    "addr:postcode":"70094",
    "addr:street":"Grambling Ct",
    "iso:country":"US",
    "sg:address":"160 Grambling Ct",
    "sg:city":"Westwego",
    "sg:classifiers":[
        {
            "category":"Professional",
            "subcategory":"Computer Services",
            "type":"Services"
        }
    ],
    "sg:phone":"+1 504 436 8422",
    "sg:postcode":"70094",
    "sg:province":"LA",
    "sg:tags":[
        "related"
    ],
    "wof:name":"Keith Batieste Cmpt Consulting",
    "wof:placetype":"venue"
},
  "geometry": {"coordinates":[-90.216611,29.913821],"type":"Point"}
}