{
  "type": "Feature",
  "properties": {
    "iso:country":"US",
    "sg:address":"13259 Broadway St",
    "sg:city":"Folsom",
    "sg:classifiers":[
        {
            "category":"Manufacturing",
            "subcategory":"Signs",
            "type":"Manufacturing & Wholesale Goods"
        }
    ],
    "sg:phone":"+1 985 796 3718",
    "sg:postcode":"70437",
    "sg:province":"LA",
    "wof:name":"Folsom Computer & Graphics",
    "wof:placetype":"venue"
},
  "geometry": {"coordinates":[-90.18659599999999,30.629441],"type":"Point"}
}