{
  "type": "Feature",
  "properties": {
    "iso:country":"US",
    "sg:address":"910 1st Ave",
    "sg:city":"Sulphur",
    "sg:classifiers":[
        {
            "category":"Health Services",
            "subcategory":"Doctor",
            "type":"Services"
        }
    ],
    "sg:phone":"+1 337 527 6752",
    "sg:postcode":"70663",
    "sg:province":"LA",
    "sg:tags":[
        "dentist"
    ],
    "wof:name":"Alpha Denture Clinic",
    "wof:placetype":"venue"
},
  "geometry": {"coordinates":[-93.36842900000001,30.231898],"type":"Point"}
}