{
  "type": "Feature",
  "properties": {
    "iso:country":"US",
    "sg:address":"210 W Napoleon St",
    "sg:city":"Sulphur",
    "sg:classifiers":[
        {
            "category":"Retail",
            "subcategory":"Car Wash",
            "type":"Services"
        }
    ],
    "sg:phone":"+1 337 527 3677",
    "sg:postcode":"70663",
    "sg:province":"LA",
    "sg:tags":[
        "automobile",
        "detail",
        "clean"
    ],
    "wof:name":"Brimestone Auto Detail",
    "wof:placetype":"venue"
},
  "geometry": {"coordinates":[-93.379532,30.23667],"type":"Point"}
}