{
  "type": "Feature",
  "properties": {
    "addr:full":"219 Burt Blvd Benton LA 71006",
    "addr:housenumber":"219",
    "addr:postcode":"71006",
    "addr:street":"Burt Blvd",
    "iso:country":"US",
    "sg:address":"219 Burt Blvd",
    "sg:city":"Benton",
    "sg:classifiers":[
        {
            "category":"Restaurant",
            "type":"Food & Drink"
        }
    ],
    "sg:menulink":"http://www.allmenus.com/la/benton/201495-sonic/menu/",
    "sg:phone":"+1 318 965 5480",
    "sg:postcode":"71006",
    "sg:province":"LA",
    "sg:tags":[
        "burger",
        "american"
    ],
    "wof:name":"Sonic",
    "wof:placetype":"venue"
},
  "geometry": {"coordinates":[-93.741585,32.679402],"type":"Point"}
}