{
  "type": "Feature",
  "properties": {
    "addr:full":"5936 US Hwy 167 Winnfield LA 71483",
    "addr:housenumber":"5936",
    "addr:postcode":"71483",
    "addr:street":"Us Hwy 167 Winnfield",
    "iso:country":"US",
    "sg:address":"5936 US Hwy 167",
    "sg:city":"Winnfield",
    "sg:classifiers":[
        {
            "category":"Shopping",
            "subcategory":"Department Store",
            "type":"Retail Goods"
        }
    ],
    "sg:phone":"+1 318 648 0572",
    "sg:postcode":"71483",
    "sg:province":"LA",
    "sg:tags":[
        "shop"
    ],
    "wof:name":"Dollar General",
    "wof:placetype":"venue"
},
  "geometry": {"coordinates":[-92.653448,31.935352],"type":"Point"}
}