{
  "type": "Feature",
  "properties": {
    "iso:country":"US",
    "sg:address":"1340 State Rte 316",
    "sg:city":"Houma",
    "sg:classifiers":[
        {
            "category":"Professional",
            "subcategory":"Lawyer & Legal Services",
            "type":"Services"
        }
    ],
    "sg:phone":"+1 985 868 4480",
    "sg:postcode":"70364",
    "sg:province":"LA",
    "sg:tags":[
        "attorney"
    ],
    "wof:name":"Harrington & Myers",
    "wof:placetype":"venue"
},
  "geometry": {"coordinates":[-90.66924299999999,29.62482],"type":"Point"}
}