{
  "type": "Feature",
  "properties": {
    "iso:country":"US",
    "sg:address":"1608 Carol Sue Ave",
    "sg:city":"Gretna",
    "sg:classifiers":[
        {
            "category":"Organizations",
            "subcategory":"Religious Organization",
            "type":"Services"
        }
    ],
    "sg:phone":"+1 504 393 7700",
    "sg:postcode":"70056",
    "sg:province":"LA",
    "wof:name":"Friendship House",
    "wof:placetype":"venue"
},
  "geometry": {"coordinates":[-90.041285,29.8998],"type":"Point"}
}