{
  "type": "Feature",
  "properties": {
    "iso:country":"US",
    "sg:address":"1663 Soniat St",
    "sg:city":"New Orleans",
    "sg:classifiers":[
        {
            "category":"Professional",
            "subcategory":"Business Services",
            "type":"Services"
        }
    ],
    "sg:phone":"+1 504 891 0123",
    "sg:postcode":"70115",
    "sg:province":"LA",
    "sg:tags":[
        "interior",
        "consultant",
        "designer",
        "design",
        "decorator"
    ],
    "sg:website":"www.designershowrooms.net",
    "wof:name":"Taylor Susan Interiors",
    "wof:placetype":"venue"
},
  "geometry": {"coordinates":[-90.10953499999999,29.928919],"type":"Point"}
}