{
  "type": "Feature",
  "properties": {
    "addr:full":"1512 Graceland Ave Abbeville LA 70510",
    "addr:housenumber":"1512",
    "addr:postcode":"70510",
    "addr:street":"Graceland Ave",
    "iso:country":"US",
    "sg:address":"1512 Graceland Ave",
    "sg:city":"Abbeville",
    "sg:classifiers":[
        {
            "category":"Personal",
            "subcategory":"Barber",
            "type":"Services"
        }
    ],
    "sg:phone":"+1 337 898 2008",
    "sg:postcode":"70510",
    "sg:province":"LA",
    "wof:name":"Cut Barber Shop",
    "wof:placetype":"venue"
},
  "geometry": {"coordinates":[-92.12039799999999,29.979119],"type":"Point"}
}