{
  "type": "Feature",
  "properties": {
    "addr:full":"11411 Lake Charles Hwy Leesville LA 71446",
    "addr:housenumber":"11411",
    "addr:postcode":"71446",
    "addr:street":"Lake Charles Hwy",
    "iso:country":"US",
    "sg:address":"11411 Lake Charles Hwy",
    "sg:city":"Leesville",
    "sg:classifiers":[
        {
            "category":"Autos & Motor Vehicles",
            "subcategory":"Auto Supplies",
            "type":"Retail Goods"
        }
    ],
    "sg:phone":"+1 337 392 0039",
    "sg:postcode":"71446",
    "sg:province":"LA",
    "wof:name":"B & R Windshield & Tire Repair",
    "wof:placetype":"venue"
},
  "geometry": {"coordinates":[-93.27030000000001,31.031836],"type":"Point"}
}