{
  "type": "Feature",
  "properties": {
    "iso:country":"US",
    "sg:address":"911 Paola St",
    "sg:city":"Baker",
    "sg:classifiers":[
        {
            "category":"Manufacturing",
            "subcategory":"Wood Products",
            "type":"Manufacturing & Wholesale Goods"
        }
    ],
    "sg:phone":"+1 225 654 2584",
    "sg:postcode":"70714",
    "sg:province":"LA",
    "wof:name":"Maxs Cajun Paddles & Swings",
    "wof:placetype":"venue"
},
  "geometry": {"coordinates":[-91.134339,30.581499],"type":"Point"}
}