{
  "type": "Feature",
  "properties": {
    "iso:country":"US",
    "sg:address":"3212 Sharon St",
    "sg:city":"Houma",
    "sg:classifiers":[
        {
            "category":"Recreation",
            "type":"Entertainment"
        }
    ],
    "sg:phone":"+1 985 879 1017",
    "sg:postcode":"70363",
    "sg:province":"LA",
    "wof:name":"Koonpop Charter Boat Service",
    "wof:placetype":"venue"
},
  "geometry": {"coordinates":[-90.67970699999999,29.592551],"type":"Point"}
}