{
  "type": "Feature",
  "properties": {
    "iso:country":"US",
    "sg:address":"6911 Cameron St",
    "sg:city":"Duson",
    "sg:classifiers":[
        {
            "category":"Health Services",
            "subcategory":"Doctor",
            "type":"Services"
        }
    ],
    "sg:phone":"+1 337 873 7463",
    "sg:postcode":"70529",
    "sg:province":"LA",
    "sg:tags":[
        "clinic"
    ],
    "wof:name":"Medical Waste Svc Of America",
    "wof:placetype":"venue"
},
  "geometry": {"coordinates":[-92.12211000000001,30.234843],"type":"Point"}
}