{
  "type": "Feature",
  "properties": {
    "iso:country":"US",
    "sg:address":"700 Macarthur Dr",
    "sg:city":"Alexandria",
    "sg:classifiers":[
        {
            "category":"Travel",
            "subcategory":"Hotels & Motels",
            "type":"Entertainment"
        }
    ],
    "sg:phone":"+1 318 445 6541",
    "sg:postcode":"71303",
    "sg:province":"LA",
    "wof:name":"Super 8 Motel",
    "wof:placetype":"venue"
},
  "geometry": {"coordinates":[-92.47846800000001,31.294208],"type":"Point"}
}