{
  "type": "Feature",
  "properties": {
    "iso:country":"US",
    "sg:address":"501 Desiard St",
    "sg:city":"Monroe",
    "sg:classifiers":[
        {
            "category":"Home & Garden",
            "subcategory":"Furniture",
            "type":"Retail Goods"
        }
    ],
    "sg:phone":"+1 318 387 2300",
    "sg:postcode":"71201",
    "sg:province":"LA",
    "wof:name":"Ivan Smith Furniture",
    "wof:placetype":"venue"
},
  "geometry": {"coordinates":[-92.113051,32.504491],"type":"Point"}
}