{
  "type": "Feature",
  "properties": {
    "iso:country":"US",
    "sg:address":"118 N Hollywood Rd",
    "sg:city":"Houma",
    "sg:classifiers":[
        {
            "category":"Wholesale",
            "subcategory":"Auto Parts",
            "type":"Manufacturing & Wholesale Goods"
        }
    ],
    "sg:phone":"+1 985 876 0672",
    "sg:postcode":"70364",
    "sg:province":"LA",
    "sg:tags":[
        "automobile",
        "supply"
    ],
    "wof:name":"Bergeron Auto Parts",
    "wof:placetype":"venue"
},
  "geometry": {"coordinates":[-90.735282,29.609244],"type":"Point"}
}