{
  "type": "Feature",
  "properties": {
    "iso:country":"US",
    "sg:address":"74576 N Lewiston Rd",
    "sg:city":"Kentwood",
    "sg:classifiers":[
        {
            "category":"Organizations",
            "subcategory":"Religious Organization",
            "type":"Services"
        }
    ],
    "sg:phone":"+1 985 229 7818",
    "sg:postcode":"70444",
    "sg:province":"LA",
    "wof:name":"Lewiston Baptist Church",
    "wof:placetype":"venue"
},
  "geometry": {"coordinates":[-90.42234500000001,30.941385],"type":"Point"}
}