{
  "type": "Feature",
  "properties": {
    "iso:country":"US",
    "sg:address":"105 Herren Ln",
    "sg:city":"Homer",
    "sg:classifiers":[
        {
            "category":"Manufacturing",
            "subcategory":"Tools & Machinery",
            "type":"Manufacturing & Wholesale Goods"
        }
    ],
    "sg:phone":"+1 318 927 3628",
    "sg:postcode":"71040",
    "sg:province":"LA",
    "sg:tags":[
        "mfg"
    ],
    "wof:name":"Hall Boat Lift",
    "wof:placetype":"venue"
},
  "geometry": {"coordinates":[-92.93689000000001,32.734341],"type":"Point"}
}