{
  "type": "Feature",
  "properties": {
    "iso:country":"US",
    "sg:address":"2700 Ambassador Caffery Pkwy",
    "sg:city":"Lafayette",
    "sg:classifiers":[
        {
            "category":"Real Estate",
            "subcategory":"Real Estate Operator",
            "type":"Services"
        }
    ],
    "sg:phone":"+1 337 984 7861",
    "sg:postcode":"70506",
    "sg:province":"LA",
    "sg:tags":[
        "apartment"
    ],
    "wof:name":"Diamond Lake Apartments",
    "wof:placetype":"venue"
},
  "geometry": {"coordinates":[-92.07529100000001,30.200216],"type":"Point"}
}