{
  "type": "Feature",
  "properties": {
    "iso:country":"US",
    "sg:address":"28805 Intracoastal Rd",
    "sg:city":"Plaquemine",
    "sg:classifiers":[
        {
            "category":"Marine",
            "type":"Transportation"
        }
    ],
    "sg:phone":"+1 225 659 2631",
    "sg:postcode":"70764",
    "sg:province":"LA",
    "sg:tags":[
        "towing"
    ],
    "wof:name":"Businelle Towing Corp",
    "wof:placetype":"venue"
},
  "geometry": {"coordinates":[-91.31604799999999,30.233288],"type":"Point"}
}