{
  "type": "Feature",
  "properties": {
    "iso:country":"US",
    "sg:address":"2621 Delaware Ave",
    "sg:city":"Kenner",
    "sg:classifiers":[
        {
            "category":"Wholesale",
            "subcategory":"Construction Materials",
            "type":"Manufacturing & Wholesale Goods"
        }
    ],
    "sg:phone":"+1 504 465 9570",
    "sg:postcode":"70062",
    "sg:province":"LA",
    "sg:tags":[
        "door"
    ],
    "wof:name":"B & M Metal Doors & Frames Inc",
    "wof:placetype":"venue"
},
  "geometry": {"coordinates":[-90.24273100000001,30.004795],"type":"Point"}
}