{
  "type": "Feature",
  "properties": {
    "iso:country":"US",
    "sg:address":"325 E 58th St",
    "sg:city":"Cut Off",
    "sg:classifiers":[
        {
            "category":"Building & Trades",
            "subcategory":"Construction",
            "type":"Services"
        }
    ],
    "sg:phone":"+1 985 632 8739",
    "sg:postcode":"70345",
    "sg:province":"LA",
    "sg:tags":[
        "hanging",
        "contractor"
    ],
    "wof:name":"Tims House Painting & Washing",
    "wof:placetype":"venue"
},
  "geometry": {"coordinates":[-90.32224600000001,29.510589],"type":"Point"}
}