{
  "type": "Feature",
  "properties": {
    "iso:country":"US",
    "sg:address":"127 Belle Terre Blvd",
    "sg:city":"La Place",
    "sg:classifiers":[
        {
            "category":"Banks & Credit Unions",
            "subcategory":"Bank",
            "type":"Services"
        }
    ],
    "sg:phone":"+1 985 652 2781",
    "sg:postcode":"70068",
    "sg:province":"LA",
    "sg:tags":[
        "cashing",
        "check"
    ],
    "wof:name":"Advance America",
    "wof:placetype":"venue"
},
  "geometry": {"coordinates":[-90.50089,30.074249],"type":"Point"}
}