{
  "type": "Feature",
  "properties": {
    "iso:country":"US",
    "sg:address":"820 Jordan St",
    "sg:city":"Shreveport",
    "sg:classifiers":[
        {
            "category":"Real Estate",
            "subcategory":"Real Estate Operator",
            "type":"Services"
        }
    ],
    "sg:phone":"+1 318 424 2502",
    "sg:postcode":"71101",
    "sg:province":"LA",
    "sg:tags":[
        "building",
        "parks"
    ],
    "wof:name":"820 Jordan Partnership",
    "wof:placetype":"venue"
},
  "geometry": {"coordinates":[-93.74635000000001,32.498226],"type":"Point"}
}