{
  "type": "Feature",
  "properties": {
    "addr:full":"15021 Crystal Dr Pride LA 70770",
    "addr:housenumber":"15021",
    "addr:postcode":"70770",
    "addr:street":"Crystal Dr Pride",
    "iso:country":"US",
    "sg:address":"15021 Crystal Dr",
    "sg:city":"Pride",
    "sg:classifiers":[
        {
            "category":"Building & Trades",
            "subcategory":"Plumbing",
            "type":"Services"
        }
    ],
    "sg:phone":"+1 225 261 8020",
    "sg:postcode":"70770",
    "sg:province":"LA",
    "sg:tags":[
        "conditioning",
        "air",
        "system",
        "contractor"
    ],
    "wof:name":"Magee Inc",
    "wof:placetype":"venue"
},
  "geometry": {"coordinates":[-91.020123,30.583988],"type":"Point"}
}