{
  "type": "Feature",
  "properties": {
    "iso:country":"US",
    "sg:address":"515 Ayo St",
    "sg:city":"Raceland",
    "sg:classifiers":[
        {
            "category":"Manufacturing",
            "subcategory":"Tools & Machinery",
            "type":"Manufacturing & Wholesale Goods"
        }
    ],
    "sg:phone":"+1 985 851 4471",
    "sg:postcode":"70394",
    "sg:province":"LA",
    "sg:tags":[
        "gage"
    ],
    "wof:name":"Hy-Tech Instruments Inc",
    "wof:placetype":"venue"
},
  "geometry": {"coordinates":[-90.609565,29.717283],"type":"Point"}
}