{
  "type": "Feature",
  "properties": {
    "addr:full":"203 E Oak St Amite LA 70422",
    "addr:housenumber":"203",
    "addr:postcode":"70422",
    "addr:street":"E Oak St",
    "iso:country":"US",
    "sg:address":"203 E Oak St",
    "sg:city":"Amite",
    "sg:classifiers":[
        {
            "category":"Health Services",
            "subcategory":"Doctor",
            "type":"Services"
        }
    ],
    "sg:phone":"+1 985 345 0050",
    "sg:postcode":"70422",
    "sg:province":"LA",
    "sg:tags":[
        "physician",
        "surgeon"
    ],
    "wof:name":"Eye Physicians & Surgeons Inc",
    "wof:placetype":"venue"
},
  "geometry": {"coordinates":[-90.50680199999999,30.726757],"type":"Point"}
}