{
  "type": "Feature",
  "properties": {
    "iso:country":"US",
    "sg:address":"104 Fremaux Ave",
    "sg:city":"Slidell",
    "sg:classifiers":[
        {
            "category":"Professional",
            "subcategory":"Computer Services",
            "type":"Services"
        }
    ],
    "sg:phone":"+1 985 645 8651",
    "sg:postcode":"70458",
    "sg:province":"LA",
    "sg:tags":[
        "consultant",
        "designer"
    ],
    "wof:name":"Garcia Technologies",
    "wof:placetype":"venue"
},
  "geometry": {"coordinates":[-89.782617,30.277618],"type":"Point"}
}