{
  "type": "Feature",
  "properties": {
    "addr:full":"507 Bayou Dr Tallulah LA 71282",
    "addr:housenumber":"507",
    "addr:postcode":"71282",
    "addr:street":"Bayou Dr",
    "iso:country":"US",
    "sg:address":"507 Bayou Dr",
    "sg:city":"Tallulah",
    "sg:classifiers":[
        {
            "category":"Education",
            "subcategory":"School",
            "type":"Public Place"
        }
    ],
    "sg:phone":"+1 318 574 1563",
    "sg:postcode":"71282",
    "sg:province":"LA",
    "wof:name":"Tallulah Jr High School",
    "wof:placetype":"venue"
},
  "geometry": {"coordinates":[-91.190566,32.404524],"type":"Point"}
}