{
  "type": "Feature",
  "properties": {
    "iso:country":"US",
    "sg:address":"2736 Opelousas St",
    "sg:city":"Lake Charles",
    "sg:classifiers":[
        {
            "category":"Professional",
            "subcategory":"Management & Consulting",
            "type":"Services"
        }
    ],
    "sg:phone":"+1 337 436 5676",
    "sg:postcode":"70615",
    "sg:province":"LA",
    "sg:tags":[
        "property",
        "maintenance"
    ],
    "wof:name":"C Morrow Tractor Service",
    "wof:placetype":"venue"
},
  "geometry": {"coordinates":[-93.175926,30.242242],"type":"Point"}
}