{
  "type": "Feature",
  "properties": {
    "iso:country":"US",
    "sg:address":"10500 Hayne Blvd",
    "sg:city":"New Orleans",
    "sg:classifiers":[
        {
            "category":"Personal",
            "subcategory":"Beauty Salon",
            "type":"Services"
        }
    ],
    "sg:phone":"+1 504 244 3221",
    "sg:postcode":"70127",
    "sg:province":"LA",
    "wof:name":"Sassy Sensual Salon",
    "wof:placetype":"venue"
},
  "geometry": {"coordinates":[-89.980734,30.050881],"type":"Point"}
}