{
  "type": "Feature",
  "properties": {
    "addr:full":"707 Ludwig St Farmerville LA 71241",
    "addr:housenumber":"707",
    "addr:postcode":"71241",
    "addr:street":"Ludwig St",
    "iso:country":"US",
    "sg:address":"707 Ludwig St",
    "sg:city":"Farmerville",
    "sg:classifiers":[
        {
            "category":"Manufacturing",
            "subcategory":"Signs",
            "type":"Manufacturing & Wholesale Goods"
        }
    ],
    "sg:phone":"+1 318 368 2075",
    "sg:postcode":"71241",
    "sg:province":"LA",
    "sg:tags":[
        "specialty",
        "mfg"
    ],
    "wof:name":"Signs By Rex D West",
    "wof:placetype":"venue"
},
  "geometry": {"coordinates":[-92.400379,32.780566],"type":"Point"}
}