{
  "type": "Feature",
  "properties": {
    "iso:country":"US",
    "sg:address":"1748 Delasalle Dr",
    "sg:city":"New Iberia",
    "sg:classifiers":[
        {
            "category":"Retail",
            "subcategory":"Auto Repair",
            "type":"Services"
        }
    ],
    "sg:phone":"+1 337 365 1140",
    "sg:postcode":"70560",
    "sg:province":"LA",
    "sg:tags":[
        "machine",
        "automobile",
        "shop"
    ],
    "wof:name":"Dugas Engine Svc",
    "wof:placetype":"venue"
},
  "geometry": {"coordinates":[-91.837451,29.987081],"type":"Point"}
}