{
  "type": "Feature",
  "properties": {
    "iso:country":"US",
    "sg:address":"1935 Choctaw Dr",
    "sg:city":"Baton Rouge",
    "sg:classifiers":[
        {
            "category":"Restaurant",
            "type":"Food & Drink"
        }
    ],
    "sg:phone":"+1 225 355 1980",
    "sg:postcode":"70805",
    "sg:province":"LA",
    "wof:name":"C & C Cafe",
    "wof:placetype":"venue"
},
  "geometry": {"coordinates":[-91.16945699999999,30.469891],"type":"Point"}
}