{
  "type": "Feature",
  "properties": {
    "iso:country":"US",
    "sg:address":"258 S Cherry Ave",
    "sg:city":"Gramercy",
    "sg:classifiers":[
        {
            "category":"Personal",
            "subcategory":"Beauty Salon",
            "type":"Services"
        }
    ],
    "sg:phone":"+1 225 869 1966",
    "sg:postcode":"70052",
    "sg:province":"LA",
    "wof:name":"Keedy's",
    "wof:placetype":"venue"
},
  "geometry": {"coordinates":[-90.685773,30.047377],"type":"Point"}
}