{
  "type": "Feature",
  "properties": {
    "iso:country":"US",
    "sg:address":"631 Main St",
    "sg:city":"Baton Rouge",
    "sg:classifiers":[
        {
            "category":"Freight",
            "type":"Transportation"
        }
    ],
    "sg:phone":"+1 225 925 5656",
    "sg:postcode":"70801",
    "sg:province":"LA",
    "sg:tags":[
        "mover"
    ],
    "sg:website":"www.relocationcenter.com",
    "wof:name":"Relocation Center",
    "wof:placetype":"venue"
},
  "geometry": {"coordinates":[-91.183879,30.451634],"type":"Point"}
}