{
  "type": "Feature",
  "properties": {
    "iso:country":"US",
    "sg:address":"1726 Prytania St",
    "sg:city":"New Orleans",
    "sg:classifiers":[
        {
            "category":"Travel",
            "subcategory":"Hotels & Motels",
            "type":"Entertainment"
        }
    ],
    "sg:phone":"+1 504 581 4540",
    "sg:postcode":"70130",
    "sg:province":"LA",
    "wof:name":"Parisian Courtyard Inn",
    "wof:placetype":"venue"
},
  "geometry": {"coordinates":[-90.076193,29.935421],"type":"Point"}
}