{
  "type": "Feature",
  "properties": {
    "iso:country":"US",
    "sg:address":"800 Decatur St",
    "sg:city":"New Orleans",
    "sg:classifiers":[
        {
            "category":"Coffee & Tea",
            "type":"Food & Drink"
        },
        {
            "category":"Donuts",
            "subcategory":"None",
            "type":"Food & Drink"
        }
    ],
    "sg:phone":"+1 504 525 4544",
    "sg:postcode":"70116",
    "sg:province":"LA",
    "sg:website":"www.cafedumonde.com",
    "wof:name":"Caf? Du Monde",
    "wof:placetype":"venue"
},
  "geometry": {"coordinates":[-90.062013,29.957549],"type":"Point"}
}