{
  "type": "Feature",
  "properties": {
    "addr:full":"3160 Sweet Gum Dr Harvey LA 70058",
    "addr:housenumber":"3160",
    "addr:postcode":"70058",
    "addr:street":"Sweet Gum Dr",
    "iso:country":"US",
    "sg:address":"3160 Sweet Gum Dr",
    "sg:city":"Harvey",
    "sg:classifiers":[
        {
            "category":"Building & Trades",
            "subcategory":"Landscaping Services",
            "type":"Services"
        }
    ],
    "sg:phone":"+1 504 340 6767",
    "sg:postcode":"70058",
    "sg:province":"LA",
    "wof:name":"Lawn Care +",
    "wof:placetype":"venue"
},
  "geometry": {"coordinates":[-90.068473,29.839374],"type":"Point"}
}