{
  "type": "Feature",
  "properties": {
    "iso:country":"US",
    "sg:address":"6750 Old Gentilly Rd",
    "sg:city":"New Orleans",
    "sg:classifiers":[
        {
            "category":"Freight",
            "type":"Transportation"
        }
    ],
    "sg:phone":"+1 504 245 2425",
    "sg:postcode":"70126",
    "sg:province":"LA",
    "sg:tags":[
        "trucking"
    ],
    "wof:name":"Arthur Rizzo Transport Inc",
    "wof:placetype":"venue"
},
  "geometry": {"coordinates":[-90.008858,30.009587],"type":"Point"}
}