{
  "type": "Feature",
  "properties": {
    "iso:country":"US",
    "sg:address":"10341 Parkview Dr",
    "sg:city":"Baton Rouge",
    "sg:classifiers":[
        {
            "category":"Shopping",
            "subcategory":"Computers & Home Electronics",
            "type":"Retail Goods"
        }
    ],
    "sg:phone":"+1 225 928 2400",
    "sg:postcode":"70815",
    "sg:province":"LA",
    "sg:tags":[
        "software"
    ],
    "wof:name":"Computer Ventures Inc",
    "wof:placetype":"venue"
},
  "geometry": {"coordinates":[-91.071403,30.445818],"type":"Point"}
}