{
  "type": "Feature",
  "properties": {
    "iso:country":"US",
    "sg:address":"102 Green Meadow Rd",
    "sg:city":"Lafayette",
    "sg:classifiers":[
        {
            "category":"Building & Trades",
            "subcategory":"Cleaning & Sanitation",
            "type":"Services"
        }
    ],
    "sg:phone":"+1 337 988 2873",
    "sg:postcode":"70503",
    "sg:province":"LA",
    "sg:tags":[
        "janitor"
    ],
    "wof:name":"Skip Perry Carpets",
    "wof:placetype":"venue"
},
  "geometry": {"coordinates":[-92.079973,30.152101],"type":"Point"}
}