{
  "type": "Feature",
  "properties": {
    "addr:full":"504 Cenla Dr Pineville LA 71360",
    "addr:housenumber":"504",
    "addr:postcode":"71360",
    "addr:street":"Cenla Dr",
    "iso:country":"US",
    "sg:address":"504 Cenla Dr",
    "sg:city":"Pineville",
    "sg:classifiers":[
        {
            "category":"Freight",
            "type":"Transportation"
        }
    ],
    "sg:phone":"+1 318 640 8896",
    "sg:postcode":"71360",
    "sg:province":"LA",
    "sg:tags":[
        "trucking"
    ],
    "sg:website":"www.fedex.com",
    "wof:name":"Fed Ex Freight",
    "wof:placetype":"venue"
},
  "geometry": {"coordinates":[-92.42466400000001,31.375408],"type":"Point"}
}