{
  "type": "Feature",
  "properties": {
    "iso:country":"US",
    "sg:address":"3544 Youree Dr",
    "sg:city":"Shreveport",
    "sg:classifiers":[
        {
            "category":"Shopping",
            "subcategory":"Gifts & Souvenirs",
            "type":"Retail Goods"
        }
    ],
    "sg:phone":"+1 318 869 2543",
    "sg:postcode":"71105",
    "sg:province":"LA",
    "sg:tags":[
        "shop"
    ],
    "wof:name":"Bungalow",
    "wof:placetype":"venue"
},
  "geometry": {"coordinates":[-93.722295,32.475467],"type":"Point"}
}