{
  "type": "Feature",
  "properties": {
    "iso:country":"US",
    "sg:address":"410 N Laurel St",
    "sg:city":"Winnfield",
    "sg:classifiers":[
        {
            "category":"Organizations",
            "subcategory":"Religious Organization",
            "type":"Services"
        }
    ],
    "sg:phone":"+1 318 628 1550",
    "sg:postcode":"71483",
    "sg:province":"LA",
    "sg:tags":[
        "church"
    ],
    "wof:name":"New Zion Outreach Ministires",
    "wof:placetype":"venue"
},
  "geometry": {"coordinates":[-92.636501,31.930396],"type":"Point"}
}