{
  "type": "Feature",
  "properties": {
    "iso:country":"US",
    "sg:address":"6511 Chippendale Dr",
    "sg:city":"Baton Rouge",
    "sg:classifiers":[
        {
            "category":"Wholesale",
            "subcategory":"Durable Goods & Equipment",
            "type":"Manufacturing & Wholesale Goods"
        }
    ],
    "sg:phone":"+1 225 751 2378",
    "sg:postcode":"70817",
    "sg:province":"LA",
    "sg:tags":[
        "representative",
        "manufacturer"
    ],
    "wof:name":"Best Business Forms & Supplies",
    "wof:placetype":"venue"
},
  "geometry": {"coordinates":[-91.024306,30.394332],"type":"Point"}
}