{
  "type": "Feature",
  "properties": {
    "iso:country":"US",
    "sg:address":"7401 Florida Blvd",
    "sg:city":"Baton Rouge",
    "sg:classifiers":[
        {
            "category":"Utilities",
            "subcategory":"Cable",
            "type":"Services"
        }
    ],
    "sg:phone":"+1 225 923 0860",
    "sg:postcode":"70806",
    "sg:province":"LA",
    "sg:tags":[
        "television"
    ],
    "sg:website":"www.dvd-register.com",
    "wof:name":"Cox Media",
    "wof:placetype":"venue"
},
  "geometry": {"coordinates":[-91.11363,30.451837],"type":"Point"}
}