{
  "type": "Feature",
  "properties": {
    "iso:country":"US",
    "sg:address":"61287 Vining Rd",
    "sg:city":"Amite",
    "sg:classifiers":[
        {
            "category":"Home & Garden",
            "subcategory":"Garden Supply",
            "type":"Retail Goods"
        }
    ],
    "sg:phone":"+1 985 748 8937",
    "sg:postcode":"70422",
    "sg:province":"LA",
    "wof:name":"Island Nursery Farm",
    "wof:placetype":"venue"
},
  "geometry": {"coordinates":[-90.41826,30.744199],"type":"Point"}
}