{
  "type": "Feature",
  "properties": {
    "addr:full":"14018 Katherine Ave Baton Rouge LA 70815",
    "addr:housenumber":"14018",
    "addr:postcode":"70815",
    "addr:street":"Katherine Ave",
    "iso:country":"US",
    "sg:address":"14018 Katherine Ave",
    "sg:city":"Baton Rouge",
    "sg:classifiers":[
        {
            "category":"Building & Trades",
            "subcategory":"Cleaning & Sanitation",
            "type":"Services"
        }
    ],
    "sg:phone":"+1 225 272 2626",
    "sg:postcode":"70815",
    "sg:province":"LA",
    "sg:tags":[
        "maintenance"
    ],
    "wof:name":"Cross Gate Services Inc",
    "wof:placetype":"venue"
},
  "geometry": {"coordinates":[-91.028651,30.456452],"type":"Point"}
}