{
  "type": "Feature",
  "properties": {
    "iso:country":"US",
    "sg:address":"2200 Saint Claude Ave",
    "sg:city":"New Orleans",
    "sg:classifiers":[
        {
            "category":"Shopping",
            "subcategory":"Shoes",
            "type":"Retail Goods"
        }
    ],
    "sg:phone":"+1 504 942 5086",
    "sg:postcode":"70117",
    "sg:province":"LA",
    "sg:tags":[
        "store"
    ],
    "sg:website":"www.theathletesfoot.com",
    "wof:name":"Athletes Foot the",
    "wof:placetype":"venue"
},
  "geometry": {"coordinates":[-90.056709,29.968423],"type":"Point"}
}