{
  "type": "Feature",
  "properties": {
    "addr:full":"7585 Westbank Expy Marrero LA 70072",
    "addr:housenumber":"7585",
    "addr:postcode":"70072",
    "addr:street":"Westbank Expy Marrero",
    "iso:country":"US",
    "sg:address":"7585 Westbank Expy",
    "sg:city":"Marrero",
    "sg:classifiers":[
        {
            "category":"Insurance",
            "subcategory":"Insurance Agent",
            "type":"Services"
        }
    ],
    "sg:phone":"+1 504 340 1004",
    "sg:postcode":"70072",
    "sg:province":"LA",
    "wof:name":"Direct General Ins Agency",
    "wof:placetype":"venue"
},
  "geometry": {"coordinates":[-90.13197,29.894654],"type":"Point"}
}