{
  "type": "Feature",
  "properties": {
    "iso:country":"US",
    "sg:address":"170 Autumn Dr",
    "sg:city":"Houma",
    "sg:classifiers":[
        {
            "category":"Professional",
            "subcategory":"Business Services",
            "type":"Services"
        }
    ],
    "sg:phone":"+1 985 872 1068",
    "sg:postcode":"70360",
    "sg:province":"LA",
    "wof:name":"Craig & Donna Enterprises Inc",
    "wof:placetype":"venue"
},
  "geometry": {"coordinates":[-90.74065400000001,29.584021],"type":"Point"}
}