{
  "type": "Feature",
  "properties": {
    "iso:country":"US",
    "sg:address":"3900 N Rampart St",
    "sg:city":"New Orleans",
    "sg:classifiers":[
        {
            "category":"Organizations",
            "subcategory":"Religious Organization",
            "type":"Services"
        }
    ],
    "sg:phone":"+1 504 943 6309",
    "sg:postcode":"70117",
    "sg:province":"LA",
    "wof:name":"Grace Baptist Church",
    "wof:placetype":"venue"
},
  "geometry": {"coordinates":[-90.03649900000001,29.9645],"type":"Point"}
}