{
  "type": "Feature",
  "properties": {
    "addr:full":"29292 Hwy 191 Many LA 71449",
    "addr:housenumber":"29292",
    "addr:postcode":"71449",
    "addr:street":"Hwy 191 Many",
    "iso:country":"US",
    "sg:address":"29292 Hwy 191",
    "sg:city":"Many",
    "sg:classifiers":[
        {
            "category":"Communications",
            "type":"Services"
        }
    ],
    "sg:phone":"+1 318 256 0097",
    "sg:postcode":"71449",
    "sg:province":"LA",
    "wof:name":"Southern Public Communications",
    "wof:placetype":"venue"
},
  "geometry": {"coordinates":[-93.652298,31.503743],"type":"Point"}
}