{
  "type": "Feature",
  "properties": {
    "iso:country":"US",
    "sg:address":"301 S Saint Charles St",
    "sg:city":"Abbeville",
    "sg:classifiers":[
        {
            "category":"Shopping",
            "subcategory":"Florist",
            "type":"Retail Goods"
        }
    ],
    "sg:phone":"+1 337 898 1557",
    "sg:postcode":"70510",
    "sg:province":"LA",
    "wof:name":"A Flower Cottage",
    "wof:placetype":"venue"
},
  "geometry": {"coordinates":[-92.135054,29.971735],"type":"Point"}
}