{
  "type": "Feature",
  "properties": {
    "iso:country":"US",
    "sg:address":"6554 Florida Blvd",
    "sg:city":"Baton Rouge",
    "sg:classifiers":[
        {
            "category":"Professional",
            "subcategory":"Business Services",
            "type":"Services"
        }
    ],
    "sg:phone":"+1 225 927 3188",
    "sg:postcode":"70806",
    "sg:province":"LA",
    "wof:name":"New Faces Agency",
    "wof:placetype":"venue"
},
  "geometry": {"coordinates":[-91.12469299999999,30.451317],"type":"Point"}
}