{
  "type": "Feature",
  "properties": {
    "iso:country":"US",
    "sg:address":"205 Choctaw Rd",
    "sg:city":"Lafayette",
    "sg:classifiers":[
        {
            "category":"Restaurant",
            "type":"Food & Drink"
        }
    ],
    "sg:phone":"+1 337 237 1677",
    "sg:postcode":"70501",
    "sg:province":"LA",
    "sg:tags":[
        "caterer"
    ],
    "wof:name":"Audrey's Catering Svc",
    "wof:placetype":"venue"
},
  "geometry": {"coordinates":[-91.987172,30.224121],"type":"Point"}
}