{
  "type": "Feature",
  "properties": {
    "iso:country":"US",
    "sg:address":"1229 Hwy 190 W",
    "sg:city":"Port Allen",
    "sg:classifiers":[
        {
            "category":"Manufacturing",
            "subcategory":"Wood Products",
            "type":"Manufacturing & Wholesale Goods"
        }
    ],
    "sg:phone":"+1 225 338 9247",
    "sg:postcode":"70767",
    "sg:province":"LA",
    "sg:tags":[
        "pallet",
        "skid"
    ],
    "wof:name":"Specialty Industrial Supplies",
    "wof:placetype":"venue"
},
  "geometry": {"coordinates":[-91.217679,30.505309],"type":"Point"}
}