{
  "type": "Feature",
  "properties": {
    "iso:country":"US",
    "sg:address":"4214 Scarborough Dr",
    "sg:city":"Baton Rouge",
    "sg:classifiers":[
        {
            "category":"Shopping",
            "subcategory":"Clothing, Apparel, & Fashions",
            "type":"Retail Goods"
        }
    ],
    "sg:phone":"+1 225 272 5030",
    "sg:postcode":"70814",
    "sg:province":"LA",
    "wof:name":"Men of Style",
    "wof:placetype":"venue"
},
  "geometry": {"coordinates":[-91.052184,30.488825],"type":"Point"}
}