{
  "type": "Feature",
  "properties": {
    "addr:full":"4551 Johnston St Lafayette LA 70503",
    "addr:housenumber":"4551",
    "addr:postcode":"70503",
    "addr:street":"Johnston St",
    "iso:country":"US",
    "sg:address":"4551 Johnston St",
    "sg:city":"Lafayette",
    "sg:classifiers":[
        {
            "category":"Wholesale",
            "subcategory":"Medical Equipment & Supplies",
            "type":"Manufacturing & Wholesale Goods"
        }
    ],
    "sg:phone":"+1 337 984 0123",
    "sg:postcode":"70503",
    "sg:province":"LA",
    "sg:tags":[
        "hospital"
    ],
    "wof:name":"Dynamic Care Home Medical Eqpt",
    "wof:placetype":"venue"
},
  "geometry": {"coordinates":[-92.05890100000001,30.193351],"type":"Point"}
}