{
  "type": "Feature",
  "properties": {
    "addr:full":"1100 Natchitoches St West Monroe LA 71291",
    "addr:housenumber":"1100",
    "addr:postcode":"71291",
    "addr:street":"Natchitoches St West",
    "iso:country":"US",
    "sg:address":"1100 Natchitoches St",
    "sg:city":"West Monroe",
    "sg:classifiers":[
        {
            "category":"Government",
            "subcategory":"Fire Station",
            "type":"Public Place"
        }
    ],
    "sg:phone":"+1 318 388 5114",
    "sg:postcode":"71291",
    "sg:province":"LA",
    "sg:tags":[
        "county",
        "protection"
    ],
    "wof:name":"Ouachita Parish Fire Dept",
    "wof:placetype":"venue"
},
  "geometry": {"coordinates":[-92.13225,32.496999],"type":"Point"}
}