{
  "type": "Feature",
  "properties": {
    "iso:country":"US",
    "sg:address":"8757 Bus Park Dr",
    "sg:city":"Shreveport",
    "sg:classifiers":[
        {
            "category":"Autos & Motor Vehicles",
            "subcategory":"Automobile Sales",
            "type":"Retail Goods"
        }
    ],
    "sg:phone":"+1 318 798 1600",
    "sg:postcode":"71105",
    "sg:province":"LA",
    "sg:tags":[
        "car",
        "dealer"
    ],
    "sg:website":"www.mikemorgan.com",
    "wof:name":"Morgan Pontiac GMC Buick",
    "wof:placetype":"venue"
},
  "geometry": {"coordinates":[-93.72467399999999,32.421369],"type":"Point"}
}