{
  "type": "Feature",
  "properties": {
    "addr:full":"27500 State Rte 441 Holden LA 70744",
    "addr:housenumber":"27500",
    "addr:postcode":"70744",
    "addr:street":"State Rte 441",
    "iso:country":"US",
    "sg:address":"27500 State Rte 441",
    "sg:city":"Holden",
    "sg:classifiers":[
        {
            "category":"Real Estate",
            "subcategory":"Real Estate Agent",
            "type":"Services"
        }
    ],
    "sg:phone":"+1 225 567 4723",
    "sg:postcode":"70744",
    "sg:province":"LA",
    "sg:tags":[
        "appraiser"
    ],
    "wof:name":"Wilder Appraisers",
    "wof:placetype":"venue"
},
  "geometry": {"coordinates":[-90.64274500000001,30.47045],"type":"Point"}
}