{
  "type": "Feature",
  "properties": {
    "addr:full":"2115 4th St Jonesville LA 71343",
    "addr:housenumber":"2115",
    "addr:postcode":"71343",
    "addr:street":"4Th St",
    "iso:country":"US",
    "sg:address":"2115 4th St",
    "sg:city":"Jonesville",
    "sg:classifiers":[
        {
            "category":"Home & Garden",
            "subcategory":"Building Materials",
            "type":"Retail Goods"
        }
    ],
    "sg:phone":"+1 318 339 7328",
    "sg:postcode":"71343",
    "sg:province":"LA",
    "sg:tags":[
        "mixed",
        "concrete"
    ],
    "wof:name":"Txi",
    "wof:placetype":"venue"
},
  "geometry": {"coordinates":[-91.83459999999999,31.62862],"type":"Point"}
}