{
  "type": "Feature",
  "properties": {
    "iso:country":"US",
    "sg:address":"1835 Bayou Dularge Rd",
    "sg:city":"Theriot",
    "sg:classifiers":[
        {
            "category":"Food & Beverages",
            "subcategory":"Groceries & Convenience Stores",
            "type":"Retail Goods"
        }
    ],
    "sg:phone":"+1 985 580 4455",
    "sg:postcode":"70397",
    "sg:province":"LA",
    "wof:name":"Tommy's Stop & Go",
    "wof:placetype":"venue"
},
  "geometry": {"coordinates":[-90.77634399999999,29.415622],"type":"Point"}
}