{
  "type": "Feature",
  "properties": {
    "addr:full":"5909 Common St Lake Charles LA 70607",
    "addr:housenumber":"5909",
    "addr:postcode":"70607",
    "addr:street":"Common St",
    "iso:country":"US",
    "sg:address":"5909 Common St",
    "sg:city":"Lake Charles",
    "sg:classifiers":[
        {
            "category":"Retail",
            "subcategory":"Auto Repair",
            "type":"Services"
        }
    ],
    "sg:phone":"+1 337 479 1700",
    "sg:postcode":"70607",
    "sg:province":"LA",
    "sg:tags":[
        "repairing",
        "automobile"
    ],
    "wof:name":"Auto Center",
    "wof:placetype":"venue"
},
  "geometry": {"coordinates":[-93.213689,30.153489],"type":"Point"}
}