{
  "type": "Feature",
  "properties": {
    "iso:country":"US",
    "sg:address":"120 191st St",
    "sg:city":"Galliano",
    "sg:classifiers":[
        {
            "category":"Professional",
            "subcategory":"Art Services",
            "type":"Services"
        }
    ],
    "sg:phone":"+1 985 475 7272",
    "sg:postcode":"70354",
    "sg:province":"LA",
    "sg:tags":[
        "photography",
        "commercial"
    ],
    "wof:name":"Fun Fotos",
    "wof:placetype":"venue"
},
  "geometry": {"coordinates":[-90.291895,29.422791],"type":"Point"}
}