{
  "type": "Feature",
  "properties": {
    "iso:country":"US",
    "sg:address":"1981 Hwy 114",
    "sg:city":"Hessmer",
    "sg:classifiers":[
        {
            "category":"Organizations",
            "subcategory":"Religious Organization",
            "type":"Services"
        }
    ],
    "sg:phone":"+1 318 563 4533",
    "sg:postcode":"71341",
    "sg:province":"LA",
    "sg:tags":[
        "church"
    ],
    "wof:name":"St Martin Of Tours Cath Church",
    "wof:placetype":"venue"
},
  "geometry": {"coordinates":[-92.17819,31.073146],"type":"Point"}
}