{
  "type": "Feature",
  "properties": {
    "iso:country":"US",
    "sg:address":"11059 Burgess Ave",
    "sg:city":"Denham Springs",
    "sg:classifiers":[
        {
            "category":"Building & Trades",
            "subcategory":"Construction",
            "type":"Services"
        }
    ],
    "sg:phone":"+1 225 665 5697",
    "sg:postcode":"70726",
    "sg:province":"LA",
    "sg:tags":[
        "contractor"
    ],
    "wof:name":"G & J Maintenance",
    "wof:placetype":"venue"
},
  "geometry": {"coordinates":[-90.90212,30.48694],"type":"Point"}
}