{
  "type": "Feature",
  "properties": {
    "addr:full":"4073 Clay Cut Rd Baton Rouge LA 70806",
    "addr:housenumber":"4073",
    "addr:postcode":"70806",
    "addr:street":"Clay Cut Rd",
    "iso:country":"US",
    "sg:address":"4073 Clay Cut Rd",
    "sg:city":"Baton Rouge",
    "sg:classifiers":[
        {
            "category":"Real Estate",
            "subcategory":"Real Estate Agent",
            "type":"Services"
        }
    ],
    "sg:phone":"+1 225 387 8684",
    "sg:postcode":"70806",
    "sg:province":"LA",
    "wof:name":"ASA Properties LTD Ptr",
    "wof:placetype":"venue"
},
  "geometry": {"coordinates":[-91.14814,30.440206],"type":"Point"}
}