{
  "type": "Feature",
  "properties": {
    "iso:country":"US",
    "sg:address":"206 E Reynolds Dr",
    "sg:city":"Ruston",
    "sg:classifiers":[
        {
            "category":"Professional",
            "subcategory":"Accounting & Tax Preparation",
            "type":"Services"
        }
    ],
    "sg:phone":"+1 318 251 2196",
    "sg:postcode":"71270",
    "sg:province":"LA",
    "sg:tags":[
        "accountant"
    ],
    "wof:name":"William D Edwards CPA",
    "wof:placetype":"venue"
},
  "geometry": {"coordinates":[-92.635137,32.543797],"type":"Point"}
}