{
  "type": "Feature",
  "properties": {
    "addr:full":"2020 N Causeway Blvd Mandeville LA 70471",
    "addr:housenumber":"2020",
    "addr:postcode":"70471",
    "addr:street":"N Causeway Blvd",
    "iso:country":"US",
    "sg:address":"2020 N Causeway Blvd",
    "sg:city":"Mandeville",
    "sg:classifiers":[
        {
            "category":"Banks & Credit Unions",
            "subcategory":"Bank",
            "type":"Services"
        }
    ],
    "sg:phone":"+1 985 624 3515",
    "sg:postcode":"70471",
    "sg:province":"LA",
    "sg:tags":[
        "loan",
        "real estate"
    ],
    "wof:name":"Fontainebleu Mortgage",
    "wof:placetype":"venue"
},
  "geometry": {"coordinates":[-90.090552,30.384363],"type":"Point"}
}