{
  "type": "Feature",
  "properties": {
    "iso:country":"US",
    "sg:address":"8539 Sharee Pl",
    "sg:city":"Denham Springs",
    "sg:classifiers":[
        {
            "category":"Professional",
            "subcategory":"Management & Consulting",
            "type":"Services"
        }
    ],
    "sg:phone":"+1 225 667 4971",
    "sg:postcode":"70726",
    "sg:province":"LA",
    "sg:tags":[
        "consultant",
        "training"
    ],
    "wof:name":"Hazardous Materials Training",
    "wof:placetype":"venue"
},
  "geometry": {"coordinates":[-90.942902,30.526175],"type":"Point"}
}