{
  "type": "Feature",
  "properties": {
    "iso:country":"US",
    "sg:address":"4428 David Dr",
    "sg:city":"Metairie",
    "sg:classifiers":[
        {
            "category":"Social Services",
            "subcategory":"Child Care",
            "type":"Services"
        }
    ],
    "sg:phone":"+1 504 887 5040",
    "sg:postcode":"70003",
    "sg:province":"LA",
    "wof:name":"Bright Beginnings Child Dev",
    "wof:placetype":"venue"
},
  "geometry": {"coordinates":[-90.22438,30.015006],"type":"Point"}
}