{
  "type": "Feature",
  "properties": {
    "iso:country":"US",
    "sg:address":"402 Ave B",
    "sg:city":"Bogalusa",
    "sg:classifiers":[
        {
            "category":"Banks & Credit Unions",
            "subcategory":"Bank",
            "type":"Services"
        }
    ],
    "sg:phone":"+1 985 732 5050",
    "sg:postcode":"70427",
    "sg:province":"LA",
    "wof:name":"Resource Bank",
    "wof:placetype":"venue"
},
  "geometry": {"coordinates":[-89.86605,30.778949],"type":"Point"}
}