{
  "type": "Feature",
  "properties": {
    "addr:full":"6272 Chris St Bastrop LA 71220",
    "addr:housenumber":"6272",
    "addr:postcode":"71220",
    "addr:street":"Chris St",
    "iso:country":"US",
    "sg:address":"6272 Chris St",
    "sg:city":"Bastrop",
    "sg:classifiers":[
        {
            "category":"Building & Trades",
            "subcategory":"Landscaping Services",
            "type":"Services"
        }
    ],
    "sg:phone":"+1 318 281 7594",
    "sg:postcode":"71220",
    "sg:province":"LA",
    "wof:name":"Martin Lawn Service",
    "wof:placetype":"venue"
},
  "geometry": {"coordinates":[-91.88514000000001,32.833732],"type":"Point"}
}