{
  "type": "Feature",
  "properties": {
    "iso:country":"US",
    "sg:address":"921 S Lewis St",
    "sg:city":"New Iberia",
    "sg:classifiers":[
        {
            "category":"Health Services",
            "subcategory":"Optometrist",
            "type":"Services"
        }
    ],
    "sg:phone":"+1 337 365 7219",
    "sg:postcode":"70560",
    "sg:province":"LA",
    "wof:name":"Iberia Vision Ctr",
    "wof:placetype":"venue"
},
  "geometry": {"coordinates":[-91.811786,29.992105],"type":"Point"}
}