{
  "type": "Feature",
  "properties": {
    "iso:country":"US",
    "sg:address":"310 Main St",
    "sg:city":"Pineville",
    "sg:classifiers":[
        {
            "category":"Shopping",
            "subcategory":"Stationery & Office Supplies",
            "type":"Retail Goods"
        }
    ],
    "sg:phone":"+1 318 484 9339",
    "sg:postcode":"71360",
    "sg:province":"LA",
    "wof:name":"Toner Time",
    "wof:placetype":"venue"
},
  "geometry": {"coordinates":[-92.439379,31.316788],"type":"Point"}
}