{
  "type": "Feature",
  "properties": {
    "iso:country":"US",
    "sg:address":"518 S Broad St",
    "sg:city":"New Orleans",
    "sg:classifiers":[
        {
            "category":"Wholesale",
            "subcategory":"Electrical",
            "type":"Manufacturing & Wholesale Goods"
        }
    ],
    "sg:phone":"+1 504 822 0751",
    "sg:postcode":"70119",
    "sg:province":"LA",
    "sg:tags":[
        "equipment",
        "electric",
        "supply"
    ],
    "wof:name":"Nu Lite Electrical",
    "wof:placetype":"venue"
},
  "geometry": {"coordinates":[-90.090687,29.96152],"type":"Point"}
}