{
  "type": "Feature",
  "properties": {
    "iso:country":"US",
    "sg:address":"3805 Pontchartrain Dr",
    "sg:city":"Slidell",
    "sg:classifiers":[
        {
            "category":"Communications",
            "subcategory":"Film & Video Production",
            "type":"Services"
        }
    ],
    "sg:phone":"+1 985 643 2758",
    "sg:postcode":"70458",
    "sg:province":"LA",
    "sg:tags":[
        "taping"
    ],
    "wof:name":"Video Specialties",
    "wof:placetype":"venue"
},
  "geometry": {"coordinates":[-89.79068100000001,30.253257],"type":"Point"}
}