{
  "type": "Feature",
  "properties": {
    "addr:full":"51 Park Place Dr Covington LA 70433",
    "addr:housenumber":"51",
    "addr:postcode":"70433",
    "addr:street":"Park Place Dr",
    "iso:country":"US",
    "sg:address":"51 Park Place Dr",
    "sg:city":"Covington",
    "sg:classifiers":[
        {
            "category":"Utilities",
            "subcategory":"Mobile Phone",
            "type":"Services"
        }
    ],
    "sg:phone":"+1 985 867 9393",
    "sg:postcode":"70433",
    "sg:province":"LA",
    "sg:tags":[
        "communication",
        "radiotelephone"
    ],
    "wof:name":"AT&T",
    "wof:placetype":"venue"
},
  "geometry": {"coordinates":[-90.08345199999999,30.441445],"type":"Point"}
}