{
  "type": "Feature",
  "properties": {
    "iso:country":"US",
    "sg:address":"707 Bernard St",
    "sg:city":"Carencro",
    "sg:classifiers":[
        {
            "category":"Shopping",
            "subcategory":"Department Store",
            "type":"Retail Goods"
        }
    ],
    "sg:phone":"+1 337 896 7895",
    "sg:postcode":"70520",
    "sg:province":"LA",
    "sg:tags":[
        "shop"
    ],
    "wof:name":"Dollar General",
    "wof:placetype":"venue"
},
  "geometry": {"coordinates":[-92.037363,30.321922],"type":"Point"}
}