{
  "type": "Feature",
  "properties": {
    "iso:country":"US",
    "sg:address":"850 Kaliste Saloom Rd",
    "sg:city":"Lafayette",
    "sg:classifiers":[
        {
            "category":"Building & Trades",
            "subcategory":"Construction",
            "type":"Services"
        }
    ],
    "sg:phone":"+1 337 769 1602",
    "sg:postcode":"70508",
    "sg:province":"LA",
    "sg:tags":[
        "house"
    ],
    "wof:name":"Sunrise Developement & Cnstr",
    "wof:placetype":"venue"
},
  "geometry": {"coordinates":[-92.02188099999999,30.180331],"type":"Point"}
}