{
  "type": "Feature",
  "properties": {
    "iso:country":"US",
    "sg:address":"9613 Brookline Ave",
    "sg:city":"Baton Rouge",
    "sg:classifiers":[
        {
            "category":"Insurance",
            "subcategory":"Insurance Agent",
            "type":"Services"
        }
    ],
    "sg:phone":"+1 225 924 1371",
    "sg:postcode":"70809",
    "sg:province":"LA",
    "wof:name":"Alexander & Sanders Insurance",
    "wof:placetype":"venue"
},
  "geometry": {"coordinates":[-91.081363,30.428312],"type":"Point"}
}