{
  "type": "Feature",
  "properties": {
    "iso:country":"US",
    "sg:address":"2066 Bonn St",
    "sg:city":"Harvey",
    "sg:classifiers":[
        {
            "category":"Building & Trades",
            "subcategory":"Construction",
            "type":"Services"
        }
    ],
    "sg:phone":"+1 504 328 7500",
    "sg:postcode":"70058",
    "sg:province":"LA",
    "sg:tags":[
        "home",
        "builder"
    ],
    "wof:name":"L A Homes Inc",
    "wof:placetype":"venue"
},
  "geometry": {"coordinates":[-90.08534899999999,29.870018],"type":"Point"}
}