{
  "type": "Feature",
  "properties": {
    "addr:full":"3822 Bienville St New Orleans LA 70119",
    "addr:housenumber":"3822",
    "addr:postcode":"70119",
    "addr:street":"Bienville St",
    "iso:country":"US",
    "sg:address":"3822 Bienville St",
    "sg:city":"New Orleans",
    "sg:classifiers":[
        {
            "category":"Health Services",
            "subcategory":"Doctor",
            "type":"Services"
        }
    ],
    "sg:phone":"+1 504 482 0434",
    "sg:postcode":"70119",
    "sg:province":"LA",
    "sg:tags":[
        "physician",
        "surgeon"
    ],
    "wof:name":"Teresa E Klainer MD",
    "wof:placetype":"venue"
},
  "geometry": {"coordinates":[-90.09689299999999,29.974637],"type":"Point"}
}