{
  "type": "Feature",
  "properties": {
    "addr:full":"2020 E 70th St Shreveport LA 71105",
    "addr:housenumber":"2020",
    "addr:postcode":"71105",
    "addr:street":"E 70Th St",
    "iso:country":"US",
    "sg:address":"2020 E 70th St",
    "sg:city":"Shreveport",
    "sg:classifiers":[
        {
            "category":"Social Services",
            "type":"Services"
        }
    ],
    "sg:phone":"+1 318 798 7664",
    "sg:postcode":"71105",
    "sg:province":"LA",
    "wof:name":"Everson D Missy Bcsw Dcsw PC",
    "wof:placetype":"venue"
},
  "geometry": {"coordinates":[-93.708237,32.444136],"type":"Point"}
}