{
  "type": "Feature",
  "properties": {
    "iso:country":"US",
    "sg:address":"8026 Main St",
    "sg:city":"Houma",
    "sg:classifiers":[
        {
            "category":"Government",
            "subcategory":"Office",
            "type":"Public Place"
        }
    ],
    "sg:phone":"+1 985 857 3626",
    "sg:postcode":"70360",
    "sg:province":"LA",
    "sg:tags":[
        "admin",
        "affairs",
        "state"
    ],
    "wof:name":"Veterans Affairs Dept",
    "wof:placetype":"venue"
},
  "geometry": {"coordinates":[-90.71845500000001,29.598219],"type":"Point"}
}