{
  "type": "Feature",
  "properties": {
    "addr:full":"300 Jefferson Ave Metairie LA 70005",
    "addr:housenumber":"300",
    "addr:postcode":"70005",
    "addr:street":"Jefferson Ave",
    "iso:country":"US",
    "sg:address":"300 Jefferson Ave",
    "sg:city":"Metairie",
    "sg:classifiers":[
        {
            "category":"Building & Trades",
            "subcategory":"Equipment Rental",
            "type":"Services"
        }
    ],
    "sg:phone":"+1 504 837 3947",
    "sg:postcode":"70005",
    "sg:province":"LA",
    "sg:tags":[
        "audio",
        "leasing"
    ],
    "sg:website":"www.corplighting.com",
    "wof:name":"Corporate Lighting & Audio",
    "wof:placetype":"venue"
},
  "geometry": {"coordinates":[-90.145072,29.980953],"type":"Point"}
}