{
  "type": "Feature",
  "properties": {
    "iso:country":"US",
    "sg:address":"6007 Financial Plz",
    "sg:city":"Shreveport",
    "sg:classifiers":[
        {
            "category":"Personal",
            "type":"Services"
        }
    ],
    "sg:phone":"+1 318 686 3030",
    "sg:postcode":"71129",
    "sg:province":"LA",
    "sg:tags":[
        "dating"
    ],
    "wof:name":"Single Resources",
    "wof:placetype":"venue"
},
  "geometry": {"coordinates":[-93.858204,32.451437],"type":"Point"}
}