{
  "type": "Feature",
  "properties": {
    "addr:full":"16155 Airline Hwy Baton Rouge LA 70817",
    "addr:housenumber":"16155",
    "addr:postcode":"70817",
    "addr:street":"Airline Hwy",
    "iso:country":"US",
    "sg:address":"16155 Airline Hwy",
    "sg:city":"Baton Rouge",
    "sg:classifiers":[
        {
            "category":"Building & Trades",
            "subcategory":"Construction",
            "type":"Services"
        }
    ],
    "sg:phone":"+1 225 755 2011",
    "sg:postcode":"70817",
    "sg:province":"LA",
    "sg:tags":[
        "contractor"
    ],
    "wof:name":"Outdoor Adventures",
    "wof:placetype":"venue"
},
  "geometry": {"coordinates":[-91.00275600000001,30.355429],"type":"Point"}
}