{
  "type": "Feature",
  "properties": {
    "iso:country":"US",
    "sg:address":"6021 Old Boyce Rd",
    "sg:city":"Alexandria",
    "sg:classifiers":[
        {
            "category":"Restaurant",
            "type":"Food & Drink"
        }
    ],
    "sg:phone":"+1 318 442 7414",
    "sg:postcode":"71303",
    "sg:province":"LA",
    "sg:tags":[
        "eating"
    ],
    "wof:name":"McDonalds",
    "wof:placetype":"venue"
},
  "geometry": {"coordinates":[-92.51978200000001,31.345343],"type":"Point"}
}