{
  "type": "Feature",
  "properties": {
    "iso:country":"US",
    "sg:address":"382 US Hwy 65",
    "sg:city":"Tallulah",
    "sg:classifiers":[
        {
            "category":"Wholesale",
            "subcategory":"Scrap",
            "type":"Manufacturing & Wholesale Goods"
        }
    ],
    "sg:phone":"+1 318 574 8061",
    "sg:postcode":"71282",
    "sg:province":"LA",
    "sg:tags":[
        "recycling",
        "center"
    ],
    "wof:name":"Earth Friends Recycling",
    "wof:placetype":"venue"
},
  "geometry": {"coordinates":[-91.185886,32.409481],"type":"Point"}
}