{
  "type": "Feature",
  "properties": {
    "addr:full":"326 E Cornerview St Gonzales LA 70737",
    "addr:housenumber":"326",
    "addr:postcode":"70737",
    "addr:street":"E Cornerview St",
    "iso:country":"US",
    "sg:address":"326 E Cornerview St",
    "sg:city":"Gonzales",
    "sg:classifiers":[
        {
            "category":"Professional",
            "subcategory":"Accounting & Tax Preparation",
            "type":"Services"
        }
    ],
    "sg:phone":"+1 225 647 2928",
    "sg:postcode":"70737",
    "sg:province":"LA",
    "sg:tags":[
        "accountant"
    ],
    "wof:name":"Perry J Smith Jr CPA",
    "wof:placetype":"venue"
},
  "geometry": {"coordinates":[-90.917919,30.232938],"type":"Point"}
}