{
  "type": "Feature",
  "properties": {
    "addr:full":"3521 Tulane Ave New Orleans LA 70119",
    "addr:housenumber":"3521",
    "addr:postcode":"70119",
    "addr:street":"Tulane Ave",
    "iso:country":"US",
    "sg:address":"3521 Tulane Ave",
    "sg:city":"New Orleans",
    "sg:classifiers":[
        {
            "category":"Wholesale",
            "subcategory":"Auto Parts",
            "type":"Manufacturing & Wholesale Goods"
        }
    ],
    "sg:phone":"+1 504 482 6815",
    "sg:postcode":"70119",
    "sg:province":"LA",
    "sg:tags":[
        "body",
        "automobile",
        "shop"
    ],
    "wof:name":"Automotive Paint & Trimming",
    "wof:placetype":"venue"
},
  "geometry": {"coordinates":[-90.10028200000001,29.966315],"type":"Point"}
}