{
  "type": "Feature",
  "properties": {
    "iso:country":"US",
    "sg:address":"441 S Goodman Rd",
    "sg:city":"Lake Charles",
    "sg:classifiers":[
        {
            "category":"Retail",
            "subcategory":"Auto Repair",
            "type":"Services"
        }
    ],
    "sg:phone":"+1 337 474 4692",
    "sg:postcode":"70615",
    "sg:province":"LA",
    "sg:tags":[
        "wrecker"
    ],
    "wof:name":"Guy's Towing Svc",
    "wof:placetype":"venue"
},
  "geometry": {"coordinates":[-93.154983,30.233477],"type":"Point"}
}