{
  "type": "Feature",
  "properties": {
    "iso:country":"US",
    "sg:address":"602 Crockett St",
    "sg:city":"Shreveport",
    "sg:classifiers":[
        {
            "category":"Banks & Credit Unions",
            "subcategory":"Bank",
            "type":"Services"
        }
    ],
    "sg:phone":"+1 318 424 2400",
    "sg:postcode":"71101",
    "sg:province":"LA",
    "sg:tags":[
        "loan",
        "real estate"
    ],
    "wof:name":"American Fidelity Inc",
    "wof:placetype":"venue"
},
  "geometry": {"coordinates":[-93.74999200000001,32.509885],"type":"Point"}
}