{
  "type": "Feature",
  "properties": {
    "addr:full":"910 Canal Blvd Thibodaux LA 70301",
    "addr:housenumber":"910",
    "addr:postcode":"70301",
    "addr:street":"Canal Blvd",
    "iso:country":"US",
    "sg:address":"910 Canal Blvd",
    "sg:city":"Thibodaux",
    "sg:classifiers":[
        {
            "category":"Government",
            "subcategory":"Post Office",
            "type":"Public Place"
        }
    ],
    "sg:phone":"+1 985 447 3737",
    "sg:postcode":"70301",
    "sg:province":"LA",
    "wof:name":"US Post Office",
    "wof:placetype":"venue"
},
  "geometry": {"coordinates":[-90.820976,29.79186],"type":"Point"}
}