{
  "type": "Feature",
  "properties": {
    "iso:country":"US",
    "sg:address":"106 Metairie Lawn Dr",
    "sg:city":"Metairie",
    "sg:classifiers":[
        {
            "category":"Communications",
            "subcategory":"Television Station",
            "type":"Services"
        }
    ],
    "sg:phone":"+1 504 840 9898",
    "sg:postcode":"70001",
    "sg:province":"LA",
    "sg:tags":[
        "organization",
        "broadcasting",
        "co",
        "religious"
    ],
    "wof:name":"Focus Worldwide Cathlic Netwrk",
    "wof:placetype":"venue"
},
  "geometry": {"coordinates":[-90.15290899999999,29.980078],"type":"Point"}
}