{
  "type": "Feature",
  "properties": {
    "addr:full":"2050 Perkins Rd Baton Rouge LA 70808",
    "addr:housenumber":"2050",
    "addr:postcode":"70808",
    "addr:street":"Perkins Rd",
    "iso:country":"US",
    "sg:address":"2050 Perkins Rd",
    "sg:city":"Baton Rouge",
    "sg:classifiers":[
        {
            "category":"Home & Garden",
            "subcategory":"Furniture",
            "type":"Retail Goods"
        }
    ],
    "sg:phone":"+1 225 346 0061",
    "sg:postcode":"70808",
    "sg:province":"LA",
    "sg:tags":[
        "builder",
        "custom"
    ],
    "wof:name":"Ricard Patrick Wood Worker",
    "wof:placetype":"venue"
},
  "geometry": {"coordinates":[-91.1614,30.430761],"type":"Point"}
}