{
  "type": "Feature",
  "properties": {
    "iso:country":"US",
    "sg:address":"68099 Hwy 59",
    "sg:city":"Mandeville",
    "sg:classifiers":[
        {
            "category":"Recreation",
            "type":"Entertainment"
        }
    ],
    "sg:phone":"+1 985 892 1466",
    "sg:postcode":"70471",
    "sg:province":"LA",
    "sg:tags":[
        "attraction",
        "tourist"
    ],
    "wof:name":"Visitor Information",
    "wof:placetype":"venue"
},
  "geometry": {"coordinates":[-90.040786,30.417192],"type":"Point"}
}