{
  "type": "Feature",
  "properties": {
    "addr:full":"6716 Johnston St Lafayette LA 70503",
    "addr:housenumber":"6716",
    "addr:postcode":"70503",
    "addr:street":"Johnston St",
    "iso:country":"US",
    "sg:address":"6716 Johnston St",
    "sg:city":"Lafayette",
    "sg:classifiers":[
        {
            "category":"Building & Trades",
            "subcategory":"Electrical",
            "type":"Services"
        }
    ],
    "sg:phone":"+1 337 216 0506",
    "sg:postcode":"70503",
    "sg:province":"LA",
    "sg:tags":[
        "electric",
        "contractor"
    ],
    "wof:name":"RFB Electric",
    "wof:placetype":"venue"
},
  "geometry": {"coordinates":[-92.09145599999999,30.153375],"type":"Point"}
}