{
  "type": "Feature",
  "properties": {
    "addr:full":"12012 US Hwy 190 Opelousas LA 70570",
    "addr:housenumber":"12012",
    "addr:postcode":"70570",
    "addr:street":"Us Hwy 190",
    "iso:country":"US",
    "sg:address":"12012 US Hwy 190",
    "sg:city":"Opelousas",
    "sg:classifiers":[
        {
            "category":"Travel",
            "subcategory":"Hotels & Motels",
            "type":"Entertainment"
        }
    ],
    "sg:phone":"+1 337 942 5624",
    "sg:postcode":"70570",
    "sg:province":"LA",
    "wof:name":"Cardinal Inn Motel",
    "wof:placetype":"venue"
},
  "geometry": {"coordinates":[-92.13283300000001,30.5313],"type":"Point"}
}