{
  "type": "Feature",
  "properties": {
    "iso:country":"US",
    "sg:address":"214 Milam St",
    "sg:city":"Shreveport",
    "sg:classifiers":[
        {
            "category":"Insurance",
            "subcategory":"Insurance Agent",
            "type":"Services"
        }
    ],
    "sg:phone":"+1 318 221 5241",
    "sg:postcode":"71101",
    "sg:province":"LA",
    "wof:name":"Querbes & Nelson",
    "wof:placetype":"venue"
},
  "geometry": {"coordinates":[-93.746836,32.513558],"type":"Point"}
}