{
  "type": "Feature",
  "properties": {
    "iso:country":"US",
    "sg:address":"2901 Independence St",
    "sg:city":"Metairie",
    "sg:classifiers":[
        {
            "category":"Professional",
            "subcategory":"Lawyer & Legal Services",
            "type":"Services"
        }
    ],
    "sg:phone":"+1 504 779 7979",
    "sg:postcode":"70006",
    "sg:province":"LA",
    "sg:tags":[
        "attorney"
    ],
    "wof:name":"John Davidson & Assoc",
    "wof:placetype":"venue"
},
  "geometry": {"coordinates":[-90.177981,30.00081],"type":"Point"}
}