{
  "type": "Feature",
  "properties": {
    "iso:country":"US",
    "sg:address":"2214 Memorial Dr",
    "sg:city":"Alexandria",
    "sg:classifiers":[
        {
            "category":"Restaurant",
            "type":"Food & Drink"
        }
    ],
    "sg:phone":"+1 318 561 9839",
    "sg:postcode":"71301",
    "sg:province":"LA",
    "wof:name":"China King Buffet",
    "wof:placetype":"venue"
},
  "geometry": {"coordinates":[-92.45794100000001,31.279531],"type":"Point"}
}