{
  "type": "Feature",
  "properties": {
    "iso:country":"US",
    "sg:address":"28446 Lapont Dr",
    "sg:city":"Lacombe",
    "sg:classifiers":[
        {
            "category":"Professional",
            "type":"Services"
        }
    ],
    "sg:phone":"+1 985 776 1550",
    "sg:postcode":"70445",
    "sg:province":"LA",
    "sg:tags":[
        "establishment"
    ],
    "wof:name":"Admiralty Associates",
    "wof:placetype":"venue"
},
  "geometry": {"coordinates":[-89.934164,30.299448],"type":"Point"}
}