{
  "type": "Feature",
  "properties": {
    "addr:full":"221 E Charles St Hammond LA 70401",
    "addr:housenumber":"221",
    "addr:postcode":"70401",
    "addr:street":"E Charles St",
    "iso:country":"US",
    "sg:address":"221 E Charles St",
    "sg:city":"Hammond",
    "sg:classifiers":[
        {
            "category":"Banks & Credit Unions",
            "subcategory":"Bank",
            "type":"Services"
        }
    ],
    "sg:phone":"+1 985 345 8666",
    "sg:postcode":"70401",
    "sg:province":"LA",
    "sg:tags":[
        "loan"
    ],
    "wof:name":"Magee Financial Corp",
    "wof:placetype":"venue"
},
  "geometry": {"coordinates":[-90.459129,30.505623],"type":"Point"}
}