{
  "type": "Feature",
  "properties": {
    "addr:full":"243 Florida Ave SE Denham Springs LA 70726",
    "addr:housenumber":"243",
    "addr:postcode":"70726",
    "addr:street":"Florida Ave Se",
    "iso:country":"US",
    "sg:address":"243 Florida Ave SE",
    "sg:city":"Denham Springs",
    "sg:classifiers":[
        {
            "category":"Restaurant",
            "type":"Food & Drink"
        }
    ],
    "sg:phone":"+1 225 667 6929",
    "sg:postcode":"70726",
    "sg:province":"LA",
    "wof:name":"Patty Denham Restaurant",
    "wof:placetype":"venue"
},
  "geometry": {"coordinates":[-90.95411900000001,30.483107],"type":"Point"}
}