{
  "type": "Feature",
  "properties": {
    "iso:country":"US",
    "sg:address":"261 Wenger Rd",
    "sg:city":"Des Allemands",
    "sg:classifiers":[
        {
            "category":"Retail",
            "subcategory":"Repair Shop",
            "type":"Services"
        }
    ],
    "sg:phone":"+1 504 915 1980",
    "sg:postcode":"70030",
    "sg:province":"LA",
    "wof:name":"Outcast Marine",
    "wof:placetype":"venue"
},
  "geometry": {"coordinates":[-90.461389,29.832889],"type":"Point"}
}