{
  "type": "Feature",
  "properties": {
    "addr:full":"1919 Eraste Landry Rd Lafayette LA 70506",
    "addr:housenumber":"1919",
    "addr:postcode":"70506",
    "addr:street":"Eraste Landry Rd",
    "iso:country":"US",
    "sg:address":"1919 Eraste Landry Rd",
    "sg:city":"Lafayette",
    "sg:classifiers":[
        {
            "category":"Organizations",
            "subcategory":"Non-profit Organization",
            "type":"Services"
        }
    ],
    "sg:phone":"+1 337 981 2229",
    "sg:postcode":"70506",
    "sg:province":"LA",
    "sg:tags":[
        "social"
    ],
    "wof:name":"Neyland Park",
    "wof:placetype":"venue"
},
  "geometry": {"coordinates":[-92.068265,30.219074],"type":"Point"}
}