{
  "type": "Feature",
  "properties": {
    "iso:country":"US",
    "sg:address":"421 Carmel Ave",
    "sg:city":"Lafayette",
    "sg:classifiers":[
        {
            "category":"Organizations",
            "subcategory":"Non-profit Organization",
            "type":"Services"
        }
    ],
    "sg:phone":"+1 337 233 4140",
    "sg:postcode":"70501",
    "sg:province":"LA",
    "sg:tags":[
        "fund",
        "counselor",
        "raising"
    ],
    "wof:name":"Holy Rosary Institute Alumi",
    "wof:placetype":"venue"
},
  "geometry": {"coordinates":[-91.998097,30.234137],"type":"Point"}
}