{
  "type": "Feature",
  "properties": {
    "addr:full":"510 Eraste Landry Rd Lafayette LA 70506",
    "addr:housenumber":"510",
    "addr:postcode":"70506",
    "addr:street":"Eraste Landry Rd",
    "iso:country":"US",
    "sg:address":"510 Eraste Landry Rd",
    "sg:city":"Lafayette",
    "sg:classifiers":[
        {
            "category":"Building & Trades",
            "subcategory":"Electrical",
            "type":"Services"
        }
    ],
    "sg:phone":"+1 337 898 1700",
    "sg:postcode":"70506",
    "sg:province":"LA",
    "sg:tags":[
        "electric",
        "contractor"
    ],
    "wof:name":"Metro Electric & Air Cond",
    "wof:placetype":"venue"
},
  "geometry": {"coordinates":[-92.046852,30.227819],"type":"Point"}
}