{
  "type": "Feature",
  "properties": {
    "addr:full":"623 Ursulines Ave New Orleans LA 70116",
    "addr:housenumber":"623",
    "addr:postcode":"70116",
    "addr:street":"Ursulines Ave",
    "iso:country":"US",
    "sg:address":"623 Ursulines Ave",
    "sg:city":"New Orleans",
    "sg:classifiers":[
        {
            "category":"Travel",
            "subcategory":"Hotels & Motels",
            "type":"Entertainment"
        }
    ],
    "sg:phone":"+1 504 581 4871",
    "sg:postcode":"70116",
    "sg:province":"LA",
    "wof:name":"French Quarter Guest House",
    "wof:placetype":"venue"
},
  "geometry": {"coordinates":[-90.0616,29.961],"type":"Point"}
}