{
  "type": "Feature",
  "properties": {
    "addr:full":"4021 Behrman Pl New Orleans LA 70114",
    "addr:housenumber":"4021",
    "addr:postcode":"70114",
    "addr:street":"Behrman Pl",
    "iso:country":"US",
    "sg:address":"4021 Behrman Pl",
    "sg:city":"New Orleans",
    "sg:classifiers":[
        {
            "category":"Banks & Credit Unions",
            "subcategory":"Bank",
            "type":"Services"
        }
    ],
    "sg:phone":"+1 504 366 8454",
    "sg:postcode":"70114",
    "sg:province":"LA",
    "sg:tags":[
        "cashing",
        "check"
    ],
    "wof:name":"Check Into Cash",
    "wof:placetype":"venue"
},
  "geometry": {"coordinates":[-90.017876,29.91305],"type":"Point"}
}