{
  "type": "Feature",
  "properties": {
    "iso:country":"US",
    "sg:address":"207 N Lejeune Ave",
    "sg:city":"Kaplan",
    "sg:classifiers":[
        {
            "category":"Professional",
            "subcategory":"Business Services",
            "type":"Services"
        }
    ],
    "sg:phone":"+1 337 643 3733",
    "sg:postcode":"70548",
    "sg:province":"LA",
    "wof:name":"Gaspard Bail Bonding",
    "wof:placetype":"venue"
},
  "geometry": {"coordinates":[-92.28692599999999,30.000504],"type":"Point"}
}