{
  "type": "Feature",
  "properties": {
    "iso:country":"US",
    "sg:address":"1309 Lakeshore Ave",
    "sg:city":"Metairie",
    "sg:classifiers":[
        {
            "category":"Education",
            "subcategory":"Special Training",
            "type":"Public Place"
        }
    ],
    "sg:phone":"+1 504 831 1823",
    "sg:postcode":"70005",
    "sg:province":"LA",
    "wof:name":"Toastmasters International",
    "wof:placetype":"venue"
},
  "geometry": {"coordinates":[-90.136162,30.015874],"type":"Point"}
}