{
  "type": "Feature",
  "properties": {
    "addr:full":"134 Kings Lake Rd West Monroe LA 71292",
    "addr:housenumber":"134",
    "addr:postcode":"71292",
    "addr:street":"Kings Lake Rd West",
    "iso:country":"US",
    "sg:address":"134 Kings Lake Rd",
    "sg:city":"West Monroe",
    "sg:classifiers":[
        {
            "category":"Bars & Pubs",
            "type":"Food & Drink"
        }
    ],
    "sg:phone":"+1 318 388 5777",
    "sg:postcode":"71292",
    "sg:province":"LA",
    "sg:tags":[
        "lounge",
        "cocktail"
    ],
    "wof:name":"Pete's",
    "wof:placetype":"venue"
},
  "geometry": {"coordinates":[-92.161368,32.455472],"type":"Point"}
}