{
  "type": "Feature",
  "properties": {
    "iso:country":"US",
    "sg:address":"204 E Thomas St",
    "sg:city":"Hammond",
    "sg:classifiers":[
        {
            "category":"Shopping",
            "subcategory":"Books",
            "type":"Retail Goods"
        }
    ],
    "sg:phone":"+1 985 542 1124",
    "sg:postcode":"70401",
    "sg:province":"LA",
    "sg:tags":[
        "dealer"
    ],
    "wof:name":"Bayou Booksellers",
    "wof:placetype":"venue"
},
  "geometry": {"coordinates":[-90.458601,30.504565],"type":"Point"}
}