{
  "type": "Feature",
  "properties": {
    "iso:country":"US",
    "sg:address":"9370 Mansfield Rd",
    "sg:city":"Shreveport",
    "sg:classifiers":[
        {
            "category":"Restaurant",
            "type":"Food & Drink"
        }
    ],
    "sg:phone":"+1 318 688 7531",
    "sg:postcode":"71118",
    "sg:province":"LA",
    "sg:tags":[
        "eating"
    ],
    "wof:name":"Thunderbird Cafe",
    "wof:placetype":"venue"
},
  "geometry": {"coordinates":[-93.809304,32.397228],"type":"Point"}
}