{
  "type": "Feature",
  "properties": {
    "iso:country":"US",
    "sg:address":"15392 Bonita Ave",
    "sg:city":"Bonita",
    "sg:classifiers":[
        {
            "category":"Government",
            "subcategory":"Post Office",
            "type":"Public Place"
        }
    ],
    "sg:phone":"+1 318 823 4520",
    "sg:postcode":"71223",
    "sg:province":"LA",
    "wof:name":"US Post Office",
    "wof:placetype":"venue"
},
  "geometry": {"coordinates":[-91.674644,32.92058],"type":"Point"}
}