{
  "type": "Feature",
  "properties": {
    "addr:full":"3623 Hwy 70 Pierre Part LA 70339",
    "addr:housenumber":"3623",
    "addr:postcode":"70339",
    "addr:street":"Hwy 70 Pierre Part",
    "iso:country":"US",
    "sg:address":"3623 Hwy 70",
    "sg:city":"Pierre Part",
    "sg:classifiers":[
        {
            "category":"Shopping",
            "subcategory":"Jewelry",
            "type":"Retail Goods"
        }
    ],
    "sg:phone":"+1 985 252 3861",
    "sg:postcode":"70339",
    "sg:province":"LA",
    "sg:tags":[
        "jeweler"
    ],
    "wof:name":"Treasure Chest",
    "wof:placetype":"venue"
},
  "geometry": {"coordinates":[-91.21280899999999,29.952032],"type":"Point"}
}