{
  "type": "Feature",
  "properties": {
    "iso:country":"US",
    "sg:address":"622 W Hutchinson Ave",
    "sg:city":"Crowley",
    "sg:classifiers":[
        {
            "category":"Restaurant",
            "type":"Food & Drink"
        }
    ],
    "sg:phone":"+1 337 783 9882",
    "sg:postcode":"70526",
    "sg:province":"LA",
    "wof:name":"Ardoin's Cafe & Station",
    "wof:placetype":"venue"
},
  "geometry": {"coordinates":[-92.38000700000001,30.211913],"type":"Point"}
}