{
  "type": "Feature",
  "properties": {
    "iso:country":"US",
    "sg:address":"108 Robinson St",
    "sg:city":"Delhi",
    "sg:classifiers":[
        {
            "category":"Organizations",
            "subcategory":"Religious Organization",
            "type":"Services"
        }
    ],
    "sg:phone":"+1 318 878 3613",
    "sg:postcode":"71232",
    "sg:province":"LA",
    "wof:name":"Vaughn St Church of Christ",
    "wof:placetype":"venue"
},
  "geometry": {"coordinates":[-91.48596499999999,32.462944],"type":"Point"}
}