{
  "type": "Feature",
  "properties": {
    "iso:country":"US",
    "sg:address":"204 Venture Blvd",
    "sg:city":"Houma",
    "sg:classifiers":[
        {
            "category":"Mining & Drilling",
            "type":"Manufacturing & Wholesale Goods"
        }
    ],
    "sg:phone":"+1 985 879 3328",
    "sg:postcode":"70360",
    "sg:province":"LA",
    "sg:tags":[
        "field",
        "oil"
    ],
    "wof:name":"Energy Catering Svc Inc",
    "wof:placetype":"venue"
},
  "geometry": {"coordinates":[-90.76461399999999,29.595731],"type":"Point"}
}