{
  "type": "Feature",
  "properties": {
    "iso:country":"US",
    "sg:address":"321 Apollo Rd",
    "sg:city":"Scott",
    "sg:classifiers":[
        {
            "category":"Wholesale",
            "subcategory":"Machinery & Supplies",
            "type":"Manufacturing & Wholesale Goods"
        }
    ],
    "sg:phone":"+1 337 237 8399",
    "sg:postcode":"70583",
    "sg:province":"LA",
    "sg:tags":[
        "field",
        "oil",
        "equipment"
    ],
    "wof:name":"Seaboard International",
    "wof:placetype":"venue"
},
  "geometry": {"coordinates":[-92.107496,30.239768],"type":"Point"}
}