{
  "type": "Feature",
  "properties": {
    "addr:full":"3622 Government St Baton Rouge LA 70806",
    "addr:housenumber":"3622",
    "addr:postcode":"70806",
    "addr:street":"Government St",
    "iso:country":"US",
    "sg:address":"3622 Government St",
    "sg:city":"Baton Rouge",
    "sg:classifiers":[
        {
            "category":"Professional",
            "subcategory":"Lawyer & Legal Services",
            "type":"Services"
        }
    ],
    "sg:phone":"+1 225 343 0643",
    "sg:postcode":"70806",
    "sg:province":"LA",
    "sg:tags":[
        "attorney"
    ],
    "wof:name":"Rex D Rainach",
    "wof:placetype":"venue"
},
  "geometry": {"coordinates":[-91.152579,30.444125],"type":"Point"}
}