{
  "type": "Feature",
  "properties": {
    "addr:full":"1201 US Hwy 90 Morgan City LA 70380",
    "addr:housenumber":"1201",
    "addr:postcode":"70380",
    "addr:street":"Us Hwy 90 Morgan",
    "iso:country":"US",
    "sg:address":"1201 US Hwy 90",
    "sg:city":"Morgan City",
    "sg:classifiers":[
        {
            "category":"Banks & Credit Unions",
            "subcategory":"Bank",
            "type":"Services"
        }
    ],
    "sg:phone":"+1 985 395 5387",
    "sg:postcode":"70380",
    "sg:province":"LA",
    "sg:tags":[
        "cashing",
        "check"
    ],
    "wof:name":"Express Check Advance",
    "wof:placetype":"venue"
},
  "geometry": {"coordinates":[-91.26050499999999,29.682792],"type":"Point"}
}