{
  "type": "Feature",
  "properties": {
    "addr:full":"1018 US Hwy 90 New Iberia LA 70560",
    "addr:housenumber":"1018",
    "addr:postcode":"70560",
    "addr:street":"Us Hwy 90",
    "iso:country":"US",
    "sg:address":"1018 US Hwy 90",
    "sg:city":"New Iberia",
    "sg:classifiers":[
        {
            "category":"Retail",
            "subcategory":"Auto Repair",
            "type":"Services"
        }
    ],
    "sg:phone":"+1 337 365 3378",
    "sg:postcode":"70560",
    "sg:province":"LA",
    "sg:tags":[
        "repairing",
        "automobile",
        "general"
    ],
    "wof:name":"Norman's Auto & Diesel Repair",
    "wof:placetype":"venue"
},
  "geometry": {"coordinates":[-91.843936,29.973192],"type":"Point"}
}