{
  "type": "Feature",
  "properties": {
    "addr:full":"5233 Dijon Dr Baton Rouge LA 70808",
    "addr:housenumber":"5233",
    "addr:postcode":"70808",
    "addr:street":"Dijon Dr",
    "iso:country":"US",
    "sg:address":"5233 Dijon Dr",
    "sg:city":"Baton Rouge",
    "sg:classifiers":[
        {
            "category":"Health Services",
            "subcategory":"Doctor",
            "type":"Services"
        }
    ],
    "sg:phone":"+1 225 766 5642",
    "sg:postcode":"70808",
    "sg:province":"LA",
    "sg:tags":[
        "physician",
        "surgeon"
    ],
    "wof:name":"Joel D Nasca MD",
    "wof:placetype":"venue"
},
  "geometry": {"coordinates":[-91.112146,30.401948],"type":"Point"}
}