{
  "type": "Feature",
  "properties": {
    "iso:country":"US",
    "sg:address":"8893 Shrimpers Row",
    "sg:city":"Dulac",
    "sg:classifiers":[
        {
            "category":"Food & Beverages",
            "subcategory":"Meat & Fish",
            "type":"Retail Goods"
        }
    ],
    "sg:phone":"+1 985 563 7153",
    "sg:postcode":"70353",
    "sg:province":"LA",
    "sg:tags":[
        "seafood"
    ],
    "wof:name":"Steven Seafood Inn",
    "wof:placetype":"venue"
},
  "geometry": {"coordinates":[-90.73146199999999,29.353653],"type":"Point"}
}