{
  "type": "Feature",
  "properties": {
    "iso:country":"US",
    "sg:address":"126 S Pierce St",
    "sg:city":"New Orleans",
    "sg:classifiers":[
        {
            "category":"Real Estate",
            "subcategory":"Architect",
            "type":"Services"
        }
    ],
    "sg:phone":"+1 504 486 0222",
    "sg:postcode":"70119",
    "sg:province":"LA",
    "sg:tags":[
        "architectural"
    ],
    "wof:name":"Gendusa Jr Aia Architure",
    "wof:placetype":"venue"
},
  "geometry": {"coordinates":[-90.10006199999999,29.973045],"type":"Point"}
}