{
  "type": "Feature",
  "properties": {
    "addr:full":"179 Northshore Blvd Slidell LA 70460",
    "addr:housenumber":"179",
    "addr:postcode":"70460",
    "addr:street":"Northshore Blvd",
    "iso:country":"US",
    "sg:address":"179 Northshore Blvd",
    "sg:city":"Slidell",
    "sg:classifiers":[
        {
            "category":"Food & Beverages",
            "subcategory":"Specialty",
            "type":"Retail Goods"
        }
    ],
    "sg:phone":"+1 985 646 2294",
    "sg:postcode":"70460",
    "sg:province":"LA",
    "sg:tags":[
        "vitamin"
    ],
    "wof:name":"Vitamin Shoppe",
    "wof:placetype":"venue"
},
  "geometry": {"coordinates":[-89.825864,30.30538],"type":"Point"}
}