{
  "type": "Feature",
  "properties": {
    "addr:full":"506 Front St Morgan City LA 70380",
    "addr:housenumber":"506",
    "addr:postcode":"70380",
    "addr:street":"Front St",
    "iso:country":"US",
    "sg:address":"506 Front St",
    "sg:city":"Morgan City",
    "sg:classifiers":[
        {
            "category":"Wholesale",
            "subcategory":"Groceries",
            "type":"Manufacturing & Wholesale Goods"
        }
    ],
    "sg:phone":"+1 985 385 2620",
    "sg:postcode":"70380",
    "sg:province":"LA",
    "sg:tags":[
        "food",
        "broker"
    ],
    "sg:website":"www.gjfood.com",
    "wof:name":"G & J Land & Marine Food Distr",
    "wof:placetype":"venue"
},
  "geometry": {"coordinates":[-91.20971400000001,29.69449],"type":"Point"}
}