{
  "type": "Feature",
  "properties": {
    "addr:full":"102 E Bayou Rd Thibodaux LA 70301",
    "addr:housenumber":"102",
    "addr:postcode":"70301",
    "addr:street":"E Bayou Rd",
    "iso:country":"US",
    "sg:address":"102 E Bayou Rd",
    "sg:city":"Thibodaux",
    "sg:phone":"+1 985 447 3345",
    "sg:postcode":"70301",
    "sg:province":"LA",
    "sg:tags":[
        "oil"
    ],
    "wof:name":"Gibbens & Lefort Inc",
    "wof:placetype":"venue"
},
  "geometry": {"coordinates":[-90.817826,29.799993],"type":"Point"}
}