{
  "type": "Feature",
  "properties": {
    "iso:country":"US",
    "sg:address":"2030 Olene Dr",
    "sg:city":"Mandeville",
    "sg:classifiers":[
        {
            "category":"Building & Trades",
            "subcategory":"Construction",
            "type":"Services"
        }
    ],
    "sg:phone":"+1 985 727 7707",
    "sg:postcode":"70448",
    "sg:province":"LA",
    "sg:tags":[
        "house"
    ],
    "wof:name":"A+ Renovations & Repairds LLC",
    "wof:placetype":"venue"
},
  "geometry": {"coordinates":[-90.044051,30.381106],"type":"Point"}
}