{
  "type": "Feature",
  "properties": {
    "iso:country":"US",
    "sg:address":"416 Shady Ln",
    "sg:city":"Natchitoches",
    "sg:classifiers":[
        {
            "category":"Real Estate",
            "subcategory":"Real Estate Agent",
            "type":"Services"
        }
    ],
    "sg:phone":"+1 318 352 9774",
    "sg:postcode":"71457",
    "sg:province":"LA",
    "sg:tags":[
        "authorities",
        "housing"
    ],
    "wof:name":"Natchitoches Housing Authority",
    "wof:placetype":"venue"
},
  "geometry": {"coordinates":[-93.07677200000001,31.757704],"type":"Point"}
}