{
  "type": "Feature",
  "properties": {
    "addr:full":"1356 Sligo Rd Bossier City LA 71112",
    "addr:housenumber":"1356",
    "addr:postcode":"71112",
    "addr:street":"Sligo Rd",
    "iso:country":"US",
    "sg:address":"1356 Sligo Rd",
    "sg:city":"Bossier City",
    "sg:classifiers":[
        {
            "category":"Retail",
            "subcategory":"Portrait Studio",
            "type":"Services"
        }
    ],
    "sg:phone":"+1 318 747 7771",
    "sg:postcode":"71112",
    "sg:province":"LA",
    "sg:tags":[
        "photographer"
    ],
    "wof:name":"Ashley Elston Photography",
    "wof:placetype":"venue"
},
  "geometry": {"coordinates":[-93.6078,32.445056],"type":"Point"}
}