{
  "type": "Feature",
  "properties": {
    "iso:country":"US",
    "sg:address":"6611 Jefferson Hwy",
    "sg:city":"Harahan",
    "sg:classifiers":[
        {
            "category":"Restaurant",
            "type":"Food & Drink"
        }
    ],
    "sg:phone":"+1 504 737 3610",
    "sg:postcode":"70123",
    "sg:province":"LA",
    "wof:name":"Red Wagon",
    "wof:placetype":"venue"
},
  "geometry": {"coordinates":[-90.195846,29.937806],"type":"Point"}
}