{
  "type": "Feature",
  "properties": {
    "iso:country":"US",
    "sg:address":"12907 Burgess Ave",
    "sg:city":"Walker",
    "sg:classifiers":[
        {
            "category":"Professional",
            "type":"Services"
        }
    ],
    "sg:phone":"+1 225 791 0380",
    "sg:postcode":"70785",
    "sg:province":"LA",
    "sg:tags":[
        "establishment"
    ],
    "wof:name":"Abrasive Source Inc",
    "wof:placetype":"venue"
},
  "geometry": {"coordinates":[-90.87166999999999,30.488529],"type":"Point"}
}