{
  "type": "Feature",
  "properties": {
    "iso:country":"US",
    "sg:address":"6862 Hwy 1",
    "sg:city":"Belle Rose",
    "sg:classifiers":[
        {
            "category":"Retail",
            "subcategory":"Repair Shop",
            "type":"Services"
        }
    ],
    "sg:phone":"+1 225 473 8386",
    "sg:postcode":"70341",
    "sg:province":"LA",
    "sg:tags":[
        "welding"
    ],
    "wof:name":"Leblancs Welding",
    "wof:placetype":"venue"
},
  "geometry": {"coordinates":[-91.050922,30.039387],"type":"Point"}
}