{
  "type": "Feature",
  "properties": {
    "iso:country":"US",
    "sg:address":"3861 Peters Rd",
    "sg:city":"Harvey",
    "sg:classifiers":[
        {
            "category":"Professional",
            "subcategory":"Business Services",
            "type":"Services"
        }
    ],
    "sg:phone":"+1 504 366 1667",
    "sg:postcode":"70058",
    "sg:province":"LA",
    "sg:tags":[
        "inspection"
    ],
    "wof:name":"Mandina's Inspection Svc Inc",
    "wof:placetype":"venue"
},
  "geometry": {"coordinates":[-90.056865,29.849892],"type":"Point"}
}