{
  "type": "Feature",
  "properties": {
    "addr:full":"3796 Veterans Memorial Blvd Metairie LA 70006",
    "addr:housenumber":"3796",
    "addr:postcode":"70006",
    "addr:street":"Veterans Memorial Blvd",
    "iso:country":"US",
    "sg:address":"3796 Veterans Memorial Blvd",
    "sg:city":"Metairie",
    "sg:classifiers":[
        {
            "category":"Health Services",
            "subcategory":"Doctor",
            "type":"Services"
        }
    ],
    "sg:phone":"+1 504 885 8869",
    "sg:postcode":"70006",
    "sg:province":"LA",
    "sg:tags":[
        "dentist"
    ],
    "wof:name":"Duane P Delaune DDS",
    "wof:placetype":"venue"
},
  "geometry": {"coordinates":[-90.167897,30.004334],"type":"Point"}
}