{
  "type": "Feature",
  "properties": {
    "iso:country":"US",
    "sg:address":"1938 Winterhalter St",
    "sg:city":"Lake Charles",
    "sg:classifiers":[
        {
            "category":"Real Estate",
            "subcategory":"Real Estate Operator",
            "type":"Services"
        }
    ],
    "sg:phone":"+1 337 433 0621",
    "sg:postcode":"70601",
    "sg:province":"LA",
    "sg:tags":[
        "apartment"
    ],
    "wof:name":"Sunlight Manor Inc",
    "wof:placetype":"venue"
},
  "geometry": {"coordinates":[-93.19367,30.234872],"type":"Point"}
}