{
  "type": "Feature",
  "properties": {
    "addr:full":"205 Allen Ave Jonesboro LA 71251",
    "addr:housenumber":"205",
    "addr:postcode":"71251",
    "addr:street":"Allen Ave",
    "iso:country":"US",
    "sg:address":"205 Allen Ave",
    "sg:city":"Jonesboro",
    "sg:classifiers":[
        {
            "category":"Professional",
            "subcategory":"Business Services",
            "type":"Services"
        }
    ],
    "sg:phone":"+1 318 259 2659",
    "sg:postcode":"71251",
    "sg:province":"LA",
    "sg:tags":[
        "embroidery"
    ],
    "wof:name":"Pine Needle",
    "wof:placetype":"venue"
},
  "geometry": {"coordinates":[-92.715902,32.244147],"type":"Point"}
}