{
  "type": "Feature",
  "properties": {
    "addr:full":"4200 Saxon St Metairie LA 70006",
    "addr:housenumber":"4200",
    "addr:postcode":"70006",
    "addr:street":"Saxon St",
    "iso:country":"US",
    "sg:address":"4200 Saxon St",
    "sg:city":"Metairie",
    "sg:classifiers":[
        {
            "category":"Professional",
            "type":"Services"
        }
    ],
    "sg:phone":"+1 504 737 9422",
    "sg:postcode":"70006",
    "sg:province":"LA",
    "wof:name":"A Wedding of Elegance Inc",
    "wof:placetype":"venue"
},
  "geometry": {"coordinates":[-90.18038799999999,30.008775],"type":"Point"}
}