{
  "type": "Feature",
  "properties": {
    "iso:country":"US",
    "sg:address":"3741 Williams Blvd",
    "sg:city":"Kenner",
    "sg:classifiers":[
        {
            "category":"Retail",
            "subcategory":"Self-service Laundry",
            "type":"Services"
        }
    ],
    "sg:phone":"+1 504 443 5454",
    "sg:postcode":"70065",
    "sg:province":"LA",
    "wof:name":"Sunny Brite Washeteria",
    "wof:placetype":"venue"
},
  "geometry": {"coordinates":[-90.23913,30.024122],"type":"Point"}
}