{
  "type": "Feature",
  "properties": {
    "iso:country":"US",
    "sg:address":"5709 Salmen Ave",
    "sg:city":"New Orleans",
    "sg:classifiers":[
        {
            "category":"Wholesale",
            "subcategory":"Hardware",
            "type":"Manufacturing & Wholesale Goods"
        }
    ],
    "sg:phone":"+1 504 734 0625",
    "sg:postcode":"70123",
    "sg:province":"LA",
    "sg:tags":[
        "fastener"
    ],
    "wof:name":"Drillco Devices LTD",
    "wof:placetype":"venue"
},
  "geometry": {"coordinates":[-90.19521400000001,29.960783],"type":"Point"}
}