{
  "type": "Feature",
  "properties": {
    "iso:country":"US",
    "sg:address":"213 W 15th St",
    "sg:city":"Cut Off",
    "sg:classifiers":[
        {
            "category":"Building & Trades",
            "subcategory":"Construction",
            "type":"Services"
        }
    ],
    "sg:phone":"+1 985 693 3924",
    "sg:postcode":"70345",
    "sg:province":"LA",
    "sg:tags":[
        "concrete",
        "contractor"
    ],
    "wof:name":"Clarence Marts Contractors Inc",
    "wof:placetype":"venue"
},
  "geometry": {"coordinates":[-90.377911,29.562108],"type":"Point"}
}