{
  "type": "Feature",
  "properties": {
    "iso:country":"US",
    "sg:address":"3617 Berkley Hills Ave",
    "sg:city":"Baton Rouge",
    "sg:classifiers":[
        {
            "category":"Professional",
            "subcategory":"Business Services",
            "type":"Services"
        }
    ],
    "sg:phone":"+1 225 291 5827",
    "sg:postcode":"70809",
    "sg:province":"LA",
    "wof:name":"James C Percy",
    "wof:placetype":"venue"
},
  "geometry": {"coordinates":[-91.08160700000001,30.416613],"type":"Point"}
}