{
  "type": "Feature",
  "properties": {
    "iso:country":"US",
    "sg:address":"12615 State Rte 159",
    "sg:city":"Shongaloo",
    "sg:classifiers":[
        {
            "category":"Restaurant",
            "type":"Food & Drink"
        }
    ],
    "sg:phone":"+1 318 846 2235",
    "sg:postcode":"71072",
    "sg:province":"LA",
    "sg:tags":[
        "eating"
    ],
    "wof:name":"Indian Run Family Restaurant",
    "wof:placetype":"venue"
},
  "geometry": {"coordinates":[-93.295704,32.938164],"type":"Point"}
}