{
  "type": "Feature",
  "properties": {
    "iso:country":"US",
    "sg:address":"17618 Old Jefferson Hwy",
    "sg:city":"Prairieville",
    "sg:classifiers":[
        {
            "category":"Manufacturing",
            "subcategory":"Food",
            "type":"Manufacturing & Wholesale Goods"
        }
    ],
    "sg:phone":"+1 225 673 6857",
    "sg:postcode":"70769",
    "sg:province":"LA",
    "sg:tags":[
        "product",
        "manufacturer"
    ],
    "wof:name":"Oak Grove Smoke House Inc",
    "wof:placetype":"venue"
},
  "geometry": {"coordinates":[-90.978604,30.326708],"type":"Point"}
}