{
  "type": "Feature",
  "properties": {
    "iso:country":"US",
    "sg:address":"405 Sinbad St",
    "sg:city":"Baker",
    "sg:classifiers":[
        {
            "category":"Professional",
            "type":"Services"
        }
    ],
    "sg:phone":"+1 225 775 0947",
    "sg:postcode":"70714",
    "sg:province":"LA",
    "wof:name":"Prep Gear & Logo Logo Is AP WI",
    "wof:placetype":"venue"
},
  "geometry": {"coordinates":[-91.146823,30.576488],"type":"Point"}
}