{
  "type": "Feature",
  "properties": {
    "iso:country":"US",
    "sg:address":"279 Ranchtown Rd",
    "sg:city":"Elm Grove",
    "sg:classifiers":[
        {
            "category":"Farming",
            "subcategory":"Farm",
            "type":"Manufacturing & Wholesale Goods"
        }
    ],
    "sg:phone":"+1 318 747 2823",
    "sg:postcode":"71051",
    "sg:province":"LA",
    "sg:tags":[
        "crop",
        "general"
    ],
    "wof:name":"Dun Muvn Farm",
    "wof:placetype":"venue"
},
  "geometry": {"coordinates":[-93.573127,32.389604],"type":"Point"}
}