{
  "type": "Feature",
  "properties": {
    "addr:full":"302 State Rte 3048 Rayville LA 71269",
    "addr:housenumber":"302",
    "addr:postcode":"3048;71269",
    "addr:street":"State Rte",
    "iso:country":"US",
    "sg:address":"302 State Rte 3048",
    "sg:city":"Rayville",
    "sg:classifiers":[
        {
            "category":"Social Services",
            "type":"Services"
        }
    ],
    "sg:phone":"+1 318 728 7819",
    "sg:postcode":"71269",
    "sg:province":"LA",
    "sg:tags":[
        "organization",
        "welfare"
    ],
    "wof:name":"Delta Head Start",
    "wof:placetype":"venue"
},
  "geometry": {"coordinates":[-91.752123,32.469672],"type":"Point"}
}