{
  "type": "Feature",
  "properties": {
    "iso:country":"US",
    "sg:address":"24 Dogwood Ln",
    "sg:city":"Covington",
    "sg:classifiers":[
        {
            "category":"Professional",
            "subcategory":"Management & Consulting",
            "type":"Services"
        }
    ],
    "sg:phone":"+1 985 898 5778",
    "sg:postcode":"70435",
    "sg:province":"LA",
    "sg:tags":[
        "marketing",
        "consultant"
    ],
    "wof:name":"Association Management LLC",
    "wof:placetype":"venue"
},
  "geometry": {"coordinates":[-90.07818899999999,30.497226],"type":"Point"}
}