{
  "type": "Feature",
  "properties": {
    "addr:full":"1716 Juanita St New Iberia LA 70560",
    "addr:housenumber":"1716",
    "addr:postcode":"70560",
    "addr:street":"Juanita St",
    "iso:country":"US",
    "sg:address":"1716 Juanita St",
    "sg:city":"New Iberia",
    "sg:classifiers":[
        {
            "category":"Organizations",
            "subcategory":"Religious Organization",
            "type":"Services"
        }
    ],
    "sg:phone":"+1 337 365 3489",
    "sg:postcode":"70560",
    "sg:province":"LA",
    "wof:name":"Temple Baptist Church",
    "wof:placetype":"venue"
},
  "geometry": {"coordinates":[-91.798947,29.982383],"type":"Point"}
}