{
  "type": "Feature",
  "properties": {
    "iso:country":"US",
    "sg:address":"241 Company Canal Rd",
    "sg:city":"Bourg",
    "sg:classifiers":[
        {
            "category":"Professional",
            "subcategory":"Business Services",
            "type":"Services"
        }
    ],
    "sg:phone":"+1 985 594 1952",
    "sg:postcode":"70343",
    "sg:province":"LA",
    "sg:tags":[
        "broker",
        "merchandise"
    ],
    "wof:name":"M B Brokerage Co LLC",
    "wof:placetype":"venue"
},
  "geometry": {"coordinates":[-90.602609,29.562721],"type":"Point"}
}