{
  "type": "Feature",
  "properties": {
    "iso:country":"US",
    "sg:address":"8120 Mansfield Rd",
    "sg:city":"Shreveport",
    "sg:classifiers":[
        {
            "category":"Professional",
            "subcategory":"Testing Lab",
            "type":"Services"
        }
    ],
    "sg:phone":"+1 318 687 6337",
    "sg:postcode":"71108",
    "sg:province":"LA",
    "sg:tags":[
        "laboratory"
    ],
    "wof:name":"Earth Materials Testing Svc",
    "wof:placetype":"venue"
},
  "geometry": {"coordinates":[-93.786523,32.424626],"type":"Point"}
}