{
  "type": "Feature",
  "properties": {
    "iso:country":"US",
    "sg:address":"120 Meadowcrest St Ste 160",
    "sg:city":"Gretna",
    "sg:classifiers":[
        {
            "category":"Health Services",
            "subcategory":"Doctor",
            "type":"Services"
        }
    ],
    "sg:phone":"+1 504 363 8041",
    "sg:postcode":"70056",
    "sg:province":"LA",
    "sg:tags":[
        "medicine",
        "practice",
        "internal",
        "family"
    ],
    "wof:name":"Westside Clinics",
    "wof:placetype":"venue"
},
  "geometry": {"coordinates":[-90.030998,29.889],"type":"Point"}
}