{
  "type": "Feature",
  "properties": {
    "iso:country":"US",
    "sg:address":"107 Front St",
    "sg:city":"Vidalia",
    "sg:classifiers":[
        {
            "category":"Health Services",
            "subcategory":"Health Practitioner",
            "type":"Services"
        }
    ],
    "sg:phone":"+1 318 336 2224",
    "sg:postcode":"71343",
    "sg:province":"LA",
    "sg:tags":[
        "therapist",
        "physical"
    ],
    "wof:name":"River Park Sports Medicine",
    "wof:placetype":"venue"
},
  "geometry": {"coordinates":[-91.81113000000001,31.627515],"type":"Point"}
}