{
  "type": "Feature",
  "properties": {
    "addr:full":"48097 Tin Can Aly Tickfaw LA 70466",
    "addr:housenumber":"48097",
    "addr:postcode":"70466",
    "addr:street":"Tin",
    "iso:country":"US",
    "sg:address":"48097 Tin Can Aly",
    "sg:city":"Tickfaw",
    "sg:classifiers":[
        {
            "category":"Building & Trades",
            "subcategory":"Equipment Rental",
            "type":"Services"
        }
    ],
    "sg:phone":"+1 985 429 0202",
    "sg:postcode":"70466",
    "sg:province":"LA",
    "sg:tags":[
        "yard"
    ],
    "wof:name":"One Stop Party Rental & Floral",
    "wof:placetype":"venue"
},
  "geometry": {"coordinates":[-90.448566,30.549977],"type":"Point"}
}