{
  "type": "Feature",
  "properties": {
    "iso:country":"US",
    "sg:address":"820 Decatur St",
    "sg:city":"New Orleans",
    "sg:classifiers":[
        {
            "category":"Shopping",
            "type":"Retail Goods"
        }
    ],
    "sg:phone":"+1 504 522 7860",
    "sg:postcode":"70116",
    "sg:province":"LA",
    "sg:tags":[
        "outdoor",
        "lighting",
        "specialty"
    ],
    "wof:name":"Merry Christmas & All That",
    "wof:placetype":"venue"
},
  "geometry": {"coordinates":[-90.061806,29.957656],"type":"Point"}
}