{
  "type": "Feature",
  "properties": {
    "iso:country":"US",
    "sg:address":"25894 Shadow Brook Ave",
    "sg:city":"Denham Springs",
    "sg:classifiers":[
        {
            "category":"Professional",
            "subcategory":"Business Services",
            "type":"Services"
        }
    ],
    "sg:phone":"+1 225 667 4301",
    "sg:postcode":"70726",
    "sg:province":"LA",
    "wof:name":"Rachel Beard",
    "wof:placetype":"venue"
},
  "geometry": {"coordinates":[-90.93847700000001,30.445075],"type":"Point"}
}