{
  "type": "Feature",
  "properties": {
    "iso:country":"US",
    "sg:address":"510 N 3rd St",
    "sg:city":"Monroe",
    "sg:classifiers":[
        {
            "category":"Retail",
            "subcategory":"Auto Repair",
            "type":"Services"
        }
    ],
    "sg:phone":"+1 318 323 6837",
    "sg:postcode":"71201",
    "sg:province":"LA",
    "sg:tags":[
        "general"
    ],
    "wof:name":"Getchells Tune Up Center",
    "wof:placetype":"venue"
},
  "geometry": {"coordinates":[-92.119202,32.507098],"type":"Point"}
}