{
  "type": "Feature",
  "properties": {
    "addr:full":"12496 Airline Hwy Gonzales LA 70737",
    "addr:housenumber":"12496",
    "addr:postcode":"70737",
    "addr:street":"Airline Hwy Gonzales La",
    "iso:country":"US",
    "sg:address":"12496 Airline Hwy",
    "sg:city":"Gonzales",
    "sg:classifiers":[
        {
            "category":"Bars & Pubs",
            "type":"Food & Drink"
        }
    ],
    "sg:phone":"+1 225 644 2327",
    "sg:postcode":"70737",
    "sg:province":"LA",
    "sg:tags":[
        "club",
        "night"
    ],
    "wof:name":"Bayou Bar",
    "wof:placetype":"venue"
},
  "geometry": {"coordinates":[-90.929354,30.255711],"type":"Point"}
}