{
  "type": "Feature",
  "properties": {
    "iso:country":"US",
    "sg:address":"100 Park Dr",
    "sg:city":"Covington",
    "sg:classifiers":[
        {
            "category":"Restaurant",
            "type":"Food & Drink"
        }
    ],
    "sg:menulink":"http://www.allmenus.com/la/madisonville/29411-outback-steakhouse/menu/",
    "sg:phone":"+1 985 893 0505",
    "sg:postcode":"70433",
    "sg:province":"LA",
    "sg:tags":[
        "american",
        "steakhouse"
    ],
    "wof:name":"Outback Steakhouse",
    "wof:placetype":"venue"
},
  "geometry": {"coordinates":[-90.09480000000001,30.472219],"type":"Point"}
}