{
  "type": "Feature",
  "properties": {
    "addr:full":"1758 Elliott St Alexandria LA 71301",
    "addr:housenumber":"1758",
    "addr:postcode":"71301",
    "addr:street":"Elliott St",
    "iso:country":"US",
    "sg:address":"1758 Elliott St",
    "sg:city":"Alexandria",
    "sg:classifiers":[
        {
            "category":"Banks & Credit Unions",
            "subcategory":"Investment Brokerage",
            "type":"Services"
        }
    ],
    "sg:phone":"+1 318 767 1127",
    "sg:postcode":"71301",
    "sg:province":"LA",
    "sg:tags":[
        "consultant",
        "planning",
        "financial"
    ],
    "wof:name":"Cenla Financial Planners",
    "wof:placetype":"venue"
},
  "geometry": {"coordinates":[-92.458378,31.304389],"type":"Point"}
}