{
  "type": "Feature",
  "properties": {
    "iso:country":"US",
    "sg:address":"100 Thomas St",
    "sg:city":"Abbeville",
    "sg:classifiers":[
        {
            "category":"Shopping",
            "type":"Retail Goods"
        }
    ],
    "sg:phone":"+1 337 898 6163",
    "sg:postcode":"70510",
    "sg:province":"LA",
    "sg:tags":[
        "hearing",
        "equipment",
        "supply",
        "impaired"
    ],
    "wof:name":"Better Hearing Ctr",
    "wof:placetype":"venue"
},
  "geometry": {"coordinates":[-92.145011,29.978102],"type":"Point"}
}