{
  "type": "Feature",
  "properties": {
    "iso:country":"US",
    "sg:address":"3701 Lake Timberlane Dr",
    "sg:city":"Gretna",
    "sg:classifiers":[
        {
            "category":"Professional",
            "subcategory":"Management & Consulting",
            "type":"Services"
        }
    ],
    "sg:phone":"+1 504 392 1095",
    "sg:postcode":"70056",
    "sg:province":"LA",
    "sg:tags":[
        "business"
    ],
    "wof:name":"Hamps Business Consultan",
    "wof:placetype":"venue"
},
  "geometry": {"coordinates":[-90.031623,29.852698],"type":"Point"}
}