{
  "type": "Feature",
  "properties": {
    "iso:country":"US",
    "sg:address":"37318 Cornerview Rd",
    "sg:city":"Geismar",
    "sg:classifiers":[
        {
            "category":"Manufacturing",
            "subcategory":"Motor Vehicles & Parts",
            "type":"Manufacturing & Wholesale Goods"
        }
    ],
    "sg:phone":"+1 225 673 6103",
    "sg:postcode":"70734",
    "sg:province":"LA",
    "sg:tags":[
        "bearing"
    ],
    "wof:name":"Quality Bearings & Machine",
    "wof:placetype":"venue"
},
  "geometry": {"coordinates":[-90.988043,30.240132],"type":"Point"}
}