{
  "type": "Feature",
  "properties": {
    "iso:country":"US",
    "sg:address":"200 State Rte 100",
    "sg:city":"Ville Platte",
    "sg:classifiers":[
        {
            "category":"Government",
            "subcategory":"Police Station",
            "type":"Public Place"
        }
    ],
    "sg:phone":"+1 337 363 2161",
    "sg:postcode":"70531",
    "sg:province":"LA",
    "sg:tags":[
        "sheriff"
    ],
    "wof:name":"Evangeline Parish Sheriff",
    "wof:placetype":"venue"
},
  "geometry": {"coordinates":[-92.50120699999999,30.250121],"type":"Point"}
}