{
  "type": "Feature",
  "properties": {
    "iso:country":"US",
    "sg:address":"2404 Ferrand St",
    "sg:city":"Monroe",
    "sg:classifiers":[
        {
            "category":"Building & Trades",
            "subcategory":"Construction",
            "type":"Services"
        }
    ],
    "sg:phone":"+1 318 329 0203",
    "sg:postcode":"71201",
    "sg:province":"LA",
    "sg:tags":[
        "general",
        "contractor"
    ],
    "wof:name":"Sauter Construction Co Inc",
    "wof:placetype":"venue"
},
  "geometry": {"coordinates":[-92.082534,32.529665],"type":"Point"}
}