{
  "type": "Feature",
  "properties": {
    "iso:country":"US",
    "sg:address":"7601 Andrea Dr",
    "sg:city":"Baton Rouge",
    "sg:classifiers":[
        {
            "category":"Restaurant",
            "type":"Food & Drink"
        }
    ],
    "sg:menulink":"http://www.allmenus.com/la/baton-rouge/173683-wendys/menu/",
    "sg:phone":"+1 225 291 0026",
    "sg:postcode":"70809",
    "sg:province":"LA",
    "sg:tags":[
        "burger",
        "american",
        "soup"
    ],
    "wof:name":"Wendy's",
    "wof:placetype":"venue"
},
  "geometry": {"coordinates":[-91.066069,30.378753],"type":"Point"}
}