{
  "type": "Feature",
  "properties": {
    "iso:country":"US",
    "sg:address":"118 Ridgelake Dr",
    "sg:city":"Metairie",
    "sg:classifiers":[
        {
            "category":"Health Services",
            "subcategory":"Health Practitioner",
            "type":"Services"
        }
    ],
    "sg:phone":"+1 504 834 2775",
    "sg:postcode":"70001",
    "sg:province":"LA",
    "sg:tags":[
        "psychologist"
    ],
    "wof:name":"Scuddy F Fontenelle III PHD",
    "wof:placetype":"venue"
},
  "geometry": {"coordinates":[-90.154658,29.978696],"type":"Point"}
}