{
  "type": "Feature",
  "properties": {
    "iso:country":"US",
    "sg:address":"9000 Mansfield Rd",
    "sg:city":"Shreveport",
    "sg:classifiers":[
        {
            "category":"Autos & Motor Vehicles",
            "subcategory":"Fuel & Gas Station",
            "type":"Retail Goods"
        }
    ],
    "sg:phone":"+1 318 688 3103",
    "sg:postcode":"71118",
    "sg:province":"LA",
    "sg:tags":[
        "oil"
    ],
    "wof:name":"Village Exxon",
    "wof:placetype":"venue"
},
  "geometry": {"coordinates":[-93.79859399999999,32.408102],"type":"Point"}
}