{
  "type": "Feature",
  "properties": {
    "iso:country":"US",
    "sg:address":"3901 Magazine St",
    "sg:city":"New Orleans",
    "sg:classifiers":[
        {
            "category":"Shopping",
            "type":"Retail Goods"
        }
    ],
    "sg:phone":"+1 504 891 1005",
    "sg:postcode":"70115",
    "sg:province":"LA",
    "sg:tags":[
        "wedding",
        "supply"
    ],
    "wof:name":"Wedding Bells",
    "wof:placetype":"venue"
},
  "geometry": {"coordinates":[-90.09573399999999,29.921227],"type":"Point"}
}