{
  "type": "Feature",
  "properties": {
    "iso:country":"US",
    "sg:address":"3236 S Carrollton Ave",
    "sg:city":"New Orleans",
    "sg:classifiers":[
        {
            "category":"Professional",
            "subcategory":"Accounting & Tax Preparation",
            "type":"Services"
        }
    ],
    "sg:phone":"+1 504 942 8000",
    "sg:postcode":"70118",
    "sg:province":"LA",
    "sg:tags":[
        "return",
        "filing"
    ],
    "wof:name":"Fast Tax",
    "wof:placetype":"venue"
},
  "geometry": {"coordinates":[-90.11391999999999,29.962202],"type":"Point"}
}