{
  "type": "Feature",
  "properties": {
    "iso:country":"US",
    "sg:address":"213 W 21st Ave",
    "sg:city":"Covington",
    "sg:classifiers":[
        {
            "category":"Banks & Credit Unions",
            "subcategory":"Bank",
            "type":"Services"
        }
    ],
    "sg:phone":"+1 985 893 7712",
    "sg:postcode":"70433",
    "sg:province":"LA",
    "sg:tags":[
        "loan",
        "real estate"
    ],
    "wof:name":"Premier Mortgage Funding Inc",
    "wof:placetype":"venue"
},
  "geometry": {"coordinates":[-90.10269700000001,30.476323],"type":"Point"}
}