{
  "type": "Feature",
  "properties": {
    "addr:full":"927 N Western Ave Crowley LA 70526",
    "addr:housenumber":"927",
    "addr:postcode":"70526",
    "addr:street":"N Western Ave",
    "iso:country":"US",
    "sg:address":"927 N Western Ave",
    "sg:city":"Crowley",
    "sg:classifiers":[
        {
            "category":"Personal",
            "subcategory":"Beauty Salon",
            "type":"Services"
        }
    ],
    "sg:phone":"+1 337 788 1144",
    "sg:postcode":"70526",
    "sg:province":"LA",
    "wof:name":"Debra's Hair Studio",
    "wof:placetype":"venue"
},
  "geometry": {"coordinates":[-92.38385,30.215466],"type":"Point"}
}