{
  "type": "Feature",
  "properties": {
    "iso:country":"US",
    "sg:address":"18680 Hwy 9",
    "sg:city":"Arcadia",
    "sg:classifiers":[
        {
            "category":"Retail",
            "subcategory":"Funeral Services",
            "type":"Services"
        }
    ],
    "sg:phone":"+1 318 263 9494",
    "sg:postcode":"71001",
    "sg:province":"LA",
    "sg:tags":[
        "director"
    ],
    "wof:name":"Memorial Funeral Home",
    "wof:placetype":"venue"
},
  "geometry": {"coordinates":[-92.94028299999999,32.561518],"type":"Point"}
}