{
  "type": "Feature",
  "properties": {
    "iso:country":"US",
    "sg:address":"22899 Hwy 22",
    "sg:city":"Maurepas",
    "sg:classifiers":[
        {
            "category":"Bars & Pubs",
            "type":"Food & Drink"
        }
    ],
    "sg:phone":"+1 225 695 3879",
    "sg:postcode":"70449",
    "sg:province":"LA",
    "sg:tags":[
        "club",
        "night"
    ],
    "wof:name":"Nolan's Hangout",
    "wof:placetype":"venue"
},
  "geometry": {"coordinates":[-90.708511,30.27908],"type":"Point"}
}