{
  "type": "Feature",
  "properties": {
    "iso:country":"US",
    "sg:address":"2600 Delaware Ave",
    "sg:city":"Kenner",
    "sg:classifiers":[
        {
            "category":"Retail",
            "subcategory":"Auto Repair",
            "type":"Services"
        }
    ],
    "sg:phone":"+1 504 469 4811",
    "sg:postcode":"70062",
    "sg:province":"LA",
    "sg:tags":[
        "body"
    ],
    "wof:name":"B & L Auto Repair",
    "wof:placetype":"venue"
},
  "geometry": {"coordinates":[-90.24262899999999,30.005155],"type":"Point"}
}