{
  "type": "Feature",
  "properties": {
    "addr:full":"4830 Lake St Lake Charles LA 70605",
    "addr:housenumber":"4830",
    "addr:postcode":"70605",
    "addr:street":"Lake St",
    "iso:country":"US",
    "sg:address":"4830 Lake St",
    "sg:city":"Lake Charles",
    "sg:classifiers":[
        {
            "category":"Professional",
            "subcategory":"Lawyer & Legal Services",
            "type":"Services"
        }
    ],
    "sg:phone":"+1 337 562 1116",
    "sg:postcode":"70605",
    "sg:province":"LA",
    "sg:tags":[
        "attorney"
    ],
    "wof:name":"L Donald Foreman & Assoc",
    "wof:placetype":"venue"
},
  "geometry": {"coordinates":[-93.232411,30.171152],"type":"Point"}
}