{
  "type": "Feature",
  "properties": {
    "iso:country":"US",
    "sg:address":"1106 Coolidge St",
    "sg:city":"Lafayette",
    "sg:classifiers":[
        {
            "category":"Organizations",
            "subcategory":"Political Organization",
            "type":"Services"
        }
    ],
    "sg:phone":"+1 337 291 9500",
    "sg:postcode":"70503",
    "sg:province":"LA",
    "wof:name":"Republican Party Of Lafayette",
    "wof:placetype":"venue"
},
  "geometry": {"coordinates":[-92.01824999999999,30.202926],"type":"Point"}
}