{
  "type": "Feature",
  "properties": {
    "iso:country":"US",
    "sg:address":"4513 Zenith St",
    "sg:city":"Metairie",
    "sg:classifiers":[
        {
            "category":"Shopping",
            "type":"Retail Goods"
        }
    ],
    "sg:phone":"+1 504 837 1711",
    "sg:postcode":"70001",
    "sg:province":"LA",
    "sg:tags":[
        "coin",
        "dealer",
        "supply"
    ],
    "sg:website":"www.scpm.com",
    "wof:name":"Southern Coins & Precious Mtls",
    "wof:placetype":"venue"
},
  "geometry": {"coordinates":[-90.18176,29.995059],"type":"Point"}
}