{
  "type": "Feature",
  "properties": {
    "addr:full":"4013 Ames Blvd Marrero LA 70072",
    "addr:housenumber":"4013",
    "addr:postcode":"70072",
    "addr:street":"Ames Blvd Marrero",
    "iso:country":"US",
    "sg:address":"4013 Ames Blvd",
    "sg:city":"Marrero",
    "sg:classifiers":[
        {
            "category":"Professional",
            "subcategory":"Business Services",
            "type":"Services"
        }
    ],
    "sg:phone":"+1 504 340 3778",
    "sg:postcode":"70072",
    "sg:province":"LA",
    "sg:tags":[
        "paralegal"
    ],
    "wof:name":"Paralegal",
    "wof:placetype":"venue"
},
  "geometry": {"coordinates":[-90.10809999999999,29.845483],"type":"Point"}
}