{
  "type": "Feature",
  "properties": {
    "addr:full":"613 Ashbourne Dr Shreveport LA 71106",
    "addr:housenumber":"613",
    "addr:postcode":"71106",
    "addr:street":"Ashbourne Dr",
    "iso:country":"US",
    "sg:address":"613 Ashbourne Dr",
    "sg:city":"Shreveport",
    "sg:classifiers":[
        {
            "category":"Organizations",
            "subcategory":"Religious Organization",
            "type":"Services"
        }
    ],
    "sg:phone":"+1 318 868 4991",
    "sg:postcode":"71106",
    "sg:province":"LA",
    "sg:tags":[
        "church"
    ],
    "sg:website":"www.vcfshreveport.org",
    "wof:name":"Vineyard Christian Fellowship",
    "wof:placetype":"venue"
},
  "geometry": {"coordinates":[-93.73843599999999,32.430346],"type":"Point"}
}