{
  "type": "Feature",
  "properties": {
    "addr:full":"17751 Crossett Rd Bastrop LA 71220",
    "addr:postcode":"17751;71220",
    "addr:street":"Crossett Rd",
    "iso:country":"US",
    "sg:address":"17751 Crossett Rd",
    "sg:city":"Bastrop",
    "sg:classifiers":[
        {
            "category":"Autos & Motor Vehicles",
            "subcategory":"Fuel & Gas Station",
            "type":"Retail Goods"
        }
    ],
    "sg:phone":"+1 318 281 9156",
    "sg:postcode":"71220",
    "sg:province":"LA",
    "sg:tags":[
        "plaza",
        "truck",
        "stops"
    ],
    "wof:name":"Norsworthy's Cafe",
    "wof:placetype":"venue"
},
  "geometry": {"coordinates":[-91.923356,32.970764],"type":"Point"}
}