{
  "type": "Feature",
  "properties": {
    "iso:country":"US",
    "sg:address":"800 W Virtue St",
    "sg:city":"Chalmette",
    "sg:classifiers":[
        {
            "category":"Health Services",
            "subcategory":"Doctor",
            "type":"Services"
        }
    ],
    "sg:phone":"+1 504 270 0908",
    "sg:postcode":"70043",
    "sg:province":"LA",
    "sg:tags":[
        "medical"
    ],
    "wof:name":"Vadiee Abdolreza",
    "wof:placetype":"venue"
},
  "geometry": {"coordinates":[-89.965046,29.958074],"type":"Point"}
}