{
  "type": "Feature",
  "properties": {
    "addr:full":"311 Chennault St Morgan City LA 70380",
    "addr:housenumber":"311",
    "addr:postcode":"70380",
    "addr:street":"Chennault St",
    "iso:country":"US",
    "sg:address":"311 Chennault St",
    "sg:city":"Morgan City",
    "sg:classifiers":[
        {
            "category":"Professional",
            "subcategory":"Computer Services",
            "type":"Services"
        }
    ],
    "sg:phone":"+1 985 385 2219",
    "sg:postcode":"70380",
    "sg:province":"LA",
    "sg:tags":[
        "internet"
    ],
    "wof:name":"Petronet",
    "wof:placetype":"venue"
},
  "geometry": {"coordinates":[-91.16768399999999,29.69186],"type":"Point"}
}