{
  "type": "Feature",
  "properties": {
    "iso:country":"US",
    "sg:address":"6801 Franklin Ave",
    "sg:city":"New Orleans",
    "sg:classifiers":[
        {
            "category":"Professional",
            "subcategory":"Business Services",
            "type":"Services"
        }
    ],
    "sg:phone":"+1 504 286 5611",
    "sg:postcode":"70122",
    "sg:province":"LA",
    "sg:tags":[
        "fund",
        "promotion",
        "raising"
    ],
    "wof:name":"Scooter Promotions",
    "wof:placetype":"venue"
},
  "geometry": {"coordinates":[-90.05222000000001,30.029264],"type":"Point"}
}