{
  "type": "Feature",
  "properties": {
    "iso:country":"US",
    "sg:address":"6552 D'Juanna Dr",
    "sg:city":"Baton Rouge",
    "sg:classifiers":[
        {
            "category":"Professional",
            "subcategory":"Accounting & Tax Preparation",
            "type":"Services"
        }
    ],
    "sg:phone":"+1 225 359 6786",
    "sg:postcode":"70811",
    "sg:province":"LA",
    "sg:tags":[
        "return",
        "filing"
    ],
    "wof:name":"Quincy Enterprises",
    "wof:placetype":"venue"
},
  "geometry": {"coordinates":[-91.128394,30.521134],"type":"Point"}
}