{
  "type": "Feature",
  "properties": {
    "addr:full":"5040 Florida Blvd Baton Rouge LA 70806",
    "addr:housenumber":"5040",
    "addr:postcode":"70806",
    "addr:street":"Florida Blvd",
    "iso:country":"US",
    "sg:address":"5040 Florida Blvd",
    "sg:city":"Baton Rouge",
    "sg:classifiers":[
        {
            "category":"Government",
            "subcategory":"Office",
            "type":"Public Place"
        }
    ],
    "sg:phone":"+1 225 248 4190",
    "sg:postcode":"70806",
    "sg:province":"LA",
    "sg:tags":[
        "state",
        "program"
    ],
    "wof:name":"Transportation Dept",
    "wof:placetype":"venue"
},
  "geometry": {"coordinates":[-91.13784099999999,30.450875],"type":"Point"}
}