{
  "type": "Feature",
  "properties": {
    "iso:country":"US",
    "sg:address":"433 Plaza St",
    "sg:city":"Bogalusa",
    "sg:classifiers":[
        {
            "category":"Health Services",
            "subcategory":"Doctor",
            "type":"Services"
        }
    ],
    "sg:phone":"+1 985 735 6408",
    "sg:postcode":"70427",
    "sg:province":"LA",
    "sg:tags":[
        "physician",
        "surgeon"
    ],
    "wof:name":"Susan A Crawford MD",
    "wof:placetype":"venue"
},
  "geometry": {"coordinates":[-89.867893,30.779155],"type":"Point"}
}