{
  "type": "Feature",
  "properties": {
    "addr:full":"7005 Magnolia Ct Metairie LA 70003",
    "addr:housenumber":"7005",
    "addr:postcode":"70003",
    "addr:street":"Magnolia Ct",
    "iso:country":"US",
    "sg:address":"7005 Magnolia Ct",
    "sg:city":"Metairie",
    "sg:classifiers":[
        {
            "category":"Professional",
            "subcategory":"Management & Consulting",
            "type":"Services"
        }
    ],
    "sg:phone":"+1 504 620 1109",
    "sg:postcode":"70003",
    "sg:province":"LA",
    "sg:tags":[
        "marketing",
        "program"
    ],
    "wof:name":"Central Marketing",
    "wof:placetype":"venue"
},
  "geometry": {"coordinates":[-90.219556,30.006871],"type":"Point"}
}