{
  "type": "Feature",
  "properties": {
    "iso:country":"US",
    "sg:address":"39 Beresford Dr",
    "sg:city":"Metairie",
    "sg:classifiers":[
        {
            "category":"Real Estate",
            "subcategory":"Real Estate Agent",
            "type":"Services"
        }
    ],
    "sg:phone":"+1 504 908 6751",
    "sg:postcode":"70005",
    "sg:province":"LA",
    "wof:name":"Keever Realty",
    "wof:placetype":"venue"
},
  "geometry": {"coordinates":[-90.138801,29.973836],"type":"Point"}
}