{
  "type": "Feature",
  "properties": {
    "iso:country":"US",
    "sg:address":"343 Chippewa St",
    "sg:city":"Baton Rouge",
    "sg:classifiers":[
        {
            "category":"Government",
            "subcategory":"Office",
            "type":"Public Place"
        }
    ],
    "sg:phone":"+1 225 389 3254",
    "sg:postcode":"70805",
    "sg:province":"LA",
    "sg:tags":[
        "city",
        "program"
    ],
    "wof:name":"Baton Rouge Waste Management",
    "wof:placetype":"venue"
},
  "geometry": {"coordinates":[-91.1857,30.471446],"type":"Point"}
}