{
  "type": "Feature",
  "properties": {
    "addr:full":"2806 Ryan St Lake Charles LA 70601",
    "addr:housenumber":"2806",
    "addr:postcode":"70601",
    "addr:street":"Ryan St",
    "iso:country":"US",
    "sg:address":"2806 Ryan St",
    "sg:city":"Lake Charles",
    "sg:classifiers":[
        {
            "category":"Shopping",
            "subcategory":"Stationery & Office Supplies",
            "type":"Retail Goods"
        }
    ],
    "sg:phone":"+1 337 439 7996",
    "sg:postcode":"70601",
    "sg:province":"LA",
    "sg:website":"www.officedepot.com",
    "wof:name":"Office Depot",
    "wof:placetype":"venue"
},
  "geometry": {"coordinates":[-93.218732,30.204451],"type":"Point"}
}