{
  "type": "Feature",
  "properties": {
    "addr:full":"5801 Hwy 56 Chauvin LA 70344",
    "addr:housenumber":"5801",
    "addr:postcode":"70344",
    "addr:street":"Hwy 56 Chauvin",
    "iso:country":"US",
    "sg:address":"5801 Hwy 56",
    "sg:city":"Chauvin",
    "sg:classifiers":[
        {
            "category":"Autos & Motor Vehicles",
            "subcategory":"Fuel & Gas Station",
            "type":"Retail Goods"
        }
    ],
    "sg:phone":"+1 985 594 2252",
    "sg:postcode":"70344",
    "sg:province":"LA",
    "sg:tags":[
        "oil"
    ],
    "wof:name":"Randall's Mobil",
    "wof:placetype":"venue"
},
  "geometry": {"coordinates":[-90.60334899999999,29.419472],"type":"Point"}
}