{
  "type": "Feature",
  "properties": {
    "iso:country":"US",
    "sg:address":"7617 Avon Park Blvd",
    "sg:city":"New Orleans",
    "sg:classifiers":[
        {
            "category":"Manufacturing",
            "subcategory":"Printing",
            "type":"Manufacturing & Wholesale Goods"
        }
    ],
    "sg:phone":"+1 504 245 8637",
    "sg:postcode":"70128",
    "sg:province":"LA",
    "sg:tags":[
        "publishing"
    ],
    "wof:name":"Orgena Enterprises LTD",
    "wof:placetype":"venue"
},
  "geometry": {"coordinates":[-89.94544500000001,30.066985],"type":"Point"}
}