{
  "type": "Feature",
  "properties": {
    "iso:country":"US",
    "sg:address":"504 Churchman Rd",
    "sg:city":"Deridder",
    "sg:classifiers":[
        {
            "category":"Farming",
            "subcategory":"Livestock Farm",
            "type":"Manufacturing & Wholesale Goods"
        }
    ],
    "sg:phone":"+1 337 463 3445",
    "sg:postcode":"70634",
    "sg:province":"LA",
    "sg:tags":[
        "beef",
        "feedlot",
        "cattle"
    ],
    "wof:name":"William Churchman",
    "wof:placetype":"venue"
},
  "geometry": {"coordinates":[-93.133786,30.905178],"type":"Point"}
}