{
  "type": "Feature",
  "properties": {
    "iso:country":"US",
    "sg:address":"3109 Common St",
    "sg:city":"Lake Charles",
    "sg:classifiers":[
        {
            "category":"Mining & Drilling",
            "type":"Manufacturing & Wholesale Goods"
        }
    ],
    "sg:phone":"+1 337 436 5004",
    "sg:postcode":"70601",
    "sg:province":"LA",
    "sg:tags":[
        "field",
        "oil"
    ],
    "wof:name":"Torch Operating Co",
    "wof:placetype":"venue"
},
  "geometry": {"coordinates":[-93.213964,30.198386],"type":"Point"}
}