{
  "type": "Feature",
  "properties": {
    "iso:country":"US",
    "sg:address":"1633 Katlan St",
    "sg:city":"Metairie",
    "sg:classifiers":[
        {
            "category":"Real Estate",
            "subcategory":"Real Estate Operator",
            "type":"Services"
        }
    ],
    "sg:phone":"+1 504 833 3070",
    "sg:postcode":"70001",
    "sg:province":"LA",
    "sg:tags":[
        "apartment"
    ],
    "wof:name":"Chateau Lori",
    "wof:placetype":"venue"
},
  "geometry": {"coordinates":[-90.16276499999999,29.97225],"type":"Point"}
}