{
  "type": "Feature",
  "properties": {
    "addr:full":"945 Beechgrove Blvd Westwego LA 70094",
    "addr:housenumber":"945",
    "addr:postcode":"70094",
    "addr:street":"Beechgrove Blvd Westwego",
    "iso:country":"US",
    "sg:address":"945 Beechgrove Blvd",
    "sg:city":"Westwego",
    "sg:classifiers":[
        {
            "category":"Real Estate",
            "subcategory":"Real Estate Operator",
            "type":"Services"
        }
    ],
    "sg:phone":"+1 504 436 0274",
    "sg:postcode":"70094",
    "sg:province":"LA",
    "sg:tags":[
        "apartment"
    ],
    "wof:name":"Beechgrove Apartments",
    "wof:placetype":"venue"
},
  "geometry": {"coordinates":[-90.158912,29.909919],"type":"Point"}
}