{
  "type": "Feature",
  "properties": {
    "iso:country":"US",
    "sg:address":"5537 Amite Dr",
    "sg:city":"Marrero",
    "sg:classifiers":[
        {
            "category":"Real Estate",
            "subcategory":"Real Estate Services",
            "type":"Services"
        }
    ],
    "sg:phone":"+1 504 328 3307",
    "sg:postcode":"70072",
    "sg:province":"LA",
    "wof:name":"Premier Abstract Co",
    "wof:placetype":"venue"
},
  "geometry": {"coordinates":[-90.10902900000001,29.865984],"type":"Point"}
}