{
  "type": "Feature",
  "properties": {
    "iso:country":"US",
    "sg:address":"1017 Harimaw Ct E",
    "sg:city":"Metairie",
    "sg:classifiers":[
        {
            "category":"Wholesale",
            "subcategory":"Seafood",
            "type":"Manufacturing & Wholesale Goods"
        }
    ],
    "sg:phone":"+1 504 833 6349",
    "sg:postcode":"70001",
    "sg:province":"LA",
    "wof:name":"T Cvitanovich & Seafood",
    "wof:placetype":"venue"
},
  "geometry": {"coordinates":[-90.134683,29.9712],"type":"Point"}
}