{
  "type": "Feature",
  "properties": {
    "iso:country":"US",
    "sg:address":"833 Orleans Ave",
    "sg:city":"New Orleans",
    "sg:classifiers":[
        {
            "category":"Professional",
            "subcategory":"Lawyer & Legal Services",
            "type":"Services"
        }
    ],
    "sg:phone":"+1 504 529 2450",
    "sg:postcode":"70116",
    "sg:province":"LA",
    "sg:tags":[
        "attorney"
    ],
    "wof:name":"Cooley L V IV A Prof Law Corp",
    "wof:placetype":"venue"
},
  "geometry": {"coordinates":[-90.06586,29.959496],"type":"Point"}
}