{
  "type": "Feature",
  "properties": {
    "iso:country":"US",
    "sg:address":"5175 Government St",
    "sg:city":"Baton Rouge",
    "sg:classifiers":[
        {
            "category":"Shopping",
            "subcategory":"Used Merchandise",
            "type":"Retail Goods"
        }
    ],
    "sg:phone":"+1 225 926 0456",
    "sg:postcode":"70806",
    "sg:province":"LA",
    "sg:tags":[
        "pawnbroker"
    ],
    "wof:name":"American Pawn",
    "wof:placetype":"venue"
},
  "geometry": {"coordinates":[-91.138491,30.44457],"type":"Point"}
}