{
  "type": "Feature",
  "properties": {
    "iso:country":"US",
    "sg:address":"111 E Kings Hwy",
    "sg:city":"Shreveport",
    "sg:classifiers":[
        {
            "category":"Home & Garden",
            "subcategory":"Garden Supply",
            "type":"Retail Goods"
        }
    ],
    "sg:phone":"+1 318 865 0001",
    "sg:postcode":"71104",
    "sg:province":"LA",
    "sg:tags":[
        "center"
    ],
    "wof:name":"Mrs Mc Gregor's Garden",
    "wof:placetype":"venue"
},
  "geometry": {"coordinates":[-93.729899,32.481859],"type":"Point"}
}