{
  "type": "Feature",
  "properties": {
    "iso:country":"US",
    "sg:address":"11888 Old Hammond Hwy",
    "sg:city":"Baton Rouge",
    "sg:classifiers":[
        {
            "category":"Real Estate",
            "subcategory":"Real Estate Operator",
            "type":"Services"
        }
    ],
    "sg:phone":"+1 225 272 5177",
    "sg:postcode":"70816",
    "sg:province":"LA",
    "sg:tags":[
        "apartment"
    ],
    "wof:name":"Spires Of Sherwood Apartments",
    "wof:placetype":"venue"
},
  "geometry": {"coordinates":[-91.055313,30.437266],"type":"Point"}
}