{
  "type": "Feature",
  "properties": {
    "iso:country":"US",
    "sg:address":"3868 Gentilly Blvd",
    "sg:city":"New Orleans",
    "sg:classifiers":[
        {
            "category":"Food & Beverages",
            "subcategory":"Groceries & Convenience Stores",
            "type":"Retail Goods"
        }
    ],
    "sg:phone":"+1 504 944 4566",
    "sg:postcode":"70122",
    "sg:province":"LA",
    "sg:tags":[
        "grocer"
    ],
    "wof:name":"Gentilly Food Market",
    "wof:placetype":"venue"
},
  "geometry": {"coordinates":[-90.046639,30.002724],"type":"Point"}
}