{
  "type": "Feature",
  "properties": {
    "addr:full":"705 6th St NW Springhill LA 71075",
    "addr:housenumber":"705",
    "addr:postcode":"71075",
    "addr:street":"6Th St Nw",
    "iso:country":"US",
    "sg:address":"705 6th St NW",
    "sg:city":"Springhill",
    "sg:classifiers":[
        {
            "category":"Personal",
            "subcategory":"Beauty Salon",
            "type":"Services"
        }
    ],
    "sg:phone":"+1 318 539 3992",
    "sg:postcode":"71075",
    "sg:province":"LA",
    "wof:name":"Sherry S Beauty Shop",
    "wof:placetype":"venue"
},
  "geometry": {"coordinates":[-93.468856,33.009965],"type":"Point"}
}