{
  "type": "Feature",
  "properties": {
    "iso:country":"US",
    "sg:address":"2816 Meriwether Rd",
    "sg:city":"Shreveport",
    "sg:classifiers":[
        {
            "category":"Retail",
            "subcategory":"Auto Repair",
            "type":"Services"
        }
    ],
    "sg:phone":"+1 318 686 0800",
    "sg:postcode":"71108",
    "sg:province":"LA",
    "sg:tags":[
        "automobile",
        "customizing"
    ],
    "wof:name":"CDX Mopar Restoration",
    "wof:placetype":"venue"
},
  "geometry": {"coordinates":[-93.8043,32.420282],"type":"Point"}
}