{
  "type": "Feature",
  "properties": {
    "iso:country":"US",
    "sg:address":"10615 Airline Hwy",
    "sg:city":"Baton Rouge",
    "sg:classifiers":[
        {
            "category":"Real Estate",
            "subcategory":"Architect",
            "type":"Services"
        }
    ],
    "sg:phone":"+1 225 291 0143",
    "sg:postcode":"70816",
    "sg:province":"LA",
    "sg:tags":[
        "building",
        "designer"
    ],
    "wof:name":"A & S Homeworks",
    "wof:placetype":"venue"
},
  "geometry": {"coordinates":[-91.059409,30.404949],"type":"Point"}
}