{
  "type": "Feature",
  "properties": {
    "iso:country":"US",
    "sg:address":"909 Dean Chapel Rd",
    "sg:city":"West Monroe",
    "sg:classifiers":[
        {
            "category":"Professional",
            "subcategory":"Accounting & Tax Preparation",
            "type":"Services"
        }
    ],
    "sg:phone":"+1 318 396 1149",
    "sg:postcode":"71291",
    "sg:province":"LA",
    "sg:tags":[
        "return"
    ],
    "wof:name":"Nancy Elmores Tax Service",
    "wof:placetype":"venue"
},
  "geometry": {"coordinates":[-92.178994,32.527668],"type":"Point"}
}