{
  "type": "Feature",
  "properties": {
    "addr:full":"4424 Ryan St Lake Charles LA 70605",
    "addr:housenumber":"4424",
    "addr:postcode":"70605",
    "addr:street":"Ryan St",
    "iso:country":"US",
    "sg:address":"4424 Ryan St",
    "sg:city":"Lake Charles",
    "sg:classifiers":[
        {
            "category":"Shopping",
            "type":"Retail Goods"
        }
    ],
    "sg:phone":"+1 337 474 9352",
    "sg:postcode":"70605",
    "sg:province":"LA",
    "sg:tags":[
        "cosmetic",
        "perfume"
    ],
    "wof:name":"Beauti Control Cosmetics Inc",
    "wof:placetype":"venue"
},
  "geometry": {"coordinates":[-93.218644,30.176619],"type":"Point"}
}