{
  "type": "Feature",
  "properties": {
    "iso:country":"US",
    "sg:address":"3725 E Texas St",
    "sg:city":"Bossier City",
    "sg:classifiers":[
        {
            "category":"Shopping",
            "type":"Retail Goods"
        }
    ],
    "sg:phone":"+1 318 746 5221",
    "sg:postcode":"71111",
    "sg:province":"LA",
    "sg:tags":[
        "wedding",
        "supply"
    ],
    "wof:name":"Taylor Rental Of Bossier City",
    "wof:placetype":"venue"
},
  "geometry": {"coordinates":[-93.685841,32.529394],"type":"Point"}
}