{
  "type": "Feature",
  "properties": {
    "addr:full":"105 N New Market St St Martinville LA 70582",
    "addr:housenumber":"105",
    "addr:postcode":"70582",
    "addr:street":"N New Market St St",
    "iso:country":"US",
    "sg:address":"105 N New Market St",
    "sg:city":"St Martinville",
    "sg:classifiers":[
        {
            "category":"Government",
            "subcategory":"Police Station",
            "type":"Public Place"
        }
    ],
    "sg:phone":"+1 337 394 2226",
    "sg:postcode":"70582",
    "sg:province":"LA",
    "sg:tags":[
        "department"
    ],
    "wof:name":"St Martinville Police Dept",
    "wof:placetype":"venue"
},
  "geometry": {"coordinates":[-91.82676499999999,30.124111],"type":"Point"}
}