{
  "type": "Feature",
  "properties": {
    "iso:country":"US",
    "sg:address":"3000 Severn Ave",
    "sg:city":"Metairie",
    "sg:classifiers":[
        {
            "category":"Health Services",
            "subcategory":"Health Practitioner",
            "type":"Services"
        }
    ],
    "sg:phone":"+1 504 885 8969",
    "sg:postcode":"70002",
    "sg:province":"LA",
    "sg:tags":[
        "therapist",
        "physical"
    ],
    "wof:name":"Southshore Physical Therapy",
    "wof:placetype":"venue"
},
  "geometry": {"coordinates":[-90.159431,30.005951],"type":"Point"}
}