{
  "type": "Feature",
  "properties": {
    "iso:country":"US",
    "sg:address":"727 Iberville St",
    "sg:city":"New Orleans",
    "sg:classifiers":[
        {
            "category":"Organizations",
            "subcategory":"Community Association",
            "type":"Services"
        }
    ],
    "sg:phone":"+1 504 524 4354",
    "sg:postcode":"70130",
    "sg:province":"LA",
    "sg:tags":[
        "club"
    ],
    "sg:website":"www.goldclubno.com",
    "wof:name":"Gold Club",
    "wof:placetype":"venue"
},
  "geometry": {"coordinates":[-90.068827,29.95457],"type":"Point"}
}