{
  "type": "Feature",
  "properties": {
    "iso:country":"US",
    "sg:address":"160 Gilmore Rd",
    "sg:city":"Lake Charles",
    "sg:classifiers":[
        {
            "category":"Freight",
            "type":"Transportation"
        }
    ],
    "sg:phone":"+1 337 855 9121",
    "sg:postcode":"70611",
    "sg:province":"LA",
    "sg:tags":[
        "special"
    ],
    "wof:name":"Larocca Mini Stor & MBL Hm Pk",
    "wof:placetype":"venue"
},
  "geometry": {"coordinates":[-93.21366500000001,30.298124],"type":"Point"}
}