{
  "type": "Feature",
  "properties": {
    "iso:country":"US",
    "sg:address":"1500 N General Pershing St",
    "sg:city":"Hammond",
    "sg:classifiers":[
        {
            "category":"Organizations",
            "subcategory":"Community Association",
            "type":"Services"
        }
    ],
    "sg:phone":"+1 985 419 0275",
    "sg:postcode":"70401",
    "sg:province":"LA",
    "sg:tags":[
        "sorority",
        "fraternity"
    ],
    "wof:name":"Alpha Sigma Tau Sorority",
    "wof:placetype":"venue"
},
  "geometry": {"coordinates":[-90.47193300000001,30.52115],"type":"Point"}
}