{
  "type": "Feature",
  "properties": {
    "addr:full":"1855 Country Club Rd Lake Charles LA 70607",
    "addr:housenumber":"1855",
    "addr:postcode":"70607",
    "addr:street":"Country Club Rd",
    "iso:country":"US",
    "sg:address":"1855 Country Club Rd",
    "sg:city":"Lake Charles",
    "sg:classifiers":[
        {
            "category":"Banks & Credit Unions",
            "subcategory":"Bank",
            "type":"Services"
        }
    ],
    "sg:phone":"+1 337 494 3322",
    "sg:postcode":"70607",
    "sg:province":"LA",
    "wof:name":"Hibernia National Bank",
    "wof:placetype":"venue"
},
  "geometry": {"coordinates":[-93.24555100000001,30.168801],"type":"Point"}
}