{
  "type": "Feature",
  "properties": {
    "iso:country":"US",
    "sg:address":"6413 Jefferson Hwy",
    "sg:city":"Harahan",
    "sg:classifiers":[
        {
            "category":"Shopping",
            "subcategory":"Clothing, Apparel, & Fashions",
            "type":"Retail Goods"
        }
    ],
    "sg:phone":"+1 504 739 9010",
    "sg:postcode":"70123",
    "sg:province":"LA",
    "sg:tags":[
        "tailor"
    ],
    "wof:name":"An's Tailor Alteration",
    "wof:placetype":"venue"
},
  "geometry": {"coordinates":[-90.194002,29.938964],"type":"Point"}
}