{
  "type": "Feature",
  "properties": {
    "iso:country":"US",
    "sg:address":"203 Hulco Dr",
    "sg:city":"Scott",
    "sg:classifiers":[
        {
            "category":"Building & Trades",
            "subcategory":"Construction",
            "type":"Services"
        }
    ],
    "sg:phone":"+1 337 266 2060",
    "sg:postcode":"70583",
    "sg:province":"LA",
    "sg:tags":[
        "contractor"
    ],
    "wof:name":"Victor Gillory Construction",
    "wof:placetype":"venue"
},
  "geometry": {"coordinates":[-92.100359,30.244187],"type":"Point"}
}