{
  "type": "Feature",
  "properties": {
    "iso:country":"US",
    "sg:address":"1722 W University Ave",
    "sg:city":"Lafayette",
    "sg:classifiers":[
        {
            "category":"Building & Trades",
            "subcategory":"Electrical",
            "type":"Services"
        }
    ],
    "sg:phone":"+1 337 289 9244",
    "sg:postcode":"70506",
    "sg:province":"LA",
    "sg:tags":[
        "electric",
        "contractor"
    ],
    "wof:name":"Alliance Electrical Svc",
    "wof:placetype":"venue"
},
  "geometry": {"coordinates":[-92.03024499999999,30.229111],"type":"Point"}
}