{
  "type": "Feature",
  "properties": {
    "iso:country":"US",
    "sg:address":"1033 Swan Ave",
    "sg:city":"Baton Rouge",
    "sg:classifiers":[
        {
            "category":"Professional",
            "subcategory":"Lawyer & Legal Services",
            "type":"Services"
        }
    ],
    "sg:phone":"+1 225 775 1200",
    "sg:postcode":"70807",
    "sg:province":"LA",
    "sg:tags":[
        "attorney"
    ],
    "wof:name":"Bates & Assoc",
    "wof:placetype":"venue"
},
  "geometry": {"coordinates":[-91.182495,30.523737],"type":"Point"}
}