{
  "type": "Feature",
  "properties": {
    "iso:country":"US",
    "sg:address":"2836 Cable St",
    "sg:city":"Arcadia",
    "sg:classifiers":[
        {
            "category":"Recreation",
            "type":"Entertainment"
        }
    ],
    "sg:phone":"+1 318 263 7303",
    "sg:postcode":"71001",
    "sg:province":"LA",
    "sg:tags":[
        "center"
    ],
    "wof:name":"Willy L Abney Recreational Ctr",
    "wof:placetype":"venue"
},
  "geometry": {"coordinates":[-92.93213,32.564859],"type":"Point"}
}