{
  "type": "Feature",
  "properties": {
    "iso:country":"US",
    "sg:address":"815 Focis St",
    "sg:city":"Metairie",
    "sg:classifiers":[
        {
            "category":"Home & Garden",
            "subcategory":"Garden Supply",
            "type":"Retail Goods"
        }
    ],
    "sg:phone":"+1 504 834 0402",
    "sg:postcode":"70005",
    "sg:province":"LA",
    "sg:tags":[
        "center"
    ],
    "wof:name":"Fischer Gambino/Land Art",
    "wof:placetype":"venue"
},
  "geometry": {"coordinates":[-90.129065,30.003893],"type":"Point"}
}