{
  "type": "Feature",
  "properties": {
    "iso:country":"US",
    "sg:address":"811 Albertson Pkwy",
    "sg:city":"Broussard",
    "sg:classifiers":[
        {
            "category":"Personal",
            "subcategory":"Tanning Parlor",
            "type":"Services"
        }
    ],
    "sg:phone":"+1 337 837 5580",
    "sg:postcode":"70518",
    "sg:province":"LA",
    "wof:name":"Island Tan",
    "wof:placetype":"venue"
},
  "geometry": {"coordinates":[-91.96116,30.138252],"type":"Point"}
}