{
  "type": "Feature",
  "properties": {
    "iso:country":"US",
    "sg:address":"801 Albertson Pkwy",
    "sg:city":"Broussard",
    "sg:classifiers":[
        {
            "category":"Banks & Credit Unions",
            "subcategory":"Bank",
            "type":"Services"
        }
    ],
    "sg:phone":"+1 337 839 2364",
    "sg:postcode":"70518",
    "sg:province":"LA",
    "wof:name":"Community First Bank",
    "wof:placetype":"venue"
},
  "geometry": {"coordinates":[-91.961427,30.138256],"type":"Point"}
}