{
  "type": "Feature",
  "properties": {
    "iso:country":"US",
    "sg:address":"14481 Old Hammond Hwy",
    "sg:city":"Baton Rouge",
    "sg:classifiers":[
        {
            "category":"Professional",
            "subcategory":"Accounting & Tax Preparation",
            "type":"Services"
        }
    ],
    "sg:phone":"+1 225 272 1177",
    "sg:postcode":"70816",
    "sg:province":"LA",
    "sg:tags":[
        "accountant"
    ],
    "wof:name":"Neil Ferrari CPA",
    "wof:placetype":"venue"
},
  "geometry": {"coordinates":[-91.02509999999999,30.451482],"type":"Point"}
}