{
  "type": "Feature",
  "properties": {
    "iso:country":"US",
    "sg:address":"2431 Manhattan Blvd",
    "sg:city":"Harvey",
    "sg:classifiers":[
        {
            "category":"Personal",
            "subcategory":"Shoe Repair & Shine",
            "type":"Services"
        }
    ],
    "sg:phone":"+1 504 367 0123",
    "sg:postcode":"70058",
    "sg:province":"LA",
    "sg:tags":[
        "repairing",
        "parlor",
        "boot"
    ],
    "wof:name":"A & A Shoe Repair",
    "wof:placetype":"venue"
},
  "geometry": {"coordinates":[-90.049176,29.876512],"type":"Point"}
}