{
  "type": "Feature",
  "properties": {
    "iso:country":"US",
    "sg:address":"7611 Maple St",
    "sg:city":"New Orleans",
    "sg:classifiers":[
        {
            "category":"Professional",
            "subcategory":"Lawyer & Legal Services",
            "type":"Services"
        }
    ],
    "sg:phone":"+1 504 242 8838",
    "sg:postcode":"70118",
    "sg:province":"LA",
    "sg:tags":[
        "attorney"
    ],
    "wof:name":"Tim Fields Law Office",
    "wof:placetype":"venue"
},
  "geometry": {"coordinates":[-90.12933,29.941872],"type":"Point"}
}