{
  "type": "Feature",
  "properties": {
    "addr:full":"1799 Stumpf Blvd Bldg 7 Terrytown LA 70056",
    "addr:housenumber":"1799",
    "addr:postcode":"70056",
    "addr:street":"Stumpf Blvd Bldg 7",
    "iso:country":"US",
    "sg:address":"1799 Stumpf Blvd Bldg 7",
    "sg:city":"Terrytown",
    "sg:classifiers":[
        {
            "category":"Personal",
            "subcategory":"Massage",
            "type":"Services"
        }
    ],
    "sg:phone":"+1 504 361 7811",
    "sg:postcode":"70056",
    "sg:province":"LA",
    "wof:name":"A Touch of Heaven Therapeutic Massage Clinic Llc",
    "wof:placetype":"venue"
},
  "geometry": {"coordinates":[-90.036558,29.911356],"type":"Point"}
}