{
  "type": "Feature",
  "properties": {
    "addr:full":"7433 Maple St New Orleans LA 70118",
    "addr:housenumber":"7433",
    "addr:postcode":"70118",
    "addr:street":"Maple St",
    "iso:country":"US",
    "sg:address":"7433 Maple St",
    "sg:city":"New Orleans",
    "sg:classifiers":[
        {
            "category":"Retail",
            "subcategory":"Portrait Studio",
            "type":"Services"
        }
    ],
    "sg:phone":"+1 504 522 9825",
    "sg:postcode":"70118",
    "sg:province":"LA",
    "sg:tags":[
        "photo"
    ],
    "sg:website":"www.grevy.com",
    "wof:name":"Grevy Photography",
    "wof:placetype":"venue"
},
  "geometry": {"coordinates":[-90.127574,29.940491],"type":"Point"}
}