{
  "type": "Feature",
  "properties": {
    "iso:country":"US",
    "sg:address":"2413 Tupelo St",
    "sg:city":"Morgan City",
    "sg:classifiers":[
        {
            "category":"Retail",
            "subcategory":"Repair Shop",
            "type":"Services"
        }
    ],
    "sg:phone":"+1 985 385 6048",
    "sg:postcode":"70380",
    "sg:province":"LA",
    "sg:tags":[
        "welding"
    ],
    "wof:name":"Sampey Services Inc",
    "wof:placetype":"venue"
},
  "geometry": {"coordinates":[-91.21266199999999,29.716147],"type":"Point"}
}