{
  "type": "Feature",
  "properties": {
    "iso:country":"US",
    "sg:address":"1312 Roper Rd",
    "sg:city":"Scott",
    "sg:classifiers":[
        {
            "category":"Building & Trades",
            "subcategory":"Landscaping Services",
            "type":"Services"
        }
    ],
    "sg:phone":"+1 337 267 7871",
    "sg:postcode":"70583",
    "sg:province":"LA",
    "wof:name":"B E D S Lawn Care",
    "wof:placetype":"venue"
},
  "geometry": {"coordinates":[-92.065185,30.264135],"type":"Point"}
}