{
  "type": "Feature",
  "properties": {
    "addr:full":"103 Westmark Blvd Lafayette LA 70506",
    "addr:housenumber":"103",
    "addr:postcode":"70506",
    "addr:street":"Westmark Blvd",
    "iso:country":"US",
    "sg:address":"103 Westmark Blvd",
    "sg:city":"Lafayette",
    "sg:classifiers":[
        {
            "category":"Health Services",
            "subcategory":"Health Practitioner",
            "type":"Services"
        }
    ],
    "sg:phone":"+1 337 988 4444",
    "sg:postcode":"70506",
    "sg:province":"LA",
    "sg:tags":[
        "therapist",
        "physical"
    ],
    "wof:name":"Physical Therapy Works Inc",
    "wof:placetype":"venue"
},
  "geometry": {"coordinates":[-92.072445,30.183963],"type":"Point"}
}