{
  "type": "Feature",
  "properties": {
    "iso:country":"US",
    "sg:address":"2014 Johnston St",
    "sg:city":"Lafayette",
    "sg:classifiers":[
        {
            "category":"Insurance",
            "subcategory":"Insurance Agent",
            "type":"Services"
        }
    ],
    "sg:phone":"+1 337 269 0600",
    "sg:postcode":"70503",
    "sg:province":"LA",
    "wof:name":"Direct General Ins Agency",
    "wof:placetype":"venue"
},
  "geometry": {"coordinates":[-92.027826,30.211157],"type":"Point"}
}