{
  "type": "Feature",
  "properties": {
    "addr:full":"103 Walnut St Bunkie LA 71322",
    "addr:housenumber":"103",
    "addr:postcode":"71322",
    "addr:street":"Walnut St",
    "iso:country":"US",
    "sg:address":"103 Walnut St",
    "sg:city":"Bunkie",
    "sg:classifiers":[
        {
            "category":"Government",
            "subcategory":"Fire Station",
            "type":"Public Place"
        }
    ],
    "sg:phone":"+1 318 346 4714",
    "sg:postcode":"71322",
    "sg:province":"LA",
    "sg:tags":[
        "department"
    ],
    "wof:name":"Bunkie Fire Chief",
    "wof:placetype":"venue"
},
  "geometry": {"coordinates":[-92.18552200000001,30.955989],"type":"Point"}
}