{
  "type": "Feature",
  "properties": {
    "iso:country":"US",
    "sg:address":"8138 Oak St",
    "sg:city":"Pleasant Hill",
    "sg:classifiers":[
        {
            "category":"Health Services",
            "subcategory":"Hospital",
            "type":"Services"
        }
    ],
    "sg:phone":"+1 318 796 3100",
    "sg:postcode":"71065",
    "sg:province":"LA",
    "wof:name":"Community Rehabilitation Hosp",
    "wof:placetype":"venue"
},
  "geometry": {"coordinates":[-93.51402299999999,31.820184],"type":"Point"}
}