{
  "type": "Feature",
  "properties": {
    "iso:country":"US",
    "sg:address":"4255 Hwy 552",
    "sg:city":"Downsville",
    "sg:classifiers":[
        {
            "category":"Retail",
            "subcategory":"Auto Repair",
            "type":"Services"
        }
    ],
    "sg:phone":"+1 318 982 9376",
    "sg:postcode":"71234",
    "sg:province":"LA",
    "sg:tags":[
        "body",
        "automobile",
        "painting"
    ],
    "wof:name":"Mc Cormick's Auto Body",
    "wof:placetype":"venue"
},
  "geometry": {"coordinates":[-92.280933,32.616826],"type":"Point"}
}