{
  "type": "Feature",
  "properties": {
    "iso:country":"US",
    "sg:address":"905 W Oak St",
    "sg:city":"Amite",
    "sg:classifiers":[
        {
            "category":"Food & Beverages",
            "subcategory":"Meat & Fish",
            "type":"Retail Goods"
        }
    ],
    "sg:phone":"+1 985 748 9300",
    "sg:postcode":"70422",
    "sg:province":"LA",
    "sg:tags":[
        "seafood"
    ],
    "wof:name":"Amite City Produce",
    "wof:placetype":"venue"
},
  "geometry": {"coordinates":[-90.52049100000001,30.726528],"type":"Point"}
}