{
  "type": "Feature",
  "properties": {
    "iso:country":"US",
    "sg:address":"36249 Hwy 433",
    "sg:city":"Slidell",
    "sg:classifiers":[
        {
            "category":"Retail",
            "subcategory":"Auto Repair",
            "type":"Services"
        }
    ],
    "sg:phone":"+1 985 661 9008",
    "sg:postcode":"70460",
    "sg:province":"LA",
    "sg:tags":[
        "body",
        "automobile",
        "painting"
    ],
    "wof:name":"Precision Auto Repair",
    "wof:placetype":"venue"
},
  "geometry": {"coordinates":[-89.798969,30.275603],"type":"Point"}
}