{
  "type": "Feature",
  "properties": {
    "iso:country":"US",
    "sg:address":"170 6th St",
    "sg:city":"Port Allen",
    "sg:classifiers":[
        {
            "category":"Personal",
            "subcategory":"Beauty Salon",
            "type":"Services"
        }
    ],
    "sg:phone":"+1 225 343 8505",
    "sg:postcode":"70767",
    "sg:province":"LA",
    "wof:name":"Venus Salon",
    "wof:placetype":"venue"
},
  "geometry": {"coordinates":[-91.206626,30.452738],"type":"Point"}
}