{
  "type": "Feature",
  "properties": {
    "iso:country":"US",
    "sg:address":"990 Main St",
    "sg:city":"Many",
    "sg:classifiers":[
        {
            "category":"Organizations",
            "subcategory":"Religious Organization",
            "type":"Services"
        }
    ],
    "sg:phone":"+1 318 256 5655",
    "sg:postcode":"71449",
    "sg:province":"LA",
    "sg:tags":[
        "church"
    ],
    "wof:name":"First Baptist Church",
    "wof:placetype":"venue"
},
  "geometry": {"coordinates":[-93.481252,31.567667],"type":"Point"}
}