{
  "type": "Feature",
  "properties": {
    "addr:full":"401 S Huntington St Sulphur LA 70663",
    "addr:housenumber":"401",
    "addr:postcode":"70663",
    "addr:street":"S Huntington St",
    "iso:country":"US",
    "sg:address":"401 S Huntington St",
    "sg:city":"Sulphur",
    "sg:classifiers":[
        {
            "category":"Social Services",
            "subcategory":"Child Care",
            "type":"Services"
        }
    ],
    "sg:phone":"+1 337 527 5534",
    "sg:postcode":"70663",
    "sg:province":"LA",
    "sg:website":"www.fbcsulphur.org",
    "wof:name":"First Baptist Church",
    "wof:placetype":"venue"
},
  "geometry": {"coordinates":[-93.377405,30.235231],"type":"Point"}
}