{
  "type": "Feature",
  "properties": {
    "iso:country":"US",
    "sg:address":"1653 Benton Rd",
    "sg:city":"Bossier City",
    "sg:classifiers":[
        {
            "category":"Wholesale",
            "subcategory":"Home Furnishings",
            "type":"Manufacturing & Wholesale Goods"
        }
    ],
    "sg:phone":"+1 318 752 4033",
    "sg:postcode":"71111",
    "sg:province":"LA",
    "sg:tags":[
        "picture",
        "frame"
    ],
    "wof:name":"Sweetheart Co",
    "wof:placetype":"venue"
},
  "geometry": {"coordinates":[-93.720378,32.533691],"type":"Point"}
}