{
  "type": "Feature",
  "properties": {
    "addr:full":"1799 Stumpf Blvd Terrytown LA 70056",
    "addr:housenumber":"1799",
    "addr:postcode":"70056",
    "addr:street":"Stumpf Blvd",
    "iso:country":"US",
    "sg:address":"1799 Stumpf Blvd",
    "sg:city":"Terrytown",
    "sg:classifiers":[
        {
            "category":"Social Services",
            "subcategory":"Child Care",
            "type":"Services"
        }
    ],
    "sg:phone":"+1 504 362 9000",
    "sg:postcode":"70056",
    "sg:province":"LA",
    "sg:tags":[
        "sitting"
    ],
    "wof:name":"Considerate Health Svc",
    "wof:placetype":"venue"
},
  "geometry": {"coordinates":[-90.037826,29.911631],"type":"Point"}
}