{
  "type": "Feature",
  "properties": {
    "addr:full":"105 Brownfield Dr Broussard LA 70518",
    "addr:housenumber":"105",
    "addr:postcode":"70518",
    "addr:street":"Brownfield Dr",
    "iso:country":"US",
    "sg:address":"105 Brownfield Dr",
    "sg:city":"Broussard",
    "sg:classifiers":[
        {
            "category":"Shopping",
            "subcategory":"Florist",
            "type":"Retail Goods"
        }
    ],
    "sg:phone":"+1 337 839 1171",
    "sg:postcode":"70518",
    "sg:province":"LA",
    "wof:name":"Oops A Daisy",
    "wof:placetype":"venue"
},
  "geometry": {"coordinates":[-91.96193700000001,30.116459],"type":"Point"}
}