{
  "type": "Feature",
  "properties": {
    "iso:country":"US",
    "sg:address":"3636 S Sherwood Forest Blvd",
    "sg:city":"Baton Rouge",
    "sg:classifiers":[
        {
            "category":"Organizations",
            "subcategory":"Professional Association",
            "type":"Services"
        }
    ],
    "sg:phone":"+1 225 291 1675",
    "sg:postcode":"70816",
    "sg:province":"LA",
    "wof:name":"Hemophilia Foundation LA Chptr",
    "wof:placetype":"venue"
},
  "geometry": {"coordinates":[-91.05157199999999,30.419582],"type":"Point"}
}