{
  "type": "Feature",
  "properties": {
    "iso:country":"US",
    "sg:address":"4242 Hwy 1192",
    "sg:city":"Marksville",
    "sg:classifiers":[
        {
            "category":"Professional",
            "type":"Services"
        }
    ],
    "sg:phone":"+1 318 253 8771",
    "sg:postcode":"71351",
    "sg:province":"LA",
    "sg:tags":[
        "establishment"
    ],
    "wof:name":"C L Woodworth Inc",
    "wof:placetype":"venue"
},
  "geometry": {"coordinates":[-92.06438300000001,31.142573],"type":"Point"}
}