{
  "type": "Feature",
  "properties": {
    "addr:full":"1729 Martin Luther King Blvd Houma LA 70360",
    "addr:housenumber":"1729",
    "addr:postcode":"70360",
    "addr:street":"Martin Luther King Blvd",
    "iso:country":"US",
    "sg:address":"1729 Martin Luther King Blvd",
    "sg:city":"Houma",
    "sg:classifiers":[
        {
            "category":"Shopping",
            "subcategory":"Computers & Home Electronics",
            "type":"Retail Goods"
        }
    ],
    "sg:phone":"+1 985 868 2226",
    "sg:postcode":"70360",
    "sg:province":"LA",
    "sg:tags":[
        "equipment",
        "electronic",
        "supply"
    ],
    "wof:name":"Circuit City",
    "wof:placetype":"venue"
},
  "geometry": {"coordinates":[-90.755369,29.612307],"type":"Point"}
}