{
  "type": "Feature",
  "properties": {
    "iso:country":"US",
    "sg:address":"2066 Coteau Rd",
    "sg:city":"Houma",
    "sg:classifiers":[
        {
            "category":"Organizations",
            "subcategory":"Religious Organization",
            "type":"Services"
        }
    ],
    "sg:phone":"+1 985 876 6089",
    "sg:postcode":"70364",
    "sg:province":"LA",
    "sg:tags":[
        "church"
    ],
    "wof:name":"Coteau Baptist Church",
    "wof:placetype":"venue"
},
  "geometry": {"coordinates":[-90.709476,29.635683],"type":"Point"}
}