{
  "type": "Feature",
  "properties": {
    "iso:country":"US",
    "sg:address":"5170 Pine Hill Rd",
    "sg:city":"Shreveport",
    "sg:classifiers":[
        {
            "category":"Retail",
            "subcategory":"Repair Shop",
            "type":"Services"
        }
    ],
    "sg:phone":"+1 318 226 1233",
    "sg:postcode":"71107",
    "sg:province":"LA",
    "sg:tags":[
        "refinishing",
        "furniture"
    ],
    "wof:name":"Apex Refinishing",
    "wof:placetype":"venue"
},
  "geometry": {"coordinates":[-93.84252499999999,32.584008],"type":"Point"}
}