{
  "type": "Feature",
  "properties": {
    "addr:full":"402 Thomas Rd West Monroe LA 71292",
    "addr:housenumber":"402",
    "addr:postcode":"71292",
    "addr:street":"Thomas Rd West",
    "iso:country":"US",
    "sg:address":"402 Thomas Rd",
    "sg:city":"West Monroe",
    "sg:classifiers":[
        {
            "category":"Banks & Credit Unions",
            "subcategory":"Bank",
            "type":"Services"
        }
    ],
    "sg:phone":"+1 318 388 4124",
    "sg:postcode":"71292",
    "sg:province":"LA",
    "sg:tags":[
        "cashing",
        "check"
    ],
    "wof:name":"Mr Payroll",
    "wof:placetype":"venue"
},
  "geometry": {"coordinates":[-92.15742299999999,32.50571],"type":"Point"}
}