{
  "type": "Feature",
  "properties": {
    "iso:country":"US",
    "sg:address":"44071 Maurice Bourgeois Rd",
    "sg:city":"St Amant",
    "sg:classifiers":[
        {
            "category":"Freight",
            "type":"Transportation"
        }
    ],
    "sg:phone":"+1 225 647 4918",
    "sg:postcode":"70774",
    "sg:province":"LA",
    "sg:tags":[
        "commercial",
        "storage"
    ],
    "wof:name":"Interstate Mini-Storage",
    "wof:placetype":"venue"
},
  "geometry": {"coordinates":[-90.868976,30.247769],"type":"Point"}
}