{
  "type": "Feature",
  "properties": {
    "addr:full":"1064 Front St Slidell LA 70458",
    "addr:housenumber":"1064",
    "addr:postcode":"70458",
    "addr:street":"Front St",
    "iso:country":"US",
    "sg:address":"1064 Front St",
    "sg:city":"Slidell",
    "sg:classifiers":[
        {
            "category":"Social Services",
            "type":"Services"
        }
    ],
    "sg:phone":"+1 985 649 1881",
    "sg:postcode":"70458",
    "sg:province":"LA",
    "sg:tags":[
        "agency",
        "adoption"
    ],
    "wof:name":"Borchert Law Office",
    "wof:placetype":"venue"
},
  "geometry": {"coordinates":[-89.777472,30.290353],"type":"Point"}
}