{
  "type": "Feature",
  "properties": {
    "iso:country":"US",
    "sg:address":"405 Monroe St",
    "sg:city":"Mansfield",
    "sg:classifiers":[
        {
            "category":"Insurance",
            "subcategory":"Insurance Agent",
            "type":"Services"
        }
    ],
    "sg:phone":"+1 318 872 6000",
    "sg:postcode":"71052",
    "sg:province":"LA",
    "wof:name":"Usagencies Casualty Insurance",
    "wof:placetype":"venue"
},
  "geometry": {"coordinates":[-93.707384,32.033414],"type":"Point"}
}