{
  "type": "Feature",
  "properties": {
    "iso:country":"US",
    "sg:address":"1306 Julia St",
    "sg:city":"Rayville",
    "sg:classifiers":[
        {
            "category":"Banks & Credit Unions",
            "subcategory":"Bank",
            "type":"Services"
        }
    ],
    "sg:phone":"+1 318 728 3256",
    "sg:postcode":"71269",
    "sg:province":"LA",
    "wof:name":"Guaranty Bank & Trust Co",
    "wof:placetype":"venue"
},
  "geometry": {"coordinates":[-91.759339,32.470618],"type":"Point"}
}