{
  "type": "Feature",
  "properties": {
    "iso:country":"US",
    "sg:address":"771 Caplis Sligo Rd",
    "sg:city":"Bossier City",
    "sg:classifiers":[
        {
            "category":"Home & Garden",
            "subcategory":"Building Materials",
            "type":"Retail Goods"
        }
    ],
    "sg:phone":"+1 318 747 1566",
    "sg:postcode":"71112",
    "sg:province":"LA",
    "sg:tags":[
        "door"
    ],
    "wof:name":"American Garage Door Inc",
    "wof:placetype":"venue"
},
  "geometry": {"coordinates":[-93.595454,32.406667],"type":"Point"}
}