{
  "type": "Feature",
  "properties": {
    "iso:country":"US",
    "sg:address":"1512 Barataria Blvd",
    "sg:city":"Marrero",
    "sg:classifiers":[
        {
            "category":"Food & Beverages",
            "subcategory":"Meat & Fish",
            "type":"Retail Goods"
        }
    ],
    "sg:phone":"+1 504 328 8661",
    "sg:postcode":"70072",
    "sg:province":"LA",
    "sg:tags":[
        "seafood"
    ],
    "wof:name":"Sal Seafood",
    "wof:placetype":"venue"
},
  "geometry": {"coordinates":[-90.099129,29.883492],"type":"Point"}
}