{
  "type": "Feature",
  "properties": {
    "iso:country":"US",
    "sg:address":"1949 State Rte 311",
    "sg:city":"Schriever",
    "sg:classifiers":[
        {
            "category":"Building & Trades",
            "subcategory":"Construction",
            "type":"Services"
        }
    ],
    "sg:phone":"+1 985 851 5624",
    "sg:postcode":"70395",
    "sg:province":"LA",
    "sg:tags":[
        "tile",
        "dealer"
    ],
    "wof:name":"Le Blanc Brothers Tile Co",
    "wof:placetype":"venue"
},
  "geometry": {"coordinates":[-90.81511,29.673022],"type":"Point"}
}