{
  "type": "Feature",
  "properties": {
    "iso:country":"US",
    "sg:address":"1981 E Main St",
    "sg:city":"New Iberia",
    "sg:classifiers":[
        {
            "category":"Shopping",
            "subcategory":"Used Merchandise",
            "type":"Retail Goods"
        }
    ],
    "sg:phone":"+1 337 367 6970",
    "sg:postcode":"70560",
    "sg:province":"LA",
    "sg:tags":[
        "furniture"
    ],
    "wof:name":"Bayou Liquidating",
    "wof:placetype":"venue"
},
  "geometry": {"coordinates":[-91.790374,29.991361],"type":"Point"}
}