{
  "type": "Feature",
  "properties": {
    "iso:country":"US",
    "sg:address":"603 W Admiral Doyle Dr",
    "sg:city":"New Iberia",
    "sg:classifiers":[
        {
            "category":"Education",
            "subcategory":"Special Training",
            "type":"Public Place"
        }
    ],
    "sg:phone":"+1 337 365 7335",
    "sg:postcode":"70560",
    "sg:province":"LA",
    "sg:tags":[
        "instruction",
        "driving"
    ],
    "wof:name":"Express Driving School",
    "wof:placetype":"venue"
},
  "geometry": {"coordinates":[-91.841104,29.999169],"type":"Point"}
}