{
  "type": "Feature",
  "properties": {
    "addr:full":"1864 Industrial Blvd Harvey LA 70058",
    "addr:housenumber":"1864",
    "addr:postcode":"70058",
    "addr:street":"Industrial Blvd",
    "iso:country":"US",
    "sg:address":"1864 Industrial Blvd",
    "sg:city":"Harvey",
    "sg:classifiers":[
        {
            "category":"Professional",
            "subcategory":"Accounting & Tax Preparation",
            "type":"Services"
        }
    ],
    "sg:phone":"+1 504 348 1816",
    "sg:postcode":"70058",
    "sg:province":"LA",
    "sg:tags":[
        "payroll"
    ],
    "wof:name":"Perfect Time Payroll",
    "wof:placetype":"venue"
},
  "geometry": {"coordinates":[-90.083533,29.878473],"type":"Point"}
}