{
  "type": "Feature",
  "properties": {
    "addr:full":"1310 Aster St Baton Rouge LA 70802",
    "addr:housenumber":"1310",
    "addr:postcode":"70802",
    "addr:street":"Aster St",
    "iso:country":"US",
    "sg:address":"1310 Aster St",
    "sg:city":"Baton Rouge",
    "sg:classifiers":[
        {
            "category":"Building & Trades",
            "subcategory":"Construction",
            "type":"Services"
        }
    ],
    "sg:phone":"+1 225 344 3303",
    "sg:postcode":"70802",
    "sg:province":"LA",
    "sg:tags":[
        "wallpaper"
    ],
    "wof:name":"Paper Rose",
    "wof:placetype":"venue"
},
  "geometry": {"coordinates":[-91.192037,30.419657],"type":"Point"}
}