{
  "type": "Feature",
  "properties": {
    "iso:country":"US",
    "sg:address":"5143 Paris Rd",
    "sg:city":"Chalmette",
    "sg:classifiers":[
        {
            "category":"Autos & Motor Vehicles",
            "subcategory":"Automobile Sales",
            "type":"Retail Goods"
        }
    ],
    "sg:phone":"+1 504 278 0207",
    "sg:postcode":"70043",
    "sg:province":"LA",
    "sg:tags":[
        "car",
        "dealer"
    ],
    "wof:name":"Big Boys Auto Finders",
    "wof:placetype":"venue"
},
  "geometry": {"coordinates":[-89.955529,29.958421],"type":"Point"}
}