{
  "type": "Feature",
  "properties": {
    "iso:country":"US",
    "sg:address":"800 Pine St",
    "sg:city":"Monroe",
    "sg:classifiers":[
        {
            "category":"Manufacturing",
            "subcategory":"Paper Products",
            "type":"Manufacturing & Wholesale Goods"
        }
    ],
    "sg:phone":"+1 318 325 0430",
    "sg:postcode":"71201",
    "sg:province":"LA",
    "sg:tags":[
        "corrugated",
        "solid",
        "fiber",
        "box"
    ],
    "wof:name":"Bocks Board Packaging Inc",
    "wof:placetype":"venue"
},
  "geometry": {"coordinates":[-92.11377,32.51068],"type":"Point"}
}