{
  "type": "Feature",
  "properties": {
    "iso:country":"US",
    "sg:address":"10 Bridle Path Ln",
    "sg:city":"Saint Rose",
    "sg:classifiers":[
        {
            "category":"Professional",
            "subcategory":"Computer Services",
            "type":"Services"
        }
    ],
    "sg:phone":"+1 504 467 8075",
    "sg:postcode":"70087",
    "sg:province":"LA",
    "sg:tags":[
        "related"
    ],
    "wof:name":"Spirit Data Systems",
    "wof:placetype":"venue"
},
  "geometry": {"coordinates":[-90.31285,29.956804],"type":"Point"}
}