{
  "type": "Feature",
  "properties": {
    "iso:country":"US",
    "sg:address":"5228 Greenwood Rd",
    "sg:city":"Shreveport",
    "sg:classifiers":[
        {
            "category":"Wholesale",
            "subcategory":"Machinery & Supplies",
            "type":"Manufacturing & Wholesale Goods"
        }
    ],
    "sg:phone":"+1 318 632 0372",
    "sg:postcode":"71109",
    "sg:province":"LA",
    "sg:tags":[
        "equipment",
        "motel",
        "hotel"
    ],
    "wof:name":"Bellman's Products & Svc",
    "wof:placetype":"venue"
},
  "geometry": {"coordinates":[-93.839975,32.46361],"type":"Point"}
}