{
  "type": "Feature",
  "properties": {
    "iso:country":"US",
    "sg:address":"333 Fountainbleau Dr",
    "sg:city":"Baton Rouge",
    "sg:classifiers":[
        {
            "category":"Building & Trades",
            "subcategory":"Construction",
            "type":"Services"
        }
    ],
    "sg:phone":"+1 225 715 9171",
    "sg:postcode":"70819",
    "sg:province":"LA",
    "sg:tags":[
        "house"
    ],
    "wof:name":"Bourgeois Home Repair",
    "wof:placetype":"venue"
},
  "geometry": {"coordinates":[-91.01969099999999,30.461753],"type":"Point"}
}