{
  "type": "Feature",
  "properties": {
    "iso:country":"US",
    "sg:address":"17402 Hwy 101",
    "sg:city":"Lacassine",
    "sg:classifiers":[
        {
            "category":"Mining & Drilling",
            "type":"Manufacturing & Wholesale Goods"
        }
    ],
    "sg:phone":"+1 337 588 4439",
    "sg:postcode":"70647",
    "sg:province":"LA",
    "sg:tags":[
        "field",
        "oil"
    ],
    "wof:name":"Dean Eneterprises",
    "wof:placetype":"venue"
},
  "geometry": {"coordinates":[-92.92954400000001,30.285622],"type":"Point"}
}