{
  "type": "Feature",
  "properties": {
    "addr:full":"1 Erin Ct New Orleans LA 70123",
    "addr:housenumber":"1",
    "addr:postcode":"70123",
    "addr:street":"Erin Ct",
    "iso:country":"US",
    "sg:address":"1 Erin Ct",
    "sg:city":"New Orleans",
    "sg:classifiers":[
        {
            "category":"Building & Trades",
            "subcategory":"Construction",
            "type":"Services"
        }
    ],
    "sg:phone":"+1 504 738 1410",
    "sg:postcode":"70123",
    "sg:province":"LA",
    "sg:tags":[
        "hanging",
        "contractor"
    ],
    "wof:name":"Trends Home Decorating",
    "wof:placetype":"venue"
},
  "geometry": {"coordinates":[-90.206954,29.935952],"type":"Point"}
}