{
  "type": "Feature",
  "properties": {
    "addr:full":"137 N 2nd St Monroe LA 71201",
    "addr:housenumber":"137",
    "addr:postcode":"71201",
    "addr:street":"N 2Nd St",
    "iso:country":"US",
    "sg:address":"137 N 2nd St",
    "sg:city":"Monroe",
    "sg:classifiers":[
        {
            "category":"Restaurant",
            "type":"Food & Drink"
        }
    ],
    "sg:phone":"+1 318 388 4175",
    "sg:postcode":"71201",
    "sg:province":"LA",
    "wof:name":"Cafe",
    "wof:placetype":"venue"
},
  "geometry": {"coordinates":[-92.11728599999999,32.502535],"type":"Point"}
}