{
  "type": "Feature",
  "properties": {
    "iso:country":"US",
    "sg:address":"1532 Rue Desiree",
    "sg:city":"Baton Rouge",
    "sg:classifiers":[
        {
            "category":"Professional",
            "subcategory":"Business Services",
            "type":"Services"
        }
    ],
    "sg:phone":"+1 225 767 7492",
    "sg:postcode":"70810",
    "sg:province":"LA",
    "wof:name":"Paula C Bradley",
    "wof:placetype":"venue"
},
  "geometry": {"coordinates":[-91.08868699999999,30.371707],"type":"Point"}
}