{
  "type": "Feature",
  "properties": {
    "iso:country":"US",
    "sg:address":"15021 State Rte 685",
    "sg:city":"Erath",
    "sg:classifiers":[
        {
            "category":"Real Estate",
            "subcategory":"Real Estate Operator",
            "type":"Services"
        }
    ],
    "sg:phone":"+1 337 937 5140",
    "sg:postcode":"70533",
    "sg:province":"LA",
    "sg:tags":[
        "property",
        "lessor"
    ],
    "wof:name":"Moss Alton",
    "wof:placetype":"venue"
},
  "geometry": {"coordinates":[-92.03958900000001,29.923324],"type":"Point"}
}