{
  "type": "Feature",
  "properties": {
    "addr:full":"16161 Airline Hwy Prairieville LA 70769",
    "addr:housenumber":"16161",
    "addr:postcode":"70769",
    "addr:street":"Airline Hwy Prairieville",
    "iso:country":"US",
    "sg:address":"16161 Airline Hwy",
    "sg:city":"Prairieville",
    "sg:classifiers":[
        {
            "category":"Manufacturing",
            "subcategory":"Tools & Machinery",
            "type":"Manufacturing & Wholesale Goods"
        }
    ],
    "sg:phone":"+1 225 673 6188",
    "sg:postcode":"70769",
    "sg:province":"LA",
    "sg:tags":[
        "equipment",
        "pump",
        "pumping"
    ],
    "sg:website":"www.pearceusa.com",
    "wof:name":"Pearce Pump Supply Inc",
    "wof:placetype":"venue"
},
  "geometry": {"coordinates":[-90.971447,30.302025],"type":"Point"}
}