{
  "type": "Feature",
  "properties": {
    "addr:full":"224 S Main St St Martinville LA 70582",
    "addr:housenumber":"224",
    "addr:postcode":"70582",
    "addr:street":"S Main St St",
    "iso:country":"US",
    "sg:address":"224 S Main St",
    "sg:city":"St Martinville",
    "sg:classifiers":[
        {
            "category":"Government",
            "subcategory":"Post Office",
            "type":"Public Place"
        }
    ],
    "sg:phone":"+1 337 000 1111",
    "sg:postcode":"70582",
    "sg:province":"LA",
    "wof:name":"US Post Office",
    "wof:placetype":"venue"
},
  "geometry": {"coordinates":[-91.829657,30.122238],"type":"Point"}
}