{
  "type": "Feature",
  "properties": {
    "iso:country":"US",
    "sg:address":"2454 Dumont Dr",
    "sg:city":"Baton Rouge",
    "sg:classifiers":[
        {
            "category":"Home & Garden",
            "subcategory":"Building Materials",
            "type":"Retail Goods"
        }
    ],
    "sg:phone":"+1 225 272 0067",
    "sg:postcode":"70815",
    "sg:province":"LA",
    "sg:tags":[
        "windows"
    ],
    "wof:name":"Quality Metal Products Inc",
    "wof:placetype":"venue"
},
  "geometry": {"coordinates":[-91.050743,30.472256],"type":"Point"}
}