{
  "type": "Feature",
  "properties": {
    "iso:country":"US",
    "sg:address":"6607 Northwood Ln",
    "sg:city":"Shreveport",
    "sg:classifiers":[
        {
            "category":"Real Estate",
            "subcategory":"Real Estate Services",
            "type":"Services"
        },
        {
            "category":"Real Estate",
            "subcategory":"Real Estate Agent",
            "type":"Services"
        }
    ],
    "sg:phone":"+1 318 347 2130",
    "sg:postcode":"71107",
    "sg:province":"LA",
    "sg:tags":[
        "buyer",
        "broker"
    ],
    "wof:name":"Coldwell Banker Agent",
    "wof:placetype":"venue"
},
  "geometry": {"coordinates":[-93.881214,32.601568],"type":"Point"}
}