{
  "type": "Feature",
  "properties": {
    "addr:full":"955 Howard Ave New Orleans LA 70113",
    "addr:housenumber":"955",
    "addr:postcode":"70113",
    "addr:street":"Howard Ave",
    "iso:country":"US",
    "sg:address":"955 Howard Ave",
    "sg:city":"New Orleans",
    "sg:classifiers":[
        {
            "category":"Professional",
            "subcategory":"Detective & Security Services",
            "type":"Services"
        }
    ],
    "sg:phone":"+1 504 529 2260",
    "sg:postcode":"70113",
    "sg:province":"LA",
    "sg:tags":[
        "guard",
        "patrol"
    ],
    "sg:website":"www.vinsonguard.com",
    "wof:name":"Vinson Guard Svc Inc",
    "wof:placetype":"venue"
},
  "geometry": {"coordinates":[-90.075428,29.945387],"type":"Point"}
}