{
  "type": "Feature",
  "properties": {
    "iso:country":"US",
    "sg:address":"101 E Point Ct",
    "sg:city":"New Orleans",
    "sg:classifiers":[
        {
            "category":"Education",
            "subcategory":"Special Training",
            "type":"Public Place"
        }
    ],
    "sg:phone":"+1 504 241 0700",
    "sg:postcode":"70128",
    "sg:province":"LA",
    "sg:tags":[
        "tutoring"
    ],
    "wof:name":"ABC To Phd",
    "wof:placetype":"venue"
},
  "geometry": {"coordinates":[-89.94559599999999,30.040084],"type":"Point"}
}