{
  "type": "Feature",
  "properties": {
    "addr:full":"412 Le Blanc St Dequincy LA 70633",
    "addr:housenumber":"412",
    "addr:postcode":"70633",
    "addr:street":"Le Blanc St",
    "iso:country":"US",
    "sg:address":"412 Le Blanc St",
    "sg:city":"Dequincy",
    "sg:classifiers":[
        {
            "category":"Mining & Drilling",
            "type":"Manufacturing & Wholesale Goods"
        }
    ],
    "sg:phone":"+1 337 786 7312",
    "sg:postcode":"70633",
    "sg:province":"LA",
    "sg:tags":[
        "field",
        "oil"
    ],
    "wof:name":"J A Martin Lease Svc",
    "wof:placetype":"venue"
},
  "geometry": {"coordinates":[-93.42838500000001,30.454923],"type":"Point"}
}