{
  "type": "Feature",
  "properties": {
    "addr:full":"555 S Ryan St Lake Charles LA 70601",
    "addr:housenumber":"555",
    "addr:postcode":"70601",
    "addr:street":"S Ryan St",
    "iso:country":"US",
    "sg:address":"555 S Ryan St",
    "sg:city":"Lake Charles",
    "sg:classifiers":[
        {
            "category":"Health Services",
            "subcategory":"Doctor",
            "type":"Services"
        }
    ],
    "sg:phone":"+1 337 439 6226",
    "sg:postcode":"70601",
    "sg:province":"LA",
    "sg:tags":[
        "clinic"
    ],
    "wof:name":"Colonade Surgery",
    "wof:placetype":"venue"
},
  "geometry": {"coordinates":[-93.228677,30.215225],"type":"Point"}
}