{
  "type": "Feature",
  "properties": {
    "addr:full":"3920 Jackson St Exd Alexandria LA 71303",
    "addr:housenumber":"3920",
    "addr:postcode":"71303",
    "addr:street":"Jackson St Exd",
    "iso:country":"US",
    "sg:address":"3920 Jackson St Exd",
    "sg:city":"Alexandria",
    "sg:classifiers":[
        {
            "category":"Shopping",
            "subcategory":"Bicycles & Sporting Goods",
            "type":"Retail Goods"
        }
    ],
    "sg:phone":"+1 318 473 4256",
    "sg:postcode":"71303",
    "sg:province":"LA",
    "wof:name":"Red River Cyclery",
    "wof:placetype":"venue"
},
  "geometry": {"coordinates":[-92.477771,31.282374],"type":"Point"}
}