{
  "type": "Feature",
  "properties": {
    "addr:full":"221 Rue de Jean Lafayette LA 70508",
    "addr:housenumber":"221",
    "addr:postcode":"70508",
    "addr:street":"Rue De Jean Lafayette",
    "iso:country":"US",
    "sg:address":"221 Rue de Jean",
    "sg:city":"Lafayette",
    "sg:classifiers":[
        {
            "category":"Shopping",
            "subcategory":"Pharmacy",
            "type":"Retail Goods"
        }
    ],
    "sg:phone":"+1 337 828 4400",
    "sg:postcode":"70508",
    "sg:province":"LA",
    "wof:name":"Eckerd",
    "wof:placetype":"venue"
},
  "geometry": {"coordinates":[-92.010193,30.189888],"type":"Point"}
}