{
  "type": "Feature",
  "properties": {
    "iso:country":"US",
    "sg:address":"975 Tech Dr",
    "sg:city":"Ruston",
    "sg:classifiers":[
        {
            "category":"Government",
            "subcategory":"Office",
            "type":"Public Place"
        }
    ],
    "sg:phone":"+1 318 251 4140",
    "sg:postcode":"71270",
    "sg:province":"LA",
    "wof:name":"LA Capitol Federal Cu",
    "wof:placetype":"venue"
},
  "geometry": {"coordinates":[-92.652126,32.521413],"type":"Point"}
}