{
  "type": "Feature",
  "properties": {
    "iso:country":"US",
    "sg:address":"3625 State Rte 14",
    "sg:city":"Lake Charles",
    "sg:classifiers":[
        {
            "category":"Building & Trades",
            "subcategory":"Construction",
            "type":"Services"
        }
    ],
    "sg:phone":"+1 337 474 6551",
    "sg:postcode":"70607",
    "sg:province":"LA",
    "wof:name":"Morgan Buildings Pools & Spas",
    "wof:placetype":"venue"
},
  "geometry": {"coordinates":[-93.15342200000001,30.158213],"type":"Point"}
}