{
  "type": "Feature",
  "properties": {
    "iso:country":"US",
    "sg:address":"837 Bayou Dularge Rd",
    "sg:city":"Houma",
    "sg:classifiers":[
        {
            "category":"Education",
            "subcategory":"Library",
            "type":"Public Place"
        }
    ],
    "sg:phone":"+1 985 851 1752",
    "sg:postcode":"70363",
    "sg:province":"LA",
    "wof:name":"Bauou Dularge Library",
    "wof:placetype":"venue"
},
  "geometry": {"coordinates":[-90.75209099999999,29.499019],"type":"Point"}
}