{
  "type": "Feature",
  "properties": {
    "addr:full":"522 Lake St Lake Providence LA 71254",
    "addr:housenumber":"522",
    "addr:postcode":"71254",
    "addr:street":"Lake St",
    "iso:country":"US",
    "sg:address":"522 Lake St",
    "sg:city":"Lake Providence",
    "sg:classifiers":[
        {
            "category":"Organizations",
            "subcategory":"Religious Organization",
            "type":"Services"
        }
    ],
    "sg:phone":"+1 318 559 1620",
    "sg:postcode":"71254",
    "sg:province":"LA",
    "sg:tags":[
        "church"
    ],
    "wof:name":"Grace Episcopal Church",
    "wof:placetype":"venue"
},
  "geometry": {"coordinates":[-91.17427000000001,32.806489],"type":"Point"}
}