{
  "type": "Feature",
  "properties": {
    "addr:full":"1715 Huey P Long Ave Gretna LA 70053",
    "addr:housenumber":"1715;p",
    "addr:postcode":"70053",
    "addr:street":"Huey;Long Ave",
    "iso:country":"US",
    "sg:address":"1715 Huey P Long Ave",
    "sg:city":"Gretna",
    "sg:classifiers":[
        {
            "category":"Freight",
            "type":"Transportation"
        }
    ],
    "sg:phone":"+1 504 367 4314",
    "sg:postcode":"70053",
    "sg:province":"LA",
    "sg:tags":[
        "operator",
        "local",
        "trucking"
    ],
    "wof:name":"White Diamond Trucking Inc",
    "wof:placetype":"venue"
},
  "geometry": {"coordinates":[-90.056271,29.904874],"type":"Point"}
}