{
  "type": "Feature",
  "properties": {
    "addr:full":"610 Canal Blvd Thibodaux LA 70301",
    "addr:housenumber":"610",
    "addr:postcode":"70301",
    "addr:street":"Canal Blvd",
    "iso:country":"US",
    "sg:address":"610 Canal Blvd",
    "sg:city":"Thibodaux",
    "sg:classifiers":[
        {
            "category":"Restaurant",
            "type":"Food & Drink"
        }
    ],
    "sg:menulink":"http://www.allmenus.com/la/thibodaux/132019-subway/menu/",
    "sg:phone":"+1 985 446 7668",
    "sg:postcode":"70301",
    "sg:province":"LA",
    "sg:tags":[
        "american",
        "sandwich"
    ],
    "wof:name":"Subway",
    "wof:placetype":"venue"
},
  "geometry": {"coordinates":[-90.819795,29.794471],"type":"Point"}
}