{
  "type": "Feature",
  "properties": {
    "iso:country":"US",
    "sg:address":"4220 Canal St",
    "sg:city":"New Orleans",
    "sg:classifiers":[
        {
            "category":"Insurance",
            "subcategory":"Insurance Agent",
            "type":"Services"
        }
    ],
    "sg:phone":"+1 504 482 0036",
    "sg:postcode":"70119",
    "sg:province":"LA",
    "wof:name":"D R Commercial Lines",
    "wof:placetype":"venue"
},
  "geometry": {"coordinates":[-90.10315300000001,29.976039],"type":"Point"}
}