{
  "type": "Feature",
  "properties": {
    "iso:country":"US",
    "sg:address":"4045 S Carrollton Ave",
    "sg:city":"New Orleans",
    "sg:classifiers":[
        {
            "category":"Autos & Motor Vehicles",
            "subcategory":"Auto Supplies",
            "type":"Retail Goods"
        }
    ],
    "sg:phone":"+1 504 482 1483",
    "sg:postcode":"70119",
    "sg:province":"LA",
    "sg:tags":[
        "automobile",
        "parts"
    ],
    "wof:name":"Advance Auto Parts Inc",
    "wof:placetype":"venue"
},
  "geometry": {"coordinates":[-90.106859,29.968857],"type":"Point"}
}