{
  "type": "Feature",
  "properties": {
    "addr:full":"320 New Natchitoches Rd West Monroe LA 71292",
    "addr:housenumber":"320",
    "addr:postcode":"71292",
    "addr:street":"New Natchitoches Rd West",
    "iso:country":"US",
    "sg:address":"320 New Natchitoches Rd",
    "sg:city":"West Monroe",
    "sg:classifiers":[
        {
            "category":"Home & Garden",
            "subcategory":"Hardware",
            "type":"Retail Goods"
        }
    ],
    "sg:phone":"+1 318 388 3373",
    "sg:postcode":"71292",
    "sg:province":"LA",
    "wof:name":"Bakers Hardware Inc",
    "wof:placetype":"venue"
},
  "geometry": {"coordinates":[-92.16454400000001,32.491914],"type":"Point"}
}