{
  "type": "Feature",
  "properties": {
    "iso:country":"US",
    "sg:address":"203 N King St",
    "sg:city":"Welsh",
    "sg:classifiers":[
        {
            "category":"Organizations",
            "subcategory":"Religious Organization",
            "type":"Services"
        }
    ],
    "sg:phone":"+1 337 734 3812",
    "sg:postcode":"70591",
    "sg:province":"LA",
    "wof:name":"Jones United Methodist Church",
    "wof:placetype":"venue"
},
  "geometry": {"coordinates":[-92.82767800000001,30.23927],"type":"Point"}
}