{
  "type": "Feature",
  "properties": {
    "addr:full":"11800 Industriplex Blvd Baton Rouge LA 70809",
    "addr:housenumber":"11800",
    "addr:postcode":"70809",
    "addr:street":"Industriplex Blvd",
    "iso:country":"US",
    "sg:address":"11800 Industriplex Blvd",
    "sg:city":"Baton Rouge",
    "sg:classifiers":[
        {
            "category":"Manufacturing",
            "subcategory":"Food",
            "type":"Manufacturing & Wholesale Goods"
        }
    ],
    "sg:phone":"+1 225 752 1110",
    "sg:postcode":"70809",
    "sg:province":"LA",
    "sg:tags":[
        "tea",
        "coffee",
        "product"
    ],
    "sg:website":"www.podpack.com",
    "wof:name":"Pod Pack Intl",
    "wof:placetype":"venue"
},
  "geometry": {"coordinates":[-91.047978,30.384359],"type":"Point"}
}