{
  "type": "Feature",
  "properties": {
    "iso:country":"US",
    "sg:address":"4869 Hwy 1",
    "sg:city":"Mathews",
    "sg:classifiers":[
        {
            "category":"Personal",
            "subcategory":"Tanning Parlor",
            "type":"Services"
        }
    ],
    "sg:phone":"+1 985 532 1661",
    "sg:postcode":"70390",
    "sg:province":"LA",
    "sg:tags":[
        "salon"
    ],
    "wof:name":"Retreat Tanning & Massage Ctr",
    "wof:placetype":"venue"
},
  "geometry": {"coordinates":[-91.02878699999999,29.945686],"type":"Point"}
}