{
  "type": "Feature",
  "properties": {
    "iso:country":"US",
    "sg:address":"11161 S Idlewood Ct",
    "sg:city":"New Orleans",
    "sg:classifiers":[
        {
            "category":"Shopping",
            "subcategory":"Catalog Store",
            "type":"Retail Goods"
        }
    ],
    "sg:phone":"+1 504 245 7845",
    "sg:postcode":"70128",
    "sg:province":"LA",
    "sg:tags":[
        "sales"
    ],
    "wof:name":"Teachers Depot of New Orleans",
    "wof:placetype":"venue"
},
  "geometry": {"coordinates":[-89.95803600000001,30.03053],"type":"Point"}
}