{
  "type": "Feature",
  "properties": {
    "iso:country":"US",
    "sg:address":"251 Commanche Rd",
    "sg:city":"Ragley",
    "sg:classifiers":[
        {
            "category":"Building & Trades",
            "subcategory":"Construction",
            "type":"Services"
        }
    ],
    "sg:phone":"+1 337 725 3991",
    "sg:postcode":"70657",
    "sg:province":"LA",
    "sg:tags":[
        "hanging",
        "contractor"
    ],
    "wof:name":"Jill King",
    "wof:placetype":"venue"
},
  "geometry": {"coordinates":[-93.147592,30.504424],"type":"Point"}
}