{
  "type": "Feature",
  "properties": {
    "iso:country":"US",
    "sg:address":"1132 Dixie St",
    "sg:city":"Natchitoches",
    "sg:classifiers":[
        {
            "category":"Organizations",
            "subcategory":"Religious Organization",
            "type":"Services"
        }
    ],
    "sg:phone":"+1 318 354 8258",
    "sg:postcode":"71457",
    "sg:province":"LA",
    "wof:name":"Christian Baptist Church",
    "wof:placetype":"venue"
},
  "geometry": {"coordinates":[-93.09439399999999,31.772549],"type":"Point"}
}