{
  "type": "Feature",
  "properties": {
    "addr:full":"182 Equity Blvd Houma LA 70360",
    "addr:housenumber":"182",
    "addr:postcode":"70360",
    "addr:street":"Equity Blvd",
    "iso:country":"US",
    "sg:address":"182 Equity Blvd",
    "sg:city":"Houma",
    "sg:classifiers":[
        {
            "category":"Mining & Drilling",
            "type":"Manufacturing & Wholesale Goods"
        }
    ],
    "sg:phone":"+1 985 868 4116",
    "sg:postcode":"70360",
    "sg:province":"LA",
    "sg:tags":[
        "field",
        "oil"
    ],
    "wof:name":"Wgps Production Systems LP",
    "wof:placetype":"venue"
},
  "geometry": {"coordinates":[-90.76690000000001,29.602339],"type":"Point"}
}