{
  "type": "Feature",
  "properties": {
    "iso:country":"US",
    "sg:address":"624 Pellerin Rd",
    "sg:city":"Jeanerette",
    "sg:classifiers":[
        {
            "category":"Organizations",
            "subcategory":"Religious Organization",
            "type":"Services"
        }
    ],
    "sg:phone":"+1 337 276 5311",
    "sg:postcode":"70544",
    "sg:province":"LA",
    "sg:tags":[
        "church"
    ],
    "wof:name":"Mt Calvary Baptist Church",
    "wof:placetype":"venue"
},
  "geometry": {"coordinates":[-91.67537400000001,29.914092],"type":"Point"}
}