{
  "type": "Feature",
  "properties": {
    "addr:full":"615 Bayou Dularge Rd Houma LA 70363",
    "addr:housenumber":"615",
    "addr:postcode":"70363",
    "addr:street":"Bayou Dularge Rd",
    "iso:country":"US",
    "sg:address":"615 Bayou Dularge Rd",
    "sg:city":"Houma",
    "sg:classifiers":[
        {
            "category":"Insurance",
            "subcategory":"Insurance Agent",
            "type":"Services"
        }
    ],
    "sg:phone":"+1 985 872 0836",
    "sg:postcode":"70363",
    "sg:province":"LA",
    "sg:tags":[
        "accident"
    ],
    "wof:name":"Ridgeland Insurance",
    "wof:placetype":"venue"
},
  "geometry": {"coordinates":[-90.743054,29.52206],"type":"Point"}
}