{
  "type": "Feature",
  "properties": {
    "iso:country":"US",
    "sg:address":"1241 E Laurel Ave",
    "sg:city":"Eunice",
    "sg:classifiers":[
        {
            "category":"Insurance",
            "subcategory":"Insurance Agent",
            "type":"Services"
        }
    ],
    "sg:phone":"+1 337 457 5231",
    "sg:postcode":"70535",
    "sg:province":"LA",
    "wof:name":"Charles Aguillard Agency Inc",
    "wof:placetype":"venue"
},
  "geometry": {"coordinates":[-92.400724,30.494809],"type":"Point"}
}