{
  "type": "Feature",
  "properties": {
    "iso:country":"US",
    "sg:address":"2614 David Dr",
    "sg:city":"Metairie",
    "sg:classifiers":[
        {
            "category":"Health Services",
            "subcategory":"Chiropractor",
            "type":"Services"
        }
    ],
    "sg:phone":"+1 504 885 2388",
    "sg:postcode":"70003",
    "sg:province":"LA",
    "wof:name":"Emergency Chiropractic Inc",
    "wof:placetype":"venue"
},
  "geometry": {"coordinates":[-90.219566,30.001811],"type":"Point"}
}