{
  "type": "Feature",
  "properties": {
    "addr:full":"8865 Siegen Ln Baton Rouge LA 70810",
    "addr:housenumber":"8865",
    "addr:postcode":"70810",
    "addr:street":"Siegen Ln",
    "iso:country":"US",
    "sg:address":"8865 Siegen Ln",
    "sg:city":"Baton Rouge",
    "sg:classifiers":[
        {
            "category":"Retail",
            "subcategory":"Car Wash",
            "type":"Services"
        }
    ],
    "sg:phone":"+1 225 769 5800",
    "sg:postcode":"70810",
    "sg:province":"LA",
    "sg:tags":[
        "polishing",
        "washing"
    ],
    "wof:name":"Siegen Lane Car Wash",
    "wof:placetype":"venue"
},
  "geometry": {"coordinates":[-91.07230800000001,30.37177],"type":"Point"}
}