{
  "type": "Feature",
  "properties": {
    "iso:country":"US",
    "sg:address":"2013 Airline Dr",
    "sg:city":"Bossier City",
    "sg:classifiers":[
        {
            "category":"Restaurant",
            "type":"Food & Drink"
        }
    ],
    "sg:phone":"+1 318 742 6660",
    "sg:postcode":"71111",
    "sg:province":"LA",
    "sg:website":"www.notinis.net",
    "wof:name":"Notini's Restaurant",
    "wof:placetype":"venue"
},
  "geometry": {"coordinates":[-93.699427,32.52571],"type":"Point"}
}