{
  "type": "Feature",
  "properties": {
    "iso:country":"US",
    "sg:address":"1314 Corporate Square Dr",
    "sg:city":"Slidell",
    "sg:classifiers":[
        {
            "category":"Shopping",
            "subcategory":"Hobbies, Toys, & Games",
            "type":"Retail Goods"
        }
    ],
    "sg:phone":"+1 985 646 0226",
    "sg:postcode":"70458",
    "sg:province":"LA",
    "sg:tags":[
        "model",
        "supply"
    ],
    "wof:name":"Aggressive Hobbies LLC",
    "wof:placetype":"venue"
},
  "geometry": {"coordinates":[-89.756271,30.28278],"type":"Point"}
}