{
  "type": "Feature",
  "properties": {
    "iso:country":"US",
    "sg:address":"3901 Downman Rd",
    "sg:city":"New Orleans",
    "sg:classifiers":[
        {
            "category":"Autos & Motor Vehicles",
            "subcategory":"Fuel & Gas Station",
            "type":"Retail Goods"
        }
    ],
    "sg:phone":"+1 504 242 4232",
    "sg:postcode":"70126",
    "sg:province":"LA",
    "sg:tags":[
        "oil"
    ],
    "wof:name":"Shell Downman Road",
    "wof:placetype":"venue"
},
  "geometry": {"coordinates":[-90.0209,30.009991],"type":"Point"}
}