{
  "type": "Feature",
  "properties": {
    "iso:country":"US",
    "sg:address":"11920 Richcroft Ave",
    "sg:city":"Baton Rouge",
    "sg:classifiers":[
        {
            "category":"Professional",
            "subcategory":"Management & Consulting",
            "type":"Services"
        }
    ],
    "sg:phone":"+1 225 273 5040",
    "sg:postcode":"70814",
    "sg:province":"LA",
    "sg:tags":[
        "fire",
        "consultant",
        "protection"
    ],
    "wof:name":"Engineered Fire Protection",
    "wof:placetype":"venue"
},
  "geometry": {"coordinates":[-91.04980500000001,30.47344],"type":"Point"}
}