{
  "type": "Feature",
  "properties": {
    "iso:country":"US",
    "sg:address":"3514 Paris Rd",
    "sg:city":"Chalmette",
    "sg:classifiers":[
        {
            "category":"Restaurant",
            "type":"Food & Drink"
        }
    ],
    "sg:phone":"+1 504 279 6108",
    "sg:postcode":"70043",
    "sg:province":"LA",
    "sg:tags":[
        "diner"
    ],
    "wof:name":"Hole & One",
    "wof:placetype":"venue"
},
  "geometry": {"coordinates":[-89.959412,29.95143],"type":"Point"}
}