{
  "type": "Feature",
  "properties": {
    "iso:country":"US",
    "sg:address":"301 Paul Maillard Rd",
    "sg:city":"Luling",
    "sg:classifiers":[
        {
            "category":"Manufacturing",
            "subcategory":"Tools & Machinery",
            "type":"Manufacturing & Wholesale Goods"
        }
    ],
    "sg:phone":"+1 985 785 6340",
    "sg:postcode":"70070",
    "sg:province":"LA",
    "sg:tags":[
        "equipment",
        "industrial",
        "supply"
    ],
    "wof:name":"Bosco Uniform Svc",
    "wof:placetype":"venue"
},
  "geometry": {"coordinates":[-90.365753,29.932512],"type":"Point"}
}