{
  "type": "Feature",
  "properties": {
    "iso:country":"US",
    "sg:address":"322 Franklin St",
    "sg:city":"Shreveport",
    "sg:classifiers":[
        {
            "category":"Autos & Motor Vehicles",
            "subcategory":"Boat Sales",
            "type":"Retail Goods"
        }
    ],
    "sg:phone":"+1 318 221 7777",
    "sg:postcode":"71101",
    "sg:province":"LA",
    "sg:tags":[
        "dealer",
        "sales"
    ],
    "wof:name":"Campbell's Marine",
    "wof:placetype":"venue"
},
  "geometry": {"coordinates":[-93.744063,32.510038],"type":"Point"}
}