{
  "type": "Feature",
  "properties": {
    "iso:country":"US",
    "sg:address":"9624 Brookline Ave",
    "sg:city":"Baton Rouge",
    "sg:classifiers":[
        {
            "category":"Insurance",
            "subcategory":"Insurance Agent",
            "type":"Services"
        }
    ],
    "sg:phone":"+1 225 927 0451",
    "sg:postcode":"70809",
    "sg:province":"LA",
    "wof:name":"Henry Insurance Svc",
    "wof:placetype":"venue"
},
  "geometry": {"coordinates":[-91.081502,30.428163],"type":"Point"}
}