{
  "type": "Feature",
  "properties": {
    "iso:country":"US",
    "sg:address":"422 Tassin St",
    "sg:city":"Moreauville",
    "sg:classifiers":[
        {
            "category":"Shopping",
            "subcategory":"Computers & Home Electronics",
            "type":"Retail Goods"
        }
    ],
    "sg:phone":"+1 318 985 2532",
    "sg:postcode":"71355",
    "sg:province":"LA",
    "sg:tags":[
        "television",
        "radio"
    ],
    "wof:name":"Clayton's TV Sales & Svc",
    "wof:placetype":"venue"
},
  "geometry": {"coordinates":[-91.97543899999999,31.03462],"type":"Point"}
}