{
  "type": "Feature",
  "properties": {
    "iso:country":"US",
    "sg:address":"550 E Sale Rd",
    "sg:city":"Lake Charles",
    "sg:classifiers":[
        {
            "category":"Health Services",
            "subcategory":"Doctor",
            "type":"Services"
        }
    ],
    "sg:phone":"+1 337 478 8650",
    "sg:postcode":"70605",
    "sg:province":"LA",
    "sg:tags":[
        "clinic"
    ],
    "wof:name":"Calcasieu Community Clinic",
    "wof:placetype":"venue"
},
  "geometry": {"coordinates":[-93.215571,30.183346],"type":"Point"}
}