{
  "type": "Feature",
  "properties": {
    "iso:country":"US",
    "sg:address":"1742 Amos Dr",
    "sg:city":"Haynesville",
    "sg:classifiers":[
        {
            "category":"Real Estate",
            "subcategory":"Real Estate Agent",
            "type":"Services"
        }
    ],
    "sg:phone":"+1 318 624 3212",
    "sg:postcode":"71038",
    "sg:province":"LA",
    "sg:tags":[
        "authorities",
        "housing"
    ],
    "wof:name":"Haynesville Housing Authority",
    "wof:placetype":"venue"
},
  "geometry": {"coordinates":[-93.14343,32.965819],"type":"Point"}
}