{
  "type": "Feature",
  "properties": {
    "addr:full":"4305 Coliseum St New Orleans LA 70115",
    "addr:housenumber":"4305",
    "addr:postcode":"70115",
    "addr:street":"Coliseum St",
    "iso:country":"US",
    "sg:address":"4305 Coliseum St",
    "sg:city":"New Orleans",
    "sg:classifiers":[
        {
            "category":"Building & Trades",
            "subcategory":"Construction",
            "type":"Services"
        }
    ],
    "sg:phone":"+1 504 895 3679",
    "sg:postcode":"70115",
    "sg:province":"LA",
    "sg:tags":[
        "carpentry",
        "contractor"
    ],
    "wof:name":"Marshall Schwartz",
    "wof:placetype":"venue"
},
  "geometry": {"coordinates":[-90.101613,29.923731],"type":"Point"}
}