{
  "type": "Feature",
  "properties": {
    "addr:full":"1010 Common St New Orleans LA 70130",
    "addr:housenumber":"1010",
    "addr:postcode":"70130",
    "addr:street":"Common St",
    "iso:country":"US",
    "sg:address":"1010 Common St",
    "sg:city":"New Orleans",
    "sg:classifiers":[
        {
            "category":"Building & Trades",
            "subcategory":"Equipment Rental",
            "type":"Services"
        }
    ],
    "sg:phone":"+1 504 581 2083",
    "sg:postcode":"70130",
    "sg:province":"LA",
    "sg:tags":[
        "oil",
        "well",
        "supply"
    ],
    "wof:name":"Patterson Services Inc",
    "wof:placetype":"venue"
},
  "geometry": {"coordinates":[-90.07388899999999,29.954029],"type":"Point"}
}