{
  "type": "Feature",
  "properties": {
    "iso:country":"US",
    "sg:address":"1155 Gecko Rd",
    "sg:city":"Breaux Bridge",
    "sg:classifiers":[
        {
            "category":"Building & Trades",
            "subcategory":"Electrical",
            "type":"Services"
        }
    ],
    "sg:phone":"+1 337 232 0951",
    "sg:postcode":"70517",
    "sg:province":"LA",
    "sg:tags":[
        "electric",
        "contractor"
    ],
    "wof:name":"P & H Electric Inc",
    "wof:placetype":"venue"
},
  "geometry": {"coordinates":[-91.94572100000001,30.300955],"type":"Point"}
}