{
  "type": "Feature",
  "properties": {
    "iso:country":"US",
    "sg:address":"39325 Hwy 190 E",
    "sg:city":"Slidell",
    "sg:classifiers":[
        {
            "category":"Manufacturing",
            "subcategory":"Building Materials",
            "type":"Manufacturing & Wholesale Goods"
        }
    ],
    "sg:phone":"+1 985 726 0392",
    "sg:postcode":"70461",
    "sg:province":"LA",
    "wof:name":"Liberty Millwork Inc",
    "wof:placetype":"venue"
},
  "geometry": {"coordinates":[-89.744195,30.268042],"type":"Point"}
}