{
  "type": "Feature",
  "properties": {
    "addr:full":"8700 Line Ave Shreveport LA 71106",
    "addr:housenumber":"8700",
    "addr:postcode":"71106",
    "addr:street":"Line Ave",
    "iso:country":"US",
    "sg:address":"8700 Line Ave",
    "sg:city":"Shreveport",
    "sg:classifiers":[
        {
            "category":"Manufacturing",
            "subcategory":"Tools & Machinery",
            "type":"Manufacturing & Wholesale Goods"
        }
    ],
    "sg:phone":"+1 318 865 1711",
    "sg:postcode":"71106",
    "sg:province":"LA",
    "sg:tags":[
        "food",
        "product"
    ],
    "sg:website":"www.frymaster.com",
    "wof:name":"Frymaster LLC",
    "wof:placetype":"venue"
},
  "geometry": {"coordinates":[-93.73631899999999,32.419173],"type":"Point"}
}