{
  "type": "Feature",
  "properties": {
    "iso:country":"US",
    "sg:address":"110 Honeysuckle Dr",
    "sg:city":"Schriever",
    "sg:classifiers":[
        {
            "category":"Banks & Credit Unions",
            "subcategory":"Financial Services",
            "type":"Services"
        }
    ],
    "sg:phone":"+1 985 446 0043",
    "sg:postcode":"70395",
    "sg:province":"LA",
    "sg:tags":[
        "investor"
    ],
    "wof:name":"Neigel Investments Inc",
    "wof:placetype":"venue"
},
  "geometry": {"coordinates":[-90.819005,29.73853],"type":"Point"}
}