{
  "type": "Feature",
  "properties": {
    "iso:country":"US",
    "sg:address":"1876 Hwy 121",
    "sg:city":"Hineston",
    "sg:classifiers":[
        {
            "category":"Wholesale",
            "subcategory":"Auto Parts",
            "type":"Manufacturing & Wholesale Goods"
        }
    ],
    "sg:phone":"+1 318 793 2260",
    "sg:postcode":"71438",
    "sg:province":"LA",
    "sg:tags":[
        "automobile",
        "rebuilt"
    ],
    "wof:name":"Kar Kare Ctr",
    "wof:placetype":"venue"
},
  "geometry": {"coordinates":[-92.759067,31.136187],"type":"Point"}
}