{
  "type": "Feature",
  "properties": {
    "addr:full":"805 W Dardeau St Ville Platte LA 70586",
    "addr:housenumber":"805",
    "addr:postcode":"70586",
    "addr:street":"W Dardeau St",
    "iso:country":"US",
    "sg:address":"805 W Dardeau St",
    "sg:city":"Ville Platte",
    "sg:classifiers":[
        {
            "category":"Building & Trades",
            "subcategory":"Equipment Rental",
            "type":"Services"
        }
    ],
    "sg:phone":"+1 337 363 0461",
    "sg:postcode":"70586",
    "sg:province":"LA",
    "sg:tags":[
        "yard"
    ],
    "wof:name":"V P Rental",
    "wof:placetype":"venue"
},
  "geometry": {"coordinates":[-92.278603,30.699352],"type":"Point"}
}