{
  "type": "Feature",
  "properties": {
    "addr:full":"7500 Westbank Expy Marrero LA 70072",
    "addr:housenumber":"7500",
    "addr:postcode":"70072",
    "addr:street":"Westbank Expy Marrero",
    "iso:country":"US",
    "sg:address":"7500 Westbank Expy",
    "sg:city":"Marrero",
    "sg:classifiers":[
        {
            "category":"Personal",
            "subcategory":"Beauty Salon",
            "type":"Services"
        }
    ],
    "sg:phone":"+1 504 340 5113",
    "sg:postcode":"70072",
    "sg:province":"LA",
    "sg:tags":[
        "manicuring"
    ],
    "wof:name":"Mary's Nails",
    "wof:placetype":"venue"
},
  "geometry": {"coordinates":[-90.132125,29.895446],"type":"Point"}
}