{
  "type": "Feature",
  "properties": {
    "addr:full":"104 Myrtle Pl Gray LA 70364",
    "addr:housenumber":"104",
    "addr:postcode":"70364",
    "addr:street":"Myrtle Pl",
    "iso:country":"US",
    "sg:address":"104 Myrtle Pl",
    "sg:city":"Gray",
    "sg:classifiers":[
        {
            "category":"Organizations",
            "subcategory":"Religious Organization",
            "type":"Services"
        }
    ],
    "sg:phone":"+1 985 876 5503",
    "sg:postcode":"70364",
    "sg:province":"LA",
    "sg:tags":[
        "church"
    ],
    "wof:name":"Lafourche Parish Council Div",
    "wof:placetype":"venue"
},
  "geometry": {"coordinates":[-90.68516,29.659353],"type":"Point"}
}