{
  "type": "Feature",
  "properties": {
    "iso:country":"US",
    "sg:address":"1245 Loreauville Hwy",
    "sg:city":"St Martinville",
    "sg:classifiers":[
        {
            "category":"Building & Trades",
            "subcategory":"Landscaping Services",
            "type":"Services"
        }
    ],
    "sg:phone":"+1 337 394 5937",
    "sg:postcode":"70582",
    "sg:province":"LA",
    "sg:tags":[
        "tree"
    ],
    "wof:name":"Jil Tree Svc",
    "wof:placetype":"venue"
},
  "geometry": {"coordinates":[-91.81008300000001,30.086784],"type":"Point"}
}