{
  "type": "Feature",
  "properties": {
    "iso:country":"US",
    "sg:address":"5221 Belle Terre Rd",
    "sg:city":"Marrero",
    "sg:classifiers":[
        {
            "category":"Restaurant",
            "type":"Food & Drink"
        }
    ],
    "sg:phone":"+1 504 341 4060",
    "sg:postcode":"70072",
    "sg:province":"LA",
    "sg:tags":[
        "eating"
    ],
    "wof:name":"Thomas I Choate",
    "wof:placetype":"venue"
},
  "geometry": {"coordinates":[-90.099633,29.878993],"type":"Point"}
}