{
  "type": "Feature",
  "properties": {
    "iso:country":"US",
    "sg:address":"108 Ray St",
    "sg:city":"Pineville",
    "sg:classifiers":[
        {
            "category":"Retail",
            "subcategory":"Auto Repair",
            "type":"Services"
        }
    ],
    "sg:phone":"+1 318 443 4846",
    "sg:postcode":"71360",
    "sg:province":"LA",
    "sg:tags":[
        "body",
        "automobile",
        "painting"
    ],
    "wof:name":"Eagle II",
    "wof:placetype":"venue"
},
  "geometry": {"coordinates":[-92.423422,31.317435],"type":"Point"}
}