{
  "type": "Feature",
  "properties": {
    "iso:country":"US",
    "sg:address":"904 Short Vine St",
    "sg:city":"Opelousas",
    "sg:classifiers":[
        {
            "category":"Food & Beverages",
            "subcategory":"Groceries & Convenience Stores",
            "type":"Retail Goods"
        }
    ],
    "sg:phone":"+1 337 942 9150",
    "sg:postcode":"70570",
    "sg:province":"LA",
    "sg:tags":[
        "grocer"
    ],
    "wof:name":"Ray's Grocery",
    "wof:placetype":"venue"
},
  "geometry": {"coordinates":[-92.07419,30.53093],"type":"Point"}
}