{
  "type": "Feature",
  "properties": {
    "iso:country":"US",
    "sg:address":"3075 State Rte 78",
    "sg:city":"Livonia",
    "sg:classifiers":[
        {
            "category":"Personal",
            "subcategory":"Tanning Parlor",
            "type":"Services"
        }
    ],
    "sg:phone":"+1 225 637 3671",
    "sg:postcode":"70755",
    "sg:province":"LA",
    "sg:tags":[
        "salon"
    ],
    "wof:name":"Sunsations Tanning Salon",
    "wof:placetype":"venue"
},
  "geometry": {"coordinates":[-91.557214,30.555337],"type":"Point"}
}