{
  "type": "Feature",
  "properties": {
    "iso:country":"US",
    "sg:address":"4041 Tulane Ave",
    "sg:city":"New Orleans",
    "sg:classifiers":[
        {
            "category":"Health Services",
            "subcategory":"Doctor",
            "type":"Services"
        }
    ],
    "sg:phone":"+1 504 301 1008",
    "sg:postcode":"70119",
    "sg:province":"LA",
    "sg:tags":[
        "physician",
        "surgeon"
    ],
    "wof:name":"Crown Medical Rehab",
    "wof:placetype":"venue"
},
  "geometry": {"coordinates":[-90.105621,29.968737],"type":"Point"}
}