{
  "type": "Feature",
  "properties": {
    "iso:country":"US",
    "sg:address":"402 S Kirkland Dr",
    "sg:city":"Brusly",
    "sg:classifiers":[
        {
            "category":"Organizations",
            "subcategory":"Religious Organization",
            "type":"Services"
        }
    ],
    "sg:phone":"+1 225 749 3387",
    "sg:postcode":"70719",
    "sg:province":"LA",
    "sg:tags":[
        "church"
    ],
    "wof:name":"John The Baptist Catholic Chr",
    "wof:placetype":"venue"
},
  "geometry": {"coordinates":[-91.236591,30.384325],"type":"Point"}
}