{
  "type": "Feature",
  "properties": {
    "iso:country":"US",
    "sg:address":"1383 Napoleon St",
    "sg:city":"Baton Rouge",
    "sg:classifiers":[
        {
            "category":"Education",
            "subcategory":"School",
            "type":"Public Place"
        }
    ],
    "sg:phone":"+1 225 387 8531",
    "sg:postcode":"70802",
    "sg:province":"LA",
    "wof:name":"Freeman/Matthews Head Start",
    "wof:placetype":"venue"
},
  "geometry": {"coordinates":[-91.18313999999999,30.435998],"type":"Point"}
}