{
  "type": "Feature",
  "properties": {
    "iso:country":"US",
    "sg:address":"10464 Mammoth Ave",
    "sg:city":"Baton Rouge",
    "sg:classifiers":[
        {
            "category":"Education",
            "subcategory":"Dance Studio",
            "type":"Public Place"
        }
    ],
    "sg:phone":"+1 225 261 6143",
    "sg:postcode":"70814",
    "sg:province":"LA",
    "wof:name":"Western Squares Inc",
    "wof:placetype":"venue"
},
  "geometry": {"coordinates":[-91.076185,30.475034],"type":"Point"}
}