{
  "type": "Feature",
  "properties": {
    "iso:country":"US",
    "sg:address":"1006 Clothilde St",
    "sg:city":"Morgan City",
    "sg:classifiers":[
        {
            "category":"Autos & Motor Vehicles",
            "subcategory":"Boat Sales",
            "type":"Retail Goods"
        }
    ],
    "sg:phone":"+1 985 384 0992",
    "sg:postcode":"70380",
    "sg:province":"LA",
    "sg:tags":[
        "electronics",
        "marine"
    ],
    "wof:name":"Rice Electronics",
    "wof:placetype":"venue"
},
  "geometry": {"coordinates":[-91.201099,29.70453],"type":"Point"}
}