{
  "type": "Feature",
  "properties": {
    "addr:full":"222 Laurel St Baton Rouge LA 70801",
    "addr:housenumber":"222",
    "addr:postcode":"70801",
    "addr:street":"Laurel St",
    "iso:country":"US",
    "sg:address":"222 Laurel St",
    "sg:city":"Baton Rouge",
    "sg:classifiers":[
        {
            "category":"Bars & Pubs",
            "type":"Food & Drink"
        }
    ],
    "sg:phone":"+1 225 346 8454",
    "sg:postcode":"70801",
    "sg:province":"LA",
    "sg:tags":[
        "club",
        "night"
    ],
    "wof:name":"Redstar",
    "wof:placetype":"venue"
},
  "geometry": {"coordinates":[-91.188546,30.45028],"type":"Point"}
}