{
  "type": "Feature",
  "properties": {
    "iso:country":"US",
    "sg:address":"120 Rogers Ln",
    "sg:city":"Houma",
    "sg:classifiers":[
        {
            "category":"Mining & Drilling",
            "type":"Manufacturing & Wholesale Goods"
        }
    ],
    "sg:phone":"+1 985 851 7622",
    "sg:postcode":"70364",
    "sg:province":"LA",
    "sg:tags":[
        "field",
        "oil"
    ],
    "wof:name":"Nabors Offshore Corp",
    "wof:placetype":"venue"
},
  "geometry": {"coordinates":[-90.623549,29.602844],"type":"Point"}
}