{
  "type": "Feature",
  "properties": {
    "addr:full":"8952 Boone Dr Baton Rouge LA 70810",
    "addr:housenumber":"8952",
    "addr:postcode":"70810",
    "addr:street":"Boone Dr",
    "iso:country":"US",
    "sg:address":"8952 Boone Dr",
    "sg:city":"Baton Rouge",
    "sg:classifiers":[
        {
            "category":"Building & Trades",
            "subcategory":"Construction",
            "type":"Services"
        }
    ],
    "sg:phone":"+1 225 819 0006",
    "sg:postcode":"70810",
    "sg:province":"LA",
    "sg:tags":[
        "general",
        "contractor"
    ],
    "wof:name":"S J Saia Construction LLC",
    "wof:placetype":"venue"
},
  "geometry": {"coordinates":[-91.11585700000001,30.375778],"type":"Point"}
}