{
  "type": "Feature",
  "properties": {
    "addr:full":"937 Field St New Iberia LA 70560",
    "addr:housenumber":"937",
    "addr:postcode":"70560",
    "addr:street":"Field St",
    "iso:country":"US",
    "sg:address":"937 Field St",
    "sg:city":"New Iberia",
    "sg:classifiers":[
        {
            "category":"Personal",
            "subcategory":"Barber",
            "type":"Services"
        }
    ],
    "sg:phone":"+1 337 560 4600",
    "sg:postcode":"70560",
    "sg:province":"LA",
    "wof:name":"Major League Kutz",
    "wof:placetype":"venue"
},
  "geometry": {"coordinates":[-91.8321,30.0128],"type":"Point"}
}