{
  "type": "Feature",
  "properties": {
    "addr:full":"2607 Caples Rd West Monroe LA 71292",
    "addr:housenumber":"2607",
    "addr:postcode":"71292",
    "addr:street":"Caples Rd West",
    "iso:country":"US",
    "sg:address":"2607 Caples Rd",
    "sg:city":"West Monroe",
    "sg:classifiers":[
        {
            "category":"Building & Trades",
            "subcategory":"Construction",
            "type":"Services"
        }
    ],
    "sg:phone":"+1 318 396 1639",
    "sg:postcode":"71292",
    "sg:province":"LA",
    "sg:tags":[
        "demolition",
        "contractor"
    ],
    "wof:name":"Hudleston's Tractor & Dozier",
    "wof:placetype":"venue"
},
  "geometry": {"coordinates":[-92.29424899999999,32.437469],"type":"Point"}
}