{
  "type": "Feature",
  "properties": {
    "iso:country":"US",
    "sg:address":"1220 E 1st St",
    "sg:city":"Deridder",
    "sg:classifiers":[
        {
            "category":"Airport",
            "type":"Transportation"
        }
    ],
    "sg:phone":"+1 337 462 0890",
    "sg:postcode":"70634",
    "sg:province":"LA",
    "sg:tags":[
        "aircraft",
        "maintenance"
    ],
    "wof:name":"Bob's Aviation",
    "wof:placetype":"venue"
},
  "geometry": {"coordinates":[-93.259128,30.846857],"type":"Point"}
}