{
  "type": "Feature",
  "properties": {
    "iso:country":"US",
    "sg:address":"2922 Cypress St",
    "sg:city":"West Monroe",
    "sg:classifiers":[
        {
            "category":"Wholesale",
            "subcategory":"Machinery & Supplies",
            "type":"Manufacturing & Wholesale Goods"
        }
    ],
    "sg:phone":"+1 318 325 4060",
    "sg:postcode":"71291",
    "sg:province":"LA",
    "sg:tags":[
        "pump"
    ],
    "wof:name":"Associated Process Products",
    "wof:placetype":"venue"
},
  "geometry": {"coordinates":[-92.15002,32.517859],"type":"Point"}
}