{
  "type": "Feature",
  "properties": {
    "addr:full":"1100 Cherry St Mamou LA 70554",
    "addr:housenumber":"1100",
    "addr:postcode":"70554",
    "addr:street":"Cherry St",
    "iso:country":"US",
    "sg:address":"1100 Cherry St",
    "sg:city":"Mamou",
    "sg:classifiers":[
        {
            "category":"Personal",
            "subcategory":"Beauty Salon",
            "type":"Services"
        }
    ],
    "sg:phone":"+1 337 468 2727",
    "sg:postcode":"70554",
    "sg:province":"LA",
    "sg:tags":[
        "shop"
    ],
    "wof:name":"Cajun Cuttery",
    "wof:placetype":"venue"
},
  "geometry": {"coordinates":[-92.413983,30.64312],"type":"Point"}
}