{
  "type": "Feature",
  "properties": {
    "iso:country":"US",
    "sg:address":"5990 Section Rd",
    "sg:city":"Port Allen",
    "sg:classifiers":[
        {
            "category":"Professional",
            "type":"Services"
        }
    ],
    "sg:phone":"+1 225 627 6220",
    "sg:postcode":"70767",
    "sg:province":"LA",
    "wof:name":"Pin-Mor Services Inc",
    "wof:placetype":"venue"
},
  "geometry": {"coordinates":[-91.299342,30.535177],"type":"Point"}
}