{
  "type": "Feature",
  "properties": {
    "iso:country":"US",
    "sg:address":"1501 Wimbledon Dr",
    "sg:city":"Alexandria",
    "sg:classifiers":[
        {
            "category":"Professional",
            "subcategory":"Management & Consulting",
            "type":"Services"
        }
    ],
    "sg:phone":"+1 318 448 8693",
    "sg:postcode":"71301",
    "sg:province":"LA",
    "sg:tags":[
        "consultant",
        "resource",
        "human"
    ],
    "wof:name":"Foster Human Resource Solution",
    "wof:placetype":"venue"
},
  "geometry": {"coordinates":[-92.47839399999999,31.277239],"type":"Point"}
}