{
  "type": "Feature",
  "properties": {
    "addr:full":"2255 University Pkwy Leesville LA 71446",
    "addr:housenumber":"2255",
    "addr:postcode":"71446",
    "addr:street":"University Pkwy",
    "iso:country":"US",
    "sg:address":"2255 University Pkwy",
    "sg:city":"Leesville",
    "sg:classifiers":[
        {
            "category":"Building & Trades",
            "subcategory":"Landscaping Services",
            "type":"Services"
        }
    ],
    "sg:phone":"+1 337 238 2660",
    "sg:postcode":"71446",
    "sg:province":"LA",
    "sg:tags":[
        "landscape",
        "contractor"
    ],
    "wof:name":"Greenhaven Landscape Contrs",
    "wof:placetype":"venue"
},
  "geometry": {"coordinates":[-93.24940100000001,31.120377],"type":"Point"}
}