{
  "type": "Feature",
  "properties": {
    "iso:country":"US",
    "sg:address":"504 S 4th St",
    "sg:city":"Monroe",
    "sg:classifiers":[
        {
            "category":"Building & Trades",
            "subcategory":"Plumbing",
            "type":"Services"
        }
    ],
    "sg:phone":"+1 318 325 1220",
    "sg:postcode":"71202",
    "sg:province":"LA",
    "sg:tags":[
        "conditioning",
        "air",
        "system",
        "contractor"
    ],
    "wof:name":"All Pro Air & Heat",
    "wof:placetype":"venue"
},
  "geometry": {"coordinates":[-92.106624,32.494478],"type":"Point"}
}