{
  "type": "Feature",
  "properties": {
    "addr:full":"11845 Gamm Rd Belcher LA 71004",
    "addr:housenumber":"11845",
    "addr:postcode":"71004",
    "addr:street":"Gamm Rd",
    "iso:country":"US",
    "sg:address":"11845 Gamm Rd",
    "sg:city":"Belcher",
    "sg:classifiers":[
        {
            "category":"Education",
            "subcategory":"School",
            "type":"Public Place"
        }
    ],
    "sg:phone":"+1 318 296 4224",
    "sg:postcode":"71004",
    "sg:province":"LA",
    "wof:name":"Herndon Magnet School",
    "wof:placetype":"venue"
},
  "geometry": {"coordinates":[-93.883968,32.779041],"type":"Point"}
}