{
  "type": "Feature",
  "properties": {
    "iso:country":"US",
    "sg:address":"803 N 4th St",
    "sg:city":"Monroe",
    "sg:classifiers":[
        {
            "category":"Personal",
            "subcategory":"Barber",
            "type":"Services"
        }
    ],
    "sg:phone":"+1 318 323 1726",
    "sg:postcode":"71201",
    "sg:province":"LA",
    "wof:name":"Northside Barber Shop",
    "wof:placetype":"venue"
},
  "geometry": {"coordinates":[-92.120261,32.510061],"type":"Point"}
}