{
  "type": "Feature",
  "properties": {
    "iso:country":"US",
    "sg:address":"14671 Plank Rd",
    "sg:city":"Baker",
    "sg:classifiers":[
        {
            "category":"Banks & Credit Unions",
            "subcategory":"Bank",
            "type":"Services"
        }
    ],
    "sg:phone":"+1 225 771 1207",
    "sg:postcode":"70714",
    "sg:province":"LA",
    "sg:tags":[
        "cashing",
        "check"
    ],
    "wof:name":"American Check Cashers",
    "wof:placetype":"venue"
},
  "geometry": {"coordinates":[-91.126829,30.580031],"type":"Point"}
}