{
  "type": "Feature",
  "properties": {
    "addr:full":"724 N Jefferson Ave Port Allen LA 70767",
    "addr:housenumber":"724",
    "addr:postcode":"70767",
    "addr:street":"N Jefferson Ave",
    "iso:country":"US",
    "sg:address":"724 N Jefferson Ave",
    "sg:city":"Port Allen",
    "sg:classifiers":[
        {
            "category":"Organizations",
            "subcategory":"Membership Organization",
            "type":"Services"
        }
    ],
    "sg:phone":"+1 225 343 7626",
    "sg:postcode":"70767",
    "sg:province":"LA",
    "wof:name":"West Baton Rouge Foundation",
    "wof:placetype":"venue"
},
  "geometry": {"coordinates":[-91.20575599999999,30.459092],"type":"Point"}
}