{
  "type": "Feature",
  "properties": {
    "iso:country":"US",
    "sg:address":"155 Mimosa Pl",
    "sg:city":"Lafayette",
    "sg:classifiers":[
        {
            "category":"Real Estate",
            "subcategory":"Real Estate Operator",
            "type":"Services"
        }
    ],
    "sg:phone":"+1 337 984 8400",
    "sg:postcode":"70506",
    "sg:province":"LA",
    "sg:tags":[
        "apartment"
    ],
    "wof:name":"Mimosa Place Apartments",
    "wof:placetype":"venue"
},
  "geometry": {"coordinates":[-92.062308,30.203473],"type":"Point"}
}