{
  "type": "Feature",
  "properties": {
    "addr:full":"301 Marquette St Harahan LA 70123",
    "addr:housenumber":"301",
    "addr:postcode":"70123",
    "addr:street":"Marquette St",
    "iso:country":"US",
    "sg:address":"301 Marquette St",
    "sg:city":"Harahan",
    "sg:classifiers":[
        {
            "category":"Building & Trades",
            "subcategory":"Electrical",
            "type":"Services"
        }
    ],
    "sg:phone":"+1 504 737 6476",
    "sg:postcode":"70123",
    "sg:province":"LA",
    "sg:tags":[
        "electric",
        "contractor"
    ],
    "wof:name":"Larry's Electrical Svc",
    "wof:placetype":"venue"
},
  "geometry": {"coordinates":[-90.197502,29.940029],"type":"Point"}
}