{
  "type": "Feature",
  "properties": {
    "addr:full":"9345 Mansfield Rd Shreveport LA 71118",
    "addr:housenumber":"9345",
    "addr:postcode":"71118",
    "addr:street":"Mansfield Rd",
    "iso:country":"US",
    "sg:address":"9345 Mansfield Rd",
    "sg:city":"Shreveport",
    "sg:classifiers":[
        {
            "category":"Food & Beverages",
            "subcategory":"Groceries & Convenience Stores",
            "type":"Retail Goods"
        }
    ],
    "sg:phone":"+1 318 688 4013",
    "sg:postcode":"71118",
    "sg:province":"LA",
    "wof:name":"Food-Fast Convenience Store",
    "wof:placetype":"venue"
},
  "geometry": {"coordinates":[-93.809104,32.396775],"type":"Point"}
}