{
  "type": "Feature",
  "properties": {
    "addr:full":"1544 Tchoupitoulas St New Orleans LA 70130",
    "addr:housenumber":"1544",
    "addr:postcode":"70130",
    "addr:street":"Tchoupitoulas St",
    "iso:country":"US",
    "sg:address":"1544 Tchoupitoulas St",
    "sg:city":"New Orleans",
    "sg:classifiers":[
        {
            "category":"Restaurant",
            "type":"Food & Drink"
        }
    ],
    "sg:phone":"+1 504 587 3777",
    "sg:postcode":"70130",
    "sg:province":"LA",
    "sg:tags":[
        "banquet",
        "rooms"
    ],
    "wof:name":"Twi Ro Pa",
    "wof:placetype":"venue"
},
  "geometry": {"coordinates":[-90.066138,29.930922],"type":"Point"}
}