{
  "type": "Feature",
  "properties": {
    "iso:country":"US",
    "sg:address":"239 Florida Ave SE",
    "sg:city":"Denham Springs",
    "sg:classifiers":[
        {
            "category":"Education",
            "subcategory":"Library",
            "type":"Public Place"
        }
    ],
    "sg:phone":"+1 225 665 8118",
    "sg:postcode":"70726",
    "sg:province":"LA",
    "wof:name":"Denham Springs Library",
    "wof:placetype":"venue"
},
  "geometry": {"coordinates":[-90.954049,30.483154],"type":"Point"}
}