{
  "type": "Feature",
  "properties": {
    "iso:country":"US",
    "sg:address":"1805 N 7th St",
    "sg:city":"West Monroe",
    "sg:classifiers":[
        {
            "category":"Wholesale",
            "subcategory":"Electrical",
            "type":"Manufacturing & Wholesale Goods"
        }
    ],
    "sg:phone":"+1 318 397 8900",
    "sg:postcode":"71291",
    "sg:province":"LA",
    "sg:tags":[
        "alarm",
        "burglar",
        "system"
    ],
    "wof:name":"Superior Protection Syst In",
    "wof:placetype":"venue"
},
  "geometry": {"coordinates":[-92.145837,32.511386],"type":"Point"}
}