{
  "type": "Feature",
  "properties": {
    "iso:country":"US",
    "sg:address":"4309 Ottawa St",
    "sg:city":"Metairie",
    "sg:classifiers":[
        {
            "category":"Building & Trades",
            "subcategory":"Cleaning & Sanitation",
            "type":"Services"
        }
    ],
    "sg:phone":"+1 504 889 0648",
    "sg:postcode":"70001",
    "sg:province":"LA",
    "sg:tags":[
        "maintenance"
    ],
    "wof:name":"M & B Industrial Maintenance",
    "wof:placetype":"venue"
},
  "geometry": {"coordinates":[-90.177555,29.986437],"type":"Point"}
}