{
  "type": "Feature",
  "properties": {
    "iso:country":"US",
    "sg:address":"55125 Cambre St",
    "sg:city":"White Castle",
    "sg:classifiers":[
        {
            "category":"Professional",
            "subcategory":"Business Services",
            "type":"Services"
        }
    ],
    "sg:phone":"+1 225 545 0112",
    "sg:postcode":"70788",
    "sg:province":"LA",
    "sg:tags":[
        "notary"
    ],
    "wof:name":"Bosley Notary Public",
    "wof:placetype":"venue"
},
  "geometry": {"coordinates":[-91.147313,30.169893],"type":"Point"}
}