{
  "type": "Feature",
  "properties": {
    "addr:full":"724 E Flournoy Lucas Rd Shreveport LA 71115",
    "addr:housenumber":"724",
    "addr:postcode":"71115",
    "addr:street":"E Flournoy Lucas Rd",
    "iso:country":"US",
    "sg:address":"724 E Flournoy Lucas Rd",
    "sg:city":"Shreveport",
    "sg:classifiers":[
        {
            "category":"Wholesale",
            "subcategory":"Fruits & Vegetables",
            "type":"Manufacturing & Wholesale Goods"
        }
    ],
    "sg:phone":"+1 318 797 0361",
    "sg:postcode":"71115",
    "sg:province":"LA",
    "wof:name":"Gullos Fresh Produce",
    "wof:placetype":"venue"
},
  "geometry": {"coordinates":[-93.704016,32.40101],"type":"Point"}
}