{
  "type": "Feature",
  "properties": {
    "iso:country":"US",
    "sg:address":"4532 Gary Mikel Ave",
    "sg:city":"Metairie",
    "sg:classifiers":[
        {
            "category":"Real Estate",
            "subcategory":"Real Estate Agent",
            "type":"Services"
        }
    ],
    "sg:phone":"+1 504 455 6203",
    "sg:postcode":"70002",
    "sg:province":"LA",
    "wof:name":"Bill Elliott Realty",
    "wof:placetype":"venue"
},
  "geometry": {"coordinates":[-90.172866,30.016494],"type":"Point"}
}