{
  "type": "Feature",
  "properties": {
    "addr:full":"18535 State Rte 77 Grosse Tete LA 70740",
    "addr:housenumber":"18535",
    "addr:postcode":"70740",
    "addr:street":"State Rte 77 Grosse Tete La",
    "iso:country":"US",
    "sg:address":"18535 State Rte 77",
    "sg:city":"Grosse Tete",
    "sg:classifiers":[
        {
            "category":"Building & Trades",
            "subcategory":"Construction",
            "type":"Services"
        }
    ],
    "sg:phone":"+1 225 648 2159",
    "sg:postcode":"70740",
    "sg:province":"LA",
    "sg:tags":[
        "company"
    ],
    "wof:name":"Lemoine Construction Inc",
    "wof:placetype":"venue"
},
  "geometry": {"coordinates":[-91.424598,30.4071],"type":"Point"}
}