{
  "type": "Feature",
  "properties": {
    "iso:country":"US",
    "sg:address":"7171 Winbourne Ave",
    "sg:city":"Baton Rouge",
    "sg:classifiers":[
        {
            "category":"Personal",
            "subcategory":"Barber",
            "type":"Services"
        }
    ],
    "sg:phone":"+1 225 355 5538",
    "sg:postcode":"70805",
    "sg:province":"LA",
    "wof:name":"Kathy's For Hair",
    "wof:placetype":"venue"
},
  "geometry": {"coordinates":[-91.12133,30.479635],"type":"Point"}
}