{
  "type": "Feature",
  "properties": {
    "addr:full":"6311 Airline Dr Metairie LA 70003",
    "addr:housenumber":"6311",
    "addr:postcode":"70003",
    "addr:street":"Airline Dr",
    "iso:country":"US",
    "sg:address":"6311 Airline Dr",
    "sg:city":"Metairie",
    "sg:classifiers":[
        {
            "category":"Restaurant",
            "type":"Food & Drink"
        }
    ],
    "sg:menulink":"http://www.allmenus.com/la/bridge-city/65417-cicis-pizza-buffet/menu/",
    "sg:phone":"+1 504 818 2422",
    "sg:postcode":"70003",
    "sg:province":"LA",
    "sg:tags":[
        "american",
        "pizza"
    ],
    "wof:name":"CiCi's Pizza Buffet",
    "wof:placetype":"venue"
},
  "geometry": {"coordinates":[-90.20249699999999,29.977326],"type":"Point"}
}