{
  "type": "Feature",
  "properties": {
    "iso:country":"US",
    "sg:address":"731 Hwy 164",
    "sg:city":"Haughton",
    "sg:classifiers":[
        {
            "category":"Organizations",
            "subcategory":"Religious Organization",
            "type":"Services"
        }
    ],
    "sg:phone":"+1 318 949 1240",
    "sg:postcode":"71037",
    "sg:province":"LA",
    "sg:tags":[
        "church"
    ],
    "wof:name":"New Hope Baptist Church",
    "wof:placetype":"venue"
},
  "geometry": {"coordinates":[-93.483937,32.556404],"type":"Point"}
}