{
  "type": "Feature",
  "properties": {
    "iso:country":"US",
    "sg:address":"2040 California Ave",
    "sg:city":"Kenner",
    "sg:classifiers":[
        {
            "category":"Building & Trades",
            "subcategory":"Construction",
            "type":"Services"
        }
    ],
    "sg:phone":"+1 504 469 4619",
    "sg:postcode":"70062",
    "sg:province":"LA",
    "sg:tags":[
        "concrete",
        "cutting",
        "breaking",
        "sawing"
    ],
    "sg:website":"www.allaroundconcrete.com",
    "wof:name":"All Around Concrete Cutting",
    "wof:placetype":"venue"
},
  "geometry": {"coordinates":[-90.24638899999999,29.994003],"type":"Point"}
}