{
  "type": "Feature",
  "properties": {
    "iso:country":"US",
    "sg:address":"17030 State Rte 10",
    "sg:city":"Pitkin",
    "sg:classifiers":[
        {
            "category":"Home & Garden",
            "subcategory":"Garden Supply",
            "type":"Retail Goods"
        }
    ],
    "sg:phone":"+1 318 634 3408",
    "sg:postcode":"70656",
    "sg:province":"LA",
    "sg:tags":[
        "tree",
        "christmas"
    ],
    "wof:name":"Grant Christmas Tree Farm",
    "wof:placetype":"venue"
},
  "geometry": {"coordinates":[-92.82583,30.888599],"type":"Point"}
}