{
  "type": "Feature",
  "properties": {
    "addr:full":"502 3rd St Kenner LA 70062",
    "addr:housenumber":"502",
    "addr:postcode":"70062",
    "addr:street":"3Rd St",
    "iso:country":"US",
    "sg:address":"502 3rd St",
    "sg:city":"Kenner",
    "sg:classifiers":[
        {
            "category":"Personal",
            "subcategory":"Beauty Salon",
            "type":"Services"
        }
    ],
    "sg:phone":"+1 504 467 0785",
    "sg:postcode":"70062",
    "sg:province":"LA",
    "wof:name":"New Expressions",
    "wof:placetype":"venue"
},
  "geometry": {"coordinates":[-90.264674,29.976606],"type":"Point"}
}