{
  "type": "Feature",
  "properties": {
    "iso:country":"US",
    "sg:address":"1105 Bellevue Dr",
    "sg:city":"La Place",
    "sg:classifiers":[
        {
            "category":"Manufacturing",
            "subcategory":"Electronics",
            "type":"Manufacturing & Wholesale Goods"
        }
    ],
    "sg:phone":"+1 985 651 9692",
    "sg:postcode":"70068",
    "sg:province":"LA",
    "sg:tags":[
        "answer",
        "auto",
        "telephone",
        "equipment"
    ],
    "sg:website":"www.ebmsinc.com",
    "wof:name":"Electronic Business Machine",
    "wof:placetype":"venue"
},
  "geometry": {"coordinates":[-90.488916,30.076043],"type":"Point"}
}