{
  "type": "Feature",
  "properties": {
    "iso:country":"US",
    "sg:address":"326 Hord St",
    "sg:city":"Harahan",
    "sg:classifiers":[
        {
            "category":"Building & Trades",
            "subcategory":"Construction",
            "type":"Services"
        }
    ],
    "sg:phone":"+1 504 734 0028",
    "sg:postcode":"70123",
    "sg:province":"LA",
    "sg:tags":[
        "painter"
    ],
    "wof:name":"G W Krail General Painting Inc",
    "wof:placetype":"venue"
},
  "geometry": {"coordinates":[-90.19320399999999,29.945137],"type":"Point"}
}