{
  "type": "Feature",
  "properties": {
    "iso:country":"US",
    "sg:address":"4059 Tulane Ave",
    "sg:city":"New Orleans",
    "sg:classifiers":[
        {
            "category":"Insurance",
            "subcategory":"Insurance Agent",
            "type":"Services"
        }
    ],
    "sg:phone":"+1 504 286 1333",
    "sg:postcode":"70119",
    "sg:province":"LA",
    "wof:name":"Olympic Insurance",
    "wof:placetype":"venue"
},
  "geometry": {"coordinates":[-90.10533,29.968579],"type":"Point"}
}