{
  "type": "Feature",
  "properties": {
    "addr:full":"1053 Hwy 401 Napoleonville LA 70390",
    "addr:housenumber":"1053",
    "addr:postcode":"70390",
    "addr:street":"Hwy 401 Napoleonville",
    "iso:country":"US",
    "sg:address":"1053 Hwy 401",
    "sg:city":"Napoleonville",
    "sg:classifiers":[
        {
            "category":"Professional",
            "type":"Services"
        }
    ],
    "sg:phone":"+1 985 369 6655",
    "sg:postcode":"70390",
    "sg:province":"LA",
    "sg:tags":[
        "reader"
    ],
    "wof:name":"Victor Syverson",
    "wof:placetype":"venue"
},
  "geometry": {"coordinates":[-91.076206,29.893236],"type":"Point"}
}