{
  "type": "Feature",
  "properties": {
    "iso:country":"US",
    "sg:address":"1013 E McNeese St",
    "sg:city":"Lake Charles",
    "sg:classifiers":[
        {
            "category":"Insurance",
            "subcategory":"Insurance Agent",
            "type":"Services"
        }
    ],
    "sg:phone":"+1 337 562 1808",
    "sg:postcode":"70607",
    "sg:province":"LA",
    "wof:name":"Insurance Unlimited",
    "wof:placetype":"venue"
},
  "geometry": {"coordinates":[-93.207403,30.176266],"type":"Point"}
}