{
  "type": "Feature",
  "properties": {
    "iso:country":"US",
    "sg:address":"4109 Pines Rd",
    "sg:city":"Shreveport",
    "sg:classifiers":[
        {
            "category":"Recreation",
            "type":"Entertainment"
        }
    ],
    "sg:phone":"+1 318 673 7790",
    "sg:postcode":"71119",
    "sg:province":"LA",
    "sg:tags":[
        "tennis",
        "court"
    ],
    "wof:name":"Cockrell Tennis Ctr",
    "wof:placetype":"venue"
},
  "geometry": {"coordinates":[-93.865494,32.464952],"type":"Point"}
}