{
  "type": "Feature",
  "properties": {
    "iso:country":"US",
    "sg:address":"244 Lee Burns Camp Rd",
    "sg:city":"Extension",
    "sg:classifiers":[
        {
            "category":"Farming",
            "subcategory":"Farm",
            "type":"Manufacturing & Wholesale Goods"
        }
    ],
    "sg:phone":"+1 318 723 4101",
    "sg:postcode":"71243",
    "sg:province":"LA",
    "sg:tags":[
        "crop",
        "general"
    ],
    "wof:name":"Withers Farm Inc",
    "wof:placetype":"venue"
},
  "geometry": {"coordinates":[-91.77728500000001,31.948804],"type":"Point"}
}