{
  "type": "Feature",
  "properties": {
    "addr:full":"8200 Jefferson Hwy Baton Rouge LA 70809",
    "addr:housenumber":"8200",
    "addr:postcode":"70809",
    "addr:street":"Jefferson Hwy",
    "iso:country":"US",
    "sg:address":"8200 Jefferson Hwy",
    "sg:city":"Baton Rouge",
    "sg:classifiers":[
        {
            "category":"Restaurant",
            "type":"Food & Drink"
        }
    ],
    "sg:menulink":"http://www.allmenus.com/la/baton-rouge/21782-las-palmas/menu/",
    "sg:phone":"+1 225 201 1818",
    "sg:postcode":"70809",
    "sg:province":"LA",
    "sg:tags":[
        "mexican"
    ],
    "wof:name":"Las Palmas",
    "wof:placetype":"venue"
},
  "geometry": {"coordinates":[-91.101883,30.422228],"type":"Point"}
}