{
  "type": "Feature",
  "properties": {
    "addr:full":"4829 E Saint Bernard Hwy Violet LA 70092",
    "addr:housenumber":"4829",
    "addr:postcode":"70092",
    "addr:street":"E Saint Bernard Hwy Violet La",
    "iso:country":"US",
    "sg:address":"4829 E Saint Bernard Hwy",
    "sg:city":"Violet",
    "sg:classifiers":[
        {
            "category":"Building & Trades",
            "subcategory":"Plumbing",
            "type":"Services"
        }
    ],
    "sg:phone":"+1 504 277 0945",
    "sg:postcode":"70092",
    "sg:province":"LA",
    "wof:name":"Superior Plumbing & Heating Co Inc",
    "wof:placetype":"venue"
},
  "geometry": {"coordinates":[-89.91300200000001,29.9168],"type":"Point"}
}