{
  "type": "Feature",
  "properties": {
    "iso:country":"US",
    "sg:address":"630 S Tyler St",
    "sg:city":"Covington",
    "sg:classifiers":[
        {
            "category":"Health Services",
            "subcategory":"Doctor",
            "type":"Services"
        }
    ],
    "sg:phone":"+1 985 893 1035",
    "sg:postcode":"70433",
    "sg:province":"LA",
    "sg:tags":[
        "physician",
        "surgeon"
    ],
    "wof:name":"Dermatology Clinic-St Tammany",
    "wof:placetype":"venue"
},
  "geometry": {"coordinates":[-90.109939,30.473938],"type":"Point"}
}