{
  "type": "Feature",
  "properties": {
    "iso:country":"US",
    "sg:address":"900 Lyman Ave",
    "sg:city":"Rayne",
    "sg:classifiers":[
        {
            "category":"Professional",
            "subcategory":"Business Services",
            "type":"Services"
        }
    ],
    "sg:phone":"+1 337 334 8315",
    "sg:postcode":"70578",
    "sg:province":"LA",
    "sg:tags":[
        "recording",
        "studio"
    ],
    "wof:name":"Non-Fiction Records",
    "wof:placetype":"venue"
},
  "geometry": {"coordinates":[-92.27377,30.245212],"type":"Point"}
}