{
  "type": "Feature",
  "properties": {
    "addr:full":"5300 Tchoupitoulas St New Orleans LA 70115",
    "addr:housenumber":"5300",
    "addr:postcode":"70115",
    "addr:street":"Tchoupitoulas St",
    "iso:country":"US",
    "sg:address":"5300 Tchoupitoulas St",
    "sg:city":"New Orleans",
    "sg:classifiers":[
        {
            "category":"Health Services",
            "subcategory":"Optometrist",
            "type":"Services"
        }
    ],
    "sg:phone":"+1 504 899 2228",
    "sg:postcode":"70115",
    "sg:province":"LA",
    "wof:name":"Crescent City Vision LLC",
    "wof:placetype":"venue"
},
  "geometry": {"coordinates":[-90.114414,29.916476],"type":"Point"}
}