{
  "type": "Feature",
  "properties": {
    "iso:country":"US",
    "sg:address":"3225 Louisiana Ave",
    "sg:city":"Lafayette",
    "sg:classifiers":[
        {
            "category":"Shopping",
            "subcategory":"Department Store",
            "type":"Retail Goods"
        }
    ],
    "sg:phone":"+1 337 572 9911",
    "sg:postcode":"70501",
    "sg:province":"LA",
    "sg:website":"www.rossstores.com",
    "wof:name":"Ross Dress For Less Store 1229",
    "wof:placetype":"venue"
},
  "geometry": {"coordinates":[-91.99456,30.26183],"type":"Point"}
}