{
  "type": "Feature",
  "properties": {
    "iso:country":"US",
    "sg:address":"1335 Governor Nicholls St",
    "sg:city":"New Orleans",
    "sg:classifiers":[
        {
            "category":"Personal",
            "type":"Services"
        }
    ],
    "sg:phone":"+1 504 522 3745",
    "sg:postcode":"70116",
    "sg:province":"LA",
    "wof:name":"Ahead",
    "wof:placetype":"venue"
},
  "geometry": {"coordinates":[-90.06699399999999,29.966296],"type":"Point"}
}