{
  "type": "Feature",
  "properties": {
    "iso:country":"US",
    "sg:address":"1029 S Genois St",
    "sg:city":"New Orleans",
    "sg:classifiers":[
        {
            "category":"Professional",
            "subcategory":"Business Services",
            "type":"Services"
        }
    ],
    "sg:phone":"+1 504 486 6387",
    "sg:postcode":"70125",
    "sg:province":"LA",
    "wof:name":"Presidential Enterprises Inc",
    "wof:placetype":"venue"
},
  "geometry": {"coordinates":[-90.104484,29.961648],"type":"Point"}
}