{
  "type": "Feature",
  "properties": {
    "iso:country":"US",
    "sg:address":"455 W 61st St",
    "sg:city":"Shreveport",
    "sg:classifiers":[
        {
            "category":"Manufacturing",
            "subcategory":"Retail Goods",
            "type":"Manufacturing & Wholesale Goods"
        }
    ],
    "sg:phone":"+1 318 868 1383",
    "sg:postcode":"71106",
    "sg:province":"LA",
    "sg:tags":[
        "manufacturer"
    ],
    "sg:website":"www.progressivecoatings.com",
    "wof:name":"Progressive Coatings Co",
    "wof:placetype":"venue"
},
  "geometry": {"coordinates":[-93.770669,32.451059],"type":"Point"}
}