{
  "type": "Feature",
  "properties": {
    "addr:full":"2125 Old Minden Rd Bossier City LA 71112",
    "addr:housenumber":"2125",
    "addr:postcode":"71112",
    "addr:street":"Old Minden Rd",
    "iso:country":"US",
    "sg:address":"2125 Old Minden Rd",
    "sg:city":"Bossier City",
    "sg:classifiers":[
        {
            "category":"Professional",
            "subcategory":"Management & Consulting",
            "type":"Services"
        }
    ],
    "sg:phone":"+1 318 746 8548",
    "sg:postcode":"71112",
    "sg:province":"LA",
    "sg:tags":[
        "consultant"
    ],
    "wof:name":"PPM Consulting Inc",
    "wof:placetype":"venue"
},
  "geometry": {"coordinates":[-93.703423,32.519501],"type":"Point"}
}