{
  "type": "Feature",
  "properties": {
    "iso:country":"US",
    "sg:address":"510 NW Evangeline Trwy",
    "sg:city":"Lafayette",
    "sg:classifiers":[
        {
            "category":"Organizations",
            "subcategory":"Religious Organization",
            "type":"Services"
        }
    ],
    "sg:phone":"+1 337 261 1225",
    "sg:postcode":"70501",
    "sg:province":"LA",
    "wof:name":"Christ the King Church",
    "wof:placetype":"venue"
},
  "geometry": {"coordinates":[-92.014198,30.233101],"type":"Point"}
}