{
  "type": "Feature",
  "properties": {
    "addr:full":"3151 Yupon St New Orleans LA 70119",
    "addr:housenumber":"3151",
    "addr:postcode":"70119",
    "addr:street":"Yupon St",
    "iso:country":"US",
    "sg:address":"3151 Yupon St",
    "sg:city":"New Orleans",
    "sg:classifiers":[
        {
            "category":"Manufacturing",
            "subcategory":"Petroleum Products",
            "type":"Manufacturing & Wholesale Goods"
        }
    ],
    "sg:phone":"+1 504 947 4920",
    "sg:postcode":"70119",
    "sg:province":"LA",
    "sg:tags":[
        "asphalt",
        "mfg"
    ],
    "wof:name":"Siplast Inc",
    "wof:placetype":"venue"
},
  "geometry": {"coordinates":[-90.08592400000001,29.99041],"type":"Point"}
}