{
  "type": "Feature",
  "properties": {
    "addr:full":"3888 S Sherwood Forest Blvd Baton Rouge LA 70816",
    "addr:housenumber":"3888",
    "addr:postcode":"70816",
    "addr:street":"S Sherwood Forest Blvd",
    "iso:country":"US",
    "sg:address":"3888 S Sherwood Forest Blvd",
    "sg:city":"Baton Rouge",
    "sg:classifiers":[
        {
            "category":"Banks & Credit Unions",
            "subcategory":"Bank",
            "type":"Services"
        }
    ],
    "sg:phone":"+1 225 293 9899",
    "sg:postcode":"70816",
    "sg:province":"LA",
    "sg:tags":[
        "loan",
        "real estate"
    ],
    "wof:name":"Premier Mortgage Funding",
    "wof:placetype":"venue"
},
  "geometry": {"coordinates":[-91.051575,30.419046],"type":"Point"}
}