{
  "type": "Feature",
  "properties": {
    "iso:country":"US",
    "sg:address":"1421 Greenlaw St",
    "sg:city":"Franklinton",
    "sg:classifiers":[
        {
            "category":"Restaurant",
            "type":"Food & Drink"
        }
    ],
    "sg:phone":"+1 985 795 0208",
    "sg:postcode":"70438",
    "sg:province":"LA",
    "wof:name":"Sister's Cafe",
    "wof:placetype":"venue"
},
  "geometry": {"coordinates":[-90.149328,30.849592],"type":"Point"}
}