{
  "type": "Feature",
  "properties": {
    "iso:country":"US",
    "sg:address":"145 Industrial Pkwy",
    "sg:city":"Lafayette",
    "sg:classifiers":[
        {
            "category":"Mining & Drilling",
            "type":"Manufacturing & Wholesale Goods"
        }
    ],
    "sg:phone":"+1 337 233 5565",
    "sg:postcode":"70508",
    "sg:province":"LA",
    "sg:tags":[
        "field",
        "oil"
    ],
    "sg:website":"www.alertweather.com",
    "wof:name":"Alert Weather Svc",
    "wof:placetype":"venue"
},
  "geometry": {"coordinates":[-92.00938499999999,30.185979],"type":"Point"}
}