{
  "type": "Feature",
  "properties": {
    "iso:country":"US",
    "sg:address":"116 W Pine St",
    "sg:city":"Ponchatoula",
    "sg:classifiers":[
        {
            "category":"Restaurant",
            "type":"Food & Drink"
        }
    ],
    "sg:phone":"+1 985 386 9007",
    "sg:postcode":"70454",
    "sg:province":"LA",
    "wof:name":"Pine Street Pub",
    "wof:placetype":"venue"
},
  "geometry": {"coordinates":[-90.441699,30.438777],"type":"Point"}
}