{
  "type": "Feature",
  "properties": {
    "iso:country":"US",
    "sg:address":"1730 US Hwy 171",
    "sg:city":"Stonewall",
    "sg:classifiers":[
        {
            "category":"Autos & Motor Vehicles",
            "subcategory":"Automobile Sales",
            "type":"Retail Goods"
        }
    ],
    "sg:phone":"+1 318 925 5151",
    "sg:postcode":"71078",
    "sg:province":"LA",
    "sg:tags":[
        "car",
        "dealer"
    ],
    "wof:name":"Wheels & Deals",
    "wof:placetype":"venue"
},
  "geometry": {"coordinates":[-93.82373,32.257073],"type":"Point"}
}