{
  "type": "Feature",
  "properties": {
    "addr:full":"506 N 16th St Monroe LA 71201",
    "addr:housenumber":"506",
    "addr:postcode":"71201",
    "addr:street":"N 16Th St",
    "iso:country":"US",
    "sg:address":"506 N 16th St",
    "sg:city":"Monroe",
    "sg:classifiers":[
        {
            "category":"Organizations",
            "subcategory":"Religious Organization",
            "type":"Services"
        }
    ],
    "sg:phone":"+1 318 388 1178",
    "sg:postcode":"71201",
    "sg:province":"LA",
    "sg:tags":[
        "church"
    ],
    "wof:name":"Beautiful Gate Christian Ctr",
    "wof:placetype":"venue"
},
  "geometry": {"coordinates":[-92.107423,32.514691],"type":"Point"}
}