{
  "type": "Feature",
  "properties": {
    "iso:country":"US",
    "sg:address":"220 Project Rd",
    "sg:city":"Thibodaux",
    "sg:classifiers":[
        {
            "category":"Wholesale",
            "subcategory":"Electrical",
            "type":"Manufacturing & Wholesale Goods"
        }
    ],
    "sg:phone":"+1 985 446 2100",
    "sg:postcode":"70301",
    "sg:province":"LA",
    "sg:tags":[
        "alarm",
        "burglar",
        "system"
    ],
    "wof:name":"See-Ya Video Security & Survei",
    "wof:placetype":"venue"
},
  "geometry": {"coordinates":[-90.826035,29.762073],"type":"Point"}
}