{
  "type": "Feature",
  "properties": {
    "addr:full":"814 Oneal Ln Baton Rouge LA 70816",
    "addr:housenumber":"814",
    "addr:postcode":"70816",
    "addr:street":"Oneal Ln",
    "iso:country":"US",
    "sg:address":"814 Oneal Ln",
    "sg:city":"Baton Rouge",
    "sg:classifiers":[
        {
            "category":"Personal",
            "subcategory":"Beauty Salon",
            "type":"Services"
        }
    ],
    "sg:phone":"+1 225 273 0887",
    "sg:postcode":"70816",
    "sg:province":"LA",
    "sg:tags":[
        "shop"
    ],
    "wof:name":"Modern Nails",
    "wof:placetype":"venue"
},
  "geometry": {"coordinates":[-91.00845099999999,30.456783],"type":"Point"}
}