{
  "type": "Feature",
  "properties": {
    "iso:country":"US",
    "sg:address":"109 Bridge St",
    "sg:city":"New Iberia",
    "sg:classifiers":[
        {
            "category":"Real Estate",
            "subcategory":"Real Estate Operator",
            "type":"Services"
        }
    ],
    "sg:phone":"+1 337 365 0108",
    "sg:postcode":"70563",
    "sg:province":"LA",
    "sg:tags":[
        "building",
        "parks"
    ],
    "wof:name":"Place Eugenie",
    "wof:placetype":"venue"
},
  "geometry": {"coordinates":[-91.816689,30.006206],"type":"Point"}
}