{
  "type": "Feature",
  "properties": {
    "addr:full":"2940 Bert Kouns Industrial Loop Shreveport LA 71118",
    "addr:housenumber":"2940",
    "addr:postcode":"71118",
    "addr:street":"Bert Kouns Industrial Loop",
    "iso:country":"US",
    "sg:address":"2940 Bert Kouns Industrial Loop",
    "sg:city":"Shreveport",
    "sg:classifiers":[
        {
            "category":"Travel",
            "subcategory":"Hotels & Motels",
            "type":"Entertainment"
        }
    ],
    "sg:phone":"+1 318 212 0421",
    "sg:postcode":"71118",
    "sg:province":"LA",
    "wof:name":"Stone America",
    "wof:placetype":"venue"
},
  "geometry": {"coordinates":[-93.807171,32.402211],"type":"Point"}
}