{
  "type": "Feature",
  "properties": {
    "iso:country":"US",
    "sg:address":"107 E 93rd St",
    "sg:city":"Cut Off",
    "sg:classifiers":[
        {
            "category":"Restaurant",
            "type":"Food & Drink"
        }
    ],
    "sg:phone":"+1 985 632 2223",
    "sg:postcode":"70345",
    "sg:province":"LA",
    "sg:tags":[
        "eating"
    ],
    "wof:name":"Taylor's Restaurant",
    "wof:placetype":"venue"
},
  "geometry": {"coordinates":[-90.309595,29.468439],"type":"Point"}
}