{
  "type": "Feature",
  "properties": {
    "iso:country":"US",
    "sg:address":"16881 Jefferson Hwy",
    "sg:city":"Baton Rouge",
    "sg:classifiers":[
        {
            "category":"Retail",
            "subcategory":"Car Wash",
            "type":"Services"
        }
    ],
    "sg:phone":"+1 225 751 8576",
    "sg:postcode":"70817",
    "sg:province":"LA",
    "sg:tags":[
        "polishing",
        "washing"
    ],
    "wof:name":"S & A Car Wash Inc",
    "wof:placetype":"venue"
},
  "geometry": {"coordinates":[-91.001199,30.362059],"type":"Point"}
}