{
  "type": "Feature",
  "properties": {
    "iso:country":"US",
    "sg:address":"111 N Causeway Blvd",
    "sg:city":"Mandeville",
    "sg:classifiers":[
        {
            "category":"Real Estate",
            "subcategory":"Real Estate Agent",
            "type":"Services"
        }
    ],
    "sg:phone":"+1 985 674 4474",
    "sg:postcode":"70448",
    "sg:province":"LA",
    "sg:website":"www.realtyexecutivesonline.com",
    "wof:name":"Realty Executives",
    "wof:placetype":"venue"
},
  "geometry": {"coordinates":[-90.092248,30.371874],"type":"Point"}
}