{
  "type": "Feature",
  "properties": {
    "iso:country":"US",
    "sg:address":"6461 State Rte 73",
    "sg:city":"Geismar",
    "sg:classifiers":[
        {
            "category":"Personal",
            "subcategory":"Beauty Salon",
            "type":"Services"
        }
    ],
    "sg:phone":"+1 225 677 5357",
    "sg:postcode":"70734",
    "sg:province":"LA",
    "wof:name":"Salon De Vie",
    "wof:placetype":"venue"
},
  "geometry": {"coordinates":[-90.99577499999999,30.230091],"type":"Point"}
}