{
  "type": "Feature",
  "properties": {
    "addr:full":"4501 W Napoleon Ave Metairie LA 70001",
    "addr:housenumber":"4501",
    "addr:postcode":"70001",
    "addr:street":"W Napoleon Ave",
    "iso:country":"US",
    "sg:address":"4501 W Napoleon Ave",
    "sg:city":"Metairie",
    "sg:classifiers":[
        {
            "category":"Insurance",
            "subcategory":"Insurance Agent",
            "type":"Services"
        }
    ],
    "sg:phone":"+1 504 883 4102",
    "sg:postcode":"70001",
    "sg:province":"LA",
    "wof:name":"Bat",
    "wof:placetype":"venue"
},
  "geometry": {"coordinates":[-90.18083799999999,29.993962],"type":"Point"}
}