{
  "type": "Feature",
  "properties": {
    "iso:country":"US",
    "sg:address":"217 Cocoville Rd",
    "sg:city":"Mansura",
    "sg:classifiers":[
        {
            "category":"Sports & Exercise",
            "subcategory":"Golf",
            "type":"Entertainment"
        }
    ],
    "sg:phone":"+1 318 240 8839",
    "sg:postcode":"71350",
    "sg:province":"LA",
    "sg:tags":[
        "course"
    ],
    "wof:name":"Tunica Golf Course-Maintenance",
    "wof:placetype":"venue"
},
  "geometry": {"coordinates":[-92.05559100000001,31.09538],"type":"Point"}
}