{
  "type": "Feature",
  "properties": {
    "iso:country":"US",
    "sg:address":"403 Hwy 71 S",
    "sg:city":"Cheneyville",
    "sg:classifiers":[
        {
            "category":"Home & Garden",
            "subcategory":"Hardware",
            "type":"Retail Goods"
        }
    ],
    "sg:phone":"+1 318 279 2115",
    "sg:postcode":"71325",
    "sg:province":"LA",
    "wof:name":"Harper Hardware & Lumber Co",
    "wof:placetype":"venue"
},
  "geometry": {"coordinates":[-92.282331,31.007778],"type":"Point"}
}