{
  "type": "Feature",
  "properties": {
    "iso:country":"US",
    "sg:address":"118 Rue Fountaine",
    "sg:city":"Lafayette",
    "sg:classifiers":[
        {
            "category":"Education",
            "subcategory":"Special Training",
            "type":"Public Place"
        }
    ],
    "sg:phone":"+1 337 993 3298",
    "sg:postcode":"70508",
    "sg:province":"LA",
    "sg:tags":[
        "educational"
    ],
    "wof:name":"Education America Lafayette",
    "wof:placetype":"venue"
},
  "geometry": {"coordinates":[-92.024111,30.169627],"type":"Point"}
}