{
  "type": "Feature",
  "properties": {
    "addr:full":"100 Veterans Blvd New Orleans LA 70124",
    "addr:housenumber":"100",
    "addr:postcode":"70124",
    "addr:street":"Veterans Blvd",
    "iso:country":"US",
    "sg:address":"100 Veterans Blvd",
    "sg:city":"New Orleans",
    "sg:classifiers":[
        {
            "category":"Government",
            "subcategory":"Office",
            "type":"Public Place"
        }
    ],
    "sg:phone":"+1 504 483 4519",
    "sg:postcode":"70124",
    "sg:province":"LA",
    "wof:name":"Safety Enforcement",
    "wof:placetype":"venue"
},
  "geometry": {"coordinates":[-90.116236,29.99956],"type":"Point"}
}