{
  "type": "Feature",
  "properties": {
    "iso:country":"US",
    "sg:address":"212 Hines Ln",
    "sg:city":"West Monroe",
    "sg:classifiers":[
        {
            "category":"Building & Trades",
            "subcategory":"Plumbing",
            "type":"Services"
        }
    ],
    "sg:phone":"+1 318 330 9990",
    "sg:postcode":"71291",
    "sg:province":"LA",
    "sg:tags":[
        "heating",
        "contractor"
    ],
    "wof:name":"Thermal Tech Environmental Svc",
    "wof:placetype":"venue"
},
  "geometry": {"coordinates":[-92.166155,32.515591],"type":"Point"}
}