{
  "type": "Feature",
  "properties": {
    "iso:country":"US",
    "sg:address":"216 N Duncan Ave",
    "sg:city":"Amite",
    "sg:classifiers":[
        {
            "category":"Education",
            "subcategory":"Dance Studio",
            "type":"Public Place"
        }
    ],
    "sg:phone":"+1 985 748 7549",
    "sg:postcode":"70422",
    "sg:province":"LA",
    "wof:name":"Rowannas Studio of Dance",
    "wof:placetype":"venue"
},
  "geometry": {"coordinates":[-90.501925,30.731166],"type":"Point"}
}