{
  "type": "Feature",
  "properties": {
    "iso:country":"US",
    "sg:address":"9303 E Park Ave",
    "sg:city":"Houma",
    "sg:classifiers":[
        {
            "category":"Autos & Motor Vehicles",
            "subcategory":"Fuel & Gas Station",
            "type":"Retail Goods"
        }
    ],
    "sg:phone":"+1 985 872 4626",
    "sg:postcode":"70363",
    "sg:province":"LA",
    "sg:tags":[
        "oil"
    ],
    "wof:name":"Prospect Shell",
    "wof:placetype":"venue"
},
  "geometry": {"coordinates":[-90.64769200000001,29.567318],"type":"Point"}
}