{
  "type": "Feature",
  "properties": {
    "addr:full":"1309 N Market St Shreveport LA 71107",
    "addr:housenumber":"1309",
    "addr:postcode":"71107",
    "addr:street":"N Market St",
    "iso:country":"US",
    "sg:address":"1309 N Market St",
    "sg:city":"Shreveport",
    "sg:classifiers":[
        {
            "category":"Retail",
            "subcategory":"Auto Repair",
            "type":"Services"
        }
    ],
    "sg:phone":"+1 318 221 3688",
    "sg:postcode":"71107",
    "sg:province":"LA",
    "sg:tags":[
        "automobile",
        "electric"
    ],
    "wof:name":"Fletcher's Automotive Electric",
    "wof:placetype":"venue"
},
  "geometry": {"coordinates":[-93.767916,32.534196],"type":"Point"}
}