{
  "type": "Feature",
  "properties": {
    "addr:full":"2110 Dumaine St New Orleans LA 70116",
    "addr:housenumber":"2110",
    "addr:postcode":"70116",
    "addr:street":"Dumaine St",
    "iso:country":"US",
    "sg:address":"2110 Dumaine St",
    "sg:city":"New Orleans",
    "sg:classifiers":[
        {
            "category":"Retail",
            "subcategory":"Auto Repair",
            "type":"Services"
        }
    ],
    "sg:phone":"+1 504 827 1915",
    "sg:postcode":"70116",
    "sg:province":"LA",
    "sg:tags":[
        "general"
    ],
    "wof:name":"Bees Auto Repairs",
    "wof:placetype":"venue"
},
  "geometry": {"coordinates":[-90.07639899999999,29.968508],"type":"Point"}
}