{
  "type": "Feature",
  "properties": {
    "addr:full":"1221 Cypremort Rd Jeanerette LA 70544",
    "addr:housenumber":"1221",
    "addr:postcode":"70544",
    "addr:street":"Cypremort Rd",
    "iso:country":"US",
    "sg:address":"1221 Cypremort Rd",
    "sg:city":"Jeanerette",
    "sg:classifiers":[
        {
            "category":"Restaurant",
            "type":"Food & Drink"
        }
    ],
    "sg:phone":"+1 337 276 9664",
    "sg:postcode":"70544",
    "sg:province":"LA",
    "sg:tags":[
        "eating"
    ],
    "wof:name":"Kens Place",
    "wof:placetype":"venue"
},
  "geometry": {"coordinates":[-91.638621,29.848647],"type":"Point"}
}