{
  "type": "Feature",
  "properties": {
    "addr:full":"306 Valencia Dr Luling LA 70070",
    "addr:housenumber":"306",
    "addr:postcode":"70070",
    "addr:street":"Valencia Dr",
    "iso:country":"US",
    "sg:address":"306 Valencia Dr",
    "sg:city":"Luling",
    "sg:classifiers":[
        {
            "category":"Shopping",
            "subcategory":"Clothing, Apparel, & Fashions",
            "type":"Retail Goods"
        }
    ],
    "sg:phone":"+1 985 785 1587",
    "sg:postcode":"70070",
    "sg:province":"LA",
    "wof:name":"Regina Allemand",
    "wof:placetype":"venue"
},
  "geometry": {"coordinates":[-90.370597,29.904371],"type":"Point"}
}