{
  "type": "Feature",
  "properties": {
    "iso:country":"US",
    "sg:address":"3482 Drusilla Ln",
    "sg:city":"Baton Rouge",
    "sg:classifiers":[
        {
            "category":"Manufacturing",
            "subcategory":"Printing",
            "type":"Manufacturing & Wholesale Goods"
        }
    ],
    "sg:phone":"+1 225 925 5000",
    "sg:postcode":"70809",
    "sg:province":"LA",
    "sg:tags":[
        "printer"
    ],
    "wof:name":"American Printing Ctr",
    "wof:placetype":"venue"
},
  "geometry": {"coordinates":[-91.088638,30.419572],"type":"Point"}
}