{
  "type": "Feature",
  "properties": {
    "iso:country":"US",
    "sg:address":"8675 Bluebonnet Blvd",
    "sg:city":"Baton Rouge",
    "sg:classifiers":[
        {
            "category":"Health Services",
            "subcategory":"Clinic",
            "type":"Services"
        }
    ],
    "sg:phone":"+1 225 769 9122",
    "sg:postcode":"70810",
    "sg:province":"LA",
    "wof:name":"Healthy Alternatives LLC",
    "wof:placetype":"venue"
},
  "geometry": {"coordinates":[-91.101871,30.370644],"type":"Point"}
}