{
  "type": "Feature",
  "properties": {
    "iso:country":"US",
    "sg:address":"6305 Elysian Fields Ave",
    "sg:city":"New Orleans",
    "sg:classifiers":[
        {
            "category":"Professional",
            "subcategory":"Computer Services",
            "type":"Services"
        }
    ],
    "sg:phone":"+1 504 282 9868",
    "sg:postcode":"70122",
    "sg:province":"LA",
    "sg:tags":[
        "repair"
    ],
    "wof:name":"Computer Troubleshooters",
    "wof:placetype":"venue"
},
  "geometry": {"coordinates":[-90.06098299999999,30.024133],"type":"Point"}
}