{
  "type": "Feature",
  "properties": {
    "addr:full":"39325 Hwy 190 E Slidell LA 70461",
    "addr:housenumber":"39325",
    "addr:postcode":"70461",
    "addr:street":"Hwy 190 E",
    "iso:country":"US",
    "sg:address":"39325 Hwy 190 E",
    "sg:city":"Slidell",
    "sg:classifiers":[
        {
            "category":"Autos & Motor Vehicles",
            "subcategory":"Automobile Sales",
            "type":"Retail Goods"
        }
    ],
    "sg:phone":"+1 985 781 7070",
    "sg:postcode":"70461",
    "sg:province":"LA",
    "sg:tags":[
        "car",
        "dealer"
    ],
    "wof:name":"Selective Auto Sales",
    "wof:placetype":"venue"
},
  "geometry": {"coordinates":[-89.744195,30.268042],"type":"Point"}
}