{
  "type": "Feature",
  "properties": {
    "iso:country":"US",
    "sg:address":"2101 Robin Ave",
    "sg:city":"Hammond",
    "sg:classifiers":[
        {
            "category":"Health Services",
            "subcategory":"Podiatrist",
            "type":"Services"
        }
    ],
    "sg:phone":"+1 985 542 0258",
    "sg:postcode":"70403",
    "sg:province":"LA",
    "wof:name":"Allen's Podiatry Clinic",
    "wof:placetype":"venue"
},
  "geometry": {"coordinates":[-90.48416,30.48523],"type":"Point"}
}