{
  "type": "Feature",
  "properties": {
    "addr:full":"1050 Westbank Expy Gretna LA 70053",
    "addr:housenumber":"1050",
    "addr:postcode":"70053",
    "addr:street":"Westbank Expy",
    "iso:country":"US",
    "sg:address":"1050 Westbank Expy",
    "sg:city":"Gretna",
    "sg:classifiers":[
        {
            "category":"Shopping",
            "subcategory":"Department Store",
            "type":"Retail Goods"
        }
    ],
    "sg:phone":"+1 504 347 7773",
    "sg:postcode":"70053",
    "sg:province":"LA",
    "sg:website":"www.dollargeneral.com",
    "wof:name":"Dollar General Stores",
    "wof:placetype":"venue"
},
  "geometry": {"coordinates":[-90.05680099999999,29.91],"type":"Point"}
}