{
  "type": "Feature",
  "properties": {
    "addr:full":"7120 Line Ave Shreveport LA 71106",
    "addr:housenumber":"7120",
    "addr:postcode":"71106",
    "addr:street":"Line Ave",
    "iso:country":"US",
    "sg:address":"7120 Line Ave",
    "sg:city":"Shreveport",
    "sg:classifiers":[
        {
            "category":"Building & Trades",
            "subcategory":"Construction",
            "type":"Services"
        }
    ],
    "sg:phone":"+1 318 865 1427",
    "sg:postcode":"71106",
    "sg:province":"LA",
    "sg:tags":[
        "designer",
        "dealer",
        "pool",
        "swimming"
    ],
    "sg:website":"www.moreheadpools.com",
    "wof:name":"Morehead Pools",
    "wof:placetype":"venue"
},
  "geometry": {"coordinates":[-93.74605,32.439661],"type":"Point"}
}