{
  "type": "Feature",
  "properties": {
    "iso:country":"US",
    "sg:address":"1700 N University Ave",
    "sg:city":"Lafayette",
    "sg:classifiers":[
        {
            "category":"Restaurant",
            "type":"Food & Drink"
        }
    ],
    "sg:phone":"+1 337 237 2704",
    "sg:postcode":"70507",
    "sg:province":"LA",
    "sg:tags":[
        "traditional",
        "american"
    ],
    "wof:name":"Cracker Barrel",
    "wof:placetype":"venue"
},
  "geometry": {"coordinates":[-92.036383,30.252547],"type":"Point"}
}