{
  "type": "Feature",
  "properties": {
    "iso:country":"US",
    "sg:address":"18339 Creek Hollow Rd",
    "sg:city":"Baton Rouge",
    "sg:classifiers":[
        {
            "category":"Professional",
            "subcategory":"Business Services",
            "type":"Services"
        }
    ],
    "sg:phone":"+1 225 752 8213",
    "sg:postcode":"70817",
    "sg:province":"LA",
    "wof:name":"June Powell Interior Design",
    "wof:placetype":"venue"
},
  "geometry": {"coordinates":[-90.984937,30.402339],"type":"Point"}
}