{
  "type": "Feature",
  "properties": {
    "iso:country":"US",
    "sg:address":"1259 Safe Energy Dr",
    "sg:city":"Port Allen",
    "sg:classifiers":[
        {
            "category":"Manufacturing",
            "subcategory":"Chemicals & Compounds",
            "type":"Manufacturing & Wholesale Goods"
        }
    ],
    "sg:phone":"+1 225 389 9133",
    "sg:postcode":"70767",
    "sg:province":"LA",
    "wof:name":"Trans Chem Inc",
    "wof:placetype":"venue"
},
  "geometry": {"coordinates":[-91.214714,30.497902],"type":"Point"}
}