{
  "type": "Feature",
  "properties": {
    "iso:country":"US",
    "sg:address":"6005 Lafreniere St",
    "sg:city":"Metairie",
    "sg:classifiers":[
        {
            "category":"Utilities",
            "subcategory":"Sewage",
            "type":"Services"
        },
        {
            "category":"Wholesale",
            "subcategory":"Machinery & Supplies",
            "type":"Manufacturing & Wholesale Goods"
        }
    ],
    "sg:phone":"+1 504 455 3216",
    "sg:postcode":"70003",
    "sg:province":"LA",
    "sg:tags":[
        "equipment",
        "industrial",
        "treatment"
    ],
    "wof:name":"Johnson Equipment Company",
    "wof:placetype":"venue"
},
  "geometry": {"coordinates":[-90.202663,29.992392],"type":"Point"}
}