{
  "type": "Feature",
  "properties": {
    "iso:country":"US",
    "sg:address":"2112 Farmerville Hwy",
    "sg:city":"Ruston",
    "sg:classifiers":[
        {
            "category":"Retail",
            "subcategory":"Auto Repair",
            "type":"Services"
        }
    ],
    "sg:phone":"+1 318 255 5063",
    "sg:postcode":"71270",
    "sg:province":"LA",
    "sg:tags":[
        "body",
        "automobile",
        "painting"
    ],
    "wof:name":"Bradshaw Body Shop",
    "wof:placetype":"venue"
},
  "geometry": {"coordinates":[-92.6105,32.549025],"type":"Point"}
}