{
  "type": "Feature",
  "properties": {
    "addr:full":"3869 Gentilly Blvd New Orleans LA 70122",
    "addr:housenumber":"3869",
    "addr:postcode":"70122",
    "addr:street":"Gentilly Blvd",
    "iso:country":"US",
    "sg:address":"3869 Gentilly Blvd",
    "sg:city":"New Orleans",
    "sg:classifiers":[
        {
            "category":"Shopping",
            "type":"Retail Goods"
        }
    ],
    "sg:phone":"+1 504 286 0439",
    "sg:postcode":"70122",
    "sg:province":"LA",
    "sg:tags":[
        "wedding",
        "supply"
    ],
    "wof:name":"Champagne & Roses",
    "wof:placetype":"venue"
},
  "geometry": {"coordinates":[-90.046087,30.002821],"type":"Point"}
}