{
  "type": "Feature",
  "properties": {
    "addr:full":"515 Lawrence St Lake Charles LA 70601",
    "addr:housenumber":"515",
    "addr:postcode":"70601",
    "addr:street":"Lawrence St",
    "iso:country":"US",
    "sg:address":"515 Lawrence St",
    "sg:city":"Lake Charles",
    "sg:classifiers":[
        {
            "category":"Building & Trades",
            "subcategory":"Construction",
            "type":"Services"
        }
    ],
    "sg:phone":"+1 337 433 0888",
    "sg:postcode":"70601",
    "sg:province":"LA",
    "sg:tags":[
        "contractor"
    ],
    "wof:name":"Artisan Tiling",
    "wof:placetype":"venue"
},
  "geometry": {"coordinates":[-93.212934,30.234261],"type":"Point"}
}