{
  "type": "Feature",
  "properties": {
    "iso:country":"US",
    "sg:address":"334 Leblanc St",
    "sg:city":"Opelousas",
    "sg:classifiers":[
        {
            "category":"Autos & Motor Vehicles",
            "subcategory":"Automobile Sales",
            "type":"Retail Goods"
        }
    ],
    "sg:phone":"+1 337 942 8499",
    "sg:postcode":"70570",
    "sg:province":"LA",
    "sg:tags":[
        "car",
        "dealer"
    ],
    "wof:name":"Winbush Auto Sales",
    "wof:placetype":"venue"
},
  "geometry": {"coordinates":[-92.08495000000001,30.540944],"type":"Point"}
}