{
  "type": "Feature",
  "properties": {
    "iso:country":"US",
    "sg:address":"5904 Fairfield Ave",
    "sg:city":"Shreveport",
    "sg:classifiers":[
        {
            "category":"Building & Trades",
            "subcategory":"Construction",
            "type":"Services"
        }
    ],
    "sg:phone":"+1 318 868 4020",
    "sg:postcode":"71106",
    "sg:province":"LA",
    "sg:tags":[
        "dry wall",
        "contractor"
    ],
    "wof:name":"Blocker Co",
    "wof:placetype":"venue"
},
  "geometry": {"coordinates":[-93.750342,32.45392],"type":"Point"}
}