{
  "type": "Feature",
  "properties": {
    "addr:full":"415 Bertrand Dr Lafayette LA 70506",
    "addr:housenumber":"415",
    "addr:postcode":"70506",
    "addr:street":"Bertrand Dr",
    "iso:country":"US",
    "sg:address":"415 Bertrand Dr",
    "sg:city":"Lafayette",
    "sg:classifiers":[
        {
            "category":"Shopping",
            "subcategory":"Department Store",
            "type":"Retail Goods"
        }
    ],
    "sg:phone":"+1 337 264 1030",
    "sg:postcode":"70506",
    "sg:province":"LA",
    "wof:name":"Dollar General",
    "wof:placetype":"venue"
},
  "geometry": {"coordinates":[-92.04434000000001,30.210893],"type":"Point"}
}