{
  "type": "Feature",
  "properties": {
    "iso:country":"US",
    "sg:address":"101 Tiffany St",
    "sg:city":"Patterson",
    "sg:classifiers":[
        {
            "category":"Organizations",
            "subcategory":"Religious Organization",
            "type":"Services"
        }
    ],
    "sg:phone":"+1 985 395 2333",
    "sg:postcode":"70392",
    "sg:province":"LA",
    "sg:tags":[
        "church"
    ],
    "wof:name":"Bethel Pentecostal Fellowship",
    "wof:placetype":"venue"
},
  "geometry": {"coordinates":[-91.30277100000001,29.684704],"type":"Point"}
}