{
  "type": "Feature",
  "properties": {
    "iso:country":"US",
    "sg:address":"4424 Country Dr",
    "sg:city":"Bourg",
    "sg:classifiers":[
        {
            "category":"Building & Trades",
            "subcategory":"Landscaping Services",
            "type":"Services"
        }
    ],
    "sg:phone":"+1 985 868 1300",
    "sg:postcode":"70343",
    "sg:province":"LA",
    "sg:tags":[
        "landscape",
        "contractor"
    ],
    "wof:name":"Grasschopper",
    "wof:placetype":"venue"
},
  "geometry": {"coordinates":[-90.602794,29.552704],"type":"Point"}
}