{
  "type": "Feature",
  "properties": {
    "addr:full":"711 S Corrine St New Iberia LA 70560",
    "addr:housenumber":"711",
    "addr:postcode":"70560",
    "addr:street":"S Corrine St",
    "iso:country":"US",
    "sg:address":"711 S Corrine St",
    "sg:city":"New Iberia",
    "sg:classifiers":[
        {
            "category":"Retail",
            "subcategory":"Funeral Services",
            "type":"Services"
        }
    ],
    "sg:phone":"+1 337 369 3638",
    "sg:postcode":"70560",
    "sg:province":"LA",
    "sg:tags":[
        "cemetery"
    ],
    "wof:name":"Journet-Bolden Funeral Home",
    "wof:placetype":"venue"
},
  "geometry": {"coordinates":[-91.829002,30.006001],"type":"Point"}
}