{
  "type": "Feature",
  "properties": {
    "iso:country":"US",
    "sg:address":"5523 S Saratoga St",
    "sg:city":"New Orleans",
    "sg:classifiers":[
        {
            "category":"Government",
            "subcategory":"Office",
            "type":"Public Place"
        }
    ],
    "sg:phone":"+1 504 899 9223",
    "sg:postcode":"70115",
    "sg:province":"LA",
    "sg:tags":[
        "development"
    ],
    "wof:name":"Rcl 1 LLC",
    "wof:placetype":"venue"
},
  "geometry": {"coordinates":[-90.114017,29.931884],"type":"Point"}
}