{
  "type": "Feature",
  "properties": {
    "iso:country":"US",
    "sg:address":"17591 Palmer Rd",
    "sg:city":"Hammond",
    "sg:classifiers":[
        {
            "category":"Retail",
            "subcategory":"Car Wash",
            "type":"Services"
        }
    ],
    "sg:phone":"+1 985 345 4440",
    "sg:postcode":"70403",
    "sg:province":"LA",
    "sg:tags":[
        "polishing",
        "washing"
    ],
    "wof:name":"Pro Coating",
    "wof:placetype":"venue"
},
  "geometry": {"coordinates":[-90.428918,30.505523],"type":"Point"}
}