{
  "type": "Feature",
  "properties": {
    "addr:full":"7341 Jefferson Hwy Baton Rouge LA 70806",
    "addr:housenumber":"7341",
    "addr:postcode":"70806",
    "addr:street":"Jefferson Hwy",
    "iso:country":"US",
    "sg:address":"7341 Jefferson Hwy",
    "sg:city":"Baton Rouge",
    "sg:classifiers":[
        {
            "category":"Professional",
            "subcategory":"Management & Consulting",
            "type":"Services"
        }
    ],
    "sg:phone":"+1 225 928 2392",
    "sg:postcode":"70806",
    "sg:province":"LA",
    "sg:tags":[
        "counselor",
        "public",
        "relations"
    ],
    "wof:name":"Rafael Bermudez & Assoc",
    "wof:placetype":"venue"
},
  "geometry": {"coordinates":[-91.11108,30.433456],"type":"Point"}
}