{
  "type": "Feature",
  "properties": {
    "iso:country":"US",
    "sg:address":"11456 Hwy 28 E",
    "sg:city":"Pineville",
    "sg:classifiers":[
        {
            "category":"Shopping",
            "subcategory":"Gifts & Souvenirs",
            "type":"Retail Goods"
        }
    ],
    "sg:phone":"+1 318 466 5653",
    "sg:postcode":"71360",
    "sg:province":"LA",
    "sg:tags":[
        "shop"
    ],
    "wof:name":"Lisa's Country Cabin",
    "wof:placetype":"venue"
},
  "geometry": {"coordinates":[-92.256924,31.379029],"type":"Point"}
}