{
  "type": "Feature",
  "properties": {
    "iso:country":"US",
    "sg:address":"1537 N Claiborne Ave",
    "sg:city":"New Orleans",
    "sg:classifiers":[
        {
            "category":"Professional",
            "subcategory":"Accounting & Tax Preparation",
            "type":"Services"
        }
    ],
    "sg:phone":"+1 504 940 0027",
    "sg:postcode":"70116",
    "sg:province":"LA",
    "sg:tags":[
        "return",
        "filing"
    ],
    "wof:name":"KBO Tac & Accounting Svc",
    "wof:placetype":"venue"
},
  "geometry": {"coordinates":[-90.067239,29.971287],"type":"Point"}
}