{
  "type": "Feature",
  "properties": {
    "iso:country":"US",
    "sg:address":"3029 Saint Charles Ave",
    "sg:city":"New Orleans",
    "sg:classifiers":[
        {
            "category":"Restaurant",
            "type":"Food & Drink"
        }
    ],
    "sg:phone":"+1 504 895 9200",
    "sg:postcode":"70115",
    "sg:province":"LA",
    "sg:tags":[
        "banquet",
        "rooms"
    ],
    "sg:website":"www.elmsmansion.com",
    "wof:name":"Elms Mansion",
    "wof:placetype":"venue"
},
  "geometry": {"coordinates":[-90.088824,29.929542],"type":"Point"}
}