{
  "type": "Feature",
  "properties": {
    "addr:full":"410 E Colorado St Hammond LA 70401",
    "addr:housenumber":"410",
    "addr:postcode":"70401",
    "addr:street":"E Colorado St",
    "iso:country":"US",
    "sg:address":"410 E Colorado St",
    "sg:city":"Hammond",
    "sg:classifiers":[
        {
            "category":"Organizations",
            "subcategory":"Religious Organization",
            "type":"Services"
        }
    ],
    "sg:phone":"+1 985 345 6959",
    "sg:postcode":"70401",
    "sg:province":"LA",
    "sg:tags":[
        "church"
    ],
    "wof:name":"St Paul Baptist Church",
    "wof:placetype":"venue"
},
  "geometry": {"coordinates":[-90.458225,30.510782],"type":"Point"}
}