{
  "type": "Feature",
  "properties": {
    "iso:country":"US",
    "sg:address":"137 N Clark St",
    "sg:city":"New Orleans",
    "sg:classifiers":[
        {
            "category":"Health Services",
            "subcategory":"Nursing And Care Facility",
            "type":"Services"
        }
    ],
    "sg:phone":"+1 504 488 8839",
    "sg:postcode":"70119",
    "sg:province":"LA",
    "sg:tags":[
        "hospice"
    ],
    "wof:name":"Concerned Care Hospice",
    "wof:placetype":"venue"
},
  "geometry": {"coordinates":[-90.094826,29.971246],"type":"Point"}
}