{
  "type": "Feature",
  "properties": {
    "iso:country":"US",
    "sg:address":"8530 Anselmo Ln",
    "sg:city":"Baton Rouge",
    "sg:classifiers":[
        {
            "category":"Professional",
            "subcategory":"Accounting & Tax Preparation",
            "type":"Services"
        }
    ],
    "sg:phone":"+1 225 766 2622",
    "sg:postcode":"70810",
    "sg:province":"LA",
    "sg:tags":[
        "payroll"
    ],
    "sg:website":"www.employersupport.com",
    "wof:name":"Employer Support Svc",
    "wof:placetype":"venue"
},
  "geometry": {"coordinates":[-91.099024,30.391934],"type":"Point"}
}