{
  "type": "Feature",
  "properties": {
    "iso:country":"US",
    "sg:address":"146 Bauch Rd",
    "sg:city":"Houma",
    "sg:classifiers":[
        {
            "category":"Manufacturing",
            "subcategory":"Tools & Machinery",
            "type":"Manufacturing & Wholesale Goods"
        }
    ],
    "sg:phone":"+1 985 223 3005",
    "sg:postcode":"70363",
    "sg:province":"LA",
    "sg:tags":[
        "machine",
        "shop"
    ],
    "wof:name":"O & M Equipment",
    "wof:placetype":"venue"
},
  "geometry": {"coordinates":[-90.665443,29.575019],"type":"Point"}
}