{
  "type": "Feature",
  "properties": {
    "iso:country":"US",
    "sg:address":"513 Martin Luther King Dr",
    "sg:city":"Rayville",
    "sg:classifiers":[
        {
            "category":"Organizations",
            "subcategory":"Religious Organization",
            "type":"Services"
        }
    ],
    "sg:phone":"+1 318 728 9700",
    "sg:postcode":"71269",
    "sg:province":"LA",
    "sg:tags":[
        "church"
    ],
    "wof:name":"Rankin Chapel AME Church",
    "wof:placetype":"venue"
},
  "geometry": {"coordinates":[-91.753946,32.473988],"type":"Point"}
}