{
  "type": "Feature",
  "properties": {
    "iso:country":"US",
    "sg:address":"44084 Parker Blvd",
    "sg:city":"Hammond",
    "sg:classifiers":[
        {
            "category":"Professional",
            "subcategory":"Business Services",
            "type":"Services"
        }
    ],
    "sg:phone":"+1 985 542 8770",
    "sg:postcode":"70403",
    "sg:province":"LA",
    "sg:tags":[
        "diver"
    ],
    "sg:website":"www.sdive.com",
    "wof:name":"Speciality Diving",
    "wof:placetype":"venue"
},
  "geometry": {"coordinates":[-90.44549499999999,30.496091],"type":"Point"}
}