{
  "type": "Feature",
  "properties": {
    "addr:full":"585 Begnaud Rd Sunset LA 70584",
    "addr:housenumber":"585",
    "addr:postcode":"70584",
    "addr:street":"Begnaud Rd",
    "iso:country":"US",
    "sg:address":"585 Begnaud Rd",
    "sg:city":"Sunset",
    "sg:classifiers":[
        {
            "category":"Building & Trades",
            "subcategory":"Landscaping Services",
            "type":"Services"
        }
    ],
    "sg:phone":"+1 337 662 5008",
    "sg:postcode":"70584",
    "sg:province":"LA",
    "sg:tags":[
        "lawn",
        "maintenance",
        "grounds"
    ],
    "wof:name":"Sunset Nursery Farm",
    "wof:placetype":"venue"
},
  "geometry": {"coordinates":[-92.074073,30.384788],"type":"Point"}
}