{
  "type": "Feature",
  "properties": {
    "iso:country":"US",
    "sg:address":"8448 Athens Ave",
    "sg:city":"Baton Rouge",
    "sg:classifiers":[
        {
            "category":"Building & Trades",
            "subcategory":"Construction",
            "type":"Services"
        }
    ],
    "sg:phone":"+1 225 201 0899",
    "sg:postcode":"70814",
    "sg:province":"LA",
    "sg:tags":[
        "general",
        "contractor"
    ],
    "wof:name":"Gerald's Electric",
    "wof:placetype":"venue"
},
  "geometry": {"coordinates":[-91.100452,30.47513],"type":"Point"}
}