{
  "type": "Feature",
  "properties": {
    "iso:country":"US",
    "sg:address":"16849 E Main St",
    "sg:city":"Cut Off",
    "sg:classifiers":[
        {
            "category":"Marine",
            "type":"Transportation"
        }
    ],
    "sg:phone":"+1 985 632 5858",
    "sg:postcode":"70345",
    "sg:province":"LA",
    "sg:tags":[
        "towing"
    ],
    "wof:name":"Louisiana Carriers Inc",
    "wof:placetype":"venue"
},
  "geometry": {"coordinates":[-90.313059,29.470565],"type":"Point"}
}