{
  "type": "Feature",
  "properties": {
    "iso:country":"US",
    "sg:address":"3064 State Rte 569",
    "sg:city":"Ferriday",
    "sg:classifiers":[
        {
            "category":"Travel",
            "subcategory":"Travel Agent",
            "type":"Entertainment"
        }
    ],
    "sg:phone":"+1 318 757 3184",
    "sg:postcode":"71334",
    "sg:province":"LA",
    "sg:tags":[
        "agency",
        "bureau"
    ],
    "wof:name":"Vacation Specialists",
    "wof:placetype":"venue"
},
  "geometry": {"coordinates":[-91.44748800000001,31.721083],"type":"Point"}
}