{
  "type": "Feature",
  "properties": {
    "addr:full":"1492 Harding Blvd Baton Rouge LA 70807",
    "addr:housenumber":"1492",
    "addr:postcode":"70807",
    "addr:street":"Harding Blvd",
    "iso:country":"US",
    "sg:address":"1492 Harding Blvd",
    "sg:city":"Baton Rouge",
    "sg:classifiers":[
        {
            "category":"Shopping",
            "subcategory":"Clothing, Apparel, & Fashions",
            "type":"Retail Goods"
        }
    ],
    "sg:phone":"+1 225 775 5247",
    "sg:postcode":"70807",
    "sg:province":"LA",
    "sg:tags":[
        "t"
    ],
    "wof:name":"Top Choice Products",
    "wof:placetype":"venue"
},
  "geometry": {"coordinates":[-91.177215,30.520496],"type":"Point"}
}