{
  "type": "Feature",
  "properties": {
    "iso:country":"US",
    "sg:address":"3451 Hwy 19",
    "sg:city":"Zachary",
    "sg:classifiers":[
        {
            "category":"Home & Garden",
            "subcategory":"Building Materials",
            "type":"Retail Goods"
        }
    ],
    "sg:phone":"+1 225 381 8207",
    "sg:postcode":"70791",
    "sg:province":"LA",
    "sg:tags":[
        "glass",
        "window",
        "plate"
    ],
    "wof:name":"Cornerstone Glass LLC",
    "wof:placetype":"venue"
},
  "geometry": {"coordinates":[-91.155528,30.638541],"type":"Point"}
}