{
  "type": "Feature",
  "properties": {
    "iso:country":"US",
    "sg:address":"1410 Gum Cove Rd",
    "sg:city":"Vinton",
    "sg:classifiers":[
        {
            "category":"Food & Beverages",
            "subcategory":"Groceries & Convenience Stores",
            "type":"Retail Goods"
        }
    ],
    "sg:phone":"+1 337 589 4312",
    "sg:postcode":"70668",
    "sg:province":"LA",
    "wof:name":"E Z Mart Stores",
    "wof:placetype":"venue"
},
  "geometry": {"coordinates":[-93.57054599999999,30.187908],"type":"Point"}
}