{
  "type": "Feature",
  "properties": {
    "iso:country":"US",
    "sg:address":"3111 Lake St",
    "sg:city":"Lake Charles",
    "sg:classifiers":[
        {
            "category":"Professional",
            "subcategory":"Secretarial Services",
            "type":"Services"
        }
    ],
    "sg:phone":"+1 337 562 8197",
    "sg:postcode":"70601",
    "sg:province":"LA",
    "sg:tags":[
        "deposition",
        "video"
    ],
    "wof:name":"Doug Douget Video Productions",
    "wof:placetype":"venue"
},
  "geometry": {"coordinates":[-93.232276,30.198475],"type":"Point"}
}