{
  "type": "Feature",
  "properties": {
    "addr:full":"278 Reeves Rd Lake Charles LA 70611",
    "addr:housenumber":"278",
    "addr:postcode":"70611",
    "addr:street":"Reeves Rd",
    "iso:country":"US",
    "sg:address":"278 Reeves Rd",
    "sg:city":"Lake Charles",
    "sg:classifiers":[
        {
            "category":"Professional",
            "subcategory":"Business Services",
            "type":"Services"
        }
    ],
    "sg:phone":"+1 337 855 5200",
    "sg:postcode":"70611",
    "sg:province":"LA",
    "sg:tags":[
        "paging",
        "answering"
    ],
    "wof:name":"K & B Connexion Inc",
    "wof:placetype":"venue"
},
  "geometry": {"coordinates":[-93.214994,30.296689],"type":"Point"}
}