{
  "type": "Feature",
  "properties": {
    "addr:full":"3344 Youree Dr Shreveport LA 71105",
    "addr:housenumber":"3344",
    "addr:postcode":"71105",
    "addr:street":"Youree Dr",
    "iso:country":"US",
    "sg:address":"3344 Youree Dr",
    "sg:city":"Shreveport",
    "sg:classifiers":[
        {
            "category":"Personal",
            "type":"Services"
        },
        {
            "category":"Health Services",
            "subcategory":"Clinic",
            "type":"Services"
        }
    ],
    "sg:phone":"+1 318 865 0339",
    "sg:postcode":"71105",
    "sg:province":"LA",
    "sg:tags":[
        "holistic",
        "practitioner"
    ],
    "wof:name":"Nancy Guillet",
    "wof:placetype":"venue"
},
  "geometry": {"coordinates":[-93.722301,32.477313],"type":"Point"}
}