{
  "type": "Feature",
  "properties": {
    "iso:country":"US",
    "sg:address":"301 Western Hills Rd",
    "sg:city":"Boyce",
    "sg:classifiers":[
        {
            "category":"Building & Trades",
            "subcategory":"Construction",
            "type":"Services"
        }
    ],
    "sg:phone":"+1 318 793 4221",
    "sg:postcode":"71409",
    "sg:province":"LA",
    "sg:tags":[
        "home",
        "builder"
    ],
    "wof:name":"Calvin Cantrell Builders",
    "wof:placetype":"venue"
},
  "geometry": {"coordinates":[-92.679908,31.266973],"type":"Point"}
}