{
  "type": "Feature",
  "properties": {
    "iso:country":"US",
    "sg:address":"6400 Press Dr",
    "sg:city":"New Orleans",
    "sg:classifiers":[
        {
            "category":"Restaurant",
            "type":"Food & Drink"
        }
    ],
    "sg:phone":"+1 504 282 3797",
    "sg:postcode":"70126",
    "sg:province":"LA",
    "sg:tags":[
        "eating"
    ],
    "wof:name":"Feltons Barbecue Ranch",
    "wof:placetype":"venue"
},
  "geometry": {"coordinates":[-90.044021,30.024479],"type":"Point"}
}