{
  "type": "Feature",
  "properties": {
    "addr:full":"110 Boyce St Broussard LA 70518",
    "addr:housenumber":"110",
    "addr:postcode":"70518",
    "addr:street":"Boyce St",
    "iso:country":"US",
    "sg:address":"110 Boyce St",
    "sg:city":"Broussard",
    "sg:classifiers":[
        {
            "category":"Shopping",
            "subcategory":"Stationery & Office Supplies",
            "type":"Retail Goods"
        }
    ],
    "sg:phone":"+1 337 839 2889",
    "sg:postcode":"70518",
    "sg:province":"LA",
    "sg:tags":[
        "equipment"
    ],
    "wof:name":"Office Furniture Liquidation",
    "wof:placetype":"venue"
},
  "geometry": {"coordinates":[-91.94740299999999,30.133101],"type":"Point"}
}