{
  "type": "Feature",
  "properties": {
    "iso:country":"US",
    "sg:address":"1609 Cottage Ln",
    "sg:city":"Harvey",
    "sg:classifiers":[
        {
            "category":"Building & Trades",
            "subcategory":"Construction",
            "type":"Services"
        }
    ],
    "sg:phone":"+1 504 366 6030",
    "sg:postcode":"70058",
    "sg:province":"LA",
    "sg:tags":[
        "contractor"
    ],
    "wof:name":"William Cummings",
    "wof:placetype":"venue"
},
  "geometry": {"coordinates":[-90.04143000000001,29.864251],"type":"Point"}
}