{
  "type": "Feature",
  "properties": {
    "iso:country":"US",
    "sg:address":"5295 Highland Rd",
    "sg:city":"Baton Rouge",
    "sg:classifiers":[
        {
            "category":"Autos & Motor Vehicles",
            "subcategory":"Fuel & Gas Station",
            "type":"Retail Goods"
        }
    ],
    "sg:phone":"+1 225 767 2223",
    "sg:postcode":"70808",
    "sg:province":"LA",
    "sg:tags":[
        "oil"
    ],
    "wof:name":"College Town Exxon",
    "wof:placetype":"venue"
},
  "geometry": {"coordinates":[-91.163754,30.397143],"type":"Point"}
}