{
  "type": "Feature",
  "properties": {
    "addr:full":"1638 S 5th St Leesville LA 71446",
    "addr:housenumber":"1638",
    "addr:postcode":"71446",
    "addr:street":"S 5Th St",
    "iso:country":"US",
    "sg:address":"1638 S 5th St",
    "sg:city":"Leesville",
    "sg:classifiers":[
        {
            "category":"Restaurant",
            "type":"Food & Drink"
        }
    ],
    "sg:phone":"+1 337 238 1555",
    "sg:postcode":"71446",
    "sg:province":"LA",
    "wof:name":"Mc Donald's",
    "wof:placetype":"venue"
},
  "geometry": {"coordinates":[-93.267055,31.127913],"type":"Point"}
}