{
  "type": "Feature",
  "properties": {
    "iso:country":"US",
    "sg:address":"114 W W St",
    "sg:city":"Belle Chasse",
    "sg:classifiers":[
        {
            "category":"Building & Trades",
            "subcategory":"Plumbing",
            "type":"Services"
        }
    ],
    "sg:phone":"+1 504 391 1300",
    "sg:postcode":"70037",
    "sg:province":"LA",
    "sg:website":"www.tomsseweranddrain.com",
    "wof:name":"Tom's Sewer & Drain Service",
    "wof:placetype":"venue"
},
  "geometry": {"coordinates":[-90.011833,29.872878],"type":"Point"}
}