{
  "type": "Feature",
  "properties": {
    "addr:full":"7742 Office Park Blvd Baton Rouge LA 70809",
    "addr:housenumber":"7742",
    "addr:postcode":"70809",
    "addr:street":"Office Park Blvd",
    "iso:country":"US",
    "sg:address":"7742 Office Park Blvd",
    "sg:city":"Baton Rouge",
    "sg:classifiers":[
        {
            "category":"Professional",
            "subcategory":"Employment Agencies",
            "type":"Services"
        }
    ],
    "sg:phone":"+1 225 927 0550",
    "sg:postcode":"70809",
    "sg:province":"LA",
    "sg:tags":[
        "opportunity"
    ],
    "wof:name":"Snelling Personnel Svc",
    "wof:placetype":"venue"
},
  "geometry": {"coordinates":[-91.103286,30.419273],"type":"Point"}
}