{
  "type": "Feature",
  "properties": {
    "addr:full":"3932 Elm St Choudrant LA 71227",
    "addr:housenumber":"3932",
    "addr:postcode":"71227",
    "addr:street":"Elm St",
    "iso:country":"US",
    "sg:address":"3932 Elm St",
    "sg:city":"Choudrant",
    "sg:classifiers":[
        {
            "category":"Home & Garden",
            "subcategory":"Household Appliances",
            "type":"Retail Goods"
        }
    ],
    "sg:phone":"+1 318 768 2360",
    "sg:postcode":"71227",
    "sg:province":"LA",
    "wof:name":"Choudrant Appliance Co",
    "wof:placetype":"venue"
},
  "geometry": {"coordinates":[-92.514212,32.528208],"type":"Point"}
}