{
  "type": "Feature",
  "properties": {
    "iso:country":"US",
    "sg:address":"410 E Lafayette St",
    "sg:city":"Abbeville",
    "sg:classifiers":[
        {
            "category":"Real Estate",
            "subcategory":"Real Estate Agent",
            "type":"Services"
        }
    ],
    "sg:phone":"+1 337 898 1166",
    "sg:postcode":"70510",
    "sg:province":"LA",
    "sg:tags":[
        "appraiser"
    ],
    "wof:name":"James Noel Appraisers",
    "wof:placetype":"venue"
},
  "geometry": {"coordinates":[-92.132594,29.972338],"type":"Point"}
}