{
  "type": "Feature",
  "properties": {
    "addr:full":"2135 McClellan St Shreveport LA 71103",
    "addr:housenumber":"2135",
    "addr:postcode":"71103",
    "addr:street":"Mcclellan St",
    "iso:country":"US",
    "sg:address":"2135 McClellan St",
    "sg:city":"Shreveport",
    "sg:classifiers":[
        {
            "category":"Wholesale",
            "subcategory":"Construction Materials",
            "type":"Manufacturing & Wholesale Goods"
        }
    ],
    "sg:phone":"+1 318 222 8118",
    "sg:postcode":"71103",
    "sg:province":"LA",
    "sg:tags":[
        "concrete",
        "form"
    ],
    "wof:name":"Construction Materials Inc",
    "wof:placetype":"venue"
},
  "geometry": {"coordinates":[-93.757831,32.491771],"type":"Point"}
}