{
  "type": "Feature",
  "properties": {
    "iso:country":"US",
    "sg:address":"1227 N. University",
    "sg:city":"Lafayette",
    "sg:classifiers":[
        {
            "category":"Restaurant",
            "type":"Food & Drink"
        }
    ],
    "sg:phone":"+1 337 266 4648",
    "sg:postcode":"70506",
    "sg:province":"LA",
    "sg:tags":[
        "cajun/creole"
    ],
    "wof:name":"Creole Cafe",
    "wof:placetype":"venue"
},
  "geometry": {"coordinates":[-92.033531,30.246042],"type":"Point"}
}