{
  "type": "Feature",
  "properties": {
    "iso:country":"US",
    "sg:address":"120 Professional Dr",
    "sg:city":"West Monroe",
    "sg:classifiers":[
        {
            "category":"Health Services",
            "subcategory":"Doctor",
            "type":"Services"
        }
    ],
    "sg:phone":"+1 318 325 4600",
    "sg:postcode":"71291",
    "sg:province":"LA",
    "sg:tags":[
        "dentist"
    ],
    "wof:name":"L King Scott DDS",
    "wof:placetype":"venue"
},
  "geometry": {"coordinates":[-92.150077,32.515144],"type":"Point"}
}