{
  "type": "Feature",
  "properties": {
    "iso:country":"US",
    "sg:address":"311 Dean Ct",
    "sg:city":"Houma",
    "sg:classifiers":[
        {
            "category":"Manufacturing",
            "subcategory":"Tools & Machinery",
            "type":"Manufacturing & Wholesale Goods"
        }
    ],
    "sg:phone":"+1 985 223 9955",
    "sg:postcode":"70363",
    "sg:province":"LA",
    "sg:tags":[
        "machine",
        "shop"
    ],
    "wof:name":"Rabco Machine",
    "wof:placetype":"venue"
},
  "geometry": {"coordinates":[-90.705287,29.569114],"type":"Point"}
}