{
  "type": "Feature",
  "properties": {
    "addr:full":"3619 Ambassador Caffery Pkwy Lafayette LA 70503",
    "addr:housenumber":"3619",
    "addr:postcode":"70503",
    "addr:street":"Ambassador Caffery Pkwy",
    "iso:country":"US",
    "sg:address":"3619 Ambassador Caffery Pkwy",
    "sg:city":"Lafayette",
    "sg:classifiers":[
        {
            "category":"Shopping",
            "subcategory":"Gifts & Souvenirs",
            "type":"Retail Goods"
        }
    ],
    "sg:phone":"+1 337 991 0732",
    "sg:postcode":"70503",
    "sg:province":"LA",
    "sg:tags":[
        "shop"
    ],
    "wof:name":"Daystar",
    "wof:placetype":"venue"
},
  "geometry": {"coordinates":[-92.06993,30.17441],"type":"Point"}
}