{
  "type": "Feature",
  "properties": {
    "iso:country":"US",
    "sg:address":"318 S Buchanan St",
    "sg:city":"Lafayette",
    "sg:classifiers":[
        {
            "category":"Health Services",
            "subcategory":"Doctor",
            "type":"Services"
        }
    ],
    "sg:phone":"+1 337 235 8585",
    "sg:postcode":"70501",
    "sg:province":"LA",
    "sg:tags":[
        "dentist"
    ],
    "wof:name":"Neil J Bernard DDS",
    "wof:placetype":"venue"
},
  "geometry": {"coordinates":[-92.017371,30.227794],"type":"Point"}
}