{
  "type": "Feature",
  "properties": {
    "addr:full":"92 W Shamrock Ave Pineville LA 71360",
    "addr:housenumber":"92",
    "addr:postcode":"71360",
    "addr:street":"W Shamrock Ave",
    "iso:country":"US",
    "sg:address":"92 W Shamrock Ave",
    "sg:city":"Pineville",
    "sg:classifiers":[
        {
            "category":"Communications",
            "subcategory":"Radio Station",
            "type":"Services"
        }
    ],
    "sg:phone":"+1 337 233 1330",
    "sg:postcode":"71360",
    "sg:province":"LA",
    "sg:tags":[
        "broadcasting"
    ],
    "wof:name":"Cajun Communications Inc",
    "wof:placetype":"venue"
},
  "geometry": {"coordinates":[-92.434843,31.322747],"type":"Point"}
}