{
  "type": "Feature",
  "properties": {
    "iso:country":"US",
    "sg:address":"3612 Coliseum Blvd",
    "sg:city":"Alexandria",
    "sg:classifiers":[
        {
            "category":"Professional",
            "type":"Services"
        }
    ],
    "sg:phone":"+1 318 487 1111",
    "sg:postcode":"71303",
    "sg:province":"LA",
    "sg:tags":[
        "establishment"
    ],
    "sg:website":"www.rentalservice.com",
    "wof:name":"Prime Industrial",
    "wof:placetype":"venue"
},
  "geometry": {"coordinates":[-92.482134,31.29985],"type":"Point"}
}