{
  "type": "Feature",
  "properties": {
    "iso:country":"US",
    "sg:address":"7105 Linwood Ave",
    "sg:city":"Shreveport",
    "sg:classifiers":[
        {
            "category":"Retail",
            "subcategory":"Repair Shop",
            "type":"Services"
        }
    ],
    "sg:phone":"+1 318 868 7178",
    "sg:postcode":"71106",
    "sg:province":"LA",
    "sg:tags":[
        "upholsterer"
    ],
    "wof:name":"Davis Upholstery",
    "wof:placetype":"venue"
},
  "geometry": {"coordinates":[-93.76300500000001,32.440617],"type":"Point"}
}