{
  "type": "Feature",
  "properties": {
    "iso:country":"US",
    "sg:address":"283 E 28th St",
    "sg:city":"Cut Off",
    "sg:classifiers":[
        {
            "category":"Wholesale",
            "subcategory":"Medical Equipment & Supplies",
            "type":"Manufacturing & Wholesale Goods"
        }
    ],
    "sg:phone":"+1 985 693 3129",
    "sg:postcode":"70345",
    "sg:province":"LA",
    "sg:tags":[
        "physician",
        "surgeon"
    ],
    "wof:name":"Lafourche DME",
    "wof:placetype":"venue"
},
  "geometry": {"coordinates":[-90.341391,29.550758],"type":"Point"}
}