{
  "type": "Feature",
  "properties": {
    "iso:country":"US",
    "sg:address":"338 Tunica Dr W",
    "sg:city":"Marksville",
    "sg:classifiers":[
        {
            "category":"Building & Trades",
            "subcategory":"Equipment Rental",
            "type":"Services"
        }
    ],
    "sg:phone":"+1 318 253 8188",
    "sg:postcode":"71351",
    "sg:province":"LA",
    "sg:tags":[
        "leasing",
        "furniture"
    ],
    "wof:name":"Quality Rentals Furniture",
    "wof:placetype":"venue"
},
  "geometry": {"coordinates":[-92.073714,31.126011],"type":"Point"}
}