{
  "type": "Feature",
  "properties": {
    "addr:full":"514 N 11th St Oakdale LA 71463",
    "addr:housenumber":"514",
    "addr:postcode":"71463",
    "addr:street":"N 11Th St",
    "iso:country":"US",
    "sg:address":"514 N 11th St",
    "sg:city":"Oakdale",
    "sg:classifiers":[
        {
            "category":"Building & Trades",
            "subcategory":"Landscaping Services",
            "type":"Services"
        }
    ],
    "sg:phone":"+1 318 335 4569",
    "sg:postcode":"71463",
    "sg:province":"LA",
    "wof:name":"P Js Lawn Service",
    "wof:placetype":"venue"
},
  "geometry": {"coordinates":[-92.660161,30.819341],"type":"Point"}
}