{
  "type": "Feature",
  "properties": {
    "addr:full":"7873 Old Monroe Rd Bastrop LA 71220",
    "addr:housenumber":"7873",
    "addr:postcode":"71220",
    "addr:street":"Old Monroe Rd",
    "iso:country":"US",
    "sg:address":"7873 Old Monroe Rd",
    "sg:city":"Bastrop",
    "sg:classifiers":[
        {
            "category":"Freight",
            "type":"Transportation"
        }
    ],
    "sg:phone":"+1 318 281 5651",
    "sg:postcode":"71220",
    "sg:province":"LA",
    "sg:tags":[
        "building",
        "house",
        "mover"
    ],
    "wof:name":"Bastrop House Moving Co",
    "wof:placetype":"venue"
},
  "geometry": {"coordinates":[-91.917597,32.736443],"type":"Point"}
}