{
  "type": "Feature",
  "properties": {
    "iso:country":"US",
    "sg:address":"204 Clinic Dr",
    "sg:city":"Donaldsonville",
    "sg:classifiers":[
        {
            "category":"Health Services",
            "subcategory":"Health Practitioner",
            "type":"Services"
        }
    ],
    "sg:phone":"+1 225 473 4719",
    "sg:postcode":"70346",
    "sg:province":"LA",
    "sg:tags":[
        "therapist",
        "physical"
    ],
    "wof:name":"Ascension Physical Therapy",
    "wof:placetype":"venue"
},
  "geometry": {"coordinates":[-91.00393099999999,30.089779],"type":"Point"}
}