{
  "type": "Feature",
  "properties": {
    "addr:full":"126 W Oak St Amite LA 70422",
    "addr:housenumber":"126",
    "addr:postcode":"70422",
    "addr:street":"W Oak St",
    "iso:country":"US",
    "sg:address":"126 W Oak St",
    "sg:city":"Amite",
    "sg:classifiers":[
        {
            "category":"Banks & Credit Unions",
            "subcategory":"Bank",
            "type":"Services"
        }
    ],
    "sg:phone":"+1 985 748 4711",
    "sg:postcode":"70422",
    "sg:province":"LA",
    "sg:tags":[
        "loan"
    ],
    "wof:name":"Security Finance Corp",
    "wof:placetype":"venue"
},
  "geometry": {"coordinates":[-90.51018500000001,30.726712],"type":"Point"}
}