{
  "type": "Feature",
  "properties": {
    "iso:country":"US",
    "sg:address":"4643 Winbourne Ave",
    "sg:city":"Baton Rouge",
    "sg:classifiers":[
        {
            "category":"Social Services",
            "type":"Services"
        }
    ],
    "sg:phone":"+1 225 355 0702",
    "sg:postcode":"70805",
    "sg:province":"LA",
    "sg:tags":[
        "organization",
        "welfare"
    ],
    "wof:name":"United Methodist Mission Ctr",
    "wof:placetype":"venue"
},
  "geometry": {"coordinates":[-91.14278899999999,30.478874],"type":"Point"}
}