{
  "type": "Feature",
  "properties": {
    "addr:full":"108 15th St NW Springhill LA 71075",
    "addr:housenumber":"108",
    "addr:postcode":"71075",
    "addr:street":"15Th St Nw",
    "iso:country":"US",
    "sg:address":"108 15th St NW",
    "sg:city":"Springhill",
    "sg:classifiers":[
        {
            "category":"Recreation",
            "subcategory":"Arcade",
            "type":"Entertainment"
        }
    ],
    "sg:phone":"+1 318 539 2972",
    "sg:postcode":"71075",
    "sg:province":"LA",
    "sg:tags":[
        "device",
        "operator",
        "amusement"
    ],
    "wof:name":"Fleming Nobelty",
    "wof:placetype":"venue"
},
  "geometry": {"coordinates":[-93.489047,33.014261],"type":"Point"}
}