{
  "type": "Feature",
  "properties": {
    "iso:country":"US",
    "sg:address":"6014 Lanier Dr",
    "sg:city":"Baton Rouge",
    "sg:classifiers":[
        {
            "category":"Social Services",
            "subcategory":"Child Care",
            "type":"Services"
        }
    ],
    "sg:phone":"+1 225 357 9822",
    "sg:postcode":"70812",
    "sg:province":"LA",
    "sg:tags":[
        "sitting"
    ],
    "wof:name":"D & M Personal Care Attendant",
    "wof:placetype":"venue"
},
  "geometry": {"coordinates":[-91.10799,30.507853],"type":"Point"}
}