{
  "type": "Feature",
  "properties": {
    "iso:country":"US",
    "sg:address":"1056 Kincade Ct",
    "sg:city":"Lake Charles",
    "sg:classifiers":[
        {
            "category":"Professional",
            "subcategory":"Management & Consulting",
            "type":"Services"
        }
    ],
    "sg:phone":"+1 337 725 3334",
    "sg:postcode":"70611",
    "sg:province":"LA",
    "sg:tags":[
        "consultant",
        "business"
    ],
    "wof:name":"Kirby & Assoc",
    "wof:placetype":"venue"
},
  "geometry": {"coordinates":[-93.174905,30.318163],"type":"Point"}
}