{
  "type": "Feature",
  "properties": {
    "iso:country":"US",
    "sg:address":"2330 Park Place Dr",
    "sg:city":"Gretna",
    "sg:classifiers":[
        {
            "category":"Social Services",
            "subcategory":"Child Care",
            "type":"Services"
        }
    ],
    "sg:phone":"+1 504 392 3428",
    "sg:postcode":"70056",
    "sg:province":"LA",
    "wof:name":"Kinder Care Learning Ctr",
    "wof:placetype":"venue"
},
  "geometry": {"coordinates":[-90.017326,29.894434],"type":"Point"}
}