{
  "type": "Feature",
  "properties": {
    "iso:country":"US",
    "sg:address":"2207 Sampson St",
    "sg:city":"Westlake",
    "sg:classifiers":[
        {
            "category":"Personal",
            "subcategory":"Beauty Salon",
            "type":"Services"
        }
    ],
    "sg:phone":"+1 337 439 5551",
    "sg:postcode":"70669",
    "sg:province":"LA",
    "sg:tags":[
        "shop"
    ],
    "wof:name":"Creative Hair Designs",
    "wof:placetype":"venue"
},
  "geometry": {"coordinates":[-93.25821000000001,30.25902],"type":"Point"}
}