{
  "type": "Feature",
  "properties": {
    "addr:full":"19317 N 10th St Covington LA 70433",
    "addr:housenumber":"19317",
    "addr:postcode":"70433",
    "addr:street":"N 10Th St",
    "iso:country":"US",
    "sg:address":"19317 N 10th St",
    "sg:city":"Covington",
    "sg:classifiers":[
        {
            "category":"Real Estate",
            "subcategory":"Real Estate Agent",
            "type":"Services"
        }
    ],
    "sg:phone":"+1 985 893 1760",
    "sg:postcode":"70433",
    "sg:province":"LA",
    "sg:tags":[
        "appraiser"
    ],
    "wof:name":"Lake Parishes Appraisal Svc",
    "wof:placetype":"venue"
},
  "geometry": {"coordinates":[-90.08226999999999,30.464851],"type":"Point"}
}