{
  "type": "Feature",
  "properties": {
    "iso:country":"US",
    "sg:address":"500 N Cary Ave",
    "sg:city":"Jennings",
    "sg:classifiers":[
        {
            "category":"Banks & Credit Unions",
            "subcategory":"Bank",
            "type":"Services"
        }
    ],
    "sg:phone":"+1 337 824 1712",
    "sg:postcode":"70546",
    "sg:province":"LA",
    "wof:name":"First Guaranty Bank",
    "wof:placetype":"venue"
},
  "geometry": {"coordinates":[-92.6592,30.225354],"type":"Point"}
}