{
  "type": "Feature",
  "properties": {
    "iso:country":"US",
    "sg:address":"58125 Barrow St",
    "sg:city":"Plaquemine",
    "sg:classifiers":[
        {
            "category":"Food & Beverages",
            "subcategory":"Groceries & Convenience Stores",
            "type":"Retail Goods"
        },
        {
            "category":"Food & Beverages",
            "subcategory":"Liquor & Beverages",
            "type":"Retail Goods"
        }
    ],
    "sg:phone":"+1 225 687 3442",
    "sg:postcode":"70764",
    "sg:province":"LA",
    "sg:tags":[
        "beer",
        "ale"
    ],
    "wof:name":"Ike's Grocery",
    "wof:placetype":"venue"
},
  "geometry": {"coordinates":[-91.22982399999999,30.275975],"type":"Point"}
}