{
  "type": "Feature",
  "properties": {
    "iso:country":"US",
    "sg:address":"1275 Belleview St",
    "sg:city":"Morgan City",
    "sg:classifiers":[
        {
            "category":"Shopping",
            "subcategory":"Pharmacy",
            "type":"Retail Goods"
        }
    ],
    "sg:phone":"+1 985 876 9993",
    "sg:postcode":"70380",
    "sg:province":"LA",
    "wof:name":"MPI Pharmacy Svc",
    "wof:placetype":"venue"
},
  "geometry": {"coordinates":[-91.265367,29.684957],"type":"Point"}
}