{
  "type": "Feature",
  "properties": {
    "iso:country":"US",
    "sg:address":"8324 Parc Place",
    "sg:city":"Chalmette",
    "sg:classifiers":[
        {
            "category":"Organizations",
            "subcategory":"Non-profit Organization",
            "type":"Services"
        }
    ],
    "sg:phone":"+1 504 277 6831",
    "sg:postcode":"70043",
    "sg:province":"LA",
    "sg:tags":[
        "service/non-profit",
        "community"
    ],
    "sg:website":"www.stbernardproject.org",
    "wof:name":"St. Bernard Project",
    "wof:placetype":"venue"
},
  "geometry": {"coordinates":[-89.973467,29.954528],"type":"Point"}
}