{
  "type": "Feature",
  "properties": {
    "addr:full":"115 Brashear St Lafayette LA 70506",
    "addr:housenumber":"115",
    "addr:postcode":"70506",
    "addr:street":"Brashear St",
    "iso:country":"US",
    "sg:address":"115 Brashear St",
    "sg:city":"Lafayette",
    "sg:classifiers":[
        {
            "category":"Social Services",
            "type":"Services"
        }
    ],
    "sg:phone":"+1 337 237 9809",
    "sg:postcode":"70506",
    "sg:province":"LA",
    "wof:name":"A Safe Place",
    "wof:placetype":"venue"
},
  "geometry": {"coordinates":[-92.020726,30.216824],"type":"Point"}
}