{
  "type": "Feature",
  "properties": {
    "iso:country":"US",
    "sg:address":"6227 Saint Charles Ave",
    "sg:city":"New Orleans",
    "sg:classifiers":[
        {
            "category":"Real Estate",
            "subcategory":"Real Estate Agent",
            "type":"Services"
        }
    ],
    "sg:phone":"+1 504 282 3473",
    "sg:postcode":"70118",
    "sg:province":"LA",
    "wof:name":"Hebrew Rest Cemetary Assn",
    "wof:placetype":"venue"
},
  "geometry": {"coordinates":[-90.119737,29.932426],"type":"Point"}
}