{
  "type": "Feature",
  "properties": {
    "addr:full":"215 E McKinley Ave Haughton LA 71037",
    "addr:housenumber":"215",
    "addr:postcode":"71037",
    "addr:street":"E Mckinley Ave",
    "iso:country":"US",
    "sg:address":"215 E McKinley Ave",
    "sg:city":"Haughton",
    "sg:classifiers":[
        {
            "category":"Organizations",
            "subcategory":"Religious Organization",
            "type":"Services"
        }
    ],
    "sg:phone":"+1 318 949 3612",
    "sg:postcode":"71037",
    "sg:province":"LA",
    "sg:tags":[
        "church"
    ],
    "wof:name":"Haughton United Methodist Chr",
    "wof:placetype":"venue"
},
  "geometry": {"coordinates":[-93.491899,32.534728],"type":"Point"}
}