{
  "type": "Feature",
  "properties": {
    "addr:full":"1101 Terry Pkwy Terrytown LA 70056",
    "addr:housenumber":"1101",
    "addr:postcode":"70056",
    "addr:street":"Terry Pkwy",
    "iso:country":"US",
    "sg:address":"1101 Terry Pkwy",
    "sg:city":"Terrytown",
    "sg:classifiers":[
        {
            "category":"Personal",
            "subcategory":"Beauty Salon",
            "type":"Services"
        }
    ],
    "sg:phone":"+1 504 398 1150",
    "sg:postcode":"70056",
    "sg:province":"LA",
    "sg:tags":[
        "manicuring"
    ],
    "wof:name":"Judy Hebert Nail Technician",
    "wof:placetype":"venue"
},
  "geometry": {"coordinates":[-90.03081400000001,29.891515],"type":"Point"}
}