{
  "type": "Feature",
  "properties": {
    "addr:full":"623 Woodland St Montgomery LA 71454",
    "addr:housenumber":"623",
    "addr:postcode":"71454",
    "addr:street":"Woodland St",
    "iso:country":"US",
    "sg:address":"623 Woodland St",
    "sg:city":"Montgomery",
    "sg:classifiers":[
        {
            "category":"Government",
            "subcategory":"Office",
            "type":"Public Place"
        }
    ],
    "sg:phone":"+1 318 646 3474",
    "sg:postcode":"71454",
    "sg:province":"LA",
    "sg:tags":[
        "village"
    ],
    "wof:name":"Montgomery Water & Gas",
    "wof:placetype":"venue"
},
  "geometry": {"coordinates":[-92.890569,31.666091],"type":"Point"}
}