{
  "type": "Feature",
  "properties": {
    "addr:full":"11838 S Harrells Ferry Rd Baton Rouge LA 70816",
    "addr:housenumber":"11838",
    "addr:postcode":"70816",
    "addr:street":"S Harrells Ferry Rd",
    "iso:country":"US",
    "sg:address":"11838 S Harrells Ferry Rd",
    "sg:city":"Baton Rouge",
    "sg:classifiers":[
        {
            "category":"Professional",
            "subcategory":"Employment Agencies",
            "type":"Services"
        }
    ],
    "sg:phone":"+1 225 293 2220",
    "sg:postcode":"70816",
    "sg:province":"LA",
    "sg:tags":[
        "opportunity"
    ],
    "wof:name":"Angel Employment Svc",
    "wof:placetype":"venue"
},
  "geometry": {"coordinates":[-91.051879,30.430861],"type":"Point"}
}