{
  "type": "Feature",
  "properties": {
    "iso:country":"US",
    "sg:address":"132 Demanade Blvd",
    "sg:city":"Lafayette",
    "sg:classifiers":[
        {
            "category":"Professional",
            "subcategory":"Business Services",
            "type":"Services"
        }
    ],
    "sg:phone":"+1 337 233 2066",
    "sg:postcode":"70503",
    "sg:province":"LA",
    "sg:tags":[
        "gas",
        "measurement"
    ],
    "wof:name":"Southern Flow Co Inc",
    "wof:placetype":"venue"
},
  "geometry": {"coordinates":[-92.012683,30.202967],"type":"Point"}
}