{
  "type": "Feature",
  "properties": {
    "iso:country":"US",
    "sg:address":"3142 Ambassador Caffery Pkwy",
    "sg:city":"Lafayette",
    "sg:classifiers":[
        {
            "category":"Personal",
            "subcategory":"Beauty Salon",
            "type":"Services"
        }
    ],
    "sg:phone":"+1 337 991 0440",
    "sg:postcode":"70506",
    "sg:province":"LA",
    "wof:name":"Smart Style Family Hair Salon",
    "wof:placetype":"venue"
},
  "geometry": {"coordinates":[-92.075092,30.187423],"type":"Point"}
}