{
  "type": "Feature",
  "properties": {
    "addr:full":"1364 Paul Maillard Rd Luling LA 70070",
    "addr:housenumber":"1364",
    "addr:postcode":"70070",
    "addr:street":"Paul Maillard Rd",
    "iso:country":"US",
    "sg:address":"1364 Paul Maillard Rd",
    "sg:city":"Luling",
    "sg:classifiers":[
        {
            "category":"Food & Beverages",
            "subcategory":"Groceries & Convenience Stores",
            "type":"Retail Goods"
        }
    ],
    "sg:phone":"+1 985 785 9277",
    "sg:postcode":"70070",
    "sg:province":"LA",
    "wof:name":"Jiff's Petroleum",
    "wof:placetype":"venue"
},
  "geometry": {"coordinates":[-90.375798,29.919174],"type":"Point"}
}