{
  "type": "Feature",
  "properties": {
    "iso:country":"US",
    "sg:address":"10555 Old Hammond Hwy",
    "sg:city":"Baton Rouge",
    "sg:classifiers":[
        {
            "category":"Freight",
            "type":"Transportation"
        }
    ],
    "sg:phone":"+1 225 928 1980",
    "sg:postcode":"70816",
    "sg:province":"LA",
    "sg:tags":[
        "commercial",
        "storage"
    ],
    "wof:name":"Storage Center",
    "wof:placetype":"venue"
},
  "geometry": {"coordinates":[-91.06754599999999,30.43426],"type":"Point"}
}