{
  "type": "Feature",
  "properties": {
    "iso:country":"US",
    "sg:address":"15555 Denham Rd",
    "sg:city":"Pride",
    "sg:classifiers":[
        {
            "category":"Retail",
            "subcategory":"Repair Shop",
            "type":"Services"
        }
    ],
    "sg:phone":"+1 225 261 2512",
    "sg:postcode":"70770",
    "sg:province":"LA",
    "sg:tags":[
        "outboard",
        "motor"
    ],
    "wof:name":"Nolan Mouton Marine Svc",
    "wof:placetype":"venue"
},
  "geometry": {"coordinates":[-91.009715,30.590872],"type":"Point"}
}