{
  "type": "Feature",
  "properties": {
    "iso:country":"US",
    "sg:address":"609 1st St",
    "sg:city":"Kentwood",
    "sg:classifiers":[
        {
            "category":"Shopping",
            "subcategory":"Jewelry",
            "type":"Retail Goods"
        }
    ],
    "sg:phone":"+1 985 229 6666",
    "sg:postcode":"70444",
    "sg:province":"LA",
    "sg:tags":[
        "jeweler"
    ],
    "wof:name":"Connie's Jewelry & Gifts",
    "wof:placetype":"venue"
},
  "geometry": {"coordinates":[-90.507273,30.937968],"type":"Point"}
}