{
  "type": "Feature",
  "properties": {
    "addr:full":"2911 Cameron St Monroe LA 71201",
    "addr:housenumber":"2911",
    "addr:postcode":"71201",
    "addr:street":"Cameron St",
    "iso:country":"US",
    "sg:address":"2911 Cameron St",
    "sg:city":"Monroe",
    "sg:classifiers":[
        {
            "category":"Banks & Credit Unions",
            "subcategory":"Investment Brokerage",
            "type":"Services"
        }
    ],
    "sg:phone":"+1 318 388 2687",
    "sg:postcode":"71201",
    "sg:province":"LA",
    "sg:tags":[
        "commodity"
    ],
    "wof:name":"Swayze Brokerage",
    "wof:placetype":"venue"
},
  "geometry": {"coordinates":[-92.090643,32.532044],"type":"Point"}
}