{
  "type": "Feature",
  "properties": {
    "addr:full":"115 Gerard St Mandeville LA 70448",
    "addr:housenumber":"115",
    "addr:postcode":"70448",
    "addr:street":"Gerard St",
    "iso:country":"US",
    "sg:address":"115 Gerard St",
    "sg:city":"Mandeville",
    "sg:classifiers":[
        {
            "category":"Restaurant",
            "type":"Food & Drink"
        }
    ],
    "sg:phone":"+1 985 624 5330",
    "sg:postcode":"70448",
    "sg:province":"LA",
    "wof:name":"Juniper",
    "wof:placetype":"venue"
},
  "geometry": {"coordinates":[-90.067849,30.353948],"type":"Point"}
}