{
  "type": "Feature",
  "properties": {
    "iso:country":"US",
    "sg:address":"501 S Pine St",
    "sg:city":"Deridder",
    "sg:classifiers":[
        {
            "category":"Health Services",
            "subcategory":"Doctor",
            "type":"Services"
        }
    ],
    "sg:phone":"+1 337 462 3937",
    "sg:postcode":"70634",
    "sg:province":"LA",
    "sg:tags":[
        "physician",
        "surgeon"
    ],
    "wof:name":"Eye Clinic",
    "wof:placetype":"venue"
},
  "geometry": {"coordinates":[-93.289108,30.842914],"type":"Point"}
}