{
  "type": "Feature",
  "properties": {
    "iso:country":"US",
    "sg:address":"101 Claymore Dr",
    "sg:city":"Lafayette",
    "sg:classifiers":[
        {
            "category":"Real Estate",
            "subcategory":"Real Estate Agent",
            "type":"Services"
        }
    ],
    "sg:phone":"+1 337 988 5632",
    "sg:postcode":"70503",
    "sg:province":"LA",
    "wof:name":"Canjun ADS LLC",
    "wof:placetype":"venue"
},
  "geometry": {"coordinates":[-92.05328799999999,30.195815],"type":"Point"}
}