{
  "type": "Feature",
  "properties": {
    "addr:full":"205 Washington St Napoleonville LA 70390",
    "addr:housenumber":"205",
    "addr:postcode":"70390",
    "addr:street":"Washington St",
    "iso:country":"US",
    "sg:address":"205 Washington St",
    "sg:city":"Napoleonville",
    "sg:classifiers":[
        {
            "category":"Banks & Credit Unions",
            "subcategory":"Bank",
            "type":"Services"
        }
    ],
    "sg:phone":"+1 985 369 4700",
    "sg:postcode":"70390",
    "sg:province":"LA",
    "wof:name":"Community Bank",
    "wof:placetype":"venue"
},
  "geometry": {"coordinates":[-91.024188,29.939809],"type":"Point"}
}