{
  "type": "Feature",
  "properties": {
    "addr:full":"109 Wall Blvd Gretna LA 70056",
    "addr:housenumber":"109",
    "addr:postcode":"70056",
    "addr:street":"Wall Blvd",
    "iso:country":"US",
    "sg:address":"109 Wall Blvd",
    "sg:city":"Gretna",
    "sg:classifiers":[
        {
            "category":"Bars & Pubs",
            "subcategory":"Nightclub",
            "type":"Food & Drink"
        }
    ],
    "sg:phone":"+1 504 393 8344",
    "sg:postcode":"70056",
    "sg:province":"LA",
    "sg:tags":[
        "nightlife"
    ],
    "wof:name":"Cocktails",
    "wof:placetype":"venue"
},
  "geometry": {"coordinates":[-90.030953,29.886781],"type":"Point"}
}