{
  "type": "Feature",
  "properties": {
    "addr:full":"67487 Armel Rd Mandeville LA 70471",
    "addr:postcode":"67487;70471",
    "addr:street":"Armel Rd",
    "iso:country":"US",
    "sg:address":"67487 Armel Rd",
    "sg:city":"Mandeville",
    "sg:classifiers":[
        {
            "category":"Retail",
            "subcategory":"Repair Shop",
            "type":"Services"
        }
    ],
    "sg:phone":"+1 985 892 4621",
    "sg:postcode":"70471",
    "sg:province":"LA",
    "wof:name":"Key Man Lock Service",
    "wof:placetype":"venue"
},
  "geometry": {"coordinates":[-90.030862,30.413759],"type":"Point"}
}