{
  "type": "Feature",
  "properties": {
    "iso:country":"US",
    "sg:address":"1300 5th St",
    "sg:city":"Lake Charles",
    "sg:classifiers":[
        {
            "category":"Education",
            "subcategory":"School",
            "type":"Public Place"
        }
    ],
    "sg:phone":"+1 337 436 5029",
    "sg:postcode":"70601",
    "sg:province":"LA",
    "wof:name":"Pearl Watson Elementary School",
    "wof:placetype":"venue"
},
  "geometry": {"coordinates":[-93.202754,30.221378],"type":"Point"}
}