{
  "type": "Feature",
  "properties": {
    "iso:country":"US",
    "sg:address":"3440 Mansfield Ave",
    "sg:city":"New Orleans",
    "sg:classifiers":[
        {
            "category":"Social Services",
            "subcategory":"Child Care",
            "type":"Services"
        }
    ],
    "sg:phone":"+1 504 392 8524",
    "sg:postcode":"70131",
    "sg:province":"LA",
    "sg:tags":[
        "day"
    ],
    "wof:name":"Gwen's Preschool Academy",
    "wof:placetype":"venue"
},
  "geometry": {"coordinates":[-89.981697,29.9177],"type":"Point"}
}