{
  "type": "Feature",
  "properties": {
    "iso:country":"US",
    "sg:address":"146 E 28th St",
    "sg:city":"Cut Off",
    "sg:classifiers":[
        {
            "category":"Health Services",
            "subcategory":"Nursing And Care Facility",
            "type":"Services"
        }
    ],
    "sg:phone":"+1 985 693 8677",
    "sg:postcode":"70345",
    "sg:province":"LA",
    "sg:tags":[
        "home",
        "convalescent"
    ],
    "wof:name":"South Lafourche Nursing Ctr",
    "wof:placetype":"venue"
},
  "geometry": {"coordinates":[-90.33804600000001,29.553249],"type":"Point"}
}