{
  "type": "Feature",
  "properties": {
    "iso:country":"US",
    "sg:address":"117 Focis St",
    "sg:city":"Metairie",
    "sg:classifiers":[
        {
            "category":"Social Services",
            "type":"Services"
        }
    ],
    "sg:phone":"+1 504 837 5003",
    "sg:postcode":"70005",
    "sg:province":"LA",
    "sg:tags":[
        "organization",
        "welfare"
    ],
    "wof:name":"Prevent Child Abuse Louisiana",
    "wof:placetype":"venue"
},
  "geometry": {"coordinates":[-90.130162,29.988265],"type":"Point"}
}