{
  "type": "Feature",
  "properties": {
    "addr:full":"401 Martin Luther King Dr Minden LA 71055",
    "addr:housenumber":"401",
    "addr:postcode":"71055",
    "addr:street":"Martin Luther King Dr",
    "iso:country":"US",
    "sg:address":"401 Martin Luther King Dr",
    "sg:city":"Minden",
    "sg:classifiers":[
        {
            "category":"Personal",
            "subcategory":"Barber",
            "type":"Services"
        }
    ],
    "sg:phone":"+1 318 371 1018",
    "sg:postcode":"71055",
    "sg:province":"LA",
    "wof:name":"Woo's Barber & Style Shop Inc",
    "wof:placetype":"venue"
},
  "geometry": {"coordinates":[-93.284323,32.60991],"type":"Point"}
}