{
  "type": "Feature",
  "properties": {
    "iso:country":"US",
    "sg:address":"8883 Highland Rd",
    "sg:city":"Baton Rouge",
    "sg:classifiers":[
        {
            "category":"Shopping",
            "subcategory":"Clothing, Apparel, & Fashions",
            "type":"Retail Goods"
        }
    ],
    "sg:phone":"+1 225 763 9526",
    "sg:postcode":"70808",
    "sg:province":"LA",
    "sg:tags":[
        "alteration"
    ],
    "wof:name":"Golden Needle Tailor Shop",
    "wof:placetype":"venue"
},
  "geometry": {"coordinates":[-91.12678,30.371507],"type":"Point"}
}