{
  "type": "Feature",
  "properties": {
    "iso:country":"US",
    "sg:address":"300 Fannin St",
    "sg:city":"Shreveport",
    "sg:classifiers":[
        {
            "category":"Government",
            "subcategory":"Office",
            "type":"Public Place"
        }
    ],
    "sg:phone":"+1 318 676 3765",
    "sg:postcode":"71101",
    "sg:province":"LA",
    "wof:name":"Honorable Carl E Stewart",
    "wof:placetype":"venue"
},
  "geometry": {"coordinates":[-93.75039099999999,32.515189],"type":"Point"}
}