{
  "type": "Feature",
  "properties": {
    "iso:country":"US",
    "sg:address":"1680 Lobdell Hwy",
    "sg:city":"Port Allen",
    "sg:classifiers":[
        {
            "category":"Restaurant",
            "type":"Food & Drink"
        }
    ],
    "sg:phone":"+1 225 381 9208",
    "sg:postcode":"70767",
    "sg:province":"LA",
    "wof:name":"Krawdaddy's",
    "wof:placetype":"venue"
},
  "geometry": {"coordinates":[-91.25036,30.474021],"type":"Point"}
}