{
  "type": "Feature",
  "properties": {
    "iso:country":"US",
    "sg:address":"1355 Polders Ln",
    "sg:city":"Covington",
    "sg:classifiers":[
        {
            "category":"Personal",
            "subcategory":"Beauty Salon",
            "type":"Services"
        }
    ],
    "sg:phone":"+1 985 892 9953",
    "sg:postcode":"70433",
    "sg:province":"LA",
    "sg:tags":[
        "school"
    ],
    "wof:name":"Aveda Institute",
    "wof:placetype":"venue"
},
  "geometry": {"coordinates":[-90.104564,30.493338],"type":"Point"}
}