{
  "type": "Feature",
  "properties": {
    "addr:full":"306 N Lewis St New Iberia LA 70563",
    "addr:housenumber":"306",
    "addr:postcode":"70563",
    "addr:street":"N Lewis St",
    "iso:country":"US",
    "sg:address":"306 N Lewis St",
    "sg:city":"New Iberia",
    "sg:classifiers":[
        {
            "category":"Shopping",
            "subcategory":"Optical Goods",
            "type":"Retail Goods"
        }
    ],
    "sg:phone":"+1 337 365 4893",
    "sg:postcode":"70563",
    "sg:province":"LA",
    "wof:name":"Evangeline Optical",
    "wof:placetype":"venue"
},
  "geometry": {"coordinates":[-91.799711,30.001449],"type":"Point"}
}