{
  "type": "Feature",
  "properties": {
    "iso:country":"US",
    "sg:address":"114 Lynwood Dr",
    "sg:city":"Ferriday",
    "sg:classifiers":[
        {
            "category":"Professional",
            "subcategory":"Business Services",
            "type":"Services"
        }
    ],
    "sg:phone":"+1 318 757 9697",
    "sg:postcode":"71334",
    "sg:province":"LA",
    "wof:name":"National Assoc of Letter",
    "wof:placetype":"venue"
},
  "geometry": {"coordinates":[-91.561976,31.648852],"type":"Point"}
}