{
  "type": "Feature",
  "properties": {
    "iso:country":"US",
    "sg:address":"40274 Parker Rd",
    "sg:city":"Prairieville",
    "sg:classifiers":[
        {
            "category":"Arts & Performance",
            "subcategory":"Theater",
            "type":"Entertainment"
        }
    ],
    "sg:phone":"+1 225 622 1653",
    "sg:postcode":"70769",
    "sg:province":"LA",
    "sg:tags":[
        "live",
        "music"
    ],
    "wof:name":"Avpro Audio Video Pro",
    "wof:placetype":"venue"
},
  "geometry": {"coordinates":[-90.930003,30.313578],"type":"Point"}
}