{
  "type": "Feature",
  "properties": {
    "iso:country":"US",
    "sg:address":"1001 N Main St",
    "sg:city":"Loreauville",
    "sg:classifiers":[
        {
            "category":"Food & Beverages",
            "subcategory":"Groceries & Convenience Stores",
            "type":"Retail Goods"
        }
    ],
    "sg:phone":"+1 337 229 3033",
    "sg:postcode":"70552",
    "sg:province":"LA",
    "sg:tags":[
        "grocer"
    ],
    "wof:name":"Piggy Wiggly Of Loreauville",
    "wof:placetype":"venue"
},
  "geometry": {"coordinates":[-91.73824999999999,30.067812],"type":"Point"}
}