{
  "type": "Feature",
  "properties": {
    "iso:country":"US",
    "sg:address":"1913 Cleary Ave",
    "sg:city":"Metairie",
    "sg:classifiers":[
        {
            "category":"Building & Trades",
            "subcategory":"Pest Control",
            "type":"Services"
        }
    ],
    "sg:phone":"+1 504 833 7039",
    "sg:postcode":"70001",
    "sg:province":"LA",
    "wof:name":"Hoffmann Pest Control Inc",
    "wof:placetype":"venue"
},
  "geometry": {"coordinates":[-90.17094299999999,29.989352],"type":"Point"}
}