{
  "type": "Feature",
  "properties": {
    "iso:country":"US",
    "sg:address":"2007 Caffin Ave",
    "sg:city":"New Orleans",
    "sg:classifiers":[
        {
            "category":"Personal",
            "subcategory":"Barber",
            "type":"Services"
        }
    ],
    "sg:phone":"+1 504 944 9833",
    "sg:postcode":"70117",
    "sg:province":"LA",
    "wof:name":"Lea & Purvis Hair Ctr",
    "wof:placetype":"venue"
},
  "geometry": {"coordinates":[-90.012591,29.970652],"type":"Point"}
}