{
  "type": "Feature",
  "properties": {
    "iso:country":"US",
    "sg:address":"4333 Emory St",
    "sg:city":"Shreveport",
    "sg:classifiers":[
        {
            "category":"Building & Trades",
            "subcategory":"Landscaping Services",
            "type":"Services"
        }
    ],
    "sg:phone":"+1 318 868 5044",
    "sg:postcode":"71109",
    "sg:province":"LA",
    "sg:tags":[
        "tree"
    ],
    "wof:name":"Moon Tree Svc",
    "wof:placetype":"venue"
},
  "geometry": {"coordinates":[-93.809817,32.46992],"type":"Point"}
}