{
  "type": "Feature",
  "properties": {
    "iso:country":"US",
    "sg:address":"880 N Hwy 190",
    "sg:city":"Covington",
    "sg:classifiers":[
        {
            "category":"Professional",
            "subcategory":"Accounting & Tax Preparation",
            "type":"Services"
        }
    ],
    "sg:phone":"+1 985 892 6228",
    "sg:postcode":"70433",
    "sg:province":"LA",
    "sg:tags":[
        "return",
        "filing"
    ],
    "wof:name":"Liberty Tax Svc",
    "wof:placetype":"venue"
},
  "geometry": {"coordinates":[-90.08231499999999,30.443038],"type":"Point"}
}