{
  "type": "Feature",
  "properties": {
    "addr:full":"3116 Cleary Ave Metairie LA 70001",
    "addr:housenumber":"3116",
    "addr:postcode":"70001",
    "addr:street":"Cleary Ave",
    "iso:country":"US",
    "sg:address":"3116 Cleary Ave",
    "sg:city":"Metairie",
    "sg:classifiers":[
        {
            "category":"Retail",
            "subcategory":"Auto Repair",
            "type":"Services"
        }
    ],
    "sg:phone":"+1 504 885 8299",
    "sg:postcode":"70001",
    "sg:province":"LA",
    "sg:tags":[
        "repairing",
        "automobile"
    ],
    "wof:name":"Mobile Auto Tech Inc",
    "wof:placetype":"venue"
},
  "geometry": {"coordinates":[-90.172316,30.002176],"type":"Point"}
}