{
  "type": "Feature",
  "properties": {
    "iso:country":"US",
    "sg:address":"715 S Broad St",
    "sg:city":"New Orleans",
    "sg:classifiers":[
        {
            "category":"Organizations",
            "subcategory":"Non-profit Organization",
            "type":"Services"
        },
        {
            "category":"Government",
            "subcategory":"Police Station",
            "type":"Public Place"
        }
    ],
    "sg:phone":"+1 504 822 1111",
    "sg:postcode":"70119",
    "sg:province":"LA",
    "sg:tags":[
        "department",
        "program",
        "prevention",
        "crime"
    ],
    "wof:name":"New Orleans Police Crime Stppr",
    "wof:placetype":"venue"
},
  "geometry": {"coordinates":[-90.092691,29.959707],"type":"Point"}
}