{
  "type": "Feature",
  "properties": {
    "iso:country":"US",
    "sg:address":"824 Canal St",
    "sg:city":"New Orleans",
    "sg:classifiers":[
        {
            "category":"Organizations",
            "subcategory":"Community Association",
            "type":"Services"
        }
    ],
    "sg:phone":"+1 504 523 3443",
    "sg:postcode":"70112",
    "sg:province":"LA",
    "sg:tags":[
        "club"
    ],
    "wof:name":"Boston Club",
    "wof:placetype":"venue"
},
  "geometry": {"coordinates":[-90.070814,29.954092],"type":"Point"}
}