{
  "type": "Feature",
  "properties": {
    "addr:full":"1071 Calvary Baptiste Rd Ville Platte LA 70586",
    "addr:housenumber":"1071",
    "addr:postcode":"70586",
    "addr:street":"Calvary Baptiste Rd",
    "iso:country":"US",
    "sg:address":"1071 Calvary Baptiste Rd",
    "sg:city":"Ville Platte",
    "sg:classifiers":[
        {
            "category":"Organizations",
            "subcategory":"Religious Organization",
            "type":"Services"
        }
    ],
    "sg:phone":"+1 337 461 2699",
    "sg:postcode":"70586",
    "sg:province":"LA",
    "sg:tags":[
        "church"
    ],
    "wof:name":"Calvary Baptist Church",
    "wof:placetype":"venue"
},
  "geometry": {"coordinates":[-92.35382799999999,30.815617],"type":"Point"}
}