{
  "type": "Feature",
  "properties": {
    "iso:country":"US",
    "sg:address":"1138 S Carrollton Ave",
    "sg:city":"New Orleans",
    "sg:classifiers":[
        {
            "category":"Recreation",
            "type":"Entertainment"
        }
    ],
    "sg:phone":"+1 504 864 1999",
    "sg:postcode":"70118",
    "sg:province":"LA",
    "wof:name":"Yoga Room",
    "wof:placetype":"venue"
},
  "geometry": {"coordinates":[-90.13009700000001,29.947124],"type":"Point"}
}