{
  "type": "Feature",
  "properties": {
    "addr:full":"1101 16th St Alexandria LA 71301",
    "addr:housenumber":"1101",
    "addr:postcode":"71301",
    "addr:street":"16Th St",
    "iso:country":"US",
    "sg:address":"1101 16th St",
    "sg:city":"Alexandria",
    "sg:classifiers":[
        {
            "category":"Social Services",
            "subcategory":"Adult Care",
            "type":"Services"
        }
    ],
    "sg:phone":"+1 318 445 7715",
    "sg:postcode":"71301",
    "sg:province":"LA",
    "sg:tags":[
        "home",
        "residential"
    ],
    "wof:name":"Canterbury House",
    "wof:placetype":"venue"
},
  "geometry": {"coordinates":[-92.450689,31.302774],"type":"Point"}
}