{
  "type": "Feature",
  "properties": {
    "addr:full":"6081 Bayou Serpent Rd Lake Charles LA 70615",
    "addr:housenumber":"6081",
    "addr:postcode":"70615",
    "addr:street":"Bayou Serpent Rd;Charles",
    "iso:country":"US",
    "sg:address":"6081 Bayou Serpent Rd",
    "sg:city":"Lake Charles",
    "sg:classifiers":[
        {
            "category":"Retail",
            "subcategory":"Repair Shop",
            "type":"Services"
        }
    ],
    "sg:phone":"+1 337 436 6741",
    "sg:postcode":"70615",
    "sg:province":"LA",
    "sg:tags":[
        "welding"
    ],
    "wof:name":"Chad Savant Welding Servi",
    "wof:placetype":"venue"
},
  "geometry": {"coordinates":[-93.099495,30.308818],"type":"Point"}
}