{
  "type": "Feature",
  "properties": {
    "iso:country":"US",
    "sg:address":"2001 Charles Dr",
    "sg:city":"Chalmette",
    "sg:classifiers":[
        {
            "category":"Professional",
            "type":"Services"
        }
    ],
    "sg:phone":"+1 504 271 2188",
    "sg:postcode":"70043",
    "sg:province":"LA",
    "sg:tags":[
        "establishment"
    ],
    "wof:name":"BTM Enterprises LLC",
    "wof:placetype":"venue"
},
  "geometry": {"coordinates":[-89.949772,29.934334],"type":"Point"}
}