{
  "type": "Feature",
  "properties": {
    "addr:full":"10112 Plainfield Dr New Orleans LA 70127",
    "addr:housenumber":"10112",
    "addr:postcode":"70127",
    "addr:street":"Plainfield Dr",
    "iso:country":"US",
    "sg:address":"10112 Plainfield Dr",
    "sg:city":"New Orleans",
    "sg:classifiers":[
        {
            "category":"Real Estate",
            "subcategory":"Real Estate Operator",
            "type":"Services"
        }
    ],
    "sg:phone":"+1 504 240 6400",
    "sg:postcode":"70127",
    "sg:province":"LA",
    "sg:tags":[
        "apartment"
    ],
    "wof:name":"J C Property Management",
    "wof:placetype":"venue"
},
  "geometry": {"coordinates":[-89.97793900000001,30.039695],"type":"Point"}
}