{
  "type": "Feature",
  "properties": {
    "iso:country":"US",
    "sg:address":"19042 Hwy 38",
    "sg:city":"Kentwood",
    "sg:classifiers":[
        {
            "category":"Utilities",
            "subcategory":"Water",
            "type":"Services"
        }
    ],
    "sg:phone":"+1 985 229 6671",
    "sg:postcode":"70444",
    "sg:province":"LA",
    "sg:tags":[
        "company",
        "sewage"
    ],
    "wof:name":"Tangipahoa Water District",
    "wof:placetype":"venue"
},
  "geometry": {"coordinates":[-90.412261,30.92715],"type":"Point"}
}