{
  "type": "Feature",
  "properties": {
    "addr:full":"2212 Broad St Lake Charles LA 70601",
    "addr:housenumber":"2212",
    "addr:postcode":"70601",
    "addr:street":"Broad St",
    "iso:country":"US",
    "sg:address":"2212 Broad St",
    "sg:city":"Lake Charles",
    "sg:classifiers":[
        {
            "category":"Bars & Pubs",
            "type":"Food & Drink"
        }
    ],
    "sg:phone":"+1 337 436 5200",
    "sg:postcode":"70601",
    "sg:province":"LA",
    "sg:tags":[
        "lounge",
        "cocktail"
    ],
    "wof:name":"Y2k's Lounge",
    "wof:placetype":"venue"
},
  "geometry": {"coordinates":[-93.188258,30.22748],"type":"Point"}
}