{
  "type": "Feature",
  "properties": {
    "iso:country":"US",
    "sg:address":"1004 W 2nd St",
    "sg:city":"Crowley",
    "sg:classifiers":[
        {
            "category":"Retail",
            "subcategory":"Auto Repair",
            "type":"Services"
        }
    ],
    "sg:phone":"+1 337 783 8035",
    "sg:postcode":"70526",
    "sg:province":"LA",
    "sg:tags":[
        "body",
        "automobile",
        "painting"
    ],
    "wof:name":"Buddy & Billy's Paint & Body",
    "wof:placetype":"venue"
},
  "geometry": {"coordinates":[-92.38140300000001,30.206809],"type":"Point"}
}