{
  "type": "Feature",
  "properties": {
    "addr:full":"1500 N Claiborne Ave New Orleans LA 70116",
    "addr:housenumber":"1500",
    "addr:postcode":"70116",
    "addr:street":"N Claiborne Ave",
    "iso:country":"US",
    "sg:address":"1500 N Claiborne Ave",
    "sg:city":"New Orleans",
    "sg:classifiers":[
        {
            "category":"Bars & Pubs",
            "type":"Food & Drink"
        }
    ],
    "sg:phone":"+1 504 947 1078",
    "sg:postcode":"70116",
    "sg:province":"LA",
    "sg:tags":[
        "lounge",
        "cocktail"
    ],
    "wof:name":"Ernie K-Doe Mother-In-Law",
    "wof:placetype":"venue"
},
  "geometry": {"coordinates":[-90.066228,29.971736],"type":"Point"}
}