{
  "type": "Feature",
  "properties": {
    "addr:full":"4734 Jackson St Exd Alexandria LA 71303",
    "addr:housenumber":"4734",
    "addr:postcode":"71303",
    "addr:street":"Jackson St Exd",
    "iso:country":"US",
    "sg:address":"4734 Jackson St Exd",
    "sg:city":"Alexandria",
    "sg:classifiers":[
        {
            "category":"Personal",
            "subcategory":"Beauty Salon",
            "type":"Services"
        }
    ],
    "sg:phone":"+1 318 487 6113",
    "sg:postcode":"71303",
    "sg:province":"LA",
    "sg:tags":[
        "manicuring"
    ],
    "wof:name":"Billie's Nails",
    "wof:placetype":"venue"
},
  "geometry": {"coordinates":[-92.48165899999999,31.276288],"type":"Point"}
}