{
  "type": "Feature",
  "properties": {
    "iso:country":"US",
    "sg:address":"15821 Mire Rd",
    "sg:city":"Kaplan",
    "sg:classifiers":[
        {
            "category":"Retail",
            "subcategory":"Repair Shop",
            "type":"Services"
        }
    ],
    "sg:phone":"+1 337 643 6331",
    "sg:postcode":"70548",
    "sg:province":"LA",
    "sg:tags":[
        "television",
        "radio"
    ],
    "wof:name":"Mire's TV Svc",
    "wof:placetype":"venue"
},
  "geometry": {"coordinates":[-92.238984,30.035127],"type":"Point"}
}