{
  "type": "Feature",
  "properties": {
    "addr:full":"5821 Hwy 1 Natchitoches LA 71457",
    "addr:housenumber":"5821",
    "addr:postcode":"71457",
    "addr:street":"Hwy 1",
    "iso:country":"US",
    "sg:address":"5821 Hwy 1",
    "sg:city":"Natchitoches",
    "sg:classifiers":[
        {
            "category":"Travel",
            "subcategory":"Hotels & Motels",
            "type":"Entertainment"
        }
    ],
    "sg:phone":"+1 318 352 1700",
    "sg:postcode":"71457",
    "sg:province":"LA",
    "wof:name":"Super 8 Motel",
    "wof:placetype":"venue"
},
  "geometry": {"coordinates":[-93.107934,31.771023],"type":"Point"}
}