{
  "type": "Feature",
  "properties": {
    "iso:country":"US",
    "sg:address":"1323 Englewood Dr",
    "sg:city":"Slidell",
    "sg:classifiers":[
        {
            "category":"Shopping",
            "subcategory":"Clothing, Apparel, & Fashions",
            "type":"Retail Goods"
        }
    ],
    "sg:phone":"+1 985 643 2162",
    "sg:postcode":"70458",
    "sg:province":"LA",
    "sg:tags":[
        "dancing",
        "supply"
    ],
    "wof:name":"Dance-N-Things",
    "wof:placetype":"venue"
},
  "geometry": {"coordinates":[-89.76157000000001,30.284282],"type":"Point"}
}