{
  "type": "Feature",
  "properties": {
    "addr:full":"9867 Cortana Pl Baton Rouge LA 70815",
    "addr:housenumber":"9867",
    "addr:postcode":"70815",
    "addr:street":"Cortana Pl",
    "iso:country":"US",
    "sg:address":"9867 Cortana Pl",
    "sg:city":"Baton Rouge",
    "sg:classifiers":[
        {
            "category":"Shopping",
            "subcategory":"Clothing, Apparel, & Fashions",
            "type":"Retail Goods"
        }
    ],
    "sg:phone":"+1 225 928 9342",
    "sg:postcode":"70815",
    "sg:province":"LA",
    "sg:tags":[
        "lingerie"
    ],
    "sg:website":"www.victoriassecret.com",
    "wof:name":"Victoria's Secret",
    "wof:placetype":"venue"
},
  "geometry": {"coordinates":[-91.093767,30.455051],"type":"Point"}
}