{
  "type": "Feature",
  "properties": {
    "addr:full":"2317 Manhattan Blvd Harvey LA 70058",
    "addr:housenumber":"2317",
    "addr:postcode":"70058",
    "addr:street":"Manhattan Blvd",
    "iso:country":"US",
    "sg:address":"2317 Manhattan Blvd",
    "sg:city":"Harvey",
    "sg:classifiers":[
        {
            "category":"Health Services",
            "subcategory":"Doctor",
            "type":"Services"
        }
    ],
    "sg:phone":"+1 504 342 1654",
    "sg:postcode":"70058",
    "sg:province":"LA",
    "sg:tags":[
        "dentist"
    ],
    "wof:name":"Family Dentistry",
    "wof:placetype":"venue"
},
  "geometry": {"coordinates":[-90.051163,29.880326],"type":"Point"}
}