{
  "type": "Feature",
  "properties": {
    "iso:country":"US",
    "sg:address":"4401 Ambassador Caffery Pkwy",
    "sg:city":"Lafayette",
    "sg:classifiers":[
        {
            "category":"Shopping",
            "subcategory":"Shoes",
            "type":"Retail Goods"
        }
    ],
    "sg:phone":"+1 337 984 0444",
    "sg:postcode":"70508",
    "sg:province":"LA",
    "wof:name":"Payless Shoe Source",
    "wof:placetype":"venue"
},
  "geometry": {"coordinates":[-92.048405,30.156655],"type":"Point"}
}