{
  "type": "Feature",
  "properties": {
    "iso:country":"US",
    "sg:address":"700 Crescent Blvd",
    "sg:city":"Houma",
    "sg:classifiers":[
        {
            "category":"Building & Trades",
            "subcategory":"Equipment Rental",
            "type":"Services"
        }
    ],
    "sg:phone":"+1 985 872 2121",
    "sg:postcode":"70360",
    "sg:province":"LA",
    "sg:tags":[
        "oil",
        "well",
        "supply"
    ],
    "wof:name":"Unique Rentals",
    "wof:placetype":"venue"
},
  "geometry": {"coordinates":[-90.721549,29.582545],"type":"Point"}
}