{
  "type": "Feature",
  "properties": {
    "iso:country":"US",
    "sg:address":"69324 Hwy 21",
    "sg:city":"Covington",
    "sg:classifiers":[
        {
            "category":"Shopping",
            "subcategory":"Department Store",
            "type":"Retail Goods"
        }
    ],
    "sg:phone":"+1 985 809 0673",
    "sg:postcode":"70433",
    "sg:province":"LA",
    "wof:name":"Marshalls",
    "wof:placetype":"venue"
},
  "geometry": {"coordinates":[-90.14532199999999,30.440673],"type":"Point"}
}