{
  "type": "Feature",
  "properties": {
    "iso:country":"US",
    "sg:address":"511 Congress St",
    "sg:city":"Napoleonville",
    "sg:classifiers":[
        {
            "category":"Health Services",
            "subcategory":"Optometrist",
            "type":"Services"
        }
    ],
    "sg:phone":"+1 985 369 6205",
    "sg:postcode":"70390",
    "sg:province":"LA",
    "wof:name":"Mark J Roy Jr OD",
    "wof:placetype":"venue"
},
  "geometry": {"coordinates":[-91.024462,29.940466],"type":"Point"}
}