{
  "type": "Feature",
  "properties": {
    "addr:full":"5410 Kennon Ln Bossier City LA 71112",
    "addr:housenumber":"5410",
    "addr:postcode":"71112",
    "addr:street":"Kennon Ln",
    "iso:country":"US",
    "sg:address":"5410 Kennon Ln",
    "sg:city":"Bossier City",
    "sg:classifiers":[
        {
            "category":"Wholesale",
            "subcategory":"Machinery & Supplies",
            "type":"Manufacturing & Wholesale Goods"
        }
    ],
    "sg:phone":"+1 318 746 2356",
    "sg:postcode":"71112",
    "sg:province":"LA",
    "sg:tags":[
        "engine"
    ],
    "wof:name":"Louisiana Machinery Power Syst",
    "wof:placetype":"venue"
},
  "geometry": {"coordinates":[-93.657186,32.529268],"type":"Point"}
}