{
  "type": "Feature",
  "properties": {
    "iso:country":"US",
    "sg:address":"4237 Magazine St",
    "sg:city":"New Orleans",
    "sg:classifiers":[
        {
            "category":"Food & Beverages",
            "subcategory":"Groceries & Convenience Stores",
            "type":"Retail Goods"
        }
    ],
    "sg:phone":"+1 504 899 8579",
    "sg:postcode":"70115",
    "sg:province":"LA",
    "sg:tags":[
        "grocer"
    ],
    "wof:name":"Vicky's Supermarket",
    "wof:placetype":"venue"
},
  "geometry": {"coordinates":[-90.099836,29.92101],"type":"Point"}
}