{
  "type": "Feature",
  "properties": {
    "addr:full":"2424 Edenborn Ave Metairie LA 70001",
    "addr:housenumber":"2424",
    "addr:postcode":"70001",
    "addr:street":"Edenborn Ave",
    "iso:country":"US",
    "sg:address":"2424 Edenborn Ave",
    "sg:city":"Metairie",
    "sg:classifiers":[
        {
            "category":"Health Services",
            "subcategory":"Nursing And Care Facility",
            "type":"Services"
        }
    ],
    "sg:phone":"+1 504 834 1655",
    "sg:postcode":"70001",
    "sg:province":"LA",
    "sg:tags":[
        "hospice"
    ],
    "wof:name":"Hospice Care Of Louisana",
    "wof:placetype":"venue"
},
  "geometry": {"coordinates":[-90.16252299999999,29.995201],"type":"Point"}
}