{
  "type": "Feature",
  "properties": {
    "iso:country":"US",
    "sg:address":"3709 Masonic Dr",
    "sg:city":"Alexandria",
    "sg:classifiers":[
        {
            "category":"Health Services",
            "subcategory":"Hospital",
            "type":"Services"
        }
    ],
    "sg:phone":"+1 318 442 9100",
    "sg:postcode":"71301",
    "sg:province":"LA",
    "wof:name":"Christus Cabrini Hospital",
    "wof:placetype":"venue"
},
  "geometry": {"coordinates":[-92.464574,31.277852],"type":"Point"}
}