{
  "type": "Feature",
  "properties": {
    "iso:country":"US",
    "sg:address":"1107 Decatur St",
    "sg:city":"New Orleans",
    "sg:classifiers":[
        {
            "category":"Restaurant",
            "type":"Food & Drink"
        }
    ],
    "sg:phone":"+1 504 218 7332",
    "sg:postcode":"70116",
    "sg:province":"LA",
    "wof:name":"Krewe De Food",
    "wof:placetype":"venue"
},
  "geometry": {"coordinates":[-90.06001999999999,29.960175],"type":"Point"}
}