{
  "type": "Feature",
  "properties": {
    "iso:country":"US",
    "sg:address":"13169 Sunshine Rd",
    "sg:city":"Baton Rouge",
    "sg:classifiers":[
        {
            "category":"Arts & Performance",
            "subcategory":"Theater",
            "type":"Entertainment"
        }
    ],
    "sg:phone":"+1 225 775 8835",
    "sg:postcode":"70811",
    "sg:province":"LA",
    "sg:tags":[
        "group"
    ],
    "wof:name":"Total Kaos Entertainment",
    "wof:placetype":"venue"
},
  "geometry": {"coordinates":[-91.14402,30.568339],"type":"Point"}
}