{
  "type": "Feature",
  "properties": {
    "iso:country":"US",
    "sg:address":"57 Dove St",
    "sg:city":"New Orleans",
    "sg:classifiers":[
        {
            "category":"Professional",
            "subcategory":"Art Services",
            "type":"Services"
        }
    ],
    "sg:phone":"+1 504 286 1001",
    "sg:postcode":"70124",
    "sg:province":"LA",
    "sg:tags":[
        "commercial",
        "design"
    ],
    "wof:name":"Designs By Word Inc",
    "wof:placetype":"venue"
},
  "geometry": {"coordinates":[-90.092253,30.019814],"type":"Point"}
}