{
  "type": "Feature",
  "properties": {
    "iso:country":"US",
    "sg:address":"2712 US Hwy 84",
    "sg:city":"Mansfield",
    "sg:classifiers":[
        {
            "category":"Government",
            "subcategory":"Office",
            "type":"Public Place"
        }
    ],
    "sg:phone":"+1 318 872 2500",
    "sg:postcode":"71052",
    "sg:province":"LA",
    "sg:tags":[
        "county",
        "program"
    ],
    "wof:name":"Mundy Sanitary Landfill",
    "wof:placetype":"venue"
},
  "geometry": {"coordinates":[-93.589991,32.057519],"type":"Point"}
}