{
  "type": "Feature",
  "properties": {
    "iso:country":"US",
    "sg:address":"2020 E Main St",
    "sg:city":"Ville Platte",
    "sg:classifiers":[
        {
            "category":"Banks & Credit Unions",
            "subcategory":"Bank",
            "type":"Services"
        }
    ],
    "sg:phone":"+1 337 363 6657",
    "sg:postcode":"70586",
    "sg:province":"LA",
    "wof:name":"Evangeline Bank & Trust Co",
    "wof:placetype":"venue"
},
  "geometry": {"coordinates":[-92.247838,30.677951],"type":"Point"}
}