{
  "type": "Feature",
  "properties": {
    "addr:full":"44030 Max Brumfield Rd Franklinton LA 70438",
    "addr:housenumber":"44030",
    "addr:postcode":"70438",
    "addr:street":"Max Brumfield Rd",
    "iso:country":"US",
    "sg:address":"44030 Max Brumfield Rd",
    "sg:city":"Franklinton",
    "sg:classifiers":[
        {
            "category":"Organizations",
            "subcategory":"Religious Organization",
            "type":"Services"
        }
    ],
    "sg:phone":"+1 985 839 5290",
    "sg:postcode":"70438",
    "sg:province":"LA",
    "sg:tags":[
        "church"
    ],
    "wof:name":"New Jerusalem Baptist",
    "wof:placetype":"venue"
},
  "geometry": {"coordinates":[-90.15728300000001,30.928537],"type":"Point"}
}