{
  "type": "Feature",
  "properties": {
    "iso:country":"US",
    "sg:address":"12484 Cate Ave",
    "sg:city":"Baton Rouge",
    "sg:classifiers":[
        {
            "category":"Professional",
            "type":"Services"
        }
    ],
    "sg:phone":"+1 225 273 7920",
    "sg:postcode":"70815",
    "sg:province":"LA",
    "sg:tags":[
        "establishment"
    ],
    "wof:name":"Byrd Master",
    "wof:placetype":"venue"
},
  "geometry": {"coordinates":[-91.04464900000001,30.463312],"type":"Point"}
}