{
  "type": "Feature",
  "properties": {
    "iso:country":"US",
    "sg:address":"5151 Dixie Garden Dr",
    "sg:city":"Shreveport",
    "sg:classifiers":[
        {
            "category":"Government",
            "subcategory":"Fire Station",
            "type":"Public Place"
        }
    ],
    "sg:phone":"+1 318 861 9210",
    "sg:postcode":"71105",
    "sg:province":"LA",
    "sg:tags":[
        "department",
        "protection"
    ],
    "wof:name":"Dixie Garden Fire Dist 5",
    "wof:placetype":"venue"
},
  "geometry": {"coordinates":[-93.69714500000001,32.453293],"type":"Point"}
}