{
  "type": "Feature",
  "properties": {
    "addr:full":"5959 W 70th St Shreveport LA 71129",
    "addr:housenumber":"5959",
    "addr:postcode":"71129",
    "addr:street":"W 70Th St",
    "iso:country":"US",
    "sg:address":"5959 W 70th St",
    "sg:city":"Shreveport",
    "sg:classifiers":[
        {
            "category":"Banks & Credit Unions",
            "subcategory":"Bank",
            "type":"Services"
        }
    ],
    "sg:phone":"+1 318 226 2713",
    "sg:postcode":"71129",
    "sg:province":"LA",
    "sg:website":"www.bankone.com",
    "wof:name":"Bank One",
    "wof:placetype":"venue"
},
  "geometry": {"coordinates":[-93.85712599999999,32.442076],"type":"Point"}
}