{
  "type": "Feature",
  "properties": {
    "addr:full":"38280 Henry Rd Prairieville LA 70769",
    "addr:housenumber":"38280",
    "addr:postcode":"70769",
    "addr:street":"Henry Rd",
    "iso:country":"US",
    "sg:address":"38280 Henry Rd",
    "sg:city":"Prairieville",
    "sg:classifiers":[
        {
            "category":"Organizations",
            "subcategory":"Religious Organization",
            "type":"Services"
        }
    ],
    "sg:phone":"+1 225 673 3603",
    "sg:postcode":"70769",
    "sg:province":"LA",
    "sg:tags":[
        "church"
    ],
    "wof:name":"Mount Gillion Baptist Church",
    "wof:placetype":"venue"
},
  "geometry": {"coordinates":[-90.96264499999999,30.305913],"type":"Point"}
}