{
  "type": "Feature",
  "properties": {
    "iso:country":"US",
    "sg:address":"735 Macarthur Dr",
    "sg:city":"Alexandria",
    "sg:classifiers":[
        {
            "category":"Insurance",
            "subcategory":"Insurance Agent",
            "type":"Services"
        }
    ],
    "sg:phone":"+1 318 445 7133",
    "sg:postcode":"71303",
    "sg:province":"LA",
    "wof:name":"Gary Clark Insurance",
    "wof:placetype":"venue"
},
  "geometry": {"coordinates":[-92.477515,31.293959],"type":"Point"}
}