{
  "type": "Feature",
  "properties": {
    "iso:country":"US",
    "sg:address":"1204 Polk St",
    "sg:city":"Mansfield",
    "sg:classifiers":[
        {
            "category":"Banks & Credit Unions",
            "subcategory":"Bank",
            "type":"Services"
        }
    ],
    "sg:phone":"+1 318 872 2711",
    "sg:postcode":"71052",
    "sg:province":"LA",
    "wof:name":"Carter Federal Credit Union",
    "wof:placetype":"venue"
},
  "geometry": {"coordinates":[-93.709547,32.037512],"type":"Point"}
}