{
  "type": "Feature",
  "properties": {
    "iso:country":"US",
    "sg:address":"1530 N Hwy 190",
    "sg:city":"Covington",
    "sg:classifiers":[
        {
            "category":"Autos & Motor Vehicles",
            "subcategory":"Auto Supplies",
            "type":"Retail Goods"
        }
    ],
    "sg:phone":"+1 985 893 5510",
    "sg:postcode":"70433",
    "sg:province":"LA",
    "sg:tags":[
        "tire"
    ],
    "wof:name":"Atlas Tire Co",
    "wof:placetype":"venue"
},
  "geometry": {"coordinates":[-90.081962,30.453652],"type":"Point"}
}