{
  "type": "Feature",
  "properties": {
    "addr:full":"5641 Commerce St St Francisville LA 70775",
    "addr:housenumber":"5641",
    "addr:postcode":"70775",
    "addr:street":"Commerce St",
    "iso:country":"US",
    "sg:address":"5641 Commerce St",
    "sg:city":"St Francisville",
    "sg:classifiers":[
        {
            "category":"Building & Trades",
            "subcategory":"Construction",
            "type":"Services"
        }
    ],
    "sg:phone":"+1 225 635 3407",
    "sg:postcode":"70775",
    "sg:province":"LA",
    "sg:tags":[
        "builder",
        "stair"
    ],
    "wof:name":"Zuccarello Custom Woodworks",
    "wof:placetype":"venue"
},
  "geometry": {"coordinates":[-91.376206,30.779968],"type":"Point"}
}