{
  "type": "Feature",
  "properties": {
    "addr:full":"1815 Line Ave Shreveport LA 71101",
    "addr:housenumber":"1815",
    "addr:postcode":"71101",
    "addr:street":"Line Ave",
    "iso:country":"US",
    "sg:address":"1815 Line Ave",
    "sg:city":"Shreveport",
    "sg:classifiers":[
        {
            "category":"Professional",
            "subcategory":"Lawyer & Legal Services",
            "type":"Services"
        }
    ],
    "sg:phone":"+1 318 222 2001",
    "sg:postcode":"71101",
    "sg:province":"LA",
    "sg:tags":[
        "attorney"
    ],
    "wof:name":"John M Lawrence",
    "wof:placetype":"venue"
},
  "geometry": {"coordinates":[-93.745965,32.492945],"type":"Point"}
}