{
  "type": "Feature",
  "properties": {
    "addr:full":"4045 Oakland Dr Lake Charles LA 70611",
    "addr:housenumber":"4045",
    "addr:postcode":"70611",
    "addr:street":"Oakland Dr",
    "iso:country":"US",
    "sg:address":"4045 Oakland Dr",
    "sg:city":"Lake Charles",
    "sg:classifiers":[
        {
            "category":"Professional",
            "subcategory":"Business Services",
            "type":"Services"
        }
    ],
    "sg:phone":"+1 337 489 2205",
    "sg:postcode":"70611",
    "sg:province":"LA",
    "sg:tags":[
        "interior",
        "consultant",
        "design",
        "decorator"
    ],
    "wof:name":"Affordable Interiors By Emily",
    "wof:placetype":"venue"
},
  "geometry": {"coordinates":[-93.287543,30.320067],"type":"Point"}
}