{
  "type": "Feature",
  "properties": {
    "iso:country":"US",
    "sg:address":"1221 Bob Pettit Blvd",
    "sg:city":"Baton Rouge",
    "sg:classifiers":[
        {
            "category":"Real Estate",
            "subcategory":"Real Estate Operator",
            "type":"Services"
        }
    ],
    "sg:phone":"+1 225 766 3720",
    "sg:postcode":"70820",
    "sg:province":"LA",
    "sg:tags":[
        "apartment"
    ],
    "wof:name":"Fountain Head Apartments",
    "wof:placetype":"venue"
},
  "geometry": {"coordinates":[-91.18131,30.395546],"type":"Point"}
}