{
  "type": "Feature",
  "properties": {
    "iso:country":"US",
    "sg:address":"3315 Nelson St",
    "sg:city":"Alexandria",
    "sg:classifiers":[
        {
            "category":"Professional",
            "subcategory":"Accounting & Tax Preparation",
            "type":"Services"
        }
    ],
    "sg:phone":"+1 318 448 0839",
    "sg:postcode":"71301",
    "sg:province":"LA",
    "sg:tags":[
        "bookkeeping",
        "general"
    ],
    "wof:name":"Charles F Buckley Federal Tax",
    "wof:placetype":"venue"
},
  "geometry": {"coordinates":[-92.47637400000001,31.291379],"type":"Point"}
}