{
  "type": "Feature",
  "properties": {
    "addr:full":"947 Cambridge Dr La Place LA 70068",
    "addr:housenumber":"947",
    "addr:postcode":"70068",
    "addr:street":"Cambridge Dr La Place",
    "iso:country":"US",
    "sg:address":"947 Cambridge Dr",
    "sg:city":"La Place",
    "sg:classifiers":[
        {
            "category":"Sports & Exercise",
            "subcategory":"Bowling",
            "type":"Entertainment"
        }
    ],
    "sg:phone":"+1 985 651 9122",
    "sg:postcode":"70068",
    "sg:province":"LA",
    "sg:tags":[
        "center"
    ],
    "wof:name":"Cypress Grill",
    "wof:placetype":"venue"
},
  "geometry": {"coordinates":[-90.486414,30.070545],"type":"Point"}
}