{
  "type": "Feature",
  "properties": {
    "iso:country":"US",
    "sg:address":"12848 Oak St",
    "sg:city":"Port Allen",
    "sg:classifiers":[
        {
            "category":"Professional",
            "subcategory":"Testing Lab",
            "type":"Services"
        }
    ],
    "sg:phone":"+1 225 627 4903",
    "sg:postcode":"70767",
    "sg:province":"LA",
    "sg:tags":[
        "laboratory"
    ],
    "wof:name":"Gamma-Tron Svc",
    "wof:placetype":"venue"
},
  "geometry": {"coordinates":[-91.41038399999999,30.526404],"type":"Point"}
}