{
  "type": "Feature",
  "properties": {
    "iso:country":"US",
    "sg:address":"22079 Hwy 21 N",
    "sg:city":"Bogalusa",
    "sg:classifiers":[
        {
            "category":"Manufacturing",
            "subcategory":"Lumber",
            "type":"Manufacturing & Wholesale Goods"
        }
    ],
    "sg:phone":"+1 985 732 5989",
    "sg:postcode":"70427",
    "sg:province":"LA",
    "sg:tags":[
        "company",
        "logging"
    ],
    "wof:name":"P & J Timber Co Inc",
    "wof:placetype":"venue"
},
  "geometry": {"coordinates":[-89.852467,30.84453],"type":"Point"}
}