{
  "type": "Feature",
  "properties": {
    "addr:full":"4491 McCain Rd Crowley LA 70526",
    "addr:housenumber":"4491",
    "addr:postcode":"70526",
    "addr:street":"Mccain Rd",
    "iso:country":"US",
    "sg:address":"4491 McCain Rd",
    "sg:city":"Crowley",
    "sg:classifiers":[
        {
            "category":"Building & Trades",
            "subcategory":"Landscaping Services",
            "type":"Services"
        }
    ],
    "sg:phone":"+1 337 247 3667",
    "sg:postcode":"70526",
    "sg:province":"LA",
    "sg:tags":[
        "landscape",
        "contractor"
    ],
    "wof:name":"Nicks Nursery & Landscaping",
    "wof:placetype":"venue"
},
  "geometry": {"coordinates":[-92.430735,30.281565],"type":"Point"}
}