{
  "type": "Feature",
  "properties": {
    "iso:country":"US",
    "sg:address":"8118 Oakbrook Dr",
    "sg:city":"Baton Rouge",
    "sg:classifiers":[
        {
            "category":"Professional",
            "subcategory":"Management & Consulting",
            "type":"Services"
        }
    ],
    "sg:phone":"+1 225 769 7842",
    "sg:postcode":"70810",
    "sg:province":"LA",
    "sg:tags":[
        "business"
    ],
    "wof:name":"Kentec Inc",
    "wof:placetype":"venue"
},
  "geometry": {"coordinates":[-91.078828,30.373914],"type":"Point"}
}