{
  "type": "Feature",
  "properties": {
    "iso:country":"US",
    "sg:address":"666 Old Spanish Trl",
    "sg:city":"Slidell",
    "sg:classifiers":[
        {
            "category":"Autos & Motor Vehicles",
            "subcategory":"Boat Sales",
            "type":"Retail Goods"
        }
    ],
    "sg:phone":"+1 985 643 9995",
    "sg:postcode":"70458",
    "sg:province":"LA",
    "sg:tags":[
        "dealer",
        "sales"
    ],
    "wof:name":"Angler Marine Inc",
    "wof:placetype":"venue"
},
  "geometry": {"coordinates":[-89.781375,30.263017],"type":"Point"}
}