{
  "type": "Feature",
  "properties": {
    "iso:country":"US",
    "sg:address":"4702 Johnston St",
    "sg:city":"Lafayette",
    "sg:classifiers":[
        {
            "category":"Personal",
            "subcategory":"Barber",
            "type":"Services"
        }
    ],
    "sg:phone":"+1 337 984 6054",
    "sg:postcode":"70503",
    "sg:province":"LA",
    "wof:name":"Southside Styling & Barber Shp",
    "wof:placetype":"venue"
},
  "geometry": {"coordinates":[-92.063591,30.188953],"type":"Point"}
}