{
  "type": "Feature",
  "properties": {
    "addr:full":"1001 Metairie Rd Metairie LA 70005",
    "addr:housenumber":"1001",
    "addr:postcode":"70005",
    "addr:street":"Metairie Rd",
    "iso:country":"US",
    "sg:address":"1001 Metairie Rd",
    "sg:city":"Metairie",
    "sg:classifiers":[
        {
            "category":"Food & Beverages",
            "subcategory":"Groceries & Convenience Stores",
            "type":"Retail Goods"
        }
    ],
    "sg:phone":"+1 504 831 7968",
    "sg:postcode":"70005",
    "sg:province":"LA",
    "wof:name":"Discount Stop",
    "wof:placetype":"venue"
},
  "geometry": {"coordinates":[-90.133506,29.989105],"type":"Point"}
}