{
  "type": "Feature",
  "properties": {
    "iso:country":"US",
    "sg:address":"6620 Line Ave",
    "sg:city":"Shreveport",
    "sg:classifiers":[
        {
            "category":"Building & Trades",
            "subcategory":"Landscaping Services",
            "type":"Services"
        }
    ],
    "sg:phone":"+1 318 865 2335",
    "sg:postcode":"71106",
    "sg:province":"LA",
    "sg:tags":[
        "landscape",
        "contractor"
    ],
    "wof:name":"Rice Landscape & Irrigation",
    "wof:placetype":"venue"
},
  "geometry": {"coordinates":[-93.74606199999999,32.4453],"type":"Point"}
}