{
  "type": "Feature",
  "properties": {
    "addr:full":"5741 Crowder Blvd New Orleans LA 70127",
    "addr:housenumber":"5741",
    "addr:postcode":"70127",
    "addr:street":"Crowder Blvd",
    "iso:country":"US",
    "sg:address":"5741 Crowder Blvd",
    "sg:city":"New Orleans",
    "sg:classifiers":[
        {
            "category":"Shopping",
            "subcategory":"Clothing, Apparel, & Fashions",
            "type":"Retail Goods"
        }
    ],
    "sg:phone":"+1 504 244 1400",
    "sg:postcode":"70127",
    "sg:province":"LA",
    "sg:tags":[
        "uniform"
    ],
    "wof:name":"Tapps Uniform & Apparel",
    "wof:placetype":"venue"
},
  "geometry": {"coordinates":[-89.99272000000001,30.028632],"type":"Point"}
}