{
  "type": "Feature",
  "properties": {
    "addr:full":"148 Boudreaux Rd Opelousas LA 70570",
    "addr:housenumber":"148",
    "addr:postcode":"70570",
    "addr:street":"Boudreaux Rd",
    "iso:country":"US",
    "sg:address":"148 Boudreaux Rd",
    "sg:city":"Opelousas",
    "sg:classifiers":[
        {
            "category":"Building & Trades",
            "subcategory":"Construction",
            "type":"Services"
        }
    ],
    "sg:phone":"+1 337 948 1763",
    "sg:postcode":"70570",
    "sg:province":"LA",
    "sg:tags":[
        "roofing",
        "contractor"
    ],
    "wof:name":"Doucet's Roofing",
    "wof:placetype":"venue"
},
  "geometry": {"coordinates":[-92.11152199999999,30.535815],"type":"Point"}
}