{
  "type": "Feature",
  "properties": {
    "addr:full":"6640 Siegen Ln Baton Rouge LA 70809",
    "addr:postcode":"6640;70809",
    "addr:street":"Siegen Ln",
    "iso:country":"US",
    "sg:address":"6640 Siegen Ln",
    "sg:city":"Baton Rouge",
    "sg:classifiers":[
        {
            "category":"Social Services",
            "subcategory":"Child Care",
            "type":"Services"
        }
    ],
    "sg:phone":"+1 225 295 1263",
    "sg:postcode":"70809",
    "sg:province":"LA",
    "wof:name":"Siegen Village Christian Day",
    "wof:placetype":"venue"
},
  "geometry": {"coordinates":[-91.062248,30.388742],"type":"Point"}
}