{
  "type": "Feature",
  "properties": {
    "iso:country":"US",
    "sg:address":"601 Mill St",
    "sg:city":"West Monroe",
    "sg:classifiers":[
        {
            "category":"Wholesale",
            "subcategory":"Machinery & Supplies",
            "type":"Manufacturing & Wholesale Goods"
        }
    ],
    "sg:phone":"+1 318 323 1985",
    "sg:postcode":"71291",
    "sg:province":"LA",
    "sg:tags":[
        "field",
        "oil",
        "equipment"
    ],
    "wof:name":"Bulk Mixer Inc",
    "wof:placetype":"venue"
},
  "geometry": {"coordinates":[-92.13227999999999,32.500729],"type":"Point"}
}