{
  "type": "Feature",
  "properties": {
    "iso:country":"US",
    "sg:address":"1575 2nd St",
    "sg:city":"Lutcher",
    "sg:classifiers":[
        {
            "category":"Communications",
            "subcategory":"Film & Video Production",
            "type":"Services"
        }
    ],
    "sg:phone":"+1 225 869 7984",
    "sg:postcode":"70071",
    "sg:province":"LA",
    "sg:tags":[
        "motion",
        "co"
    ],
    "wof:name":"Duhes Heating & Air LLC",
    "wof:placetype":"venue"
},
  "geometry": {"coordinates":[-90.700757,30.051115],"type":"Point"}
}