{
  "type": "Feature",
  "properties": {
    "iso:country":"US",
    "sg:address":"2315 Fort Miro Ave",
    "sg:city":"Monroe",
    "sg:classifiers":[
        {
            "category":"Professional",
            "subcategory":"Computer Services",
            "type":"Services"
        }
    ],
    "sg:phone":"+1 318 323 0404",
    "sg:postcode":"71201",
    "sg:province":"LA",
    "sg:tags":[
        "repair"
    ],
    "wof:name":"A-1 Technologies",
    "wof:placetype":"venue"
},
  "geometry": {"coordinates":[-92.106324,32.538408],"type":"Point"}
}