{
  "type": "Feature",
  "properties": {
    "addr:full":"2923 Government St Baton Rouge LA 70806",
    "addr:housenumber":"2923",
    "addr:postcode":"70806",
    "addr:street":"Government St",
    "iso:country":"US",
    "sg:address":"2923 Government St",
    "sg:city":"Baton Rouge",
    "sg:classifiers":[
        {
            "category":"Shopping",
            "subcategory":"Bicycles & Sporting Goods",
            "type":"Retail Goods"
        }
    ],
    "sg:phone":"+1 225 343 1918",
    "sg:postcode":"70806",
    "sg:province":"LA",
    "sg:tags":[
        "skateboard",
        "accessory"
    ],
    "wof:name":"Urban 9",
    "wof:placetype":"venue"
},
  "geometry": {"coordinates":[-91.158598,30.44415],"type":"Point"}
}