{
  "type": "Feature",
  "properties": {
    "addr:full":"1000 Mac Arthur Ave Harvey LA 70058",
    "addr:housenumber":"1000",
    "addr:postcode":"70058",
    "addr:street":"Mac Arthur Ave",
    "iso:country":"US",
    "sg:address":"1000 Mac Arthur Ave",
    "sg:city":"Harvey",
    "sg:classifiers":[
        {
            "category":"Wholesale",
            "subcategory":"Machinery & Supplies",
            "type":"Manufacturing & Wholesale Goods"
        }
    ],
    "sg:phone":"+1 504 328 4033",
    "sg:postcode":"70058",
    "sg:province":"LA",
    "sg:tags":[
        "field",
        "oil"
    ],
    "sg:website":"www.natoil.com",
    "wof:name":"National-Oilwell Varco",
    "wof:placetype":"venue"
},
  "geometry": {"coordinates":[-90.085151,29.896155],"type":"Point"}
}