{
  "type": "Feature",
  "properties": {
    "iso:country":"US",
    "sg:address":"3883 Pontchartrain Dr",
    "sg:city":"Slidell",
    "sg:classifiers":[
        {
            "category":"Retail",
            "subcategory":"Auto Repair",
            "type":"Services"
        }
    ],
    "sg:phone":"+1 985 643 7066",
    "sg:postcode":"70458",
    "sg:province":"LA",
    "sg:tags":[
        "repairing",
        "automobile"
    ],
    "wof:name":"Auto Master Of Slidell Inc",
    "wof:placetype":"venue"
},
  "geometry": {"coordinates":[-89.791434,30.251849],"type":"Point"}
}