{
  "type": "Feature",
  "properties": {
    "addr:full":"849 Agnes Dr Breaux Bridge LA 70517",
    "addr:housenumber":"849",
    "addr:postcode":"la 70517",
    "addr:street":"Agnes Dr",
    "iso:country":"US",
    "sg:address":"849 Agnes Dr",
    "sg:city":"Breaux Bridge",
    "sg:classifiers":[
        {
            "category":"Real Estate",
            "subcategory":"Real Estate Operator",
            "type":"Services"
        }
    ],
    "sg:phone":"+1 337 332 6043",
    "sg:postcode":"70517",
    "sg:province":"LA",
    "sg:tags":[
        "apartment"
    ],
    "wof:name":"Highland Creek Apartments",
    "wof:placetype":"venue"
},
  "geometry": {"coordinates":[-91.896704,30.284088],"type":"Point"}
}