{
  "type": "Feature",
  "properties": {
    "addr:full":"101 N Ave H Crowley LA 70526",
    "addr:housenumber":"101",
    "addr:postcode":"70526",
    "addr:street":"N Ave H Crowley",
    "iso:country":"US",
    "sg:address":"101 N Ave H",
    "sg:city":"Crowley",
    "sg:classifiers":[
        {
            "category":"Building & Trades",
            "subcategory":"Equipment Rental",
            "type":"Services"
        }
    ],
    "sg:phone":"+1 337 783 6259",
    "sg:postcode":"70526",
    "sg:province":"LA",
    "sg:tags":[
        "leasing",
        "furniture"
    ],
    "wof:name":"Ken's Rental",
    "wof:placetype":"venue"
},
  "geometry": {"coordinates":[-92.36941299999999,30.211779],"type":"Point"}
}