{
  "type": "Feature",
  "properties": {
    "iso:country":"US",
    "sg:address":"5900 S Front St",
    "sg:city":"New Orleans",
    "sg:classifiers":[
        {
            "category":"Restaurant",
            "type":"Food & Drink"
        }
    ],
    "sg:menulink":"http://www.allmenus.com/la/new-orleans/224747-gumbo-shop/menu/",
    "sg:phone":"+1 504 899 2362",
    "sg:postcode":"70115",
    "sg:province":"LA",
    "sg:tags":[
        "american",
        "creole",
        "cajun"
    ],
    "wof:name":"Gumbo Shop",
    "wof:placetype":"venue"
},
  "geometry": {"coordinates":[-90.121407,29.91601],"type":"Point"}
}