{
  "type": "Feature",
  "properties": {
    "addr:full":"126 Iberia St New Iberia LA 70560",
    "addr:housenumber":"126",
    "addr:postcode":"70560",
    "addr:street":"Iberia St",
    "iso:country":"US",
    "sg:address":"126 Iberia St",
    "sg:city":"New Iberia",
    "sg:classifiers":[
        {
            "category":"Arts & Performance",
            "subcategory":"Arts Center",
            "type":"Entertainment"
        },
        {
            "category":"Cinema",
            "subcategory":"Movie Theater",
            "type":"Entertainment"
        }
    ],
    "sg:phone":"+1 337 364 6114",
    "sg:postcode":"70560",
    "sg:province":"LA",
    "sg:tags":[
        "performing"
    ],
    "wof:name":"I Pal",
    "wof:placetype":"venue"
},
  "geometry": {"coordinates":[-91.8181,30.0063],"type":"Point"}
}