{
  "type": "Feature",
  "properties": {
    "iso:country":"US",
    "sg:address":"819 W 1st St",
    "sg:city":"Thibodaux",
    "sg:classifiers":[
        {
            "category":"Food & Beverages",
            "subcategory":"Specialty",
            "type":"Retail Goods"
        }
    ],
    "sg:phone":"+1 985 447 5006",
    "sg:postcode":"70301",
    "sg:province":"LA",
    "sg:tags":[
        "health",
        "diet"
    ],
    "wof:name":"Carrot Patch Health Food",
    "wof:placetype":"venue"
},
  "geometry": {"coordinates":[-90.823696,29.796273],"type":"Point"}
}