{
  "type": "Feature",
  "properties": {
    "iso:country":"US",
    "sg:address":"1177 Acadian Dr",
    "sg:city":"Ville Platte",
    "sg:classifiers":[
        {
            "category":"Personal",
            "subcategory":"Beauty Salon",
            "type":"Services"
        }
    ],
    "sg:phone":"+1 337 363 6479",
    "sg:postcode":"70546",
    "sg:province":"LA",
    "wof:name":"Lisa's Family Hair Care",
    "wof:placetype":"venue"
},
  "geometry": {"coordinates":[-92.650734,30.236633],"type":"Point"}
}