{
  "type": "Feature",
  "properties": {
    "iso:country":"US",
    "sg:address":"1100 24th St",
    "sg:city":"Kenner",
    "sg:classifiers":[
        {
            "category":"Building & Trades",
            "subcategory":"Construction",
            "type":"Services"
        }
    ],
    "sg:phone":"+1 504 469 6494",
    "sg:postcode":"70062",
    "sg:province":"LA",
    "sg:tags":[
        "downspouts",
        "gutter"
    ],
    "sg:website":"www.audubongutters.com",
    "wof:name":"Audubon Gutters",
    "wof:placetype":"venue"
},
  "geometry": {"coordinates":[-90.253669,30.000003],"type":"Point"}
}