{
  "type": "Feature",
  "properties": {
    "iso:country":"US",
    "sg:address":"1107 W 9th St",
    "sg:city":"Bogalusa",
    "sg:classifiers":[
        {
            "category":"Organizations",
            "subcategory":"Religious Organization",
            "type":"Services"
        }
    ],
    "sg:phone":"+1 985 732 9602",
    "sg:postcode":"70427",
    "sg:province":"LA",
    "sg:tags":[
        "church"
    ],
    "sg:website":"www.webcbogalusa.com",
    "wof:name":"Westside Emmanuel Baptist Chr",
    "wof:placetype":"venue"
},
  "geometry": {"coordinates":[-89.87775999999999,30.772227],"type":"Point"}
}