{
  "type": "Feature",
  "properties": {
    "addr:full":"428 Seattle St New Orleans LA 70124",
    "addr:housenumber":"428",
    "addr:postcode":"70124",
    "addr:street":"Seattle St",
    "iso:country":"US",
    "sg:address":"428 Seattle St",
    "sg:city":"New Orleans",
    "sg:classifiers":[
        {
            "category":"Communications",
            "subcategory":"Film & Video Production",
            "type":"Services"
        }
    ],
    "sg:phone":"+1 504 482 2615",
    "sg:postcode":"70124",
    "sg:province":"LA",
    "sg:tags":[
        "taping"
    ],
    "wof:name":"Paul Ulfers Video Production",
    "wof:placetype":"venue"
},
  "geometry": {"coordinates":[-90.120608,30.01274],"type":"Point"}
}