{
  "type": "Feature",
  "properties": {
    "iso:country":"US",
    "sg:address":"3500 Houma Blvd",
    "sg:city":"Metairie",
    "sg:classifiers":[
        {
            "category":"Insurance",
            "subcategory":"Hazard Insurance",
            "type":"Services"
        }
    ],
    "sg:phone":"+1 504 231 0731",
    "sg:postcode":"70006",
    "sg:province":"LA",
    "sg:tags":[
        "commercial",
        "business"
    ],
    "wof:name":"Ryan Ginn Insurance Contractor",
    "wof:placetype":"venue"
},
  "geometry": {"coordinates":[-90.18,30.006559],"type":"Point"}
}