{
  "type": "Feature",
  "properties": {
    "iso:country":"US",
    "sg:address":"1221 Elmwood Park Blvd",
    "sg:city":"Harahan",
    "sg:classifiers":[
        {
            "category":"Government",
            "subcategory":"Office",
            "type":"Public Place"
        }
    ],
    "sg:phone":"+1 504 736 6964",
    "sg:postcode":"70123",
    "sg:province":"LA",
    "sg:website":"www.jeffparish.net",
    "wof:name":"Jefferson Parish Bldg Inspctn",
    "wof:placetype":"venue"
},
  "geometry": {"coordinates":[-90.18916900000001,29.96237],"type":"Point"}
}