{
  "type": "Feature",
  "properties": {
    "iso:country":"US",
    "sg:address":"205 Hwy 462",
    "sg:city":"Pitkin",
    "sg:classifiers":[
        {
            "category":"Organizations",
            "subcategory":"Religious Organization",
            "type":"Services"
        }
    ],
    "sg:phone":"+1 318 634 7127",
    "sg:postcode":"70656",
    "sg:province":"LA",
    "sg:tags":[
        "church"
    ],
    "wof:name":"Shady Grove Baptist Church",
    "wof:placetype":"venue"
},
  "geometry": {"coordinates":[-92.800065,30.966537],"type":"Point"}
}