{
  "type": "Feature",
  "properties": {
    "addr:full":"521 Central Ave Jefferson LA 70121",
    "addr:housenumber":"521",
    "addr:postcode":"70121",
    "addr:street":"Central Ave",
    "iso:country":"US",
    "sg:address":"521 Central Ave",
    "sg:city":"Jefferson",
    "sg:classifiers":[
        {
            "category":"Restaurant",
            "type":"Food & Drink"
        }
    ],
    "sg:phone":"+1 504 733 9538",
    "sg:postcode":"70121",
    "sg:province":"LA",
    "wof:name":"Cajun Catfish Restaurant",
    "wof:placetype":"venue"
},
  "geometry": {"coordinates":[-90.171846,29.960544],"type":"Point"}
}