{
  "type": "Feature",
  "properties": {
    "iso:country":"US",
    "sg:address":"803 Brownswitch Rd",
    "sg:city":"Slidell",
    "sg:classifiers":[
        {
            "category":"Real Estate",
            "subcategory":"Real Estate Agent",
            "type":"Services"
        }
    ],
    "sg:phone":"+1 985 646 1888",
    "sg:postcode":"70458",
    "sg:province":"LA",
    "sg:website":"www.louisianalistings.com",
    "wof:name":"Re/Max Real Estate Partners",
    "wof:placetype":"venue"
},
  "geometry": {"coordinates":[-89.749014,30.310456],"type":"Point"}
}