{
  "type": "Feature",
  "properties": {
    "iso:country":"US",
    "sg:address":"1009 Highland Ave",
    "sg:city":"Metairie",
    "sg:classifiers":[
        {
            "category":"Wholesale",
            "subcategory":"Vending Machines",
            "type":"Manufacturing & Wholesale Goods"
        }
    ],
    "sg:phone":"+1 504 468 2202",
    "sg:postcode":"70001",
    "sg:province":"LA",
    "wof:name":"Breaktime Vending",
    "wof:placetype":"venue"
},
  "geometry": {"coordinates":[-90.18054600000001,29.974157],"type":"Point"}
}