{
  "type": "Feature",
  "properties": {
    "iso:country":"US",
    "sg:address":"801 S Arkansas St",
    "sg:city":"Springhill",
    "sg:classifiers":[
        {
            "category":"Personal",
            "subcategory":"Beauty Salon",
            "type":"Services"
        }
    ],
    "sg:phone":"+1 318 539 5786",
    "sg:postcode":"71075",
    "sg:province":"LA",
    "wof:name":"Holiday Salon",
    "wof:placetype":"venue"
},
  "geometry": {"coordinates":[-93.463036,32.996541],"type":"Point"}
}