{
  "type": "Feature",
  "properties": {
    "iso:country":"US",
    "sg:address":"269 Blue Lake Rd",
    "sg:city":"Forest Hill",
    "sg:classifiers":[
        {
            "category":"Home & Garden",
            "subcategory":"Garden Supply",
            "type":"Retail Goods"
        }
    ],
    "sg:phone":"+1 318 748 6418",
    "sg:postcode":"71430",
    "sg:province":"LA",
    "sg:tags":[
        "nurseryman"
    ],
    "wof:name":"Hurricane Creek Nursery",
    "wof:placetype":"venue"
},
  "geometry": {"coordinates":[-92.50133099999999,31.035026],"type":"Point"}
}