{
  "type": "Feature",
  "properties": {
    "iso:country":"US",
    "sg:address":"631 Flournoy Lucas Rd",
    "sg:city":"Shreveport",
    "sg:classifiers":[
        {
            "category":"Building & Trades",
            "subcategory":"Plumbing",
            "type":"Services"
        }
    ],
    "sg:phone":"+1 318 686 4582",
    "sg:postcode":"71118",
    "sg:province":"LA",
    "sg:tags":[
        "plumbing",
        "contractor"
    ],
    "wof:name":"Michael Robinson Plumbing",
    "wof:placetype":"venue"
},
  "geometry": {"coordinates":[-93.763413,32.391002],"type":"Point"}
}