{
  "type": "Feature",
  "properties": {
    "iso:country":"US",
    "sg:address":"1550 Shreveport Rd",
    "sg:city":"Minden",
    "sg:classifiers":[
        {
            "category":"Building & Trades",
            "subcategory":"Construction",
            "type":"Services"
        }
    ],
    "sg:phone":"+1 318 377 6027",
    "sg:postcode":"71055",
    "sg:province":"LA",
    "sg:tags":[
        "local",
        "wrecker"
    ],
    "wof:name":"Halls Wrecker Service",
    "wof:placetype":"venue"
},
  "geometry": {"coordinates":[-93.31356100000001,32.606754],"type":"Point"}
}