{
  "type": "Feature",
  "properties": {
    "iso:country":"US",
    "sg:address":"416 Hamilton St",
    "sg:city":"Lockport",
    "sg:classifiers":[
        {
            "category":"Shopping",
            "subcategory":"Computers & Home Electronics",
            "type":"Retail Goods"
        }
    ],
    "sg:phone":"+1 985 798 5856",
    "sg:postcode":"70374",
    "sg:province":"LA",
    "sg:tags":[
        "television",
        "radio"
    ],
    "wof:name":"DPS Smart Zone Radio Project",
    "wof:placetype":"venue"
},
  "geometry": {"coordinates":[-90.392385,29.586274],"type":"Point"}
}