{
  "type": "Feature",
  "properties": {
    "addr:full":"9 W Main St Ville Platte LA 70586",
    "addr:housenumber":"9",
    "addr:postcode":"70586",
    "addr:street":"W Main St",
    "iso:country":"US",
    "sg:address":"9 W Main St",
    "sg:city":"Ville Platte",
    "sg:classifiers":[
        {
            "category":"Banks & Credit Unions",
            "subcategory":"Bank",
            "type":"Services"
        }
    ],
    "sg:phone":"+1 337 363 0077",
    "sg:postcode":"70586",
    "sg:province":"LA",
    "sg:tags":[
        "loan"
    ],
    "wof:name":"Randy's Pay Day Loans Inc",
    "wof:placetype":"venue"
},
  "geometry": {"coordinates":[-92.27537599999999,30.688944],"type":"Point"}
}