{
  "type": "Feature",
  "properties": {
    "iso:country":"US",
    "sg:address":"1233 Government St",
    "sg:city":"Baton Rouge",
    "sg:classifiers":[
        {
            "category":"Organizations",
            "subcategory":"Labor Organization",
            "type":"Services"
        }
    ],
    "sg:phone":"+1 225 383 2464",
    "sg:postcode":"70802",
    "sg:province":"LA",
    "wof:name":"Construction & Genl Laborers'",
    "wof:placetype":"venue"
},
  "geometry": {"coordinates":[-91.17618400000001,30.443709],"type":"Point"}
}