{
  "type": "Feature",
  "properties": {
    "iso:country":"US",
    "sg:address":"213 Bendel Rd",
    "sg:city":"Lafayette",
    "sg:classifiers":[
        {
            "category":"Travel",
            "subcategory":"Hotels & Motels",
            "type":"Entertainment"
        }
    ],
    "sg:phone":"+1 337 261 0604",
    "sg:postcode":"70503",
    "sg:province":"LA",
    "sg:website":"www.bendelexec.com",
    "wof:name":"Bendel Executive Suites",
    "wof:placetype":"venue"
},
  "geometry": {"coordinates":[-92.01639,30.199102],"type":"Point"}
}