{
  "type": "Feature",
  "properties": {
    "iso:country":"US",
    "sg:address":"1640 W Laurel Ave",
    "sg:city":"Eunice",
    "sg:classifiers":[
        {
            "category":"Restaurant",
            "type":"Food & Drink"
        }
    ],
    "sg:phone":"+1 337 457 9978",
    "sg:postcode":"70535",
    "sg:province":"LA",
    "wof:name":"Mama's Fried Chicken",
    "wof:placetype":"venue"
},
  "geometry": {"coordinates":[-92.432576,30.495034],"type":"Point"}
}