{
  "type": "Feature",
  "properties": {
    "addr:full":"3650 Millhaven Rd Monroe LA 71203",
    "addr:housenumber":"3650",
    "addr:postcode":"71203",
    "addr:street":"Millhaven Rd",
    "iso:country":"US",
    "sg:address":"3650 Millhaven Rd",
    "sg:city":"Monroe",
    "sg:classifiers":[
        {
            "category":"Home & Garden",
            "subcategory":"Household Appliances",
            "type":"Retail Goods"
        }
    ],
    "sg:phone":"+1 318 361 4471",
    "sg:postcode":"71203",
    "sg:province":"LA",
    "sg:website":"www.4cost.com",
    "wof:name":"4 Cost Internet Network",
    "wof:placetype":"venue"
},
  "geometry": {"coordinates":[-92.075126,32.501484],"type":"Point"}
}