{
  "type": "Feature",
  "properties": {
    "iso:country":"US",
    "sg:address":"3839 Ulloa St",
    "sg:city":"New Orleans",
    "sg:classifiers":[
        {
            "category":"Banks & Credit Unions",
            "subcategory":"Investment Brokerage",
            "type":"Services"
        }
    ],
    "sg:phone":"+1 504 488 5306",
    "sg:postcode":"70119",
    "sg:province":"LA",
    "sg:tags":[
        "consultant",
        "planning",
        "financial"
    ],
    "wof:name":"Merchant Financial Svc",
    "wof:placetype":"venue"
},
  "geometry": {"coordinates":[-90.10217299999999,29.967373],"type":"Point"}
}