{
  "type": "Feature",
  "properties": {
    "iso:country":"US",
    "sg:address":"17354 Airline Hwy",
    "sg:city":"Prairieville",
    "sg:classifiers":[
        {
            "category":"Restaurant",
            "type":"Food & Drink"
        }
    ],
    "sg:phone":"+1 225 673 1639",
    "sg:postcode":"70769",
    "sg:province":"LA",
    "wof:name":"Gail's Diner",
    "wof:placetype":"venue"
},
  "geometry": {"coordinates":[-90.981392,30.326229],"type":"Point"}
}