{
  "type": "Feature",
  "properties": {
    "iso:country":"US",
    "sg:address":"1849 Barataria Blvd",
    "sg:city":"Marrero",
    "sg:classifiers":[
        {
            "category":"Sports & Exercise",
            "subcategory":"Gym",
            "type":"Entertainment"
        }
    ],
    "sg:phone":"+1 504 341 2582",
    "sg:postcode":"70072",
    "sg:province":"LA",
    "sg:tags":[
        "club",
        "health",
        "studio",
        "gymnasium"
    ],
    "wof:name":"Manhattan Athletic Club",
    "wof:placetype":"venue"
},
  "geometry": {"coordinates":[-90.09827300000001,29.877267],"type":"Point"}
}