{
  "type": "Feature",
  "properties": {
    "iso:country":"US",
    "sg:address":"630 Chartres St",
    "sg:city":"New Orleans",
    "sg:classifiers":[
        {
            "category":"Shopping",
            "subcategory":"Crafts & Fabrics",
            "type":"Retail Goods"
        }
    ],
    "sg:phone":"+1 504 522 4451",
    "sg:postcode":"70130",
    "sg:province":"LA",
    "sg:tags":[
        "knitting",
        "material",
        "needlework",
        "supply"
    ],
    "wof:name":"The Quarter Stitch",
    "wof:placetype":"venue"
},
  "geometry": {"coordinates":[-90.06379699999999,29.957199],"type":"Point"}
}