{
  "type": "Feature",
  "properties": {
    "iso:country":"US",
    "sg:address":"120 Westchester Blvd",
    "sg:city":"Slidell",
    "sg:classifiers":[
        {
            "category":"Health Services",
            "subcategory":"Doctor",
            "type":"Services"
        }
    ],
    "sg:phone":"+1 985 646 0123",
    "sg:postcode":"70458",
    "sg:province":"LA",
    "sg:tags":[
        "physician",
        "surgeon"
    ],
    "wof:name":"Aleta De Clouet MD",
    "wof:placetype":"venue"
},
  "geometry": {"coordinates":[-89.79130600000001,30.251382],"type":"Point"}
}