{
  "type": "Feature",
  "properties": {
    "iso:country":"US",
    "sg:address":"1611 Park Loop Dr",
    "sg:city":"Bastrop",
    "sg:classifiers":[
        {
            "category":"Communications",
            "subcategory":"Television Station",
            "type":"Services"
        },
        {
            "category":"Utilities",
            "subcategory":"Telephone",
            "type":"Services"
        },
        {
            "category":"Professional",
            "subcategory":"Computer Services",
            "type":"Services"
        }
    ],
    "sg:phone":"+1 318 251 5999",
    "sg:postcode":"71220",
    "sg:province":"LA",
    "sg:tags":[
        "satellite",
        "telecommunication",
        "cable",
        "isp",
        "provider",
        "internet"
    ],
    "sg:website":"http://www.suddenlink.com",
    "wof:name":"Suddenlink Communications",
    "wof:placetype":"venue"
},
  "geometry": {"coordinates":[-91.892876,32.780185],"type":"Point"}
}