{
  "type": "Feature",
  "properties": {
    "addr:full":"7037 Canal Blvd New Orleans LA 70124",
    "addr:housenumber":"7037",
    "addr:postcode":"70124",
    "addr:street":"Canal Blvd",
    "iso:country":"US",
    "sg:address":"7037 Canal Blvd",
    "sg:city":"New Orleans",
    "sg:classifiers":[
        {
            "category":"Real Estate",
            "subcategory":"Real Estate Services",
            "type":"Services"
        }
    ],
    "sg:phone":"+1 504 286 0331",
    "sg:postcode":"70124",
    "sg:province":"LA",
    "sg:tags":[
        "company",
        "title"
    ],
    "wof:name":"Stewart Title Co",
    "wof:placetype":"venue"
},
  "geometry": {"coordinates":[-90.106066,30.01945],"type":"Point"}
}