{
  "type": "Feature",
  "properties": {
    "iso:country":"US",
    "sg:address":"509 Presbytere Pkwy",
    "sg:city":"Lafayette",
    "sg:classifiers":[
        {
            "category":"Retail",
            "subcategory":"Repair Shop",
            "type":"Services"
        }
    ],
    "sg:phone":"+1 337 984 6195",
    "sg:postcode":"70503",
    "sg:province":"LA",
    "wof:name":"Clean International Envmtl",
    "wof:placetype":"venue"
},
  "geometry": {"coordinates":[-92.08137499999999,30.152472],"type":"Point"}
}