{
  "type": "Feature",
  "properties": {
    "iso:country":"US",
    "sg:address":"111 E Pine Ave",
    "sg:city":"Bastrop",
    "sg:classifiers":[
        {
            "category":"Insurance",
            "subcategory":"Insurance Agent",
            "type":"Services"
        }
    ],
    "sg:phone":"+1 318 281 7547",
    "sg:postcode":"71220",
    "sg:province":"LA",
    "wof:name":"American National Insurance Co",
    "wof:placetype":"venue"
},
  "geometry": {"coordinates":[-91.914343,32.779166],"type":"Point"}
}