{
  "type": "Feature",
  "properties": {
    "iso:country":"US",
    "sg:address":"128 Eric's Ln",
    "sg:city":"Plaucheville",
    "sg:classifiers":[
        {
            "category":"Building & Trades",
            "subcategory":"Construction",
            "type":"Services"
        }
    ],
    "sg:phone":"+1 318 922 3249",
    "sg:postcode":"71362",
    "sg:province":"LA",
    "sg:tags":[
        "insulation",
        "heat",
        "contractor"
    ],
    "wof:name":"Eric's Insulation",
    "wof:placetype":"venue"
},
  "geometry": {"coordinates":[-91.965748,30.989128],"type":"Point"}
}