{
  "type": "Feature",
  "properties": {
    "iso:country":"US",
    "sg:address":"27320 State Rte 405",
    "sg:city":"Plaquemine",
    "sg:classifiers":[
        {
            "category":"Organizations",
            "subcategory":"Religious Organization",
            "type":"Services"
        }
    ],
    "sg:phone":"+1 225 687 2452",
    "sg:postcode":"70764",
    "sg:province":"LA",
    "sg:tags":[
        "church"
    ],
    "wof:name":"Mount Olive Baptist Church",
    "wof:placetype":"venue"
},
  "geometry": {"coordinates":[-91.133655,30.267095],"type":"Point"}
}