{
  "type": "Feature",
  "properties": {
    "addr:full":"2717 Athania Pkwy Metairie LA 70002",
    "addr:housenumber":"2717",
    "addr:postcode":"70002",
    "addr:street":"Athania Pkwy",
    "iso:country":"US",
    "sg:address":"2717 Athania Pkwy",
    "sg:city":"Metairie",
    "sg:classifiers":[
        {
            "category":"Social Services",
            "subcategory":"Child Care",
            "type":"Services"
        }
    ],
    "sg:phone":"+1 504 835 1235",
    "sg:postcode":"70002",
    "sg:province":"LA",
    "wof:name":"Children's Center-Love & Learn",
    "wof:placetype":"venue"
},
  "geometry": {"coordinates":[-90.157302,29.999772],"type":"Point"}
}