{
  "type": "Feature",
  "properties": {
    "iso:country":"US",
    "sg:address":"911 Princesa Cir",
    "sg:city":"Haughton",
    "sg:classifiers":[
        {
            "category":"Building & Trades",
            "subcategory":"Plumbing",
            "type":"Services"
        }
    ],
    "sg:phone":"+1 318 949 9366",
    "sg:postcode":"71037",
    "sg:province":"LA",
    "sg:tags":[
        "conditioning",
        "air",
        "system",
        "contractor"
    ],
    "wof:name":"Air-Star Air Cond & Heating",
    "wof:placetype":"venue"
},
  "geometry": {"coordinates":[-93.610316,32.550641],"type":"Point"}
}