{
  "type": "Feature",
  "properties": {
    "iso:country":"US",
    "sg:address":"5801 G St",
    "sg:city":"New Orleans",
    "sg:classifiers":[
        {
            "category":"Manufacturing",
            "subcategory":"Food",
            "type":"Manufacturing & Wholesale Goods"
        }
    ],
    "sg:phone":"+1 504 733 7500",
    "sg:postcode":"70123",
    "sg:province":"LA",
    "sg:tags":[
        "preparation"
    ],
    "wof:name":"Dixie Produce & Packaging Inc",
    "wof:placetype":"venue"
},
  "geometry": {"coordinates":[-90.191513,29.9513],"type":"Point"}
}