{
  "type": "Feature",
  "properties": {
    "iso:country":"US",
    "sg:address":"3708 Commercial Dr",
    "sg:city":"New Iberia",
    "sg:classifiers":[
        {
            "category":"Building & Trades",
            "subcategory":"Landscaping Services",
            "type":"Services"
        }
    ],
    "sg:phone":"+1 337 560 5813",
    "sg:postcode":"70560",
    "sg:province":"LA",
    "wof:name":"Estis Lawn Maintenance & Busho",
    "wof:placetype":"venue"
},
  "geometry": {"coordinates":[-91.839135,29.954409],"type":"Point"}
}