{
  "type": "Feature",
  "properties": {
    "iso:country":"US",
    "sg:address":"12133 Industriplex Blvd",
    "sg:city":"Baton Rouge",
    "sg:classifiers":[
        {
            "category":"Health Services",
            "subcategory":"Clinic",
            "type":"Services"
        }
    ],
    "sg:phone":"+1 225 293 2276",
    "sg:postcode":"70809",
    "sg:province":"LA",
    "sg:tags":[
        "organization",
        "medical",
        "surgical"
    ],
    "sg:website":"www.adtnuclear.com",
    "wof:name":"American Diagnostic Techs",
    "wof:placetype":"venue"
},
  "geometry": {"coordinates":[-91.043682,30.384117],"type":"Point"}
}