{
  "type": "Feature",
  "properties": {
    "addr:full":"30034 Hwy 16 Sun LA 70427",
    "addr:housenumber":"30034",
    "addr:postcode":"70427",
    "addr:street":"Hwy 16 Sun",
    "iso:country":"US",
    "sg:address":"30034 Hwy 16",
    "sg:city":"Sun",
    "sg:classifiers":[
        {
            "category":"Government",
            "subcategory":"Post Office",
            "type":"Public Place"
        }
    ],
    "sg:phone":"+1 985 886 3136",
    "sg:postcode":"70427",
    "sg:province":"LA",
    "wof:name":"US Post Office",
    "wof:placetype":"venue"
},
  "geometry": {"coordinates":[-89.897659,30.649049],"type":"Point"}
}