{
  "type": "Feature",
  "properties": {
    "iso:country":"US",
    "sg:address":"5820 Sumrall Dr",
    "sg:city":"Baton Rouge",
    "sg:classifiers":[
        {
            "category":"Building & Trades",
            "subcategory":"Construction",
            "type":"Services"
        }
    ],
    "sg:phone":"+1 225 356 0201",
    "sg:postcode":"70811",
    "sg:province":"LA",
    "sg:tags":[
        "house",
        "family"
    ],
    "wof:name":"Plain Construction Inc",
    "wof:placetype":"venue"
},
  "geometry": {"coordinates":[-91.131756,30.51358],"type":"Point"}
}