{
  "type": "Feature",
  "properties": {
    "iso:country":"US",
    "sg:address":"1309 Pine St",
    "sg:city":"Monroe",
    "sg:classifiers":[
        {
            "category":"Retail",
            "subcategory":"Auto Repair",
            "type":"Services"
        }
    ],
    "sg:phone":"+1 318 322 0450",
    "sg:postcode":"71201",
    "sg:province":"LA",
    "sg:tags":[
        "repairing",
        "automobile"
    ],
    "wof:name":"Bulloch's Garage Inc",
    "wof:placetype":"venue"
},
  "geometry": {"coordinates":[-92.110011,32.513084],"type":"Point"}
}