{
  "type": "Feature",
  "properties": {
    "iso:country":"US",
    "sg:address":"13126 Texas Hwy",
    "sg:city":"Many",
    "sg:classifiers":[
        {
            "category":"Building & Trades",
            "subcategory":"Construction",
            "type":"Services"
        }
    ],
    "sg:phone":"+1 318 256 2021",
    "sg:postcode":"71449",
    "sg:province":"LA",
    "sg:tags":[
        "shelter",
        "dealer",
        "storm",
        "contractor"
    ],
    "wof:name":"Nuclear Defense Shelters",
    "wof:placetype":"venue"
},
  "geometry": {"coordinates":[-93.674105,31.493156],"type":"Point"}
}