{
  "type": "Feature",
  "properties": {
    "iso:country":"US",
    "sg:address":"803 Weldon St",
    "sg:city":"New Iberia",
    "sg:classifiers":[
        {
            "category":"Freight",
            "type":"Transportation"
        }
    ],
    "sg:phone":"+1 337 364 9882",
    "sg:postcode":"70560",
    "sg:province":"LA",
    "sg:tags":[
        "commercial",
        "storage"
    ],
    "wof:name":"AAA Self Storage Warehouses",
    "wof:placetype":"venue"
},
  "geometry": {"coordinates":[-91.81435500000001,29.988084],"type":"Point"}
}