{
  "type": "Feature",
  "properties": {
    "iso:country":"US",
    "sg:address":"366 Holomon Cemetery Rd",
    "sg:city":"Dubberly",
    "sg:classifiers":[
        {
            "category":"Professional",
            "subcategory":"Business Services",
            "type":"Services"
        }
    ],
    "sg:phone":"+1 318 377 4780",
    "sg:postcode":"71024",
    "sg:province":"LA",
    "wof:name":"Ach Express Inc",
    "wof:placetype":"venue"
},
  "geometry": {"coordinates":[-93.187057,32.561407],"type":"Point"}
}