{
  "type": "Feature",
  "properties": {
    "iso:country":"US",
    "sg:address":"200 W Genie St",
    "sg:city":"Chalmette",
    "sg:classifiers":[
        {
            "category":"Health Services",
            "subcategory":"Doctor",
            "type":"Services"
        }
    ],
    "sg:phone":"+1 504 277 0101",
    "sg:postcode":"70043",
    "sg:province":"LA",
    "sg:tags":[
        "dentist"
    ],
    "wof:name":"Gerald A Williams DDS",
    "wof:placetype":"venue"
},
  "geometry": {"coordinates":[-89.961034,29.953028],"type":"Point"}
}