{
  "type": "Feature",
  "properties": {
    "iso:country":"US",
    "sg:address":"2317 S Range Ave",
    "sg:city":"Denham Springs",
    "sg:classifiers":[
        {
            "category":"Shopping",
            "subcategory":"Optical Goods",
            "type":"Retail Goods"
        }
    ],
    "sg:phone":"+1 225 664 5000",
    "sg:postcode":"70726",
    "sg:province":"LA",
    "wof:name":"J J Lee Discount Optical",
    "wof:placetype":"venue"
},
  "geometry": {"coordinates":[-90.956565,30.454841],"type":"Point"}
}