{
  "type": "Feature",
  "properties": {
    "addr:full":"2449 N River Rd Port Allen LA 70767",
    "addr:housenumber":"2449",
    "addr:postcode":"70767",
    "addr:street":"N River Rd",
    "iso:country":"US",
    "sg:address":"2449 N River Rd",
    "sg:city":"Port Allen",
    "sg:classifiers":[
        {
            "category":"Freight",
            "type":"Transportation"
        }
    ],
    "sg:phone":"+1 225 389 0170",
    "sg:postcode":"70767",
    "sg:province":"LA",
    "sg:tags":[
        "bulk",
        "storage"
    ],
    "wof:name":"Intercontinental Terminals Co",
    "wof:placetype":"venue"
},
  "geometry": {"coordinates":[-91.20196,30.479367],"type":"Point"}
}