{
  "type": "Feature",
  "properties": {
    "iso:country":"US",
    "sg:address":"1101 Benton Rd",
    "sg:city":"Bossier City",
    "sg:classifiers":[
        {
            "category":"Building & Trades",
            "subcategory":"Construction",
            "type":"Services"
        }
    ],
    "sg:phone":"+1 318 549 2422",
    "sg:postcode":"71111",
    "sg:province":"LA",
    "sg:tags":[
        "downspouts",
        "gutter"
    ],
    "wof:name":"Add-On",
    "wof:placetype":"venue"
},
  "geometry": {"coordinates":[-93.719926,32.532164],"type":"Point"}
}