{
  "type": "Feature",
  "properties": {
    "iso:country":"US",
    "sg:address":"12998 Hwy 699",
    "sg:city":"Maurice",
    "sg:classifiers":[
        {
            "category":"Food & Beverages",
            "subcategory":"Groceries & Convenience Stores",
            "type":"Retail Goods"
        }
    ],
    "sg:phone":"+1 337 893 3032",
    "sg:postcode":"70555",
    "sg:province":"LA",
    "sg:tags":[
        "grocer"
    ],
    "wof:name":"Breaux Grocery",
    "wof:placetype":"venue"
},
  "geometry": {"coordinates":[-92.19096399999999,30.078953],"type":"Point"}
}