{
  "type": "Feature",
  "properties": {
    "iso:country":"US",
    "sg:address":"5967 US Hwy 80",
    "sg:city":"Start",
    "sg:classifiers":[
        {
            "category":"Shopping",
            "subcategory":"Music",
            "type":"Retail Goods"
        }
    ],
    "sg:phone":"+1 318 728 3360",
    "sg:postcode":"71279",
    "sg:province":"LA",
    "sg:tags":[
        "video",
        "disc",
        "tape",
        "cassette"
    ],
    "wof:name":"Video Magic",
    "wof:placetype":"venue"
},
  "geometry": {"coordinates":[-91.87307699999999,32.487291],"type":"Point"}
}