{
  "type": "Feature",
  "properties": {
    "addr:full":"4325 Lake St Lake Charles LA 70605",
    "addr:housenumber":"4325",
    "addr:postcode":"70605",
    "addr:street":"Lake St",
    "iso:country":"US",
    "sg:address":"4325 Lake St",
    "sg:city":"Lake Charles",
    "sg:classifiers":[
        {
            "category":"Retail",
            "subcategory":"Funeral Services",
            "type":"Services"
        }
    ],
    "sg:phone":"+1 337 478 8685",
    "sg:postcode":"70605",
    "sg:province":"LA",
    "sg:tags":[
        "crematory"
    ],
    "wof:name":"Lake Charles Crematory",
    "wof:placetype":"venue"
},
  "geometry": {"coordinates":[-93.232285,30.178078],"type":"Point"}
}