{
  "type": "Feature",
  "properties": {
    "iso:country":"US",
    "sg:address":"4480 Johnston St",
    "sg:city":"Lafayette",
    "sg:classifiers":[
        {
            "category":"Retail",
            "subcategory":"Auto Rental",
            "type":"Services"
        }
    ],
    "sg:phone":"+1 337 983 0111",
    "sg:postcode":"70503",
    "sg:province":"LA",
    "sg:tags":[
        "renting",
        "automobile"
    ],
    "wof:name":"Priceless Rent-A-Car",
    "wof:placetype":"venue"
},
  "geometry": {"coordinates":[-92.05827600000001,30.194267],"type":"Point"}
}