{
  "type": "Feature",
  "properties": {
    "iso:country":"US",
    "sg:address":"105 E Genie St",
    "sg:city":"Chalmette",
    "sg:classifiers":[
        {
            "category":"Autos & Motor Vehicles",
            "subcategory":"Auto Supplies",
            "type":"Retail Goods"
        }
    ],
    "sg:phone":"+1 504 277 7518",
    "sg:postcode":"70043",
    "sg:province":"LA",
    "sg:tags":[
        "tire"
    ],
    "wof:name":"Discount Tire City Inc",
    "wof:placetype":"venue"
},
  "geometry": {"coordinates":[-89.9589,29.9524],"type":"Point"}
}