{
  "type": "Feature",
  "properties": {
    "iso:country":"US",
    "sg:address":"3640 Airline Dr",
    "sg:city":"Metairie",
    "sg:classifiers":[
        {
            "category":"Retail",
            "subcategory":"Laundry & Dry Cleaning",
            "type":"Services"
        }
    ],
    "sg:phone":"+1 504 832 0024",
    "sg:postcode":"70001",
    "sg:province":"LA",
    "sg:tags":[
        "cleaners"
    ],
    "wof:name":"Airline Premier Dry Cleaners",
    "wof:placetype":"venue"
},
  "geometry": {"coordinates":[-90.166166,29.975004],"type":"Point"}
}