{
  "type": "Feature",
  "properties": {
    "iso:country":"US",
    "sg:address":"6104 Line Ave",
    "sg:city":"Shreveport",
    "sg:classifiers":[
        {
            "category":"Restaurant",
            "type":"Food & Drink"
        }
    ],
    "sg:menulink":"http://www.allmenus.com/la/cedar-grove/284538-bistro-byronz/menu/",
    "sg:phone":"+1 318 219 4848",
    "sg:postcode":"71106",
    "sg:province":"LA",
    "sg:tags":[
        "american",
        "southern"
    ],
    "wof:name":"Bistro Byronz",
    "wof:placetype":"venue"
},
  "geometry": {"coordinates":[-93.74601,32.450891],"type":"Point"}
}