{
  "type": "Feature",
  "properties": {
    "iso:country":"US",
    "sg:address":"3328 US Hwy 51",
    "sg:city":"La Place",
    "sg:classifiers":[
        {
            "category":"Education",
            "subcategory":"School",
            "type":"Public Place"
        }
    ],
    "sg:phone":"+1 985 652 2003",
    "sg:postcode":"70068",
    "sg:province":"LA",
    "wof:name":"Glade Middle School",
    "wof:placetype":"venue"
},
  "geometry": {"coordinates":[-90.464873,30.081714],"type":"Point"}
}