{
  "type": "Feature",
  "properties": {
    "iso:country":"US",
    "sg:address":"3712 General Meyer Ave",
    "sg:city":"New Orleans",
    "sg:classifiers":[
        {
            "category":"Retail",
            "subcategory":"Auto Repair",
            "type":"Services"
        }
    ],
    "sg:phone":"+1 504 367 9416",
    "sg:postcode":"70114",
    "sg:province":"LA",
    "wof:name":"Aurora Auto Repair",
    "wof:placetype":"venue"
},
  "geometry": {"coordinates":[-90.017303,29.938101],"type":"Point"}
}