{
  "type": "Feature",
  "properties": {
    "iso:country":"US",
    "sg:address":"3215 Louisville Ave",
    "sg:city":"Monroe",
    "sg:classifiers":[
        {
            "category":"Personal",
            "subcategory":"Barber",
            "type":"Services"
        }
    ],
    "sg:phone":"+1 318 651 8300",
    "sg:postcode":"71201",
    "sg:province":"LA",
    "wof:name":"Anuhtha Level",
    "wof:placetype":"venue"
},
  "geometry": {"coordinates":[-92.08274299999999,32.521855],"type":"Point"}
}