{
  "type": "Feature",
  "properties": {
    "iso:country":"US",
    "sg:address":"252 Magnolia St",
    "sg:city":"Mandeville",
    "sg:classifiers":[
        {
            "category":"Social Services",
            "subcategory":"Child Care",
            "type":"Services"
        }
    ],
    "sg:phone":"+1 985 674 9303",
    "sg:postcode":"70448",
    "sg:province":"LA",
    "sg:tags":[
        "kindergarten",
        "academic",
        "school"
    ],
    "sg:website":"www.kinderhausmontessori.com",
    "wof:name":"Kinder Haus Montessori",
    "wof:placetype":"venue"
},
  "geometry": {"coordinates":[-90.100292,30.373336],"type":"Point"}
}