{
  "type": "Feature",
  "properties": {
    "iso:country":"US",
    "sg:address":"12616 Jefferson Hwy",
    "sg:city":"Baton Rouge",
    "sg:classifiers":[
        {
            "category":"Building & Trades",
            "subcategory":"Construction",
            "type":"Services"
        }
    ],
    "sg:phone":"+1 225 751 5201",
    "sg:postcode":"70816",
    "sg:province":"LA",
    "sg:tags":[
        "resurfacing",
        "laying",
        "refinishing",
        "floor"
    ],
    "wof:name":"Liberty Countertops & Flooring",
    "wof:placetype":"venue"
},
  "geometry": {"coordinates":[-91.043071,30.394355],"type":"Point"}
}