{
  "type": "Feature",
  "properties": {
    "iso:country":"US",
    "sg:address":"701 Superior Ave",
    "sg:city":"Bogalusa",
    "sg:classifiers":[
        {
            "category":"Restaurant",
            "type":"Food & Drink"
        }
    ],
    "sg:phone":"+1 985 735 7277",
    "sg:postcode":"70427",
    "sg:province":"LA",
    "sg:tags":[
        "sandwich"
    ],
    "wof:name":"Deb-N-Odes Sandwich Shop",
    "wof:placetype":"venue"
},
  "geometry": {"coordinates":[-89.87334199999999,30.790639],"type":"Point"}
}