{
  "type": "Feature",
  "properties": {
    "iso:country":"US",
    "sg:address":"11410 Cedar Park Ave",
    "sg:city":"Baton Rouge",
    "sg:classifiers":[
        {
            "category":"Manufacturing",
            "subcategory":"Metals",
            "type":"Manufacturing & Wholesale Goods"
        }
    ],
    "sg:phone":"+1 225 755 0553",
    "sg:postcode":"70809",
    "sg:province":"LA",
    "sg:tags":[
        "coating"
    ],
    "wof:name":"International Paint Inc",
    "wof:placetype":"venue"
},
  "geometry": {"coordinates":[-91.05474700000001,30.389337],"type":"Point"}
}