{
  "type": "Feature",
  "properties": {
    "iso:country":"US",
    "sg:address":"208 S Washington St",
    "sg:city":"Bastrop",
    "sg:classifiers":[
        {
            "category":"Personal",
            "type":"Services"
        }
    ],
    "sg:phone":"+1 318 556 4416",
    "sg:postcode":"71220",
    "sg:province":"LA",
    "sg:tags":[
        "costume"
    ],
    "wof:name":"Sew Crazy Costumes",
    "wof:placetype":"venue"
},
  "geometry": {"coordinates":[-91.914494,32.777199],"type":"Point"}
}