{
  "type": "Feature",
  "properties": {
    "addr:full":"5409 Common St Lake Charles LA 70607",
    "addr:housenumber":"5409",
    "addr:postcode":"70607",
    "addr:street":"Common St",
    "iso:country":"US",
    "sg:address":"5409 Common St",
    "sg:city":"Lake Charles",
    "sg:classifiers":[
        {
            "category":"Shopping",
            "subcategory":"Florist",
            "type":"Retail Goods"
        }
    ],
    "sg:phone":"+1 337 478 8885",
    "sg:postcode":"70607",
    "sg:province":"LA",
    "wof:name":"Tou Les Fleurs",
    "wof:placetype":"venue"
},
  "geometry": {"coordinates":[-93.213712,30.157183],"type":"Point"}
}