{
  "type": "Feature",
  "properties": {
    "iso:country":"US",
    "sg:address":"2800 Manhattan Blvd",
    "sg:city":"Harvey",
    "sg:classifiers":[
        {
            "category":"Personal",
            "subcategory":"Beauty Salon",
            "type":"Services"
        }
    ],
    "sg:phone":"+1 504 365 7005",
    "sg:postcode":"70058",
    "sg:province":"LA",
    "wof:name":"Salon Centro",
    "wof:placetype":"venue"
},
  "geometry": {"coordinates":[-90.04821800000001,29.870899],"type":"Point"}
}