{
  "type": "Feature",
  "properties": {
    "iso:country":"US",
    "sg:address":"1812 Kirkman St",
    "sg:city":"Lake Charles",
    "sg:classifiers":[
        {
            "category":"Real Estate",
            "subcategory":"Real Estate Agent",
            "type":"Services"
        }
    ],
    "sg:phone":"+1 337 436 0000",
    "sg:postcode":"70601",
    "sg:province":"LA",
    "wof:name":"Corporate Commercial Proprties",
    "wof:placetype":"venue"
},
  "geometry": {"coordinates":[-93.209889,30.214336],"type":"Point"}
}