{
  "type": "Feature",
  "properties": {
    "addr:full":"4501 US Hwy 90 New Iberia LA 70560",
    "addr:housenumber":"4501",
    "addr:postcode":"70560",
    "addr:street":"Us Hwy 90",
    "iso:country":"US",
    "sg:address":"4501 US Hwy 90",
    "sg:city":"New Iberia",
    "sg:classifiers":[
        {
            "category":"Real Estate",
            "subcategory":"Surveying",
            "type":"Services"
        }
    ],
    "sg:phone":"+1 337 367 1741",
    "sg:postcode":"70560",
    "sg:province":"LA",
    "sg:tags":[
        "surveyor"
    ],
    "wof:name":"C H Fenstermaker & Assoc",
    "wof:placetype":"venue"
},
  "geometry": {"coordinates":[-91.90748600000001,30.016826],"type":"Point"}
}