{
  "type": "Feature",
  "properties": {
    "iso:country":"US",
    "sg:address":"5610 US Hwy 84",
    "sg:city":"Vidalia",
    "sg:classifiers":[
        {
            "category":"Mining & Drilling",
            "type":"Manufacturing & Wholesale Goods"
        }
    ],
    "sg:phone":"+1 318 757 3274",
    "sg:postcode":"71373",
    "sg:province":"LA",
    "sg:tags":[
        "oil",
        "well"
    ],
    "wof:name":"D & D Drilling & Exploration",
    "wof:placetype":"venue"
},
  "geometry": {"coordinates":[-91.518456,31.603889],"type":"Point"}
}