{
  "type": "Feature",
  "properties": {
    "addr:full":"504 N Foote Ave Kaplan LA 70548",
    "addr:housenumber":"504",
    "addr:postcode":"70548",
    "addr:street":"N Foote Ave Kaplan La",
    "iso:country":"US",
    "sg:address":"504 N Foote Ave",
    "sg:city":"Kaplan",
    "sg:classifiers":[
        {
            "category":"Building & Trades",
            "subcategory":"Plumbing",
            "type":"Services"
        }
    ],
    "sg:phone":"+1 337 643 2645",
    "sg:postcode":"70548",
    "sg:province":"LA",
    "sg:tags":[
        "conditioning",
        "air",
        "system",
        "contractor"
    ],
    "wof:name":"Matthew's AC & Heating Inc",
    "wof:placetype":"venue"
},
  "geometry": {"coordinates":[-92.29577500000001,30.006112],"type":"Point"}
}