{
  "type": "Feature",
  "properties": {
    "iso:country":"US",
    "sg:address":"4624 Cypress St",
    "sg:city":"West Monroe",
    "sg:classifiers":[
        {
            "category":"Shopping",
            "subcategory":"Clothing, Apparel, & Fashions",
            "type":"Retail Goods"
        }
    ],
    "sg:phone":"+1 318 396 2396",
    "sg:postcode":"71291",
    "sg:province":"LA",
    "wof:name":"Pa Mela's",
    "wof:placetype":"venue"
},
  "geometry": {"coordinates":[-92.178145,32.5141],"type":"Point"}
}