{
  "type": "Feature",
  "properties": {
    "iso:country":"US",
    "sg:address":"808 E 1st St",
    "sg:city":"Deridder",
    "sg:classifiers":[
        {
            "category":"Insurance",
            "subcategory":"Insurance Agent",
            "type":"Services"
        }
    ],
    "sg:phone":"+1 337 462 5000",
    "sg:postcode":"70634",
    "sg:province":"LA",
    "wof:name":"Louisiana Low Cost Auto Ins",
    "wof:placetype":"venue"
},
  "geometry": {"coordinates":[-93.27104799999999,30.846805],"type":"Point"}
}