{
  "type": "Feature",
  "properties": {
    "addr:full":"11200 Florida Blvd Walker LA 70785",
    "addr:housenumber":"11200",
    "addr:postcode":"70785",
    "addr:street":"Florida Blvd",
    "iso:country":"US",
    "sg:address":"11200 Florida Blvd",
    "sg:city":"Walker",
    "sg:classifiers":[
        {
            "category":"Autos & Motor Vehicles",
            "subcategory":"Automobile Sales",
            "type":"Retail Goods"
        }
    ],
    "sg:phone":"+1 225 791 2674",
    "sg:postcode":"70785",
    "sg:province":"LA",
    "sg:tags":[
        "car",
        "dealer"
    ],
    "wof:name":"Davis Jones Used Trucks & Cars",
    "wof:placetype":"venue"
},
  "geometry": {"coordinates":[-90.901869,30.48398],"type":"Point"}
}