{
  "type": "Feature",
  "properties": {
    "iso:country":"US",
    "sg:address":"705 River Oaks Dr",
    "sg:city":"Covington",
    "sg:classifiers":[
        {
            "category":"Insurance",
            "subcategory":"Insurance Agent",
            "type":"Services"
        }
    ],
    "sg:phone":"+1 985 809 0200",
    "sg:postcode":"70433",
    "sg:province":"LA",
    "wof:name":"Pro-Equity Inc",
    "wof:placetype":"venue"
},
  "geometry": {"coordinates":[-90.085604,30.42566],"type":"Point"}
}