{
  "type": "Feature",
  "properties": {
    "addr:full":"1037 US Hwy 171 Stonewall LA 71078",
    "addr:housenumber":"1037",
    "addr:postcode":"71078",
    "addr:street":"Us Hwy 171",
    "iso:country":"US",
    "sg:address":"1037 US Hwy 171",
    "sg:city":"Stonewall",
    "sg:classifiers":[
        {
            "category":"Restaurant",
            "type":"Food & Drink"
        }
    ],
    "sg:phone":"+1 318 925 4191",
    "sg:postcode":"71078",
    "sg:province":"LA",
    "wof:name":"Snack Shack",
    "wof:placetype":"venue"
},
  "geometry": {"coordinates":[-93.826596,32.293071],"type":"Point"}
}