{
  "type": "Feature",
  "properties": {
    "addr:full":"2111 Houston St Alexandria LA 71301",
    "addr:housenumber":"2111",
    "addr:postcode":"71301",
    "addr:street":"Houston St",
    "iso:country":"US",
    "sg:address":"2111 Houston St",
    "sg:city":"Alexandria",
    "sg:classifiers":[
        {
            "category":"Organizations",
            "subcategory":"Religious Organization",
            "type":"Services"
        }
    ],
    "sg:phone":"+1 318 443 6860",
    "sg:postcode":"71301",
    "sg:province":"LA",
    "sg:tags":[
        "church"
    ],
    "wof:name":"Gospel Temple Church Of God",
    "wof:placetype":"venue"
},
  "geometry": {"coordinates":[-92.446031,31.295485],"type":"Point"}
}