{
  "type": "Feature",
  "properties": {
    "iso:country":"US",
    "sg:address":"500 Lake Marina Ave",
    "sg:city":"New Orleans",
    "sg:classifiers":[
        {
            "category":"Professional",
            "subcategory":"Lawyer & Legal Services",
            "type":"Services"
        }
    ],
    "sg:phone":"+1 504 288 2800",
    "sg:postcode":"70124",
    "sg:province":"LA",
    "sg:tags":[
        "attorney"
    ],
    "wof:name":"Harry J Boyer",
    "wof:placetype":"venue"
},
  "geometry": {"coordinates":[-90.120073,30.02124],"type":"Point"}
}