{
  "type": "Feature",
  "properties": {
    "addr:full":"300 Pere Megret St Abbeville LA 70511",
    "addr:housenumber":"300",
    "addr:postcode":"70511",
    "addr:street":"Pere Megret St",
    "iso:country":"US",
    "sg:address":"300 Pere Megret St",
    "sg:city":"Abbeville",
    "sg:classifiers":[
        {
            "category":"Organizations",
            "subcategory":"Religious Organization",
            "type":"Services"
        }
    ],
    "sg:phone":"+1 337 893 0244",
    "sg:postcode":"70511",
    "sg:province":"LA",
    "sg:tags":[
        "church"
    ],
    "sg:website":"www.stmarymagdalenparish.org",
    "wof:name":"St Mary Magdalen Church",
    "wof:placetype":"venue"
},
  "geometry": {"coordinates":[-92.13838699999999,29.974619],"type":"Point"}
}