{
  "type": "Feature",
  "properties": {
    "iso:country":"US",
    "sg:address":"1291 Florida Ave SW",
    "sg:city":"Denham Springs",
    "sg:classifiers":[
        {
            "category":"Health Services",
            "subcategory":"Doctor",
            "type":"Services"
        }
    ],
    "sg:phone":"+1 225 664 4118",
    "sg:postcode":"70726",
    "sg:province":"LA",
    "sg:tags":[
        "dentist"
    ],
    "wof:name":"Joseph A De Paula DDS",
    "wof:placetype":"venue"
},
  "geometry": {"coordinates":[-90.963471,30.472899],"type":"Point"}
}