{
  "type": "Feature",
  "properties": {
    "addr:full":"1901 Westbank Expy Harvey LA 70058",
    "addr:housenumber":"1901",
    "addr:postcode":"70058",
    "addr:street":"Westbank Expy Harvey",
    "iso:country":"US",
    "sg:address":"1901 Westbank Expy",
    "sg:city":"Harvey",
    "sg:classifiers":[
        {
            "category":"Organizations",
            "subcategory":"Non-profit Organization",
            "type":"Services"
        }
    ],
    "sg:phone":"+1 504 362 9461",
    "sg:postcode":"70058",
    "sg:province":"LA",
    "sg:tags":[
        "handicapped"
    ],
    "wof:name":"Access Vans-Louisiana New",
    "wof:placetype":"venue"
},
  "geometry": {"coordinates":[-90.073791,29.900091],"type":"Point"}
}