{
  "type": "Feature",
  "properties": {
    "addr:full":"4015 Moss St Lafayette LA 70507",
    "addr:postcode":"4015;70507",
    "addr:street":"Moss St",
    "iso:country":"US",
    "sg:address":"4015 Moss St",
    "sg:city":"Lafayette",
    "sg:classifiers":[
        {
            "category":"Organizations",
            "subcategory":"Religious Organization",
            "type":"Services"
        }
    ],
    "sg:phone":"+1 337 269 0976",
    "sg:postcode":"70507",
    "sg:province":"LA",
    "sg:tags":[
        "church"
    ],
    "wof:name":"Calvary Baptist Church",
    "wof:placetype":"venue"
},
  "geometry": {"coordinates":[-92.007313,30.281862],"type":"Point"}
}