{
  "type": "Feature",
  "properties": {
    "iso:country":"US",
    "sg:address":"1061 Capitol Ave",
    "sg:city":"Crowley",
    "sg:classifiers":[
        {
            "category":"Government",
            "subcategory":"Police Station",
            "type":"Public Place"
        }
    ],
    "sg:phone":"+1 337 788 8740",
    "sg:postcode":"70526",
    "sg:province":"LA",
    "sg:tags":[
        "protection"
    ],
    "wof:name":"Acadia Parish Detention",
    "wof:placetype":"venue"
},
  "geometry": {"coordinates":[-92.400305,30.211401],"type":"Point"}
}