{
  "type": "Feature",
  "properties": {
    "iso:country":"US",
    "sg:address":"1231 Skokie Dr",
    "sg:city":"Ruston",
    "sg:classifiers":[
        {
            "category":"Insurance",
            "subcategory":"Insurance Agent",
            "type":"Services"
        }
    ],
    "sg:phone":"+1 318 254 2981",
    "sg:postcode":"71270",
    "sg:province":"LA",
    "wof:name":"American Interstate Insur Co",
    "wof:placetype":"venue"
},
  "geometry": {"coordinates":[-92.661027,32.516218],"type":"Point"}
}