{
  "type": "Feature",
  "properties": {
    "iso:country":"US",
    "sg:address":"202 Magnate Dr",
    "sg:city":"Lafayette",
    "sg:classifiers":[
        {
            "category":"Professional",
            "subcategory":"Lawyer & Legal Services",
            "type":"Services"
        }
    ],
    "sg:phone":"+1 337 235 2425",
    "sg:postcode":"70508",
    "sg:province":"LA",
    "sg:tags":[
        "attorney"
    ],
    "wof:name":"Rush Rush & Calogero",
    "wof:placetype":"venue"
},
  "geometry": {"coordinates":[-92.010127,30.18265],"type":"Point"}
}