{
  "type": "Feature",
  "properties": {
    "iso:country":"US",
    "sg:address":"7731 Office Park Blvd",
    "sg:city":"Baton Rouge",
    "sg:classifiers":[
        {
            "category":"Professional",
            "subcategory":"Business Services",
            "type":"Services"
        }
    ],
    "sg:phone":"+1 225 295 1200",
    "sg:postcode":"70809",
    "sg:province":"LA",
    "sg:tags":[
        "water",
        "treatment"
    ],
    "sg:website":"www.etec-sales.com",
    "wof:name":"Environmental Technical Sales",
    "wof:placetype":"venue"
},
  "geometry": {"coordinates":[-91.10349100000001,30.41921],"type":"Point"}
}