{
  "type": "Feature",
  "properties": {
    "addr:full":"5454 Bluebonnet Rd Baton Rouge LA 70809",
    "addr:housenumber":"5454",
    "addr:postcode":"70809",
    "addr:street":"Bluebonnet Rd",
    "iso:country":"US",
    "sg:address":"5454 Bluebonnet Rd",
    "sg:city":"Baton Rouge",
    "sg:classifiers":[
        {
            "category":"Banks & Credit Unions",
            "subcategory":"Bank",
            "type":"Services"
        }
    ],
    "sg:phone":"+1 225 295 7028",
    "sg:postcode":"70809",
    "sg:province":"LA",
    "sg:tags":[
        "financing"
    ],
    "wof:name":"Citi Financial",
    "wof:placetype":"venue"
},
  "geometry": {"coordinates":[-91.084395,30.400122],"type":"Point"}
}