{
  "type": "Feature",
  "properties": {
    "iso:country":"US",
    "sg:address":"205 Venture Blvd",
    "sg:city":"Houma",
    "sg:classifiers":[
        {
            "category":"Wholesale",
            "subcategory":"Electrical",
            "type":"Manufacturing & Wholesale Goods"
        }
    ],
    "sg:phone":"+1 985 868 0430",
    "sg:postcode":"70360",
    "sg:province":"LA",
    "sg:tags":[
        "battery"
    ],
    "wof:name":"Fleet Supply Warehouse Inc",
    "wof:placetype":"venue"
},
  "geometry": {"coordinates":[-90.76447899999999,29.595665],"type":"Point"}
}