{
  "type": "Feature",
  "properties": {
    "addr:full":"2180 N Causeway Blvd Mandeville LA 70471",
    "addr:housenumber":"2180",
    "addr:postcode":"70471",
    "addr:street":"N Causeway Blvd",
    "iso:country":"US",
    "sg:address":"2180 N Causeway Blvd",
    "sg:city":"Mandeville",
    "sg:classifiers":[
        {
            "category":"Personal",
            "subcategory":"Tanning Parlor",
            "type":"Services"
        }
    ],
    "sg:phone":"+1 985 674 2326",
    "sg:postcode":"70471",
    "sg:province":"LA",
    "sg:tags":[
        "salon"
    ],
    "wof:name":"Private Beach Travel",
    "wof:placetype":"venue"
},
  "geometry": {"coordinates":[-90.09065,30.38344],"type":"Point"}
}