{
  "type": "Feature",
  "properties": {
    "iso:country":"US",
    "sg:address":"6007 Financial Plz",
    "sg:city":"Shreveport",
    "sg:classifiers":[
        {
            "category":"Utilities",
            "subcategory":"Telephone",
            "type":"Services"
        }
    ],
    "sg:phone":"+1 318 687 7600",
    "sg:postcode":"71129",
    "sg:province":"LA",
    "sg:tags":[
        "telecommunication"
    ],
    "wof:name":"Vision Voice & Data",
    "wof:placetype":"venue"
},
  "geometry": {"coordinates":[-93.858204,32.451437],"type":"Point"}
}