{
  "type": "Feature",
  "properties": {
    "iso:country":"US",
    "sg:address":"7801 Earhart Blvd",
    "sg:city":"New Orleans",
    "sg:classifiers":[
        {
            "category":"Retail",
            "subcategory":"Auto Repair",
            "type":"Services"
        }
    ],
    "sg:phone":"+1 504 488 8726",
    "sg:postcode":"70125",
    "sg:province":"LA",
    "sg:tags":[
        "transmission"
    ],
    "wof:name":"Cottman Transmission Ctr",
    "wof:placetype":"venue"
},
  "geometry": {"coordinates":[-90.11315999999999,29.959877],"type":"Point"}
}