{
  "type": "Feature",
  "properties": {
    "iso:country":"US",
    "sg:address":"1101 W Pinhook Rd",
    "sg:city":"Lafayette",
    "sg:classifiers":[
        {
            "category":"Travel",
            "subcategory":"Hotels & Motels",
            "type":"Entertainment"
        }
    ],
    "sg:phone":"+1 337 234 7402",
    "sg:postcode":"70503",
    "sg:province":"LA",
    "sg:tags":[
        "operation"
    ],
    "sg:website":"www.travelodge.com",
    "wof:name":"Travelodge",
    "wof:placetype":"venue"
},
  "geometry": {"coordinates":[-92.01418099999999,30.203017],"type":"Point"}
}