{
  "type": "Feature",
  "properties": {
    "iso:country":"US",
    "sg:address":"4313 Emory St",
    "sg:city":"Shreveport",
    "sg:classifiers":[
        {
            "category":"Manufacturing",
            "subcategory":"Tools & Machinery",
            "type":"Manufacturing & Wholesale Goods"
        }
    ],
    "sg:phone":"+1 318 938 7424",
    "sg:postcode":"71109",
    "sg:province":"LA",
    "sg:tags":[
        "polishing",
        "car",
        "washing",
        "equipment"
    ],
    "wof:name":"Pro Car Products",
    "wof:placetype":"venue"
},
  "geometry": {"coordinates":[-93.809816,32.469529],"type":"Point"}
}