{
  "type": "Feature",
  "properties": {
    "addr:full":"809 N Trenton St Ruston LA 71270",
    "addr:housenumber":"809",
    "addr:postcode":"71270",
    "addr:street":"N Trenton St",
    "iso:country":"US",
    "sg:address":"809 N Trenton St",
    "sg:city":"Ruston",
    "sg:classifiers":[
        {
            "category":"Utilities",
            "subcategory":"Mobile Phone",
            "type":"Services"
        }
    ],
    "sg:phone":"+1 318 255 8797",
    "sg:postcode":"71270",
    "sg:province":"LA",
    "sg:tags":[
        "telephone",
        "cellular"
    ],
    "wof:name":"Alltel",
    "wof:placetype":"venue"
},
  "geometry": {"coordinates":[-92.639185,32.536395],"type":"Point"}
}