{
  "type": "Feature",
  "properties": {
    "iso:country":"US",
    "sg:address":"105 Shelburn Cir",
    "sg:city":"Lafayette",
    "sg:classifiers":[
        {
            "category":"Building & Trades",
            "subcategory":"Landscaping Services",
            "type":"Services"
        }
    ],
    "sg:phone":"+1 337 981 7543",
    "sg:postcode":"70508",
    "sg:province":"LA",
    "sg:tags":[
        "landscape"
    ],
    "wof:name":"Adams Landscape Mant",
    "wof:placetype":"venue"
},
  "geometry": {"coordinates":[-92.02641800000001,30.15047],"type":"Point"}
}