{
  "type": "Feature",
  "properties": {
    "addr:full":"24100 Carl Hoppe Rd Iowa LA 70647",
    "addr:housenumber":"24100",
    "addr:postcode":"70647",
    "addr:street":"Carl Hoppe Rd",
    "iso:country":"US",
    "sg:address":"24100 Carl Hoppe Rd",
    "sg:city":"Iowa",
    "sg:classifiers":[
        {
            "category":"Wholesale",
            "subcategory":"Stationery",
            "type":"Manufacturing & Wholesale Goods"
        }
    ],
    "sg:phone":"+1 337 582 4357",
    "sg:postcode":"70647",
    "sg:province":"LA",
    "sg:tags":[
        "business",
        "form",
        "system"
    ],
    "wof:name":"Capital Tax & Accounting",
    "wof:placetype":"venue"
},
  "geometry": {"coordinates":[-93.027967,30.320192],"type":"Point"}
}