{
  "type": "Feature",
  "properties": {
    "iso:country":"US",
    "sg:address":"110 Keating Dr",
    "sg:city":"Belle Chasse",
    "sg:classifiers":[
        {
            "category":"Building & Trades",
            "subcategory":"Construction",
            "type":"Services"
        }
    ],
    "sg:phone":"+1 504 393 7777",
    "sg:postcode":"70037",
    "sg:province":"LA",
    "sg:tags":[
        "home",
        "builder",
        "contractor"
    ],
    "wof:name":"Morse Homes Inc",
    "wof:placetype":"venue"
},
  "geometry": {"coordinates":[-89.98539700000001,29.8999],"type":"Point"}
}