{
  "type": "Feature",
  "properties": {
    "iso:country":"US",
    "sg:address":"5953 W Park Ave",
    "sg:city":"Houma",
    "sg:classifiers":[
        {
            "category":"Shopping",
            "subcategory":"Shoes",
            "type":"Retail Goods"
        }
    ],
    "sg:phone":"+1 985 853 1950",
    "sg:postcode":"70364",
    "sg:province":"LA",
    "wof:name":"On Time Fashion Inc",
    "wof:placetype":"venue"
},
  "geometry": {"coordinates":[-90.76353,29.64989],"type":"Point"}
}