{
  "type": "Feature",
  "properties": {
    "iso:country":"US",
    "sg:address":"6219 E Texas St",
    "sg:city":"Bossier City",
    "sg:classifiers":[
        {
            "category":"Manufacturing",
            "subcategory":"Retail Goods",
            "type":"Manufacturing & Wholesale Goods"
        }
    ],
    "sg:phone":"+1 318 746 5709",
    "sg:postcode":"71111",
    "sg:province":"LA",
    "sg:tags":[
        "product",
        "merchandise",
        "mfg"
    ],
    "wof:name":"Henrietta Redman Stewart",
    "wof:placetype":"venue"
},
  "geometry": {"coordinates":[-93.650248,32.540751],"type":"Point"}
}