{
  "type": "Feature",
  "properties": {
    "addr:full":"7064 Siegen Ln Baton Rouge LA 70809",
    "addr:housenumber":"7064",
    "addr:postcode":"70809",
    "addr:street":"Siegen Ln",
    "iso:country":"US",
    "sg:address":"7064 Siegen Ln",
    "sg:city":"Baton Rouge",
    "sg:classifiers":[
        {
            "category":"Education",
            "subcategory":"Special Training",
            "type":"Public Place"
        }
    ],
    "sg:phone":"+1 225 291 7323",
    "sg:postcode":"70809",
    "sg:province":"LA",
    "sg:tags":[
        "tutoring"
    ],
    "sg:website":"www.educate.com",
    "wof:name":"Sylvan Learning Ctr",
    "wof:placetype":"venue"
},
  "geometry": {"coordinates":[-91.063982,30.385901],"type":"Point"}
}