{
  "type": "Feature",
  "properties": {
    "iso:country":"US",
    "sg:address":"1119 Carter St",
    "sg:city":"Vidalia",
    "sg:classifiers":[
        {
            "category":"Restaurant",
            "type":"Food & Drink"
        }
    ],
    "sg:menulink":"http://www.allmenus.com/la/minorca/201549-sonic/menu/",
    "sg:phone":"+1 318 336 3663",
    "sg:postcode":"71373",
    "sg:province":"LA",
    "sg:tags":[
        "burger",
        "american"
    ],
    "wof:name":"Sonic",
    "wof:placetype":"venue"
},
  "geometry": {"coordinates":[-91.43616,31.569461],"type":"Point"}
}