{
  "type": "Feature",
  "properties": {
    "iso:country":"US",
    "sg:address":"100 E Pont Des Mouton Rd",
    "sg:city":"Lafayette",
    "sg:classifiers":[
        {
            "category":"Autos & Motor Vehicles",
            "subcategory":"Fuel & Gas Station",
            "type":"Retail Goods"
        },
        {
            "category":"Food & Beverages",
            "subcategory":"Groceries & Convenience Stores",
            "type":"Retail Goods"
        }
    ],
    "sg:phone":"+1 337 232 6617",
    "sg:postcode":"70507",
    "sg:province":"LA",
    "wof:name":"Chiassons'corner Mart",
    "wof:placetype":"venue"
},
  "geometry": {"coordinates":[-92.0168,30.2733],"type":"Point"}
}