{
  "type": "Feature",
  "properties": {
    "iso:country":"US",
    "sg:address":"4509 Hastings St",
    "sg:city":"Metairie",
    "sg:classifiers":[
        {
            "category":"Shopping",
            "subcategory":"Clothing, Apparel, & Fashions",
            "type":"Retail Goods"
        }
    ],
    "sg:phone":"+1 504 779 1761",
    "sg:postcode":"70006",
    "sg:province":"LA",
    "wof:name":"Mona Clothing",
    "wof:placetype":"venue"
},
  "geometry": {"coordinates":[-90.187248,30.013288],"type":"Point"}
}