{
  "type": "Feature",
  "properties": {
    "iso:country":"US",
    "sg:address":"45500 Puma Dr",
    "sg:city":"Hammond",
    "sg:classifiers":[
        {
            "category":"Building & Trades",
            "subcategory":"Electrical",
            "type":"Services"
        }
    ],
    "sg:phone":"+1 985 345 8583",
    "sg:postcode":"70401",
    "sg:province":"LA",
    "sg:tags":[
        "electric",
        "contractor"
    ],
    "wof:name":"A/C Power Electric & Generator",
    "wof:placetype":"venue"
},
  "geometry": {"coordinates":[-90.50103900000001,30.516254],"type":"Point"}
}