{
  "type": "Feature",
  "properties": {
    "addr:full":"911 S Union St Opelousas LA 70570",
    "addr:housenumber":"911",
    "addr:postcode":"70570",
    "addr:street":"S Union St",
    "iso:country":"US",
    "sg:address":"911 S Union St",
    "sg:city":"Opelousas",
    "sg:classifiers":[
        {
            "category":"Autos & Motor Vehicles",
            "subcategory":"Auto Supplies",
            "type":"Retail Goods"
        }
    ],
    "sg:phone":"+1 337 942 6153",
    "sg:postcode":"70570",
    "sg:province":"LA",
    "sg:tags":[
        "automobile",
        "parts"
    ],
    "wof:name":"O'Reilly Auto Parts",
    "wof:placetype":"venue"
},
  "geometry": {"coordinates":[-92.082329,30.525371],"type":"Point"}
}