{
  "type": "Feature",
  "properties": {
    "iso:country":"US",
    "sg:address":"2772 Old Hwy 90",
    "sg:city":"Vinton",
    "sg:classifiers":[
        {
            "category":"Organizations",
            "subcategory":"Community Association",
            "type":"Services"
        }
    ],
    "sg:phone":"+1 337 589 6003",
    "sg:postcode":"70668",
    "sg:province":"LA",
    "sg:tags":[
        "club"
    ],
    "sg:website":"www.themarshclub.com",
    "wof:name":"Marsh Club",
    "wof:placetype":"venue"
},
  "geometry": {"coordinates":[-93.652779,30.123559],"type":"Point"}
}