{
  "type": "Feature",
  "properties": {
    "iso:country":"US",
    "sg:address":"70345 Highway 21",
    "sg:city":"Covington",
    "sg:classifiers":[
        {
            "category":"Restaurant",
            "type":"Food & Drink"
        }
    ],
    "sg:menulink":"http://www.allmenus.com/la/madisonville/188297-mcdonalds/menu/",
    "sg:postcode":"70433",
    "sg:province":"LA",
    "sg:tags":[
        "burger",
        "american"
    ],
    "wof:name":"McDonald's",
    "wof:placetype":"venue"
},
  "geometry": {"coordinates":[-90.13735,30.451028],"type":"Point"}
}