{
  "type": "Feature",
  "properties": {
    "iso:country":"US",
    "sg:address":"4524 Senac Dr",
    "sg:city":"Metairie",
    "sg:classifiers":[
        {
            "category":"Freight",
            "type":"Transportation"
        }
    ],
    "sg:phone":"+1 504 888 8228",
    "sg:postcode":"70003",
    "sg:province":"LA",
    "wof:name":"Southern Cross Shipping Co",
    "wof:placetype":"venue"
},
  "geometry": {"coordinates":[-90.220009,30.020686],"type":"Point"}
}