{
  "type": "Feature",
  "properties": {
    "addr:full":"2801 Northside Dr Bossier City LA 71111",
    "addr:housenumber":"2801",
    "addr:postcode":"71111",
    "addr:street":"Northside Dr",
    "iso:country":"US",
    "sg:address":"2801 Northside Dr",
    "sg:city":"Bossier City",
    "sg:classifiers":[
        {
            "category":"Banks & Credit Unions",
            "subcategory":"Bank",
            "type":"Services"
        }
    ],
    "sg:phone":"+1 318 747 7999",
    "sg:postcode":"71111",
    "sg:province":"LA",
    "sg:tags":[
        "loan",
        "real estate"
    ],
    "wof:name":"Home Town Mortgage",
    "wof:placetype":"venue"
},
  "geometry": {"coordinates":[-93.709087,32.539062],"type":"Point"}
}