{
  "type": "Feature",
  "properties": {
    "addr:full":"1440 Dorchester Dr Alexandria LA 71301",
    "addr:housenumber":"1440",
    "addr:postcode":"71301",
    "addr:street":"Dorchester Dr",
    "iso:country":"US",
    "sg:address":"1440 Dorchester Dr",
    "sg:city":"Alexandria",
    "sg:classifiers":[
        {
            "category":"Banks & Credit Unions",
            "subcategory":"Bank",
            "type":"Services"
        }
    ],
    "sg:phone":"+1 318 484 4797",
    "sg:postcode":"71301",
    "sg:province":"LA",
    "sg:website":"www.regions.com",
    "wof:name":"Regions",
    "wof:placetype":"venue"
},
  "geometry": {"coordinates":[-92.477841,31.28212],"type":"Point"}
}