{
  "type": "Feature",
  "properties": {
    "iso:country":"US",
    "sg:address":"640 A O Rappelet Rd",
    "sg:city":"Golden Meadow",
    "sg:classifiers":[
        {
            "category":"Autos & Motor Vehicles",
            "subcategory":"Fuel & Gas Station",
            "type":"Retail Goods"
        }
    ],
    "sg:phone":"+1 985 396 8550",
    "sg:postcode":"70357",
    "sg:province":"LA",
    "sg:tags":[
        "plaza",
        "truck",
        "stops"
    ],
    "wof:name":"Kajun Truck Plaza",
    "wof:placetype":"venue"
},
  "geometry": {"coordinates":[-90.19468500000001,29.121192],"type":"Point"}
}