{
  "type": "Feature",
  "properties": {
    "iso:country":"US",
    "sg:address":"3225 Pontchartrain Dr",
    "sg:city":"Slidell",
    "sg:classifiers":[
        {
            "category":"Restaurant",
            "type":"Food & Drink"
        }
    ],
    "sg:menulink":"http://www.allmenus.com/la/slidell/201433-sonic/menu/",
    "sg:phone":"+1 985 643 3671",
    "sg:postcode":"70458",
    "sg:province":"LA",
    "sg:tags":[
        "burger",
        "american"
    ],
    "wof:name":"Sonic",
    "wof:placetype":"venue"
},
  "geometry": {"coordinates":[-89.786676,30.260156],"type":"Point"}
}