{
  "type": "Feature",
  "properties": {
    "addr:full":"203 Marquette St New Iberia LA 70563",
    "addr:housenumber":"203",
    "addr:postcode":"70563",
    "addr:street":"Marquette St",
    "iso:country":"US",
    "sg:address":"203 Marquette St",
    "sg:city":"New Iberia",
    "sg:classifiers":[
        {
            "category":"Professional",
            "type":"Services"
        }
    ],
    "sg:phone":"+1 337 365 5327",
    "sg:postcode":"70563",
    "sg:province":"LA",
    "wof:name":"Woodys Trk Inc",
    "wof:placetype":"venue"
},
  "geometry": {"coordinates":[-91.79808,29.999339],"type":"Point"}
}