{
  "type": "Feature",
  "properties": {
    "iso:country":"US",
    "sg:address":"151 3rd St",
    "sg:city":"Baton Rouge",
    "sg:classifiers":[
        {
            "category":"Restaurant",
            "type":"Food & Drink"
        }
    ],
    "sg:menulink":"http://www.allmenus.com/la/baton-rouge/271484-dagostinos-restaurant/menu/",
    "sg:phone":"+1 225 379 8587",
    "sg:postcode":"70801",
    "sg:province":"LA",
    "sg:tags":[
        "italian"
    ],
    "wof:name":"D'Agostino's Restaurant",
    "wof:placetype":"venue"
},
  "geometry": {"coordinates":[-91.18849299999999,30.447872],"type":"Point"}
}