{
  "type": "Feature",
  "properties": {
    "iso:country":"US",
    "sg:address":"512 W Convent St",
    "sg:city":"Lafayette",
    "sg:classifiers":[
        {
            "category":"Professional",
            "subcategory":"Business Services",
            "type":"Services"
        }
    ],
    "sg:phone":"+1 337 234 2427",
    "sg:postcode":"70501",
    "sg:province":"LA",
    "sg:tags":[
        "appraiser"
    ],
    "sg:website":"www.cbtalley.com",
    "wof:name":"C B Talley Real Estate",
    "wof:placetype":"venue"
},
  "geometry": {"coordinates":[-92.02405899999999,30.22121],"type":"Point"}
}