{
  "type": "Feature",
  "properties": {
    "iso:country":"US",
    "sg:address":"1100 Wright Ave",
    "sg:city":"Terrytown",
    "sg:classifiers":[
        {
            "category":"Shopping",
            "type":"Retail Goods"
        }
    ],
    "sg:phone":"+1 504 393 2026",
    "sg:postcode":"70056",
    "sg:province":"LA",
    "sg:tags":[
        "monument"
    ],
    "wof:name":"Alfortish Cast Stone Products",
    "wof:placetype":"venue"
},
  "geometry": {"coordinates":[-90.038083,29.898675],"type":"Point"}
}