{
  "type": "Feature",
  "properties": {
    "iso:country":"US",
    "sg:address":"7101 Ivy St",
    "sg:city":"Metairie",
    "sg:classifiers":[
        {
            "category":"Autos & Motor Vehicles",
            "subcategory":"Automobile Sales",
            "type":"Retail Goods"
        }
    ],
    "sg:phone":"+1 504 738 1811",
    "sg:postcode":"70003",
    "sg:province":"LA",
    "sg:tags":[
        "car",
        "dealer"
    ],
    "wof:name":"Bronson Autoplex",
    "wof:placetype":"venue"
},
  "geometry": {"coordinates":[-90.217063,29.974425],"type":"Point"}
}