{
  "type": "Feature",
  "properties": {
    "iso:country":"US",
    "sg:address":"3 Sanctuary Blvd",
    "sg:city":"Mandeville",
    "sg:classifiers":[
        {
            "category":"Professional",
            "subcategory":"Lawyer & Legal Services",
            "type":"Services"
        }
    ],
    "sg:phone":"+1 985 626 4588",
    "sg:postcode":"70471",
    "sg:province":"LA",
    "sg:tags":[
        "attorney"
    ],
    "wof:name":"Donelson Bearman Caldwell",
    "wof:placetype":"venue"
},
  "geometry": {"coordinates":[-90.103966,30.393929],"type":"Point"}
}