{
  "type": "Feature",
  "properties": {
    "iso:country":"US",
    "sg:address":"7317 Meadowpark Ave",
    "sg:city":"Baton Rouge",
    "sg:classifiers":[
        {
            "category":"Professional",
            "type":"Services"
        }
    ],
    "sg:phone":"+1 225 766 1498",
    "sg:postcode":"70810",
    "sg:province":"LA",
    "wof:name":"Hurst Electronics Inc",
    "wof:placetype":"venue"
},
  "geometry": {"coordinates":[-91.07102500000001,30.369401],"type":"Point"}
}