{
  "type": "Feature",
  "properties": {
    "addr:full":"820 Austria Rd Duson LA 70529",
    "addr:housenumber":"820",
    "addr:postcode":"70529",
    "addr:street":"Austria Rd",
    "iso:country":"US",
    "sg:address":"820 Austria Rd",
    "sg:city":"Duson",
    "sg:classifiers":[
        {
            "category":"Personal",
            "subcategory":"Beauty Salon",
            "type":"Services"
        }
    ],
    "sg:phone":"+1 337 873 8200",
    "sg:postcode":"70529",
    "sg:province":"LA",
    "sg:tags":[
        "shop"
    ],
    "wof:name":"Kutting Image By Yvette",
    "wof:placetype":"venue"
},
  "geometry": {"coordinates":[-92.19310900000001,30.234202],"type":"Point"}
}