{
  "type": "Feature",
  "properties": {
    "addr:full":"1501 Opelousas Ave New Orleans LA 70114",
    "addr:housenumber":"1501",
    "addr:postcode":"70114",
    "addr:street":"Opelousas Ave",
    "iso:country":"US",
    "sg:address":"1501 Opelousas Ave",
    "sg:city":"New Orleans",
    "sg:classifiers":[
        {
            "category":"Education",
            "subcategory":"Preschool",
            "type":"Public Place"
        },
        {
            "category":"Education",
            "subcategory":"School",
            "type":"Public Place"
        }
    ],
    "sg:phone":"+1 504 376 8966",
    "sg:postcode":"70114",
    "sg:province":"LA",
    "sg:tags":[
        "elementary"
    ],
    "sg:website":"www.fellowschildrensacademy.com",
    "wof:name":"Fellows Children's Academy",
    "wof:placetype":"venue"
},
  "geometry": {"coordinates":[-90.041918,29.948173],"type":"Point"}
}