{
  "type": "Feature",
  "properties": {
    "addr:full":"263 N Common St Shreveport LA 71101",
    "addr:housenumber":"263",
    "addr:postcode":"71101",
    "addr:street":"N Common",
    "iso:country":"US",
    "sg:address":"263 N Common St",
    "sg:city":"Shreveport",
    "sg:classifiers":[
        {
            "category":"Government",
            "subcategory":"Fire Station",
            "type":"Public Place"
        }
    ],
    "sg:phone":"+1 318 673 6655",
    "sg:postcode":"71101",
    "sg:province":"LA",
    "sg:tags":[
        "department"
    ],
    "wof:name":"Shreveport Fire Chief",
    "wof:placetype":"venue"
},
  "geometry": {"coordinates":[-93.76033099999999,32.521705],"type":"Point"}
}