{
  "type": "Feature",
  "properties": {
    "iso:country":"US",
    "sg:address":"1046 W Tunnel Blvd",
    "sg:city":"Houma",
    "sg:classifiers":[
        {
            "category":"Food & Beverages",
            "subcategory":"Groceries & Convenience Stores",
            "type":"Retail Goods"
        }
    ],
    "sg:phone":"+1 985 223 2246",
    "sg:postcode":"70360",
    "sg:province":"LA",
    "wof:name":"S & T Food Mart",
    "wof:placetype":"venue"
},
  "geometry": {"coordinates":[-90.73591999999999,29.592834],"type":"Point"}
}