{
  "type": "Feature",
  "properties": {
    "iso:country":"US",
    "sg:address":"1825 Orleans Ave",
    "sg:city":"New Orleans",
    "sg:classifiers":[
        {
            "category":"Organizations",
            "subcategory":"Community Association",
            "type":"Services"
        }
    ],
    "sg:phone":"+1 504 821 4225",
    "sg:postcode":"70116",
    "sg:province":"LA",
    "sg:tags":[
        "fraternal"
    ],
    "wof:name":"Knights Of Peter Claver",
    "wof:placetype":"venue"
},
  "geometry": {"coordinates":[-90.07481300000001,29.96557],"type":"Point"}
}