{
  "type": "Feature",
  "properties": {
    "addr:full":"515 Howard St Natchitoches LA 71457",
    "addr:housenumber":"515",
    "addr:postcode":"71457",
    "addr:street":"Howard St",
    "iso:country":"US",
    "sg:address":"515 Howard St",
    "sg:city":"Natchitoches",
    "sg:classifiers":[
        {
            "category":"Building & Trades",
            "subcategory":"Construction",
            "type":"Services"
        }
    ],
    "sg:phone":"+1 318 356 9717",
    "sg:postcode":"71457",
    "sg:province":"LA",
    "sg:tags":[
        "contractor"
    ],
    "wof:name":"Rachal Contracting Inc",
    "wof:placetype":"venue"
},
  "geometry": {"coordinates":[-93.077871,31.762778],"type":"Point"}
}