{
  "type": "Feature",
  "properties": {
    "addr:full":"130 Edgewood Dr Pineville LA 71360",
    "addr:housenumber":"130",
    "addr:postcode":"71360",
    "addr:street":"Edgewood Dr",
    "iso:country":"US",
    "sg:address":"130 Edgewood Dr",
    "sg:city":"Pineville",
    "sg:classifiers":[
        {
            "category":"Autos & Motor Vehicles",
            "subcategory":"Automobile Sales",
            "type":"Retail Goods"
        }
    ],
    "sg:phone":"+1 318 561 6373",
    "sg:postcode":"71360",
    "sg:province":"LA",
    "sg:tags":[
        "used"
    ],
    "wof:name":"Auto Outlet",
    "wof:placetype":"venue"
},
  "geometry": {"coordinates":[-92.398959,31.335884],"type":"Point"}
}