{
  "type": "Feature",
  "properties": {
    "addr:full":"829 Smith Dr Metairie LA 70005",
    "addr:housenumber":"829",
    "addr:postcode":"70005",
    "addr:street":"Smith Dr",
    "iso:country":"US",
    "sg:address":"829 Smith Dr",
    "sg:city":"Metairie",
    "sg:classifiers":[
        {
            "category":"Manufacturing",
            "subcategory":"Printing",
            "type":"Manufacturing & Wholesale Goods"
        }
    ],
    "sg:phone":"+1 504 835 5093",
    "sg:postcode":"70005",
    "sg:province":"LA",
    "sg:tags":[
        "lithographic",
        "commercial"
    ],
    "wof:name":"Rite-Way Printing Co",
    "wof:placetype":"venue"
},
  "geometry": {"coordinates":[-90.12950600000001,30.009328],"type":"Point"}
}