{
  "type": "Feature",
  "properties": {
    "addr:full":"2156 3rd St Mandeville LA 70471",
    "addr:housenumber":"2156",
    "addr:postcode":"70471",
    "addr:street":"3Rd St",
    "iso:country":"US",
    "sg:address":"2156 3rd St",
    "sg:city":"Mandeville",
    "sg:classifiers":[
        {
            "category":"Social Services",
            "type":"Services"
        }
    ],
    "sg:phone":"+1 985 626 3800",
    "sg:postcode":"70471",
    "sg:province":"LA",
    "sg:tags":[
        "agency",
        "adoption"
    ],
    "wof:name":"Acorn Adoption",
    "wof:placetype":"venue"
},
  "geometry": {"coordinates":[-90.08410600000001,30.397614],"type":"Point"}
}