{
  "type": "Feature",
  "properties": {
    "iso:country":"US",
    "sg:address":"2830 Franklin Ave",
    "sg:city":"New Orleans",
    "sg:classifiers":[
        {
            "category":"Shopping",
            "subcategory":"Bicycles & Sporting Goods",
            "type":"Retail Goods"
        }
    ],
    "sg:phone":"+1 504 669 4602",
    "sg:postcode":"70122",
    "sg:province":"LA",
    "sg:tags":[
        "gun",
        "gunsmith"
    ],
    "wof:name":"B R Machine Works",
    "wof:placetype":"venue"
},
  "geometry": {"coordinates":[-90.04928,29.988034],"type":"Point"}
}