{
  "type": "Feature",
  "properties": {
    "iso:country":"US",
    "sg:address":"1323 12th St",
    "sg:city":"Lake Charles",
    "sg:classifiers":[
        {
            "category":"Personal",
            "subcategory":"Beauty Salon",
            "type":"Services"
        }
    ],
    "sg:phone":"+1 337 436 3096",
    "sg:postcode":"70601",
    "sg:province":"LA",
    "wof:name":"Innovations Hair Design",
    "wof:placetype":"venue"
},
  "geometry": {"coordinates":[-93.203085,30.213289],"type":"Point"}
}