{
  "type": "Feature",
  "properties": {
    "iso:country":"US",
    "sg:address":"1006 N Airline Hwy",
    "sg:city":"Gonzales",
    "sg:classifiers":[
        {
            "category":"Bars & Pubs",
            "type":"Food & Drink"
        }
    ],
    "sg:phone":"+1 225 647 6020",
    "sg:postcode":"70737",
    "sg:province":"LA",
    "sg:tags":[
        "club",
        "night"
    ],
    "wof:name":"New Orleans Original Daiquiris",
    "wof:placetype":"venue"
},
  "geometry": {"coordinates":[-90.915628,30.240621],"type":"Point"}
}