{
  "type": "Feature",
  "properties": {
    "addr:full":"3014 Holiday Dr New Orleans LA 70131",
    "addr:housenumber":"3014",
    "addr:postcode":"70131",
    "addr:street":"Holiday Dr",
    "iso:country":"US",
    "sg:address":"3014 Holiday Dr",
    "sg:city":"New Orleans",
    "sg:classifiers":[
        {
            "category":"Education",
            "subcategory":"Library",
            "type":"Public Place"
        }
    ],
    "sg:phone":"+1 504 596 2642",
    "sg:postcode":"70131",
    "sg:province":"LA",
    "wof:name":"Algiers Regional Public Libr",
    "wof:placetype":"venue"
},
  "geometry": {"coordinates":[-90.013792,29.924076],"type":"Point"}
}