{
  "type": "Feature",
  "properties": {
    "iso:country":"US",
    "sg:address":"11365 Perret St",
    "sg:city":"Hammond",
    "sg:classifiers":[
        {
            "category":"Social Services",
            "type":"Services"
        }
    ],
    "sg:phone":"+1 225 567 5158",
    "sg:postcode":"70401",
    "sg:province":"LA",
    "sg:tags":[
        "organization",
        "welfare"
    ],
    "wof:name":"Happy Haven Homes Inc",
    "wof:placetype":"venue"
},
  "geometry": {"coordinates":[-90.54190699999999,30.511045],"type":"Point"}
}