{
  "type": "Feature",
  "properties": {
    "addr:full":"17505 Old Jefferson Hwy Prairieville LA 70769",
    "addr:housenumber":"17505",
    "addr:postcode":"70769",
    "addr:street":"Old Jefferson Hwy Prairieville",
    "iso:country":"US",
    "sg:address":"17505 Old Jefferson Hwy",
    "sg:city":"Prairieville",
    "sg:classifiers":[
        {
            "category":"Health Services",
            "subcategory":"Doctor",
            "type":"Services"
        }
    ],
    "sg:phone":"+1 225 744 2273",
    "sg:postcode":"70769",
    "sg:province":"LA",
    "sg:tags":[
        "physician",
        "surgeon"
    ],
    "wof:name":"First Care After Hours",
    "wof:placetype":"venue"
},
  "geometry": {"coordinates":[-90.976206,30.320579],"type":"Point"}
}