{
  "type": "Feature",
  "properties": {
    "addr:full":"11817 Jefferson Hwy Baton Rouge LA 70816",
    "addr:housenumber":"11817",
    "addr:postcode":"70816",
    "addr:street":"Jefferson Hwy",
    "iso:country":"US",
    "sg:address":"11817 Jefferson Hwy",
    "sg:city":"Baton Rouge",
    "sg:classifiers":[
        {
            "category":"Real Estate",
            "subcategory":"Developer",
            "type":"Services"
        }
    ],
    "sg:phone":"+1 225 753 1440",
    "sg:postcode":"70816",
    "sg:province":"LA",
    "sg:tags":[
        "cemetery"
    ],
    "wof:name":"Resthaven Gardens Of Memory",
    "wof:placetype":"venue"
},
  "geometry": {"coordinates":[-91.05006299999999,30.39599],"type":"Point"}
}