{
  "type": "Feature",
  "properties": {
    "iso:country":"US",
    "sg:address":"268 Corporate Dr",
    "sg:city":"Houma",
    "sg:classifiers":[
        {
            "category":"Health Services",
            "subcategory":"Doctor",
            "type":"Services"
        }
    ],
    "sg:phone":"+1 985 223 1901",
    "sg:postcode":"70360",
    "sg:province":"LA",
    "sg:tags":[
        "physician",
        "surgeon"
    ],
    "wof:name":"Tulane Retinal Clinic",
    "wof:placetype":"venue"
},
  "geometry": {"coordinates":[-90.748132,29.599074],"type":"Point"}
}