{
  "type": "Feature",
  "properties": {
    "iso:country":"US",
    "sg:address":"10273 Cardiff Dr",
    "sg:city":"Keithville",
    "sg:classifiers":[
        {
            "category":"Building & Trades",
            "subcategory":"Construction",
            "type":"Services"
        }
    ],
    "sg:phone":"+1 318 925 0137",
    "sg:postcode":"71047",
    "sg:province":"LA",
    "sg:tags":[
        "roofing",
        "contractor",
        "industrial",
        "contractors-commercial",
        "consultant"
    ],
    "wof:name":"Quality Roofing",
    "wof:placetype":"venue"
},
  "geometry": {"coordinates":[-93.86432,32.368706],"type":"Point"}
}