{
  "type": "Feature",
  "properties": {
    "iso:country":"US",
    "sg:address":"73765 Penn Mill Rd",
    "sg:city":"Covington",
    "sg:classifiers":[
        {
            "category":"Wholesale",
            "subcategory":"Machinery & Supplies",
            "type":"Manufacturing & Wholesale Goods"
        }
    ],
    "sg:phone":"+1 985 871 8996",
    "sg:postcode":"70435",
    "sg:province":"LA",
    "sg:tags":[
        "crane",
        "derrick"
    ],
    "sg:website":"www.natoil.com",
    "wof:name":"National-Oilwell Varco",
    "wof:placetype":"venue"
},
  "geometry": {"coordinates":[-90.156567,30.506134],"type":"Point"}
}