{
  "type": "Feature",
  "properties": {
    "addr:full":"2545 Delaware Ave Kenner LA 70062",
    "addr:housenumber":"2545",
    "addr:postcode":"70062",
    "addr:street":"Delaware Ave",
    "iso:country":"US",
    "sg:address":"2545 Delaware Ave",
    "sg:city":"Kenner",
    "sg:classifiers":[
        {
            "category":"Building & Trades",
            "subcategory":"Plumbing",
            "type":"Services"
        }
    ],
    "sg:phone":"+1 504 466 8581",
    "sg:postcode":"70062",
    "sg:province":"LA",
    "sg:tags":[
        "plumbing",
        "contractor"
    ],
    "wof:name":"Rooter-Man",
    "wof:placetype":"venue"
},
  "geometry": {"coordinates":[-90.24291700000001,30.002581],"type":"Point"}
}