{
  "type": "Feature",
  "properties": {
    "addr:full":"5856 Line Ave Shreveport LA 71106",
    "addr:housenumber":"5856",
    "addr:postcode":"71106",
    "addr:street":"Line Ave",
    "iso:country":"US",
    "sg:address":"5856 Line Ave",
    "sg:city":"Shreveport",
    "sg:classifiers":[
        {
            "category":"Restaurant",
            "type":"Food & Drink"
        }
    ],
    "sg:menulink":"http://www.allmenus.com/la/shreveport/132138-subway/menu/",
    "sg:phone":"+1 318 865 2855",
    "sg:postcode":"71106",
    "sg:province":"LA",
    "sg:tags":[
        "american",
        "sandwich"
    ],
    "wof:name":"Subway",
    "wof:placetype":"venue"
},
  "geometry": {"coordinates":[-93.746047,32.455548],"type":"Point"}
}