{
  "type": "Feature",
  "properties": {
    "iso:country":"US",
    "sg:address":"8176 Hwy 79",
    "sg:city":"Haynesville",
    "sg:classifiers":[
        {
            "category":"Organizations",
            "subcategory":"Religious Organization",
            "type":"Services"
        }
    ],
    "sg:phone":"+1 318 624 1415",
    "sg:postcode":"71038",
    "sg:province":"LA",
    "wof:name":"Bethel Baptist Church",
    "wof:placetype":"venue"
},
  "geometry": {"coordinates":[-93.120997,32.945028],"type":"Point"}
}