{
  "type": "Feature",
  "properties": {
    "iso:country":"US",
    "sg:address":"1717 Winchester Pl",
    "sg:city":"Harvey",
    "sg:classifiers":[
        {
            "category":"Real Estate",
            "subcategory":"Real Estate Operator",
            "type":"Services"
        }
    ],
    "sg:phone":"+1 504 347 8332",
    "sg:postcode":"70058",
    "sg:province":"LA",
    "sg:tags":[
        "property",
        "lessor"
    ],
    "wof:name":"Avid Innovations LLC",
    "wof:placetype":"venue"
},
  "geometry": {"coordinates":[-90.085072,29.884042],"type":"Point"}
}