{
  "type": "Feature",
  "properties": {
    "addr:full":"2124 3rd St Kenner LA 70062",
    "addr:housenumber":"2124",
    "addr:postcode":"70062",
    "addr:street":"3Rd St",
    "iso:country":"US",
    "sg:address":"2124 3rd St",
    "sg:city":"Kenner",
    "sg:classifiers":[
        {
            "category":"Shopping",
            "subcategory":"Clothing, Apparel, & Fashions",
            "type":"Retail Goods"
        }
    ],
    "sg:phone":"+1 504 305 3042",
    "sg:postcode":"70062",
    "sg:province":"LA",
    "wof:name":"Lois's Boutique",
    "wof:placetype":"venue"
},
  "geometry": {"coordinates":[-90.245299,29.973103],"type":"Point"}
}