{
  "type": "Feature",
  "properties": {
    "addr:full":"1019 Albertson Pkwy Broussard LA 70518",
    "addr:housenumber":"1019",
    "addr:postcode":"70518",
    "addr:street":"Albertson Pkwy",
    "iso:country":"US",
    "sg:address":"1019 Albertson Pkwy",
    "sg:city":"Broussard",
    "sg:classifiers":[
        {
            "category":"Food & Beverages",
            "subcategory":"Meat & Fish",
            "type":"Retail Goods"
        }
    ],
    "sg:phone":"+1 337 837 6446",
    "sg:postcode":"70518",
    "sg:province":"LA",
    "sg:tags":[
        "shop"
    ],
    "wof:name":"Chops Specialty Meats Inc",
    "wof:placetype":"venue"
},
  "geometry": {"coordinates":[-91.95714099999999,30.138193],"type":"Point"}
}