{
  "type": "Feature",
  "properties": {
    "iso:country":"US",
    "sg:address":"4430 S I- 10 Svc Rd W",
    "sg:city":"Metairie",
    "sg:classifiers":[
        {
            "category":"Wholesale",
            "subcategory":"Motor Vehicles",
            "type":"Manufacturing & Wholesale Goods"
        }
    ],
    "sg:phone":"+1 504 888 2986",
    "sg:postcode":"70001",
    "sg:province":"LA",
    "sg:tags":[
        "automobile",
        "truck",
        "broker"
    ],
    "wof:name":"T & S Investments",
    "wof:placetype":"venue"
},
  "geometry": {"coordinates":[-90.17847399999999,29.998302],"type":"Point"}
}