{
  "type": "Feature",
  "properties": {
    "iso:country":"US",
    "sg:address":"2905 Robinson Dr",
    "sg:city":"Winnsboro",
    "sg:classifiers":[
        {
            "category":"Professional",
            "subcategory":"Management & Consulting",
            "type":"Services"
        }
    ],
    "sg:phone":"+1 318 435 9310",
    "sg:postcode":"71295",
    "sg:province":"LA",
    "sg:tags":[
        "business"
    ],
    "wof:name":"Clays Consultant Service",
    "wof:placetype":"venue"
},
  "geometry": {"coordinates":[-91.722534,32.153337],"type":"Point"}
}