{
  "type": "Feature",
  "properties": {
    "iso:country":"US",
    "sg:address":"499 4th St",
    "sg:city":"Bridge City",
    "sg:classifiers":[
        {
            "category":"Retail",
            "subcategory":"Laundry & Dry Cleaning",
            "type":"Services"
        }
    ],
    "sg:phone":"+1 504 328 0608",
    "sg:postcode":"70094",
    "sg:province":"LA",
    "sg:tags":[
        "cleaners"
    ],
    "wof:name":"Cleaning Depot",
    "wof:placetype":"venue"
},
  "geometry": {"coordinates":[-90.14239499999999,29.907892],"type":"Point"}
}