{
  "type": "Feature",
  "properties": {
    "iso:country":"US",
    "sg:address":"1914 Cypress St",
    "sg:city":"West Monroe",
    "sg:classifiers":[
        {
            "category":"Autos & Motor Vehicles",
            "subcategory":"Auto Supplies",
            "type":"Retail Goods"
        }
    ],
    "sg:phone":"+1 318 387 3018",
    "sg:postcode":"71291",
    "sg:province":"LA",
    "sg:tags":[
        "tire"
    ],
    "wof:name":"Tillman Tire Ctrs",
    "wof:placetype":"venue"
},
  "geometry": {"coordinates":[-92.13837100000001,32.515893],"type":"Point"}
}