{
  "type": "Feature",
  "properties": {
    "addr:full":"1415 Beglis Pkwy Sulphur LA 70663",
    "addr:housenumber":"1415",
    "addr:postcode":"70663",
    "addr:street":"Beglis Pkwy",
    "iso:country":"US",
    "sg:address":"1415 Beglis Pkwy",
    "sg:city":"Sulphur",
    "sg:classifiers":[
        {
            "category":"Restaurant",
            "type":"Food & Drink"
        }
    ],
    "sg:menulink":"http://www.allmenus.com/la/sulphur/81556-papa-johns-pizza/menu/",
    "sg:phone":"+1 337 528 7272",
    "sg:postcode":"70663",
    "sg:province":"LA",
    "sg:tags":[
        "american",
        "pizza"
    ],
    "wof:name":"Papa John's Pizza",
    "wof:placetype":"venue"
},
  "geometry": {"coordinates":[-93.35938899999999,30.22795],"type":"Point"}
}