{
  "type": "Feature",
  "properties": {
    "iso:country":"US",
    "sg:address":"1618 Winnsboro Rd",
    "sg:city":"Monroe",
    "sg:classifiers":[
        {
            "category":"Food & Beverages",
            "subcategory":"Liquor & Beverages",
            "type":"Retail Goods"
        }
    ],
    "sg:phone":"+1 318 323 0660",
    "sg:postcode":"71202",
    "sg:province":"LA",
    "wof:name":"Super Discount Liquor",
    "wof:placetype":"venue"
},
  "geometry": {"coordinates":[-92.085736,32.48425],"type":"Point"}
}