{
  "type": "Feature",
  "properties": {
    "iso:country":"US",
    "sg:address":"802 Pine St",
    "sg:city":"West Monroe",
    "sg:classifiers":[
        {
            "category":"Personal",
            "subcategory":"Beauty Salon",
            "type":"Services"
        }
    ],
    "sg:phone":"+1 318 325 7819",
    "sg:postcode":"71291",
    "sg:province":"LA",
    "sg:tags":[
        "shop"
    ],
    "wof:name":"Donnas Beauty Shop",
    "wof:placetype":"venue"
},
  "geometry": {"coordinates":[-92.132014,32.498583],"type":"Point"}
}