{
  "type": "Feature",
  "properties": {
    "iso:country":"US",
    "sg:address":"7811 E Saint Bernard Hwy",
    "sg:city":"Violet",
    "sg:classifiers":[
        {
            "category":"Health Services",
            "subcategory":"Doctor",
            "type":"Services"
        }
    ],
    "sg:phone":"+1 504 682 8774",
    "sg:postcode":"70092",
    "sg:province":"LA",
    "sg:tags":[
        "practice",
        "family"
    ],
    "wof:name":"Health Clinic Inc",
    "wof:placetype":"venue"
},
  "geometry": {"coordinates":[-89.895203,29.873301],"type":"Point"}
}