{
  "type": "Feature",
  "properties": {
    "iso:country":"US",
    "sg:address":"2009 Hwy 190 Byp",
    "sg:city":"Covington",
    "sg:classifiers":[
        {
            "category":"Shopping",
            "subcategory":"Bicycles & Sporting Goods",
            "type":"Retail Goods"
        }
    ],
    "sg:phone":"+1 985 892 2521",
    "sg:postcode":"70433",
    "sg:province":"LA",
    "sg:tags":[
        "equipment",
        "archery",
        "supply"
    ],
    "wof:name":"American Hunter Gun & Archery",
    "wof:placetype":"venue"
},
  "geometry": {"coordinates":[-90.114294,30.496927],"type":"Point"}
}