{
  "type": "Feature",
  "properties": {
    "addr:full":"4846 General Meyer Ave New Orleans LA 70131",
    "addr:housenumber":"4846",
    "addr:postcode":"70131",
    "addr:street":"General Meyer Ave",
    "iso:country":"US",
    "sg:address":"4846 General Meyer Ave",
    "sg:city":"New Orleans",
    "sg:classifiers":[
        {
            "category":"Shopping",
            "subcategory":"Department Store",
            "type":"Retail Goods"
        }
    ],
    "sg:phone":"+1 504 394 3149",
    "sg:postcode":"70131",
    "sg:province":"LA",
    "sg:website":"www.familydollar.com",
    "wof:name":"Family Dollar Store",
    "wof:placetype":"venue"
},
  "geometry": {"coordinates":[-90.003304,29.9319],"type":"Point"}
}