{
  "type": "Feature",
  "properties": {
    "iso:country":"US",
    "sg:address":"4312 Emory St",
    "sg:city":"Shreveport",
    "sg:classifiers":[
        {
            "category":"Freight",
            "type":"Transportation"
        }
    ],
    "sg:phone":"+1 318 635 7422",
    "sg:postcode":"71109",
    "sg:province":"LA",
    "sg:tags":[
        "delivery"
    ],
    "sg:website":"www.cdl.net",
    "wof:name":"C D & L Inc",
    "wof:placetype":"venue"
},
  "geometry": {"coordinates":[-93.809966,32.469528],"type":"Point"}
}