{
  "type": "Feature",
  "properties": {
    "addr:full":"105 Janet Cir Lafayette LA 70506",
    "addr:housenumber":"105",
    "addr:postcode":"70506",
    "addr:street":"Janet Cir",
    "iso:country":"US",
    "sg:address":"105 Janet Cir",
    "sg:city":"Lafayette",
    "sg:classifiers":[
        {
            "category":"Wholesale",
            "subcategory":"Office Equipment",
            "type":"Manufacturing & Wholesale Goods"
        }
    ],
    "sg:phone":"+1 337 981 5070",
    "sg:postcode":"70506",
    "sg:province":"LA",
    "sg:tags":[
        "dictating",
        "machine",
        "supply"
    ],
    "wof:name":"Electronic Business Systems",
    "wof:placetype":"venue"
},
  "geometry": {"coordinates":[-92.059603,30.211898],"type":"Point"}
}