{
  "type": "Feature",
  "properties": {
    "addr:full":"2246 Ambassador Caffery Pkwy Lafayette LA 70506",
    "addr:housenumber":"2246",
    "addr:postcode":"70506",
    "addr:street":"Ambassador Caffery Pkwy",
    "iso:country":"US",
    "sg:address":"2246 Ambassador Caffery Pkwy",
    "sg:city":"Lafayette",
    "sg:classifiers":[
        {
            "category":"Cinema",
            "subcategory":"Movie Rental",
            "type":"Entertainment"
        }
    ],
    "sg:phone":"+1 337 993 8500",
    "sg:postcode":"70506",
    "sg:province":"LA",
    "sg:tags":[
        "leasing",
        "video",
        "disc",
        "tape"
    ],
    "wof:name":"Blockbuster Video",
    "wof:placetype":"venue"
},
  "geometry": {"coordinates":[-92.07578599999999,30.211387],"type":"Point"}
}