{
  "type": "Feature",
  "properties": {
    "iso:country":"US",
    "sg:address":"70452 Highway 21",
    "sg:city":"Covington",
    "sg:classifiers":[
        {
            "category":"Restaurant",
            "type":"Food & Drink"
        }
    ],
    "sg:menulink":"http://www.allmenus.com/la/madisonville/28720-isabellas-pizzeria/menu/",
    "sg:phone":"+1 985 875 7620",
    "sg:postcode":"70433",
    "sg:province":"LA",
    "sg:tags":[
        "american",
        "pizza"
    ],
    "wof:name":"Isabella's Pizzeria",
    "wof:placetype":"venue"
},
  "geometry": {"coordinates":[-90.085943,30.477146],"type":"Point"}
}