{
  "type": "Feature",
  "properties": {
    "iso:country":"US",
    "sg:address":"1424 Manhattan Blvd",
    "sg:city":"Harvey",
    "sg:classifiers":[
        {
            "category":"Retail",
            "subcategory":"Auto Repair",
            "type":"Services"
        }
    ],
    "sg:phone":"+1 504 362 8226",
    "sg:postcode":"70058",
    "sg:province":"LA",
    "sg:tags":[
        "body",
        "shop",
        "painting",
        "automobile"
    ],
    "wof:name":"California Customs Collision Center",
    "wof:placetype":"venue"
},
  "geometry": {"coordinates":[-90.05950199999999,29.8927],"type":"Point"}
}