{
  "type": "Feature",
  "properties": {
    "iso:country":"US",
    "sg:address":"5419 Jackson St Exd",
    "sg:city":"Alexandria",
    "sg:classifiers":[
        {
            "category":"Social Services",
            "type":"Services"
        }
    ],
    "sg:phone":"+1 318 487 5228",
    "sg:postcode":"71303",
    "sg:province":"LA",
    "sg:tags":[
        "government"
    ],
    "wof:name":"Family Support Office",
    "wof:placetype":"venue"
},
  "geometry": {"coordinates":[-92.485294,31.270333],"type":"Point"}
}