{
  "type": "Feature",
  "properties": {
    "addr:full":"10970 Florida Blvd Baton Rouge LA 70815",
    "addr:housenumber":"10970",
    "addr:postcode":"70815",
    "addr:street":"Florida Blvd",
    "iso:country":"US",
    "sg:address":"10970 Florida Blvd",
    "sg:city":"Baton Rouge",
    "sg:classifiers":[
        {
            "category":"Retail",
            "subcategory":"Auto Repair",
            "type":"Services"
        }
    ],
    "sg:phone":"+1 225 273 0041",
    "sg:postcode":"70815",
    "sg:province":"LA",
    "sg:tags":[
        "repairing",
        "automobile"
    ],
    "wof:name":"Kustom Auto Repair",
    "wof:placetype":"venue"
},
  "geometry": {"coordinates":[-91.060181,30.458496],"type":"Point"}
}