{
  "type": "Feature",
  "properties": {
    "iso:country":"US",
    "sg:address":"27460 Greenwood Dr",
    "sg:city":"Kinder",
    "sg:classifiers":[
        {
            "category":"Wholesale",
            "subcategory":"Groceries",
            "type":"Manufacturing & Wholesale Goods"
        }
    ],
    "sg:phone":"+1 337 738 7009",
    "sg:postcode":"70648",
    "sg:province":"LA",
    "sg:tags":[
        "rice"
    ],
    "wof:name":"USA Rice Federation",
    "wof:placetype":"venue"
},
  "geometry": {"coordinates":[-92.943654,30.434638],"type":"Point"}
}