{
  "type": "Feature",
  "properties": {
    "addr:full":"181 del Norte Ave Denham Springs LA 70726",
    "addr:housenumber":"181",
    "addr:postcode":"70726",
    "addr:street":"Del Norte Ave",
    "iso:country":"US",
    "sg:address":"181 del Norte Ave",
    "sg:city":"Denham Springs",
    "sg:classifiers":[
        {
            "category":"Personal",
            "subcategory":"Beauty Salon",
            "type":"Services"
        }
    ],
    "sg:phone":"+1 225 664 7226",
    "sg:postcode":"70726",
    "sg:province":"LA",
    "wof:name":"All About Hair",
    "wof:placetype":"venue"
},
  "geometry": {"coordinates":[-90.95608900000001,30.471043],"type":"Point"}
}