{
  "type": "Feature",
  "properties": {
    "iso:country":"US",
    "sg:address":"613 Barrow St",
    "sg:city":"Houma",
    "sg:classifiers":[
        {
            "category":"Wholesale",
            "subcategory":"Non-durable Goods",
            "type":"Manufacturing & Wholesale Goods"
        }
    ],
    "sg:phone":"+1 985 879 4529",
    "sg:postcode":"70360",
    "sg:province":"LA",
    "sg:tags":[
        "advertising"
    ],
    "wof:name":"All Print Unlimited",
    "wof:placetype":"venue"
},
  "geometry": {"coordinates":[-90.719655,29.593485],"type":"Point"}
}