{
  "type": "Feature",
  "properties": {
    "iso:country":"US",
    "sg:address":"832 Golden Grain Rd",
    "sg:city":"Duson",
    "sg:classifiers":[
        {
            "category":"Freight",
            "type":"Transportation"
        }
    ],
    "sg:phone":"+1 337 873 3548",
    "sg:postcode":"70529",
    "sg:province":"LA",
    "sg:tags":[
        "operator",
        "local",
        "trucking"
    ],
    "wof:name":"Mra Trucking Inc",
    "wof:placetype":"venue"
},
  "geometry": {"coordinates":[-92.166533,30.159337],"type":"Point"}
}