{
  "type": "Feature",
  "properties": {
    "iso:country":"US",
    "sg:address":"101 1st St",
    "sg:city":"Benton",
    "sg:classifiers":[
        {
            "category":"Railroad",
            "type":"Transportation"
        }
    ],
    "sg:phone":"+1 318 742 0237",
    "sg:postcode":"71006",
    "sg:province":"LA",
    "wof:name":"Kcs Transportation",
    "wof:placetype":"venue"
},
  "geometry": {"coordinates":[-93.739893,32.702019],"type":"Point"}
}