{
  "type": "Feature",
  "properties": {
    "iso:country":"US",
    "sg:address":"719 Federal Ave",
    "sg:city":"Morgan City",
    "sg:classifiers":[
        {
            "category":"Freight",
            "type":"Transportation"
        }
    ],
    "sg:phone":"+1 985 384 8787",
    "sg:postcode":"70380",
    "sg:province":"LA",
    "sg:tags":[
        "trucking"
    ],
    "wof:name":"C F S Trucking Inc",
    "wof:placetype":"venue"
},
  "geometry": {"coordinates":[-91.20676,29.698079],"type":"Point"}
}