{
  "type": "Feature",
  "properties": {
    "addr:full":"3545 NW Evangeline Trwy Carencro LA 70520",
    "addr:housenumber":"3545",
    "addr:postcode":"70520",
    "addr:street":"Nw Evangeline Trwy",
    "iso:country":"US",
    "sg:address":"3545 NW Evangeline Trwy",
    "sg:city":"Carencro",
    "sg:classifiers":[
        {
            "category":"Sports & Exercise",
            "subcategory":"Gym",
            "type":"Entertainment"
        }
    ],
    "sg:phone":"+1 337 886 2878",
    "sg:postcode":"70520",
    "sg:province":"LA",
    "sg:website":"www.curves.com",
    "wof:name":"Curves For Women",
    "wof:placetype":"venue"
},
  "geometry": {"coordinates":[-92.0513,30.319599],"type":"Point"}
}