{
  "type": "Feature",
  "properties": {
    "addr:full":"60225 Bayou Rd Plaquemine LA 70764",
    "addr:housenumber":"60225",
    "addr:postcode":"70764",
    "addr:street":"Bayou Rd",
    "iso:country":"US",
    "sg:address":"60225 Bayou Rd",
    "sg:city":"Plaquemine",
    "sg:classifiers":[
        {
            "category":"Personal",
            "subcategory":"Beauty Salon",
            "type":"Services"
        }
    ],
    "sg:phone":"+1 225 687 7992",
    "sg:postcode":"70764",
    "sg:province":"LA",
    "sg:tags":[
        "shop",
        "barber"
    ],
    "wof:name":"Classy Cuts By Donna",
    "wof:placetype":"venue"
},
  "geometry": {"coordinates":[-91.26234700000001,30.267608],"type":"Point"}
}