{
  "type": "Feature",
  "properties": {
    "iso:country":"US",
    "sg:address":"8501 Line Ave",
    "sg:city":"Shreveport",
    "sg:classifiers":[
        {
            "category":"Real Estate",
            "subcategory":"Real Estate Agent",
            "type":"Services"
        }
    ],
    "sg:phone":"+1 318 869 3576",
    "sg:postcode":"71106",
    "sg:province":"LA",
    "wof:name":"Spring Lake Estates",
    "wof:placetype":"venue"
},
  "geometry": {"coordinates":[-93.741258,32.426815],"type":"Point"}
}