{
  "type": "Feature",
  "properties": {
    "addr:full":"108 S Burnside Ave Gonzales LA 70737",
    "addr:housenumber":"108",
    "addr:postcode":"70737",
    "addr:street":"S Burnside Ave",
    "iso:country":"US",
    "sg:address":"108 S Burnside Ave",
    "sg:city":"Gonzales",
    "sg:classifiers":[
        {
            "category":"Retail",
            "subcategory":"Auto Repair",
            "type":"Services"
        }
    ],
    "sg:phone":"+1 225 647 5823",
    "sg:postcode":"70737",
    "sg:province":"LA",
    "sg:tags":[
        "automobile",
        "lubrication"
    ],
    "wof:name":"Gonzales Xpress Lube",
    "wof:placetype":"venue"
},
  "geometry": {"coordinates":[-90.920603,30.232754],"type":"Point"}
}