{
  "type": "Feature",
  "properties": {
    "iso:country":"US",
    "sg:address":"6630 Siegen Ln",
    "sg:city":"Baton Rouge",
    "sg:classifiers":[
        {
            "category":"Freight",
            "type":"Transportation"
        }
    ],
    "sg:phone":"+1 225 293 0080",
    "sg:postcode":"70809",
    "sg:province":"LA",
    "sg:tags":[
        "operator",
        "local",
        "trucking"
    ],
    "wof:name":"Jesus Trusting Trucking",
    "wof:placetype":"venue"
},
  "geometry": {"coordinates":[-91.06230600000001,30.388632],"type":"Point"}
}