{
  "type": "Feature",
  "properties": {
    "iso:country":"US",
    "sg:address":"1220 Jeanne St",
    "sg:city":"Lafayette",
    "sg:classifiers":[
        {
            "category":"Restaurant",
            "type":"Food & Drink"
        }
    ],
    "sg:phone":"+1 337 235 9612",
    "sg:postcode":"70506",
    "sg:province":"LA",
    "sg:tags":[
        "eating",
        "association"
    ],
    "wof:name":"American Italian Federation",
    "wof:placetype":"venue"
},
  "geometry": {"coordinates":[-92.041391,30.226519],"type":"Point"}
}