{
  "type": "Feature",
  "properties": {
    "iso:country":"US",
    "sg:address":"3619 Ambassador Caffery Pkwy",
    "sg:city":"Lafayette",
    "sg:classifiers":[
        {
            "category":"Home & Garden",
            "subcategory":"Household Appliances",
            "type":"Retail Goods"
        }
    ],
    "sg:phone":"+1 337 406 0590",
    "sg:postcode":"70503",
    "sg:province":"LA",
    "sg:tags":[
        "cleaners",
        "vacuum"
    ],
    "wof:name":"Oreck Factory Showroom",
    "wof:placetype":"venue"
},
  "geometry": {"coordinates":[-92.06993,30.17441],"type":"Point"}
}