{
  "type": "Feature",
  "properties": {
    "iso:country":"US",
    "sg:address":"105 Federal Ave",
    "sg:city":"Morgan City",
    "sg:classifiers":[
        {
            "category":"Professional",
            "type":"Services"
        }
    ],
    "sg:phone":"+1 985 385 2033",
    "sg:postcode":"70380",
    "sg:province":"LA",
    "sg:tags":[
        "establishment"
    ],
    "wof:name":"St Mary Consolidated",
    "wof:placetype":"venue"
},
  "geometry": {"coordinates":[-91.203412,29.691799],"type":"Point"}
}