{
  "type": "Feature",
  "properties": {
    "iso:country":"US",
    "sg:address":"38101 State Rte 621",
    "sg:city":"Gonzales",
    "sg:classifiers":[
        {
            "category":"Education",
            "subcategory":"School",
            "type":"Public Place"
        }
    ],
    "sg:phone":"+1 225 621 8100",
    "sg:postcode":"70737",
    "sg:province":"LA",
    "sg:website":"www.apsb.org",
    "wof:name":"Duplessis Primary School",
    "wof:placetype":"venue"
},
  "geometry": {"coordinates":[-90.967956,30.269263],"type":"Point"}
}