{
  "type": "Feature",
  "properties": {
    "iso:country":"US",
    "sg:address":"120 Northpark Blvd",
    "sg:city":"Covington",
    "sg:classifiers":[
        {
            "category":"Professional",
            "subcategory":"Accounting & Tax Preparation",
            "type":"Services"
        }
    ],
    "sg:phone":"+1 985 892 8776",
    "sg:postcode":"70433",
    "sg:province":"LA",
    "sg:tags":[
        "accountant"
    ],
    "wof:name":"Frentz Dyer & Assoc",
    "wof:placetype":"venue"
},
  "geometry": {"coordinates":[-90.08357700000001,30.442699],"type":"Point"}
}