{
  "type": "Feature",
  "properties": {
    "iso:country":"US",
    "sg:address":"12491 Forest Braud Ln",
    "sg:city":"Gonzales",
    "sg:classifiers":[
        {
            "category":"Real Estate",
            "subcategory":"Real Estate Operator",
            "type":"Services"
        }
    ],
    "sg:phone":"+1 225 644 2653",
    "sg:postcode":"70737",
    "sg:province":"LA",
    "sg:tags":[
        "building",
        "apartment"
    ],
    "wof:name":"Mc Gaha Apartments",
    "wof:placetype":"venue"
},
  "geometry": {"coordinates":[-90.937862,30.253494],"type":"Point"}
}