{
  "type": "Feature",
  "properties": {
    "iso:country":"US",
    "sg:address":"550 Eraste Landry Rd",
    "sg:city":"Lafayette",
    "sg:classifiers":[
        {
            "category":"Real Estate",
            "subcategory":"Real Estate Operator",
            "type":"Services"
        }
    ],
    "sg:phone":"+1 337 233 6554",
    "sg:postcode":"70506",
    "sg:province":"LA",
    "sg:tags":[
        "apartment"
    ],
    "wof:name":"Whispering Oaks Apartments",
    "wof:placetype":"venue"
},
  "geometry": {"coordinates":[-92.049509,30.226511],"type":"Point"}
}