{
  "type": "Feature",
  "properties": {
    "addr:full":"3121 Van Buren St Baker LA 70714",
    "addr:housenumber":"3121",
    "addr:postcode":"70714",
    "addr:street":"Van Buren St",
    "iso:country":"US",
    "sg:address":"3121 Van Buren St",
    "sg:city":"Baker",
    "sg:classifiers":[
        {
            "category":"Professional",
            "subcategory":"Accounting & Tax Preparation",
            "type":"Services"
        }
    ],
    "sg:phone":"+1 225 775 7710",
    "sg:postcode":"70714",
    "sg:province":"LA",
    "sg:tags":[
        "return",
        "filing"
    ],
    "wof:name":"Generations Tax Svc",
    "wof:placetype":"venue"
},
  "geometry": {"coordinates":[-91.16732399999999,30.584273],"type":"Point"}
}