{
  "type": "Feature",
  "properties": {
    "addr:full":"8670 Pecue Ln Baton Rouge LA 70809",
    "addr:housenumber":"8670",
    "addr:postcode":"70809",
    "addr:street":"Pecue Ln",
    "iso:country":"US",
    "sg:address":"8670 Pecue Ln",
    "sg:city":"Baton Rouge",
    "sg:classifiers":[
        {
            "category":"Building & Trades",
            "subcategory":"Construction",
            "type":"Services"
        }
    ],
    "sg:phone":"+1 225 756 5525",
    "sg:postcode":"70809",
    "sg:province":"LA",
    "sg:tags":[
        "demolition",
        "contractor"
    ],
    "wof:name":"Environmental Abatement Svc",
    "wof:placetype":"venue"
},
  "geometry": {"coordinates":[-91.042751,30.374709],"type":"Point"}
}