{
  "type": "Feature",
  "properties": {
    "addr:full":"956 N 39th St Baton Rouge LA 70802",
    "addr:housenumber":"956",
    "addr:postcode":"70802",
    "addr:street":"N 39Th St",
    "iso:country":"US",
    "sg:address":"956 N 39th St",
    "sg:city":"Baton Rouge",
    "sg:classifiers":[
        {
            "category":"Organizations",
            "subcategory":"Religious Organization",
            "type":"Services"
        }
    ],
    "sg:phone":"+1 225 344 2478",
    "sg:postcode":"70802",
    "sg:province":"LA",
    "wof:name":"Evergreen Baptist Church",
    "wof:placetype":"venue"
},
  "geometry": {"coordinates":[-91.151101,30.456951],"type":"Point"}
}