{
  "type": "Feature",
  "properties": {
    "iso:country":"US",
    "sg:address":"1125 Church Point Hwy",
    "sg:city":"Rayne",
    "sg:classifiers":[
        {
            "category":"Travel",
            "subcategory":"Hotels & Motels",
            "type":"Entertainment"
        }
    ],
    "sg:phone":"+1 337 334 0000",
    "sg:postcode":"70578",
    "sg:province":"LA",
    "wof:name":"Days Inn",
    "wof:placetype":"venue"
},
  "geometry": {"coordinates":[-92.269812,30.253154],"type":"Point"}
}