{
  "type": "Feature",
  "properties": {
    "iso:country":"US",
    "sg:address":"2531 Dulles Dr",
    "sg:city":"Lafayette",
    "sg:classifiers":[
        {
            "category":"Personal",
            "subcategory":"Beauty Salon",
            "type":"Services"
        }
    ],
    "sg:phone":"+1 337 988 2320",
    "sg:postcode":"70506",
    "sg:province":"LA",
    "wof:name":"Hair Techniques By Janet & Co",
    "wof:placetype":"venue"
},
  "geometry": {"coordinates":[-92.10493200000001,30.210538],"type":"Point"}
}