{
  "type": "Feature",
  "properties": {
    "iso:country":"US",
    "sg:address":"5007 Lapalco Blvd",
    "sg:city":"Marrero",
    "sg:classifiers":[
        {
            "category":"Personal",
            "subcategory":"Beauty Salon",
            "type":"Services"
        }
    ],
    "sg:phone":"+1 504 328 9936",
    "sg:postcode":"70072",
    "sg:province":"LA",
    "sg:tags":[
        "manicuring"
    ],
    "wof:name":"Lucky Nails",
    "wof:placetype":"venue"
},
  "geometry": {"coordinates":[-90.101905,29.87524],"type":"Point"}
}