{
  "type": "Feature",
  "properties": {
    "iso:country":"US",
    "sg:address":"500 Hemlock St",
    "sg:city":"La Place",
    "sg:classifiers":[
        {
            "category":"Autos & Motor Vehicles",
            "subcategory":"Auto Supplies",
            "type":"Retail Goods"
        }
    ],
    "sg:phone":"+1 985 652 2241",
    "sg:postcode":"70068",
    "sg:province":"LA",
    "sg:tags":[
        "automobile",
        "parts"
    ],
    "wof:name":"Carquest Auto Parts",
    "wof:placetype":"venue"
},
  "geometry": {"coordinates":[-90.49658599999999,30.06966],"type":"Point"}
}