{
  "type": "Feature",
  "properties": {
    "addr:full":"2601 Newcombe St Monroe LA 71201",
    "addr:housenumber":"2601",
    "addr:postcode":"71201",
    "addr:street":"Newcombe St",
    "iso:country":"US",
    "sg:address":"2601 Newcombe St",
    "sg:city":"Monroe",
    "sg:classifiers":[
        {
            "category":"Professional",
            "type":"Services"
        }
    ],
    "sg:phone":"+1 318 322 1445",
    "sg:postcode":"71201",
    "sg:province":"LA",
    "wof:name":"Rack Service Co Inc",
    "wof:placetype":"venue"
},
  "geometry": {"coordinates":[-92.09741699999999,32.521785],"type":"Point"}
}