{
  "type": "Feature",
  "properties": {
    "iso:country":"US",
    "sg:address":"2116 Carey St",
    "sg:city":"Slidell",
    "sg:classifiers":[
        {
            "category":"Professional",
            "subcategory":"Business Services",
            "type":"Services"
        }
    ],
    "sg:phone":"+1 985 781 4126",
    "sg:postcode":"70458",
    "sg:province":"LA",
    "sg:tags":[
        "notary"
    ],
    "wof:name":"Positive Minds LLC",
    "wof:placetype":"venue"
},
  "geometry": {"coordinates":[-89.783976,30.27504],"type":"Point"}
}