{
  "type": "Feature",
  "properties": {
    "addr:full":"402 W Easy St Destrehan LA 70047",
    "addr:housenumber":"402",
    "addr:postcode":"70047",
    "addr:street":"W Easy St",
    "iso:country":"US",
    "sg:address":"402 W Easy St",
    "sg:city":"Destrehan",
    "sg:classifiers":[
        {
            "category":"Building & Trades",
            "subcategory":"Construction",
            "type":"Services"
        }
    ],
    "sg:phone":"+1 985 764 8125",
    "sg:postcode":"70047",
    "sg:province":"LA",
    "sg:tags":[
        "hanging",
        "contractor"
    ],
    "wof:name":"Faust Painting",
    "wof:placetype":"venue"
},
  "geometry": {"coordinates":[-90.386258,29.975691],"type":"Point"}
}