{
  "type": "Feature",
  "properties": {
    "addr:full":"4525 Johnston St Lafayette LA 70503",
    "addr:housenumber":"4525",
    "addr:postcode":"70503",
    "addr:street":"Johnston St",
    "iso:country":"US",
    "sg:address":"4525 Johnston St",
    "sg:city":"Lafayette",
    "sg:classifiers":[
        {
            "category":"Building & Trades",
            "subcategory":"Construction",
            "type":"Services"
        }
    ],
    "sg:phone":"+1 337 988 6080",
    "sg:postcode":"70503",
    "sg:province":"LA",
    "sg:tags":[
        "concrete",
        "contractor"
    ],
    "wof:name":"Hot Stamped Cups",
    "wof:placetype":"venue"
},
  "geometry": {"coordinates":[-92.060091,30.192284],"type":"Point"}
}