{
  "type": "Feature",
  "properties": {
    "iso:country":"US",
    "sg:address":"209 Little John Dr",
    "sg:city":"Baton Rouge",
    "sg:classifiers":[
        {
            "category":"Shopping",
            "subcategory":"Used Merchandise",
            "type":"Retail Goods"
        }
    ],
    "sg:phone":"+1 225 272 9900",
    "sg:postcode":"70815",
    "sg:province":"LA",
    "sg:tags":[
        "shop",
        "thrift"
    ],
    "wof:name":"Family Thrift Center",
    "wof:placetype":"venue"
},
  "geometry": {"coordinates":[-91.051214,30.458795],"type":"Point"}
}