{
  "type": "Feature",
  "properties": {
    "iso:country":"US",
    "sg:address":"409 Moss St",
    "sg:city":"Winnfield",
    "sg:classifiers":[
        {
            "category":"Organizations",
            "subcategory":"Religious Organization",
            "type":"Services"
        }
    ],
    "sg:phone":"+1 318 628 5002",
    "sg:postcode":"71483",
    "sg:province":"LA",
    "sg:tags":[
        "church"
    ],
    "wof:name":"God's Holy Redeemed Ministries",
    "wof:placetype":"venue"
},
  "geometry": {"coordinates":[-92.645133,31.917378],"type":"Point"}
}