{
  "type": "Feature",
  "properties": {
    "addr:full":"22472 Hwy 1084 Covington LA 70435",
    "addr:housenumber":"22472",
    "addr:postcode":"1084;70435",
    "addr:street":"Hwy",
    "iso:country":"US",
    "sg:address":"22472 Hwy 1084",
    "sg:city":"Covington",
    "sg:classifiers":[
        {
            "category":"Recreation",
            "type":"Entertainment"
        }
    ],
    "sg:phone":"+1 985 893 3990",
    "sg:postcode":"70435",
    "sg:province":"LA",
    "sg:tags":[
        "stable"
    ],
    "wof:name":"Party Ponies",
    "wof:placetype":"venue"
},
  "geometry": {"coordinates":[-90.03039,30.533553],"type":"Point"}
}