{
  "type": "Feature",
  "properties": {
    "iso:country":"US",
    "sg:address":"14015 Rosewood Dr",
    "sg:city":"Folsom",
    "sg:classifiers":[
        {
            "category":"Autos & Motor Vehicles",
            "subcategory":"Motorcycle Sales",
            "type":"Retail Goods"
        }
    ],
    "sg:phone":"+1 985 796 8002",
    "sg:postcode":"70437",
    "sg:province":"LA",
    "sg:tags":[
        "scooter"
    ],
    "wof:name":"British Bikes LTD",
    "wof:placetype":"venue"
},
  "geometry": {"coordinates":[-90.17780999999999,30.617628],"type":"Point"}
}