{
  "type": "Feature",
  "properties": {
    "iso:country":"US",
    "sg:address":"3338 Ave B",
    "sg:city":"Mandeville",
    "sg:classifiers":[
        {
            "category":"Organizations",
            "subcategory":"Religious Organization",
            "type":"Services"
        }
    ],
    "sg:phone":"+1 985 624 5028",
    "sg:postcode":"70448",
    "sg:province":"LA",
    "sg:tags":[
        "church"
    ],
    "wof:name":"Goodwill Baptist Church",
    "wof:placetype":"venue"
},
  "geometry": {"coordinates":[-90.083248,30.371782],"type":"Point"}
}