{
  "type": "Feature",
  "properties": {
    "iso:country":"US",
    "sg:address":"175 Hector Ave",
    "sg:city":"Gretna",
    "sg:classifiers":[
        {
            "category":"Health Services",
            "subcategory":"Doctor",
            "type":"Services"
        }
    ],
    "sg:phone":"+1 504 365 1697",
    "sg:postcode":"70056",
    "sg:province":"LA",
    "sg:tags":[
        "practice",
        "family"
    ],
    "wof:name":"Nicewander R Kurt MD Faafp",
    "wof:placetype":"venue"
},
  "geometry": {"coordinates":[-90.040802,29.9179],"type":"Point"}
}