{
  "type": "Feature",
  "properties": {
    "iso:country":"US",
    "sg:address":"1532 E Airline Hwy",
    "sg:city":"La Place",
    "sg:classifiers":[
        {
            "category":"Autos & Motor Vehicles",
            "subcategory":"Automobile Sales",
            "type":"Retail Goods"
        }
    ],
    "sg:phone":"+1 985 652 9321",
    "sg:postcode":"70068",
    "sg:province":"LA",
    "sg:tags":[
        "car",
        "dealer"
    ],
    "wof:name":"Easy Auto Sales",
    "wof:placetype":"venue"
},
  "geometry": {"coordinates":[-90.442582,30.041566],"type":"Point"}
}