{
  "type": "Feature",
  "properties": {
    "addr:full":"2717 State Rte 3063 Vinton LA 70668",
    "addr:housenumber":"2717",
    "addr:postcode":"3063;70668",
    "addr:street":"State Rte",
    "iso:country":"US",
    "sg:address":"2717 State Rte 3063",
    "sg:city":"Vinton",
    "sg:classifiers":[
        {
            "category":"Sports & Exercise",
            "subcategory":"Race Track",
            "type":"Entertainment"
        }
    ],
    "sg:phone":"+1 337 589 3278",
    "sg:postcode":"70668",
    "sg:province":"LA",
    "sg:website":"www.deltadowns.com",
    "wof:name":"Delta Downs Race Results",
    "wof:placetype":"venue"
},
  "geometry": {"coordinates":[-93.622748,30.197731],"type":"Point"}
}