{
  "type": "Feature",
  "properties": {
    "iso:country":"US",
    "sg:address":"129 Andrea St",
    "sg:city":"New Orleans",
    "sg:classifiers":[
        {
            "category":"Retail",
            "subcategory":"Repair Shop",
            "type":"Services"
        },
        {
            "category":"Building & Trades",
            "subcategory":"Plumbing",
            "type":"Services"
        }
    ],
    "sg:phone":"+1 504 739 9567",
    "sg:postcode":"70123",
    "sg:province":"LA",
    "sg:tags":[
        "plumbing",
        "house",
        "contractor"
    ],
    "wof:name":"Paces Plumbing Inc",
    "wof:placetype":"venue"
},
  "geometry": {"coordinates":[-90.22468499999999,29.964042],"type":"Point"}
}