{
  "type": "Feature",
  "properties": {
    "iso:country":"US",
    "sg:address":"2916 Lake Palourde Rd",
    "sg:city":"Morgan City",
    "sg:classifiers":[
        {
            "category":"Manufacturing",
            "subcategory":"Watercraft",
            "type":"Manufacturing & Wholesale Goods"
        }
    ],
    "sg:phone":"+1 985 631 0888",
    "sg:postcode":"70340",
    "sg:province":"LA",
    "sg:tags":[
        "builder",
        "ship",
        "repairer"
    ],
    "wof:name":"A & B Industry Of Morgan City",
    "wof:placetype":"venue"
},
  "geometry": {"coordinates":[-91.10178399999999,29.681962],"type":"Point"}
}