{
  "type": "Feature",
  "properties": {
    "iso:country":"US",
    "sg:address":"4529 Lee St",
    "sg:city":"Alexandria",
    "sg:classifiers":[
        {
            "category":"Shopping",
            "subcategory":"Hobbies, Toys, & Games",
            "type":"Retail Goods"
        }
    ],
    "sg:phone":"+1 318 443 2755",
    "sg:postcode":"71302",
    "sg:province":"LA",
    "sg:tags":[
        "model",
        "supply"
    ],
    "wof:name":"Hare's Art & Hobby",
    "wof:placetype":"venue"
},
  "geometry": {"coordinates":[-92.445874,31.265464],"type":"Point"}
}