{
  "type": "Feature",
  "properties": {
    "addr:full":"5115 Clay Cut Rd Baton Rouge LA 70806",
    "addr:housenumber":"5115",
    "addr:postcode":"70806",
    "addr:street":"Clay Cut Rd",
    "iso:country":"US",
    "sg:address":"5115 Clay Cut Rd",
    "sg:city":"Baton Rouge",
    "sg:classifiers":[
        {
            "category":"Professional",
            "subcategory":"Art Services",
            "type":"Services"
        }
    ],
    "sg:phone":"+1 225 923 2384",
    "sg:postcode":"70806",
    "sg:province":"LA",
    "sg:tags":[
        "commercial",
        "design"
    ],
    "wof:name":"Cathy Zeilinski Design",
    "wof:placetype":"venue"
},
  "geometry": {"coordinates":[-91.13656,30.441484],"type":"Point"}
}