{
  "type": "Feature",
  "properties": {
    "addr:full":"16037 Hickory Knoll Ave Baton Rouge LA 70810",
    "addr:housenumber":"16037",
    "addr:postcode":"70810",
    "addr:street":"Hickory Knoll Ave",
    "iso:country":"US",
    "sg:address":"16037 Hickory Knoll Ave",
    "sg:city":"Baton Rouge",
    "sg:classifiers":[
        {
            "category":"Professional",
            "subcategory":"Employment Agencies",
            "type":"Services"
        }
    ],
    "sg:phone":"+1 225 751 2707",
    "sg:postcode":"70810",
    "sg:province":"LA",
    "sg:tags":[
        "help",
        "contractor"
    ],
    "wof:name":"Professional Staffing Personal",
    "wof:placetype":"venue"
},
  "geometry": {"coordinates":[-91.04598799999999,30.352321],"type":"Point"}
}