{
  "type": "Feature",
  "properties": {
    "iso:country":"US",
    "sg:address":"901 31st St",
    "sg:city":"Kenner",
    "sg:classifiers":[
        {
            "category":"Organizations",
            "subcategory":"Religious Organization",
            "type":"Services"
        }
    ],
    "sg:phone":"+1 504 467 5552",
    "sg:postcode":"70065",
    "sg:province":"LA",
    "sg:tags":[
        "church"
    ],
    "wof:name":"Cypress Grove Mssnry Bapt Ch",
    "wof:placetype":"venue"
},
  "geometry": {"coordinates":[-90.256294,30.011053],"type":"Point"}
}