{
  "type": "Feature",
  "properties": {
    "iso:country":"US",
    "sg:address":"532 E Main St",
    "sg:city":"Ville Platte",
    "sg:classifiers":[
        {
            "category":"Education",
            "subcategory":"School",
            "type":"Public Place"
        }
    ],
    "sg:phone":"+1 337 363 8050",
    "sg:postcode":"70586",
    "sg:province":"LA",
    "wof:name":"Sacred Heart Development Dir",
    "wof:placetype":"venue"
},
  "geometry": {"coordinates":[-92.268787,30.68602],"type":"Point"}
}