{
  "type": "Feature",
  "properties": {
    "addr:full":"615 Tideland Rd Broussard LA 70518",
    "addr:housenumber":"615",
    "addr:postcode":"70518",
    "addr:street":"Tideland Rd",
    "iso:country":"US",
    "sg:address":"615 Tideland Rd",
    "sg:city":"Broussard",
    "sg:classifiers":[
        {
            "category":"Wholesale",
            "subcategory":"Metals & Minerals",
            "type":"Manufacturing & Wholesale Goods"
        }
    ],
    "sg:phone":"+1 337 837 9821",
    "sg:postcode":"70518",
    "sg:province":"LA",
    "sg:tags":[
        "steel",
        "warehouse"
    ],
    "wof:name":"Integris Metals",
    "wof:placetype":"venue"
},
  "geometry": {"coordinates":[-91.984155,30.166472],"type":"Point"}
}