{
  "type": "Feature",
  "properties": {
    "iso:country":"US",
    "sg:address":"14105 Bert Allen Rd",
    "sg:city":"Gonzales",
    "sg:classifiers":[
        {
            "category":"Personal",
            "subcategory":"Beauty Salon",
            "type":"Services"
        }
    ],
    "sg:phone":"+1 225 755 3078",
    "sg:postcode":"70737",
    "sg:province":"LA",
    "sg:tags":[
        "shop"
    ],
    "wof:name":"PH Designers",
    "wof:placetype":"venue"
},
  "geometry": {"coordinates":[-90.91285999999999,30.273085],"type":"Point"}
}