{
  "type": "Feature",
  "properties": {
    "addr:full":"1409 Church St Jeanerette LA 70544",
    "addr:housenumber":"1409",
    "addr:postcode":"70544",
    "addr:street":"Church St",
    "iso:country":"US",
    "sg:address":"1409 Church St",
    "sg:city":"Jeanerette",
    "sg:classifiers":[
        {
            "category":"Health Services",
            "subcategory":"Doctor",
            "type":"Services"
        }
    ],
    "sg:phone":"+1 337 276 6018",
    "sg:postcode":"70544",
    "sg:province":"LA",
    "sg:tags":[
        "physician",
        "surgeon"
    ],
    "wof:name":"L Barrow Bourgeois MD",
    "wof:placetype":"venue"
},
  "geometry": {"coordinates":[-91.668637,29.914364],"type":"Point"}
}