{
  "type": "Feature",
  "properties": {
    "iso:country":"US",
    "sg:address":"222 N Roman St",
    "sg:city":"New Orleans",
    "sg:classifiers":[
        {
            "category":"Organizations",
            "subcategory":"Religious Organization",
            "type":"Services"
        }
    ],
    "sg:phone":"+1 504 586 8381",
    "sg:postcode":"70112",
    "sg:province":"LA",
    "sg:tags":[
        "church"
    ],
    "wof:name":"St James AME Church",
    "wof:placetype":"venue"
},
  "geometry": {"coordinates":[-90.07813299999999,29.96198],"type":"Point"}
}