{
  "type": "Feature",
  "properties": {
    "iso:country":"US",
    "sg:address":"2025 Nelson St",
    "sg:city":"Shreveport",
    "sg:classifiers":[
        {
            "category":"Wholesale",
            "subcategory":"Auto Parts",
            "type":"Manufacturing & Wholesale Goods"
        }
    ],
    "sg:phone":"+1 318 429 8403",
    "sg:postcode":"71107",
    "sg:province":"LA",
    "sg:tags":[
        "equipment",
        "truck"
    ],
    "wof:name":"Truck Pro",
    "wof:placetype":"venue"
},
  "geometry": {"coordinates":[-93.774969,32.54457],"type":"Point"}
}