{
  "type": "Feature",
  "properties": {
    "addr:full":"2903 Bufforn St New Orleans LA 70112",
    "addr:housenumber":"2903",
    "addr:postcode":"70112",
    "addr:street":"Bufforn St",
    "iso:country":"US",
    "sg:address":"2903 Bufforn St",
    "sg:city":"New Orleans",
    "sg:classifiers":[
        {
            "category":"Real Estate",
            "subcategory":"Real Estate Services",
            "type":"Services"
        }
    ],
    "sg:phone":"+1 504 271 0914",
    "sg:postcode":"70112",
    "sg:province":"LA",
    "sg:tags":[
        "management",
        "property"
    ],
    "sg:website":"www.tlcrealty-inc.com",
    "wof:name":"Tlc Realty Inc",
    "wof:placetype":"venue"
},
  "geometry": {"coordinates":[-89.96111999999999,29.944986],"type":"Point"}
}