{
  "type": "Feature",
  "properties": {
    "addr:full":"3012 N 8th St West Monroe LA 71291",
    "addr:housenumber":"3012",
    "addr:postcode":"71291",
    "addr:street":"N 8Th St West",
    "iso:country":"US",
    "sg:address":"3012 N 8th St",
    "sg:city":"West Monroe",
    "sg:classifiers":[
        {
            "category":"Government",
            "subcategory":"Office",
            "type":"Public Place"
        }
    ],
    "sg:phone":"+1 318 397 7935",
    "sg:postcode":"71291",
    "sg:province":"LA",
    "sg:tags":[
        "federal",
        "program",
        "adm"
    ],
    "wof:name":"US Small Business Adm",
    "wof:placetype":"venue"
},
  "geometry": {"coordinates":[-92.14833900000001,32.532985],"type":"Point"}
}