{
  "type": "Feature",
  "properties": {
    "iso:country":"US",
    "sg:address":"504 Edgewood Dr",
    "sg:city":"Thibodaux",
    "sg:classifiers":[
        {
            "category":"Government",
            "subcategory":"Office",
            "type":"Public Place"
        }
    ],
    "sg:phone":"+1 985 449 0555",
    "sg:postcode":"70301",
    "sg:province":"LA",
    "sg:tags":[
        "research",
        "fellow"
    ],
    "wof:name":"Morris Grady",
    "wof:placetype":"venue"
},
  "geometry": {"coordinates":[-90.78602600000001,29.782692],"type":"Point"}
}