{
  "type": "Feature",
  "properties": {
    "iso:country":"US",
    "sg:address":"101 Berard St",
    "sg:city":"Breaux Bridge",
    "sg:classifiers":[
        {
            "category":"Government",
            "subcategory":"Office",
            "type":"Public Place"
        }
    ],
    "sg:phone":"+1 337 332 8333",
    "sg:postcode":"70517",
    "sg:province":"LA",
    "sg:tags":[
        "village"
    ],
    "wof:name":"Breaux Bridge City Planning",
    "wof:placetype":"venue"
},
  "geometry": {"coordinates":[-91.90017899999999,30.272676],"type":"Point"}
}