{
  "type": "Feature",
  "properties": {
    "addr:full":"9107 State Rte 23 Belle Chasse LA 70037",
    "addr:housenumber":"9107",
    "addr:postcode":"70037",
    "addr:street":"State Rte 23",
    "iso:country":"US",
    "sg:address":"9107 State Rte 23",
    "sg:city":"Belle Chasse",
    "sg:classifiers":[
        {
            "category":"Wholesale",
            "subcategory":"Machinery & Supplies",
            "type":"Manufacturing & Wholesale Goods"
        }
    ],
    "sg:phone":"+1 504 392 9321",
    "sg:postcode":"70037",
    "sg:province":"LA",
    "sg:tags":[
        "compressor",
        "gas"
    ],
    "wof:name":"HUB Energy Svc Inc",
    "wof:placetype":"venue"
},
  "geometry": {"coordinates":[-89.99986199999999,29.83917],"type":"Point"}
}