{
  "type": "Feature",
  "properties": {
    "iso:country":"US",
    "sg:address":"400 Canal St",
    "sg:city":"Jeanerette",
    "sg:classifiers":[
        {
            "category":"Manufacturing",
            "subcategory":"Tools & Machinery",
            "type":"Manufacturing & Wholesale Goods"
        }
    ],
    "sg:phone":"+1 337 276 6314",
    "sg:postcode":"70544",
    "sg:province":"LA",
    "sg:tags":[
        "construction"
    ],
    "sg:website":"www.honiron.com",
    "wof:name":"Honiron Corp",
    "wof:placetype":"venue"
},
  "geometry": {"coordinates":[-91.666104,29.908214],"type":"Point"}
}