{
  "type": "Feature",
  "properties": {
    "iso:country":"US",
    "sg:address":"240 Highland Dr",
    "sg:city":"Many",
    "sg:classifiers":[
        {
            "category":"Health Services",
            "subcategory":"Doctor",
            "type":"Services"
        }
    ],
    "sg:phone":"+1 318 256 3820",
    "sg:postcode":"71449",
    "sg:province":"LA",
    "sg:tags":[
        "clinic"
    ],
    "wof:name":"Sabine Medical Clinics",
    "wof:placetype":"venue"
},
  "geometry": {"coordinates":[-93.471242,31.560725],"type":"Point"}
}