{
  "type": "Feature",
  "properties": {
    "addr:full":"4629 Beau Lac Ln Metairie LA 70002",
    "addr:housenumber":"4629",
    "addr:postcode":"70002",
    "addr:street":"Beau Lac Ln",
    "iso:country":"US",
    "sg:address":"4629 Beau Lac Ln",
    "sg:city":"Metairie",
    "sg:classifiers":[
        {
            "category":"Professional",
            "type":"Services"
        }
    ],
    "sg:phone":"+1 504 888 2908",
    "sg:postcode":"70002",
    "sg:province":"LA",
    "wof:name":"Obet",
    "wof:placetype":"venue"
},
  "geometry": {"coordinates":[-90.172211,30.019589],"type":"Point"}
}