{
  "type": "Feature",
  "properties": {
    "addr:full":"701 Little Farms Ave Metairie LA 70003",
    "addr:housenumber":"701",
    "addr:postcode":"70003",
    "addr:street":"Little Farms Ave",
    "iso:country":"US",
    "sg:address":"701 Little Farms Ave",
    "sg:city":"Metairie",
    "sg:classifiers":[
        {
            "category":"Building & Trades",
            "subcategory":"Construction",
            "type":"Services"
        }
    ],
    "sg:phone":"+1 504 738 1326",
    "sg:postcode":"70003",
    "sg:province":"LA",
    "sg:tags":[
        "home",
        "improvement"
    ],
    "wof:name":"Superior Contractors",
    "wof:placetype":"venue"
},
  "geometry": {"coordinates":[-90.21337699999999,29.977521],"type":"Point"}
}