{
  "type": "Feature",
  "properties": {
    "addr:full":"409 Ave F Bogalusa LA 70427",
    "addr:housenumber":"409",
    "addr:postcode":"70427",
    "addr:street":"Ave F Bogalusa",
    "iso:country":"US",
    "sg:address":"409 Ave F",
    "sg:city":"Bogalusa",
    "sg:classifiers":[
        {
            "category":"Health Services",
            "subcategory":"Doctor",
            "type":"Services"
        }
    ],
    "sg:phone":"+1 985 735 8137",
    "sg:postcode":"70427",
    "sg:province":"LA",
    "sg:tags":[
        "physician",
        "surgeon"
    ],
    "wof:name":"Eye Surgery Ctr",
    "wof:placetype":"venue"
},
  "geometry": {"coordinates":[-89.87042599999999,30.779275],"type":"Point"}
}