{
  "type": "Feature",
  "properties": {
    "iso:country":"US",
    "sg:address":"1103 Royal Ave",
    "sg:city":"Monroe",
    "sg:classifiers":[
        {
            "category":"Professional",
            "subcategory":"Lawyer & Legal Services",
            "type":"Services"
        }
    ],
    "sg:phone":"+1 318 322 9700",
    "sg:postcode":"71201",
    "sg:province":"LA",
    "sg:tags":[
        "attorney"
    ],
    "wof:name":"Watson Mc Millin & Harrison",
    "wof:placetype":"venue"
},
  "geometry": {"coordinates":[-92.113472,32.518156],"type":"Point"}
}