{
  "type": "Feature",
  "properties": {
    "iso:country":"US",
    "sg:address":"2416 Bobwhite Dr",
    "sg:city":"Saint Bernard",
    "sg:classifiers":[
        {
            "category":"Retail",
            "subcategory":"Repair Shop",
            "type":"Services"
        }
    ],
    "sg:phone":"+1 504 682 7338",
    "sg:postcode":"70085",
    "sg:province":"LA",
    "sg:tags":[
        "refrigeration"
    ],
    "wof:name":"Louies AC & Rfrgn Svcs",
    "wof:placetype":"venue"
},
  "geometry": {"coordinates":[-89.885261,29.873077],"type":"Point"}
}