{
  "type": "Feature",
  "properties": {
    "addr:full":"211 Republic Ave Lafayette LA 70508",
    "addr:housenumber":"211",
    "addr:postcode":"70508",
    "addr:street":"Republic Ave",
    "iso:country":"US",
    "sg:address":"211 Republic Ave",
    "sg:city":"Lafayette",
    "sg:classifiers":[
        {
            "category":"Real Estate",
            "subcategory":"Real Estate Operator",
            "type":"Services"
        }
    ],
    "sg:phone":"+1 337 984 8825",
    "sg:postcode":"70508",
    "sg:province":"LA",
    "sg:tags":[
        "apartment"
    ],
    "wof:name":"Grove At Plantation",
    "wof:placetype":"venue"
},
  "geometry": {"coordinates":[-92.044038,30.160723],"type":"Point"}
}