{
  "type": "Feature",
  "properties": {
    "iso:country":"US",
    "sg:address":"200 N Columbia St",
    "sg:city":"Covington",
    "sg:classifiers":[
        {
            "category":"Professional",
            "subcategory":"Lawyer & Legal Services",
            "type":"Services"
        }
    ],
    "sg:phone":"+1 985 892 4024",
    "sg:postcode":"70433",
    "sg:province":"LA",
    "sg:tags":[
        "attorney"
    ],
    "wof:name":"Grace P Gremillion",
    "wof:placetype":"venue"
},
  "geometry": {"coordinates":[-90.09422000000001,30.475187],"type":"Point"}
}