{
  "type": "Feature",
  "properties": {
    "iso:country":"US",
    "sg:address":"251 Florida St",
    "sg:city":"Baton Rouge",
    "sg:classifiers":[
        {
            "category":"Professional",
            "subcategory":"Lawyer & Legal Services",
            "type":"Services"
        }
    ],
    "sg:phone":"+1 225 709 9999",
    "sg:postcode":"70801",
    "sg:province":"LA",
    "sg:tags":[
        "attorney"
    ],
    "wof:name":"Don L Jr Attorney At Law",
    "wof:placetype":"venue"
},
  "geometry": {"coordinates":[-91.188802,30.449367],"type":"Point"}
}