{
  "type": "Feature",
  "properties": {
    "iso:country":"US",
    "sg:address":"3859 Choctaw Dr",
    "sg:city":"Baton Rouge",
    "sg:classifiers":[
        {
            "category":"Shopping",
            "subcategory":"Shoes",
            "type":"Retail Goods"
        }
    ],
    "sg:phone":"+1 225 355 4232",
    "sg:postcode":"70805",
    "sg:province":"LA",
    "wof:name":"Athlete's Foot",
    "wof:placetype":"venue"
},
  "geometry": {"coordinates":[-91.15022999999999,30.470407],"type":"Point"}
}