{
  "type": "Feature",
  "properties": {
    "iso:country":"US",
    "sg:address":"Oakwood Food Ct",
    "sg:city":"Gretna",
    "sg:classifiers":[
        {
            "category":"Restaurant",
            "type":"Food & Drink"
        }
    ],
    "sg:phone":"+1 504 368 3305",
    "sg:postcode":"70053",
    "sg:province":"LA",
    "sg:tags":[
        "pizza"
    ],
    "wof:name":"Cafe Ditali's",
    "wof:placetype":"venue"
},
  "geometry": {"coordinates":[-90.049896,29.914],"type":"Point"}
}