{
  "type": "Feature",
  "properties": {
    "iso:country":"US",
    "sg:address":"1300 4th St",
    "sg:city":"Westwego",
    "sg:classifiers":[
        {
            "category":"Real Estate",
            "subcategory":"Real Estate Operator",
            "type":"Services"
        }
    ],
    "sg:phone":"+1 504 861 4357",
    "sg:postcode":"70094",
    "sg:province":"LA",
    "sg:tags":[
        "mall",
        "shopping",
        "center"
    ],
    "wof:name":"Westwego Shopping Ctr",
    "wof:placetype":"venue"
},
  "geometry": {"coordinates":[-90.133895,29.903316],"type":"Point"}
}