{
  "type": "Feature",
  "properties": {
    "addr:full":"41208 Tiffany Rd Prairieville LA 70769",
    "addr:housenumber":"41208",
    "addr:postcode":"70769",
    "addr:street":"Tiffany Rd",
    "iso:country":"US",
    "sg:address":"41208 Tiffany Rd",
    "sg:city":"Prairieville",
    "sg:classifiers":[
        {
            "category":"Freight",
            "type":"Transportation"
        }
    ],
    "sg:phone":"+1 225 622 3976",
    "sg:postcode":"70769",
    "sg:province":"LA",
    "sg:tags":[
        "operator",
        "local",
        "trucking"
    ],
    "wof:name":"Mark S Trucking",
    "wof:placetype":"venue"
},
  "geometry": {"coordinates":[-90.918255,30.311521],"type":"Point"}
}