{
  "type": "Feature",
  "properties": {
    "addr:full":"11652 Investor Ave Baton Rouge LA 70809",
    "addr:housenumber":"11652",
    "addr:postcode":"70809",
    "addr:street":"Investor Ave",
    "iso:country":"US",
    "sg:address":"11652 Investor Ave",
    "sg:city":"Baton Rouge",
    "sg:classifiers":[
        {
            "category":"Building & Trades",
            "subcategory":"Construction",
            "type":"Services"
        }
    ],
    "sg:phone":"+1 225 756 0458",
    "sg:postcode":"70809",
    "sg:province":"LA",
    "sg:tags":[
        "general",
        "contractor"
    ],
    "wof:name":"Ronnie Howard Construction",
    "wof:placetype":"venue"
},
  "geometry": {"coordinates":[-91.051306,30.391905],"type":"Point"}
}