{
  "type": "Feature",
  "properties": {
    "iso:country":"US",
    "sg:address":"800 Birdnest Rd",
    "sg:city":"Lake Charles",
    "sg:classifiers":[
        {
            "category":"Freight",
            "type":"Transportation"
        }
    ],
    "sg:phone":"+1 337 855 6798",
    "sg:postcode":"70611",
    "sg:province":"LA",
    "sg:tags":[
        "operator",
        "trucking"
    ],
    "wof:name":"M G Nixon",
    "wof:placetype":"venue"
},
  "geometry": {"coordinates":[-93.179643,30.359152],"type":"Point"}
}