{
  "type": "Feature",
  "properties": {
    "addr:full":"5808 Cameron St Scott LA 70583",
    "addr:housenumber":"5808",
    "addr:postcode":"70583",
    "addr:street":"Cameron St",
    "iso:country":"US",
    "sg:address":"5808 Cameron St",
    "sg:city":"Scott",
    "sg:classifiers":[
        {
            "category":"Banks & Credit Unions",
            "subcategory":"Bank",
            "type":"Services"
        }
    ],
    "sg:phone":"+1 337 232 0642",
    "sg:postcode":"70583",
    "sg:province":"LA",
    "sg:website":"www.statefarm.com",
    "wof:name":"State Farm Ins Co",
    "wof:placetype":"venue"
},
  "geometry": {"coordinates":[-92.093597,30.233601],"type":"Point"}
}