{
  "type": "Feature",
  "properties": {
    "iso:country":"US",
    "sg:address":"200 S Audubon Blvd",
    "sg:city":"Lafayette",
    "sg:classifiers":[
        {
            "category":"Professional",
            "subcategory":"Management & Consulting",
            "type":"Services"
        }
    ],
    "sg:phone":"+1 337 233 8973",
    "sg:postcode":"70503",
    "sg:province":"LA",
    "sg:tags":[
        "consultant",
        "business"
    ],
    "wof:name":"Lingua Inc",
    "wof:placetype":"venue"
},
  "geometry": {"coordinates":[-92.01036499999999,30.200003],"type":"Point"}
}