{
  "type": "Feature",
  "properties": {
    "iso:country":"US",
    "sg:address":"2044 Magazine St",
    "sg:city":"New Orleans",
    "sg:classifiers":[
        {
            "category":"Shopping",
            "subcategory":"Clothing, Apparel, & Fashions",
            "type":"Retail Goods"
        }
    ],
    "sg:phone":"+1 504 671 8300",
    "sg:postcode":"70130",
    "sg:province":"LA",
    "sg:tags":[
        "lingerie"
    ],
    "wof:name":"House Of Lounge",
    "wof:placetype":"venue"
},
  "geometry": {"coordinates":[-90.07526,29.93051],"type":"Point"}
}