{
  "type": "Feature",
  "properties": {
    "addr:full":"702 Washington St Franklinton LA 70438",
    "addr:housenumber":"702",
    "addr:postcode":"70438",
    "addr:street":"Washington St",
    "iso:country":"US",
    "sg:address":"702 Washington St",
    "sg:city":"Franklinton",
    "sg:classifiers":[
        {
            "category":"Restaurant",
            "type":"Food & Drink"
        }
    ],
    "sg:phone":"+1 985 795 9556",
    "sg:postcode":"70438",
    "sg:province":"LA",
    "wof:name":"Mc Donald's",
    "wof:placetype":"venue"
},
  "geometry": {"coordinates":[-90.15817,30.844751],"type":"Point"}
}