{
  "type": "Feature",
  "properties": {
    "iso:country":"US",
    "sg:address":"9160 Mansfield Rd",
    "sg:city":"Shreveport",
    "sg:classifiers":[
        {
            "category":"Shopping",
            "subcategory":"Department Store",
            "type":"Retail Goods"
        }
    ],
    "sg:phone":"+1 318 686 1369",
    "sg:postcode":"71118",
    "sg:province":"LA",
    "sg:tags":[
        "shop"
    ],
    "wof:name":"Dollar Tree",
    "wof:placetype":"venue"
},
  "geometry": {"coordinates":[-93.803079,32.403812],"type":"Point"}
}