{
  "type": "Feature",
  "properties": {
    "iso:country":"US",
    "sg:address":"557 Bayou Ln",
    "sg:city":"Pineville",
    "sg:classifiers":[
        {
            "category":"Professional",
            "type":"Services"
        }
    ],
    "sg:phone":"+1 318 240 9681",
    "sg:postcode":"71331",
    "sg:province":"LA",
    "wof:name":"Southern Laser Company Inc",
    "wof:placetype":"venue"
},
  "geometry": {"coordinates":[-92.196063,31.197999],"type":"Point"}
}