{
  "type": "Feature",
  "properties": {
    "iso:country":"US",
    "sg:address":"13507 Lake Charles Hwy",
    "sg:city":"Leesville",
    "sg:classifiers":[
        {
            "category":"Wholesale",
            "subcategory":"Scrap",
            "type":"Manufacturing & Wholesale Goods"
        }
    ],
    "sg:phone":"+1 337 537 3740",
    "sg:postcode":"71446",
    "sg:province":"LA",
    "sg:tags":[
        "recycling",
        "center"
    ],
    "wof:name":"Taylor & Anderson Recycling",
    "wof:placetype":"venue"
},
  "geometry": {"coordinates":[-93.274942,31.01259],"type":"Point"}
}