{
  "type": "Feature",
  "properties": {
    "iso:country":"US",
    "sg:address":"906 E 5th St",
    "sg:city":"Natchitoches",
    "sg:classifiers":[
        {
            "category":"Professional",
            "subcategory":"Accounting & Tax Preparation",
            "type":"Services"
        }
    ],
    "sg:phone":"+1 318 354 9488",
    "sg:postcode":"71457",
    "sg:province":"LA",
    "sg:tags":[
        "billing"
    ],
    "wof:name":"Morgan Cox Inc",
    "wof:placetype":"venue"
},
  "geometry": {"coordinates":[-93.078131,31.765967],"type":"Point"}
}