{
  "type": "Feature",
  "properties": {
    "addr:full":"719 N Eastern Ave Crowley LA 70526",
    "addr:housenumber":"719",
    "addr:postcode":"70526",
    "addr:street":"N Eastern Ave",
    "iso:country":"US",
    "sg:address":"719 N Eastern Ave",
    "sg:city":"Crowley",
    "sg:classifiers":[
        {
            "category":"Health Services",
            "subcategory":"Doctor",
            "type":"Services"
        }
    ],
    "sg:phone":"+1 337 783 5900",
    "sg:postcode":"70526",
    "sg:province":"LA",
    "sg:tags":[
        "clinic"
    ],
    "wof:name":"Cannon Family Medicine",
    "wof:placetype":"venue"
},
  "geometry": {"coordinates":[-92.36753299999999,30.220219],"type":"Point"}
}