{
  "type": "Feature",
  "properties": {
    "iso:country":"US",
    "sg:address":"230 Charles Dr",
    "sg:city":"Lafayette",
    "sg:classifiers":[
        {
            "category":"Building & Trades",
            "subcategory":"Landscaping Services",
            "type":"Services"
        }
    ],
    "sg:phone":"+1 337 233 5887",
    "sg:postcode":"70508",
    "sg:province":"LA",
    "sg:tags":[
        "tree"
    ],
    "wof:name":"Lantier Tree Expert Co",
    "wof:placetype":"venue"
},
  "geometry": {"coordinates":[-91.98572900000001,30.154971],"type":"Point"}
}