{
  "type": "Feature",
  "properties": {
    "iso:country":"US",
    "sg:address":"209 NE Railroad Ave",
    "sg:city":"Ville Platte",
    "sg:classifiers":[
        {
            "category":"Food & Beverages",
            "subcategory":"Groceries & Convenience Stores",
            "type":"Retail Goods"
        }
    ],
    "sg:phone":"+1 337 363 5384",
    "sg:postcode":"70586",
    "sg:province":"LA",
    "sg:tags":[
        "grocer"
    ],
    "wof:name":"Ortego's Food Lane",
    "wof:placetype":"venue"
},
  "geometry": {"coordinates":[-92.2726,30.689695],"type":"Point"}
}