{
  "type": "Feature",
  "properties": {
    "iso:country":"US",
    "sg:address":"8050 Scenic Hwy",
    "sg:city":"Baton Rouge",
    "sg:classifiers":[
        {
            "category":"Food & Beverages",
            "subcategory":"Candy",
            "type":"Retail Goods"
        }
    ],
    "sg:phone":"+1 225 774 7726",
    "sg:postcode":"70807",
    "sg:province":"LA",
    "sg:tags":[
        "confectionery"
    ],
    "wof:name":"Gourmet Goodies By Mensia",
    "wof:placetype":"venue"
},
  "geometry": {"coordinates":[-91.179143,30.520606],"type":"Point"}
}