{
  "type": "Feature",
  "properties": {
    "iso:country":"US",
    "sg:address":"7862 Highway 23",
    "sg:city":"Belle Chasse",
    "sg:classifiers":[
        {
            "category":"Food & Beverages",
            "subcategory":"Bakery",
            "type":"Retail Goods"
        }
    ],
    "sg:phone":"+1 504 394 7951",
    "sg:postcode":"70037",
    "sg:province":"LA",
    "sg:tags":[
        "sandwich"
    ],
    "wof:name":"McDonald's",
    "wof:placetype":"venue"
},
  "geometry": {"coordinates":[-89.996803,29.862801],"type":"Point"}
}