{
  "type": "Feature",
  "properties": {
    "iso:country":"US",
    "sg:address":"33700 Bowie St",
    "sg:city":"White Castle",
    "sg:classifiers":[
        {
            "category":"Organizations",
            "subcategory":"Religious Organization",
            "type":"Services"
        }
    ],
    "sg:phone":"+1 225 545 8916",
    "sg:postcode":"70788",
    "sg:province":"LA",
    "wof:name":"Hold Up Light Ministry Church",
    "wof:placetype":"venue"
},
  "geometry": {"coordinates":[-91.153482,30.15051],"type":"Point"}
}