{
  "type": "Feature",
  "properties": {
    "addr:full":"609 E Gibson St Covington LA 70433",
    "addr:housenumber":"609",
    "addr:postcode":"70433",
    "addr:street":"E Gibson St",
    "iso:country":"US",
    "sg:address":"609 E Gibson St",
    "sg:city":"Covington",
    "sg:classifiers":[
        {
            "category":"Health Services",
            "subcategory":"Health Practitioner",
            "type":"Services"
        }
    ],
    "sg:phone":"+1 985 871 0788",
    "sg:postcode":"70433",
    "sg:province":"LA",
    "wof:name":"Mary J Frost",
    "wof:placetype":"venue"
},
  "geometry": {"coordinates":[-90.093419,30.477138],"type":"Point"}
}