{
  "type": "Feature",
  "properties": {
    "iso:country":"US",
    "sg:address":"22799 N Oak St",
    "sg:city":"Vacherie",
    "sg:classifiers":[
        {
            "category":"Freight",
            "type":"Transportation"
        }
    ],
    "sg:phone":"+1 225 265 7797",
    "sg:postcode":"70090",
    "sg:province":"LA",
    "sg:tags":[
        "operator",
        "local",
        "trucking"
    ],
    "wof:name":"Hymel Trucking Inc",
    "wof:placetype":"venue"
},
  "geometry": {"coordinates":[-90.702315,29.947453],"type":"Point"}
}