{
  "type": "Feature",
  "properties": {
    "addr:full":"12031 Plank Rd Baton Rouge LA 70811",
    "addr:housenumber":"12031",
    "addr:postcode":"70811",
    "addr:street":"Plank Rd",
    "iso:country":"US",
    "sg:address":"12031 Plank Rd",
    "sg:city":"Baton Rouge",
    "sg:classifiers":[
        {
            "category":"Shopping",
            "type":"Retail Goods"
        }
    ],
    "sg:phone":"+1 225 775 1011",
    "sg:postcode":"70811",
    "sg:province":"LA",
    "sg:tags":[
        "cosmetic",
        "perfume"
    ],
    "sg:website":"www.basichairbows.com",
    "wof:name":"BASICHAIRBOWS.COM",
    "wof:placetype":"venue"
},
  "geometry": {"coordinates":[-91.13444800000001,30.555531],"type":"Point"}
}