{
  "type": "Feature",
  "properties": {
    "iso:country":"US",
    "sg:address":"102 William O Stutes St",
    "sg:city":"Lafayette",
    "sg:classifiers":[
        {
            "category":"Retail",
            "subcategory":"Veterinary Services",
            "type":"Services"
        }
    ],
    "sg:phone":"+1 337 981 9299",
    "sg:postcode":"70506",
    "sg:province":"LA",
    "sg:tags":[
        "veterinarian"
    ],
    "wof:name":"Orgeron Veterinary Hospital",
    "wof:placetype":"venue"
},
  "geometry": {"coordinates":[-92.076645,30.184978],"type":"Point"}
}