{
  "type": "Feature",
  "properties": {
    "iso:country":"US",
    "sg:address":"307 Howard Ave",
    "sg:city":"Houma",
    "sg:classifiers":[
        {
            "category":"Autos & Motor Vehicles",
            "subcategory":"Auto Supplies",
            "type":"Retail Goods"
        }
    ],
    "sg:phone":"+1 985 876 1441",
    "sg:postcode":"70363",
    "sg:province":"LA",
    "sg:tags":[
        "tire"
    ],
    "wof:name":"Tcb Tire & Auto Repair Inc",
    "wof:placetype":"venue"
},
  "geometry": {"coordinates":[-90.697399,29.590617],"type":"Point"}
}