{
  "type": "Feature",
  "properties": {
    "addr:full":"145 Harding St New Orleans LA 70121",
    "addr:housenumber":"145",
    "addr:postcode":"70121",
    "addr:street":"Harding St",
    "iso:country":"US",
    "sg:address":"145 Harding St",
    "sg:city":"New Orleans",
    "sg:classifiers":[
        {
            "category":"Building & Trades",
            "subcategory":"Construction",
            "type":"Services"
        }
    ],
    "sg:phone":"+1 504 834 8538",
    "sg:postcode":"70121",
    "sg:province":"LA",
    "sg:tags":[
        "resurfacing",
        "laying",
        "refinishing",
        "floor"
    ],
    "wof:name":"Southern Floors",
    "wof:placetype":"venue"
},
  "geometry": {"coordinates":[-90.143226,29.959548],"type":"Point"}
}