{
  "type": "Feature",
  "properties": {
    "iso:country":"US",
    "sg:address":"2920 Johnston St",
    "sg:city":"Lafayette",
    "sg:classifiers":[
        {
            "category":"Utilities",
            "subcategory":"Mobile Phone",
            "type":"Services"
        }
    ],
    "sg:phone":"+1 337 231 0009",
    "sg:postcode":"70503",
    "sg:province":"LA",
    "sg:tags":[
        "telephone",
        "cellular"
    ],
    "wof:name":"Sprint PCS",
    "wof:placetype":"venue"
},
  "geometry": {"coordinates":[-92.041628,30.20546],"type":"Point"}
}