{
  "type": "Feature",
  "properties": {
    "addr:full":"5135 Bluebonnet Rd Baton Rouge LA 70809",
    "addr:housenumber":"5135",
    "addr:postcode":"70809",
    "addr:street":"Bluebonnet Rd",
    "iso:country":"US",
    "sg:address":"5135 Bluebonnet Rd",
    "sg:city":"Baton Rouge",
    "sg:classifiers":[
        {
            "category":"Real Estate",
            "subcategory":"Developer",
            "type":"Services"
        }
    ],
    "sg:phone":"+1 225 293 2328",
    "sg:postcode":"70809",
    "sg:province":"LA",
    "wof:name":"Business Investment Group",
    "wof:placetype":"venue"
},
  "geometry": {"coordinates":[-91.08384700000001,30.40104],"type":"Point"}
}