{
  "type": "Feature",
  "properties": {
    "iso:country":"US",
    "sg:address":"103 Northpark Blvd",
    "sg:city":"Covington",
    "sg:classifiers":[
        {
            "category":"Banks & Credit Unions",
            "subcategory":"Investment Brokerage",
            "type":"Services"
        }
    ],
    "sg:phone":"+1 985 893 7772",
    "sg:postcode":"70433",
    "sg:province":"LA",
    "sg:tags":[
        "security"
    ],
    "wof:name":"Morgan Stanley",
    "wof:placetype":"venue"
},
  "geometry": {"coordinates":[-90.083665,30.44291],"type":"Point"}
}