{
  "type": "Feature",
  "properties": {
    "addr:full":"14989 River Rd Hahnville LA 70057",
    "addr:housenumber":"14989",
    "addr:postcode":"70057",
    "addr:street":"River Rd",
    "iso:country":"US",
    "sg:address":"14989 River Rd",
    "sg:city":"Hahnville",
    "sg:classifiers":[
        {
            "category":"Organizations",
            "subcategory":"Religious Organization",
            "type":"Services"
        }
    ],
    "sg:phone":"+1 985 783 2624",
    "sg:postcode":"70057",
    "sg:province":"LA",
    "sg:tags":[
        "church"
    ],
    "wof:name":"Bethlehem Baptist Church",
    "wof:placetype":"venue"
},
  "geometry": {"coordinates":[-90.403674,29.96097],"type":"Point"}
}