{
  "type": "Feature",
  "properties": {
    "addr:full":"425 Industrial Pkwy Lafayette LA 70508",
    "addr:housenumber":"425",
    "addr:postcode":"70508",
    "addr:street":"Industrial Pkwy",
    "iso:country":"US",
    "sg:address":"425 Industrial Pkwy",
    "sg:city":"Lafayette",
    "sg:classifiers":[
        {
            "category":"Wholesale",
            "subcategory":"Machinery & Supplies",
            "type":"Manufacturing & Wholesale Goods"
        },
        {
            "category":"Mining & Drilling",
            "type":"Manufacturing & Wholesale Goods"
        }
    ],
    "sg:phone":"+1 337 234 0405",
    "sg:postcode":"70508",
    "sg:province":"LA",
    "sg:tags":[
        "oil",
        "additive",
        "material",
        "well",
        "fluid",
        "mud"
    ],
    "wof:name":"J & J Specialty Products Inc",
    "wof:placetype":"venue"
},
  "geometry": {"coordinates":[-91.99674,30.181894],"type":"Point"}
}