{
  "type": "Feature",
  "properties": {
    "addr:full":"2706 Shed Rd Bossier City LA 71111",
    "addr:housenumber":"2706",
    "addr:postcode":"71111",
    "addr:street":"Shed Rd",
    "iso:country":"US",
    "sg:address":"2706 Shed Rd",
    "sg:city":"Bossier City",
    "sg:classifiers":[
        {
            "category":"Health Services",
            "subcategory":"Doctor",
            "type":"Services"
        }
    ],
    "sg:phone":"+1 318 747 5272",
    "sg:postcode":"71111",
    "sg:province":"LA",
    "sg:tags":[
        "physician",
        "surgeon"
    ],
    "wof:name":"Willis'Knighton Pediatrics",
    "wof:placetype":"venue"
},
  "geometry": {"coordinates":[-93.705451,32.532234],"type":"Point"}
}