{
  "type": "Feature",
  "properties": {
    "iso:country":"US",
    "sg:address":"106 Charlene St",
    "sg:city":"New Roads",
    "sg:classifiers":[
        {
            "category":"Real Estate",
            "subcategory":"Real Estate Agent",
            "type":"Services"
        }
    ],
    "sg:phone":"+1 225 638 9559",
    "sg:postcode":"70760",
    "sg:province":"LA",
    "wof:name":"Callegari Realty",
    "wof:placetype":"venue"
},
  "geometry": {"coordinates":[-91.45065,30.689525],"type":"Point"}
}