{
  "type": "Feature",
  "properties": {
    "addr:full":"95 E Fairway Dr Covington LA 70433",
    "addr:housenumber":"95",
    "addr:postcode":"70433",
    "addr:street":"E Fairway Dr",
    "iso:country":"US",
    "sg:address":"95 E Fairway Dr",
    "sg:city":"Covington",
    "sg:classifiers":[
        {
            "category":"Health Services",
            "subcategory":"Hospital",
            "type":"Services"
        }
    ],
    "sg:phone":"+1 985 867 3800",
    "sg:postcode":"70433",
    "sg:province":"LA",
    "wof:name":"Lakeview Regional Medical Ctr",
    "wof:placetype":"venue"
},
  "geometry": {"coordinates":[-90.08196100000001,30.409866],"type":"Point"}
}