{
  "type": "Feature",
  "properties": {
    "addr:full":"5150 Mounes St New Orleans LA 70123",
    "addr:housenumber":"5150",
    "addr:postcode":"70123",
    "addr:street":"Mounes St",
    "iso:country":"US",
    "sg:address":"5150 Mounes St",
    "sg:city":"New Orleans",
    "sg:classifiers":[
        {
            "category":"Travel",
            "subcategory":"Hotels & Motels",
            "type":"Entertainment"
        }
    ],
    "sg:phone":"+1 504 733 5646",
    "sg:postcode":"70123",
    "sg:province":"LA",
    "sg:tags":[
        "operation"
    ],
    "wof:name":"Hampton Inn",
    "wof:placetype":"venue"
},
  "geometry": {"coordinates":[-90.18360800000001,29.958031],"type":"Point"}
}