{
  "type": "Feature",
  "properties": {
    "iso:country":"US",
    "sg:address":"2426 W Congress St",
    "sg:city":"Lafayette",
    "sg:classifiers":[
        {
            "category":"Restaurant",
            "type":"Food & Drink"
        }
    ],
    "sg:phone":"+1 337 572 9966",
    "sg:postcode":"70506",
    "sg:province":"LA",
    "wof:name":"Raising Canes",
    "wof:placetype":"venue"
},
  "geometry": {"coordinates":[-92.048028,30.214295],"type":"Point"}
}