{
  "type": "Feature",
  "properties": {
    "iso:country":"US",
    "sg:address":"6100 Renoir Ave",
    "sg:city":"Baton Rouge",
    "sg:classifiers":[
        {
            "category":"Organizations",
            "subcategory":"Religious Organization",
            "type":"Services"
        }
    ],
    "sg:phone":"+1 225 218 9555",
    "sg:postcode":"70806",
    "sg:province":"LA",
    "sg:tags":[
        "church"
    ],
    "wof:name":"Abundant Harvest Refuge Svc",
    "wof:placetype":"venue"
},
  "geometry": {"coordinates":[-91.12525599999999,30.460926],"type":"Point"}
}