{
  "type": "Feature",
  "properties": {
    "iso:country":"US",
    "sg:address":"207 Farmington Dr",
    "sg:city":"Lafayette",
    "sg:classifiers":[
        {
            "category":"Banks & Credit Unions",
            "subcategory":"Investment Brokerage",
            "type":"Services"
        }
    ],
    "sg:phone":"+1 337 984 2157",
    "sg:postcode":"70503",
    "sg:province":"LA",
    "sg:tags":[
        "advisory"
    ],
    "wof:name":"Daugherty Investmnts L L C",
    "wof:placetype":"venue"
},
  "geometry": {"coordinates":[-92.061226,30.163703],"type":"Point"}
}