{
  "type": "Feature",
  "properties": {
    "iso:country":"US",
    "sg:address":"9542 Brookline Ave",
    "sg:city":"Baton Rouge",
    "sg:classifiers":[
        {
            "category":"Professional",
            "subcategory":"Research",
            "type":"Services"
        }
    ],
    "sg:phone":"+1 225 293 1506",
    "sg:postcode":"70809",
    "sg:province":"LA",
    "sg:tags":[
        "environmental",
        "ecological"
    ],
    "wof:name":"Intek Corp",
    "wof:placetype":"venue"
},
  "geometry": {"coordinates":[-91.080561,30.428156],"type":"Point"}
}