{
  "type": "Feature",
  "properties": {
    "addr:full":"779 Hwy 18 Edgard LA 70049",
    "addr:housenumber":"779",
    "addr:postcode":"70049",
    "addr:street":"Hwy 18 Edgard La",
    "iso:country":"US",
    "sg:address":"779 Hwy 18",
    "sg:city":"Edgard",
    "sg:classifiers":[
        {
            "category":"Personal",
            "subcategory":"Barber",
            "type":"Services"
        }
    ],
    "sg:phone":"+1 985 497 8825",
    "sg:postcode":"70049",
    "sg:province":"LA",
    "wof:name":"William's Barber Shop",
    "wof:placetype":"venue"
},
  "geometry": {"coordinates":[-90.500742,30.04685],"type":"Point"}
}