{
  "type": "Feature",
  "properties": {
    "iso:country":"US",
    "sg:address":"110 Breard St",
    "sg:city":"Monroe",
    "sg:classifiers":[
        {
            "category":"Wholesale",
            "subcategory":"Electrical",
            "type":"Manufacturing & Wholesale Goods"
        }
    ],
    "sg:phone":"+1 318 322 0880",
    "sg:postcode":"71201",
    "sg:province":"LA",
    "sg:tags":[
        "alarm",
        "burglar",
        "system"
    ],
    "sg:website":"www.diamondsecurity.biz",
    "wof:name":"Diamond Security & Comms",
    "wof:placetype":"venue"
},
  "geometry": {"coordinates":[-92.11903599999999,32.50474],"type":"Point"}
}