{
  "type": "Feature",
  "properties": {
    "iso:country":"US",
    "sg:address":"667 N Foster Dr",
    "sg:city":"Baton Rouge",
    "sg:classifiers":[
        {
            "category":"Food & Beverages",
            "subcategory":"Meat & Fish",
            "type":"Retail Goods"
        }
    ],
    "sg:phone":"+1 225 928 7214",
    "sg:postcode":"70806",
    "sg:province":"LA",
    "sg:tags":[
        "seafood"
    ],
    "wof:name":"John's Seafood Market",
    "wof:placetype":"venue"
},
  "geometry": {"coordinates":[-91.13926600000001,30.454413],"type":"Point"}
}