{
  "type": "Feature",
  "properties": {
    "iso:country":"US",
    "sg:address":"5330 Hwy 114",
    "sg:city":"Mansura",
    "sg:phone":"+1 318 964 2380",
    "sg:postcode":"71350",
    "sg:province":"LA",
    "sg:tags":[
        "farm",
        "field",
        "crop"
    ],
    "wof:name":"Chad Helminger Farms",
    "wof:placetype":"venue"
},
  "geometry": {"coordinates":[-92.08968900000001,31.05389],"type":"Point"}
}