{
  "type": "Feature",
  "properties": {
    "iso:country":"US",
    "sg:address":"10605 Sugar Maple Ave",
    "sg:city":"Baton Rouge",
    "sg:classifiers":[
        {
            "category":"Organizations",
            "subcategory":"Religious Organization",
            "type":"Services"
        }
    ],
    "sg:phone":"+1 225 291 5386",
    "sg:postcode":"70809",
    "sg:province":"LA",
    "wof:name":"J Cody Leger",
    "wof:placetype":"venue"
},
  "geometry": {"coordinates":[-91.064443,30.398705],"type":"Point"}
}