{
  "type": "Feature",
  "properties": {
    "iso:country":"US",
    "sg:address":"416 Post Oak Rd",
    "sg:city":"Sulphur",
    "sg:classifiers":[
        {
            "category":"Professional",
            "subcategory":"Testing Lab",
            "type":"Services"
        }
    ],
    "sg:phone":"+1 337 625 3463",
    "sg:postcode":"70663",
    "sg:province":"LA",
    "sg:tags":[
        "calibration"
    ],
    "wof:name":"Mass Flow Technology Inc",
    "wof:placetype":"venue"
},
  "geometry": {"coordinates":[-93.35077099999999,30.234662],"type":"Point"}
}