{
  "type": "Feature",
  "properties": {
    "iso:country":"US",
    "sg:address":"805 S Ave F",
    "sg:city":"Crowley",
    "sg:classifiers":[
        {
            "category":"Social Services",
            "subcategory":"Child Care",
            "type":"Services"
        }
    ],
    "sg:phone":"+1 337 783 6185",
    "sg:postcode":"70526",
    "sg:province":"LA",
    "wof:name":"Elizabeth Guidry",
    "wof:placetype":"venue"
},
  "geometry": {"coordinates":[-92.37125,30.204978],"type":"Point"}
}