{
  "type": "Feature",
  "properties": {
    "addr:full":"1103 Royal Ave Monroe LA 71201",
    "addr:housenumber":"1103",
    "addr:postcode":"71201",
    "addr:street":"Royal Ave",
    "iso:country":"US",
    "sg:address":"1103 Royal Ave",
    "sg:city":"Monroe",
    "sg:classifiers":[
        {
            "category":"Professional",
            "subcategory":"Lawyer & Legal Services",
            "type":"Services"
        }
    ],
    "sg:phone":"+1 318 324 0101",
    "sg:postcode":"71201",
    "sg:province":"LA",
    "sg:tags":[
        "attorney"
    ],
    "wof:name":"Hammonds & Sills",
    "wof:placetype":"venue"
},
  "geometry": {"coordinates":[-92.113472,32.518156],"type":"Point"}
}