{
  "type": "Feature",
  "properties": {
    "addr:full":"2119 State Rte 30 Gonzales LA 70737",
    "addr:housenumber":"2119",
    "addr:postcode":"70737",
    "addr:street":"State Rte 30 Gonzales La",
    "iso:country":"US",
    "sg:address":"2119 State Rte 30",
    "sg:city":"Gonzales",
    "sg:classifiers":[
        {
            "category":"Freight",
            "type":"Transportation"
        }
    ],
    "sg:phone":"+1 225 647 1257",
    "sg:postcode":"70737",
    "sg:province":"LA",
    "sg:tags":[
        "operator",
        "local",
        "eating",
        "trucking"
    ],
    "wof:name":"USA Truck Stop",
    "wof:placetype":"venue"
},
  "geometry": {"coordinates":[-90.945542,30.210613],"type":"Point"}
}