{
  "type": "Feature",
  "properties": {
    "addr:full":"424 11th Ave Franklinton LA 70438",
    "addr:housenumber":"424",
    "addr:postcode":"70438",
    "addr:street":"11Th Ave",
    "iso:country":"US",
    "sg:address":"424 11th Ave",
    "sg:city":"Franklinton",
    "sg:classifiers":[
        {
            "category":"Insurance",
            "subcategory":"Insurance Agent",
            "type":"Services"
        }
    ],
    "sg:phone":"+1 985 839 4546",
    "sg:postcode":"70438",
    "sg:province":"LA",
    "wof:name":"Farm Bureau Insurance",
    "wof:placetype":"venue"
},
  "geometry": {"coordinates":[-90.15758,30.853252],"type":"Point"}
}