{
  "type": "Feature",
  "properties": {
    "iso:country":"US",
    "sg:address":"1827 Palmyra St",
    "sg:city":"New Orleans",
    "sg:classifiers":[
        {
            "category":"Building & Trades",
            "subcategory":"Construction",
            "type":"Services"
        }
    ],
    "sg:phone":"+1 504 581 7889",
    "sg:postcode":"70112",
    "sg:province":"LA",
    "sg:tags":[
        "general",
        "contractor"
    ],
    "wof:name":"Mid-South Mechanical",
    "wof:placetype":"venue"
},
  "geometry": {"coordinates":[-90.080938,29.95847],"type":"Point"}
}