{
  "type": "Feature",
  "properties": {
    "iso:country":"US",
    "sg:address":"10628 Thibodeaux Rd",
    "sg:city":"Denham Springs",
    "sg:classifiers":[
        {
            "category":"Professional",
            "type":"Services"
        },
        {
            "category":"Building & Trades",
            "subcategory":"Construction",
            "type":"Services"
        }
    ],
    "sg:phone":"+1 225 665 7769",
    "sg:postcode":"70706",
    "sg:province":"LA",
    "sg:tags":[
        "home",
        "improvement"
    ],
    "wof:name":"First & Select Designs",
    "wof:placetype":"venue"
},
  "geometry": {"coordinates":[-90.910415,30.551355],"type":"Point"}
}