{
  "type": "Feature",
  "properties": {
    "addr:full":"6131 Mickens Rd Baton Rouge LA 70811",
    "addr:housenumber":"6131",
    "addr:postcode":"70811",
    "addr:street":"Mickens Rd",
    "iso:country":"US",
    "sg:address":"6131 Mickens Rd",
    "sg:city":"Baton Rouge",
    "sg:classifiers":[
        {
            "category":"Personal",
            "subcategory":"Barber",
            "type":"Services"
        }
    ],
    "sg:phone":"+1 225 354 0040",
    "sg:postcode":"70811",
    "sg:province":"LA",
    "wof:name":"Cook's New Look",
    "wof:placetype":"venue"
},
  "geometry": {"coordinates":[-91.12698399999999,30.526039],"type":"Point"}
}