{
  "type": "Feature",
  "properties": {
    "iso:country":"US",
    "sg:address":"8186 Villavaso St",
    "sg:city":"St James",
    "sg:classifiers":[
        {
            "category":"Education",
            "subcategory":"School",
            "type":"Public Place"
        }
    ],
    "sg:phone":"+1 225 473 6705",
    "sg:postcode":"70086",
    "sg:province":"LA",
    "wof:name":"Welcome Headstart Ctr",
    "wof:placetype":"venue"
},
  "geometry": {"coordinates":[-90.89622,30.054556],"type":"Point"}
}