{
  "type": "Feature",
  "properties": {
    "iso:country":"US",
    "sg:address":"8051 Dorsey Pl",
    "sg:city":"Oak Ridge",
    "sg:classifiers":[
        {
            "category":"Professional",
            "subcategory":"Engineering",
            "type":"Services"
        }
    ],
    "sg:phone":"+1 318 244 5683",
    "sg:postcode":"71264",
    "sg:province":"LA",
    "sg:tags":[
        "architectural"
    ],
    "wof:name":"Jack D Carey Jr",
    "wof:placetype":"venue"
},
  "geometry": {"coordinates":[-91.827657,32.595637],"type":"Point"}
}