{
  "type": "Feature",
  "properties": {
    "iso:country":"US",
    "sg:address":"200 Turn Row",
    "sg:city":"Lafayette",
    "sg:classifiers":[
        {
            "category":"Wholesale",
            "subcategory":"Machinery & Supplies",
            "type":"Manufacturing & Wholesale Goods"
        }
    ],
    "sg:phone":"+1 337 233 5207",
    "sg:postcode":"70508",
    "sg:province":"LA",
    "sg:tags":[
        "field",
        "oil",
        "equipment"
    ],
    "wof:name":"Jim Camel Specialty Co Inc",
    "wof:placetype":"venue"
},
  "geometry": {"coordinates":[-92.00135299999999,30.166603],"type":"Point"}
}