{
  "type": "Feature",
  "properties": {
    "iso:country":"US",
    "sg:address":"1900 S Morrison Blvd",
    "sg:city":"Hammond",
    "sg:classifiers":[
        {
            "category":"Health Services",
            "subcategory":"Hospital",
            "type":"Services"
        }
    ],
    "sg:phone":"+1 985 230 1400",
    "sg:postcode":"70403",
    "sg:province":"LA",
    "sg:tags":[
        "mental"
    ],
    "wof:name":"North Oaks Medical Ctr",
    "wof:placetype":"venue"
},
  "geometry": {"coordinates":[-90.482708,30.483959],"type":"Point"}
}