{
  "type": "Feature",
  "properties": {
    "iso:country":"US",
    "sg:address":"1319 N 7th St",
    "sg:city":"West Monroe",
    "sg:classifiers":[
        {
            "category":"Retail",
            "subcategory":"Auto Repair",
            "type":"Services"
        }
    ],
    "sg:phone":"+1 318 388 4321",
    "sg:postcode":"71291",
    "sg:province":"LA",
    "sg:tags":[
        "body",
        "automobile",
        "painting"
    ],
    "wof:name":"Auto Body Specialist",
    "wof:placetype":"venue"
},
  "geometry": {"coordinates":[-92.140202,32.507364],"type":"Point"}
}