{
  "type": "Feature",
  "properties": {
    "addr:full":"15218 Joe Rd Kaplan LA 70548",
    "addr:housenumber":"15218",
    "addr:postcode":"70548",
    "addr:street":"Joe Rd",
    "iso:country":"US",
    "sg:address":"15218 Joe Rd",
    "sg:city":"Kaplan",
    "sg:classifiers":[
        {
            "category":"Real Estate",
            "subcategory":"Real Estate Operator",
            "type":"Services"
        }
    ],
    "sg:phone":"+1 337 643 8077",
    "sg:postcode":"70548",
    "sg:province":"LA",
    "sg:tags":[
        "property",
        "lessor"
    ],
    "wof:name":"Susan B Trahan",
    "wof:placetype":"venue"
},
  "geometry": {"coordinates":[-92.359709,29.928198],"type":"Point"}
}