{
  "type": "Feature",
  "properties": {
    "iso:country":"US",
    "sg:address":"7791 Florida Blvd",
    "sg:city":"Baton Rouge",
    "sg:classifiers":[
        {
            "category":"Autos & Motor Vehicles",
            "subcategory":"Automobile Sales",
            "type":"Retail Goods"
        }
    ],
    "sg:phone":"+1 225 928 6100",
    "sg:postcode":"70806",
    "sg:province":"LA",
    "sg:tags":[
        "car",
        "dealer"
    ],
    "sg:website":"www.richardshonda.com",
    "wof:name":"Richards Honda",
    "wof:placetype":"venue"
},
  "geometry": {"coordinates":[-91.105919,30.45206],"type":"Point"}
}