{
  "type": "Feature",
  "properties": {
    "addr:full":"3888 Victoria Dr Baton Rouge LA 70812",
    "addr:housenumber":"3888",
    "addr:postcode":"70812",
    "addr:street":"Victoria Dr",
    "iso:country":"US",
    "sg:address":"3888 Victoria Dr",
    "sg:city":"Baton Rouge",
    "sg:classifiers":[
        {
            "category":"Building & Trades",
            "subcategory":"Electrical",
            "type":"Services"
        }
    ],
    "sg:phone":"+1 225 358 8226",
    "sg:postcode":"70812",
    "sg:province":"LA",
    "sg:tags":[
        "electric",
        "contractor"
    ],
    "wof:name":"Delta Electric Co",
    "wof:placetype":"venue"
},
  "geometry": {"coordinates":[-91.11780400000001,30.487505],"type":"Point"}
}