{
  "type": "Feature",
  "properties": {
    "addr:full":"28315 Hwy 424 Franklinton LA 70438",
    "addr:housenumber":"28315",
    "addr:postcode":"70438",
    "addr:street":"Hwy 424",
    "iso:country":"US",
    "sg:address":"28315 Hwy 424",
    "sg:city":"Franklinton",
    "sg:classifiers":[
        {
            "category":"Building & Trades",
            "subcategory":"Electrical",
            "type":"Services"
        }
    ],
    "sg:phone":"+1 985 848 0100",
    "sg:postcode":"70438",
    "sg:province":"LA",
    "sg:tags":[
        "electric",
        "contractor"
    ],
    "wof:name":"Nevers Electrical",
    "wof:placetype":"venue"
},
  "geometry": {"coordinates":[-90.015552,30.92928],"type":"Point"}
}