{
  "type": "Feature",
  "properties": {
    "iso:country":"US",
    "sg:address":"2126 Airline Dr",
    "sg:city":"Bossier City",
    "sg:classifiers":[
        {
            "category":"Restaurant",
            "type":"Food & Drink"
        }
    ],
    "sg:phone":"+1 318 742 5484",
    "sg:postcode":"71111",
    "sg:province":"LA",
    "wof:name":"Applebee's Neighborhood Grill",
    "wof:placetype":"venue"
},
  "geometry": {"coordinates":[-93.700271,32.526772],"type":"Point"}
}