{
  "type": "Feature",
  "properties": {
    "iso:country":"US",
    "sg:address":"6723 Pines Rd",
    "sg:city":"Shreveport",
    "sg:classifiers":[
        {
            "category":"Professional",
            "subcategory":"Accounting & Tax Preparation",
            "type":"Services"
        }
    ],
    "sg:phone":"+1 318 686 3369",
    "sg:postcode":"71129",
    "sg:province":"LA",
    "sg:tags":[
        "return",
        "filing"
    ],
    "wof:name":"H & R Block Tax Svc",
    "wof:placetype":"venue"
},
  "geometry": {"coordinates":[-93.864968,32.447953],"type":"Point"}
}