{
  "type": "Feature",
  "properties": {
    "addr:full":"714 Front St Morgan City LA 70380",
    "addr:housenumber":"714",
    "addr:postcode":"70380",
    "addr:street":"Front St",
    "iso:country":"US",
    "sg:address":"714 Front St",
    "sg:city":"Morgan City",
    "sg:classifiers":[
        {
            "category":"Professional",
            "subcategory":"Business Services",
            "type":"Services"
        }
    ],
    "sg:phone":"+1 985 702 0333",
    "sg:postcode":"70380",
    "sg:province":"LA",
    "sg:tags":[
        "interior",
        "consultant",
        "design",
        "decorator"
    ],
    "wof:name":"Interiors",
    "wof:placetype":"venue"
},
  "geometry": {"coordinates":[-91.21054599999999,29.696124],"type":"Point"}
}