{
  "type": "Feature",
  "properties": {
    "iso:country":"US",
    "sg:address":"7334 Communi St",
    "sg:city":"St James",
    "sg:classifiers":[
        {
            "category":"Retail",
            "subcategory":"Laundry & Dry Cleaning",
            "type":"Services"
        },
        {
            "category":"Shopping",
            "subcategory":"Clothing, Apparel, & Fashions",
            "type":"Retail Goods"
        }
    ],
    "sg:phone":"+1 225 265 7090",
    "sg:postcode":"70086",
    "sg:province":"LA",
    "sg:tags":[
        "shop",
        "bridal"
    ],
    "wof:name":"Salaine's",
    "wof:placetype":"venue"
},
  "geometry": {"coordinates":[-90.854235,30.041521],"type":"Point"}
}