{
  "type": "Feature",
  "properties": {
    "addr:full":"3767 General Degaulle Dr New Orleans LA 70114",
    "addr:housenumber":"3767",
    "addr:postcode":"70114",
    "addr:street":"General Degaulle Dr",
    "iso:country":"US",
    "sg:address":"3767 General Degaulle Dr",
    "sg:city":"New Orleans",
    "sg:classifiers":[
        {
            "category":"Taxi",
            "type":"Transportation"
        }
    ],
    "sg:phone":"+1 504 366 1011",
    "sg:postcode":"70114",
    "sg:province":"LA",
    "sg:tags":[
        "taxicab"
    ],
    "wof:name":"New Orleans Traffic Ctr",
    "wof:placetype":"venue"
},
  "geometry": {"coordinates":[-90.021152,29.924575],"type":"Point"}
}