{
  "type": "Feature",
  "properties": {
    "addr:full":"601 Hwy 34 West Monroe LA 71292",
    "addr:housenumber":"601",
    "addr:postcode":"71292",
    "addr:street":"Hwy 34 West",
    "iso:country":"US",
    "sg:address":"601 Hwy 34",
    "sg:city":"West Monroe",
    "sg:classifiers":[
        {
            "category":"Organizations",
            "subcategory":"Religious Organization",
            "type":"Services"
        }
    ],
    "sg:phone":"+1 318 325 5671",
    "sg:postcode":"71292",
    "sg:province":"LA",
    "sg:tags":[
        "church"
    ],
    "wof:name":"Pleasant Hill Church",
    "wof:placetype":"venue"
},
  "geometry": {"coordinates":[-92.242957,32.4161],"type":"Point"}
}