{
  "type": "Feature",
  "properties": {
    "iso:country":"US",
    "sg:address":"102 High St",
    "sg:city":"Sterlington",
    "sg:classifiers":[
        {
            "category":"Government",
            "subcategory":"Post Office",
            "type":"Public Place"
        }
    ],
    "sg:phone":"+1 318 665 4560",
    "sg:postcode":"71280",
    "sg:province":"LA",
    "wof:name":"US Post Office",
    "wof:placetype":"venue"
},
  "geometry": {"coordinates":[-92.074484,32.69391],"type":"Point"}
}