{
  "type": "Feature",
  "properties": {
    "iso:country":"US",
    "sg:address":"901 Poydras St",
    "sg:city":"New Orleans",
    "sg:classifiers":[
        {
            "category":"Travel",
            "subcategory":"Hotels & Motels",
            "type":"Entertainment"
        }
    ],
    "sg:phone":"+1 504 581 5599",
    "sg:postcode":"70112",
    "sg:province":"LA",
    "wof:name":"Homewood Suites By Hilton",
    "wof:placetype":"venue"
},
  "geometry": {"coordinates":[-90.07347300000001,29.950291],"type":"Point"}
}