{
  "type": "Feature",
  "properties": {
    "addr:full":"3060 Lake St Lake Charles LA 70601",
    "addr:housenumber":"3060",
    "addr:postcode":"70601",
    "addr:street":"Lake St",
    "iso:country":"US",
    "sg:address":"3060 Lake St",
    "sg:city":"Lake Charles",
    "sg:classifiers":[
        {
            "category":"Professional",
            "subcategory":"Lawyer & Legal Services",
            "type":"Services"
        }
    ],
    "sg:phone":"+1 337 474 4442",
    "sg:postcode":"70601",
    "sg:province":"LA",
    "sg:tags":[
        "attorney"
    ],
    "wof:name":"D & M Properties",
    "wof:placetype":"venue"
},
  "geometry": {"coordinates":[-93.23242399999999,30.201189],"type":"Point"}
}