{
  "type": "Feature",
  "properties": {
    "iso:country":"US",
    "sg:address":"16530 Oakridge Dr",
    "sg:city":"Prairieville",
    "sg:classifiers":[
        {
            "category":"Building & Trades",
            "subcategory":"Construction",
            "type":"Services"
        }
    ],
    "sg:phone":"+1 225 622 0581",
    "sg:postcode":"70769",
    "sg:province":"LA",
    "sg:tags":[
        "railroad",
        "contractor"
    ],
    "wof:name":"Railworks Track Sytems Inc",
    "wof:placetype":"venue"
},
  "geometry": {"coordinates":[-90.88886599999999,30.313491],"type":"Point"}
}