{
  "type": "Feature",
  "properties": {
    "addr:full":"1131 Church Point Hwy Rayne LA 70578",
    "addr:housenumber":"1131",
    "addr:postcode":"70578",
    "addr:street":"Church Point Hwy",
    "iso:country":"US",
    "sg:address":"1131 Church Point Hwy",
    "sg:city":"Rayne",
    "sg:classifiers":[
        {
            "category":"Restaurant",
            "type":"Food & Drink"
        }
    ],
    "sg:phone":"+1 337 334 7913",
    "sg:postcode":"70578",
    "sg:province":"LA",
    "sg:website":"www.chefroy.com",
    "wof:name":"Chef Roy's Frog City Cafe",
    "wof:placetype":"venue"
},
  "geometry": {"coordinates":[-92.269813,30.253113],"type":"Point"}
}