{
  "type": "Feature",
  "properties": {
    "iso:country":"US",
    "sg:address":"221 Peach View Dr",
    "sg:city":"Ruston",
    "sg:classifiers":[
        {
            "category":"Professional",
            "subcategory":"Business Services",
            "type":"Services"
        }
    ],
    "sg:phone":"+1 318 255 9663",
    "sg:postcode":"71270",
    "sg:province":"LA",
    "sg:tags":[
        "embroidery"
    ],
    "wof:name":"Penguin Perfect Monograms",
    "wof:placetype":"venue"
},
  "geometry": {"coordinates":[-92.678391,32.569808],"type":"Point"}
}