{
  "type": "Feature",
  "properties": {
    "iso:country":"US",
    "sg:address":"668 W Prien Lake Rd",
    "sg:city":"Lake Charles",
    "sg:classifiers":[
        {
            "category":"Personal",
            "subcategory":"Beauty Salon",
            "type":"Services"
        }
    ],
    "sg:phone":"+1 337 478 7788",
    "sg:postcode":"70601",
    "sg:province":"LA",
    "wof:name":"Regis Salons",
    "wof:placetype":"venue"
},
  "geometry": {"coordinates":[-93.228921,30.198171],"type":"Point"}
}