{
  "type": "Feature",
  "properties": {
    "addr:full":"812 Champagne Dr Kenner LA 70065",
    "addr:housenumber":"812",
    "addr:postcode":"70065",
    "addr:street":"Champagne Dr",
    "iso:country":"US",
    "sg:address":"812 Champagne Dr",
    "sg:city":"Kenner",
    "sg:classifiers":[
        {
            "category":"Organizations",
            "subcategory":"Religious Organization",
            "type":"Services"
        }
    ],
    "sg:phone":"+1 504 467 9970",
    "sg:postcode":"70065",
    "sg:province":"LA",
    "sg:tags":[
        "energy",
        "management"
    ],
    "wof:name":"Trinity Energy Mgt Systems",
    "wof:placetype":"venue"
},
  "geometry": {"coordinates":[-90.257904,30.034671],"type":"Point"}
}