{
  "type": "Feature",
  "properties": {
    "iso:country":"US",
    "sg:address":"1038 N 9th St",
    "sg:city":"Monroe",
    "sg:classifiers":[
        {
            "category":"Professional",
            "subcategory":"Lawyer & Legal Services",
            "type":"Services"
        }
    ],
    "sg:phone":"+1 318 388 1655",
    "sg:postcode":"71201",
    "sg:province":"LA",
    "wof:name":"Blaine Adkins",
    "wof:placetype":"venue"
},
  "geometry": {"coordinates":[-92.116941,32.514472],"type":"Point"}
}