{
  "type": "Feature",
  "properties": {
    "addr:full":"1612 Chatsworth Dr Morgan City LA 70380",
    "addr:housenumber":"1612",
    "addr:postcode":"70380",
    "addr:street":"Chatsworth Dr",
    "iso:country":"US",
    "sg:address":"1612 Chatsworth Dr",
    "sg:city":"Morgan City",
    "sg:classifiers":[
        {
            "category":"Professional",
            "subcategory":"Secretarial Services",
            "type":"Services"
        }
    ],
    "sg:phone":"+1 985 384 7577",
    "sg:postcode":"70380",
    "sg:province":"LA",
    "sg:tags":[
        "reporting",
        "court"
    ],
    "wof:name":"Elizabeth R Mc Cleary",
    "wof:placetype":"venue"
},
  "geometry": {"coordinates":[-91.174324,29.702304],"type":"Point"}
}