{
  "type": "Feature",
  "properties": {
    "iso:country":"US",
    "sg:address":"108 Toups Ln",
    "sg:city":"Golden Meadow",
    "sg:classifiers":[
        {
            "category":"Personal",
            "subcategory":"Beauty Salon",
            "type":"Services"
        }
    ],
    "sg:phone":"+1 985 475 6739",
    "sg:postcode":"70357",
    "sg:province":"LA",
    "wof:name":"Designing Women",
    "wof:placetype":"venue"
},
  "geometry": {"coordinates":[-90.274782,29.40481],"type":"Point"}
}