{
  "type": "Feature",
  "properties": {
    "iso:country":"US",
    "sg:address":"2968 E Texas St",
    "sg:city":"Bossier City",
    "sg:classifiers":[
        {
            "category":"Restaurant",
            "type":"Food & Drink"
        }
    ],
    "sg:phone":"+1 318 741 3618",
    "sg:postcode":"71111",
    "sg:province":"LA",
    "sg:website":"www.dardenrestaurants.com",
    "wof:name":"Red Lobster Restaurant",
    "wof:placetype":"venue"
},
  "geometry": {"coordinates":[-93.706767,32.528568],"type":"Point"}
}