{
  "type": "Feature",
  "properties": {
    "addr:full":"5602 Hwy 26 Jennings LA 70546",
    "addr:housenumber":"5602",
    "addr:postcode":"70546",
    "addr:street":"Hwy 26",
    "iso:country":"US",
    "sg:address":"5602 Hwy 26",
    "sg:city":"Jennings",
    "sg:classifiers":[
        {
            "category":"Building & Trades",
            "subcategory":"Landscaping Services",
            "type":"Services"
        }
    ],
    "sg:phone":"+1 337 774 2657",
    "sg:postcode":"70546",
    "sg:province":"LA",
    "sg:tags":[
        "landscape",
        "contractor"
    ],
    "wof:name":"Hornsby Landscaping",
    "wof:placetype":"venue"
},
  "geometry": {"coordinates":[-92.672105,30.105585],"type":"Point"}
}