{
  "type": "Feature",
  "properties": {
    "iso:country":"US",
    "sg:address":"3952 Magazine St",
    "sg:city":"New Orleans",
    "sg:classifiers":[
        {
            "category":"Shopping",
            "subcategory":"Jewelry",
            "type":"Retail Goods"
        }
    ],
    "sg:phone":"+1 504 899 0064",
    "sg:postcode":"70115",
    "sg:province":"LA",
    "sg:tags":[
        "jeweler"
    ],
    "wof:name":"Mon Coeur By Janet Bruno Small",
    "wof:placetype":"venue"
},
  "geometry": {"coordinates":[-90.096507,29.921101],"type":"Point"}
}