{
  "type": "Feature",
  "properties": {
    "iso:country":"US",
    "sg:address":"3950 Jacobs Way",
    "sg:city":"Lake Charles",
    "sg:classifiers":[
        {
            "category":"Building & Trades",
            "subcategory":"Landscaping Services",
            "type":"Services"
        }
    ],
    "sg:phone":"+1 337 477 4257",
    "sg:postcode":"70605",
    "sg:province":"LA",
    "sg:tags":[
        "landscape",
        "contractor"
    ],
    "wof:name":"Calcasieu Turf Svc",
    "wof:placetype":"venue"
},
  "geometry": {"coordinates":[-93.296752,30.137532],"type":"Point"}
}