{
  "type": "Feature",
  "properties": {
    "addr:full":"1881 E Main St Ville Platte LA 70586",
    "addr:housenumber":"1881",
    "addr:postcode":"70586",
    "addr:street":"E Main St",
    "iso:country":"US",
    "sg:address":"1881 E Main St",
    "sg:city":"Ville Platte",
    "sg:classifiers":[
        {
            "category":"Utilities",
            "subcategory":"Mobile Phone",
            "type":"Services"
        }
    ],
    "sg:phone":"+1 337 363 9113",
    "sg:postcode":"70586",
    "sg:province":"LA",
    "sg:tags":[
        "telephone",
        "cellular"
    ],
    "wof:name":"Cingular Wireless",
    "wof:placetype":"venue"
},
  "geometry": {"coordinates":[-92.25527099999999,30.680349],"type":"Point"}
}