{
  "type": "Feature",
  "properties": {
    "iso:country":"US",
    "sg:address":"406 Marilyn Dr",
    "sg:city":"Lafayette",
    "sg:classifiers":[
        {
            "category":"Banks & Credit Unions",
            "subcategory":"Investment Brokerage",
            "type":"Services"
        }
    ],
    "sg:phone":"+1 337 984 7870",
    "sg:postcode":"70503",
    "sg:province":"LA",
    "sg:tags":[
        "security",
        "exploration"
    ],
    "wof:name":"Quinto Resources Inc",
    "wof:placetype":"venue"
},
  "geometry": {"coordinates":[-92.045175,30.190228],"type":"Point"}
}