{
  "type": "Feature",
  "properties": {
    "iso:country":"US",
    "sg:address":"7591 Mary Ann Cir",
    "sg:city":"Shreveport",
    "sg:classifiers":[
        {
            "category":"Building & Trades",
            "subcategory":"Construction",
            "type":"Services"
        }
    ],
    "sg:phone":"+1 318 929 3760",
    "sg:postcode":"71107",
    "sg:province":"LA",
    "sg:tags":[
        "general",
        "contractor"
    ],
    "wof:name":"Richey Construction Co Inc",
    "wof:placetype":"venue"
},
  "geometry": {"coordinates":[-93.885672,32.590196],"type":"Point"}
}