{
  "type": "Feature",
  "properties": {
    "iso:country":"US",
    "sg:address":"7745 Jefferson Hwy",
    "sg:city":"Baton Rouge",
    "sg:classifiers":[
        {
            "category":"Shopping",
            "subcategory":"Clothing, Apparel, & Fashions",
            "type":"Retail Goods"
        }
    ],
    "sg:phone":"+1 225 926 5371",
    "sg:postcode":"70809",
    "sg:province":"LA",
    "sg:tags":[
        "uniform"
    ],
    "sg:website":"www.schooltimeuniforms.com",
    "wof:name":"School Time",
    "wof:placetype":"venue"
},
  "geometry": {"coordinates":[-91.108998,30.430723],"type":"Point"}
}