{
  "type": "Feature",
  "properties": {
    "addr:full":"601 Saint Charles Ave New Orleans LA 70130",
    "addr:housenumber":"601",
    "addr:postcode":"70130",
    "addr:street":"Saint Charles Ave",
    "iso:country":"US",
    "sg:address":"601 Saint Charles Ave",
    "sg:city":"New Orleans",
    "sg:classifiers":[
        {
            "category":"Organizations",
            "subcategory":"Professional Association",
            "type":"Services"
        }
    ],
    "sg:phone":"+1 504 566 1600",
    "sg:postcode":"70130",
    "sg:province":"LA",
    "sg:tags":[
        "attorney"
    ],
    "wof:name":"Louisiana State Bar Assn",
    "wof:placetype":"venue"
},
  "geometry": {"coordinates":[-90.07107999999999,29.947861],"type":"Point"}
}