{
  "type": "Feature",
  "properties": {
    "iso:country":"US",
    "sg:address":"2310 Montgomery Ln",
    "sg:city":"Bossier City",
    "sg:classifiers":[
        {
            "category":"Building & Trades",
            "subcategory":"Construction",
            "type":"Services"
        }
    ],
    "sg:phone":"+1 318 746 4141",
    "sg:postcode":"71111",
    "sg:province":"LA",
    "sg:tags":[
        "steam",
        "cleaning"
    ],
    "wof:name":"R J Svc Inc",
    "wof:placetype":"venue"
},
  "geometry": {"coordinates":[-93.719841,32.535745],"type":"Point"}
}