{
  "type": "Feature",
  "properties": {
    "iso:country":"US",
    "sg:address":"8221 Jewella Ave",
    "sg:city":"Shreveport",
    "sg:classifiers":[
        {
            "category":"Freight",
            "type":"Transportation"
        }
    ],
    "sg:phone":"+1 318 686 1646",
    "sg:postcode":"71108",
    "sg:province":"LA",
    "sg:tags":[
        "commercial",
        "storage"
    ],
    "wof:name":"Amazingspace Storage",
    "wof:placetype":"venue"
},
  "geometry": {"coordinates":[-93.797229,32.423136],"type":"Point"}
}