{
  "type": "Feature",
  "properties": {
    "addr:full":"246 N Hollywood Rd Houma LA 70364",
    "addr:housenumber":"246",
    "addr:postcode":"70364",
    "addr:street":"N Hollywood Rd",
    "iso:country":"US",
    "sg:address":"246 N Hollywood Rd",
    "sg:city":"Houma",
    "sg:classifiers":[
        {
            "category":"Retail",
            "subcategory":"Repair Shop",
            "type":"Services"
        }
    ],
    "sg:phone":"+1 985 917 0111",
    "sg:postcode":"70364",
    "sg:province":"LA",
    "sg:tags":[
        "marine",
        "electric"
    ],
    "wof:name":"Marine Electric",
    "wof:placetype":"venue"
},
  "geometry": {"coordinates":[-90.732702,29.610307],"type":"Point"}
}