{
  "type": "Feature",
  "properties": {
    "iso:country":"US",
    "sg:address":"1450 Seabord Dr",
    "sg:city":"Baton Rouge",
    "sg:classifiers":[
        {
            "category":"Manufacturing",
            "subcategory":"Tools & Machinery",
            "type":"Manufacturing & Wholesale Goods"
        }
    ],
    "sg:phone":"+1 225 769 3051",
    "sg:postcode":"70810",
    "sg:province":"LA",
    "sg:tags":[
        "search"
    ],
    "sg:website":"www.odomhydrographic.com",
    "wof:name":"Odom Hydrographic Systems Inc",
    "wof:placetype":"venue"
},
  "geometry": {"coordinates":[-91.124548,30.357248],"type":"Point"}
}