{
  "type": "Feature",
  "properties": {
    "iso:country":"US",
    "sg:address":"527 Delmar St",
    "sg:city":"Terrytown",
    "sg:classifiers":[
        {
            "category":"Professional",
            "subcategory":"Business Services",
            "type":"Services"
        }
    ],
    "sg:phone":"+1 504 343 3700",
    "sg:postcode":"70056",
    "sg:province":"LA",
    "sg:tags":[
        "interior",
        "consultant",
        "design",
        "decorator"
    ],
    "wof:name":"Interior Decorating & Home",
    "wof:placetype":"venue"
},
  "geometry": {"coordinates":[-90.029053,29.904527],"type":"Point"}
}