{
  "type": "Feature",
  "properties": {
    "iso:country":"US",
    "sg:address":"200 Reed St",
    "sg:city":"Hammond",
    "sg:classifiers":[
        {
            "category":"Shopping",
            "subcategory":"Clothing, Apparel, & Fashions",
            "type":"Retail Goods"
        }
    ],
    "sg:phone":"+1 985 542 2425",
    "sg:postcode":"70403",
    "sg:province":"LA",
    "wof:name":"Shephard's Closet Inc",
    "wof:placetype":"venue"
},
  "geometry": {"coordinates":[-90.481499,30.496309],"type":"Point"}
}