{
  "type": "Feature",
  "properties": {
    "iso:country":"US",
    "sg:address":"405 Debonnaire Rd",
    "sg:city":"Scott",
    "sg:classifiers":[
        {
            "category":"Education",
            "subcategory":"Dance Studio",
            "type":"Public Place"
        }
    ],
    "sg:phone":"+1 337 234 0681",
    "sg:postcode":"70583",
    "sg:province":"LA",
    "sg:tags":[
        "instruction",
        "dancing"
    ],
    "wof:name":"Scott Academy Of Dance",
    "wof:placetype":"venue"
},
  "geometry": {"coordinates":[-92.081436,30.238317],"type":"Point"}
}