{
  "type": "Feature",
  "properties": {
    "iso:country":"US",
    "sg:address":"912 Riverside Dr",
    "sg:city":"Monroe",
    "sg:classifiers":[
        {
            "category":"Real Estate",
            "subcategory":"Real Estate Operator",
            "type":"Services"
        }
    ],
    "sg:phone":"+1 318 387 2310",
    "sg:postcode":"71201",
    "sg:province":"LA",
    "sg:tags":[
        "building",
        "apartment"
    ],
    "wof:name":"Riverwalk Apartments",
    "wof:placetype":"venue"
},
  "geometry": {"coordinates":[-92.12473199999999,32.508575],"type":"Point"}
}