{
  "type": "Feature",
  "properties": {
    "addr:full":"600 Camp St New Orleans LA 70130",
    "addr:housenumber":"600",
    "addr:postcode":"70130",
    "addr:street":"Camp St",
    "iso:country":"US",
    "sg:address":"600 Camp St",
    "sg:city":"New Orleans",
    "sg:classifiers":[
        {
            "category":"Building & Trades",
            "subcategory":"Cleaning & Sanitation",
            "type":"Services"
        }
    ],
    "sg:phone":"+1 504 529 5676",
    "sg:postcode":"70130",
    "sg:province":"LA",
    "sg:tags":[
        "janitor"
    ],
    "wof:name":"Goodworks Janitorial Svc",
    "wof:placetype":"venue"
},
  "geometry": {"coordinates":[-90.069862,29.947542],"type":"Point"}
}