{
  "type": "Feature",
  "properties": {
    "addr:full":"1371 W Tunnel Blvd Houma LA 70360",
    "addr:housenumber":"1371",
    "addr:postcode":"70360",
    "addr:street":"W Tunnel Blvd",
    "iso:country":"US",
    "sg:address":"1371 W Tunnel Blvd",
    "sg:city":"Houma",
    "sg:classifiers":[
        {
            "category":"Sports & Exercise",
            "subcategory":"Bowling",
            "type":"Entertainment"
        }
    ],
    "sg:phone":"+1 985 872 1203",
    "sg:postcode":"70360",
    "sg:province":"LA",
    "sg:tags":[
        "center"
    ],
    "wof:name":"Creole Lanes",
    "wof:placetype":"venue"
},
  "geometry": {"coordinates":[-90.74588799999999,29.599549],"type":"Point"}
}