{
  "type": "Feature",
  "properties": {
    "iso:country":"US",
    "sg:address":"724 Fairlawn Dr",
    "sg:city":"Terrytown",
    "sg:classifiers":[
        {
            "category":"Retail",
            "subcategory":"Auto Repair",
            "type":"Services"
        }
    ],
    "sg:phone":"+1 504 361 4491",
    "sg:postcode":"70056",
    "sg:province":"LA",
    "sg:tags":[
        "wrecker"
    ],
    "wof:name":"A-Tow Inc",
    "wof:placetype":"venue"
},
  "geometry": {"coordinates":[-90.03672299999999,29.901372],"type":"Point"}
}