{
  "type": "Feature",
  "properties": {
    "addr:full":"809 E 4th St Bogalusa LA 70427",
    "addr:housenumber":"809",
    "addr:postcode":"70427",
    "addr:street":"E 4Th St",
    "iso:country":"US",
    "sg:address":"809 E 4th St",
    "sg:city":"Bogalusa",
    "sg:classifiers":[
        {
            "category":"Restaurant",
            "type":"Food & Drink"
        }
    ],
    "sg:phone":"+1 985 735 0868",
    "sg:postcode":"70427",
    "sg:province":"LA",
    "wof:name":"Community Cafe",
    "wof:placetype":"venue"
},
  "geometry": {"coordinates":[-89.849389,30.776315],"type":"Point"}
}