{
  "type": "Feature",
  "properties": {
    "addr:full":"701 Poydras St New Orleans LA 70130",
    "addr:housenumber":"701",
    "addr:postcode":"70130",
    "addr:street":"Poydras St",
    "iso:country":"US",
    "sg:address":"701 Poydras St",
    "sg:city":"New Orleans",
    "sg:classifiers":[
        {
            "category":"Restaurant",
            "type":"Food & Drink"
        }
    ],
    "sg:phone":"+1 504 522 0138",
    "sg:postcode":"70130",
    "sg:province":"LA",
    "wof:name":"Jambalaya Shoppe",
    "wof:placetype":"venue"
},
  "geometry": {"coordinates":[-90.071815,29.949934],"type":"Point"}
}