{
  "type": "Feature",
  "properties": {
    "iso:country":"US",
    "sg:address":"4604 Perkins Rd",
    "sg:city":"Baton Rouge",
    "sg:classifiers":[
        {
            "category":"Health Services",
            "subcategory":"Nursing And Care Facility",
            "type":"Services"
        }
    ],
    "sg:phone":"+1 225 922 9923",
    "sg:postcode":"70808",
    "sg:province":"LA",
    "sg:tags":[
        "home",
        "retirement",
        "community"
    ],
    "wof:name":"Southside Gardens",
    "wof:placetype":"venue"
},
  "geometry": {"coordinates":[-91.142246,30.415975],"type":"Point"}
}