{
  "type": "Feature",
  "properties": {
    "addr:full":"5900 Paris Ave New Orleans LA 70122",
    "addr:housenumber":"5900",
    "addr:postcode":"70122",
    "addr:street":"Paris Ave",
    "iso:country":"US",
    "sg:address":"5900 Paris Ave",
    "sg:city":"New Orleans",
    "sg:classifiers":[
        {
            "category":"Organizations",
            "subcategory":"Religious Organization",
            "type":"Services"
        }
    ],
    "sg:phone":"+1 504 288 1461",
    "sg:postcode":"70122",
    "sg:province":"LA",
    "sg:tags":[
        "child",
        "day",
        "care"
    ],
    "wof:name":"Edgewater Baptst Play Day Care",
    "wof:placetype":"venue"
},
  "geometry": {"coordinates":[-90.075378,30.01841],"type":"Point"}
}