{
  "type": "Feature",
  "properties": {
    "addr:full":"141 S Washington St Marksville LA 71351",
    "addr:housenumber":"141",
    "addr:postcode":"71351",
    "addr:street":"S Washington St",
    "iso:country":"US",
    "sg:address":"141 S Washington St",
    "sg:city":"Marksville",
    "sg:classifiers":[
        {
            "category":"Organizations",
            "subcategory":"Religious Organization",
            "type":"Services"
        }
    ],
    "sg:phone":"+1 318 253 7561",
    "sg:postcode":"71351",
    "sg:province":"LA",
    "sg:tags":[
        "church"
    ],
    "wof:name":"St Joseph's Catholic Church",
    "wof:placetype":"venue"
},
  "geometry": {"coordinates":[-92.06894,31.12334],"type":"Point"}
}