{
  "type": "Feature",
  "properties": {
    "iso:country":"US",
    "sg:address":"818 Howard Ave",
    "sg:city":"New Orleans",
    "sg:classifiers":[
        {
            "category":"Professional",
            "subcategory":"Business Services",
            "type":"Services"
        }
    ],
    "sg:phone":"+1 504 568 0860",
    "sg:postcode":"70113",
    "sg:province":"LA",
    "sg:tags":[
        "recording",
        "studio"
    ],
    "wof:name":"Ad Sound Recording",
    "wof:placetype":"venue"
},
  "geometry": {"coordinates":[-90.074653,29.944525],"type":"Point"}
}