{
  "type": "Feature",
  "properties": {
    "iso:country":"US",
    "sg:address":"3262 Wyoming St",
    "sg:city":"Baton Rouge",
    "sg:classifiers":[
        {
            "category":"Shopping",
            "subcategory":"Gifts & Souvenirs",
            "type":"Retail Goods"
        }
    ],
    "sg:phone":"+1 225 388 9300",
    "sg:postcode":"70802",
    "sg:province":"LA",
    "sg:tags":[
        "shop"
    ],
    "wof:name":"Cashy Pads",
    "wof:placetype":"venue"
},
  "geometry": {"coordinates":[-91.18851100000001,30.419319],"type":"Point"}
}