{
  "type": "Feature",
  "properties": {
    "iso:country":"US",
    "sg:address":"6365 US Hwy 165",
    "sg:city":"Columbia",
    "sg:classifiers":[
        {
            "category":"Building & Trades",
            "subcategory":"Plumbing",
            "type":"Services"
        }
    ],
    "sg:phone":"+1 318 649 9964",
    "sg:postcode":"71418",
    "sg:province":"LA",
    "sg:tags":[
        "mechanical",
        "contractor"
    ],
    "sg:website":"www.edsmechanical.net",
    "wof:name":"Ed's Mechanical & Welding Svc",
    "wof:placetype":"venue"
},
  "geometry": {"coordinates":[-92.08990300000001,32.08786],"type":"Point"}
}