{
  "type": "Feature",
  "properties": {
    "iso:country":"US",
    "sg:address":"1348 Chippenham Dr",
    "sg:city":"Baton Rouge",
    "sg:classifiers":[
        {
            "category":"Professional",
            "subcategory":"Management & Consulting",
            "type":"Services"
        }
    ],
    "sg:phone":"+1 225 767 5519",
    "sg:postcode":"70808",
    "sg:province":"LA",
    "sg:tags":[
        "business"
    ],
    "wof:name":"Ada Consultants",
    "wof:placetype":"venue"
},
  "geometry": {"coordinates":[-91.13035499999999,30.390868],"type":"Point"}
}