{
  "type": "Feature",
  "properties": {
    "iso:country":"US",
    "sg:address":"224 Pecan View Dr",
    "sg:city":"Minden",
    "sg:classifiers":[
        {
            "category":"Social Services",
            "subcategory":"Child Care",
            "type":"Services"
        }
    ],
    "sg:phone":"+1 318 377 8252",
    "sg:postcode":"71055",
    "sg:province":"LA",
    "sg:tags":[
        "day"
    ],
    "wof:name":"Renees Daycare",
    "wof:placetype":"venue"
},
  "geometry": {"coordinates":[-93.287569,32.631505],"type":"Point"}
}