{
  "type": "Feature",
  "properties": {
    "addr:full":"9880 Deepwoods Dr Shreveport LA 71118",
    "addr:housenumber":"9880",
    "addr:postcode":"71118",
    "addr:street":"Deepwoods Dr",
    "iso:country":"US",
    "sg:address":"9880 Deepwoods Dr",
    "sg:city":"Shreveport",
    "sg:classifiers":[
        {
            "category":"Professional",
            "subcategory":"Management & Consulting",
            "type":"Services"
        }
    ],
    "sg:phone":"+1 318 688 4965",
    "sg:postcode":"71118",
    "sg:province":"LA",
    "wof:name":"Creamer Enterprises LLC",
    "wof:placetype":"venue"
},
  "geometry": {"coordinates":[-93.803487,32.375237],"type":"Point"}
}