{
  "type": "Feature",
  "properties": {
    "iso:country":"US",
    "sg:address":"2720 Metairie Lawn Dr",
    "sg:city":"Metairie",
    "sg:classifiers":[
        {
            "category":"Building & Trades",
            "subcategory":"Construction",
            "type":"Services"
        }
    ],
    "sg:phone":"+1 504 831 2545",
    "sg:postcode":"70002",
    "sg:province":"LA",
    "sg:tags":[
        "general",
        "contractor"
    ],
    "wof:name":"Beloumagner Construction Co",
    "wof:placetype":"venue"
},
  "geometry": {"coordinates":[-90.15210999999999,30.000733],"type":"Point"}
}