{
  "type": "Feature",
  "properties": {
    "iso:country":"US",
    "sg:address":"210 E Green St",
    "sg:city":"Tallulah",
    "sg:classifiers":[
        {
            "category":"Autos & Motor Vehicles",
            "subcategory":"Auto Supplies",
            "type":"Retail Goods"
        }
    ],
    "sg:phone":"+1 318 574 0313",
    "sg:postcode":"71282",
    "sg:province":"LA",
    "sg:tags":[
        "automobile",
        "parts"
    ],
    "wof:name":"Bumper To Bumper Auto Parts",
    "wof:placetype":"venue"
},
  "geometry": {"coordinates":[-91.18964099999999,32.409896],"type":"Point"}
}