{
  "type": "Feature",
  "properties": {
    "addr:full":"781 Behrman Hwy Terrytown LA 70056",
    "addr:housenumber":"781",
    "addr:postcode":"70056",
    "addr:street":"Behrman Hwy",
    "iso:country":"US",
    "sg:address":"781 Behrman Hwy",
    "sg:city":"Terrytown",
    "sg:classifiers":[
        {
            "category":"Organizations",
            "subcategory":"Religious Organization",
            "type":"Services"
        }
    ],
    "sg:phone":"+1 504 944 1980",
    "sg:postcode":"70056",
    "sg:province":"LA",
    "sg:tags":[
        "clergy"
    ],
    "wof:name":"Devon Oten",
    "wof:placetype":"venue"
},
  "geometry": {"coordinates":[-90.018732,29.89817],"type":"Point"}
}