{
  "type": "Feature",
  "properties": {
    "iso:country":"US",
    "sg:address":"7123 Gum Cove Rd",
    "sg:city":"Sulphur",
    "sg:classifiers":[
        {
            "category":"Building & Trades",
            "subcategory":"Landscaping Services",
            "type":"Services"
        }
    ],
    "sg:phone":"+1 337 583 7632",
    "sg:postcode":"70665",
    "sg:province":"LA",
    "wof:name":"Pickett Pike",
    "wof:placetype":"venue"
},
  "geometry": {"coordinates":[-93.51845400000001,30.120777],"type":"Point"}
}