{
  "type": "Feature",
  "properties": {
    "addr:full":"1108 E Main St New Iberia LA 70560",
    "addr:housenumber":"1108",
    "addr:postcode":"70560",
    "addr:street":"E Main St",
    "iso:country":"US",
    "sg:address":"1108 E Main St",
    "sg:city":"New Iberia",
    "sg:classifiers":[
        {
            "category":"Shopping",
            "subcategory":"Pharmacy",
            "type":"Retail Goods"
        }
    ],
    "sg:phone":"+1 337 365 4514",
    "sg:postcode":"70560",
    "sg:province":"LA",
    "wof:name":"Rite Aid Pharmacy",
    "wof:placetype":"venue"
},
  "geometry": {"coordinates":[-91.804146,29.997868],"type":"Point"}
}