{
  "type": "Feature",
  "properties": {
    "iso:country":"US",
    "sg:address":"4328 Government St",
    "sg:city":"Baton Rouge",
    "sg:classifiers":[
        {
            "category":"Personal",
            "subcategory":"Beauty Salon",
            "type":"Services"
        }
    ],
    "sg:phone":"+1 225 343 7441",
    "sg:postcode":"70806",
    "sg:province":"LA",
    "wof:name":"Lew & Jude Hair Salon",
    "wof:placetype":"venue"
},
  "geometry": {"coordinates":[-91.144852,30.444305],"type":"Point"}
}