{
  "type": "Feature",
  "properties": {
    "addr:full":"781 Huckleberry Ln Gretna LA 70056",
    "addr:housenumber":"781",
    "addr:postcode":"70056",
    "addr:street":"Huckleberry Ln",
    "iso:country":"US",
    "sg:address":"781 Huckleberry Ln",
    "sg:city":"Gretna",
    "sg:classifiers":[
        {
            "category":"Professional",
            "type":"Services"
        }
    ],
    "sg:phone":"+1 504 392 0338",
    "sg:postcode":"70056",
    "sg:province":"LA",
    "sg:tags":[
        "establishment"
    ],
    "wof:name":"Ocean Dynamics",
    "wof:placetype":"venue"
},
  "geometry": {"coordinates":[-90.031597,29.896027],"type":"Point"}
}