{
  "type": "Feature",
  "properties": {
    "addr:full":"9625 Cortana Pl Baton Rouge LA 70815",
    "addr:housenumber":"9625",
    "addr:postcode":"70815",
    "addr:street":"Cortana Pl",
    "iso:country":"US",
    "sg:address":"9625 Cortana Pl",
    "sg:city":"Baton Rouge",
    "sg:classifiers":[
        {
            "category":"Shopping",
            "subcategory":"Shoes",
            "type":"Retail Goods"
        }
    ],
    "sg:phone":"+1 225 926 9852",
    "sg:postcode":"70815",
    "sg:province":"LA",
    "wof:name":"Bakers",
    "wof:placetype":"venue"
},
  "geometry": {"coordinates":[-91.095174,30.455071],"type":"Point"}
}