{
  "type": "Feature",
  "properties": {
    "iso:country":"US",
    "sg:address":"801 Dante St",
    "sg:city":"New Orleans",
    "sg:classifiers":[
        {
            "category":"Shopping",
            "subcategory":"Gifts & Souvenirs",
            "type":"Retail Goods"
        }
    ],
    "sg:phone":"+1 504 896 5845",
    "sg:postcode":"70118",
    "sg:province":"LA",
    "sg:tags":[
        "shop"
    ],
    "wof:name":"Pretentious Whimsy",
    "wof:placetype":"venue"
},
  "geometry": {"coordinates":[-90.13381699999999,29.946665],"type":"Point"}
}