{
  "type": "Feature",
  "properties": {
    "iso:country":"US",
    "sg:address":"3846 Dublin St",
    "sg:city":"New Orleans",
    "sg:classifiers":[
        {
            "category":"Banks & Credit Unions",
            "subcategory":"Bank",
            "type":"Services"
        }
    ],
    "sg:phone":"+1 504 486 7285",
    "sg:postcode":"70118",
    "sg:province":"LA",
    "wof:name":"Bank Of Louisiana",
    "wof:placetype":"venue"
},
  "geometry": {"coordinates":[-90.11048700000001,29.967193],"type":"Point"}
}