{
  "type": "Feature",
  "properties": {
    "iso:country":"US",
    "sg:address":"5516 Powell St",
    "sg:city":"New Orleans",
    "sg:classifiers":[
        {
            "category":"Wholesale",
            "subcategory":"Machinery & Supplies",
            "type":"Manufacturing & Wholesale Goods"
        }
    ],
    "sg:phone":"+1 504 733 7140",
    "sg:postcode":"70123",
    "sg:province":"LA",
    "sg:tags":[
        "bearing"
    ],
    "sg:website":"www.applied.com",
    "wof:name":"Applied Industrial Tech Inc",
    "wof:placetype":"venue"
},
  "geometry": {"coordinates":[-90.19206,29.960356],"type":"Point"}
}