{
  "type": "Feature",
  "properties": {
    "iso:country":"US",
    "sg:address":"3921 Peoples St",
    "sg:city":"Metairie",
    "sg:classifiers":[
        {
            "category":"Professional",
            "subcategory":"Management & Consulting",
            "type":"Services"
        }
    ],
    "sg:phone":"+1 504 887 4033",
    "sg:postcode":"70002",
    "sg:province":"LA",
    "sg:tags":[
        "public",
        "relations"
    ],
    "wof:name":"Flowtex",
    "wof:placetype":"venue"
},
  "geometry": {"coordinates":[-90.17518800000001,30.011924],"type":"Point"}
}