{
  "type": "Feature",
  "properties": {
    "addr:full":"312 Pershing Ave Bunkie LA 71322",
    "addr:housenumber":"312",
    "addr:postcode":"71322",
    "addr:street":"Pershing Ave",
    "iso:country":"US",
    "sg:address":"312 Pershing Ave",
    "sg:city":"Bunkie",
    "sg:classifiers":[
        {
            "category":"Social Services",
            "type":"Services"
        }
    ],
    "sg:phone":"+1 318 346 4447",
    "sg:postcode":"71322",
    "sg:province":"LA",
    "sg:tags":[
        "senior",
        "citizen"
    ],
    "wof:name":"Bunkie Senior Ctr",
    "wof:placetype":"venue"
},
  "geometry": {"coordinates":[-92.18383,30.949361],"type":"Point"}
}