{
  "type": "Feature",
  "properties": {
    "iso:country":"US",
    "sg:address":"1022 Royal St",
    "sg:city":"New Orleans",
    "sg:classifiers":[
        {
            "category":"Shopping",
            "subcategory":"Used Merchandise",
            "type":"Retail Goods"
        }
    ],
    "sg:phone":"+1 504 595 6777",
    "sg:postcode":"70116",
    "sg:province":"LA",
    "sg:tags":[
        "book",
        "rare",
        "dealer"
    ],
    "wof:name":"Starling Books & Crafts",
    "wof:placetype":"venue"
},
  "geometry": {"coordinates":[-90.061905,29.961006],"type":"Point"}
}