{
  "type": "Feature",
  "properties": {
    "iso:country":"US",
    "sg:address":"1319 W Pinhook Rd",
    "sg:city":"Lafayette",
    "sg:classifiers":[
        {
            "category":"Mining & Drilling",
            "type":"Manufacturing & Wholesale Goods"
        }
    ],
    "sg:phone":"+1 337 237 4373",
    "sg:postcode":"70503",
    "sg:province":"LA",
    "sg:tags":[
        "field",
        "oil"
    ],
    "wof:name":"Complete Oilfield Management",
    "wof:placetype":"venue"
},
  "geometry": {"coordinates":[-92.015697,30.200363],"type":"Point"}
}