{
  "type": "Feature",
  "properties": {
    "addr:full":"2500 Archbishop Philip M Hannan Blvd Meraux LA 70075",
    "addr:postcode":"2500;70075",
    "addr:street":"Hannan Blvd Meraux",
    "iso:country":"US",
    "sg:address":"2500 Archbishop Philip M Hannan Blvd",
    "sg:city":"Meraux",
    "sg:classifiers":[
        {
            "category":"Freight",
            "type":"Transportation"
        }
    ],
    "sg:phone":"+1 504 279 4030",
    "sg:postcode":"70075",
    "sg:province":"LA",
    "sg:tags":[
        "warehouse",
        "merchandise"
    ],
    "wof:name":"A Storage Inn",
    "wof:placetype":"venue"
},
  "geometry": {"coordinates":[-89.92331,29.934375],"type":"Point"}
}