{
  "type": "Feature",
  "properties": {
    "addr:full":"42290 Pumpkin Center Rd Hammond LA 70403",
    "addr:housenumber":"42290",
    "addr:postcode":"70403",
    "addr:street":"Pumpkin Center Rd",
    "iso:country":"US",
    "sg:address":"42290 Pumpkin Center Rd",
    "sg:city":"Hammond",
    "sg:classifiers":[
        {
            "category":"Building & Trades",
            "subcategory":"Construction",
            "type":"Services"
        }
    ],
    "sg:phone":"+1 225 567 4443",
    "sg:postcode":"70403",
    "sg:province":"LA",
    "sg:tags":[
        "carpenter"
    ],
    "wof:name":"Interior Trim Unlimited",
    "wof:placetype":"venue"
},
  "geometry": {"coordinates":[-90.542239,30.466723],"type":"Point"}
}