{
  "type": "Feature",
  "properties": {
    "addr:full":"2730 State Rte 182 Morgan City LA 70380",
    "addr:housenumber":"2730",
    "addr:postcode":"70380",
    "addr:street":"State Rte 182 Morgan",
    "iso:country":"US",
    "sg:address":"2730 State Rte 182",
    "sg:city":"Morgan City",
    "sg:classifiers":[
        {
            "category":"Freight",
            "type":"Transportation"
        }
    ],
    "sg:phone":"+1 985 399 2111",
    "sg:postcode":"70380",
    "sg:province":"LA",
    "sg:tags":[
        "broker",
        "trucking"
    ],
    "wof:name":"Wildcat Transportation",
    "wof:placetype":"venue"
},
  "geometry": {"coordinates":[-91.263873,29.704038],"type":"Point"}
}