{
  "type": "Feature",
  "properties": {
    "addr:full":"14857 Colonel Allen Ct Baton Rouge LA 70816",
    "addr:housenumber":"14857",
    "addr:postcode":"70816",
    "addr:street":"Colonel Allen Ct",
    "iso:country":"US",
    "sg:address":"14857 Colonel Allen Ct",
    "sg:city":"Baton Rouge",
    "sg:classifiers":[
        {
            "category":"Social Services",
            "type":"Services"
        }
    ],
    "sg:phone":"+1 225 754 7724",
    "sg:postcode":"70816",
    "sg:province":"LA",
    "sg:tags":[
        "organization",
        "welfare"
    ],
    "wof:name":"Evergreen Pesbyterian Ministry",
    "wof:placetype":"venue"
},
  "geometry": {"coordinates":[-91.021762,30.427535],"type":"Point"}
}