{
  "type": "Feature",
  "properties": {
    "addr:full":"2121 N Causeway Blvd Metairie LA 70001",
    "addr:housenumber":"2121",
    "addr:postcode":"70001",
    "addr:street":"N Causeway Blvd",
    "iso:country":"US",
    "sg:address":"2121 N Causeway Blvd",
    "sg:city":"Metairie",
    "sg:classifiers":[
        {
            "category":"Insurance",
            "subcategory":"Insurance Agent",
            "type":"Services"
        }
    ],
    "sg:phone":"+1 504 833 7150",
    "sg:postcode":"70001",
    "sg:province":"LA",
    "wof:name":"Proclaim America Inc",
    "wof:placetype":"venue"
},
  "geometry": {"coordinates":[-90.15543,29.990962],"type":"Point"}
}