{
  "type": "Feature",
  "properties": {
    "iso:country":"US",
    "sg:address":"5637 Galeria Dr",
    "sg:city":"Baton Rouge",
    "sg:classifiers":[
        {
            "category":"Banks & Credit Unions",
            "subcategory":"Bank",
            "type":"Services"
        }
    ],
    "sg:phone":"+1 225 293 7283",
    "sg:postcode":"70816",
    "sg:province":"LA",
    "sg:tags":[
        "loan",
        "real estate"
    ],
    "wof:name":"Flagstar Bank Home Loan Ctr",
    "wof:placetype":"venue"
},
  "geometry": {"coordinates":[-91.05004099999999,30.405443],"type":"Point"}
}