{
  "type": "Feature",
  "properties": {
    "iso:country":"US",
    "sg:address":"119 Jefferson St",
    "sg:city":"Mansfield",
    "sg:classifiers":[
        {
            "category":"Health Services",
            "subcategory":"Doctor",
            "type":"Services"
        }
    ],
    "sg:phone":"+1 318 871 0081",
    "sg:postcode":"71052",
    "sg:province":"LA",
    "sg:tags":[
        "physician",
        "surgeon"
    ],
    "wof:name":"Pediatric Clinic",
    "wof:placetype":"venue"
},
  "geometry": {"coordinates":[-93.70911599999999,32.037174],"type":"Point"}
}