{
  "type": "Feature",
  "properties": {
    "iso:country":"US",
    "sg:address":"511 Patsy Brown Rd",
    "sg:city":"Monterey",
    "sg:classifiers":[
        {
            "category":"Building & Trades",
            "subcategory":"Plumbing",
            "type":"Services"
        }
    ],
    "sg:phone":"+1 318 386 2792",
    "sg:postcode":"71354",
    "sg:province":"LA",
    "sg:tags":[
        "conditioning",
        "air",
        "system",
        "contractor"
    ],
    "wof:name":"Lee's Air Cond & Refrigeration",
    "wof:placetype":"venue"
},
  "geometry": {"coordinates":[-91.776736,31.438524],"type":"Point"}
}