{
  "type": "Feature",
  "properties": {
    "iso:country":"US",
    "sg:address":"9308 Mansfield Rd",
    "sg:city":"Shreveport",
    "sg:classifiers":[
        {
            "category":"Professional",
            "subcategory":"Accounting & Tax Preparation",
            "type":"Services"
        }
    ],
    "sg:phone":"+1 318 688 8299",
    "sg:postcode":"71118",
    "sg:province":"LA",
    "sg:tags":[
        "accountant"
    ],
    "sg:website":"www.todaycpa.com",
    "wof:name":"Castellano & Assoc",
    "wof:placetype":"venue"
},
  "geometry": {"coordinates":[-93.810301,32.396122],"type":"Point"}
}