{
  "type": "Feature",
  "properties": {
    "iso:country":"US",
    "sg:address":"140 State Rte 653",
    "sg:city":"Raceland",
    "sg:classifiers":[
        {
            "category":"Insurance",
            "subcategory":"Insurance Agent",
            "type":"Services"
        }
    ],
    "sg:phone":"+1 985 537 3376",
    "sg:postcode":"70394",
    "sg:province":"LA",
    "wof:name":"Woodmen Of The World Insurance",
    "wof:placetype":"venue"
},
  "geometry": {"coordinates":[-90.622906,29.700105],"type":"Point"}
}