{
  "type": "Feature",
  "properties": {
    "iso:country":"US",
    "sg:address":"425 Wylie Dr",
    "sg:city":"Baton Rouge",
    "sg:classifiers":[
        {
            "category":"Restaurant",
            "type":"Food & Drink"
        }
    ],
    "sg:phone":"+1 225 763 9876",
    "sg:postcode":"70808",
    "sg:province":"LA",
    "sg:tags":[
        "eating"
    ],
    "wof:name":"Oriental Express Cuisine",
    "wof:placetype":"venue"
},
  "geometry": {"coordinates":[-91.138547,30.383376],"type":"Point"}
}