{
  "type": "Feature",
  "properties": {
    "addr:full":"41428 Black Bayou Rd Gonzales LA 70737",
    "addr:housenumber":"41428",
    "addr:postcode":"70737",
    "addr:street":"Black Bayou Rd",
    "iso:country":"US",
    "sg:address":"41428 Black Bayou Rd",
    "sg:city":"Gonzales",
    "sg:classifiers":[
        {
            "category":"Retail",
            "subcategory":"Auto Repair",
            "type":"Services"
        }
    ],
    "sg:phone":"+1 225 647 3264",
    "sg:postcode":"70737",
    "sg:province":"LA",
    "sg:tags":[
        "repairing",
        "automobile"
    ],
    "wof:name":"Bob & Eddie's Inc",
    "wof:placetype":"venue"
},
  "geometry": {"coordinates":[-90.90779499999999,30.262015],"type":"Point"}
}