{
  "type": "Feature",
  "properties": {
    "iso:country":"US",
    "sg:address":"605 Dublin St",
    "sg:city":"New Orleans",
    "sg:classifiers":[
        {
            "category":"Building & Trades",
            "subcategory":"Landscaping Services",
            "type":"Services"
        }
    ],
    "sg:phone":"+1 504 866 4548",
    "sg:postcode":"70118",
    "sg:province":"LA",
    "sg:tags":[
        "designer",
        "landscape"
    ],
    "wof:name":"Cashio Cochran",
    "wof:placetype":"venue"
},
  "geometry": {"coordinates":[-90.134299,29.944505],"type":"Point"}
}