{
  "type": "Feature",
  "properties": {
    "iso:country":"US",
    "sg:address":"613 Alamo St",
    "sg:city":"Lake Charles",
    "sg:classifiers":[
        {
            "category":"Wholesale",
            "subcategory":"Stationery",
            "type":"Manufacturing & Wholesale Goods"
        }
    ],
    "sg:phone":"+1 337 436 0814",
    "sg:postcode":"70601",
    "sg:province":"LA",
    "sg:tags":[
        "business",
        "form",
        "system"
    ],
    "sg:website":"www.fontenotsforms.com",
    "wof:name":"Fontenot Business Forms",
    "wof:placetype":"venue"
},
  "geometry": {"coordinates":[-93.212194,30.203453],"type":"Point"}
}