{
  "type": "Feature",
  "properties": {
    "addr:full":"906 N 2nd St Ferriday LA 71334",
    "addr:housenumber":"906",
    "addr:postcode":"71334",
    "addr:street":"N 2Nd St",
    "iso:country":"US",
    "sg:address":"906 N 2nd St",
    "sg:city":"Ferriday",
    "sg:classifiers":[
        {
            "category":"Personal",
            "subcategory":"Beauty Salon",
            "type":"Services"
        }
    ],
    "sg:phone":"+1 318 757 0050",
    "sg:postcode":"71334",
    "sg:province":"LA",
    "wof:name":"Bowl Cut",
    "wof:placetype":"venue"
},
  "geometry": {"coordinates":[-91.552575,31.631086],"type":"Point"}
}