{
  "type": "Feature",
  "properties": {
    "iso:country":"US",
    "sg:address":"3716 Redwood Dr",
    "sg:city":"New Iberia",
    "sg:classifiers":[
        {
            "category":"Professional",
            "subcategory":"Management & Consulting",
            "type":"Services"
        }
    ],
    "sg:phone":"+1 337 364 5506",
    "sg:postcode":"70560",
    "sg:province":"LA",
    "sg:tags":[
        "business"
    ],
    "wof:name":"Iarc Angel Acres For Ment",
    "wof:placetype":"venue"
},
  "geometry": {"coordinates":[-91.76669699999999,29.976581],"type":"Point"}
}