{
  "type": "Feature",
  "properties": {
    "iso:country":"US",
    "sg:address":"2347 Westbank Expy",
    "sg:city":"Harvey",
    "sg:classifiers":[
        {
            "category":"Restaurant",
            "type":"Food & Drink"
        }
    ],
    "sg:phone":"+1 504 376 8487",
    "sg:postcode":"70058",
    "sg:province":"LA",
    "sg:tags":[
        "delicatessen"
    ],
    "wof:name":"Expressway Deli & Groc Store",
    "wof:placetype":"venue"
},
  "geometry": {"coordinates":[-90.074183,29.900097],"type":"Point"}
}