{
  "type": "Feature",
  "properties": {
    "iso:country":"US",
    "sg:address":"718 N Rampart St",
    "sg:city":"New Orleans",
    "sg:classifiers":[
        {
            "category":"Bars & Pubs",
            "type":"Food & Drink"
        }
    ],
    "sg:phone":"+1 504 527 0703",
    "sg:postcode":"70116",
    "sg:province":"LA",
    "wof:name":"Voodoo At Congo Square",
    "wof:placetype":"venue"
},
  "geometry": {"coordinates":[-90.068394,29.960448],"type":"Point"}
}