{
  "type": "Feature",
  "properties": {
    "iso:country":"US",
    "sg:address":"501 Trenton St",
    "sg:city":"West Monroe",
    "sg:classifiers":[
        {
            "category":"Building & Trades",
            "subcategory":"Construction",
            "type":"Services"
        }
    ],
    "sg:phone":"+1 318 323 1932",
    "sg:postcode":"71291",
    "sg:province":"LA",
    "sg:tags":[
        "general",
        "contractor"
    ],
    "wof:name":"Tom Hicks Right-Of-Way Cntrctr",
    "wof:placetype":"venue"
},
  "geometry": {"coordinates":[-92.12653899999999,32.50421],"type":"Point"}
}