{
  "type": "Feature",
  "properties": {
    "iso:country":"US",
    "sg:address":"8092 W 70th St",
    "sg:city":"Greenwood",
    "sg:classifiers":[
        {
            "category":"Retail",
            "subcategory":"Auto Repair",
            "type":"Services"
        }
    ],
    "sg:phone":"+1 318 938 7392",
    "sg:postcode":"71033",
    "sg:province":"LA",
    "sg:tags":[
        "repairing",
        "automobile"
    ],
    "wof:name":"West 70th Auto Svc Ctr",
    "wof:placetype":"venue"
},
  "geometry": {"coordinates":[-93.951573,32.442838],"type":"Point"}
}