{
  "type": "Feature",
  "properties": {
    "iso:country":"US",
    "sg:address":"1912 N Claiborne Ave",
    "sg:city":"New Orleans",
    "sg:classifiers":[
        {
            "category":"Building & Trades",
            "subcategory":"Plumbing",
            "type":"Services"
        }
    ],
    "sg:phone":"+1 504 945 5685",
    "sg:postcode":"70116",
    "sg:province":"LA",
    "wof:name":"Carter & Son Plumbing Heating & Air Conditinng Inc",
    "wof:placetype":"venue"
},
  "geometry": {"coordinates":[-90.059998,29.973],"type":"Point"}
}