{
  "type": "Feature",
  "properties": {
    "addr:full":"1404 Carmel Ave Lafayette LA 70501",
    "addr:housenumber":"1404",
    "addr:postcode":"70501",
    "addr:street":"Carmel Ave",
    "iso:country":"US",
    "sg:address":"1404 Carmel Ave",
    "sg:city":"Lafayette",
    "sg:classifiers":[
        {
            "category":"Organizations",
            "subcategory":"Religious Organization",
            "type":"Services"
        }
    ],
    "sg:phone":"+1 337 233 7584",
    "sg:postcode":"70501",
    "sg:province":"LA",
    "sg:tags":[
        "monastery",
        "convent"
    ],
    "wof:name":"Marianites Of Holy Cross",
    "wof:placetype":"venue"
},
  "geometry": {"coordinates":[-91.985506,30.23245],"type":"Point"}
}