{
  "type": "Feature",
  "properties": {
    "addr:full":"565 Hickory Ave New Orleans LA 70123",
    "addr:housenumber":"565",
    "addr:postcode":"70123",
    "addr:street":"Hickory Ave",
    "iso:country":"US",
    "sg:address":"565 Hickory Ave",
    "sg:city":"New Orleans",
    "sg:classifiers":[
        {
            "category":"Real Estate",
            "subcategory":"Real Estate Agent",
            "type":"Services"
        }
    ],
    "sg:phone":"+1 504 362 3628",
    "sg:postcode":"70123",
    "sg:province":"LA",
    "sg:tags":[
        "inspection"
    ],
    "wof:name":"A-Pro Home-Building Inspection",
    "wof:placetype":"venue"
},
  "geometry": {"coordinates":[-90.19857500000001,29.944729],"type":"Point"}
}