{
  "type": "Feature",
  "properties": {
    "iso:country":"US",
    "sg:address":"1176 Tara Blvd",
    "sg:city":"Baton Rouge",
    "sg:classifiers":[
        {
            "category":"Retail",
            "subcategory":"Auto Repair",
            "type":"Services"
        }
    ],
    "sg:phone":"+1 225 387 9838",
    "sg:postcode":"70806",
    "sg:province":"LA",
    "sg:tags":[
        "repairing",
        "automobile"
    ],
    "wof:name":"Gene Cabral's Automotive",
    "wof:placetype":"venue"
},
  "geometry": {"coordinates":[-91.094826,30.438429],"type":"Point"}
}