{
  "type": "Feature",
  "properties": {
    "iso:country":"US",
    "sg:address":"708 San Jacinto Cir",
    "sg:city":"New Iberia",
    "sg:classifiers":[
        {
            "category":"Retail",
            "subcategory":"Repair Shop",
            "type":"Services"
        }
    ],
    "sg:phone":"+1 337 367 1136",
    "sg:postcode":"70563",
    "sg:province":"LA",
    "sg:tags":[
        "refinishing",
        "furniture"
    ],
    "wof:name":"Wicker & Woods",
    "wof:placetype":"venue"
},
  "geometry": {"coordinates":[-91.814795,30.030095],"type":"Point"}
}