{
  "type": "Feature",
  "properties": {
    "addr:full":"3038 Lexington St Kenner LA 70065",
    "addr:housenumber":"3038",
    "addr:postcode":"70065",
    "addr:street":"Lexington St",
    "iso:country":"US",
    "sg:address":"3038 Lexington St",
    "sg:city":"Kenner",
    "sg:classifiers":[
        {
            "category":"Social Services",
            "subcategory":"Child Care",
            "type":"Services"
        }
    ],
    "sg:phone":"+1 504 469 2856",
    "sg:postcode":"70065",
    "sg:province":"LA",
    "wof:name":"Haynes & Gale Child Care Ctr",
    "wof:placetype":"venue"
},
  "geometry": {"coordinates":[-90.25173599999999,30.010685],"type":"Point"}
}