{
  "type": "Feature",
  "properties": {
    "addr:full":"1501 Cypress St West Monroe LA 71291",
    "addr:housenumber":"1501",
    "addr:postcode":"71291",
    "addr:street":"Cypress St West",
    "iso:country":"US",
    "sg:address":"1501 Cypress St",
    "sg:city":"West Monroe",
    "sg:classifiers":[
        {
            "category":"Food & Beverages",
            "subcategory":"Bakery",
            "type":"Retail Goods"
        }
    ],
    "sg:phone":"+1 318 323 5292",
    "sg:postcode":"71291",
    "sg:province":"LA",
    "sg:tags":[
        "doughnut"
    ],
    "wof:name":"Shipley Do-Nut Shop",
    "wof:placetype":"venue"
},
  "geometry": {"coordinates":[-92.13656899999999,32.51339],"type":"Point"}
}