{
  "type": "Feature",
  "properties": {
    "addr:full":"727 E Simcoe St Lafayette LA 70501",
    "addr:housenumber":"727",
    "addr:postcode":"70501",
    "addr:street":"E Simcoe St",
    "iso:country":"US",
    "sg:address":"727 E Simcoe St",
    "sg:city":"Lafayette",
    "sg:classifiers":[
        {
            "category":"Personal",
            "subcategory":"Barber",
            "type":"Services"
        }
    ],
    "sg:phone":"+1 337 232 0208",
    "sg:postcode":"70501",
    "sg:province":"LA",
    "wof:name":"Hollywood's Barber Shop",
    "wof:placetype":"venue"
},
  "geometry": {"coordinates":[-92.008301,30.2306],"type":"Point"}
}