{
  "type": "Feature",
  "properties": {
    "iso:country":"US",
    "sg:address":"3501 Holiday Dr",
    "sg:city":"New Orleans",
    "sg:classifiers":[
        {
            "category":"Shopping",
            "subcategory":"Optician",
            "type":"Retail Goods"
        }
    ],
    "sg:phone":"+1 504 368 8650",
    "sg:postcode":"70114",
    "sg:province":"LA",
    "sg:tags":[
        "eyewear"
    ],
    "wof:name":"Nautical Optical Lab",
    "wof:placetype":"venue"
},
  "geometry": {"coordinates":[-90.016098,29.920099],"type":"Point"}
}