{
  "type": "Feature",
  "properties": {
    "addr:full":"816 W 1st St Kaplan LA 70548",
    "addr:housenumber":"816",
    "addr:postcode":"70548",
    "addr:street":"W 1St St",
    "iso:country":"US",
    "sg:address":"816 W 1st St",
    "sg:city":"Kaplan",
    "sg:classifiers":[
        {
            "category":"Bars & Pubs",
            "type":"Food & Drink"
        }
    ],
    "sg:phone":"+1 337 643 9652",
    "sg:postcode":"70548",
    "sg:province":"LA",
    "sg:tags":[
        "lounge",
        "cocktail"
    ],
    "wof:name":"Sunset Lounge",
    "wof:placetype":"venue"
},
  "geometry": {"coordinates":[-92.293953,30.000741],"type":"Point"}
}