{
  "type": "Feature",
  "properties": {
    "iso:country":"US",
    "sg:address":"1401 L B Landry Ave",
    "sg:city":"New Orleans",
    "sg:classifiers":[
        {
            "category":"Social Services",
            "subcategory":"Child Care",
            "type":"Services"
        }
    ],
    "sg:phone":"+1 504 361 1203",
    "sg:postcode":"70114",
    "sg:province":"LA",
    "sg:tags":[
        "day"
    ],
    "wof:name":"Day Haven Adult Day Care Center",
    "wof:placetype":"venue"
},
  "geometry": {"coordinates":[-90.04119900000001,29.941],"type":"Point"}
}