{
  "type": "Feature",
  "properties": {
    "iso:country":"US",
    "sg:address":"1860 Coteau Holmes Hwy",
    "sg:city":"St Martinville",
    "sg:classifiers":[
        {
            "category":"Government",
            "subcategory":"Fire Station",
            "type":"Public Place"
        }
    ],
    "sg:phone":"+1 337 394 6084",
    "sg:postcode":"70582",
    "sg:province":"LA",
    "sg:tags":[
        "department"
    ],
    "wof:name":"Coteau Holmes Volunteer Fire",
    "wof:placetype":"venue"
},
  "geometry": {"coordinates":[-91.730818,30.131865],"type":"Point"}
}