{
  "type": "Feature",
  "properties": {
    "addr:full":"408 W Suncrest Loop Slidell LA 70458",
    "addr:housenumber":"408",
    "addr:postcode":"70458",
    "addr:street":"W Suncrest Loop",
    "iso:country":"US",
    "sg:address":"408 W Suncrest Loop",
    "sg:city":"Slidell",
    "sg:classifiers":[
        {
            "category":"Real Estate",
            "subcategory":"Real Estate Agent",
            "type":"Services"
        }
    ],
    "sg:phone":"+1 985 781 0718",
    "sg:postcode":"70458",
    "sg:province":"LA",
    "wof:name":"Buyer Advocate Real Estate Co",
    "wof:placetype":"venue"
},
  "geometry": {"coordinates":[-89.755996,30.294901],"type":"Point"}
}