{
  "type": "Feature",
  "properties": {
    "iso:country":"US",
    "sg:address":"409 Vicky Ln",
    "sg:city":"Alexandria",
    "sg:classifiers":[
        {
            "category":"Professional",
            "subcategory":"Business Services",
            "type":"Services"
        }
    ],
    "sg:phone":"+1 318 445 2209",
    "sg:postcode":"71303",
    "sg:province":"LA",
    "sg:tags":[
        "interior",
        "decorator"
    ],
    "wof:name":"Loutex Colors Inc",
    "wof:placetype":"venue"
},
  "geometry": {"coordinates":[-92.505576,31.268459],"type":"Point"}
}