{
  "type": "Feature",
  "properties": {
    "iso:country":"US",
    "sg:address":"1060 Front St",
    "sg:city":"Slidell",
    "sg:classifiers":[
        {
            "category":"Shopping",
            "subcategory":"Used Merchandise",
            "type":"Retail Goods"
        }
    ],
    "sg:phone":"+1 985 646 1166",
    "sg:postcode":"70458",
    "sg:province":"LA",
    "sg:tags":[
        "shop",
        "consignment"
    ],
    "wof:name":"Repeat Performance Clothing",
    "wof:placetype":"venue"
},
  "geometry": {"coordinates":[-89.777449,30.29042],"type":"Point"}
}