{
  "type": "Feature",
  "properties": {
    "addr:full":"4713 Loreauville Rd New Iberia LA 70563",
    "addr:housenumber":"4713",
    "addr:postcode":"70563",
    "addr:street":"Loreauville Rd",
    "iso:country":"US",
    "sg:address":"4713 Loreauville Rd",
    "sg:city":"New Iberia",
    "sg:classifiers":[
        {
            "category":"Manufacturing",
            "subcategory":"Metals",
            "type":"Manufacturing & Wholesale Goods"
        }
    ],
    "sg:phone":"+1 337 367 8419",
    "sg:postcode":"70563",
    "sg:province":"LA",
    "sg:tags":[
        "steel"
    ],
    "wof:name":"Unlimited Fabricators & Sales",
    "wof:placetype":"venue"
},
  "geometry": {"coordinates":[-91.74353499999999,30.009444],"type":"Point"}
}