{
  "type": "Feature",
  "properties": {
    "iso:country":"US",
    "sg:address":"130 Desiard St",
    "sg:city":"Monroe",
    "sg:classifiers":[
        {
            "category":"Insurance",
            "subcategory":"Insurance Agent",
            "type":"Services"
        }
    ],
    "sg:phone":"+1 318 329 1108",
    "sg:postcode":"71201",
    "sg:province":"LA",
    "wof:name":"AIG Sunamerica",
    "wof:placetype":"venue"
},
  "geometry": {"coordinates":[-92.117852,32.501396],"type":"Point"}
}