{
  "type": "Feature",
  "properties": {
    "iso:country":"US",
    "sg:address":"2410 S 5th St",
    "sg:city":"Leesville",
    "sg:classifiers":[
        {
            "category":"Restaurant",
            "type":"Food & Drink"
        }
    ],
    "sg:phone":"+1 337 238 5935",
    "sg:postcode":"71446",
    "sg:province":"LA",
    "wof:name":"Popeyes Chicken & Biscuits",
    "wof:placetype":"venue"
},
  "geometry": {"coordinates":[-93.26945600000001,31.119104],"type":"Point"}
}