{
  "type": "Feature",
  "properties": {
    "iso:country":"US",
    "sg:address":"2165 Besson Ln",
    "sg:city":"Sunshine",
    "sg:classifiers":[
        {
            "category":"Organizations",
            "subcategory":"Religious Organization",
            "type":"Services"
        }
    ],
    "sg:phone":"+1 225 642 7772",
    "sg:postcode":"70780",
    "sg:province":"LA",
    "sg:tags":[
        "church"
    ],
    "sg:website":"www.ibervillechristiancenter.com",
    "wof:name":"Iberville Christian Center",
    "wof:placetype":"venue"
},
  "geometry": {"coordinates":[-91.128694,30.279198],"type":"Point"}
}