{
  "type": "Feature",
  "properties": {
    "addr:full":"17327 Womack Dr Hammond LA 70403",
    "addr:housenumber":"17327",
    "addr:postcode":"70403",
    "addr:street":"Womack Dr",
    "iso:country":"US",
    "sg:address":"17327 Womack Dr",
    "sg:city":"Hammond",
    "sg:classifiers":[
        {
            "category":"Taxi",
            "type":"Transportation"
        }
    ],
    "sg:phone":"+1 985 542 5074",
    "sg:postcode":"70403",
    "sg:province":"LA",
    "sg:tags":[
        "taxicab"
    ],
    "wof:name":"Red Carpet Taxi Svc",
    "wof:placetype":"venue"
},
  "geometry": {"coordinates":[-90.437764,30.50158],"type":"Point"}
}