{
  "type": "Feature",
  "properties": {
    "iso:country":"US",
    "sg:address":"28 Fairfield Ave",
    "sg:city":"Gretna",
    "sg:classifiers":[
        {
            "category":"Wholesale",
            "subcategory":"Durable Goods & Equipment",
            "type":"Manufacturing & Wholesale Goods"
        },
        {
            "category":"Shopping",
            "subcategory":"Gifts & Souvenirs",
            "type":"Retail Goods"
        }
    ],
    "sg:phone":"+1 504 392 7217",
    "sg:postcode":"70056",
    "sg:province":"LA",
    "sg:tags":[
        "importer",
        "novelty"
    ],
    "wof:name":"T J's Carnival & Bingo Supls",
    "wof:placetype":"venue"
},
  "geometry": {"coordinates":[-90.04158700000001,29.901061],"type":"Point"}
}