{
  "type": "Feature",
  "properties": {
    "iso:country":"US",
    "sg:address":"3221 Nature Dr",
    "sg:city":"Marrero",
    "sg:classifiers":[
        {
            "category":"Building & Trades",
            "subcategory":"Electrical",
            "type":"Services"
        }
    ],
    "sg:phone":"+1 504 340 8572",
    "sg:postcode":"70072",
    "sg:province":"LA",
    "sg:tags":[
        "electric",
        "contractor"
    ],
    "wof:name":"Premier Electrical Svc",
    "wof:placetype":"venue"
},
  "geometry": {"coordinates":[-90.13014699999999,29.845973],"type":"Point"}
}