{
  "type": "Feature",
  "properties": {
    "addr:full":"800 W Genie St Chalmette LA 70043",
    "addr:housenumber":"800",
    "addr:postcode":"70043",
    "addr:street":"W Genie St",
    "iso:country":"US",
    "sg:address":"800 W Genie St",
    "sg:city":"Chalmette",
    "sg:classifiers":[
        {
            "category":"Health Services",
            "subcategory":"Doctor",
            "type":"Services"
        }
    ],
    "sg:phone":"+1 504 277 5834",
    "sg:postcode":"70043",
    "sg:province":"LA",
    "sg:tags":[
        "physician",
        "surgeon"
    ],
    "wof:name":"Maynard E Garrett Pmc",
    "wof:placetype":"venue"
},
  "geometry": {"coordinates":[-89.966437,29.954995],"type":"Point"}
}