{
  "type": "Feature",
  "properties": {
    "iso:country":"US",
    "sg:address":"939 Cleveland St",
    "sg:city":"Franklinton",
    "sg:classifiers":[
        {
            "category":"Banks & Credit Unions",
            "subcategory":"Bank",
            "type":"Services"
        }
    ],
    "sg:phone":"+1 985 839 4455",
    "sg:postcode":"70438",
    "sg:province":"LA",
    "wof:name":"Parish National Bank",
    "wof:placetype":"venue"
},
  "geometry": {"coordinates":[-90.157774,30.847114],"type":"Point"}
}