{
  "type": "Feature",
  "properties": {
    "iso:country":"US",
    "sg:address":"314 S Hollywood Rd",
    "sg:city":"Houma",
    "sg:classifiers":[
        {
            "category":"Building & Trades",
            "subcategory":"Equipment Rental",
            "type":"Services"
        }
    ],
    "sg:phone":"+1 985 868 7337",
    "sg:postcode":"70360",
    "sg:province":"LA",
    "sg:tags":[
        "camping"
    ],
    "sg:website":"www.coolestcustomers.com",
    "wof:name":"RGS Christmas Trees",
    "wof:placetype":"venue"
},
  "geometry": {"coordinates":[-90.758399,29.599764],"type":"Point"}
}