{
  "type": "Feature",
  "properties": {
    "iso:country":"US",
    "sg:address":"2808 Court St",
    "sg:city":"Port Allen",
    "sg:classifiers":[
        {
            "category":"Utilities",
            "subcategory":"Mobile Phone",
            "type":"Services"
        }
    ],
    "sg:phone":"+1 225 242 8700",
    "sg:postcode":"70767",
    "sg:province":"LA",
    "sg:tags":[
        "telephone",
        "cellular"
    ],
    "wof:name":"Alltel",
    "wof:placetype":"venue"
},
  "geometry": {"coordinates":[-91.241812,30.45117],"type":"Point"}
}