{
  "type": "Feature",
  "properties": {
    "iso:country":"US",
    "sg:address":"4000 Davey St",
    "sg:city":"New Orleans",
    "sg:classifiers":[
        {
            "category":"Cinema",
            "subcategory":"Movie Rental",
            "type":"Entertainment"
        }
    ],
    "sg:phone":"+1 504 288 3412",
    "sg:postcode":"70122",
    "sg:province":"LA",
    "sg:tags":[
        "video",
        "membership",
        "tape",
        "organization"
    ],
    "wof:name":"Internatl Turkish Video Ctr",
    "wof:placetype":"venue"
},
  "geometry": {"coordinates":[-90.084299,29.99683],"type":"Point"}
}