{
  "type": "Feature",
  "properties": {
    "iso:country":"US",
    "sg:address":"126 Hospital Dr",
    "sg:city":"Lafayette",
    "sg:classifiers":[
        {
            "category":"Health Services",
            "subcategory":"Doctor",
            "type":"Services"
        }
    ],
    "sg:phone":"+1 337 232 0689",
    "sg:postcode":"70503",
    "sg:province":"LA",
    "sg:tags":[
        "dentist"
    ],
    "wof:name":"Gonsoulin & Gonsoulin",
    "wof:placetype":"venue"
},
  "geometry": {"coordinates":[-92.020003,30.203913],"type":"Point"}
}