{
  "type": "Feature",
  "properties": {
    "addr:full":"505 Norris Ln West Monroe LA 71291",
    "addr:housenumber":"505",
    "addr:postcode":"71291",
    "addr:street":"Norris Ln West",
    "iso:country":"US",
    "sg:address":"505 Norris Ln",
    "sg:city":"West Monroe",
    "sg:classifiers":[
        {
            "category":"Home & Garden",
            "subcategory":"Carpets & Floor Coverings",
            "type":"Retail Goods"
        }
    ],
    "sg:phone":"+1 318 396 1206",
    "sg:postcode":"71291",
    "sg:province":"LA",
    "sg:tags":[
        "dealer",
        "rug"
    ],
    "wof:name":"Carpet Mill",
    "wof:placetype":"venue"
},
  "geometry": {"coordinates":[-92.17466899999999,32.51672],"type":"Point"}
}