{
  "type": "Feature",
  "properties": {
    "iso:country":"US",
    "sg:address":"1020 Carmadelle St",
    "sg:city":"Marrero",
    "sg:classifiers":[
        {
            "category":"Professional",
            "subcategory":"Accounting & Tax Preparation",
            "type":"Services"
        }
    ],
    "sg:phone":"+1 504 340 3396",
    "sg:postcode":"70072",
    "sg:province":"LA",
    "sg:tags":[
        "return"
    ],
    "wof:name":"Mitchell Tax",
    "wof:placetype":"venue"
},
  "geometry": {"coordinates":[-90.121101,29.889595],"type":"Point"}
}