{
  "type": "Feature",
  "properties": {
    "iso:country":"US",
    "sg:address":"5025 Lapalco Blvd",
    "sg:city":"Marrero",
    "sg:classifiers":[
        {
            "category":"Restaurant",
            "type":"Food & Drink"
        }
    ],
    "sg:menulink":"http://www.allmenus.com/la/avondale/73013-pizza-hut/menu/",
    "sg:phone":"+1 504 340 9348",
    "sg:postcode":"70072",
    "sg:province":"LA",
    "sg:tags":[
        "american",
        "pizza"
    ],
    "wof:name":"Pizza Hut",
    "wof:placetype":"venue"
},
  "geometry": {"coordinates":[-90.100279,29.874484],"type":"Point"}
}