{
  "type": "Feature",
  "properties": {
    "iso:country":"US",
    "sg:address":"7732 Goodwood Blvd",
    "sg:city":"Baton Rouge",
    "sg:classifiers":[
        {
            "category":"Professional",
            "subcategory":"Lawyer & Legal Services",
            "type":"Services"
        }
    ],
    "sg:phone":"+1 225 248 8500",
    "sg:postcode":"70806",
    "sg:province":"LA",
    "sg:tags":[
        "attorney"
    ],
    "wof:name":"Hank Des Bordes",
    "wof:placetype":"venue"
},
  "geometry": {"coordinates":[-91.10546600000001,30.442385],"type":"Point"}
}