{
  "type": "Feature",
  "properties": {
    "iso:country":"US",
    "sg:address":"4860 Hickory Branch Rd",
    "sg:city":"Lake Charles",
    "sg:classifiers":[
        {
            "category":"Professional",
            "type":"Services"
        }
    ],
    "sg:phone":"+1 337 855 6497",
    "sg:postcode":"70611",
    "sg:province":"LA",
    "wof:name":"Gary Parish",
    "wof:placetype":"venue"
},
  "geometry": {"coordinates":[-93.256488,30.373494],"type":"Point"}
}