{
  "type": "Feature",
  "properties": {
    "iso:country":"US",
    "sg:address":"552 Lake Ave",
    "sg:city":"Metairie",
    "sg:classifiers":[
        {
            "category":"Shopping",
            "subcategory":"Music",
            "type":"Retail Goods"
        }
    ],
    "sg:phone":"+1 504 452 0059",
    "sg:postcode":"70005",
    "sg:province":"LA",
    "sg:tags":[
        "record",
        "vinyl"
    ],
    "wof:name":"Forever Vinyl Inc",
    "wof:placetype":"venue"
},
  "geometry": {"coordinates":[-90.125203,29.994342],"type":"Point"}
}