{
  "type": "Feature",
  "properties": {
    "iso:country":"US",
    "sg:address":"810 White Ave",
    "sg:city":"Bastrop",
    "sg:classifiers":[
        {
            "category":"Organizations",
            "subcategory":"Religious Organization",
            "type":"Services"
        }
    ],
    "sg:phone":"+1 318 281 3529",
    "sg:postcode":"71220",
    "sg:province":"LA",
    "sg:tags":[
        "church"
    ],
    "wof:name":"White Avenue Baptist Church",
    "wof:placetype":"venue"
},
  "geometry": {"coordinates":[-91.904219,32.770526],"type":"Point"}
}