{
  "type": "Feature",
  "properties": {
    "addr:full":"185 Gause Blvd W Slidell LA 70460",
    "addr:housenumber":"185",
    "addr:postcode":"70460",
    "addr:street":"Gause Blvd W",
    "iso:country":"US",
    "sg:address":"185 Gause Blvd W",
    "sg:city":"Slidell",
    "sg:classifiers":[
        {
            "category":"Building & Trades",
            "subcategory":"Equipment Rental",
            "type":"Services"
        }
    ],
    "sg:phone":"+1 985 646 0777",
    "sg:postcode":"70460",
    "sg:province":"LA",
    "sg:tags":[
        "leasing",
        "furniture"
    ],
    "wof:name":"Aarons Sales & Lease Ownership",
    "wof:placetype":"venue"
},
  "geometry": {"coordinates":[-89.780776,30.287101],"type":"Point"}
}