{
  "type": "Feature",
  "properties": {
    "iso:country":"US",
    "sg:address":"14737 W Main St",
    "sg:city":"Cut Off",
    "sg:classifiers":[
        {
            "category":"Retail",
            "subcategory":"Repair Shop",
            "type":"Services"
        }
    ],
    "sg:phone":"+1 985 632 8469",
    "sg:postcode":"70345",
    "sg:province":"LA",
    "sg:tags":[
        "valve"
    ],
    "wof:name":"Production Valve Svc",
    "wof:placetype":"venue"
},
  "geometry": {"coordinates":[-90.33629500000001,29.53701],"type":"Point"}
}