{
  "type": "Feature",
  "properties": {
    "iso:country":"US",
    "sg:address":"517 Sena Dr",
    "sg:city":"Metairie",
    "sg:classifiers":[
        {
            "category":"Professional",
            "type":"Services"
        }
    ],
    "sg:phone":"+1 504 833 2341",
    "sg:postcode":"70005",
    "sg:province":"LA",
    "wof:name":"Bucktown All Stars LLC",
    "wof:placetype":"venue"
},
  "geometry": {"coordinates":[-90.13521299999999,30.001195],"type":"Point"}
}