{
  "type": "Feature",
  "properties": {
    "iso:country":"US",
    "sg:address":"235 Byles St",
    "sg:city":"Many",
    "sg:classifiers":[
        {
            "category":"Organizations",
            "subcategory":"Religious Organization",
            "type":"Services"
        }
    ],
    "sg:phone":"+1 318 256 5400",
    "sg:postcode":"71449",
    "sg:province":"LA",
    "wof:name":"Alford Heights Baptist Church",
    "wof:placetype":"venue"
},
  "geometry": {"coordinates":[-93.465693,31.552178],"type":"Point"}
}