{
  "type": "Feature",
  "properties": {
    "iso:country":"US",
    "sg:address":"221 Lake St",
    "sg:city":"Mooringsport",
    "sg:classifiers":[
        {
            "category":"Organizations",
            "subcategory":"Religious Organization",
            "type":"Services"
        }
    ],
    "sg:phone":"+1 318 996 7439",
    "sg:postcode":"71060",
    "sg:province":"LA",
    "sg:tags":[
        "church"
    ],
    "wof:name":"Mooringsport United Meth Chr",
    "wof:placetype":"venue"
},
  "geometry": {"coordinates":[-93.96101299999999,32.691693],"type":"Point"}
}