{
  "type": "Feature",
  "properties": {
    "iso:country":"US",
    "sg:address":"600 N Hwy 190",
    "sg:city":"Covington",
    "sg:classifiers":[
        {
            "category":"Restaurant",
            "type":"Food & Drink"
        }
    ],
    "sg:phone":"+1 985 893 3866",
    "sg:postcode":"70433",
    "sg:province":"LA",
    "wof:name":"Four Seasons Buffett",
    "wof:placetype":"venue"
},
  "geometry": {"coordinates":[-90.08280600000001,30.439913],"type":"Point"}
}