{
  "type": "Feature",
  "properties": {
    "addr:full":"1717 Franklin Ave New Orleans LA 70117",
    "addr:housenumber":"1717",
    "addr:postcode":"70117",
    "addr:street":"Franklin Ave",
    "iso:country":"US",
    "sg:address":"1717 Franklin Ave",
    "sg:city":"New Orleans",
    "sg:classifiers":[
        {
            "category":"Retail",
            "subcategory":"Auto Repair",
            "type":"Services"
        }
    ],
    "sg:phone":"+1 504 945 8825",
    "sg:postcode":"70117",
    "sg:province":"LA",
    "sg:tags":[
        "repairing",
        "automobile"
    ],
    "wof:name":"Lott's Service Ctr",
    "wof:placetype":"venue"
},
  "geometry": {"coordinates":[-90.047997,29.975956],"type":"Point"}
}