{
  "type": "Feature",
  "properties": {
    "iso:country":"US",
    "sg:address":"2045 Pelopidas St",
    "sg:city":"New Orleans",
    "sg:classifiers":[
        {
            "category":"Building & Trades",
            "subcategory":"Construction",
            "type":"Services"
        }
    ],
    "sg:phone":"+1 504 288 9470",
    "sg:postcode":"70122",
    "sg:province":"LA",
    "sg:tags":[
        "demolition",
        "contractor"
    ],
    "wof:name":"Cournet Demolisher Land Clrng",
    "wof:placetype":"venue"
},
  "geometry": {"coordinates":[-90.062127,30.000896],"type":"Point"}
}