{
  "type": "Feature",
  "properties": {
    "addr:full":"8867 Highland Rd Baton Rouge LA 70808",
    "addr:housenumber":"8867",
    "addr:postcode":"70808",
    "addr:street":"Highland Rd",
    "iso:country":"US",
    "sg:address":"8867 Highland Rd",
    "sg:city":"Baton Rouge",
    "sg:classifiers":[
        {
            "category":"Building & Trades",
            "subcategory":"Landscaping Services",
            "type":"Services"
        }
    ],
    "sg:phone":"+1 225 413 1595",
    "sg:postcode":"70808",
    "sg:province":"LA",
    "sg:tags":[
        "lawn",
        "maintenance",
        "grounds"
    ],
    "wof:name":"Louisiana Grounds Mgmt",
    "wof:placetype":"venue"
},
  "geometry": {"coordinates":[-91.12665699999999,30.371442],"type":"Point"}
}