{
  "type": "Feature",
  "properties": {
    "addr:full":"6005 Parliament Dr Bossier City LA 71111",
    "addr:housenumber":"6005",
    "addr:postcode":"71111",
    "addr:street":"Parliament Dr",
    "iso:country":"US",
    "sg:address":"6005 Parliament Dr",
    "sg:city":"Bossier City",
    "sg:classifiers":[
        {
            "category":"Real Estate",
            "subcategory":"Developer",
            "type":"Services"
        }
    ],
    "sg:phone":"+1 318 742 2487",
    "sg:postcode":"71111",
    "sg:province":"LA",
    "wof:name":"Victorian Pointe Development",
    "wof:placetype":"venue"
},
  "geometry": {"coordinates":[-93.64227700000001,32.575514],"type":"Point"}
}