{
  "type": "Feature",
  "properties": {
    "iso:country":"US",
    "sg:address":"13500 Chef Menteur Hwy",
    "sg:city":"New Orleans",
    "sg:classifiers":[
        {
            "category":"Health Services",
            "subcategory":"Nursing And Care Facility",
            "type":"Services"
        }
    ],
    "sg:phone":"+1 504 254 9431",
    "sg:postcode":"70129",
    "sg:province":"LA",
    "sg:tags":[
        "home",
        "convalescent"
    ],
    "wof:name":"Maison Orleans Nursing Home",
    "wof:placetype":"venue"
},
  "geometry": {"coordinates":[-89.925545,30.031724],"type":"Point"}
}