{
  "type": "Feature",
  "properties": {
    "addr:full":"7043 W Tamaron Blvd New Orleans LA 70128",
    "addr:housenumber":"7043",
    "addr:postcode":"70128",
    "addr:street":"W Tamaron Blvd",
    "iso:country":"US",
    "sg:address":"7043 W Tamaron Blvd",
    "sg:city":"New Orleans",
    "sg:classifiers":[
        {
            "category":"Shopping",
            "subcategory":"Shoes",
            "type":"Retail Goods"
        }
    ],
    "sg:phone":"+1 504 975 7005",
    "sg:postcode":"70128",
    "sg:province":"LA",
    "wof:name":"V P Shoes",
    "wof:placetype":"venue"
},
  "geometry": {"coordinates":[-89.95028499999999,30.056647],"type":"Point"}
}