{
  "type": "Feature",
  "properties": {
    "iso:country":"US",
    "sg:address":"14140 Dallas Dr",
    "sg:city":"Denham Springs",
    "sg:classifiers":[
        {
            "category":"Building & Trades",
            "subcategory":"Construction",
            "type":"Services"
        }
    ],
    "sg:phone":"+1 225 664 4727",
    "sg:postcode":"70726",
    "sg:province":"LA",
    "sg:tags":[
        "hanging",
        "contractor"
    ],
    "wof:name":"Watco Painting Inc",
    "wof:placetype":"venue"
},
  "geometry": {"coordinates":[-90.84948300000001,30.4013],"type":"Point"}
}