{
  "type": "Feature",
  "properties": {
    "iso:country":"US",
    "sg:address":"410 N Canal Blvd",
    "sg:city":"Thibodaux",
    "sg:classifiers":[
        {
            "category":"Bakery",
            "type":"Food & Drink"
        }
    ],
    "sg:menulink":"http://www.allmenus.com/la/thibodaux/219948-auntie-annes-pretzels/menu/",
    "sg:phone":"+1 985 448 3087",
    "sg:postcode":"70301",
    "sg:province":"LA",
    "sg:tags":[
        "american",
        "pastry"
    ],
    "wof:name":"Auntie Anne's Pretzels",
    "wof:placetype":"venue"
},
  "geometry": {"coordinates":[-90.81582299999999,29.807328],"type":"Point"}
}