{
  "type": "Feature",
  "properties": {
    "iso:country":"US",
    "sg:address":"769 Credeur Rd",
    "sg:city":"Scott",
    "sg:classifiers":[
        {
            "category":"Utilities",
            "subcategory":"Telephone",
            "type":"Services"
        }
    ],
    "sg:phone":"+1 337 654 5916",
    "sg:postcode":"70583",
    "sg:province":"LA",
    "sg:tags":[
        "wireless",
        "internet",
        "provider"
    ],
    "wof:name":"Gator Internet Inc",
    "wof:placetype":"venue"
},
  "geometry": {"coordinates":[-92.15951699999999,30.285476],"type":"Point"}
}