{
  "type": "Feature",
  "properties": {
    "iso:country":"US",
    "sg:address":"2144 Belle Chasse Hwy",
    "sg:city":"Terrytown",
    "sg:classifiers":[
        {
            "category":"Banks & Credit Unions",
            "subcategory":"Bank",
            "type":"Services"
        }
    ],
    "sg:phone":"+1 504 394 4063",
    "sg:postcode":"70056",
    "sg:province":"LA",
    "sg:tags":[
        "savings",
        "loan",
        "association"
    ],
    "wof:name":"Eureka Homestead Society",
    "wof:placetype":"venue"
},
  "geometry": {"coordinates":[-90.03179299999999,29.889083],"type":"Point"}
}