{
  "type": "Feature",
  "properties": {
    "iso:country":"US",
    "sg:address":"116 Margi Dr",
    "sg:city":"Scott",
    "sg:classifiers":[
        {
            "category":"Education",
            "subcategory":"School",
            "type":"Public Place"
        }
    ],
    "sg:phone":"+1 337 235 9698",
    "sg:postcode":"70583",
    "sg:province":"LA",
    "wof:name":"Scott Middle School",
    "wof:placetype":"venue"
},
  "geometry": {"coordinates":[-92.062185,30.266091],"type":"Point"}
}