{
  "type": "Feature",
  "properties": {
    "iso:country":"US",
    "sg:address":"2063 Spanish Oaks Dr",
    "sg:city":"Harvey",
    "sg:classifiers":[
        {
            "category":"Social Services",
            "type":"Services"
        }
    ],
    "sg:phone":"+1 504 361 1015",
    "sg:postcode":"70058",
    "sg:province":"LA",
    "sg:tags":[
        "organization",
        "welfare"
    ],
    "wof:name":"DELF",
    "wof:placetype":"venue"
},
  "geometry": {"coordinates":[-90.048828,29.868716],"type":"Point"}
}