{
  "type": "Feature",
  "properties": {
    "iso:country":"US",
    "sg:address":"6570 Louis Xiv St",
    "sg:city":"New Orleans",
    "sg:classifiers":[
        {
            "category":"Local Transit",
            "type":"Transportation"
        }
    ],
    "sg:phone":"+1 504 486 4562",
    "sg:postcode":"70124",
    "sg:province":"LA",
    "sg:tags":[
        "limousine"
    ],
    "sg:website":"www.flagshiplimo.com",
    "wof:name":"Flagship Limousine LTD",
    "wof:placetype":"venue"
},
  "geometry": {"coordinates":[-90.108825,30.009257],"type":"Point"}
}