{
  "type": "Feature",
  "properties": {
    "iso:country":"US",
    "sg:address":"1002 N Main St",
    "sg:city":"Jennings",
    "sg:classifiers":[
        {
            "category":"Shopping",
            "subcategory":"Gifts & Souvenirs",
            "type":"Retail Goods"
        }
    ],
    "sg:phone":"+1 337 824 8128",
    "sg:postcode":"70546",
    "sg:province":"LA",
    "sg:tags":[
        "shop"
    ],
    "wof:name":"Solari Designs & Gifts Inc",
    "wof:placetype":"venue"
},
  "geometry": {"coordinates":[-92.657954,30.230499],"type":"Point"}
}