{
  "type": "Feature",
  "properties": {
    "addr:full":"3812 Sterkx Rd Alexandria LA 71301",
    "addr:housenumber":"3812",
    "addr:postcode":"71301",
    "addr:street":"Sterkx Rd",
    "iso:country":"US",
    "sg:address":"3812 Sterkx Rd",
    "sg:city":"Alexandria",
    "sg:classifiers":[
        {
            "category":"Freight",
            "type":"Transportation"
        }
    ],
    "sg:phone":"+1 318 448 1602",
    "sg:postcode":"71301",
    "sg:province":"LA",
    "sg:tags":[
        "commercial",
        "storage"
    ],
    "wof:name":"All Star Self Storage",
    "wof:placetype":"venue"
},
  "geometry": {"coordinates":[-92.451089,31.270194],"type":"Point"}
}