{
  "type": "Feature",
  "properties": {
    "addr:full":"1407 S Carrollton Ave New Orleans LA 70118",
    "addr:housenumber":"1407",
    "addr:postcode":"70118",
    "addr:street":"S Carrollton Ave",
    "iso:country":"US",
    "sg:address":"1407 S Carrollton Ave",
    "sg:city":"New Orleans",
    "sg:classifiers":[
        {
            "category":"Shopping",
            "subcategory":"Optical Goods",
            "type":"Retail Goods"
        }
    ],
    "sg:phone":"+1 504 861 7820",
    "sg:postcode":"70118",
    "sg:province":"LA",
    "wof:name":"University Optical & Contact",
    "wof:placetype":"venue"
},
  "geometry": {"coordinates":[-90.12732800000001,29.949269],"type":"Point"}
}