{
  "type": "Feature",
  "properties": {
    "iso:country":"US",
    "sg:address":"61245 Crestline Dr",
    "sg:city":"Lacombe",
    "sg:classifiers":[
        {
            "category":"Professional",
            "subcategory":"Advertising",
            "type":"Services"
        }
    ],
    "sg:phone":"+1 225 445 5369",
    "sg:postcode":"70445",
    "sg:province":"LA",
    "sg:tags":[
        "counselor"
    ],
    "wof:name":"Graphix Lab",
    "wof:placetype":"venue"
},
  "geometry": {"coordinates":[-89.91641,30.320867],"type":"Point"}
}