{
  "type": "Feature",
  "properties": {
    "iso:country":"US",
    "sg:address":"2316 Keene Dr",
    "sg:city":"Sulphur",
    "sg:classifiers":[
        {
            "category":"Building & Trades",
            "subcategory":"Landscaping Services",
            "type":"Services"
        }
    ],
    "sg:phone":"+1 337 436 5212",
    "sg:postcode":"70663",
    "sg:province":"LA",
    "sg:tags":[
        "tree"
    ],
    "wof:name":"Ripley's A Tree Svc",
    "wof:placetype":"venue"
},
  "geometry": {"coordinates":[-93.35060900000001,30.221638],"type":"Point"}
}