{
  "type": "Feature",
  "properties": {
    "iso:country":"US",
    "sg:address":"3525 N Causeway Blvd",
    "sg:city":"Metairie",
    "sg:classifiers":[
        {
            "category":"Professional",
            "subcategory":"Accounting & Tax Preparation",
            "type":"Services"
        }
    ],
    "sg:phone":"+1 504 835 0426",
    "sg:postcode":"70002",
    "sg:province":"LA",
    "wof:name":"Terry Randazzo CPA",
    "wof:placetype":"venue"
},
  "geometry": {"coordinates":[-90.15463699999999,30.013198],"type":"Point"}
}