{
  "type": "Feature",
  "properties": {
    "addr:full":"610 Girl Scout Rd Simsboro LA 71275",
    "addr:housenumber":"610",
    "addr:postcode":"71275",
    "addr:street":"Girl Scout Rd",
    "iso:country":"US",
    "sg:address":"610 Girl Scout Rd",
    "sg:city":"Simsboro",
    "sg:classifiers":[
        {
            "category":"Travel",
            "subcategory":"Campground",
            "type":"Entertainment"
        }
    ],
    "sg:phone":"+1 318 263 3941",
    "sg:postcode":"71275",
    "sg:province":"LA",
    "sg:tags":[
        "camp"
    ],
    "wof:name":"Camp Wawbansee",
    "wof:placetype":"venue"
},
  "geometry": {"coordinates":[-92.87970300000001,32.522183],"type":"Point"}
}