{
  "type": "Feature",
  "properties": {
    "iso:country":"US",
    "sg:address":"40159 Black Bayou Exd",
    "sg:city":"Gonzales",
    "sg:classifiers":[
        {
            "category":"Retail",
            "subcategory":"Veterinary Services",
            "type":"Services"
        }
    ],
    "sg:phone":"+1 225 647 7050",
    "sg:postcode":"70737",
    "sg:province":"LA",
    "sg:tags":[
        "veterinarian"
    ],
    "wof:name":"East Ascension Veterinarian",
    "wof:placetype":"venue"
},
  "geometry": {"coordinates":[-90.93372100000001,30.26219],"type":"Point"}
}