{
  "type": "Feature",
  "properties": {
    "addr:full":"174 Blue Heron Rd Dubach LA 71235",
    "addr:housenumber":"174",
    "addr:postcode":"71235",
    "addr:street":"Blue Heron Rd",
    "iso:country":"US",
    "sg:address":"174 Blue Heron Rd",
    "sg:city":"Dubach",
    "sg:classifiers":[
        {
            "category":"Farming",
            "subcategory":"Livestock Farm",
            "type":"Manufacturing & Wholesale Goods"
        }
    ],
    "sg:phone":"+1 318 255 6275",
    "sg:postcode":"71235",
    "sg:province":"LA",
    "sg:tags":[
        "beef",
        "feedlot",
        "cattle"
    ],
    "wof:name":"Cardinal Hill Farms",
    "wof:placetype":"venue"
},
  "geometry": {"coordinates":[-92.548942,32.64448],"type":"Point"}
}