{
  "type": "Feature",
  "properties": {
    "addr:full":"1031 E 1st St Deridder LA 70634",
    "addr:housenumber":"1031",
    "addr:postcode":"70634",
    "addr:street":"E 1St St",
    "iso:country":"US",
    "sg:address":"1031 E 1st St",
    "sg:city":"Deridder",
    "sg:classifiers":[
        {
            "category":"Shopping",
            "type":"Retail Goods"
        }
    ],
    "sg:phone":"+1 337 463 5548",
    "sg:postcode":"70634",
    "sg:province":"LA",
    "sg:tags":[
        "monument"
    ],
    "wof:name":"Welborn Monument Co",
    "wof:placetype":"venue"
},
  "geometry": {"coordinates":[-93.26483399999999,30.847367],"type":"Point"}
}