{
  "type": "Feature",
  "properties": {
    "iso:country":"US",
    "sg:address":"5180 Highland Dr",
    "sg:city":"Marrero",
    "sg:classifiers":[
        {
            "category":"Manufacturing",
            "subcategory":"Tools & Machinery",
            "type":"Manufacturing & Wholesale Goods"
        }
    ],
    "sg:phone":"+1 504 347 1207",
    "sg:postcode":"70072",
    "sg:province":"LA",
    "sg:tags":[
        "conductive",
        "wiring",
        "devices",
        "mfg"
    ],
    "wof:name":"Power Leads Inc",
    "wof:placetype":"venue"
},
  "geometry": {"coordinates":[-90.10288,29.866576],"type":"Point"}
}