{
  "type": "Feature",
  "properties": {
    "iso:country":"US",
    "sg:address":"714 Railroad St",
    "sg:city":"Belcher",
    "sg:classifiers":[
        {
            "category":"Government",
            "subcategory":"Post Office",
            "type":"Public Place"
        }
    ],
    "sg:phone":"+1 318 378 4364",
    "sg:postcode":"71004",
    "sg:province":"LA",
    "wof:name":"US Post Office",
    "wof:placetype":"venue"
},
  "geometry": {"coordinates":[-93.834127,32.759324],"type":"Point"}
}