{
  "type": "Feature",
  "properties": {
    "iso:country":"US",
    "sg:address":"8010 Arcadian Shores Dr",
    "sg:city":"Shreveport",
    "sg:classifiers":[
        {
            "category":"Professional",
            "subcategory":"Business Services",
            "type":"Services"
        }
    ],
    "sg:phone":"+1 318 687 4348",
    "sg:postcode":"71129",
    "sg:province":"LA",
    "wof:name":"One Fine Day Weddings",
    "wof:placetype":"venue"
},
  "geometry": {"coordinates":[-93.864626,32.424363],"type":"Point"}
}