{
  "type": "Feature",
  "properties": {
    "addr:full":"3201 Monroe Hwy Pineville LA 71360",
    "addr:housenumber":"3201",
    "addr:postcode":"71360",
    "addr:street":"Monroe Hwy",
    "iso:country":"US",
    "sg:address":"3201 Monroe Hwy",
    "sg:city":"Pineville",
    "sg:classifiers":[
        {
            "category":"Banks & Credit Unions",
            "subcategory":"Bank",
            "type":"Services"
        }
    ],
    "sg:phone":"+1 318 484 4733",
    "sg:postcode":"71360",
    "sg:province":"LA",
    "wof:name":"Regions",
    "wof:placetype":"venue"
},
  "geometry": {"coordinates":[-92.414248,31.360932],"type":"Point"}
}