{
  "type": "Feature",
  "properties": {
    "iso:country":"US",
    "sg:address":"9654 Brookline Ave",
    "sg:city":"Baton Rouge",
    "sg:classifiers":[
        {
            "category":"Manufacturing",
            "subcategory":"Tools & Machinery",
            "type":"Manufacturing & Wholesale Goods"
        }
    ],
    "sg:phone":"+1 225 926 6311",
    "sg:postcode":"70809",
    "sg:province":"LA",
    "sg:tags":[
        "filter"
    ],
    "wof:name":"Pollard Industries LLC",
    "wof:placetype":"venue"
},
  "geometry": {"coordinates":[-91.081847,30.428166],"type":"Point"}
}