{
  "type": "Feature",
  "properties": {
    "iso:country":"US",
    "sg:address":"125 Industrial Ave",
    "sg:city":"Jefferson",
    "sg:classifiers":[
        {
            "category":"Professional",
            "subcategory":"Computer Services",
            "type":"Services"
        }
    ],
    "sg:phone":"+1 504 831 7999",
    "sg:postcode":"70121",
    "sg:province":"LA",
    "sg:tags":[
        "consultant",
        "designer"
    ],
    "wof:name":"Epic Management Consulting",
    "wof:placetype":"venue"
},
  "geometry": {"coordinates":[-90.137292,29.961072],"type":"Point"}
}