{
  "type": "Feature",
  "properties": {
    "iso:country":"US",
    "sg:address":"3895 State Rte 30",
    "sg:city":"St Gabriel",
    "sg:classifiers":[
        {
            "category":"Wholesale",
            "subcategory":"Machinery & Supplies",
            "type":"Manufacturing & Wholesale Goods"
        }
    ],
    "sg:phone":"+1 225 642 0667",
    "sg:postcode":"70776",
    "sg:province":"LA",
    "sg:tags":[
        "tank"
    ],
    "wof:name":"Tidal Tank",
    "wof:placetype":"venue"
},
  "geometry": {"coordinates":[-91.07966399999999,30.249409],"type":"Point"}
}