{
  "type": "Feature",
  "properties": {
    "addr:full":"1984 Airline Dr Bossier City LA 71112",
    "addr:housenumber":"1984",
    "addr:postcode":"71112",
    "addr:street":"Airline Dr",
    "iso:country":"US",
    "sg:address":"1984 Airline Dr",
    "sg:city":"Bossier City",
    "sg:classifiers":[
        {
            "category":"Travel",
            "subcategory":"Hotels & Motels",
            "type":"Entertainment"
        }
    ],
    "sg:phone":"+1 318 742 6000",
    "sg:postcode":"71112",
    "sg:province":"LA",
    "sg:website":"www.bestwestern.com",
    "wof:name":"Best Western Inn",
    "wof:placetype":"venue"
},
  "geometry": {"coordinates":[-93.699107,32.525623],"type":"Point"}
}