{
  "type": "Feature",
  "properties": {
    "iso:country":"US",
    "sg:address":"860 Behrman Hwy",
    "sg:city":"Gretna",
    "sg:classifiers":[
        {
            "category":"Professional",
            "subcategory":"Lawyer & Legal Services",
            "type":"Services"
        }
    ],
    "sg:phone":"+1 504 391 1990",
    "sg:postcode":"70056",
    "sg:province":"LA",
    "wof:name":"Nass Tiemann & Nass",
    "wof:placetype":"venue"
},
  "geometry": {"coordinates":[-90.019402,29.892],"type":"Point"}
}