{
  "type": "Feature",
  "properties": {
    "iso:country":"US",
    "sg:address":"836 Olive St",
    "sg:city":"Shreveport",
    "sg:classifiers":[
        {
            "category":"Health Services",
            "subcategory":"Doctor",
            "type":"Services"
        }
    ],
    "sg:phone":"+1 318 222 8421",
    "sg:postcode":"71104",
    "sg:province":"LA",
    "sg:tags":[
        "physician",
        "surgeon"
    ],
    "wof:name":"Vitreo-Retinal Assoc",
    "wof:placetype":"venue"
},
  "geometry": {"coordinates":[-93.74767300000001,32.492761],"type":"Point"}
}