{
  "type": "Feature",
  "properties": {
    "addr:full":"200 Walnut St Bunkie LA 71322",
    "addr:housenumber":"200",
    "addr:postcode":"71322",
    "addr:street":"Walnut St",
    "iso:country":"US",
    "sg:address":"200 Walnut St",
    "sg:city":"Bunkie",
    "sg:classifiers":[
        {
            "category":"Government",
            "subcategory":"Office",
            "type":"Public Place"
        }
    ],
    "sg:phone":"+1 318 346 9978",
    "sg:postcode":"71322",
    "sg:province":"LA",
    "sg:tags":[
        "govt",
        "city"
    ],
    "wof:name":"Bunkie City Utility Collection",
    "wof:placetype":"venue"
},
  "geometry": {"coordinates":[-92.18469899999999,30.953529],"type":"Point"}
}