{
  "type": "Feature",
  "properties": {
    "iso:country":"US",
    "sg:address":"199 Stonegate Dr",
    "sg:city":"Monroe",
    "sg:classifiers":[
        {
            "category":"Professional",
            "type":"Services"
        }
    ],
    "sg:phone":"+1 318 410 1859",
    "sg:postcode":"71202",
    "sg:province":"LA",
    "sg:tags":[
        "establishment"
    ],
    "wof:name":"Utilitydata Service",
    "wof:placetype":"venue"
},
  "geometry": {"coordinates":[-92.07749,32.46194],"type":"Point"}
}