{
  "type": "Feature",
  "properties": {
    "addr:full":"211 Beacon Ln Franklin LA 70538",
    "addr:housenumber":"211",
    "addr:postcode":"70538",
    "addr:street":"Beacon Ln",
    "iso:country":"US",
    "sg:address":"211 Beacon Ln",
    "sg:city":"Franklin",
    "sg:classifiers":[
        {
            "category":"Recreation",
            "subcategory":"Marina",
            "type":"Entertainment"
        }
    ],
    "sg:phone":"+1 337 867 4895",
    "sg:postcode":"70538",
    "sg:province":"LA",
    "wof:name":"Cypremont Point Supply House",
    "wof:placetype":"venue"
},
  "geometry": {"coordinates":[-91.877876,29.714022],"type":"Point"}
}