{
  "type": "Feature",
  "properties": {
    "iso:country":"US",
    "sg:address":"1602 Thomas Rd",
    "sg:city":"West Monroe",
    "sg:classifiers":[
        {
            "category":"Food & Beverages",
            "subcategory":"Groceries & Convenience Stores",
            "type":"Retail Goods"
        }
    ],
    "sg:phone":"+1 318 398 9611",
    "sg:postcode":"71292",
    "sg:province":"LA",
    "wof:name":"Stop & Save",
    "wof:placetype":"venue"
},
  "geometry": {"coordinates":[-92.15459799999999,32.485862],"type":"Point"}
}