{
  "type": "Feature",
  "properties": {
    "iso:country":"US",
    "sg:address":"121 Old Hwy 171",
    "sg:city":"Lake Charles",
    "sg:classifiers":[
        {
            "category":"Home & Garden",
            "subcategory":"Carpets & Floor Coverings",
            "type":"Retail Goods"
        }
    ],
    "sg:phone":"+1 337 855 8700",
    "sg:postcode":"70611",
    "sg:province":"LA",
    "sg:tags":[
        "dealer",
        "rug"
    ],
    "wof:name":"Moss Bluff Floors",
    "wof:placetype":"venue"
},
  "geometry": {"coordinates":[-93.18950599999999,30.301021],"type":"Point"}
}