{
  "type": "Feature",
  "properties": {
    "iso:country":"US",
    "sg:address":"10613 Veterans Memorial Hwy",
    "sg:city":"Pine Prairie",
    "sg:classifiers":[
        {
            "category":"Autos & Motor Vehicles",
            "subcategory":"Automobile Sales",
            "type":"Retail Goods"
        }
    ],
    "sg:phone":"+1 337 599 2425",
    "sg:postcode":"70576",
    "sg:province":"LA",
    "sg:tags":[
        "car",
        "dealer"
    ],
    "wof:name":"R & J Motors LLC",
    "wof:placetype":"venue"
},
  "geometry": {"coordinates":[-92.428918,30.754306],"type":"Point"}
}