{
  "type": "Feature",
  "properties": {
    "addr:full":"1051 Gause Blvd Slidell LA 70458",
    "addr:housenumber":"1051",
    "addr:postcode":"70458",
    "addr:street":"Gause Blvd",
    "iso:country":"US",
    "sg:address":"1051 Gause Blvd",
    "sg:city":"Slidell",
    "sg:classifiers":[
        {
            "category":"Health Services",
            "subcategory":"Doctor",
            "type":"Services"
        }
    ],
    "sg:phone":"+1 985 641 9025",
    "sg:postcode":"70458",
    "sg:province":"LA",
    "sg:tags":[
        "physician",
        "surgeon"
    ],
    "wof:name":"Gastroenterology & Hepatology",
    "wof:placetype":"venue"
},
  "geometry": {"coordinates":[-89.76972000000001,30.284636],"type":"Point"}
}