{
  "type": "Feature",
  "properties": {
    "addr:full":"402 State Rte 30 Gonzales LA 70737",
    "addr:housenumber":"402",
    "addr:postcode":"70737",
    "addr:street":"State Rte 30 Gonzales La",
    "iso:country":"US",
    "sg:address":"402 State Rte 30",
    "sg:city":"Gonzales",
    "sg:classifiers":[
        {
            "category":"Shopping",
            "subcategory":"Department Store",
            "type":"Retail Goods"
        }
    ],
    "sg:phone":"+1 225 644 1505",
    "sg:postcode":"70737",
    "sg:province":"LA",
    "sg:tags":[
        "shop"
    ],
    "wof:name":"Dollar General",
    "wof:placetype":"venue"
},
  "geometry": {"coordinates":[-90.92371799999999,30.210981],"type":"Point"}
}