{
  "type": "Feature",
  "properties": {
    "addr:full":"156 Franklin Estates Rd Homer LA 71048",
    "addr:housenumber":"156",
    "addr:postcode":"71048",
    "addr:street":"Franklin Estates Rd",
    "iso:country":"US",
    "sg:address":"156 Franklin Estates Rd",
    "sg:city":"Homer",
    "sg:classifiers":[
        {
            "category":"Freight",
            "type":"Transportation"
        }
    ],
    "sg:phone":"+1 318 353 1822",
    "sg:postcode":"71048",
    "sg:province":"LA",
    "sg:tags":[
        "trucking"
    ],
    "wof:name":"L C Ford Trucking",
    "wof:placetype":"venue"
},
  "geometry": {"coordinates":[-92.923485,32.803587],"type":"Point"}
}