{
  "type": "Feature",
  "properties": {
    "iso:country":"US",
    "sg:address":"538 Nashville Ave",
    "sg:city":"New Orleans",
    "sg:classifiers":[
        {
            "category":"Personal",
            "subcategory":"Beauty Salon",
            "type":"Services"
        }
    ],
    "sg:phone":"+1 504 895 5333",
    "sg:postcode":"70115",
    "sg:province":"LA",
    "sg:tags":[
        "spa",
        "day"
    ],
    "wof:name":"Pampered Soul & Body Day Spa",
    "wof:placetype":"venue"
},
  "geometry": {"coordinates":[-90.119547,29.919404],"type":"Point"}
}