{
  "type": "Feature",
  "properties": {
    "iso:country":"US",
    "sg:address":"6324 Brownfields Dr",
    "sg:city":"Baton Rouge",
    "sg:classifiers":[
        {
            "category":"Manufacturing",
            "subcategory":"Tools & Machinery",
            "type":"Manufacturing & Wholesale Goods"
        }
    ],
    "sg:phone":"+1 225 775 0636",
    "sg:postcode":"70811",
    "sg:province":"LA",
    "sg:tags":[
        "distribution",
        "retail",
        "knife"
    ],
    "wof:name":"H&H Enterprises",
    "wof:placetype":"venue"
},
  "geometry": {"coordinates":[-91.12242999999999,30.555701],"type":"Point"}
}