{
  "type": "Feature",
  "properties": {
    "iso:country":"US",
    "sg:address":"4707 Magazine St",
    "sg:city":"New Orleans",
    "sg:classifiers":[
        {
            "category":"Restaurant",
            "type":"Food & Drink"
        }
    ],
    "sg:phone":"+1 504 899 4665",
    "sg:postcode":"70115",
    "sg:province":"LA",
    "wof:name":"Danny's Seafood",
    "wof:placetype":"venue"
},
  "geometry": {"coordinates":[-90.106042,29.920476],"type":"Point"}
}