{
  "type": "Feature",
  "properties": {
    "addr:full":"414 Providence St New Iberia LA 70560",
    "addr:housenumber":"414",
    "addr:postcode":"70560",
    "addr:street":"Providence St",
    "iso:country":"US",
    "sg:address":"414 Providence St",
    "sg:city":"New Iberia",
    "sg:classifiers":[
        {
            "category":"Professional",
            "subcategory":"Accounting & Tax Preparation",
            "type":"Services"
        },
        {
            "category":"Professional",
            "subcategory":"Lawyer & Legal Services",
            "type":"Services"
        }
    ],
    "sg:phone":"+1 337 367 3896",
    "sg:postcode":"70560",
    "sg:province":"LA",
    "sg:tags":[
        "notary",
        "accountant"
    ],
    "wof:name":"St Mary Water Works",
    "wof:placetype":"venue"
},
  "geometry": {"coordinates":[-91.82232,30.004073],"type":"Point"}
}