{
  "type": "Feature",
  "properties": {
    "addr:full":"533 Best Rd Simsboro LA 71275",
    "addr:housenumber":"533",
    "addr:postcode":"71275",
    "addr:street":"Best Rd",
    "iso:country":"US",
    "sg:address":"533 Best Rd",
    "sg:city":"Simsboro",
    "sg:classifiers":[
        {
            "category":"Manufacturing",
            "subcategory":"Rubber & Plastics",
            "type":"Manufacturing & Wholesale Goods"
        }
    ],
    "sg:phone":"+1 318 247 8308",
    "sg:postcode":"71275",
    "sg:province":"LA",
    "sg:tags":[
        "product",
        "mfg"
    ],
    "wof:name":"Glass Molders Pottery Pla",
    "wof:placetype":"venue"
},
  "geometry": {"coordinates":[-92.794124,32.511399],"type":"Point"}
}