{
  "type": "Feature",
  "properties": {
    "iso:country":"US",
    "sg:address":"8700 Florida Blvd",
    "sg:city":"Baton Rouge",
    "sg:classifiers":[
        {
            "category":"Banks & Credit Unions",
            "subcategory":"Bank",
            "type":"Services"
        }
    ],
    "sg:phone":"+1 225 925 5930",
    "sg:postcode":"70815",
    "sg:province":"LA",
    "sg:tags":[
        "loan"
    ],
    "wof:name":"AAA Payday",
    "wof:placetype":"venue"
},
  "geometry": {"coordinates":[-91.094189,30.453172],"type":"Point"}
}