{
  "type": "Feature",
  "properties": {
    "addr:full":"76915 Cedar St Grosse Tete LA 70740",
    "addr:housenumber":"76915",
    "addr:postcode":"70740",
    "addr:street":"Cedar St",
    "iso:country":"US",
    "sg:address":"76915 Cedar St",
    "sg:city":"Grosse Tete",
    "sg:classifiers":[
        {
            "category":"Home & Garden",
            "subcategory":"Hardware",
            "type":"Retail Goods"
        }
    ],
    "sg:phone":"+1 225 648 2062",
    "sg:postcode":"70740",
    "sg:province":"LA",
    "wof:name":"Gene's Hardware & Auto Parts",
    "wof:placetype":"venue"
},
  "geometry": {"coordinates":[-91.433789,30.411907],"type":"Point"}
}