{
  "type": "Feature",
  "properties": {
    "iso:country":"US",
    "sg:address":"38184 Ozone St",
    "sg:city":"Slidell",
    "sg:classifiers":[
        {
            "category":"Building & Trades",
            "subcategory":"Plumbing",
            "type":"Services"
        }
    ],
    "sg:phone":"+1 985 641 9830",
    "sg:postcode":"70458",
    "sg:province":"LA",
    "sg:tags":[
        "contractor"
    ],
    "wof:name":"Surbirbin Plumming & Heating",
    "wof:placetype":"venue"
},
  "geometry": {"coordinates":[-89.76733900000001,30.242377],"type":"Point"}
}