{
  "type": "Feature",
  "properties": {
    "iso:country":"US",
    "sg:address":"214 W 2nd St",
    "sg:city":"Deridder",
    "sg:classifiers":[
        {
            "category":"Government",
            "subcategory":"Police Station",
            "type":"Public Place"
        }
    ],
    "sg:phone":"+1 337 463 7019",
    "sg:postcode":"70634",
    "sg:province":"LA",
    "sg:tags":[
        "sheriff"
    ],
    "wof:name":"Beauregard Parish Police Jury",
    "wof:placetype":"venue"
},
  "geometry": {"coordinates":[-93.288873,30.845917],"type":"Point"}
}