{
  "type": "Feature",
  "properties": {
    "addr:full":"1605 Carol Sue Ave Gretna LA 70056",
    "addr:housenumber":"1605",
    "addr:postcode":"70056",
    "addr:street":"Carol Sue Ave",
    "iso:country":"US",
    "sg:address":"1605 Carol Sue Ave",
    "sg:city":"Gretna",
    "sg:classifiers":[
        {
            "category":"Home & Garden",
            "subcategory":"Carpets & Floor Coverings",
            "type":"Retail Goods"
        }
    ],
    "sg:phone":"+1 504 392 5050",
    "sg:postcode":"70056",
    "sg:province":"LA",
    "sg:tags":[
        "mattress"
    ],
    "sg:website":"www.thebabyshopla.com",
    "wof:name":"Baby Shop the",
    "wof:placetype":"venue"
},
  "geometry": {"coordinates":[-90.041,29.9002],"type":"Point"}
}