{
  "type": "Feature",
  "properties": {
    "addr:full":"175 Ward Line Rd Deridder LA 70634",
    "addr:housenumber":"175",
    "addr:postcode":"70634",
    "addr:street":"Ward Line Rd",
    "iso:country":"US",
    "sg:address":"175 Ward Line Rd",
    "sg:city":"Deridder",
    "sg:classifiers":[
        {
            "category":"Farming",
            "subcategory":"Farm & Veterinary Services",
            "type":"Manufacturing & Wholesale Goods"
        }
    ],
    "sg:phone":"+1 337 463 9851",
    "sg:postcode":"70634",
    "sg:province":"LA",
    "sg:tags":[
        "a",
        "horse",
        "ranch",
        "operates",
        "cattle"
    ],
    "wof:name":"Jesse Higman",
    "wof:placetype":"venue"
},
  "geometry": {"coordinates":[-93.37771100000001,30.774455],"type":"Point"}
}