{
  "type": "Feature",
  "properties": {
    "iso:country":"US",
    "sg:address":"5989 Lapalco Blvd",
    "sg:city":"Marrero",
    "sg:classifiers":[
        {
            "category":"Shopping",
            "subcategory":"Clothing, Apparel, & Fashions",
            "type":"Retail Goods"
        }
    ],
    "sg:phone":"+1 504 347 4768",
    "sg:postcode":"70072",
    "sg:province":"LA",
    "wof:name":"Cachet Inc",
    "wof:placetype":"venue"
},
  "geometry": {"coordinates":[-90.10992899999999,29.875244],"type":"Point"}
}