{
  "type": "Feature",
  "properties": {
    "iso:country":"US",
    "sg:address":"212 Main St",
    "sg:city":"Pineville",
    "sg:classifiers":[
        {
            "category":"Professional",
            "subcategory":"Research",
            "type":"Services"
        }
    ],
    "sg:phone":"+1 318 445 7352",
    "sg:postcode":"71360",
    "sg:province":"LA",
    "sg:tags":[
        "environmental",
        "ecological"
    ],
    "wof:name":"Pac Environmental",
    "wof:placetype":"venue"
},
  "geometry": {"coordinates":[-92.439937,31.316181],"type":"Point"}
}