{
  "type": "Feature",
  "properties": {
    "addr:full":"600 E Miller St Iowa LA 70647",
    "addr:housenumber":"600",
    "addr:postcode":"70647",
    "addr:street":"E Miller St",
    "iso:country":"US",
    "sg:address":"600 E Miller St",
    "sg:city":"Iowa",
    "sg:classifiers":[
        {
            "category":"Real Estate",
            "subcategory":"Real Estate Agent",
            "type":"Services"
        }
    ],
    "sg:phone":"+1 337 582 7460",
    "sg:postcode":"70647",
    "sg:province":"LA",
    "sg:tags":[
        "building",
        "leasing"
    ],
    "wof:name":"Alexander Waymon",
    "wof:placetype":"venue"
},
  "geometry": {"coordinates":[-93.00314299999999,30.245934],"type":"Point"}
}