{
  "type": "Feature",
  "properties": {
    "iso:country":"US",
    "sg:address":"1636 W Main St",
    "sg:city":"Ville Platte",
    "sg:classifiers":[
        {
            "category":"Restaurant",
            "type":"Food & Drink"
        }
    ],
    "sg:phone":"+1 337 363 9103",
    "sg:postcode":"70586",
    "sg:province":"LA",
    "wof:name":"Jungle Dinner Club",
    "wof:placetype":"venue"
},
  "geometry": {"coordinates":[-92.294691,30.694279],"type":"Point"}
}