{
  "type": "Feature",
  "properties": {
    "addr:full":"9 Bennett Dr Covington LA 70435",
    "addr:housenumber":"9",
    "addr:postcode":"70435",
    "addr:street":"Bennett Dr",
    "iso:country":"US",
    "sg:address":"9 Bennett Dr",
    "sg:city":"Covington",
    "sg:classifiers":[
        {
            "category":"Professional",
            "subcategory":"Engineering",
            "type":"Services"
        }
    ],
    "sg:phone":"+1 985 892 8932",
    "sg:postcode":"70435",
    "sg:province":"LA",
    "sg:tags":[
        "engineer"
    ],
    "wof:name":"Villere Engineering & Constr",
    "wof:placetype":"venue"
},
  "geometry": {"coordinates":[-90.092545,30.551555],"type":"Point"}
}