{
  "type": "Feature",
  "properties": {
    "addr:full":"1711 Royal Ave Monroe LA 71201",
    "addr:housenumber":"1711",
    "addr:postcode":"71201",
    "addr:street":"Royal Ave",
    "iso:country":"US",
    "sg:address":"1711 Royal Ave",
    "sg:city":"Monroe",
    "sg:classifiers":[
        {
            "category":"Insurance",
            "subcategory":"Insurance Agent",
            "type":"Services"
        }
    ],
    "sg:phone":"+1 318 329 2997",
    "sg:postcode":"71201",
    "sg:province":"LA",
    "wof:name":"Strategic Advisors Inc",
    "wof:placetype":"venue"
},
  "geometry": {"coordinates":[-92.11283299999999,32.518504],"type":"Point"}
}