{
  "type": "Feature",
  "properties": {
    "addr:full":"827 S Hopkins St New Iberia LA 70560",
    "addr:housenumber":"827",
    "addr:postcode":"70560",
    "addr:street":"S Hopkins St",
    "iso:country":"US",
    "sg:address":"827 S Hopkins St",
    "sg:city":"New Iberia",
    "sg:classifiers":[
        {
            "category":"Food & Beverages",
            "subcategory":"Groceries & Convenience Stores",
            "type":"Retail Goods"
        }
    ],
    "sg:phone":"+1 337 365 8864",
    "sg:postcode":"70560",
    "sg:province":"LA",
    "sg:tags":[
        "grocer"
    ],
    "wof:name":"Stacie's Food Market",
    "wof:placetype":"venue"
},
  "geometry": {"coordinates":[-91.831473,30.006138],"type":"Point"}
}