{
  "type": "Feature",
  "properties": {
    "iso:country":"US",
    "sg:address":"1539 Bartholomew St",
    "sg:city":"New Orleans",
    "sg:classifiers":[
        {
            "category":"Social Services",
            "subcategory":"Child Care",
            "type":"Services"
        }
    ],
    "sg:phone":"+1 504 947 1665",
    "sg:postcode":"70117",
    "sg:province":"LA",
    "sg:tags":[
        "day"
    ],
    "wof:name":"Miss Dee's Child Care Learning Center",
    "wof:placetype":"venue"
},
  "geometry": {"coordinates":[-90.034103,29.970501],"type":"Point"}
}