{
  "type": "Feature",
  "properties": {
    "addr:full":"611 Jessie Jones Rd Benton LA 71006",
    "addr:housenumber":"611",
    "addr:postcode":"71006",
    "addr:street":"Jessie Jones Rd",
    "iso:country":"US",
    "sg:address":"611 Jessie Jones Rd",
    "sg:city":"Benton",
    "sg:classifiers":[
        {
            "category":"Autos & Motor Vehicles",
            "subcategory":"Fuel & Gas Station",
            "type":"Retail Goods"
        }
    ],
    "sg:phone":"+1 318 965 1753",
    "sg:postcode":"71006",
    "sg:province":"LA",
    "sg:tags":[
        "oil"
    ],
    "wof:name":"Pelican Gas Management Inc",
    "wof:placetype":"venue"
},
  "geometry": {"coordinates":[-93.68565700000001,32.644302],"type":"Point"}
}