{
  "type": "Feature",
  "properties": {
    "iso:country":"US",
    "sg:address":"105 Rockne Dr",
    "sg:city":"Lafayette",
    "sg:classifiers":[
        {
            "category":"Manufacturing",
            "subcategory":"Tools & Machinery",
            "type":"Manufacturing & Wholesale Goods"
        }
    ],
    "sg:phone":"+1 337 234 6338",
    "sg:postcode":"70506",
    "sg:province":"LA",
    "sg:tags":[
        "measuring",
        "instrument",
        "electrical",
        "mfg"
    ],
    "wof:name":"Moores Computer Technology",
    "wof:placetype":"venue"
},
  "geometry": {"coordinates":[-92.08377400000001,30.224879],"type":"Point"}
}