{
  "type": "Feature",
  "properties": {
    "addr:full":"679 Noah Haymon Rd Leesville LA 71446",
    "addr:housenumber":"679",
    "addr:postcode":"71446",
    "addr:street":"Noah Haymon Rd",
    "iso:country":"US",
    "sg:address":"679 Noah Haymon Rd",
    "sg:city":"Leesville",
    "sg:classifiers":[
        {
            "category":"Building & Trades",
            "subcategory":"Plumbing",
            "type":"Services"
        }
    ],
    "sg:phone":"+1 337 238 9831",
    "sg:postcode":"71446",
    "sg:province":"LA",
    "sg:tags":[
        "plumbing",
        "contractor"
    ],
    "wof:name":"Dewayne Phillips Plumbing",
    "wof:placetype":"venue"
},
  "geometry": {"coordinates":[-93.20841,31.199123],"type":"Point"}
}