{
  "type": "Feature",
  "properties": {
    "iso:country":"US",
    "sg:address":"40329 Woodland Ave",
    "sg:city":"Gonzales",
    "sg:classifiers":[
        {
            "category":"Real Estate",
            "subcategory":"Real Estate Agent",
            "type":"Services"
        }
    ],
    "sg:phone":"+1 225 622 7441",
    "sg:postcode":"70737",
    "sg:province":"LA",
    "sg:tags":[
        "business"
    ],
    "wof:name":"James Kennerly Consulting",
    "wof:placetype":"venue"
},
  "geometry": {"coordinates":[-90.929568,30.293801],"type":"Point"}
}