{
  "type": "Feature",
  "properties": {
    "iso:country":"US",
    "sg:address":"211 S Broad St",
    "sg:city":"New Orleans",
    "sg:classifiers":[
        {
            "category":"Professional",
            "subcategory":"Accounting & Tax Preparation",
            "type":"Services"
        }
    ],
    "sg:phone":"+1 504 821 6073",
    "sg:postcode":"70119",
    "sg:province":"LA",
    "sg:tags":[
        "return",
        "filing"
    ],
    "wof:name":"Pritchett-Franklin Tax Svc",
    "wof:placetype":"venue"
},
  "geometry": {"coordinates":[-90.088649,29.96435],"type":"Point"}
}