{
  "type": "Feature",
  "properties": {
    "iso:country":"US",
    "sg:address":"1245 Grand Caillou Rd",
    "sg:city":"Houma",
    "sg:classifiers":[
        {
            "category":"Shopping",
            "type":"Retail Goods"
        }
    ],
    "sg:phone":"+1 985 868 6039",
    "sg:postcode":"70363",
    "sg:province":"LA",
    "sg:tags":[
        "telephone",
        "cellular"
    ],
    "wof:name":"Radio Shack",
    "wof:placetype":"venue"
},
  "geometry": {"coordinates":[-90.68948899999999,29.578072],"type":"Point"}
}