{
  "type": "Feature",
  "properties": {
    "iso:country":"US",
    "sg:address":"2409 Rue Pinckney",
    "sg:city":"Mandeville",
    "sg:classifiers":[
        {
            "category":"Social Services",
            "subcategory":"Child Care",
            "type":"Services"
        }
    ],
    "sg:phone":"+1 985 626 5726",
    "sg:postcode":"70448",
    "sg:province":"LA",
    "wof:name":"LA Petite Acad On The North",
    "wof:placetype":"venue"
},
  "geometry": {"coordinates":[-90.02370999999999,30.369417],"type":"Point"}
}