{
  "type": "Feature",
  "properties": {
    "addr:full":"37225 Knollwood Ct Denham Springs LA 70706",
    "addr:housenumber":"37225",
    "addr:postcode":"70706",
    "addr:street":"Knollwood Ct",
    "iso:country":"US",
    "sg:address":"37225 Knollwood Ct",
    "sg:city":"Denham Springs",
    "sg:classifiers":[
        {
            "category":"Retail",
            "subcategory":"Repair Shop",
            "type":"Services"
        }
    ],
    "sg:phone":"+1 225 664 1527",
    "sg:postcode":"70706",
    "sg:province":"LA",
    "wof:name":"Adams Taxidermy",
    "wof:placetype":"venue"
},
  "geometry": {"coordinates":[-90.925611,30.607978],"type":"Point"}
}