{
  "type": "Feature",
  "properties": {
    "addr:full":"4145 Piedmont Dr New Orleans LA 70122",
    "addr:housenumber":"4145",
    "addr:postcode":"70122",
    "addr:street":"Piedmont Dr",
    "iso:country":"US",
    "sg:address":"4145 Piedmont Dr",
    "sg:city":"New Orleans",
    "sg:classifiers":[
        {
            "category":"Building & Trades",
            "subcategory":"Electrical",
            "type":"Services"
        }
    ],
    "sg:phone":"+1 504 943 7836",
    "sg:postcode":"70122",
    "sg:province":"LA",
    "sg:tags":[
        "electric",
        "contractor"
    ],
    "wof:name":"Reliance Electric",
    "wof:placetype":"venue"
},
  "geometry": {"coordinates":[-90.05709299999999,30.001247],"type":"Point"}
}