{
  "type": "Feature",
  "properties": {
    "addr:full":"509 Carmel Loop Mansfield LA 71052",
    "addr:housenumber":"509",
    "addr:postcode":"71052",
    "addr:street":"Carmel Loop",
    "iso:country":"US",
    "sg:address":"509 Carmel Loop",
    "sg:city":"Mansfield",
    "sg:classifiers":[
        {
            "category":"Organizations",
            "subcategory":"Religious Organization",
            "type":"Services"
        }
    ],
    "sg:phone":"+1 318 872 9504",
    "sg:postcode":"71052",
    "sg:province":"LA",
    "wof:name":"New Hope Baptist Church",
    "wof:placetype":"venue"
},
  "geometry": {"coordinates":[-93.62056699999999,32.086777],"type":"Point"}
}