{
  "type": "Feature",
  "properties": {
    "addr:full":"527 W Gloria Switch Rd Lafayette LA 70507",
    "addr:housenumber":"527",
    "addr:postcode":"70507",
    "addr:street":"W Gloria Switch Rd",
    "iso:country":"US",
    "sg:address":"527 W Gloria Switch Rd",
    "sg:city":"Lafayette",
    "sg:classifiers":[
        {
            "category":"Banks & Credit Unions",
            "subcategory":"Financial Services",
            "type":"Services"
        }
    ],
    "sg:phone":"+1 337 886 9991",
    "sg:postcode":"70507",
    "sg:province":"LA",
    "sg:tags":[
        "broker",
        "mortgage"
    ],
    "wof:name":"Oakridge Residential Lenders",
    "wof:placetype":"venue"
},
  "geometry": {"coordinates":[-92.036039,30.297693],"type":"Point"}
}