{
  "type": "Feature",
  "properties": {
    "iso:country":"US",
    "sg:address":"11999 Longridge Ave",
    "sg:city":"Baton Rouge",
    "sg:classifiers":[
        {
            "category":"Real Estate",
            "subcategory":"Real Estate Operator",
            "type":"Services"
        }
    ],
    "sg:phone":"+1 225 295 9990",
    "sg:postcode":"70816",
    "sg:province":"LA",
    "sg:tags":[
        "apartment"
    ],
    "sg:website":"www.apartsments.com",
    "wof:name":"Longridge Apartments",
    "wof:placetype":"venue"
},
  "geometry": {"coordinates":[-91.048316,30.422436],"type":"Point"}
}