{
  "type": "Feature",
  "properties": {
    "addr:full":"205 Couvillion Rd Simmesport LA 71369",
    "addr:housenumber":"205",
    "addr:postcode":"71369",
    "addr:street":"Couvillion Rd",
    "iso:country":"US",
    "sg:address":"205 Couvillion Rd",
    "sg:city":"Simmesport",
    "sg:classifiers":[
        {
            "category":"Farming",
            "subcategory":"Farm",
            "type":"Manufacturing & Wholesale Goods"
        }
    ],
    "sg:phone":"+1 318 941 2713",
    "sg:postcode":"71369",
    "sg:province":"LA",
    "sg:tags":[
        "crop",
        "general"
    ],
    "wof:name":"Couvillion Bros",
    "wof:placetype":"venue"
},
  "geometry": {"coordinates":[-91.811983,30.926915],"type":"Point"}
}