{
  "type": "Feature",
  "properties": {
    "iso:country":"US",
    "sg:address":"302 S Washington St",
    "sg:city":"Marksville",
    "sg:classifiers":[
        {
            "category":"Personal",
            "subcategory":"Shoe Repair & Shine",
            "type":"Services"
        }
    ],
    "sg:phone":"+1 318 253 7463",
    "sg:postcode":"71351",
    "sg:province":"LA",
    "sg:tags":[
        "repairing",
        "boot"
    ],
    "wof:name":"Jackson's Shoe Repair",
    "wof:placetype":"venue"
},
  "geometry": {"coordinates":[-92.06974099999999,31.122644],"type":"Point"}
}