{
  "type": "Feature",
  "properties": {
    "iso:country":"US",
    "sg:address":"720 Brantford Dr",
    "sg:city":"Port Allen",
    "sg:classifiers":[
        {
            "category":"Building & Trades",
            "subcategory":"Plumbing",
            "type":"Services"
        }
    ],
    "sg:phone":"+1 225 343 7260",
    "sg:postcode":"70767",
    "sg:province":"LA",
    "sg:tags":[
        "conditioning",
        "air",
        "system",
        "contractor"
    ],
    "wof:name":"A-1 Air Conditioning",
    "wof:placetype":"venue"
},
  "geometry": {"coordinates":[-91.27481400000001,30.458442],"type":"Point"}
}