{
  "type": "Feature",
  "properties": {
    "iso:country":"US",
    "sg:address":"995 Main St",
    "sg:city":"Many",
    "sg:classifiers":[
        {
            "category":"Professional",
            "subcategory":"Employment Agencies",
            "type":"Services"
        }
    ],
    "sg:phone":"+1 318 256 2400",
    "sg:postcode":"71449",
    "sg:province":"LA",
    "wof:name":"Westaff",
    "wof:placetype":"venue"
},
  "geometry": {"coordinates":[-93.48112399999999,31.567816],"type":"Point"}
}