{
  "type": "Feature",
  "properties": {
    "iso:country":"US",
    "sg:address":"413 Interlude Rd",
    "sg:city":"New Iberia",
    "sg:classifiers":[
        {
            "category":"Farming",
            "subcategory":"Farm & Veterinary Services",
            "type":"Manufacturing & Wholesale Goods"
        }
    ],
    "sg:phone":"+1 337 560 4581",
    "sg:postcode":"70563",
    "sg:province":"LA",
    "sg:tags":[
        "control",
        "weed"
    ],
    "wof:name":"Spraymax Inc",
    "wof:placetype":"venue"
},
  "geometry": {"coordinates":[-91.74936,30.005097],"type":"Point"}
}