{
  "type": "Feature",
  "properties": {
    "iso:country":"US",
    "sg:address":"105 Blanchard Dr",
    "sg:city":"West Monroe",
    "sg:classifiers":[
        {
            "category":"Professional",
            "subcategory":"Management & Consulting",
            "type":"Services"
        }
    ],
    "sg:phone":"+1 318 322 5523",
    "sg:postcode":"71291",
    "sg:province":"LA",
    "sg:tags":[
        "party",
        "planning"
    ],
    "sg:website":"www.thejunglegym.net",
    "wof:name":"Jungle Gym",
    "wof:placetype":"venue"
},
  "geometry": {"coordinates":[-92.165019,32.512562],"type":"Point"}
}