{
  "type": "Feature",
  "properties": {
    "addr:full":"1001 Canal Blvd Thibodaux LA 70301",
    "addr:housenumber":"1001",
    "addr:postcode":"70301",
    "addr:street":"Canal Blvd",
    "iso:country":"US",
    "sg:address":"1001 Canal Blvd",
    "sg:city":"Thibodaux",
    "sg:classifiers":[
        {
            "category":"Museum",
            "type":"Entertainment"
        }
    ],
    "sg:phone":"+1 985 446 2200",
    "sg:postcode":"70301",
    "sg:province":"LA",
    "wof:name":"Bayou Country Children's Msm",
    "wof:placetype":"venue"
},
  "geometry": {"coordinates":[-90.82132300000001,29.790967],"type":"Point"}
}