{
  "type": "Feature",
  "properties": {
    "addr:full":"15041 Speas Ct Leesville LA 71459",
    "addr:postcode":"15041;71459",
    "addr:street":"Speas Ct",
    "iso:country":"US",
    "sg:address":"15041 Speas Ct",
    "sg:city":"Leesville",
    "sg:classifiers":[
        {
            "category":"Arts & Performance",
            "subcategory":"Theater",
            "type":"Entertainment"
        }
    ],
    "sg:phone":"+1 337 535 0471",
    "sg:postcode":"71459",
    "sg:province":"LA",
    "sg:tags":[
        "musician"
    ],
    "wof:name":"Rolanda F Blake",
    "wof:placetype":"venue"
},
  "geometry": {"coordinates":[-93.19694699999999,31.104892],"type":"Point"}
}