{
  "type": "Feature",
  "properties": {
    "iso:country":"US",
    "sg:address":"1126 N Airline Hwy",
    "sg:city":"Gonzales",
    "sg:classifiers":[
        {
            "category":"Retail",
            "subcategory":"Car Wash",
            "type":"Services"
        }
    ],
    "sg:phone":"+1 225 644 7269",
    "sg:postcode":"70737",
    "sg:province":"LA",
    "sg:tags":[
        "polishing",
        "washing"
    ],
    "wof:name":"Buffy's Carwash & Xpress Lube",
    "wof:placetype":"venue"
},
  "geometry": {"coordinates":[-90.916532,30.241507],"type":"Point"}
}