{
  "type": "Feature",
  "properties": {
    "addr:full":"4114 Old Gentilly Rd New Orleans LA 70126",
    "addr:housenumber":"4114",
    "addr:postcode":"70126",
    "addr:street":"Old Gentilly Rd",
    "iso:country":"US",
    "sg:address":"4114 Old Gentilly Rd",
    "sg:city":"New Orleans",
    "sg:classifiers":[
        {
            "category":"Organizations",
            "subcategory":"Religious Organization",
            "type":"Services"
        }
    ],
    "sg:phone":"+1 504 943 8050",
    "sg:postcode":"70126",
    "sg:province":"LA",
    "sg:tags":[
        "church"
    ],
    "wof:name":"New Life Ministry",
    "wof:placetype":"venue"
},
  "geometry": {"coordinates":[-90.03986,30.002597],"type":"Point"}
}