{
  "type": "Feature",
  "properties": {
    "iso:country":"US",
    "sg:address":"1106 S Chestnut St",
    "sg:city":"Hammond",
    "sg:classifiers":[
        {
            "category":"Building & Trades",
            "subcategory":"Landscaping Services",
            "type":"Services"
        }
    ],
    "sg:phone":"+1 985 350 6590",
    "sg:postcode":"70403",
    "sg:province":"LA",
    "sg:tags":[
        "landscape",
        "contractor"
    ],
    "wof:name":"Classic Landscape & Irrigation",
    "wof:placetype":"venue"
},
  "geometry": {"coordinates":[-90.451669,30.494626],"type":"Point"}
}