{
  "type": "Feature",
  "properties": {
    "iso:country":"US",
    "sg:address":"122 Robinhood Rd",
    "sg:city":"Covington",
    "sg:classifiers":[
        {
            "category":"Retail",
            "subcategory":"Portrait Studio",
            "type":"Services"
        }
    ],
    "sg:phone":"+1 985 898 0387",
    "sg:postcode":"70433",
    "sg:province":"LA",
    "sg:tags":[
        "photo"
    ],
    "wof:name":"Armin Diblin Photography",
    "wof:placetype":"venue"
},
  "geometry": {"coordinates":[-90.079491,30.435872],"type":"Point"}
}