{
  "type": "Feature",
  "properties": {
    "addr:full":"807 Ridgefield Rd Thibodaux LA 70301",
    "addr:housenumber":"807",
    "addr:postcode":"70301",
    "addr:street":"Ridgefield Rd",
    "iso:country":"US",
    "sg:address":"807 Ridgefield Rd",
    "sg:city":"Thibodaux",
    "sg:classifiers":[
        {
            "category":"Professional",
            "subcategory":"Accounting & Tax Preparation",
            "type":"Services"
        }
    ],
    "sg:phone":"+1 985 446 6819",
    "sg:postcode":"70301",
    "sg:province":"LA",
    "sg:tags":[
        "billing"
    ],
    "wof:name":"Children's Clinic",
    "wof:placetype":"venue"
},
  "geometry": {"coordinates":[-90.827065,29.793422],"type":"Point"}
}