{
  "type": "Feature",
  "properties": {
    "iso:country":"US",
    "sg:address":"107 S Monroe St",
    "sg:city":"West Monroe",
    "sg:classifiers":[
        {
            "category":"Restaurant",
            "type":"Food & Drink"
        }
    ],
    "sg:phone":"+1 318 387 8120",
    "sg:postcode":"71270",
    "sg:province":"LA",
    "wof:name":"Captain D's Seafood",
    "wof:placetype":"venue"
},
  "geometry": {"coordinates":[-92.640702,32.528356],"type":"Point"}
}