{
  "type": "Feature",
  "properties": {
    "iso:country":"US",
    "sg:address":"4133 N Miro St",
    "sg:city":"New Orleans",
    "sg:classifiers":[
        {
            "category":"Personal",
            "subcategory":"Beauty Salon",
            "type":"Services"
        }
    ],
    "sg:phone":"+1 504 944 0944",
    "sg:postcode":"70117",
    "sg:province":"LA",
    "sg:tags":[
        "shop"
    ],
    "wof:name":"Trichology Adornment Center",
    "wof:placetype":"venue"
},
  "geometry": {"coordinates":[-90.030387,29.976668],"type":"Point"}
}