{
  "type": "Feature",
  "properties": {
    "iso:country":"US",
    "sg:address":"515 Decatur St",
    "sg:city":"New Orleans",
    "sg:classifiers":[
        {
            "category":"Shopping",
            "subcategory":"Gifts & Souvenirs",
            "type":"Retail Goods"
        }
    ],
    "sg:phone":"+1 504 522 1505",
    "sg:postcode":"70130",
    "sg:province":"LA",
    "sg:tags":[
        "shop"
    ],
    "wof:name":"Mask Factory",
    "wof:placetype":"venue"
},
  "geometry": {"coordinates":[-90.063619,29.95584],"type":"Point"}
}