{
  "type": "Feature",
  "properties": {
    "iso:country":"US",
    "sg:address":"1448 Evangeline Rd",
    "sg:city":"Jennings",
    "sg:classifiers":[
        {
            "category":"Education",
            "subcategory":"Library",
            "type":"Public Place"
        }
    ],
    "sg:phone":"+1 337 824 6443",
    "sg:postcode":"70546",
    "sg:province":"LA",
    "wof:name":"Evangeline Branch Library",
    "wof:placetype":"venue"
},
  "geometry": {"coordinates":[-92.642844,30.235764],"type":"Point"}
}