{
  "type": "Feature",
  "properties": {
    "iso:country":"US",
    "sg:address":"2849 Verot School Rd",
    "sg:city":"Lafayette",
    "sg:classifiers":[
        {
            "category":"Building & Trades",
            "subcategory":"Pest Control",
            "type":"Services"
        }
    ],
    "sg:phone":"+1 337 856 8785",
    "sg:postcode":"70508",
    "sg:province":"LA",
    "wof:name":"Foti Exterminating Co",
    "wof:placetype":"venue"
},
  "geometry": {"coordinates":[-92.03261500000001,30.14328],"type":"Point"}
}