{
  "type": "Feature",
  "properties": {
    "addr:full":"3112 Loyola Dr Kenner LA 70065",
    "addr:housenumber":"3112",
    "addr:postcode":"70065",
    "addr:street":"Loyola Dr",
    "iso:country":"US",
    "sg:address":"3112 Loyola Dr",
    "sg:city":"Kenner",
    "sg:classifiers":[
        {
            "category":"Shopping",
            "type":"Retail Goods"
        }
    ],
    "sg:phone":"+1 504 464 7978",
    "sg:postcode":"70065",
    "sg:province":"LA",
    "sg:tags":[
        "cosmetic",
        "perfume"
    ],
    "wof:name":"Acme Beauty Supply",
    "wof:placetype":"venue"
},
  "geometry": {"coordinates":[-90.266352,30.010719],"type":"Point"}
}