{
  "type": "Feature",
  "properties": {
    "iso:country":"US",
    "sg:address":"49 Thompson Rd",
    "sg:city":"Lecompte",
    "sg:classifiers":[
        {
            "category":"Freight",
            "type":"Transportation"
        }
    ],
    "sg:phone":"+1 318 776 1637",
    "sg:postcode":"71346",
    "sg:province":"LA",
    "wof:name":"Ambassador Hill Trnsprtn & Ls",
    "wof:placetype":"venue"
},
  "geometry": {"coordinates":[-92.427584,31.112374],"type":"Point"}
}