{
  "type": "Feature",
  "properties": {
    "iso:country":"US",
    "sg:address":"2051 Metairie Rd",
    "sg:city":"Metairie",
    "sg:classifiers":[
        {
            "category":"Cafe",
            "type":"Food & Drink"
        }
    ],
    "sg:menulink":"http://www.allmenus.com/la/metairie/280551-vega-tapas-cafe/menu/",
    "sg:phone":"+1 504 836 2007",
    "sg:postcode":"70005",
    "sg:province":"LA",
    "sg:tags":[
        "new",
        "american"
    ],
    "wof:name":"Vega Tapas Cafe",
    "wof:placetype":"venue"
},
  "geometry": {"coordinates":[-90.14534500000001,29.985414],"type":"Point"}
}