{
  "type": "Feature",
  "properties": {
    "addr:full":"400 E Kaliste Saloom Rd Lafayette LA 70508",
    "addr:housenumber":"400",
    "addr:postcode":"70508",
    "addr:street":"E Kaliste Saloom Rd",
    "iso:country":"US",
    "sg:address":"400 E Kaliste Saloom Rd",
    "sg:city":"Lafayette",
    "sg:classifiers":[
        {
            "category":"Professional",
            "subcategory":"Lawyer & Legal Services",
            "type":"Services"
        }
    ],
    "sg:phone":"+1 337 232 3333",
    "sg:postcode":"70508",
    "sg:province":"LA",
    "sg:tags":[
        "attorney"
    ],
    "wof:name":"Bob Broussard",
    "wof:placetype":"venue"
},
  "geometry": {"coordinates":[-92.006309,30.195332],"type":"Point"}
}