{
  "type": "Feature",
  "properties": {
    "iso:country":"US",
    "sg:address":"1257 Shreveport Barksdale Hwy",
    "sg:city":"Shreveport",
    "sg:classifiers":[
        {
            "category":"Shopping",
            "subcategory":"Shoes",
            "type":"Retail Goods"
        }
    ],
    "sg:phone":"+1 318 688 0494",
    "sg:postcode":"71105",
    "sg:province":"LA",
    "wof:name":"Wenzhou Chasan Jinshida Shoes",
    "wof:placetype":"venue"
},
  "geometry": {"coordinates":[-93.70560500000001,32.487469],"type":"Point"}
}