{
  "type": "Feature",
  "properties": {
    "iso:country":"US",
    "sg:address":"900 Wilkinson St",
    "sg:city":"Mandeville",
    "sg:classifiers":[
        {
            "category":"Government",
            "subcategory":"Office",
            "type":"Public Place"
        }
    ],
    "sg:phone":"+1 985 624 4450",
    "sg:postcode":"70448",
    "sg:province":"LA",
    "sg:tags":[
        "state",
        "program",
        "health"
    ],
    "wof:name":"Lurline Smith Mental Health",
    "wof:placetype":"venue"
},
  "geometry": {"coordinates":[-90.070268,30.369705],"type":"Point"}
}