{
  "type": "Feature",
  "properties": {
    "addr:full":"900 Sterlington Rd Monroe LA 71203",
    "addr:housenumber":"900",
    "addr:postcode":"71203",
    "addr:street":"Sterlington Rd",
    "iso:country":"US",
    "sg:address":"900 Sterlington Rd",
    "sg:city":"Monroe",
    "sg:classifiers":[
        {
            "category":"Restaurant",
            "type":"Food & Drink"
        }
    ],
    "sg:menulink":"http://www.allmenus.com/la/monroe/208635-taco-bell/menu/",
    "sg:phone":"+1 318 343 9797",
    "sg:postcode":"71203",
    "sg:province":"LA",
    "sg:tags":[
        "mexican"
    ],
    "wof:name":"Taco Bell",
    "wof:placetype":"venue"
},
  "geometry": {"coordinates":[-92.080003,32.529948],"type":"Point"}
}