{
  "type": "Feature",
  "properties": {
    "iso:country":"US",
    "sg:address":"222 W Saint Peter St",
    "sg:city":"New Iberia",
    "sg:classifiers":[
        {
            "category":"Professional",
            "subcategory":"Lawyer & Legal Services",
            "type":"Services"
        }
    ],
    "sg:phone":"+1 337 367 8451",
    "sg:postcode":"70560",
    "sg:province":"LA",
    "wof:name":"Akers Donald D Jr",
    "wof:placetype":"venue"
},
  "geometry": {"coordinates":[-91.821404,30.007601],"type":"Point"}
}