{
  "type": "Feature",
  "properties": {
    "iso:country":"US",
    "sg:address":"1801 Natchitoches Hwy",
    "sg:city":"Many",
    "sg:classifiers":[
        {
            "category":"Education",
            "subcategory":"School",
            "type":"Public Place"
        }
    ],
    "sg:phone":"+1 318 256 3573",
    "sg:postcode":"71449",
    "sg:province":"LA",
    "wof:name":"Many Junior High School",
    "wof:placetype":"venue"
},
  "geometry": {"coordinates":[-93.448196,31.593494],"type":"Point"}
}