{
  "type": "Feature",
  "properties": {
    "addr:full":"914 Union St New Orleans LA 70112",
    "addr:housenumber":"914",
    "addr:postcode":"70112",
    "addr:street":"Union St",
    "iso:country":"US",
    "sg:address":"914 Union St",
    "sg:city":"New Orleans",
    "sg:classifiers":[
        {
            "category":"Health Services",
            "subcategory":"Clinic",
            "type":"Services"
        }
    ],
    "sg:phone":"+1 504 528 3750",
    "sg:postcode":"70112",
    "sg:province":"LA",
    "wof:name":"Homeless Health Care Clinic",
    "wof:placetype":"venue"
},
  "geometry": {"coordinates":[-90.073604,29.952051],"type":"Point"}
}