{
  "type": "Feature",
  "properties": {
    "addr:full":"609 East St Houma LA 70363",
    "addr:housenumber":"609",
    "addr:postcode":"70363",
    "addr:street":"East St",
    "iso:country":"US",
    "sg:address":"609 East St",
    "sg:city":"Houma",
    "sg:classifiers":[
        {
            "category":"Education",
            "subcategory":"School",
            "type":"Public Place"
        }
    ],
    "sg:phone":"+1 985 872 3378",
    "sg:postcode":"70363",
    "sg:province":"LA",
    "wof:name":"East Street School",
    "wof:placetype":"venue"
},
  "geometry": {"coordinates":[-90.68928,29.592793],"type":"Point"}
}