{
  "type": "Feature",
  "properties": {
    "addr:full":"2023 Plank Rd Baton Rouge LA 70802",
    "addr:housenumber":"2023",
    "addr:postcode":"70802",
    "addr:street":"Plank Rd",
    "iso:country":"US",
    "sg:address":"2023 Plank Rd",
    "sg:city":"Baton Rouge",
    "sg:classifiers":[
        {
            "category":"Social Services",
            "subcategory":"Child Care",
            "type":"Services"
        }
    ],
    "sg:phone":"+1 225 357 8011",
    "sg:postcode":"70802",
    "sg:province":"LA",
    "sg:tags":[
        "day"
    ],
    "wof:name":"Lolly Pop Day Care",
    "wof:placetype":"venue"
},
  "geometry": {"coordinates":[-91.16509000000001,30.465602],"type":"Point"}
}