{
  "type": "Feature",
  "properties": {
    "addr:full":"36444 Weiss Rd Walker LA 70785",
    "addr:postcode":"36444;70785",
    "addr:street":"Weiss Rd",
    "iso:country":"US",
    "sg:address":"36444 Weiss Rd",
    "sg:city":"Walker",
    "sg:classifiers":[
        {
            "category":"Professional",
            "type":"Services"
        }
    ],
    "sg:phone":"+1 225 665 3151",
    "sg:postcode":"70785",
    "sg:province":"LA",
    "sg:tags":[
        "establishment"
    ],
    "wof:name":"Restivo & Holland",
    "wof:placetype":"venue"
},
  "geometry": {"coordinates":[-90.783886,30.597145],"type":"Point"}
}