{
  "type": "Feature",
  "properties": {
    "iso:country":"US",
    "sg:address":"3600 4th St",
    "sg:city":"Harvey",
    "sg:classifiers":[
        {
            "category":"Bars & Pubs",
            "type":"Food & Drink"
        }
    ],
    "sg:phone":"+1 504 340 8323",
    "sg:postcode":"70058",
    "sg:province":"LA",
    "wof:name":"Laurie's Tavern",
    "wof:placetype":"venue"
},
  "geometry": {"coordinates":[-90.089159,29.906257],"type":"Point"}
}