{
  "type": "Feature",
  "properties": {
    "addr:full":"732 Domengeaux Rd Sunset LA 70584",
    "addr:housenumber":"732",
    "addr:postcode":"70584",
    "addr:street":"Domengeaux Rd",
    "iso:country":"US",
    "sg:address":"732 Domengeaux Rd",
    "sg:city":"Sunset",
    "sg:classifiers":[
        {
            "category":"Retail",
            "subcategory":"Animal Services",
            "type":"Services"
        }
    ],
    "sg:phone":"+1 337 668 4241",
    "sg:postcode":"70584",
    "sg:province":"LA",
    "wof:name":"Corey Lanerie Enterprises Inc",
    "wof:placetype":"venue"
},
  "geometry": {"coordinates":[-92.101845,30.355104],"type":"Point"}
}