{
  "type": "Feature",
  "properties": {
    "iso:country":"US",
    "sg:address":"393 Mountain Rd",
    "sg:city":"West Monroe",
    "sg:classifiers":[
        {
            "category":"Professional",
            "subcategory":"Computer Services",
            "type":"Services"
        }
    ],
    "sg:phone":"+1 318 397 0390",
    "sg:postcode":"71291",
    "sg:province":"LA",
    "wof:name":"Internet Business Consultants",
    "wof:placetype":"venue"
},
  "geometry": {"coordinates":[-92.266621,32.522518],"type":"Point"}
}