{
  "type": "Feature",
  "properties": {
    "iso:country":"US",
    "sg:address":"1216 Macarthur Dr",
    "sg:city":"Alexandria",
    "sg:classifiers":[
        {
            "category":"Building & Trades",
            "subcategory":"Landscaping Services",
            "type":"Services"
        }
    ],
    "sg:phone":"+1 318 443 2898",
    "sg:postcode":"71303",
    "sg:province":"LA",
    "sg:tags":[
        "lawn",
        "maintenance",
        "grounds"
    ],
    "wof:name":"Petrus Lawn & Shrub Inc",
    "wof:placetype":"venue"
},
  "geometry": {"coordinates":[-92.47636,31.289061],"type":"Point"}
}