{
  "type": "Feature",
  "properties": {
    "iso:country":"US",
    "sg:address":"502 N Verone St",
    "sg:city":"Leesville",
    "sg:classifiers":[
        {
            "category":"Restaurant",
            "type":"Food & Drink"
        }
    ],
    "sg:phone":"+1 337 392 0076",
    "sg:postcode":"71446",
    "sg:province":"LA",
    "wof:name":"Destiny's Cafe & Snow Cone Shp",
    "wof:placetype":"venue"
},
  "geometry": {"coordinates":[-93.27182000000001,31.147313],"type":"Point"}
}