{
  "type": "Feature",
  "properties": {
    "iso:country":"US",
    "sg:address":"1925 Hwy 15",
    "sg:city":"West Monroe",
    "sg:classifiers":[
        {
            "category":"Real Estate",
            "subcategory":"Real Estate Agent",
            "type":"Services"
        }
    ],
    "sg:phone":"+1 318 396 2898",
    "sg:postcode":"71291",
    "sg:province":"LA",
    "wof:name":"Barbara Carter Realty",
    "wof:placetype":"venue"
},
  "geometry": {"coordinates":[-92.267708,32.556176],"type":"Point"}
}