{
  "type": "Feature",
  "properties": {
    "iso:country":"US",
    "sg:address":"3000 Kingman St",
    "sg:city":"Metairie",
    "sg:classifiers":[
        {
            "category":"Personal",
            "subcategory":"Beauty Salon",
            "type":"Services"
        }
    ],
    "sg:phone":"+1 504 887 6452",
    "sg:postcode":"70006",
    "sg:province":"LA",
    "sg:tags":[
        "shop",
        "treatment",
        "skin"
    ],
    "wof:name":"Exquisite Skin Care Clinic",
    "wof:placetype":"venue"
},
  "geometry": {"coordinates":[-90.180278,30.002257],"type":"Point"}
}