{
  "type": "Feature",
  "properties": {
    "iso:country":"US",
    "sg:address":"3042 Ryan St",
    "sg:city":"Lake Charles",
    "sg:classifiers":[
        {
            "category":"Shopping",
            "subcategory":"Gifts & Souvenirs",
            "type":"Retail Goods"
        }
    ],
    "sg:phone":"+1 337 436 2109",
    "sg:postcode":"70601",
    "sg:province":"LA",
    "sg:tags":[
        "party",
        "supply"
    ],
    "wof:name":"Balloon Delights",
    "wof:placetype":"venue"
},
  "geometry": {"coordinates":[-93.21872399999999,30.200631],"type":"Point"}
}