{
  "type": "Feature",
  "properties": {
    "iso:country":"US",
    "sg:address":"509 W 8th St",
    "sg:city":"Bogalusa",
    "sg:classifiers":[
        {
            "category":"Restaurant",
            "type":"Food & Drink"
        }
    ],
    "sg:phone":"+1 985 732 0102",
    "sg:postcode":"70427",
    "sg:province":"LA",
    "wof:name":"Drummonds Hot Tamales",
    "wof:placetype":"venue"
},
  "geometry": {"coordinates":[-89.87209300000001,30.772935],"type":"Point"}
}