{
  "type": "Feature",
  "properties": {
    "iso:country":"US",
    "sg:address":"101 Eucharist Rd",
    "sg:city":"Lafayette",
    "sg:classifiers":[
        {
            "category":"Building & Trades",
            "subcategory":"Construction",
            "type":"Services"
        }
    ],
    "sg:phone":"+1 337 896 4414",
    "sg:postcode":"70507",
    "sg:province":"LA",
    "sg:tags":[
        "product",
        "mfg",
        "contractor",
        "wood",
        "cabinet",
        "maker",
        "carpentry"
    ],
    "wof:name":"Howk's Custom Woodworks Inc",
    "wof:placetype":"venue"
},
  "geometry": {"coordinates":[-92.09553099999999,30.288273],"type":"Point"}
}