{
  "type": "Feature",
  "properties": {
    "iso:country":"US",
    "sg:address":"280 N Leo St",
    "sg:city":"Baton Rouge",
    "sg:classifiers":[
        {
            "category":"Retail",
            "subcategory":"Auto Repair",
            "type":"Services"
        }
    ],
    "sg:phone":"+1 225 383 0671",
    "sg:postcode":"70806",
    "sg:province":"LA",
    "sg:tags":[
        "repairing",
        "automobile",
        "general"
    ],
    "wof:name":"Auto Brake & Electric Svc",
    "wof:placetype":"venue"
},
  "geometry": {"coordinates":[-91.14628,30.449597],"type":"Point"}
}