{
  "type": "Feature",
  "properties": {
    "iso:country":"US",
    "sg:address":"5216 Airline Dr",
    "sg:city":"Bossier City",
    "sg:classifiers":[
        {
            "category":"Personal",
            "type":"Services"
        }
    ],
    "sg:phone":"+1 318 742 5300",
    "sg:postcode":"71111",
    "sg:province":"LA",
    "wof:name":"North Airline Self Storage",
    "wof:placetype":"venue"
},
  "geometry": {"coordinates":[-93.714264,32.612242],"type":"Point"}
}