{
  "type": "Feature",
  "properties": {
    "iso:country":"US",
    "sg:address":"906 Bourbon St",
    "sg:city":"New Orleans",
    "sg:classifiers":[
        {
            "category":"Personal",
            "subcategory":"Beauty Salon",
            "type":"Services"
        }
    ],
    "sg:phone":"+1 504 568 0465",
    "sg:postcode":"70116",
    "sg:province":"LA",
    "sg:tags":[
        "shop"
    ],
    "wof:name":"Moulin Rouge Beauty Salon Inc",
    "wof:placetype":"venue"
},
  "geometry": {"coordinates":[-90.06343099999999,29.960978],"type":"Point"}
}