{
  "type": "Feature",
  "properties": {
    "addr:full":"1932 Joliet St New Orleans LA 70118",
    "addr:housenumber":"1932",
    "addr:postcode":"70118",
    "addr:street":"Joliet St",
    "iso:country":"US",
    "sg:address":"1932 Joliet St",
    "sg:city":"New Orleans",
    "sg:classifiers":[
        {
            "category":"Bars & Pubs",
            "type":"Food & Drink"
        }
    ],
    "sg:phone":"+1 504 865 7408",
    "sg:postcode":"70118",
    "sg:province":"LA",
    "sg:tags":[
        "lounge",
        "cocktail"
    ],
    "wof:name":"Blue Flame Lounge",
    "wof:placetype":"venue"
},
  "geometry": {"coordinates":[-90.12739500000001,29.955571],"type":"Point"}
}