{
  "type": "Feature",
  "properties": {
    "iso:country":"US",
    "sg:address":"1041 Walnut Ln",
    "sg:city":"Downsville",
    "sg:classifiers":[
        {
            "category":"Real Estate",
            "subcategory":"Surveying",
            "type":"Services"
        }
    ],
    "sg:phone":"+1 318 381 7182",
    "sg:postcode":"71234",
    "sg:province":"LA",
    "sg:tags":[
        "surveyor"
    ],
    "wof:name":"Ballard Forestry & Surveying",
    "wof:placetype":"venue"
},
  "geometry": {"coordinates":[-92.37716500000001,32.608503],"type":"Point"}
}