{
  "type": "Feature",
  "properties": {
    "addr:full":"1050 Convention St Baton Rouge LA 70802",
    "addr:housenumber":"1050",
    "addr:postcode":"70802",
    "addr:street":"Convention St",
    "iso:country":"US",
    "sg:address":"1050 Convention St",
    "sg:city":"Baton Rouge",
    "sg:classifiers":[
        {
            "category":"Health Services",
            "subcategory":"Hospital",
            "type":"Services"
        }
    ],
    "sg:phone":"+1 225 343 3827",
    "sg:postcode":"70802",
    "sg:province":"LA",
    "sg:tags":[
        "mental"
    ],
    "wof:name":"Maison Des Ami Boarding Care",
    "wof:placetype":"venue"
},
  "geometry": {"coordinates":[-91.179181,30.448452],"type":"Point"}
}