{
  "type": "Feature",
  "properties": {
    "addr:full":"2524 Common St Lake Charles LA 70601",
    "addr:housenumber":"2524",
    "addr:postcode":"70601",
    "addr:street":"Common St",
    "iso:country":"US",
    "sg:address":"2524 Common St",
    "sg:city":"Lake Charles",
    "sg:classifiers":[
        {
            "category":"Manufacturing",
            "subcategory":"Tools & Machinery",
            "type":"Manufacturing & Wholesale Goods"
        }
    ],
    "sg:phone":"+1 337 433 3641",
    "sg:postcode":"70601",
    "sg:province":"LA",
    "sg:tags":[
        "engine",
        "comb"
    ],
    "wof:name":"Auto Electric & Magneto Shop",
    "wof:placetype":"venue"
},
  "geometry": {"coordinates":[-93.21411000000001,30.206926],"type":"Point"}
}