{
  "type": "Feature",
  "properties": {
    "iso:country":"US",
    "sg:address":"602 Metairie Rd",
    "sg:city":"Metairie",
    "sg:classifiers":[
        {
            "category":"Manufacturing",
            "subcategory":"Printing",
            "type":"Manufacturing & Wholesale Goods"
        }
    ],
    "sg:phone":"+1 504 838 6111",
    "sg:postcode":"70005",
    "sg:province":"LA",
    "sg:tags":[
        "publisher"
    ],
    "wof:name":"Arthur Hardy Enterprises Inc",
    "wof:placetype":"venue"
},
  "geometry": {"coordinates":[-90.129707,29.98661],"type":"Point"}
}