{
  "type": "Feature",
  "properties": {
    "iso:country":"US",
    "sg:address":"4800 Chef Menteur Hwy",
    "sg:city":"New Orleans",
    "sg:classifiers":[
        {
            "category":"Restaurant",
            "type":"Food & Drink"
        }
    ],
    "sg:phone":"+1 504 944 8990",
    "sg:postcode":"70126",
    "sg:province":"LA",
    "sg:tags":[
        "chinese"
    ],
    "wof:name":"Min Moon",
    "wof:placetype":"venue"
},
  "geometry": {"coordinates":[-90.033533,30.005624],"type":"Point"}
}