{
  "type": "Feature",
  "properties": {
    "iso:country":"US",
    "sg:address":"601 W Lafayette St",
    "sg:city":"Winnfield",
    "sg:classifiers":[
        {
            "category":"Health Services",
            "subcategory":"Health Practitioner",
            "type":"Services"
        }
    ],
    "sg:phone":"+1 318 648 3058",
    "sg:postcode":"71483",
    "sg:province":"LA",
    "sg:tags":[
        "therapist",
        "physical"
    ],
    "wof:name":"Specialty Clinic",
    "wof:placetype":"venue"
},
  "geometry": {"coordinates":[-92.64637999999999,31.924982],"type":"Point"}
}