{
  "type": "Feature",
  "properties": {
    "iso:country":"US",
    "sg:address":"600 Grantham Ave",
    "sg:city":"West Monroe",
    "sg:classifiers":[
        {
            "category":"Home & Garden",
            "subcategory":"Hardware",
            "type":"Retail Goods"
        }
    ],
    "sg:phone":"+1 318 388 2539",
    "sg:postcode":"71292",
    "sg:province":"LA",
    "sg:tags":[
        "saw"
    ],
    "wof:name":"U S Blades",
    "wof:placetype":"venue"
},
  "geometry": {"coordinates":[-92.16882,32.497574],"type":"Point"}
}