{
  "type": "Feature",
  "properties": {
    "iso:country":"US",
    "sg:address":"2020 Highway 59",
    "sg:city":"Mandeville",
    "sg:classifiers":[
        {
            "category":"Restaurant",
            "type":"Food & Drink"
        }
    ],
    "sg:menulink":"http://www.allmenus.com/la/mandeville/31222-petunias-place/menu/",
    "sg:phone":"+1 985 674 3436",
    "sg:postcode":"70448",
    "sg:province":"LA",
    "sg:tags":[
        "american",
        "southern"
    ],
    "wof:name":"Petunia's Place",
    "wof:placetype":"venue"
},
  "geometry": {"coordinates":[-90.05103200000001,30.382214],"type":"Point"}
}