{
  "type": "Feature",
  "properties": {
    "iso:country":"US",
    "sg:address":"2458 W Congress St",
    "sg:city":"Lafayette",
    "sg:classifiers":[
        {
            "category":"Retail",
            "subcategory":"Laundry & Dry Cleaning",
            "type":"Services"
        }
    ],
    "sg:phone":"+1 337 232 3816",
    "sg:postcode":"70506",
    "sg:province":"LA",
    "sg:tags":[
        "cleaners"
    ],
    "wof:name":"Camellis Cleaners",
    "wof:placetype":"venue"
},
  "geometry": {"coordinates":[-92.050686,30.211906],"type":"Point"}
}