{
  "type": "Feature",
  "properties": {
    "addr:full":"13054 Quick Blvd Hammond LA 70401",
    "addr:housenumber":"13054",
    "addr:postcode":"70401",
    "addr:street":"Quick Blvd",
    "iso:country":"US",
    "sg:address":"13054 Quick Blvd",
    "sg:city":"Hammond",
    "sg:classifiers":[
        {
            "category":"Real Estate",
            "subcategory":"Real Estate Operator",
            "type":"Services"
        }
    ],
    "sg:phone":"+1 985 542 0500",
    "sg:postcode":"70401",
    "sg:province":"LA",
    "sg:tags":[
        "apartment"
    ],
    "wof:name":"Contempo Apartments",
    "wof:placetype":"venue"
},
  "geometry": {"coordinates":[-90.516216,30.524011],"type":"Point"}
}