{
  "type": "Feature",
  "properties": {
    "iso:country":"US",
    "sg:address":"892 Bayou Rd",
    "sg:city":"Thibodaux",
    "sg:classifiers":[
        {
            "category":"Shopping",
            "type":"Retail Goods"
        }
    ],
    "sg:phone":"+1 985 446 5706",
    "sg:postcode":"70301",
    "sg:province":"LA",
    "sg:tags":[
        "cosmetic",
        "perfume"
    ],
    "wof:name":"Merle Norman Cosmetics",
    "wof:placetype":"venue"
},
  "geometry": {"coordinates":[-90.82216099999999,29.798959],"type":"Point"}
}