{
  "type": "Feature",
  "properties": {
    "iso:country":"US",
    "sg:address":"4826 Belcher River Rd",
    "sg:city":"Belcher",
    "sg:classifiers":[
        {
            "category":"Place Of Worship",
            "subcategory":"Church",
            "type":"Public Place"
        },
        {
            "category":"Place Of Worship",
            "type":"Public Place"
        }
    ],
    "sg:phone":"+1 318 378 4733",
    "sg:postcode":"71004",
    "sg:province":"LA",
    "sg:tags":[
        "churches-baptist-general",
        "churches-interdenominational",
        "churches-baptist",
        "churches-various",
        "denomination"
    ],
    "wof:name":"New Bethel Baptist Church",
    "wof:placetype":"venue"
},
  "geometry": {"coordinates":[-93.82150799999999,32.760898],"type":"Point"}
}