{
  "type": "Feature",
  "properties": {
    "addr:full":"1290 Saint Maurice Ln Natchitoches LA 71457",
    "addr:housenumber":"1290",
    "addr:postcode":"71457",
    "addr:street":"Saint Maurice Ln",
    "iso:country":"US",
    "sg:address":"1290 Saint Maurice Ln",
    "sg:city":"Natchitoches",
    "sg:classifiers":[
        {
            "category":"Retail",
            "subcategory":"Auto Repair",
            "type":"Services"
        }
    ],
    "sg:phone":"+1 318 357 1073",
    "sg:postcode":"71457",
    "sg:province":"LA",
    "sg:tags":[
        "repairing",
        "automobile"
    ],
    "wof:name":"A & B Auto",
    "wof:placetype":"venue"
},
  "geometry": {"coordinates":[-93.056011,31.763871],"type":"Point"}
}