{
  "type": "Feature",
  "properties": {
    "addr:full":"9660 Natchez St Wisner LA 71378",
    "addr:housenumber":"9660",
    "addr:postcode":"71378",
    "addr:street":"Natchez St",
    "iso:country":"US",
    "sg:address":"9660 Natchez St",
    "sg:city":"Wisner",
    "sg:classifiers":[
        {
            "category":"Food & Beverages",
            "subcategory":"Groceries & Convenience Stores",
            "type":"Retail Goods"
        }
    ],
    "sg:phone":"+1 318 724 7627",
    "sg:postcode":"71378",
    "sg:province":"LA",
    "wof:name":"Cypress Market",
    "wof:placetype":"venue"
},
  "geometry": {"coordinates":[-91.65516599999999,31.975818],"type":"Point"}
}