{
  "type": "Feature",
  "properties": {
    "addr:full":"9768 E Main St Houma LA 70363",
    "addr:housenumber":"9768",
    "addr:postcode":"70363",
    "addr:street":"E Main St",
    "iso:country":"US",
    "sg:address":"9768 E Main St",
    "sg:city":"Houma",
    "sg:classifiers":[
        {
            "category":"Manufacturing",
            "subcategory":"Tools & Machinery",
            "type":"Manufacturing & Wholesale Goods"
        }
    ],
    "sg:phone":"+1 985 851 2020",
    "sg:postcode":"70363",
    "sg:province":"LA",
    "sg:tags":[
        "machine",
        "shop"
    ],
    "wof:name":"Preferred Industries Inc",
    "wof:placetype":"venue"
},
  "geometry": {"coordinates":[-90.673035,29.588997],"type":"Point"}
}