{
  "type": "Feature",
  "properties": {
    "addr:full":"150 Staring Ln Baton Rouge LA 70810",
    "addr:housenumber":"150",
    "addr:postcode":"70810",
    "addr:street":"Staring Ln",
    "iso:country":"US",
    "sg:address":"150 Staring Ln",
    "sg:city":"Baton Rouge",
    "sg:classifiers":[
        {
            "category":"Insurance",
            "subcategory":"Insurance Agent",
            "type":"Services"
        }
    ],
    "sg:phone":"+1 225 753 6658",
    "sg:postcode":"70810",
    "sg:province":"LA",
    "wof:name":"Federated Insurance Co",
    "wof:placetype":"venue"
},
  "geometry": {"coordinates":[-91.122535,30.369486],"type":"Point"}
}