{
  "type": "Feature",
  "properties": {
    "iso:country":"US",
    "sg:address":"1723 Manhattan Blvd Ste G",
    "sg:city":"Harvey",
    "sg:classifiers":[
        {
            "category":"Shopping",
            "subcategory":"Used Merchandise",
            "type":"Retail Goods"
        }
    ],
    "sg:phone":"+1 504 361 7603",
    "sg:postcode":"70058",
    "sg:province":"LA",
    "sg:tags":[
        "vintage",
        "consignment"
    ],
    "wof:name":"Rue 21 #602",
    "wof:placetype":"venue"
},
  "geometry": {"coordinates":[-90.056803,29.889433],"type":"Point"}
}