{
  "type": "Feature",
  "properties": {
    "iso:country":"US",
    "sg:address":"3901 Houma Blvd",
    "sg:city":"Metairie",
    "sg:classifiers":[
        {
            "category":"Health Services",
            "subcategory":"Doctor",
            "type":"Services"
        }
    ],
    "sg:phone":"+1 504 885 4833",
    "sg:postcode":"70006",
    "sg:province":"LA",
    "sg:tags":[
        "physician",
        "surgeon"
    ],
    "wof:name":"Guzzetta & De Corte",
    "wof:placetype":"venue"
},
  "geometry": {"coordinates":[-90.180723,30.011035],"type":"Point"}
}