{
  "type": "Feature",
  "properties": {
    "iso:country":"US",
    "sg:address":"501 Klock",
    "sg:city":"Cheneyville",
    "sg:classifiers":[
        {
            "category":"Insurance",
            "subcategory":"Insurance Agent",
            "type":"Services"
        }
    ],
    "sg:phone":"+1 318 279 2206",
    "sg:postcode":"71325",
    "sg:province":"LA",
    "sg:tags":[
        "processing"
    ],
    "wof:name":"FTR Medical Billing",
    "wof:placetype":"venue"
},
  "geometry": {"coordinates":[-92.288054,31.013804],"type":"Point"}
}