{
  "type": "Feature",
  "properties": {
    "addr:full":"12665 Lilly Ln Deville LA 71328",
    "addr:housenumber":"12665",
    "addr:postcode":"71328",
    "addr:street":"Lilly Ln Deville",
    "iso:country":"US",
    "sg:address":"12665 Lilly Ln",
    "sg:city":"Deville",
    "sg:classifiers":[
        {
            "category":"Professional",
            "subcategory":"Detective & Security Services",
            "type":"Services"
        }
    ],
    "sg:phone":"+1 318 466 1091",
    "sg:postcode":"71328",
    "sg:province":"LA",
    "sg:tags":[
        "system"
    ],
    "wof:name":"Progressive Security",
    "wof:placetype":"venue"
},
  "geometry": {"coordinates":[-92.235765,31.396469],"type":"Point"}
}