{
  "type": "Feature",
  "properties": {
    "iso:country":"US",
    "sg:address":"6515 Greenwell Springs Rd",
    "sg:city":"Baton Rouge",
    "sg:classifiers":[
        {
            "category":"Professional",
            "subcategory":"Management & Consulting",
            "type":"Services"
        }
    ],
    "sg:phone":"+1 225 383 2240",
    "sg:postcode":"70806",
    "sg:province":"LA",
    "sg:tags":[
        "accident",
        "reconstruction"
    ],
    "wof:name":"National Collision Tech",
    "wof:placetype":"venue"
},
  "geometry": {"coordinates":[-91.125592,30.470163],"type":"Point"}
}