{
  "type": "Feature",
  "properties": {
    "iso:country":"US",
    "sg:address":"18031 Beechwood Rd",
    "sg:city":"Prairieville",
    "sg:classifiers":[
        {
            "category":"Building & Trades",
            "subcategory":"Pest Control",
            "type":"Services"
        }
    ],
    "sg:phone":"+1 225 622 5237",
    "sg:postcode":"70769",
    "sg:province":"LA",
    "wof:name":"Ted's Exterminating Co",
    "wof:placetype":"venue"
},
  "geometry": {"coordinates":[-90.879597,30.334597],"type":"Point"}
}