{
  "type": "Feature",
  "properties": {
    "addr:full":"4217 E Judge Perez Dr Meraux LA 70075",
    "addr:housenumber":"4217",
    "addr:postcode":"70075",
    "addr:street":"E Judge Perez Dr Meraux",
    "iso:country":"US",
    "sg:address":"4217 E Judge Perez Dr",
    "sg:city":"Meraux",
    "sg:classifiers":[
        {
            "category":"Professional",
            "subcategory":"Accounting & Tax Preparation",
            "type":"Services"
        }
    ],
    "sg:phone":"+1 504 278 5556",
    "sg:postcode":"70075",
    "sg:province":"LA",
    "sg:tags":[
        "return",
        "filing"
    ],
    "wof:name":"St Bernard Speedie Income",
    "wof:placetype":"venue"
},
  "geometry": {"coordinates":[-89.921532,29.93483],"type":"Point"}
}