{
  "type": "Feature",
  "properties": {
    "iso:country":"US",
    "sg:address":"57272 Pace Rd",
    "sg:city":"Slidell",
    "sg:classifiers":[
        {
            "category":"Building & Trades",
            "subcategory":"Landscaping Services",
            "type":"Services"
        }
    ],
    "sg:phone":"+1 985 649 3684",
    "sg:postcode":"70461",
    "sg:province":"LA",
    "wof:name":"Hortons Ldscpg & Lawn Maint",
    "wof:placetype":"venue"
},
  "geometry": {"coordinates":[-89.73035900000001,30.261144],"type":"Point"}
}