{
  "type": "Feature",
  "properties": {
    "addr:full":"9970 Lake Forest Blvd New Orleans LA 70127",
    "addr:housenumber":"9970",
    "addr:postcode":"70127",
    "addr:street":"Lake Forest Blvd",
    "iso:country":"US",
    "sg:address":"9970 Lake Forest Blvd",
    "sg:city":"New Orleans",
    "sg:classifiers":[
        {
            "category":"Health Services",
            "subcategory":"Podiatrist",
            "type":"Services"
        }
    ],
    "sg:phone":"+1 504 246 8907",
    "sg:postcode":"70127",
    "sg:province":"LA",
    "wof:name":"Louisiana Medical Foot Ctr",
    "wof:placetype":"venue"
},
  "geometry": {"coordinates":[-89.976765,30.030665],"type":"Point"}
}