{
  "type": "Feature",
  "properties": {
    "iso:country":"US",
    "sg:address":"8160 Old Gentilly Rd",
    "sg:city":"New Orleans",
    "sg:classifiers":[
        {
            "category":"Retail",
            "subcategory":"Auto Repair",
            "type":"Services"
        }
    ],
    "sg:phone":"+1 504 245 1123",
    "sg:postcode":"70126",
    "sg:province":"LA",
    "sg:tags":[
        "body",
        "shop"
    ],
    "wof:name":"Coleman's Auto Body Shop",
    "wof:placetype":"venue"
},
  "geometry": {"coordinates":[-89.98809799999999,30.0123],"type":"Point"}
}