{
  "type": "Feature",
  "properties": {
    "addr:full":"721 Bolton Ave Alexandria LA 71301",
    "addr:housenumber":"721",
    "addr:postcode":"71301",
    "addr:street":"Bolton Ave",
    "iso:country":"US",
    "sg:address":"721 Bolton Ave",
    "sg:city":"Alexandria",
    "sg:classifiers":[
        {
            "category":"Shopping",
            "subcategory":"Pharmacy",
            "type":"Retail Goods"
        }
    ],
    "sg:phone":"+1 318 473 0546",
    "sg:postcode":"71301",
    "sg:province":"LA",
    "wof:name":"CVS Pharmacy",
    "wof:placetype":"venue"
},
  "geometry": {"coordinates":[-92.454562,31.304987],"type":"Point"}
}