{
  "type": "Feature",
  "properties": {
    "addr:full":"4730 US Hwy 84 Mansfield LA 71052",
    "addr:housenumber":"4730",
    "addr:postcode":"71052",
    "addr:street":"Us Hwy 84",
    "iso:country":"US",
    "sg:address":"4730 US Hwy 84",
    "sg:city":"Mansfield",
    "sg:classifiers":[
        {
            "category":"Government",
            "subcategory":"Office",
            "type":"Public Place"
        }
    ],
    "sg:phone":"+1 318 872 4578",
    "sg:postcode":"71052",
    "sg:province":"LA",
    "sg:tags":[
        "state",
        "program"
    ],
    "wof:name":"Transportation Dept",
    "wof:placetype":"venue"
},
  "geometry": {"coordinates":[-93.65688400000001,32.049221],"type":"Point"}
}