{
  "type": "Feature",
  "properties": {
    "iso:country":"US",
    "sg:address":"122 E 5th St",
    "sg:city":"Crowley",
    "sg:classifiers":[
        {
            "category":"Professional",
            "subcategory":"Accounting & Tax Preparation",
            "type":"Services"
        }
    ],
    "sg:phone":"+1 337 783 0650",
    "sg:postcode":"70526",
    "sg:province":"LA",
    "wof:name":"Dawn Latiolais",
    "wof:placetype":"venue"
},
  "geometry": {"coordinates":[-92.37307699999999,30.21351],"type":"Point"}
}