{
  "type": "Feature",
  "properties": {
    "addr:full":"400 E Texas St Bossier City LA 71111",
    "addr:housenumber":"400",
    "addr:postcode":"71111",
    "addr:street":"E Texas St",
    "iso:country":"US",
    "sg:address":"400 E Texas St",
    "sg:city":"Bossier City",
    "sg:classifiers":[
        {
            "category":"Autos & Motor Vehicles",
            "subcategory":"Auto Supplies",
            "type":"Retail Goods"
        }
    ],
    "sg:phone":"+1 318 742 5871",
    "sg:postcode":"71111",
    "sg:province":"LA",
    "sg:tags":[
        "tire"
    ],
    "wof:name":"Discount Tire Co",
    "wof:placetype":"venue"
},
  "geometry": {"coordinates":[-93.734645,32.521175],"type":"Point"}
}