{
  "type": "Feature",
  "properties": {
    "iso:country":"US",
    "sg:address":"143 Booner Miller Rd",
    "sg:city":"Deville",
    "sg:classifiers":[
        {
            "category":"Organizations",
            "subcategory":"Religious Organization",
            "type":"Services"
        }
    ],
    "sg:phone":"+1 318 443 5118",
    "sg:postcode":"71328",
    "sg:province":"LA",
    "sg:tags":[
        "church"
    ],
    "wof:name":"St Francis & Anne's Church",
    "wof:placetype":"venue"
},
  "geometry": {"coordinates":[-92.31953300000001,31.285983],"type":"Point"}
}