{
  "type": "Feature",
  "properties": {
    "iso:country":"US",
    "sg:address":"8924 Jewella Ave",
    "sg:city":"Shreveport",
    "sg:classifiers":[
        {
            "category":"Shopping",
            "subcategory":"Books",
            "type":"Retail Goods"
        }
    ],
    "sg:phone":"+1 318 686 0440",
    "sg:postcode":"71118",
    "sg:province":"LA",
    "sg:tags":[
        "dealer"
    ],
    "wof:name":"Reruns Are Fun",
    "wof:placetype":"venue"
},
  "geometry": {"coordinates":[-93.797539,32.415323],"type":"Point"}
}