{
  "type": "Feature",
  "properties": {
    "addr:full":"200 Burt Blvd Benton LA 71006",
    "addr:housenumber":"200",
    "addr:postcode":"71006",
    "addr:street":"Burt Blvd",
    "iso:country":"US",
    "sg:address":"200 Burt Blvd",
    "sg:city":"Benton",
    "sg:classifiers":[
        {
            "category":"Government",
            "subcategory":"Office",
            "type":"Public Place"
        }
    ],
    "sg:phone":"+1 318 965 2108",
    "sg:postcode":"71006",
    "sg:province":"LA",
    "sg:tags":[
        "federal"
    ],
    "wof:name":"Natural Resources Conservation",
    "wof:placetype":"venue"
},
  "geometry": {"coordinates":[-93.744411,32.679266],"type":"Point"}
}