{
  "type": "Feature",
  "properties": {
    "iso:country":"US",
    "sg:address":"6025 Section Rd",
    "sg:city":"Port Allen",
    "sg:classifiers":[
        {
            "category":"Organizations",
            "subcategory":"Religious Organization",
            "type":"Services"
        }
    ],
    "sg:phone":"+1 225 627 4937",
    "sg:postcode":"70767",
    "sg:province":"LA",
    "sg:tags":[
        "church"
    ],
    "wof:name":"St Marks Baptist Church",
    "wof:placetype":"venue"
},
  "geometry": {"coordinates":[-91.298665,30.535007],"type":"Point"}
}