{
  "type": "Feature",
  "properties": {
    "iso:country":"US",
    "sg:address":"31505 Highway 1",
    "sg:city":"White Castle",
    "sg:classifiers":[
        {
            "category":"Education",
            "subcategory":"School",
            "type":"Public Place"
        }
    ],
    "sg:phone":"+1 225 545 3465",
    "sg:postcode":"70788",
    "sg:province":"LA",
    "sg:tags":[
        "high",
        "middle",
        "elementary"
    ],
    "wof:name":"Dorseyville Middle School",
    "wof:placetype":"venue"
},
  "geometry": {"coordinates":[-91.16439800000001,30.1772],"type":"Point"}
}