{
  "type": "Feature",
  "properties": {
    "iso:country":"US",
    "sg:address":"2160 Grand Caillou Rd",
    "sg:city":"Houma",
    "sg:classifiers":[
        {
            "category":"Wholesale",
            "subcategory":"Machinery & Supplies",
            "type":"Manufacturing & Wholesale Goods"
        }
    ],
    "sg:phone":"+1 985 868 8600",
    "sg:postcode":"70363",
    "sg:province":"LA",
    "sg:tags":[
        "tubing",
        "hose",
        "plastic"
    ],
    "wof:name":"Taylor's Industrial Spec Inc",
    "wof:placetype":"venue"
},
  "geometry": {"coordinates":[-90.679455,29.550314],"type":"Point"}
}