{
  "type": "Feature",
  "properties": {
    "iso:country":"US",
    "sg:address":"3105 Kirkman St",
    "sg:city":"Lake Charles",
    "sg:classifiers":[
        {
            "category":"Building & Trades",
            "subcategory":"Construction",
            "type":"Services"
        }
    ],
    "sg:phone":"+1 337 478 7391",
    "sg:postcode":"70601",
    "sg:province":"LA",
    "sg:tags":[
        "roofing",
        "contractor"
    ],
    "wof:name":"Hawk's Roofing Co",
    "wof:placetype":"venue"
},
  "geometry": {"coordinates":[-93.209692,30.199836],"type":"Point"}
}