{
  "type": "Feature",
  "properties": {
    "iso:country":"US",
    "sg:address":"1001 E Gloria Switch Rd",
    "sg:city":"Lafayette",
    "sg:classifiers":[
        {
            "category":"Shopping",
            "subcategory":"Crafts & Fabrics",
            "type":"Retail Goods"
        }
    ],
    "sg:phone":"+1 337 232 7847",
    "sg:postcode":"70507",
    "sg:province":"LA",
    "sg:tags":[
        "store"
    ],
    "sg:website":"www.quiltknit.com",
    "wof:name":"Ginger's Needlework",
    "wof:placetype":"venue"
},
  "geometry": {"coordinates":[-92.00460099999999,30.2948],"type":"Point"}
}