{
  "type": "Feature",
  "properties": {
    "iso:country":"US",
    "sg:address":"4448 Transcontinental Dr",
    "sg:city":"Metairie",
    "sg:classifiers":[
        {
            "category":"Shopping",
            "subcategory":"Jewelry",
            "type":"Retail Goods"
        }
    ],
    "sg:phone":"+1 504 889 2333",
    "sg:postcode":"70006",
    "sg:province":"LA",
    "sg:tags":[
        "jeweler"
    ],
    "wof:name":"Metairie Jewelers",
    "wof:placetype":"venue"
},
  "geometry": {"coordinates":[-90.19906,30.018138],"type":"Point"}
}