{
  "type": "Feature",
  "properties": {
    "addr:full":"2109 17th St Kenner LA 70062",
    "addr:housenumber":"2109",
    "addr:postcode":"70062",
    "addr:street":"17Th St",
    "iso:country":"US",
    "sg:address":"2109 17th St",
    "sg:city":"Kenner",
    "sg:classifiers":[
        {
            "category":"Organizations",
            "subcategory":"Religious Organization",
            "type":"Services"
        }
    ],
    "sg:phone":"+1 504 469 4535",
    "sg:postcode":"70062",
    "sg:province":"LA",
    "sg:tags":[
        "church"
    ],
    "wof:name":"St John's Episcopal Church",
    "wof:placetype":"venue"
},
  "geometry": {"coordinates":[-90.241719,29.988283],"type":"Point"}
}