{
  "type": "Feature",
  "properties": {
    "iso:country":"US",
    "sg:address":"5810 Main St",
    "sg:city":"Zachary",
    "sg:classifiers":[
        {
            "category":"Government",
            "subcategory":"Office",
            "type":"Public Place"
        }
    ],
    "sg:phone":"+1 225 658 5784",
    "sg:postcode":"70791",
    "sg:province":"LA",
    "sg:tags":[
        "armed",
        "force",
        "recruiting"
    ],
    "wof:name":"US Army Recruiting",
    "wof:placetype":"venue"
},
  "geometry": {"coordinates":[-91.141139,30.649187],"type":"Point"}
}