{
  "type": "Feature",
  "properties": {
    "addr:full":"215 Industrial Pkwy West Monroe LA 71291",
    "addr:housenumber":"215",
    "addr:postcode":"71291",
    "addr:street":"Industrial Pkwy West",
    "iso:country":"US",
    "sg:address":"215 Industrial Pkwy",
    "sg:city":"West Monroe",
    "sg:classifiers":[
        {
            "category":"Building & Trades",
            "subcategory":"Construction",
            "type":"Services"
        }
    ],
    "sg:phone":"+1 318 397 9909",
    "sg:postcode":"71291",
    "sg:province":"LA",
    "sg:tags":[
        "general",
        "contractor"
    ],
    "sg:website":"www.amethystconstruction.com",
    "wof:name":"Amethyst Construction",
    "wof:placetype":"venue"
},
  "geometry": {"coordinates":[-92.276358,32.511751],"type":"Point"}
}