{
  "type": "Feature",
  "properties": {
    "iso:country":"US",
    "sg:address":"12538 North Rd",
    "sg:city":"Erath",
    "sg:classifiers":[
        {
            "category":"Autos & Motor Vehicles",
            "subcategory":"Auto Supplies",
            "type":"Retail Goods"
        }
    ],
    "sg:phone":"+1 337 937 9920",
    "sg:postcode":"70533",
    "sg:province":"LA",
    "sg:tags":[
        "filter"
    ],
    "wof:name":"Bayou State Marine & Ind Supl",
    "wof:placetype":"venue"
},
  "geometry": {"coordinates":[-92.048265,29.974577],"type":"Point"}
}