{
  "type": "Feature",
  "properties": {
    "addr:full":"2531 Creswell Ave Shreveport LA 71104",
    "addr:housenumber":"2531",
    "addr:postcode":"71104",
    "addr:street":"Creswell Ave",
    "iso:country":"US",
    "sg:address":"2531 Creswell Ave",
    "sg:city":"Shreveport",
    "sg:classifiers":[
        {
            "category":"Social Services",
            "subcategory":"Adult Care",
            "type":"Services"
        }
    ],
    "sg:phone":"+1 318 424 6698",
    "sg:postcode":"71104",
    "sg:province":"LA",
    "sg:tags":[
        "home",
        "group"
    ],
    "wof:name":"United Veterans Beacon House",
    "wof:placetype":"venue"
},
  "geometry": {"coordinates":[-93.74165499999999,32.486905],"type":"Point"}
}