{
  "type": "Feature",
  "properties": {
    "iso:country":"US",
    "sg:address":"5921 Dover Pl",
    "sg:city":"New Orleans",
    "sg:classifiers":[
        {
            "category":"Real Estate",
            "subcategory":"Real Estate Agent",
            "type":"Services"
        }
    ],
    "sg:phone":"+1 504 433 9315",
    "sg:postcode":"70131",
    "sg:province":"LA",
    "sg:tags":[
        "rental",
        "sales"
    ],
    "wof:name":"Fav-R Investments LLC",
    "wof:placetype":"venue"
},
  "geometry": {"coordinates":[-89.99237100000001,29.920501],"type":"Point"}
}