{
  "type": "Feature",
  "properties": {
    "addr:full":"5443 Jones Creek Rd Baton Rouge LA 70817",
    "addr:housenumber":"5443",
    "addr:postcode":"70817",
    "addr:street":"Jones Creek Rd",
    "iso:country":"US",
    "sg:address":"5443 Jones Creek Rd",
    "sg:city":"Baton Rouge",
    "sg:classifiers":[
        {
            "category":"Restaurant",
            "type":"Food & Drink"
        }
    ],
    "sg:menulink":"http://www.allmenus.com/la/baton-rouge/80269-dominos-pizza/menu/",
    "sg:phone":"+1 225 751 8193",
    "sg:postcode":"70817",
    "sg:province":"LA",
    "sg:tags":[
        "american",
        "wing",
        "pizza"
    ],
    "wof:name":"Domino's Pizza",
    "wof:placetype":"venue"
},
  "geometry": {"coordinates":[-91.015204,30.404633],"type":"Point"}
}