{
  "type": "Feature",
  "properties": {
    "iso:country":"US",
    "sg:address":"3406 College St",
    "sg:city":"Jackson",
    "sg:classifiers":[
        {
            "category":"Social Services",
            "type":"Services"
        }
    ],
    "sg:phone":"+1 225 634 9931",
    "sg:postcode":"70748",
    "sg:province":"LA",
    "sg:tags":[
        "info",
        "program",
        "referral"
    ],
    "wof:name":"Families In Need Of Svc",
    "wof:placetype":"venue"
},
  "geometry": {"coordinates":[-91.213414,30.840246],"type":"Point"}
}