{
  "type": "Feature",
  "properties": {
    "addr:full":"242 Keyser Ave Natchitoches LA 71457",
    "addr:housenumber":"242",
    "addr:postcode":"71457",
    "addr:street":"Keyser Ave",
    "iso:country":"US",
    "sg:address":"242 Keyser Ave",
    "sg:city":"Natchitoches",
    "sg:classifiers":[
        {
            "category":"Building & Trades",
            "subcategory":"Construction",
            "type":"Services"
        }
    ],
    "sg:phone":"+1 318 357 8709",
    "sg:postcode":"71457",
    "sg:province":"LA",
    "sg:tags":[
        "concrete",
        "contractor"
    ],
    "wof:name":"Crocket Paving",
    "wof:placetype":"venue"
},
  "geometry": {"coordinates":[-93.082599,31.75378],"type":"Point"}
}