{
  "type": "Feature",
  "properties": {
    "iso:country":"US",
    "sg:address":"2812 Benton Rd",
    "sg:city":"Bossier City",
    "sg:classifiers":[
        {
            "category":"Shopping",
            "subcategory":"Bicycles & Sporting Goods",
            "type":"Retail Goods"
        }
    ],
    "sg:phone":"+1 318 746 3833",
    "sg:postcode":"71111",
    "sg:province":"LA",
    "sg:tags":[
        "equipment",
        "golf",
        "supply"
    ],
    "wof:name":"International Golf Discount",
    "wof:placetype":"venue"
},
  "geometry": {"coordinates":[-93.727166,32.560298],"type":"Point"}
}