{
  "type": "Feature",
  "properties": {
    "iso:country":"US",
    "sg:address":"810 N Burnside Ave",
    "sg:city":"Gonzales",
    "sg:classifiers":[
        {
            "category":"Health Services",
            "subcategory":"Podiatrist",
            "type":"Services"
        }
    ],
    "sg:phone":"+1 225 647 6654",
    "sg:postcode":"70737",
    "sg:province":"LA",
    "wof:name":"Alternative Foot Clinic",
    "wof:placetype":"venue"
},
  "geometry": {"coordinates":[-90.920676,30.239014],"type":"Point"}
}