{
  "type": "Feature",
  "properties": {
    "iso:country":"US",
    "sg:address":"1108 Stubbs Ave",
    "sg:city":"Monroe",
    "sg:classifiers":[
        {
            "category":"Health Services",
            "subcategory":"Doctor",
            "type":"Services"
        }
    ],
    "sg:phone":"+1 318 323 8824",
    "sg:postcode":"71201",
    "sg:province":"LA",
    "sg:tags":[
        "physician",
        "surgeon"
    ],
    "wof:name":"Gary Stanley MD",
    "wof:placetype":"venue"
},
  "geometry": {"coordinates":[-92.11436,32.516289],"type":"Point"}
}