{
  "type": "Feature",
  "properties": {
    "iso:country":"US",
    "sg:address":"4227 Erato St",
    "sg:city":"New Orleans",
    "sg:classifiers":[
        {
            "category":"Organizations",
            "subcategory":"Religious Organization",
            "type":"Services"
        }
    ],
    "sg:phone":"+1 504 822 1397",
    "sg:postcode":"70125",
    "sg:province":"LA",
    "wof:name":"First Grt St James Bapt Chrch",
    "wof:placetype":"venue"
},
  "geometry": {"coordinates":[-90.101465,29.955744],"type":"Point"}
}