{
  "type": "Feature",
  "properties": {
    "addr:full":"5212 Masonic Dr Alexandria LA 71301",
    "addr:housenumber":"5212",
    "addr:postcode":"71301",
    "addr:street":"Masonic Dr",
    "iso:country":"US",
    "sg:address":"5212 Masonic Dr",
    "sg:city":"Alexandria",
    "sg:classifiers":[
        {
            "category":"Restaurant",
            "type":"Food & Drink"
        }
    ],
    "sg:phone":"+1 318 445 2211",
    "sg:postcode":"71301",
    "sg:province":"LA",
    "sg:tags":[
        "parlor",
        "ice",
        "cream"
    ],
    "wof:name":"Dippin' Dots",
    "wof:placetype":"venue"
},
  "geometry": {"coordinates":[-92.471225,31.267764],"type":"Point"}
}