{
  "type": "Feature",
  "properties": {
    "iso:country":"US",
    "sg:address":"1772 Monroe St",
    "sg:city":"Alexandria",
    "sg:classifiers":[
        {
            "category":"Real Estate",
            "subcategory":"Real Estate Operator",
            "type":"Services"
        }
    ],
    "sg:phone":"+1 318 445 0054",
    "sg:postcode":"71301",
    "sg:province":"LA",
    "sg:tags":[
        "management",
        "property",
        "oil"
    ],
    "wof:name":"Mc Ginty-Durham Inc",
    "wof:placetype":"venue"
},
  "geometry": {"coordinates":[-92.45940899999999,31.308222],"type":"Point"}
}