{
  "type": "Feature",
  "properties": {
    "iso:country":"US",
    "sg:address":"3401 Ryan St",
    "sg:city":"Lake Charles",
    "sg:classifiers":[
        {
            "category":"Professional",
            "subcategory":"Lawyer & Legal Services",
            "type":"Services"
        }
    ],
    "sg:phone":"+1 337 477 4655",
    "sg:postcode":"70605",
    "sg:province":"LA",
    "sg:tags":[
        "attorney"
    ],
    "wof:name":"Joseph A Delafield Law Office",
    "wof:placetype":"venue"
},
  "geometry": {"coordinates":[-93.21862400000001,30.19464],"type":"Point"}
}