{
  "type": "Feature",
  "properties": {
    "iso:country":"US",
    "sg:address":"1705 Simmons St",
    "sg:city":"Alexandria",
    "sg:classifiers":[
        {
            "category":"Professional",
            "subcategory":"Advertising",
            "type":"Services"
        }
    ],
    "sg:phone":"+1 318 443 8818",
    "sg:postcode":"71301",
    "sg:province":"LA",
    "wof:name":"L K Graphics",
    "wof:placetype":"venue"
},
  "geometry": {"coordinates":[-92.46974299999999,31.280209],"type":"Point"}
}