{
  "type": "Feature",
  "properties": {
    "iso:country":"US",
    "sg:address":"100 Live Oak Dr",
    "sg:city":"Slidell",
    "sg:classifiers":[
        {
            "category":"Professional",
            "subcategory":"Business Services",
            "type":"Services"
        }
    ],
    "sg:phone":"+1 985 649 1569",
    "sg:postcode":"70461",
    "sg:province":"LA",
    "sg:tags":[
        "special",
        "investigator"
    ],
    "wof:name":"Dixie L Boyles",
    "wof:placetype":"venue"
},
  "geometry": {"coordinates":[-89.695723,30.258577],"type":"Point"}
}