{
  "type": "Feature",
  "properties": {
    "iso:country":"US",
    "sg:address":"1036 W Airline Hwy",
    "sg:city":"La Place",
    "sg:classifiers":[
        {
            "category":"Shopping",
            "subcategory":"Clothing, Apparel, & Fashions",
            "type":"Retail Goods"
        }
    ],
    "sg:phone":"+1 985 652 3193",
    "sg:postcode":"70068",
    "sg:province":"LA",
    "sg:tags":[
        "uniform"
    ],
    "wof:name":"School House Uniform Inc",
    "wof:placetype":"venue"
},
  "geometry": {"coordinates":[-90.487831,30.070566],"type":"Point"}
}