{
  "type": "Feature",
  "properties": {
    "iso:country":"US",
    "sg:address":"433 E Vermilion St",
    "sg:city":"Lafayette",
    "sg:classifiers":[
        {
            "category":"Shopping",
            "subcategory":"Computers & Home Electronics",
            "type":"Retail Goods"
        }
    ],
    "sg:phone":"+1 337 237 6669",
    "sg:postcode":"70501",
    "sg:province":"LA",
    "sg:tags":[
        "equipment",
        "satellite",
        "system"
    ],
    "wof:name":"Dishes Satellite Systems",
    "wof:placetype":"venue"
},
  "geometry": {"coordinates":[-92.01615200000001,30.223947],"type":"Point"}
}