{
  "type": "Feature",
  "properties": {
    "iso:country":"US",
    "sg:address":"406 Main St",
    "sg:city":"Bernice",
    "sg:classifiers":[
        {
            "category":"Health Services",
            "subcategory":"Clinic",
            "type":"Services"
        }
    ],
    "sg:phone":"+1 318 285 9347",
    "sg:postcode":"71232",
    "sg:province":"LA",
    "sg:tags":[
        "home"
    ],
    "wof:name":"Professional Home Health",
    "wof:placetype":"venue"
},
  "geometry": {"coordinates":[-91.492519,32.46428],"type":"Point"}
}