{
  "type": "Feature",
  "properties": {
    "iso:country":"US",
    "sg:address":"1325 N Hwy 190",
    "sg:city":"Covington",
    "sg:classifiers":[
        {
            "category":"Autos & Motor Vehicles",
            "subcategory":"Automobile Sales",
            "type":"Retail Goods"
        }
    ],
    "sg:phone":"+1 985 871 0031",
    "sg:postcode":"70433",
    "sg:province":"LA",
    "sg:tags":[
        "car",
        "dealer"
    ],
    "wof:name":"Mandeville Auto Sales",
    "wof:placetype":"venue"
},
  "geometry": {"coordinates":[-90.082409,30.45141],"type":"Point"}
}