{
  "type": "Feature",
  "properties": {
    "addr:full":"400 Lovette St Jeanerette LA 70544",
    "addr:housenumber":"400",
    "addr:postcode":"70544",
    "addr:street":"Lovette St",
    "iso:country":"US",
    "sg:address":"400 Lovette St",
    "sg:city":"Jeanerette",
    "sg:classifiers":[
        {
            "category":"Organizations",
            "subcategory":"Non-profit Organization",
            "type":"Services"
        }
    ],
    "sg:phone":"+1 337 276 9275",
    "sg:postcode":"70544",
    "sg:province":"LA",
    "wof:name":"Fantasy Land Nursery",
    "wof:placetype":"venue"
},
  "geometry": {"coordinates":[-91.67918899999999,29.926185],"type":"Point"}
}