{
  "type": "Feature",
  "properties": {
    "iso:country":"US",
    "sg:address":"402 Hill Church Rd",
    "sg:city":"Oak Grove",
    "sg:classifiers":[
        {
            "category":"Organizations",
            "subcategory":"Religious Organization",
            "type":"Services"
        }
    ],
    "sg:phone":"+1 318 428 2293",
    "sg:postcode":"71263",
    "sg:province":"LA",
    "sg:tags":[
        "church"
    ],
    "wof:name":"Hill Baptist Parsonage",
    "wof:placetype":"venue"
},
  "geometry": {"coordinates":[-91.366777,32.951208],"type":"Point"}
}