{
  "type": "Feature",
  "properties": {
    "addr:full":"11553 Cedar Park Ave Baton Rouge LA 70809",
    "addr:housenumber":"11553",
    "addr:postcode":"70809",
    "addr:street":"Cedar Park Ave",
    "iso:country":"US",
    "sg:address":"11553 Cedar Park Ave",
    "sg:city":"Baton Rouge",
    "sg:classifiers":[
        {
            "category":"Building & Trades",
            "subcategory":"Equipment Rental",
            "type":"Services"
        }
    ],
    "sg:phone":"+1 225 753 3937",
    "sg:postcode":"70809",
    "sg:province":"LA",
    "sg:tags":[
        "field"
    ],
    "wof:name":"Hallmark Engineering",
    "wof:placetype":"venue"
},
  "geometry": {"coordinates":[-91.053928,30.38936],"type":"Point"}
}