{
  "type": "Feature",
  "properties": {
    "addr:full":"3505 Ryan St Lake Charles LA 70605",
    "addr:housenumber":"3505",
    "addr:postcode":"70605",
    "addr:street":"Ryan St",
    "iso:country":"US",
    "sg:address":"3505 Ryan St",
    "sg:city":"Lake Charles",
    "sg:classifiers":[
        {
            "category":"Restaurant",
            "type":"Food & Drink"
        }
    ],
    "sg:phone":"+1 337 478 4258",
    "sg:postcode":"70605",
    "sg:province":"LA",
    "wof:name":"Church's Chicken",
    "wof:placetype":"venue"
},
  "geometry": {"coordinates":[-93.218542,30.193213],"type":"Point"}
}