{
  "type": "Feature",
  "properties": {
    "iso:country":"US",
    "sg:address":"1401 Main St",
    "sg:city":"Jeanerette",
    "sg:classifiers":[
        {
            "category":"Insurance",
            "subcategory":"Insurance Agent",
            "type":"Services"
        }
    ],
    "sg:phone":"+1 337 276 3683",
    "sg:postcode":"70544",
    "sg:province":"LA",
    "sg:website":"www.barbararogersrealtor.com",
    "wof:name":"Barbara Rogers Insurance",
    "wof:placetype":"venue"
},
  "geometry": {"coordinates":[-91.66879900000001,29.916977],"type":"Point"}
}