{
  "type": "Feature",
  "properties": {
    "addr:full":"101 Old Bastrop Rd Monroe LA 71203",
    "addr:housenumber":"101",
    "addr:postcode":"71203",
    "addr:street":"Old Bastrop Rd",
    "iso:country":"US",
    "sg:address":"101 Old Bastrop Rd",
    "sg:city":"Monroe",
    "sg:classifiers":[
        {
            "category":"Autos & Motor Vehicles",
            "subcategory":"Auto Supplies",
            "type":"Retail Goods"
        }
    ],
    "sg:phone":"+1 318 345 5417",
    "sg:postcode":"71203",
    "sg:province":"LA",
    "sg:tags":[
        "automobile",
        "parts"
    ],
    "wof:name":"O'Reilly Auto Parts",
    "wof:placetype":"venue"
},
  "geometry": {"coordinates":[-92.034291,32.529092],"type":"Point"}
}