{
  "type": "Feature",
  "properties": {
    "addr:full":"101 W Lee St Leesville LA 71446",
    "addr:housenumber":"101",
    "addr:postcode":"71446",
    "addr:street":"W Lee St",
    "iso:country":"US",
    "sg:address":"101 W Lee St",
    "sg:city":"Leesville",
    "sg:classifiers":[
        {
            "category":"Government",
            "subcategory":"Police Station",
            "type":"Public Place"
        }
    ],
    "sg:phone":"+1 337 238 0332",
    "sg:postcode":"71446",
    "sg:province":"LA",
    "sg:tags":[
        "department"
    ],
    "wof:name":"Leesville Police-Civil Defense",
    "wof:placetype":"venue"
},
  "geometry": {"coordinates":[-93.265033,31.143939],"type":"Point"}
}