{
  "type": "Feature",
  "properties": {
    "addr:full":"514 Franklin Ave New Orleans LA 70117",
    "addr:housenumber":"514",
    "addr:postcode":"70117",
    "addr:street":"Franklin Ave",
    "iso:country":"US",
    "sg:address":"514 Franklin Ave",
    "sg:city":"New Orleans",
    "sg:classifiers":[
        {
            "category":"Building & Trades",
            "subcategory":"Cleaning & Sanitation",
            "type":"Services"
        }
    ],
    "sg:phone":"+1 504 944 5505",
    "sg:postcode":"70117",
    "sg:province":"LA",
    "sg:tags":[
        "janitor"
    ],
    "wof:name":"One Source",
    "wof:placetype":"venue"
},
  "geometry": {"coordinates":[-90.05181899999999,29.963773],"type":"Point"}
}