{
  "type": "Feature",
  "properties": {
    "iso:country":"US",
    "sg:address":"9228 Mammoth Ave",
    "sg:city":"Baton Rouge",
    "sg:classifiers":[
        {
            "category":"Wholesale",
            "subcategory":"Machinery & Supplies",
            "type":"Manufacturing & Wholesale Goods"
        }
    ],
    "sg:phone":"+1 225 928 3483",
    "sg:postcode":"70814",
    "sg:province":"LA",
    "sg:tags":[
        "equipment",
        "welding"
    ],
    "wof:name":"Metro Welding Supply Inc",
    "wof:placetype":"venue"
},
  "geometry": {"coordinates":[-91.084013,30.473878],"type":"Point"}
}