{
  "type": "Feature",
  "properties": {
    "addr:full":"37067 Lirocchi Park Prairieville LA 70769",
    "addr:postcode":"37067;70769",
    "addr:street":"Lirocchi Park Prairieville",
    "iso:country":"US",
    "sg:address":"37067 Lirocchi Park",
    "sg:city":"Prairieville",
    "sg:classifiers":[
        {
            "category":"Manufacturing",
            "subcategory":"Printing",
            "type":"Manufacturing & Wholesale Goods"
        }
    ],
    "sg:phone":"+1 225 673 8097",
    "sg:postcode":"70769",
    "sg:province":"LA",
    "sg:tags":[
        "screen"
    ],
    "wof:name":"Acadian Graphics",
    "wof:placetype":"venue"
},
  "geometry": {"coordinates":[-90.98733900000001,30.280272],"type":"Point"}
}