{
  "type": "Feature",
  "properties": {
    "iso:country":"US",
    "sg:address":"112 N Hazel St",
    "sg:city":"Haughton",
    "sg:classifiers":[
        {
            "category":"Professional",
            "subcategory":"Detective & Security Services",
            "type":"Services"
        }
    ],
    "sg:phone":"+1 318 949 6182",
    "sg:postcode":"71037",
    "sg:province":"LA",
    "sg:tags":[
        "guard"
    ],
    "wof:name":"Kyle Tanner",
    "wof:placetype":"venue"
},
  "geometry": {"coordinates":[-93.502623,32.533217],"type":"Point"}
}