{
  "type": "Feature",
  "properties": {
    "iso:country":"US",
    "sg:address":"10779 Yarlin St",
    "sg:city":"Denham Springs",
    "sg:classifiers":[
        {
            "category":"Organizations",
            "subcategory":"Religious Organization",
            "type":"Services"
        }
    ],
    "sg:phone":"+1 225 667 0396",
    "sg:postcode":"70726",
    "sg:province":"LA",
    "wof:name":"Faith Fllwship Pntcstal Church",
    "wof:placetype":"venue"
},
  "geometry": {"coordinates":[-90.907601,30.480675],"type":"Point"}
}