{
  "type": "Feature",
  "properties": {
    "iso:country":"US",
    "sg:address":"9866 Royal St",
    "sg:city":"St Francisville",
    "sg:classifiers":[
        {
            "category":"Organizations",
            "subcategory":"Religious Organization",
            "type":"Services"
        }
    ],
    "sg:phone":"+1 225 635 3763",
    "sg:postcode":"70775",
    "sg:province":"LA",
    "sg:tags":[
        "church"
    ],
    "wof:name":"United Methodist Church",
    "wof:placetype":"venue"
},
  "geometry": {"coordinates":[-91.38507799999999,30.774981],"type":"Point"}
}