{
  "type": "Feature",
  "properties": {
    "iso:country":"US",
    "sg:address":"220 Travis St",
    "sg:city":"Shreveport",
    "sg:classifiers":[
        {
            "category":"Professional",
            "subcategory":"Lawyer & Legal Services",
            "type":"Services"
        }
    ],
    "sg:phone":"+1 318 213 9350",
    "sg:postcode":"71101",
    "sg:province":"LA",
    "sg:tags":[
        "attorney"
    ],
    "wof:name":"Walter D White",
    "wof:placetype":"venue"
},
  "geometry": {"coordinates":[-93.74847699999999,32.515287],"type":"Point"}
}