{
  "type": "Feature",
  "properties": {
    "addr:full":"24314 Eden St Plaquemine LA 70764",
    "addr:housenumber":"24314",
    "addr:postcode":"70764",
    "addr:street":"Eden St",
    "iso:country":"US",
    "sg:address":"24314 Eden St",
    "sg:city":"Plaquemine",
    "sg:classifiers":[
        {
            "category":"Personal",
            "subcategory":"Barber",
            "type":"Services"
        }
    ],
    "sg:phone":"+1 225 687 6658",
    "sg:postcode":"70764",
    "sg:province":"LA",
    "wof:name":"Hair Masters",
    "wof:placetype":"venue"
},
  "geometry": {"coordinates":[-91.230024,30.283095],"type":"Point"}
}