{
  "type": "Feature",
  "properties": {
    "iso:country":"US",
    "sg:address":"815 Tally Aly",
    "sg:city":"Shreveport",
    "sg:classifiers":[
        {
            "category":"Home & Garden",
            "subcategory":"Carpets & Floor Coverings",
            "type":"Retail Goods"
        }
    ],
    "sg:phone":"+1 318 221 2987",
    "sg:postcode":"71101",
    "sg:province":"LA",
    "sg:tags":[
        "dealer",
        "rug"
    ],
    "wof:name":"Southern Carpets Of Louisiana",
    "wof:placetype":"venue"
},
  "geometry": {"coordinates":[-93.75021599999999,32.507368],"type":"Point"}
}