{
  "type": "Feature",
  "properties": {
    "iso:country":"US",
    "sg:address":"3277 Hwy 107",
    "sg:city":"Effie",
    "sg:classifiers":[
        {
            "category":"Government",
            "subcategory":"Post Office",
            "type":"Public Place"
        }
    ],
    "sg:phone":"+1 318 253 8333",
    "sg:postcode":"71331",
    "sg:province":"LA",
    "wof:name":"US Post Office",
    "wof:placetype":"venue"
},
  "geometry": {"coordinates":[-92.15351699999999,31.21345],"type":"Point"}
}