{
  "type": "Feature",
  "properties": {
    "addr:full":"222 S Washington St Bastrop LA 71220",
    "addr:housenumber":"222",
    "addr:postcode":"71220",
    "addr:street":"S Washington St",
    "iso:country":"US",
    "sg:address":"222 S Washington St",
    "sg:city":"Bastrop",
    "sg:classifiers":[
        {
            "category":"Organizations",
            "subcategory":"Religious Organization",
            "type":"Services"
        }
    ],
    "sg:phone":"+1 318 281 2872",
    "sg:postcode":"71220",
    "sg:province":"LA",
    "sg:tags":[
        "church"
    ],
    "wof:name":"First United Methodist Church",
    "wof:placetype":"venue"
},
  "geometry": {"coordinates":[-91.914495,32.777056],"type":"Point"}
}