{
  "type": "Feature",
  "properties": {
    "addr:full":"8445 Youree Dr Shreveport LA 71115",
    "addr:housenumber":"8445",
    "addr:postcode":"71115",
    "addr:street":"Youree Dr",
    "iso:country":"US",
    "sg:address":"8445 Youree Dr",
    "sg:city":"Shreveport",
    "sg:classifiers":[
        {
            "category":"Real Estate",
            "subcategory":"Real Estate Operator",
            "type":"Services"
        }
    ],
    "sg:phone":"+1 318 798 6963",
    "sg:postcode":"71115",
    "sg:province":"LA",
    "sg:tags":[
        "apartment"
    ],
    "wof:name":"Apts",
    "wof:placetype":"venue"
},
  "geometry": {"coordinates":[-93.70999999999999,32.42882],"type":"Point"}
}