{
  "type": "Feature",
  "properties": {
    "iso:country":"US",
    "sg:address":"1301 Eastridge Dr",
    "sg:city":"Slidell",
    "sg:classifiers":[
        {
            "category":"Retail",
            "subcategory":"Portrait Studio",
            "type":"Services"
        }
    ],
    "sg:phone":"+1 985 641 3005",
    "sg:postcode":"70458",
    "sg:province":"LA",
    "sg:tags":[
        "photographer"
    ],
    "wof:name":"Crockett Hope Photography",
    "wof:placetype":"venue"
},
  "geometry": {"coordinates":[-89.76575699999999,30.283735],"type":"Point"}
}