{
  "type": "Feature",
  "properties": {
    "iso:country":"US",
    "sg:address":"35086 Old State Hwy 16",
    "sg:city":"Denham Springs",
    "sg:classifiers":[
        {
            "category":"Education",
            "subcategory":"School",
            "type":"Public Place"
        }
    ],
    "sg:phone":"+1 225 665 8858",
    "sg:postcode":"70706",
    "sg:province":"LA",
    "sg:website":"www.lpsb.org",
    "wof:name":"Live Oak High School",
    "wof:placetype":"venue"
},
  "geometry": {"coordinates":[-90.952658,30.57748],"type":"Point"}
}