{
  "type": "Feature",
  "properties": {
    "iso:country":"US",
    "sg:address":"29695 Bankston Rd S",
    "sg:city":"Albany",
    "sg:classifiers":[
        {
            "category":"Retail",
            "subcategory":"Repair Shop",
            "type":"Services"
        }
    ],
    "sg:phone":"+1 225 567 1811",
    "sg:postcode":"70711",
    "sg:province":"LA",
    "sg:tags":[
        "equipment",
        "conditioning",
        "air"
    ],
    "wof:name":"Quality Air Conditioning Rpr",
    "wof:placetype":"venue"
},
  "geometry": {"coordinates":[-90.60022600000001,30.497985],"type":"Point"}
}