{
  "type": "Feature",
  "properties": {
    "iso:country":"US",
    "sg:address":"522 Bourbon St",
    "sg:city":"New Orleans",
    "sg:classifiers":[
        {
            "category":"Shopping",
            "subcategory":"Gifts & Souvenirs",
            "type":"Retail Goods"
        }
    ],
    "sg:phone":"+1 504 525 9911",
    "sg:postcode":"70130",
    "sg:province":"LA",
    "sg:tags":[
        "shop"
    ],
    "wof:name":"Boudreaux' Backyard",
    "wof:placetype":"venue"
},
  "geometry": {"coordinates":[-90.066423,29.957599],"type":"Point"}
}