{
  "type": "Feature",
  "properties": {
    "addr:full":"304 W Port St Deridder LA 70634",
    "addr:housenumber":"304",
    "addr:postcode":"70634",
    "addr:street":"W Port St",
    "iso:country":"US",
    "sg:address":"304 W Port St",
    "sg:city":"Deridder",
    "sg:classifiers":[
        {
            "category":"Organizations",
            "subcategory":"Religious Organization",
            "type":"Services"
        }
    ],
    "sg:phone":"+1 337 463 7087",
    "sg:postcode":"70634",
    "sg:province":"LA",
    "wof:name":"Gods Temple of Refuge",
    "wof:placetype":"venue"
},
  "geometry": {"coordinates":[-93.289008,30.848904],"type":"Point"}
}