{
  "type": "Feature",
  "properties": {
    "iso:country":"US",
    "sg:address":"7629 Quitman Hwy",
    "sg:city":"Quitman",
    "sg:classifiers":[
        {
            "category":"Home & Garden",
            "subcategory":"Furniture",
            "type":"Retail Goods"
        }
    ],
    "sg:phone":"+1 318 259 2261",
    "sg:postcode":"71268",
    "sg:province":"LA",
    "wof:name":"Stewart's Furniture Waterbeds",
    "wof:placetype":"venue"
},
  "geometry": {"coordinates":[-92.70252000000001,32.341318],"type":"Point"}
}