{
  "type": "Feature",
  "properties": {
    "addr:full":"306 Redmond Rd Houma LA 70363",
    "addr:housenumber":"306",
    "addr:postcode":"70363",
    "addr:street":"Redmond Rd",
    "iso:country":"US",
    "sg:address":"306 Redmond Rd",
    "sg:city":"Houma",
    "sg:classifiers":[
        {
            "category":"Building & Trades",
            "subcategory":"Equipment Rental",
            "type":"Services"
        }
    ],
    "sg:phone":"+1 985 872 1960",
    "sg:postcode":"70363",
    "sg:province":"LA",
    "sg:tags":[
        "oil",
        "well",
        "supply"
    ],
    "sg:website":"www.tarponrentals.com",
    "wof:name":"Tarpon Rentals",
    "wof:placetype":"venue"
},
  "geometry": {"coordinates":[-90.683356,29.549322],"type":"Point"}
}