{
  "type": "Feature",
  "properties": {
    "iso:country":"US",
    "sg:address":"709 N 3rd St",
    "sg:city":"Alexandria",
    "sg:classifiers":[
        {
            "category":"Retail",
            "subcategory":"Auto Repair",
            "type":"Services"
        }
    ],
    "sg:phone":"+1 318 445 3235",
    "sg:postcode":"71301",
    "sg:province":"LA",
    "sg:tags":[
        "automotive",
        "wrecker"
    ],
    "wof:name":"AA Towing Of Alexandria",
    "wof:placetype":"venue"
},
  "geometry": {"coordinates":[-92.457078,31.321358],"type":"Point"}
}