{
  "type": "Feature",
  "properties": {
    "iso:country":"US",
    "sg:address":"8717 W Judge Perez Dr",
    "sg:city":"Chalmette",
    "sg:classifiers":[
        {
            "category":"Restaurant",
            "type":"Food & Drink"
        }
    ],
    "sg:phone":"+1 504 279 4405",
    "sg:postcode":"70043",
    "sg:province":"LA",
    "wof:name":"Lostres Amigos Grill",
    "wof:placetype":"venue"
},
  "geometry": {"coordinates":[-89.97215300000001,29.950404],"type":"Point"}
}