{
  "type": "Feature",
  "properties": {
    "iso:country":"US",
    "sg:address":"723 Hwy 154",
    "sg:city":"Elm Grove",
    "sg:classifiers":[
        {
            "category":"Organizations",
            "subcategory":"Religious Organization",
            "type":"Services"
        }
    ],
    "sg:phone":"+1 318 741 0071",
    "sg:postcode":"71051",
    "sg:province":"LA",
    "wof:name":"New Zion Baptist Church",
    "wof:placetype":"venue"
},
  "geometry": {"coordinates":[-93.53920599999999,32.354501],"type":"Point"}
}