{
  "type": "Feature",
  "properties": {
    "iso:country":"US",
    "sg:address":"1075 Hwy 80",
    "sg:city":"Haughton",
    "sg:classifiers":[
        {
            "category":"Shopping",
            "subcategory":"Department Store",
            "type":"Retail Goods"
        }
    ],
    "sg:phone":"+1 318 390 7711",
    "sg:postcode":"71037",
    "sg:province":"LA",
    "sg:tags":[
        "shop"
    ],
    "wof:name":"Fred's Discount Store",
    "wof:placetype":"venue"
},
  "geometry": {"coordinates":[-93.611374,32.55604],"type":"Point"}
}