{
  "type": "Feature",
  "properties": {
    "addr:full":"2069 Deer Ridge Ave Baton Rouge LA 70816",
    "addr:housenumber":"2069",
    "addr:postcode":"70816",
    "addr:street":"Deer Ridge Ave",
    "iso:country":"US",
    "sg:address":"2069 Deer Ridge Ave",
    "sg:city":"Baton Rouge",
    "sg:classifiers":[
        {
            "category":"Professional",
            "type":"Services"
        }
    ],
    "sg:phone":"+1 225 273 6168",
    "sg:postcode":"70816",
    "sg:province":"LA",
    "wof:name":"Bofingers Tree Service LLC",
    "wof:placetype":"venue"
},
  "geometry": {"coordinates":[-91.025358,30.444075],"type":"Point"}
}