{
  "type": "Feature",
  "properties": {
    "iso:country":"US",
    "sg:address":"13173 George Rouyea Rd",
    "sg:city":"Gonzales",
    "sg:classifiers":[
        {
            "category":"Building & Trades",
            "subcategory":"Construction",
            "type":"Services"
        }
    ],
    "sg:phone":"+1 225 644 8518",
    "sg:postcode":"70737",
    "sg:province":"LA",
    "sg:tags":[
        "painter"
    ],
    "wof:name":"Kelly's Painting & Siding",
    "wof:placetype":"venue"
},
  "geometry": {"coordinates":[-90.88730700000001,30.259233],"type":"Point"}
}