{
  "type": "Feature",
  "properties": {
    "addr:full":"1143 S 11th St Baton Rouge LA 70802",
    "addr:housenumber":"1143",
    "addr:postcode":"70802",
    "addr:street":"S 11Th St",
    "iso:country":"US",
    "sg:address":"1143 S 11th St",
    "sg:city":"Baton Rouge",
    "sg:classifiers":[
        {
            "category":"Organizations",
            "subcategory":"Religious Organization",
            "type":"Services"
        }
    ],
    "sg:phone":"+1 225 383 3479",
    "sg:postcode":"70802",
    "sg:province":"LA",
    "sg:tags":[
        "church"
    ],
    "wof:name":"St Francis Xavier Catholic Chr",
    "wof:placetype":"venue"
},
  "geometry": {"coordinates":[-91.177269,30.437789],"type":"Point"}
}