{
  "type": "Feature",
  "properties": {
    "addr:full":"711 Arial St Alexandria LA 71302",
    "addr:housenumber":"711",
    "addr:postcode":"71302",
    "addr:street":"Arial St",
    "iso:country":"US",
    "sg:address":"711 Arial St",
    "sg:city":"Alexandria",
    "sg:classifiers":[
        {
            "category":"Wholesale",
            "subcategory":"Scrap",
            "type":"Manufacturing & Wholesale Goods"
        }
    ],
    "sg:phone":"+1 318 445 2441",
    "sg:postcode":"71302",
    "sg:province":"LA",
    "sg:tags":[
        "metal",
        "iron"
    ],
    "wof:name":"Alexandria Iron & Supply Co",
    "wof:placetype":"venue"
},
  "geometry": {"coordinates":[-92.441182,31.302758],"type":"Point"}
}