{
  "type": "Feature",
  "properties": {
    "addr:full":"720 Veterans Memorial Dr Abbeville LA 70510",
    "addr:housenumber":"720",
    "addr:postcode":"70510",
    "addr:street":"Veterans Memorial Dr",
    "iso:country":"US",
    "sg:address":"720 Veterans Memorial Dr",
    "sg:city":"Abbeville",
    "sg:classifiers":[
        {
            "category":"Restaurant",
            "type":"Food & Drink"
        }
    ],
    "sg:phone":"+1 337 893 9373",
    "sg:postcode":"70510",
    "sg:province":"LA",
    "sg:tags":[
        "pizza"
    ],
    "wof:name":"Pizza Hut",
    "wof:placetype":"venue"
},
  "geometry": {"coordinates":[-92.14415099999999,29.984786],"type":"Point"}
}