{
  "type": "Feature",
  "properties": {
    "addr:full":"3410 Sherwood St Baton Rouge LA 70805",
    "addr:housenumber":"3410",
    "addr:postcode":"70805",
    "addr:street":"Sherwood St",
    "iso:country":"US",
    "sg:address":"3410 Sherwood St",
    "sg:city":"Baton Rouge",
    "sg:classifiers":[
        {
            "category":"Restaurant",
            "type":"Food & Drink"
        }
    ],
    "sg:menulink":"http://www.allmenus.com/la/baton-rouge/21771-brew-bachers/menu/",
    "sg:phone":"+1 225 291 7669",
    "sg:postcode":"70805",
    "sg:province":"LA",
    "sg:tags":[
        "american"
    ],
    "wof:name":"Brew-Bacher's",
    "wof:placetype":"venue"
},
  "geometry": {"coordinates":[-91.153093,30.490018],"type":"Point"}
}