{
  "type": "Feature",
  "properties": {
    "iso:country":"US",
    "sg:address":"117 N Richardson St",
    "sg:city":"Hammond",
    "sg:classifiers":[
        {
            "category":"Organizations",
            "subcategory":"Religious Organization",
            "type":"Services"
        }
    ],
    "sg:phone":"+1 225 567 3186",
    "sg:postcode":"70401",
    "sg:province":"LA",
    "sg:tags":[
        "church"
    ],
    "wof:name":"Bethel Worship Ctr COG",
    "wof:placetype":"venue"
},
  "geometry": {"coordinates":[-90.47788300000001,30.502476],"type":"Point"}
}