{
  "type": "Feature",
  "properties": {
    "addr:full":"502 Main Project Rd Schriever LA 70395",
    "addr:housenumber":"502",
    "addr:postcode":"70395",
    "addr:street":"Project Rd",
    "iso:country":"US",
    "sg:address":"502 Main Project Rd",
    "sg:city":"Schriever",
    "sg:classifiers":[
        {
            "category":"Social Services",
            "subcategory":"Child Care",
            "type":"Services"
        }
    ],
    "sg:phone":"+1 985 448 1009",
    "sg:postcode":"70395",
    "sg:province":"LA",
    "wof:name":"Ms Patti's Playhouse",
    "wof:placetype":"venue"
},
  "geometry": {"coordinates":[-90.818477,29.725921],"type":"Point"}
}