{
  "type": "Feature",
  "properties": {
    "iso:country":"US",
    "sg:address":"4400 N Galvez St",
    "sg:city":"New Orleans",
    "sg:classifiers":[
        {
            "category":"Wholesale",
            "subcategory":"Machinery & Supplies",
            "type":"Manufacturing & Wholesale Goods"
        }
    ],
    "sg:phone":"+1 504 944 6185",
    "sg:postcode":"70117",
    "sg:province":"LA",
    "sg:tags":[
        "cargo",
        "container",
        "freight"
    ],
    "wof:name":"W W Rowland Trucking Co Inc",
    "wof:placetype":"venue"
},
  "geometry": {"coordinates":[-90.02751600000001,29.974836],"type":"Point"}
}