{
  "type": "Feature",
  "properties": {
    "iso:country":"US",
    "sg:address":"6815 Louis Xiv St",
    "sg:city":"New Orleans",
    "sg:classifiers":[
        {
            "category":"Professional",
            "type":"Services"
        }
    ],
    "sg:phone":"+1 504 282 0530",
    "sg:postcode":"70124",
    "sg:province":"LA",
    "wof:name":"Bower Inc",
    "wof:placetype":"venue"
},
  "geometry": {"coordinates":[-90.10792499999999,30.015673],"type":"Point"}
}