{
  "type": "Feature",
  "properties": {
    "iso:country":"US",
    "sg:address":"1531 Hwy 10 W",
    "sg:city":"Oakdale",
    "sg:classifiers":[
        {
            "category":"Shopping",
            "type":"Retail Goods"
        }
    ],
    "sg:phone":"+1 318 335 2612",
    "sg:postcode":"71463",
    "sg:province":"LA",
    "sg:tags":[
        "monument"
    ],
    "wof:name":"Memorials Unlimited",
    "wof:placetype":"venue"
},
  "geometry": {"coordinates":[-92.698739,30.829431],"type":"Point"}
}