{
  "type": "Feature",
  "properties": {
    "iso:country":"US",
    "sg:address":"2717 Massachusetts Ave",
    "sg:city":"Metairie",
    "sg:classifiers":[
        {
            "category":"Professional",
            "subcategory":"Business Services",
            "type":"Services"
        }
    ],
    "sg:phone":"+1 504 467 3655",
    "sg:postcode":"70003",
    "sg:province":"LA",
    "sg:tags":[
        "recording",
        "studio"
    ],
    "wof:name":"Audio Video Solutions Inc",
    "wof:placetype":"venue"
},
  "geometry": {"coordinates":[-90.22781500000001,30.00549],"type":"Point"}
}