{
  "type": "Feature",
  "properties": {
    "iso:country":"US",
    "sg:address":"716 S Sterling St",
    "sg:city":"Lafayette",
    "sg:classifiers":[
        {
            "category":"Retail",
            "subcategory":"Laundry & Dry Cleaning",
            "type":"Services"
        }
    ],
    "sg:phone":"+1 337 235 6301",
    "sg:postcode":"70501",
    "sg:province":"LA",
    "sg:tags":[
        "cleaners"
    ],
    "wof:name":"Professional Cleaners & Drpry",
    "wof:placetype":"venue"
},
  "geometry": {"coordinates":[-92.00433099999999,30.225107],"type":"Point"}
}