{
  "type": "Feature",
  "properties": {
    "addr:full":"3003 Knight St Shreveport LA 71105",
    "addr:housenumber":"3003",
    "addr:postcode":"71105",
    "addr:street":"Knight St",
    "iso:country":"US",
    "sg:address":"3003 Knight St",
    "sg:city":"Shreveport",
    "sg:classifiers":[
        {
            "category":"Organizations",
            "subcategory":"Non-profit Organization",
            "type":"Services"
        }
    ],
    "sg:phone":"+1 318 861 1778",
    "sg:postcode":"71105",
    "sg:province":"LA",
    "wof:name":"Junior Achievement",
    "wof:placetype":"venue"
},
  "geometry": {"coordinates":[-93.702741,32.480386],"type":"Point"}
}