{
  "type": "Feature",
  "properties": {
    "iso:country":"US",
    "sg:address":"6601 Hwy 565",
    "sg:city":"Monterey",
    "sg:classifiers":[
        {
            "category":"Building & Trades",
            "subcategory":"Construction",
            "type":"Services"
        }
    ],
    "sg:phone":"+1 318 386 2721",
    "sg:postcode":"71354",
    "sg:province":"LA",
    "sg:tags":[
        "pumping",
        "contractor"
    ],
    "wof:name":"Rig Masters Inc",
    "wof:placetype":"venue"
},
  "geometry": {"coordinates":[-91.71801000000001,31.449366],"type":"Point"}
}