{
  "type": "Feature",
  "properties": {
    "addr:full":"1702 Pub Works Rd Jennings LA 70546",
    "addr:postcode":"70546",
    "addr:street":"Works Rd",
    "iso:country":"US",
    "sg:address":"1702 Pub Works Rd",
    "sg:city":"Jennings",
    "sg:classifiers":[
        {
            "category":"Farming",
            "subcategory":"Farm & Veterinary Services",
            "type":"Manufacturing & Wholesale Goods"
        }
    ],
    "sg:phone":"+1 337 824 1567",
    "sg:postcode":"70546",
    "sg:province":"LA",
    "sg:tags":[
        "aerial",
        "applicator"
    ],
    "wof:name":"Riceland Aviation Inc",
    "wof:placetype":"venue"
},
  "geometry": {"coordinates":[-92.66954200000001,30.237513],"type":"Point"}
}