{
  "type": "Feature",
  "properties": {
    "iso:country":"US",
    "sg:address":"1130 Sampson St",
    "sg:city":"Westlake",
    "sg:classifiers":[
        {
            "category":"Food & Beverages",
            "subcategory":"Groceries & Convenience Stores",
            "type":"Retail Goods"
        }
    ],
    "sg:phone":"+1 337 433 9541",
    "sg:postcode":"70669",
    "sg:province":"LA",
    "wof:name":"Westlake Fast Stop",
    "wof:placetype":"venue"
},
  "geometry": {"coordinates":[-93.25804100000001,30.246967],"type":"Point"}
}