{
  "type": "Feature",
  "properties": {
    "addr:full":"12146 Hwy 190 Kinder LA 70648",
    "addr:housenumber":"12146",
    "addr:postcode":"70648",
    "addr:street":"Hwy 190 Kinder",
    "iso:country":"US",
    "sg:address":"12146 Hwy 190",
    "sg:city":"Kinder",
    "sg:classifiers":[
        {
            "category":"Retail",
            "subcategory":"Auto Repair",
            "type":"Services"
        }
    ],
    "sg:phone":"+1 337 738 3006",
    "sg:postcode":"70648",
    "sg:province":"LA",
    "sg:tags":[
        "repairing",
        "automobile"
    ],
    "wof:name":"Mona's Auto Svc",
    "wof:placetype":"venue"
},
  "geometry": {"coordinates":[-92.807439,30.482022],"type":"Point"}
}