{
  "type": "Feature",
  "properties": {
    "iso:country":"US",
    "sg:address":"1100 N. Peters St. Bay 13",
    "sg:city":"New Orleans",
    "sg:classifiers":[
        {
            "category":"Restaurant",
            "type":"Food & Drink"
        }
    ],
    "sg:phone":"+1 504 525 1953",
    "sg:postcode":"70116",
    "sg:province":"LA",
    "wof:name":"Meals From the Heart Cafe",
    "wof:placetype":"venue"
},
  "geometry": {"coordinates":[-90.059545,29.959596],"type":"Point"}
}