{
  "type": "Feature",
  "properties": {
    "addr:full":"905 Jefferson St Lafayette LA 70501",
    "addr:housenumber":"905",
    "addr:postcode":"70501",
    "addr:street":"Jefferson St",
    "iso:country":"US",
    "sg:address":"905 Jefferson St",
    "sg:city":"Lafayette",
    "sg:classifiers":[
        {
            "category":"Government",
            "subcategory":"Office",
            "type":"Public Place"
        }
    ],
    "sg:phone":"+1 318 262 6601",
    "sg:postcode":"70501",
    "sg:province":"LA",
    "sg:tags":[
        "development",
        "grant",
        "federal",
        "loan",
        "dev",
        "planning",
        "delivery",
        "program",
        "rural"
    ],
    "wof:name":"USDA Rural Development",
    "wof:placetype":"venue"
},
  "geometry": {"coordinates":[-92.01798700000001,30.220738],"type":"Point"}
}