{
  "type": "Feature",
  "properties": {
    "iso:country":"US",
    "sg:address":"200 Republic Ave",
    "sg:city":"Lafayette",
    "sg:classifiers":[
        {
            "category":"Health Services",
            "subcategory":"Doctor",
            "type":"Services"
        }
    ],
    "sg:phone":"+1 318 264 1870",
    "sg:postcode":"70508",
    "sg:province":"LA",
    "wof:name":"Randolph B Malloy DDS",
    "wof:placetype":"venue"
},
  "geometry": {"coordinates":[-92.03985299999999,30.156903],"type":"Point"}
}