{
  "type": "Feature",
  "properties": {
    "iso:country":"US",
    "sg:address":"2140 Airline Dr",
    "sg:city":"Bossier City",
    "sg:classifiers":[
        {
            "category":"Organizations",
            "subcategory":"Non-profit Organization",
            "type":"Services"
        }
    ],
    "sg:phone":"+1 318 747 6497",
    "sg:postcode":"71111",
    "sg:province":"LA",
    "wof:name":"Holy Cross Villas",
    "wof:placetype":"venue"
},
  "geometry": {"coordinates":[-93.706249,32.533543],"type":"Point"}
}