{
  "type": "Feature",
  "properties": {
    "iso:country":"US",
    "sg:address":"1517 N Tonti St",
    "sg:city":"New Orleans",
    "sg:classifiers":[
        {
            "category":"Social Services",
            "subcategory":"Child Care",
            "type":"Services"
        }
    ],
    "sg:phone":"+1 504 616 3905",
    "sg:postcode":"70119",
    "sg:province":"LA",
    "wof:name":"F F Properties",
    "wof:placetype":"venue"
},
  "geometry": {"coordinates":[-90.072896,29.975799],"type":"Point"}
}