{
  "type": "Feature",
  "properties": {
    "addr:full":"212 E Kings Hwy Shreveport LA 71104",
    "addr:housenumber":"212",
    "addr:postcode":"71104",
    "addr:street":"E Kings Hwy",
    "iso:country":"US",
    "sg:address":"212 E Kings Hwy",
    "sg:city":"Shreveport",
    "sg:classifiers":[
        {
            "category":"Retail",
            "subcategory":"Veterinary Services",
            "type":"Services"
        }
    ],
    "sg:phone":"+1 318 631 6015",
    "sg:postcode":"71104",
    "sg:province":"LA",
    "sg:tags":[
        "specialty"
    ],
    "wof:name":"Vallian Arabian Ranch",
    "wof:placetype":"venue"
},
  "geometry": {"coordinates":[-93.72715700000001,32.481686],"type":"Point"}
}