{
  "type": "Feature",
  "properties": {
    "iso:country":"US",
    "sg:address":"6477 Joe Daniel Rd",
    "sg:city":"St Francisville",
    "sg:classifiers":[
        {
            "category":"Manufacturing",
            "subcategory":"Building Materials",
            "type":"Manufacturing & Wholesale Goods"
        }
    ],
    "sg:phone":"+1 225 784 1001",
    "sg:postcode":"70775",
    "sg:province":"LA",
    "wof:name":"RTE",
    "wof:placetype":"venue"
},
  "geometry": {"coordinates":[-91.32119400000001,30.824262],"type":"Point"}
}