{
  "type": "Feature",
  "properties": {
    "iso:country":"US",
    "sg:address":"24836 State Rte 333",
    "sg:city":"Abbeville",
    "sg:classifiers":[
        {
            "category":"Airline",
            "type":"Transportation"
        }
    ],
    "sg:phone":"+1 337 893 1882",
    "sg:postcode":"70510",
    "sg:province":"LA",
    "sg:tags":[
        "helicopter",
        "rental"
    ],
    "wof:name":"Petroleum Helicopters Inc",
    "wof:placetype":"venue"
},
  "geometry": {"coordinates":[-92.165601,29.839551],"type":"Point"}
}