{
  "type": "Feature",
  "properties": {
    "iso:country":"US",
    "sg:address":"188 Little Lake Rd",
    "sg:city":"West Monroe",
    "sg:classifiers":[
        {
            "category":"Professional",
            "subcategory":"Management & Consulting",
            "type":"Services"
        }
    ],
    "sg:phone":"+1 318 387 5337",
    "sg:postcode":"71292",
    "sg:province":"LA",
    "sg:tags":[
        "business"
    ],
    "wof:name":"Evans Integrated Consultants I",
    "wof:placetype":"venue"
},
  "geometry": {"coordinates":[-92.237213,32.443045],"type":"Point"}
}