{
  "type": "Feature",
  "properties": {
    "iso:country":"US",
    "sg:address":"4615 Monkhouse Dr",
    "sg:city":"Shreveport",
    "sg:classifiers":[
        {
            "category":"Organizations",
            "subcategory":"Religious Organization",
            "type":"Services"
        }
    ],
    "sg:phone":"+1 318 868 0062",
    "sg:postcode":"71109",
    "sg:province":"LA",
    "sg:tags":[
        "church"
    ],
    "wof:name":"I AM Five-Fold Ministries",
    "wof:placetype":"venue"
},
  "geometry": {"coordinates":[-93.827371,32.467939],"type":"Point"}
}