{
  "type": "Feature",
  "properties": {
    "iso:country":"US",
    "sg:address":"26080 Wax Rd",
    "sg:city":"Denham Springs",
    "sg:classifiers":[
        {
            "category":"Organizations",
            "subcategory":"Religious Organization",
            "type":"Services"
        }
    ],
    "sg:phone":"+1 225 664 3223",
    "sg:postcode":"70726",
    "sg:province":"LA",
    "wof:name":"Grace Bible Baptist Church",
    "wof:placetype":"venue"
},
  "geometry": {"coordinates":[-90.924221,30.445471],"type":"Point"}
}