{
  "type": "Feature",
  "properties": {
    "addr:full":"4720 Cameron St Lafayette LA 70506",
    "addr:housenumber":"4720",
    "addr:postcode":"70506",
    "addr:street":"Cameron St",
    "iso:country":"US",
    "sg:address":"4720 Cameron St",
    "sg:city":"Lafayette",
    "sg:classifiers":[
        {
            "category":"Retail",
            "subcategory":"Auto Repair",
            "type":"Services"
        }
    ],
    "sg:phone":"+1 337 235 0150",
    "sg:postcode":"70506",
    "sg:province":"LA",
    "sg:tags":[
        "truck"
    ],
    "wof:name":"Onsite Mechanical Svc",
    "wof:placetype":"venue"
},
  "geometry": {"coordinates":[-92.075867,30.232238],"type":"Point"}
}