{
  "type": "Feature",
  "properties": {
    "iso:country":"US",
    "sg:address":"1117 Kirkman St",
    "sg:city":"Lake Charles",
    "sg:classifiers":[
        {
            "category":"Real Estate",
            "subcategory":"Real Estate Services",
            "type":"Services"
        }
    ],
    "sg:phone":"+1 337 436 3419",
    "sg:postcode":"70601",
    "sg:province":"LA",
    "wof:name":"Pelican Land & Abstract Co",
    "wof:placetype":"venue"
},
  "geometry": {"coordinates":[-93.20972500000001,30.223476],"type":"Point"}
}