{
  "type": "Feature",
  "properties": {
    "iso:country":"US",
    "sg:address":"1911 Cypress St",
    "sg:city":"West Monroe",
    "sg:classifiers":[
        {
            "category":"Manufacturing",
            "subcategory":"Printing",
            "type":"Manufacturing & Wholesale Goods"
        }
    ],
    "sg:phone":"+1 318 361 3852",
    "sg:postcode":"71291",
    "sg:province":"LA",
    "sg:tags":[
        "printer"
    ],
    "wof:name":"Printing Pros",
    "wof:placetype":"venue"
},
  "geometry": {"coordinates":[-92.138533,32.515848],"type":"Point"}
}