{
  "type": "Feature",
  "properties": {
    "iso:country":"US",
    "sg:address":"1152 Marshall Dr",
    "sg:city":"Marrero",
    "sg:classifiers":[
        {
            "category":"Retail",
            "subcategory":"Car Wash",
            "type":"Services"
        }
    ],
    "sg:phone":"+1 504 340 3509",
    "sg:postcode":"70072",
    "sg:province":"LA",
    "sg:tags":[
        "carwash"
    ],
    "wof:name":"Aarons Car Wash",
    "wof:placetype":"venue"
},
  "geometry": {"coordinates":[-90.119033,29.891292],"type":"Point"}
}