{
  "type": "Feature",
  "properties": {
    "addr:full":"1320 Willow St Zwolle LA 71486",
    "addr:housenumber":"1320",
    "addr:postcode":"71486",
    "addr:street":"Willow St",
    "iso:country":"US",
    "sg:address":"1320 Willow St",
    "sg:city":"Zwolle",
    "sg:classifiers":[
        {
            "category":"Building & Trades",
            "subcategory":"Construction",
            "type":"Services"
        }
    ],
    "sg:phone":"+1 318 645 2900",
    "sg:postcode":"71486",
    "sg:province":"LA",
    "sg:tags":[
        "concrete",
        "contractor"
    ],
    "wof:name":"A & M Concrete Construction",
    "wof:placetype":"venue"
},
  "geometry": {"coordinates":[-93.639639,31.64495],"type":"Point"}
}