{
  "type": "Feature",
  "properties": {
    "iso:country":"US",
    "sg:address":"910 E Kings Hwy",
    "sg:city":"Shreveport",
    "sg:classifiers":[
        {
            "category":"Arts & Performance",
            "subcategory":"Theater",
            "type":"Entertainment"
        }
    ],
    "sg:phone":"+1 318 869 1791",
    "sg:postcode":"71105",
    "sg:province":"LA",
    "sg:tags":[
        "group"
    ],
    "wof:name":"Ark La Tex Entertainment Inc",
    "wof:placetype":"venue"
},
  "geometry": {"coordinates":[-93.715199,32.47434],"type":"Point"}
}