{
  "type": "Feature",
  "properties": {
    "addr:full":"1127 N Dupre St New Orleans LA 70119",
    "addr:housenumber":"1127",
    "addr:postcode":"70119",
    "addr:street":"N Dupre St",
    "iso:country":"US",
    "sg:address":"1127 N Dupre St",
    "sg:city":"New Orleans",
    "sg:classifiers":[
        {
            "category":"Professional",
            "subcategory":"Lawyer & Legal Services",
            "type":"Services"
        }
    ],
    "sg:phone":"+1 504 388 1466",
    "sg:postcode":"70119",
    "sg:province":"LA",
    "sg:tags":[
        "attorney"
    ],
    "wof:name":"P Landry Cullen",
    "wof:placetype":"venue"
},
  "geometry": {"coordinates":[-90.08219,29.976537],"type":"Point"}
}