{
  "type": "Feature",
  "properties": {
    "iso:country":"US",
    "sg:address":"3108 John Bunch Rd",
    "sg:city":"Sulphur",
    "sg:classifiers":[
        {
            "category":"Building & Trades",
            "subcategory":"Landscaping Services",
            "type":"Services"
        }
    ],
    "sg:phone":"+1 337 528 3432",
    "sg:postcode":"70663",
    "sg:province":"LA",
    "sg:tags":[
        "lawn",
        "maintenance"
    ],
    "wof:name":"Gound Effects",
    "wof:placetype":"venue"
},
  "geometry": {"coordinates":[-93.33384,30.2882],"type":"Point"}
}