{
  "type": "Feature",
  "properties": {
    "iso:country":"US",
    "sg:address":"21143 Shady Ln",
    "sg:city":"Covington",
    "sg:classifiers":[
        {
            "category":"Freight",
            "type":"Transportation"
        }
    ],
    "sg:phone":"+1 985 892 7285",
    "sg:postcode":"70435",
    "sg:province":"LA",
    "sg:tags":[
        "operator",
        "local",
        "trucking"
    ],
    "wof:name":"Shockley Trucking",
    "wof:placetype":"venue"
},
  "geometry": {"coordinates":[-90.057739,30.497764],"type":"Point"}
}