{
  "type": "Feature",
  "properties": {
    "iso:country":"US",
    "sg:address":"2611 Viking Dr",
    "sg:city":"Bossier City",
    "sg:classifiers":[
        {
            "category":"Restaurant",
            "type":"Food & Drink"
        }
    ],
    "sg:menulink":"http://www.allmenus.com/la/vanceville/103633-ruby-tuesdays/menu/",
    "sg:phone":"+1 318 752 1379",
    "sg:postcode":"71111",
    "sg:province":"LA",
    "sg:tags":[
        "burger",
        "american"
    ],
    "wof:name":"Ruby Tuesdays",
    "wof:placetype":"venue"
},
  "geometry": {"coordinates":[-93.71713099999999,32.555187],"type":"Point"}
}