{
  "type": "Feature",
  "properties": {
    "addr:full":"2332 Eastgate Dr Baton Rouge LA 70816",
    "addr:housenumber":"2332",
    "addr:postcode":"70816",
    "addr:street":"Eastgate Dr",
    "iso:country":"US",
    "sg:address":"2332 Eastgate Dr",
    "sg:city":"Baton Rouge",
    "sg:classifiers":[
        {
            "category":"Personal",
            "subcategory":"Beauty Salon",
            "type":"Services"
        }
    ],
    "sg:phone":"+1 225 291 2332",
    "sg:postcode":"70816",
    "sg:province":"LA",
    "wof:name":"Magnolia's Beauty Salon",
    "wof:placetype":"venue"
},
  "geometry": {"coordinates":[-91.049094,30.431039],"type":"Point"}
}