{
  "type": "Feature",
  "properties": {
    "iso:country":"US",
    "sg:address":"125 Swartz School Rd",
    "sg:city":"Monroe",
    "sg:classifiers":[
        {
            "category":"Building & Trades",
            "subcategory":"Construction",
            "type":"Services"
        }
    ],
    "sg:phone":"+1 318 329 9984",
    "sg:postcode":"71203",
    "sg:province":"LA",
    "sg:tags":[
        "residential",
        "general"
    ],
    "wof:name":"Kimberly Cockerham Cnstr",
    "wof:placetype":"venue"
},
  "geometry": {"coordinates":[-91.99704,32.568647],"type":"Point"}
}