{
  "type": "Feature",
  "properties": {
    "addr:full":"1003 N Gladys St Leesville LA 71446",
    "addr:housenumber":"1003",
    "addr:postcode":"71446",
    "addr:street":"N Gladys St",
    "iso:country":"US",
    "sg:address":"1003 N Gladys St",
    "sg:city":"Leesville",
    "sg:classifiers":[
        {
            "category":"Recreation",
            "type":"Entertainment"
        }
    ],
    "sg:phone":"+1 337 238 3271",
    "sg:postcode":"71446",
    "sg:province":"LA",
    "sg:tags":[
        "parks"
    ],
    "wof:name":"Leesville Neighborhood Ctr",
    "wof:placetype":"venue"
},
  "geometry": {"coordinates":[-93.270456,31.15203],"type":"Point"}
}