{
  "type": "Feature",
  "properties": {
    "iso:country":"US",
    "sg:address":"105 Branch St",
    "sg:city":"West Monroe",
    "sg:classifiers":[
        {
            "category":"Building & Trades",
            "subcategory":"Construction",
            "type":"Services"
        }
    ],
    "sg:phone":"+1 318 324 2122",
    "sg:postcode":"71292",
    "sg:province":"LA",
    "sg:tags":[
        "home",
        "improvement"
    ],
    "wof:name":"Thomas Remodeling",
    "wof:placetype":"venue"
},
  "geometry": {"coordinates":[-92.11766799999999,32.489183],"type":"Point"}
}