{
  "type": "Feature",
  "properties": {
    "iso:country":"US",
    "sg:address":"408 Kansas Ln",
    "sg:city":"Monroe",
    "sg:classifiers":[
        {
            "category":"Insurance",
            "subcategory":"Insurance Agent",
            "type":"Services"
        }
    ],
    "sg:phone":"+1 318 345 1340",
    "sg:postcode":"71203",
    "sg:province":"LA",
    "wof:name":"Perkins Insurance Inc",
    "wof:placetype":"venue"
},
  "geometry": {"coordinates":[-92.05366100000001,32.518646],"type":"Point"}
}