{
  "type": "Feature",
  "properties": {
    "addr:full":"607 1st St Melville LA 71353",
    "addr:housenumber":"607",
    "addr:postcode":"71353",
    "addr:street":"1St St",
    "iso:country":"US",
    "sg:address":"607 1st St",
    "sg:city":"Melville",
    "sg:classifiers":[
        {
            "category":"Retail",
            "subcategory":"Funeral Services",
            "type":"Services"
        }
    ],
    "sg:phone":"+1 337 623 5823",
    "sg:postcode":"71353",
    "sg:province":"LA",
    "sg:tags":[
        "director"
    ],
    "wof:name":"Lafond-Ardoin Funeral Home",
    "wof:placetype":"venue"
},
  "geometry": {"coordinates":[-91.744542,30.694675],"type":"Point"}
}