{
  "type": "Feature",
  "properties": {
    "iso:country":"US",
    "sg:address":"8160 US Hwy 190",
    "sg:city":"Opelousas",
    "sg:classifiers":[
        {
            "category":"Freight",
            "type":"Transportation"
        }
    ],
    "sg:phone":"+1 337 543 6731",
    "sg:postcode":"70570",
    "sg:province":"LA",
    "sg:tags":[
        "operator",
        "local",
        "trucking"
    ],
    "wof:name":"Economy Trucking LLC",
    "wof:placetype":"venue"
},
  "geometry": {"coordinates":[-91.963036,30.546246],"type":"Point"}
}