{
  "type": "Feature",
  "properties": {
    "iso:country":"US",
    "sg:address":"2275 Oneal Ln",
    "sg:city":"Baton Rouge",
    "sg:classifiers":[
        {
            "category":"Personal",
            "subcategory":"Beauty Salon",
            "type":"Services"
        }
    ],
    "sg:phone":"+1 225 751 6767",
    "sg:postcode":"70816",
    "sg:province":"LA",
    "wof:name":"Supercuts",
    "wof:placetype":"venue"
},
  "geometry": {"coordinates":[-91.007594,30.438109],"type":"Point"}
}