{
  "type": "Feature",
  "properties": {
    "iso:country":"US",
    "sg:address":"4348 Hwy 19",
    "sg:city":"Zachary",
    "sg:classifiers":[
        {
            "category":"Professional",
            "subcategory":"Accounting & Tax Preparation",
            "type":"Services"
        }
    ],
    "sg:phone":"+1 225 658 0262",
    "sg:postcode":"70791",
    "sg:province":"LA",
    "sg:tags":[
        "accountant"
    ],
    "wof:name":"Dennis Maciasz CPA",
    "wof:placetype":"venue"
},
  "geometry": {"coordinates":[-91.150586,30.646353],"type":"Point"}
}