{
  "type": "Feature",
  "properties": {
    "iso:country":"US",
    "sg:address":"1546 Hwy 190 W",
    "sg:city":"Port Allen",
    "sg:classifiers":[
        {
            "category":"Personal",
            "subcategory":"Massage",
            "type":"Services"
        }
    ],
    "sg:phone":"+1 225 387 1433",
    "sg:postcode":"70767",
    "sg:province":"LA",
    "wof:name":"Oriental Health Spa",
    "wof:placetype":"venue"
},
  "geometry": {"coordinates":[-91.220069,30.505591],"type":"Point"}
}