{
  "type": "Feature",
  "properties": {
    "addr:full":"805 N Parkerson Ave Crowley LA 70526",
    "addr:housenumber":"805",
    "addr:postcode":"70526",
    "addr:street":"N Parkerson Ave",
    "iso:country":"US",
    "sg:address":"805 N Parkerson Ave",
    "sg:city":"Crowley",
    "sg:classifiers":[
        {
            "category":"Banks & Credit Unions",
            "subcategory":"Investment Brokerage",
            "type":"Services"
        }
    ],
    "sg:phone":"+1 337 788 0373",
    "sg:postcode":"70526",
    "sg:province":"LA",
    "sg:tags":[
        "consultant",
        "planning",
        "financial"
    ],
    "wof:name":"Mc Makin Financial Inc",
    "wof:placetype":"venue"
},
  "geometry": {"coordinates":[-92.375809,30.21799],"type":"Point"}
}