{
  "type": "Feature",
  "properties": {
    "addr:full":"334 Lee St Minden LA 71055",
    "addr:housenumber":"334",
    "addr:postcode":"71055",
    "addr:street":"Lee St",
    "iso:country":"US",
    "sg:address":"334 Lee St",
    "sg:city":"Minden",
    "sg:classifiers":[
        {
            "category":"Real Estate",
            "subcategory":"Real Estate Operator",
            "type":"Services"
        }
    ],
    "sg:phone":"+1 318 371 1760",
    "sg:postcode":"71055",
    "sg:province":"LA",
    "sg:tags":[
        "apartment"
    ],
    "wof:name":"Mt Calm Senior Hamlet Svc",
    "wof:placetype":"venue"
},
  "geometry": {"coordinates":[-93.287228,32.611035],"type":"Point"}
}