{
  "type": "Feature",
  "properties": {
    "addr:full":"11224 Pennywood Ave Baton Rouge LA 70809",
    "addr:housenumber":"11224",
    "addr:postcode":"70809",
    "addr:street":"Pennywood Ave",
    "iso:country":"US",
    "sg:address":"11224 Pennywood Ave",
    "sg:city":"Baton Rouge",
    "sg:classifiers":[
        {
            "category":"Building & Trades",
            "subcategory":"Plumbing",
            "type":"Services"
        }
    ],
    "sg:phone":"+1 225 756 0777",
    "sg:postcode":"70809",
    "sg:province":"LA",
    "sg:tags":[
        "conditioning",
        "air",
        "system",
        "contractor"
    ],
    "wof:name":"Keith Kaiser Sales & Svc Inc",
    "wof:placetype":"venue"
},
  "geometry": {"coordinates":[-91.05662100000001,30.392609],"type":"Point"}
}