{
  "type": "Feature",
  "properties": {
    "iso:country":"US",
    "sg:address":"11763 Ferdinand St",
    "sg:city":"St Francisville",
    "sg:classifiers":[
        {
            "category":"Real Estate",
            "subcategory":"Real Estate Agent",
            "type":"Services"
        }
    ],
    "sg:phone":"+1 225 635 4223",
    "sg:postcode":"70775",
    "sg:province":"LA",
    "wof:name":"Smart Real Estate",
    "wof:placetype":"venue"
},
  "geometry": {"coordinates":[-91.383387,30.776912],"type":"Point"}
}