{
  "type": "Feature",
  "properties": {
    "addr:full":"1747 Old Hwy 6 Natchitoches LA 71457",
    "addr:housenumber":"1747",
    "addr:postcode":"71457",
    "addr:street":"Old Hwy 6",
    "iso:country":"US",
    "sg:address":"1747 Old Hwy 6",
    "sg:city":"Natchitoches",
    "sg:classifiers":[
        {
            "category":"Utilities",
            "subcategory":"Refuse",
            "type":"Services"
        }
    ],
    "sg:phone":"+1 318 356 0000",
    "sg:postcode":"71457",
    "sg:province":"LA",
    "sg:tags":[
        "garbage",
        "collection"
    ],
    "wof:name":"IESI",
    "wof:placetype":"venue"
},
  "geometry": {"coordinates":[-93.17073000000001,31.721307],"type":"Point"}
}