{
  "type": "Feature",
  "properties": {
    "iso:country":"US",
    "sg:address":"4649 Apricot St",
    "sg:city":"Metairie",
    "sg:classifiers":[
        {
            "category":"Professional",
            "subcategory":"Computer Services",
            "type":"Services"
        }
    ],
    "sg:phone":"+1 504 756 7195",
    "sg:postcode":"70001",
    "sg:province":"LA",
    "sg:tags":[
        "programing",
        "custom"
    ],
    "wof:name":"Accounting Information Systems",
    "wof:placetype":"venue"
},
  "geometry": {"coordinates":[-90.18340000000001,29.992185],"type":"Point"}
}