{
  "type": "Feature",
  "properties": {
    "iso:country":"US",
    "sg:address":"208 Corona Dr",
    "sg:city":"Lafayette",
    "sg:classifiers":[
        {
            "category":"Professional",
            "type":"Services"
        }
    ],
    "sg:phone":"+1 337 984 8783",
    "sg:postcode":"70503",
    "sg:province":"LA",
    "wof:name":"Professional Environmental",
    "wof:placetype":"venue"
},
  "geometry": {"coordinates":[-92.05540000000001,30.18351],"type":"Point"}
}