{
  "type": "Feature",
  "properties": {
    "addr:full":"159 Mulligan Inn Loop Winnfield LA 71483",
    "addr:housenumber":"159",
    "addr:postcode":"71483",
    "addr:street":"Mulligan Inn Loop Winnfield",
    "iso:country":"US",
    "sg:address":"159 Mulligan Inn Loop",
    "sg:city":"Winnfield",
    "sg:classifiers":[
        {
            "category":"Building & Trades",
            "subcategory":"Plumbing",
            "type":"Services"
        }
    ],
    "sg:phone":"+1 318 727 9582",
    "sg:postcode":"71483",
    "sg:province":"LA",
    "sg:tags":[
        "plumbing",
        "contractor"
    ],
    "wof:name":"Little Plumbing & Utility",
    "wof:placetype":"venue"
},
  "geometry": {"coordinates":[-92.889121,31.880355],"type":"Point"}
}