{
  "type": "Feature",
  "properties": {
    "iso:country":"US",
    "sg:address":"2310 E Madison Ave",
    "sg:city":"Bastrop",
    "sg:classifiers":[
        {
            "category":"Wholesale",
            "subcategory":"Machinery & Supplies",
            "type":"Manufacturing & Wholesale Goods"
        }
    ],
    "sg:phone":"+1 318 281 2781",
    "sg:postcode":"71220",
    "sg:province":"LA",
    "sg:tags":[
        "farm",
        "equipment"
    ],
    "wof:name":"Scott Tractor Co",
    "wof:placetype":"venue"
},
  "geometry": {"coordinates":[-91.882609,32.775952],"type":"Point"}
}