{
  "type": "Feature",
  "properties": {
    "addr:full":"4673 Main St Collinston LA 71229",
    "addr:housenumber":"4673;collinston",
    "addr:postcode":"71229",
    "addr:street":"Main St",
    "iso:country":"US",
    "sg:address":"4673 Main St",
    "sg:city":"Collinston",
    "sg:classifiers":[
        {
            "category":"Organizations",
            "subcategory":"Religious Organization",
            "type":"Services"
        }
    ],
    "sg:phone":"+1 318 874 3631",
    "sg:postcode":"71229",
    "sg:province":"LA",
    "sg:tags":[
        "church"
    ],
    "wof:name":"First Baptist Church",
    "wof:placetype":"venue"
},
  "geometry": {"coordinates":[-91.870941,32.690454],"type":"Point"}
}