{
  "type": "Feature",
  "properties": {
    "addr:full":"1905 W Thomas St Hammond LA 70401",
    "addr:housenumber":"1905",
    "addr:postcode":"70401",
    "addr:street":"W Thomas St",
    "iso:country":"US",
    "sg:address":"1905 W Thomas St",
    "sg:city":"Hammond",
    "sg:classifiers":[
        {
            "category":"Shopping",
            "subcategory":"Clothing, Apparel, & Fashions",
            "type":"Retail Goods"
        }
    ],
    "sg:phone":"+1 985 542 0476",
    "sg:postcode":"70401",
    "sg:province":"LA",
    "wof:name":"Fashion & Beauty Mart",
    "wof:placetype":"venue"
},
  "geometry": {"coordinates":[-90.4811,30.500994],"type":"Point"}
}