{
  "type": "Feature",
  "properties": {
    "addr:full":"7011 Read Ln New Orleans LA 70127",
    "addr:housenumber":"7011",
    "addr:postcode":"70127",
    "addr:street":"Read Ln",
    "iso:country":"US",
    "sg:address":"7011 Read Ln",
    "sg:city":"New Orleans",
    "sg:classifiers":[
        {
            "category":"Personal",
            "subcategory":"Beauty Salon",
            "type":"Services"
        }
    ],
    "sg:phone":"+1 504 241 2411",
    "sg:postcode":"70127",
    "sg:province":"LA",
    "wof:name":"Blessed Hands",
    "wof:placetype":"venue"
},
  "geometry": {"coordinates":[-89.976528,30.039898],"type":"Point"}
}