{
  "type": "Feature",
  "properties": {
    "addr:full":"626 Robert Blvd Slidell LA 70458",
    "addr:housenumber":"626",
    "addr:postcode":"70458",
    "addr:street":"Robert Blvd",
    "iso:country":"US",
    "sg:address":"626 Robert Blvd",
    "sg:city":"Slidell",
    "sg:classifiers":[
        {
            "category":"Insurance",
            "subcategory":"Insurance Agent",
            "type":"Services"
        }
    ],
    "sg:phone":"+1 985 641 1739",
    "sg:postcode":"70458",
    "sg:province":"LA",
    "wof:name":"Allstate Insurance",
    "wof:placetype":"venue"
},
  "geometry": {"coordinates":[-89.76160400000001,30.297068],"type":"Point"}
}