{
  "type": "Feature",
  "properties": {
    "addr:full":"5310 Glouster Rd New Orleans LA 70127",
    "addr:housenumber":"5310",
    "addr:postcode":"70127",
    "addr:street":"Glouster Rd",
    "iso:country":"US",
    "sg:address":"5310 Glouster Rd",
    "sg:city":"New Orleans",
    "sg:classifiers":[
        {
            "category":"Professional",
            "type":"Services"
        }
    ],
    "sg:phone":"+1 504 244 1692",
    "sg:postcode":"70127",
    "sg:province":"LA",
    "wof:name":"Alcide J Bennett",
    "wof:placetype":"venue"
},
  "geometry": {"coordinates":[-89.984915,30.026834],"type":"Point"}
}