{
  "type": "Feature",
  "properties": {
    "iso:country":"US",
    "sg:address":"1539 Jackson Ave",
    "sg:city":"New Orleans",
    "sg:classifiers":[
        {
            "category":"Building & Trades",
            "subcategory":"Construction",
            "type":"Services"
        }
    ],
    "sg:phone":"+1 504 581 7333",
    "sg:postcode":"70130",
    "sg:province":"LA",
    "sg:tags":[
        "residential",
        "industrial"
    ],
    "wof:name":"Angelo Farrell Construction Co",
    "wof:placetype":"venue"
},
  "geometry": {"coordinates":[-90.08014,29.933674],"type":"Point"}
}