{
  "type": "Feature",
  "properties": {
    "iso:country":"US",
    "sg:address":"4321 Eastview Dr",
    "sg:city":"New Orleans",
    "sg:classifiers":[
        {
            "category":"Building & Trades",
            "subcategory":"Construction",
            "type":"Services"
        }
    ],
    "sg:phone":"+1 504 242 5500",
    "sg:postcode":"70126",
    "sg:province":"LA",
    "sg:tags":[
        "painter"
    ],
    "wof:name":"J B Painting Svc",
    "wof:placetype":"venue"
},
  "geometry": {"coordinates":[-89.99212799999999,30.01556],"type":"Point"}
}