{
  "type": "Feature",
  "properties": {
    "iso:country":"US",
    "sg:address":"536 S Main St",
    "sg:city":"Opelousas",
    "sg:classifiers":[
        {
            "category":"Shopping",
            "subcategory":"Hobbies, Toys, & Games",
            "type":"Retail Goods"
        }
    ],
    "sg:phone":"+1 337 942 1271",
    "sg:postcode":"70570",
    "sg:province":"LA",
    "sg:tags":[
        "equipment",
        "ceramic",
        "supply"
    ],
    "wof:name":"Ceramics Plus",
    "wof:placetype":"venue"
},
  "geometry": {"coordinates":[-92.08227599999999,30.52938],"type":"Point"}
}