{
  "type": "Feature",
  "properties": {
    "iso:country":"US",
    "sg:address":"2200 Houma Blvd",
    "sg:city":"Metairie",
    "sg:classifiers":[
        {
            "category":"Real Estate",
            "subcategory":"Architect",
            "type":"Services"
        }
    ],
    "sg:phone":"+1 504 455 8911",
    "sg:postcode":"70001",
    "sg:province":"LA",
    "sg:tags":[
        "architectural"
    ],
    "wof:name":"Ehlinger & Associates",
    "wof:placetype":"venue"
},
  "geometry": {"coordinates":[-90.177909,29.994922],"type":"Point"}
}