{
  "type": "Feature",
  "properties": {
    "iso:country":"US",
    "sg:address":"220 Pico St",
    "sg:city":"Many",
    "sg:classifiers":[
        {
            "category":"Home & Garden",
            "subcategory":"Household Appliances",
            "type":"Retail Goods"
        }
    ],
    "sg:phone":"+1 318 256 9300",
    "sg:postcode":"71449",
    "sg:province":"LA",
    "sg:tags":[
        "cleaners",
        "vacuum"
    ],
    "wof:name":"Coy's Vacuum Cleaners Svc",
    "wof:placetype":"venue"
},
  "geometry": {"coordinates":[-93.487244,31.566852],"type":"Point"}
}