{
  "type": "Feature",
  "properties": {
    "addr:full":"169 S Beadle Rd Lafayette LA 70508",
    "addr:housenumber":"169",
    "addr:postcode":"70508",
    "addr:street":"S Beadle Rd",
    "iso:country":"US",
    "sg:address":"169 S Beadle Rd",
    "sg:city":"Lafayette",
    "sg:classifiers":[
        {
            "category":"Personal",
            "subcategory":"Beauty Salon",
            "type":"Services"
        }
    ],
    "sg:phone":"+1 337 234 9336",
    "sg:postcode":"70508",
    "sg:province":"LA",
    "wof:name":"Theresas Hair & Nail Salon",
    "wof:placetype":"venue"
},
  "geometry": {"coordinates":[-92.018086,30.17687],"type":"Point"}
}