{
  "type": "Feature",
  "properties": {
    "addr:full":"11027 Oak Grove Hwy Mer Rouge LA 71261",
    "addr:housenumber":"11027",
    "addr:postcode":"71261",
    "addr:street":"Oak Grove Hwy Mer",
    "iso:country":"US",
    "sg:address":"11027 Oak Grove Hwy",
    "sg:city":"Mer Rouge",
    "sg:classifiers":[
        {
            "category":"Utilities",
            "subcategory":"Water",
            "type":"Services"
        }
    ],
    "sg:phone":"+1 318 647 5148",
    "sg:postcode":"71261",
    "sg:province":"LA",
    "sg:tags":[
        "system",
        "supply"
    ],
    "wof:name":"Bonne Idee Water System",
    "wof:placetype":"venue"
},
  "geometry": {"coordinates":[-91.733647,32.768707],"type":"Point"}
}