{
  "type": "Feature",
  "properties": {
    "addr:full":"1870 Bayou Blue Rd Houma LA 70364",
    "addr:housenumber":"1870",
    "addr:postcode":"70364",
    "addr:street":"Bayou Blue Rd",
    "iso:country":"US",
    "sg:address":"1870 Bayou Blue Rd",
    "sg:city":"Houma",
    "sg:classifiers":[
        {
            "category":"Government",
            "subcategory":"Fire Station",
            "type":"Public Place"
        }
    ],
    "sg:phone":"+1 985 876 5234",
    "sg:postcode":"70364",
    "sg:province":"LA",
    "sg:tags":[
        "department"
    ],
    "wof:name":"Bayou Blue Volunteer Fire Dept",
    "wof:placetype":"venue"
},
  "geometry": {"coordinates":[-90.683663,29.641901],"type":"Point"}
}