{
  "type": "Feature",
  "properties": {
    "addr:full":"100 Mystic Blvd Houma LA 70360",
    "addr:housenumber":"100",
    "addr:postcode":"70360",
    "addr:street":"Mystic Blvd",
    "iso:country":"US",
    "sg:address":"100 Mystic Blvd",
    "sg:city":"Houma",
    "sg:classifiers":[
        {
            "category":"Insurance",
            "subcategory":"Insurance Agent",
            "type":"Services"
        }
    ],
    "sg:phone":"+1 985 873 5000",
    "sg:postcode":"70360",
    "sg:province":"LA",
    "wof:name":"State Farm Insurance",
    "wof:placetype":"venue"
},
  "geometry": {"coordinates":[-90.74389499999999,29.587694],"type":"Point"}
}