{
  "type": "Feature",
  "properties": {
    "iso:country":"US",
    "sg:address":"919 Celeste St",
    "sg:city":"Lafayette",
    "sg:classifiers":[
        {
            "category":"Shopping",
            "subcategory":"Clothing, Apparel, & Fashions",
            "type":"Retail Goods"
        }
    ],
    "sg:phone":"+1 337 232 0617",
    "sg:postcode":"70501",
    "sg:province":"LA",
    "sg:tags":[
        "shop",
        "bridal"
    ],
    "wof:name":"Creative Accents",
    "wof:placetype":"venue"
},
  "geometry": {"coordinates":[-92.027922,30.239956],"type":"Point"}
}