{
  "type": "Feature",
  "properties": {
    "addr:full":"5523 N Galvez St New Orleans LA 70117",
    "addr:housenumber":"5523",
    "addr:postcode":"70117",
    "addr:street":"N Galvez St",
    "iso:country":"US",
    "sg:address":"5523 N Galvez St",
    "sg:city":"New Orleans",
    "sg:classifiers":[
        {
            "category":"Food & Beverages",
            "subcategory":"Groceries & Convenience Stores",
            "type":"Retail Goods"
        }
    ],
    "sg:phone":"+1 504 944 5563",
    "sg:postcode":"70117",
    "sg:province":"LA",
    "sg:tags":[
        "grocer"
    ],
    "wof:name":"T & T Grocery Inc",
    "wof:placetype":"venue"
},
  "geometry": {"coordinates":[-90.012715,29.971552],"type":"Point"}
}