{
  "type": "Feature",
  "properties": {
    "addr:full":"1829 N Airline Hwy Gonzales LA 70737",
    "addr:housenumber":"1829",
    "addr:postcode":"70737",
    "addr:street":"N Airline Hwy Gonzales La",
    "iso:country":"US",
    "sg:address":"1829 N Airline Hwy",
    "sg:city":"Gonzales",
    "sg:classifiers":[
        {
            "category":"Restaurant",
            "type":"Food & Drink"
        }
    ],
    "sg:phone":"+1 225 647 9442",
    "sg:postcode":"70737",
    "sg:province":"LA",
    "sg:tags":[
        "eating"
    ],
    "wof:name":"Domino's Pizza",
    "wof:placetype":"venue"
},
  "geometry": {"coordinates":[-90.92219799999999,30.247612],"type":"Point"}
}