{
  "type": "Feature",
  "properties": {
    "iso:country":"US",
    "sg:address":"4640 S Carrollton Ave",
    "sg:city":"New Orleans",
    "sg:classifiers":[
        {
            "category":"Utilities",
            "subcategory":"Telephone",
            "type":"Services"
        }
    ],
    "sg:phone":"+1 504 488 5401",
    "sg:postcode":"70119",
    "sg:province":"LA",
    "sg:tags":[
        "telecommunication"
    ],
    "sg:website":"www.quad.com",
    "wof:name":"Quad.Com Telecommunications",
    "wof:placetype":"venue"
},
  "geometry": {"coordinates":[-90.101704,29.973267],"type":"Point"}
}