{
  "type": "Feature",
  "properties": {
    "iso:country":"US",
    "sg:address":"13580 Coursey Blvd",
    "sg:city":"Baton Rouge",
    "sg:classifiers":[
        {
            "category":"Personal",
            "subcategory":"Beauty Salon",
            "type":"Services"
        }
    ],
    "sg:phone":"+1 225 751 6626",
    "sg:postcode":"70816",
    "sg:province":"LA",
    "wof:name":"U Know",
    "wof:placetype":"venue"
},
  "geometry": {"coordinates":[-91.031913,30.408909],"type":"Point"}
}