{
  "type": "Feature",
  "properties": {
    "addr:full":"333 Canal St New Orleans LA 70130",
    "addr:housenumber":"333",
    "addr:postcode":"70130",
    "addr:street":"Canal St",
    "iso:country":"US",
    "sg:address":"333 Canal St",
    "sg:city":"New Orleans",
    "sg:classifiers":[
        {
            "category":"Restaurant",
            "type":"Food & Drink"
        }
    ],
    "sg:menulink":"http://www.allmenus.com/la/new-orleans/72417-sbarro/menu/",
    "sg:phone":"+1 504 581 9943",
    "sg:postcode":"70130",
    "sg:province":"LA",
    "sg:tags":[
        "american",
        "pizza"
    ],
    "wof:name":"Sbarro",
    "wof:placetype":"venue"
},
  "geometry": {"coordinates":[-90.065659,29.950989],"type":"Point"}
}