{
  "type": "Feature",
  "properties": {
    "iso:country":"US",
    "sg:address":"3009 Desoto St",
    "sg:city":"Monroe",
    "sg:classifiers":[
        {
            "category":"Communications",
            "type":"Services"
        }
    ],
    "sg:phone":"+1 318 323 8616",
    "sg:postcode":"71201",
    "sg:province":"LA",
    "wof:name":"LDS Communications",
    "wof:placetype":"venue"
},
  "geometry": {"coordinates":[-92.089409,32.53032],"type":"Point"}
}