{
  "type": "Feature",
  "properties": {
    "addr:full":"12537 Scenic Hwy Baton Rouge LA 70807",
    "addr:housenumber":"12537",
    "addr:postcode":"70807",
    "addr:street":"Scenic Hwy",
    "iso:country":"US",
    "sg:address":"12537 Scenic Hwy",
    "sg:city":"Baton Rouge",
    "sg:classifiers":[
        {
            "category":"Manufacturing",
            "subcategory":"Glass & Minerals",
            "type":"Manufacturing & Wholesale Goods"
        }
    ],
    "sg:phone":"+1 225 774 4201",
    "sg:postcode":"70807",
    "sg:province":"LA",
    "sg:tags":[
        "lime"
    ],
    "wof:name":"Pelican State Lime",
    "wof:placetype":"venue"
},
  "geometry": {"coordinates":[-91.203513,30.561674],"type":"Point"}
}