{
  "type": "Feature",
  "properties": {
    "iso:country":"US",
    "sg:address":"2100 NE Evangeline Trwy",
    "sg:city":"Lafayette",
    "sg:classifiers":[
        {
            "category":"Travel",
            "subcategory":"Hotels & Motels",
            "type":"Entertainment"
        }
    ],
    "sg:phone":"+1 337 233 5610",
    "sg:postcode":"70501",
    "sg:province":"LA",
    "wof:name":"La Quinta",
    "wof:placetype":"venue"
},
  "geometry": {"coordinates":[-92.013397,30.249901],"type":"Point"}
}