{
  "type": "Feature",
  "properties": {
    "iso:country":"US",
    "sg:address":"5224 Florida Blvd",
    "sg:city":"Baton Rouge",
    "sg:classifiers":[
        {
            "category":"Restaurant",
            "type":"Food & Drink"
        }
    ],
    "sg:menulink":"http://www.allmenus.com/la/baton-rouge/188264-mcdonalds/menu/",
    "sg:postcode":"70806",
    "sg:province":"LA",
    "sg:tags":[
        "burger",
        "american"
    ],
    "wof:name":"McDonald's",
    "wof:placetype":"venue"
},
  "geometry": {"coordinates":[-91.13577100000001,30.450524],"type":"Point"}
}