{
  "type": "Feature",
  "properties": {
    "iso:country":"US",
    "sg:address":"17425 Dogwood Trl",
    "sg:city":"Tickfaw",
    "sg:classifiers":[
        {
            "category":"Professional",
            "subcategory":"Business Services",
            "type":"Services"
        }
    ],
    "sg:phone":"+1 985 542 1047",
    "sg:postcode":"70466",
    "sg:province":"LA",
    "wof:name":"Tardign It Solutions",
    "wof:placetype":"venue"
},
  "geometry": {"coordinates":[-90.437456,30.586399],"type":"Point"}
}