{
  "type": "Feature",
  "properties": {
    "iso:country":"US",
    "sg:address":"4947 W Napoleon Ave",
    "sg:city":"Metairie",
    "sg:classifiers":[
        {
            "category":"Restaurant",
            "type":"Food & Drink"
        }
    ],
    "sg:phone":"+1 504 309 7300",
    "sg:postcode":"70001",
    "sg:province":"LA",
    "sg:tags":[
        "caterer"
    ],
    "wof:name":"Good Food To You",
    "wof:placetype":"venue"
},
  "geometry": {"coordinates":[-90.19273200000001,29.994739],"type":"Point"}
}