{
  "type": "Feature",
  "properties": {
    "iso:country":"US",
    "sg:address":"153 Douglas Dr",
    "sg:city":"Houma",
    "sg:classifiers":[
        {
            "category":"Professional",
            "type":"Services"
        }
    ],
    "sg:phone":"+1 985 868 2328",
    "sg:postcode":"70364",
    "sg:province":"LA",
    "wof:name":"Concerned Clergy and Laity of",
    "wof:placetype":"venue"
},
  "geometry": {"coordinates":[-90.75251900000001,29.628829],"type":"Point"}
}