{
  "type": "Feature",
  "properties": {
    "addr:full":"5105 W Napoleon Ave Metairie LA 70001",
    "addr:housenumber":"5105",
    "addr:postcode":"70001",
    "addr:street":"W Napoleon Ave",
    "iso:country":"US",
    "sg:address":"5105 W Napoleon Ave",
    "sg:city":"Metairie",
    "sg:classifiers":[
        {
            "category":"Building & Trades",
            "subcategory":"Plumbing",
            "type":"Services"
        }
    ],
    "sg:phone":"+1 504 887 8911",
    "sg:postcode":"70001",
    "sg:province":"LA",
    "sg:tags":[
        "leak",
        "detecting"
    ],
    "wof:name":"Accurate Leak Detection",
    "wof:placetype":"venue"
},
  "geometry": {"coordinates":[-90.193693,29.994868],"type":"Point"}
}