{
  "type": "Feature",
  "properties": {
    "addr:full":"1816 N Claiborne Ave New Orleans LA 70116",
    "addr:housenumber":"1816",
    "addr:postcode":"70116",
    "addr:street":"N Claiborne Ave",
    "iso:country":"US",
    "sg:address":"1816 N Claiborne Ave",
    "sg:city":"New Orleans",
    "sg:classifiers":[
        {
            "category":"Real Estate",
            "subcategory":"Real Estate Services",
            "type":"Services"
        }
    ],
    "sg:phone":"+1 504 940 2192",
    "sg:postcode":"70116",
    "sg:province":"LA",
    "sg:tags":[
        "management",
        "property"
    ],
    "wof:name":"Elite Property Management",
    "wof:placetype":"venue"
},
  "geometry": {"coordinates":[-90.06119099999999,29.972891],"type":"Point"}
}