{
  "type": "Feature",
  "properties": {
    "addr:full":"4031 N University Ave Carencro LA 70520",
    "addr:housenumber":"4031",
    "addr:postcode":"70520",
    "addr:street":"N University Ave",
    "iso:country":"US",
    "sg:address":"4031 N University Ave",
    "sg:city":"Carencro",
    "sg:classifiers":[
        {
            "category":"Restaurant",
            "type":"Food & Drink"
        }
    ],
    "sg:menulink":"http://www.allmenus.com/la/carencro/201447-sonic/menu/",
    "sg:phone":"+1 337 896 7552",
    "sg:postcode":"70520",
    "sg:province":"LA",
    "sg:tags":[
        "burger",
        "american"
    ],
    "wof:name":"Sonic",
    "wof:placetype":"venue"
},
  "geometry": {"coordinates":[-92.04943400000001,30.303043],"type":"Point"}
}