{
  "type": "Feature",
  "properties": {
    "iso:country":"US",
    "sg:address":"740 Clouet St",
    "sg:city":"New Orleans",
    "sg:classifiers":[
        {
            "category":"Manufacturing",
            "subcategory":"Apparel",
            "type":"Manufacturing & Wholesale Goods"
        }
    ],
    "sg:phone":"+1 504 943 0123",
    "sg:postcode":"70117",
    "sg:province":"LA",
    "sg:tags":[
        "bag",
        "canvas"
    ],
    "sg:website":"www.kalencom.com",
    "wof:name":"Kalencom Corp",
    "wof:placetype":"venue"
},
  "geometry": {"coordinates":[-90.04534099999999,29.964089],"type":"Point"}
}