{
  "type": "Feature",
  "properties": {
    "iso:country":"US",
    "sg:address":"948 Cambridge Dr",
    "sg:city":"La Place",
    "sg:classifiers":[
        {
            "category":"Health Services",
            "subcategory":"Hospital",
            "type":"Services"
        }
    ],
    "sg:phone":"+1 985 652 0025",
    "sg:postcode":"70068",
    "sg:province":"LA",
    "sg:tags":[
        "mental"
    ],
    "wof:name":"Professional Healthcare Svc",
    "wof:placetype":"venue"
},
  "geometry": {"coordinates":[-90.48522800000001,30.072018],"type":"Point"}
}