{
  "type": "Feature",
  "properties": {
    "iso:country":"US",
    "sg:address":"5713 Johnston St",
    "sg:city":"Lafayette",
    "sg:classifiers":[
        {
            "category":"Restaurant",
            "type":"Food & Drink"
        }
    ],
    "sg:menulink":"http://www.allmenus.com/la/broadmoor/229643-tampico-mexican-restaurant--cantina/menu/",
    "sg:phone":"+1 337 988 0102",
    "sg:postcode":"70503",
    "sg:province":"LA",
    "sg:tags":[
        "american"
    ],
    "wof:name":"Tampico Mexican Restaurant & Cantina",
    "wof:placetype":"venue"
},
  "geometry": {"coordinates":[-92.07752600000001,30.174951],"type":"Point"}
}