{
  "type": "Feature",
  "properties": {
    "addr:full":"5612 Jackson St Exd Alexandria LA 71303",
    "addr:housenumber":"5612",
    "addr:postcode":"71303",
    "addr:street":"Jackson St Exd",
    "iso:country":"US",
    "sg:address":"5612 Jackson St Exd",
    "sg:city":"Alexandria",
    "sg:classifiers":[
        {
            "category":"Insurance",
            "subcategory":"Insurance Agent",
            "type":"Services"
        }
    ],
    "sg:phone":"+1 318 487 0095",
    "sg:postcode":"71303",
    "sg:province":"LA",
    "wof:name":"New York Life Insurance Co",
    "wof:placetype":"venue"
},
  "geometry": {"coordinates":[-92.48649,31.268757],"type":"Point"}
}