{
  "type": "Feature",
  "properties": {
    "iso:country":"US",
    "sg:address":"320 S Cities Service Hwy",
    "sg:city":"Sulphur",
    "sg:classifiers":[
        {
            "category":"Travel",
            "subcategory":"Hotels & Motels",
            "type":"Entertainment"
        }
    ],
    "sg:phone":"+1 337 626 7000",
    "sg:postcode":"70663",
    "sg:province":"LA",
    "wof:name":"Comfort Inn",
    "wof:placetype":"venue"
},
  "geometry": {"coordinates":[-93.325526,30.220192],"type":"Point"}
}