{
  "type": "Feature",
  "properties": {
    "iso:country":"US",
    "sg:address":"3209 E Judge Perez Dr",
    "sg:city":"Meraux",
    "sg:classifiers":[
        {
            "category":"Autos & Motor Vehicles",
            "subcategory":"Recreational Vehicle Sales",
            "type":"Retail Goods"
        }
    ],
    "sg:phone":"+1 504 271 2836",
    "sg:postcode":"70075",
    "sg:province":"LA",
    "wof:name":"Steves Rv Ctr Inc",
    "wof:placetype":"venue"
},
  "geometry": {"coordinates":[-89.92867,29.937316],"type":"Point"}
}