{
  "type": "Feature",
  "properties": {
    "iso:country":"US",
    "sg:address":"24677 Abernathy Rd",
    "sg:city":"Springfield",
    "sg:classifiers":[
        {
            "category":"Wholesale",
            "subcategory":"Durable Goods & Equipment",
            "type":"Manufacturing & Wholesale Goods"
        }
    ],
    "sg:phone":"+1 225 294 6445",
    "sg:postcode":"70462",
    "sg:province":"LA",
    "sg:tags":[
        "compact",
        "record",
        "disc",
        "tape"
    ],
    "wof:name":"Set-Fire Records",
    "wof:placetype":"venue"
},
  "geometry": {"coordinates":[-90.57273499999999,30.426569],"type":"Point"}
}