{
  "type": "Feature",
  "properties": {
    "iso:country":"US",
    "sg:address":"1455 Hwy 15",
    "sg:city":"West Monroe",
    "sg:classifiers":[
        {
            "category":"Autos & Motor Vehicles",
            "subcategory":"Automobile Sales",
            "type":"Retail Goods"
        }
    ],
    "sg:phone":"+1 318 388 1989",
    "sg:postcode":"71291",
    "sg:province":"LA",
    "sg:tags":[
        "used"
    ],
    "wof:name":"Jerry Used Cars",
    "wof:placetype":"venue"
},
  "geometry": {"coordinates":[-92.24531899999999,32.546015],"type":"Point"}
}