{
  "type": "Feature",
  "properties": {
    "addr:full":"705 W Pinhook Rd Lafayette LA 70503",
    "addr:housenumber":"705",
    "addr:postcode":"70503",
    "addr:street":"W Pinhook Rd",
    "iso:country":"US",
    "sg:address":"705 W Pinhook Rd",
    "sg:city":"Lafayette",
    "sg:classifiers":[
        {
            "category":"Professional",
            "subcategory":"Management & Consulting",
            "type":"Services"
        }
    ],
    "sg:phone":"+1 337 237 2923",
    "sg:postcode":"70503",
    "sg:province":"LA",
    "sg:tags":[
        "field",
        "oil",
        "consultant"
    ],
    "wof:name":"Chalmers Collins & Alwell Inc",
    "wof:placetype":"venue"
},
  "geometry": {"coordinates":[-92.012085,30.20643],"type":"Point"}
}