{
  "type": "Feature",
  "properties": {
    "iso:country":"US",
    "sg:address":"1105 State Rte 30",
    "sg:city":"St Gabriel",
    "sg:classifiers":[
        {
            "category":"Utilities",
            "subcategory":"Refuse",
            "type":"Services"
        }
    ],
    "sg:phone":"+1 225 642 9621",
    "sg:postcode":"70776",
    "sg:province":"LA",
    "sg:tags":[
        "waste",
        "container"
    ],
    "wof:name":"Material Containment Inc",
    "wof:placetype":"venue"
},
  "geometry": {"coordinates":[-91.118652,30.300309],"type":"Point"}
}