{
  "type": "Feature",
  "properties": {
    "iso:country":"US",
    "sg:address":"29825 Hwy 21",
    "sg:city":"Angie",
    "sg:classifiers":[
        {
            "category":"Organizations",
            "subcategory":"Religious Organization",
            "type":"Services"
        }
    ],
    "sg:phone":"+1 985 986 2546",
    "sg:postcode":"70426",
    "sg:province":"LA",
    "sg:tags":[
        "church"
    ],
    "wof:name":"Center Baptist Church",
    "wof:placetype":"venue"
},
  "geometry": {"coordinates":[-89.81289200000001,30.957328],"type":"Point"}
}