{
  "type": "Feature",
  "properties": {
    "addr:full":"2008 Roselawn Ave Monroe LA 71201",
    "addr:housenumber":"2008",
    "addr:postcode":"71201",
    "addr:street":"Roselawn Ave",
    "iso:country":"US",
    "sg:address":"2008 Roselawn Ave",
    "sg:city":"Monroe",
    "sg:classifiers":[
        {
            "category":"Professional",
            "type":"Services"
        }
    ],
    "sg:phone":"+1 318 323 8186",
    "sg:postcode":"71201",
    "sg:province":"LA",
    "sg:tags":[
        "establishment"
    ],
    "wof:name":"Hannum & Co",
    "wof:placetype":"venue"
},
  "geometry": {"coordinates":[-92.10482,32.523316],"type":"Point"}
}