{
  "type": "Feature",
  "properties": {
    "iso:country":"US",
    "sg:address":"517 W Simcoe St",
    "sg:city":"Lafayette",
    "sg:classifiers":[
        {
            "category":"Wholesale",
            "subcategory":"Durable Goods & Equipment",
            "type":"Manufacturing & Wholesale Goods"
        },
        {
            "category":"Shopping",
            "subcategory":"Music",
            "type":"Retail Goods"
        }
    ],
    "sg:phone":"+1 337 234 6231",
    "sg:postcode":"70501",
    "sg:province":"LA",
    "sg:tags":[
        "compact",
        "record",
        "disc",
        "tape"
    ],
    "wof:name":"House Rockers Records Shop",
    "wof:placetype":"venue"
},
  "geometry": {"coordinates":[-92.021694,30.23047],"type":"Point"}
}