{
  "type": "Feature",
  "properties": {
    "addr:full":"2131 Canal St New Orleans LA 70112",
    "addr:housenumber":"2131",
    "addr:postcode":"70112",
    "addr:street":"Canal St",
    "iso:country":"US",
    "sg:address":"2131 Canal St",
    "sg:city":"New Orleans",
    "sg:classifiers":[
        {
            "category":"Banks & Credit Unions",
            "subcategory":"Bank",
            "type":"Services"
        }
    ],
    "sg:phone":"+1 504 523 6669",
    "sg:postcode":"70112",
    "sg:province":"LA",
    "sg:tags":[
        "cashing",
        "check"
    ],
    "wof:name":"Money Mart",
    "wof:placetype":"venue"
},
  "geometry": {"coordinates":[-90.082043,29.961744],"type":"Point"}
}