{
  "type": "Feature",
  "properties": {
    "addr:full":"2018 Gus Kaplan Dr Alexandria LA 71301",
    "addr:housenumber":"2018",
    "addr:postcode":"71301",
    "addr:street":"Gus Kaplan Dr",
    "iso:country":"US",
    "sg:address":"2018 Gus Kaplan Dr",
    "sg:city":"Alexandria",
    "sg:classifiers":[
        {
            "category":"Personal",
            "subcategory":"Tanning Parlor",
            "type":"Services"
        }
    ],
    "sg:phone":"+1 318 442 0900",
    "sg:postcode":"71301",
    "sg:province":"LA",
    "sg:tags":[
        "salon"
    ],
    "wof:name":"Nu-Weigh Tan & Tone",
    "wof:placetype":"venue"
},
  "geometry": {"coordinates":[-92.472919,31.274876],"type":"Point"}
}