{
  "type": "Feature",
  "properties": {
    "iso:country":"US",
    "sg:address":"2001 Main St",
    "sg:city":"Franklinton",
    "sg:classifiers":[
        {
            "category":"Professional",
            "subcategory":"Business Services",
            "type":"Services"
        }
    ],
    "sg:phone":"+1 985 839 4050",
    "sg:postcode":"70438",
    "sg:province":"LA",
    "sg:tags":[
        "shop",
        "gift",
        "monogramming"
    ],
    "wof:name":"Monograms Plus",
    "wof:placetype":"venue"
},
  "geometry": {"coordinates":[-90.151859,30.834976],"type":"Point"}
}