{
  "type": "Feature",
  "properties": {
    "iso:country":"US",
    "sg:address":"4949 Essen Ln",
    "sg:city":"Baton Rouge",
    "sg:classifiers":[
        {
            "category":"Professional",
            "subcategory":"Advertising",
            "type":"Services"
        }
    ],
    "sg:phone":"+1 225 769 3090",
    "sg:postcode":"70809",
    "sg:province":"LA",
    "sg:tags":[
        "guide"
    ],
    "sg:website":"www.bellsouthrealpages.com",
    "wof:name":"BELLSOUTHREALPAGES.COM",
    "wof:placetype":"venue"
},
  "geometry": {"coordinates":[-91.104877,30.40278],"type":"Point"}
}