{
  "type": "Feature",
  "properties": {
    "iso:country":"US",
    "sg:address":"59080 N Pearl Dr",
    "sg:city":"Slidell",
    "sg:classifiers":[
        {
            "category":"Personal",
            "subcategory":"Beauty Salon",
            "type":"Services"
        }
    ],
    "sg:phone":"+1 985 781 1991",
    "sg:postcode":"70461",
    "sg:province":"LA",
    "wof:name":"Cosmo Salon",
    "wof:placetype":"venue"
},
  "geometry": {"coordinates":[-89.73614499999999,30.286852],"type":"Point"}
}