{
  "type": "Feature",
  "properties": {
    "addr:full":"18583 S Harrells Ferry Rd Baton Rouge LA 70816",
    "addr:housenumber":"18583",
    "addr:postcode":"70816",
    "addr:street":"S Harrells Ferry Rd",
    "iso:country":"US",
    "sg:address":"18583 S Harrells Ferry Rd",
    "sg:city":"Baton Rouge",
    "sg:classifiers":[
        {
            "category":"Home & Garden",
            "subcategory":"Home Furnishings",
            "type":"Retail Goods"
        }
    ],
    "sg:phone":"+1 225 751 3646",
    "sg:postcode":"70816",
    "sg:province":"LA",
    "sg:tags":[
        "curtain",
        "made",
        "drapery"
    ],
    "wof:name":"Cleveland's House Of Draperies",
    "wof:placetype":"venue"
},
  "geometry": {"coordinates":[-90.98042100000001,30.418708],"type":"Point"}
}