{
  "type": "Feature",
  "properties": {
    "addr:full":"503 N Walnut St Opelousas LA 70570",
    "addr:housenumber":"503",
    "addr:postcode":"70570",
    "addr:street":"N Walnut St",
    "iso:country":"US",
    "sg:address":"503 N Walnut St",
    "sg:city":"Opelousas",
    "sg:classifiers":[
        {
            "category":"Social Services",
            "subcategory":"Child Care",
            "type":"Services"
        }
    ],
    "sg:phone":"+1 337 943 1900",
    "sg:postcode":"70570",
    "sg:province":"LA",
    "wof:name":"First Steps Developmental Ctr",
    "wof:placetype":"venue"
},
  "geometry": {"coordinates":[-92.079166,30.536612],"type":"Point"}
}