{
  "type": "Feature",
  "properties": {
    "addr:full":"2766 Belle Chasse Hwy Terrytown LA 70056",
    "addr:housenumber":"2766",
    "addr:postcode":"70056",
    "addr:street":"Belle Chasse Hwy",
    "iso:country":"US",
    "sg:address":"2766 Belle Chasse Hwy",
    "sg:city":"Terrytown",
    "sg:classifiers":[
        {
            "category":"Bars & Pubs",
            "type":"Food & Drink"
        }
    ],
    "sg:phone":"+1 504 393 0155",
    "sg:postcode":"70056",
    "sg:province":"LA",
    "wof:name":"Vinnie's Sports Bar & Grill",
    "wof:placetype":"venue"
},
  "geometry": {"coordinates":[-90.04749,29.901249],"type":"Point"}
}