{
  "type": "Feature",
  "properties": {
    "addr:full":"585 Terry Pkwy Terrytown LA 70056",
    "addr:housenumber":"585",
    "addr:postcode":"70056",
    "addr:street":"Terry Pkwy",
    "iso:country":"US",
    "sg:address":"585 Terry Pkwy",
    "sg:city":"Terrytown",
    "sg:classifiers":[
        {
            "category":"Autos & Motor Vehicles",
            "subcategory":"Fuel & Gas Station",
            "type":"Retail Goods"
        }
    ],
    "sg:phone":"+1 504 366 9755",
    "sg:postcode":"70056",
    "sg:province":"LA",
    "wof:name":"One #1 Discount",
    "wof:placetype":"venue"
},
  "geometry": {"coordinates":[-90.02984499999999,29.904306],"type":"Point"}
}