{
  "type": "Feature",
  "properties": {
    "iso:country":"US",
    "sg:address":"114 S Cities Service Hwy",
    "sg:city":"Sulphur",
    "sg:classifiers":[
        {
            "category":"Autos & Motor Vehicles",
            "subcategory":"Recreational Vehicle Sales",
            "type":"Retail Goods"
        }
    ],
    "sg:phone":"+1 337 626 9225",
    "sg:postcode":"70663",
    "sg:province":"LA",
    "sg:tags":[
        "parts",
        "trailer"
    ],
    "wof:name":"Zack's Pro Truck & Trailer",
    "wof:placetype":"venue"
},
  "geometry": {"coordinates":[-93.325587,30.227129],"type":"Point"}
}