{
  "type": "Feature",
  "properties": {
    "addr:full":"202 Miller St Vidalia LA 71373",
    "addr:housenumber":"202",
    "addr:postcode":"71373",
    "addr:street":"Miller St",
    "iso:country":"US",
    "sg:address":"202 Miller St",
    "sg:city":"Vidalia",
    "sg:classifiers":[
        {
            "category":"Personal",
            "subcategory":"Barber",
            "type":"Services"
        }
    ],
    "sg:phone":"+1 318 336 5618",
    "sg:postcode":"71373",
    "sg:province":"LA",
    "sg:tags":[
        "shop"
    ],
    "wof:name":"Rickies Style Box",
    "wof:placetype":"venue"
},
  "geometry": {"coordinates":[-91.428211,31.564437],"type":"Point"}
}