{
  "type": "Feature",
  "properties": {
    "iso:country":"US",
    "sg:address":"650 Wooddale Blvd",
    "sg:city":"Baton Rouge",
    "sg:classifiers":[
        {
            "category":"Communications",
            "subcategory":"Radio Station",
            "type":"Services"
        }
    ],
    "sg:phone":"+1 225 499 0937",
    "sg:postcode":"70806",
    "sg:province":"LA",
    "sg:tags":[
        "company",
        "broadcasting"
    ],
    "wof:name":"KOOL",
    "wof:placetype":"venue"
},
  "geometry": {"coordinates":[-91.104218,30.452413],"type":"Point"}
}