{
  "type": "Feature",
  "properties": {
    "addr:full":"3616 Bayou Rd St Bernard LA 70085",
    "addr:housenumber":"3616",
    "addr:postcode":"70085",
    "addr:street":"Bayou Rd",
    "iso:country":"US",
    "sg:address":"3616 Bayou Rd",
    "sg:city":"St Bernard",
    "sg:classifiers":[
        {
            "category":"Professional",
            "type":"Services"
        },
        {
            "category":"Government",
            "subcategory":"Office",
            "type":"Public Place"
        }
    ],
    "sg:phone":"+1 504 682 0591",
    "sg:postcode":"70085",
    "sg:province":"LA",
    "sg:tags":[
        "management",
        "resource",
        "solid",
        "water",
        "waste",
        "establishment"
    ],
    "wof:name":"Lake Bornge Basin Levee Dist",
    "wof:placetype":"venue"
},
  "geometry": {"coordinates":[-89.781567,29.862675],"type":"Point"}
}