{
  "type": "Feature",
  "properties": {
    "addr:full":"4935 W Monkhouse Dr Shreveport LA 71109",
    "addr:housenumber":"4935",
    "addr:postcode":"71109",
    "addr:street":"W Monkhouse Dr",
    "iso:country":"US",
    "sg:address":"4935 W Monkhouse Dr",
    "sg:city":"Shreveport",
    "sg:classifiers":[
        {
            "category":"Travel",
            "subcategory":"Hotels & Motels",
            "type":"Entertainment"
        }
    ],
    "sg:phone":"+1 318 636 0080",
    "sg:postcode":"71109",
    "sg:province":"LA",
    "wof:name":"Days Inn",
    "wof:placetype":"venue"
},
  "geometry": {"coordinates":[-93.830536,32.462369],"type":"Point"}
}