{
  "type": "Feature",
  "properties": {
    "iso:country":"US",
    "sg:address":"70 Shoemaker Ln",
    "sg:city":"Marthaville",
    "sg:classifiers":[
        {
            "category":"Building & Trades",
            "subcategory":"Construction",
            "type":"Services"
        }
    ],
    "sg:phone":"+1 318 256 0430",
    "sg:postcode":"71450",
    "sg:province":"LA",
    "wof:name":"Anita Shoemaker",
    "wof:placetype":"venue"
},
  "geometry": {"coordinates":[-93.46249,31.720471],"type":"Point"}
}