{
  "type": "Feature",
  "properties": {
    "iso:country":"US",
    "sg:address":"9315 Cortana Pl",
    "sg:city":"Baton Rouge",
    "sg:classifiers":[
        {
            "category":"Shopping",
            "subcategory":"Gifts & Souvenirs",
            "type":"Retail Goods"
        }
    ],
    "sg:phone":"+1 225 927 0233",
    "sg:postcode":"70815",
    "sg:province":"LA",
    "sg:tags":[
        "shop"
    ],
    "wof:name":"Fragrance Shop",
    "wof:placetype":"venue"
},
  "geometry": {"coordinates":[-91.094801,30.460742],"type":"Point"}
}