{
  "type": "Feature",
  "properties": {
    "iso:country":"US",
    "sg:address":"41049 State Rte 42",
    "sg:city":"Prairieville",
    "sg:classifiers":[
        {
            "category":"Autos & Motor Vehicles",
            "subcategory":"Auto Supplies",
            "type":"Retail Goods"
        }
    ],
    "sg:phone":"+1 225 622 6272",
    "sg:postcode":"70769",
    "sg:province":"LA",
    "sg:tags":[
        "automobile",
        "parts"
    ],
    "wof:name":"Carquest Auto Parts",
    "wof:placetype":"venue"
},
  "geometry": {"coordinates":[-90.92133,30.324316],"type":"Point"}
}