{
  "type": "Feature",
  "properties": {
    "addr:full":"503 Soniat St New Orleans LA 70115",
    "addr:housenumber":"503",
    "addr:postcode":"70115",
    "addr:street":"Soniat St",
    "iso:country":"US",
    "sg:address":"503 Soniat St",
    "sg:city":"New Orleans",
    "sg:classifiers":[
        {
            "category":"Local Transit",
            "type":"Transportation"
        }
    ],
    "sg:phone":"+1 504 269 5466",
    "sg:postcode":"70115",
    "sg:province":"LA",
    "sg:tags":[
        "limousine"
    ],
    "sg:website":"www.american-limo.com",
    "wof:name":"American Luxury Limousines",
    "wof:placetype":"venue"
},
  "geometry": {"coordinates":[-90.110108,29.917482],"type":"Point"}
}