{
  "type": "Feature",
  "properties": {
    "iso:country":"US",
    "sg:address":"3601 N University Ave",
    "sg:city":"Carencro",
    "sg:classifiers":[
        {
            "category":"Bars & Pubs",
            "subcategory":"Nightclub",
            "type":"Food & Drink"
        }
    ],
    "sg:phone":"+1 337 896 0539",
    "sg:postcode":"70520",
    "sg:province":"LA",
    "sg:tags":[
        "nightlife"
    ],
    "wof:name":"Wrangler's",
    "wof:placetype":"venue"
},
  "geometry": {"coordinates":[-92.04940000000001,30.298201],"type":"Point"}
}