{
  "type": "Feature",
  "properties": {
    "iso:country":"US",
    "sg:address":"1814 N Morrison Blvd",
    "sg:city":"Hammond",
    "sg:classifiers":[
        {
            "category":"Insurance",
            "subcategory":"Insurance Agent",
            "type":"Services"
        }
    ],
    "sg:phone":"+1 985 345 2186",
    "sg:postcode":"70401",
    "sg:province":"LA",
    "wof:name":"Western-Southern Life Ins Co",
    "wof:placetype":"venue"
},
  "geometry": {"coordinates":[-90.482702,30.518581],"type":"Point"}
}