{
  "type": "Feature",
  "properties": {
    "iso:country":"US",
    "sg:address":"3440 Division St",
    "sg:city":"Metairie",
    "sg:classifiers":[
        {
            "category":"Wholesale",
            "subcategory":"Hardware",
            "type":"Manufacturing & Wholesale Goods"
        }
    ],
    "sg:phone":"+1 504 885 3738",
    "sg:postcode":"70002",
    "sg:province":"LA",
    "sg:tags":[
        "plumbing",
        "fixture",
        "supply"
    ],
    "wof:name":"Maxplumb Parts LLC",
    "wof:placetype":"venue"
},
  "geometry": {"coordinates":[-90.164644,30.00629],"type":"Point"}
}