{
  "type": "Feature",
  "properties": {
    "addr:full":"1426 Tiger Dr Thibodaux LA 70301",
    "addr:housenumber":"1426",
    "addr:postcode":"70301",
    "addr:street":"Tiger Dr",
    "iso:country":"US",
    "sg:address":"1426 Tiger Dr",
    "sg:city":"Thibodaux",
    "sg:classifiers":[
        {
            "category":"Travel",
            "subcategory":"Hotels & Motels",
            "type":"Entertainment"
        }
    ],
    "sg:phone":"+1 985 447 2633",
    "sg:postcode":"70301",
    "sg:province":"LA",
    "sg:tags":[
        "operation"
    ],
    "wof:name":"Jungle Casino",
    "wof:placetype":"venue"
},
  "geometry": {"coordinates":[-90.84214900000001,29.773965],"type":"Point"}
}