{
  "type": "Feature",
  "properties": {
    "addr:full":"1901 Jefferson Hwy New Orleans LA 70121",
    "addr:housenumber":"1901",
    "addr:postcode":"70121",
    "addr:street":"Jefferson Hwy",
    "iso:country":"US",
    "sg:address":"1901 Jefferson Hwy",
    "sg:city":"New Orleans",
    "sg:classifiers":[
        {
            "category":"Professional",
            "subcategory":"Computer Services",
            "type":"Services"
        }
    ],
    "sg:phone":"+1 504 836 6800",
    "sg:postcode":"70121",
    "sg:province":"LA",
    "wof:name":"Amann Business Systems Inc",
    "wof:placetype":"venue"
},
  "geometry": {"coordinates":[-90.147796,29.963323],"type":"Point"}
}