{
  "type": "Feature",
  "properties": {
    "addr:full":"679 Jefferson Hwy Baton Rouge LA 70806",
    "addr:housenumber":"679",
    "addr:postcode":"70806",
    "addr:street":"Jefferson Hwy",
    "iso:country":"US",
    "sg:address":"679 Jefferson Hwy",
    "sg:city":"Baton Rouge",
    "sg:classifiers":[
        {
            "category":"Organizations",
            "subcategory":"Community Association",
            "type":"Services"
        }
    ],
    "sg:phone":"+1 225 387 9667",
    "sg:postcode":"70806",
    "sg:province":"LA",
    "sg:tags":[
        "fraternal"
    ],
    "wof:name":"Knights Of Columbus",
    "wof:placetype":"venue"
},
  "geometry": {"coordinates":[-91.130424,30.444486],"type":"Point"}
}