{
  "type": "Feature",
  "properties": {
    "addr:full":"121 Audubon Blvd Lafayette LA 70503",
    "addr:housenumber":"121",
    "addr:postcode":"70503",
    "addr:street":"Audubon Blvd",
    "iso:country":"US",
    "sg:address":"121 Audubon Blvd",
    "sg:city":"Lafayette",
    "sg:classifiers":[
        {
            "category":"Professional",
            "type":"Services"
        }
    ],
    "sg:phone":"+1 337 289 8874",
    "sg:postcode":"70503",
    "sg:province":"LA",
    "wof:name":"Lafayette General Medical Ctr",
    "wof:placetype":"venue"
},
  "geometry": {"coordinates":[-92.015331,30.203826],"type":"Point"}
}