{
  "type": "Feature",
  "properties": {
    "addr:full":"210 Spinnaker Dr Slidell LA 70458",
    "addr:housenumber":"210",
    "addr:postcode":"70458",
    "addr:street":"Spinnaker Dr",
    "iso:country":"US",
    "sg:address":"210 Spinnaker Dr",
    "sg:city":"Slidell",
    "sg:classifiers":[
        {
            "category":"Building & Trades",
            "subcategory":"Construction",
            "type":"Services"
        }
    ],
    "sg:phone":"+1 985 643 1546",
    "sg:postcode":"70458",
    "sg:province":"LA",
    "sg:tags":[
        "house",
        "builder",
        "operative"
    ],
    "wof:name":"Gordon Construction",
    "wof:placetype":"venue"
},
  "geometry": {"coordinates":[-89.79301,30.231152],"type":"Point"}
}