{
  "type": "Feature",
  "properties": {
    "addr:full":"1026 Julia St New Iberia LA 70560",
    "addr:housenumber":"1026",
    "addr:postcode":"70560",
    "addr:street":"Julia St",
    "iso:country":"US",
    "sg:address":"1026 Julia St",
    "sg:city":"New Iberia",
    "sg:classifiers":[
        {
            "category":"Retail",
            "subcategory":"Repair Shop",
            "type":"Services"
        }
    ],
    "sg:phone":"+1 337 369 3539",
    "sg:postcode":"70560",
    "sg:province":"LA",
    "sg:tags":[
        "lock",
        "locksmith"
    ],
    "wof:name":"Keys On Wheels",
    "wof:placetype":"venue"
},
  "geometry": {"coordinates":[-91.828249,29.996923],"type":"Point"}
}