{
  "type": "Feature",
  "properties": {
    "iso:country":"US",
    "sg:address":"3010 Knight St",
    "sg:city":"Shreveport",
    "sg:classifiers":[
        {
            "category":"Professional",
            "subcategory":"Detective & Security Services",
            "type":"Services"
        }
    ],
    "sg:phone":"+1 318 865 8250",
    "sg:postcode":"71105",
    "sg:province":"LA",
    "sg:tags":[
        "guard",
        "patrol"
    ],
    "wof:name":"Vinson Guard Svc",
    "wof:placetype":"venue"
},
  "geometry": {"coordinates":[-93.702837,32.480257],"type":"Point"}
}