{
  "type": "Feature",
  "properties": {
    "iso:country":"US",
    "sg:address":"380 Rosenwald St",
    "sg:city":"Reserve",
    "sg:classifiers":[
        {
            "category":"Building & Trades",
            "subcategory":"Pest Control",
            "type":"Services"
        }
    ],
    "sg:phone":"+1 985 536 7720",
    "sg:postcode":"70084",
    "sg:province":"LA",
    "wof:name":"Degesch America Inc",
    "wof:placetype":"venue"
},
  "geometry": {"coordinates":[-90.573542,30.066559],"type":"Point"}
}