{
  "type": "Feature",
  "properties": {
    "iso:country":"US",
    "sg:address":"312 Vennard Ave",
    "sg:city":"Lafayette",
    "sg:classifiers":[
        {
            "category":"Insurance",
            "subcategory":"Insurance Agent",
            "type":"Services"
        }
    ],
    "sg:phone":"+1 337 232 2446",
    "sg:postcode":"70501",
    "sg:province":"LA",
    "wof:name":"Short Financial Group",
    "wof:placetype":"venue"
},
  "geometry": {"coordinates":[-91.981557,30.222674],"type":"Point"}
}