{
  "type": "Feature",
  "properties": {
    "iso:country":"US",
    "sg:address":"1545 E 70th St",
    "sg:city":"Shreveport",
    "sg:classifiers":[
        {
            "category":"Banks & Credit Unions",
            "subcategory":"Bank",
            "type":"Services"
        }
    ],
    "sg:phone":"+1 318 797 7707",
    "sg:postcode":"71105",
    "sg:province":"LA",
    "wof:name":"Citizens National Bank NA",
    "wof:placetype":"venue"
},
  "geometry": {"coordinates":[-93.72323,32.443544],"type":"Point"}
}