{
  "type": "Feature",
  "properties": {
    "addr:full":"10364 S Choctaw Dr Baton Rouge LA 70815",
    "addr:housenumber":"10364",
    "addr:postcode":"70815",
    "addr:street":"S Choctaw Dr",
    "iso:country":"US",
    "sg:address":"10364 S Choctaw Dr",
    "sg:city":"Baton Rouge",
    "sg:classifiers":[
        {
            "category":"Shopping",
            "subcategory":"News",
            "type":"Retail Goods"
        }
    ],
    "sg:phone":"+1 225 274 0609",
    "sg:postcode":"70815",
    "sg:province":"LA",
    "sg:tags":[
        "magazine"
    ],
    "wof:name":"Mopar Collectors Guide",
    "wof:placetype":"venue"
},
  "geometry": {"coordinates":[-91.07050599999999,30.472001],"type":"Point"}
}