{
  "type": "Feature",
  "properties": {
    "iso:country":"US",
    "sg:address":"609 W William David Pkwy",
    "sg:city":"Metairie",
    "sg:classifiers":[
        {
            "category":"Organizations",
            "subcategory":"Political Organization",
            "type":"Services"
        }
    ],
    "sg:phone":"+1 504 828 7448",
    "sg:postcode":"70005",
    "sg:province":"LA",
    "wof:name":"Republican Headquarters",
    "wof:placetype":"venue"
},
  "geometry": {"coordinates":[-90.134187,30.003919],"type":"Point"}
}