{
  "type": "Feature",
  "properties": {
    "addr:full":"843 Carondelet St New Orleans LA 70130",
    "addr:housenumber":"843",
    "addr:postcode":"70130",
    "addr:street":"Carondelet St",
    "iso:country":"US",
    "sg:address":"843 Carondelet St",
    "sg:city":"New Orleans",
    "sg:classifiers":[
        {
            "category":"Communications",
            "subcategory":"Film & Video Production",
            "type":"Services"
        }
    ],
    "sg:phone":"+1 504 523 3818",
    "sg:postcode":"70130",
    "sg:province":"LA",
    "sg:tags":[
        "motion",
        "picture"
    ],
    "wof:name":"New Orleans Film & Video Fstvl",
    "wof:placetype":"venue"
},
  "geometry": {"coordinates":[-90.073272,29.945338],"type":"Point"}
}