{
  "type": "Feature",
  "properties": {
    "iso:country":"US",
    "sg:address":"504 Belanger St",
    "sg:city":"Houma",
    "sg:classifiers":[
        {
            "category":"Mining & Drilling",
            "type":"Manufacturing & Wholesale Goods"
        }
    ],
    "sg:phone":"+1 985 858 5000",
    "sg:postcode":"70360",
    "sg:province":"LA",
    "sg:tags":[
        "oil",
        "gas",
        "producer"
    ],
    "wof:name":"Hunt Petroleum Corp",
    "wof:placetype":"venue"
},
  "geometry": {"coordinates":[-90.720951,29.596625],"type":"Point"}
}