{
  "type": "Feature",
  "properties": {
    "iso:country":"US",
    "sg:address":"7593 Beebe Dr",
    "sg:city":"Greenwood",
    "sg:classifiers":[
        {
            "category":"Travel",
            "subcategory":"Travel Agent",
            "type":"Entertainment"
        }
    ],
    "sg:phone":"+1 318 938 7749",
    "sg:postcode":"71033",
    "sg:province":"LA",
    "sg:tags":[
        "agency",
        "bureau"
    ],
    "wof:name":"Dixie Tours",
    "wof:placetype":"venue"
},
  "geometry": {"coordinates":[-93.941975,32.425262],"type":"Point"}
}