{
  "type": "Feature",
  "properties": {
    "addr:full":"6001 Financial Plz Shreveport LA 71129",
    "addr:housenumber":"6001",
    "addr:postcode":"71129",
    "addr:street":"Financial Plz",
    "iso:country":"US",
    "sg:address":"6001 Financial Plz",
    "sg:city":"Shreveport",
    "sg:classifiers":[
        {
            "category":"Insurance",
            "subcategory":"Insurance Agent",
            "type":"Services"
        }
    ],
    "sg:phone":"+1 318 212 0238",
    "sg:postcode":"71129",
    "sg:province":"LA",
    "wof:name":"Equitable Life Assurance",
    "wof:placetype":"venue"
},
  "geometry": {"coordinates":[-93.857958,32.451603],"type":"Point"}
}