{
  "type": "Feature",
  "properties": {
    "iso:country":"US",
    "sg:address":"413 Lee Ave",
    "sg:city":"Lafayette",
    "sg:classifiers":[
        {
            "category":"Professional",
            "subcategory":"Printing & Photocopies",
            "type":"Services"
        }
    ],
    "sg:phone":"+1 337 232 2040",
    "sg:postcode":"70501",
    "sg:province":"LA",
    "sg:tags":[
        "duplicating",
        "copying"
    ],
    "wof:name":"Scan Solutions",
    "wof:placetype":"venue"
},
  "geometry": {"coordinates":[-92.016447,30.224084],"type":"Point"}
}