{
  "type": "Feature",
  "properties": {
    "iso:country":"US",
    "sg:address":"811 Toulouse St",
    "sg:city":"New Orleans",
    "sg:classifiers":[
        {
            "category":"Bars & Pubs",
            "type":"Food & Drink"
        }
    ],
    "sg:phone":"+1 504 586 0707",
    "sg:postcode":"70112",
    "sg:province":"LA",
    "wof:name":"Old Opera House Annex",
    "wof:placetype":"venue"
},
  "geometry": {"coordinates":[-90.067139,29.958407],"type":"Point"}
}