{
  "type": "Feature",
  "properties": {
    "iso:country":"US",
    "sg:address":"9325 Normandie Dr",
    "sg:city":"Shreveport",
    "sg:classifiers":[
        {
            "category":"Real Estate",
            "subcategory":"Real Estate Operator",
            "type":"Services"
        }
    ],
    "sg:phone":"+1 318 688 1677",
    "sg:postcode":"71118",
    "sg:province":"LA",
    "sg:tags":[
        "apartment"
    ],
    "wof:name":"Normandie Living Center",
    "wof:placetype":"venue"
},
  "geometry": {"coordinates":[-93.806959,32.395578],"type":"Point"}
}