{
  "type": "Feature",
  "properties": {
    "iso:country":"US",
    "sg:address":"2310 Ambassador Caffery Pkwy",
    "sg:city":"Lafayette",
    "sg:classifiers":[
        {
            "category":"Local Transit",
            "type":"Transportation"
        }
    ],
    "sg:phone":"+1 337 983 2266",
    "sg:postcode":"70506",
    "sg:province":"LA",
    "sg:tags":[
        "limousine"
    ],
    "wof:name":"Louisiana Limo Inc",
    "wof:placetype":"venue"
},
  "geometry": {"coordinates":[-92.07570800000001,30.210297],"type":"Point"}
}