{
  "type": "Feature",
  "properties": {
    "iso:country":"US",
    "sg:address":"2911 Centenary Blvd",
    "sg:city":"Shreveport",
    "sg:classifiers":[
        {
            "category":"Social Services",
            "type":"Services"
        }
    ],
    "sg:phone":"+1 318 869 2411",
    "sg:postcode":"71104",
    "sg:province":"LA",
    "sg:tags":[
        "organization",
        "welfare"
    ],
    "wof:name":"Literacy Volunteeers",
    "wof:placetype":"venue"
},
  "geometry": {"coordinates":[-93.733054,32.485659],"type":"Point"}
}