{
  "type": "Feature",
  "properties": {
    "addr:full":"2003 Florida St Mandeville LA 70448",
    "addr:housenumber":"2003",
    "addr:postcode":"70448",
    "addr:street":"Florida St",
    "iso:country":"US",
    "sg:address":"2003 Florida St",
    "sg:city":"Mandeville",
    "sg:classifiers":[
        {
            "category":"Utilities",
            "subcategory":"Mobile Phone",
            "type":"Services"
        }
    ],
    "sg:phone":"+1 985 626 1282",
    "sg:postcode":"70448",
    "sg:province":"LA",
    "sg:tags":[
        "telephone",
        "cellular"
    ],
    "wof:name":"Nationwide Communications",
    "wof:placetype":"venue"
},
  "geometry": {"coordinates":[-90.06202999999999,30.363801],"type":"Point"}
}