{
  "type": "Feature",
  "properties": {
    "addr:full":"225 Brule Rd Labadieville LA 70372",
    "addr:housenumber":"225",
    "addr:postcode":"70372",
    "addr:street":"Brule Rd",
    "iso:country":"US",
    "sg:address":"225 Brule Rd",
    "sg:city":"Labadieville",
    "sg:classifiers":[
        {
            "category":"Building & Trades",
            "subcategory":"Construction",
            "type":"Services"
        }
    ],
    "sg:phone":"+1 985 526 6525",
    "sg:postcode":"70372",
    "sg:province":"LA",
    "sg:tags":[
        "home",
        "improvement"
    ],
    "wof:name":"Custom Home Improvements",
    "wof:placetype":"venue"
},
  "geometry": {"coordinates":[-90.95693199999999,29.836262],"type":"Point"}
}