{
  "type": "Feature",
  "properties": {
    "iso:country":"US",
    "sg:address":"540 E Mill St",
    "sg:city":"Crowley",
    "sg:classifiers":[
        {
            "category":"Manufacturing",
            "subcategory":"Food",
            "type":"Manufacturing & Wholesale Goods"
        }
    ],
    "sg:phone":"+1 337 783 3284",
    "sg:postcode":"70526",
    "sg:province":"LA",
    "sg:tags":[
        "product",
        "rice"
    ],
    "wof:name":"Crowley Grain Drier Inc",
    "wof:placetype":"venue"
},
  "geometry": {"coordinates":[-92.364991,30.210537],"type":"Point"}
}