{
  "type": "Feature",
  "properties": {
    "iso:country":"US",
    "sg:address":"2409 Delachaise St",
    "sg:city":"New Orleans",
    "sg:classifiers":[
        {
            "category":"Shopping",
            "type":"Retail Goods"
        }
    ],
    "sg:phone":"+1 504 891 1139",
    "sg:postcode":"70115",
    "sg:province":"LA",
    "sg:tags":[
        "art",
        "gallery",
        "dealer"
    ],
    "wof:name":"Leo's Art Design",
    "wof:placetype":"venue"
},
  "geometry": {"coordinates":[-90.096416,29.935936],"type":"Point"}
}