{
  "type": "Feature",
  "properties": {
    "iso:country":"US",
    "sg:address":"735 Peters Rd",
    "sg:city":"Harvey",
    "sg:classifiers":[
        {
            "category":"Mining & Drilling",
            "type":"Manufacturing & Wholesale Goods"
        }
    ],
    "sg:phone":"+1 504 367 3194",
    "sg:postcode":"70058",
    "sg:province":"LA",
    "sg:tags":[
        "field",
        "oil"
    ],
    "wof:name":"Francis Services Inc",
    "wof:placetype":"venue"
},
  "geometry": {"coordinates":[-90.078799,29.901165],"type":"Point"}
}