{
  "type": "Feature",
  "properties": {
    "addr:full":"18167 Petroleum Dr Baton Rouge LA 70809",
    "addr:housenumber":"18167",
    "addr:postcode":"70809",
    "addr:street":"Petroleum Dr",
    "iso:country":"US",
    "sg:address":"18167 Petroleum Dr",
    "sg:city":"Baton Rouge",
    "sg:classifiers":[
        {
            "category":"Wholesale",
            "subcategory":"Chemicals & Plastics",
            "type":"Manufacturing & Wholesale Goods"
        }
    ],
    "sg:phone":"+1 225 756 3930",
    "sg:postcode":"70809",
    "sg:province":"LA",
    "wof:name":"Hexion Specialty Chemicals Inc",
    "wof:placetype":"venue"
},
  "geometry": {"coordinates":[-91.019374,30.349931],"type":"Point"}
}