{
  "type": "Feature",
  "properties": {
    "iso:country":"US",
    "sg:address":"7640 Grimm Rd",
    "sg:city":"Shreveport",
    "sg:classifiers":[
        {
            "category":"Building & Trades",
            "subcategory":"Construction",
            "type":"Services"
        }
    ],
    "sg:phone":"+1 318 929 3151",
    "sg:postcode":"71107",
    "sg:province":"LA",
    "sg:tags":[
        "general",
        "contractor"
    ],
    "wof:name":"Steve's Acoustics & Dry Wall",
    "wof:placetype":"venue"
},
  "geometry": {"coordinates":[-93.916698,32.646797],"type":"Point"}
}