{
  "type": "Feature",
  "properties": {
    "iso:country":"US",
    "sg:address":"1115 Shreveport Barksdale Hwy",
    "sg:city":"Shreveport",
    "sg:classifiers":[
        {
            "category":"Shopping",
            "subcategory":"Music",
            "type":"Retail Goods"
        }
    ],
    "sg:phone":"+1 318 868 4268",
    "sg:postcode":"71105",
    "sg:province":"LA",
    "sg:tags":[
        "compact",
        "record",
        "disc",
        "tape"
    ],
    "wof:name":"Disc Daddy Inc",
    "wof:placetype":"venue"
},
  "geometry": {"coordinates":[-93.707019,32.486417],"type":"Point"}
}