{
  "type": "Feature",
  "properties": {
    "addr:full":"5638 Superior Dr Baton Rouge LA 70816",
    "addr:housenumber":"5638",
    "addr:postcode":"70816",
    "addr:street":"Superior Dr",
    "iso:country":"US",
    "sg:address":"5638 Superior Dr",
    "sg:city":"Baton Rouge",
    "sg:classifiers":[
        {
            "category":"Utilities",
            "subcategory":"Telephone",
            "type":"Services"
        }
    ],
    "sg:phone":"+1 225 303 0462",
    "sg:postcode":"70816",
    "sg:province":"LA",
    "sg:tags":[
        "company"
    ],
    "wof:name":"Telnet Of Baton Rouge",
    "wof:placetype":"venue"
},
  "geometry": {"coordinates":[-91.049097,30.40451],"type":"Point"}
}