{
  "type": "Feature",
  "properties": {
    "addr:full":"814 Grand Caillou Rd Houma LA 70363",
    "addr:housenumber":"814",
    "addr:postcode":"70363",
    "addr:street":"Grand Caillou Rd",
    "iso:country":"US",
    "sg:address":"814 Grand Caillou Rd",
    "sg:city":"Houma",
    "sg:classifiers":[
        {
            "category":"Health Services",
            "subcategory":"Optometrist",
            "type":"Services"
        }
    ],
    "sg:phone":"+1 985 223 2020",
    "sg:postcode":"70363",
    "sg:province":"LA",
    "wof:name":"Cloutier Eyecare",
    "wof:placetype":"venue"
},
  "geometry": {"coordinates":[-90.69810200000001,29.584613],"type":"Point"}
}