{
  "type": "Feature",
  "properties": {
    "addr:full":"812 Doyle St Farmerville LA 71241",
    "addr:housenumber":"812",
    "addr:postcode":"71241",
    "addr:street":"Doyle St",
    "iso:country":"US",
    "sg:address":"812 Doyle St",
    "sg:city":"Farmerville",
    "sg:classifiers":[
        {
            "category":"Personal",
            "subcategory":"Beauty Salon",
            "type":"Services"
        }
    ],
    "sg:phone":"+1 318 368 0130",
    "sg:postcode":"71241",
    "sg:province":"LA",
    "wof:name":"Millsap's Hair Salon",
    "wof:placetype":"venue"
},
  "geometry": {"coordinates":[-92.415133,32.781068],"type":"Point"}
}