{
  "type": "Feature",
  "properties": {
    "iso:country":"US",
    "sg:address":"68099 Hwy 59",
    "sg:city":"Mandeville",
    "sg:classifiers":[
        {
            "category":"Travel",
            "subcategory":"Travel Agent",
            "type":"Entertainment"
        }
    ],
    "sg:phone":"+1 985 892 0520",
    "sg:postcode":"70471",
    "sg:province":"LA",
    "sg:tags":[
        "information",
        "tourist"
    ],
    "sg:website":"www.neworleansnorthshore.com",
    "wof:name":"St Tammany Tourist Commission",
    "wof:placetype":"venue"
},
  "geometry": {"coordinates":[-90.040786,30.417192],"type":"Point"}
}