{
  "type": "Feature",
  "properties": {
    "iso:country":"US",
    "sg:address":"10103 Florida Blvd",
    "sg:city":"Walker",
    "sg:classifiers":[
        {
            "category":"Shopping",
            "subcategory":"Used Merchandise",
            "type":"Retail Goods"
        }
    ],
    "sg:phone":"+1 225 667 4011",
    "sg:postcode":"70785",
    "sg:province":"LA",
    "sg:tags":[
        "antique"
    ],
    "wof:name":"Kindred Hearts Antiques & Gfts",
    "wof:placetype":"venue"
},
  "geometry": {"coordinates":[-90.914885,30.482872],"type":"Point"}
}