{
  "type": "Feature",
  "properties": {
    "addr:full":"220 Carroll St Shreveport LA 71105",
    "addr:housenumber":"220",
    "addr:postcode":"71105",
    "addr:street":"Carroll St",
    "iso:country":"US",
    "sg:address":"220 Carroll St",
    "sg:city":"Shreveport",
    "sg:classifiers":[
        {
            "category":"Personal",
            "type":"Services"
        }
    ],
    "sg:phone":"+1 318 861 6869",
    "sg:postcode":"71105",
    "sg:province":"LA",
    "sg:tags":[
        "shop",
        "beauty"
    ],
    "wof:name":"Karens Electrolysis",
    "wof:placetype":"venue"
},
  "geometry": {"coordinates":[-93.722042,32.453082],"type":"Point"}
}