{
  "type": "Feature",
  "properties": {
    "iso:country":"US",
    "sg:address":"565 N Crocker St",
    "sg:city":"Sulphur",
    "sg:classifiers":[
        {
            "category":"Education",
            "subcategory":"School",
            "type":"Public Place"
        }
    ],
    "sg:phone":"+1 337 527 7401",
    "sg:postcode":"70663",
    "sg:province":"LA",
    "wof:name":"D S Perkins Elementary School",
    "wof:placetype":"venue"
},
  "geometry": {"coordinates":[-93.38074400000001,30.24255],"type":"Point"}
}