{
  "type": "Feature",
  "properties": {
    "addr:full":"3002 Roberson St Bernice LA 71222",
    "addr:housenumber":"3002",
    "addr:postcode":"71222",
    "addr:street":"Roberson St",
    "iso:country":"US",
    "sg:address":"3002 Roberson St",
    "sg:city":"Bernice",
    "sg:classifiers":[
        {
            "category":"Organizations",
            "subcategory":"Religious Organization",
            "type":"Services"
        }
    ],
    "sg:phone":"+1 318 353 6496",
    "sg:postcode":"71222",
    "sg:province":"LA",
    "sg:tags":[
        "church"
    ],
    "wof:name":"Sharon Baptist Church",
    "wof:placetype":"venue"
},
  "geometry": {"coordinates":[-92.65964700000001,32.807225],"type":"Point"}
}