{
  "type": "Feature",
  "properties": {
    "addr:full":"11940 Richcroft Ave Baton Rouge LA 70814",
    "addr:housenumber":"11940",
    "addr:postcode":"70814",
    "addr:street":"Richcroft Ave",
    "iso:country":"US",
    "sg:address":"11940 Richcroft Ave",
    "sg:city":"Baton Rouge",
    "sg:classifiers":[
        {
            "category":"Building & Trades",
            "subcategory":"Electrical",
            "type":"Services"
        }
    ],
    "sg:phone":"+1 225 273 8996",
    "sg:postcode":"70814",
    "sg:province":"LA",
    "sg:tags":[
        "electric",
        "contractor"
    ],
    "wof:name":"Goodwin Services Inc",
    "wof:placetype":"venue"
},
  "geometry": {"coordinates":[-91.05009099999999,30.473556],"type":"Point"}
}