{
  "type": "Feature",
  "properties": {
    "iso:country":"US",
    "sg:address":"108 K O L Dr",
    "sg:city":"Broussard",
    "sg:classifiers":[
        {
            "category":"Professional",
            "subcategory":"Management & Consulting",
            "type":"Services"
        }
    ],
    "sg:phone":"+1 337 839 1020",
    "sg:postcode":"70518",
    "sg:province":"LA",
    "sg:tags":[
        "communications",
        "consultant"
    ],
    "wof:name":"Net Scada Inc",
    "wof:placetype":"venue"
},
  "geometry": {"coordinates":[-91.96768400000001,30.157248],"type":"Point"}
}