{
  "type": "Feature",
  "properties": {
    "iso:country":"US",
    "sg:address":"125 E Grolee St",
    "sg:city":"Opelousas",
    "sg:classifiers":[
        {
            "category":"Government",
            "subcategory":"Office",
            "type":"Public Place"
        }
    ],
    "sg:phone":"+1 337 948 2522",
    "sg:postcode":"70570",
    "sg:province":"LA",
    "sg:tags":[
        "village"
    ],
    "wof:name":"Opelousas Purchasing Dept",
    "wof:placetype":"venue"
},
  "geometry": {"coordinates":[-92.08218599999999,30.536167],"type":"Point"}
}