{
  "type": "Feature",
  "properties": {
    "iso:country":"US",
    "sg:address":"12900 Jeanne Ct",
    "sg:city":"New Orleans",
    "sg:classifiers":[
        {
            "category":"Retail",
            "subcategory":"Auto Repair",
            "type":"Services"
        }
    ],
    "sg:phone":"+1 504 240 2762",
    "sg:postcode":"70128",
    "sg:province":"LA",
    "sg:tags":[
        "automotive",
        "wrecker"
    ],
    "wof:name":"Spiderman's Towing & Recovery",
    "wof:placetype":"venue"
},
  "geometry": {"coordinates":[-89.95554,30.05464],"type":"Point"}
}