{
  "type": "Feature",
  "properties": {
    "addr:full":"3201 Kaliste Saloom Rd Lafayette LA 70508",
    "addr:housenumber":"3201",
    "addr:postcode":"70508",
    "addr:street":"Kaliste Saloom Rd",
    "iso:country":"US",
    "sg:address":"3201 Kaliste Saloom Rd",
    "sg:city":"Lafayette",
    "sg:classifiers":[
        {
            "category":"Autos & Motor Vehicles",
            "subcategory":"Automobile Sales",
            "type":"Retail Goods"
        }
    ],
    "sg:phone":"+1 337 406 1000",
    "sg:postcode":"70508",
    "sg:province":"LA",
    "sg:tags":[
        "car",
        "dealer"
    ],
    "wof:name":"Alette Autos",
    "wof:placetype":"venue"
},
  "geometry": {"coordinates":[-92.05655,30.147771],"type":"Point"}
}