{
  "type": "Feature",
  "properties": {
    "iso:country":"US",
    "sg:address":"1303 Moss St",
    "sg:city":"Lafayette",
    "sg:classifiers":[
        {
            "category":"Retail",
            "subcategory":"Car Wash",
            "type":"Services"
        }
    ],
    "sg:phone":"+1 337 237 7886",
    "sg:postcode":"70501",
    "sg:province":"LA",
    "sg:tags":[
        "polishing",
        "washing"
    ],
    "wof:name":"Da Carwash",
    "wof:placetype":"venue"
},
  "geometry": {"coordinates":[-92.006704,30.242562],"type":"Point"}
}