{
  "type": "Feature",
  "properties": {
    "addr:full":"425 N Ave G Crowley LA 70526",
    "addr:housenumber":"425",
    "addr:postcode":"70526",
    "addr:street":"N Ave G",
    "iso:country":"US",
    "sg:address":"425 N Ave G",
    "sg:city":"Crowley",
    "sg:classifiers":[
        {
            "category":"Banks & Credit Unions",
            "subcategory":"Bank",
            "type":"Services"
        }
    ],
    "sg:phone":"+1 337 783 0412",
    "sg:postcode":"70526",
    "sg:province":"LA",
    "sg:website":"www.therealbank.com",
    "wof:name":"Evangeline Bank & Trust Co",
    "wof:placetype":"venue"
},
  "geometry": {"coordinates":[-92.37194100000001,30.213722],"type":"Point"}
}