{
  "type": "Feature",
  "properties": {
    "addr:full":"3813 Laurel St New Orleans LA 70115",
    "addr:housenumber":"3813",
    "addr:postcode":"70115",
    "addr:street":"Laurel St",
    "iso:country":"US",
    "sg:address":"3813 Laurel St",
    "sg:city":"New Orleans",
    "sg:classifiers":[
        {
            "category":"Building & Trades",
            "subcategory":"Construction",
            "type":"Services"
        }
    ],
    "sg:phone":"+1 504 895 3089",
    "sg:postcode":"70115",
    "sg:province":"LA",
    "sg:tags":[
        "residential"
    ],
    "wof:name":"Gavin Macarthur",
    "wof:placetype":"venue"
},
  "geometry": {"coordinates":[-90.094353,29.919397],"type":"Point"}
}