{
  "type": "Feature",
  "properties": {
    "iso:country":"US",
    "sg:address":"8500 Oak St",
    "sg:city":"New Orleans",
    "sg:classifiers":[
        {
            "category":"Shopping",
            "subcategory":"Used Merchandise",
            "type":"Retail Goods"
        }
    ],
    "sg:phone":"+1 504 866 7795",
    "sg:postcode":"70118",
    "sg:province":"LA",
    "sg:tags":[
        "antique"
    ],
    "sg:website":"www.driscollantiques.com",
    "wof:name":"Driscoll Antiques",
    "wof:placetype":"venue"
},
  "geometry": {"coordinates":[-90.133968,29.95074],"type":"Point"}
}