{
  "type": "Feature",
  "properties": {
    "addr:full":"3000 Fairfield Ave Shreveport LA 71104",
    "addr:housenumber":"3000",
    "addr:postcode":"71104",
    "addr:street":"Fairfield Ave",
    "iso:country":"US",
    "sg:address":"3000 Fairfield Ave",
    "sg:city":"Shreveport",
    "sg:classifiers":[
        {
            "category":"Banks & Credit Unions",
            "subcategory":"Bank",
            "type":"Services"
        }
    ],
    "sg:phone":"+1 318 212 0600",
    "sg:postcode":"71104",
    "sg:province":"LA",
    "wof:name":"Community Bank Of Louisiana",
    "wof:placetype":"venue"
},
  "geometry": {"coordinates":[-93.75032899999999,32.481505],"type":"Point"}
}