{
  "type": "Feature",
  "properties": {
    "iso:country":"US",
    "sg:address":"700 Elmwood Park Blvd",
    "sg:city":"Harahan",
    "sg:classifiers":[
        {
            "category":"Manufacturing",
            "subcategory":"Glass & Minerals",
            "type":"Manufacturing & Wholesale Goods"
        }
    ],
    "sg:phone":"+1 504 818 0118",
    "sg:postcode":"70123",
    "sg:province":"LA",
    "sg:tags":[
        "tile"
    ],
    "wof:name":"Dal-Tile",
    "wof:placetype":"venue"
},
  "geometry": {"coordinates":[-90.185722,29.952747],"type":"Point"}
}