{
  "type": "Feature",
  "properties": {
    "addr:full":"148 Woodland Dr La Place LA 70068",
    "addr:housenumber":"148",
    "addr:postcode":"70068",
    "addr:street":"Woodland Dr La Place",
    "iso:country":"US",
    "sg:address":"148 Woodland Dr",
    "sg:city":"La Place",
    "sg:classifiers":[
        {
            "category":"Retail",
            "subcategory":"Repair Shop",
            "type":"Services"
        }
    ],
    "sg:phone":"+1 985 651 0442",
    "sg:postcode":"70068",
    "sg:province":"LA",
    "sg:tags":[
        "equipment",
        "conditioning",
        "air"
    ],
    "wof:name":"Murry's Heating & Air Cond",
    "wof:placetype":"venue"
},
  "geometry": {"coordinates":[-90.45020599999999,30.086108],"type":"Point"}
}