{
  "type": "Feature",
  "properties": {
    "iso:country":"US",
    "sg:address":"385 Albany Ave",
    "sg:city":"Shreveport",
    "sg:classifiers":[
        {
            "category":"Manufacturing",
            "subcategory":"Retail Goods",
            "type":"Manufacturing & Wholesale Goods"
        }
    ],
    "sg:phone":"+1 318 865 6008",
    "sg:postcode":"71105",
    "sg:province":"LA",
    "sg:tags":[
        "aerosol"
    ],
    "wof:name":"Apple Car Care Inc",
    "wof:placetype":"venue"
},
  "geometry": {"coordinates":[-93.7229,32.469697],"type":"Point"}
}