{
  "type": "Feature",
  "properties": {
    "addr:full":"22120 John Prats Rd Covington LA 70435",
    "addr:housenumber":"22120",
    "addr:postcode":"70435",
    "addr:street":"John Prats Rd",
    "iso:country":"US",
    "sg:address":"22120 John Prats Rd",
    "sg:city":"Covington",
    "sg:classifiers":[
        {
            "category":"Professional",
            "subcategory":"Research",
            "type":"Services"
        }
    ],
    "sg:phone":"+1 985 893 1774",
    "sg:postcode":"70435",
    "sg:province":"LA",
    "sg:tags":[
        "environmental",
        "ecological"
    ],
    "wof:name":"Northpark Environmental Svc",
    "wof:placetype":"venue"
},
  "geometry": {"coordinates":[-90.039304,30.519697],"type":"Point"}
}