{
  "type": "Feature",
  "properties": {
    "iso:country":"US",
    "sg:address":"518 Fortson St",
    "sg:city":"Shreveport",
    "sg:classifiers":[
        {
            "category":"Utilities",
            "subcategory":"Telephone",
            "type":"Services"
        }
    ],
    "sg:phone":"+1 318 670 1315",
    "sg:postcode":"71107",
    "sg:province":"LA",
    "sg:tags":[
        "telecommunication"
    ],
    "wof:name":"David C Pigott",
    "wof:placetype":"venue"
},
  "geometry": {"coordinates":[-93.76551600000001,32.526503],"type":"Point"}
}