{
  "type": "Feature",
  "properties": {
    "iso:country":"US",
    "sg:address":"1200 Victor II Blvd",
    "sg:city":"Morgan City",
    "sg:classifiers":[
        {
            "category":"Shopping",
            "subcategory":"Pharmacy",
            "type":"Retail Goods"
        }
    ],
    "sg:phone":"+1 985 384 3847",
    "sg:postcode":"70380",
    "sg:province":"LA",
    "wof:name":"Spitale Drugs Inc",
    "wof:placetype":"venue"
},
  "geometry": {"coordinates":[-91.19852899999999,29.704115],"type":"Point"}
}