{
  "type": "Feature",
  "properties": {
    "iso:country":"US",
    "sg:address":"325 Kaliste Saloom Rd",
    "sg:city":"Lafayette",
    "sg:classifiers":[
        {
            "category":"Professional",
            "subcategory":"Credit Reporting & Collection",
            "type":"Services"
        }
    ],
    "sg:phone":"+1 337 237 0436",
    "sg:postcode":"70508",
    "sg:province":"LA",
    "sg:tags":[
        "agency"
    ],
    "wof:name":"KCB Collections",
    "wof:placetype":"venue"
},
  "geometry": {"coordinates":[-92.015913,30.184722],"type":"Point"}
}