{
  "type": "Feature",
  "properties": {
    "iso:country":"US",
    "sg:address":"2216 Screamville Rd",
    "sg:city":"Grand Cane",
    "sg:classifiers":[
        {
            "category":"Shopping",
            "subcategory":"Bicycles & Sporting Goods",
            "type":"Retail Goods"
        }
    ],
    "sg:phone":"+1 318 858 0010",
    "sg:postcode":"71032",
    "sg:province":"LA",
    "sg:tags":[
        "mail",
        "house"
    ],
    "wof:name":"Outlaw Outdoors",
    "wof:placetype":"venue"
},
  "geometry": {"coordinates":[-93.841725,32.090779],"type":"Point"}
}