{
  "type": "Feature",
  "properties": {
    "addr:full":"6823 Pines Rd Shreveport LA 71129",
    "addr:housenumber":"6823",
    "addr:postcode":"71129",
    "addr:street":"Pines Rd",
    "iso:country":"US",
    "sg:address":"6823 Pines Rd",
    "sg:city":"Shreveport",
    "sg:classifiers":[
        {
            "category":"Health Services",
            "subcategory":"Optometrist",
            "type":"Services"
        }
    ],
    "sg:phone":"+1 318 688 3050",
    "sg:postcode":"71129",
    "sg:province":"LA",
    "wof:name":"Eyes & Eyewear",
    "wof:placetype":"venue"
},
  "geometry": {"coordinates":[-93.863061,32.446716],"type":"Point"}
}