{
  "type": "Feature",
  "properties": {
    "iso:country":"US",
    "sg:address":"570 College Ave",
    "sg:city":"Grambling",
    "sg:classifiers":[
        {
            "category":"Real Estate",
            "subcategory":"Real Estate Operator",
            "type":"Services"
        }
    ],
    "sg:phone":"+1 318 247 0615",
    "sg:postcode":"71245",
    "sg:province":"LA",
    "sg:tags":[
        "apartment"
    ],
    "wof:name":"Pinecrest II",
    "wof:placetype":"venue"
},
  "geometry": {"coordinates":[-92.72586800000001,32.526148],"type":"Point"}
}