{
  "type": "Feature",
  "properties": {
    "iso:country":"US",
    "sg:address":"2021 Lizardi St",
    "sg:city":"New Orleans",
    "sg:classifiers":[
        {
            "category":"Social Services",
            "subcategory":"Child Care",
            "type":"Services"
        }
    ],
    "sg:phone":"+1 504 944 4105",
    "sg:postcode":"70117",
    "sg:province":"LA",
    "wof:name":"Imperial Infant & Child Care",
    "wof:placetype":"venue"
},
  "geometry": {"coordinates":[-90.017053,29.972209],"type":"Point"}
}