{
  "type": "Feature",
  "properties": {
    "addr:full":"3012 Broadway Ave Alexandria LA 71302",
    "addr:housenumber":"3012",
    "addr:postcode":"71302",
    "addr:street":"Broadway Ave",
    "iso:country":"US",
    "sg:address":"3012 Broadway Ave",
    "sg:city":"Alexandria",
    "sg:classifiers":[
        {
            "category":"Wholesale",
            "subcategory":"Hardware",
            "type":"Manufacturing & Wholesale Goods"
        }
    ],
    "sg:phone":"+1 318 487 9626",
    "sg:postcode":"71302",
    "sg:province":"LA",
    "sg:tags":[
        "plumbing",
        "fixture",
        "supply"
    ],
    "wof:name":"Southern Pipe & Supply Co",
    "wof:placetype":"venue"
},
  "geometry": {"coordinates":[-92.441969,31.284232],"type":"Point"}
}