{
  "type": "Feature",
  "properties": {
    "addr:full":"4235 Van Deeman St Bossier City LA 71112",
    "addr:housenumber":"4235",
    "addr:postcode":"71112",
    "addr:street":"Van Deeman St",
    "iso:country":"US",
    "sg:address":"4235 Van Deeman St",
    "sg:city":"Bossier City",
    "sg:classifiers":[
        {
            "category":"Organizations",
            "subcategory":"Religious Organization",
            "type":"Services"
        }
    ],
    "sg:phone":"+1 318 746 2125",
    "sg:postcode":"71112",
    "sg:province":"LA",
    "sg:tags":[
        "clergy"
    ],
    "wof:name":"R Dennis Blankenship",
    "wof:placetype":"venue"
},
  "geometry": {"coordinates":[-93.66717199999999,32.473537],"type":"Point"}
}