{
  "type": "Feature",
  "properties": {
    "addr:full":"71453 Gordon Ave Abita Springs LA 70420",
    "addr:housenumber":"71453",
    "addr:postcode":"70420",
    "addr:street":"Gordon Ave",
    "iso:country":"US",
    "sg:address":"71453 Gordon Ave",
    "sg:city":"Abita Springs",
    "sg:classifiers":[
        {
            "category":"Personal",
            "subcategory":"Beauty Salon",
            "type":"Services"
        }
    ],
    "sg:phone":"+1 985 892 8224",
    "sg:postcode":"70420",
    "sg:province":"LA",
    "wof:name":"Tony Dutruch Hair Stylist",
    "wof:placetype":"venue"
},
  "geometry": {"coordinates":[-90.042962,30.472076],"type":"Point"}
}