{
  "type": "Feature",
  "properties": {
    "iso:country":"US",
    "sg:address":"613 Clearview Pkwy",
    "sg:city":"Metairie",
    "sg:classifiers":[
        {
            "category":"Restaurant",
            "type":"Food & Drink"
        }
    ],
    "sg:phone":"+1 504 887 3456",
    "sg:postcode":"70001",
    "sg:province":"LA",
    "wof:name":"Quarter View Restaurant",
    "wof:placetype":"venue"
},
  "geometry": {"coordinates":[-90.179142,29.979895],"type":"Point"}
}