{
  "type": "Feature",
  "properties": {
    "addr:full":"422 Madeline St Rayville LA 71269",
    "addr:housenumber":"422",
    "addr:postcode":"71269",
    "addr:street":"Madeline St",
    "iso:country":"US",
    "sg:address":"422 Madeline St",
    "sg:city":"Rayville",
    "sg:classifiers":[
        {
            "category":"Professional",
            "type":"Services"
        }
    ],
    "sg:phone":"+1 318 728 5888",
    "sg:postcode":"71269",
    "sg:province":"LA",
    "sg:tags":[
        "establishment"
    ],
    "wof:name":"Rene Potter",
    "wof:placetype":"venue"
},
  "geometry": {"coordinates":[-91.761703,32.476532],"type":"Point"}
}