{
  "type": "Feature",
  "properties": {
    "iso:country":"US",
    "sg:address":"10260 Gulf Hwy",
    "sg:city":"Lake Charles",
    "sg:classifiers":[
        {
            "category":"Autos & Motor Vehicles",
            "subcategory":"Automobile Sales",
            "type":"Retail Goods"
        }
    ],
    "sg:phone":"+1 337 625 0913",
    "sg:postcode":"70607",
    "sg:province":"LA",
    "sg:tags":[
        "car",
        "dealer"
    ],
    "wof:name":"Dan's Auto Mart",
    "wof:placetype":"venue"
},
  "geometry": {"coordinates":[-93.212757,30.026231],"type":"Point"}
}