{
  "type": "Feature",
  "properties": {
    "iso:country":"US",
    "sg:address":"307 Bayou Gardens Blvd",
    "sg:city":"Houma",
    "sg:classifiers":[
        {
            "category":"Mining & Drilling",
            "type":"Manufacturing & Wholesale Goods"
        }
    ],
    "sg:phone":"+1 985 868 3030",
    "sg:postcode":"70364",
    "sg:province":"LA",
    "sg:tags":[
        "development",
        "gas",
        "oil",
        "exploration"
    ],
    "wof:name":"Imperial Resources",
    "wof:placetype":"venue"
},
  "geometry": {"coordinates":[-90.756029,29.636871],"type":"Point"}
}