{
  "type": "Feature",
  "properties": {
    "iso:country":"US",
    "sg:address":"7829 Bluebonnet Blvd",
    "sg:city":"Baton Rouge",
    "sg:classifiers":[
        {
            "category":"Professional",
            "subcategory":"Accounting & Tax Preparation",
            "type":"Services"
        }
    ],
    "sg:phone":"+1 225 767 7829",
    "sg:postcode":"70810",
    "sg:province":"LA",
    "sg:tags":[
        "accountant"
    ],
    "wof:name":"Donald C De Ville CPA",
    "wof:placetype":"venue"
},
  "geometry": {"coordinates":[-91.09839100000001,30.378087],"type":"Point"}
}