{
  "type": "Feature",
  "properties": {
    "addr:full":"1128 Coolidge St Lafayette LA 70503",
    "addr:housenumber":"1128",
    "addr:postcode":"70503",
    "addr:street":"Coolidge St",
    "iso:country":"US",
    "sg:address":"1128 Coolidge St",
    "sg:city":"Lafayette",
    "sg:classifiers":[
        {
            "category":"Mining & Drilling",
            "type":"Manufacturing & Wholesale Goods"
        }
    ],
    "sg:phone":"+1 337 233 5667",
    "sg:postcode":"70503",
    "sg:province":"LA",
    "sg:tags":[
        "field",
        "oil"
    ],
    "wof:name":"Chapman Well Control",
    "wof:placetype":"venue"
},
  "geometry": {"coordinates":[-92.017903,30.203407],"type":"Point"}
}