{
  "type": "Feature",
  "properties": {
    "addr:full":"3404 Jackson St Alexandria LA 71301",
    "addr:housenumber":"3404",
    "addr:postcode":"71301",
    "addr:street":"Jackson St",
    "iso:country":"US",
    "sg:address":"3404 Jackson St",
    "sg:city":"Alexandria",
    "sg:classifiers":[
        {
            "category":"Banks & Credit Unions",
            "subcategory":"Bank",
            "type":"Services"
        }
    ],
    "sg:phone":"+1 318 473 0298",
    "sg:postcode":"71301",
    "sg:province":"LA",
    "sg:tags":[
        "financing"
    ],
    "wof:name":"Rapides Credit Corp",
    "wof:placetype":"venue"
},
  "geometry": {"coordinates":[-92.47458899999999,31.286469],"type":"Point"}
}