{
  "type": "Feature",
  "properties": {
    "addr:full":"4317 Avron Blvd Metairie LA 70006",
    "addr:housenumber":"4317",
    "addr:postcode":"70006",
    "addr:street":"Avron Blvd",
    "iso:country":"US",
    "sg:address":"4317 Avron Blvd",
    "sg:city":"Metairie",
    "sg:classifiers":[
        {
            "category":"Real Estate",
            "subcategory":"Real Estate Agent",
            "type":"Services"
        }
    ],
    "sg:phone":"+1 504 887 0787",
    "sg:postcode":"70006",
    "sg:province":"LA",
    "wof:name":"Blue Dolphin Group",
    "wof:placetype":"venue"
},
  "geometry": {"coordinates":[-90.182357,30.019705],"type":"Point"}
}