{
  "type": "Feature",
  "properties": {
    "addr:full":"2509 Giuffrias Ave Metairie LA 70001",
    "addr:housenumber":"2509",
    "addr:postcode":"70001",
    "addr:street":"Giuffrias Ave",
    "iso:country":"US",
    "sg:address":"2509 Giuffrias Ave",
    "sg:city":"Metairie",
    "sg:classifiers":[
        {
            "category":"Real Estate",
            "subcategory":"Real Estate Operator",
            "type":"Services"
        }
    ],
    "sg:phone":"+1 504 887 1531",
    "sg:postcode":"70001",
    "sg:province":"LA",
    "sg:tags":[
        "condominium"
    ],
    "wof:name":"Woodridge Condominiums Assn",
    "wof:placetype":"venue"
},
  "geometry": {"coordinates":[-90.175432,29.99801],"type":"Point"}
}