{
  "type": "Feature",
  "properties": {
    "addr:full":"1824 Looney St Shreveport LA 71103",
    "addr:housenumber":"1824",
    "addr:postcode":"71103",
    "addr:street":"Looney St",
    "iso:country":"US",
    "sg:address":"1824 Looney St",
    "sg:city":"Shreveport",
    "sg:classifiers":[
        {
            "category":"Personal",
            "subcategory":"Beauty Salon",
            "type":"Services"
        }
    ],
    "sg:phone":"+1 318 222 2275",
    "sg:postcode":"71103",
    "sg:province":"LA",
    "wof:name":"Klassy Beauty Lounge",
    "wof:placetype":"venue"
},
  "geometry": {"coordinates":[-93.76914600000001,32.502718],"type":"Point"}
}