{
  "type": "Feature",
  "properties": {
    "addr:full":"105 Oak St Mansfield LA 71052",
    "addr:housenumber":"105",
    "addr:postcode":"71052",
    "addr:street":"Oak St",
    "iso:country":"US",
    "sg:address":"105 Oak St",
    "sg:city":"Mansfield",
    "sg:classifiers":[
        {
            "category":"Insurance",
            "subcategory":"Hazard Insurance",
            "type":"Services"
        },
        {
            "category":"Professional",
            "subcategory":"Business Services",
            "type":"Services"
        }
    ],
    "sg:phone":"+1 318 872 8224",
    "sg:postcode":"71052",
    "sg:province":"LA",
    "sg:tags":[
        "bond"
    ],
    "wof:name":"Xpress Bail Bonds",
    "wof:placetype":"venue"
},
  "geometry": {"coordinates":[-93.717628,32.040832],"type":"Point"}
}