{
  "type": "Feature",
  "properties": {
    "iso:country":"US",
    "sg:address":"2323 Ormond Blvd",
    "sg:city":"Destrehan",
    "sg:classifiers":[
        {
            "category":"Building & Trades",
            "subcategory":"Cleaning & Sanitation",
            "type":"Services"
        }
    ],
    "sg:phone":"+1 985 764 3255",
    "sg:postcode":"70047",
    "sg:province":"LA",
    "sg:tags":[
        "ventilating",
        "system"
    ],
    "wof:name":"Mc Andrew & Assoc",
    "wof:placetype":"venue"
},
  "geometry": {"coordinates":[-90.36438800000001,29.976104],"type":"Point"}
}