{
  "type": "Feature",
  "properties": {
    "iso:country":"US",
    "sg:address":"7091 Winbourne Ave",
    "sg:city":"Baton Rouge",
    "sg:classifiers":[
        {
            "category":"Retail",
            "subcategory":"Laundry & Dry Cleaning",
            "type":"Services"
        }
    ],
    "sg:phone":"+1 225 357 7689",
    "sg:postcode":"70805",
    "sg:province":"LA",
    "wof:name":"Norge Town Laundry & Dry Clean",
    "wof:placetype":"venue"
},
  "geometry": {"coordinates":[-91.120277,30.479681],"type":"Point"}
}