{
  "type": "Feature",
  "properties": {
    "addr:full":"810 W Port St Abbeville LA 70510",
    "addr:housenumber":"810",
    "addr:postcode":"70510",
    "addr:street":"W Port St",
    "iso:country":"US",
    "sg:address":"810 W Port St",
    "sg:city":"Abbeville",
    "sg:classifiers":[
        {
            "category":"Retail",
            "subcategory":"Repair Shop",
            "type":"Services"
        }
    ],
    "sg:phone":"+1 337 893 8589",
    "sg:postcode":"70510",
    "sg:province":"LA",
    "sg:tags":[
        "repairing",
        "lawn",
        "mower"
    ],
    "wof:name":"Scalisi's Small Engine Repair",
    "wof:placetype":"venue"
},
  "geometry": {"coordinates":[-92.143422,29.975984],"type":"Point"}
}