{
  "type": "Feature",
  "properties": {
    "addr:full":"3624 Ryan St Lake Charles LA 70605",
    "addr:housenumber":"3624",
    "addr:postcode":"70605",
    "addr:street":"Ryan St",
    "iso:country":"US",
    "sg:address":"3624 Ryan St",
    "sg:city":"Lake Charles",
    "sg:classifiers":[
        {
            "category":"Restaurant",
            "type":"Food & Drink"
        }
    ],
    "sg:phone":"+1 337 562 9900",
    "sg:postcode":"70605",
    "sg:province":"LA",
    "wof:name":"Applebee's Neighborhood Grill",
    "wof:placetype":"venue"
},
  "geometry": {"coordinates":[-93.218677,30.191353],"type":"Point"}
}