{
  "type": "Feature",
  "properties": {
    "iso:country":"US",
    "sg:address":"2005 Melrose St",
    "sg:city":"Pineville",
    "sg:classifiers":[
        {
            "category":"Shopping",
            "subcategory":"Clothing, Apparel, & Fashions",
            "type":"Retail Goods"
        }
    ],
    "sg:phone":"+1 318 473 9684",
    "sg:postcode":"71360",
    "sg:province":"LA",
    "sg:tags":[
        "uniform",
        "supply"
    ],
    "wof:name":"Cintas-Service Professionals",
    "wof:placetype":"venue"
},
  "geometry": {"coordinates":[-92.41501599999999,31.324436],"type":"Point"}
}