{
  "type": "Feature",
  "properties": {
    "iso:country":"US",
    "sg:address":"701 Murray St",
    "sg:city":"Alexandria",
    "sg:classifiers":[
        {
            "category":"Government",
            "subcategory":"Police Station",
            "type":"Public Place"
        }
    ],
    "sg:phone":"+1 318 473 6730",
    "sg:postcode":"71301",
    "sg:province":"LA",
    "sg:tags":[
        "sheriff"
    ],
    "wof:name":"Sheriff's Dept-Duty Officer",
    "wof:placetype":"venue"
},
  "geometry": {"coordinates":[-92.447667,31.308729],"type":"Point"}
}