{
  "type": "Feature",
  "properties": {
    "iso:country":"US",
    "sg:address":"610 John Churchill Chase St",
    "sg:city":"New Orleans",
    "sg:classifiers":[
        {
            "category":"Real Estate",
            "subcategory":"Real Estate Operator",
            "type":"Services"
        }
    ],
    "sg:phone":"+1 504 561 0200",
    "sg:postcode":"70130",
    "sg:province":"LA",
    "sg:tags":[
        "building",
        "parks"
    ],
    "wof:name":"Lengsfield Lofts",
    "wof:placetype":"venue"
},
  "geometry": {"coordinates":[-90.06758000000001,29.940522],"type":"Point"}
}