{
  "type": "Feature",
  "properties": {
    "iso:country":"US",
    "sg:address":"1318 E Main St",
    "sg:city":"New Iberia",
    "sg:classifiers":[
        {
            "category":"Shopping",
            "subcategory":"Department Store",
            "type":"Retail Goods"
        }
    ],
    "sg:phone":"+1 337 365 7127",
    "sg:postcode":"70560",
    "sg:province":"LA",
    "wof:name":"Liz's Family Clothing",
    "wof:placetype":"venue"
},
  "geometry": {"coordinates":[-91.80121200000001,29.996506],"type":"Point"}
}