{
  "type": "Feature",
  "properties": {
    "addr:full":"929 Keyser Ave Natchitoches LA 71457",
    "addr:housenumber":"929",
    "addr:postcode":"71457",
    "addr:street":"Keyser Ave",
    "iso:country":"US",
    "sg:address":"929 Keyser Ave",
    "sg:city":"Natchitoches",
    "sg:classifiers":[
        {
            "category":"Shopping",
            "subcategory":"Shoes",
            "type":"Retail Goods"
        }
    ],
    "sg:phone":"+1 318 356 0277",
    "sg:postcode":"71457",
    "sg:province":"LA",
    "wof:name":"Shoe Show",
    "wof:placetype":"venue"
},
  "geometry": {"coordinates":[-93.067532,31.752617],"type":"Point"}
}