{
  "type": "Feature",
  "properties": {
    "iso:country":"US",
    "sg:address":"2418 S Union St",
    "sg:city":"Opelousas",
    "sg:classifiers":[
        {
            "category":"Food & Beverages",
            "subcategory":"Groceries & Convenience Stores",
            "type":"Retail Goods"
        }
    ],
    "sg:phone":"+1 337 948 4002",
    "sg:postcode":"70570",
    "sg:province":"LA",
    "sg:tags":[
        "grocer"
    ],
    "wof:name":"Winn-Dixie",
    "wof:placetype":"venue"
},
  "geometry": {"coordinates":[-92.085655,30.507012],"type":"Point"}
}