{
  "type": "Feature",
  "properties": {
    "addr:full":"520 Fisher Rd Many LA 71449",
    "addr:housenumber":"520",
    "addr:postcode":"71449",
    "addr:street":"Fisher Rd",
    "iso:country":"US",
    "sg:address":"520 Fisher Rd",
    "sg:city":"Many",
    "sg:classifiers":[
        {
            "category":"Autos & Motor Vehicles",
            "subcategory":"Automobile Sales",
            "type":"Retail Goods"
        }
    ],
    "sg:phone":"+1 318 256 6662",
    "sg:postcode":"71449",
    "sg:province":"LA",
    "sg:tags":[
        "car",
        "dealer"
    ],
    "wof:name":"Cook James Used Cars",
    "wof:placetype":"venue"
},
  "geometry": {"coordinates":[-93.468818,31.551774],"type":"Point"}
}