{
  "type": "Feature",
  "properties": {
    "addr:full":"315 Audubon Blvd Lafayette LA 70503",
    "addr:housenumber":"315",
    "addr:postcode":"70503",
    "addr:street":"Audubon Blvd",
    "iso:country":"US",
    "sg:address":"315 Audubon Blvd",
    "sg:city":"Lafayette",
    "sg:classifiers":[
        {
            "category":"Health Services",
            "subcategory":"Doctor",
            "type":"Services"
        }
    ],
    "sg:phone":"+1 337 233 3308",
    "sg:postcode":"70503",
    "sg:province":"LA",
    "sg:tags":[
        "medical"
    ],
    "wof:name":"James S Wade Jr MD",
    "wof:placetype":"venue"
},
  "geometry": {"coordinates":[-92.01649399999999,30.204894],"type":"Point"}
}