{
  "type": "Feature",
  "properties": {
    "iso:country":"US",
    "sg:address":"14221 N Jake Dr",
    "sg:city":"Hammond",
    "sg:classifiers":[
        {
            "category":"Retail",
            "subcategory":"Repair Shop",
            "type":"Services"
        }
    ],
    "sg:phone":"+1 985 345 2488",
    "sg:postcode":"70401",
    "sg:province":"LA",
    "sg:tags":[
        "refrigeration"
    ],
    "wof:name":"Air-Coil AC & Rfrgn",
    "wof:placetype":"venue"
},
  "geometry": {"coordinates":[-90.497011,30.526288],"type":"Point"}
}