{
  "type": "Feature",
  "properties": {
    "addr:full":"474 Cycle Plant Rd Benton LA 71006",
    "addr:housenumber":"474",
    "addr:postcode":"71006",
    "addr:street":"Plant Rd",
    "iso:country":"US",
    "sg:address":"474 Cycle Plant Rd",
    "sg:city":"Benton",
    "sg:classifiers":[
        {
            "category":"Building & Trades",
            "subcategory":"Construction",
            "type":"Services"
        }
    ],
    "sg:phone":"+1 318 965 4658",
    "sg:postcode":"71006",
    "sg:province":"LA",
    "sg:tags":[
        "nonresidential"
    ],
    "wof:name":"Francis J Moody",
    "wof:placetype":"venue"
},
  "geometry": {"coordinates":[-93.640772,32.746275],"type":"Point"}
}