{
  "type": "Feature",
  "properties": {
    "addr:full":"1414 Fernwood Dr Slidell LA 70458",
    "addr:housenumber":"1414",
    "addr:postcode":"70458",
    "addr:street":"Fernwood Dr",
    "iso:country":"US",
    "sg:address":"1414 Fernwood Dr",
    "sg:city":"Slidell",
    "sg:classifiers":[
        {
            "category":"Education",
            "subcategory":"Special Training",
            "type":"Public Place"
        }
    ],
    "sg:phone":"+1 985 641 3590",
    "sg:postcode":"70458",
    "sg:province":"LA",
    "wof:name":"Toastmasters International",
    "wof:placetype":"venue"
},
  "geometry": {"coordinates":[-89.760464,30.28246],"type":"Point"}
}