{
  "type": "Feature",
  "properties": {
    "iso:country":"US",
    "sg:address":"65 Bayou Oaks Dr",
    "sg:city":"Alexandria",
    "sg:classifiers":[
        {
            "category":"Retail",
            "subcategory":"Auto Repair",
            "type":"Services"
        }
    ],
    "sg:phone":"+1 318 448 1442",
    "sg:postcode":"71303",
    "sg:province":"LA",
    "sg:tags":[
        "body",
        "automobile",
        "painting"
    ],
    "wof:name":"Dent Experts",
    "wof:placetype":"venue"
},
  "geometry": {"coordinates":[-92.536914,31.248017],"type":"Point"}
}