{
  "type": "Feature",
  "properties": {
    "iso:country":"US",
    "sg:address":"9013 Jefferson Hwy",
    "sg:city":"New Orleans",
    "sg:classifiers":[
        {
            "category":"Food & Beverages",
            "subcategory":"Meat & Fish",
            "type":"Retail Goods"
        }
    ],
    "sg:phone":"+1 504 738 2104",
    "sg:postcode":"70123",
    "sg:province":"LA",
    "sg:tags":[
        "seafood"
    ],
    "wof:name":"Bobby's Seafood",
    "wof:placetype":"venue"
},
  "geometry": {"coordinates":[-90.213458,29.947014],"type":"Point"}
}