{
  "type": "Feature",
  "properties": {
    "addr:full":"3110 Paris Rd Chalmette LA 70043",
    "addr:housenumber":"3110",
    "addr:postcode":"70043",
    "addr:street":"Paris Rd",
    "iso:country":"US",
    "sg:address":"3110 Paris Rd",
    "sg:city":"Chalmette",
    "sg:classifiers":[
        {
            "category":"Building & Trades",
            "subcategory":"Plumbing",
            "type":"Services"
        }
    ],
    "sg:phone":"+1 504 271 2227",
    "sg:postcode":"70043",
    "sg:province":"LA",
    "sg:tags":[
        "plumbing",
        "contractor"
    ],
    "wof:name":"A & A Mechanical Inc",
    "wof:placetype":"venue"
},
  "geometry": {"coordinates":[-89.96092899999999,29.94825],"type":"Point"}
}