{
  "type": "Feature",
  "properties": {
    "addr:full":"5201 Nicholson Dr Baton Rouge LA 70820",
    "addr:housenumber":"5201",
    "addr:postcode":"70820",
    "addr:street":"Nicholson Dr",
    "iso:country":"US",
    "sg:address":"5201 Nicholson Dr",
    "sg:city":"Baton Rouge",
    "sg:classifiers":[
        {
            "category":"Bars & Pubs",
            "type":"Food & Drink"
        }
    ],
    "sg:menulink":"http://www.allmenus.com/la/baton-rouge/235644-wahada-japanese-sushi-bar--grill/menu/",
    "sg:phone":"+1 225 767 1880",
    "sg:postcode":"70820",
    "sg:province":"LA",
    "sg:tags":[
        "japanese",
        "asian"
    ],
    "wof:name":"Wahada Japanese Sushi Bar & Grill",
    "wof:placetype":"venue"
},
  "geometry": {"coordinates":[-91.172589,30.38938],"type":"Point"}
}