{
  "type": "Feature",
  "properties": {
    "iso:country":"US",
    "sg:address":"3600 Jackson St Exd",
    "sg:city":"Alexandria",
    "sg:classifiers":[
        {
            "category":"Professional",
            "subcategory":"Lawyer & Legal Services",
            "type":"Services"
        }
    ],
    "sg:phone":"+1 318 442 2929",
    "sg:postcode":"71303",
    "sg:province":"LA",
    "sg:tags":[
        "attorney"
    ],
    "wof:name":"Rebecca Alexander",
    "wof:placetype":"venue"
},
  "geometry": {"coordinates":[-92.477177,31.283196],"type":"Point"}
}