{
  "type": "Feature",
  "properties": {
    "iso:country":"US",
    "sg:address":"599 Lincoln Rd",
    "sg:city":"Monroe",
    "sg:classifiers":[
        {
            "category":"Retail",
            "subcategory":"Auto Repair",
            "type":"Services"
        }
    ],
    "sg:phone":"+1 318 345 1439",
    "sg:postcode":"71203",
    "sg:province":"LA",
    "sg:tags":[
        "repairing",
        "automobile"
    ],
    "wof:name":"Lincoln Express Lube",
    "wof:placetype":"venue"
},
  "geometry": {"coordinates":[-92.015298,32.545392],"type":"Point"}
}