{
  "type": "Feature",
  "properties": {
    "addr:full":"1728 Martin Luther King Blvd Houma LA 70360",
    "addr:housenumber":"1728",
    "addr:postcode":"70360",
    "addr:street":"Martin Luther King Blvd",
    "iso:country":"US",
    "sg:address":"1728 Martin Luther King Blvd",
    "sg:city":"Houma",
    "sg:classifiers":[
        {
            "category":"Travel",
            "subcategory":"Hotels & Motels",
            "type":"Entertainment"
        }
    ],
    "sg:phone":"+1 985 873 3140",
    "sg:postcode":"70360",
    "sg:province":"LA",
    "wof:name":"Hampton Inn",
    "wof:placetype":"venue"
},
  "geometry": {"coordinates":[-90.75598100000001,29.613827],"type":"Point"}
}