{
  "type": "Feature",
  "properties": {
    "addr:full":"3728 Whites Ferry Rd West Monroe LA 71291",
    "addr:housenumber":"3728",
    "addr:postcode":"71291",
    "addr:street":"Whites Ferry Rd West",
    "iso:country":"US",
    "sg:address":"3728 Whites Ferry Rd",
    "sg:city":"West Monroe",
    "sg:classifiers":[
        {
            "category":"Retail",
            "subcategory":"Auto Repair",
            "type":"Services"
        }
    ],
    "sg:phone":"+1 318 361 5090",
    "sg:postcode":"71291",
    "sg:province":"LA",
    "sg:tags":[
        "body",
        "automobile",
        "painting"
    ],
    "sg:website":"www.fixitmoose.com",
    "wof:name":"Moose Antley's Collision",
    "wof:placetype":"venue"
},
  "geometry": {"coordinates":[-92.14878,32.54643],"type":"Point"}
}