{
  "type": "Feature",
  "properties": {
    "iso:country":"US",
    "sg:address":"3705 9th St",
    "sg:city":"Alexandria",
    "sg:classifiers":[
        {
            "category":"Building & Trades",
            "subcategory":"Landscaping Services",
            "type":"Services"
        }
    ],
    "sg:phone":"+1 318 473 1004",
    "sg:postcode":"71302",
    "sg:province":"LA",
    "sg:tags":[
        "tree"
    ],
    "wof:name":"Mike Mitchell Tree Svc",
    "wof:placetype":"venue"
},
  "geometry": {"coordinates":[-92.424058,31.289235],"type":"Point"}
}