{
  "type": "Feature",
  "properties": {
    "iso:country":"US",
    "sg:address":"108 Finley Rd",
    "sg:city":"Vivian",
    "sg:classifiers":[
        {
            "category":"Building & Trades",
            "subcategory":"Construction",
            "type":"Services"
        }
    ],
    "sg:phone":"+1 318 375 2464",
    "sg:postcode":"71049",
    "sg:province":"LA",
    "sg:tags":[
        "grading",
        "contractor"
    ],
    "wof:name":"Caddo Parish Highway Dept",
    "wof:placetype":"venue"
},
  "geometry": {"coordinates":[-93.948941,32.053331],"type":"Point"}
}