{
  "type": "Feature",
  "properties": {
    "iso:country":"US",
    "sg:address":"5423 S Sherwood Forest Blvd",
    "sg:city":"Baton Rouge",
    "sg:classifiers":[
        {
            "category":"Banks & Credit Unions",
            "subcategory":"Bank",
            "type":"Services"
        }
    ],
    "sg:phone":"+1 225 214 9400",
    "sg:postcode":"70816",
    "sg:province":"LA",
    "sg:website":"www.keypointfcu.com",
    "wof:name":"Keypoint Federal Credit Union",
    "wof:placetype":"venue"
},
  "geometry": {"coordinates":[-91.051349,30.405927],"type":"Point"}
}