{
  "type": "Feature",
  "properties": {
    "addr:full":"23838 Greenwell Springs Rd Greenwell Spgs LA 70739",
    "addr:housenumber":"23838",
    "addr:postcode":"70739",
    "addr:street":"Greenwell Springs Rd;Spgs",
    "iso:country":"US",
    "sg:address":"23838 Greenwell Springs Rd",
    "sg:city":"Greenwell Spgs",
    "sg:classifiers":[
        {
            "category":"Home & Garden",
            "subcategory":"Furniture",
            "type":"Retail Goods"
        }
    ],
    "sg:phone":"+1 225 261 0116",
    "sg:postcode":"70739",
    "sg:province":"LA",
    "sg:tags":[
        "cabinet"
    ],
    "wof:name":"Ron's Custom Cabinet's",
    "wof:placetype":"venue"
},
  "geometry": {"coordinates":[-90.996168,30.584678],"type":"Point"}
}