{
  "type": "Feature",
  "properties": {
    "iso:country":"US",
    "sg:address":"2255 N Foster Dr",
    "sg:city":"Baton Rouge",
    "sg:classifiers":[
        {
            "category":"Shopping",
            "subcategory":"Clothing, Apparel, & Fashions",
            "type":"Retail Goods"
        }
    ],
    "sg:phone":"+1 225 354 7931",
    "sg:postcode":"70806",
    "sg:province":"LA",
    "sg:tags":[
        "salvage",
        "surplus",
        "merchandise"
    ],
    "wof:name":"Capitol City Wholesale",
    "wof:placetype":"venue"
},
  "geometry": {"coordinates":[-91.139864,30.468945],"type":"Point"}
}