{
  "type": "Feature",
  "properties": {
    "addr:full":"1004 N 18th St Monroe LA 71201",
    "addr:housenumber":"1004",
    "addr:postcode":"71201",
    "addr:street":"N 18Th St",
    "iso:country":"US",
    "sg:address":"1004 N 18th St",
    "sg:city":"Monroe",
    "sg:classifiers":[
        {
            "category":"Shopping",
            "subcategory":"Used Merchandise",
            "type":"Retail Goods"
        }
    ],
    "sg:phone":"+1 318 322 2101",
    "sg:postcode":"71201",
    "sg:province":"LA",
    "sg:tags":[
        "shop",
        "consignment"
    ],
    "wof:name":"Classy Consignments",
    "wof:placetype":"venue"
},
  "geometry": {"coordinates":[-92.108918,32.519818],"type":"Point"}
}