{
  "type": "Feature",
  "properties": {
    "addr:full":"415 Homer Rd Minden LA 71055",
    "addr:housenumber":"415",
    "addr:postcode":"71055",
    "addr:street":"Homer Rd",
    "iso:country":"US",
    "sg:address":"415 Homer Rd",
    "sg:city":"Minden",
    "sg:classifiers":[
        {
            "category":"Real Estate",
            "subcategory":"Real Estate Operator",
            "type":"Services"
        }
    ],
    "sg:phone":"+1 318 377 5115",
    "sg:postcode":"71055",
    "sg:province":"LA",
    "sg:tags":[
        "property",
        "dweller"
    ],
    "wof:name":"Raintree Inv Corp Eighteen",
    "wof:placetype":"venue"
},
  "geometry": {"coordinates":[-93.272762,32.62163],"type":"Point"}
}