{
  "type": "Feature",
  "properties": {
    "iso:country":"US",
    "sg:address":"5559 Plank Rd",
    "sg:city":"Baton Rouge",
    "sg:classifiers":[
        {
            "category":"Insurance",
            "subcategory":"Insurance Agent",
            "type":"Services"
        }
    ],
    "sg:phone":"+1 225 355 1102",
    "sg:postcode":"70805",
    "sg:province":"LA",
    "wof:name":"Banner Insurance Inc",
    "wof:placetype":"venue"
},
  "geometry": {"coordinates":[-91.15287499999999,30.500454],"type":"Point"}
}