{
  "type": "Feature",
  "properties": {
    "iso:country":"US",
    "sg:address":"8350 Earhart Blvd",
    "sg:city":"New Orleans",
    "sg:classifiers":[
        {
            "category":"Sports & Exercise",
            "subcategory":"Gym",
            "type":"Entertainment"
        }
    ],
    "sg:phone":"+1 504 862 9995",
    "sg:postcode":"70118",
    "sg:province":"LA",
    "sg:tags":[
        "club",
        "health",
        "studio",
        "gymnasium"
    ],
    "wof:name":"French Riviera Spa",
    "wof:placetype":"venue"
},
  "geometry": {"coordinates":[-90.117395,29.962799],"type":"Point"}
}