{
  "type": "Feature",
  "properties": {
    "addr:full":"303 Davis Dr Sulphur LA 70663",
    "addr:housenumber":"303",
    "addr:postcode":"70663",
    "addr:street":"Davis Dr",
    "iso:country":"US",
    "sg:address":"303 Davis Dr",
    "sg:city":"Sulphur",
    "sg:classifiers":[
        {
            "category":"Personal",
            "subcategory":"Beauty Salon",
            "type":"Services"
        }
    ],
    "sg:phone":"+1 337 625 2444",
    "sg:postcode":"70663",
    "sg:province":"LA",
    "wof:name":"Studio 303",
    "wof:placetype":"venue"
},
  "geometry": {"coordinates":[-93.32018600000001,30.232674],"type":"Point"}
}