{
  "type": "Feature",
  "properties": {
    "addr:full":"4105 Perkins Rd Baton Rouge LA 70808",
    "addr:housenumber":"4105",
    "addr:postcode":"70808",
    "addr:street":"Perkins Rd",
    "iso:country":"US",
    "sg:address":"4105 Perkins Rd",
    "sg:city":"Baton Rouge",
    "sg:classifiers":[
        {
            "category":"Retail",
            "subcategory":"Car Wash",
            "type":"Services"
        }
    ],
    "sg:phone":"+1 225 214 9274",
    "sg:postcode":"70808",
    "sg:province":"LA",
    "sg:tags":[
        "polishing",
        "washing"
    ],
    "wof:name":"Benny's Xpress Lube",
    "wof:placetype":"venue"
},
  "geometry": {"coordinates":[-91.146811,30.418118],"type":"Point"}
}