{
  "type": "Feature",
  "properties": {
    "iso:country":"US",
    "sg:address":"149 Woodland Dr",
    "sg:city":"La Place",
    "sg:classifiers":[
        {
            "category":"Building & Trades",
            "subcategory":"Cleaning & Sanitation",
            "type":"Services"
        }
    ],
    "sg:phone":"+1 985 536 3560",
    "sg:postcode":"70068",
    "sg:province":"LA",
    "sg:tags":[
        "chemical"
    ],
    "wof:name":"Onyx Industrial Svc",
    "wof:placetype":"venue"
},
  "geometry": {"coordinates":[-90.450328,30.086021],"type":"Point"}
}