{
  "type": "Feature",
  "properties": {
    "addr:full":"2350 Airline Dr Bossier City LA 71111",
    "addr:housenumber":"2350",
    "addr:postcode":"71111",
    "addr:street":"Airline Dr",
    "iso:country":"US",
    "sg:address":"2350 Airline Dr",
    "sg:city":"Bossier City",
    "sg:classifiers":[
        {
            "category":"Shopping",
            "subcategory":"Computers & Home Electronics",
            "type":"Retail Goods"
        }
    ],
    "sg:phone":"+1 318 549 3651",
    "sg:postcode":"71111",
    "sg:province":"LA",
    "sg:tags":[
        "equipment",
        "electronic",
        "supply"
    ],
    "wof:name":"Rex TV",
    "wof:placetype":"venue"
},
  "geometry": {"coordinates":[-93.706687,32.534268],"type":"Point"}
}