{
  "type": "Feature",
  "properties": {
    "iso:country":"US",
    "sg:address":"2705 Senator St",
    "sg:city":"Houma",
    "sg:classifiers":[
        {
            "category":"Shopping",
            "subcategory":"Clothing, Apparel, & Fashions",
            "type":"Retail Goods"
        }
    ],
    "sg:phone":"+1 985 876 9850",
    "sg:postcode":"70363",
    "sg:province":"LA",
    "sg:tags":[
        "item",
        "boutique"
    ],
    "wof:name":"Betty's Boutique",
    "wof:placetype":"venue"
},
  "geometry": {"coordinates":[-90.688254,29.592417],"type":"Point"}
}