{
  "type": "Feature",
  "properties": {
    "iso:country":"US",
    "sg:address":"608 Lafitte St",
    "sg:city":"Mandeville",
    "sg:classifiers":[
        {
            "category":"Education",
            "subcategory":"Special Training",
            "type":"Public Place"
        }
    ],
    "sg:phone":"+1 985 674 2800",
    "sg:postcode":"70448",
    "sg:province":"LA",
    "wof:name":"Study Whiz",
    "wof:placetype":"venue"
},
  "geometry": {"coordinates":[-90.065179,30.36129],"type":"Point"}
}