{
  "type": "Feature",
  "properties": {
    "addr:full":"213 Bendel Rd Lafayette LA 70503",
    "addr:housenumber":"213",
    "addr:postcode":"70503",
    "addr:street":"Bendel Rd",
    "iso:country":"US",
    "sg:address":"213 Bendel Rd",
    "sg:city":"Lafayette",
    "sg:classifiers":[
        {
            "category":"Real Estate",
            "subcategory":"Real Estate Operator",
            "type":"Services"
        }
    ],
    "sg:phone":"+1 337 261 4080",
    "sg:postcode":"70503",
    "sg:province":"LA",
    "sg:tags":[
        "apartment"
    ],
    "wof:name":"Greenwood Investments LLC",
    "wof:placetype":"venue"
},
  "geometry": {"coordinates":[-92.01639,30.199102],"type":"Point"}
}