{
  "type": "Feature",
  "properties": {
    "addr:full":"17801 Highland Rd Baton Rouge LA 70810",
    "addr:housenumber":"17801",
    "addr:postcode":"70810",
    "addr:street":"Highland Rd",
    "iso:country":"US",
    "sg:address":"17801 Highland Rd",
    "sg:city":"Baton Rouge",
    "sg:classifiers":[
        {
            "category":"Government",
            "subcategory":"Police Station",
            "type":"Public Place"
        }
    ],
    "sg:phone":"+1 225 754 8500",
    "sg:postcode":"70810",
    "sg:province":"LA",
    "sg:tags":[
        "state"
    ],
    "wof:name":"State Police",
    "wof:placetype":"venue"
},
  "geometry": {"coordinates":[-91.03245200000001,30.344559],"type":"Point"}
}