{
  "type": "Feature",
  "properties": {
    "iso:country":"US",
    "sg:address":"211 Guilbeau Rd",
    "sg:city":"Lafayette",
    "sg:classifiers":[
        {
            "category":"Shopping",
            "subcategory":"Computers & Home Electronics",
            "type":"Retail Goods"
        }
    ],
    "sg:phone":"+1 337 984 9442",
    "sg:postcode":"70506",
    "sg:province":"LA",
    "sg:tags":[
        "high",
        "fidelity",
        "stereophonic"
    ],
    "wof:name":"Kajun Audio Sounds",
    "wof:placetype":"venue"
},
  "geometry": {"coordinates":[-92.062547,30.195375],"type":"Point"}
}