{
  "type": "Feature",
  "properties": {
    "iso:country":"US",
    "sg:address":"18 Englewood Pkwy",
    "sg:city":"Metairie",
    "sg:classifiers":[
        {
            "category":"Professional",
            "subcategory":"Business Services",
            "type":"Services"
        }
    ],
    "sg:phone":"+1 504 838 6208",
    "sg:postcode":"70005",
    "sg:province":"LA",
    "wof:name":"Bebe Designs",
    "wof:placetype":"venue"
},
  "geometry": {"coordinates":[-90.130049,29.974378],"type":"Point"}
}