{
  "type": "Feature",
  "properties": {
    "iso:country":"US",
    "sg:address":"5024 Windfall Ct",
    "sg:city":"Baton Rouge",
    "sg:classifiers":[
        {
            "category":"Arts & Performance",
            "subcategory":"Theater",
            "type":"Entertainment"
        }
    ],
    "sg:phone":"+1 225 357 0718",
    "sg:postcode":"70812",
    "sg:province":"LA",
    "sg:tags":[
        "group"
    ],
    "wof:name":"Larry Garner",
    "wof:placetype":"venue"
},
  "geometry": {"coordinates":[-91.112122,30.497085],"type":"Point"}
}