{
  "type": "Feature",
  "properties": {
    "addr:full":"8750 Bus Park Dr Shreveport LA 71105",
    "addr:housenumber":"8750",
    "addr:postcode":"71105",
    "addr:street":"Bus Park Dr",
    "iso:country":"US",
    "sg:address":"8750 Bus Park Dr",
    "sg:city":"Shreveport",
    "sg:classifiers":[
        {
            "category":"Autos & Motor Vehicles",
            "subcategory":"Automobile Sales",
            "type":"Retail Goods"
        }
    ],
    "sg:phone":"+1 318 798 7250",
    "sg:postcode":"71105",
    "sg:province":"LA",
    "sg:tags":[
        "car",
        "dealer"
    ],
    "wof:name":"Roundtree Hummer",
    "wof:placetype":"venue"
},
  "geometry": {"coordinates":[-93.72446600000001,32.42113],"type":"Point"}
}