{
  "type": "Feature",
  "properties": {
    "addr:full":"272 Desonier Rd Jeanerette LA 70544",
    "addr:housenumber":"272",
    "addr:postcode":"70544",
    "addr:street":"Desonier Rd",
    "iso:country":"US",
    "sg:address":"272 Desonier Rd",
    "sg:city":"Jeanerette",
    "sg:classifiers":[
        {
            "category":"Retail",
            "subcategory":"Repair Shop",
            "type":"Services"
        }
    ],
    "sg:phone":"+1 337 276 4288",
    "sg:postcode":"70544",
    "sg:province":"LA",
    "sg:tags":[
        "welding"
    ],
    "wof:name":"Provost Brothers Welding",
    "wof:placetype":"venue"
},
  "geometry": {"coordinates":[-91.62465,29.866543],"type":"Point"}
}