{
  "type": "Feature",
  "properties": {
    "iso:country":"US",
    "sg:address":"1000 8th St",
    "sg:city":"Morgan City",
    "sg:classifiers":[
        {
            "category":"Utilities",
            "subcategory":"Mobile Phone",
            "type":"Services"
        }
    ],
    "sg:phone":"+1 985 385 5009",
    "sg:postcode":"70380",
    "sg:province":"LA",
    "sg:tags":[
        "telephone",
        "cellular"
    ],
    "wof:name":"M C Communications",
    "wof:placetype":"venue"
},
  "geometry": {"coordinates":[-91.20228299999999,29.704138],"type":"Point"}
}