{
  "type": "Feature",
  "properties": {
    "iso:country":"US",
    "sg:address":"916 Barron Rd",
    "sg:city":"Keithville",
    "sg:classifiers":[
        {
            "category":"Retail",
            "subcategory":"Repair Shop",
            "type":"Services"
        }
    ],
    "sg:phone":"+1 318 925 8144",
    "sg:postcode":"71047",
    "sg:province":"LA",
    "sg:tags":[
        "equipment",
        "conditioning",
        "air"
    ],
    "wof:name":"Affordable Air",
    "wof:placetype":"venue"
},
  "geometry": {"coordinates":[-93.820036,32.350478],"type":"Point"}
}