{
  "type": "Feature",
  "properties": {
    "iso:country":"US",
    "sg:address":"1960 Surgi Dr",
    "sg:city":"Mandeville",
    "sg:classifiers":[
        {
            "category":"Wholesale",
            "subcategory":"Medical Equipment & Supplies",
            "type":"Manufacturing & Wholesale Goods"
        }
    ],
    "sg:phone":"+1 985 624 9959",
    "sg:postcode":"70448",
    "sg:province":"LA",
    "sg:tags":[
        "hospital"
    ],
    "wof:name":"Covington Medical Systems Inc",
    "wof:placetype":"venue"
},
  "geometry": {"coordinates":[-90.04622500000001,30.379157],"type":"Point"}
}