{
  "type": "Feature",
  "properties": {
    "addr:full":"14441 Coursey Blvd Baton Rouge LA 70817",
    "addr:housenumber":"14441",
    "addr:postcode":"70817",
    "addr:street":"Coursey Blvd",
    "iso:country":"US",
    "sg:address":"14441 Coursey Blvd",
    "sg:city":"Baton Rouge",
    "sg:classifiers":[
        {
            "category":"Autos & Motor Vehicles",
            "subcategory":"Fuel & Gas Station",
            "type":"Retail Goods"
        }
    ],
    "sg:phone":"+1 225 751 0159",
    "sg:postcode":"70817",
    "sg:province":"LA",
    "sg:tags":[
        "oil"
    ],
    "wof:name":"Shannondor Exxon",
    "wof:placetype":"venue"
},
  "geometry": {"coordinates":[-91.02062599999999,30.408186],"type":"Point"}
}