{
  "type": "Feature",
  "properties": {
    "iso:country":"US",
    "sg:address":"1232 Curtis St",
    "sg:city":"Harvey",
    "sg:classifiers":[
        {
            "category":"Farming",
            "subcategory":"Livestock Farm",
            "type":"Manufacturing & Wholesale Goods"
        }
    ],
    "sg:phone":"+1 504 347 5527",
    "sg:postcode":"70058",
    "sg:province":"LA",
    "wof:name":"L&N Friendship Corporation",
    "wof:placetype":"venue"
},
  "geometry": {"coordinates":[-90.087735,29.889915],"type":"Point"}
}