{
  "type": "Feature",
  "properties": {
    "iso:country":"US",
    "sg:address":"2098 Barataria Blvd",
    "sg:city":"Marrero",
    "sg:classifiers":[
        {
            "category":"Banks & Credit Unions",
            "subcategory":"Bank",
            "type":"Services"
        }
    ],
    "sg:phone":"+1 504 362 6313",
    "sg:postcode":"70072",
    "sg:province":"LA",
    "sg:tags":[
        "national",
        "commercial",
        "mortgage"
    ],
    "wof:name":"Regions Bank",
    "wof:placetype":"venue"
},
  "geometry": {"coordinates":[-90.09792899999999,29.871015],"type":"Point"}
}