{
  "type": "Feature",
  "properties": {
    "addr:full":"1211 Coolidge St Lafayette LA 70503",
    "addr:housenumber":"1211",
    "addr:postcode":"70503",
    "addr:street":"Coolidge St",
    "iso:country":"US",
    "sg:address":"1211 Coolidge St",
    "sg:city":"Lafayette",
    "sg:classifiers":[
        {
            "category":"Health Services",
            "subcategory":"Doctor",
            "type":"Services"
        }
    ],
    "sg:phone":"+1 337 234 3278",
    "sg:postcode":"70503",
    "sg:province":"LA",
    "sg:tags":[
        "physician",
        "surgeon"
    ],
    "wof:name":"Lester L Ducote Jr MD",
    "wof:placetype":"venue"
},
  "geometry": {"coordinates":[-92.018406,30.202346],"type":"Point"}
}