{
  "type": "Feature",
  "properties": {
    "iso:country":"US",
    "sg:address":"1106 Center St",
    "sg:city":"New Iberia",
    "sg:classifiers":[
        {
            "category":"Restaurant",
            "type":"Food & Drink"
        }
    ],
    "sg:phone":"+1 337 365 2326",
    "sg:postcode":"70560",
    "sg:province":"LA",
    "wof:name":"Duffy's Diner",
    "wof:placetype":"venue"
},
  "geometry": {"coordinates":[-91.82773299999999,29.994743],"type":"Point"}
}