{
  "type": "Feature",
  "properties": {
    "iso:country":"US",
    "sg:address":"450 Ashley Ridge Blvd",
    "sg:city":"Shreveport",
    "sg:classifiers":[
        {
            "category":"Health Services",
            "subcategory":"Doctor",
            "type":"Services"
        }
    ],
    "sg:phone":"+1 318 868 3688",
    "sg:postcode":"71106",
    "sg:province":"LA",
    "sg:tags":[
        "dentist"
    ],
    "wof:name":"Smile-Brite Family Dental Grp",
    "wof:placetype":"venue"
},
  "geometry": {"coordinates":[-93.73647200000001,32.418318],"type":"Point"}
}