{
  "type": "Feature",
  "properties": {
    "addr:full":"1461 Smyrna Rd Keatchie LA 71046",
    "addr:housenumber":"1461",
    "addr:postcode":"71046",
    "addr:street":"Smyrna Rd",
    "iso:country":"US",
    "sg:address":"1461 Smyrna Rd",
    "sg:city":"Keatchie",
    "sg:classifiers":[
        {
            "category":"Professional",
            "subcategory":"Business Services",
            "type":"Services"
        }
    ],
    "sg:phone":"+1 318 933 8437",
    "sg:postcode":"71046",
    "sg:province":"LA",
    "wof:name":"Adam's Superior Svc",
    "wof:placetype":"venue"
},
  "geometry": {"coordinates":[-93.883145,32.143879],"type":"Point"}
}