{
  "type": "Feature",
  "properties": {
    "iso:country":"US",
    "sg:address":"283 Main St",
    "sg:city":"Grambling",
    "sg:classifiers":[
        {
            "category":"Personal",
            "subcategory":"Beauty Salon",
            "type":"Services"
        }
    ],
    "sg:phone":"+1 318 247 1166",
    "sg:postcode":"71245",
    "sg:province":"LA",
    "wof:name":"Hair Shack",
    "wof:placetype":"venue"
},
  "geometry": {"coordinates":[-92.71397899999999,32.527427],"type":"Point"}
}