{
  "type": "Feature",
  "properties": {
    "iso:country":"US",
    "sg:address":"1823 Magazine St",
    "sg:city":"New Orleans",
    "sg:classifiers":[
        {
            "category":"Restaurant",
            "type":"Food & Drink"
        }
    ],
    "sg:phone":"+1 504 895 1858",
    "sg:postcode":"70130",
    "sg:province":"LA",
    "sg:tags":[
        "eating"
    ],
    "wof:name":"Cuisine Concepts of Louisiana",
    "wof:placetype":"venue"
},
  "geometry": {"coordinates":[-90.073744,29.931767],"type":"Point"}
}