{
  "type": "Feature",
  "properties": {
    "addr:full":"214 Texas Hwy Many LA 71449",
    "addr:housenumber":"214",
    "addr:postcode":"71449",
    "addr:street":"Texas Hwy",
    "iso:country":"US",
    "sg:address":"214 Texas Hwy",
    "sg:city":"Many",
    "sg:classifiers":[
        {
            "category":"Autos & Motor Vehicles",
            "subcategory":"Auto Supplies",
            "type":"Retail Goods"
        }
    ],
    "sg:phone":"+1 318 256 0524",
    "sg:postcode":"71449",
    "sg:province":"LA",
    "sg:tags":[
        "tire"
    ],
    "sg:website":"www.tires.hypermart.net",
    "wof:name":"Mark's Wholesale Tire",
    "wof:placetype":"venue"
},
  "geometry": {"coordinates":[-93.49319,31.564539],"type":"Point"}
}