{
  "type": "Feature",
  "properties": {
    "addr:full":"3513 42nd St Metairie LA 70001",
    "addr:housenumber":"3513",
    "addr:postcode":"70001",
    "addr:street":"42Nd St",
    "iso:country":"US",
    "sg:address":"3513 42nd St",
    "sg:city":"Metairie",
    "sg:classifiers":[
        {
            "category":"Professional",
            "subcategory":"Computer Services",
            "type":"Services"
        }
    ],
    "sg:phone":"+1 504 301 0295",
    "sg:postcode":"70001",
    "sg:province":"LA",
    "wof:name":"American PC Solutions",
    "wof:placetype":"venue"
},
  "geometry": {"coordinates":[-90.161115,29.988721],"type":"Point"}
}