{
  "type": "Feature",
  "properties": {
    "addr:full":"2023 State Rte 15 Winnsboro LA 71295",
    "addr:housenumber":"2023",
    "addr:postcode":"71295",
    "addr:street":"State Rte 15",
    "iso:country":"US",
    "sg:address":"2023 State Rte 15",
    "sg:city":"Winnsboro",
    "sg:classifiers":[
        {
            "category":"Wholesale",
            "subcategory":"Auto Parts",
            "type":"Manufacturing & Wholesale Goods"
        }
    ],
    "sg:phone":"+1 318 435 5815",
    "sg:postcode":"71295",
    "sg:province":"LA",
    "sg:tags":[
        "automobile",
        "rebuilt"
    ],
    "wof:name":"Winnsboro Salvage",
    "wof:placetype":"venue"
},
  "geometry": {"coordinates":[-91.735946,32.228611],"type":"Point"}
}