{
  "type": "Feature",
  "properties": {
    "addr:full":"7777 Hennessy Blvd Baton Rouge LA 70809",
    "addr:housenumber":"7777",
    "addr:postcode":"70809",
    "addr:street":"Hennessy Blvd",
    "iso:country":"US",
    "sg:address":"7777 Hennessy Blvd",
    "sg:city":"Baton Rouge",
    "sg:classifiers":[
        {
            "category":"Professional",
            "subcategory":"Accounting & Tax Preparation",
            "type":"Services"
        }
    ],
    "sg:phone":"+1 225 214 9350",
    "sg:postcode":"70809",
    "sg:province":"LA",
    "sg:tags":[
        "billing"
    ],
    "wof:name":"Lake After Hours-Billing Ofc",
    "wof:placetype":"venue"
},
  "geometry": {"coordinates":[-91.106487,30.402299],"type":"Point"}
}