{
  "type": "Feature",
  "properties": {
    "addr:full":"4150 General Degaulle Dr New Orleans LA 70131",
    "addr:housenumber":"4150",
    "addr:postcode":"70131",
    "addr:street":"General Degaulle Dr",
    "iso:country":"US",
    "sg:address":"4150 General Degaulle Dr",
    "sg:city":"New Orleans",
    "sg:classifiers":[
        {
            "category":"Restaurant",
            "type":"Food & Drink"
        }
    ],
    "sg:phone":"+1 504 392 7030",
    "sg:postcode":"70131",
    "sg:province":"LA",
    "sg:website":"www.piccadilly.com",
    "wof:name":"Piccadilly Cafeteria",
    "wof:placetype":"venue"
},
  "geometry": {"coordinates":[-90.012604,29.9203],"type":"Point"}
}