{
  "type": "Feature",
  "properties": {
    "addr:full":"2438 E Texas St Bossier City LA 71111",
    "addr:housenumber":"2438",
    "addr:postcode":"71111",
    "addr:street":"E Texas St",
    "iso:country":"US",
    "sg:address":"2438 E Texas St",
    "sg:city":"Bossier City",
    "sg:classifiers":[
        {
            "category":"Social Services",
            "type":"Services"
        }
    ],
    "sg:phone":"+1 318 746 1516",
    "sg:postcode":"71111",
    "sg:province":"LA",
    "sg:tags":[
        "counselor",
        "marriage",
        "family"
    ],
    "sg:website":"www.louisianafamilycouncil.com",
    "wof:name":"Louisiana Family Council",
    "wof:placetype":"venue"
},
  "geometry": {"coordinates":[-93.71498200000001,32.528369],"type":"Point"}
}