{
  "type": "Feature",
  "properties": {
    "addr:full":"81635 Hwy 41 Bush LA 70431",
    "addr:housenumber":"81635",
    "addr:postcode":"70431",
    "addr:street":"Hwy 41 Bush La",
    "iso:country":"US",
    "sg:address":"81635 Hwy 41",
    "sg:city":"Bush",
    "sg:classifiers":[
        {
            "category":"Government",
            "subcategory":"Police Station",
            "type":"Public Place"
        }
    ],
    "sg:phone":"+1 985 886 8995",
    "sg:postcode":"70431",
    "sg:province":"LA",
    "sg:tags":[
        "sheriff"
    ],
    "sg:website":"www.stpso.com",
    "wof:name":"St Tammany Parish Sheriff",
    "wof:placetype":"venue"
},
  "geometry": {"coordinates":[-89.896951,30.609157],"type":"Point"}
}