{
  "type": "Feature",
  "properties": {
    "addr:full":"1002 5th Ave Kinder LA 70648",
    "addr:housenumber":"1002",
    "addr:postcode":"70648",
    "addr:street":"5Th Ave",
    "iso:country":"US",
    "sg:address":"1002 5th Ave",
    "sg:city":"Kinder",
    "sg:classifiers":[
        {
            "category":"Organizations",
            "subcategory":"Religious Organization",
            "type":"Services"
        }
    ],
    "sg:phone":"+1 337 738 2254",
    "sg:postcode":"70648",
    "sg:province":"LA",
    "sg:tags":[
        "church"
    ],
    "wof:name":"First United Methodist Church",
    "wof:placetype":"venue"
},
  "geometry": {"coordinates":[-92.846448,30.489138],"type":"Point"}
}