{
  "type": "Feature",
  "properties": {
    "addr:full":"1525 Fullilove Dr Bossier City LA 71112",
    "addr:housenumber":"1525",
    "addr:postcode":"71112",
    "addr:street":"Fullilove Dr",
    "iso:country":"US",
    "sg:address":"1525 Fullilove Dr",
    "sg:city":"Bossier City",
    "sg:classifiers":[
        {
            "category":"Organizations",
            "subcategory":"Non-profit Organization",
            "type":"Services"
        }
    ],
    "sg:phone":"+1 318 747 1211",
    "sg:postcode":"71112",
    "sg:province":"LA",
    "sg:tags":[
        "info",
        "addiction",
        "abuse",
        "treatment",
        "drug"
    ],
    "wof:name":"Adolescent Center",
    "wof:placetype":"venue"
},
  "geometry": {"coordinates":[-93.68888099999999,32.503857],"type":"Point"}
}