{
  "type": "Feature",
  "properties": {
    "iso:country":"US",
    "sg:address":"766 Hwy 1207",
    "sg:city":"Deville",
    "sg:classifiers":[
        {
            "category":"Retail",
            "subcategory":"Repair Shop",
            "type":"Services"
        }
    ],
    "sg:phone":"+1 318 466 0099",
    "sg:postcode":"71328",
    "sg:province":"LA",
    "sg:tags":[
        "equipment",
        "conditioning",
        "air"
    ],
    "wof:name":"Quality Repair",
    "wof:placetype":"venue"
},
  "geometry": {"coordinates":[-92.186258,31.365528],"type":"Point"}
}