{
  "type": "Feature",
  "properties": {
    "addr:full":"9410 Lindale Ave Baton Rouge LA 70815",
    "addr:housenumber":"9410",
    "addr:postcode":"70815",
    "addr:street":"Lindale Ave",
    "iso:country":"US",
    "sg:address":"9410 Lindale Ave",
    "sg:city":"Baton Rouge",
    "sg:phone":"+1 225 926 2944",
    "sg:postcode":"70815",
    "sg:province":"LA",
    "sg:tags":[
        "equipment",
        "station"
    ],
    "wof:name":"Le Blanc & Theriot Equipment",
    "wof:placetype":"venue"
},
  "geometry": {"coordinates":[-91.084795,30.439036],"type":"Point"}
}