{
  "type": "Feature",
  "properties": {
    "iso:country":"US",
    "sg:address":"1036 Bernis Rd",
    "sg:city":"St Martinville",
    "sg:classifiers":[
        {
            "category":"Retail",
            "subcategory":"Repair Shop",
            "type":"Services"
        }
    ],
    "sg:phone":"+1 337 394 3969",
    "sg:postcode":"70582",
    "sg:province":"LA",
    "sg:tags":[
        "welding"
    ],
    "wof:name":"Brian's Welding & Fabrication",
    "wof:placetype":"venue"
},
  "geometry": {"coordinates":[-91.75594599999999,30.18974],"type":"Point"}
}