{
  "type": "Feature",
  "properties": {
    "addr:full":"2233 Saint Charles Ave New Orleans LA 70130",
    "addr:housenumber":"2233",
    "addr:postcode":"70130",
    "addr:street":"Saint Charles Ave",
    "iso:country":"US",
    "sg:address":"2233 Saint Charles Ave",
    "sg:city":"New Orleans",
    "sg:classifiers":[
        {
            "category":"Health Services",
            "subcategory":"Doctor",
            "type":"Services"
        }
    ],
    "sg:phone":"+1 504 891 7762",
    "sg:postcode":"70130",
    "sg:province":"LA",
    "sg:tags":[
        "medical"
    ],
    "wof:name":"Monica McGauly MD",
    "wof:placetype":"venue"
},
  "geometry": {"coordinates":[-90.081709,29.933611],"type":"Point"}
}