{
  "type": "Feature",
  "properties": {
    "addr:full":"2123 Abundance St New Orleans LA 70122",
    "addr:housenumber":"2123",
    "addr:postcode":"70122",
    "addr:street":"Abundance St",
    "iso:country":"US",
    "sg:address":"2123 Abundance St",
    "sg:city":"New Orleans",
    "sg:classifiers":[
        {
            "category":"Retail",
            "subcategory":"Repair Shop",
            "type":"Services"
        }
    ],
    "sg:phone":"+1 504 944 7994",
    "sg:postcode":"70122",
    "sg:province":"LA",
    "sg:tags":[
        "ironwork"
    ],
    "wof:name":"Judo Ornamental Iron Works",
    "wof:placetype":"venue"
},
  "geometry": {"coordinates":[-90.06047700000001,29.988771],"type":"Point"}
}