{
  "type": "Feature",
  "properties": {
    "iso:country":"US",
    "sg:address":"587 N Preston St",
    "sg:city":"Marksville",
    "sg:classifiers":[
        {
            "category":"Professional",
            "subcategory":"Business Services",
            "type":"Services"
        }
    ],
    "sg:phone":"+1 318 253 0803",
    "sg:postcode":"71351",
    "sg:province":"LA",
    "sg:tags":[
        "repossessing"
    ],
    "sg:website":"www.reposses.com",
    "wof:name":"Acadian Associates",
    "wof:placetype":"venue"
},
  "geometry": {"coordinates":[-92.060199,31.13404],"type":"Point"}
}