{
  "type": "Feature",
  "properties": {
    "iso:country":"US",
    "sg:address":"513 Oaklawn Dr",
    "sg:city":"Metairie",
    "sg:classifiers":[
        {
            "category":"Banks & Credit Unions",
            "subcategory":"Bank",
            "type":"Services"
        }
    ],
    "sg:phone":"+1 504 837 0966",
    "sg:postcode":"70005",
    "sg:province":"LA",
    "sg:tags":[
        "national",
        "commercial",
        "product",
        "mfg"
    ],
    "wof:name":"Krasnoff Marketing Group",
    "wof:placetype":"venue"
},
  "geometry": {"coordinates":[-90.13267399999999,30.001205],"type":"Point"}
}