{
  "type": "Feature",
  "properties": {
    "addr:full":"4307 Airline Hwy Baton Rouge LA 70805",
    "addr:housenumber":"4307",
    "addr:postcode":"70805",
    "addr:street":"Airline Hwy",
    "iso:country":"US",
    "sg:address":"4307 Airline Hwy",
    "sg:city":"Baton Rouge",
    "sg:classifiers":[
        {
            "category":"Personal",
            "subcategory":"Beauty Salon",
            "type":"Services"
        }
    ],
    "sg:phone":"+1 225 355 9464",
    "sg:postcode":"70805",
    "sg:province":"LA",
    "sg:tags":[
        "manicuring"
    ],
    "wof:name":"Exquisite Nails",
    "wof:placetype":"venue"
},
  "geometry": {"coordinates":[-91.14825399999999,30.509427],"type":"Point"}
}