{
  "type": "Feature",
  "properties": {
    "iso:country":"US",
    "sg:address":"3233 S Sherwood Forest Blvd",
    "sg:city":"Baton Rouge",
    "sg:classifiers":[
        {
            "category":"Health Services",
            "subcategory":"Doctor",
            "type":"Services"
        }
    ],
    "sg:phone":"+1 225 766 3404",
    "sg:postcode":"70816",
    "sg:province":"LA",
    "sg:tags":[
        "medical"
    ],
    "wof:name":"Dr Tilton Carry",
    "wof:placetype":"venue"
},
  "geometry": {"coordinates":[-91.051402,30.422702],"type":"Point"}
}