{
  "type": "Feature",
  "properties": {
    "iso:country":"US",
    "sg:address":"6502 State Rte 182",
    "sg:city":"Morgan City",
    "sg:classifiers":[
        {
            "category":"Insurance",
            "subcategory":"Insurance Agent",
            "type":"Services"
        }
    ],
    "sg:phone":"+1 985 384 4336",
    "sg:postcode":"70380",
    "sg:province":"LA",
    "sg:tags":[
        "accident"
    ],
    "wof:name":"Milton Le Blanc Insurance",
    "wof:placetype":"venue"
},
  "geometry": {"coordinates":[-91.19575399999999,29.697501],"type":"Point"}
}