{
  "type": "Feature",
  "properties": {
    "addr:full":"16942 Old Hammond Hwy Baton Rouge LA 70816",
    "addr:housenumber":"16942",
    "addr:postcode":"70816",
    "addr:street":"Old Hammond Hwy",
    "iso:country":"US",
    "sg:address":"16942 Old Hammond Hwy",
    "sg:city":"Baton Rouge",
    "sg:classifiers":[
        {
            "category":"Manufacturing",
            "subcategory":"Metals",
            "type":"Manufacturing & Wholesale Goods"
        }
    ],
    "sg:phone":"+1 225 272 1420",
    "sg:postcode":"70816",
    "sg:province":"LA",
    "sg:tags":[
        "pipe",
        "bending",
        "fabricating"
    ],
    "wof:name":"Delta Mechanical Inc",
    "wof:placetype":"venue"
},
  "geometry": {"coordinates":[-91.001665,30.463501],"type":"Point"}
}