{
  "type": "Feature",
  "properties": {
    "iso:country":"US",
    "sg:address":"1502 Front St",
    "sg:city":"Slidell",
    "sg:classifiers":[
        {
            "category":"Health Services",
            "subcategory":"Nursing And Care Facility",
            "type":"Services"
        }
    ],
    "sg:phone":"+1 985 641 7373",
    "sg:postcode":"70458",
    "sg:province":"LA",
    "sg:tags":[
        "hospice"
    ],
    "wof:name":"Hospice Of The Delta",
    "wof:placetype":"venue"
},
  "geometry": {"coordinates":[-89.78093,30.281814],"type":"Point"}
}