{
  "type": "Feature",
  "properties": {
    "addr:full":"7505 Pines Rd Shreveport LA 71129",
    "addr:housenumber":"7505",
    "addr:postcode":"71129",
    "addr:street":"Pines Rd",
    "iso:country":"US",
    "sg:address":"7505 Pines Rd",
    "sg:city":"Shreveport",
    "sg:classifiers":[
        {
            "category":"Building & Trades",
            "subcategory":"Construction",
            "type":"Services"
        }
    ],
    "sg:phone":"+1 318 688 3990",
    "sg:postcode":"71129",
    "sg:province":"LA",
    "sg:tags":[
        "home",
        "builder"
    ],
    "wof:name":"Phillips Custom Home Designs",
    "wof:placetype":"venue"
},
  "geometry": {"coordinates":[-93.86202400000001,32.434981],"type":"Point"}
}