{
  "type": "Feature",
  "properties": {
    "addr:full":"230 Duson St Lafayette LA 70506",
    "addr:housenumber":"230",
    "addr:postcode":"70506",
    "addr:street":"Duson St",
    "iso:country":"US",
    "sg:address":"230 Duson St",
    "sg:city":"Lafayette",
    "sg:classifiers":[
        {
            "category":"Communications",
            "subcategory":"Newspaper",
            "type":"Services"
        }
    ],
    "sg:phone":"+1 337 779 2025",
    "sg:postcode":"70506",
    "sg:province":"LA",
    "sg:tags":[
        "print",
        "medium"
    ],
    "wof:name":"Iota the News",
    "wof:placetype":"venue"
},
  "geometry": {"coordinates":[-92.044549,30.23083],"type":"Point"}
}