{
  "type": "Feature",
  "properties": {
    "addr:full":"340 Aycock St Morgan City LA 70380",
    "addr:housenumber":"340",
    "addr:postcode":"70380",
    "addr:street":"Aycock St",
    "iso:country":"US",
    "sg:address":"340 Aycock St",
    "sg:city":"Morgan City",
    "sg:classifiers":[
        {
            "category":"Building & Trades",
            "subcategory":"Construction",
            "type":"Services"
        }
    ],
    "sg:phone":"+1 985 384 8951",
    "sg:postcode":"70380",
    "sg:province":"LA",
    "sg:tags":[
        "general",
        "contractor"
    ],
    "wof:name":"Babin Construction Inc",
    "wof:placetype":"venue"
},
  "geometry": {"coordinates":[-91.165329,29.691254],"type":"Point"}
}