{
  "type": "Feature",
  "properties": {
    "addr:full":"3330 Front St Winnsboro LA 71295",
    "addr:housenumber":"3330",
    "addr:postcode":"71295",
    "addr:street":"Front St",
    "iso:country":"US",
    "sg:address":"3330 Front St",
    "sg:city":"Winnsboro",
    "sg:classifiers":[
        {
            "category":"Restaurant",
            "type":"Food & Drink"
        }
    ],
    "sg:menulink":"http://www.allmenus.com/la/winnsboro/188479-mcdonalds/menu/",
    "sg:postcode":"71295",
    "sg:province":"LA",
    "sg:tags":[
        "burger",
        "american"
    ],
    "wof:name":"McDonald's",
    "wof:placetype":"venue"
},
  "geometry": {"coordinates":[-91.715265,32.156875],"type":"Point"}
}