{
  "type": "Feature",
  "properties": {
    "iso:country":"US",
    "sg:address":"3100 River Rd",
    "sg:city":"Jefferson",
    "sg:classifiers":[
        {
            "category":"Manufacturing",
            "subcategory":"Watercraft",
            "type":"Manufacturing & Wholesale Goods"
        }
    ],
    "sg:phone":"+1 504 835 8531",
    "sg:postcode":"70121",
    "sg:province":"LA",
    "sg:tags":[
        "barge"
    ],
    "wof:name":"Intercoastal Marine Repairs",
    "wof:placetype":"venue"
},
  "geometry": {"coordinates":[-90.15751,29.958787],"type":"Point"}
}