{
  "type": "Feature",
  "properties": {
    "addr:full":"10044 Hooper Rd Baton Rouge LA 70818",
    "addr:housenumber":"10044",
    "addr:postcode":"70818",
    "addr:street":"Hooper Rd",
    "iso:country":"US",
    "sg:address":"10044 Hooper Rd",
    "sg:city":"Baton Rouge",
    "sg:classifiers":[
        {
            "category":"Shopping",
            "subcategory":"Bicycles & Sporting Goods",
            "type":"Retail Goods"
        }
    ],
    "sg:phone":"+1 225 261 4860",
    "sg:postcode":"70818",
    "sg:province":"LA",
    "sg:tags":[
        "gun",
        "gunsmith"
    ],
    "wof:name":"Reynerson's Gunsmith Svc Inc",
    "wof:placetype":"venue"
},
  "geometry": {"coordinates":[-91.074873,30.538152],"type":"Point"}
}