{
  "type": "Feature",
  "properties": {
    "iso:country":"US",
    "sg:address":"408 Marchand Dr",
    "sg:city":"Donaldsonville",
    "sg:classifiers":[
        {
            "category":"Insurance",
            "subcategory":"Insurance Agent",
            "type":"Services"
        }
    ],
    "sg:phone":"+1 225 473 4226",
    "sg:postcode":"70346",
    "sg:province":"LA",
    "wof:name":"D'Ville Insurance Inc",
    "wof:placetype":"venue"
},
  "geometry": {"coordinates":[-90.990289,30.099153],"type":"Point"}
}