{
  "type": "Feature",
  "properties": {
    "addr:full":"805 Tanglewood Dr Alexandria LA 71303",
    "addr:housenumber":"805",
    "addr:postcode":"71303",
    "addr:street":"Tanglewood Dr",
    "iso:country":"US",
    "sg:address":"805 Tanglewood Dr",
    "sg:city":"Alexandria",
    "sg:classifiers":[
        {
            "category":"Professional",
            "subcategory":"Secretarial Services",
            "type":"Services"
        }
    ],
    "sg:phone":"+1 318 443 8759",
    "sg:postcode":"71303",
    "sg:province":"LA",
    "sg:tags":[
        "reporting",
        "court"
    ],
    "wof:name":"M & S Court Reporters Inc",
    "wof:placetype":"venue"
},
  "geometry": {"coordinates":[-92.48402299999999,31.292692],"type":"Point"}
}