{
  "type": "Feature",
  "properties": {
    "addr:full":"202 Toledo Dr Lafayette LA 70506",
    "addr:housenumber":"202",
    "addr:postcode":"70506",
    "addr:street":"Toledo Dr",
    "iso:country":"US",
    "sg:address":"202 Toledo Dr",
    "sg:city":"Lafayette",
    "sg:classifiers":[
        {
            "category":"Building & Trades",
            "subcategory":"Construction",
            "type":"Services"
        }
    ],
    "sg:phone":"+1 337 235 9401",
    "sg:postcode":"70506",
    "sg:province":"LA",
    "sg:tags":[
        "contractor"
    ],
    "wof:name":"Mouton J B Inc",
    "wof:placetype":"venue"
},
  "geometry": {"coordinates":[-92.060097,30.228901],"type":"Point"}
}