{
  "type": "Feature",
  "properties": {
    "iso:country":"US",
    "sg:address":"1408 W Thomas St",
    "sg:city":"Hammond",
    "sg:classifiers":[
        {
            "category":"Manufacturing",
            "subcategory":"Printing",
            "type":"Manufacturing & Wholesale Goods"
        }
    ],
    "sg:phone":"+1 985 345 0651",
    "sg:postcode":"70401",
    "sg:province":"LA",
    "sg:tags":[
        "printer"
    ],
    "wof:name":"Speedway Printing & Copy Ctr",
    "wof:placetype":"venue"
},
  "geometry": {"coordinates":[-90.47577200000001,30.50104],"type":"Point"}
}