{
  "type": "Feature",
  "properties": {
    "iso:country":"US",
    "sg:address":"405 Vernon St",
    "sg:city":"Newllano",
    "sg:classifiers":[
        {
            "category":"Personal",
            "subcategory":"Beauty Salon",
            "type":"Services"
        }
    ],
    "sg:phone":"+1 337 392 0670",
    "sg:postcode":"71461",
    "sg:province":"LA",
    "wof:name":"Hair It Is",
    "wof:placetype":"venue"
},
  "geometry": {"coordinates":[-93.274253,31.112792],"type":"Point"}
}