{
  "type": "Feature",
  "properties": {
    "iso:country":"US",
    "sg:address":"7643 Jefferson Hwy",
    "sg:city":"Baton Rouge",
    "sg:classifiers":[
        {
            "category":"Shopping",
            "subcategory":"Jewelry",
            "type":"Retail Goods"
        }
    ],
    "sg:phone":"+1 225 927 6299",
    "sg:postcode":"70809",
    "sg:province":"LA",
    "sg:tags":[
        "jeweler"
    ],
    "wof:name":"Classic Jewelers",
    "wof:placetype":"venue"
},
  "geometry": {"coordinates":[-91.108362,30.429912],"type":"Point"}
}