{
  "type": "Feature",
  "properties": {
    "addr:full":"2306 W Pinhook Rd Lafayette LA 70508",
    "addr:housenumber":"2306",
    "addr:postcode":"70508",
    "addr:street":"W Pinhook Rd",
    "iso:country":"US",
    "sg:address":"2306 W Pinhook Rd",
    "sg:city":"Lafayette",
    "sg:classifiers":[
        {
            "category":"Banks & Credit Unions",
            "subcategory":"Bank",
            "type":"Services"
        }
    ],
    "sg:phone":"+1 337 232 3221",
    "sg:postcode":"70508",
    "sg:province":"LA",
    "wof:name":"M C Bank & Trust Co",
    "wof:placetype":"venue"
},
  "geometry": {"coordinates":[-92.008223,30.183688],"type":"Point"}
}