{
  "type": "Feature",
  "properties": {
    "iso:country":"US",
    "sg:address":"602 Ardoin St",
    "sg:city":"Ville Platte",
    "sg:classifiers":[
        {
            "category":"Organizations",
            "subcategory":"Religious Organization",
            "type":"Services"
        }
    ],
    "sg:phone":"+1 337 363 2034",
    "sg:postcode":"70586",
    "sg:province":"LA",
    "sg:tags":[
        "church"
    ],
    "wof:name":"Greater Mt Pleasant Bapt Chr",
    "wof:placetype":"venue"
},
  "geometry": {"coordinates":[-92.288853,30.688221],"type":"Point"}
}