{
  "type": "Feature",
  "properties": {
    "iso:country":"US",
    "sg:address":"3341 Magazine St",
    "sg:city":"New Orleans",
    "sg:classifiers":[
        {
            "category":"Professional",
            "subcategory":"Accounting & Tax Preparation",
            "type":"Services"
        }
    ],
    "sg:phone":"+1 504 895 8666",
    "sg:postcode":"70115",
    "sg:province":"LA",
    "sg:tags":[
        "return",
        "filing"
    ],
    "wof:name":"Jackson Hewitt Tax Svc",
    "wof:placetype":"venue"
},
  "geometry": {"coordinates":[-90.088458,29.923255],"type":"Point"}
}