{
  "type": "Feature",
  "properties": {
    "iso:country":"US",
    "sg:address":"925 Fulwar Skipwith Rd",
    "sg:city":"Baton Rouge",
    "sg:classifiers":[
        {
            "category":"Professional",
            "subcategory":"Business Services",
            "type":"Services"
        }
    ],
    "sg:phone":"+1 225 752 7406",
    "sg:postcode":"70810",
    "sg:province":"LA",
    "sg:tags":[
        "report"
    ],
    "wof:name":"Nancy Rabalais",
    "wof:placetype":"venue"
},
  "geometry": {"coordinates":[-91.047512,30.341371],"type":"Point"}
}