{
  "type": "Feature",
  "properties": {
    "addr:full":"208 E Thomas St Hammond LA 70401",
    "addr:housenumber":"208",
    "addr:postcode":"70401",
    "addr:street":"E Thomas St",
    "iso:country":"US",
    "sg:address":"208 E Thomas St",
    "sg:city":"Hammond",
    "sg:classifiers":[
        {
            "category":"Professional",
            "subcategory":"Computer Services",
            "type":"Services"
        }
    ],
    "sg:phone":"+1 985 345 1548",
    "sg:postcode":"70401",
    "sg:province":"LA",
    "sg:tags":[
        "consultant",
        "designer"
    ],
    "wof:name":"Ram Computer Svc LLC",
    "wof:placetype":"venue"
},
  "geometry": {"coordinates":[-90.458641,30.504554],"type":"Point"}
}