{
  "type": "Feature",
  "properties": {
    "iso:country":"US",
    "sg:address":"3401 N Hullen St",
    "sg:city":"Metairie",
    "sg:classifiers":[
        {
            "category":"Restaurant",
            "type":"Food & Drink"
        }
    ],
    "sg:menulink":"http://www.allmenus.com/la/metairie/25583-anselmos/menu/",
    "sg:phone":"+1 504 889 1212",
    "sg:postcode":"70002",
    "sg:province":"LA",
    "sg:tags":[
        "italian"
    ],
    "wof:name":"Anselmo's",
    "wof:placetype":"venue"
},
  "geometry": {"coordinates":[-90.15800400000001,30.010181],"type":"Point"}
}