{
  "type": "Feature",
  "properties": {
    "iso:country":"US",
    "sg:address":"600 Thompson Rd",
    "sg:city":"Houma",
    "sg:classifiers":[
        {
            "category":"Retail",
            "subcategory":"Repair Shop",
            "type":"Services"
        }
    ],
    "sg:phone":"+1 985 851 3755",
    "sg:postcode":"70363",
    "sg:province":"LA",
    "sg:tags":[
        "welding"
    ],
    "wof:name":"U S Welding Svc Inc",
    "wof:placetype":"venue"
},
  "geometry": {"coordinates":[-90.678894,29.545555],"type":"Point"}
}