{
  "type": "Feature",
  "properties": {
    "iso:country":"US",
    "sg:address":"9000 Patricia St",
    "sg:city":"Chalmette",
    "sg:classifiers":[
        {
            "category":"Health Services",
            "subcategory":"Doctor",
            "type":"Services"
        }
    ],
    "sg:phone":"+1 504 277 0434",
    "sg:postcode":"70043",
    "sg:province":"LA",
    "sg:tags":[
        "cardiologist"
    ],
    "wof:name":"Chalmette Patricia",
    "wof:placetype":"venue"
},
  "geometry": {"coordinates":[-89.971001,29.9568],"type":"Point"}
}