{
  "type": "Feature",
  "properties": {
    "iso:country":"US",
    "sg:address":"6744 Kinloch St",
    "sg:city":"Winnsboro",
    "sg:classifiers":[
        {
            "category":"Insurance",
            "subcategory":"Insurance Agent",
            "type":"Services"
        }
    ],
    "sg:phone":"+1 318 435 5643",
    "sg:postcode":"71295",
    "sg:province":"LA",
    "wof:name":"Cuave Insurance",
    "wof:placetype":"venue"
},
  "geometry": {"coordinates":[-91.72171400000001,32.167316],"type":"Point"}
}