{
  "type": "Feature",
  "properties": {
    "iso:country":"US",
    "sg:address":"622 18th Ave",
    "sg:city":"Franklinton",
    "sg:classifiers":[
        {
            "category":"Organizations",
            "subcategory":"Religious Organization",
            "type":"Services"
        }
    ],
    "sg:phone":"+1 985 839 2318",
    "sg:postcode":"70438",
    "sg:province":"LA",
    "sg:tags":[
        "church"
    ],
    "wof:name":"Winan United Methodist Church",
    "wof:placetype":"venue"
},
  "geometry": {"coordinates":[-90.146755,30.854432],"type":"Point"}
}