{
  "type": "Feature",
  "properties": {
    "iso:country":"US",
    "sg:address":"111 Little Creek Ln",
    "sg:city":"Covington",
    "sg:classifiers":[
        {
            "category":"Building & Trades",
            "subcategory":"Plumbing",
            "type":"Services"
        }
    ],
    "sg:phone":"+1 985 893 2794",
    "sg:postcode":"70433",
    "sg:province":"LA",
    "sg:tags":[
        "conditioning",
        "air",
        "system",
        "contractor"
    ],
    "wof:name":"A Efficient A/C & Heat",
    "wof:placetype":"venue"
},
  "geometry": {"coordinates":[-90.067167,30.417558],"type":"Point"}
}