{
  "type": "Feature",
  "properties": {
    "iso:country":"US",
    "sg:address":"4225 Franklin Ave",
    "sg:city":"New Orleans",
    "sg:classifiers":[
        {
            "category":"Organizations",
            "subcategory":"Religious Organization",
            "type":"Services"
        }
    ],
    "sg:phone":"+1 504 941 6010",
    "sg:postcode":"70122",
    "sg:province":"LA",
    "wof:name":"Presbytery of South Louisiana",
    "wof:placetype":"venue"
},
  "geometry": {"coordinates":[-90.049983,30.002187],"type":"Point"}
}