{
  "type": "Feature",
  "properties": {
    "iso:country":"US",
    "sg:address":"13202 Rodrigue Rd",
    "sg:city":"Loreauville",
    "sg:classifiers":[
        {
            "category":"Farming",
            "subcategory":"Farm",
            "type":"Manufacturing & Wholesale Goods"
        }
    ],
    "sg:phone":"+1 337 229 6607",
    "sg:postcode":"70552",
    "sg:province":"LA",
    "wof:name":"Bret Frederick Farm Inc",
    "wof:placetype":"venue"
},
  "geometry": {"coordinates":[-91.654337,30.080857],"type":"Point"}
}