{
  "type": "Feature",
  "properties": {
    "iso:country":"US",
    "sg:address":"16175 Shenandoah Ave",
    "sg:city":"Baton Rouge",
    "sg:classifiers":[
        {
            "category":"Personal",
            "type":"Services"
        }
    ],
    "sg:phone":"+1 225 755 2425",
    "sg:postcode":"70817",
    "sg:province":"LA",
    "sg:tags":[
        "miscellaneous"
    ],
    "wof:name":"Dinner's Ready Personal Chef",
    "wof:placetype":"venue"
},
  "geometry": {"coordinates":[-91.00615500000001,30.396272],"type":"Point"}
}