{
  "type": "Feature",
  "properties": {
    "addr:full":"2632 N Dumont Dr Baton Rouge LA 70814",
    "addr:housenumber":"2632",
    "addr:postcode":"70814",
    "addr:street":"N Dumont Dr",
    "iso:country":"US",
    "sg:address":"2632 N Dumont Dr",
    "sg:city":"Baton Rouge",
    "sg:classifiers":[
        {
            "category":"Wholesale",
            "subcategory":"Construction Materials",
            "type":"Manufacturing & Wholesale Goods"
        }
    ],
    "sg:phone":"+1 225 272 8044",
    "sg:postcode":"70814",
    "sg:province":"LA",
    "sg:tags":[
        "marble"
    ],
    "wof:name":"Alfortish Marble & Granite",
    "wof:placetype":"venue"
},
  "geometry": {"coordinates":[-91.050792,30.473576],"type":"Point"}
}