{
  "type": "Feature",
  "properties": {
    "addr:full":"2436 Jolet St Houma LA 70360",
    "addr:postcode":"2436;70360",
    "addr:street":"Jolet St",
    "iso:country":"US",
    "sg:address":"2436 Jolet St",
    "sg:city":"Houma",
    "sg:classifiers":[
        {
            "category":"Building & Trades",
            "subcategory":"Construction",
            "type":"Services"
        }
    ],
    "sg:phone":"+1 985 868 4324",
    "sg:postcode":"70360",
    "sg:province":"LA",
    "sg:tags":[
        "contractor",
        "painting",
        "hanging"
    ],
    "wof:name":"Cb S Painting",
    "wof:placetype":"venue"
},
  "geometry": {"coordinates":[-90.755242,29.625502],"type":"Point"}
}