{
  "type": "Feature",
  "properties": {
    "iso:country":"US",
    "sg:address":"100 S River Rd",
    "sg:city":"Port Allen",
    "sg:classifiers":[
        {
            "category":"Museum",
            "type":"Entertainment"
        }
    ],
    "sg:phone":"+1 225 344 5272",
    "sg:postcode":"70767",
    "sg:province":"LA",
    "sg:website":"www.lascmuseum.org",
    "wof:name":"Louisiana Arts & Science Ctr",
    "wof:placetype":"venue"
},
  "geometry": {"coordinates":[-91.202986,30.45166],"type":"Point"}
}