{
  "type": "Feature",
  "properties": {
    "iso:country":"US",
    "sg:address":"307 Dunboyne Pl",
    "sg:city":"Thibodaux",
    "sg:classifiers":[
        {
            "category":"Wholesale",
            "subcategory":"Computers",
            "type":"Manufacturing & Wholesale Goods"
        }
    ],
    "sg:phone":"+1 985 691 3013",
    "sg:postcode":"70301",
    "sg:province":"LA",
    "sg:tags":[
        "software"
    ],
    "wof:name":"Navigator Offshore LLC",
    "wof:placetype":"venue"
},
  "geometry": {"coordinates":[-90.80580500000001,29.793092],"type":"Point"}
}