{
  "type": "Feature",
  "properties": {
    "iso:country":"US",
    "sg:address":"2119 Elysian Fields Ave",
    "sg:city":"New Orleans",
    "sg:classifiers":[
        {
            "category":"Real Estate",
            "subcategory":"Real Estate Services",
            "type":"Services"
        }
    ],
    "sg:phone":"+1 504 944 2100",
    "sg:postcode":"70117",
    "sg:province":"LA",
    "sg:tags":[
        "management",
        "property"
    ],
    "sg:website":"www.tlcrealty-inc.com",
    "wof:name":"Tlc Realty Inc",
    "wof:placetype":"venue"
},
  "geometry": {"coordinates":[-90.057602,29.979],"type":"Point"}
}