{
  "type": "Feature",
  "properties": {
    "iso:country":"US",
    "sg:address":"9955 Old Hammond Hwy",
    "sg:city":"Baton Rouge",
    "sg:classifiers":[
        {
            "category":"Organizations",
            "subcategory":"Religious Organization",
            "type":"Services"
        }
    ],
    "sg:phone":"+1 225 926 8358",
    "sg:postcode":"70816",
    "sg:province":"LA",
    "sg:tags":[
        "church"
    ],
    "sg:website":"www.1stnazarene.org",
    "wof:name":"First Church Of The Nazarene",
    "wof:placetype":"venue"
},
  "geometry": {"coordinates":[-91.078485,30.43187],"type":"Point"}
}