{
  "type": "Feature",
  "properties": {
    "iso:country":"US",
    "sg:address":"532 Front St",
    "sg:city":"Cottonport",
    "sg:classifiers":[
        {
            "category":"Banks & Credit Unions",
            "subcategory":"Bank",
            "type":"Services"
        }
    ],
    "sg:phone":"+1 318 876 2511",
    "sg:postcode":"71327",
    "sg:province":"LA",
    "sg:tags":[
        "financing"
    ],
    "wof:name":"Cypress Financial Corp",
    "wof:placetype":"venue"
},
  "geometry": {"coordinates":[-92.06650399999999,30.994426],"type":"Point"}
}