{
  "type": "Feature",
  "properties": {
    "iso:country":"US",
    "sg:address":"19177 State Rte 643",
    "sg:city":"Vacherie",
    "sg:classifiers":[
        {
            "category":"Education",
            "subcategory":"School",
            "type":"Public Place"
        }
    ],
    "sg:phone":"+1 225 265 7747",
    "sg:postcode":"70090",
    "sg:province":"LA",
    "wof:name":"Vacherie Primary School",
    "wof:placetype":"venue"
},
  "geometry": {"coordinates":[-90.67592500000001,29.930082],"type":"Point"}
}