{
  "type": "Feature",
  "properties": {
    "iso:country":"US",
    "sg:address":"770 Gause Blvd",
    "sg:city":"Slidell",
    "sg:classifiers":[
        {
            "category":"Insurance",
            "subcategory":"Insurance Agent",
            "type":"Services"
        }
    ],
    "sg:phone":"+1 985 641 4551",
    "sg:postcode":"70458",
    "sg:province":"LA",
    "wof:name":"Allstate Insurance",
    "wof:placetype":"venue"
},
  "geometry": {"coordinates":[-89.771063,30.284799],"type":"Point"}
}