{
  "type": "Feature",
  "properties": {
    "iso:country":"US",
    "sg:address":"23425 Railroad Ave",
    "sg:city":"Plaquemine",
    "sg:classifiers":[
        {
            "category":"Building & Trades",
            "subcategory":"Construction",
            "type":"Services"
        }
    ],
    "sg:phone":"+1 225 687 3200",
    "sg:postcode":"70764",
    "sg:province":"LA",
    "sg:tags":[
        "general",
        "contractor"
    ],
    "wof:name":"J E Jumonville Contractors Inc",
    "wof:placetype":"venue"
},
  "geometry": {"coordinates":[-91.236644,30.290574],"type":"Point"}
}