{
  "type": "Feature",
  "properties": {
    "addr:full":"4715 Line Ave Shreveport LA 71106",
    "addr:housenumber":"4715",
    "addr:postcode":"71106",
    "addr:street":"Line Ave",
    "iso:country":"US",
    "sg:address":"4715 Line Ave",
    "sg:city":"Shreveport",
    "sg:classifiers":[
        {
            "category":"Freight",
            "type":"Transportation"
        }
    ],
    "sg:phone":"+1 318 869 4900",
    "sg:postcode":"71106",
    "sg:province":"LA",
    "sg:tags":[
        "broker",
        "agent"
    ],
    "wof:name":"TPS",
    "wof:placetype":"venue"
},
  "geometry": {"coordinates":[-93.74597,32.459267],"type":"Point"}
}