{
  "type": "Feature",
  "properties": {
    "iso:country":"US",
    "sg:address":"5908 Caroline Dr",
    "sg:city":"Alexandria",
    "sg:classifiers":[
        {
            "category":"Building & Trades",
            "subcategory":"Landscaping Services",
            "type":"Services"
        }
    ],
    "sg:phone":"+1 318 442 2682",
    "sg:postcode":"71301",
    "sg:province":"LA",
    "sg:tags":[
        "landscape",
        "contractor"
    ],
    "wof:name":"Donald R Mc Math",
    "wof:placetype":"venue"
},
  "geometry": {"coordinates":[-92.468654,31.256121],"type":"Point"}
}