{
  "type": "Feature",
  "properties": {
    "addr:full":"583 I- 10 Mobile Village Rd Lake Charles LA 70615",
    "addr:housenumber":"583;10",
    "addr:postcode":"70615",
    "addr:street":"I;Mobile Village Rd",
    "iso:country":"US",
    "sg:address":"583 I- 10 Mobile Village Rd",
    "sg:city":"Lake Charles",
    "sg:classifiers":[
        {
            "category":"Travel",
            "subcategory":"Campground",
            "type":"Entertainment"
        }
    ],
    "sg:phone":"+1 337 433 2077",
    "sg:postcode":"70615",
    "sg:province":"LA",
    "wof:name":"I-10 Mobile Home Village",
    "wof:placetype":"venue"
},
  "geometry": {"coordinates":[-93.08097100000001,30.250143],"type":"Point"}
}