{
  "type": "Feature",
  "properties": {
    "addr:full":"2061 Hwy 557 West Monroe LA 71292",
    "addr:housenumber":"2061",
    "addr:postcode":"71292",
    "addr:street":"Hwy 557 West;La",
    "iso:country":"US",
    "sg:address":"2061 Hwy 557",
    "sg:city":"West Monroe",
    "sg:classifiers":[
        {
            "category":"Wholesale",
            "subcategory":"Electrical",
            "type":"Manufacturing & Wholesale Goods"
        }
    ],
    "sg:phone":"+1 318 325 0090",
    "sg:postcode":"71292",
    "sg:province":"LA",
    "sg:tags":[
        "communication",
        "radio",
        "system"
    ],
    "wof:name":"Custom Communication Svc",
    "wof:placetype":"venue"
},
  "geometry": {"coordinates":[-92.205262,32.376012],"type":"Point"}
}