{
  "type": "Feature",
  "properties": {
    "addr:full":"1611 Bertrand Dr Lafayette LA 70506",
    "addr:housenumber":"1611",
    "addr:postcode":"70506",
    "addr:street":"Bertrand Dr",
    "iso:country":"US",
    "sg:address":"1611 Bertrand Dr",
    "sg:city":"Lafayette",
    "sg:classifiers":[
        {
            "category":"Autos & Motor Vehicles",
            "subcategory":"Fuel & Gas Station",
            "type":"Retail Goods"
        }
    ],
    "sg:phone":"+1 337 232 9664",
    "sg:postcode":"70506",
    "sg:province":"LA",
    "sg:tags":[
        "oil"
    ],
    "wof:name":"Bertrand Chevron",
    "wof:placetype":"venue"
},
  "geometry": {"coordinates":[-92.05587199999999,30.224634],"type":"Point"}
}