{
  "type": "Feature",
  "properties": {
    "iso:country":"US",
    "sg:address":"309 E Mark St",
    "sg:city":"Marksville",
    "sg:classifiers":[
        {
            "category":"Professional",
            "subcategory":"Business Services",
            "type":"Services"
        }
    ],
    "sg:phone":"+1 318 253 5044",
    "sg:postcode":"71351",
    "sg:province":"LA",
    "sg:website":"www.infinitynet.org",
    "wof:name":"Infinity Networks",
    "wof:placetype":"venue"
},
  "geometry": {"coordinates":[-92.06314,31.124885],"type":"Point"}
}