{
  "type": "Feature",
  "properties": {
    "addr:full":"1002 8th St Morgan City LA 70380",
    "addr:housenumber":"1002",
    "addr:postcode":"70380",
    "addr:street":"8Th St",
    "iso:country":"US",
    "sg:address":"1002 8th St",
    "sg:city":"Morgan City",
    "sg:classifiers":[
        {
            "category":"Insurance",
            "subcategory":"Insurance Agent",
            "type":"Services"
        }
    ],
    "sg:phone":"+1 985 702 0607",
    "sg:postcode":"70380",
    "sg:province":"LA",
    "wof:name":"Allstate Insurance",
    "wof:placetype":"venue"
},
  "geometry": {"coordinates":[-91.20220500000001,29.704148],"type":"Point"}
}