{
  "type": "Feature",
  "properties": {
    "iso:country":"US",
    "sg:address":"4401 Lake St",
    "sg:city":"Lake Charles",
    "sg:classifiers":[
        {
            "category":"Personal",
            "subcategory":"Beauty Salon",
            "type":"Services"
        }
    ],
    "sg:phone":"+1 337 474 4606",
    "sg:postcode":"70605",
    "sg:province":"LA",
    "wof:name":"Ritz Inc",
    "wof:placetype":"venue"
},
  "geometry": {"coordinates":[-93.232294,30.179442],"type":"Point"}
}