{
  "type": "Feature",
  "properties": {
    "iso:country":"US",
    "sg:address":"820 W 15th St",
    "sg:city":"Crowley",
    "sg:classifiers":[
        {
            "category":"Education",
            "subcategory":"School",
            "type":"Public Place"
        }
    ],
    "sg:phone":"+1 337 783 8755",
    "sg:postcode":"70526",
    "sg:province":"LA",
    "wof:name":"North Crowley Elementary Schl",
    "wof:placetype":"venue"
},
  "geometry": {"coordinates":[-92.386855,30.220593],"type":"Point"}
}