{
  "type": "Feature",
  "properties": {
    "iso:country":"US",
    "sg:address":"908 Harrison Ave",
    "sg:city":"New Orleans",
    "sg:classifiers":[
        {
            "category":"Personal",
            "subcategory":"Shoe Repair & Shine",
            "type":"Services"
        }
    ],
    "sg:phone":"+1 504 488 5505",
    "sg:postcode":"70124",
    "sg:province":"LA",
    "sg:tags":[
        "repairing",
        "parlor",
        "boot"
    ],
    "wof:name":"Joe's Cobbler Workbench Inc",
    "wof:placetype":"venue"
},
  "geometry": {"coordinates":[-90.103651,30.004134],"type":"Point"}
}