{
  "type": "Feature",
  "properties": {
    "iso:country":"US",
    "sg:address":"1306 Octavia St",
    "sg:city":"New Orleans",
    "sg:classifiers":[
        {
            "category":"Communications",
            "subcategory":"Film & Video Production",
            "type":"Services"
        }
    ],
    "sg:phone":"+1 504 269 3033",
    "sg:postcode":"70115",
    "sg:province":"LA",
    "sg:tags":[
        "motion"
    ],
    "wof:name":"Purple Cow Productions",
    "wof:placetype":"venue"
},
  "geometry": {"coordinates":[-90.114617,29.926763],"type":"Point"}
}