{
  "type": "Feature",
  "properties": {
    "addr:full":"1821 Royal Ave Monroe LA 71201",
    "addr:housenumber":"1821",
    "addr:postcode":"71201",
    "addr:street":"Royal Ave",
    "iso:country":"US",
    "sg:address":"1821 Royal Ave",
    "sg:city":"Monroe",
    "sg:classifiers":[
        {
            "category":"Professional",
            "subcategory":"Management & Consulting",
            "type":"Services"
        }
    ],
    "sg:phone":"+1 318 322 3846",
    "sg:postcode":"71201",
    "sg:province":"LA",
    "sg:tags":[
        "fuel"
    ],
    "wof:name":"Royal Plaza Management Ofc",
    "wof:placetype":"venue"
},
  "geometry": {"coordinates":[-92.108519,32.521332],"type":"Point"}
}