{
  "type": "Feature",
  "properties": {
    "addr:full":"4020 Pontchartrain Dr Slidell LA 70458",
    "addr:housenumber":"4020",
    "addr:postcode":"70458",
    "addr:street":"Pontchartrain Dr",
    "iso:country":"US",
    "sg:address":"4020 Pontchartrain Dr",
    "sg:city":"Slidell",
    "sg:classifiers":[
        {
            "category":"Food & Beverages",
            "subcategory":"Groceries & Convenience Stores",
            "type":"Retail Goods"
        }
    ],
    "sg:phone":"+1 985 646 1720",
    "sg:postcode":"70458",
    "sg:province":"LA",
    "sg:tags":[
        "grocer"
    ],
    "wof:name":"Pontchartrain Fresh Foods",
    "wof:placetype":"venue"
},
  "geometry": {"coordinates":[-89.791588,30.251288],"type":"Point"}
}