{
  "type": "Feature",
  "properties": {
    "iso:country":"US",
    "sg:address":"3211 Rose Pl",
    "sg:city":"Bossier City",
    "sg:classifiers":[
        {
            "category":"Professional",
            "subcategory":"Business Services",
            "type":"Services"
        }
    ],
    "sg:phone":"+1 318 742 6337",
    "sg:postcode":"71112",
    "sg:province":"LA",
    "wof:name":"Hot Shot Express",
    "wof:placetype":"venue"
},
  "geometry": {"coordinates":[-93.691125,32.494157],"type":"Point"}
}