{
  "type": "Feature",
  "properties": {
    "addr:full":"542 N Washington St Bastrop LA 71220",
    "addr:housenumber":"542",
    "addr:postcode":"71220",
    "addr:street":"N Washington St",
    "iso:country":"US",
    "sg:address":"542 N Washington St",
    "sg:city":"Bastrop",
    "sg:classifiers":[
        {
            "category":"Shopping",
            "subcategory":"Department Store",
            "type":"Retail Goods"
        }
    ],
    "sg:phone":"+1 318 283 0141",
    "sg:postcode":"71220",
    "sg:province":"LA",
    "sg:tags":[
        "shop"
    ],
    "wof:name":"Family Dollar Store",
    "wof:placetype":"venue"
},
  "geometry": {"coordinates":[-91.914165,32.782144],"type":"Point"}
}