{
  "type": "Feature",
  "properties": {
    "iso:country":"US",
    "sg:address":"305 N Sibley St",
    "sg:city":"Metairie",
    "sg:classifiers":[
        {
            "category":"Professional",
            "type":"Services"
        }
    ],
    "sg:phone":"+1 504 464 4671",
    "sg:postcode":"70003",
    "sg:province":"LA",
    "wof:name":"Roberts Handy Works",
    "wof:placetype":"venue"
},
  "geometry": {"coordinates":[-90.23092699999999,29.984093],"type":"Point"}
}