{
  "type": "Feature",
  "properties": {
    "iso:country":"US",
    "sg:address":"505 N Parkerson Ave",
    "sg:city":"Crowley",
    "sg:classifiers":[
        {
            "category":"Home & Garden",
            "subcategory":"Hardware",
            "type":"Retail Goods"
        }
    ],
    "sg:phone":"+1 337 783 3736",
    "sg:postcode":"70526",
    "sg:province":"LA",
    "wof:name":"Dixie True Value Hardware",
    "wof:placetype":"venue"
},
  "geometry": {"coordinates":[-92.373507,30.21398],"type":"Point"}
}