{
  "type": "Feature",
  "properties": {
    "addr:full":"4901 Tristian Ave Baker LA 70714",
    "addr:housenumber":"4901",
    "addr:postcode":"70714",
    "addr:street":"Tristian Ave",
    "iso:country":"US",
    "sg:address":"4901 Tristian Ave",
    "sg:city":"Baker",
    "sg:classifiers":[
        {
            "category":"Personal",
            "subcategory":"Beauty Salon",
            "type":"Services"
        }
    ],
    "sg:phone":"+1 225 774 7054",
    "sg:postcode":"70714",
    "sg:province":"LA",
    "wof:name":"Blessing's Hair Creation",
    "wof:placetype":"venue"
},
  "geometry": {"coordinates":[-91.148625,30.598983],"type":"Point"}
}