{
  "type": "Feature",
  "properties": {
    "iso:country":"US",
    "sg:address":"2096 Mandolin St",
    "sg:city":"New Orleans",
    "sg:classifiers":[
        {
            "category":"Retail",
            "subcategory":"Auto Repair",
            "type":"Services"
        }
    ],
    "sg:phone":"+1 504 283 7521",
    "sg:postcode":"70122",
    "sg:province":"LA",
    "sg:tags":[
        "body",
        "automobile",
        "painting"
    ],
    "wof:name":"Mike's Automotive Fasteners",
    "wof:placetype":"venue"
},
  "geometry": {"coordinates":[-90.062202,30.001801],"type":"Point"}
}