{
  "type": "Feature",
  "properties": {
    "iso:country":"US",
    "sg:address":"4717 Janice Ave",
    "sg:city":"Kenner",
    "sg:classifiers":[
        {
            "category":"Personal",
            "type":"Services"
        }
    ],
    "sg:phone":"+1 504 885 6776",
    "sg:postcode":"70065",
    "sg:province":"LA",
    "sg:tags":[
        "control",
        "weight"
    ],
    "wof:name":"Women's Nutrition & Weight",
    "wof:placetype":"venue"
},
  "geometry": {"coordinates":[-90.226709,30.026056],"type":"Point"}
}