{
  "type": "Feature",
  "properties": {
    "iso:country":"US",
    "sg:address":"1034 W Raymond St",
    "sg:city":"Gonzales",
    "sg:classifiers":[
        {
            "category":"Freight",
            "type":"Transportation"
        }
    ],
    "sg:phone":"+1 225 647 2727",
    "sg:postcode":"70737",
    "sg:province":"LA",
    "sg:tags":[
        "warehouse",
        "merchandise"
    ],
    "wof:name":"Ascension Moving & Storage",
    "wof:placetype":"venue"
},
  "geometry": {"coordinates":[-90.93019,30.219433],"type":"Point"}
}