{
  "type": "Feature",
  "properties": {
    "iso:country":"US",
    "sg:address":"6363 Hearne Ave Ste 103",
    "sg:city":"Shreveport",
    "sg:classifiers":[
        {
            "category":"Personal",
            "subcategory":"Tattoo Parlor",
            "type":"Services"
        },
        {
            "category":"Personal",
            "subcategory":"Piercing",
            "type":"Services"
        }
    ],
    "sg:phone":"+1 318 636 0510",
    "sg:postcode":"71108",
    "sg:province":"LA",
    "sg:tags":[
        "body"
    ],
    "wof:name":"Black Dragon Tattoo Studio",
    "wof:placetype":"venue"
},
  "geometry": {"coordinates":[-93.781068,32.448993],"type":"Point"}
}