{
  "type": "Feature",
  "properties": {
    "addr:full":"1607 Macarthur Dr Alexandria LA 71301",
    "addr:housenumber":"1607",
    "addr:postcode":"71301",
    "addr:street":"Macarthur Dr",
    "iso:country":"US",
    "sg:address":"1607 Macarthur Dr",
    "sg:city":"Alexandria",
    "sg:classifiers":[
        {
            "category":"Retail",
            "subcategory":"Auto Rental",
            "type":"Services"
        }
    ],
    "sg:phone":"+1 318 445 0099",
    "sg:postcode":"71301",
    "sg:province":"LA",
    "sg:tags":[
        "renting",
        "automobile"
    ],
    "wof:name":"Enterprise Rent-A-Car",
    "wof:placetype":"venue"
},
  "geometry": {"coordinates":[-92.47344200000001,31.284146],"type":"Point"}
}