{
  "type": "Feature",
  "properties": {
    "addr:full":"6514 Pampie Ln New Iberia LA 70560",
    "addr:housenumber":"6514",
    "addr:postcode":"70560",
    "addr:street":"Pampie Ln",
    "iso:country":"US",
    "sg:address":"6514 Pampie Ln",
    "sg:city":"New Iberia",
    "sg:classifiers":[
        {
            "category":"Professional",
            "subcategory":"Management & Consulting",
            "type":"Services"
        }
    ],
    "sg:phone":"+1 337 365 9970",
    "sg:postcode":"70560",
    "sg:province":"LA",
    "wof:name":"Sugarconsultantcom",
    "wof:placetype":"venue"
},
  "geometry": {"coordinates":[-91.8193,29.904399],"type":"Point"}
}