{
  "type": "Feature",
  "properties": {
    "iso:country":"US",
    "sg:address":"134 Teresa Dr",
    "sg:city":"Saint Martinville",
    "sg:classifiers":[
        {
            "category":"Building & Trades",
            "subcategory":"Construction",
            "type":"Services"
        }
    ],
    "sg:phone":"+1 337 394 5954",
    "sg:postcode":"70582",
    "sg:province":"LA",
    "sg:tags":[
        "carpentry",
        "contractor"
    ],
    "wof:name":"Integrity Woodworks Inc",
    "wof:placetype":"venue"
},
  "geometry": {"coordinates":[-91.82317500000001,30.141796],"type":"Point"}
}