{
  "type": "Feature",
  "properties": {
    "iso:country":"US",
    "sg:address":"2616 Marietta St",
    "sg:city":"Kenner",
    "sg:classifiers":[
        {
            "category":"Retail",
            "subcategory":"Repair Shop",
            "type":"Services"
        }
    ],
    "sg:phone":"+1 504 466 2300",
    "sg:postcode":"70062",
    "sg:province":"LA",
    "sg:tags":[
        "bathtub",
        "sink",
        "refinishing"
    ],
    "wof:name":"Lambro Refinishing",
    "wof:placetype":"venue"
},
  "geometry": {"coordinates":[-90.251831,30.003965],"type":"Point"}
}