{
  "type": "Feature",
  "properties": {
    "iso:country":"US",
    "sg:address":"300 Washington St",
    "sg:city":"Monroe",
    "sg:classifiers":[
        {
            "category":"Professional",
            "subcategory":"Engineering",
            "type":"Services"
        }
    ],
    "sg:phone":"+1 318 323 6228",
    "sg:postcode":"71201",
    "sg:province":"LA",
    "sg:tags":[
        "engineer"
    ],
    "wof:name":"Design Professionals Inc",
    "wof:placetype":"venue"
},
  "geometry": {"coordinates":[-92.11615999999999,32.504789],"type":"Point"}
}