{
  "type": "Feature",
  "properties": {
    "addr:full":"643 Magazine St. Suite 102 New Orleans LA 70130",
    "addr:housenumber":"643;102",
    "addr:postcode":"70130",
    "addr:street":"Magazine St. Suite",
    "iso:country":"US",
    "sg:address":"643 Magazine St. Suite 102",
    "sg:city":"New Orleans",
    "sg:classifiers":[
        {
            "category":"Professional",
            "subcategory":"Management & Consulting",
            "type":"Services"
        }
    ],
    "sg:phone":"+1 540 860 4119",
    "sg:postcode":"70130",
    "sg:province":"LA",
    "sg:tags":[
        "venture-capital",
        "seed",
        "consulting",
        "strategy",
        "finance"
    ],
    "sg:website":"http://www.unstructuredventures.com",
    "wof:name":"Unstructured Ventures",
    "wof:placetype":"venue"
},
  "geometry": {"coordinates":[-90.06859300000001,29.947734],"type":"Point"}
}