{
  "type": "Feature",
  "properties": {
    "addr:full":"10666 Scotland Ave Baton Rouge LA 70807",
    "addr:postcode":"10666;70807",
    "addr:street":"Scotland Ave",
    "iso:country":"US",
    "sg:address":"10666 Scotland Ave",
    "sg:city":"Baton Rouge",
    "sg:classifiers":[
        {
            "category":"Real Estate",
            "subcategory":"Real Estate Agent",
            "type":"Services"
        }
    ],
    "sg:phone":"+1 225 774 3926",
    "sg:postcode":"70807",
    "sg:province":"LA",
    "sg:tags":[
        "authorities",
        "housing"
    ],
    "wof:name":"Housing Authority",
    "wof:placetype":"venue"
},
  "geometry": {"coordinates":[-91.177153,30.541143],"type":"Point"}
}