{
  "type": "Feature",
  "properties": {
    "iso:country":"US",
    "sg:address":"60378 Rohner Rd",
    "sg:city":"Amite",
    "sg:classifiers":[
        {
            "category":"Building & Trades",
            "subcategory":"Construction",
            "type":"Services"
        }
    ],
    "sg:phone":"+1 985 747 8139",
    "sg:postcode":"70422",
    "sg:province":"LA",
    "sg:tags":[
        "contractor"
    ],
    "wof:name":"Rohner Dozier & Dirt Contr LLC",
    "wof:placetype":"venue"
},
  "geometry": {"coordinates":[-90.340436,30.729149],"type":"Point"}
}