{
  "type": "Feature",
  "properties": {
    "addr:full":"1201 7th St Glenmora LA 71433",
    "addr:housenumber":"1201",
    "addr:postcode":"71433",
    "addr:street":"7Th St",
    "iso:country":"US",
    "sg:address":"1201 7th St",
    "sg:city":"Glenmora",
    "sg:classifiers":[
        {
            "category":"Government",
            "subcategory":"Post Office",
            "type":"Public Place"
        }
    ],
    "sg:phone":"+1 318 748 4952",
    "sg:postcode":"71433",
    "sg:province":"LA",
    "wof:name":"US Post Office",
    "wof:placetype":"venue"
},
  "geometry": {"coordinates":[-92.585356,30.966393],"type":"Point"}
}