{
  "type": "Feature",
  "properties": {
    "addr:full":"731 Caddo St Baton Rouge LA 70806",
    "addr:housenumber":"731",
    "addr:postcode":"70806",
    "addr:street":"Caddo St",
    "iso:country":"US",
    "sg:address":"731 Caddo St",
    "sg:city":"Baton Rouge",
    "sg:classifiers":[
        {
            "category":"Professional",
            "subcategory":"Lawyer & Legal Services",
            "type":"Services"
        }
    ],
    "sg:phone":"+1 225 927 9252",
    "sg:postcode":"70806",
    "sg:province":"LA",
    "sg:tags":[
        "attorney",
        "bureau"
    ],
    "wof:name":"Legal Professional LLC",
    "wof:placetype":"venue"
},
  "geometry": {"coordinates":[-91.137381,30.441749],"type":"Point"}
}