{
  "type": "Feature",
  "properties": {
    "iso:country":"US",
    "sg:address":"2430 Oak St",
    "sg:city":"Zwolle",
    "sg:classifiers":[
        {
            "category":"Retail",
            "subcategory":"Photofinishing",
            "type":"Services"
        }
    ],
    "sg:phone":"+1 318 645 2183",
    "sg:postcode":"71486",
    "sg:province":"LA",
    "sg:tags":[
        "laboratory"
    ],
    "wof:name":"Photo Design",
    "wof:placetype":"venue"
},
  "geometry": {"coordinates":[-93.630768,31.641304],"type":"Point"}
}