{
  "type": "Feature",
  "properties": {
    "iso:country":"US",
    "sg:address":"4131 Sterlington Rd",
    "sg:city":"Monroe",
    "sg:classifiers":[
        {
            "category":"Retail",
            "subcategory":"Auto Repair",
            "type":"Services"
        }
    ],
    "sg:phone":"+1 318 323 2228",
    "sg:postcode":"71203",
    "sg:province":"LA",
    "sg:tags":[
        "repairing",
        "automobile"
    ],
    "wof:name":"Jaz Automotive",
    "wof:placetype":"venue"
},
  "geometry": {"coordinates":[-92.073705,32.571212],"type":"Point"}
}