{
  "type": "Feature",
  "properties": {
    "addr:full":"2930 Magazine St New Orleans LA 70115",
    "addr:housenumber":"2930",
    "addr:postcode":"70115",
    "addr:street":"Magazine St",
    "iso:country":"US",
    "sg:address":"2930 Magazine St",
    "sg:city":"New Orleans",
    "sg:classifiers":[
        {
            "category":"Professional",
            "subcategory":"Business Services",
            "type":"Services"
        }
    ],
    "sg:phone":"+1 504 899 2931",
    "sg:postcode":"70115",
    "sg:province":"LA",
    "sg:tags":[
        "interior",
        "consultant",
        "design",
        "decorator"
    ],
    "wof:name":"Villa Vici",
    "wof:placetype":"venue"
},
  "geometry": {"coordinates":[-90.08435299999999,29.925087],"type":"Point"}
}