{
  "type": "Feature",
  "properties": {
    "iso:country":"US",
    "sg:address":"13355 US Hwy 90",
    "sg:city":"Boutte",
    "sg:classifiers":[
        {
            "category":"Banks & Credit Unions",
            "subcategory":"Bank",
            "type":"Services"
        }
    ],
    "sg:phone":"+1 985 785 8901",
    "sg:postcode":"70039",
    "sg:province":"LA",
    "wof:name":"First American Bank & Trust",
    "wof:placetype":"venue"
},
  "geometry": {"coordinates":[-90.37752,29.904681],"type":"Point"}
}