{
  "type": "Feature",
  "properties": {
    "addr:full":"7676 Airline Hwy Baton Rouge LA 70814",
    "addr:housenumber":"7676",
    "addr:postcode":"70814",
    "addr:street":"Airline Hwy",
    "iso:country":"US",
    "sg:address":"7676 Airline Hwy",
    "sg:city":"Baton Rouge",
    "sg:classifiers":[
        {
            "category":"Wholesale",
            "subcategory":"Electrical",
            "type":"Manufacturing & Wholesale Goods"
        }
    ],
    "sg:phone":"+1 225 926 2020",
    "sg:postcode":"70814",
    "sg:province":"LA",
    "sg:tags":[
        "equipment",
        "electric",
        "supply"
    ],
    "sg:website":"www.graybar.com",
    "wof:name":"Graybar Electric Co",
    "wof:placetype":"venue"
},
  "geometry": {"coordinates":[-91.109959,30.472905],"type":"Point"}
}