{
  "type": "Feature",
  "properties": {
    "iso:country":"US",
    "sg:address":"4021 Ambassador Caffery Pkwy",
    "sg:city":"Lafayette",
    "sg:classifiers":[
        {
            "category":"Utilities",
            "subcategory":"Telephone",
            "type":"Services"
        }
    ],
    "sg:phone":"+1 337 984 4229",
    "sg:postcode":"70503",
    "sg:province":"LA",
    "sg:tags":[
        "telecommunication"
    ],
    "wof:name":"Omega Telecom",
    "wof:placetype":"venue"
},
  "geometry": {"coordinates":[-92.058998,30.165438],"type":"Point"}
}