{
  "type": "Feature",
  "properties": {
    "iso:country":"US",
    "sg:address":"1450 Hawn Ave",
    "sg:city":"Shreveport",
    "sg:classifiers":[
        {
            "category":"Shopping",
            "subcategory":"Computers & Home Electronics",
            "type":"Retail Goods"
        }
    ],
    "sg:phone":"+1 318 221 1248",
    "sg:postcode":"71107",
    "sg:province":"LA",
    "sg:tags":[
        "software"
    ],
    "wof:name":"Classic Solutions",
    "wof:placetype":"venue"
},
  "geometry": {"coordinates":[-93.763857,32.536461],"type":"Point"}
}