{
  "type": "Feature",
  "properties": {
    "iso:country":"US",
    "sg:address":"1234 Mehle St",
    "sg:city":"Arabi",
    "sg:classifiers":[
        {
            "category":"Shopping",
            "subcategory":"Florist",
            "type":"Retail Goods"
        }
    ],
    "sg:phone":"+1 504 279 4747",
    "sg:postcode":"70032",
    "sg:province":"LA",
    "wof:name":"Cousin's Florist",
    "wof:placetype":"venue"
},
  "geometry": {"coordinates":[-90.00413,29.95911],"type":"Point"}
}