{
  "type": "Feature",
  "properties": {
    "addr:full":"45 26th St Kenner LA 70062",
    "addr:housenumber":"45",
    "addr:postcode":"70062",
    "addr:street":"26Th St",
    "iso:country":"US",
    "sg:address":"45 26th St",
    "sg:city":"Kenner",
    "sg:classifiers":[
        {
            "category":"Building & Trades",
            "subcategory":"Construction",
            "type":"Services"
        }
    ],
    "sg:phone":"+1 504 466 8995",
    "sg:postcode":"70062",
    "sg:province":"LA",
    "sg:tags":[
        "contractor"
    ],
    "wof:name":"ARC Welding Svc",
    "wof:placetype":"venue"
},
  "geometry": {"coordinates":[-90.27305800000001,30.002433],"type":"Point"}
}