{
  "type": "Feature",
  "properties": {
    "iso:country":"US",
    "sg:address":"312 Lapalco Blvd",
    "sg:city":"Gretna",
    "sg:classifiers":[
        {
            "category":"Wholesale",
            "subcategory":"Machinery & Supplies",
            "type":"Manufacturing & Wholesale Goods"
        }
    ],
    "sg:phone":"+1 504 393 0811",
    "sg:postcode":"70056",
    "sg:province":"LA",
    "sg:tags":[
        "carnival"
    ],
    "wof:name":"Accent Annex Enterprises Inc",
    "wof:placetype":"venue"
},
  "geometry": {"coordinates":[-90.028035,29.880905],"type":"Point"}
}