{
  "type": "Feature",
  "properties": {
    "iso:country":"US",
    "sg:address":"1682 N Broad St",
    "sg:city":"New Orleans",
    "sg:classifiers":[
        {
            "category":"Personal",
            "subcategory":"Barber",
            "type":"Services"
        }
    ],
    "sg:phone":"+1 504 945 9179",
    "sg:postcode":"70119",
    "sg:province":"LA",
    "wof:name":"His & Hers Place Of Styles",
    "wof:placetype":"venue"
},
  "geometry": {"coordinates":[-90.074229,29.980228],"type":"Point"}
}