{
  "type": "Feature",
  "properties": {
    "iso:country":"US",
    "sg:address":"1510 Hwy 80 E",
    "sg:city":"Calhoun",
    "sg:classifiers":[
        {
            "category":"Shopping",
            "subcategory":"Bicycles & Sporting Goods",
            "type":"Retail Goods"
        }
    ],
    "sg:phone":"+1 318 366 3996",
    "sg:postcode":"71225",
    "sg:province":"LA",
    "wof:name":"First Shot",
    "wof:placetype":"venue"
},
  "geometry": {"coordinates":[-92.30376200000001,32.525059],"type":"Point"}
}