{
  "type": "Feature",
  "properties": {
    "iso:country":"US",
    "sg:address":"3519 Jewella Ave",
    "sg:city":"Shreveport",
    "sg:classifiers":[
        {
            "category":"Communications",
            "subcategory":"Television Station",
            "type":"Services"
        }
    ],
    "sg:phone":"+1 318 631 4545",
    "sg:postcode":"71109",
    "sg:province":"LA",
    "sg:tags":[
        "broadcasting",
        "co"
    ],
    "sg:website":"www.kmsstv.com",
    "wof:name":"KSHV",
    "wof:placetype":"venue"
},
  "geometry": {"coordinates":[-93.797173,32.478419],"type":"Point"}
}