{
  "type": "Feature",
  "properties": {
    "addr:full":"39359 Mc Cahill Ln Ponchatoula LA 70454",
    "addr:housenumber":"39359",
    "addr:postcode":"70454",
    "addr:street":"Mc Cahill Ln",
    "iso:country":"US",
    "sg:address":"39359 Mc Cahill Ln",
    "sg:city":"Ponchatoula",
    "sg:classifiers":[
        {
            "category":"Building & Trades",
            "subcategory":"Landscaping Services",
            "type":"Services"
        }
    ],
    "sg:phone":"+1 225 294 4000",
    "sg:postcode":"70454",
    "sg:province":"LA",
    "sg:tags":[
        "landscape",
        "contractor"
    ],
    "wof:name":"Gold Leaf LLC",
    "wof:placetype":"venue"
},
  "geometry": {"coordinates":[-90.510836,30.42938],"type":"Point"}
}