{
  "type": "Feature",
  "properties": {
    "iso:country":"US",
    "sg:address":"8580 Greenwood Rd",
    "sg:city":"Greenwood",
    "sg:classifiers":[
        {
            "category":"Travel",
            "subcategory":"Hotels & Motels",
            "type":"Entertainment"
        }
    ],
    "sg:phone":"+1 318 938 5423",
    "sg:postcode":"71033",
    "sg:province":"LA",
    "wof:name":"Mid Continent Inn",
    "wof:placetype":"venue"
},
  "geometry": {"coordinates":[-93.946881,32.44604],"type":"Point"}
}