{
  "type": "Feature",
  "properties": {
    "iso:country":"US",
    "sg:address":"1500 4th St",
    "sg:city":"Harvey",
    "sg:classifiers":[
        {
            "category":"Wholesale",
            "subcategory":"Auto Parts",
            "type":"Manufacturing & Wholesale Goods"
        }
    ],
    "sg:phone":"+1 504 367 8365",
    "sg:postcode":"70058",
    "sg:province":"LA",
    "sg:tags":[
        "automobile",
        "rebuilt"
    ],
    "wof:name":"BRH Distributors-New Orleans",
    "wof:placetype":"venue"
},
  "geometry": {"coordinates":[-90.06863800000001,29.912992],"type":"Point"}
}