{
  "type": "Feature",
  "properties": {
    "iso:country":"US",
    "sg:address":"90 First St",
    "sg:city":"New Orleans",
    "sg:classifiers":[
        {
            "category":"Local Transit",
            "type":"Transportation"
        }
    ],
    "sg:phone":"+1 504 818 1077",
    "sg:postcode":"70112",
    "sg:province":"LA",
    "sg:tags":[
        "public"
    ],
    "wof:name":"Jefferson Parrish",
    "wof:placetype":"venue"
},
  "geometry": {"coordinates":[-90.059641,29.922077],"type":"Point"}
}