{
  "type": "Feature",
  "properties": {
    "iso:country":"US",
    "sg:address":"3304 Marietta St",
    "sg:city":"Chalmette",
    "sg:classifiers":[
        {
            "category":"Building & Trades",
            "subcategory":"Plumbing",
            "type":"Services"
        }
    ],
    "sg:phone":"+1 504 271 9503",
    "sg:postcode":"70043",
    "sg:province":"LA",
    "sg:tags":[
        "contractor"
    ],
    "wof:name":"Sams Heating & AC",
    "wof:placetype":"venue"
},
  "geometry": {"coordinates":[-89.954375,29.94618],"type":"Point"}
}