{
  "type": "Feature",
  "properties": {
    "iso:country":"US",
    "sg:address":"1409 Fernwood Dr",
    "sg:city":"Slidell",
    "sg:classifiers":[
        {
            "category":"Professional",
            "subcategory":"Accounting & Tax Preparation",
            "type":"Services"
        }
    ],
    "sg:phone":"+1 985 649 3847",
    "sg:postcode":"70458",
    "sg:province":"LA",
    "sg:tags":[
        "return"
    ],
    "wof:name":"Accounting Services",
    "wof:placetype":"venue"
},
  "geometry": {"coordinates":[-89.76061300000001,30.282586],"type":"Point"}
}