{
  "type": "Feature",
  "properties": {
    "iso:country":"US",
    "sg:address":"2164 Milton St",
    "sg:city":"New Orleans",
    "sg:classifiers":[
        {
            "category":"Restaurant",
            "type":"Food & Drink"
        }
    ],
    "sg:phone":"+1 504 948 8800",
    "sg:postcode":"70122",
    "sg:province":"LA",
    "sg:tags":[
        "caterer"
    ],
    "wof:name":"Soul Food Cafe & Catering Svc",
    "wof:placetype":"venue"
},
  "geometry": {"coordinates":[-90.059853,29.996804],"type":"Point"}
}