{
  "type": "Feature",
  "properties": {
    "iso:country":"US",
    "sg:address":"601 Poydras St",
    "sg:city":"New Orleans",
    "sg:classifiers":[
        {
            "category":"Insurance",
            "subcategory":"Insurance Agent",
            "type":"Services"
        }
    ],
    "sg:phone":"+1 504 522 8541",
    "sg:postcode":"70130",
    "sg:province":"LA",
    "sg:website":"www.marsh.com",
    "wof:name":"Marsh Inc",
    "wof:placetype":"venue"
},
  "geometry": {"coordinates":[-90.070539,29.949665],"type":"Point"}
}