{
  "type": "Feature",
  "properties": {
    "iso:country":"US",
    "sg:address":"111 Trafalgar Sq",
    "sg:city":"Slidell",
    "sg:classifiers":[
        {
            "category":"Professional",
            "subcategory":"Research",
            "type":"Services"
        }
    ],
    "sg:phone":"+1 985 847 2886",
    "sg:postcode":"70461",
    "sg:province":"LA",
    "wof:name":"Devalcourt Research & Dev",
    "wof:placetype":"venue"
},
  "geometry": {"coordinates":[-89.747235,30.257677],"type":"Point"}
}