{
  "type": "Feature",
  "properties": {
    "addr:full":"5615 Jackson St Exd Alexandria LA 71303",
    "addr:housenumber":"5615",
    "addr:postcode":"71303",
    "addr:street":"Jackson St Exd",
    "iso:country":"US",
    "sg:address":"5615 Jackson St Exd",
    "sg:city":"Alexandria",
    "sg:classifiers":[
        {
            "category":"Social Services",
            "type":"Services"
        }
    ],
    "sg:phone":"+1 318 443 7711",
    "sg:postcode":"71303",
    "sg:province":"LA",
    "sg:tags":[
        "professional",
        "counselor"
    ],
    "wof:name":"Center For Family & Individual",
    "wof:placetype":"venue"
},
  "geometry": {"coordinates":[-92.486349,31.268703],"type":"Point"}
}