{
  "type": "Feature",
  "properties": {
    "iso:country":"US",
    "sg:address":"414 N Cary Ave",
    "sg:city":"Jennings",
    "sg:classifiers":[
        {
            "category":"Retail",
            "subcategory":"Repair Shop",
            "type":"Services"
        }
    ],
    "sg:phone":"+1 337 824 1047",
    "sg:postcode":"70546",
    "sg:province":"LA",
    "wof:name":"Pop-A-Lock",
    "wof:placetype":"venue"
},
  "geometry": {"coordinates":[-92.65911199999999,30.224306],"type":"Point"}
}