{
  "type": "Feature",
  "properties": {
    "iso:country":"US",
    "sg:address":"515 Marchand Dr",
    "sg:city":"Donaldsonville",
    "sg:classifiers":[
        {
            "category":"Banks & Credit Unions",
            "subcategory":"Bank",
            "type":"Services"
        }
    ],
    "sg:phone":"+1 225 474 0238",
    "sg:postcode":"70346",
    "sg:province":"LA",
    "sg:tags":[
        "cashing",
        "check"
    ],
    "wof:name":"Finance America",
    "wof:placetype":"venue"
},
  "geometry": {"coordinates":[-90.98984799999999,30.098524],"type":"Point"}
}