{
  "type": "Feature",
  "properties": {
    "iso:country":"US",
    "sg:address":"15958 Perkins Rd",
    "sg:city":"Baton Rouge",
    "sg:classifiers":[
        {
            "category":"Home & Garden",
            "subcategory":"Building Materials",
            "type":"Retail Goods"
        }
    ],
    "sg:phone":"+1 225 753 9663",
    "sg:postcode":"70810",
    "sg:province":"LA",
    "sg:tags":[
        "lumber"
    ],
    "wof:name":"Martin Lumber Co Inc",
    "wof:placetype":"venue"
},
  "geometry": {"coordinates":[-91.045957,30.354835],"type":"Point"}
}