{
  "type": "Feature",
  "properties": {
    "iso:country":"US",
    "sg:address":"105 Murria St",
    "sg:city":"Cullen",
    "sg:classifiers":[
        {
            "category":"Social Services",
            "type":"Services"
        }
    ],
    "sg:phone":"+1 318 994 2313",
    "sg:postcode":"71021",
    "sg:province":"LA",
    "sg:tags":[
        "organization",
        "welfare"
    ],
    "wof:name":"Webster Parish Community Svc",
    "wof:placetype":"venue"
},
  "geometry": {"coordinates":[-93.44659299999999,32.972815],"type":"Point"}
}