{
  "type": "Feature",
  "properties": {
    "addr:full":"300 Decatur St New Orleans LA 70130",
    "addr:housenumber":"300",
    "addr:postcode":"70130",
    "addr:street":"Decatur St",
    "iso:country":"US",
    "sg:address":"300 Decatur St",
    "sg:city":"New Orleans",
    "sg:classifiers":[
        {
            "category":"Bars & Pubs",
            "subcategory":"Nightclub",
            "type":"Food & Drink"
        }
    ],
    "sg:phone":"+1 504 581 2135",
    "sg:postcode":"70130",
    "sg:province":"LA",
    "sg:tags":[
        "nightlife"
    ],
    "wof:name":"300 Decatur Street Bar Llc",
    "wof:placetype":"venue"
},
  "geometry": {"coordinates":[-90.065399,29.953699],"type":"Point"}
}