{
  "type": "Feature",
  "properties": {
    "iso:country":"US",
    "sg:address":"4345 Illinois Ave",
    "sg:city":"Shreveport",
    "sg:classifiers":[
        {
            "category":"Building & Trades",
            "subcategory":"Construction",
            "type":"Services"
        }
    ],
    "sg:phone":"+1 318 636 3865",
    "sg:postcode":"71109",
    "sg:province":"LA",
    "sg:tags":[
        "painter"
    ],
    "wof:name":"Eric's Painting",
    "wof:placetype":"venue"
},
  "geometry": {"coordinates":[-93.812281,32.460166],"type":"Point"}
}