{
  "type": "Feature",
  "properties": {
    "iso:country":"US",
    "sg:address":"413 Hesper Ave",
    "sg:city":"Metairie",
    "sg:classifiers":[
        {
            "category":"Building & Trades",
            "subcategory":"Plumbing",
            "type":"Services"
        }
    ],
    "sg:phone":"+1 504 838 8802",
    "sg:postcode":"70005",
    "sg:province":"LA",
    "sg:tags":[
        "plumbing",
        "contractor"
    ],
    "wof:name":"R L Falcon Plumbing Co Inc",
    "wof:placetype":"venue"
},
  "geometry": {"coordinates":[-90.145473,29.994256],"type":"Point"}
}