{
  "type": "Feature",
  "properties": {
    "iso:country":"US",
    "sg:address":"6180 Airline Hwy",
    "sg:city":"Baton Rouge",
    "sg:classifiers":[
        {
            "category":"Building & Trades",
            "subcategory":"Equipment Rental",
            "type":"Services"
        }
    ],
    "sg:phone":"+1 225 355 8000",
    "sg:postcode":"70805",
    "sg:province":"LA",
    "sg:tags":[
        "leasing",
        "furniture"
    ],
    "wof:name":"First Choice Furniture",
    "wof:placetype":"venue"
},
  "geometry": {"coordinates":[-91.128687,30.498857],"type":"Point"}
}