{
  "type": "Feature",
  "properties": {
    "addr:full":"3648 Southdown Mandalay Rd Houma LA 70360",
    "addr:housenumber":"3648",
    "addr:postcode":"70360",
    "addr:street":"Southdown Mandalay Rd",
    "iso:country":"US",
    "sg:address":"3648 Southdown Mandalay Rd",
    "sg:city":"Houma",
    "sg:classifiers":[
        {
            "category":"Freight",
            "type":"Transportation"
        }
    ],
    "sg:phone":"+1 985 580 0209",
    "sg:postcode":"70360",
    "sg:province":"LA",
    "sg:tags":[
        "hauling",
        "trucking"
    ],
    "wof:name":"Maverick Trucking",
    "wof:placetype":"venue"
},
  "geometry": {"coordinates":[-90.788068,29.559744],"type":"Point"}
}