{
  "type": "Feature",
  "properties": {
    "addr:full":"29017 Crowley Eunice Hwy Eunice LA 70535",
    "addr:housenumber":"29017",
    "addr:postcode":"70535",
    "addr:street":"Eunice Hwy",
    "iso:country":"US",
    "sg:address":"29017 Crowley Eunice Hwy",
    "sg:city":"Eunice",
    "sg:classifiers":[
        {
            "category":"Restaurant",
            "type":"Food & Drink"
        }
    ],
    "sg:phone":"+1 337 550 1992",
    "sg:postcode":"70535",
    "sg:province":"LA",
    "wof:name":"Bubba Frey's",
    "wof:placetype":"venue"
},
  "geometry": {"coordinates":[-92.397671,30.366274],"type":"Point"}
}