{
  "type": "Feature",
  "properties": {
    "iso:country":"US",
    "sg:address":"1301 Simon Bolivar Ave",
    "sg:city":"New Orleans",
    "sg:classifiers":[
        {
            "category":"Real Estate",
            "subcategory":"Real Estate Agent",
            "type":"Services"
        }
    ],
    "sg:phone":"+1 504 569 9506",
    "sg:postcode":"70113",
    "sg:province":"LA",
    "sg:tags":[
        "authorities",
        "housing"
    ],
    "wof:name":"Housing Authority Cops Sub Sta",
    "wof:placetype":"venue"
},
  "geometry": {"coordinates":[-90.080046,29.944744],"type":"Point"}
}