{
  "type": "Feature",
  "properties": {
    "addr:full":"3333 Kingman St Metairie LA 70006",
    "addr:housenumber":"3333",
    "addr:postcode":"70006",
    "addr:street":"Kingman St",
    "iso:country":"US",
    "sg:address":"3333 Kingman St",
    "sg:city":"Metairie",
    "sg:classifiers":[
        {
            "category":"Wholesale",
            "subcategory":"Medical Equipment & Supplies",
            "type":"Manufacturing & Wholesale Goods"
        }
    ],
    "sg:phone":"+1 504 455 9900",
    "sg:postcode":"70006",
    "sg:province":"LA",
    "sg:tags":[
        "alarm"
    ],
    "wof:name":"Louisiana Health Monitoring",
    "wof:placetype":"venue"
},
  "geometry": {"coordinates":[-90.180862,30.006221],"type":"Point"}
}