{
  "type": "Feature",
  "properties": {
    "iso:country":"US",
    "sg:address":"1508 Court St",
    "sg:city":"Port Allen",
    "sg:classifiers":[
        {
            "category":"Building & Trades",
            "subcategory":"Construction",
            "type":"Services"
        }
    ],
    "sg:phone":"+1 225 334 9335",
    "sg:postcode":"70767",
    "sg:province":"LA",
    "sg:tags":[
        "general",
        "contractor"
    ],
    "wof:name":"Superior Construction II",
    "wof:placetype":"venue"
},
  "geometry": {"coordinates":[-91.218137,30.451977],"type":"Point"}
}