{
  "type": "Feature",
  "properties": {
    "iso:country":"US",
    "sg:address":"514 Guilbeau Rd",
    "sg:city":"Lafayette",
    "sg:classifiers":[
        {
            "category":"Health Services",
            "subcategory":"Chiropractor",
            "type":"Services"
        }
    ],
    "sg:phone":"+1 337 981 7773",
    "sg:postcode":"70506",
    "sg:province":"LA",
    "wof:name":"Optimal Health Chiropractic",
    "wof:placetype":"venue"
},
  "geometry": {"coordinates":[-92.069379,30.197839],"type":"Point"}
}