{
  "type": "Feature",
  "properties": {
    "iso:country":"US",
    "sg:address":"6750 Exchequer Dr",
    "sg:city":"Baton Rouge",
    "sg:classifiers":[
        {
            "category":"Building & Trades",
            "subcategory":"Construction",
            "type":"Services"
        }
    ],
    "sg:phone":"+1 225 752 3733",
    "sg:postcode":"70809",
    "sg:province":"LA",
    "sg:tags":[
        "general",
        "contractor"
    ],
    "wof:name":"Cribran Inc",
    "wof:placetype":"venue"
},
  "geometry": {"coordinates":[-91.05017599999999,30.37866],"type":"Point"}
}