{
  "type": "Feature",
  "properties": {
    "iso:country":"US",
    "sg:address":"2029 Roosevelt Blvd",
    "sg:city":"Kenner",
    "sg:classifiers":[
        {
            "category":"Manufacturing",
            "subcategory":"Glass & Minerals",
            "type":"Manufacturing & Wholesale Goods"
        }
    ],
    "sg:phone":"+1 504 305 0737",
    "sg:postcode":"70062",
    "sg:province":"LA",
    "sg:tags":[
        "product",
        "mfg"
    ],
    "wof:name":"Nuckleys Glass Co",
    "wof:placetype":"venue"
},
  "geometry": {"coordinates":[-90.233918,29.992971],"type":"Point"}
}