{
  "type": "Feature",
  "properties": {
    "iso:country":"US",
    "sg:address":"1614 Myrtle Walk",
    "sg:city":"Baton Rouge",
    "sg:classifiers":[
        {
            "category":"Professional",
            "subcategory":"Computer Services",
            "type":"Services"
        }
    ],
    "sg:phone":"+1 225 344 4891",
    "sg:postcode":"70802",
    "sg:province":"LA",
    "sg:tags":[
        "consultant"
    ],
    "wof:name":"Wisham & Associates LLC",
    "wof:placetype":"venue"
},
  "geometry": {"coordinates":[-91.171041,30.438378],"type":"Point"}
}