{
  "type": "Feature",
  "properties": {
    "addr:full":"5725 Powell St New Orleans LA 70123",
    "addr:housenumber":"5725",
    "addr:postcode":"70123",
    "addr:street":"Powell St",
    "iso:country":"US",
    "sg:address":"5725 Powell St",
    "sg:city":"New Orleans",
    "sg:classifiers":[
        {
            "category":"Wholesale",
            "subcategory":"Construction Materials",
            "type":"Manufacturing & Wholesale Goods"
        }
    ],
    "sg:phone":"+1 504 733 1585",
    "sg:postcode":"70123",
    "sg:province":"LA",
    "sg:tags":[
        "glass"
    ],
    "wof:name":"ACI Distribution",
    "wof:placetype":"venue"
},
  "geometry": {"coordinates":[-90.196113,29.959366],"type":"Point"}
}