{
  "type": "Feature",
  "properties": {
    "addr:full":"1601 University Pkwy Leesville LA 71446",
    "addr:housenumber":"1601",
    "addr:postcode":"71446",
    "addr:street":"University Pkwy",
    "iso:country":"US",
    "sg:address":"1601 University Pkwy",
    "sg:city":"Leesville",
    "sg:classifiers":[
        {
            "category":"Real Estate",
            "subcategory":"Real Estate Operator",
            "type":"Services"
        }
    ],
    "sg:phone":"+1 337 238 1010",
    "sg:postcode":"71446",
    "sg:province":"LA",
    "sg:tags":[
        "apartment"
    ],
    "wof:name":"Jeter Apartments",
    "wof:placetype":"venue"
},
  "geometry": {"coordinates":[-93.26211000000001,31.131524],"type":"Point"}
}