{
  "type": "Feature",
  "properties": {
    "iso:country":"US",
    "sg:address":"1409 Gibbs St",
    "sg:city":"Mansfield",
    "sg:classifiers":[
        {
            "category":"Personal",
            "subcategory":"Barber",
            "type":"Services"
        }
    ],
    "sg:phone":"+1 318 871 8585",
    "sg:postcode":"71052",
    "sg:province":"LA",
    "wof:name":"Carroll's Barber Shop",
    "wof:placetype":"venue"
},
  "geometry": {"coordinates":[-93.69171900000001,32.034608],"type":"Point"}
}