{
  "type": "Feature",
  "properties": {
    "iso:country":"US",
    "sg:address":"4403 Sterlington Rd",
    "sg:city":"Monroe",
    "sg:classifiers":[
        {
            "category":"Health Services",
            "subcategory":"Doctor",
            "type":"Services"
        }
    ],
    "sg:phone":"+1 318 322 0995",
    "sg:postcode":"71203",
    "sg:province":"LA",
    "sg:tags":[
        "clinic"
    ],
    "wof:name":"PMN Medical LLC",
    "wof:placetype":"venue"
},
  "geometry": {"coordinates":[-92.072549,32.578164],"type":"Point"}
}