{
  "type": "Feature",
  "properties": {
    "iso:country":"US",
    "sg:address":"2118 Staring Ln",
    "sg:city":"Baton Rouge",
    "sg:classifiers":[
        {
            "category":"Organizations",
            "subcategory":"Religious Organization",
            "type":"Services"
        }
    ],
    "sg:phone":"+1 225 766 0344",
    "sg:postcode":"70810",
    "sg:province":"LA",
    "sg:tags":[
        "church"
    ],
    "wof:name":"Greater Hollywood Baptist Chr",
    "wof:placetype":"venue"
},
  "geometry": {"coordinates":[-91.11008,30.393844],"type":"Point"}
}