{
  "type": "Feature",
  "properties": {
    "addr:full":"317 2nd St Mamou LA 70554",
    "addr:housenumber":"317",
    "addr:postcode":"70554",
    "addr:street":"2Nd St",
    "iso:country":"US",
    "sg:address":"317 2nd St",
    "sg:city":"Mamou",
    "sg:classifiers":[
        {
            "category":"Education",
            "subcategory":"Library",
            "type":"Public Place"
        }
    ],
    "sg:phone":"+1 337 468 5750",
    "sg:postcode":"70554",
    "sg:province":"LA",
    "wof:name":"Mamou Branch Public Library",
    "wof:placetype":"venue"
},
  "geometry": {"coordinates":[-92.424172,30.629322],"type":"Point"}
}