{
  "type": "Feature",
  "properties": {
    "addr:full":"1027 Enterprise Blvd Lake Charles LA 70601",
    "addr:housenumber":"1027",
    "addr:postcode":"70601",
    "addr:street":"Enterprise Blvd",
    "iso:country":"US",
    "sg:address":"1027 Enterprise Blvd",
    "sg:city":"Lake Charles",
    "sg:classifiers":[
        {
            "category":"Retail",
            "subcategory":"Auto Repair",
            "type":"Services"
        }
    ],
    "sg:phone":"+1 337 439 8112",
    "sg:postcode":"70601",
    "sg:province":"LA",
    "sg:tags":[
        "repairing",
        "automobile"
    ],
    "wof:name":"Louis' Bug Shop",
    "wof:placetype":"venue"
},
  "geometry": {"coordinates":[-93.204221,30.224198],"type":"Point"}
}