{
  "type": "Feature",
  "properties": {
    "addr:full":"1508 Aristocrat Ct Covington LA 70433",
    "addr:housenumber":"1508",
    "addr:postcode":"70433",
    "addr:street":"Aristocrat Ct",
    "iso:country":"US",
    "sg:address":"1508 Aristocrat Ct",
    "sg:city":"Covington",
    "sg:classifiers":[
        {
            "category":"Professional",
            "subcategory":"Management & Consulting",
            "type":"Services"
        }
    ],
    "sg:phone":"+1 985 809 9030",
    "sg:postcode":"70433",
    "sg:province":"LA",
    "sg:tags":[
        "employment",
        "screening"
    ],
    "wof:name":"Research Depot",
    "wof:placetype":"venue"
},
  "geometry": {"coordinates":[-90.096723,30.428855],"type":"Point"}
}