{
  "type": "Feature",
  "properties": {
    "iso:country":"US",
    "sg:address":"1033 Gerard St",
    "sg:city":"Mandeville",
    "sg:classifiers":[
        {
            "category":"Freight",
            "type":"Transportation"
        }
    ],
    "sg:phone":"+1 985 626 1536",
    "sg:postcode":"70448",
    "sg:province":"LA",
    "sg:tags":[
        "commercial",
        "storage"
    ],
    "wof:name":"ABC Mini Storage Inc",
    "wof:placetype":"venue"
},
  "geometry": {"coordinates":[-90.059945,30.365691],"type":"Point"}
}