{
  "type": "Feature",
  "properties": {
    "iso:country":"US",
    "sg:address":"100 Prestige Cir",
    "sg:city":"Lafayette",
    "sg:classifiers":[
        {
            "category":"Real Estate",
            "subcategory":"Real Estate Operator",
            "type":"Services"
        }
    ],
    "sg:phone":"+1 337 989 1171",
    "sg:postcode":"70508",
    "sg:province":"LA",
    "sg:tags":[
        "mobile",
        "home",
        "community"
    ],
    "wof:name":"Sport's Manufactured Home",
    "wof:placetype":"venue"
},
  "geometry": {"coordinates":[-92.045411,30.146535],"type":"Point"}
}