{
  "type": "Feature",
  "properties": {
    "iso:country":"US",
    "sg:address":"2300 Tanger Blvd",
    "sg:city":"Gonzales",
    "sg:classifiers":[
        {
            "category":"Shopping",
            "subcategory":"Clothing, Apparel, & Fashions",
            "type":"Retail Goods"
        }
    ],
    "sg:phone":"+1 225 647 3111",
    "sg:postcode":"70737",
    "sg:province":"LA",
    "wof:name":"Kasper LTD",
    "wof:placetype":"venue"
},
  "geometry": {"coordinates":[-90.95095499999999,30.2139],"type":"Point"}
}