{
  "type": "Feature",
  "properties": {
    "addr:full":"700 N 5th St Monroe LA 71201",
    "addr:housenumber":"700",
    "addr:postcode":"71201",
    "addr:street":"N 5Th St",
    "iso:country":"US",
    "sg:address":"700 N 5th St",
    "sg:city":"Monroe",
    "sg:classifiers":[
        {
            "category":"Personal",
            "subcategory":"Beauty Salon",
            "type":"Services"
        }
    ],
    "sg:phone":"+1 318 387 6425",
    "sg:postcode":"71201",
    "sg:province":"LA",
    "sg:tags":[
        "shop"
    ],
    "wof:name":"Uptown Cuts",
    "wof:placetype":"venue"
},
  "geometry": {"coordinates":[-92.11862000000001,32.5099],"type":"Point"}
}