{
  "type": "Feature",
  "properties": {
    "addr:full":"3627 Magazine St New Orleans LA 70115",
    "addr:housenumber":"3627",
    "addr:postcode":"70115",
    "addr:street":"Magazine St",
    "iso:country":"US",
    "sg:address":"3627 Magazine St",
    "sg:city":"New Orleans",
    "sg:classifiers":[
        {
            "category":"Manufacturing",
            "subcategory":"Tools & Machinery",
            "type":"Manufacturing & Wholesale Goods"
        }
    ],
    "sg:phone":"+1 504 897 6248",
    "sg:postcode":"70115",
    "sg:province":"LA",
    "sg:tags":[
        "orthopedic"
    ],
    "wof:name":"Lambert's Orthotics & Prsthtcs",
    "wof:placetype":"venue"
},
  "geometry": {"coordinates":[-90.091965,29.922101],"type":"Point"}
}