{
  "type": "Feature",
  "properties": {
    "iso:country":"US",
    "sg:address":"10619 Lyons St",
    "sg:city":"New Orleans",
    "sg:classifiers":[
        {
            "category":"Building & Trades",
            "subcategory":"Electrical",
            "type":"Services"
        }
    ],
    "sg:phone":"+1 504 738 6428",
    "sg:postcode":"70123",
    "sg:province":"LA",
    "sg:tags":[
        "electrical",
        "contractor"
    ],
    "wof:name":"K Heffner Electric",
    "wof:placetype":"venue"
},
  "geometry": {"coordinates":[-90.22371099999999,29.973436],"type":"Point"}
}