{
  "type": "Feature",
  "properties": {
    "iso:country":"US",
    "sg:address":"320 Magazine St",
    "sg:city":"New Orleans",
    "sg:classifiers":[
        {
            "category":"Professional",
            "type":"Services"
        }
    ],
    "sg:phone":"+1 504 525 3271",
    "sg:postcode":"70130",
    "sg:province":"LA",
    "sg:tags":[
        "establishment"
    ],
    "wof:name":"Joffray Maritime Inc",
    "wof:placetype":"venue"
},
  "geometry": {"coordinates":[-90.067759,29.949789],"type":"Point"}
}