{
  "type": "Feature",
  "properties": {
    "iso:country":"US",
    "sg:address":"5613 Kenilworth Cir",
    "sg:city":"Shreveport",
    "sg:classifiers":[
        {
            "category":"Real Estate",
            "subcategory":"Real Estate Agent",
            "type":"Services"
        }
    ],
    "sg:phone":"+1 318 688 2743",
    "sg:postcode":"71129",
    "sg:province":"LA",
    "sg:tags":[
        "appraiser"
    ],
    "wof:name":"Randy Brossette",
    "wof:placetype":"venue"
},
  "geometry": {"coordinates":[-93.852818,32.399546],"type":"Point"}
}