{
  "type": "Feature",
  "properties": {
    "addr:full":"285 S Morrison Blvd Hammond LA 70403",
    "addr:housenumber":"285",
    "addr:postcode":"70403",
    "addr:street":"S Morrison Blvd",
    "iso:country":"US",
    "sg:address":"285 S Morrison Blvd",
    "sg:city":"Hammond",
    "sg:classifiers":[
        {
            "category":"Food & Beverages",
            "subcategory":"Groceries & Convenience Stores",
            "type":"Retail Goods"
        }
    ],
    "sg:phone":"+1 985 345 6171",
    "sg:postcode":"70403",
    "sg:province":"LA",
    "wof:name":"Best Price",
    "wof:placetype":"venue"
},
  "geometry": {"coordinates":[-90.48258,30.498192],"type":"Point"}
}