{
  "type": "Feature",
  "properties": {
    "addr:full":"4900 W Main St Houma LA 70360",
    "addr:housenumber":"4900",
    "addr:postcode":"70360",
    "addr:street":"W Main St",
    "iso:country":"US",
    "sg:address":"4900 W Main St",
    "sg:city":"Houma",
    "sg:classifiers":[
        {
            "category":"Retail",
            "subcategory":"Auto Repair",
            "type":"Services"
        }
    ],
    "sg:phone":"+1 985 868 6501",
    "sg:postcode":"70360",
    "sg:province":"LA",
    "sg:tags":[
        "repairing",
        "automobile"
    ],
    "wof:name":"Car Doctor",
    "wof:placetype":"venue"
},
  "geometry": {"coordinates":[-90.771237,29.661878],"type":"Point"}
}