{
  "type": "Feature",
  "properties": {
    "iso:country":"US",
    "sg:address":"2005 Stumpf Blvd",
    "sg:city":"Gretna",
    "sg:classifiers":[
        {
            "category":"Personal",
            "subcategory":"Beauty Salon",
            "type":"Services"
        }
    ],
    "sg:phone":"+1 504 368 5050",
    "sg:postcode":"70056",
    "sg:province":"LA",
    "sg:tags":[
        "shop"
    ],
    "wof:name":"Professional Hair Care Inc",
    "wof:placetype":"venue"
},
  "geometry": {"coordinates":[-90.029617,29.908604],"type":"Point"}
}