{
  "type": "Feature",
  "properties": {
    "addr:full":"200 W 3rd St Edgard LA 70049",
    "addr:housenumber":"200",
    "addr:postcode":"70049",
    "addr:street":"W 3Rd St Edgard La",
    "iso:country":"US",
    "sg:address":"200 W 3rd St",
    "sg:city":"Edgard",
    "sg:classifiers":[
        {
            "category":"Organizations",
            "subcategory":"Religious Organization",
            "type":"Services"
        }
    ],
    "sg:phone":"+1 985 497 8311",
    "sg:postcode":"70049",
    "sg:province":"LA",
    "sg:tags":[
        "church"
    ],
    "wof:name":"New St Peter BC",
    "wof:placetype":"venue"
},
  "geometry": {"coordinates":[-90.60304499999999,30.03278],"type":"Point"}
}