{
  "type": "Feature",
  "properties": {
    "iso:country":"US",
    "sg:address":"34199 Jules Dr",
    "sg:city":"Donaldsonville",
    "sg:classifiers":[
        {
            "category":"Professional",
            "subcategory":"Accounting & Tax Preparation",
            "type":"Services"
        }
    ],
    "sg:phone":"+1 225 474 5954",
    "sg:postcode":"70346",
    "sg:province":"LA",
    "sg:tags":[
        "return",
        "filing"
    ],
    "wof:name":"Executive Decisions'",
    "wof:placetype":"venue"
},
  "geometry": {"coordinates":[-91.030401,30.077353],"type":"Point"}
}