{
  "type": "Feature",
  "properties": {
    "iso:country":"US",
    "sg:address":"600 Decatur St Ste 400",
    "sg:city":"New Orleans",
    "sg:classifiers":[
        {
            "category":"Professional",
            "type":"Services"
        }
    ],
    "sg:phone":"+1 504 525 3000",
    "sg:postcode":"70130",
    "sg:province":"LA",
    "sg:tags":[
        "caterer"
    ],
    "sg:website":"www.riverviewroom.com",
    "wof:name":"Riverview Room",
    "wof:placetype":"venue"
},
  "geometry": {"coordinates":[-90.063499,29.955799],"type":"Point"}
}