{
  "type": "Feature",
  "properties": {
    "iso:country":"US",
    "sg:address":"4100 Gus Young Ave",
    "sg:city":"Baton Rouge",
    "sg:classifiers":[
        {
            "category":"Government",
            "subcategory":"Office",
            "type":"Public Place"
        }
    ],
    "sg:phone":"+1 225 389 7805",
    "sg:postcode":"70802",
    "sg:province":"LA",
    "sg:tags":[
        "village"
    ],
    "wof:name":"Martin Luther King Ctr Adm",
    "wof:placetype":"venue"
},
  "geometry": {"coordinates":[-91.149192,30.461905],"type":"Point"}
}