{
  "type": "Feature",
  "properties": {
    "iso:country":"US",
    "sg:address":"3512 18th St",
    "sg:city":"Metairie",
    "sg:classifiers":[
        {
            "category":"Education",
            "subcategory":"Dance Studio",
            "type":"Public Place"
        }
    ],
    "sg:phone":"+1 504 888 4525",
    "sg:postcode":"70002",
    "sg:province":"LA",
    "sg:tags":[
        "instruction",
        "dancing"
    ],
    "wof:name":"Release Dance & Fitness Studio",
    "wof:placetype":"venue"
},
  "geometry": {"coordinates":[-90.159972,30.008485],"type":"Point"}
}