{
  "type": "Feature",
  "properties": {
    "iso:country":"US",
    "sg:address":"13935 US Hwy 90",
    "sg:city":"Boutte",
    "sg:classifiers":[
        {
            "category":"Freight",
            "type":"Transportation"
        }
    ],
    "sg:phone":"+1 985 785 7702",
    "sg:postcode":"70039",
    "sg:province":"LA",
    "sg:tags":[
        "commercial",
        "storage"
    ],
    "wof:name":"Boutte Mini Storage",
    "wof:placetype":"venue"
},
  "geometry": {"coordinates":[-90.39174300000001,29.898832],"type":"Point"}
}