{
  "type": "Feature",
  "properties": {
    "addr:full":"1650 Florida Blvd Baton Rouge LA 70802",
    "addr:housenumber":"1650",
    "addr:postcode":"70802",
    "addr:street":"Florida Blvd",
    "iso:country":"US",
    "sg:address":"1650 Florida Blvd",
    "sg:city":"Baton Rouge",
    "sg:classifiers":[
        {
            "category":"Banks & Credit Unions",
            "subcategory":"Bank",
            "type":"Services"
        }
    ],
    "sg:phone":"+1 225 354 0688",
    "sg:postcode":"70802",
    "sg:province":"LA",
    "sg:tags":[
        "loan"
    ],
    "wof:name":"Cash Loans Til Payday",
    "wof:placetype":"venue"
},
  "geometry": {"coordinates":[-91.171171,30.449752],"type":"Point"}
}