{
  "type": "Feature",
  "properties": {
    "iso:country":"US",
    "sg:address":"9160 Methodist St",
    "sg:city":"Convent",
    "sg:classifiers":[
        {
            "category":"Organizations",
            "subcategory":"Religious Organization",
            "type":"Services"
        }
    ],
    "sg:phone":"+1 225 562 3415",
    "sg:postcode":"70723",
    "sg:province":"LA",
    "wof:name":"St James United Methdst Church",
    "wof:placetype":"venue"
},
  "geometry": {"coordinates":[-90.89689300000001,30.077005],"type":"Point"}
}