{
  "type": "Feature",
  "properties": {
    "iso:country":"US",
    "sg:address":"1010 Common St",
    "sg:city":"New Orleans",
    "sg:classifiers":[
        {
            "category":"Personal",
            "type":"Services"
        }
    ],
    "sg:phone":"+1 504 218 4000",
    "sg:postcode":"70130",
    "sg:province":"LA",
    "sg:tags":[
        "dating"
    ],
    "wof:name":"It's Just Lunch",
    "wof:placetype":"venue"
},
  "geometry": {"coordinates":[-90.07388899999999,29.954029],"type":"Point"}
}