{
  "type": "Feature",
  "properties": {
    "iso:country":"US",
    "sg:address":"1700 S Westport Dr",
    "sg:city":"Port Allen",
    "sg:classifiers":[
        {
            "category":"Manufacturing",
            "subcategory":"Metals",
            "type":"Manufacturing & Wholesale Goods"
        }
    ],
    "sg:phone":"+1 225 381 9422",
    "sg:postcode":"70767",
    "sg:province":"LA",
    "sg:tags":[
        "pipe",
        "bending",
        "fabricating"
    ],
    "wof:name":"International Piping Systems",
    "wof:placetype":"venue"
},
  "geometry": {"coordinates":[-91.223358,30.442085],"type":"Point"}
}