{
  "type": "Feature",
  "properties": {
    "addr:full":"610 Frenchmen St New Orleans LA 70116",
    "addr:housenumber":"610",
    "addr:postcode":"70116",
    "addr:street":"Frenchmen St",
    "iso:country":"US",
    "sg:address":"610 Frenchmen St",
    "sg:city":"New Orleans",
    "sg:classifiers":[
        {
            "category":"Personal",
            "subcategory":"Tattoo Parlor",
            "type":"Services"
        }
    ],
    "sg:phone":"+1 504 947 8286",
    "sg:postcode":"70116",
    "sg:province":"LA",
    "sg:tags":[
        "tattooing",
        "piercing"
    ],
    "sg:website":"www.electricladyland.net",
    "wof:name":"Electric Ladyland Tattoo",
    "wof:placetype":"venue"
},
  "geometry": {"coordinates":[-90.057801,29.963807],"type":"Point"}
}