{
  "type": "Feature",
  "properties": {
    "iso:country":"US",
    "sg:address":"1630 E Bert Kouns Industrial Loop",
    "sg:city":"Shreveport",
    "sg:classifiers":[
        {
            "category":"Restaurant",
            "type":"Food & Drink"
        }
    ],
    "sg:menulink":"http://www.allmenus.com/la/shreveport/208646-taco-bell/menu/",
    "sg:phone":"+1 318 798 2787",
    "sg:postcode":"71105",
    "sg:province":"LA",
    "sg:tags":[
        "mexican"
    ],
    "wof:name":"Taco Bell",
    "wof:placetype":"venue"
},
  "geometry": {"coordinates":[-93.71724500000001,32.428023],"type":"Point"}
}