{
  "type": "Feature",
  "properties": {
    "addr:full":"334 Hord St New Orleans LA 70123",
    "addr:housenumber":"334",
    "addr:postcode":"70123",
    "addr:street":"Hord St",
    "iso:country":"US",
    "sg:address":"334 Hord St",
    "sg:city":"New Orleans",
    "sg:classifiers":[
        {
            "category":"Building & Trades",
            "subcategory":"Construction",
            "type":"Services"
        }
    ],
    "sg:phone":"+1 504 734 5454",
    "sg:postcode":"70123",
    "sg:province":"LA",
    "sg:tags":[
        "maker",
        "cabinet"
    ],
    "wof:name":"Copeland's Fine Woodworks",
    "wof:placetype":"venue"
},
  "geometry": {"coordinates":[-90.193117,29.944954],"type":"Point"}
}