{
  "type": "Feature",
  "properties": {
    "iso:country":"US",
    "sg:address":"1300 E Pont Des Mouton Rd Ofc",
    "sg:city":"Lafayette",
    "sg:classifiers":[
        {
            "category":"Real Estate",
            "subcategory":"Real Estate Operator",
            "type":"Services"
        }
    ],
    "sg:phone":"+1 337 233 6545",
    "sg:postcode":"70507",
    "sg:province":"LA",
    "sg:tags":[
        "apartment"
    ],
    "wof:name":"Castille Charles A Jr Ofc",
    "wof:placetype":"venue"
},
  "geometry": {"coordinates":[-91.990501,30.272301],"type":"Point"}
}