{
  "type": "Feature",
  "properties": {
    "iso:country":"US",
    "sg:address":"344 Frederick St",
    "sg:city":"New Iberia",
    "sg:classifiers":[
        {
            "category":"Real Estate",
            "subcategory":"Real Estate Operator",
            "type":"Services"
        }
    ],
    "sg:phone":"+1 337 365 6816",
    "sg:postcode":"70560",
    "sg:province":"LA",
    "sg:tags":[
        "apartment"
    ],
    "wof:name":"Bacmonila Garden Apts",
    "wof:placetype":"venue"
},
  "geometry": {"coordinates":[-91.837502,29.998699],"type":"Point"}
}