{
  "type": "Feature",
  "properties": {
    "iso:country":"US",
    "sg:address":"2215 Engineers Rd",
    "sg:city":"Belle Chasse",
    "sg:classifiers":[
        {
            "category":"Building & Trades",
            "subcategory":"Construction",
            "type":"Services"
        }
    ],
    "sg:phone":"+1 504 393 8904",
    "sg:postcode":"70037",
    "sg:province":"LA",
    "sg:tags":[
        "contractor"
    ],
    "wof:name":"Competitive Contracting LLC",
    "wof:placetype":"venue"
},
  "geometry": {"coordinates":[-90.03398,29.846144],"type":"Point"}
}