{
  "type": "Feature",
  "properties": {
    "addr:full":"5324 Cypress St West Monroe LA 71291",
    "addr:housenumber":"5324",
    "addr:postcode":"71291",
    "addr:street":"Cypress St West",
    "iso:country":"US",
    "sg:address":"5324 Cypress St",
    "sg:city":"West Monroe",
    "sg:classifiers":[
        {
            "category":"Retail",
            "subcategory":"Laundry & Dry Cleaning",
            "type":"Services"
        }
    ],
    "sg:phone":"+1 318 397 8700",
    "sg:postcode":"71291",
    "sg:province":"LA",
    "sg:tags":[
        "cleaners"
    ],
    "wof:name":"Weil Cleaners",
    "wof:placetype":"venue"
},
  "geometry": {"coordinates":[-92.190845,32.515987],"type":"Point"}
}