{
  "type": "Feature",
  "properties": {
    "iso:country":"US",
    "sg:address":"550 Farenzie Rd",
    "sg:city":"Colfax",
    "sg:classifiers":[
        {
            "category":"Real Estate",
            "subcategory":"Real Estate Operator",
            "type":"Services"
        }
    ],
    "sg:phone":"+1 318 627 3740",
    "sg:postcode":"71417",
    "sg:province":"LA",
    "sg:tags":[
        "building",
        "apartment"
    ],
    "wof:name":"Pecan Grove Apartments",
    "wof:placetype":"venue"
},
  "geometry": {"coordinates":[-92.688569,31.525709],"type":"Point"}
}