{
  "type": "Feature",
  "properties": {
    "addr:full":"1119 Barrow St Houma LA 70360",
    "addr:housenumber":"1119",
    "addr:postcode":"70360",
    "addr:street":"Barrow St",
    "iso:country":"US",
    "sg:address":"1119 Barrow St",
    "sg:city":"Houma",
    "sg:classifiers":[
        {
            "category":"Personal",
            "subcategory":"Beauty Salon",
            "type":"Services"
        }
    ],
    "sg:phone":"+1 985 851 3344",
    "sg:postcode":"70360",
    "sg:province":"LA",
    "wof:name":"Progressive Hair Nails/Designs",
    "wof:placetype":"venue"
},
  "geometry": {"coordinates":[-90.720266,29.590235],"type":"Point"}
}