{
  "type": "Feature",
  "properties": {
    "iso:country":"US",
    "sg:address":"7851 State Rte 87",
    "sg:city":"Jeanerette",
    "sg:classifiers":[
        {
            "category":"Building & Trades",
            "subcategory":"Landscaping Services",
            "type":"Services"
        }
    ],
    "sg:phone":"+1 337 924 7001",
    "sg:postcode":"70544",
    "sg:province":"LA",
    "sg:tags":[
        "landscape",
        "contractor"
    ],
    "wof:name":"Creative Landscaping",
    "wof:placetype":"venue"
},
  "geometry": {"coordinates":[-91.537167,29.887843],"type":"Point"}
}