{
  "type": "Feature",
  "properties": {
    "addr:full":"338 Belleville St New Orleans LA 70114",
    "addr:housenumber":"338",
    "addr:postcode":"70114",
    "addr:street":"Belleville St",
    "iso:country":"US",
    "sg:address":"338 Belleville St",
    "sg:city":"New Orleans",
    "sg:classifiers":[
        {
            "category":"Banks & Credit Unions",
            "subcategory":"Financial Services",
            "type":"Services"
        }
    ],
    "sg:phone":"+1 504 361 0710",
    "sg:postcode":"70114",
    "sg:province":"LA",
    "sg:tags":[
        "annuity",
        "insurance"
    ],
    "wof:name":"Members Group",
    "wof:placetype":"venue"
},
  "geometry": {"coordinates":[-90.047864,29.952508],"type":"Point"}
}