{
  "type": "Feature",
  "properties": {
    "iso:country":"US",
    "sg:address":"6309 Ernwood Cir",
    "sg:city":"Shreveport",
    "sg:classifiers":[
        {
            "category":"Building & Trades",
            "subcategory":"Cleaning & Sanitation",
            "type":"Services"
        }
    ],
    "sg:phone":"+1 318 631 7698",
    "sg:postcode":"71119",
    "sg:province":"LA",
    "sg:tags":[
        "janitor"
    ],
    "wof:name":"W & W Janitorial Svc",
    "wof:placetype":"venue"
},
  "geometry": {"coordinates":[-93.872603,32.473479],"type":"Point"}
}