{
  "type": "Feature",
  "properties": {
    "iso:country":"US",
    "sg:address":"105 Derrick Rd",
    "sg:city":"Broussard",
    "sg:classifiers":[
        {
            "category":"Home & Garden",
            "subcategory":"Household Appliances",
            "type":"Retail Goods"
        }
    ],
    "sg:phone":"+1 337 837 4772",
    "sg:postcode":"70518",
    "sg:province":"LA",
    "sg:tags":[
        "pump"
    ],
    "wof:name":"Moore's Pump & Svc Inc",
    "wof:placetype":"venue"
},
  "geometry": {"coordinates":[-91.984863,30.165686],"type":"Point"}
}