{
  "type": "Feature",
  "properties": {
    "addr:full":"1801 S Sherwood Forest Blvd Baton Rouge LA 70816",
    "addr:housenumber":"1801",
    "addr:postcode":"70816",
    "addr:street":"S Sherwood Forest Blvd",
    "iso:country":"US",
    "sg:address":"1801 S Sherwood Forest Blvd",
    "sg:city":"Baton Rouge",
    "sg:classifiers":[
        {
            "category":"Restaurant",
            "type":"Food & Drink"
        }
    ],
    "sg:menulink":"http://www.allmenus.com/la/baton-rouge/201491-sonic/menu/",
    "sg:phone":"+1 225 273 6220",
    "sg:postcode":"70816",
    "sg:province":"LA",
    "sg:tags":[
        "burger",
        "american"
    ],
    "wof:name":"Sonic",
    "wof:placetype":"venue"
},
  "geometry": {"coordinates":[-91.05733600000001,30.43679],"type":"Point"}
}