{
  "type": "Feature",
  "properties": {
    "iso:country":"US",
    "sg:address":"249 W Saint Peter St",
    "sg:city":"New Iberia",
    "sg:classifiers":[
        {
            "category":"Retail",
            "subcategory":"Laundry & Dry Cleaning",
            "type":"Services"
        }
    ],
    "sg:phone":"+1 337 369 6021",
    "sg:postcode":"70560",
    "sg:province":"LA",
    "sg:tags":[
        "cleaners"
    ],
    "wof:name":"Derouen Cleaners",
    "wof:placetype":"venue"
},
  "geometry": {"coordinates":[-91.821023,30.006658],"type":"Point"}
}