{
  "type": "Feature",
  "properties": {
    "iso:country":"US",
    "sg:address":"3711 Cypress St",
    "sg:city":"West Monroe",
    "sg:classifiers":[
        {
            "category":"Professional",
            "subcategory":"Business Services",
            "type":"Services"
        }
    ],
    "sg:phone":"+1 318 397 2729",
    "sg:postcode":"71291",
    "sg:province":"LA",
    "sg:tags":[
        "sales",
        "estate"
    ],
    "wof:name":"QPC Real Estate Svc",
    "wof:placetype":"venue"
},
  "geometry": {"coordinates":[-92.16791600000001,32.517116],"type":"Point"}
}