{
  "type": "Feature",
  "properties": {
    "iso:country":"US",
    "sg:address":"810 Union St",
    "sg:city":"New Orleans",
    "sg:classifiers":[
        {
            "category":"Real Estate",
            "subcategory":"Architect",
            "type":"Services"
        }
    ],
    "sg:phone":"+1 504 525 4491",
    "sg:postcode":"70112",
    "sg:province":"LA",
    "wof:name":"Lyons & Hudson Architects LTD",
    "wof:placetype":"venue"
},
  "geometry": {"coordinates":[-90.07238599999999,29.9517],"type":"Point"}
}