{
  "type": "Feature",
  "properties": {
    "iso:country":"US",
    "sg:address":"1058 Smede Rd",
    "sg:city":"Saint Martinville",
    "sg:classifiers":[
        {
            "category":"Bars & Pubs",
            "subcategory":"Nightclub",
            "type":"Food & Drink"
        }
    ],
    "sg:phone":"+1 337 367 5106",
    "sg:postcode":"70582",
    "sg:province":"LA",
    "sg:tags":[
        "nightlife"
    ],
    "wof:name":"Macks Place",
    "wof:placetype":"venue"
},
  "geometry": {"coordinates":[-91.825798,30.1367],"type":"Point"}
}