{
  "type": "Feature",
  "properties": {
    "iso:country":"US",
    "sg:address":"4 Sanctuary Blvd",
    "sg:city":"Mandeville",
    "sg:classifiers":[
        {
            "category":"Real Estate",
            "subcategory":"Developer",
            "type":"Services"
        }
    ],
    "sg:phone":"+1 985 845 0730",
    "sg:postcode":"70471",
    "sg:province":"LA",
    "wof:name":"Bedico Creek Development",
    "wof:placetype":"venue"
},
  "geometry": {"coordinates":[-90.10403100000001,30.392759],"type":"Point"}
}