{
  "type": "Feature",
  "properties": {
    "iso:country":"US",
    "sg:address":"3500 Houston River Rd",
    "sg:city":"Westlake",
    "sg:classifiers":[
        {
            "category":"Building & Trades",
            "subcategory":"Construction",
            "type":"Services"
        }
    ],
    "sg:phone":"+1 337 436 8038",
    "sg:postcode":"70669",
    "sg:province":"LA",
    "sg:tags":[
        "material",
        "paving"
    ],
    "wof:name":"ISG Resources Inc",
    "wof:placetype":"venue"
},
  "geometry": {"coordinates":[-93.298202,30.2721],"type":"Point"}
}