{
  "type": "Feature",
  "properties": {
    "iso:country":"US",
    "sg:address":"4242 Hwy 191",
    "sg:city":"Converse",
    "sg:classifiers":[
        {
            "category":"Organizations",
            "subcategory":"Religious Organization",
            "type":"Services"
        }
    ],
    "sg:phone":"+1 318 567 3670",
    "sg:postcode":"71419",
    "sg:province":"LA",
    "sg:tags":[
        "church"
    ],
    "wof:name":"Henrietta Congregational Meth",
    "wof:placetype":"venue"
},
  "geometry": {"coordinates":[-93.781644,31.791285],"type":"Point"}
}