{
  "type": "Feature",
  "properties": {
    "addr:full":"1109 Garden Dr Westlake LA 70669",
    "addr:housenumber":"1109",
    "addr:postcode":"70669",
    "addr:street":"Garden Dr",
    "iso:country":"US",
    "sg:address":"1109 Garden Dr",
    "sg:city":"Westlake",
    "sg:classifiers":[
        {
            "category":"Real Estate",
            "subcategory":"Real Estate Operator",
            "type":"Services"
        }
    ],
    "sg:phone":"+1 337 433 1103",
    "sg:postcode":"70669",
    "sg:province":"LA",
    "sg:tags":[
        "apartment"
    ],
    "wof:name":"Westlake Eldery Apartments",
    "wof:placetype":"venue"
},
  "geometry": {"coordinates":[-93.267442,30.26043],"type":"Point"}
}