{
  "type": "Feature",
  "properties": {
    "iso:country":"US",
    "sg:address":"3615 Groom Rd",
    "sg:city":"Baker",
    "sg:classifiers":[
        {
            "category":"Social Services",
            "subcategory":"Child Care",
            "type":"Services"
        }
    ],
    "sg:phone":"+1 225 775 6491",
    "sg:postcode":"70714",
    "sg:province":"LA",
    "wof:name":"Baker's Busy Bee Learning Ctr",
    "wof:placetype":"venue"
},
  "geometry": {"coordinates":[-91.16135199999999,30.587795],"type":"Point"}
}