{
  "type": "Feature",
  "properties": {
    "iso:country":"US",
    "sg:address":"303 S Young St",
    "sg:city":"Abbeville",
    "sg:classifiers":[
        {
            "category":"Building & Trades",
            "subcategory":"Plumbing",
            "type":"Services"
        }
    ],
    "sg:phone":"+1 337 893 2198",
    "sg:postcode":"70510",
    "sg:province":"LA",
    "sg:tags":[
        "heating",
        "contractor"
    ],
    "wof:name":"Desormeaux's Heating & AC",
    "wof:placetype":"venue"
},
  "geometry": {"coordinates":[-92.129825,29.970883],"type":"Point"}
}