{
  "type": "Feature",
  "properties": {
    "iso:country":"US",
    "sg:address":"503 Comanche Trl",
    "sg:city":"West Monroe",
    "sg:classifiers":[
        {
            "category":"Manufacturing",
            "subcategory":"Metals",
            "type":"Manufacturing & Wholesale Goods"
        }
    ],
    "sg:phone":"+1 318 396 7517",
    "sg:postcode":"71291",
    "sg:province":"LA",
    "sg:tags":[
        "industrial",
        "valve",
        "mfg"
    ],
    "wof:name":"Velan Valve Corporation",
    "wof:placetype":"venue"
},
  "geometry": {"coordinates":[-92.23559899999999,32.550239],"type":"Point"}
}