{
  "type": "Feature",
  "properties": {
    "addr:full":"5381 Moss St Lafayette LA 70507",
    "addr:postcode":"5381;70507",
    "addr:street":"Moss St",
    "iso:country":"US",
    "sg:address":"5381 Moss St",
    "sg:city":"Lafayette",
    "sg:classifiers":[
        {
            "category":"Recreation",
            "type":"Entertainment"
        }
    ],
    "sg:phone":"+1 337 896 2902",
    "sg:postcode":"70507",
    "sg:province":"LA",
    "sg:tags":[
        "riding",
        "academy"
    ],
    "wof:name":"Acadiana Therapeutic Riding",
    "wof:placetype":"venue"
},
  "geometry": {"coordinates":[-92.008431,30.310774],"type":"Point"}
}