{
  "type": "Feature",
  "properties": {
    "iso:country":"US",
    "sg:address":"14214 State Rte 73",
    "sg:city":"Prairieville",
    "sg:classifiers":[
        {
            "category":"Bars & Pubs",
            "type":"Food & Drink"
        }
    ],
    "sg:phone":"+1 225 673 6755",
    "sg:postcode":"70769",
    "sg:province":"LA",
    "sg:tags":[
        "lounge",
        "cocktail"
    ],
    "wof:name":"Cottage Inn",
    "wof:placetype":"venue"
},
  "geometry": {"coordinates":[-90.983875,30.274503],"type":"Point"}
}