{
  "type": "Feature",
  "properties": {
    "iso:country":"US",
    "sg:address":"39 Deloaks Dr",
    "sg:city":"Madisonville",
    "sg:classifiers":[
        {
            "category":"Wholesale",
            "subcategory":"Non-durable Goods",
            "type":"Manufacturing & Wholesale Goods"
        }
    ],
    "sg:phone":"+1 985 845 0662",
    "sg:postcode":"70447",
    "sg:province":"LA",
    "sg:tags":[
        "architectural",
        "supply"
    ],
    "wof:name":"Kohler Building Specialties",
    "wof:placetype":"venue"
},
  "geometry": {"coordinates":[-90.137238,30.413557],"type":"Point"}
}