{
  "type": "Feature",
  "properties": {
    "iso:country":"US",
    "sg:address":"644 E Broussard Rd",
    "sg:city":"Lafayette",
    "sg:classifiers":[
        {
            "category":"Mining & Drilling",
            "type":"Manufacturing & Wholesale Goods"
        }
    ],
    "sg:phone":"+1 337 984 5257",
    "sg:postcode":"70503",
    "sg:province":"LA",
    "sg:tags":[
        "limestone"
    ],
    "wof:name":"Construction Aggregate Supply",
    "wof:placetype":"venue"
},
  "geometry": {"coordinates":[-92.07762099999999,30.142186],"type":"Point"}
}