{
  "type": "Feature",
  "properties": {
    "iso:country":"US",
    "sg:address":"201 3rd St",
    "sg:city":"Jonesville",
    "sg:classifiers":[
        {
            "category":"Health Services",
            "subcategory":"Doctor",
            "type":"Services"
        }
    ],
    "sg:phone":"+1 318 339 9852",
    "sg:postcode":"71343",
    "sg:province":"LA",
    "sg:tags":[
        "dentist"
    ],
    "wof:name":"James Jones DDS",
    "wof:placetype":"venue"
},
  "geometry": {"coordinates":[-91.81547999999999,31.626089],"type":"Point"}
}