{
  "type": "Feature",
  "properties": {
    "iso:country":"US",
    "sg:address":"2668 Johnston St",
    "sg:city":"Lafayette",
    "sg:classifiers":[
        {
            "category":"Retail",
            "subcategory":"Laundry & Dry Cleaning",
            "type":"Services"
        }
    ],
    "sg:phone":"+1 337 237 8004",
    "sg:postcode":"70503",
    "sg:province":"LA",
    "sg:tags":[
        "cleaners"
    ],
    "wof:name":"Golden Cleaners",
    "wof:placetype":"venue"
},
  "geometry": {"coordinates":[-92.037764,30.207738],"type":"Point"}
}