{
  "type": "Feature",
  "properties": {
    "addr:full":"1024 Pierre Ave Shreveport LA 71103",
    "addr:housenumber":"1024",
    "addr:postcode":"71103",
    "addr:street":"Pierre Ave",
    "iso:country":"US",
    "sg:address":"1024 Pierre Ave",
    "sg:city":"Shreveport",
    "sg:classifiers":[
        {
            "category":"Organizations",
            "subcategory":"Professional Association",
            "type":"Services"
        }
    ],
    "sg:phone":"+1 318 425 2002",
    "sg:postcode":"71103",
    "sg:province":"LA",
    "wof:name":"Association For Community",
    "wof:placetype":"venue"
},
  "geometry": {"coordinates":[-93.76321900000001,32.501983],"type":"Point"}
}