{
  "type": "Feature",
  "properties": {
    "addr:full":"224 Woodland Dr La Place LA 70068",
    "addr:housenumber":"224",
    "addr:postcode":"70068",
    "addr:street":"Woodland Dr La Place",
    "iso:country":"US",
    "sg:address":"224 Woodland Dr",
    "sg:city":"La Place",
    "sg:classifiers":[
        {
            "category":"Wholesale",
            "subcategory":"Machinery & Supplies",
            "type":"Manufacturing & Wholesale Goods"
        }
    ],
    "sg:phone":"+1 985 651 6250",
    "sg:postcode":"70068",
    "sg:province":"LA",
    "sg:tags":[
        "equipment",
        "laundry"
    ],
    "wof:name":"ITEC Corp",
    "wof:placetype":"venue"
},
  "geometry": {"coordinates":[-90.453373,30.090087],"type":"Point"}
}