{
  "type": "Feature",
  "properties": {
    "addr:full":"680 Robert E Lee Blvd New Orleans LA 70124",
    "addr:housenumber":"680",
    "addr:postcode":"70124",
    "addr:street":"Robert E Lee Blvd",
    "iso:country":"US",
    "sg:address":"680 Robert E Lee Blvd",
    "sg:city":"New Orleans",
    "sg:classifiers":[
        {
            "category":"Professional",
            "type":"Services"
        }
    ],
    "sg:phone":"+1 504 288 2286",
    "sg:postcode":"70124",
    "sg:province":"LA",
    "wof:name":"Ivanhoe LLC",
    "wof:placetype":"venue"
},
  "geometry": {"coordinates":[-90.106799,30.01943],"type":"Point"}
}