{
  "type": "Feature",
  "properties": {
    "iso:country":"US",
    "sg:address":"1455 Curtis St",
    "sg:city":"Baton Rouge",
    "sg:classifiers":[
        {
            "category":"Insurance",
            "subcategory":"Insurance Agent",
            "type":"Services"
        }
    ],
    "sg:phone":"+1 225 775 0996",
    "sg:postcode":"70807",
    "sg:province":"LA",
    "wof:name":"Hayes Insurance Inc",
    "wof:placetype":"venue"
},
  "geometry": {"coordinates":[-91.17800200000001,30.521432],"type":"Point"}
}