{
  "type": "Feature",
  "properties": {
    "iso:country":"US",
    "sg:address":"5908 Industrial Dr Exd",
    "sg:city":"Bossier City",
    "sg:classifiers":[
        {
            "category":"Wholesale",
            "subcategory":"Machinery & Supplies",
            "type":"Manufacturing & Wholesale Goods"
        }
    ],
    "sg:phone":"+1 318 746 5272",
    "sg:postcode":"71112",
    "sg:province":"LA",
    "sg:tags":[
        "contractor"
    ],
    "wof:name":"H & E Equipment Svc",
    "wof:placetype":"venue"
},
  "geometry": {"coordinates":[-93.65705,32.53251],"type":"Point"}
}