{
  "type": "Feature",
  "properties": {
    "addr:full":"1460 Annunciation St New Orleans LA 70130",
    "addr:housenumber":"1460",
    "addr:postcode":"70130",
    "addr:street":"Annunciation St",
    "iso:country":"US",
    "sg:address":"1460 Annunciation St",
    "sg:city":"New Orleans",
    "sg:classifiers":[
        {
            "category":"Wholesale",
            "subcategory":"Machinery & Supplies",
            "type":"Manufacturing & Wholesale Goods"
        }
    ],
    "sg:phone":"+1 504 522 9322",
    "sg:postcode":"70130",
    "sg:province":"LA",
    "sg:tags":[
        "tool",
        "oil",
        "well",
        "fishing"
    ],
    "wof:name":"Tri-Tech Fishing Svc",
    "wof:placetype":"venue"
},
  "geometry": {"coordinates":[-90.069709,29.934015],"type":"Point"}
}