{
  "type": "Feature",
  "properties": {
    "iso:country":"US",
    "sg:address":"5438 Pauline Dr",
    "sg:city":"New Orleans",
    "sg:classifiers":[
        {
            "category":"Real Estate",
            "subcategory":"Real Estate Agent",
            "type":"Services"
        }
    ],
    "sg:phone":"+1 504 288 7307",
    "sg:postcode":"70126",
    "sg:province":"LA",
    "sg:tags":[
        "appraiser"
    ],
    "wof:name":"Warren Williams Enterprises",
    "wof:placetype":"venue"
},
  "geometry": {"coordinates":[-90.034069,30.018129],"type":"Point"}
}