{
  "type": "Feature",
  "properties": {
    "iso:country":"US",
    "sg:address":"500 Flournoy Lucas Rd",
    "sg:city":"Shreveport",
    "sg:classifiers":[
        {
            "category":"Recreation",
            "type":"Entertainment"
        }
    ],
    "sg:phone":"+1 318 686 2295",
    "sg:postcode":"71106",
    "sg:province":"LA",
    "sg:tags":[
        "instruction",
        "gymnastic"
    ],
    "wof:name":"Cheer Connection",
    "wof:placetype":"venue"
},
  "geometry": {"coordinates":[-93.77013599999999,32.391008],"type":"Point"}
}