{
  "type": "Feature",
  "properties": {
    "iso:country":"US",
    "sg:address":"200 S Long St",
    "sg:city":"Lafayette",
    "sg:classifiers":[
        {
            "category":"Building & Trades",
            "subcategory":"Construction",
            "type":"Services"
        }
    ],
    "sg:phone":"+1 337 233 5114",
    "sg:postcode":"70506",
    "sg:province":"LA",
    "sg:tags":[
        "contractor"
    ],
    "wof:name":"J L Ducharme Construction",
    "wof:placetype":"venue"
},
  "geometry": {"coordinates":[-92.053769,30.221142],"type":"Point"}
}