{
  "type": "Feature",
  "properties": {
    "addr:full":"1550 Northgate Rd Bossier City LA 71112",
    "addr:housenumber":"1550",
    "addr:postcode":"71112",
    "addr:street":"Northgate Rd",
    "iso:country":"US",
    "sg:address":"1550 Northgate Rd",
    "sg:city":"Bossier City",
    "sg:classifiers":[
        {
            "category":"Health Services",
            "subcategory":"Medical Lab",
            "type":"Services"
        }
    ],
    "sg:phone":"+1 318 742 7229",
    "sg:postcode":"71112",
    "sg:province":"LA",
    "sg:tags":[
        "laboratory"
    ],
    "wof:name":"CDS Dental Studio",
    "wof:placetype":"venue"
},
  "geometry": {"coordinates":[-93.688108,32.51614],"type":"Point"}
}