{
  "type": "Feature",
  "properties": {
    "addr:full":"34045 Walker Rd N Walker LA 70785",
    "addr:housenumber":"34045",
    "addr:postcode":"70785",
    "addr:street":"Walker Rd N",
    "iso:country":"US",
    "sg:address":"34045 Walker Rd N",
    "sg:city":"Walker",
    "sg:classifiers":[
        {
            "category":"Retail",
            "subcategory":"Animal Services",
            "type":"Services"
        }
    ],
    "sg:phone":"+1 225 667 0823",
    "sg:postcode":"70785",
    "sg:province":"LA",
    "sg:tags":[
        "organization",
        "show"
    ],
    "sg:website":"www.ckcusa.com",
    "wof:name":"Continental Kennel Club",
    "wof:placetype":"venue"
},
  "geometry": {"coordinates":[-90.870093,30.56176],"type":"Point"}
}