{
  "type": "Feature",
  "properties": {
    "addr:full":"3825 Plaza Dr Chalmette LA 70043",
    "addr:housenumber":"3825",
    "addr:postcode":"70043",
    "addr:street":"Plaza Dr Chalmette",
    "iso:country":"US",
    "sg:address":"3825 Plaza Dr",
    "sg:city":"Chalmette",
    "sg:classifiers":[
        {
            "category":"Wholesale",
            "subcategory":"Seafood",
            "type":"Manufacturing & Wholesale Goods"
        }
    ],
    "sg:phone":"+1 504 279 5377",
    "sg:postcode":"70043",
    "sg:province":"LA",
    "wof:name":"Southern Seafood Exchange",
    "wof:placetype":"venue"
},
  "geometry": {"coordinates":[-89.94897899999999,29.952721],"type":"Point"}
}