{
  "type": "Feature",
  "properties": {
    "iso:country":"US",
    "sg:address":"1215 Texas Ave",
    "sg:city":"Shreveport",
    "sg:classifiers":[
        {
            "category":"Real Estate",
            "subcategory":"Developer",
            "type":"Services"
        }
    ],
    "sg:phone":"+1 318 221 0559",
    "sg:postcode":"71101",
    "sg:province":"LA",
    "wof:name":"Downtown Development Authority",
    "wof:placetype":"venue"
},
  "geometry": {"coordinates":[-93.754653,32.500133],"type":"Point"}
}