{
  "type": "Feature",
  "properties": {
    "iso:country":"US",
    "sg:address":"7140 Florita Ct",
    "sg:city":"New Orleans",
    "sg:classifiers":[
        {
            "category":"Recreation",
            "type":"Entertainment"
        }
    ],
    "sg:phone":"+1 504 242 5331",
    "sg:postcode":"70126",
    "sg:province":"LA",
    "sg:tags":[
        "amusement"
    ],
    "wof:name":"DCP Motorsports Inc",
    "wof:placetype":"venue"
},
  "geometry": {"coordinates":[-90.024759,30.024551],"type":"Point"}
}