{
  "type": "Feature",
  "properties": {
    "iso:country":"US",
    "sg:address":"2022 Tamvest Ct",
    "sg:city":"Mandeville",
    "sg:classifiers":[
        {
            "category":"Wholesale",
            "subcategory":"Machinery & Supplies",
            "type":"Manufacturing & Wholesale Goods"
        }
    ],
    "sg:phone":"+1 985 626 0077",
    "sg:postcode":"70448",
    "sg:province":"LA",
    "sg:tags":[
        "valve"
    ],
    "sg:website":"www.fairengineering.com",
    "wof:name":"Fair T Engineering Sales",
    "wof:placetype":"venue"
},
  "geometry": {"coordinates":[-90.054855,30.377147],"type":"Point"}
}