{
  "type": "Feature",
  "properties": {
    "addr:full":"3401 W Esplanade Ave S Metairie LA 70002",
    "addr:housenumber":"3401",
    "addr:postcode":"70002",
    "addr:street":"W Esplanade Ave S Metairie",
    "iso:country":"US",
    "sg:address":"3401 W Esplanade Ave S",
    "sg:city":"Metairie",
    "sg:classifiers":[
        {
            "category":"Professional",
            "subcategory":"Lawyer & Legal Services",
            "type":"Services"
        }
    ],
    "sg:phone":"+1 985 674 1492",
    "sg:postcode":"70002",
    "sg:province":"LA",
    "sg:tags":[
        "attorney"
    ],
    "wof:name":"Dunn Law Firm",
    "wof:placetype":"venue"
},
  "geometry": {"coordinates":[-90.15897200000001,30.014104],"type":"Point"}
}