{
  "type": "Feature",
  "properties": {
    "iso:country":"US",
    "sg:address":"3832 Chinkapin St",
    "sg:city":"Harvey",
    "sg:classifiers":[
        {
            "category":"Professional",
            "subcategory":"Detective & Security Services",
            "type":"Services"
        }
    ],
    "sg:phone":"+1 504 348 2705",
    "sg:postcode":"70058",
    "sg:province":"LA",
    "sg:tags":[
        "guard",
        "patrol"
    ],
    "wof:name":"Guaranted Guard Svc",
    "wof:placetype":"venue"
},
  "geometry": {"coordinates":[-90.07558400000001,29.853558],"type":"Point"}
}