{
  "type": "Feature",
  "properties": {
    "iso:country":"US",
    "sg:address":"1174 Cormier Rd",
    "sg:city":"Breaux Bridge",
    "sg:classifiers":[
        {
            "category":"Building & Trades",
            "subcategory":"Construction",
            "type":"Services"
        }
    ],
    "sg:phone":"+1 337 845 5003",
    "sg:postcode":"70517",
    "sg:province":"LA",
    "sg:tags":[
        "trenching",
        "contractor"
    ],
    "wof:name":"Trenching",
    "wof:placetype":"venue"
},
  "geometry": {"coordinates":[-91.84044900000001,30.251762],"type":"Point"}
}