{
  "type": "Feature",
  "properties": {
    "iso:country":"US",
    "sg:address":"2700 Napoleon Ave",
    "sg:city":"New Orleans",
    "sg:classifiers":[
        {
            "category":"Health Services",
            "subcategory":"Hospital",
            "type":"Services"
        }
    ],
    "sg:phone":"+1 504 894 2273",
    "sg:postcode":"70115",
    "sg:province":"LA",
    "sg:tags":[
        "clinic",
        "specialty"
    ],
    "wof:name":"Lifecare Hosp New Orleans LLC",
    "wof:placetype":"venue"
},
  "geometry": {"coordinates":[-90.10334899999999,29.938081],"type":"Point"}
}