{
  "type": "Feature",
  "properties": {
    "iso:country":"US",
    "sg:address":"1919 Sugar Oaks Rd",
    "sg:city":"New Iberia",
    "sg:classifiers":[
        {
            "category":"Retail",
            "subcategory":"Animal Services",
            "type":"Services"
        }
    ],
    "sg:phone":"+1 337 560 0003",
    "sg:postcode":"70563",
    "sg:province":"LA",
    "sg:tags":[
        "pet",
        "grooming",
        "washing"
    ],
    "wof:name":"Acadiana Pet Spa",
    "wof:placetype":"venue"
},
  "geometry": {"coordinates":[-91.774001,30.015432],"type":"Point"}
}