{
  "type": "Feature",
  "properties": {
    "addr:full":"135 Yuroni Trl Marksville LA 71351",
    "addr:housenumber":"135",
    "addr:postcode":"71351",
    "addr:street":"Yuroni Trl",
    "iso:country":"US",
    "sg:address":"135 Yuroni Trl",
    "sg:city":"Marksville",
    "sg:classifiers":[
        {
            "category":"Organizations",
            "subcategory":"Non-profit Organization",
            "type":"Services"
        }
    ],
    "sg:phone":"+1 318 253 8372",
    "sg:postcode":"71351",
    "sg:province":"LA",
    "wof:name":"Tunica Biloxi",
    "wof:placetype":"venue"
},
  "geometry": {"coordinates":[-92.062438,31.109803],"type":"Point"}
}