{
  "type": "Feature",
  "properties": {
    "iso:country":"US",
    "sg:address":"4436 Veterans Memorial Blvd",
    "sg:city":"Metairie",
    "sg:classifiers":[
        {
            "category":"Cafe",
            "type":"Food & Drink"
        }
    ],
    "sg:menulink":"http://www.allmenus.com/la/metairie/155737-wow-cafe--wingery/menu/",
    "sg:phone":"+1 504 889 9693",
    "sg:postcode":"70006",
    "sg:province":"LA",
    "sg:tags":[
        "american"
    ],
    "wof:name":"Wow Cafe & Wingery",
    "wof:placetype":"venue"
},
  "geometry": {"coordinates":[-90.182441,30.004599],"type":"Point"}
}