{
  "type": "Feature",
  "properties": {
    "iso:country":"US",
    "sg:address":"1381 W Tunnel Blvd",
    "sg:city":"Houma",
    "sg:classifiers":[
        {
            "category":"Travel",
            "subcategory":"Hotels & Motels",
            "type":"Entertainment"
        }
    ],
    "sg:phone":"+1 985 868 0500",
    "sg:postcode":"70360",
    "sg:province":"LA",
    "wof:name":"Plantation Inn",
    "wof:placetype":"venue"
},
  "geometry": {"coordinates":[-90.746634,29.602525],"type":"Point"}
}