{
  "type": "Feature",
  "properties": {
    "addr:full":"56388 Hwy 445 Husser LA 70442",
    "addr:housenumber":"56388",
    "addr:postcode":"70442",
    "addr:street":"Hwy 445 Husser",
    "iso:country":"US",
    "sg:address":"56388 Hwy 445",
    "sg:city":"Husser",
    "sg:classifiers":[
        {
            "category":"Food & Beverages",
            "subcategory":"Groceries & Convenience Stores",
            "type":"Retail Goods"
        }
    ],
    "sg:phone":"+1 985 747 0355",
    "sg:postcode":"70442",
    "sg:province":"LA",
    "sg:tags":[
        "grocer"
    ],
    "wof:name":"Family Grocery & Deli",
    "wof:placetype":"venue"
},
  "geometry": {"coordinates":[-90.352408,30.693115],"type":"Point"}
}