{
  "type": "Feature",
  "properties": {
    "addr:full":"3713 Kings Dr Chalmette LA 70043",
    "addr:housenumber":"3713",
    "addr:postcode":"70043",
    "addr:street":"Kings Dr Chalmette",
    "iso:country":"US",
    "sg:address":"3713 Kings Dr",
    "sg:city":"Chalmette",
    "sg:classifiers":[
        {
            "category":"Building & Trades",
            "subcategory":"Construction",
            "type":"Services"
        }
    ],
    "sg:phone":"+1 504 277 0047",
    "sg:postcode":"70043",
    "sg:province":"LA",
    "sg:tags":[
        "general",
        "contractor"
    ],
    "wof:name":"Chalmette Roofing Co",
    "wof:placetype":"venue"
},
  "geometry": {"coordinates":[-89.971535,29.957753],"type":"Point"}
}