{
  "type": "Feature",
  "properties": {
    "iso:country":"US",
    "sg:address":"263 3rd St",
    "sg:city":"Baton Rouge",
    "sg:classifiers":[
        {
            "category":"Professional",
            "subcategory":"Lawyer & Legal Services",
            "type":"Services"
        }
    ],
    "sg:phone":"+1 225 344 7972",
    "sg:postcode":"70801",
    "sg:province":"LA",
    "sg:tags":[
        "attorney"
    ],
    "wof:name":"Burden & Scott",
    "wof:placetype":"venue"
},
  "geometry": {"coordinates":[-91.188288,30.448635],"type":"Point"}
}