{
  "type": "Feature",
  "properties": {
    "iso:country":"US",
    "sg:address":"2612 W Thomas St",
    "sg:city":"Hammond",
    "sg:classifiers":[
        {
            "category":"Wholesale",
            "subcategory":"Electrical",
            "type":"Manufacturing & Wholesale Goods"
        }
    ],
    "sg:phone":"+1 985 345 0661",
    "sg:postcode":"70401",
    "sg:province":"LA",
    "sg:tags":[
        "alarm",
        "burglar",
        "system"
    ],
    "wof:name":"Marty's Lock & Security Co",
    "wof:placetype":"venue"
},
  "geometry": {"coordinates":[-90.489952,30.501308],"type":"Point"}
}