{
  "type": "Feature",
  "properties": {
    "iso:country":"US",
    "sg:address":"7950 Youree Dr",
    "sg:city":"Shreveport",
    "sg:classifiers":[
        {
            "category":"Food & Beverages",
            "subcategory":"Groceries & Convenience Stores",
            "type":"Retail Goods"
        }
    ],
    "sg:phone":"+1 318 798 7990",
    "sg:postcode":"71105",
    "sg:province":"LA",
    "wof:name":"Interstate No 75 Store",
    "wof:placetype":"venue"
},
  "geometry": {"coordinates":[-93.713267,32.434016],"type":"Point"}
}