{
  "type": "Feature",
  "properties": {
    "iso:country":"US",
    "sg:address":"7064 Siegen Ln",
    "sg:city":"Baton Rouge",
    "sg:classifiers":[
        {
            "category":"Personal",
            "subcategory":"Beauty Salon",
            "type":"Services"
        }
    ],
    "sg:phone":"+1 225 293 3535",
    "sg:postcode":"70809",
    "sg:province":"LA",
    "sg:tags":[
        "manicuring"
    ],
    "wof:name":"Exotic Nails",
    "wof:placetype":"venue"
},
  "geometry": {"coordinates":[-91.063982,30.385901],"type":"Point"}
}