{
  "type": "Feature",
  "properties": {
    "iso:country":"US",
    "sg:address":"6041 Bullard Ave",
    "sg:city":"New Orleans",
    "sg:classifiers":[
        {
            "category":"Autos & Motor Vehicles",
            "subcategory":"Fuel & Gas Station",
            "type":"Retail Goods"
        }
    ],
    "sg:phone":"+1 504 246 8244",
    "sg:postcode":"70128",
    "sg:province":"LA",
    "sg:tags":[
        "oil"
    ],
    "wof:name":"Bullard Shell",
    "wof:placetype":"venue"
},
  "geometry": {"coordinates":[-89.959326,30.044282],"type":"Point"}
}