{
  "type": "Feature",
  "properties": {
    "iso:country":"US",
    "sg:address":"112 Ridgeway St",
    "sg:city":"Thibodaux",
    "sg:classifiers":[
        {
            "category":"Professional",
            "subcategory":"Business Services",
            "type":"Services"
        }
    ],
    "sg:phone":"+1 985 447 1405",
    "sg:postcode":"70301",
    "sg:province":"LA",
    "wof:name":"T Bail Bond Service",
    "wof:placetype":"venue"
},
  "geometry": {"coordinates":[-90.837062,29.766315],"type":"Point"}
}