{
  "type": "Feature",
  "properties": {
    "iso:country":"US",
    "sg:address":"3529 Myrtle Grove Dr",
    "sg:city":"Baton Rouge",
    "sg:classifiers":[
        {
            "category":"Wholesale",
            "subcategory":"Furniture",
            "type":"Manufacturing & Wholesale Goods"
        }
    ],
    "sg:phone":"+1 225 819 2959",
    "sg:postcode":"70810",
    "sg:province":"LA",
    "wof:name":"Dependable Installation Svc",
    "wof:placetype":"venue"
},
  "geometry": {"coordinates":[-91.097943,30.390012],"type":"Point"}
}