{
  "type": "Feature",
  "properties": {
    "addr:full":"1008 Henderson Levee Rd Breaux Bridge LA 70517",
    "addr:housenumber":"1008",
    "addr:postcode":"70517",
    "addr:street":"Henderson Levee Rd;Bridge",
    "iso:country":"US",
    "sg:address":"1008 Henderson Levee Rd",
    "sg:city":"Breaux Bridge",
    "sg:classifiers":[
        {
            "category":"Restaurant",
            "type":"Food & Drink"
        }
    ],
    "sg:menulink":"http://www.allmenus.com/la/henderson/224737-pats-fishermans-wharf/menu/",
    "sg:phone":"+1 337 228 7512",
    "sg:postcode":"70517",
    "sg:province":"LA",
    "sg:tags":[
        "seafood",
        "american"
    ],
    "wof:name":"Pat's Fisherman's Wharf",
    "wof:placetype":"venue"
},
  "geometry": {"coordinates":[-91.711275,30.241838],"type":"Point"}
}