{
  "type": "Feature",
  "properties": {
    "addr:full":"303 Hickory St Thibodaux LA 70301",
    "addr:housenumber":"303",
    "addr:postcode":"70301",
    "addr:street":"Hickory St",
    "iso:country":"US",
    "sg:address":"303 Hickory St",
    "sg:city":"Thibodaux",
    "sg:classifiers":[
        {
            "category":"Government",
            "subcategory":"Office",
            "type":"Public Place"
        }
    ],
    "sg:phone":"+1 985 447 0851",
    "sg:postcode":"70301",
    "sg:province":"LA",
    "sg:tags":[
        "state",
        "program",
        "health"
    ],
    "wof:name":"Alcohol & Drug Abuse",
    "wof:placetype":"venue"
},
  "geometry": {"coordinates":[-90.833111,29.795011],"type":"Point"}
}