{
  "type": "Feature",
  "properties": {
    "addr:full":"1149 State Rte 495 Cloutierville LA 71416",
    "addr:housenumber":"1149",
    "addr:postcode":"71416",
    "addr:street":"State Rte 495 Cloutierville",
    "iso:country":"US",
    "sg:address":"1149 State Rte 495",
    "sg:city":"Cloutierville",
    "sg:classifiers":[
        {
            "category":"Organizations",
            "subcategory":"Religious Organization",
            "type":"Services"
        }
    ],
    "sg:phone":"+1 318 379 9653",
    "sg:postcode":"71416",
    "sg:province":"LA",
    "sg:tags":[
        "church"
    ],
    "wof:name":"St Davis Missionary Baptist",
    "wof:placetype":"venue"
},
  "geometry": {"coordinates":[-92.89093099999999,31.552],"type":"Point"}
}