{
  "type": "Feature",
  "properties": {
    "iso:country":"US",
    "sg:address":"831 Chartres St",
    "sg:city":"New Orleans",
    "sg:classifiers":[
        {
            "category":"Shopping",
            "subcategory":"Clothing, Apparel, & Fashions",
            "type":"Retail Goods"
        }
    ],
    "sg:phone":"+1 504 454 6444",
    "sg:postcode":"70116",
    "sg:province":"LA",
    "sg:tags":[
        "theatrical",
        "costume"
    ],
    "wof:name":"Mardi Gras Ctr",
    "wof:placetype":"venue"
},
  "geometry": {"coordinates":[-90.06292999999999,29.958435],"type":"Point"}
}