{
  "type": "Feature",
  "properties": {
    "addr:full":"748 Chevelle Dr Baton Rouge LA 70806",
    "addr:housenumber":"748",
    "addr:postcode":"70806",
    "addr:street":"Chevelle Dr",
    "iso:country":"US",
    "sg:address":"748 Chevelle Dr",
    "sg:city":"Baton Rouge",
    "sg:classifiers":[
        {
            "category":"Health Services",
            "subcategory":"Doctor",
            "type":"Services"
        }
    ],
    "sg:phone":"+1 225 927 5095",
    "sg:postcode":"70806",
    "sg:province":"LA",
    "sg:tags":[
        "dentist"
    ],
    "wof:name":"E D Bateman PC",
    "wof:placetype":"venue"
},
  "geometry": {"coordinates":[-91.098676,30.443648],"type":"Point"}
}