{
  "type": "Feature",
  "properties": {
    "iso:country":"US",
    "sg:address":"594 Jefferson Dr",
    "sg:city":"Lake Charles",
    "sg:classifiers":[
        {
            "category":"Retail",
            "subcategory":"Car Wash",
            "type":"Services"
        }
    ],
    "sg:phone":"+1 337 310 1648",
    "sg:postcode":"70605",
    "sg:province":"LA",
    "sg:tags":[
        "polishing",
        "washing"
    ],
    "wof:name":"M C's Detailing Specialists",
    "wof:placetype":"venue"
},
  "geometry": {"coordinates":[-93.217501,30.165389],"type":"Point"}
}