{
  "type": "Feature",
  "properties": {
    "iso:country":"US",
    "sg:address":"5110 Jefferson Hwy",
    "sg:city":"New Orleans",
    "sg:classifiers":[
        {
            "category":"Retail",
            "subcategory":"Portrait Studio",
            "type":"Services"
        }
    ],
    "sg:phone":"+1 504 818 2429",
    "sg:postcode":"70123",
    "sg:province":"LA",
    "sg:tags":[
        "photo"
    ],
    "wof:name":"PCA International LLC",
    "wof:placetype":"venue"
},
  "geometry": {"coordinates":[-90.17904900000001,29.953254],"type":"Point"}
}