{
  "type": "Feature",
  "properties": {
    "iso:country":"US",
    "sg:address":"6001 Ozenne Rd",
    "sg:city":"New Iberia",
    "sg:classifiers":[
        {
            "category":"Building & Trades",
            "subcategory":"Electrical",
            "type":"Services"
        }
    ],
    "sg:phone":"+1 337 365 3360",
    "sg:postcode":"70560",
    "sg:province":"LA",
    "sg:tags":[
        "electric",
        "contractor"
    ],
    "wof:name":"Macon Power & Controls",
    "wof:placetype":"venue"
},
  "geometry": {"coordinates":[-91.766497,29.937187],"type":"Point"}
}