{
  "type": "Feature",
  "properties": {
    "addr:full":"903 Washington St Franklinton LA 70438",
    "addr:housenumber":"903",
    "addr:postcode":"70438",
    "addr:street":"Washington St",
    "iso:country":"US",
    "sg:address":"903 Washington St",
    "sg:city":"Franklinton",
    "sg:classifiers":[
        {
            "category":"Food & Beverages",
            "subcategory":"Bakery",
            "type":"Retail Goods"
        }
    ],
    "sg:phone":"+1 985 795 1523",
    "sg:postcode":"70438",
    "sg:province":"LA",
    "sg:tags":[
        "doughnut"
    ],
    "wof:name":"Mom & Pops Donut Deli",
    "wof:placetype":"venue"
},
  "geometry": {"coordinates":[-90.15526,30.84487],"type":"Point"}
}