{
  "type": "Feature",
  "properties": {
    "iso:country":"US",
    "sg:address":"1113 E Airline Hwy",
    "sg:city":"La Place",
    "sg:classifiers":[
        {
            "category":"Restaurant",
            "type":"Food & Drink"
        }
    ],
    "sg:phone":"+1 985 651 7745",
    "sg:postcode":"70068",
    "sg:province":"LA",
    "wof:name":"Frisco Deli",
    "wof:placetype":"venue"
},
  "geometry": {"coordinates":[-90.458714,30.052421],"type":"Point"}
}