{
  "type": "Feature",
  "properties": {
    "addr:full":"10100 Chef Menteur Hwy New Orleans LA 70127",
    "addr:housenumber":"10100",
    "addr:postcode":"70127",
    "addr:street":"Chef Menteur Hwy",
    "iso:country":"US",
    "sg:address":"10100 Chef Menteur Hwy",
    "sg:city":"New Orleans",
    "sg:classifiers":[
        {
            "category":"Retail",
            "subcategory":"Auto Repair",
            "type":"Services"
        }
    ],
    "sg:phone":"+1 504 241 6350",
    "sg:postcode":"70127",
    "sg:province":"LA",
    "sg:tags":[
        "repairing",
        "automobile",
        "glass"
    ],
    "sg:website":"www.safelite.com",
    "wof:name":"Star Safelite Auto Glass",
    "wof:placetype":"venue"
},
  "geometry": {"coordinates":[-89.967173,30.018506],"type":"Point"}
}