{
  "type": "Feature",
  "properties": {
    "addr:full":"30304 Hwy 21 Angie LA 70426",
    "addr:housenumber":"30304",
    "addr:postcode":"70426",
    "addr:street":"Hwy 21 Angie",
    "iso:country":"US",
    "sg:address":"30304 Hwy 21",
    "sg:city":"Angie",
    "sg:classifiers":[
        {
            "category":"Health Services",
            "subcategory":"Doctor",
            "type":"Services"
        }
    ],
    "sg:phone":"+1 985 986 0016",
    "sg:postcode":"70426",
    "sg:province":"LA",
    "sg:tags":[
        "clinic"
    ],
    "wof:name":"Angie Medical Clinic",
    "wof:placetype":"venue"
},
  "geometry": {"coordinates":[-89.811289,30.962259],"type":"Point"}
}