{
  "type": "Feature",
  "properties": {
    "iso:country":"US",
    "sg:address":"3500 Edenborn Ave",
    "sg:city":"Metairie",
    "sg:classifiers":[
        {
            "category":"Building & Trades",
            "subcategory":"Construction",
            "type":"Services"
        }
    ],
    "sg:phone":"+1 504 885 5064",
    "sg:postcode":"70002",
    "sg:province":"LA",
    "sg:tags":[
        "resurfacing",
        "laying",
        "refinishing",
        "floor"
    ],
    "wof:name":"Bunch's Floor Care",
    "wof:placetype":"venue"
},
  "geometry": {"coordinates":[-90.16176,30.014386],"type":"Point"}
}