{
  "type": "Feature",
  "properties": {
    "iso:country":"US",
    "sg:address":"9940 Airline Hwy",
    "sg:city":"Baton Rouge",
    "sg:classifiers":[
        {
            "category":"Travel",
            "subcategory":"Hotels & Motels",
            "type":"Entertainment"
        }
    ],
    "sg:phone":"+1 225 924 7021",
    "sg:postcode":"70816",
    "sg:province":"LA",
    "wof:name":"Holiday Inn Baton Rouge-South",
    "wof:placetype":"venue"
},
  "geometry": {"coordinates":[-91.076308,30.425632],"type":"Point"}
}