{
  "type": "Feature",
  "properties": {
    "iso:country":"US",
    "sg:address":"5355 Government St",
    "sg:city":"Baton Rouge",
    "sg:classifiers":[
        {
            "category":"Food & Beverages",
            "subcategory":"Groceries & Convenience Stores",
            "type":"Retail Goods"
        }
    ],
    "sg:phone":"+1 225 926 2075",
    "sg:postcode":"70806",
    "sg:province":"LA",
    "sg:tags":[
        "grocer"
    ],
    "wof:name":"Winn-Dixie",
    "wof:placetype":"venue"
},
  "geometry": {"coordinates":[-91.13488099999999,30.444664],"type":"Point"}
}