{
  "type": "Feature",
  "properties": {
    "iso:country":"US",
    "sg:address":"1029 D C Crain Rd",
    "sg:city":"Winnsboro",
    "sg:classifiers":[
        {
            "category":"Personal",
            "subcategory":"Beauty Salon",
            "type":"Services"
        }
    ],
    "sg:phone":"+1 318 723 5512",
    "sg:postcode":"71295",
    "sg:province":"LA",
    "sg:tags":[
        "shop"
    ],
    "wof:name":"Verna's Beauty Shop",
    "wof:placetype":"venue"
},
  "geometry": {"coordinates":[-91.767213,32.046863],"type":"Point"}
}