{
  "type": "Feature",
  "properties": {
    "addr:full":"1720 Manhattan Blvd Harvey LA 70058",
    "addr:housenumber":"1720",
    "addr:postcode":"70058",
    "addr:street":"Manhattan Blvd",
    "iso:country":"US",
    "sg:address":"1720 Manhattan Blvd",
    "sg:city":"Harvey",
    "sg:classifiers":[
        {
            "category":"Autos & Motor Vehicles",
            "subcategory":"Auto Supplies",
            "type":"Retail Goods"
        }
    ],
    "sg:phone":"+1 504 366 7805",
    "sg:postcode":"70058",
    "sg:province":"LA",
    "sg:tags":[
        "repair",
        "automobile",
        "equipment",
        "air conditioning"
    ],
    "wof:name":"AAA Auto Air & Accessories Inc",
    "wof:placetype":"venue"
},
  "geometry": {"coordinates":[-90.057503,29.8895],"type":"Point"}
}