{
  "type": "Feature",
  "properties": {
    "iso:country":"US",
    "sg:address":"1 E 2nd St",
    "sg:city":"Lafayette",
    "sg:classifiers":[
        {
            "category":"Social Services",
            "subcategory":"Child Care",
            "type":"Services"
        }
    ],
    "sg:phone":"+1 337 269 1187",
    "sg:postcode":"70501",
    "sg:province":"LA",
    "wof:name":"Hug-A-Bunch Day Care Ctr",
    "wof:placetype":"venue"
},
  "geometry": {"coordinates":[-92.01549799999999,30.229484],"type":"Point"}
}