{
  "type": "Feature",
  "properties": {
    "addr:full":"7125 Scenic Hwy Baton Rouge LA 70807",
    "addr:housenumber":"7125",
    "addr:postcode":"70807",
    "addr:street":"Scenic Hwy",
    "iso:country":"US",
    "sg:address":"7125 Scenic Hwy",
    "sg:city":"Baton Rouge",
    "sg:classifiers":[
        {
            "category":"Retail",
            "subcategory":"Auto Repair",
            "type":"Services"
        }
    ],
    "sg:phone":"+1 225 357 5775",
    "sg:postcode":"70807",
    "sg:province":"LA",
    "sg:tags":[
        "repairing",
        "tire"
    ],
    "wof:name":"Triple B Tire Repair & Detail",
    "wof:placetype":"venue"
},
  "geometry": {"coordinates":[-91.175468,30.514128],"type":"Point"}
}