{
  "type": "Feature",
  "properties": {
    "addr:full":"1702 Laurel St Baton Rouge LA 70802",
    "addr:housenumber":"1702",
    "addr:postcode":"70802",
    "addr:street":"Laurel St",
    "iso:country":"US",
    "sg:address":"1702 Laurel St",
    "sg:city":"Baton Rouge",
    "sg:classifiers":[
        {
            "category":"Professional",
            "subcategory":"Management & Consulting",
            "type":"Services"
        }
    ],
    "sg:phone":"+1 225 346 8585",
    "sg:postcode":"70802",
    "sg:province":"LA",
    "sg:tags":[
        "consultant",
        "educational"
    ],
    "wof:name":"SCI Tech Projects",
    "wof:placetype":"venue"
},
  "geometry": {"coordinates":[-91.16997000000001,30.450836],"type":"Point"}
}