{
  "type": "Feature",
  "properties": {
    "addr:full":"117 E Arkansas Ave Vivian LA 71082",
    "addr:housenumber":"117",
    "addr:postcode":"71082",
    "addr:street":"E Arkansas Ave Vivian",
    "iso:country":"US",
    "sg:address":"117 E Arkansas Ave",
    "sg:city":"Vivian",
    "sg:classifiers":[
        {
            "category":"Retail",
            "subcategory":"Auto Repair",
            "type":"Services"
        }
    ],
    "sg:phone":"+1 318 375 5823",
    "sg:postcode":"71082",
    "sg:province":"LA",
    "sg:tags":[
        "automobile",
        "lubrication"
    ],
    "wof:name":"Texaco Xpress Lube",
    "wof:placetype":"venue"
},
  "geometry": {"coordinates":[-93.985877,32.871035],"type":"Point"}
}