{
  "type": "Feature",
  "properties": {
    "iso:country":"US",
    "sg:address":"102 Fairfax St",
    "sg:city":"Lafayette",
    "sg:classifiers":[
        {
            "category":"Personal",
            "subcategory":"Beauty Salon",
            "type":"Services"
        }
    ],
    "sg:phone":"+1 337 984 7467",
    "sg:postcode":"70506",
    "sg:province":"LA",
    "wof:name":"Mary Adams Hair Salon",
    "wof:placetype":"venue"
},
  "geometry": {"coordinates":[-92.098984,30.205729],"type":"Point"}
}