{
  "type": "Feature",
  "properties": {
    "iso:country":"US",
    "sg:address":"3742 S Macarthur Dr",
    "sg:city":"Alexandria",
    "sg:classifiers":[
        {
            "category":"Banks & Credit Unions",
            "subcategory":"Bank",
            "type":"Services"
        }
    ],
    "sg:phone":"+1 318 767 1628",
    "sg:postcode":"71302",
    "sg:province":"LA",
    "sg:tags":[
        "loan"
    ],
    "wof:name":"Excel Finance Co",
    "wof:placetype":"venue"
},
  "geometry": {"coordinates":[-92.45048300000001,31.262415],"type":"Point"}
}