{
  "type": "Feature",
  "properties": {
    "iso:country":"US",
    "sg:address":"11175 Florida Blvd",
    "sg:city":"Baton Rouge",
    "sg:classifiers":[
        {
            "category":"Insurance",
            "subcategory":"Insurance Agent",
            "type":"Services"
        }
    ],
    "sg:phone":"+1 225 272 2284",
    "sg:postcode":"70815",
    "sg:province":"LA",
    "wof:name":"State Farm Insurance",
    "wof:placetype":"venue"
},
  "geometry": {"coordinates":[-91.06246400000001,30.458232],"type":"Point"}
}