{
  "type": "Feature",
  "properties": {
    "addr:full":"16159 State Bank Dr Prairieville LA 70769",
    "addr:housenumber":"16159",
    "addr:postcode":"70769",
    "addr:street":"State Bank Dr Prairieville",
    "iso:country":"US",
    "sg:address":"16159 State Bank Dr",
    "sg:city":"Prairieville",
    "sg:classifiers":[
        {
            "category":"Professional",
            "subcategory":"Lawyer & Legal Services",
            "type":"Services"
        }
    ],
    "sg:phone":"+1 225 673 2889",
    "sg:postcode":"70769",
    "sg:province":"LA",
    "sg:tags":[
        "attorney"
    ],
    "wof:name":"Kimball Law Office",
    "wof:placetype":"venue"
},
  "geometry": {"coordinates":[-90.973364,30.302305],"type":"Point"}
}