{
  "type": "Feature",
  "properties": {
    "addr:full":"30 E Airline Hwy Kenner LA 70062",
    "addr:housenumber":"30",
    "addr:postcode":"70062",
    "addr:street":"E Airline Hwy",
    "iso:country":"US",
    "sg:address":"30 E Airline Hwy",
    "sg:city":"Kenner",
    "sg:classifiers":[
        {
            "category":"Freight",
            "type":"Transportation"
        }
    ],
    "sg:phone":"+1 504 712 3472",
    "sg:postcode":"70062",
    "sg:province":"LA",
    "sg:tags":[
        "warehouse",
        "merchandise"
    ],
    "wof:name":"Cross Road Ctr",
    "wof:placetype":"venue"
},
  "geometry": {"coordinates":[-90.275148,29.980766],"type":"Point"}
}