{
  "type": "Feature",
  "properties": {
    "addr:full":"18860 Wildlife Way Dr Baton Rouge LA 70817",
    "addr:housenumber":"18860",
    "addr:postcode":"70817",
    "addr:street":"Wildlife Way Dr",
    "iso:country":"US",
    "sg:address":"18860 Wildlife Way Dr",
    "sg:city":"Baton Rouge",
    "sg:classifiers":[
        {
            "category":"Professional",
            "subcategory":"Management & Consulting",
            "type":"Services"
        }
    ],
    "sg:phone":"+1 225 751 3300",
    "sg:postcode":"70817",
    "sg:province":"LA",
    "sg:tags":[
        "party",
        "planning"
    ],
    "wof:name":"Carnival Time LLC",
    "wof:placetype":"venue"
},
  "geometry": {"coordinates":[-90.977907,30.394344],"type":"Point"}
}