{
  "type": "Feature",
  "properties": {
    "iso:country":"US",
    "sg:address":"2237 S Acadian Throughway",
    "sg:city":"Baton Rouge",
    "sg:classifiers":[
        {
            "category":"Insurance",
            "subcategory":"Insurance Agent",
            "type":"Services"
        }
    ],
    "sg:phone":"+1 225 709 6256",
    "sg:postcode":"70808",
    "sg:province":"LA",
    "wof:name":"Spera Co",
    "wof:placetype":"venue"
},
  "geometry": {"coordinates":[-91.150578,30.425756],"type":"Point"}
}