{
  "type": "Feature",
  "properties": {
    "addr:full":"401 Carrollton Ave Metairie LA 70005",
    "addr:housenumber":"401",
    "addr:postcode":"70005",
    "addr:street":"Carrollton Ave",
    "iso:country":"US",
    "sg:address":"401 Carrollton Ave",
    "sg:city":"Metairie",
    "sg:classifiers":[
        {
            "category":"Building & Trades",
            "subcategory":"Construction",
            "type":"Services"
        }
    ],
    "sg:phone":"+1 504 835 0626",
    "sg:postcode":"70005",
    "sg:province":"LA",
    "sg:tags":[
        "house"
    ],
    "wof:name":"Stars and Bars Cnstr Logo I",
    "wof:placetype":"venue"
},
  "geometry": {"coordinates":[-90.12662400000001,29.989241],"type":"Point"}
}