{
  "type": "Feature",
  "properties": {
    "iso:country":"US",
    "sg:address":"220 W Main St",
    "sg:city":"Lafayette",
    "sg:classifiers":[
        {
            "category":"Government",
            "subcategory":"Police Station",
            "type":"Public Place"
        }
    ],
    "sg:phone":"+1 337 231 6346",
    "sg:postcode":"70501",
    "sg:province":"LA",
    "sg:tags":[
        "sheriff"
    ],
    "wof:name":"Lafayette Parish Sheriff Dept",
    "wof:placetype":"venue"
},
  "geometry": {"coordinates":[-92.020618,30.222669],"type":"Point"}
}