{
  "type": "Feature",
  "properties": {
    "iso:country":"US",
    "sg:address":"10215 Lathers Ln",
    "sg:city":"Slaughter",
    "sg:classifiers":[
        {
            "category":"Manufacturing",
            "subcategory":"Wood Products",
            "type":"Manufacturing & Wholesale Goods"
        }
    ],
    "sg:phone":"+1 225 683 3972",
    "sg:postcode":"70777",
    "sg:province":"LA",
    "sg:tags":[
        "pallet",
        "skid"
    ],
    "wof:name":"B & M Pallets Inc",
    "wof:placetype":"venue"
},
  "geometry": {"coordinates":[-91.003742,30.799484],"type":"Point"}
}