{
  "type": "Feature",
  "properties": {
    "iso:country":"US",
    "sg:address":"8731 Greenwell Springs Rd",
    "sg:city":"Baton Rouge",
    "sg:classifiers":[
        {
            "category":"Freight",
            "type":"Transportation"
        }
    ],
    "sg:phone":"+1 225 925 2680",
    "sg:postcode":"70814",
    "sg:province":"LA",
    "sg:tags":[
        "warehouse",
        "merchandise"
    ],
    "wof:name":"D & G Warehousing & Logistics",
    "wof:placetype":"venue"
},
  "geometry": {"coordinates":[-91.095271,30.482018],"type":"Point"}
}