{
  "type": "Feature",
  "properties": {
    "addr:full":"54696 Hwy 16 Bogalusa LA 70427",
    "addr:housenumber":"54696",
    "addr:postcode":"70427",
    "addr:street":"Hwy 16 Bogalusa",
    "iso:country":"US",
    "sg:address":"54696 Hwy 16",
    "sg:city":"Bogalusa",
    "sg:classifiers":[
        {
            "category":"Freight",
            "type":"Transportation"
        }
    ],
    "sg:phone":"+1 985 732 0125",
    "sg:postcode":"70427",
    "sg:province":"LA",
    "sg:tags":[
        "operator",
        "local",
        "trucking"
    ],
    "wof:name":"Litl Heart Trucking",
    "wof:placetype":"venue"
},
  "geometry": {"coordinates":[-89.981228,30.667551],"type":"Point"}
}