{
  "type": "Feature",
  "properties": {
    "addr:full":"17212 Airline Hwy Prairieville LA 70769",
    "addr:housenumber":"17212",
    "addr:postcode":"70769",
    "addr:street":"Airline Hwy Prairieville",
    "iso:country":"US",
    "sg:address":"17212 Airline Hwy",
    "sg:city":"Prairieville",
    "sg:classifiers":[
        {
            "category":"Retail",
            "subcategory":"Auto Repair",
            "type":"Services"
        }
    ],
    "sg:phone":"+1 225 673 5442",
    "sg:postcode":"70769",
    "sg:province":"LA",
    "sg:tags":[
        "repairing",
        "automobile"
    ],
    "sg:website":"www.checkengineautomotive.com",
    "wof:name":"Check Engine Automotive Svc",
    "wof:placetype":"venue"
},
  "geometry": {"coordinates":[-90.98293700000001,30.328959],"type":"Point"}
}