{
  "type": "Feature",
  "properties": {
    "iso:country":"US",
    "sg:address":"1818 Veterans Memorial Dr",
    "sg:city":"Abbeville",
    "sg:classifiers":[
        {
            "category":"Shopping",
            "subcategory":"Clothing, Apparel, & Fashions",
            "type":"Retail Goods"
        }
    ],
    "sg:phone":"+1 337 893 9413",
    "sg:postcode":"70510",
    "sg:province":"LA",
    "sg:tags":[
        "alteration"
    ],
    "wof:name":"ANH Alterations",
    "wof:placetype":"venue"
},
  "geometry": {"coordinates":[-92.149131,29.985052],"type":"Point"}
}