{
  "type": "Feature",
  "properties": {
    "iso:country":"US",
    "sg:address":"104 Park Ave",
    "sg:city":"Abbeville",
    "sg:classifiers":[
        {
            "category":"Airport",
            "type":"Transportation"
        }
    ],
    "sg:phone":"+1 337 892 0501",
    "sg:postcode":"70510",
    "sg:province":"LA",
    "sg:tags":[
        "aircraft",
        "maintenance"
    ],
    "wof:name":"Avtech",
    "wof:placetype":"venue"
},
  "geometry": {"coordinates":[-92.14138,29.976692],"type":"Point"}
}