{
  "type": "Feature",
  "properties": {
    "iso:country":"US",
    "sg:address":"1106 Saint Peter St",
    "sg:city":"Mamou",
    "sg:classifiers":[
        {
            "category":"Building & Trades",
            "subcategory":"Construction",
            "type":"Services"
        }
    ],
    "sg:phone":"+1 337 468 2832",
    "sg:postcode":"70544",
    "sg:province":"LA",
    "sg:tags":[
        "nonresidential"
    ],
    "wof:name":"Fontenot Richard J Gen Contr",
    "wof:placetype":"venue"
},
  "geometry": {"coordinates":[-91.67194600000001,29.890842],"type":"Point"}
}