{
  "type": "Feature",
  "properties": {
    "addr:full":"41416 Brown Rd Ponchatoula LA 70454",
    "addr:housenumber":"41416",
    "addr:postcode":"70454",
    "addr:street":"Brown Rd",
    "iso:country":"US",
    "sg:address":"41416 Brown Rd",
    "sg:city":"Ponchatoula",
    "sg:classifiers":[
        {
            "category":"Professional",
            "subcategory":"Business Services",
            "type":"Services"
        },
        {
            "category":"Manufacturing",
            "subcategory":"Lumber",
            "type":"Manufacturing & Wholesale Goods"
        }
    ],
    "sg:phone":"+1 985 386 9729",
    "sg:postcode":"70454",
    "sg:province":"LA",
    "sg:tags":[
        "sawmill"
    ],
    "wof:name":"Mitchell Saw Mill",
    "wof:placetype":"venue"
},
  "geometry": {"coordinates":[-90.380066,30.457545],"type":"Point"}
}