{
  "type": "Feature",
  "properties": {
    "iso:country":"US",
    "sg:address":"1620 S Hopkins St",
    "sg:city":"New Iberia",
    "sg:classifiers":[
        {
            "category":"Shopping",
            "subcategory":"Jewelry",
            "type":"Retail Goods"
        }
    ],
    "sg:phone":"+1 337 369 9345",
    "sg:postcode":"70560",
    "sg:province":"LA",
    "sg:tags":[
        "jeweler"
    ],
    "wof:name":"Ackal's Too",
    "wof:placetype":"venue"
},
  "geometry": {"coordinates":[-91.841904,30.001699],"type":"Point"}
}