{
  "type": "Feature",
  "properties": {
    "iso:country":"US",
    "sg:address":"11030 Coursey Blvd",
    "sg:city":"Baton Rouge",
    "sg:classifiers":[
        {
            "category":"Wholesale",
            "subcategory":"Hardware",
            "type":"Manufacturing & Wholesale Goods"
        }
    ],
    "sg:phone":"+1 225 295 7019",
    "sg:postcode":"70816",
    "sg:province":"LA",
    "sg:tags":[
        "air",
        "parts",
        "conditioning",
        "supply"
    ],
    "sg:website":"www.johnstonesupply.com",
    "wof:name":"Johnstone Supply",
    "wof:placetype":"venue"
},
  "geometry": {"coordinates":[-91.057918,30.41499],"type":"Point"}
}