{
  "type": "Feature",
  "properties": {
    "iso:country":"US",
    "sg:address":"716 Orleans Ave",
    "sg:city":"New Orleans",
    "sg:classifiers":[
        {
            "category":"Farming",
            "subcategory":"Farm",
            "type":"Manufacturing & Wholesale Goods"
        }
    ],
    "sg:phone":"+1 504 523 4146",
    "sg:postcode":"70116",
    "sg:province":"LA",
    "sg:tags":[
        "crop",
        "general"
    ],
    "wof:name":"Steve S Framing Shop",
    "wof:placetype":"venue"
},
  "geometry": {"coordinates":[-90.065196,29.958861],"type":"Point"}
}