{
  "type": "Feature",
  "properties": {
    "addr:full":"6020 W Cyrus Ave Baton Rouge LA 70805",
    "addr:housenumber":"6020",
    "addr:postcode":"70805",
    "addr:street":"W Cyrus Ave",
    "iso:country":"US",
    "sg:address":"6020 W Cyrus Ave",
    "sg:city":"Baton Rouge",
    "sg:classifiers":[
        {
            "category":"Building & Trades",
            "subcategory":"Construction",
            "type":"Services"
        }
    ],
    "sg:phone":"+1 225 357 3548",
    "sg:postcode":"70805",
    "sg:province":"LA",
    "sg:tags":[
        "hanging",
        "contractor"
    ],
    "wof:name":"Ozunas Painting Inc",
    "wof:placetype":"venue"
},
  "geometry": {"coordinates":[-91.130557,30.48934],"type":"Point"}
}