{
  "type": "Feature",
  "properties": {
    "iso:country":"US",
    "sg:address":"297 Mallet Rd",
    "sg:city":"Arnaudville",
    "sg:classifiers":[
        {
            "category":"Manufacturing",
            "subcategory":"Chemicals & Compounds",
            "type":"Manufacturing & Wholesale Goods"
        }
    ],
    "sg:phone":"+1 225 921 8040",
    "sg:postcode":"70512",
    "sg:province":"LA",
    "sg:tags":[
        "consulting",
        "testing",
        "method"
    ],
    "wof:name":"Chemsource LLC",
    "wof:placetype":"venue"
},
  "geometry": {"coordinates":[-91.922527,30.463943],"type":"Point"}
}