{
  "type": "Feature",
  "properties": {
    "addr:full":"102 W Division St Jennings LA 70546",
    "addr:housenumber":"102",
    "addr:postcode":"70546",
    "addr:street":"W Division St",
    "iso:country":"US",
    "sg:address":"102 W Division St",
    "sg:city":"Jennings",
    "sg:classifiers":[
        {
            "category":"Food & Beverages",
            "subcategory":"Liquor & Beverages",
            "type":"Retail Goods"
        }
    ],
    "sg:phone":"+1 337 824 8976",
    "sg:postcode":"70546",
    "sg:province":"LA",
    "wof:name":"Paw's Liquor",
    "wof:placetype":"venue"
},
  "geometry": {"coordinates":[-92.660499,30.220732],"type":"Point"}
}