{
  "type": "Feature",
  "properties": {
    "iso:country":"US",
    "sg:address":"235 Abercrombie Rd",
    "sg:city":"Eros",
    "sg:classifiers":[
        {
            "category":"Building & Trades",
            "subcategory":"Construction",
            "type":"Services"
        }
    ],
    "sg:phone":"+1 318 368 2144",
    "sg:postcode":"71238",
    "sg:province":"LA",
    "sg:tags":[
        "contractor"
    ],
    "wof:name":"GHC Builders",
    "wof:placetype":"venue"
},
  "geometry": {"coordinates":[-92.322197,32.451804],"type":"Point"}
}