{
  "type": "Feature",
  "properties": {
    "addr:full":"70180 Carmel Rd Mandeville LA 70471",
    "addr:housenumber":"70180",
    "addr:postcode":"70471",
    "addr:street":"Carmel Rd",
    "iso:country":"US",
    "sg:address":"70180 Carmel Rd",
    "sg:city":"Mandeville",
    "sg:classifiers":[
        {
            "category":"Building & Trades",
            "subcategory":"Construction",
            "type":"Services"
        }
    ],
    "sg:phone":"+1 985 867 8030",
    "sg:postcode":"70471",
    "sg:province":"LA",
    "sg:tags":[
        "handyman"
    ],
    "wof:name":"Honey Do Home Svc",
    "wof:placetype":"venue"
},
  "geometry": {"coordinates":[-90.021608,30.447822],"type":"Point"}
}