{
  "type": "Feature",
  "properties": {
    "iso:country":"US",
    "sg:address":"5236 Hearst St",
    "sg:city":"Metairie",
    "sg:classifiers":[
        {
            "category":"Professional",
            "subcategory":"Business Services",
            "type":"Services"
        }
    ],
    "sg:phone":"+1 504 885 7355",
    "sg:postcode":"70001",
    "sg:province":"LA",
    "wof:name":"Casbros Enterprises Inc",
    "wof:placetype":"venue"
},
  "geometry": {"coordinates":[-90.195373,29.99772],"type":"Point"}
}