{
  "type": "Feature",
  "properties": {
    "addr:full":"1821 Wedgwood Dr Harvey LA 70058",
    "addr:housenumber":"1821",
    "addr:postcode":"70058",
    "addr:street":"Wedgwood Dr",
    "iso:country":"US",
    "sg:address":"1821 Wedgwood Dr",
    "sg:city":"Harvey",
    "sg:classifiers":[
        {
            "category":"Building & Trades",
            "subcategory":"Landscaping Services",
            "type":"Services"
        }
    ],
    "sg:phone":"+1 504 340 9218",
    "sg:postcode":"70058",
    "sg:province":"LA",
    "sg:tags":[
        "landscape",
        "contractor"
    ],
    "wof:name":"Sun Tropic Landscapes",
    "wof:placetype":"venue"
},
  "geometry": {"coordinates":[-90.081031,29.875534],"type":"Point"}
}