{
  "type": "Feature",
  "properties": {
    "addr:full":"9100 Industrial Rd Shreveport LA 71129",
    "addr:housenumber":"9100",
    "addr:postcode":"71129",
    "addr:street":"Industrial Rd",
    "iso:country":"US",
    "sg:address":"9100 Industrial Rd",
    "sg:city":"Shreveport",
    "sg:classifiers":[
        {
            "category":"Autos & Motor Vehicles",
            "subcategory":"Automobile Sales",
            "type":"Retail Goods"
        }
    ],
    "sg:phone":"+1 318 687 2700",
    "sg:postcode":"71129",
    "sg:province":"LA",
    "sg:tags":[
        "equipment",
        "aircraft",
        "parts",
        "supply"
    ],
    "wof:name":"Mc Gill Aircraft Parts Inc",
    "wof:placetype":"venue"
},
  "geometry": {"coordinates":[-93.84795200000001,32.40211],"type":"Point"}
}