{
  "type": "Feature",
  "properties": {
    "iso:country":"US",
    "sg:address":"58730 Saint Clement Ave",
    "sg:city":"Plaquemine",
    "sg:classifiers":[
        {
            "category":"Shopping",
            "type":"Retail Goods"
        }
    ],
    "sg:phone":"+1 225 687 4004",
    "sg:postcode":"70764",
    "sg:province":"LA",
    "sg:tags":[
        "miscellaneous",
        "store"
    ],
    "wof:name":"LA Shoppe",
    "wof:placetype":"venue"
},
  "geometry": {"coordinates":[-91.244258,30.274905],"type":"Point"}
}