{
  "type": "Feature",
  "properties": {
    "addr:full":"1617 Surrey St Lafayette LA 70508",
    "addr:housenumber":"1617",
    "addr:postcode":"70508",
    "addr:street":"Surrey St",
    "iso:country":"US",
    "sg:address":"1617 Surrey St",
    "sg:city":"Lafayette",
    "sg:classifiers":[
        {
            "category":"Building & Trades",
            "subcategory":"Construction",
            "type":"Services"
        }
    ],
    "sg:phone":"+1 337 267 7064",
    "sg:postcode":"70508",
    "sg:province":"LA",
    "sg:tags":[
        "grading",
        "contractor"
    ],
    "wof:name":"Public Works Dept",
    "wof:placetype":"venue"
},
  "geometry": {"coordinates":[-91.992497,30.215768],"type":"Point"}
}