{
  "type": "Feature",
  "properties": {
    "iso:country":"US",
    "sg:address":"1104 N Upland Ave",
    "sg:city":"Metairie",
    "sg:classifiers":[
        {
            "category":"Building & Trades",
            "subcategory":"Plumbing",
            "type":"Services"
        }
    ],
    "sg:phone":"+1 504 467 9689",
    "sg:postcode":"70003",
    "sg:province":"LA",
    "sg:tags":[
        "contractor"
    ],
    "wof:name":"A A A Air Conditioning & Htg",
    "wof:placetype":"venue"
},
  "geometry": {"coordinates":[-90.222345,29.99081],"type":"Point"}
}