{
  "type": "Feature",
  "properties": {
    "addr:full":"208 Mike St Houma LA 70360",
    "addr:housenumber":"208",
    "addr:postcode":"70360",
    "addr:street":"Mike St",
    "iso:country":"US",
    "sg:address":"208 Mike St",
    "sg:city":"Houma",
    "sg:classifiers":[
        {
            "category":"Building & Trades",
            "subcategory":"Plumbing",
            "type":"Services"
        }
    ],
    "sg:phone":"+1 985 917 0200",
    "sg:postcode":"70360",
    "sg:province":"LA",
    "sg:tags":[
        "conditioning",
        "air",
        "system",
        "contractor"
    ],
    "wof:name":"Champions AC & Heat",
    "wof:placetype":"venue"
},
  "geometry": {"coordinates":[-90.752916,29.618495],"type":"Point"}
}