{
  "type": "Feature",
  "properties": {
    "iso:country":"US",
    "sg:address":"220 Louie St",
    "sg:city":"Lake Charles",
    "sg:classifiers":[
        {
            "category":"Social Services",
            "type":"Services"
        }
    ],
    "sg:phone":"+1 337 436 9533",
    "sg:postcode":"70601",
    "sg:province":"LA",
    "sg:tags":[
        "counselor",
        "marriage",
        "family"
    ],
    "sg:website":"www.fyca.org",
    "wof:name":"Family & Youth Counseling Agcy",
    "wof:placetype":"venue"
},
  "geometry": {"coordinates":[-93.22264300000001,30.210062],"type":"Point"}
}