{
  "type": "Feature",
  "properties": {
    "addr:full":"1534 Lindberg Dr Slidell LA 70458",
    "addr:housenumber":"1534",
    "addr:postcode":"70458",
    "addr:street":"Lindberg Dr",
    "iso:country":"US",
    "sg:address":"1534 Lindberg Dr",
    "sg:city":"Slidell",
    "sg:classifiers":[
        {
            "category":"Professional",
            "subcategory":"Employment Agencies",
            "type":"Services"
        },
        {
            "category":"Social Services",
            "type":"Services"
        }
    ],
    "sg:phone":"+1 985 641 4460",
    "sg:postcode":"70458",
    "sg:province":"LA",
    "sg:tags":[
        "care",
        "individual",
        "center",
        "family",
        "day"
    ],
    "wof:name":"Employment Transition Services",
    "wof:placetype":"venue"
},
  "geometry": {"coordinates":[-89.75241200000001,30.280246],"type":"Point"}
}