{
  "type": "Feature",
  "properties": {
    "iso:country":"US",
    "sg:address":"264 Tunica Dr E",
    "sg:city":"Marksville",
    "sg:classifiers":[
        {
            "category":"Home & Garden",
            "subcategory":"Household Appliances",
            "type":"Retail Goods"
        }
    ],
    "sg:phone":"+1 318 253 6571",
    "sg:postcode":"71351",
    "sg:province":"LA",
    "wof:name":"Ira's Appliance Ctr",
    "wof:placetype":"venue"
},
  "geometry": {"coordinates":[-92.068316,31.122031],"type":"Point"}
}