{
  "type": "Feature",
  "properties": {
    "addr:full":"825 Murray St Alexandria LA 71301",
    "addr:housenumber":"825",
    "addr:postcode":"71301",
    "addr:street":"Murray St",
    "iso:country":"US",
    "sg:address":"825 Murray St",
    "sg:city":"Alexandria",
    "sg:classifiers":[
        {
            "category":"Communications",
            "type":"Services"
        }
    ],
    "sg:phone":"+1 318 449 1984",
    "sg:postcode":"71301",
    "sg:province":"LA",
    "wof:name":"Bellsouth",
    "wof:placetype":"venue"
},
  "geometry": {"coordinates":[-92.44807400000001,31.308264],"type":"Point"}
}