{
  "type": "Feature",
  "properties": {
    "iso:country":"US",
    "sg:address":"1327 State Rte 75",
    "sg:city":"Sunshine",
    "sg:classifiers":[
        {
            "category":"Professional",
            "subcategory":"Advertising",
            "type":"Services"
        }
    ],
    "sg:phone":"+1 225 642 9080",
    "sg:postcode":"70780",
    "sg:province":"LA",
    "wof:name":"Clear Channel Communications",
    "wof:placetype":"venue"
},
  "geometry": {"coordinates":[-91.199186,30.285823],"type":"Point"}
}