{
  "type": "Feature",
  "properties": {
    "iso:country":"US",
    "sg:address":"425 Ashley Ridge Blvd",
    "sg:city":"Shreveport",
    "sg:classifiers":[
        {
            "category":"Sports & Exercise",
            "subcategory":"Gym",
            "type":"Entertainment"
        }
    ],
    "sg:phone":"+1 318 868 3489",
    "sg:postcode":"71106",
    "sg:province":"LA",
    "sg:tags":[
        "club",
        "health",
        "studio",
        "gymnasium"
    ],
    "wof:name":"Fit Rx",
    "wof:placetype":"venue"
},
  "geometry": {"coordinates":[-93.736036,32.418281],"type":"Point"}
}