{
  "type": "Feature",
  "properties": {
    "iso:country":"US",
    "sg:address":"80 David Rawls Rd",
    "sg:city":"Rayville",
    "sg:phone":"+1 318 728 3844",
    "sg:postcode":"71269",
    "sg:province":"LA",
    "sg:tags":[
        "farm",
        "corn"
    ],
    "wof:name":"Rawls Farm",
    "wof:placetype":"venue"
},
  "geometry": {"coordinates":[-91.62716399999999,32.595147],"type":"Point"}
}