{
  "type": "Feature",
  "properties": {
    "iso:country":"US",
    "sg:address":"1918 Maplewood Dr",
    "sg:city":"Sulphur",
    "sg:classifiers":[
        {
            "category":"Insurance",
            "subcategory":"Insurance Agent",
            "type":"Services"
        }
    ],
    "sg:phone":"+1 337 625 2147",
    "sg:postcode":"70663",
    "sg:province":"LA",
    "wof:name":"Allstate",
    "wof:placetype":"venue"
},
  "geometry": {"coordinates":[-93.35586000000001,30.227473],"type":"Point"}
}