{
  "type": "Feature",
  "properties": {
    "addr:full":"3912 Parliament Dr Alexandria LA 71303",
    "addr:housenumber":"3912",
    "addr:postcode":"71303",
    "addr:street":"Parliament Dr",
    "iso:country":"US",
    "sg:address":"3912 Parliament Dr",
    "sg:city":"Alexandria",
    "sg:classifiers":[
        {
            "category":"Health Services",
            "subcategory":"Health Practitioner",
            "type":"Services"
        }
    ],
    "sg:phone":"+1 318 487 0211",
    "sg:postcode":"71303",
    "sg:province":"LA",
    "sg:tags":[
        "therapist",
        "physical"
    ],
    "wof:name":"Miller Physical Therapy Svc",
    "wof:placetype":"venue"
},
  "geometry": {"coordinates":[-92.478812,31.283437],"type":"Point"}
}