{
  "type": "Feature",
  "properties": {
    "addr:full":"202 N Latour St Ville Platte LA 70586",
    "addr:housenumber":"202",
    "addr:postcode":"70586",
    "addr:street":"N Latour St",
    "iso:country":"US",
    "sg:address":"202 N Latour St",
    "sg:city":"Ville Platte",
    "sg:classifiers":[
        {
            "category":"Professional",
            "subcategory":"Business Services",
            "type":"Services"
        }
    ],
    "sg:phone":"+1 337 363 2261",
    "sg:postcode":"70586",
    "sg:province":"LA",
    "wof:name":"Vanessa A Ramirez",
    "wof:placetype":"venue"
},
  "geometry": {"coordinates":[-92.268264,30.687982],"type":"Point"}
}