{
  "type": "Feature",
  "properties": {
    "iso:country":"US",
    "sg:address":"2121 W Laurel Ave",
    "sg:city":"Eunice",
    "sg:classifiers":[
        {
            "category":"Restaurant",
            "type":"Food & Drink"
        }
    ],
    "sg:menulink":"http://www.allmenus.com/la/eunice/208606-taco-bell/menu/",
    "sg:phone":"+1 337 457 3408",
    "sg:postcode":"70535",
    "sg:province":"LA",
    "sg:tags":[
        "mexican"
    ],
    "wof:name":"Taco Bell",
    "wof:placetype":"venue"
},
  "geometry": {"coordinates":[-92.43776800000001,30.494929],"type":"Point"}
}