{
  "type": "Feature",
  "properties": {
    "iso:country":"US",
    "sg:address":"209 Sunflower Dr",
    "sg:city":"Lafayette",
    "sg:classifiers":[
        {
            "category":"Professional",
            "subcategory":"Computer Services",
            "type":"Services"
        }
    ],
    "sg:phone":"+1 337 349 0931",
    "sg:postcode":"70508",
    "sg:province":"LA",
    "sg:tags":[
        "repair"
    ],
    "wof:name":"Acadiana Computer Support",
    "wof:placetype":"venue"
},
  "geometry": {"coordinates":[-92.050757,30.129199],"type":"Point"}
}