{
  "type": "Feature",
  "properties": {
    "iso:country":"US",
    "sg:address":"5311 3rd St",
    "sg:city":"Alexandria",
    "sg:classifiers":[
        {
            "category":"Building & Trades",
            "subcategory":"Construction",
            "type":"Services"
        }
    ],
    "sg:phone":"+1 318 487 9263",
    "sg:postcode":"71302",
    "sg:province":"LA",
    "sg:tags":[
        "general",
        "contractor"
    ],
    "sg:website":"www.luhralex.com",
    "wof:name":"Luhr Brothers Inc",
    "wof:placetype":"venue"
},
  "geometry": {"coordinates":[-92.407388,31.283138],"type":"Point"}
}