{
  "type": "Feature",
  "properties": {
    "iso:country":"US",
    "sg:address":"833 Faun St",
    "sg:city":"Metairie",
    "sg:classifiers":[
        {
            "category":"Professional",
            "subcategory":"Business Services",
            "type":"Services"
        }
    ],
    "sg:phone":"+1 504 736 0021",
    "sg:postcode":"70003",
    "sg:province":"LA",
    "sg:tags":[
        "convention",
        "meeting",
        "facility"
    ],
    "wof:name":"Du Four Productions",
    "wof:placetype":"venue"
},
  "geometry": {"coordinates":[-90.20233399999999,29.98348],"type":"Point"}
}