{
  "type": "Feature",
  "properties": {
    "addr:full":"2727 Virginia St Kenner LA 70062",
    "addr:housenumber":"2727",
    "addr:postcode":"70062",
    "addr:street":"Virginia St",
    "iso:country":"US",
    "sg:address":"2727 Virginia St",
    "sg:city":"Kenner",
    "sg:classifiers":[
        {
            "category":"Retail",
            "subcategory":"Auto Repair",
            "type":"Services"
        }
    ],
    "sg:phone":"+1 504 469 1680",
    "sg:postcode":"70062",
    "sg:province":"LA",
    "sg:tags":[
        "body",
        "automobile",
        "painting"
    ],
    "wof:name":"Jerry Ford's Body & Paint Shop",
    "wof:placetype":"venue"
},
  "geometry": {"coordinates":[-90.24661999999999,30.005447],"type":"Point"}
}