{
  "type": "Feature",
  "properties": {
    "iso:country":"US",
    "sg:address":"909 W Monroe St",
    "sg:city":"Broussard",
    "sg:classifiers":[
        {
            "category":"Building & Trades",
            "subcategory":"Landscaping Services",
            "type":"Services"
        }
    ],
    "sg:phone":"+1 337 837 5363",
    "sg:postcode":"70518",
    "sg:province":"LA",
    "sg:tags":[
        "lawn",
        "maintenance",
        "grounds"
    ],
    "wof:name":"Grass Busters",
    "wof:placetype":"venue"
},
  "geometry": {"coordinates":[-91.969379,30.146839],"type":"Point"}
}