{
  "type": "Feature",
  "properties": {
    "iso:country":"US",
    "sg:address":"902 Jenkins St",
    "sg:city":"Mansfield",
    "sg:classifiers":[
        {
            "category":"Home & Garden",
            "subcategory":"Building Materials",
            "type":"Retail Goods"
        }
    ],
    "sg:phone":"+1 318 872 0424",
    "sg:postcode":"71052",
    "sg:province":"LA",
    "sg:tags":[
        "glass",
        "window",
        "plate"
    ],
    "wof:name":"Toledo Glass Co",
    "wof:placetype":"venue"
},
  "geometry": {"coordinates":[-93.713694,32.025774],"type":"Point"}
}