{
  "type": "Feature",
  "properties": {
    "iso:country":"US",
    "sg:address":"1032 Belton St",
    "sg:city":"Basile",
    "sg:classifiers":[
        {
            "category":"Education",
            "subcategory":"School",
            "type":"Public Place"
        }
    ],
    "sg:phone":"+1 337 432 6412",
    "sg:postcode":"70515",
    "sg:province":"LA",
    "wof:name":"W W Stewart Elementary School",
    "wof:placetype":"venue"
},
  "geometry": {"coordinates":[-92.607052,30.482472],"type":"Point"}
}