{
  "type": "Feature",
  "properties": {
    "iso:country":"US",
    "sg:address":"3101 Lee St",
    "sg:city":"Alexandria",
    "sg:classifiers":[
        {
            "category":"Retail",
            "subcategory":"Auto Rental",
            "type":"Services"
        }
    ],
    "sg:phone":"+1 318 443 8278",
    "sg:postcode":"71301",
    "sg:province":"LA",
    "sg:tags":[
        "renting",
        "automobile"
    ],
    "wof:name":"USA Discount Car Rentals",
    "wof:placetype":"venue"
},
  "geometry": {"coordinates":[-92.448779,31.282014],"type":"Point"}
}