{
  "type": "Feature",
  "properties": {
    "addr:full":"312 Hunter St Pineville LA 71360",
    "addr:housenumber":"312",
    "addr:postcode":"71360",
    "addr:street":"Hunter St",
    "iso:country":"US",
    "sg:address":"312 Hunter St",
    "sg:city":"Pineville",
    "sg:classifiers":[
        {
            "category":"Organizations",
            "subcategory":"Religious Organization",
            "type":"Services"
        }
    ],
    "sg:phone":"+1 318 767 0106",
    "sg:postcode":"71360",
    "sg:province":"LA",
    "sg:tags":[
        "church"
    ],
    "wof:name":"Zion Hill Baptist Church",
    "wof:placetype":"venue"
},
  "geometry": {"coordinates":[-92.435954,31.315047],"type":"Point"}
}