{
  "type": "Feature",
  "properties": {
    "iso:country":"US",
    "sg:address":"1713 Sgt Alfred Dr",
    "sg:city":"Slidell",
    "sg:classifiers":[
        {
            "category":"Retail",
            "subcategory":"Animal Services",
            "type":"Services"
        }
    ],
    "sg:phone":"+1 985 649 1150",
    "sg:postcode":"70458",
    "sg:province":"LA",
    "sg:tags":[
        "pet",
        "boarding",
        "sitting"
    ],
    "wof:name":"Ryans Dogs R Us Training Ctr",
    "wof:placetype":"venue"
},
  "geometry": {"coordinates":[-89.78057200000001,30.279524],"type":"Point"}
}