{
  "type": "Feature",
  "properties": {
    "addr:full":"900 N Carrollton Ave New Orleans LA 70119",
    "addr:housenumber":"900",
    "addr:postcode":"70119",
    "addr:street":"N Carrollton Ave",
    "iso:country":"US",
    "sg:address":"900 N Carrollton Ave",
    "sg:city":"New Orleans",
    "sg:classifiers":[
        {
            "category":"Restaurant",
            "type":"Food & Drink"
        }
    ],
    "sg:phone":"+1 504 488 2155",
    "sg:postcode":"70119",
    "sg:province":"LA",
    "sg:tags":[
        "product",
        "italian"
    ],
    "wof:name":"Fellini's Cafe",
    "wof:placetype":"venue"
},
  "geometry": {"coordinates":[-90.09274499999999,29.981747],"type":"Point"}
}