{
  "type": "Feature",
  "properties": {
    "iso:country":"US",
    "sg:address":"2900 Maplewood Dr",
    "sg:city":"Sulphur",
    "sg:classifiers":[
        {
            "category":"Shopping",
            "subcategory":"Jewelry",
            "type":"Retail Goods"
        }
    ],
    "sg:phone":"+1 337 625 5555",
    "sg:postcode":"70663",
    "sg:province":"LA",
    "sg:tags":[
        "jeweler"
    ],
    "wof:name":"Lewis' Jewelry & Coins",
    "wof:placetype":"venue"
},
  "geometry": {"coordinates":[-93.344038,30.227594],"type":"Point"}
}