{
  "type": "Feature",
  "properties": {
    "iso:country":"US",
    "sg:address":"8660 Fern Ave",
    "sg:city":"Shreveport",
    "sg:classifiers":[
        {
            "category":"Professional",
            "type":"Services"
        }
    ],
    "sg:phone":"+1 318 798 5500",
    "sg:postcode":"71105",
    "sg:province":"LA",
    "sg:tags":[
        "establishment"
    ],
    "wof:name":"Executive Aviation-LA",
    "wof:placetype":"venue"
},
  "geometry": {"coordinates":[-93.724019,32.425812],"type":"Point"}
}