{
  "type": "Feature",
  "properties": {
    "iso:country":"US",
    "sg:address":"8919 World Ministry Ave",
    "sg:city":"Baton Rouge",
    "sg:classifiers":[
        {
            "category":"Organizations",
            "subcategory":"Membership Organization",
            "type":"Services"
        }
    ],
    "sg:phone":"+1 225 766 6800",
    "sg:postcode":"70810",
    "sg:province":"LA",
    "sg:tags":[
        "athletic"
    ],
    "wof:name":"National Senior Games Assn",
    "wof:placetype":"venue"
},
  "geometry": {"coordinates":[-91.092522,30.383687],"type":"Point"}
}