{
  "type": "Feature",
  "properties": {
    "addr:full":"4312 E Judge Perez Dr Meraux LA 70075",
    "addr:housenumber":"4312",
    "addr:postcode":"70075",
    "addr:street":"E Judge Perez Dr Meraux",
    "iso:country":"US",
    "sg:address":"4312 E Judge Perez Dr",
    "sg:city":"Meraux",
    "sg:classifiers":[
        {
            "category":"Food & Beverages",
            "subcategory":"Specialty",
            "type":"Retail Goods"
        }
    ],
    "sg:phone":"+1 504 276 9050",
    "sg:postcode":"70075",
    "sg:province":"LA",
    "sg:tags":[
        "tea",
        "coffee"
    ],
    "wof:name":"Big Easy Cafe",
    "wof:placetype":"venue"
},
  "geometry": {"coordinates":[-89.916287,29.931104],"type":"Point"}
}