{
  "type": "Feature",
  "properties": {
    "iso:country":"US",
    "sg:address":"70217 Hwy 59",
    "sg:city":"Abita Springs",
    "sg:classifiers":[
        {
            "category":"Wholesale",
            "subcategory":"Metals & Minerals",
            "type":"Manufacturing & Wholesale Goods"
        }
    ],
    "sg:phone":"+1 985 892 4223",
    "sg:postcode":"70420",
    "sg:province":"LA",
    "sg:tags":[
        "steel",
        "warehouse"
    ],
    "wof:name":"Water Cut Inc",
    "wof:placetype":"venue"
},
  "geometry": {"coordinates":[-90.04078199999999,30.460251],"type":"Point"}
}