{
  "type": "Feature",
  "properties": {
    "addr:full":"4760 Old Scenic Hwy Zachary LA 70791",
    "addr:housenumber":"4760",
    "addr:postcode":"70791",
    "addr:street":"Old Scenic Hwy Zachary",
    "iso:country":"US",
    "sg:address":"4760 Old Scenic Hwy",
    "sg:city":"Zachary",
    "sg:classifiers":[
        {
            "category":"Retail",
            "subcategory":"Portrait Studio",
            "type":"Services"
        }
    ],
    "sg:phone":"+1 225 658 0883",
    "sg:postcode":"70791",
    "sg:province":"LA",
    "sg:tags":[
        "photographer"
    ],
    "wof:name":"Amy Martin Photography",
    "wof:placetype":"venue"
},
  "geometry": {"coordinates":[-91.19257899999999,30.658959],"type":"Point"}
}