{
  "type": "Feature",
  "properties": {
    "iso:country":"US",
    "sg:address":"2212 Prentiss Ave",
    "sg:city":"New Orleans",
    "sg:classifiers":[
        {
            "category":"Organizations",
            "subcategory":"Religious Organization",
            "type":"Services"
        }
    ],
    "sg:phone":"+1 504 282 6494",
    "sg:postcode":"70122",
    "sg:province":"LA",
    "sg:tags":[
        "church"
    ],
    "wof:name":"St Raphael Church",
    "wof:placetype":"venue"
},
  "geometry": {"coordinates":[-90.05844399999999,30.016705],"type":"Point"}
}