{
  "type": "Feature",
  "properties": {
    "iso:country":"US",
    "sg:address":"1423 1st St",
    "sg:city":"New Orleans",
    "sg:classifiers":[
        {
            "category":"Travel",
            "subcategory":"Hotels & Motels",
            "type":"Entertainment"
        }
    ],
    "sg:phone":"+1 504 566 1411",
    "sg:postcode":"70130",
    "sg:province":"LA",
    "wof:name":"Acadian Orlean Inn",
    "wof:placetype":"venue"
},
  "geometry": {"coordinates":[-90.081598,29.931343],"type":"Point"}
}