{
  "type": "Feature",
  "properties": {
    "iso:country":"US",
    "sg:address":"4045 Scenic Hwy",
    "sg:city":"Baton Rouge",
    "sg:classifiers":[
        {
            "category":"Professional",
            "subcategory":"Management & Consulting",
            "type":"Services"
        }
    ],
    "sg:phone":"+1 225 355 1007",
    "sg:postcode":"70805",
    "sg:province":"LA",
    "sg:tags":[
        "consultant",
        "safety"
    ],
    "wof:name":"WSI Ind Safety Div",
    "wof:placetype":"venue"
},
  "geometry": {"coordinates":[-91.169057,30.485933],"type":"Point"}
}