{
  "type": "Feature",
  "properties": {
    "addr:full":"8517 Victory Dr Chalmette LA 70043",
    "addr:housenumber":"8517",
    "addr:postcode":"70043",
    "addr:street":"Victory Dr Chalmette",
    "iso:country":"US",
    "sg:address":"8517 Victory Dr",
    "sg:city":"Chalmette",
    "sg:classifiers":[
        {
            "category":"Insurance",
            "subcategory":"Insurance Agent",
            "type":"Services"
        }
    ],
    "sg:phone":"+1 504 277 1895",
    "sg:postcode":"70043",
    "sg:province":"LA",
    "wof:name":"Benefit Resource Group",
    "wof:placetype":"venue"
},
  "geometry": {"coordinates":[-89.970597,29.960478],"type":"Point"}
}