{
  "type": "Feature",
  "properties": {
    "iso:country":"US",
    "sg:address":"428 Jefferson St",
    "sg:city":"Lafayette",
    "sg:classifiers":[
        {
            "category":"Professional",
            "subcategory":"Lawyer & Legal Services",
            "type":"Services"
        }
    ],
    "sg:phone":"+1 337 232 8177",
    "sg:postcode":"70501",
    "sg:province":"LA",
    "sg:tags":[
        "attorney"
    ],
    "wof:name":"Guilliot St Pe & Soileau",
    "wof:placetype":"venue"
},
  "geometry": {"coordinates":[-92.018159,30.226006],"type":"Point"}
}