{
  "type": "Feature",
  "properties": {
    "iso:country":"US",
    "sg:address":"1144 Homer Rd",
    "sg:city":"Minden",
    "sg:classifiers":[
        {
            "category":"Retail",
            "subcategory":"Laundry & Dry Cleaning",
            "type":"Services"
        }
    ],
    "sg:phone":"+1 318 371 1188",
    "sg:postcode":"71055",
    "sg:province":"LA",
    "wof:name":"Mam Ma's Washboard",
    "wof:placetype":"venue"
},
  "geometry": {"coordinates":[-93.25350299999999,32.624526],"type":"Point"}
}