{
  "type": "Feature",
  "properties": {
    "addr:full":"1310 S Laurel St Metairie LA 70003",
    "addr:housenumber":"1310",
    "addr:postcode":"70003",
    "addr:street":"S Laurel St",
    "iso:country":"US",
    "sg:address":"1310 S Laurel St",
    "sg:city":"Metairie",
    "sg:classifiers":[
        {
            "category":"Organizations",
            "subcategory":"Religious Organization",
            "type":"Services"
        }
    ],
    "sg:phone":"+1 504 738 3335",
    "sg:postcode":"70003",
    "sg:province":"LA",
    "wof:name":"Faith Hope & Deliverance Full",
    "wof:placetype":"venue"
},
  "geometry": {"coordinates":[-90.216825,29.977421],"type":"Point"}
}