{
  "type": "Feature",
  "properties": {
    "iso:country":"US",
    "sg:address":"9618 Jefferson Hwy",
    "sg:city":"Baton Rouge",
    "sg:classifiers":[
        {
            "category":"Personal",
            "subcategory":"Beauty Salon",
            "type":"Services"
        }
    ],
    "sg:phone":"+1 225 296 1555",
    "sg:postcode":"70809",
    "sg:province":"LA",
    "sg:tags":[
        "manicuring"
    ],
    "wof:name":"Luxury Nails",
    "wof:placetype":"venue"
},
  "geometry": {"coordinates":[-91.077562,30.410857],"type":"Point"}
}