{
  "type": "Feature",
  "properties": {
    "iso:country":"US",
    "sg:address":"800 S Main St",
    "sg:city":"Church Point",
    "sg:classifiers":[
        {
            "category":"Organizations",
            "subcategory":"Religious Organization",
            "type":"Services"
        }
    ],
    "sg:phone":"+1 337 684 2678",
    "sg:postcode":"70525",
    "sg:province":"LA",
    "sg:tags":[
        "church"
    ],
    "wof:name":"First Pentecostal Church",
    "wof:placetype":"venue"
},
  "geometry": {"coordinates":[-92.20752899999999,30.394522],"type":"Point"}
}