{
  "type": "Feature",
  "properties": {
    "iso:country":"US",
    "sg:address":"6500 Kennedy Dr",
    "sg:city":"Shreveport",
    "sg:classifiers":[
        {
            "category":"Recreation",
            "type":"Entertainment"
        }
    ],
    "sg:phone":"+1 318 673 7793",
    "sg:postcode":"71109",
    "sg:province":"LA",
    "sg:tags":[
        "tennis",
        "court"
    ],
    "wof:name":"Airport Park Tennis Ctr",
    "wof:placetype":"venue"
},
  "geometry": {"coordinates":[-93.810132,32.449323],"type":"Point"}
}