{
  "type": "Feature",
  "properties": {
    "addr:full":"4020 Old Gentilly Rd New Orleans LA 70126",
    "addr:housenumber":"4020",
    "addr:postcode":"70126",
    "addr:street":"Old Gentilly Rd",
    "iso:country":"US",
    "sg:address":"4020 Old Gentilly Rd",
    "sg:city":"New Orleans",
    "sg:classifiers":[
        {
            "category":"Autos & Motor Vehicles",
            "subcategory":"Auto Supplies",
            "type":"Retail Goods"
        }
    ],
    "sg:phone":"+1 504 949 2703",
    "sg:postcode":"70126",
    "sg:province":"LA",
    "sg:tags":[
        "tire"
    ],
    "wof:name":"Direct Tire Town",
    "wof:placetype":"venue"
},
  "geometry": {"coordinates":[-90.042801,30.002399],"type":"Point"}
}