{
  "type": "Feature",
  "properties": {
    "addr:full":"7368 Magnolia Beach Rd Denham Springs LA 70706",
    "addr:housenumber":"7368",
    "addr:postcode":"70706",
    "addr:street":"Magnolia Beach Rd",
    "iso:country":"US",
    "sg:address":"7368 Magnolia Beach Rd",
    "sg:city":"Denham Springs",
    "sg:classifiers":[
        {
            "category":"Utilities",
            "subcategory":"Mobile Phone",
            "type":"Services"
        }
    ],
    "sg:phone":"+1 225 667 9003",
    "sg:postcode":"70706",
    "sg:province":"LA",
    "sg:tags":[
        "telephone",
        "cellular"
    ],
    "wof:name":"A A Nail's Installations",
    "wof:placetype":"venue"
},
  "geometry": {"coordinates":[-90.967359,30.535613],"type":"Point"}
}