{
  "type": "Feature",
  "properties": {
    "iso:country":"US",
    "sg:address":"103 Parkway St",
    "sg:city":"Minden",
    "sg:classifiers":[
        {
            "category":"Autos & Motor Vehicles",
            "subcategory":"Automobile Sales",
            "type":"Retail Goods"
        }
    ],
    "sg:phone":"+1 318 377 0700",
    "sg:postcode":"71055",
    "sg:province":"LA",
    "sg:tags":[
        "car",
        "dealer"
    ],
    "wof:name":"Ed's Auto Sales",
    "wof:placetype":"venue"
},
  "geometry": {"coordinates":[-93.295194,32.608],"type":"Point"}
}