{
  "type": "Feature",
  "properties": {
    "iso:country":"US",
    "sg:address":"87 Myers Rd",
    "sg:city":"Epps",
    "sg:classifiers":[
        {
            "category":"Organizations",
            "subcategory":"Religious Organization",
            "type":"Services"
        }
    ],
    "sg:phone":"+1 318 878 2414",
    "sg:postcode":"71232",
    "sg:province":"LA",
    "sg:tags":[
        "church"
    ],
    "wof:name":"Hegwood Baptist Church",
    "wof:placetype":"venue"
},
  "geometry": {"coordinates":[-91.579729,32.557324],"type":"Point"}
}