{
  "type": "Feature",
  "properties": {
    "addr:full":"219 Sterlington Rd Monroe LA 71203",
    "addr:housenumber":"219",
    "addr:postcode":"71203",
    "addr:street":"Sterlington Rd",
    "iso:country":"US",
    "sg:address":"219 Sterlington Rd",
    "sg:city":"Monroe",
    "sg:classifiers":[
        {
            "category":"Shopping",
            "subcategory":"Florist",
            "type":"Retail Goods"
        }
    ],
    "sg:phone":"+1 318 325 8283",
    "sg:postcode":"71203",
    "sg:province":"LA",
    "wof:name":"Mc Mullen Flower Shop",
    "wof:placetype":"venue"
},
  "geometry": {"coordinates":[-92.081765,32.524575],"type":"Point"}
}