{
  "type": "Feature",
  "properties": {
    "addr:full":"4944 Bullard Ave New Orleans LA 70128",
    "addr:housenumber":"4944",
    "addr:postcode":"70128",
    "addr:street":"Bullard Ave",
    "iso:country":"US",
    "sg:address":"4944 Bullard Ave",
    "sg:city":"New Orleans",
    "sg:classifiers":[
        {
            "category":"Insurance",
            "subcategory":"Insurance Agent",
            "type":"Services"
        }
    ],
    "sg:phone":"+1 504 241 4444",
    "sg:postcode":"70128",
    "sg:province":"LA",
    "wof:name":"State Farm Insurance",
    "wof:placetype":"venue"
},
  "geometry": {"coordinates":[-89.94790399999999,30.026851],"type":"Point"}
}