{
  "type": "Feature",
  "properties": {
    "iso:country":"US",
    "sg:address":"219 E Thomas St",
    "sg:city":"Hammond",
    "sg:classifiers":[
        {
            "category":"Health Services",
            "subcategory":"Clinic",
            "type":"Services"
        }
    ],
    "sg:phone":"+1 985 345 3182",
    "sg:postcode":"70401",
    "sg:province":"LA",
    "wof:name":"Active Treatment Inc",
    "wof:placetype":"venue"
},
  "geometry": {"coordinates":[-90.458777,30.504673],"type":"Point"}
}