{
  "type": "Feature",
  "properties": {
    "addr:full":"8181 Lake Forest Blvd New Orleans LA 70126",
    "addr:housenumber":"8181",
    "addr:postcode":"70126",
    "addr:street":"Lake Forest Blvd",
    "iso:country":"US",
    "sg:address":"8181 Lake Forest Blvd",
    "sg:city":"New Orleans",
    "sg:classifiers":[
        {
            "category":"Building & Trades",
            "subcategory":"Cleaning & Sanitation",
            "type":"Services"
        }
    ],
    "sg:phone":"+1 504 241 4546",
    "sg:postcode":"70126",
    "sg:province":"LA",
    "sg:tags":[
        "janitorial"
    ],
    "wof:name":"Clean Etc",
    "wof:placetype":"venue"
},
  "geometry": {"coordinates":[-89.99454,30.025429],"type":"Point"}
}