{
  "type": "Feature",
  "properties": {
    "addr:full":"4521 Jamestown Ave Baton Rouge LA 70808",
    "addr:housenumber":"4521",
    "addr:postcode":"70808",
    "addr:street":"Jamestown Ave",
    "iso:country":"US",
    "sg:address":"4521 Jamestown Ave",
    "sg:city":"Baton Rouge",
    "sg:classifiers":[
        {
            "category":"Professional",
            "type":"Services"
        }
    ],
    "sg:phone":"+1 225 201 0334",
    "sg:postcode":"70808",
    "sg:province":"LA",
    "sg:tags":[
        "establishment"
    ],
    "wof:name":"Louisiana Challenger Network",
    "wof:placetype":"venue"
},
  "geometry": {"coordinates":[-91.13713799999999,30.420856],"type":"Point"}
}