{
  "type": "Feature",
  "properties": {
    "iso:country":"US",
    "sg:address":"2 Country Club Park",
    "sg:city":"Covington",
    "sg:classifiers":[
        {
            "category":"Organizations",
            "subcategory":"Community Association",
            "type":"Services"
        }
    ],
    "sg:phone":"+1 985 892 0925",
    "sg:postcode":"70433",
    "sg:province":"LA",
    "sg:tags":[
        "club"
    ],
    "wof:name":"Tchefuncta Country Club",
    "wof:placetype":"venue"
},
  "geometry": {"coordinates":[-90.129803,30.428943],"type":"Point"}
}