{
  "type": "Feature",
  "properties": {
    "addr:full":"1318 Florida Ave SW Denham Springs LA 70726",
    "addr:housenumber":"1318",
    "addr:postcode":"70726",
    "addr:street":"Florida Ave Sw Denham Springs",
    "iso:country":"US",
    "sg:address":"1318 Florida Ave SW",
    "sg:city":"Denham Springs",
    "sg:classifiers":[
        {
            "category":"Food & Beverages",
            "subcategory":"Specialty",
            "type":"Retail Goods"
        }
    ],
    "sg:phone":"+1 225 667 4524",
    "sg:postcode":"70726",
    "sg:province":"LA",
    "sg:tags":[
        "water",
        "bulk",
        "company"
    ],
    "wof:name":"Artic Pure Water",
    "wof:placetype":"venue"
},
  "geometry": {"coordinates":[-90.96361,30.47264],"type":"Point"}
}