{
  "type": "Feature",
  "properties": {
    "addr:full":"702 N Carrollton Ave New Orleans LA 70119",
    "addr:housenumber":"702",
    "addr:postcode":"70119",
    "addr:street":"N Carrollton Ave",
    "iso:country":"US",
    "sg:address":"702 N Carrollton Ave",
    "sg:city":"New Orleans",
    "sg:classifiers":[
        {
            "category":"Health Services",
            "subcategory":"Clinic",
            "type":"Services"
        }
    ],
    "sg:phone":"+1 504 486 5044",
    "sg:postcode":"70119",
    "sg:province":"LA",
    "sg:tags":[
        "home"
    ],
    "sg:website":"www.dependablehomecare.com",
    "wof:name":"Dependable Home Care",
    "wof:placetype":"venue"
},
  "geometry": {"coordinates":[-90.095567,29.979021],"type":"Point"}
}