{
  "type": "Feature",
  "properties": {
    "addr:full":"9171 Cockerham Rd Denham Springs LA 70726",
    "addr:housenumber":"9171",
    "addr:postcode":"70726",
    "addr:street":"Cockerham Rd",
    "iso:country":"US",
    "sg:address":"9171 Cockerham Rd",
    "sg:city":"Denham Springs",
    "sg:classifiers":[
        {
            "category":"Health Services",
            "subcategory":"Nursing And Care Facility",
            "type":"Services"
        }
    ],
    "sg:phone":"+1 225 665 8946",
    "sg:postcode":"70726",
    "sg:province":"LA",
    "sg:tags":[
        "home",
        "convalescent"
    ],
    "wof:name":"Harvest Manor Nursing Home",
    "wof:placetype":"venue"
},
  "geometry": {"coordinates":[-90.935439,30.504798],"type":"Point"}
}