{
  "type": "Feature",
  "properties": {
    "iso:country":"US",
    "sg:address":"210 Terrace Ave",
    "sg:city":"Baton Rouge",
    "sg:classifiers":[
        {
            "category":"Home & Garden",
            "subcategory":"Carpets & Floor Coverings",
            "type":"Retail Goods"
        }
    ],
    "sg:phone":"+1 225 343 5702",
    "sg:postcode":"70802",
    "sg:province":"LA",
    "sg:tags":[
        "dealer",
        "rug"
    ],
    "wof:name":"Unit Design Inc",
    "wof:placetype":"venue"
},
  "geometry": {"coordinates":[-91.188079,30.436224],"type":"Point"}
}