{
  "type": "Feature",
  "properties": {
    "iso:country":"US",
    "sg:address":"8831 Bluebonnet Blvd",
    "sg:city":"Baton Rouge",
    "sg:classifiers":[
        {
            "category":"Sports & Exercise",
            "subcategory":"Gym",
            "type":"Entertainment"
        }
    ],
    "sg:phone":"+1 225 767 2345",
    "sg:postcode":"70810",
    "sg:province":"LA",
    "sg:tags":[
        "spa",
        "health"
    ],
    "wof:name":"Christian Avery Spa",
    "wof:placetype":"venue"
},
  "geometry": {"coordinates":[-91.10269700000001,30.369184],"type":"Point"}
}