{
  "type": "Feature",
  "properties": {
    "iso:country":"US",
    "sg:address":"337 Rich Rd",
    "sg:city":"Arcadia",
    "sg:classifiers":[
        {
            "category":"Farming",
            "subcategory":"Orchard",
            "type":"Manufacturing & Wholesale Goods"
        }
    ],
    "sg:phone":"+1 318 263 8319",
    "sg:postcode":"71001",
    "sg:province":"LA",
    "sg:tags":[
        "fruit",
        "tree"
    ],
    "wof:name":"Farm On Mayhaw Hill",
    "wof:placetype":"venue"
},
  "geometry": {"coordinates":[-92.92377500000001,32.597041],"type":"Point"}
}