{
  "type": "Feature",
  "properties": {
    "iso:country":"US",
    "sg:address":"10271 Florida Blvd",
    "sg:city":"Walker",
    "sg:classifiers":[
        {
            "category":"Wholesale",
            "subcategory":"Machinery & Supplies",
            "type":"Manufacturing & Wholesale Goods"
        }
    ],
    "sg:phone":"+1 225 665 9907",
    "sg:postcode":"70785",
    "sg:province":"LA",
    "sg:tags":[
        "equipment",
        "safety",
        "clothing"
    ],
    "wof:name":"Pharma-Safe Industrial",
    "wof:placetype":"venue"
},
  "geometry": {"coordinates":[-90.91415600000001,30.482945],"type":"Point"}
}