{
  "type": "Feature",
  "properties": {
    "addr:full":"50023 Hwy 51 Tickfaw LA 70466",
    "addr:housenumber":"50023",
    "addr:postcode":"70466",
    "addr:street":"Hwy 51",
    "iso:country":"US",
    "sg:address":"50023 Hwy 51",
    "sg:city":"Tickfaw",
    "sg:classifiers":[
        {
            "category":"Travel",
            "subcategory":"Hotels & Motels",
            "type":"Entertainment"
        }
    ],
    "sg:phone":"+1 985 542 7159",
    "sg:postcode":"70466",
    "sg:province":"LA",
    "sg:tags":[
        "breakfast",
        "accommodation",
        "bed"
    ],
    "wof:name":"G W Nesom House",
    "wof:placetype":"venue"
},
  "geometry": {"coordinates":[-90.483407,30.576588],"type":"Point"}
}