{
  "type": "Feature",
  "properties": {
    "addr:full":"1001 E Genie St Chalmette LA 70043",
    "addr:housenumber":"1001",
    "addr:postcode":"70043",
    "addr:street":"E Genie St",
    "iso:country":"US",
    "sg:address":"1001 E Genie St",
    "sg:city":"Chalmette",
    "sg:classifiers":[
        {
            "category":"Building & Trades",
            "subcategory":"Construction",
            "type":"Services"
        }
    ],
    "sg:phone":"+1 504 279 8607",
    "sg:postcode":"70043",
    "sg:province":"LA",
    "sg:tags":[
        "tile",
        "dealer"
    ],
    "wof:name":"Imperial Tile Co Inc",
    "wof:placetype":"venue"
},
  "geometry": {"coordinates":[-89.94885499999999,29.948546],"type":"Point"}
}