{
  "type": "Feature",
  "properties": {
    "iso:country":"US",
    "sg:address":"830 Tunica Dr E",
    "sg:city":"Marksville",
    "sg:classifiers":[
        {
            "category":"Utilities",
            "subcategory":"Mobile Phone",
            "type":"Services"
        }
    ],
    "sg:phone":"+1 337 363 9113",
    "sg:postcode":"71351",
    "sg:province":"LA",
    "sg:tags":[
        "telephone",
        "cellular"
    ],
    "wof:name":"Cingular Wireless",
    "wof:placetype":"venue"
},
  "geometry": {"coordinates":[-92.064809,31.112445],"type":"Point"}
}