{
  "type": "Feature",
  "properties": {
    "addr:full":"3368 Hwy 1 Raceland LA 70394",
    "addr:housenumber":"3368",
    "addr:postcode":"70394",
    "addr:street":"Hwy 1",
    "iso:country":"US",
    "sg:address":"3368 Hwy 1",
    "sg:city":"Raceland",
    "sg:classifiers":[
        {
            "category":"Retail",
            "subcategory":"Animal Services",
            "type":"Services"
        }
    ],
    "sg:phone":"+1 985 537 3083",
    "sg:postcode":"70394",
    "sg:province":"LA",
    "wof:name":"Willow Run Kennels",
    "wof:placetype":"venue"
},
  "geometry": {"coordinates":[-90.635851,29.73268],"type":"Point"}
}