{
  "type": "Feature",
  "properties": {
    "iso:country":"US",
    "sg:address":"113 Federal Ave",
    "sg:city":"Morgan City",
    "sg:classifiers":[
        {
            "category":"Organizations",
            "subcategory":"Religious Organization",
            "type":"Services"
        }
    ],
    "sg:phone":"+1 985 384 7512",
    "sg:postcode":"70380",
    "sg:province":"LA",
    "wof:name":"Mount Pilgrim Baptist Church",
    "wof:placetype":"venue"
},
  "geometry": {"coordinates":[-91.20338599999999,29.691743],"type":"Point"}
}