{
  "type": "Feature",
  "properties": {
    "iso:country":"US",
    "sg:address":"1 Summerton Dr",
    "sg:city":"St Rose",
    "sg:classifiers":[
        {
            "category":"Real Estate",
            "subcategory":"Real Estate Operator",
            "type":"Services"
        }
    ],
    "sg:phone":"+1 504 468 9639",
    "sg:postcode":"70087",
    "sg:province":"LA",
    "sg:tags":[
        "apartment"
    ],
    "wof:name":"Ole Man River Apartments",
    "wof:placetype":"venue"
},
  "geometry": {"coordinates":[-90.30805100000001,29.96133],"type":"Point"}
}