{
  "type": "Feature",
  "properties": {
    "addr:full":"206 S Washburn St Converse LA 71419",
    "addr:housenumber":"206",
    "addr:postcode":"71419",
    "addr:street":"S Washburn St",
    "iso:country":"US",
    "sg:address":"206 S Washburn St",
    "sg:city":"Converse",
    "sg:classifiers":[
        {
            "category":"Mining & Drilling",
            "type":"Manufacturing & Wholesale Goods"
        }
    ],
    "sg:phone":"+1 318 567 2032",
    "sg:postcode":"71419",
    "sg:province":"LA",
    "sg:tags":[
        "operator",
        "oil"
    ],
    "wof:name":"Converse Oil Corp",
    "wof:placetype":"venue"
},
  "geometry": {"coordinates":[-93.700137,31.781457],"type":"Point"}
}