{
  "type": "Feature",
  "properties": {
    "iso:country":"US",
    "sg:address":"16189 River Rd",
    "sg:city":"Hahnville",
    "sg:classifiers":[
        {
            "category":"Manufacturing",
            "subcategory":"Rubber & Plastics",
            "type":"Manufacturing & Wholesale Goods"
        }
    ],
    "sg:phone":"+1 985 783 1260",
    "sg:postcode":"70057",
    "sg:province":"LA",
    "sg:tags":[
        "gasket"
    ],
    "wof:name":"Ameraflex Rubber & Gasket",
    "wof:placetype":"venue"
},
  "geometry": {"coordinates":[-90.41663200000001,29.98862],"type":"Point"}
}