{
  "type": "Feature",
  "properties": {
    "iso:country":"US",
    "sg:address":"600 E 2nd St",
    "sg:city":"Bogalusa",
    "sg:classifiers":[
        {
            "category":"Wholesale",
            "subcategory":"Hardware",
            "type":"Manufacturing & Wholesale Goods"
        }
    ],
    "sg:phone":"+1 985 732 2554",
    "sg:postcode":"70427",
    "sg:province":"LA",
    "sg:tags":[
        "fastener"
    ],
    "wof:name":"M-Pak Fasteners Inc",
    "wof:placetype":"venue"
},
  "geometry": {"coordinates":[-89.853431,30.779051],"type":"Point"}
}