{
  "type": "Feature",
  "properties": {
    "iso:country":"US",
    "sg:address":"314 Cherry Blossom Ln",
    "sg:city":"Terrytown",
    "sg:classifiers":[
        {
            "category":"Building & Trades",
            "subcategory":"Construction",
            "type":"Services"
        }
    ],
    "sg:phone":"+1 504 367 3673",
    "sg:postcode":"70056",
    "sg:province":"LA",
    "sg:tags":[
        "contractor"
    ],
    "wof:name":"Miller Edward J",
    "wof:placetype":"venue"
},
  "geometry": {"coordinates":[-90.034401,29.9137],"type":"Point"}
}