{
  "type": "Feature",
  "properties": {
    "iso:country":"US",
    "sg:address":"111 E Vermilion St",
    "sg:city":"Abbeville",
    "sg:classifiers":[
        {
            "category":"Organizations",
            "subcategory":"Membership Organization",
            "type":"Services"
        }
    ],
    "sg:phone":"+1 337 892 9942",
    "sg:postcode":"70510",
    "sg:province":"LA",
    "wof:name":"B Rase Community Center",
    "wof:placetype":"venue"
},
  "geometry": {"coordinates":[-92.13493200000001,29.976434],"type":"Point"}
}