{
  "type": "Feature",
  "properties": {
    "iso:country":"US",
    "sg:address":"427 Mermentau River Rd",
    "sg:city":"Grand Chenier",
    "sg:classifiers":[
        {
            "category":"Professional",
            "type":"Services"
        }
    ],
    "sg:phone":"+1 337 538 2288",
    "sg:postcode":"70643",
    "sg:province":"LA",
    "sg:tags":[
        "establishment"
    ],
    "wof:name":"Auto Comm",
    "wof:placetype":"venue"
},
  "geometry": {"coordinates":[-92.98688,29.771765],"type":"Point"}
}