{
  "type": "Feature",
  "properties": {
    "iso:country":"US",
    "sg:address":"1709 W University Ave",
    "sg:city":"Lafayette",
    "sg:classifiers":[
        {
            "category":"Wholesale",
            "subcategory":"Groceries",
            "type":"Manufacturing & Wholesale Goods"
        }
    ],
    "sg:phone":"+1 337 235 7438",
    "sg:postcode":"70506",
    "sg:province":"LA",
    "sg:tags":[
        "confectionery"
    ],
    "wof:name":"R J Nodd Snacks",
    "wof:placetype":"venue"
},
  "geometry": {"coordinates":[-92.03046399999999,30.229186],"type":"Point"}
}