{
  "type": "Feature",
  "properties": {
    "addr:full":"960 Turquoise St New Orleans LA 70124",
    "addr:housenumber":"960",
    "addr:postcode":"70124",
    "addr:street":"Turquoise St",
    "iso:country":"US",
    "sg:address":"960 Turquoise St",
    "sg:city":"New Orleans",
    "sg:classifiers":[
        {
            "category":"Manufacturing",
            "subcategory":"Jewelry",
            "type":"Manufacturing & Wholesale Goods"
        }
    ],
    "sg:phone":"+1 504 288 8349",
    "sg:postcode":"70124",
    "sg:province":"LA",
    "sg:tags":[
        "costume",
        "mfg"
    ],
    "wof:name":"Shannon M Prince LLC",
    "wof:placetype":"venue"
},
  "geometry": {"coordinates":[-90.10009599999999,30.020592],"type":"Point"}
}