{
  "type": "Feature",
  "properties": {
    "addr:full":"3079 Government St Baton Rouge LA 70806",
    "addr:housenumber":"3079",
    "addr:postcode":"70806",
    "addr:street":"Government St",
    "iso:country":"US",
    "sg:address":"3079 Government St",
    "sg:city":"Baton Rouge",
    "sg:classifiers":[
        {
            "category":"Retail",
            "subcategory":"Auto Repair",
            "type":"Services"
        }
    ],
    "sg:phone":"+1 225 336 0201",
    "sg:postcode":"70806",
    "sg:province":"LA",
    "sg:tags":[
        "general"
    ],
    "wof:name":"Expert Car Care",
    "wof:placetype":"venue"
},
  "geometry": {"coordinates":[-91.157939,30.444157],"type":"Point"}
}