{
  "type": "Feature",
  "properties": {
    "addr:full":"4275 Government St Baton Rouge LA 70806",
    "addr:housenumber":"4275",
    "addr:postcode":"70806",
    "addr:street":"Government St",
    "iso:country":"US",
    "sg:address":"4275 Government St",
    "sg:city":"Baton Rouge",
    "sg:classifiers":[
        {
            "category":"Insurance",
            "subcategory":"Insurance Agent",
            "type":"Services"
        }
    ],
    "sg:phone":"+1 225 383 0682",
    "sg:postcode":"70806",
    "sg:province":"LA",
    "wof:name":"Fourrier Insurance",
    "wof:placetype":"venue"
},
  "geometry": {"coordinates":[-91.14602600000001,30.444435],"type":"Point"}
}