{
  "type": "Feature",
  "properties": {
    "iso:country":"US",
    "sg:address":"1004 Surrey St",
    "sg:city":"Lafayette",
    "sg:classifiers":[
        {
            "category":"Retail",
            "subcategory":"Funeral Services",
            "type":"Services"
        }
    ],
    "sg:phone":"+1 337 234 1356",
    "sg:postcode":"70501",
    "sg:province":"LA",
    "sg:tags":[
        "director"
    ],
    "wof:name":"Henry G Raphael Inc",
    "wof:placetype":"venue"
},
  "geometry": {"coordinates":[-91.999567,30.22457],"type":"Point"}
}