{
  "type": "Feature",
  "properties": {
    "addr:full":"811 N Alexander Ave Gonzales LA 70737",
    "addr:housenumber":"811",
    "addr:postcode":"70737",
    "addr:street":"N Alexander Ave",
    "iso:country":"US",
    "sg:address":"811 N Alexander Ave",
    "sg:city":"Gonzales",
    "sg:classifiers":[
        {
            "category":"Shopping",
            "subcategory":"Department Store",
            "type":"Retail Goods"
        }
    ],
    "sg:phone":"+1 225 791 5845",
    "sg:postcode":"70737",
    "sg:province":"LA",
    "sg:tags":[
        "shop"
    ],
    "wof:name":"Discount Auto Parts",
    "wof:placetype":"venue"
},
  "geometry": {"coordinates":[-90.919883,30.239018],"type":"Point"}
}