{
  "type": "Feature",
  "properties": {
    "iso:country":"US",
    "sg:address":"88 Norton Ave",
    "sg:city":"Arabi",
    "sg:classifiers":[
        {
            "category":"Organizations",
            "subcategory":"Religious Organization",
            "type":"Services"
        }
    ],
    "sg:phone":"+1 504 278 0113",
    "sg:postcode":"70032",
    "sg:province":"LA",
    "sg:tags":[
        "church"
    ],
    "wof:name":"Freedom Fellowship Assembly",
    "wof:placetype":"venue"
},
  "geometry": {"coordinates":[-89.994007,29.952079],"type":"Point"}
}