{
  "type": "Feature",
  "properties": {
    "iso:country":"US",
    "sg:address":"2824 Brentwood Dr",
    "sg:city":"Baton Rouge",
    "sg:classifiers":[
        {
            "category":"Professional",
            "subcategory":"Business Services",
            "type":"Services"
        }
    ],
    "sg:phone":"+1 225 926 4005",
    "sg:postcode":"70809",
    "sg:province":"LA",
    "wof:name":"Decorating Den Interiors",
    "wof:placetype":"venue"
},
  "geometry": {"coordinates":[-91.09738299999999,30.423572],"type":"Point"}
}