{
  "type": "Feature",
  "properties": {
    "iso:country":"US",
    "sg:address":"1102 S 5th St",
    "sg:city":"Leesville",
    "sg:classifiers":[
        {
            "category":"Building & Trades",
            "subcategory":"Construction",
            "type":"Services"
        }
    ],
    "sg:phone":"+1 337 238 3399",
    "sg:postcode":"71446",
    "sg:province":"LA",
    "sg:tags":[
        "industrial",
        "general",
        "tile",
        "warehouse",
        "contractor",
        "dealer"
    ],
    "wof:name":"The Tile Shop",
    "wof:placetype":"venue"
},
  "geometry": {"coordinates":[-93.265327,31.134088],"type":"Point"}
}