{
  "type": "Feature",
  "properties": {
    "iso:country":"US",
    "sg:address":"4709 Bruce St",
    "sg:city":"Bossier City",
    "sg:classifiers":[
        {
            "category":"Building & Trades",
            "subcategory":"Construction",
            "type":"Services"
        }
    ],
    "sg:phone":"+1 318 746 0556",
    "sg:postcode":"71111",
    "sg:province":"LA",
    "sg:tags":[
        "home",
        "builder"
    ],
    "wof:name":"Larry Higgins Construction Inc",
    "wof:placetype":"venue"
},
  "geometry": {"coordinates":[-93.66837700000001,32.53881],"type":"Point"}
}