{
  "type": "Feature",
  "properties": {
    "iso:country":"US",
    "sg:address":"270 Carter Rd",
    "sg:city":"Downsville",
    "sg:classifiers":[
        {
            "category":"Professional",
            "subcategory":"Management & Consulting",
            "type":"Services"
        }
    ],
    "sg:phone":"+1 318 245 2312",
    "sg:postcode":"71234",
    "sg:province":"LA",
    "sg:tags":[
        "consultant",
        "hospital",
        "health"
    ],
    "wof:name":"Mariah Consulting Inc",
    "wof:placetype":"venue"
},
  "geometry": {"coordinates":[-92.31295,32.685235],"type":"Point"}
}