{
  "type": "Feature",
  "properties": {
    "addr:full":"18002 Old Barker Rd Covington LA 70435",
    "addr:housenumber":"18002",
    "addr:postcode":"70435",
    "addr:street":"Old Barker Rd",
    "iso:country":"US",
    "sg:address":"18002 Old Barker Rd",
    "sg:city":"Covington",
    "sg:classifiers":[
        {
            "category":"Professional",
            "subcategory":"Detective & Security Services",
            "type":"Services"
        }
    ],
    "sg:phone":"+1 985 892 6297",
    "sg:postcode":"70435",
    "sg:province":"LA",
    "sg:tags":[
        "car"
    ],
    "wof:name":"North Shore Investigation Corp",
    "wof:placetype":"venue"
},
  "geometry": {"coordinates":[-90.108942,30.587022],"type":"Point"}
}