{
  "type": "Feature",
  "properties": {
    "iso:country":"US",
    "sg:address":"111 Deer Ln",
    "sg:city":"Mansfield",
    "sg:classifiers":[
        {
            "category":"Home & Garden",
            "subcategory":"Furniture",
            "type":"Retail Goods"
        }
    ],
    "sg:phone":"+1 318 872 6171",
    "sg:postcode":"71052",
    "sg:province":"LA",
    "wof:name":"Ivan Smith Furniture",
    "wof:placetype":"venue"
},
  "geometry": {"coordinates":[-93.680594,32.037566],"type":"Point"}
}