{
  "type": "Feature",
  "properties": {
    "iso:country":"US",
    "sg:address":"729 Saint Louis St",
    "sg:city":"New Orleans",
    "sg:classifiers":[
        {
            "category":"Shopping",
            "subcategory":"Tobacco",
            "type":"Retail Goods"
        }
    ],
    "sg:phone":"+1 504 586 0994",
    "sg:postcode":"70130",
    "sg:province":"LA",
    "sg:tags":[
        "cigarette",
        "cigar",
        "dealer"
    ],
    "wof:name":"Jai Bawani",
    "wof:placetype":"venue"
},
  "geometry": {"coordinates":[-90.066774,29.9569],"type":"Point"}
}