{
  "type": "Feature",
  "properties": {
    "iso:country":"US",
    "sg:address":"11960 Bricksome Ave",
    "sg:city":"Baton Rouge",
    "sg:classifiers":[
        {
            "category":"Professional",
            "type":"Services"
        }
    ],
    "sg:phone":"+1 225 292 1165",
    "sg:postcode":"70816",
    "sg:province":"LA",
    "sg:tags":[
        "establishment"
    ],
    "wof:name":"Geo Logistics Americas Inc",
    "wof:placetype":"venue"
},
  "geometry": {"coordinates":[-91.048891,30.425953],"type":"Point"}
}