{
  "type": "Feature",
  "properties": {
    "iso:country":"US",
    "sg:address":"17497 Old Jefferson Hwy",
    "sg:city":"Prairieville",
    "sg:classifiers":[
        {
            "category":"Health Services",
            "subcategory":"Doctor",
            "type":"Services"
        }
    ],
    "sg:phone":"+1 225 673 9600",
    "sg:postcode":"70769",
    "sg:province":"LA",
    "sg:tags":[
        "dentist"
    ],
    "wof:name":"Robert L Delarosa DDS",
    "wof:placetype":"venue"
},
  "geometry": {"coordinates":[-90.976258,30.320725],"type":"Point"}
}