{
  "type": "Feature",
  "properties": {
    "iso:country":"US",
    "sg:address":"4630 Wilson Ave",
    "sg:city":"New Orleans",
    "sg:classifiers":[
        {
            "category":"Building & Trades",
            "subcategory":"Construction",
            "type":"Services"
        }
    ],
    "sg:phone":"+1 504 218 5269",
    "sg:postcode":"70126",
    "sg:province":"LA",
    "sg:tags":[
        "contractor"
    ],
    "sg:website":"www.dapremontconstruction.com",
    "wof:name":"Dapremont Construction",
    "wof:placetype":"venue"
},
  "geometry": {"coordinates":[-89.999293,30.017256],"type":"Point"}
}