{
  "type": "Feature",
  "properties": {
    "addr:full":"3809 Ryan St Lake Charles LA 70605",
    "addr:housenumber":"3809",
    "addr:postcode":"70605",
    "addr:street":"Ryan St",
    "iso:country":"US",
    "sg:address":"3809 Ryan St",
    "sg:city":"Lake Charles",
    "sg:classifiers":[
        {
            "category":"Organizations",
            "subcategory":"Religious Organization",
            "type":"Services"
        }
    ],
    "sg:phone":"+1 337 477 8463",
    "sg:postcode":"70605",
    "sg:province":"LA",
    "wof:name":"Beth Mssiah Mssnic Cngregation",
    "wof:placetype":"venue"
},
  "geometry": {"coordinates":[-93.218515,30.188154],"type":"Point"}
}