{
  "type": "Feature",
  "properties": {
    "iso:country":"US",
    "sg:address":"11732 Plank Rd",
    "sg:city":"Baton Rouge",
    "sg:classifiers":[
        {
            "category":"Personal",
            "subcategory":"Beauty Salon",
            "type":"Services"
        }
    ],
    "sg:phone":"+1 225 775 1718",
    "sg:postcode":"70811",
    "sg:province":"LA",
    "wof:name":"Pat's Beauty Salon & Braids",
    "wof:placetype":"venue"
},
  "geometry": {"coordinates":[-91.13506700000001,30.552997],"type":"Point"}
}