{
  "type": "Feature",
  "properties": {
    "iso:country":"US",
    "sg:address":"57360 Cpl Herman Brown Jr St",
    "sg:city":"White Castle",
    "sg:classifiers":[
        {
            "category":"Organizations",
            "subcategory":"Religious Organization",
            "type":"Services"
        }
    ],
    "sg:phone":"+1 225 545 8309",
    "sg:postcode":"70788",
    "sg:province":"LA",
    "wof:name":"Word of Truth New Life Center Inc",
    "wof:placetype":"venue"
},
  "geometry": {"coordinates":[-91.186274,30.210324],"type":"Point"}
}