{
  "type": "Feature",
  "properties": {
    "iso:country":"US",
    "sg:address":"3768 Drusilla Dr",
    "sg:city":"Baton Rouge",
    "sg:classifiers":[
        {
            "category":"Wholesale",
            "subcategory":"Plants",
            "type":"Manufacturing & Wholesale Goods"
        }
    ],
    "sg:phone":"+1 225 927 1140",
    "sg:postcode":"70809",
    "sg:province":"LA",
    "sg:tags":[
        "florist"
    ],
    "wof:name":"Gene's Enterprises",
    "wof:placetype":"venue"
},
  "geometry": {"coordinates":[-91.08987999999999,30.417171],"type":"Point"}
}