{
  "type": "Feature",
  "properties": {
    "addr:full":"2811 S Union St Opelousas LA 70570",
    "addr:housenumber":"2811",
    "addr:postcode":"70570",
    "addr:street":"S Union St",
    "iso:country":"US",
    "sg:address":"2811 S Union St",
    "sg:city":"Opelousas",
    "sg:classifiers":[
        {
            "category":"Restaurant",
            "type":"Food & Drink"
        }
    ],
    "sg:phone":"+1 337 826 0404",
    "sg:postcode":"70570",
    "sg:province":"LA",
    "wof:name":"Checkerboard Restaurants",
    "wof:placetype":"venue"
},
  "geometry": {"coordinates":[-92.08751599999999,30.500998],"type":"Point"}
}