{
  "type": "Feature",
  "properties": {
    "iso:country":"US",
    "sg:address":"1514 Doctors Dr",
    "sg:city":"Bossier City",
    "sg:classifiers":[
        {
            "category":"Health Services",
            "subcategory":"Doctor",
            "type":"Services"
        }
    ],
    "sg:phone":"+1 318 742 3996",
    "sg:postcode":"71111",
    "sg:province":"LA",
    "sg:tags":[
        "physician",
        "surgeon"
    ],
    "wof:name":"Chandler Family Practice",
    "wof:placetype":"venue"
},
  "geometry": {"coordinates":[-93.710241,32.53626],"type":"Point"}
}