{
  "type": "Feature",
  "properties": {
    "iso:country":"US",
    "sg:address":"333 W Main St",
    "sg:city":"Thibodaux",
    "sg:classifiers":[
        {
            "category":"Professional",
            "subcategory":"Employment Agencies",
            "type":"Services"
        }
    ],
    "sg:phone":"+1 985 873 6850",
    "sg:postcode":"70301",
    "sg:province":"LA",
    "sg:tags":[
        "opportunity"
    ],
    "wof:name":"Tpcg LA Jet/Jtpa Job Search",
    "wof:placetype":"venue"
},
  "geometry": {"coordinates":[-90.815825,29.770049],"type":"Point"}
}