{
  "type": "Feature",
  "properties": {
    "iso:country":"US",
    "sg:address":"1723 Paktank Rd",
    "sg:city":"Sulphur",
    "sg:classifiers":[
        {
            "category":"Manufacturing",
            "subcategory":"Retail Goods",
            "type":"Manufacturing & Wholesale Goods"
        }
    ],
    "sg:phone":"+1 337 583 3200",
    "sg:postcode":"70665",
    "sg:province":"LA",
    "sg:tags":[
        "manufacturer"
    ],
    "wof:name":"Lake Charles Calcine Plant",
    "wof:placetype":"venue"
},
  "geometry": {"coordinates":[-93.34177099999999,30.149019],"type":"Point"}
}