{
  "type": "Feature",
  "properties": {
    "iso:country":"US",
    "sg:address":"222 Tate Rd",
    "sg:city":"Denham Springs",
    "sg:classifiers":[
        {
            "category":"Professional",
            "subcategory":"Accounting & Tax Preparation",
            "type":"Services"
        }
    ],
    "sg:phone":"+1 225 791 2135",
    "sg:postcode":"70726",
    "sg:province":"LA",
    "sg:tags":[
        "return",
        "filing"
    ],
    "wof:name":"Louisiana Taxmasters",
    "wof:placetype":"venue"
},
  "geometry": {"coordinates":[-90.953474,30.466703],"type":"Point"}
}