{
  "type": "Feature",
  "properties": {
    "iso:country":"US",
    "sg:address":"1512 S College Rd",
    "sg:city":"Lafayette",
    "sg:classifiers":[
        {
            "category":"Personal",
            "subcategory":"Barber",
            "type":"Services"
        }
    ],
    "sg:phone":"+1 337 232 4868",
    "sg:postcode":"70503",
    "sg:province":"LA",
    "wof:name":"Ike's Barber Shop",
    "wof:placetype":"venue"
},
  "geometry": {"coordinates":[-92.017191,30.201776],"type":"Point"}
}