{
  "type": "Feature",
  "properties": {
    "iso:country":"US",
    "sg:address":"9091 Ellerbe Rd",
    "sg:city":"Shreveport",
    "sg:classifiers":[
        {
            "category":"Home & Garden",
            "subcategory":"Household Appliances",
            "type":"Retail Goods"
        }
    ],
    "sg:phone":"+1 318 868 2828",
    "sg:postcode":"71106",
    "sg:province":"LA",
    "sg:tags":[
        "cleaners",
        "vacuum"
    ],
    "wof:name":"RMAC Enterprises",
    "wof:placetype":"venue"
},
  "geometry": {"coordinates":[-93.73836799999999,32.411328],"type":"Point"}
}