{
  "type": "Feature",
  "properties": {
    "iso:country":"US",
    "sg:address":"1014 Creswell Ave",
    "sg:city":"Shreveport",
    "sg:classifiers":[
        {
            "category":"Wholesale",
            "subcategory":"Medical Equipment & Supplies",
            "type":"Manufacturing & Wholesale Goods"
        }
    ],
    "sg:phone":"+1 318 425 7432",
    "sg:postcode":"71101",
    "sg:province":"LA",
    "sg:tags":[
        "optical"
    ],
    "wof:name":"Tri State Optical Co",
    "wof:placetype":"venue"
},
  "geometry": {"coordinates":[-93.74169999999999,32.50193],"type":"Point"}
}