{
  "type": "Feature",
  "properties": {
    "iso:country":"US",
    "sg:address":"800 W Laurel Ave",
    "sg:city":"Eunice",
    "sg:classifiers":[
        {
            "category":"Manufacturing",
            "subcategory":"Printing",
            "type":"Manufacturing & Wholesale Goods"
        }
    ],
    "sg:phone":"+1 337 457 2105",
    "sg:postcode":"70535",
    "sg:province":"LA",
    "sg:tags":[
        "printer"
    ],
    "wof:name":"Johnson's Printing Office",
    "wof:placetype":"venue"
},
  "geometry": {"coordinates":[-92.42440000000001,30.494881],"type":"Point"}
}