{
  "type": "Feature",
  "properties": {
    "addr:full":"5101 Belle Terre Rd Marrero LA 70072",
    "addr:housenumber":"5101",
    "addr:postcode":"70072",
    "addr:street":"Belle Terre Rd Marrero",
    "iso:country":"US",
    "sg:address":"5101 Belle Terre Rd",
    "sg:city":"Marrero",
    "sg:classifiers":[
        {
            "category":"Building & Trades",
            "subcategory":"Plumbing",
            "type":"Services"
        }
    ],
    "sg:phone":"+1 504 347 4947",
    "sg:postcode":"70072",
    "sg:province":"LA",
    "sg:tags":[
        "conditioning",
        "air",
        "system",
        "contractor"
    ],
    "wof:name":"Walters Air Cond & Heating",
    "wof:placetype":"venue"
},
  "geometry": {"coordinates":[-90.102159,29.878938],"type":"Point"}
}