{
  "type": "Feature",
  "properties": {
    "iso:country":"US",
    "sg:address":"3835 N Teak Ave",
    "sg:city":"New Orleans",
    "sg:classifiers":[
        {
            "category":"Insurance",
            "subcategory":"Insurance Agent",
            "type":"Services"
        }
    ],
    "sg:phone":"+1 504 433 9898",
    "sg:postcode":"70131",
    "sg:province":"LA",
    "wof:name":"Great American Insurance Group",
    "wof:placetype":"venue"
},
  "geometry": {"coordinates":[-90.000449,29.908828],"type":"Point"}
}