{
  "type": "Feature",
  "properties": {
    "addr:full":"1603 E Judge Perez Dr Chalmette LA 70043",
    "addr:housenumber":"1603",
    "addr:postcode":"70043",
    "addr:street":"E Judge Perez Dr Chalmette",
    "iso:country":"US",
    "sg:address":"1603 E Judge Perez Dr",
    "sg:city":"Chalmette",
    "sg:classifiers":[
        {
            "category":"Restaurant",
            "type":"Food & Drink"
        }
    ],
    "sg:phone":"+1 504 279 8955",
    "sg:postcode":"70043",
    "sg:province":"LA",
    "wof:name":"Jakes Bingo Pizza Palace",
    "wof:placetype":"venue"
},
  "geometry": {"coordinates":[-89.94904699999999,29.937794],"type":"Point"}
}