{
  "type": "Feature",
  "properties": {
    "iso:country":"US",
    "sg:address":"69408 Hwy 59",
    "sg:city":"Abita Springs",
    "sg:classifiers":[
        {
            "category":"Building & Trades",
            "subcategory":"Construction",
            "type":"Services"
        }
    ],
    "sg:phone":"+1 985 893 2729",
    "sg:postcode":"70420",
    "sg:province":"LA",
    "sg:tags":[
        "stucco",
        "contractor"
    ],
    "wof:name":"Saba Stucco LLC",
    "wof:placetype":"venue"
},
  "geometry": {"coordinates":[-90.04124400000001,30.444566],"type":"Point"}
}