{
  "type": "Feature",
  "properties": {
    "iso:country":"US",
    "sg:address":"408 Bertrand Dr",
    "sg:city":"Lafayette",
    "sg:classifiers":[
        {
            "category":"Shopping",
            "subcategory":"Clothing, Apparel, & Fashions",
            "type":"Retail Goods"
        }
    ],
    "sg:phone":"+1 337 268 9486",
    "sg:postcode":"70506",
    "sg:province":"LA",
    "sg:tags":[
        "alteration"
    ],
    "wof:name":"Leona's Alterations",
    "wof:placetype":"venue"
},
  "geometry": {"coordinates":[-92.044034,30.210691],"type":"Point"}
}