{
  "type": "Feature",
  "properties": {
    "iso:country":"US",
    "sg:address":"2640 Hodges St",
    "sg:city":"Lake Charles",
    "sg:classifiers":[
        {
            "category":"Personal",
            "subcategory":"Beauty Salon",
            "type":"Services"
        }
    ],
    "sg:phone":"+1 337 436 2455",
    "sg:postcode":"70601",
    "sg:province":"LA",
    "sg:tags":[
        "shop"
    ],
    "wof:name":"Studio Ten",
    "wof:placetype":"venue"
},
  "geometry": {"coordinates":[-93.216099,30.206002],"type":"Point"}
}