{
  "type": "Feature",
  "properties": {
    "iso:country":"US",
    "sg:address":"34641 Grantham College Dr",
    "sg:city":"Slidell",
    "sg:classifiers":[
        {
            "category":"Education",
            "subcategory":"College",
            "type":"Public Place"
        }
    ],
    "sg:phone":"+1 985 649 4191",
    "sg:postcode":"70460",
    "sg:province":"LA",
    "sg:tags":[
        "academic",
        "school"
    ],
    "wof:name":"Grantham University",
    "wof:placetype":"venue"
},
  "geometry": {"coordinates":[-89.810728,30.310244],"type":"Point"}
}