{
  "type": "Feature",
  "properties": {
    "iso:country":"US",
    "sg:address":"312 Estainville Ave",
    "sg:city":"Lafayette",
    "sg:classifiers":[
        {
            "category":"Professional",
            "type":"Services"
        }
    ],
    "sg:phone":"+1 337 235 0732",
    "sg:postcode":"70508",
    "sg:province":"LA",
    "wof:name":"Josh Inc",
    "wof:placetype":"venue"
},
  "geometry": {"coordinates":[-92.01461500000001,30.167529],"type":"Point"}
}