{
  "type": "Feature",
  "properties": {
    "addr:full":"11811 Industriplex Blvd Baton Rouge LA 70809",
    "addr:housenumber":"11811",
    "addr:postcode":"70809",
    "addr:street":"Industriplex Blvd",
    "iso:country":"US",
    "sg:address":"11811 Industriplex Blvd",
    "sg:city":"Baton Rouge",
    "sg:classifiers":[
        {
            "category":"Home & Garden",
            "subcategory":"Household Appliances",
            "type":"Retail Goods"
        }
    ],
    "sg:phone":"+1 225 752 8716",
    "sg:postcode":"70809",
    "sg:province":"LA",
    "sg:tags":[
        "cleaners",
        "vacuum"
    ],
    "wof:name":"PMI",
    "wof:placetype":"venue"
},
  "geometry": {"coordinates":[-91.048057,30.384463],"type":"Point"}
}