{
  "type": "Feature",
  "properties": {
    "addr:full":"2300 Brooklyn Ave Harvey LA 70058",
    "addr:housenumber":"2300",
    "addr:postcode":"70058",
    "addr:street":"Brooklyn Ave",
    "iso:country":"US",
    "sg:address":"2300 Brooklyn Ave",
    "sg:city":"Harvey",
    "sg:classifiers":[
        {
            "category":"Wholesale",
            "subcategory":"Electrical",
            "type":"Manufacturing & Wholesale Goods"
        }
    ],
    "sg:phone":"+1 504 366 3264",
    "sg:postcode":"70058",
    "sg:province":"LA",
    "sg:tags":[
        "control"
    ],
    "wof:name":"Fogarty Eng Sales Co",
    "wof:placetype":"venue"
},
  "geometry": {"coordinates":[-90.058464,29.874786],"type":"Point"}
}