{
  "type": "Feature",
  "properties": {
    "iso:country":"US",
    "sg:address":"4532 W Napoleon Ave",
    "sg:city":"Metairie",
    "sg:classifiers":[
        {
            "category":"Building & Trades",
            "subcategory":"Construction",
            "type":"Services"
        }
    ],
    "sg:phone":"+1 504 738 3445",
    "sg:postcode":"70001",
    "sg:province":"LA",
    "sg:tags":[
        "residential",
        "designer"
    ],
    "wof:name":"Falati Designs LLC",
    "wof:placetype":"venue"
},
  "geometry": {"coordinates":[-90.180589,29.993561],"type":"Point"}
}