{
  "type": "Feature",
  "properties": {
    "iso:country":"US",
    "sg:address":"958 Pastureview Dr",
    "sg:city":"Baton Rouge",
    "sg:classifiers":[
        {
            "category":"Building & Trades",
            "subcategory":"Construction",
            "type":"Services"
        }
    ],
    "sg:phone":"+1 225 769 3793",
    "sg:postcode":"70810",
    "sg:province":"LA",
    "sg:tags":[
        "house",
        "nonresidential"
    ],
    "wof:name":"Persac Construction",
    "wof:placetype":"venue"
},
  "geometry": {"coordinates":[-91.085205,30.358977],"type":"Point"}
}