{
  "type": "Feature",
  "properties": {
    "iso:country":"US",
    "sg:address":"1025 Central Park Dr",
    "sg:city":"Bossier City",
    "sg:classifiers":[
        {
            "category":"Building & Trades",
            "subcategory":"Landscaping Services",
            "type":"Services"
        }
    ],
    "sg:phone":"+1 318 742 5911",
    "sg:postcode":"71112",
    "sg:province":"LA",
    "sg:tags":[
        "landscape",
        "contractor"
    ],
    "wof:name":"Chamberlain's Landscape",
    "wof:placetype":"venue"
},
  "geometry": {"coordinates":[-93.714017,32.511327],"type":"Point"}
}