{
  "type": "Feature",
  "properties": {
    "addr:full":"338 W Prien Lake Rd Lake Charles LA 70601",
    "addr:housenumber":"338",
    "addr:postcode":"70601",
    "addr:street":"W Prien Lake Rd",
    "iso:country":"US",
    "sg:address":"338 W Prien Lake Rd",
    "sg:city":"Lake Charles",
    "sg:classifiers":[
        {
            "category":"Restaurant",
            "type":"Food & Drink"
        }
    ],
    "sg:menulink":"http://www.allmenus.com/la/lake-charles/200487-long-john-silvers/menu/",
    "sg:phone":"+1 337 478 4636",
    "sg:postcode":"70601",
    "sg:province":"LA",
    "sg:tags":[
        "seafood",
        "american"
    ],
    "wof:name":"Long John Silver's",
    "wof:placetype":"venue"
},
  "geometry": {"coordinates":[-93.22383000000001,30.19827],"type":"Point"}
}