{
  "type": "Feature",
  "properties": {
    "iso:country":"US",
    "sg:address":"636 Stratford Dr",
    "sg:city":"New Orleans",
    "sg:classifiers":[
        {
            "category":"Professional",
            "subcategory":"Art Services",
            "type":"Services"
        }
    ],
    "sg:phone":"+1 504 738 6080",
    "sg:postcode":"70123",
    "sg:province":"LA",
    "sg:tags":[
        "commercial",
        "design"
    ],
    "wof:name":"S&S Signs and Graphics",
    "wof:placetype":"venue"
},
  "geometry": {"coordinates":[-90.204121,29.944968],"type":"Point"}
}