{
  "type": "Feature",
  "properties": {
    "addr:full":"1701 N Market St Shreveport LA 71107",
    "addr:housenumber":"1701",
    "addr:postcode":"71107",
    "addr:street":"N Market St",
    "iso:country":"US",
    "sg:address":"1701 N Market St",
    "sg:city":"Shreveport",
    "sg:classifiers":[
        {
            "category":"Banks & Credit Unions",
            "subcategory":"Bank",
            "type":"Services"
        }
    ],
    "sg:phone":"+1 318 227 0675",
    "sg:postcode":"71107",
    "sg:province":"LA",
    "sg:website":"www.bancorpsouth.com",
    "wof:name":"Bancorp South Bank",
    "wof:placetype":"venue"
},
  "geometry": {"coordinates":[-93.776089,32.544106],"type":"Point"}
}