{
  "type": "Feature",
  "properties": {
    "addr:full":"131 US Hwy 65 Tallulah LA 71282",
    "addr:housenumber":"131",
    "addr:postcode":"71282",
    "addr:street":"Us Hwy 65",
    "iso:country":"US",
    "sg:address":"131 US Hwy 65",
    "sg:city":"Tallulah",
    "sg:classifiers":[
        {
            "category":"Restaurant",
            "type":"Food & Drink"
        }
    ],
    "sg:phone":"+1 318 574 3313",
    "sg:postcode":"71282",
    "sg:province":"LA",
    "wof:name":"Mc Donald's",
    "wof:placetype":"venue"
},
  "geometry": {"coordinates":[-91.18688299999999,32.408244],"type":"Point"}
}