{
  "type": "Feature",
  "properties": {
    "iso:country":"US",
    "sg:address":"2847 N Macarthur Dr",
    "sg:city":"Alexandria",
    "sg:classifiers":[
        {
            "category":"Food & Beverages",
            "subcategory":"Specialty",
            "type":"Retail Goods"
        }
    ],
    "sg:phone":"+1 318 448 4808",
    "sg:postcode":"71303",
    "sg:province":"LA",
    "sg:tags":[
        "health",
        "diet"
    ],
    "wof:name":"Rockys Supplement Shop LLC",
    "wof:placetype":"venue"
},
  "geometry": {"coordinates":[-92.47732499999999,31.310452],"type":"Point"}
}