{
  "type": "Feature",
  "properties": {
    "addr:full":"200 N Luke St Lafayette LA 70506",
    "addr:housenumber":"200",
    "addr:postcode":"70506",
    "addr:street":"N Luke St",
    "iso:country":"US",
    "sg:address":"200 N Luke St",
    "sg:city":"Lafayette",
    "sg:classifiers":[
        {
            "category":"Wholesale",
            "subcategory":"Hardware",
            "type":"Manufacturing & Wholesale Goods"
        }
    ],
    "sg:phone":"+1 337 235 9755",
    "sg:postcode":"70506",
    "sg:province":"LA",
    "sg:tags":[
        "refrigerating"
    ],
    "sg:website":"www.beaullieurefrigeration.com",
    "wof:name":"Beaullieu Refrigeration Inc",
    "wof:placetype":"venue"
},
  "geometry": {"coordinates":[-92.06249200000001,30.223777],"type":"Point"}
}