{
  "type": "Feature",
  "properties": {
    "iso:country":"US",
    "sg:address":"6755 Broadacres Rd",
    "sg:city":"Shreveport",
    "sg:classifiers":[
        {
            "category":"Professional",
            "subcategory":"Business Services",
            "type":"Services"
        }
    ],
    "sg:phone":"+1 318 682 4870",
    "sg:postcode":"71129",
    "sg:province":"LA",
    "wof:name":"H&H Motor Sales",
    "wof:placetype":"venue"
},
  "geometry": {"coordinates":[-93.874211,32.443559],"type":"Point"}
}