{
  "type": "Feature",
  "properties": {
    "iso:country":"US",
    "sg:address":"201 N Lasalle St",
    "sg:city":"New Iberia",
    "sg:classifiers":[
        {
            "category":"Retail",
            "subcategory":"Repair Shop",
            "type":"Services"
        }
    ],
    "sg:phone":"+1 337 364 8060",
    "sg:postcode":"70560",
    "sg:province":"LA",
    "sg:tags":[
        "related"
    ],
    "wof:name":"Outboard Repair Svc",
    "wof:placetype":"venue"
},
  "geometry": {"coordinates":[-91.824816,30.015371],"type":"Point"}
}