{
  "type": "Feature",
  "properties": {
    "iso:country":"US",
    "sg:address":"2557 Carey St",
    "sg:city":"Slidell",
    "sg:classifiers":[
        {
            "category":"Retail",
            "subcategory":"Repair Shop",
            "type":"Services"
        }
    ],
    "sg:phone":"+1 985 643 5439",
    "sg:postcode":"70458",
    "sg:province":"LA",
    "sg:tags":[
        "repairing",
        "lawn",
        "mower"
    ],
    "wof:name":"Spiehler's Service",
    "wof:placetype":"venue"
},
  "geometry": {"coordinates":[-89.78380300000001,30.269815],"type":"Point"}
}