{
  "type": "Feature",
  "properties": {
    "iso:country":"US",
    "sg:address":"1020 Marlbrook Dr",
    "sg:city":"Baton Rouge",
    "sg:classifiers":[
        {
            "category":"Education",
            "subcategory":"School",
            "type":"Public Place"
        }
    ],
    "sg:phone":"+1 225 272 3090",
    "sg:postcode":"70815",
    "sg:province":"LA",
    "sg:website":"www.ebrschools.org",
    "wof:name":"Sherwood Middle School",
    "wof:placetype":"venue"
},
  "geometry": {"coordinates":[-91.06250300000001,30.445928],"type":"Point"}
}