{
  "type": "Feature",
  "properties": {
    "addr:full":"329 Iberia St Youngsville LA 70592",
    "addr:housenumber":"329",
    "addr:postcode":"70592",
    "addr:street":"Iberia St",
    "iso:country":"US",
    "sg:address":"329 Iberia St",
    "sg:city":"Youngsville",
    "sg:classifiers":[
        {
            "category":"Health Services",
            "subcategory":"Doctor",
            "type":"Services"
        }
    ],
    "sg:phone":"+1 337 856 7268",
    "sg:postcode":"70592",
    "sg:province":"LA",
    "sg:tags":[
        "surgeon",
        "oral"
    ],
    "sg:website":"www.thomasandharmonfamilydentist...",
    "wof:name":"Harmon E Kevin DDS",
    "wof:placetype":"venue"
},
  "geometry": {"coordinates":[-91.990898,30.1021],"type":"Point"}
}