{
  "type": "Feature",
  "properties": {
    "addr:full":"128 5th St Mamou LA 70554",
    "addr:housenumber":"128",
    "addr:postcode":"70554",
    "addr:street":"5Th St",
    "iso:country":"US",
    "sg:address":"128 5th St",
    "sg:city":"Mamou",
    "sg:classifiers":[
        {
            "category":"Personal",
            "subcategory":"Tanning Parlor",
            "type":"Services"
        },
        {
            "category":"Personal",
            "type":"Services"
        }
    ],
    "sg:phone":"+1 337 468 3375",
    "sg:postcode":"70554",
    "sg:province":"LA",
    "sg:tags":[
        "salon"
    ],
    "wof:name":"Tina's Tanning Zone",
    "wof:placetype":"venue"
},
  "geometry": {"coordinates":[-92.420627,30.627603],"type":"Point"}
}