{
  "type": "Feature",
  "properties": {
    "addr:full":"298 Fisher Robeline LA 71469",
    "addr:housenumber":"298",
    "addr:postcode":"71469",
    "addr:street":"Fisher",
    "iso:country":"US",
    "sg:address":"298 Fisher",
    "sg:city":"Robeline",
    "sg:classifiers":[
        {
            "category":"Manufacturing",
            "subcategory":"Apparel",
            "type":"Manufacturing & Wholesale Goods"
        }
    ],
    "sg:phone":"+1 318 472 8953",
    "sg:postcode":"71469",
    "sg:province":"LA",
    "wof:name":"Little Creations",
    "wof:placetype":"venue"
},
  "geometry": {"coordinates":[-93.32132300000001,31.672179],"type":"Point"}
}