{
  "type": "Feature",
  "properties": {
    "iso:country":"US",
    "sg:address":"517 Benton Rd",
    "sg:city":"Bossier City",
    "sg:classifiers":[
        {
            "category":"Autos & Motor Vehicles",
            "subcategory":"Automobile Sales",
            "type":"Retail Goods"
        }
    ],
    "sg:phone":"+1 318 746 7517",
    "sg:postcode":"71111",
    "sg:province":"LA",
    "sg:tags":[
        "car",
        "dealer"
    ],
    "wof:name":"Elkins KIA",
    "wof:placetype":"venue"
},
  "geometry": {"coordinates":[-93.71627100000001,32.520578],"type":"Point"}
}