{
  "type": "Feature",
  "properties": {
    "addr:full":"125 W Main St New Iberia LA 70560",
    "addr:housenumber":"125",
    "addr:postcode":"70560",
    "addr:street":"W Main St",
    "iso:country":"US",
    "sg:address":"125 W Main St",
    "sg:city":"New Iberia",
    "sg:classifiers":[
        {
            "category":"Shopping",
            "subcategory":"Florist",
            "type":"Retail Goods"
        }
    ],
    "sg:phone":"+1 337 364 3686",
    "sg:postcode":"70560",
    "sg:province":"LA",
    "wof:name":"Luci Blooms Flowers & Gifts",
    "wof:placetype":"venue"
},
  "geometry": {"coordinates":[-91.819073,30.006636],"type":"Point"}
}