{
  "type": "Feature",
  "properties": {
    "iso:country":"US",
    "sg:address":"106 Rosewood Dr",
    "sg:city":"Houma",
    "sg:classifiers":[
        {
            "category":"Professional",
            "subcategory":"Business Services",
            "type":"Services"
        }
    ],
    "sg:phone":"+1 985 872 5493",
    "sg:postcode":"70360",
    "sg:province":"LA",
    "wof:name":"Triple J LLC",
    "wof:placetype":"venue"
},
  "geometry": {"coordinates":[-90.736761,29.575134],"type":"Point"}
}