{
  "type": "Feature",
  "properties": {
    "iso:country":"US",
    "sg:address":"4643 Camelot Dr",
    "sg:city":"New Orleans",
    "sg:classifiers":[
        {
            "category":"Professional",
            "type":"Services"
        }
    ],
    "sg:phone":"+1 504 242 1257",
    "sg:postcode":"70127",
    "sg:province":"LA",
    "wof:name":"Happy Kids R Us LLC",
    "wof:placetype":"venue"
},
  "geometry": {"coordinates":[-89.982288,30.021168],"type":"Point"}
}