{
  "type": "Feature",
  "properties": {
    "iso:country":"US",
    "sg:address":"800 Bonin Rd",
    "sg:city":"Lafayette",
    "sg:classifiers":[
        {
            "category":"Real Estate",
            "subcategory":"Real Estate Operator",
            "type":"Services"
        }
    ],
    "sg:phone":"+1 337 837 1907",
    "sg:postcode":"70508",
    "sg:province":"LA",
    "sg:tags":[
        "mobile",
        "home",
        "community"
    ],
    "wof:name":"Norbert's Golden Gate Mobile",
    "wof:placetype":"venue"
},
  "geometry": {"coordinates":[-92.00651000000001,30.152044],"type":"Point"}
}