{
  "type": "Feature",
  "properties": {
    "iso:country":"US",
    "sg:address":"921 Lafourche St",
    "sg:city":"Donaldsonville",
    "sg:phone":"+1 225 473 1300",
    "sg:postcode":"70346",
    "sg:province":"LA",
    "sg:tags":[
        "gas"
    ],
    "wof:name":"Thibaut Oil Co",
    "wof:placetype":"venue"
},
  "geometry": {"coordinates":[-90.993416,30.0982],"type":"Point"}
}