{
  "type": "Feature",
  "properties": {
    "iso:country":"US",
    "sg:address":"1221 Amelia St",
    "sg:city":"Gretna",
    "sg:classifiers":[
        {
            "category":"Health Services",
            "subcategory":"Clinic",
            "type":"Services"
        }
    ],
    "sg:phone":"+1 504 368 9188",
    "sg:postcode":"70053",
    "sg:province":"LA",
    "wof:name":"Adults & Child Health Imprvmt",
    "wof:placetype":"venue"
},
  "geometry": {"coordinates":[-90.055345,29.911106],"type":"Point"}
}