{
  "type": "Feature",
  "properties": {
    "addr:full":"3226 Broad Magnolia Ct Baton Rouge LA 70810",
    "addr:housenumber":"3226",
    "addr:postcode":"70810",
    "addr:street":"Broad Magnolia Ct",
    "iso:country":"US",
    "sg:address":"3226 Broad Magnolia Ct",
    "sg:city":"Baton Rouge",
    "sg:classifiers":[
        {
            "category":"Professional",
            "subcategory":"Art Services",
            "type":"Services"
        }
    ],
    "sg:phone":"+1 225 761 4800",
    "sg:postcode":"70810",
    "sg:province":"LA",
    "sg:tags":[
        "graphic",
        "designer"
    ],
    "sg:website":"www.accardodesign.com",
    "wof:name":"Accardo Design LLC",
    "wof:placetype":"venue"
},
  "geometry": {"coordinates":[-91.124211,30.31713],"type":"Point"}
}