{
  "type": "Feature",
  "properties": {
    "iso:country":"US",
    "sg:address":"13623 Hooper Rd",
    "sg:city":"Baton Rouge",
    "sg:classifiers":[
        {
            "category":"Shopping",
            "subcategory":"Gifts & Souvenirs",
            "type":"Retail Goods"
        }
    ],
    "sg:phone":"+1 225 261 2651",
    "sg:postcode":"70818",
    "sg:province":"LA",
    "sg:tags":[
        "shop"
    ],
    "wof:name":"Uniquely Yours Fine Gifts",
    "wof:placetype":"venue"
},
  "geometry": {"coordinates":[-91.03601399999999,30.554735],"type":"Point"}
}