{
  "type": "Feature",
  "properties": {
    "iso:country":"US",
    "sg:address":"221 W Tish Dr",
    "sg:city":"Westwego",
    "sg:classifiers":[
        {
            "category":"Building & Trades",
            "subcategory":"Pest Control",
            "type":"Services"
        }
    ],
    "sg:phone":"+1 504 436 1660",
    "sg:postcode":"70094",
    "sg:province":"LA",
    "sg:tags":[
        "disinfecting"
    ],
    "wof:name":"A J's Pest Control",
    "wof:placetype":"venue"
},
  "geometry": {"coordinates":[-90.207047,29.910408],"type":"Point"}
}