{
  "type": "Feature",
  "properties": {
    "addr:full":"506 S 5th St Monroe LA 71202",
    "addr:housenumber":"506",
    "addr:postcode":"71202",
    "addr:street":"S 5Th St",
    "iso:country":"US",
    "sg:address":"506 S 5th St",
    "sg:city":"Monroe",
    "sg:classifiers":[
        {
            "category":"Health Services",
            "subcategory":"Clinic",
            "type":"Services"
        }
    ],
    "sg:phone":"+1 318 398 9152",
    "sg:postcode":"71202",
    "sg:province":"LA",
    "sg:tags":[
        "home"
    ],
    "wof:name":"Gulf South Health Care",
    "wof:placetype":"venue"
},
  "geometry": {"coordinates":[-92.105717,32.495118],"type":"Point"}
}