{
  "type": "Feature",
  "properties": {
    "iso:country":"US",
    "sg:address":"2916 Fairchild Dr",
    "sg:city":"New Iberia",
    "sg:classifiers":[
        {
            "category":"Mining & Drilling",
            "type":"Manufacturing & Wholesale Goods"
        }
    ],
    "sg:phone":"+1 337 364 5409",
    "sg:postcode":"70560",
    "sg:province":"LA",
    "sg:tags":[
        "field",
        "oil"
    ],
    "wof:name":"Geophysical Research Corp",
    "wof:placetype":"venue"
},
  "geometry": {"coordinates":[-91.841016,29.968443],"type":"Point"}
}