{
  "type": "Feature",
  "properties": {
    "addr:full":"1615 Barton Dr Shreveport LA 71107",
    "addr:housenumber":"1615",
    "addr:postcode":"71107",
    "addr:street":"Barton Dr",
    "iso:country":"US",
    "sg:address":"1615 Barton Dr",
    "sg:city":"Shreveport",
    "sg:classifiers":[
        {
            "category":"Manufacturing",
            "subcategory":"Signs",
            "type":"Manufacturing & Wholesale Goods"
        }
    ],
    "sg:phone":"+1 318 425 7626",
    "sg:postcode":"71107",
    "sg:province":"LA",
    "wof:name":"Shreveport Neon Signs",
    "wof:placetype":"venue"
},
  "geometry": {"coordinates":[-93.775009,32.53807],"type":"Point"}
}