{
  "type": "Feature",
  "properties": {
    "addr:full":"4301 S Claiborne Ave New Orleans LA 70125",
    "addr:housenumber":"4301",
    "addr:postcode":"70125",
    "addr:street":"S Claiborne Ave",
    "iso:country":"US",
    "sg:address":"4301 S Claiborne Ave",
    "sg:city":"New Orleans",
    "sg:classifiers":[
        {
            "category":"Autos & Motor Vehicles",
            "subcategory":"Auto Supplies",
            "type":"Retail Goods"
        }
    ],
    "sg:phone":"+1 504 821 8262",
    "sg:postcode":"70125",
    "sg:province":"LA",
    "sg:tags":[
        "automobile",
        "stereo",
        "radio"
    ],
    "wof:name":"Rhythms Car Audio & Alarms",
    "wof:placetype":"venue"
},
  "geometry": {"coordinates":[-90.10310200000001,29.940431],"type":"Point"}
}