{
  "type": "Feature",
  "properties": {
    "addr:full":"7227 Lapin Ln Iowa LA 70647",
    "addr:postcode":"7227;70647",
    "addr:street":"Lapin Ln",
    "iso:country":"US",
    "sg:address":"7227 Lapin Ln",
    "sg:city":"Iowa",
    "sg:classifiers":[
        {
            "category":"Organizations",
            "subcategory":"Religious Organization",
            "type":"Services"
        }
    ],
    "sg:phone":"+1 337 582 6653",
    "sg:postcode":"70647",
    "sg:province":"LA",
    "wof:name":"Matthew J Church",
    "wof:placetype":"venue"
},
  "geometry": {"coordinates":[-93.050872,30.292751],"type":"Point"}
}