{
  "type": "Feature",
  "properties": {
    "addr:full":"145 Elk Pl New Orleans LA 70112",
    "addr:housenumber":"145",
    "addr:postcode":"70112",
    "addr:street":"Elk Pl",
    "iso:country":"US",
    "sg:address":"145 Elk Pl",
    "sg:city":"New Orleans",
    "sg:classifiers":[
        {
            "category":"Shopping",
            "subcategory":"Pharmacy",
            "type":"Retail Goods"
        }
    ],
    "sg:phone":"+1 504 525 5322",
    "sg:postcode":"70112",
    "sg:province":"LA",
    "wof:name":"Walgreens",
    "wof:placetype":"venue"
},
  "geometry": {"coordinates":[-90.07488600000001,29.954778],"type":"Point"}
}