{
  "type": "Feature",
  "properties": {
    "iso:country":"US",
    "sg:address":"148 Airport Dr",
    "sg:city":"Shreveport",
    "sg:classifiers":[
        {
            "category":"Wholesale",
            "subcategory":"Hardware",
            "type":"Manufacturing & Wholesale Goods"
        }
    ],
    "sg:phone":"+1 318 424 0186",
    "sg:postcode":"71107",
    "sg:province":"LA",
    "sg:tags":[
        "nut",
        "bolt"
    ],
    "wof:name":"Interstate Industries Inc",
    "wof:placetype":"venue"
},
  "geometry": {"coordinates":[-93.752619,32.521402],"type":"Point"}
}