{
  "type": "Feature",
  "properties": {
    "iso:country":"US",
    "sg:address":"118 Railroad Ave",
    "sg:city":"Donaldsonville",
    "sg:classifiers":[
        {
            "category":"Professional",
            "subcategory":"Management & Consulting",
            "type":"Services"
        }
    ],
    "sg:phone":"+1 225 473 1638",
    "sg:postcode":"70346",
    "sg:province":"LA",
    "sg:tags":[
        "fuel"
    ],
    "wof:name":"Ourso Management Co Inc",
    "wof:placetype":"venue"
},
  "geometry": {"coordinates":[-90.987188,30.106092],"type":"Point"}
}