{
  "type": "Feature",
  "properties": {
    "iso:country":"US",
    "sg:address":"245 Carrollton Ave",
    "sg:city":"Shreveport",
    "sg:classifiers":[
        {
            "category":"Professional",
            "subcategory":"Advertising",
            "type":"Services"
        }
    ],
    "sg:phone":"+1 318 861 2305",
    "sg:postcode":"71105",
    "sg:province":"LA",
    "sg:tags":[
        "mailing",
        "shipping"
    ],
    "wof:name":"T & R Shipping",
    "wof:placetype":"venue"
},
  "geometry": {"coordinates":[-93.714288,32.464436],"type":"Point"}
}