{
  "type": "Feature",
  "properties": {
    "iso:country":"US",
    "sg:address":"1422 Monroe St",
    "sg:city":"Mandeville",
    "sg:classifiers":[
        {
            "category":"Professional",
            "subcategory":"Research",
            "type":"Services"
        }
    ],
    "sg:phone":"+1 985 674 5338",
    "sg:postcode":"70448",
    "sg:province":"LA",
    "sg:tags":[
        "environmental",
        "ecological"
    ],
    "wof:name":"Thompson Environmental Cnsltng",
    "wof:placetype":"venue"
},
  "geometry": {"coordinates":[-90.055554,30.353248],"type":"Point"}
}