{
  "type": "Feature",
  "properties": {
    "addr:full":"320 N Carrollton Ave New Orleans LA 70119",
    "addr:housenumber":"320",
    "addr:postcode":"70119",
    "addr:street":"N Carrollton Ave",
    "iso:country":"US",
    "sg:address":"320 N Carrollton Ave",
    "sg:city":"New Orleans",
    "sg:classifiers":[
        {
            "category":"Government",
            "subcategory":"Office",
            "type":"Public Place"
        }
    ],
    "sg:phone":"+1 504 483 4000",
    "sg:postcode":"70119",
    "sg:province":"LA",
    "sg:tags":[
        "state",
        "inspection"
    ],
    "wof:name":"Racing Commission",
    "wof:placetype":"venue"
},
  "geometry": {"coordinates":[-90.09854199999999,29.976193],"type":"Point"}
}