{
  "type": "Feature",
  "properties": {
    "addr:full":"100 Westmark Blvd Lafayette LA 70506",
    "addr:housenumber":"100",
    "addr:postcode":"70506",
    "addr:street":"Westmark Blvd",
    "iso:country":"US",
    "sg:address":"100 Westmark Blvd",
    "sg:city":"Lafayette",
    "sg:classifiers":[
        {
            "category":"Health Services",
            "subcategory":"Health Practitioner",
            "type":"Services"
        }
    ],
    "sg:phone":"+1 337 989 9745",
    "sg:postcode":"70506",
    "sg:province":"LA",
    "sg:tags":[
        "pathologist",
        "speech"
    ],
    "wof:name":"Speech Language Specialists",
    "wof:placetype":"venue"
},
  "geometry": {"coordinates":[-92.07016299999999,30.182425],"type":"Point"}
}