{
  "type": "Feature",
  "properties": {
    "addr:full":"3314 Front St Winnsboro LA 71295",
    "addr:housenumber":"3314",
    "addr:postcode":"71295",
    "addr:street":"Front St",
    "iso:country":"US",
    "sg:address":"3314 Front St",
    "sg:city":"Winnsboro",
    "sg:classifiers":[
        {
            "category":"Shopping",
            "subcategory":"Clothing, Apparel, & Fashions",
            "type":"Retail Goods"
        }
    ],
    "sg:phone":"+1 318 435 3525",
    "sg:postcode":"71295",
    "sg:province":"LA",
    "wof:name":"Cato",
    "wof:placetype":"venue"
},
  "geometry": {"coordinates":[-91.72685199999999,32.182415],"type":"Point"}
}