{
  "type": "Feature",
  "properties": {
    "iso:country":"US",
    "sg:address":"9340 Pascagoula Dr",
    "sg:city":"Baton Rouge",
    "sg:classifiers":[
        {
            "category":"Communications",
            "subcategory":"Film & Video Production",
            "type":"Services"
        }
    ],
    "sg:phone":"+1 225 766 5176",
    "sg:postcode":"70810",
    "sg:province":"LA",
    "sg:tags":[
        "motion",
        "picture",
        "computer"
    ],
    "wof:name":"T & B Creations & Video Taping",
    "wof:placetype":"venue"
},
  "geometry": {"coordinates":[-91.131113,30.348907],"type":"Point"}
}