{
  "type": "Feature",
  "properties": {
    "iso:country":"US",
    "sg:address":"626 Main St",
    "sg:city":"Baton Rouge",
    "sg:classifiers":[
        {
            "category":"Home & Garden",
            "subcategory":"Furniture",
            "type":"Retail Goods"
        }
    ],
    "sg:phone":"+1 225 343 2823",
    "sg:postcode":"70801",
    "sg:province":"LA",
    "wof:name":"Butler Furniture Co",
    "wof:placetype":"venue"
},
  "geometry": {"coordinates":[-91.18383,30.451486],"type":"Point"}
}