{
  "type": "Feature",
  "properties": {
    "addr:full":"876 Verret St Houma LA 70360",
    "addr:housenumber":"876",
    "addr:postcode":"70360",
    "addr:street":"Verret St",
    "iso:country":"US",
    "sg:address":"876 Verret St",
    "sg:city":"Houma",
    "sg:classifiers":[
        {
            "category":"Social Services",
            "type":"Services"
        }
    ],
    "sg:phone":"+1 985 879 4071",
    "sg:postcode":"70360",
    "sg:province":"LA",
    "sg:tags":[
        "senior",
        "citizen"
    ],
    "wof:name":"Terrebonne Council On Aging",
    "wof:placetype":"venue"
},
  "geometry": {"coordinates":[-90.715029,29.594401],"type":"Point"}
}