{
  "type": "Feature",
  "properties": {
    "addr:full":"19374 N 3rd St Covington LA 70433",
    "addr:housenumber":"19374",
    "addr:postcode":"70433",
    "addr:street":"N 3Rd St",
    "iso:country":"US",
    "sg:address":"19374 N 3rd St",
    "sg:city":"Covington",
    "sg:classifiers":[
        {
            "category":"Government",
            "subcategory":"Office",
            "type":"Public Place"
        }
    ],
    "sg:phone":"+1 985 871 1258",
    "sg:postcode":"70433",
    "sg:province":"LA",
    "sg:tags":[
        "state",
        "resource"
    ],
    "wof:name":"Workers' Compensation Office",
    "wof:placetype":"venue"
},
  "geometry": {"coordinates":[-90.08317700000001,30.47053],"type":"Point"}
}