{
  "type": "Feature",
  "properties": {
    "iso:country":"US",
    "sg:address":"263 Eddie Robinson Sr Dr",
    "sg:city":"Baton Rouge",
    "sg:classifiers":[
        {
            "category":"Retail",
            "subcategory":"Funeral Services",
            "type":"Services"
        }
    ],
    "sg:phone":"+1 225 383 8891",
    "sg:postcode":"70802",
    "sg:province":"LA",
    "sg:tags":[
        "director"
    ],
    "wof:name":"Desselle's Funeral Home",
    "wof:placetype":"venue"
},
  "geometry": {"coordinates":[-91.17582,30.445844],"type":"Point"}
}