{
  "type": "Feature",
  "properties": {
    "iso:country":"US",
    "sg:address":"2129 State Rte 20",
    "sg:city":"Vacherie",
    "sg:classifiers":[
        {
            "category":"Personal",
            "type":"Services"
        }
    ],
    "sg:phone":"+1 225 265 7022",
    "sg:postcode":"70090",
    "sg:province":"LA",
    "sg:tags":[
        "wear",
        "formal"
    ],
    "wof:name":"Unique Creations",
    "wof:placetype":"venue"
},
  "geometry": {"coordinates":[-90.730102,30.007258],"type":"Point"}
}