{
  "type": "Feature",
  "properties": {
    "iso:country":"US",
    "sg:address":"320 3rd St",
    "sg:city":"Baton Rouge",
    "sg:classifiers":[
        {
            "category":"Professional",
            "subcategory":"Lawyer & Legal Services",
            "type":"Services"
        }
    ],
    "sg:phone":"+1 225 383 7800",
    "sg:postcode":"70801",
    "sg:province":"LA",
    "sg:tags":[
        "attorney"
    ],
    "wof:name":"Antwine Harvey Law Offices",
    "wof:placetype":"venue"
},
  "geometry": {"coordinates":[-91.188202,30.450152],"type":"Point"}
}