{
  "type": "Feature",
  "properties": {
    "addr:full":"216 Murrell St Minden LA 71055",
    "addr:housenumber":"216",
    "addr:postcode":"71055",
    "addr:street":"Murrell St",
    "iso:country":"US",
    "sg:address":"216 Murrell St",
    "sg:city":"Minden",
    "sg:classifiers":[
        {
            "category":"Personal",
            "subcategory":"Beauty Salon",
            "type":"Services"
        }
    ],
    "sg:phone":"+1 318 371 7895",
    "sg:postcode":"71055",
    "sg:province":"LA",
    "wof:name":"Tangles",
    "wof:placetype":"venue"
},
  "geometry": {"coordinates":[-93.282833,32.615636],"type":"Point"}
}