{
  "type": "Feature",
  "properties": {
    "iso:country":"US",
    "sg:address":"8642 S Choctaw Dr",
    "sg:city":"Baton Rouge",
    "sg:classifiers":[
        {
            "category":"Retail",
            "subcategory":"Auto Repair",
            "type":"Services"
        }
    ],
    "sg:phone":"+1 225 923 0202",
    "sg:postcode":"70815",
    "sg:province":"LA",
    "sg:tags":[
        "body",
        "automobile",
        "painting"
    ],
    "wof:name":"Lemoine's Paint & Body Shop",
    "wof:placetype":"venue"
},
  "geometry": {"coordinates":[-91.094836,30.471369],"type":"Point"}
}