{
  "type": "Feature",
  "properties": {
    "iso:country":"US",
    "sg:address":"140 Fremont St",
    "sg:city":"Shreveport",
    "sg:classifiers":[
        {
            "category":"Professional",
            "type":"Services"
        }
    ],
    "sg:phone":"+1 318 861 3317",
    "sg:postcode":"71105",
    "sg:province":"LA",
    "sg:tags":[
        "establishment"
    ],
    "wof:name":"Bamburg & Bamburg",
    "wof:placetype":"venue"
},
  "geometry": {"coordinates":[-93.714433,32.469957],"type":"Point"}
}