{
  "type": "Feature",
  "properties": {
    "iso:country":"US",
    "sg:address":"400 N Dugas Rd",
    "sg:city":"Lafayette",
    "sg:classifiers":[
        {
            "category":"Government",
            "subcategory":"Office",
            "type":"Public Place"
        }
    ],
    "sg:phone":"+1 337 291 8529",
    "sg:postcode":"70507",
    "sg:province":"LA",
    "sg:tags":[
        "village"
    ],
    "wof:name":"Lafayette Recycling Dept",
    "wof:placetype":"venue"
},
  "geometry": {"coordinates":[-92.05919900000001,30.283134],"type":"Point"}
}