{
  "type": "Feature",
  "properties": {
    "addr:full":"100 Commission Blvd Lafayette LA 70508",
    "addr:housenumber":"100",
    "addr:postcode":"70508",
    "addr:street":"Commission Blvd",
    "iso:country":"US",
    "sg:address":"100 Commission Blvd",
    "sg:city":"Lafayette",
    "sg:classifiers":[
        {
            "category":"Mining & Drilling",
            "type":"Manufacturing & Wholesale Goods"
        }
    ],
    "sg:phone":"+1 337 837 2245",
    "sg:postcode":"70508",
    "sg:province":"LA",
    "sg:tags":[
        "consultant",
        "oil",
        "gas"
    ],
    "wof:name":"Copestone Inc",
    "wof:placetype":"venue"
},
  "geometry": {"coordinates":[-91.986982,30.170928],"type":"Point"}
}