{
  "type": "Feature",
  "properties": {
    "addr:full":"73 Louisiana St Westwego LA 70094",
    "addr:housenumber":"73",
    "addr:postcode":"70094",
    "addr:street":"Louisiana St",
    "iso:country":"US",
    "sg:address":"73 Louisiana St",
    "sg:city":"Westwego",
    "sg:classifiers":[
        {
            "category":"Manufacturing",
            "subcategory":"Watercraft",
            "type":"Manufacturing & Wholesale Goods"
        }
    ],
    "sg:phone":"+1 504 340 9349",
    "sg:postcode":"70094",
    "sg:province":"LA",
    "sg:tags":[
        "boat"
    ],
    "wof:name":"WEGO Aluminum & Steel Fbrctrs",
    "wof:placetype":"venue"
},
  "geometry": {"coordinates":[-90.144822,29.914286],"type":"Point"}
}