{
  "type": "Feature",
  "properties": {
    "addr:full":"65135 Hwy 3081 Pearl River LA 70452",
    "addr:housenumber":"65135",
    "addr:postcode":"70452",
    "addr:street":"Hwy 3081",
    "iso:country":"US",
    "sg:address":"65135 Hwy 3081",
    "sg:city":"Pearl River",
    "sg:classifiers":[
        {
            "category":"Building & Trades",
            "subcategory":"Landscaping Services",
            "type":"Services"
        }
    ],
    "sg:phone":"+1 985 893 4202",
    "sg:postcode":"70452",
    "sg:province":"LA",
    "sg:tags":[
        "tree"
    ],
    "wof:name":"Tim's Trees",
    "wof:placetype":"venue"
},
  "geometry": {"coordinates":[-89.74368,30.378404],"type":"Point"}
}