{
  "type": "Feature",
  "properties": {
    "addr:full":"2899 Derek Dr Lake Charles LA 70607",
    "addr:housenumber":"2899",
    "addr:postcode":"70607",
    "addr:street":"Derek Dr",
    "iso:country":"US",
    "sg:address":"2899 Derek Dr",
    "sg:city":"Lake Charles",
    "sg:classifiers":[
        {
            "category":"Shopping",
            "subcategory":"Department Store",
            "type":"Retail Goods"
        }
    ],
    "sg:phone":"+1 337 562 2367",
    "sg:postcode":"70607",
    "sg:province":"LA",
    "sg:tags":[
        "shop"
    ],
    "wof:name":"Dollar Tree",
    "wof:placetype":"venue"
},
  "geometry": {"coordinates":[-93.17420199999999,30.195804],"type":"Point"}
}