{
  "type": "Feature",
  "properties": {
    "addr:full":"619 W Main St New Roads LA 70760",
    "addr:housenumber":"619",
    "addr:postcode":"70760",
    "addr:street":"W Main St",
    "iso:country":"US",
    "sg:address":"619 W Main St",
    "sg:city":"New Roads",
    "sg:classifiers":[
        {
            "category":"Personal",
            "subcategory":"Barber",
            "type":"Services"
        }
    ],
    "sg:phone":"+1 225 638 3189",
    "sg:postcode":"70760",
    "sg:province":"LA",
    "wof:name":"New Image",
    "wof:placetype":"venue"
},
  "geometry": {"coordinates":[-91.436126,30.692969],"type":"Point"}
}