{
  "type": "Feature",
  "properties": {
    "iso:country":"US",
    "sg:address":"6603 4th St",
    "sg:city":"Marrero",
    "sg:classifiers":[
        {
            "category":"Retail",
            "subcategory":"Auto Repair",
            "type":"Services"
        }
    ],
    "sg:phone":"+1 504 348 3430",
    "sg:postcode":"70072",
    "sg:province":"LA",
    "sg:tags":[
        "repairing",
        "automobile"
    ],
    "wof:name":"Marques Leasing",
    "wof:placetype":"venue"
},
  "geometry": {"coordinates":[-90.118892,29.900419],"type":"Point"}
}