{
  "type": "Feature",
  "properties": {
    "addr:full":"125 Wolf Lair Dr West Monroe LA 71292",
    "addr:housenumber":"125",
    "addr:postcode":"71292",
    "addr:street":"Wolf Lair Dr West",
    "iso:country":"US",
    "sg:address":"125 Wolf Lair Dr",
    "sg:city":"West Monroe",
    "sg:classifiers":[
        {
            "category":"Building & Trades",
            "subcategory":"Construction",
            "type":"Services"
        }
    ],
    "sg:phone":"+1 318 651 0454",
    "sg:postcode":"71292",
    "sg:province":"LA",
    "sg:tags":[
        "house"
    ],
    "wof:name":"Cost Plus Builders",
    "wof:placetype":"venue"
},
  "geometry": {"coordinates":[-92.195626,32.504643],"type":"Point"}
}