{
  "type": "Feature",
  "properties": {
    "addr:full":"8550 United Plaza Blvd Baton Rouge LA 70809",
    "addr:postcode":"8550;70809",
    "addr:street":"Plaza Blvd",
    "iso:country":"US",
    "sg:address":"8550 United Plaza Blvd",
    "sg:city":"Baton Rouge",
    "sg:classifiers":[
        {
            "category":"Restaurant",
            "type":"Food & Drink"
        }
    ],
    "sg:phone":"+1 225 927 1070",
    "sg:postcode":"70809",
    "sg:province":"LA",
    "wof:name":"Subway Sandwiches & Salads",
    "wof:placetype":"venue"
},
  "geometry": {"coordinates":[-91.095983,30.409447],"type":"Point"}
}