{
  "type": "Feature",
  "properties": {
    "addr:full":"855 N 37th St Baton Rouge LA 70802",
    "addr:housenumber":"855",
    "addr:postcode":"70802",
    "addr:street":"N 37Th St",
    "iso:country":"US",
    "sg:address":"855 N 37th St",
    "sg:city":"Baton Rouge",
    "sg:classifiers":[
        {
            "category":"Freight",
            "type":"Transportation"
        }
    ],
    "sg:phone":"+1 225 343 6464",
    "sg:postcode":"70802",
    "sg:province":"LA",
    "sg:tags":[
        "operator",
        "local",
        "trucking"
    ],
    "wof:name":"Chaney Trucking",
    "wof:placetype":"venue"
},
  "geometry": {"coordinates":[-91.15285799999999,30.45765],"type":"Point"}
}