{
  "type": "Feature",
  "properties": {
    "addr:full":"1801 Dale St Morgan City LA 70380",
    "addr:housenumber":"1801",
    "addr:postcode":"70380",
    "addr:street":"Dale St",
    "iso:country":"US",
    "sg:address":"1801 Dale St",
    "sg:city":"Morgan City",
    "sg:classifiers":[
        {
            "category":"Mining & Drilling",
            "type":"Manufacturing & Wholesale Goods"
        }
    ],
    "sg:phone":"+1 985 384 5276",
    "sg:postcode":"70380",
    "sg:province":"LA",
    "sg:tags":[
        "well"
    ],
    "wof:name":"Robert A Lay Sr",
    "wof:placetype":"venue"
},
  "geometry": {"coordinates":[-91.18718800000001,29.697841],"type":"Point"}
}