{
  "type": "Feature",
  "properties": {
    "iso:country":"US",
    "sg:address":"1514 Prytania St",
    "sg:city":"New Orleans",
    "sg:classifiers":[
        {
            "category":"Manufacturing",
            "subcategory":"Printing",
            "type":"Manufacturing & Wholesale Goods"
        }
    ],
    "sg:phone":"+1 504 586 8063",
    "sg:postcode":"70130",
    "sg:province":"LA",
    "sg:tags":[
        "publisher",
        "book",
        "publishing"
    ],
    "wof:name":"Martin St Martin Publishing Co",
    "wof:placetype":"venue"
},
  "geometry": {"coordinates":[-90.074124,29.938281],"type":"Point"}
}