{
  "type": "Feature",
  "properties": {
    "iso:country":"US",
    "sg:address":"107 Bayou Gardens Blvd",
    "sg:city":"Houma",
    "sg:classifiers":[
        {
            "category":"Health Services",
            "subcategory":"Doctor",
            "type":"Services"
        }
    ],
    "sg:phone":"+1 985 851 5662",
    "sg:postcode":"70364",
    "sg:province":"LA",
    "sg:tags":[
        "dentist"
    ],
    "wof:name":"Bayou Dental",
    "wof:placetype":"venue"
},
  "geometry": {"coordinates":[-90.75433200000001,29.637639],"type":"Point"}
}