{
  "type": "Feature",
  "properties": {
    "addr:full":"410 E Rutland St Covington LA 70433",
    "addr:housenumber":"410",
    "addr:postcode":"70433",
    "addr:street":"E Rutland St",
    "iso:country":"US",
    "sg:address":"410 E Rutland St",
    "sg:city":"Covington",
    "sg:classifiers":[
        {
            "category":"Shopping",
            "type":"Retail Goods"
        }
    ],
    "sg:phone":"+1 985 809 1890",
    "sg:postcode":"70433",
    "sg:province":"LA",
    "sg:tags":[
        "hearing",
        "equipment",
        "supply",
        "impaired"
    ],
    "wof:name":"Physicians Choice Hearing Aid",
    "wof:placetype":"venue"
},
  "geometry": {"coordinates":[-90.09677499999999,30.474247],"type":"Point"}
}