{
  "type": "Feature",
  "properties": {
    "addr:full":"5612 Crawford St New Orleans LA 70123",
    "addr:housenumber":"5612",
    "addr:postcode":"70123",
    "addr:street":"Crawford St",
    "iso:country":"US",
    "sg:address":"5612 Crawford St",
    "sg:city":"New Orleans",
    "sg:classifiers":[
        {
            "category":"Wholesale",
            "subcategory":"Non-durable Goods",
            "type":"Manufacturing & Wholesale Goods"
        }
    ],
    "sg:phone":"+1 504 734 2240",
    "sg:postcode":"70123",
    "sg:province":"LA",
    "wof:name":"Helling Holdings",
    "wof:placetype":"venue"
},
  "geometry": {"coordinates":[-90.193856,29.964025],"type":"Point"}
}