{
  "type": "Feature",
  "properties": {
    "iso:country":"US",
    "sg:address":"7502 Hoben Ln",
    "sg:city":"Lake Charles",
    "sg:classifiers":[
        {
            "category":"Professional",
            "subcategory":"Management & Consulting",
            "type":"Services"
        }
    ],
    "sg:phone":"+1 337 474 7721",
    "sg:postcode":"70607",
    "sg:province":"LA",
    "sg:tags":[
        "party",
        "planning"
    ],
    "wof:name":"David's Party Ponies",
    "wof:placetype":"venue"
},
  "geometry": {"coordinates":[-93.20220999999999,30.129258],"type":"Point"}
}