{
  "type": "Feature",
  "properties": {
    "iso:country":"US",
    "sg:address":"745 W Jim Pickens Rd",
    "sg:city":"Sulphur",
    "sg:classifiers":[
        {
            "category":"Utilities",
            "subcategory":"Water",
            "type":"Services"
        }
    ],
    "sg:phone":"+1 337 528 3446",
    "sg:postcode":"70663",
    "sg:province":"LA",
    "sg:tags":[
        "company",
        "sewage"
    ],
    "wof:name":"Houston River Waterworks Dist",
    "wof:placetype":"venue"
},
  "geometry": {"coordinates":[-93.38070500000001,30.271045],"type":"Point"}
}