{
  "type": "Feature",
  "properties": {
    "addr:full":"202 N Range Ave Denham Springs LA 70726",
    "addr:housenumber":"202",
    "addr:postcode":"70726",
    "addr:street":"N Range Ave",
    "iso:country":"US",
    "sg:address":"202 N Range Ave",
    "sg:city":"Denham Springs",
    "sg:classifiers":[
        {
            "category":"Shopping",
            "subcategory":"Used Merchandise",
            "type":"Retail Goods"
        }
    ],
    "sg:phone":"+1 225 667 6327",
    "sg:postcode":"70726",
    "sg:province":"LA",
    "sg:tags":[
        "shop",
        "consignment"
    ],
    "wof:name":"Britches N Bows",
    "wof:placetype":"venue"
},
  "geometry": {"coordinates":[-90.956059,30.485588],"type":"Point"}
}