{
  "type": "Feature",
  "properties": {
    "addr:full":"3310 N University Ave Lafayette LA 70507",
    "addr:housenumber":"3310",
    "addr:postcode":"70507",
    "addr:street":"N University Ave",
    "iso:country":"US",
    "sg:address":"3310 N University Ave",
    "sg:city":"Lafayette",
    "sg:classifiers":[
        {
            "category":"Freight",
            "type":"Transportation"
        }
    ],
    "sg:phone":"+1 337 896 8131",
    "sg:postcode":"70507",
    "sg:province":"LA",
    "sg:tags":[
        "operator",
        "local",
        "trucking"
    ],
    "wof:name":"B&B Trucking",
    "wof:placetype":"venue"
},
  "geometry": {"coordinates":[-92.04972600000001,30.292831],"type":"Point"}
}