{
  "type": "Feature",
  "properties": {
    "iso:country":"US",
    "sg:address":"439 Terry Pkwy",
    "sg:city":"Terrytown",
    "sg:classifiers":[
        {
            "category":"Shopping",
            "subcategory":"Clothing, Apparel, & Fashions",
            "type":"Retail Goods"
        }
    ],
    "sg:phone":"+1 504 362 5133",
    "sg:postcode":"70056",
    "sg:province":"LA",
    "wof:name":"Diva Style",
    "wof:placetype":"venue"
},
  "geometry": {"coordinates":[-90.030399,29.911119],"type":"Point"}
}