{
  "type": "Feature",
  "properties": {
    "iso:country":"US",
    "sg:address":"1128 Main Hwy",
    "sg:city":"Arnaudville",
    "sg:classifiers":[
        {
            "category":"Utilities",
            "subcategory":"Fuel Oil & Lpg",
            "type":"Services"
        }
    ],
    "sg:phone":"+1 337 754 5980",
    "sg:postcode":"70512",
    "sg:province":"LA",
    "sg:tags":[
        "dealer"
    ],
    "wof:name":"Louis A Olivier",
    "wof:placetype":"venue"
},
  "geometry": {"coordinates":[-91.929337,30.390647],"type":"Point"}
}