{
  "type": "Feature",
  "properties": {
    "addr:full":"103 Master's Rd Grayson LA 71418",
    "addr:housenumber":"103",
    "addr:postcode":"71418",
    "addr:street":"Master'S Rd",
    "iso:country":"US",
    "sg:address":"103 Master's Rd",
    "sg:city":"Grayson",
    "sg:classifiers":[
        {
            "category":"Organizations",
            "subcategory":"Religious Organization",
            "type":"Services"
        }
    ],
    "sg:phone":"+1 318 649 2515",
    "sg:postcode":"71418",
    "sg:province":"LA",
    "sg:tags":[
        "church"
    ],
    "wof:name":"Grayson Pentecostal Church",
    "wof:placetype":"venue"
},
  "geometry": {"coordinates":[-92.086916,32.087561],"type":"Point"}
}