{
  "type": "Feature",
  "properties": {
    "iso:country":"US",
    "sg:address":"701 N 7th St",
    "sg:city":"West Monroe",
    "sg:classifiers":[
        {
            "category":"Health Services",
            "subcategory":"Clinic",
            "type":"Services"
        }
    ],
    "sg:phone":"+1 318 329 1101",
    "sg:postcode":"71291",
    "sg:province":"LA",
    "sg:tags":[
        "home"
    ],
    "wof:name":"Comforcare",
    "wof:placetype":"venue"
},
  "geometry": {"coordinates":[-92.13475200000001,32.501827],"type":"Point"}
}