{
  "type": "Feature",
  "properties": {
    "addr:full":"758 Hwy 1191 Marksville LA 71351",
    "addr:housenumber":"758",
    "addr:postcode":"1191;71351",
    "addr:street":"Hwy",
    "iso:country":"US",
    "sg:address":"758 Hwy 1191",
    "sg:city":"Marksville",
    "sg:classifiers":[
        {
            "category":"Building & Trades",
            "subcategory":"Construction",
            "type":"Services"
        }
    ],
    "sg:phone":"+1 318 253 5394",
    "sg:postcode":"71351",
    "sg:province":"LA",
    "sg:tags":[
        "excavation",
        "contractor"
    ],
    "wof:name":"Jerrys Backhoe Service",
    "wof:placetype":"venue"
},
  "geometry": {"coordinates":[-92.08699900000001,31.152696],"type":"Point"}
}