{
  "type": "Feature",
  "properties": {
    "iso:country":"US",
    "sg:address":"617 S Claiborne Ave",
    "sg:city":"New Orleans",
    "sg:classifiers":[
        {
            "category":"Retail",
            "subcategory":"Auto Repair",
            "type":"Services"
        }
    ],
    "sg:phone":"+1 504 525 5618",
    "sg:postcode":"70125",
    "sg:province":"LA",
    "sg:tags":[
        "automobile",
        "electric"
    ],
    "wof:name":"A A Auto Electric Inc",
    "wof:placetype":"venue"
},
  "geometry": {"coordinates":[-90.08332799999999,29.953195],"type":"Point"}
}