{
  "type": "Feature",
  "properties": {
    "iso:country":"US",
    "sg:address":"2848 Slidell Ave",
    "sg:city":"Slidell",
    "sg:classifiers":[
        {
            "category":"Professional",
            "subcategory":"Business Services",
            "type":"Services"
        }
    ],
    "sg:phone":"+1 985 781 6003",
    "sg:postcode":"70458",
    "sg:province":"LA",
    "sg:tags":[
        "drafting"
    ],
    "wof:name":"Norhtshore Design Ctr",
    "wof:placetype":"venue"
},
  "geometry": {"coordinates":[-89.780412,30.261953],"type":"Point"}
}