{
  "type": "Feature",
  "properties": {
    "iso:country":"US",
    "sg:address":"1208 S Walnut St",
    "sg:city":"Tallulah",
    "sg:classifiers":[
        {
            "category":"Professional",
            "type":"Services"
        }
    ],
    "sg:phone":"+1 318 574 0077",
    "sg:postcode":"71282",
    "sg:province":"LA",
    "sg:tags":[
        "establishment"
    ],
    "wof:name":"Farley Fargo",
    "wof:placetype":"venue"
},
  "geometry": {"coordinates":[-91.198402,32.400787],"type":"Point"}
}