{
  "type": "Feature",
  "properties": {
    "iso:country":"US",
    "sg:address":"310 Northbrook Dr",
    "sg:city":"Shreveport",
    "sg:classifiers":[
        {
            "category":"Building & Trades",
            "subcategory":"Construction",
            "type":"Services"
        }
    ],
    "sg:phone":"+1 318 925 0808",
    "sg:postcode":"71106",
    "sg:province":"LA",
    "sg:tags":[
        "floor",
        "laying",
        "contractor"
    ],
    "wof:name":"Creative FL Covering",
    "wof:placetype":"venue"
},
  "geometry": {"coordinates":[-93.75885,32.394483],"type":"Point"}
}