{
  "type": "Feature",
  "properties": {
    "iso:country":"US",
    "sg:address":"1203 University Pkwy",
    "sg:city":"Leesville",
    "sg:classifiers":[
        {
            "category":"Freight",
            "type":"Transportation"
        }
    ],
    "sg:phone":"+1 337 238 1131",
    "sg:postcode":"71446",
    "sg:province":"LA",
    "wof:name":"Williams Transportation",
    "wof:placetype":"venue"
},
  "geometry": {"coordinates":[-93.262125,31.132899],"type":"Point"}
}