{
  "type": "Feature",
  "properties": {
    "iso:country":"US",
    "sg:address":"4165 I-49 S Service Rd",
    "sg:city":"Opelousas",
    "sg:classifiers":[
        {
            "category":"Travel",
            "subcategory":"Hotels & Motels",
            "type":"Entertainment"
        },
        {
            "category":"Travel",
            "subcategory":"Bed & Breakfast",
            "type":"Entertainment"
        }
    ],
    "sg:phone":"+1 337 948 9500",
    "sg:postcode":"70570",
    "sg:province":"LA",
    "sg:tags":[
        "inn",
        "lodging"
    ],
    "sg:website":"http://www.abvi.com/bestv.cfm?idp=932&rcode=lcl",
    "wof:name":"Americas Best Value Inn",
    "wof:placetype":"venue"
},
  "geometry": {"coordinates":[-92.06955,30.51536],"type":"Point"}
}