{
  "type": "Feature",
  "properties": {
    "iso:country":"US",
    "sg:address":"1072 Vincent Settlement Rd",
    "sg:city":"Sulphur",
    "sg:classifiers":[
        {
            "category":"Education",
            "subcategory":"School",
            "type":"Public Place"
        }
    ],
    "sg:phone":"+1 337 583 4148",
    "sg:postcode":"70665",
    "sg:province":"LA",
    "wof:name":"Vincent Settlement Elementary",
    "wof:placetype":"venue"
},
  "geometry": {"coordinates":[-93.35924799999999,30.150199],"type":"Point"}
}