{
  "type": "Feature",
  "properties": {
    "iso:country":"US",
    "sg:address":"179 W Preston Ave",
    "sg:city":"Shreveport",
    "sg:classifiers":[
        {
            "category":"Organizations",
            "subcategory":"Membership Organization",
            "type":"Services"
        }
    ],
    "sg:phone":"+1 318 797 5500",
    "sg:postcode":"71105",
    "sg:province":"LA",
    "wof:name":"Louisiana Lacrosse Assoc",
    "wof:placetype":"venue"
},
  "geometry": {"coordinates":[-93.71078300000001,32.468481],"type":"Point"}
}