{
  "type": "Feature",
  "properties": {
    "iso:country":"US",
    "sg:address":"1111 Ryan St",
    "sg:city":"Lake Charles",
    "sg:classifiers":[
        {
            "category":"Professional",
            "subcategory":"Lawyer & Legal Services",
            "type":"Services"
        }
    ],
    "sg:phone":"+1 337 436 7582",
    "sg:postcode":"70601",
    "sg:province":"LA",
    "sg:tags":[
        "attorney"
    ],
    "wof:name":"Rick Robinson",
    "wof:placetype":"venue"
},
  "geometry": {"coordinates":[-93.21815700000001,30.223866],"type":"Point"}
}