{
  "type": "Feature",
  "properties": {
    "iso:country":"US",
    "sg:address":"3650 18th St",
    "sg:city":"Metairie",
    "sg:classifiers":[
        {
            "category":"Retail",
            "subcategory":"Auto Rental",
            "type":"Services"
        }
    ],
    "sg:phone":"+1 504 454 1178",
    "sg:postcode":"70002",
    "sg:province":"LA",
    "sg:tags":[
        "passenger",
        "van",
        "transport",
        "car"
    ],
    "wof:name":"Wheelchair Getaways",
    "wof:placetype":"venue"
},
  "geometry": {"coordinates":[-90.164359,30.008674],"type":"Point"}
}