{
  "type": "Feature",
  "properties": {
    "iso:country":"US",
    "sg:address":"325 Loyola Ave",
    "sg:city":"New Orleans",
    "sg:classifiers":[
        {
            "category":"Government",
            "subcategory":"Office",
            "type":"Public Place"
        }
    ],
    "sg:phone":"+1 504 568 2509",
    "sg:postcode":"70112",
    "sg:province":"LA",
    "sg:tags":[
        "state",
        "program",
        "health"
    ],
    "wof:name":"Public Health-Disability Prog",
    "wof:placetype":"venue"
},
  "geometry": {"coordinates":[-90.07555499999999,29.953365],"type":"Point"}
}