{
  "type": "Feature",
  "properties": {
    "addr:full":"2400 Lapalco Blvd Harvey LA 70058",
    "addr:housenumber":"2400",
    "addr:postcode":"70058",
    "addr:street":"Lapalco Blvd",
    "iso:country":"US",
    "sg:address":"2400 Lapalco Blvd",
    "sg:city":"Harvey",
    "sg:classifiers":[
        {
            "category":"Home & Garden",
            "subcategory":"Furniture",
            "type":"Retail Goods"
        }
    ],
    "sg:phone":"+1 504 366 2922",
    "sg:postcode":"70058",
    "sg:province":"LA",
    "wof:name":"Price Smart",
    "wof:placetype":"venue"
},
  "geometry": {"coordinates":[-90.05602,29.873247],"type":"Point"}
}