{
  "type": "Feature",
  "properties": {
    "iso:country":"US",
    "sg:address":"130 Plantation Rd",
    "sg:city":"Destrehan",
    "sg:classifiers":[
        {
            "category":"Education",
            "subcategory":"School",
            "type":"Public Place"
        }
    ],
    "sg:phone":"+1 985 764 1275",
    "sg:postcode":"70047",
    "sg:province":"LA",
    "sg:website":"www.louisianaschools.com",
    "wof:name":"New Sarpy Elementary School",
    "wof:placetype":"venue"
},
  "geometry": {"coordinates":[-90.376987,29.971457],"type":"Point"}
}