{
  "type": "Feature",
  "properties": {
    "addr:full":"756 S Lyons St Lake Charles LA 70601",
    "addr:housenumber":"756",
    "addr:postcode":"70601",
    "addr:street":"S Lyons St",
    "iso:country":"US",
    "sg:address":"756 S Lyons St",
    "sg:city":"Lake Charles",
    "sg:classifiers":[
        {
            "category":"Building & Trades",
            "subcategory":"Construction",
            "type":"Services"
        }
    ],
    "sg:phone":"+1 337 439 2481",
    "sg:postcode":"70601",
    "sg:province":"LA",
    "sg:tags":[
        "home",
        "improvement"
    ],
    "wof:name":"Kushner-Berard Building Mtrls",
    "wof:placetype":"venue"
},
  "geometry": {"coordinates":[-93.20037499999999,30.228587],"type":"Point"}
}