{
  "type": "Feature",
  "properties": {
    "iso:country":"US",
    "sg:address":"12329 Industriplex Blvd",
    "sg:city":"Baton Rouge",
    "sg:classifiers":[
        {
            "category":"Wholesale",
            "subcategory":"Hardware",
            "type":"Manufacturing & Wholesale Goods"
        }
    ],
    "sg:phone":"+1 225 752 7100",
    "sg:postcode":"70809",
    "sg:province":"LA",
    "sg:tags":[
        "fastener"
    ],
    "wof:name":"Fastenal Co",
    "wof:placetype":"venue"
},
  "geometry": {"coordinates":[-91.04681100000001,30.384096],"type":"Point"}
}