{
  "type": "Feature",
  "properties": {
    "iso:country":"US",
    "sg:address":"356 East Blvd",
    "sg:city":"Baton Rouge",
    "sg:classifiers":[
        {
            "category":"Education",
            "subcategory":"School",
            "type":"Public Place"
        }
    ],
    "sg:phone":"+1 225 346 0067",
    "sg:postcode":"70802",
    "sg:province":"LA",
    "wof:name":"J K Haynes Elementary School",
    "wof:placetype":"venue"
},
  "geometry": {"coordinates":[-91.180386,30.444622],"type":"Point"}
}