{
  "type": "Feature",
  "properties": {
    "addr:full":"305 Bernard Ave Chalmette LA 70031",
    "addr:housenumber":"305",
    "addr:postcode":"70031",
    "addr:street":"Bernard Ave",
    "iso:country":"US",
    "sg:address":"305 Bernard Ave",
    "sg:city":"Chalmette",
    "sg:classifiers":[
        {
            "category":"Organizations",
            "subcategory":"Religious Organization",
            "type":"Services"
        }
    ],
    "sg:phone":"+1 504 279 7401",
    "sg:postcode":"70031",
    "sg:province":"LA",
    "sg:tags":[
        "church"
    ],
    "sg:website":"www.fbcchalmette.org",
    "wof:name":"First Baptist Church",
    "wof:placetype":"venue"
},
  "geometry": {"coordinates":[-90.287175,29.946357],"type":"Point"}
}