{
  "type": "Feature",
  "properties": {
    "iso:country":"US",
    "sg:address":"5900 Airline Hwy",
    "sg:city":"Baton Rouge",
    "sg:classifiers":[
        {
            "category":"Banks & Credit Unions",
            "subcategory":"Bank",
            "type":"Services"
        }
    ],
    "sg:phone":"+1 225 332 4361",
    "sg:postcode":"70805",
    "sg:province":"LA",
    "wof:name":"Bank One",
    "wof:placetype":"venue"
},
  "geometry": {"coordinates":[-91.13109900000001,30.502322],"type":"Point"}
}