{
  "type": "Feature",
  "properties": {
    "iso:country":"US",
    "sg:address":"3306 Industrial Dr",
    "sg:city":"Bossier City",
    "sg:classifiers":[
        {
            "category":"Home & Garden",
            "subcategory":"Carpets & Floor Coverings",
            "type":"Retail Goods"
        }
    ],
    "sg:phone":"+1 318 747 5950",
    "sg:postcode":"71112",
    "sg:province":"LA",
    "sg:tags":[
        "dealer",
        "rug"
    ],
    "wof:name":"Snyder Floor Covering",
    "wof:placetype":"venue"
},
  "geometry": {"coordinates":[-93.68823500000001,32.52342],"type":"Point"}
}