{
  "type": "Feature",
  "properties": {
    "iso:country":"US",
    "sg:address":"201 N Claiborne Ave",
    "sg:city":"New Orleans",
    "sg:classifiers":[
        {
            "category":"Autos & Motor Vehicles",
            "subcategory":"Automobile Sales",
            "type":"Retail Goods"
        }
    ],
    "sg:phone":"+1 504 299 0386",
    "sg:postcode":"70112",
    "sg:province":"LA",
    "sg:tags":[
        "car",
        "dealer"
    ],
    "wof:name":"Rainbow Repair Auto & Sales",
    "wof:placetype":"venue"
},
  "geometry": {"coordinates":[-90.07648399999999,29.960866],"type":"Point"}
}