{
  "type": "Feature",
  "properties": {
    "iso:country":"US",
    "sg:address":"235 Highlandia Dr",
    "sg:city":"Baton Rouge",
    "sg:classifiers":[
        {
            "category":"Insurance",
            "subcategory":"Insurance Agent",
            "type":"Services"
        }
    ],
    "sg:phone":"+1 225 292 3515",
    "sg:postcode":"70810",
    "sg:province":"LA",
    "sg:website":"www.ajg.com",
    "wof:name":"Arthur J Gallagher & Co",
    "wof:placetype":"venue"
},
  "geometry": {"coordinates":[-91.029692,30.343683],"type":"Point"}
}