{
  "type": "Feature",
  "properties": {
    "iso:country":"US",
    "sg:address":"4723 Palmetto Rd",
    "sg:city":"Benton",
    "sg:classifiers":[
        {
            "category":"Restaurant",
            "type":"Food & Drink"
        }
    ],
    "sg:phone":"+1 318 965 9883",
    "sg:postcode":"71006",
    "sg:province":"LA",
    "sg:tags":[
        "pizza"
    ],
    "wof:name":"Perky's Pizza",
    "wof:placetype":"venue"
},
  "geometry": {"coordinates":[-93.71330500000001,32.638225],"type":"Point"}
}