{
  "type": "Feature",
  "properties": {
    "iso:country":"US",
    "sg:address":"4604 Folse Dr",
    "sg:city":"Metairie",
    "sg:classifiers":[
        {
            "category":"Building & Trades",
            "subcategory":"Construction",
            "type":"Services"
        }
    ],
    "sg:phone":"+1 504 885 5354",
    "sg:postcode":"70006",
    "sg:province":"LA",
    "sg:tags":[
        "specializing",
        "new",
        "contractor",
        "f"
    ],
    "wof:name":"Ernie Nagim Construction Co",
    "wof:placetype":"venue"
},
  "geometry": {"coordinates":[-90.189306,30.023411],"type":"Point"}
}