{
  "type": "Feature",
  "properties": {
    "addr:full":"71630 Maple St Abita Springs LA 70420",
    "addr:housenumber":"71630",
    "addr:postcode":"70420",
    "addr:street":"Maple St",
    "iso:country":"US",
    "sg:address":"71630 Maple St",
    "sg:city":"Abita Springs",
    "sg:classifiers":[
        {
            "category":"Personal",
            "type":"Services"
        }
    ],
    "sg:phone":"+1 985 871 4004",
    "sg:postcode":"70420",
    "sg:province":"LA",
    "sg:tags":[
        "wedding",
        "chapel"
    ],
    "wof:name":"Maison D'Amour",
    "wof:placetype":"venue"
},
  "geometry": {"coordinates":[-90.037539,30.476509],"type":"Point"}
}