{
  "type": "Feature",
  "properties": {
    "iso:country":"US",
    "sg:address":"3414 Marshfield Rd",
    "sg:city":"New Iberia",
    "sg:classifiers":[
        {
            "category":"Government",
            "subcategory":"Office",
            "type":"Public Place"
        }
    ],
    "sg:phone":"+1 337 229 4632",
    "sg:postcode":"70552",
    "sg:province":"LA",
    "wof:name":"Iberia Parish Bridge Tender Hs",
    "wof:placetype":"venue"
},
  "geometry": {"coordinates":[-91.674774,30.024977],"type":"Point"}
}