{
  "type": "Feature",
  "properties": {
    "iso:country":"US",
    "sg:address":"3026 Ryan St",
    "sg:city":"Lake Charles",
    "sg:classifiers":[
        {
            "category":"Banks & Credit Unions",
            "subcategory":"Bank",
            "type":"Services"
        }
    ],
    "sg:phone":"+1 337 433 1413",
    "sg:postcode":"70601",
    "sg:province":"LA",
    "sg:tags":[
        "loan",
        "real estate"
    ],
    "wof:name":"Magnolia Mortgage Inc",
    "wof:placetype":"venue"
},
  "geometry": {"coordinates":[-93.21865099999999,30.202403],"type":"Point"}
}