{
  "type": "Feature",
  "properties": {
    "addr:full":"1011 Linton Bellevue Rd Benton LA 71006",
    "addr:housenumber":"1011",
    "addr:postcode":"71006",
    "addr:street":"Linton Bellevue Rd",
    "iso:country":"US",
    "sg:address":"1011 Linton Bellevue Rd",
    "sg:city":"Benton",
    "sg:classifiers":[
        {
            "category":"Retail",
            "subcategory":"Repair Shop",
            "type":"Services"
        }
    ],
    "sg:phone":"+1 318 965 0327",
    "sg:postcode":"71006",
    "sg:province":"LA",
    "sg:tags":[
        "electrical"
    ],
    "wof:name":"Coker Electronics",
    "wof:placetype":"venue"
},
  "geometry": {"coordinates":[-93.62331,32.679262],"type":"Point"}
}