{
  "type": "Feature",
  "properties": {
    "iso:country":"US",
    "sg:address":"1200 S Morrison Blvd",
    "sg:city":"Hammond",
    "sg:classifiers":[
        {
            "category":"Food & Beverages",
            "subcategory":"Groceries & Convenience Stores",
            "type":"Retail Goods"
        }
    ],
    "sg:phone":"+1 985 345 2517",
    "sg:postcode":"70403",
    "sg:province":"LA",
    "wof:name":"Circle K",
    "wof:placetype":"venue"
},
  "geometry": {"coordinates":[-90.48269999999999,30.487893],"type":"Point"}
}