{
  "type": "Feature",
  "properties": {
    "addr:full":"902 N Broad St New Orleans LA 70119",
    "addr:housenumber":"902",
    "addr:postcode":"70119",
    "addr:street":"N Broad St",
    "iso:country":"US",
    "sg:address":"902 N Broad St",
    "sg:city":"New Orleans",
    "sg:classifiers":[
        {
            "category":"Personal",
            "subcategory":"Beauty Salon",
            "type":"Services"
        }
    ],
    "sg:phone":"+1 504 821 4858",
    "sg:postcode":"70119",
    "sg:province":"LA",
    "wof:name":"Impressive Hair Design",
    "wof:placetype":"venue"
},
  "geometry": {"coordinates":[-90.080746,29.972941],"type":"Point"}
}