{
  "type": "Feature",
  "properties": {
    "addr:full":"1414 Green St Franklinton LA 70438",
    "addr:housenumber":"1414",
    "addr:postcode":"70438",
    "addr:street":"Green St",
    "iso:country":"US",
    "sg:address":"1414 Green St",
    "sg:city":"Franklinton",
    "sg:classifiers":[
        {
            "category":"Wholesale",
            "subcategory":"Machinery & Supplies",
            "type":"Manufacturing & Wholesale Goods"
        }
    ],
    "sg:phone":"+1 985 839 4291",
    "sg:postcode":"70438",
    "sg:province":"LA",
    "sg:tags":[
        "farm",
        "equipment"
    ],
    "wof:name":"Manning Enterprises",
    "wof:placetype":"venue"
},
  "geometry": {"coordinates":[-90.152017,30.840297],"type":"Point"}
}