{
  "type": "Feature",
  "properties": {
    "iso:country":"US",
    "sg:address":"402 E Main St",
    "sg:city":"Ville Platte",
    "sg:classifiers":[
        {
            "category":"Shopping",
            "subcategory":"Gifts & Souvenirs",
            "type":"Retail Goods"
        }
    ],
    "sg:phone":"+1 337 363 3252",
    "sg:postcode":"70586",
    "sg:province":"LA",
    "sg:tags":[
        "bridal",
        "registry"
    ],
    "wof:name":"Les Petite Cadeaux Inc",
    "wof:placetype":"venue"
},
  "geometry": {"coordinates":[-92.269938,30.686503],"type":"Point"}
}