{
  "type": "Feature",
  "properties": {
    "iso:country":"US",
    "sg:address":"11838 Richcroft Ave",
    "sg:city":"Baton Rouge",
    "sg:classifiers":[
        {
            "category":"Building & Trades",
            "subcategory":"Construction",
            "type":"Services"
        }
    ],
    "sg:phone":"+1 225 272 0333",
    "sg:postcode":"70814",
    "sg:province":"LA",
    "sg:tags":[
        "general",
        "contractor"
    ],
    "wof:name":"Fakouri Construction",
    "wof:placetype":"venue"
},
  "geometry": {"coordinates":[-91.048509,30.473439],"type":"Point"}
}