{
  "type": "Feature",
  "properties": {
    "iso:country":"US",
    "sg:address":"4306 Parkway Dr",
    "sg:city":"Bossier City",
    "sg:classifiers":[
        {
            "category":"Personal",
            "subcategory":"Beauty Salon",
            "type":"Services"
        }
    ],
    "sg:phone":"+1 318 752 8337",
    "sg:postcode":"71112",
    "sg:province":"LA",
    "wof:name":"Je'Nay's House Of Beauty",
    "wof:placetype":"venue"
},
  "geometry": {"coordinates":[-93.671522,32.474001],"type":"Point"}
}