{
  "type": "Feature",
  "properties": {
    "iso:country":"US",
    "sg:address":"2615 Westbank Expy",
    "sg:city":"Harvey",
    "sg:classifiers":[
        {
            "category":"Autos & Motor Vehicles",
            "subcategory":"Automobile Sales",
            "type":"Retail Goods"
        }
    ],
    "sg:phone":"+1 504 368 4848",
    "sg:postcode":"70058",
    "sg:province":"LA",
    "sg:tags":[
        "sport",
        "trailer",
        "utility"
    ],
    "wof:name":"Payless Trailer Sales",
    "wof:placetype":"venue"
},
  "geometry": {"coordinates":[-90.07807699999999,29.899054],"type":"Point"}
}