{
  "type": "Feature",
  "properties": {
    "iso:country":"US",
    "sg:address":"6289 W Park Ave",
    "sg:city":"Houma",
    "sg:classifiers":[
        {
            "category":"Local Transit",
            "type":"Transportation"
        }
    ],
    "sg:phone":"+1 985 851 4386",
    "sg:postcode":"70364",
    "sg:province":"LA",
    "sg:tags":[
        "handicapped"
    ],
    "wof:name":"Fun Tours Inc",
    "wof:placetype":"venue"
},
  "geometry": {"coordinates":[-90.75194399999999,29.626159],"type":"Point"}
}