{
  "type": "Feature",
  "properties": {
    "iso:country":"US",
    "sg:address":"731 E McNeese St",
    "sg:city":"Lake Charles",
    "sg:classifiers":[
        {
            "category":"Health Services",
            "subcategory":"Doctor",
            "type":"Services"
        }
    ],
    "sg:phone":"+1 337 477 6928",
    "sg:postcode":"70607",
    "sg:province":"LA",
    "sg:tags":[
        "dentist"
    ],
    "wof:name":"Miles R Mitchem DDS",
    "wof:placetype":"venue"
},
  "geometry": {"coordinates":[-93.211423,30.17627],"type":"Point"}
}