{
  "type": "Feature",
  "properties": {
    "iso:country":"US",
    "sg:address":"1935 E 70th St",
    "sg:city":"Shreveport",
    "sg:classifiers":[
        {
            "category":"Personal",
            "subcategory":"Beauty Salon",
            "type":"Services"
        }
    ],
    "sg:phone":"+1 318 798 9455",
    "sg:postcode":"71105",
    "sg:province":"LA",
    "wof:name":"Leslie Zaffater",
    "wof:placetype":"venue"
},
  "geometry": {"coordinates":[-93.70948799999999,32.443852],"type":"Point"}
}