{
  "type": "Feature",
  "properties": {
    "iso:country":"US",
    "sg:address":"1520 E Airline Hwy",
    "sg:city":"La Place",
    "sg:classifiers":[
        {
            "category":"Banks & Credit Unions",
            "subcategory":"Bank",
            "type":"Services"
        }
    ],
    "sg:phone":"+1 985 651 5770",
    "sg:postcode":"70068",
    "sg:province":"LA",
    "sg:tags":[
        "cashing",
        "check"
    ],
    "wof:name":"Check Into Cash",
    "wof:placetype":"venue"
},
  "geometry": {"coordinates":[-90.44330600000001,30.042068],"type":"Point"}
}