{
  "type": "Feature",
  "properties": {
    "iso:country":"US",
    "sg:address":"8564 Main St",
    "sg:city":"Houma",
    "sg:classifiers":[
        {
            "category":"Building & Trades",
            "subcategory":"Electrical",
            "type":"Services"
        }
    ],
    "sg:phone":"+1 985 872 9502",
    "sg:postcode":"70363",
    "sg:province":"LA",
    "sg:tags":[
        "electrical",
        "contractor"
    ],
    "wof:name":"Autins Tubby Electrical Svc",
    "wof:placetype":"venue"
},
  "geometry": {"coordinates":[-90.70175399999999,29.59769],"type":"Point"}
}