{
  "type": "Feature",
  "properties": {
    "iso:country":"US",
    "sg:address":"206 S Tyler St",
    "sg:city":"Covington",
    "sg:classifiers":[
        {
            "category":"Health Services",
            "subcategory":"Doctor",
            "type":"Services"
        }
    ],
    "sg:phone":"+1 985 867 8272",
    "sg:postcode":"70433",
    "sg:province":"LA",
    "sg:tags":[
        "clinic"
    ],
    "wof:name":"Child & Family Resource Clinic",
    "wof:placetype":"venue"
},
  "geometry": {"coordinates":[-90.10718900000001,30.477576],"type":"Point"}
}