{
  "type": "Feature",
  "properties": {
    "iso:country":"US",
    "sg:address":"5630 Crowder Blvd",
    "sg:city":"New Orleans",
    "sg:classifiers":[
        {
            "category":"Education",
            "subcategory":"Vocational School",
            "type":"Public Place"
        }
    ],
    "sg:phone":"+1 504 244 0041",
    "sg:postcode":"70127",
    "sg:province":"LA",
    "sg:tags":[
        "training",
        "computer"
    ],
    "wof:name":"Dolphin Technologies",
    "wof:placetype":"venue"
},
  "geometry": {"coordinates":[-89.99247200000001,30.027494],"type":"Point"}
}