{
  "type": "Feature",
  "properties": {
    "iso:country":"US",
    "sg:address":"8280 Siegen Ln",
    "sg:city":"Baton Rouge",
    "sg:classifiers":[
        {
            "category":"Manufacturing",
            "subcategory":"Retail Goods",
            "type":"Manufacturing & Wholesale Goods"
        }
    ],
    "sg:phone":"+1 225 766 4632",
    "sg:postcode":"70810",
    "sg:province":"LA",
    "sg:tags":[
        "product",
        "mfg"
    ],
    "wof:name":"K Tek Corp",
    "wof:placetype":"venue"
},
  "geometry": {"coordinates":[-91.070578,30.37407],"type":"Point"}
}