{
  "type": "Feature",
  "properties": {
    "addr:full":"410 N Bonner St Ruston LA 71270",
    "addr:housenumber":"410",
    "addr:postcode":"71270",
    "addr:street":"N Bonner St",
    "iso:country":"US",
    "sg:address":"410 N Bonner St",
    "sg:city":"Ruston",
    "sg:classifiers":[
        {
            "category":"Shopping",
            "subcategory":"Gifts & Souvenirs",
            "type":"Retail Goods"
        }
    ],
    "sg:phone":"+1 318 255 3350",
    "sg:postcode":"71270",
    "sg:province":"LA",
    "sg:tags":[
        "shop"
    ],
    "wof:name":"Townsend House Gifts",
    "wof:placetype":"venue"
},
  "geometry": {"coordinates":[-92.636578,32.532249],"type":"Point"}
}