{
  "type": "Feature",
  "properties": {
    "addr:full":"3030 Barrow St Houma LA 70360",
    "addr:housenumber":"3030",
    "addr:postcode":"70360",
    "addr:street":"Barrow St",
    "iso:country":"US",
    "sg:address":"3030 Barrow St",
    "sg:city":"Houma",
    "sg:classifiers":[
        {
            "category":"Manufacturing",
            "subcategory":"Printing",
            "type":"Manufacturing & Wholesale Goods"
        }
    ],
    "sg:phone":"+1 985 857 2210",
    "sg:postcode":"70360",
    "sg:province":"LA",
    "sg:tags":[
        "newspaper",
        "publishing"
    ],
    "sg:website":"www.houmatoday.com",
    "wof:name":"Houma Daily Courier & The Terr",
    "wof:placetype":"venue"
},
  "geometry": {"coordinates":[-90.726136,29.576653],"type":"Point"}
}