{
  "type": "Feature",
  "properties": {
    "iso:country":"US",
    "sg:address":"101 Westridge Dr",
    "sg:city":"West Monroe",
    "sg:classifiers":[
        {
            "category":"Shopping",
            "subcategory":"Computers & Home Electronics",
            "type":"Retail Goods"
        }
    ],
    "sg:phone":"+1 318 397 1341",
    "sg:postcode":"71291",
    "sg:province":"LA",
    "sg:tags":[
        "parts",
        "supply"
    ],
    "wof:name":"Computer Supplies Unlimited",
    "wof:placetype":"venue"
},
  "geometry": {"coordinates":[-92.17694899999999,32.515729],"type":"Point"}
}