{
  "type": "Feature",
  "properties": {
    "iso:country":"US",
    "sg:address":"506 Martin Luther King Dr",
    "sg:city":"Deridder",
    "sg:classifiers":[
        {
            "category":"Education",
            "subcategory":"School",
            "type":"Public Place"
        }
    ],
    "sg:phone":"+1 337 462 2709",
    "sg:postcode":"70634",
    "sg:province":"LA",
    "wof:name":"Beauregard Alternative School",
    "wof:placetype":"venue"
},
  "geometry": {"coordinates":[-93.272133,30.841274],"type":"Point"}
}