{
  "type": "Feature",
  "properties": {
    "iso:country":"US",
    "sg:address":"6721 Exchequer Dr",
    "sg:city":"Baton Rouge",
    "sg:classifiers":[
        {
            "category":"Restaurant",
            "type":"Food & Drink"
        }
    ],
    "sg:phone":"+1 225 755 1577",
    "sg:postcode":"70809",
    "sg:province":"LA",
    "wof:name":"Samuel's Restaurant",
    "wof:placetype":"venue"
},
  "geometry": {"coordinates":[-91.050094,30.378308],"type":"Point"}
}