{
  "type": "Feature",
  "properties": {
    "iso:country":"US",
    "sg:address":"2134 Bayou Rd",
    "sg:city":"Thibodaux",
    "sg:classifiers":[
        {
            "category":"Professional",
            "type":"Services"
        }
    ],
    "sg:phone":"+1 985 447 5656",
    "sg:postcode":"70301",
    "sg:province":"LA",
    "sg:tags":[
        "establishment"
    ],
    "wof:name":"Opportunity Place Find Work",
    "wof:placetype":"venue"
},
  "geometry": {"coordinates":[-90.896573,29.820865],"type":"Point"}
}