{
  "type": "Feature",
  "properties": {
    "addr:full":"862 Lark Ave Shreveport LA 71105",
    "addr:housenumber":"862",
    "addr:postcode":"71105",
    "addr:street":"Lark Ave",
    "iso:country":"US",
    "sg:address":"862 Lark Ave",
    "sg:city":"Shreveport",
    "sg:classifiers":[
        {
            "category":"Wholesale",
            "subcategory":"Home Furnishings",
            "type":"Manufacturing & Wholesale Goods"
        }
    ],
    "sg:phone":"+1 318 865 0901",
    "sg:postcode":"71105",
    "sg:province":"LA",
    "sg:tags":[
        "pottery"
    ],
    "wof:name":"George Peters Wholesale Pttry",
    "wof:placetype":"venue"
},
  "geometry": {"coordinates":[-93.710234,32.477493],"type":"Point"}
}