{
  "type": "Feature",
  "properties": {
    "addr:full":"2815 Monroe Ave Baton Rouge LA 70802",
    "addr:housenumber":"2815",
    "addr:postcode":"70802",
    "addr:street":"Monroe Ave",
    "iso:country":"US",
    "sg:address":"2815 Monroe Ave",
    "sg:city":"Baton Rouge",
    "sg:classifiers":[
        {
            "category":"Professional",
            "subcategory":"Business Services",
            "type":"Services"
        }
    ],
    "sg:phone":"+1 225 344 4777",
    "sg:postcode":"70802",
    "sg:province":"LA",
    "sg:tags":[
        "packaging"
    ],
    "wof:name":"Industrial Packaging & Supply",
    "wof:placetype":"venue"
},
  "geometry": {"coordinates":[-91.15894900000001,30.469452],"type":"Point"}
}