{
  "type": "Feature",
  "properties": {
    "addr:full":"13434 Plank Rd Baker LA 70714",
    "addr:housenumber":"13434",
    "addr:postcode":"70714",
    "addr:street":"Plank Rd",
    "iso:country":"US",
    "sg:address":"13434 Plank Rd",
    "sg:city":"Baker",
    "sg:classifiers":[
        {
            "category":"Freight",
            "type":"Transportation"
        }
    ],
    "sg:phone":"+1 225 938 3110",
    "sg:postcode":"70714",
    "sg:province":"LA",
    "sg:tags":[
        "distance",
        "long",
        "trucking"
    ],
    "wof:name":"M D Lowe Transport",
    "wof:placetype":"venue"
},
  "geometry": {"coordinates":[-91.130551,30.567262],"type":"Point"}
}