{
  "type": "Feature",
  "properties": {
    "addr:full":"1408 W Willow St Lafayette LA 70506",
    "addr:housenumber":"1408",
    "addr:postcode":"70506",
    "addr:street":"W Willow St",
    "iso:country":"US",
    "sg:address":"1408 W Willow St",
    "sg:city":"Lafayette",
    "sg:classifiers":[
        {
            "category":"Real Estate",
            "subcategory":"Real Estate Operator",
            "type":"Services"
        }
    ],
    "sg:phone":"+1 337 235 7611",
    "sg:postcode":"70506",
    "sg:province":"LA",
    "sg:tags":[
        "apartment"
    ],
    "wof:name":"Willow Creek Apartments",
    "wof:placetype":"venue"
},
  "geometry": {"coordinates":[-92.039717,30.244693],"type":"Point"}
}