{
  "type": "Feature",
  "properties": {
    "iso:country":"US",
    "sg:address":"60267 8th St",
    "sg:city":"Lacombe",
    "sg:classifiers":[
        {
            "category":"Government",
            "subcategory":"Fire Station",
            "type":"Public Place"
        }
    ],
    "sg:phone":"+1 985 000 1111",
    "sg:postcode":"70445",
    "sg:province":"LA",
    "sg:tags":[
        "department"
    ],
    "wof:name":"Franklinton Fire Dept",
    "wof:placetype":"venue"
},
  "geometry": {"coordinates":[-89.938655,30.311742],"type":"Point"}
}