{
  "type": "Feature",
  "properties": {
    "iso:country":"US",
    "sg:address":"5839 E Kings Hwy",
    "sg:city":"Shreveport",
    "sg:classifiers":[
        {
            "category":"Health Services",
            "subcategory":"Doctor",
            "type":"Services"
        }
    ],
    "sg:phone":"+1 318 868 4072",
    "sg:postcode":"71105",
    "sg:province":"LA",
    "sg:tags":[
        "dentist"
    ],
    "wof:name":"East Kings Dental Arts",
    "wof:placetype":"venue"
},
  "geometry": {"coordinates":[-93.708361,32.455532],"type":"Point"}
}