{
  "type": "Feature",
  "properties": {
    "iso:country":"US",
    "sg:address":"1120 Veterans Memorial Dr",
    "sg:city":"Abbeville",
    "sg:classifiers":[
        {
            "category":"Food & Beverages",
            "subcategory":"Meat & Fish",
            "type":"Retail Goods"
        }
    ],
    "sg:phone":"+1 337 740 0806",
    "sg:postcode":"70510",
    "sg:province":"LA",
    "sg:tags":[
        "seafood"
    ],
    "wof:name":"Stelly's Boiling Spot",
    "wof:placetype":"venue"
},
  "geometry": {"coordinates":[-92.123963,29.981575],"type":"Point"}
}