{
  "type": "Feature",
  "properties": {
    "iso:country":"US",
    "sg:address":"505 Main St",
    "sg:city":"La Place",
    "sg:classifiers":[
        {
            "category":"Manufacturing",
            "subcategory":"Tools & Machinery",
            "type":"Manufacturing & Wholesale Goods"
        }
    ],
    "sg:phone":"+1 985 651 6245",
    "sg:postcode":"70068",
    "sg:province":"LA",
    "sg:tags":[
        "equipment",
        "industrial",
        "supply"
    ],
    "wof:name":"Industrial Analyzer Specialist",
    "wof:placetype":"venue"
},
  "geometry": {"coordinates":[-90.483861,30.063813],"type":"Point"}
}