{
  "type": "Feature",
  "properties": {
    "iso:country":"US",
    "sg:address":"1765 Oneal Ln",
    "sg:city":"Baton Rouge",
    "sg:classifiers":[
        {
            "category":"Freight",
            "type":"Transportation"
        }
    ],
    "sg:phone":"+1 225 275 6891",
    "sg:postcode":"70816",
    "sg:province":"LA",
    "sg:tags":[
        "record"
    ],
    "wof:name":"Precise Records Management",
    "wof:placetype":"venue"
},
  "geometry": {"coordinates":[-91.00741499999999,30.444269],"type":"Point"}
}