{
  "type": "Feature",
  "properties": {
    "addr:full":"408 S Adams Ave Rayne LA 70578",
    "addr:housenumber":"408",
    "addr:postcode":"70578",
    "addr:street":"S Adams Ave",
    "iso:country":"US",
    "sg:address":"408 S Adams Ave",
    "sg:city":"Rayne",
    "sg:classifiers":[
        {
            "category":"Shopping",
            "subcategory":"Books",
            "type":"Retail Goods"
        }
    ],
    "sg:phone":"+1 337 334 7322",
    "sg:postcode":"70578",
    "sg:province":"LA",
    "wof:name":"Rayne Religious Shop",
    "wof:placetype":"venue"
},
  "geometry": {"coordinates":[-92.26885900000001,30.232882],"type":"Point"}
}