{
  "type": "Feature",
  "properties": {
    "iso:country":"US",
    "sg:address":"4217 E Judge Perez Dr",
    "sg:city":"Meraux",
    "sg:classifiers":[
        {
            "category":"Shopping",
            "subcategory":"Discount & Variety Stores",
            "type":"Retail Goods"
        }
    ],
    "sg:phone":"+1 504 277 8703",
    "sg:postcode":"70075",
    "sg:province":"LA",
    "wof:name":"Dollar Mart",
    "wof:placetype":"venue"
},
  "geometry": {"coordinates":[-89.921532,29.93483],"type":"Point"}
}