{
  "type": "Feature",
  "properties": {
    "iso:country":"US",
    "sg:address":"303 Sweetbriar Dr",
    "sg:city":"Alexandria",
    "sg:classifiers":[
        {
            "category":"Shopping",
            "subcategory":"Bicycles & Sporting Goods",
            "type":"Retail Goods"
        }
    ],
    "sg:phone":"+1 318 445 8553",
    "sg:postcode":"71303",
    "sg:province":"LA",
    "wof:name":"Davis Wholesale Inc",
    "wof:placetype":"venue"
},
  "geometry": {"coordinates":[-92.48439500000001,31.29705],"type":"Point"}
}