{
  "type": "Feature",
  "properties": {
    "addr:full":"6076 Dorchester Cir Keithville LA 71047",
    "addr:housenumber":"6076",
    "addr:postcode":"71047",
    "addr:street":"Dorchester Cir",
    "iso:country":"US",
    "sg:address":"6076 Dorchester Cir",
    "sg:city":"Keithville",
    "sg:classifiers":[
        {
            "category":"Real Estate",
            "subcategory":"Real Estate Agent",
            "type":"Services"
        }
    ],
    "sg:phone":"+1 318 925 6697",
    "sg:postcode":"71047",
    "sg:province":"LA",
    "sg:tags":[
        "broker"
    ],
    "wof:name":"Veterans Real Estate",
    "wof:placetype":"venue"
},
  "geometry": {"coordinates":[-93.867047,32.364385],"type":"Point"}
}