{
  "type": "Feature",
  "properties": {
    "iso:country":"US",
    "sg:address":"32365 Burgess Rd Exd",
    "sg:city":"Denham Springs",
    "sg:classifiers":[
        {
            "category":"Building & Trades",
            "subcategory":"Electrical",
            "type":"Services"
        }
    ],
    "sg:phone":"+1 225 665 5314",
    "sg:postcode":"70706",
    "sg:province":"LA",
    "sg:tags":[
        "electric",
        "contractor"
    ],
    "wof:name":"Martello Electric Inc",
    "wof:placetype":"venue"
},
  "geometry": {"coordinates":[-90.89622,30.534869],"type":"Point"}
}