{
  "type": "Feature",
  "properties": {
    "addr:full":"405 Gretna Blvd Gretna LA 70053",
    "addr:housenumber":"405",
    "addr:postcode":"70053",
    "addr:street":"Gretna Blvd",
    "iso:country":"US",
    "sg:address":"405 Gretna Blvd",
    "sg:city":"Gretna",
    "sg:classifiers":[
        {
            "category":"Social Services",
            "type":"Services"
        }
    ],
    "sg:phone":"+1 504 361 3672",
    "sg:postcode":"70053",
    "sg:province":"LA",
    "sg:tags":[
        "worker"
    ],
    "wof:name":"Counseling & Consultation",
    "wof:placetype":"venue"
},
  "geometry": {"coordinates":[-90.045979,29.901245],"type":"Point"}
}