{
  "type": "Feature",
  "properties": {
    "addr:full":"600 Aurora Dr New Orleans LA 70131",
    "addr:housenumber":"600",
    "addr:postcode":"70131",
    "addr:street":"Aurora Dr",
    "iso:country":"US",
    "sg:address":"600 Aurora Dr",
    "sg:city":"New Orleans",
    "sg:classifiers":[
        {
            "category":"Building & Trades",
            "subcategory":"Construction",
            "type":"Services"
        }
    ],
    "sg:phone":"+1 504 392 2764",
    "sg:postcode":"70131",
    "sg:province":"LA",
    "sg:tags":[
        "house"
    ],
    "wof:name":"Wiechers Renovation Services",
    "wof:placetype":"venue"
},
  "geometry": {"coordinates":[-89.98820000000001,29.920503],"type":"Point"}
}