{
  "type": "Feature",
  "properties": {
    "iso:country":"US",
    "sg:address":"136 Saint David Church Rd",
    "sg:city":"Ruston",
    "sg:classifiers":[
        {
            "category":"Organizations",
            "subcategory":"Religious Organization",
            "type":"Services"
        }
    ],
    "sg:phone":"+1 318 255 5434",
    "sg:postcode":"71270",
    "sg:province":"LA",
    "sg:tags":[
        "church"
    ],
    "wof:name":"St David Baptist Church",
    "wof:placetype":"venue"
},
  "geometry": {"coordinates":[-92.655147,32.590031],"type":"Point"}
}