{
  "type": "Feature",
  "properties": {
    "iso:country":"US",
    "sg:address":"392 Longwood Dr",
    "sg:city":"Destrehan",
    "sg:classifiers":[
        {
            "category":"Professional",
            "subcategory":"Business Services",
            "type":"Services"
        }
    ],
    "sg:phone":"+1 985 764 7857",
    "sg:postcode":"70047",
    "sg:province":"LA",
    "wof:name":"Corvette Solutions",
    "wof:placetype":"venue"
},
  "geometry": {"coordinates":[-90.374409,29.954343],"type":"Point"}
}