{
  "type": "Feature",
  "properties": {
    "addr:full":"761 W Tunnel Blvd Houma LA 70360",
    "addr:housenumber":"761",
    "addr:postcode":"70360",
    "addr:street":"W Tunnel Blvd",
    "iso:country":"US",
    "sg:address":"761 W Tunnel Blvd",
    "sg:city":"Houma",
    "sg:classifiers":[
        {
            "category":"Health Services",
            "subcategory":"Doctor",
            "type":"Services"
        }
    ],
    "sg:phone":"+1 985 868 4681",
    "sg:postcode":"70360",
    "sg:province":"LA",
    "sg:tags":[
        "dentist"
    ],
    "wof:name":"Benoit Family Dentistry",
    "wof:placetype":"venue"
},
  "geometry": {"coordinates":[-90.73048199999999,29.590471],"type":"Point"}
}