{
  "type": "Feature",
  "properties": {
    "addr:full":"1901 N 18th St Baton Rouge LA 70802",
    "addr:housenumber":"1901",
    "addr:postcode":"70802",
    "addr:street":"N 18Th St",
    "iso:country":"US",
    "sg:address":"1901 N 18th St",
    "sg:city":"Baton Rouge",
    "sg:classifiers":[
        {
            "category":"Organizations",
            "subcategory":"Religious Organization",
            "type":"Services"
        }
    ],
    "sg:phone":"+1 225 343 6500",
    "sg:postcode":"70802",
    "sg:province":"LA",
    "sg:tags":[
        "church"
    ],
    "wof:name":"New Beginnings Ministries",
    "wof:placetype":"venue"
},
  "geometry": {"coordinates":[-91.170856,30.467375],"type":"Point"}
}