{
  "type": "Feature",
  "properties": {
    "addr:full":"3752 North Blvd Baton Rouge LA 70806",
    "addr:housenumber":"3752",
    "addr:postcode":"70806",
    "addr:street":"North Blvd",
    "iso:country":"US",
    "sg:address":"3752 North Blvd",
    "sg:city":"Baton Rouge",
    "sg:classifiers":[
        {
            "category":"Professional",
            "subcategory":"Accounting & Tax Preparation",
            "type":"Services"
        }
    ],
    "sg:phone":"+1 225 343 4715",
    "sg:postcode":"70806",
    "sg:province":"LA",
    "wof:name":"Bennett Group The",
    "wof:placetype":"venue"
},
  "geometry": {"coordinates":[-91.150769,30.448332],"type":"Point"}
}