{
  "type": "Feature",
  "properties": {
    "iso:country":"US",
    "sg:address":"7650 State Rte 23",
    "sg:city":"Belle Chasse",
    "sg:classifiers":[
        {
            "category":"Autos & Motor Vehicles",
            "subcategory":"Auto Supplies",
            "type":"Retail Goods"
        }
    ],
    "sg:phone":"+1 504 394 5654",
    "sg:postcode":"70037",
    "sg:province":"LA",
    "sg:tags":[
        "tire"
    ],
    "wof:name":"Delta Tire & Automotive",
    "wof:placetype":"venue"
},
  "geometry": {"coordinates":[-90.001357,29.866335],"type":"Point"}
}