{
  "type": "Feature",
  "properties": {
    "addr:full":"3414 Canal St New Orleans LA 70119",
    "addr:housenumber":"3414",
    "addr:postcode":"70119",
    "addr:street":"Canal St",
    "iso:country":"US",
    "sg:address":"3414 Canal St",
    "sg:city":"New Orleans",
    "sg:classifiers":[
        {
            "category":"Professional",
            "subcategory":"Lawyer & Legal Services",
            "type":"Services"
        }
    ],
    "sg:phone":"+1 504 483 9330",
    "sg:postcode":"70119",
    "sg:province":"LA",
    "sg:tags":[
        "attorney"
    ],
    "wof:name":"Locicero & Labourdette",
    "wof:placetype":"venue"
},
  "geometry": {"coordinates":[-90.095119,29.970639],"type":"Point"}
}