{
  "type": "Feature",
  "properties": {
    "addr:full":"3750 Hwy 1 Raceland LA 70394",
    "addr:housenumber":"3750",
    "addr:postcode":"70394",
    "addr:street":"Hwy 1",
    "iso:country":"US",
    "sg:address":"3750 Hwy 1",
    "sg:city":"Raceland",
    "sg:classifiers":[
        {
            "category":"Banks & Credit Unions",
            "subcategory":"Bank",
            "type":"Services"
        }
    ],
    "sg:phone":"+1 985 537 6324",
    "sg:postcode":"70394",
    "sg:province":"LA",
    "wof:name":"Community Bank",
    "wof:placetype":"venue"
},
  "geometry": {"coordinates":[-90.608306,29.730556],"type":"Point"}
}