{
  "type": "Feature",
  "properties": {
    "iso:country":"US",
    "sg:address":"1615 N Florida St",
    "sg:city":"Covington",
    "sg:classifiers":[
        {
            "category":"Education",
            "subcategory":"School",
            "type":"Public Place"
        }
    ],
    "sg:phone":"+1 985 892 0869",
    "sg:postcode":"70433",
    "sg:province":"LA",
    "wof:name":"ELMER E Lyon Elementary School",
    "wof:placetype":"venue"
},
  "geometry": {"coordinates":[-90.096751,30.490874],"type":"Point"}
}