{
  "type": "Feature",
  "properties": {
    "addr:full":"4051 Clematis St New Orleans LA 70122",
    "addr:housenumber":"4051",
    "addr:postcode":"70122",
    "addr:street":"Clematis St",
    "iso:country":"US",
    "sg:address":"4051 Clematis St",
    "sg:city":"New Orleans",
    "sg:classifiers":[
        {
            "category":"Shopping",
            "subcategory":"Florist",
            "type":"Retail Goods"
        }
    ],
    "sg:phone":"+1 504 949 3395",
    "sg:postcode":"70122",
    "sg:province":"LA",
    "wof:name":"Beauty Rose Florist",
    "wof:placetype":"venue"
},
  "geometry": {"coordinates":[-90.055381,30.000449],"type":"Point"}
}