{
  "type": "Feature",
  "properties": {
    "iso:country":"US",
    "sg:address":"308 W Tampico St",
    "sg:city":"New Iberia",
    "sg:classifiers":[
        {
            "category":"Shopping",
            "subcategory":"Gifts & Souvenirs",
            "type":"Retail Goods"
        }
    ],
    "sg:phone":"+1 337 367 7839",
    "sg:postcode":"70563",
    "sg:province":"LA",
    "sg:tags":[
        "shop",
        "novelty"
    ],
    "wof:name":"Broussards Old House Florist",
    "wof:placetype":"venue"
},
  "geometry": {"coordinates":[-91.815507,30.027862],"type":"Point"}
}