{
  "type": "Feature",
  "properties": {
    "iso:country":"US",
    "sg:address":"317 Senate Dr",
    "sg:city":"Westwego",
    "sg:classifiers":[
        {
            "category":"Building & Trades",
            "subcategory":"Construction",
            "type":"Services"
        }
    ],
    "sg:phone":"+1 504 436 6212",
    "sg:postcode":"70094",
    "sg:province":"LA",
    "sg:tags":[
        "house"
    ],
    "wof:name":"Fgm Construction Company Inc",
    "wof:placetype":"venue"
},
  "geometry": {"coordinates":[-90.226596,29.912813],"type":"Point"}
}