{
  "type": "Feature",
  "properties": {
    "iso:country":"US",
    "sg:address":"111 W 3rd St",
    "sg:city":"Crowley",
    "sg:classifiers":[
        {
            "category":"Personal",
            "subcategory":"Beauty Salon",
            "type":"Services"
        }
    ],
    "sg:phone":"+1 337 783 1317",
    "sg:postcode":"70526",
    "sg:province":"LA",
    "wof:name":"Dugar's Klassy Kutts Beauty",
    "wof:placetype":"venue"
},
  "geometry": {"coordinates":[-92.372271,30.211571],"type":"Point"}
}