{
  "type": "Feature",
  "properties": {
    "addr:full":"2474 Hwy 118 Florien LA 71429",
    "addr:housenumber":"2474",
    "addr:postcode":"71429",
    "addr:street":"Hwy 118 Florien",
    "iso:country":"US",
    "sg:address":"2474 Hwy 118",
    "sg:city":"Florien",
    "sg:classifiers":[
        {
            "category":"Professional",
            "type":"Services"
        }
    ],
    "sg:phone":"+1 318 586 3948",
    "sg:postcode":"71429",
    "sg:province":"LA",
    "wof:name":"Funderburk Timber Inc",
    "wof:placetype":"venue"
},
  "geometry": {"coordinates":[-93.42288600000001,31.465659],"type":"Point"}
}