{
  "type": "Feature",
  "properties": {
    "iso:country":"US",
    "sg:address":"128 Skinner St",
    "sg:city":"Merryville",
    "sg:classifiers":[
        {
            "category":"Organizations",
            "subcategory":"Religious Organization",
            "type":"Services"
        }
    ],
    "sg:phone":"+1 337 825 7700",
    "sg:postcode":"70653",
    "sg:province":"LA",
    "sg:tags":[
        "church"
    ],
    "wof:name":"Antioch Baptist Church",
    "wof:placetype":"venue"
},
  "geometry": {"coordinates":[-93.539691,30.769336],"type":"Point"}
}