{
  "type": "Feature",
  "properties": {
    "addr:full":"4204 Lac Bienville Dr Harvey LA 70058",
    "addr:housenumber":"4204",
    "addr:postcode":"70058",
    "addr:street":"Lac Bienville Dr",
    "iso:country":"US",
    "sg:address":"4204 Lac Bienville Dr",
    "sg:city":"Harvey",
    "sg:classifiers":[
        {
            "category":"Building & Trades",
            "subcategory":"Cleaning & Sanitation",
            "type":"Services"
        }
    ],
    "sg:phone":"+1 504 263 1559",
    "sg:postcode":"70058",
    "sg:province":"LA",
    "sg:tags":[
        "maintenance"
    ],
    "wof:name":"Cousins Cleaning Svcs",
    "wof:placetype":"venue"
},
  "geometry": {"coordinates":[-90.04514,29.843787],"type":"Point"}
}