{
  "type": "Feature",
  "properties": {
    "iso:country":"US",
    "sg:address":"2000 Oak Park Blvd",
    "sg:city":"Lake Charles",
    "sg:classifiers":[
        {
            "category":"Health Services",
            "subcategory":"Health Practitioner",
            "type":"Services"
        }
    ],
    "sg:phone":"+1 337 474 3880",
    "sg:postcode":"70601",
    "sg:province":"LA",
    "sg:tags":[
        "audiologists"
    ],
    "wof:name":"Hearing Center Of Lake Charles",
    "wof:placetype":"venue"
},
  "geometry": {"coordinates":[-93.18924,30.203405],"type":"Point"}
}