{
  "type": "Feature",
  "properties": {
    "iso:country":"US",
    "sg:address":"108 Lirette St",
    "sg:city":"Chauvin",
    "sg:classifiers":[
        {
            "category":"Recreation",
            "type":"Entertainment"
        }
    ],
    "sg:phone":"+1 985 594 4242",
    "sg:postcode":"70360",
    "sg:province":"LA",
    "sg:tags":[
        "pool",
        "swimming"
    ],
    "wof:name":"Chauvin Swimming Pool",
    "wof:placetype":"venue"
},
  "geometry": {"coordinates":[-90.806999,29.582415],"type":"Point"}
}