{
  "type": "Feature",
  "properties": {
    "iso:country":"US",
    "sg:address":"1636 Toledano St",
    "sg:city":"New Orleans",
    "sg:classifiers":[
        {
            "category":"Organizations",
            "subcategory":"Non-profit Organization",
            "type":"Services"
        }
    ],
    "sg:phone":"+1 504 897 2606",
    "sg:postcode":"70115",
    "sg:province":"LA",
    "sg:website":"www.noshc.org",
    "wof:name":"New Orleans Speech & Hearing",
    "wof:placetype":"venue"
},
  "geometry": {"coordinates":[-90.090688,29.92931],"type":"Point"}
}