{
  "type": "Feature",
  "properties": {
    "iso:country":"US",
    "sg:address":"725 E Cornerview St",
    "sg:city":"Gonzales",
    "sg:classifiers":[
        {
            "category":"Insurance",
            "subcategory":"Insurance Agent",
            "type":"Services"
        }
    ],
    "sg:phone":"+1 225 647 2168",
    "sg:postcode":"70737",
    "sg:province":"LA",
    "sg:website":"www.robertinsurance.com",
    "wof:name":"Harry Robert Insurance",
    "wof:placetype":"venue"
},
  "geometry": {"coordinates":[-90.914492,30.232822],"type":"Point"}
}