{
  "type": "Feature",
  "properties": {
    "addr:full":"308 Church St Houma LA 70360",
    "addr:housenumber":"308",
    "addr:postcode":"70360",
    "addr:street":"Church St",
    "iso:country":"US",
    "sg:address":"308 Church St",
    "sg:city":"Houma",
    "sg:classifiers":[
        {
            "category":"Insurance",
            "subcategory":"Insurance Agent",
            "type":"Services"
        }
    ],
    "sg:phone":"+1 985 868 9226",
    "sg:postcode":"70360",
    "sg:province":"LA",
    "sg:tags":[
        "adjuster"
    ],
    "wof:name":"M G & Assoc Adjusting Svc",
    "wof:placetype":"venue"
},
  "geometry": {"coordinates":[-90.722568,29.596281],"type":"Point"}
}