{
  "type": "Feature",
  "properties": {
    "iso:country":"US",
    "sg:address":"2600 Mary Dr",
    "sg:city":"Slidell",
    "sg:classifiers":[
        {
            "category":"Real Estate",
            "subcategory":"Real Estate Agent",
            "type":"Services"
        }
    ],
    "sg:phone":"+1 985 781 6080",
    "sg:postcode":"70458",
    "sg:province":"LA",
    "sg:tags":[
        "authorities",
        "housing"
    ],
    "wof:name":"Sunshine Village Housing Corp",
    "wof:placetype":"venue"
},
  "geometry": {"coordinates":[-89.78285099999999,30.268404],"type":"Point"}
}