{
  "type": "Feature",
  "properties": {
    "iso:country":"US",
    "sg:address":"815 Ravendale Dr",
    "sg:city":"Shreveport",
    "sg:classifiers":[
        {
            "category":"Health Services",
            "subcategory":"Nursing And Care Facility",
            "type":"Services"
        }
    ],
    "sg:phone":"+1 318 424 8457",
    "sg:postcode":"71107",
    "sg:province":"LA",
    "wof:name":"Evergreen Presbt Ministries",
    "wof:placetype":"venue"
},
  "geometry": {"coordinates":[-93.78139400000001,32.559504],"type":"Point"}
}