{
  "type": "Feature",
  "properties": {
    "iso:country":"US",
    "sg:address":"1010 Jack Wells Blvd",
    "sg:city":"Shreveport",
    "sg:classifiers":[
        {
            "category":"Wholesale",
            "subcategory":"Stationery",
            "type":"Manufacturing & Wholesale Goods"
        }
    ],
    "sg:phone":"+1 318 222 3668",
    "sg:postcode":"71107",
    "sg:province":"LA",
    "sg:tags":[
        "box",
        "fiber"
    ],
    "wof:name":"Boxes For Less",
    "wof:placetype":"venue"
},
  "geometry": {"coordinates":[-93.75344699999999,32.533871],"type":"Point"}
}