{
  "type": "Feature",
  "properties": {
    "iso:country":"US",
    "sg:address":"5928 W Metairie Ave",
    "sg:city":"Metairie",
    "sg:classifiers":[
        {
            "category":"Education",
            "subcategory":"Dance Studio",
            "type":"Public Place"
        }
    ],
    "sg:phone":"+1 504 818 0895",
    "sg:postcode":"70003",
    "sg:province":"LA",
    "sg:tags":[
        "instruction",
        "dancing"
    ],
    "wof:name":"Planet Dance Productions",
    "wof:placetype":"venue"
},
  "geometry": {"coordinates":[-90.200912,29.983857],"type":"Point"}
}