{
  "type": "Feature",
  "properties": {
    "addr:full":"2921 Williamson Way Shreveport LA 71118",
    "addr:housenumber":"2921",
    "addr:postcode":"71118",
    "addr:street":"Williamson Way",
    "iso:country":"US",
    "sg:address":"2921 Williamson Way",
    "sg:city":"Shreveport",
    "sg:classifiers":[
        {
            "category":"Banks & Credit Unions",
            "subcategory":"Bank",
            "type":"Services"
        }
    ],
    "sg:phone":"+1 318 687 8700",
    "sg:postcode":"71118",
    "sg:province":"LA",
    "sg:tags":[
        "financial"
    ],
    "sg:website":"http://www.wesla.org",
    "wof:name":"Wesla Federal Credit Union",
    "wof:placetype":"venue"
},
  "geometry": {"coordinates":[-93.81519299999999,32.381978],"type":"Point"}
}