{
  "type": "Feature",
  "properties": {
    "iso:country":"US",
    "sg:address":"7329 Freret St",
    "sg:city":"New Orleans",
    "sg:classifiers":[
        {
            "category":"Cafe",
            "type":"Food & Drink"
        }
    ],
    "sg:menulink":"http://www.allmenus.com/la/new-orleans/281653-cafe-freret/menu/",
    "sg:phone":"+1 504 861 8014",
    "sg:postcode":"70118",
    "sg:province":"LA",
    "sg:tags":[
        "american"
    ],
    "wof:name":"Cafe Freret",
    "wof:placetype":"venue"
},
  "geometry": {"coordinates":[-90.125213,29.94116],"type":"Point"}
}