{
  "type": "Feature",
  "properties": {
    "iso:country":"US",
    "sg:address":"5208 Jackson St Exd",
    "sg:city":"Alexandria",
    "sg:classifiers":[
        {
            "category":"Professional",
            "subcategory":"Lawyer & Legal Services",
            "type":"Services"
        }
    ],
    "sg:phone":"+1 318 487 4848",
    "sg:postcode":"71303",
    "sg:province":"LA",
    "sg:tags":[
        "attorney"
    ],
    "wof:name":"Michael A Walters",
    "wof:placetype":"venue"
},
  "geometry": {"coordinates":[-92.484893,31.2712],"type":"Point"}
}