{
  "type": "Feature",
  "properties": {
    "iso:country":"US",
    "sg:address":"1301 Homer Rd",
    "sg:city":"Minden",
    "sg:classifiers":[
        {
            "category":"Real Estate",
            "subcategory":"Real Estate Operator",
            "type":"Services"
        }
    ],
    "sg:phone":"+1 318 377 1405",
    "sg:postcode":"71055",
    "sg:province":"LA",
    "sg:tags":[
        "mall",
        "shopping",
        "center"
    ],
    "wof:name":"Minden Shopping Ctr",
    "wof:placetype":"venue"
},
  "geometry": {"coordinates":[-93.252875,32.625003],"type":"Point"}
}