{
  "type": "Feature",
  "properties": {
    "iso:country":"US",
    "sg:address":"4141 Linstrom Dr",
    "sg:city":"Baton Rouge",
    "sg:classifiers":[
        {
            "category":"Health Services",
            "subcategory":"Clinic",
            "type":"Services"
        }
    ],
    "sg:phone":"+1 225 275 0709",
    "sg:postcode":"70814",
    "sg:province":"LA",
    "wof:name":"Extended Family Healthcare Svc",
    "wof:placetype":"venue"
},
  "geometry": {"coordinates":[-91.04579,30.488025],"type":"Point"}
}