{
  "type": "Feature",
  "properties": {
    "addr:full":"9464 Mansfield Rd Shreveport LA 71118",
    "addr:housenumber":"9464",
    "addr:postcode":"71118",
    "addr:street":"Mansfield Rd",
    "iso:country":"US",
    "sg:address":"9464 Mansfield Rd",
    "sg:city":"Shreveport",
    "sg:classifiers":[
        {
            "category":"Communications",
            "subcategory":"Film & Video Production",
            "type":"Services"
        }
    ],
    "sg:phone":"+1 318 687 8785",
    "sg:postcode":"71118",
    "sg:province":"LA",
    "sg:tags":[
        "motion",
        "picture",
        "studio",
        "producer"
    ],
    "wof:name":"Jim Mc Cullough Productions",
    "wof:placetype":"venue"
},
  "geometry": {"coordinates":[-93.811645,32.394613],"type":"Point"}
}