{
  "type": "Feature",
  "properties": {
    "addr:full":"20332 Vineyard Rd Hammond LA 70401",
    "addr:housenumber":"20332",
    "addr:postcode":"70401",
    "addr:street":"Vineyard Rd",
    "iso:country":"US",
    "sg:address":"20332 Vineyard Rd",
    "sg:city":"Hammond",
    "sg:classifiers":[
        {
            "category":"Personal",
            "subcategory":"Beauty Salon",
            "type":"Services"
        }
    ],
    "sg:phone":"+1 985 345 0892",
    "sg:postcode":"70401",
    "sg:province":"LA",
    "sg:tags":[
        "shop"
    ],
    "wof:name":"Judy's Beauty Salon",
    "wof:placetype":"venue"
},
  "geometry": {"coordinates":[-90.38677,30.542017],"type":"Point"}
}