{
  "type": "Feature",
  "properties": {
    "iso:country":"US",
    "sg:address":"121 Bank Ave",
    "sg:city":"New Iberia",
    "sg:classifiers":[
        {
            "category":"Food & Beverages",
            "subcategory":"Specialty",
            "type":"Retail Goods"
        }
    ],
    "sg:phone":"+1 337 365 1552",
    "sg:postcode":"70560",
    "sg:province":"LA",
    "sg:tags":[
        "vitamin"
    ],
    "wof:name":"Bank Avenue Distributors",
    "wof:placetype":"venue"
},
  "geometry": {"coordinates":[-91.813238,30.002141],"type":"Point"}
}