{
  "type": "Feature",
  "properties": {
    "addr:full":"6213 Westbank Expy Marrero LA 70072",
    "addr:housenumber":"6213",
    "addr:postcode":"70072",
    "addr:street":"Westbank Expy Marrero",
    "iso:country":"US",
    "sg:address":"6213 Westbank Expy",
    "sg:city":"Marrero",
    "sg:classifiers":[
        {
            "category":"Bars & Pubs",
            "type":"Food & Drink"
        }
    ],
    "sg:phone":"+1 504 371 4200",
    "sg:postcode":"70072",
    "sg:province":"LA",
    "sg:tags":[
        "lounge",
        "cocktail"
    ],
    "wof:name":"Brass Rail",
    "wof:placetype":"venue"
},
  "geometry": {"coordinates":[-90.11533799999999,29.893397],"type":"Point"}
}