{
  "type": "Feature",
  "properties": {
    "iso:country":"US",
    "sg:address":"113 River Bend Trlr Pk Rd",
    "sg:city":"Winnfield",
    "sg:classifiers":[
        {
            "category":"Personal",
            "subcategory":"Beauty Salon",
            "type":"Services"
        }
    ],
    "sg:phone":"+1 318 628 2700",
    "sg:postcode":"71483",
    "sg:province":"LA",
    "wof:name":"Personal Touch",
    "wof:placetype":"venue"
},
  "geometry": {"coordinates":[-92.602272,31.938753],"type":"Point"}
}