{
  "type": "Feature",
  "properties": {
    "addr:full":"1833 Ryan St Lake Charles LA 70601",
    "addr:housenumber":"1833",
    "addr:postcode":"70601",
    "addr:street":"Ryan St",
    "iso:country":"US",
    "sg:address":"1833 Ryan St",
    "sg:city":"Lake Charles",
    "sg:classifiers":[
        {
            "category":"Home & Garden",
            "subcategory":"Carpets & Floor Coverings",
            "type":"Retail Goods"
        }
    ],
    "sg:phone":"+1 337 433 1464",
    "sg:postcode":"70601",
    "sg:province":"LA",
    "sg:tags":[
        "dealer",
        "rug"
    ],
    "wof:name":"House Of Interiors",
    "wof:placetype":"venue"
},
  "geometry": {"coordinates":[-93.219048,30.214473],"type":"Point"}
}