{
  "type": "Feature",
  "properties": {
    "addr:full":"2021 1st St New Orleans LA 70113",
    "addr:housenumber":"2021",
    "addr:postcode":"70113",
    "addr:street":"1St St",
    "iso:country":"US",
    "sg:address":"2021 1st St",
    "sg:city":"New Orleans",
    "sg:classifiers":[
        {
            "category":"Organizations",
            "subcategory":"Religious Organization",
            "type":"Services"
        }
    ],
    "sg:phone":"+1 504 891 9846",
    "sg:postcode":"70113",
    "sg:province":"LA",
    "sg:tags":[
        "church"
    ],
    "wof:name":"Second New Light Missionary",
    "wof:placetype":"venue"
},
  "geometry": {"coordinates":[-90.085605,29.936804],"type":"Point"}
}