{
  "type": "Feature",
  "properties": {
    "addr:full":"402 Williams St Springhill LA 71075",
    "addr:housenumber":"402",
    "addr:postcode":"71075",
    "addr:street":"Williams St",
    "iso:country":"US",
    "sg:address":"402 Williams St",
    "sg:city":"Springhill",
    "sg:classifiers":[
        {
            "category":"Organizations",
            "subcategory":"Religious Organization",
            "type":"Services"
        }
    ],
    "sg:phone":"+1 318 539 4181",
    "sg:postcode":"71075",
    "sg:province":"LA",
    "sg:tags":[
        "church"
    ],
    "wof:name":"Temple Baptist Church",
    "wof:placetype":"venue"
},
  "geometry": {"coordinates":[-93.457075,32.990793],"type":"Point"}
}