{
  "type": "Feature",
  "properties": {
    "addr:full":"1307 Lake St Natchitoches LA 71457",
    "addr:housenumber":"1307",
    "addr:postcode":"71457",
    "addr:street":"Lake St",
    "iso:country":"US",
    "sg:address":"1307 Lake St",
    "sg:city":"Natchitoches",
    "sg:classifiers":[
        {
            "category":"Organizations",
            "subcategory":"Religious Organization",
            "type":"Services"
        }
    ],
    "sg:phone":"+1 318 352 6474",
    "sg:postcode":"71457",
    "sg:province":"LA",
    "sg:tags":[
        "church"
    ],
    "wof:name":"Lake Street Church Of Christ",
    "wof:placetype":"venue"
},
  "geometry": {"coordinates":[-93.102193,31.757771],"type":"Point"}
}