{
  "type": "Feature",
  "properties": {
    "iso:country":"US",
    "sg:address":"3833 Dulaney Ln",
    "sg:city":"Harvey",
    "sg:classifiers":[
        {
            "category":"Organizations",
            "subcategory":"Religious Organization",
            "type":"Services"
        }
    ],
    "sg:phone":"+1 504 348 7681",
    "sg:postcode":"70058",
    "sg:province":"LA",
    "wof:name":"Faith Enterprise",
    "wof:placetype":"venue"
},
  "geometry": {"coordinates":[-90.06917799999999,29.849159],"type":"Point"}
}