{
  "type": "Feature",
  "properties": {
    "addr:full":"1089 Bayou Dularge Rd Houma LA 70363",
    "addr:housenumber":"1089",
    "addr:postcode":"70363",
    "addr:street":"Bayou Dularge Rd",
    "iso:country":"US",
    "sg:address":"1089 Bayou Dularge Rd",
    "sg:city":"Houma",
    "sg:classifiers":[
        {
            "category":"Organizations",
            "subcategory":"Religious Organization",
            "type":"Services"
        }
    ],
    "sg:phone":"+1 985 873 8103",
    "sg:postcode":"70363",
    "sg:province":"LA",
    "sg:tags":[
        "church"
    ],
    "wof:name":"St Luke Baptist Church",
    "wof:placetype":"venue"
},
  "geometry": {"coordinates":[-90.74822,29.467479],"type":"Point"}
}