{
  "type": "Feature",
  "properties": {
    "iso:country":"US",
    "sg:address":"618 Weston St",
    "sg:city":"Minden",
    "sg:classifiers":[
        {
            "category":"Social Services",
            "subcategory":"Child Care",
            "type":"Services"
        }
    ],
    "sg:phone":"+1 318 371 1101",
    "sg:postcode":"71055",
    "sg:province":"LA",
    "sg:tags":[
        "day"
    ],
    "wof:name":"Mother Goose",
    "wof:placetype":"venue"
},
  "geometry": {"coordinates":[-93.30577099999999,32.615563],"type":"Point"}
}