{
  "type": "Feature",
  "properties": {
    "addr:full":"3421 Hwy 70 Pierre Part LA 70339",
    "addr:housenumber":"3421",
    "addr:postcode":"70339",
    "addr:street":"Hwy 70 Pierre Part",
    "iso:country":"US",
    "sg:address":"3421 Hwy 70",
    "sg:city":"Pierre Part",
    "sg:classifiers":[
        {
            "category":"Shopping",
            "subcategory":"Discount & Variety Stores",
            "type":"Retail Goods"
        }
    ],
    "sg:phone":"+1 985 252 6261",
    "sg:postcode":"70339",
    "sg:province":"LA",
    "sg:tags":[
        "merchandise",
        "general"
    ],
    "sg:website":"www.pierrepartstore.com",
    "wof:name":"Pierre Part Store LLC",
    "wof:placetype":"venue"
},
  "geometry": {"coordinates":[-91.212812,29.95782],"type":"Point"}
}