{
  "type": "Feature",
  "properties": {
    "addr:full":"809 W Vine St Opelousas LA 70570",
    "addr:housenumber":"809",
    "addr:postcode":"70570",
    "addr:street":"W Vine St",
    "iso:country":"US",
    "sg:address":"809 W Vine St",
    "sg:city":"Opelousas",
    "sg:classifiers":[
        {
            "category":"Autos & Motor Vehicles",
            "subcategory":"Fuel & Gas Station",
            "type":"Retail Goods"
        }
    ],
    "sg:phone":"+1 337 948 9086",
    "sg:postcode":"70570",
    "sg:province":"LA",
    "sg:tags":[
        "oil"
    ],
    "wof:name":"Ortego",
    "wof:placetype":"venue"
},
  "geometry": {"coordinates":[-92.09283600000001,30.533201],"type":"Point"}
}