{
  "type": "Feature",
  "properties": {
    "iso:country":"US",
    "sg:address":"802 Broadway Ave",
    "sg:city":"Alexandria",
    "sg:classifiers":[
        {
            "category":"Shopping",
            "subcategory":"Florist",
            "type":"Retail Goods"
        }
    ],
    "sg:phone":"+1 318 442 1102",
    "sg:postcode":"71302",
    "sg:province":"LA",
    "wof:name":"Mabel's Florist & Gift Shoppe",
    "wof:placetype":"venue"
},
  "geometry": {"coordinates":[-92.435907,31.29761],"type":"Point"}
}