{
  "type": "Feature",
  "properties": {
    "iso:country":"US",
    "sg:address":"30047 Industrial Park Dr",
    "sg:city":"Walker",
    "sg:classifiers":[
        {
            "category":"Building & Trades",
            "subcategory":"Construction",
            "type":"Services"
        }
    ],
    "sg:phone":"+1 225 791 8866",
    "sg:postcode":"70785",
    "sg:province":"LA",
    "sg:tags":[
        "insulation",
        "heat",
        "contractor"
    ],
    "wof:name":"Apex Insulation Inc",
    "wof:placetype":"venue"
},
  "geometry": {"coordinates":[-90.82810499999999,30.503461],"type":"Point"}
}