{
  "type": "Feature",
  "properties": {
    "addr:full":"119 Highway Alt 2 Shongaloo LA 71072",
    "addr:housenumber":"119;2",
    "addr:postcode":"71072",
    "addr:street":"Highway Alt;La",
    "iso:country":"US",
    "sg:address":"119 Highway Alt 2",
    "sg:city":"Shongaloo",
    "sg:classifiers":[
        {
            "category":"Government",
            "subcategory":"City Hall",
            "type":"Public Place"
        },
        {
            "category":"Government",
            "subcategory":"Office",
            "type":"Public Place"
        }
    ],
    "sg:phone":"+1 318 846 2876",
    "sg:postcode":"71072",
    "sg:province":"LA",
    "sg:tags":[
        "town",
        "township",
        "planner",
        "government-city",
        "village"
    ],
    "wof:name":"Village Of Shongaloo",
    "wof:placetype":"venue"
},
  "geometry": {"coordinates":[-93.29630400000001,32.941681],"type":"Point"}
}