{
  "type": "Feature",
  "properties": {
    "addr:full":"7900 Vanderkloot Ave New Orleans LA 70127",
    "addr:housenumber":"7900",
    "addr:postcode":"70127",
    "addr:street":"Vanderkloot Ave",
    "iso:country":"US",
    "sg:address":"7900 Vanderkloot Ave",
    "sg:city":"New Orleans",
    "sg:classifiers":[
        {
            "category":"Building & Trades",
            "subcategory":"Landscaping Services",
            "type":"Services"
        }
    ],
    "sg:phone":"+1 504 241 0225",
    "sg:postcode":"70127",
    "sg:province":"LA",
    "sg:tags":[
        "tree"
    ],
    "wof:name":"Bajon's Tree Svc",
    "wof:placetype":"venue"
},
  "geometry": {"coordinates":[-89.99221799999999,30.045436],"type":"Point"}
}