{
  "type": "Feature",
  "properties": {
    "iso:country":"US",
    "sg:address":"42161 Veterans Ave",
    "sg:city":"Hammond",
    "sg:classifiers":[
        {
            "category":"Health Services",
            "subcategory":"Podiatrist",
            "type":"Services"
        }
    ],
    "sg:phone":"+1 985 345 3100",
    "sg:postcode":"70403",
    "sg:province":"LA",
    "wof:name":"Foot & Ankle Health Ctr",
    "wof:placetype":"venue"
},
  "geometry": {"coordinates":[-90.45719099999999,30.47038],"type":"Point"}
}