{
  "type": "Feature",
  "properties": {
    "iso:country":"US",
    "sg:address":"258 Bendel Rd",
    "sg:city":"Lafayette",
    "sg:classifiers":[
        {
            "category":"Restaurant",
            "type":"Food & Drink"
        }
    ],
    "sg:phone":"+1 337 235 4239",
    "sg:postcode":"70503",
    "sg:province":"LA",
    "wof:name":"Edie's Express",
    "wof:placetype":"venue"
},
  "geometry": {"coordinates":[-92.01746,30.199868],"type":"Point"}
}