{
  "type": "Feature",
  "properties": {
    "addr:full":"643 Magazine St. Suite 301 New Orleans LA 70130",
    "addr:housenumber":"643;301",
    "addr:postcode":"70130",
    "addr:street":"Magazine St. Suite",
    "iso:country":"US",
    "sg:address":"643 Magazine St. Suite 301",
    "sg:city":"New Orleans",
    "sg:classifiers":[
        {
            "category":"Professional",
            "subcategory":"Advertising",
            "type":"Services"
        }
    ],
    "sg:phone":"+1 504 684 2340",
    "sg:postcode":"70130",
    "sg:province":"LA",
    "sg:tags":[
        "market-research",
        "sample",
        "technology"
    ],
    "sg:website":"http://jacksonsquaregroup.com/",
    "wof:name":"Jackson Square Group",
    "wof:placetype":"venue"
},
  "geometry": {"coordinates":[-90.06859300000001,29.947734],"type":"Point"}
}