{
  "type": "Feature",
  "properties": {
    "addr:full":"6898 Highway 1 Shreveport LA 71107",
    "addr:housenumber":"6898",
    "addr:postcode":"71107",
    "addr:street":"Highway 1",
    "iso:country":"US",
    "sg:address":"6898 Highway 1",
    "sg:city":"Shreveport",
    "sg:classifiers":[
        {
            "category":"Autos & Motor Vehicles",
            "subcategory":"Automobile Sales",
            "type":"Retail Goods"
        }
    ],
    "sg:phone":"+1 318 309 2200",
    "sg:postcode":"71107",
    "sg:province":"LA",
    "sg:tags":[
        "used",
        "car",
        "dealers-used",
        "new",
        "cars-wholesale"
    ],
    "wof:name":"Ace Auto Sales",
    "wof:placetype":"venue"
},
  "geometry": {"coordinates":[-93.885649,32.624518],"type":"Point"}
}