{
  "type": "Feature",
  "properties": {
    "addr:full":"2005 Vandevelde Ave Alexandria LA 71303",
    "addr:housenumber":"2005",
    "addr:postcode":"71303",
    "addr:street":"Vandevelde Ave",
    "iso:country":"US",
    "sg:address":"2005 Vandevelde Ave",
    "sg:city":"Alexandria",
    "sg:classifiers":[
        {
            "category":"Utilities",
            "type":"Services"
        }
    ],
    "sg:phone":"+1 318 427 1790",
    "sg:postcode":"71303",
    "sg:province":"LA",
    "wof:name":"Cleco Midstream Resources LLC",
    "wof:placetype":"venue"
},
  "geometry": {"coordinates":[-92.534015,31.33071],"type":"Point"}
}