{
  "type": "Feature",
  "properties": {
    "addr:full":"9162 Scotland Ave Baton Rouge LA 70807",
    "addr:housenumber":"9162",
    "addr:postcode":"70807",
    "addr:street":"Scotland Ave",
    "iso:country":"US",
    "sg:address":"9162 Scotland Ave",
    "sg:city":"Baton Rouge",
    "sg:classifiers":[
        {
            "category":"Shopping",
            "subcategory":"Music",
            "type":"Retail Goods"
        }
    ],
    "sg:phone":"+1 225 775 6786",
    "sg:postcode":"70807",
    "sg:province":"LA",
    "wof:name":"Bowies Record Shop Inc",
    "wof:placetype":"venue"
},
  "geometry": {"coordinates":[-91.179446,30.529426],"type":"Point"}
}