{
  "type": "Feature",
  "properties": {
    "addr:full":"358 N Acadian Throughway Baton Rouge LA 70806",
    "addr:housenumber":"358",
    "addr:postcode":"70806",
    "addr:street":"N Acadian",
    "iso:country":"US",
    "sg:address":"358 N Acadian Throughway",
    "sg:city":"Baton Rouge",
    "sg:classifiers":[
        {
            "category":"Insurance",
            "subcategory":"Insurance Agent",
            "type":"Services"
        }
    ],
    "sg:phone":"+1 225 638 6202",
    "sg:postcode":"70806",
    "sg:province":"LA",
    "wof:name":"Olympic Insurance",
    "wof:placetype":"venue"
},
  "geometry": {"coordinates":[-91.154605,30.450765],"type":"Point"}
}