{
  "type": "Feature",
  "properties": {
    "iso:country":"US",
    "sg:address":"14376 State Rte 44",
    "sg:city":"Gonzales",
    "sg:classifiers":[
        {
            "category":"Building & Trades",
            "subcategory":"Construction",
            "type":"Services"
        }
    ],
    "sg:phone":"+1 225 753 0055",
    "sg:postcode":"70737",
    "sg:province":"LA",
    "sg:tags":[
        "general",
        "contractor"
    ],
    "wof:name":"Discovery Homes",
    "wof:placetype":"venue"
},
  "geometry": {"coordinates":[-90.921269,30.277507],"type":"Point"}
}