{
  "type": "Feature",
  "properties": {
    "addr:full":"2045 Bert Kouns Industrial Loop Shreveport LA 71118",
    "addr:housenumber":"2045",
    "addr:postcode":"71118",
    "addr:street":"Bert Kouns Industrial Loop",
    "iso:country":"US",
    "sg:address":"2045 Bert Kouns Industrial Loop",
    "sg:city":"Shreveport",
    "sg:classifiers":[
        {
            "category":"Real Estate",
            "subcategory":"Real Estate Services",
            "type":"Services"
        },
        {
            "category":"Real Estate",
            "subcategory":"Real Estate Operator",
            "type":"Services"
        }
    ],
    "sg:phone":"+1 318 686 5686",
    "sg:postcode":"71118",
    "sg:province":"LA",
    "sg:tags":[
        "vacancy",
        "apartment",
        "rental",
        "finder",
        "listing"
    ],
    "sg:website":"http://www.tlproperties.com",
    "wof:name":"Brighton Manor Apartments",
    "wof:placetype":"venue"
},
  "geometry": {"coordinates":[-93.791214,32.402016],"type":"Point"}
}