{
  "type": "Feature",
  "properties": {
    "iso:country":"US",
    "sg:address":"3307 Chateau Blvd",
    "sg:city":"Kenner",
    "sg:classifiers":[
        {
            "category":"Building & Trades",
            "subcategory":"Construction",
            "type":"Services"
        }
    ],
    "sg:phone":"+1 504 468 8513",
    "sg:postcode":"70065",
    "sg:province":"LA",
    "sg:tags":[
        "coping",
        "plastering",
        "tiling",
        "pool",
        "swimming"
    ],
    "wof:name":"G & S Pool Svc",
    "wof:placetype":"venue"
},
  "geometry": {"coordinates":[-90.258005,30.017993],"type":"Point"}
}