{
  "type": "Feature",
  "properties": {
    "addr:full":"602 N Adams St Welsh LA 70591",
    "addr:housenumber":"602",
    "addr:postcode":"70591",
    "addr:street":"N Adams St",
    "iso:country":"US",
    "sg:address":"602 N Adams St",
    "sg:city":"Welsh",
    "sg:classifiers":[
        {
            "category":"Ice Cream",
            "type":"Food & Drink"
        }
    ],
    "sg:menulink":"http://www.allmenus.com/la/welsh/168398-dairy-queen/menu/",
    "sg:phone":"+1 337 734 3506",
    "sg:postcode":"70591",
    "sg:province":"LA",
    "sg:tags":[
        "burger",
        "american"
    ],
    "wof:name":"Dairy Queen",
    "wof:placetype":"venue"
},
  "geometry": {"coordinates":[-92.821652,30.242341],"type":"Point"}
}