{
  "type": "Feature",
  "properties": {
    "iso:country":"US",
    "sg:address":"44463 State Rte 431",
    "sg:city":"St Amant",
    "sg:classifiers":[
        {
            "category":"Banks & Credit Unions",
            "subcategory":"Investment Brokerage",
            "type":"Services"
        }
    ],
    "sg:phone":"+1 225 622 2623",
    "sg:postcode":"70774",
    "sg:province":"LA",
    "sg:tags":[
        "advisory",
        "financial"
    ],
    "wof:name":"Alternative Financial Sltns",
    "wof:placetype":"venue"
},
  "geometry": {"coordinates":[-90.85827,30.284734],"type":"Point"}
}