{
  "type": "Feature",
  "properties": {
    "iso:country":"US",
    "sg:address":"797 Ed Edelen Rd",
    "sg:city":"Monroe",
    "sg:classifiers":[
        {
            "category":"Real Estate",
            "subcategory":"Real Estate Operator",
            "type":"Services"
        }
    ],
    "sg:phone":"+1 318 343 0122",
    "sg:postcode":"71203",
    "sg:province":"LA",
    "sg:tags":[
        "property",
        "lessor"
    ],
    "wof:name":"4 TS Turtle Farm",
    "wof:placetype":"venue"
},
  "geometry": {"coordinates":[-91.961474,32.547065],"type":"Point"}
}