{
  "type": "Feature",
  "properties": {
    "iso:country":"US",
    "sg:address":"500 Flournoy Lucas Rd",
    "sg:city":"Shreveport",
    "sg:classifiers":[
        {
            "category":"Shopping",
            "subcategory":"Catalog Store",
            "type":"Retail Goods"
        }
    ],
    "sg:phone":"+1 318 688 1365",
    "sg:postcode":"71106",
    "sg:province":"LA",
    "sg:tags":[
        "mail",
        "order"
    ],
    "wof:name":"NIC Law Enforcement Supply",
    "wof:placetype":"venue"
},
  "geometry": {"coordinates":[-93.77013599999999,32.391008],"type":"Point"}
}