{
  "type": "Feature",
  "properties": {
    "iso:country":"US",
    "sg:address":"1260 Fisher Rd",
    "sg:city":"Many",
    "sg:classifiers":[
        {
            "category":"Real Estate",
            "subcategory":"Real Estate Operator",
            "type":"Services"
        }
    ],
    "sg:phone":"+1 318 256 8830",
    "sg:postcode":"71449",
    "sg:province":"LA",
    "sg:tags":[
        "apartment"
    ],
    "wof:name":"William E Ruffin Apartments",
    "wof:placetype":"venue"
},
  "geometry": {"coordinates":[-93.45814,31.542977],"type":"Point"}
}