{
  "type": "Feature",
  "properties": {
    "iso:country":"US",
    "sg:address":"4108 Auburn St",
    "sg:city":"Lake Charles",
    "sg:classifiers":[
        {
            "category":"Restaurant",
            "type":"Food & Drink"
        }
    ],
    "sg:phone":"+1 337 708 1480",
    "sg:postcode":"70607",
    "sg:province":"LA",
    "wof:name":"Gary's Karaoke Cafe",
    "wof:placetype":"venue"
},
  "geometry": {"coordinates":[-93.212806,30.184132],"type":"Point"}
}