{
  "type": "Feature",
  "properties": {
    "addr:full":"1132 N Carrollton Ave Baton Rouge LA 70806",
    "addr:housenumber":"1132",
    "addr:postcode":"70806",
    "addr:street":"N Carrollton Ave",
    "iso:country":"US",
    "sg:address":"1132 N Carrollton Ave",
    "sg:city":"Baton Rouge",
    "sg:classifiers":[
        {
            "category":"Wholesale",
            "subcategory":"Machinery & Supplies",
            "type":"Manufacturing & Wholesale Goods"
        }
    ],
    "sg:phone":"+1 225 924 1463",
    "sg:postcode":"70806",
    "sg:province":"LA",
    "sg:tags":[
        "equipment",
        "safety",
        "clothing"
    ],
    "sg:website":"www.spedmill.com",
    "wof:name":"Spedmill Inc",
    "wof:placetype":"venue"
},
  "geometry": {"coordinates":[-91.12381499999999,30.458662],"type":"Point"}
}