{
  "type": "Feature",
  "properties": {
    "iso:country":"US",
    "sg:address":"6920 Veterans Memorial Blvd",
    "sg:city":"Metairie",
    "sg:classifiers":[
        {
            "category":"Restaurant",
            "type":"Food & Drink"
        }
    ],
    "sg:menulink":"http://www.allmenus.com/la/kenner/241820-new-orleans-hamburger--seafood-co/menu/",
    "sg:phone":"+1 504 455 1271",
    "sg:postcode":"70003",
    "sg:province":"LA",
    "sg:tags":[
        "american"
    ],
    "wof:name":"New Orleans Hamburger & Seafood Co.",
    "wof:placetype":"venue"
},
  "geometry": {"coordinates":[-90.216269,30.004819],"type":"Point"}
}