{
  "type": "Feature",
  "properties": {
    "addr:full":"496 W Prien Lake Rd Lake Charles LA 70601",
    "addr:housenumber":"496",
    "addr:postcode":"70601",
    "addr:street":"W Prien Lake Rd",
    "iso:country":"US",
    "sg:address":"496 W Prien Lake Rd",
    "sg:city":"Lake Charles",
    "sg:classifiers":[
        {
            "category":"Ice Cream",
            "type":"Food & Drink"
        }
    ],
    "sg:menulink":"http://www.allmenus.com/la/lake-charles/227120-dippin-dots/menu/",
    "sg:phone":"+1 337 562 2966",
    "sg:postcode":"70601",
    "sg:province":"LA",
    "sg:tags":[
        "american"
    ],
    "wof:name":"Dippin' Dots",
    "wof:placetype":"venue"
},
  "geometry": {"coordinates":[-93.226238,30.198267],"type":"Point"}
}