{
  "type": "Feature",
  "properties": {
    "iso:country":"US",
    "sg:address":"233 Leo Ave",
    "sg:city":"Shreveport",
    "sg:classifiers":[
        {
            "category":"Personal",
            "subcategory":"Beauty Salon",
            "type":"Services"
        }
    ],
    "sg:phone":"+1 318 868 1902",
    "sg:postcode":"71105",
    "sg:province":"LA",
    "sg:tags":[
        "shop"
    ],
    "wof:name":"Young American Hair Styling",
    "wof:placetype":"venue"
},
  "geometry": {"coordinates":[-93.715813,32.464825],"type":"Point"}
}