{
  "type": "Feature",
  "properties": {
    "iso:country":"US",
    "sg:address":"3437 Masonic Dr",
    "sg:city":"Alexandria",
    "sg:classifiers":[
        {
            "category":"Shopping",
            "subcategory":"Department Store",
            "type":"Retail Goods"
        }
    ],
    "sg:phone":"+1 318 445 9992",
    "sg:postcode":"71301",
    "sg:province":"LA",
    "sg:website":"www.dillards.com",
    "wof:name":"Dillard's",
    "wof:placetype":"venue"
},
  "geometry": {"coordinates":[-92.462433,31.280551],"type":"Point"}
}