{
  "type": "Feature",
  "properties": {
    "addr:full":"3254 Front St Winnsboro LA 71295",
    "addr:housenumber":"3254",
    "addr:postcode":"71295",
    "addr:street":"Front St",
    "iso:country":"US",
    "sg:address":"3254 Front St",
    "sg:city":"Winnsboro",
    "sg:classifiers":[
        {
            "category":"Personal",
            "subcategory":"Beauty Salon",
            "type":"Services"
        }
    ],
    "sg:phone":"+1 318 435 0063",
    "sg:postcode":"71295",
    "sg:province":"LA",
    "sg:tags":[
        "manicuring"
    ],
    "wof:name":"Queen Nails",
    "wof:placetype":"venue"
},
  "geometry": {"coordinates":[-91.727223,32.184675],"type":"Point"}
}