{
  "type": "Feature",
  "properties": {
    "iso:country":"US",
    "sg:address":"8414 Parc Pl",
    "sg:city":"Chalmette",
    "sg:classifiers":[
        {
            "category":"Wholesale",
            "subcategory":"Tobacco Products",
            "type":"Manufacturing & Wholesale Goods"
        }
    ],
    "sg:phone":"+1 504 277 5881",
    "sg:postcode":"70043",
    "sg:province":"LA",
    "sg:tags":[
        "cigarette",
        "cigar",
        "dealer"
    ],
    "wof:name":"Frank Silva & Son Inc",
    "wof:placetype":"venue"
},
  "geometry": {"coordinates":[-89.97344099999999,29.954587],"type":"Point"}
}