{
  "type": "Feature",
  "properties": {
    "iso:country":"US",
    "sg:address":"8317 W Judge Perez Dr",
    "sg:city":"Chalmette",
    "sg:classifiers":[
        {
            "category":"Restaurant",
            "type":"Food & Drink"
        }
    ],
    "sg:phone":"+1 504 277 4905",
    "sg:postcode":"70043",
    "sg:province":"LA",
    "wof:name":"Taco Bell",
    "wof:placetype":"venue"
},
  "geometry": {"coordinates":[-89.978916,29.953662],"type":"Point"}
}