{
  "type": "Feature",
  "properties": {
    "addr:full":"9541 Chef Menteur Hwy New Orleans LA 70127",
    "addr:housenumber":"9541",
    "addr:postcode":"70127",
    "addr:street":"Chef Menteur Hwy",
    "iso:country":"US",
    "sg:address":"9541 Chef Menteur Hwy",
    "sg:city":"New Orleans",
    "sg:classifiers":[
        {
            "category":"Professional",
            "subcategory":"Management & Consulting",
            "type":"Services"
        }
    ],
    "sg:phone":"+1 504 246 0011",
    "sg:postcode":"70127",
    "sg:province":"LA",
    "sg:tags":[
        "consultant",
        "educational"
    ],
    "wof:name":"Reclaiming The Land Inc",
    "wof:placetype":"venue"
},
  "geometry": {"coordinates":[-89.973091,30.017408],"type":"Point"}
}