{
  "type": "Feature",
  "properties": {
    "iso:country":"US",
    "sg:address":"2007 Daniels Rd",
    "sg:city":"Terrytown",
    "sg:classifiers":[
        {
            "category":"Professional",
            "subcategory":"Computer Services",
            "type":"Services"
        }
    ],
    "sg:phone":"+1 504 371 5277",
    "sg:postcode":"70056",
    "sg:province":"LA",
    "sg:tags":[
        "internet"
    ],
    "wof:name":"J M Internet Cafe",
    "wof:placetype":"venue"
},
  "geometry": {"coordinates":[-90.03008199999999,29.903917],"type":"Point"}
}