{
  "type": "Feature",
  "properties": {
    "iso:country":"US",
    "sg:address":"1855 Barataria Blvd",
    "sg:city":"Marrero",
    "sg:classifiers":[
        {
            "category":"Restaurant",
            "type":"Food & Drink"
        }
    ],
    "sg:menulink":"http://www.allmenus.com/la/bridge-city/131677-quiznos-sub/menu/",
    "sg:phone":"+1 504 340 0887",
    "sg:postcode":"70072",
    "sg:province":"LA",
    "sg:tags":[
        "wrap",
        "american",
        "sandwich"
    ],
    "wof:name":"Quiznos Sub",
    "wof:placetype":"venue"
},
  "geometry": {"coordinates":[-90.098293,29.877236],"type":"Point"}
}