{
  "type": "Feature",
  "properties": {
    "addr:full":"39529 Bradbury Ln Prairieville LA 70769",
    "addr:postcode":"39529;70769",
    "addr:street":"Bradbury Ln",
    "iso:country":"US",
    "sg:address":"39529 Bradbury Ln",
    "sg:city":"Prairieville",
    "sg:classifiers":[
        {
            "category":"Building & Trades",
            "subcategory":"Construction",
            "type":"Services"
        }
    ],
    "sg:phone":"+1 225 622 1520",
    "sg:postcode":"70769",
    "sg:province":"LA",
    "sg:tags":[
        "restoration",
        "cleaning",
        "patio",
        "deck"
    ],
    "wof:name":"Water Works Ind Svc Inc",
    "wof:placetype":"venue"
},
  "geometry": {"coordinates":[-90.939081,30.301418],"type":"Point"}
}