{
  "type": "Feature",
  "properties": {
    "iso:country":"US",
    "sg:address":"307 Pershing St",
    "sg:city":"Morgan City",
    "sg:classifiers":[
        {
            "category":"Building & Trades",
            "subcategory":"Plumbing",
            "type":"Services"
        }
    ],
    "sg:phone":"+1 985 384 6833",
    "sg:postcode":"70380",
    "sg:province":"LA",
    "sg:tags":[
        "conditioning",
        "air",
        "system",
        "contractor"
    ],
    "wof:name":"A & E AC Svc",
    "wof:placetype":"venue"
},
  "geometry": {"coordinates":[-91.20994399999999,29.699513],"type":"Point"}
}