{
  "type": "Feature",
  "properties": {
    "iso:country":"US",
    "sg:address":"4771 Lavey Ln",
    "sg:city":"Baker",
    "sg:classifiers":[
        {
            "category":"Organizations",
            "subcategory":"Religious Organization",
            "type":"Services"
        }
    ],
    "sg:phone":"+1 225 778 0570",
    "sg:postcode":"70714",
    "sg:province":"LA",
    "wof:name":"Easley Marantha",
    "wof:placetype":"venue"
},
  "geometry": {"coordinates":[-91.150633,30.575541],"type":"Point"}
}