{
  "type": "Feature",
  "properties": {
    "addr:full":"2917 Magazine St New Orleans LA 70115",
    "addr:housenumber":"2917",
    "addr:postcode":"70115",
    "addr:street":"Magazine St",
    "iso:country":"US",
    "sg:address":"2917 Magazine St",
    "sg:city":"New Orleans",
    "sg:classifiers":[
        {
            "category":"Restaurant",
            "type":"Food & Drink"
        }
    ],
    "sg:phone":"+1 504 891 2115",
    "sg:postcode":"70115",
    "sg:province":"LA",
    "sg:tags":[
        "shop",
        "coffee"
    ],
    "wof:name":"C C's Gourmet Coffee House",
    "wof:placetype":"venue"
},
  "geometry": {"coordinates":[-90.084542,29.925143],"type":"Point"}
}