{
  "type": "Feature",
  "properties": {
    "addr:full":"2387 N Airway Dr Baton Rouge LA 70815",
    "addr:housenumber":"2387",
    "addr:postcode":"70815",
    "addr:street":"N Airway Dr",
    "iso:country":"US",
    "sg:address":"2387 N Airway Dr",
    "sg:city":"Baton Rouge",
    "sg:classifiers":[
        {
            "category":"Wholesale",
            "subcategory":"Machinery & Supplies",
            "type":"Manufacturing & Wholesale Goods"
        }
    ],
    "sg:phone":"+1 225 927 2688",
    "sg:postcode":"70815",
    "sg:province":"LA",
    "sg:tags":[
        "valve"
    ],
    "sg:website":"www.lcpvf.com",
    "wof:name":"Louisiana Chemical Pipe Valve",
    "wof:placetype":"venue"
},
  "geometry": {"coordinates":[-91.098932,30.470983],"type":"Point"}
}