{
  "type": "Feature",
  "properties": {
    "iso:country":"US",
    "sg:address":"9374 Mansfield Rd",
    "sg:city":"Shreveport",
    "sg:classifiers":[
        {
            "category":"Personal",
            "subcategory":"Beauty Salon",
            "type":"Services"
        }
    ],
    "sg:phone":"+1 318 687 8056",
    "sg:postcode":"71118",
    "sg:province":"LA",
    "wof:name":"Los Angeles Beauty Salon",
    "wof:placetype":"venue"
},
  "geometry": {"coordinates":[-93.809016,32.397349],"type":"Point"}
}