{
  "type": "Feature",
  "properties": {
    "iso:country":"US",
    "sg:address":"1501 Kaliste Saloom Rd",
    "sg:city":"Lafayette",
    "sg:classifiers":[
        {
            "category":"Shopping",
            "subcategory":"Florist",
            "type":"Retail Goods"
        }
    ],
    "sg:phone":"+1 337 991 9050",
    "sg:postcode":"70508",
    "sg:province":"LA",
    "sg:website":"http://www.aflowerloft.com",
    "wof:name":"A Flower Loft",
    "wof:placetype":"venue"
},
  "geometry": {"coordinates":[-92.03067,30.172041],"type":"Point"}
}