{
  "type": "Feature",
  "properties": {
    "iso:country":"US",
    "sg:address":"1402 E Airline Hwy",
    "sg:city":"La Place",
    "sg:classifiers":[
        {
            "category":"Professional",
            "subcategory":"Lawyer & Legal Services",
            "type":"Services"
        }
    ],
    "sg:phone":"+1 985 651 9763",
    "sg:postcode":"70068",
    "sg:province":"LA",
    "sg:tags":[
        "attorney"
    ],
    "wof:name":"Robert D Levenstein Law Office",
    "wof:placetype":"venue"
},
  "geometry": {"coordinates":[-90.447013,30.044563],"type":"Point"}
}