{
  "type": "Feature",
  "properties": {
    "iso:country":"US",
    "sg:address":"608 4th St",
    "sg:city":"Westwego",
    "sg:classifiers":[
        {
            "category":"Shopping",
            "subcategory":"Gifts & Souvenirs",
            "type":"Retail Goods"
        }
    ],
    "sg:phone":"+1 504 348 2194",
    "sg:postcode":"70094",
    "sg:province":"LA",
    "sg:tags":[
        "shop"
    ],
    "wof:name":"A G Fashion & Gift Shop",
    "wof:placetype":"venue"
},
  "geometry": {"coordinates":[-90.14178,29.907471],"type":"Point"}
}