{
  "type": "Feature",
  "properties": {
    "addr:full":"3053 N Rampart St New Orleans LA 70117",
    "addr:housenumber":"3053",
    "addr:postcode":"70117",
    "addr:street":"N Rampart St",
    "iso:country":"US",
    "sg:address":"3053 N Rampart St",
    "sg:city":"New Orleans",
    "sg:classifiers":[
        {
            "category":"Wholesale",
            "subcategory":"Metals & Minerals",
            "type":"Manufacturing & Wholesale Goods"
        }
    ],
    "sg:phone":"+1 504 945 4466",
    "sg:postcode":"70117",
    "sg:province":"LA",
    "sg:tags":[
        "ironwork"
    ],
    "wof:name":"Orleans Ornamental Iron Inc",
    "wof:placetype":"venue"
},
  "geometry": {"coordinates":[-90.04537999999999,29.966688],"type":"Point"}
}