{
  "type": "Feature",
  "properties": {
    "addr:full":"2109 Caton St New Orleans LA 70122",
    "addr:housenumber":"2109",
    "addr:postcode":"70122",
    "addr:street":"Caton St",
    "iso:country":"US",
    "sg:address":"2109 Caton St",
    "sg:city":"New Orleans",
    "sg:classifiers":[
        {
            "category":"Personal",
            "subcategory":"Beauty Salon",
            "type":"Services"
        }
    ],
    "sg:phone":"+1 504 282 9043",
    "sg:postcode":"70122",
    "sg:province":"LA",
    "wof:name":"Jireh Hair Studio",
    "wof:placetype":"venue"
},
  "geometry": {"coordinates":[-90.06074,29.998937],"type":"Point"}
}