{
  "type": "Feature",
  "properties": {
    "iso:country":"US",
    "sg:address":"893 Brownswitch Rd",
    "sg:city":"Slidell",
    "sg:classifiers":[
        {
            "category":"Professional",
            "subcategory":"Business Services",
            "type":"Services"
        }
    ],
    "sg:phone":"+1 985 649 9633",
    "sg:postcode":"70458",
    "sg:province":"LA",
    "sg:tags":[
        "paging",
        "answering"
    ],
    "wof:name":"Message Center",
    "wof:placetype":"venue"
},
  "geometry": {"coordinates":[-89.744927,30.310312],"type":"Point"}
}