{
  "type": "Feature",
  "properties": {
    "iso:country":"US",
    "sg:address":"805 Homestead Ave",
    "sg:city":"Metairie",
    "sg:classifiers":[
        {
            "category":"Building & Trades",
            "subcategory":"Construction",
            "type":"Services"
        }
    ],
    "sg:phone":"+1 504 309 8460",
    "sg:postcode":"70005",
    "sg:province":"LA",
    "sg:tags":[
        "handyman"
    ],
    "wof:name":"Handyman Depot",
    "wof:placetype":"venue"
},
  "geometry": {"coordinates":[-90.137793,30.004173],"type":"Point"}
}