{
  "type": "Feature",
  "properties": {
    "iso:country":"US",
    "sg:address":"4444 S Galvez St",
    "sg:city":"New Orleans",
    "sg:classifiers":[
        {
            "category":"Personal",
            "type":"Services"
        },
        {
            "category":"Retail",
            "subcategory":"Animal Services",
            "type":"Services"
        }
    ],
    "sg:phone":"+1 504 821 9293",
    "sg:postcode":"70125",
    "sg:province":"LA",
    "sg:tags":[
        "pet",
        "boarding",
        "sitting"
    ],
    "wof:name":"Carina's Critter Care",
    "wof:placetype":"venue"
},
  "geometry": {"coordinates":[-90.104713,29.944579],"type":"Point"}
}