{
  "type": "Feature",
  "properties": {
    "addr:full":"8121 Aberdeen Rd New Orleans LA 70126",
    "addr:housenumber":"8121",
    "addr:postcode":"70126",
    "addr:street":"Aberdeen Rd",
    "iso:country":"US",
    "sg:address":"8121 Aberdeen Rd",
    "sg:city":"New Orleans",
    "sg:classifiers":[
        {
            "category":"Building & Trades",
            "subcategory":"Equipment Rental",
            "type":"Services"
        }
    ],
    "sg:phone":"+1 504 246 8319",
    "sg:postcode":"70126",
    "sg:province":"LA",
    "wof:name":"World Card Services",
    "wof:placetype":"venue"
},
  "geometry": {"coordinates":[-89.99775099999999,30.037699],"type":"Point"}
}