{
  "type": "Feature",
  "properties": {
    "iso:country":"US",
    "sg:address":"2000 S 5th St",
    "sg:city":"Leesville",
    "sg:classifiers":[
        {
            "category":"Autos & Motor Vehicles",
            "subcategory":"Automobile Sales",
            "type":"Retail Goods"
        }
    ],
    "sg:phone":"+1 337 238 1394",
    "sg:postcode":"71446",
    "sg:province":"LA",
    "sg:tags":[
        "car",
        "dealer"
    ],
    "wof:name":"Pynes Chrysler Inc",
    "wof:placetype":"venue"
},
  "geometry": {"coordinates":[-93.267886,31.124552],"type":"Point"}
}