{
  "type": "Feature",
  "properties": {
    "addr:full":"509 David St New Orleans LA 70119",
    "addr:housenumber":"509",
    "addr:postcode":"70119",
    "addr:street":"David St",
    "iso:country":"US",
    "sg:address":"509 David St",
    "sg:city":"New Orleans",
    "sg:classifiers":[
        {
            "category":"Retail",
            "subcategory":"Auto Repair",
            "type":"Services"
        }
    ],
    "sg:phone":"+1 504 488 2511",
    "sg:postcode":"70119",
    "sg:province":"LA",
    "sg:tags":[
        "repairing",
        "automobile",
        "general"
    ],
    "wof:name":"Paul's Automotive",
    "wof:placetype":"venue"
},
  "geometry": {"coordinates":[-90.097973,29.978902],"type":"Point"}
}