{
  "type": "Feature",
  "properties": {
    "iso:country":"US",
    "sg:address":"910 N Vienna St",
    "sg:city":"Ruston",
    "sg:classifiers":[
        {
            "category":"Real Estate",
            "subcategory":"Real Estate Operator",
            "type":"Services"
        }
    ],
    "sg:phone":"+1 318 251 9106",
    "sg:postcode":"71270",
    "sg:province":"LA",
    "sg:tags":[
        "apartment"
    ],
    "wof:name":"Gilbert Realty",
    "wof:placetype":"venue"
},
  "geometry": {"coordinates":[-92.63775699999999,32.538677],"type":"Point"}
}