{
  "type": "Feature",
  "properties": {
    "iso:country":"US",
    "sg:address":"375 N Main St",
    "sg:city":"Monroe Twp",
    "sg:classifiers":[
        {
            "category":"Building & Trades",
            "subcategory":"Cleaning & Sanitation",
            "type":"Services"
        }
    ],
    "sg:phone":"+1 856 875 9959",
    "sg:postcode":"71241",
    "sg:province":"LA",
    "sg:tags":[
        "janitor"
    ],
    "wof:name":"Starbrite Cleaning Svc",
    "wof:placetype":"venue"
},
  "geometry": {"coordinates":[-92.40542499999999,32.77583],"type":"Point"}
}