{
  "type": "Feature",
  "properties": {
    "addr:full":"206 Greenhaven Dr Baton Rouge LA 70810",
    "addr:housenumber":"206",
    "addr:postcode":"70810",
    "addr:street":"Greenhaven Dr",
    "iso:country":"US",
    "sg:address":"206 Greenhaven Dr",
    "sg:city":"Baton Rouge",
    "sg:classifiers":[
        {
            "category":"Building & Trades",
            "subcategory":"Electrical",
            "type":"Services"
        }
    ],
    "sg:phone":"+1 225 769 9788",
    "sg:postcode":"70810",
    "sg:province":"LA",
    "sg:tags":[
        "electric",
        "contractor"
    ],
    "wof:name":"K & N Electric",
    "wof:placetype":"venue"
},
  "geometry": {"coordinates":[-91.111307,30.359167],"type":"Point"}
}