{
  "type": "Feature",
  "properties": {
    "iso:country":"US",
    "sg:address":"2540 Beene Blvd",
    "sg:city":"Bossier City",
    "sg:classifiers":[
        {
            "category":"Social Services",
            "subcategory":"Adult Care",
            "type":"Services"
        }
    ],
    "sg:phone":"+1 318 747 2114",
    "sg:postcode":"71111",
    "sg:province":"LA",
    "sg:tags":[
        "home",
        "residential"
    ],
    "sg:website":"www.merrillgardens.com",
    "wof:name":"Merrill Gardens",
    "wof:placetype":"venue"
},
  "geometry": {"coordinates":[-93.71232000000001,32.55963],"type":"Point"}
}