{
  "type": "Feature",
  "properties": {
    "addr:full":"416 Hudson Ave Jonesboro LA 71251",
    "addr:housenumber":"416",
    "addr:postcode":"71251",
    "addr:street":"Hudson Ave",
    "iso:country":"US",
    "sg:address":"416 Hudson Ave",
    "sg:city":"Jonesboro",
    "sg:classifiers":[
        {
            "category":"Personal",
            "subcategory":"Beauty Salon",
            "type":"Services"
        }
    ],
    "sg:phone":"+1 318 259 8805",
    "sg:postcode":"71251",
    "sg:province":"LA",
    "wof:name":"Hair Crafters",
    "wof:placetype":"venue"
},
  "geometry": {"coordinates":[-92.713471,32.241814],"type":"Point"}
}