{
  "type": "Feature",
  "properties": {
    "iso:country":"US",
    "sg:address":"31 McAlister Dr",
    "sg:city":"New Orleans",
    "sg:classifiers":[
        {
            "category":"Sports & Exercise",
            "subcategory":"Gym",
            "type":"Entertainment"
        }
    ],
    "sg:phone":"+1 504 865 5431",
    "sg:postcode":"70118",
    "sg:province":"LA",
    "sg:tags":[
        "club",
        "health",
        "studio",
        "gymnasium"
    ],
    "sg:website":"www.reilycenter.com",
    "wof:name":"Reily Student Recreation Ctr",
    "wof:placetype":"venue"
},
  "geometry": {"coordinates":[-90.119736,29.939622],"type":"Point"}
}