{
  "type": "Feature",
  "properties": {
    "iso:country":"US",
    "sg:address":"101 W Robert E Lee Blvd",
    "sg:city":"New Orleans",
    "sg:classifiers":[
        {
            "category":"Banks & Credit Unions",
            "subcategory":"Bank",
            "type":"Services"
        }
    ],
    "sg:phone":"+1 504 561 7442",
    "sg:postcode":"70124",
    "sg:province":"LA",
    "wof:name":"Regions",
    "wof:placetype":"venue"
},
  "geometry": {"coordinates":[-90.11551900000001,30.020196],"type":"Point"}
}