{
  "type": "Feature",
  "properties": {
    "addr:full":"5675 Hwy 145 Ruston LA 71270",
    "addr:housenumber":"5675",
    "addr:postcode":"71270",
    "addr:street":"Hwy 145",
    "iso:country":"US",
    "sg:address":"5675 Hwy 145",
    "sg:city":"Ruston",
    "sg:classifiers":[
        {
            "category":"Farming",
            "subcategory":"Farm",
            "type":"Manufacturing & Wholesale Goods"
        }
    ],
    "sg:phone":"+1 318 254 5247",
    "sg:postcode":"71270",
    "sg:province":"LA",
    "sg:tags":[
        "crop",
        "general"
    ],
    "wof:name":"Pesnell Farms",
    "wof:placetype":"venue"
},
  "geometry": {"coordinates":[-92.55531499999999,32.481004],"type":"Point"}
}