{
  "type": "Feature",
  "properties": {
    "addr:full":"3251 Wall Blvd Gretna LA 70056",
    "addr:housenumber":"3251",
    "addr:postcode":"70056",
    "addr:street":"Wall Blvd",
    "iso:country":"US",
    "sg:address":"3251 Wall Blvd",
    "sg:city":"Gretna",
    "sg:classifiers":[
        {
            "category":"Real Estate",
            "subcategory":"Real Estate Operator",
            "type":"Services"
        }
    ],
    "sg:phone":"+1 504 392 5022",
    "sg:postcode":"70056",
    "sg:province":"LA",
    "sg:tags":[
        "apartment"
    ],
    "wof:name":"Calypso Bay Apartments",
    "wof:placetype":"venue"
},
  "geometry": {"coordinates":[-90.031898,29.865],"type":"Point"}
}