{
  "type": "Feature",
  "properties": {
    "iso:country":"US",
    "sg:address":"1035 N 9th St",
    "sg:city":"Monroe",
    "sg:classifiers":[
        {
            "category":"Health Services",
            "subcategory":"Health Practitioner",
            "type":"Services"
        }
    ],
    "sg:phone":"+1 318 387 4973",
    "sg:postcode":"71201",
    "sg:province":"LA",
    "sg:tags":[
        "therapist",
        "physical"
    ],
    "wof:name":"Physical Therapy Inc-Monroe",
    "wof:placetype":"venue"
},
  "geometry": {"coordinates":[-92.11709999999999,32.51442],"type":"Point"}
}