{
  "type": "Feature",
  "properties": {
    "iso:country":"US",
    "sg:address":"9147 State Rte 23",
    "sg:city":"Belle Chasse",
    "sg:classifiers":[
        {
            "category":"Manufacturing",
            "subcategory":"Signs",
            "type":"Manufacturing & Wholesale Goods"
        }
    ],
    "sg:phone":"+1 504 391 2980",
    "sg:postcode":"70037",
    "sg:province":"LA",
    "wof:name":"Say It Signs",
    "wof:placetype":"venue"
},
  "geometry": {"coordinates":[-90.000835,29.836781],"type":"Point"}
}