{
  "type": "Feature",
  "properties": {
    "iso:country":"US",
    "sg:address":"2121 N Causeway Blvd",
    "sg:city":"Metairie",
    "sg:classifiers":[
        {
            "category":"Professional",
            "subcategory":"Accounting & Tax Preparation",
            "type":"Services"
        }
    ],
    "sg:phone":"+1 504 828 5557",
    "sg:postcode":"70001",
    "sg:province":"LA",
    "sg:tags":[
        "accountant"
    ],
    "wof:name":"Ernest Langlinais CPA",
    "wof:placetype":"venue"
},
  "geometry": {"coordinates":[-90.15543,29.990962],"type":"Point"}
}