{
  "type": "Feature",
  "properties": {
    "addr:full":"5003 Lee St Alexandria LA 71302",
    "addr:housenumber":"5003",
    "addr:postcode":"71302",
    "addr:street":"Lee St",
    "iso:country":"US",
    "sg:address":"5003 Lee St",
    "sg:city":"Alexandria",
    "sg:classifiers":[
        {
            "category":"Autos & Motor Vehicles",
            "subcategory":"Fuel & Gas Station",
            "type":"Retail Goods"
        }
    ],
    "sg:phone":"+1 318 442 3117",
    "sg:postcode":"71302",
    "sg:province":"LA",
    "sg:tags":[
        "oil"
    ],
    "wof:name":"Jubilee Chevron",
    "wof:placetype":"venue"
},
  "geometry": {"coordinates":[-92.447515,31.263532],"type":"Point"}
}