{
  "type": "Feature",
  "properties": {
    "iso:country":"US",
    "sg:address":"2 Phlox Dr",
    "sg:city":"Lafayette",
    "sg:classifiers":[
        {
            "category":"Personal",
            "type":"Services"
        }
    ],
    "sg:phone":"+1 337 232 1500",
    "sg:postcode":"70507",
    "sg:province":"LA",
    "sg:tags":[
        "mover"
    ],
    "wof:name":"A A A Budget Furniture Movers",
    "wof:placetype":"venue"
},
  "geometry": {"coordinates":[-92.013603,30.2777],"type":"Point"}
}