{
  "type": "Feature",
  "properties": {
    "addr:full":"406 N Lewis St New Iberia LA 70563",
    "addr:housenumber":"406",
    "addr:postcode":"70563",
    "addr:street":"N Lewis St",
    "iso:country":"US",
    "sg:address":"406 N Lewis St",
    "sg:city":"New Iberia",
    "sg:classifiers":[
        {
            "category":"Health Services",
            "subcategory":"Clinic",
            "type":"Services"
        }
    ],
    "sg:phone":"+1 337 367 8220",
    "sg:postcode":"70563",
    "sg:province":"LA",
    "wof:name":"JKL Health Care Svc",
    "wof:placetype":"venue"
},
  "geometry": {"coordinates":[-91.79826,30.003622],"type":"Point"}
}