{
  "type": "Feature",
  "properties": {
    "iso:country":"US",
    "sg:address":"2301 N Macarthur Dr",
    "sg:city":"Alexandria",
    "sg:classifiers":[
        {
            "category":"Travel",
            "subcategory":"Hotels & Motels",
            "type":"Entertainment"
        }
    ],
    "sg:phone":"+1 318 487 8500",
    "sg:postcode":"71303",
    "sg:province":"LA",
    "wof:name":"Louisina Convention Ctr & H",
    "wof:placetype":"venue"
},
  "geometry": {"coordinates":[-92.473028,31.314396],"type":"Point"}
}