{
  "type": "Feature",
  "properties": {
    "iso:country":"US",
    "sg:address":"1525 Lapalco Blvd Ste 25",
    "sg:city":"Harvey",
    "sg:classifiers":[
        {
            "category":"Professional",
            "subcategory":"Lawyer & Legal Services",
            "type":"Services"
        }
    ],
    "sg:phone":"+1 504 361 4626",
    "sg:postcode":"70058",
    "sg:province":"LA",
    "wof:name":"Jacobs and Sarratt",
    "wof:placetype":"venue"
},
  "geometry": {"coordinates":[-90.049004,29.875],"type":"Point"}
}