{
  "type": "Feature",
  "properties": {
    "iso:country":"US",
    "sg:address":"36488 Cane Market Rd",
    "sg:city":"Denham Springs",
    "sg:classifiers":[
        {
            "category":"Retail",
            "subcategory":"Auto Repair",
            "type":"Services"
        }
    ],
    "sg:phone":"+1 225 791 4556",
    "sg:postcode":"70706",
    "sg:province":"LA",
    "sg:tags":[
        "repairing",
        "automobile"
    ],
    "wof:name":"Action Automotive",
    "wof:placetype":"venue"
},
  "geometry": {"coordinates":[-90.95531,30.561488],"type":"Point"}
}