{
  "type": "Feature",
  "properties": {
    "addr:full":"1501 Veterans Memorial Dr Abbeville LA 70510",
    "addr:housenumber":"1501",
    "addr:postcode":"70510",
    "addr:street":"Veterans Memorial Dr",
    "iso:country":"US",
    "sg:address":"1501 Veterans Memorial Dr",
    "sg:city":"Abbeville",
    "sg:classifiers":[
        {
            "category":"Insurance",
            "subcategory":"Insurance Agent",
            "type":"Services"
        }
    ],
    "sg:phone":"+1 337 893 5871",
    "sg:postcode":"70510",
    "sg:province":"LA",
    "wof:name":"Dave Holley Insurance",
    "wof:placetype":"venue"
},
  "geometry": {"coordinates":[-92.121197,29.981499],"type":"Point"}
}