{
  "type": "Feature",
  "properties": {
    "addr:full":"1612 S Columbia St Bogalusa LA 70427",
    "addr:housenumber":"1612",
    "addr:postcode":"70427",
    "addr:street":"S Columbia St",
    "iso:country":"US",
    "sg:address":"1612 S Columbia St",
    "sg:city":"Bogalusa",
    "sg:classifiers":[
        {
            "category":"Shopping",
            "type":"Retail Goods"
        }
    ],
    "sg:phone":"+1 985 730 5555",
    "sg:postcode":"70427",
    "sg:province":"LA",
    "sg:tags":[
        "merchandise"
    ],
    "wof:name":"Picture This Frames & Stuff",
    "wof:placetype":"venue"
},
  "geometry": {"coordinates":[-89.851153,30.75895],"type":"Point"}
}