{
  "type": "Feature",
  "properties": {
    "iso:country":"US",
    "sg:address":"33720 Cane Market Rd",
    "sg:city":"Walker",
    "sg:classifiers":[
        {
            "category":"Retail",
            "subcategory":"Animal Services",
            "type":"Services"
        }
    ],
    "sg:phone":"+1 225 791 0475",
    "sg:postcode":"70785",
    "sg:province":"LA",
    "sg:tags":[
        "cat",
        "dog",
        "kennel"
    ],
    "wof:name":"Continental Kennel Club",
    "wof:placetype":"venue"
},
  "geometry": {"coordinates":[-90.870619,30.561404],"type":"Point"}
}