{
  "type": "Feature",
  "properties": {
    "iso:country":"US",
    "sg:address":"2211 E Madison Ave",
    "sg:city":"Bastrop",
    "sg:classifiers":[
        {
            "category":"Shopping",
            "subcategory":"Pharmacy",
            "type":"Retail Goods"
        }
    ],
    "sg:phone":"+1 318 281 3284",
    "sg:postcode":"71220",
    "sg:province":"LA",
    "wof:name":"Super 1 Pharmacy",
    "wof:placetype":"venue"
},
  "geometry": {"coordinates":[-91.884322,32.776629],"type":"Point"}
}