{
  "type": "Feature",
  "properties": {
    "addr:full":"44364 Parker Blvd Hammond LA 70403",
    "addr:housenumber":"44364",
    "addr:postcode":"70403",
    "addr:street":"Parker Blvd",
    "iso:country":"US",
    "sg:address":"44364 Parker Blvd",
    "sg:city":"Hammond",
    "sg:classifiers":[
        {
            "category":"Shopping",
            "subcategory":"Musical Instruments",
            "type":"Retail Goods"
        }
    ],
    "sg:phone":"+1 985 345 8049",
    "sg:postcode":"70403",
    "sg:province":"LA",
    "sg:tags":[
        "piano"
    ],
    "wof:name":"Rushing Piano & Organ Svc",
    "wof:placetype":"venue"
},
  "geometry": {"coordinates":[-90.445415,30.502852],"type":"Point"}
}