{
  "type": "Feature",
  "properties": {
    "iso:country":"US",
    "sg:address":"9409 Ferrara Dr",
    "sg:city":"Shreveport",
    "sg:classifiers":[
        {
            "category":"Social Services",
            "subcategory":"Child Care",
            "type":"Services"
        }
    ],
    "sg:phone":"+1 318 603 2001",
    "sg:postcode":"71118",
    "sg:province":"LA",
    "wof:name":"Discovery Kids Educational Ctr",
    "wof:placetype":"venue"
},
  "geometry": {"coordinates":[-93.80273800000001,32.390972],"type":"Point"}
}