{
  "type": "Feature",
  "properties": {
    "iso:country":"US",
    "sg:address":"2825 Houma Blvd",
    "sg:city":"Metairie",
    "sg:classifiers":[
        {
            "category":"Health Services",
            "subcategory":"Doctor",
            "type":"Services"
        }
    ],
    "sg:phone":"+1 504 887 3121",
    "sg:postcode":"70006",
    "sg:province":"LA",
    "sg:tags":[
        "dentist"
    ],
    "wof:name":"Ganucheau Dental Group",
    "wof:placetype":"venue"
},
  "geometry": {"coordinates":[-90.17867200000001,29.999574],"type":"Point"}
}