{
  "type": "Feature",
  "properties": {
    "iso:country":"US",
    "sg:address":"150 Belle Terre Blvd",
    "sg:city":"La Place",
    "sg:classifiers":[
        {
            "category":"Health Services",
            "subcategory":"Health Practitioner",
            "type":"Services"
        }
    ],
    "sg:phone":"+1 985 651 8808",
    "sg:postcode":"70068",
    "sg:province":"LA",
    "sg:tags":[
        "therapist",
        "physical"
    ],
    "wof:name":"Affiliated Therapy Svc Inc",
    "wof:placetype":"venue"
},
  "geometry": {"coordinates":[-90.500934,30.075685],"type":"Point"}
}