{
  "type": "Feature",
  "properties": {
    "iso:country":"US",
    "sg:address":"128 Yellowstone St",
    "sg:city":"Kenner",
    "sg:classifiers":[
        {
            "category":"Retail",
            "subcategory":"Laundry & Dry Cleaning",
            "type":"Services"
        }
    ],
    "sg:phone":"+1 504 468 2895",
    "sg:postcode":"70065",
    "sg:province":"LA",
    "sg:tags":[
        "cleaners",
        "rug",
        "carpet"
    ],
    "wof:name":"Delise Carpet & Upholstery",
    "wof:placetype":"venue"
},
  "geometry": {"coordinates":[-90.27188,30.044052],"type":"Point"}
}