{
  "type": "Feature",
  "properties": {
    "addr:full":"223 Martin Oaks Dr Lafayette LA 70501",
    "addr:housenumber":"223",
    "addr:postcode":"70501",
    "addr:street":"Martin Oaks Dr",
    "iso:country":"US",
    "sg:address":"223 Martin Oaks Dr",
    "sg:city":"Lafayette",
    "sg:classifiers":[
        {
            "category":"Professional",
            "subcategory":"Management & Consulting",
            "type":"Services"
        }
    ],
    "sg:phone":"+1 337 232 2566",
    "sg:postcode":"70501",
    "sg:province":"LA",
    "sg:tags":[
        "business"
    ],
    "wof:name":"C & R Group Consultants Agency",
    "wof:placetype":"venue"
},
  "geometry": {"coordinates":[-91.997212,30.249803],"type":"Point"}
}