{
  "type": "Feature",
  "properties": {
    "addr:full":"7115 Exchequer Dr Baton Rouge LA 70809",
    "addr:housenumber":"7115",
    "addr:postcode":"70809",
    "addr:street":"Exchequer Dr",
    "iso:country":"US",
    "sg:address":"7115 Exchequer Dr",
    "sg:city":"Baton Rouge",
    "sg:classifiers":[
        {
            "category":"Wholesale",
            "subcategory":"Sporting Goods",
            "type":"Manufacturing & Wholesale Goods"
        }
    ],
    "sg:phone":"+1 225 752 9300",
    "sg:postcode":"70809",
    "sg:province":"LA",
    "sg:tags":[
        "equipment",
        "pool",
        "swimming"
    ],
    "sg:website":"www.scppools.com",
    "wof:name":"Scp Distributors LLC",
    "wof:placetype":"venue"
},
  "geometry": {"coordinates":[-91.050155,30.378001],"type":"Point"}
}