{
  "type": "Feature",
  "properties": {
    "addr:full":"127 Pearl St Minden LA 71055",
    "addr:housenumber":"127",
    "addr:postcode":"71055",
    "addr:street":"Pearl St",
    "iso:country":"US",
    "sg:address":"127 Pearl St",
    "sg:city":"Minden",
    "sg:classifiers":[
        {
            "category":"Shopping",
            "subcategory":"Used Merchandise",
            "type":"Retail Goods"
        }
    ],
    "sg:phone":"+1 318 377 2680",
    "sg:postcode":"71055",
    "sg:province":"LA",
    "sg:tags":[
        "shop",
        "thrift"
    ],
    "wof:name":"Evergreen/Possibilities",
    "wof:placetype":"venue"
},
  "geometry": {"coordinates":[-93.288383,32.615823],"type":"Point"}
}