{
  "type": "Feature",
  "properties": {
    "addr:full":"7805 Highway 90 W New Iberia LA 70560",
    "addr:housenumber":"7805",
    "addr:postcode":"70560",
    "addr:street":"Highway 90 W",
    "iso:country":"US",
    "sg:address":"7805 Highway 90 W",
    "sg:city":"New Iberia",
    "sg:classifiers":[
        {
            "category":"Home & Garden",
            "subcategory":"Garden Supply",
            "type":"Retail Goods"
        }
    ],
    "sg:phone":"+1 337 560 1361",
    "sg:postcode":"70560",
    "sg:province":"LA",
    "sg:tags":[
        "nursery",
        "gardening"
    ],
    "wof:name":"Hi-Crop Equipment Co",
    "wof:placetype":"venue"
},
  "geometry": {"coordinates":[-91.935097,30.063299],"type":"Point"}
}