{
  "type": "Feature",
  "properties": {
    "iso:country":"US",
    "sg:address":"3078 N Foster Dr",
    "sg:city":"Baton Rouge",
    "sg:classifiers":[
        {
            "category":"Personal",
            "subcategory":"Barber",
            "type":"Services"
        }
    ],
    "sg:phone":"+1 225 357 6757",
    "sg:postcode":"70805",
    "sg:province":"LA",
    "wof:name":"Family Affair",
    "wof:placetype":"venue"
},
  "geometry": {"coordinates":[-91.14039200000001,30.47667],"type":"Point"}
}