{
  "type": "Feature",
  "properties": {
    "addr:full":"200 Crofton Rd Kenner LA 70062",
    "addr:housenumber":"200",
    "addr:postcode":"70062",
    "addr:street":"Crofton Rd",
    "iso:country":"US",
    "sg:address":"200 Crofton Rd",
    "sg:city":"Kenner",
    "sg:classifiers":[
        {
            "category":"Transit Center",
            "subcategory":"Freight",
            "type":"Transportation"
        },
        {
            "category":"Professional",
            "subcategory":"Business Services",
            "type":"Services"
        },
        {
            "category":"Taxi",
            "type":"Transportation"
        },
        {
            "category":"Government",
            "subcategory":"Post Office",
            "type":"Public Place"
        }
    ],
    "sg:phone":"+1 888 463 3339",
    "sg:postcode":"70062",
    "sg:province":"LA",
    "sg:tags":[
        "cargo",
        "courier",
        "package",
        "express",
        "shipping",
        "air",
        "delivery",
        "mail",
        "forwarding"
    ],
    "sg:website":"http://www.fedex.com/us/",
    "wof:name":"FedEx",
    "wof:placetype":"venue"
},
  "geometry": {"coordinates":[-90.27174599999999,29.986288],"type":"Point"}
}