{
  "type": "Feature",
  "properties": {
    "addr:full":"1900 Eraste Landry Rd Lafayette LA 70506",
    "addr:postcode":"1900;70506",
    "addr:street":"Eraste Landry Rd",
    "iso:country":"US",
    "sg:address":"1900 Eraste Landry Rd",
    "sg:city":"Lafayette",
    "sg:classifiers":[
        {
            "category":"Recreation",
            "subcategory":"Marina",
            "type":"Entertainment"
        }
    ],
    "sg:phone":"+1 337 984 1900",
    "sg:postcode":"70506",
    "sg:province":"LA",
    "sg:tags":[
        "storage",
        "boat"
    ],
    "wof:name":"EZ-Rv Boat Storage",
    "wof:placetype":"venue"
},
  "geometry": {"coordinates":[-92.069011,30.219221],"type":"Point"}
}