{
  "type": "Feature",
  "properties": {
    "iso:country":"US",
    "sg:address":"9672 E Main St",
    "sg:city":"Houma",
    "sg:classifiers":[
        {
            "category":"Building & Trades",
            "subcategory":"Landscaping Services",
            "type":"Services"
        }
    ],
    "sg:phone":"+1 985 876 5332",
    "sg:postcode":"70363",
    "sg:province":"LA",
    "sg:tags":[
        "landscape",
        "contractor"
    ],
    "wof:name":"Landscaping By Kenneth Inc",
    "wof:placetype":"venue"
},
  "geometry": {"coordinates":[-90.670405,29.588048],"type":"Point"}
}