{
  "type": "Feature",
  "properties": {
    "iso:country":"US",
    "sg:address":"405 W Convent St",
    "sg:city":"Lafayette",
    "sg:classifiers":[
        {
            "category":"Professional",
            "subcategory":"Lawyer & Legal Services",
            "type":"Services"
        }
    ],
    "sg:phone":"+1 337 232 7747",
    "sg:postcode":"70501",
    "sg:province":"LA",
    "sg:tags":[
        "attorney"
    ],
    "wof:name":"William T Babin",
    "wof:placetype":"venue"
},
  "geometry": {"coordinates":[-92.022813,30.221633],"type":"Point"}
}