{
  "type": "Feature",
  "properties": {
    "addr:full":"554 Lonita St Baton Rouge LA 70815",
    "addr:housenumber":"554",
    "addr:postcode":"70815",
    "addr:street":"Lonita St",
    "iso:country":"US",
    "sg:address":"554 Lonita St",
    "sg:city":"Baton Rouge",
    "sg:classifiers":[
        {
            "category":"Professional",
            "subcategory":"Art Services",
            "type":"Services"
        }
    ],
    "sg:phone":"+1 225 216 0626",
    "sg:postcode":"70815",
    "sg:province":"LA",
    "sg:tags":[
        "commercial",
        "design"
    ],
    "wof:name":"Graphics Etc",
    "wof:placetype":"venue"
},
  "geometry": {"coordinates":[-91.073488,30.447459],"type":"Point"}
}