{
  "type": "Feature",
  "properties": {
    "iso:country":"US",
    "sg:address":"8929 Brookwood Dr",
    "sg:city":"Shreveport",
    "sg:classifiers":[
        {
            "category":"Social Services",
            "subcategory":"Child Care",
            "type":"Services"
        }
    ],
    "sg:phone":"+1 318 686 9820",
    "sg:postcode":"71118",
    "sg:province":"LA",
    "wof:name":"Southern Hills Child Care Svc",
    "wof:placetype":"venue"
},
  "geometry": {"coordinates":[-93.781615,32.40904],"type":"Point"}
}