{
  "type": "Feature",
  "properties": {
    "iso:country":"US",
    "sg:address":"21435 Hwy 191",
    "sg:city":"Zwolle",
    "sg:classifiers":[
        {
            "category":"Building & Trades",
            "subcategory":"Construction",
            "type":"Services"
        }
    ],
    "sg:phone":"+1 318 645 7603",
    "sg:postcode":"71486",
    "sg:province":"LA",
    "sg:tags":[
        "contractor"
    ],
    "wof:name":"Rivers Builders Supply",
    "wof:placetype":"venue"
},
  "geometry": {"coordinates":[-93.65544300000001,31.606562],"type":"Point"}
}