{
  "type": "Feature",
  "properties": {
    "iso:country":"US",
    "sg:address":"232 Lake Marina Ave",
    "sg:city":"New Orleans",
    "sg:classifiers":[
        {
            "category":"Real Estate",
            "subcategory":"Real Estate Operator",
            "type":"Services"
        }
    ],
    "sg:phone":"+1 504 286 0091",
    "sg:postcode":"70124",
    "sg:province":"LA",
    "sg:tags":[
        "condominium"
    ],
    "wof:name":"Marseilles Condominiums",
    "wof:placetype":"venue"
},
  "geometry": {"coordinates":[-90.119951,30.021246],"type":"Point"}
}