{
  "type": "Feature",
  "properties": {
    "iso:country":"US",
    "sg:address":"1800 Cypress St",
    "sg:city":"West Monroe",
    "sg:classifiers":[
        {
            "category":"Retail",
            "subcategory":"Auto Repair",
            "type":"Services"
        }
    ],
    "sg:phone":"+1 318 388 2147",
    "sg:postcode":"71291",
    "sg:province":"LA",
    "sg:tags":[
        "recreational",
        "vehicle"
    ],
    "wof:name":"Mahoney's Camp-R-Land Inc",
    "wof:placetype":"venue"
},
  "geometry": {"coordinates":[-92.13789,32.51506],"type":"Point"}
}