{
  "type": "Feature",
  "properties": {
    "iso:country":"US",
    "sg:address":"1415 Sylvia Ave",
    "sg:city":"Metairie",
    "sg:classifiers":[
        {
            "category":"Social Services",
            "subcategory":"Child Care",
            "type":"Services"
        }
    ],
    "sg:phone":"+1 504 833 1704",
    "sg:postcode":"70005",
    "sg:province":"LA",
    "wof:name":"Kinder Schule Montessori Schl",
    "wof:placetype":"venue"
},
  "geometry": {"coordinates":[-90.13353600000001,30.017846],"type":"Point"}
}