{
  "type": "Feature",
  "properties": {
    "iso:country":"US",
    "sg:address":"306 Guilbeau Rd",
    "sg:city":"Lafayette",
    "sg:classifiers":[
        {
            "category":"Retail",
            "subcategory":"Laundry & Dry Cleaning",
            "type":"Services"
        }
    ],
    "sg:phone":"+1 337 984 2542",
    "sg:postcode":"70506",
    "sg:province":"LA",
    "sg:tags":[
        "cleaners"
    ],
    "wof:name":"National Cleaners",
    "wof:placetype":"venue"
},
  "geometry": {"coordinates":[-92.06544100000001,30.196225],"type":"Point"}
}