{
  "type": "Feature",
  "properties": {
    "iso:country":"US",
    "sg:address":"351 Mount Zion Rd",
    "sg:city":"Shreveport",
    "sg:classifiers":[
        {
            "category":"Real Estate",
            "subcategory":"Real Estate Agent",
            "type":"Services"
        }
    ],
    "sg:phone":"+1 318 682 3740",
    "sg:postcode":"71106",
    "sg:province":"LA",
    "sg:tags":[
        "agency",
        "rental"
    ],
    "wof:name":"BNB Rentals & Sales",
    "wof:placetype":"venue"
},
  "geometry": {"coordinates":[-93.757544,32.412954],"type":"Point"}
}