{
  "type": "Feature",
  "properties": {
    "addr:full":"5733 US Hwy 167 Winnfield LA 71483",
    "addr:housenumber":"5733",
    "addr:postcode":"71483",
    "addr:street":"Us Hwy 167 Winnfield",
    "iso:country":"US",
    "sg:address":"5733 US Hwy 167",
    "sg:city":"Winnfield",
    "sg:classifiers":[
        {
            "category":"Autos & Motor Vehicles",
            "subcategory":"Fuel & Gas Station",
            "type":"Retail Goods"
        }
    ],
    "sg:phone":"+1 318 628 3100",
    "sg:postcode":"71483",
    "sg:province":"LA",
    "sg:tags":[
        "station",
        "gasoline"
    ],
    "wof:name":"Country Boy Truck Stop",
    "wof:placetype":"venue"
},
  "geometry": {"coordinates":[-92.653453,31.935404],"type":"Point"}
}