{
  "type": "Feature",
  "properties": {
    "addr:full":"1548 Martin Luther King Blvd Houma LA 70360",
    "addr:housenumber":"1548",
    "addr:postcode":"70360",
    "addr:street":"Martin Luther King Blvd",
    "iso:country":"US",
    "sg:address":"1548 Martin Luther King Blvd",
    "sg:city":"Houma",
    "sg:classifiers":[
        {
            "category":"Shopping",
            "subcategory":"Hobbies, Toys, & Games",
            "type":"Retail Goods"
        }
    ],
    "sg:phone":"+1 985 872 0278",
    "sg:postcode":"70360",
    "sg:province":"LA",
    "sg:tags":[
        "craft",
        "supply"
    ],
    "wof:name":"Michaels Arts & Crafts Store",
    "wof:placetype":"venue"
},
  "geometry": {"coordinates":[-90.75075699999999,29.610108],"type":"Point"}
}