{
  "type": "Feature",
  "properties": {
    "addr:full":"1040 Magazine St New Orleans LA 70130",
    "addr:housenumber":"1040",
    "addr:postcode":"70130",
    "addr:street":"Magazine St",
    "iso:country":"US",
    "sg:address":"1040 Magazine St",
    "sg:city":"New Orleans",
    "sg:classifiers":[
        {
            "category":"Wholesale",
            "subcategory":"Wine & Distilled Alcoholic Beverages",
            "type":"Manufacturing & Wholesale Goods"
        }
    ],
    "sg:phone":"+1 504 523 5230",
    "sg:postcode":"70130",
    "sg:province":"LA",
    "sg:website":"www.purveyors.net",
    "wof:name":"Purveyor Of Fine Wines LTD",
    "wof:placetype":"venue"
},
  "geometry": {"coordinates":[-90.070336,29.941254],"type":"Point"}
}