{
  "type": "Feature",
  "properties": {
    "iso:country":"US",
    "sg:address":"1001 Live Oak St",
    "sg:city":"Metairie",
    "sg:classifiers":[
        {
            "category":"Restaurant",
            "type":"Food & Drink"
        }
    ],
    "sg:phone":"+1 504 838 0022",
    "sg:postcode":"70005",
    "sg:province":"LA",
    "wof:name":"Mr Ed's Restaurant & Catering",
    "wof:placetype":"venue"
},
  "geometry": {"coordinates":[-90.133613,30.018141],"type":"Point"}
}