{
  "type": "Feature",
  "properties": {
    "iso:country":"US",
    "sg:address":"4948 Hwy 1",
    "sg:city":"Mathews",
    "sg:classifiers":[
        {
            "category":"Shopping",
            "subcategory":"Florist",
            "type":"Retail Goods"
        }
    ],
    "sg:phone":"+1 985 532 8313",
    "sg:postcode":"70390",
    "sg:province":"LA",
    "wof:name":"Angela's Antiques Jewlery Gift",
    "wof:placetype":"venue"
},
  "geometry": {"coordinates":[-91.028374,29.945367],"type":"Point"}
}