{
  "type": "Feature",
  "properties": {
    "addr:full":"15142 Seven Pines Ave Baton Rouge LA 70817",
    "addr:housenumber":"15142",
    "addr:postcode":"70817",
    "addr:street":"Seven Pines Ave",
    "iso:country":"US",
    "sg:address":"15142 Seven Pines Ave",
    "sg:city":"Baton Rouge",
    "sg:classifiers":[
        {
            "category":"Professional",
            "subcategory":"Management & Consulting",
            "type":"Services"
        }
    ],
    "sg:phone":"+1 225 756 8675",
    "sg:postcode":"70817",
    "sg:province":"LA",
    "sg:tags":[
        "business"
    ],
    "wof:name":"Alpha Environmental Associates",
    "wof:placetype":"venue"
},
  "geometry": {"coordinates":[-91.01383199999999,30.392465],"type":"Point"}
}