{
  "type": "Feature",
  "properties": {
    "iso:country":"US",
    "sg:address":"200 Post Dr",
    "sg:city":"Luling",
    "sg:classifiers":[
        {
            "category":"Retail",
            "subcategory":"Repair Shop",
            "type":"Services"
        }
    ],
    "sg:phone":"+1 985 785 6212",
    "sg:postcode":"70070",
    "sg:province":"LA",
    "sg:tags":[
        "television",
        "radio"
    ],
    "wof:name":"Walton Service Center",
    "wof:placetype":"venue"
},
  "geometry": {"coordinates":[-90.36736999999999,29.926741],"type":"Point"}
}