{
  "type": "Feature",
  "properties": {
    "iso:country":"US",
    "sg:address":"2602 S Range Ave",
    "sg:city":"Denham Springs",
    "sg:classifiers":[
        {
            "category":"Food & Beverages",
            "subcategory":"Groceries & Convenience Stores",
            "type":"Retail Goods"
        }
    ],
    "sg:phone":"+1 225 665 1836",
    "sg:postcode":"70726",
    "sg:province":"LA",
    "sg:tags":[
        "grocer"
    ],
    "wof:name":"Cracker Barrel Stores Inc",
    "wof:placetype":"venue"
},
  "geometry": {"coordinates":[-90.956424,30.449282],"type":"Point"}
}