{
  "type": "Feature",
  "properties": {
    "iso:country":"US",
    "sg:address":"3017 14th St",
    "sg:city":"Metairie",
    "sg:classifiers":[
        {
            "category":"Shopping",
            "subcategory":"Gifts & Souvenirs",
            "type":"Retail Goods"
        }
    ],
    "sg:phone":"+1 504 833 9108",
    "sg:postcode":"70002",
    "sg:province":"LA",
    "wof:name":"Special Things Just 4u",
    "wof:placetype":"venue"
},
  "geometry": {"coordinates":[-90.15301599999999,30.011549],"type":"Point"}
}