{
  "type": "Feature",
  "properties": {
    "addr:full":"1604 Metro Dr Alexandria LA 71301",
    "addr:postcode":"1604;71301",
    "addr:street":"Metro Dr",
    "iso:country":"US",
    "sg:address":"1604 Metro Dr",
    "sg:city":"Alexandria",
    "sg:classifiers":[
        {
            "category":"Shopping",
            "subcategory":"Clothing, Apparel, & Fashions",
            "type":"Retail Goods"
        }
    ],
    "sg:phone":"+1 318 442 4713",
    "sg:postcode":"71301",
    "sg:province":"LA",
    "sg:tags":[
        "infant",
        "wear"
    ],
    "wof:name":"Sue's Child Shop",
    "wof:placetype":"venue"
},
  "geometry": {"coordinates":[-92.474704,31.275306],"type":"Point"}
}