{
  "type": "Feature",
  "properties": {
    "addr:full":"1201 N 3rd St Baton Rouge LA 70802",
    "addr:housenumber":"1201",
    "addr:postcode":"70802",
    "addr:street":"N 3Rd St",
    "iso:country":"US",
    "sg:address":"1201 N 3rd St",
    "sg:city":"Baton Rouge",
    "sg:classifiers":[
        {
            "category":"Education",
            "subcategory":"College",
            "type":"Public Place"
        }
    ],
    "sg:phone":"+1 225 342 6950",
    "sg:postcode":"70802",
    "sg:province":"LA",
    "sg:tags":[
        "academic",
        "school"
    ],
    "sg:website":"www.ulsystem.net",
    "wof:name":"Board Of Trustees-State Clg",
    "wof:placetype":"venue"
},
  "geometry": {"coordinates":[-91.187614,30.461188],"type":"Point"}
}