{
  "type": "Feature",
  "properties": {
    "iso:country":"US",
    "sg:address":"315 S Broad St",
    "sg:city":"New Orleans",
    "sg:classifiers":[
        {
            "category":"Organizations",
            "subcategory":"Labor Organization",
            "type":"Services"
        }
    ],
    "sg:phone":"+1 504 822 4624",
    "sg:postcode":"70119",
    "sg:province":"LA",
    "wof:name":"Carpenter's",
    "wof:placetype":"venue"
},
  "geometry": {"coordinates":[-90.089213,29.963727],"type":"Point"}
}