{
  "type": "Feature",
  "properties": {
    "iso:country":"US",
    "sg:address":"10466 Airline Hwy",
    "sg:city":"Baton Rouge",
    "sg:classifiers":[
        {
            "category":"Professional",
            "subcategory":"Advertising",
            "type":"Services"
        }
    ],
    "sg:phone":"+1 225 295 0095",
    "sg:postcode":"70816",
    "sg:province":"LA",
    "sg:tags":[
        "distribution"
    ],
    "wof:name":"Danco Distributing Inc",
    "wof:placetype":"venue"
},
  "geometry": {"coordinates":[-91.067498,30.413683],"type":"Point"}
}