{
  "type": "Feature",
  "properties": {
    "iso:country":"US",
    "sg:address":"1017 US Hwy 71",
    "sg:city":"Campti",
    "sg:classifiers":[
        {
            "category":"Government",
            "subcategory":"Office",
            "type":"Public Place"
        }
    ],
    "sg:phone":"+1 318 476 3192",
    "sg:postcode":"71411",
    "sg:province":"LA",
    "wof:name":"Campti Voting Precinct",
    "wof:placetype":"venue"
},
  "geometry": {"coordinates":[-93.161698,31.951624],"type":"Point"}
}