{
  "type": "Feature",
  "properties": {
    "iso:country":"US",
    "sg:address":"455 2nd St",
    "sg:city":"Natchitoches",
    "sg:classifiers":[
        {
            "category":"Professional",
            "type":"Services"
        }
    ],
    "sg:phone":"+1 318 352 9129",
    "sg:postcode":"71457",
    "sg:province":"LA",
    "sg:tags":[
        "establishment"
    ],
    "wof:name":"Habitate For Humanity",
    "wof:placetype":"venue"
},
  "geometry": {"coordinates":[-93.08835000000001,31.759028],"type":"Point"}
}