{
  "type": "Feature",
  "properties": {
    "addr:full":"803 Brownswitch Rd Slidell LA 70458",
    "addr:housenumber":"803",
    "addr:postcode":"70458",
    "addr:street":"Brownswitch Rd",
    "iso:country":"US",
    "sg:address":"803 Brownswitch Rd",
    "sg:city":"Slidell",
    "sg:classifiers":[
        {
            "category":"Real Estate",
            "subcategory":"Real Estate Agent",
            "type":"Services"
        }
    ],
    "sg:phone":"+1 985 690 1527",
    "sg:postcode":"70458",
    "sg:province":"LA",
    "wof:name":"Joann Ponthier",
    "wof:placetype":"venue"
},
  "geometry": {"coordinates":[-89.749014,30.310456],"type":"Point"}
}