{
  "type": "Feature",
  "properties": {
    "iso:country":"US",
    "sg:address":"515 W University Ave",
    "sg:city":"Lafayette",
    "sg:classifiers":[
        {
            "category":"Professional",
            "subcategory":"Secretarial Services",
            "type":"Services"
        }
    ],
    "sg:phone":"+1 337 237 5039",
    "sg:postcode":"70506",
    "sg:province":"LA",
    "sg:tags":[
        "reporting"
    ],
    "wof:name":"Court Reporters",
    "wof:placetype":"venue"
},
  "geometry": {"coordinates":[-92.022794,30.220067],"type":"Point"}
}