{
  "type": "Feature",
  "properties": {
    "iso:country":"US",
    "sg:address":"200 N Bernard St",
    "sg:city":"Ruston",
    "sg:classifiers":[
        {
            "category":"Education",
            "subcategory":"School",
            "type":"Public Place"
        }
    ],
    "sg:phone":"+1 318 255 4714",
    "sg:postcode":"71270",
    "sg:province":"LA",
    "wof:name":"Ruston Elementary School",
    "wof:placetype":"venue"
},
  "geometry": {"coordinates":[-92.622525,32.530746],"type":"Point"}
}