{
  "type": "Feature",
  "properties": {
    "iso:country":"US",
    "sg:address":"105 E Lincoln Rd",
    "sg:city":"Ville Platte",
    "sg:phone":"+1 337 363 5674",
    "sg:postcode":"70586",
    "sg:province":"LA",
    "sg:tags":[
        "oil",
        "gasoline"
    ],
    "wof:name":"Ortego Services",
    "wof:placetype":"venue"
},
  "geometry": {"coordinates":[-92.269532,30.695487],"type":"Point"}
}