{
  "type": "Feature",
  "properties": {
    "iso:country":"US",
    "sg:address":"15490 River Rd",
    "sg:city":"Hahnville",
    "sg:classifiers":[
        {
            "category":"Retail",
            "subcategory":"Funeral Services",
            "type":"Services"
        }
    ],
    "sg:phone":"+1 985 783 2215",
    "sg:postcode":"70057",
    "sg:province":"LA",
    "sg:tags":[
        "director"
    ],
    "wof:name":"Robottom Mortuary",
    "wof:placetype":"venue"
},
  "geometry": {"coordinates":[-90.417171,29.988753],"type":"Point"}
}