{
  "type": "Feature",
  "properties": {
    "iso:country":"US",
    "sg:address":"709 Tchoupitoulas St",
    "sg:city":"New Orleans",
    "sg:classifiers":[
        {
            "category":"Retail",
            "subcategory":"Repair Shop",
            "type":"Services"
        }
    ],
    "sg:phone":"+1 504 523 5397",
    "sg:postcode":"70130",
    "sg:province":"LA",
    "sg:tags":[
        "lock",
        "locksmith"
    ],
    "wof:name":"Dr Lock Locksmiths Inc",
    "wof:placetype":"venue"
},
  "geometry": {"coordinates":[-90.06746699999999,29.945905],"type":"Point"}
}