{
  "type": "Feature",
  "properties": {
    "addr:full":"417 Frenchmen St New Orleans LA 70116",
    "addr:housenumber":"417",
    "addr:postcode":"70116",
    "addr:street":"Frenchmen St",
    "iso:country":"US",
    "sg:address":"417 Frenchmen St",
    "sg:city":"New Orleans",
    "sg:classifiers":[
        {
            "category":"Travel",
            "subcategory":"Hotels & Motels",
            "type":"Entertainment"
        }
    ],
    "sg:phone":"+1 504 948 2166",
    "sg:postcode":"70116",
    "sg:province":"LA",
    "sg:website":"www.frenchmenhotel.com",
    "wof:name":"The Frenchmen Hotel",
    "wof:placetype":"venue"
},
  "geometry": {"coordinates":[-90.0578,29.962099],"type":"Point"}
}