{
  "type": "Feature",
  "properties": {
    "iso:country":"US",
    "sg:address":"199 Grand Ave",
    "sg:city":"Lafayette",
    "sg:classifiers":[
        {
            "category":"Professional",
            "type":"Services"
        }
    ],
    "sg:phone":"+1 337 993 9262",
    "sg:postcode":"70503",
    "sg:province":"LA",
    "wof:name":"Square Root of PI Inc",
    "wof:placetype":"venue"
},
  "geometry": {"coordinates":[-92.06591899999999,30.186563],"type":"Point"}
}