{
  "type": "Feature",
  "properties": {
    "addr:full":"17660 George Oneal Rd Baton Rouge LA 70817",
    "addr:housenumber":"17660",
    "addr:postcode":"70817",
    "addr:street":"George Oneal Rd",
    "iso:country":"US",
    "sg:address":"17660 George Oneal Rd",
    "sg:city":"Baton Rouge",
    "sg:classifiers":[
        {
            "category":"Restaurant",
            "type":"Food & Drink"
        }
    ],
    "sg:phone":"+1 225 751 1882",
    "sg:postcode":"70817",
    "sg:province":"LA",
    "sg:tags":[
        "caterer"
    ],
    "sg:website":"www.jfolse.com",
    "wof:name":"White Oak Plantation",
    "wof:placetype":"venue"
},
  "geometry": {"coordinates":[-90.99824599999999,30.414202],"type":"Point"}
}