{
  "type": "Feature",
  "properties": {
    "iso:country":"US",
    "sg:address":"675 Kansas Ln",
    "sg:city":"Monroe",
    "sg:classifiers":[
        {
            "category":"Wholesale",
            "subcategory":"Scrap",
            "type":"Manufacturing & Wholesale Goods"
        }
    ],
    "sg:phone":"+1 318 322 3770",
    "sg:postcode":"71203",
    "sg:province":"LA",
    "sg:tags":[
        "recycling",
        "center"
    ],
    "wof:name":"Interstate Metals Inc",
    "wof:placetype":"venue"
},
  "geometry": {"coordinates":[-92.053816,32.517237],"type":"Point"}
}