{
  "type": "Feature",
  "properties": {
    "iso:country":"US",
    "sg:address":"856 Broadway St",
    "sg:city":"Delhi",
    "sg:classifiers":[
        {
            "category":"Social Services",
            "type":"Services"
        }
    ],
    "sg:phone":"+1 318 878 9520",
    "sg:postcode":"71232",
    "sg:province":"LA",
    "sg:tags":[
        "organization",
        "welfare"
    ],
    "wof:name":"Richland Council On Aging Sr",
    "wof:placetype":"venue"
},
  "geometry": {"coordinates":[-91.493008,32.450209],"type":"Point"}
}