{
  "type": "Feature",
  "properties": {
    "iso:country":"US",
    "sg:address":"5432 Magazine St",
    "sg:city":"New Orleans",
    "sg:classifiers":[
        {
            "category":"Restaurant",
            "type":"Food & Drink"
        }
    ],
    "sg:phone":"+1 504 895 2202",
    "sg:postcode":"70115",
    "sg:province":"LA",
    "sg:tags":[
        "shop",
        "coffee"
    ],
    "wof:name":"Pj's Coffee & Tea Co",
    "wof:placetype":"venue"
},
  "geometry": {"coordinates":[-90.115758,29.920953],"type":"Point"}
}