{
  "type": "Feature",
  "properties": {
    "addr:full":"38026 State Rte 621 Gonzales LA 70737",
    "addr:housenumber":"38026",
    "addr:postcode":"70737",
    "addr:street":"State Rte 621 Gonzales La",
    "iso:country":"US",
    "sg:address":"38026 State Rte 621",
    "sg:city":"Gonzales",
    "sg:classifiers":[
        {
            "category":"Social Services",
            "subcategory":"Child Care",
            "type":"Services"
        }
    ],
    "sg:phone":"+1 225 673 3797",
    "sg:postcode":"70737",
    "sg:province":"LA",
    "sg:tags":[
        "kindergarten",
        "academic",
        "school"
    ],
    "wof:name":"Little Lads & Lassies Child",
    "wof:placetype":"venue"
},
  "geometry": {"coordinates":[-90.968138,30.269113],"type":"Point"}
}