{
  "type": "Feature",
  "properties": {
    "iso:country":"US",
    "sg:address":"3103 Monterrey Dr",
    "sg:city":"Baton Rouge",
    "sg:classifiers":[
        {
            "category":"Sports & Exercise",
            "subcategory":"Gym",
            "type":"Entertainment"
        }
    ],
    "sg:phone":"+1 225 926 7222",
    "sg:postcode":"70814",
    "sg:province":"LA",
    "sg:tags":[
        "club",
        "health",
        "studio",
        "gymnasium"
    ],
    "sg:website":"www.spectrumfitness.com",
    "wof:name":"Spectrum Fitness Club Inc",
    "wof:placetype":"venue"
},
  "geometry": {"coordinates":[-91.08375599999999,30.477126],"type":"Point"}
}