{
  "type": "Feature",
  "properties": {
    "iso:country":"US",
    "sg:address":"1201 Royal St",
    "sg:city":"New Orleans",
    "sg:classifiers":[
        {
            "category":"Deli",
            "type":"Food & Drink"
        }
    ],
    "sg:menulink":"http://www.allmenus.com/la/new-orleans/282863-verti-marte/menu/",
    "sg:phone":"+1 504 525 4767",
    "sg:postcode":"70116",
    "sg:province":"LA",
    "sg:tags":[
        "american"
    ],
    "wof:name":"Verti Marte",
    "wof:placetype":"venue"
},
  "geometry": {"coordinates":[-90.061154,29.961981],"type":"Point"}
}