{
  "type": "Feature",
  "properties": {
    "iso:country":"US",
    "sg:address":"132 Murray Ln",
    "sg:city":"Natchitoches",
    "sg:classifiers":[
        {
            "category":"Freight",
            "type":"Transportation"
        }
    ],
    "sg:phone":"+1 318 357 0056",
    "sg:postcode":"71457",
    "sg:province":"LA",
    "sg:tags":[
        "operator",
        "local",
        "trucking"
    ],
    "wof:name":"Moran Trucking",
    "wof:placetype":"venue"
},
  "geometry": {"coordinates":[-93.146739,31.760272],"type":"Point"}
}