{
  "type": "Feature",
  "properties": {
    "iso:country":"US",
    "sg:address":"239 Meredith Rd",
    "sg:city":"Columbia",
    "sg:classifiers":[
        {
            "category":"Retail",
            "subcategory":"Auto Repair",
            "type":"Services"
        }
    ],
    "sg:phone":"+1 318 649 9321",
    "sg:postcode":"71418",
    "sg:province":"LA",
    "sg:tags":[
        "repairing",
        "automobile"
    ],
    "wof:name":"A & H Auto Truck Repair",
    "wof:placetype":"venue"
},
  "geometry": {"coordinates":[-91.995752,32.250259],"type":"Point"}
}