{
  "type": "Feature",
  "properties": {
    "addr:full":"3851 S Sherwood Forest Blvd Baton Rouge LA 70816",
    "addr:housenumber":"3851",
    "addr:postcode":"70816",
    "addr:street":"S Sherwood Forest Blvd",
    "iso:country":"US",
    "sg:address":"3851 S Sherwood Forest Blvd",
    "sg:city":"Baton Rouge",
    "sg:classifiers":[
        {
            "category":"Restaurant",
            "type":"Food & Drink"
        }
    ],
    "sg:menulink":"http://www.allmenus.com/la/baton-rouge/136636-smoothie-king/menu/",
    "sg:phone":"+1 225 291 5464",
    "sg:postcode":"70816",
    "sg:province":"LA",
    "sg:tags":[
        "smoothy",
        "juice",
        "american"
    ],
    "wof:name":"Smoothie King",
    "wof:placetype":"venue"
},
  "geometry": {"coordinates":[-91.05109400000001,30.417739],"type":"Point"}
}