{
  "type": "Feature",
  "properties": {
    "iso:country":"US",
    "sg:address":"622 E 1st St",
    "sg:city":"Kaplan",
    "sg:classifiers":[
        {
            "category":"Shopping",
            "subcategory":"Pharmacy",
            "type":"Retail Goods"
        }
    ],
    "sg:phone":"+1 337 643 8611",
    "sg:postcode":"70548",
    "sg:province":"LA",
    "wof:name":"Eckerd",
    "wof:placetype":"venue"
},
  "geometry": {"coordinates":[-92.279805,29.996554],"type":"Point"}
}