{
  "type": "Feature",
  "properties": {
    "iso:country":"US",
    "sg:address":"905 Pearl St",
    "sg:city":"Franklinton",
    "sg:classifiers":[
        {
            "category":"Professional",
            "subcategory":"Lawyer & Legal Services",
            "type":"Services"
        }
    ],
    "sg:phone":"+1 985 795 8713",
    "sg:postcode":"70438",
    "sg:province":"LA",
    "sg:tags":[
        "attorney"
    ],
    "wof:name":"District Attorney Investigatio",
    "wof:placetype":"venue"
},
  "geometry": {"coordinates":[-90.15465500000001,30.844332],"type":"Point"}
}