{
  "type": "Feature",
  "properties": {
    "iso:country":"US",
    "sg:address":"1430 Dalzell St",
    "sg:city":"Shreveport",
    "sg:classifiers":[
        {
            "category":"Shopping",
            "subcategory":"Computers & Home Electronics",
            "type":"Retail Goods"
        }
    ],
    "sg:phone":"+1 318 425 2525",
    "sg:postcode":"71103",
    "sg:province":"LA",
    "sg:tags":[
        "high",
        "fidelity",
        "stereophonic"
    ],
    "sg:website":"www.12volt.com",
    "wof:name":"12 Volt Group",
    "wof:placetype":"venue"
},
  "geometry": {"coordinates":[-93.757994,32.489154],"type":"Point"}
}