{
  "type": "Feature",
  "properties": {
    "iso:country":"US",
    "sg:address":"712 Wilson St",
    "sg:city":"Monroe",
    "sg:classifiers":[
        {
            "category":"Organizations",
            "subcategory":"Religious Organization",
            "type":"Services"
        }
    ],
    "sg:phone":"+1 318 387 3938",
    "sg:postcode":"71202",
    "sg:province":"LA",
    "sg:tags":[
        "church"
    ],
    "wof:name":"Gaines Chapel Baptist Church",
    "wof:placetype":"venue"
},
  "geometry": {"coordinates":[-92.099664,32.474783],"type":"Point"}
}