{
  "type": "Feature",
  "properties": {
    "addr:full":"804 Doucet Rd Lafayette LA 70503",
    "addr:housenumber":"804",
    "addr:postcode":"70503",
    "addr:street":"Doucet Rd",
    "iso:country":"US",
    "sg:address":"804 Doucet Rd",
    "sg:city":"Lafayette",
    "sg:classifiers":[
        {
            "category":"Restaurant",
            "type":"Food & Drink"
        }
    ],
    "sg:phone":"+1 337 988 9873",
    "sg:postcode":"70503",
    "sg:province":"LA",
    "sg:tags":[
        "eating"
    ],
    "wof:name":"Sheetal Enterprise Inc",
    "wof:placetype":"venue"
},
  "geometry": {"coordinates":[-92.037114,30.192751],"type":"Point"}
}