{
  "type": "Feature",
  "properties": {
    "iso:country":"US",
    "sg:address":"212 S Adams Ave",
    "sg:city":"Rayne",
    "sg:classifiers":[
        {
            "category":"Recreation",
            "type":"Entertainment"
        }
    ],
    "sg:phone":"+1 337 334 6200",
    "sg:postcode":"70578",
    "sg:province":"LA",
    "sg:tags":[
        "martial",
        "arts",
        "instruction"
    ],
    "wof:name":"Rayne Karate Club",
    "wof:placetype":"venue"
},
  "geometry": {"coordinates":[-92.268884,30.234982],"type":"Point"}
}