{
  "type": "Feature",
  "properties": {
    "iso:country":"US",
    "sg:address":"304 Beaullieu Dr",
    "sg:city":"Lafayette",
    "sg:classifiers":[
        {
            "category":"Professional",
            "type":"Services"
        }
    ],
    "sg:phone":"+1 337 267 4150",
    "sg:postcode":"70508",
    "sg:province":"LA",
    "sg:tags":[
        "establishment"
    ],
    "wof:name":"Spirit Global Trading",
    "wof:placetype":"venue"
},
  "geometry": {"coordinates":[-92.047495,30.164921],"type":"Point"}
}