{
  "type": "Feature",
  "properties": {
    "iso:country":"US",
    "sg:address":"720 Lafitte St",
    "sg:city":"Mandeville",
    "sg:classifiers":[
        {
            "category":"Organizations",
            "subcategory":"Community Association",
            "type":"Services"
        }
    ],
    "sg:phone":"+1 985 626 8862",
    "sg:postcode":"70448",
    "sg:province":"LA",
    "sg:tags":[
        "club"
    ],
    "wof:name":"Mandeville Lions",
    "wof:placetype":"venue"
},
  "geometry": {"coordinates":[-90.064183,30.362881],"type":"Point"}
}