{
  "type": "Feature",
  "properties": {
    "iso:country":"US",
    "sg:address":"13312 Alba Dr",
    "sg:city":"Baker",
    "sg:classifiers":[
        {
            "category":"Professional",
            "subcategory":"Management & Consulting",
            "type":"Services"
        }
    ],
    "sg:phone":"+1 225 774 8777",
    "sg:postcode":"70714",
    "sg:province":"LA",
    "sg:tags":[
        "business"
    ],
    "wof:name":"Charles Vincent",
    "wof:placetype":"venue"
},
  "geometry": {"coordinates":[-91.152872,30.567003],"type":"Point"}
}