{
  "type": "Feature",
  "properties": {
    "addr:full":"1709 Wells Island Rd Shreveport LA 71107",
    "addr:housenumber":"1709",
    "addr:postcode":"71107",
    "addr:street":"Wells Island Rd",
    "iso:country":"US",
    "sg:address":"1709 Wells Island Rd",
    "sg:city":"Shreveport",
    "sg:classifiers":[
        {
            "category":"Wholesale",
            "subcategory":"Construction Materials",
            "type":"Manufacturing & Wholesale Goods"
        }
    ],
    "sg:phone":"+1 318 221 6109",
    "sg:postcode":"71107",
    "sg:province":"LA",
    "sg:tags":[
        "marble"
    ],
    "wof:name":"Grecian Marble Mfg Co",
    "wof:placetype":"venue"
},
  "geometry": {"coordinates":[-93.769972,32.549663],"type":"Point"}
}