{
  "type": "Feature",
  "properties": {
    "iso:country":"US",
    "sg:address":"6320 Hayne Blvd",
    "sg:city":"New Orleans",
    "sg:classifiers":[
        {
            "category":"Real Estate",
            "subcategory":"Real Estate Operator",
            "type":"Services"
        }
    ],
    "sg:phone":"+1 504 242 1380",
    "sg:postcode":"70126",
    "sg:province":"LA",
    "sg:tags":[
        "apartment"
    ],
    "wof:name":"Seabrook Apartments",
    "wof:placetype":"venue"
},
  "geometry": {"coordinates":[-90.02055300000001,30.034761],"type":"Point"}
}