{
  "type": "Feature",
  "properties": {
    "iso:country":"US",
    "sg:address":"760 W Ave B",
    "sg:city":"Houma",
    "sg:classifiers":[
        {
            "category":"Social Services",
            "type":"Services"
        }
    ],
    "sg:phone":"+1 985 879 2001",
    "sg:postcode":"70345",
    "sg:province":"LA",
    "sg:tags":[
        "organization",
        "welfare"
    ],
    "sg:website":"www.fhfla.org",
    "wof:name":"Bayou Land Families Helping",
    "wof:placetype":"venue"
},
  "geometry": {"coordinates":[-90.36756699999999,29.559195],"type":"Point"}
}