{
  "type": "Feature",
  "properties": {
    "iso:country":"US",
    "sg:address":"137 N Clark St",
    "sg:city":"New Orleans",
    "sg:classifiers":[
        {
            "category":"Professional",
            "subcategory":"Advertising",
            "type":"Services"
        }
    ],
    "sg:phone":"+1 504 483 8014",
    "sg:postcode":"70119",
    "sg:province":"LA",
    "sg:tags":[
        "counselor"
    ],
    "wof:name":"Brandmarken Communications",
    "wof:placetype":"venue"
},
  "geometry": {"coordinates":[-90.094826,29.971246],"type":"Point"}
}