{
  "type": "Feature",
  "properties": {
    "iso:country":"US",
    "sg:address":"15045 Old Hammond Hwy",
    "sg:city":"Baton Rouge",
    "sg:classifiers":[
        {
            "category":"Manufacturing",
            "subcategory":"Tools & Machinery",
            "type":"Manufacturing & Wholesale Goods"
        }
    ],
    "sg:phone":"+1 225 272 7364",
    "sg:postcode":"70816",
    "sg:province":"LA",
    "sg:tags":[
        "physician",
        "surgeon"
    ],
    "sg:website":"www.motionlabsystems.com",
    "wof:name":"Motion Lab Systems Inc",
    "wof:placetype":"venue"
},
  "geometry": {"coordinates":[-91.0197,30.454308],"type":"Point"}
}