{
  "type": "Feature",
  "properties": {
    "addr:full":"1831 Turner St Alexandria LA 71301",
    "addr:housenumber":"1831",
    "addr:postcode":"71301",
    "addr:street":"Turner St",
    "iso:country":"US",
    "sg:address":"1831 Turner St",
    "sg:city":"Alexandria",
    "sg:classifiers":[
        {
            "category":"Sports & Exercise",
            "subcategory":"Gym",
            "type":"Entertainment"
        }
    ],
    "sg:phone":"+1 318 445 8261",
    "sg:postcode":"71301",
    "sg:province":"LA",
    "sg:tags":[
        "club",
        "health",
        "studio",
        "gymnasium"
    ],
    "wof:name":"YMCA",
    "wof:placetype":"venue"
},
  "geometry": {"coordinates":[-92.453222,31.298905],"type":"Point"}
}