{
  "type": "Feature",
  "properties": {
    "iso:country":"US",
    "sg:address":"518 Rosier Rd",
    "sg:city":"Deville",
    "sg:classifiers":[
        {
            "category":"Building & Trades",
            "subcategory":"Plumbing",
            "type":"Services"
        }
    ],
    "sg:phone":"+1 318 466 3396",
    "sg:postcode":"71328",
    "sg:province":"LA",
    "sg:tags":[
        "contractor"
    ],
    "wof:name":"Waynes Plumbing",
    "wof:placetype":"venue"
},
  "geometry": {"coordinates":[-92.226097,31.422373],"type":"Point"}
}