{
  "type": "Feature",
  "properties": {
    "iso:country":"US",
    "sg:address":"827 Royal St",
    "sg:city":"New Orleans",
    "sg:classifiers":[
        {
            "category":"Arts & Performance",
            "subcategory":"Art Gallery",
            "type":"Entertainment"
        }
    ],
    "sg:phone":"+1 504 592 9886",
    "sg:postcode":"70116",
    "sg:province":"LA",
    "sg:website":"www.paintedalive.com",
    "wof:name":"Craig Tracy Fine Art Bodypainting Gallery",
    "wof:placetype":"venue"
},
  "geometry": {"coordinates":[-90.063534,29.959317],"type":"Point"}
}