{
  "type": "Feature",
  "properties": {
    "addr:full":"9000 Patricia St Chalmette LA 70043",
    "addr:housenumber":"9000",
    "addr:postcode":"70043",
    "addr:street":"Patricia St",
    "iso:country":"US",
    "sg:address":"9000 Patricia St",
    "sg:city":"Chalmette",
    "sg:classifiers":[
        {
            "category":"Health Services",
            "subcategory":"Doctor",
            "type":"Services"
        }
    ],
    "sg:phone":"+1 504 277 0123",
    "sg:postcode":"70043",
    "sg:province":"LA",
    "sg:tags":[
        "physician",
        "surgeon"
    ],
    "wof:name":"Louisiana Heart Ctr",
    "wof:placetype":"venue"
},
  "geometry": {"coordinates":[-89.969994,29.956338],"type":"Point"}
}