{
  "type": "Feature",
  "properties": {
    "iso:country":"US",
    "sg:address":"101 Metals Dr",
    "sg:city":"Youngsville",
    "sg:classifiers":[
        {
            "category":"Retail",
            "subcategory":"Repair Shop",
            "type":"Services"
        }
    ],
    "sg:phone":"+1 337 856 9100",
    "sg:postcode":"70592",
    "sg:province":"LA",
    "sg:tags":[
        "valve"
    ],
    "sg:website":"www.lavalve.com",
    "wof:name":"Louisiana Valve Source Inc",
    "wof:placetype":"venue"
},
  "geometry": {"coordinates":[-91.97861899999999,30.099278],"type":"Point"}
}