{
  "type": "Feature",
  "properties": {
    "iso:country":"US",
    "sg:address":"3700 Delille St",
    "sg:city":"Chalmette",
    "sg:classifiers":[
        {
            "category":"Building & Trades",
            "subcategory":"Construction",
            "type":"Services"
        }
    ],
    "sg:phone":"+1 504 276 8778",
    "sg:postcode":"70043",
    "sg:province":"LA",
    "sg:tags":[
        "general",
        "contractor"
    ],
    "wof:name":"Ellis Construction",
    "wof:placetype":"venue"
},
  "geometry": {"coordinates":[-89.960655,29.956343],"type":"Point"}
}