{
  "type": "Feature",
  "properties": {
    "addr:full":"451 New Mineral Spring Rd Calhoun LA 71225",
    "addr:housenumber":"451",
    "addr:postcode":"71225",
    "addr:street":"New Mineral Spring Rd",
    "iso:country":"US",
    "sg:address":"451 New Mineral Spring Rd",
    "sg:city":"Calhoun",
    "sg:classifiers":[
        {
            "category":"Organizations",
            "subcategory":"Religious Organization",
            "type":"Services"
        }
    ],
    "sg:phone":"+1 318 644 2997",
    "sg:postcode":"71225",
    "sg:province":"LA",
    "sg:tags":[
        "church"
    ],
    "wof:name":"Mineral Springs CME Church",
    "wof:placetype":"venue"
},
  "geometry": {"coordinates":[-92.374629,32.452446],"type":"Point"}
}