{
  "type": "Feature",
  "properties": {
    "iso:country":"US",
    "sg:address":"862 Tchoupitoulas St",
    "sg:city":"New Orleans",
    "sg:classifiers":[
        {
            "category":"Home & Garden",
            "subcategory":"Home Furnishings",
            "type":"Retail Goods"
        }
    ],
    "sg:phone":"+1 504 522 3240",
    "sg:postcode":"70130",
    "sg:province":"LA",
    "sg:tags":[
        "pottery"
    ],
    "wof:name":"Chez Clay",
    "wof:placetype":"venue"
},
  "geometry": {"coordinates":[-90.06741599999999,29.944347],"type":"Point"}
}