{
  "type": "Feature",
  "properties": {
    "addr:full":"720 Genny Dr Breaux Bridge LA 70517",
    "addr:housenumber":"720",
    "addr:postcode":"la 70517",
    "addr:street":"Genny Dr",
    "iso:country":"US",
    "sg:address":"720 Genny Dr",
    "sg:city":"Breaux Bridge",
    "sg:classifiers":[
        {
            "category":"Real Estate",
            "subcategory":"Real Estate Agent",
            "type":"Services"
        }
    ],
    "sg:phone":"+1 337 332 2808",
    "sg:postcode":"70517",
    "sg:province":"LA",
    "sg:tags":[
        "authorities",
        "housing"
    ],
    "wof:name":"Breaux Bridge Housing Auth",
    "wof:placetype":"venue"
},
  "geometry": {"coordinates":[-91.898754,30.265306],"type":"Point"}
}