{
  "type": "Feature",
  "properties": {
    "addr:full":"215 Darden Rd Baldwin LA 70508",
    "addr:housenumber":"215",
    "addr:postcode":"70508",
    "addr:street":"Darden Rd",
    "iso:country":"US",
    "sg:address":"215 Darden Rd",
    "sg:city":"Baldwin",
    "sg:classifiers":[
        {
            "category":"Banks & Credit Unions",
            "subcategory":"Bank",
            "type":"Services"
        }
    ],
    "sg:phone":"+1 337 923 0513",
    "sg:postcode":"70508",
    "sg:province":"LA",
    "wof:name":"First National Bank Of Baldwin",
    "wof:placetype":"venue"
},
  "geometry": {"coordinates":[-92.041477,30.131218],"type":"Point"}
}