{
  "type": "Feature",
  "properties": {
    "iso:country":"US",
    "sg:address":"37466 White Rd",
    "sg:city":"Prairieville",
    "sg:classifiers":[
        {
            "category":"Professional",
            "subcategory":"Lawyer & Legal Services",
            "type":"Services"
        }
    ],
    "sg:phone":"+1 225 673 6159",
    "sg:postcode":"70769",
    "sg:province":"LA",
    "sg:tags":[
        "attorney"
    ],
    "wof:name":"Steve Joffrion",
    "wof:placetype":"venue"
},
  "geometry": {"coordinates":[-90.980778,30.291579],"type":"Point"}
}