{
  "type": "Feature",
  "properties": {
    "iso:country":"US",
    "sg:address":"100 Lancaster Ave",
    "sg:city":"Ferriday",
    "sg:classifiers":[
        {
            "category":"Retail",
            "subcategory":"Veterinary Services",
            "type":"Services"
        }
    ],
    "sg:phone":"+1 318 757 3842",
    "sg:postcode":"71334",
    "sg:province":"LA",
    "sg:tags":[
        "veterinarian"
    ],
    "wof:name":"Joe P Lancaster DVM",
    "wof:placetype":"venue"
},
  "geometry": {"coordinates":[-91.549488,31.637452],"type":"Point"}
}