{
  "type": "Feature",
  "properties": {
    "iso:country":"US",
    "sg:address":"11441 Clyde Place-Vivian Rd",
    "sg:city":"Vivian",
    "sg:classifiers":[
        {
            "category":"Freight",
            "type":"Transportation"
        }
    ],
    "sg:phone":"+1 318 375 5277",
    "sg:postcode":"71082",
    "sg:province":"LA",
    "sg:tags":[
        "commercial",
        "storage"
    ],
    "wof:name":"Boat Storage Allen",
    "wof:placetype":"venue"
},
  "geometry": {"coordinates":[-93.93104,32.789548],"type":"Point"}
}