{
  "type": "Feature",
  "properties": {
    "iso:country":"US",
    "sg:address":"1835 N Spring St",
    "sg:city":"Shreveport",
    "sg:classifiers":[
        {
            "category":"Government",
            "subcategory":"Office",
            "type":"Public Place"
        }
    ],
    "sg:phone":"+1 318 226 6757",
    "sg:postcode":"71101",
    "sg:province":"LA",
    "wof:name":"Honorable Vernon Claville",
    "wof:placetype":"venue"
},
  "geometry": {"coordinates":[-93.73505900000001,32.504107],"type":"Point"}
}