{
  "type": "Feature",
  "properties": {
    "iso:country":"US",
    "sg:address":"3200 N River Rd",
    "sg:city":"Port Allen",
    "sg:classifiers":[
        {
            "category":"Professional",
            "type":"Services"
        }
    ],
    "sg:phone":"+1 225 387 3200",
    "sg:postcode":"70767",
    "sg:province":"LA",
    "sg:tags":[
        "establishment"
    ],
    "wof:name":"Poplar Grove Planting & Refnsh",
    "wof:placetype":"venue"
},
  "geometry": {"coordinates":[-91.20322899999999,30.494418],"type":"Point"}
}