{
  "type": "Feature",
  "properties": {
    "iso:country":"US",
    "sg:address":"1087 S Flannery Rd",
    "sg:city":"Baton Rouge",
    "sg:classifiers":[
        {
            "category":"Food & Beverages",
            "subcategory":"Groceries & Convenience Stores",
            "type":"Retail Goods"
        }
    ],
    "sg:phone":"+1 225 272 0058",
    "sg:postcode":"70815",
    "sg:province":"LA",
    "wof:name":"Minute Mart",
    "wof:placetype":"venue"
},
  "geometry": {"coordinates":[-91.034395,30.45164],"type":"Point"}
}