{
  "type": "Feature",
  "properties": {
    "addr:full":"4933 Hastings St Metairie LA 70006",
    "addr:housenumber":"4933",
    "addr:postcode":"70006",
    "addr:street":"Hastings St",
    "iso:country":"US",
    "sg:address":"4933 Hastings St",
    "sg:city":"Metairie",
    "sg:classifiers":[
        {
            "category":"Personal",
            "subcategory":"Shoe Repair & Shine",
            "type":"Services"
        }
    ],
    "sg:phone":"+1 504 455 2364",
    "sg:postcode":"70006",
    "sg:province":"LA",
    "sg:tags":[
        "parlor",
        "shoeshine"
    ],
    "wof:name":"Busy Bee Hive Shoe Repair Shop",
    "wof:placetype":"venue"
},
  "geometry": {"coordinates":[-90.19753900000001,30.013944],"type":"Point"}
}