{
  "type": "Feature",
  "properties": {
    "addr:full":"2232 Wilton St Marrero LA 70072",
    "addr:housenumber":"2232",
    "addr:postcode":"70072",
    "addr:street":"Wilton St Marrero",
    "iso:country":"US",
    "sg:address":"2232 Wilton St",
    "sg:city":"Marrero",
    "sg:classifiers":[
        {
            "category":"Freight",
            "type":"Transportation"
        }
    ],
    "sg:phone":"+1 504 340 1212",
    "sg:postcode":"70072",
    "sg:province":"LA",
    "sg:tags":[
        "operator",
        "local",
        "trucking"
    ],
    "wof:name":"G&S Transportation",
    "wof:placetype":"venue"
},
  "geometry": {"coordinates":[-90.103712,29.862274],"type":"Point"}
}