{
  "type": "Feature",
  "properties": {
    "iso:country":"US",
    "sg:address":"4905 Westbank Expy",
    "sg:city":"Marrero",
    "sg:classifiers":[
        {
            "category":"Restaurant",
            "type":"Food & Drink"
        }
    ],
    "sg:phone":"+1 504 340 1003",
    "sg:postcode":"70072",
    "sg:province":"LA",
    "wof:name":"Popeyes Chicken & Biscuits",
    "wof:placetype":"venue"
},
  "geometry": {"coordinates":[-90.09906100000001,29.894323],"type":"Point"}
}