{
  "type": "Feature",
  "properties": {
    "addr:full":"4905 Westbank Expy Marrero LA 70072",
    "addr:housenumber":"4905",
    "addr:postcode":"70072",
    "addr:street":"Westbank Expy Marrero",
    "iso:country":"US",
    "sg:address":"4905 Westbank Expy",
    "sg:city":"Marrero",
    "sg:classifiers":[
        {
            "category":"Restaurant",
            "type":"Food & Drink"
        }
    ],
    "sg:phone":"+1 504 340 1003",
    "sg:postcode":"70072",
    "sg:province":"LA",
    "wof:name":"Popeyes Chicken & Biscuits",
    "wof:placetype":"venue"
},
  "geometry": {"coordinates":[-90.09906100000001,29.894323],"type":"Point"}
}