{
  "type": "Feature",
  "properties": {
    "iso:country":"US",
    "sg:address":"2235 Grapevine Ln",
    "sg:city":"Haughton",
    "sg:classifiers":[
        {
            "category":"Home & Garden",
            "subcategory":"Hardware",
            "type":"Retail Goods"
        }
    ],
    "sg:phone":"+1 318 390 8925",
    "sg:postcode":"71037",
    "sg:province":"LA",
    "sg:tags":[
        "tool",
        "used"
    ],
    "wof:name":"Tool & Torque Specialty",
    "wof:placetype":"venue"
},
  "geometry": {"coordinates":[-93.574658,32.548811],"type":"Point"}
}