{
  "type": "Feature",
  "properties": {
    "addr:full":"1329 N Hwy 190 Covington LA 70433",
    "addr:housenumber":"1329",
    "addr:postcode":"70433",
    "addr:street":"N Hwy 190",
    "iso:country":"US",
    "sg:address":"1329 N Hwy 190",
    "sg:city":"Covington",
    "sg:classifiers":[
        {
            "category":"Retail",
            "subcategory":"Auto Repair",
            "type":"Services"
        }
    ],
    "sg:phone":"+1 985 893 7725",
    "sg:postcode":"70433",
    "sg:province":"LA",
    "sg:tags":[
        "repairing",
        "engine"
    ],
    "wof:name":"Northshore Engine Exchange",
    "wof:placetype":"venue"
},
  "geometry": {"coordinates":[-90.082409,30.451363],"type":"Point"}
}