{
  "type": "Feature",
  "properties": {
    "iso:country":"US",
    "sg:address":"1802 Ridge Rd",
    "sg:city":"Duson",
    "sg:classifiers":[
        {
            "category":"Home & Garden",
            "subcategory":"Building Materials",
            "type":"Retail Goods"
        }
    ],
    "sg:phone":"+1 337 258 0654",
    "sg:postcode":"70529",
    "sg:province":"LA",
    "sg:tags":[
        "glass",
        "window",
        "plate"
    ],
    "wof:name":"Imperial Glass",
    "wof:placetype":"venue"
},
  "geometry": {"coordinates":[-92.138532,30.18125],"type":"Point"}
}