{
  "type": "Feature",
  "properties": {
    "iso:country":"US",
    "sg:address":"8201 State Rte 182",
    "sg:city":"Morgan City",
    "sg:classifiers":[
        {
            "category":"Autos & Motor Vehicles",
            "subcategory":"Boat Sales",
            "type":"Retail Goods"
        }
    ],
    "sg:phone":"+1 985 384 3000",
    "sg:postcode":"70380",
    "sg:province":"LA",
    "sg:tags":[
        "equipment",
        "marine",
        "supply"
    ],
    "wof:name":"American Supply Co",
    "wof:placetype":"venue"
},
  "geometry": {"coordinates":[-91.16814100000001,29.692902],"type":"Point"}
}