{
  "type": "Feature",
  "properties": {
    "iso:country":"US",
    "sg:address":"1405 Moss St",
    "sg:city":"Lafayette",
    "sg:classifiers":[
        {
            "category":"Professional",
            "subcategory":"Credit Reporting & Collection",
            "type":"Services"
        }
    ],
    "sg:phone":"+1 337 233 4826",
    "sg:postcode":"70501",
    "sg:province":"LA",
    "sg:tags":[
        "agency"
    ],
    "sg:website":"www.lbccinc.com",
    "wof:name":"Lafayette Bureau Credit Inc",
    "wof:placetype":"venue"
},
  "geometry": {"coordinates":[-92.006333,30.245207],"type":"Point"}
}