{
  "type": "Feature",
  "properties": {
    "iso:country":"US",
    "sg:address":"1016 Division Rd",
    "sg:city":"St Martinville",
    "sg:classifiers":[
        {
            "category":"Professional",
            "subcategory":"Management & Consulting",
            "type":"Services"
        }
    ],
    "sg:phone":"+1 337 380 8039",
    "sg:postcode":"70582",
    "sg:province":"LA",
    "sg:tags":[
        "field",
        "oil",
        "consultant"
    ],
    "wof:name":"H & L Inspection Svc",
    "wof:placetype":"venue"
},
  "geometry": {"coordinates":[-91.79199300000001,30.076333],"type":"Point"}
}