{
  "type": "Feature",
  "properties": {
    "iso:country":"US",
    "sg:address":"2041 Willowick St",
    "sg:city":"Lake Charles",
    "sg:classifiers":[
        {
            "category":"Manufacturing",
            "subcategory":"Motor Vehicles & Parts",
            "type":"Manufacturing & Wholesale Goods"
        }
    ],
    "sg:phone":"+1 337 802 1313",
    "sg:postcode":"70607",
    "sg:province":"LA",
    "sg:tags":[
        "mfg"
    ],
    "wof:name":"S&S Motorcycle Accessories LLC",
    "wof:placetype":"venue"
},
  "geometry": {"coordinates":[-93.19089200000001,30.193119],"type":"Point"}
}