{
  "type": "Feature",
  "properties": {
    "iso:country":"US",
    "sg:address":"233 State Rte 1008",
    "sg:city":"Napoleonville",
    "sg:classifiers":[
        {
            "category":"Government",
            "subcategory":"Jail",
            "type":"Public Place"
        }
    ],
    "sg:phone":"+1 985 369 7669",
    "sg:postcode":"70390",
    "sg:province":"LA",
    "sg:tags":[
        "county",
        "govt",
        "institution"
    ],
    "wof:name":"Assumption Parish Jail",
    "wof:placetype":"venue"
},
  "geometry": {"coordinates":[-91.031412,29.938844],"type":"Point"}
}