{
  "type": "Feature",
  "properties": {
    "iso:country":"US",
    "sg:address":"2313 Salem St",
    "sg:city":"Kenner",
    "sg:classifiers":[
        {
            "category":"Retail",
            "subcategory":"Auto Repair",
            "type":"Services"
        }
    ],
    "sg:phone":"+1 504 712 0097",
    "sg:postcode":"70062",
    "sg:province":"LA",
    "sg:tags":[
        "automobile",
        "customizing"
    ],
    "wof:name":"Moore Customs",
    "wof:placetype":"venue"
},
  "geometry": {"coordinates":[-90.268691,30.001539],"type":"Point"}
}