{
  "type": "Feature",
  "properties": {
    "iso:country":"US",
    "sg:address":"1714 US Hwy 190",
    "sg:city":"Slidell",
    "sg:classifiers":[
        {
            "category":"Restaurant",
            "type":"Food & Drink"
        }
    ],
    "sg:phone":"+1 985 646 1205",
    "sg:postcode":"70460",
    "sg:province":"LA",
    "sg:tags":[
        "eating"
    ],
    "wof:name":"South Seas Chinese Restaurants",
    "wof:placetype":"venue"
},
  "geometry": {"coordinates":[-89.80197099999999,30.294832],"type":"Point"}
}