{
  "type": "Feature",
  "properties": {
    "addr:full":"5005 US Hwy 84 Vidalia LA 71373",
    "addr:housenumber":"5005",
    "addr:postcode":"71373",
    "addr:street":"Us Hwy 84 Vidalia",
    "iso:country":"US",
    "sg:address":"5005 US Hwy 84",
    "sg:city":"Vidalia",
    "sg:classifiers":[
        {
            "category":"Building & Trades",
            "subcategory":"Electrical",
            "type":"Services"
        }
    ],
    "sg:phone":"+1 318 336 5738",
    "sg:postcode":"71373",
    "sg:province":"LA",
    "sg:tags":[
        "electric",
        "contractor"
    ],
    "wof:name":"Olsen Electric Supply Co",
    "wof:placetype":"venue"
},
  "geometry": {"coordinates":[-91.49888,31.587252],"type":"Point"}
}