{
  "type": "Feature",
  "properties": {
    "addr:full":"385 Hwy 860 Delhi LA 71232",
    "addr:housenumber":"385",
    "addr:postcode":"71232",
    "addr:street":"Hwy 860",
    "iso:country":"US",
    "sg:address":"385 Hwy 860",
    "sg:city":"Delhi",
    "sg:classifiers":[
        {
            "category":"Farming",
            "subcategory":"Farm & Veterinary Services",
            "type":"Manufacturing & Wholesale Goods"
        }
    ],
    "sg:phone":"+1 318 722 3501",
    "sg:postcode":"71232",
    "sg:province":"LA",
    "sg:tags":[
        "aerial",
        "applicator"
    ],
    "wof:name":"Bear Flying Svc",
    "wof:placetype":"venue"
},
  "geometry": {"coordinates":[-91.54016900000001,32.301131],"type":"Point"}
}