{
  "type": "Feature",
  "properties": {
    "iso:country":"US",
    "sg:address":"208 N Church St",
    "sg:city":"Carencro",
    "sg:classifiers":[
        {
            "category":"Health Services",
            "subcategory":"Doctor",
            "type":"Services"
        }
    ],
    "sg:phone":"+1 337 896 4090",
    "sg:postcode":"70520",
    "sg:province":"LA",
    "sg:tags":[
        "practice",
        "family"
    ],
    "wof:name":"Nguyen Nhu Vong MD",
    "wof:placetype":"venue"
},
  "geometry": {"coordinates":[-92.046303,30.3186],"type":"Point"}
}