{
  "type": "Feature",
  "properties": {
    "addr:full":"553 Central Ave Reserve LA 70084",
    "addr:housenumber":"553",
    "addr:postcode":"70084",
    "addr:street":"Central Ave",
    "iso:country":"US",
    "sg:address":"553 Central Ave",
    "sg:city":"Reserve",
    "sg:classifiers":[
        {
            "category":"Professional",
            "type":"Services"
        }
    ],
    "sg:phone":"+1 985 479 1316",
    "sg:postcode":"70084",
    "sg:province":"LA",
    "wof:name":"E S & H Turnaround Svc",
    "wof:placetype":"venue"
},
  "geometry": {"coordinates":[-90.552322,30.073614],"type":"Point"}
}