{
  "type": "Feature",
  "properties": {
    "addr:full":"8132 Willow St New Orleans LA 70118",
    "addr:housenumber":"8132",
    "addr:postcode":"70118",
    "addr:street":"Willow St",
    "iso:country":"US",
    "sg:address":"8132 Willow St",
    "sg:city":"New Orleans",
    "sg:classifiers":[
        {
            "category":"Recreation",
            "type":"Entertainment"
        }
    ],
    "sg:phone":"+1 504 866 2241",
    "sg:postcode":"70118",
    "sg:province":"LA",
    "sg:tags":[
        "martial",
        "arts",
        "instruction"
    ],
    "wof:name":"Tamashii Karate & Tai Chi Ctr",
    "wof:placetype":"venue"
},
  "geometry": {"coordinates":[-90.128963,29.949209],"type":"Point"}
}