{
  "type": "Feature",
  "properties": {
    "iso:country":"US",
    "sg:address":"224 Saint Landry St",
    "sg:city":"Lafayette",
    "sg:classifiers":[
        {
            "category":"Professional",
            "subcategory":"Lawyer & Legal Services",
            "type":"Services"
        }
    ],
    "sg:phone":"+1 337 232 7231",
    "sg:postcode":"70506",
    "sg:province":"LA",
    "sg:tags":[
        "attorney"
    ],
    "wof:name":"Bernard & Angelle",
    "wof:placetype":"venue"
},
  "geometry": {"coordinates":[-92.025412,30.218797],"type":"Point"}
}