{
  "type": "Feature",
  "properties": {
    "iso:country":"US",
    "sg:address":"600 Chartres St",
    "sg:city":"New Orleans",
    "sg:classifiers":[
        {
            "category":"Manufacturing",
            "subcategory":"Jewelry",
            "type":"Manufacturing & Wholesale Goods"
        }
    ],
    "sg:phone":"+1 504 522 8333",
    "sg:postcode":"70130",
    "sg:province":"LA",
    "sg:tags":[
        "goldsmith",
        "product",
        "silversmith"
    ],
    "sg:website":"www.neworleanssilversmiths.com",
    "wof:name":"New Orleans Silversmiths",
    "wof:placetype":"venue"
},
  "geometry": {"coordinates":[-90.06440000000001,29.9566],"type":"Point"}
}