{
  "type": "Feature",
  "properties": {
    "iso:country":"US",
    "sg:address":"62229 Garrick Rd",
    "sg:city":"Roseland",
    "sg:classifiers":[
        {
            "category":"Organizations",
            "subcategory":"Religious Organization",
            "type":"Services"
        }
    ],
    "sg:phone":"+1 985 747 1102",
    "sg:postcode":"70456",
    "sg:province":"LA",
    "sg:tags":[
        "church"
    ],
    "wof:name":"Revival Center Church Of God",
    "wof:placetype":"venue"
},
  "geometry": {"coordinates":[-90.51506500000001,30.757229],"type":"Point"}
}