{
  "type": "Feature",
  "properties": {
    "iso:country":"US",
    "sg:address":"806 Engineers Rd",
    "sg:city":"Belle Chasse",
    "sg:classifiers":[
        {
            "category":"Mining & Drilling",
            "type":"Manufacturing & Wholesale Goods"
        }
    ],
    "sg:phone":"+1 504 393 2095",
    "sg:postcode":"70037",
    "sg:province":"LA",
    "sg:tags":[
        "field",
        "oil"
    ],
    "wof:name":"Tuboscope",
    "wof:placetype":"venue"
},
  "geometry": {"coordinates":[-90.016723,29.865139],"type":"Point"}
}