{
  "type": "Feature",
  "properties": {
    "iso:country":"US",
    "sg:address":"134 Appletree Ln",
    "sg:city":"Gretna",
    "sg:classifiers":[
        {
            "category":"Retail",
            "subcategory":"Repair Shop",
            "type":"Services"
        }
    ],
    "sg:phone":"+1 504 367 6801",
    "sg:postcode":"70056",
    "sg:province":"LA",
    "sg:tags":[
        "electrical"
    ],
    "wof:name":"American Biomedical Elec Svc",
    "wof:placetype":"venue"
},
  "geometry": {"coordinates":[-90.033424,29.918815],"type":"Point"}
}