{
  "type": "Feature",
  "properties": {
    "iso:country":"US",
    "sg:address":"3132 College Dr",
    "sg:city":"Baton Rouge",
    "sg:classifiers":[
        {
            "category":"Shopping",
            "subcategory":"Computers & Home Electronics",
            "type":"Retail Goods"
        }
    ],
    "sg:phone":"+1 225 927 4247",
    "sg:postcode":"70808",
    "sg:province":"LA",
    "sg:tags":[
        "equipment",
        "electronic",
        "supply"
    ],
    "wof:name":"Radio Shack",
    "wof:placetype":"venue"
},
  "geometry": {"coordinates":[-91.141966,30.418276],"type":"Point"}
}