{
  "type": "Feature",
  "properties": {
    "iso:country":"US",
    "sg:address":"1221 S Clearview Pkwy",
    "sg:city":"Jefferson",
    "sg:classifiers":[
        {
            "category":"Health Services",
            "subcategory":"Hospital",
            "type":"Services"
        }
    ],
    "sg:phone":"+1 504 734 1298",
    "sg:postcode":"70121",
    "sg:province":"LA",
    "wof:name":"Pioneer Medical Ctr",
    "wof:placetype":"venue"
},
  "geometry": {"coordinates":[-90.184696,29.963138],"type":"Point"}
}