{
  "type": "Feature",
  "properties": {
    "iso:country":"US",
    "sg:address":"5003 Hot Wells Rd",
    "sg:city":"Boyce",
    "sg:phone":"+1 318 793 2458",
    "sg:postcode":"71409",
    "sg:province":"LA",
    "sg:tags":[
        "farm",
        "soybean",
        "cotton"
    ],
    "wof:name":"Verzwyvelt John",
    "wof:placetype":"venue"
},
  "geometry": {"coordinates":[-92.63234199999999,31.311688],"type":"Point"}
}