{
  "type": "Feature",
  "properties": {
    "iso:country":"US",
    "sg:address":"803 W University Ave",
    "sg:city":"Lafayette",
    "sg:classifiers":[
        {
            "category":"Wholesale",
            "subcategory":"Electrical",
            "type":"Manufacturing & Wholesale Goods"
        }
    ],
    "sg:phone":"+1 337 235 6404",
    "sg:postcode":"70506",
    "sg:province":"LA",
    "sg:tags":[
        "control",
        "security",
        "system"
    ],
    "wof:name":"Louisiana Video Systems Inc",
    "wof:placetype":"venue"
},
  "geometry": {"coordinates":[-92.02444300000001,30.221289],"type":"Point"}
}