{
  "type": "Feature",
  "properties": {
    "iso:country":"US",
    "sg:address":"100 Price Dr",
    "sg:city":"West Monroe",
    "sg:classifiers":[
        {
            "category":"Education",
            "subcategory":"School",
            "type":"Public Place"
        }
    ],
    "sg:phone":"+1 318 387 0567",
    "sg:postcode":"71292",
    "sg:province":"LA",
    "sg:website":"www.opsb.net",
    "wof:name":"Riser Junior High School",
    "wof:placetype":"venue"
},
  "geometry": {"coordinates":[-92.17822,32.48695],"type":"Point"}
}