{
  "type": "Feature",
  "properties": {
    "iso:country":"US",
    "sg:address":"1653 Valverda Rd",
    "sg:city":"Maringouin",
    "sg:classifiers":[
        {
            "category":"Education",
            "subcategory":"School",
            "type":"Public Place"
        }
    ],
    "sg:phone":"+1 225 637 2695",
    "sg:postcode":"70757",
    "sg:province":"LA",
    "wof:name":"Valverda Elementary School",
    "wof:placetype":"venue"
},
  "geometry": {"coordinates":[-91.537554,30.53434],"type":"Point"}
}