{
  "type": "Feature",
  "properties": {
    "addr:full":"56157 Blue Ridge Dr Slidell LA 70461",
    "addr:housenumber":"56157",
    "addr:postcode":"70461",
    "addr:street":"Blue Ridge Dr",
    "iso:country":"US",
    "sg:address":"56157 Blue Ridge Dr",
    "sg:city":"Slidell",
    "sg:classifiers":[
        {
            "category":"Real Estate",
            "subcategory":"Architect",
            "type":"Services"
        }
    ],
    "sg:phone":"+1 985 643 4476",
    "sg:postcode":"70461",
    "sg:province":"LA",
    "sg:tags":[
        "architectural"
    ],
    "wof:name":"Otis V Ramke Jr Architect",
    "wof:placetype":"venue"
},
  "geometry": {"coordinates":[-89.70074700000001,30.245627],"type":"Point"}
}