{
  "type": "Feature",
  "properties": {
    "iso:country":"US",
    "sg:address":"4704 Viking Dr",
    "sg:city":"Bossier City",
    "sg:classifiers":[
        {
            "category":"Professional",
            "subcategory":"Advertising",
            "type":"Services"
        }
    ],
    "sg:phone":"+1 318 549 9670",
    "sg:postcode":"71111",
    "sg:province":"LA",
    "sg:tags":[
        "distribution"
    ],
    "wof:name":"Red Strokes Distribution",
    "wof:placetype":"venue"
},
  "geometry": {"coordinates":[-93.67294699999999,32.552425],"type":"Point"}
}