{
  "type": "Feature",
  "properties": {
    "iso:country":"US",
    "sg:address":"6603 Main St",
    "sg:city":"Winnsboro",
    "sg:classifiers":[
        {
            "category":"Professional",
            "subcategory":"Lawyer & Legal Services",
            "type":"Services"
        }
    ],
    "sg:phone":"+1 318 435 9903",
    "sg:postcode":"71295",
    "sg:province":"LA",
    "sg:tags":[
        "attorney"
    ],
    "wof:name":"Samuel T Singer",
    "wof:placetype":"venue"
},
  "geometry": {"coordinates":[-91.71604000000001,32.165381],"type":"Point"}
}