{
  "type": "Feature",
  "properties": {
    "iso:country":"US",
    "sg:address":"133 Triple Oaks Dr",
    "sg:city":"Raceland",
    "sg:classifiers":[
        {
            "category":"Professional",
            "subcategory":"Accounting & Tax Preparation",
            "type":"Services"
        }
    ],
    "sg:phone":"+1 985 872 5734",
    "sg:postcode":"70394",
    "sg:province":"LA",
    "sg:tags":[
        "return"
    ],
    "wof:name":"Sandra Harding Income Tax",
    "wof:placetype":"venue"
},
  "geometry": {"coordinates":[-90.617395,29.740496],"type":"Point"}
}