{
  "type": "Feature",
  "properties": {
    "iso:country":"US",
    "sg:address":"912 4th St",
    "sg:city":"Westwego",
    "sg:classifiers":[
        {
            "category":"Retail",
            "subcategory":"Auto Repair",
            "type":"Services"
        }
    ],
    "sg:phone":"+1 504 340 3411",
    "sg:postcode":"70094",
    "sg:province":"LA",
    "sg:tags":[
        "body",
        "automobile",
        "painting"
    ],
    "wof:name":"Quality Collision Ctr",
    "wof:placetype":"venue"
},
  "geometry": {"coordinates":[-90.13901199999999,29.905919],"type":"Point"}
}