{
  "type": "Feature",
  "properties": {
    "iso:country":"US",
    "sg:address":"1820 Veterans Memorial Dr",
    "sg:city":"Abbeville",
    "sg:classifiers":[
        {
            "category":"Government",
            "subcategory":"Office",
            "type":"Public Place"
        }
    ],
    "sg:phone":"+1 337 898 2854",
    "sg:postcode":"70510",
    "sg:province":"LA",
    "sg:tags":[
        "state",
        "program",
        "health"
    ],
    "wof:name":"Health & Hospitals Dept",
    "wof:placetype":"venue"
},
  "geometry": {"coordinates":[-92.149147,29.98505],"type":"Point"}
}