{
  "type": "Feature",
  "properties": {
    "addr:full":"2801 S Galvez St New Orleans LA 70125",
    "addr:housenumber":"2801",
    "addr:postcode":"70125",
    "addr:street":"S Galvez St",
    "iso:country":"US",
    "sg:address":"2801 S Galvez St",
    "sg:city":"New Orleans",
    "sg:classifiers":[
        {
            "category":"Retail",
            "subcategory":"Auto Repair",
            "type":"Services"
        }
    ],
    "sg:phone":"+1 504 821 2333",
    "sg:postcode":"70125",
    "sg:province":"LA",
    "sg:tags":[
        "repairing",
        "automobile"
    ],
    "wof:name":"Grease Rack",
    "wof:placetype":"venue"
},
  "geometry": {"coordinates":[-90.09828899999999,29.946153],"type":"Point"}
}