{
  "type": "Feature",
  "properties": {
    "addr:full":"23444 N Heidi Dr Covington LA 70435",
    "addr:housenumber":"23444",
    "addr:postcode":"70435",
    "addr:street":"N Heidi Dr",
    "iso:country":"US",
    "sg:address":"23444 N Heidi Dr",
    "sg:city":"Covington",
    "sg:classifiers":[
        {
            "category":"Building & Trades",
            "subcategory":"Construction",
            "type":"Services"
        }
    ],
    "sg:phone":"+1 985 809 1373",
    "sg:postcode":"70435",
    "sg:province":"LA",
    "sg:tags":[
        "resurfacing",
        "laying",
        "refinishing",
        "floor"
    ],
    "wof:name":"Bullinger Floor Co",
    "wof:placetype":"venue"
},
  "geometry": {"coordinates":[-90.012934,30.54127],"type":"Point"}
}