{
  "type": "Feature",
  "properties": {
    "iso:country":"US",
    "sg:address":"410 Maurice St",
    "sg:city":"Lafayette",
    "sg:classifiers":[
        {
            "category":"Personal",
            "subcategory":"Beauty Salon",
            "type":"Services"
        }
    ],
    "sg:phone":"+1 337 237 3001",
    "sg:postcode":"70506",
    "sg:province":"LA",
    "wof:name":"Kim & Stephanie's Hair Salon",
    "wof:placetype":"venue"
},
  "geometry": {"coordinates":[-92.043938,30.207041],"type":"Point"}
}