{
  "type": "Feature",
  "properties": {
    "iso:country":"US",
    "sg:address":"3612 Tulane Dr",
    "sg:city":"Kenner",
    "sg:classifiers":[
        {
            "category":"Real Estate",
            "subcategory":"Real Estate Agent",
            "type":"Services"
        }
    ],
    "sg:phone":"+1 504 467 1523",
    "sg:postcode":"70065",
    "sg:province":"LA",
    "wof:name":"Jeanette Neeley Real Estate",
    "wof:placetype":"venue"
},
  "geometry": {"coordinates":[-90.274945,30.028862],"type":"Point"}
}