{
  "type": "Feature",
  "properties": {
    "iso:country":"US",
    "sg:address":"110 W 2nd St",
    "sg:city":"Broussard",
    "sg:classifiers":[
        {
            "category":"Personal",
            "subcategory":"Beauty Salon",
            "type":"Services"
        }
    ],
    "sg:phone":"+1 337 839 8434",
    "sg:postcode":"70518",
    "sg:province":"LA",
    "wof:name":"Victory Cuts",
    "wof:placetype":"venue"
},
  "geometry": {"coordinates":[-91.961912,30.151597],"type":"Point"}
}