{
  "type": "Feature",
  "properties": {
    "iso:country":"US",
    "sg:address":"130 Rue Beauregard",
    "sg:city":"Lafayette",
    "sg:classifiers":[
        {
            "category":"Mining & Drilling",
            "type":"Manufacturing & Wholesale Goods"
        }
    ],
    "sg:phone":"+1 337 261 3130",
    "sg:postcode":"70508",
    "sg:province":"LA",
    "sg:tags":[
        "field",
        "oil"
    ],
    "wof:name":"Industrial & Oilfield Svc",
    "wof:placetype":"venue"
},
  "geometry": {"coordinates":[-92.012261,30.192686],"type":"Point"}
}