{
  "type": "Feature",
  "properties": {
    "iso:country":"US",
    "sg:address":"28316 State Rte 441",
    "sg:city":"Holden",
    "sg:classifiers":[
        {
            "category":"Food & Beverages",
            "subcategory":"Groceries & Convenience Stores",
            "type":"Retail Goods"
        }
    ],
    "sg:phone":"+1 225 567 5680",
    "sg:postcode":"70744",
    "sg:province":"LA",
    "wof:name":"L & W One Stop",
    "wof:placetype":"venue"
},
  "geometry": {"coordinates":[-90.642754,30.475123],"type":"Point"}
}