{
  "type": "Feature",
  "properties": {
    "iso:country":"US",
    "sg:address":"205 W Worthy St",
    "sg:city":"Gonzales",
    "sg:classifiers":[
        {
            "category":"Manufacturing",
            "subcategory":"Printing",
            "type":"Manufacturing & Wholesale Goods"
        }
    ],
    "sg:phone":"+1 225 647 4569",
    "sg:postcode":"70737",
    "sg:province":"LA",
    "sg:tags":[
        "newspaper"
    ],
    "sg:website":"www.gonzalesweekly.com",
    "wof:name":"Gonzales Weekly",
    "wof:placetype":"venue"
},
  "geometry": {"coordinates":[-90.921565,30.225495],"type":"Point"}
}