{
  "type": "Feature",
  "properties": {
    "iso:country":"US",
    "sg:address":"807 Hugh Wallis Rd S",
    "sg:city":"Lafayette",
    "sg:classifiers":[
        {
            "category":"Travel",
            "subcategory":"Hotels & Motels",
            "type":"Entertainment"
        }
    ],
    "sg:phone":"+1 337 232 8313",
    "sg:postcode":"70508",
    "sg:province":"LA",
    "wof:name":"Extended Stay America",
    "wof:placetype":"venue"
},
  "geometry": {"coordinates":[-91.99924,30.190775],"type":"Point"}
}