{
  "type": "Feature",
  "properties": {
    "iso:country":"US",
    "sg:address":"568 W 70th St",
    "sg:city":"Shreveport",
    "sg:classifiers":[
        {
            "category":"Retail",
            "subcategory":"Car Wash",
            "type":"Services"
        }
    ],
    "sg:phone":"+1 318 219 0906",
    "sg:postcode":"71106",
    "sg:province":"LA",
    "sg:tags":[
        "automobile",
        "detail",
        "clean"
    ],
    "wof:name":"One Stop Shop",
    "wof:placetype":"venue"
},
  "geometry": {"coordinates":[-93.76594299999999,32.442126],"type":"Point"}
}