{
  "type": "Feature",
  "properties": {
    "iso:country":"US",
    "sg:address":"102 Beau Soleil Pl",
    "sg:city":"Mandeville",
    "sg:classifiers":[
        {
            "category":"Professional",
            "subcategory":"Employment Agencies",
            "type":"Services"
        }
    ],
    "sg:phone":"+1 985 792 1411",
    "sg:postcode":"70471",
    "sg:province":"LA",
    "sg:tags":[
        "help",
        "contractor"
    ],
    "wof:name":"Bourgeois Staffing",
    "wof:placetype":"venue"
},
  "geometry": {"coordinates":[-90.107696,30.400597],"type":"Point"}
}