{
  "type": "Feature",
  "properties": {
    "iso:country":"US",
    "sg:address":"5700 Rhodes Ave",
    "sg:city":"New Orleans",
    "sg:classifiers":[
        {
            "category":"Mining & Drilling",
            "type":"Manufacturing & Wholesale Goods"
        }
    ],
    "sg:phone":"+1 504 393 8100",
    "sg:postcode":"70131",
    "sg:province":"LA",
    "sg:tags":[
        "field"
    ],
    "wof:name":"Jack Wade & Associates",
    "wof:placetype":"venue"
},
  "geometry": {"coordinates":[-89.992564,29.921477],"type":"Point"}
}