{
  "type": "Feature",
  "properties": {
    "iso:country":"US",
    "sg:address":"1911 Citizens Bank Dr",
    "sg:city":"Bossier City",
    "sg:classifiers":[
        {
            "category":"Professional",
            "subcategory":"Management & Consulting",
            "type":"Services"
        }
    ],
    "sg:phone":"+1 318 741 1242",
    "sg:postcode":"71111",
    "sg:province":"LA",
    "sg:tags":[
        "fuel"
    ],
    "wof:name":"Forcap Management LLC",
    "wof:placetype":"venue"
},
  "geometry": {"coordinates":[-93.723159,32.539461],"type":"Point"}
}