{
  "type": "Feature",
  "properties": {
    "iso:country":"US",
    "sg:address":"680 Firetower Rd",
    "sg:city":"Jonesboro",
    "sg:classifiers":[
        {
            "category":"Building & Trades",
            "subcategory":"Construction",
            "type":"Services"
        }
    ],
    "sg:phone":"+1 318 395 9254",
    "sg:postcode":"71251",
    "sg:province":"LA",
    "sg:tags":[
        "general",
        "contractor"
    ],
    "wof:name":"Ingles & Ingles Dirt Contract",
    "wof:placetype":"venue"
},
  "geometry": {"coordinates":[-92.694903,32.203528],"type":"Point"}
}