{
  "type": "Feature",
  "properties": {
    "addr:full":"3508 Beverly Pl Shreveport LA 71104",
    "addr:housenumber":"3508",
    "addr:postcode":"71104",
    "addr:street":"Beverly Pl",
    "iso:country":"US",
    "sg:address":"3508 Beverly Pl",
    "sg:city":"Shreveport",
    "sg:classifiers":[
        {
            "category":"Social Services",
            "type":"Services"
        }
    ],
    "sg:phone":"+1 318 868 2774",
    "sg:postcode":"71104",
    "sg:province":"LA",
    "sg:tags":[
        "youth",
        "organization",
        "center"
    ],
    "sg:website":"www.norwela.org",
    "wof:name":"Boy Scouts Of America",
    "wof:placetype":"venue"
},
  "geometry": {"coordinates":[-93.728398,32.478053],"type":"Point"}
}