{
  "type": "Feature",
  "properties": {
    "addr:full":"9477 Lansdowne Rd Baton Rouge LA 70818",
    "addr:housenumber":"9477",
    "addr:postcode":"70818",
    "addr:street":"Lansdowne Rd",
    "iso:country":"US",
    "sg:address":"9477 Lansdowne Rd",
    "sg:city":"Baton Rouge",
    "sg:classifiers":[
        {
            "category":"Real Estate",
            "subcategory":"Real Estate Operator",
            "type":"Services"
        }
    ],
    "sg:phone":"+1 225 261 9418",
    "sg:postcode":"70818",
    "sg:province":"LA",
    "sg:tags":[
        "mobile",
        "home",
        "community"
    ],
    "wof:name":"Tanglewood West Trailer Park",
    "wof:placetype":"venue"
},
  "geometry": {"coordinates":[-91.075504,30.535402],"type":"Point"}
}