{
  "type": "Feature",
  "properties": {
    "addr:full":"17123 Hooper Rd Greenwell Spgs LA 70739",
    "addr:housenumber":"17123",
    "addr:postcode":"70739",
    "addr:street":"Hooper Rd;Spgs",
    "iso:country":"US",
    "sg:address":"17123 Hooper Rd",
    "sg:city":"Greenwell Spgs",
    "sg:classifiers":[
        {
            "category":"Wholesale",
            "subcategory":"Furniture",
            "type":"Manufacturing & Wholesale Goods"
        }
    ],
    "sg:phone":"+1 225 261 5639",
    "sg:postcode":"70739",
    "sg:province":"LA",
    "sg:tags":[
        "furnishing",
        "church"
    ],
    "wof:name":"Mid-South Church Furnishings",
    "wof:placetype":"venue"
},
  "geometry": {"coordinates":[-90.999585,30.569941],"type":"Point"}
}