{
  "type": "Feature",
  "properties": {
    "addr:full":"2810 NE Evangeline Trwy Lafayette LA 70507",
    "addr:housenumber":"2810",
    "addr:postcode":"70507",
    "addr:street":"Ne Evangeline",
    "iso:country":"US",
    "sg:address":"2810 NE Evangeline Trwy",
    "sg:city":"Lafayette",
    "sg:classifiers":[
        {
            "category":"Travel",
            "subcategory":"Hotels & Motels",
            "type":"Entertainment"
        }
    ],
    "sg:phone":"+1 337 232 7285",
    "sg:postcode":"70507",
    "sg:province":"LA",
    "wof:name":"Plantation Motor Inn",
    "wof:placetype":"venue"
},
  "geometry": {"coordinates":[-92.01709700000001,30.2735],"type":"Point"}
}