{
  "type": "Feature",
  "properties": {
    "iso:country":"US",
    "sg:address":"2202 Macarthur Dr",
    "sg:city":"Alexandria",
    "sg:classifiers":[
        {
            "category":"Wholesale",
            "subcategory":"Construction Materials",
            "type":"Manufacturing & Wholesale Goods"
        }
    ],
    "sg:phone":"+1 318 443 0475",
    "sg:postcode":"71301",
    "sg:province":"LA",
    "sg:tags":[
        "brick",
        "common",
        "face"
    ],
    "wof:name":"Acme Brick Tile & More",
    "wof:placetype":"venue"
},
  "geometry": {"coordinates":[-92.46978300000001,31.275482],"type":"Point"}
}