{
  "type": "Feature",
  "properties": {
    "iso:country":"US",
    "sg:address":"108 E Hardtner Dr",
    "sg:city":"Urania",
    "sg:classifiers":[
        {
            "category":"Food & Beverages",
            "subcategory":"Groceries & Convenience Stores",
            "type":"Retail Goods"
        }
    ],
    "sg:phone":"+1 318 495 5868",
    "sg:postcode":"71480",
    "sg:province":"LA",
    "sg:tags":[
        "grocer"
    ],
    "wof:name":"Candy's General Store",
    "wof:placetype":"venue"
},
  "geometry": {"coordinates":[-92.293121,31.862274],"type":"Point"}
}