{
  "type": "Feature",
  "properties": {
    "addr:full":"108 Commerce St Belle Chasse LA 70037",
    "addr:housenumber":"108",
    "addr:postcode":"70037",
    "addr:street":"Commerce St",
    "iso:country":"US",
    "sg:address":"108 Commerce St",
    "sg:city":"Belle Chasse",
    "sg:classifiers":[
        {
            "category":"Food & Beverages",
            "subcategory":"Groceries & Convenience Stores",
            "type":"Retail Goods"
        }
    ],
    "sg:phone":"+1 225 784 0014",
    "sg:postcode":"70037",
    "sg:province":"LA",
    "wof:name":"JFM Inc",
    "wof:placetype":"venue"
},
  "geometry": {"coordinates":[-90.015108,29.871697],"type":"Point"}
}