{
  "type": "Feature",
  "properties": {
    "addr:full":"15344 Airline Hwy Prairieville LA 70769",
    "addr:housenumber":"15344",
    "addr:postcode":"70769",
    "addr:street":"Airline Hwy Prairieville",
    "iso:country":"US",
    "sg:address":"15344 Airline Hwy",
    "sg:city":"Prairieville",
    "sg:classifiers":[
        {
            "category":"Insurance",
            "subcategory":"Hazard Insurance",
            "type":"Services"
        }
    ],
    "sg:phone":"+1 225 647 2546",
    "sg:postcode":"70769",
    "sg:province":"LA",
    "sg:tags":[
        "bond"
    ],
    "wof:name":"Andre's 24 Hour Bail Bonding",
    "wof:placetype":"venue"
},
  "geometry": {"coordinates":[-90.959676,30.289292],"type":"Point"}
}