{
  "type": "Feature",
  "properties": {
    "addr:full":"991 Mouton St New Orleans LA 70124",
    "addr:housenumber":"991",
    "addr:postcode":"70124",
    "addr:street":"Mouton St",
    "iso:country":"US",
    "sg:address":"991 Mouton St",
    "sg:city":"New Orleans",
    "sg:classifiers":[
        {
            "category":"Professional",
            "subcategory":"Management & Consulting",
            "type":"Services"
        }
    ],
    "sg:phone":"+1 504 283 6106",
    "sg:postcode":"70124",
    "sg:province":"LA",
    "wof:name":"H J Cavalier",
    "wof:placetype":"venue"
},
  "geometry": {"coordinates":[-90.099329,30.015219],"type":"Point"}
}