{
  "type": "Feature",
  "properties": {
    "iso:country":"US",
    "sg:address":"6445 US Hwy 90",
    "sg:city":"Morgan City",
    "sg:classifiers":[
        {
            "category":"Home & Garden",
            "subcategory":"Household Appliances",
            "type":"Retail Goods"
        }
    ],
    "sg:phone":"+1 985 384 2740",
    "sg:postcode":"70380",
    "sg:province":"LA",
    "sg:tags":[
        "cleaners",
        "vacuum"
    ],
    "wof:name":"Morgan City Sewing Ctr",
    "wof:placetype":"venue"
},
  "geometry": {"coordinates":[-91.200199,29.700511],"type":"Point"}
}