{
  "type": "Feature",
  "properties": {
    "addr:full":"3709 General Taylor St New Orleans LA 70125",
    "addr:housenumber":"3709",
    "addr:postcode":"70125",
    "addr:street":"General Taylor St",
    "iso:country":"US",
    "sg:address":"3709 General Taylor St",
    "sg:city":"New Orleans",
    "sg:classifiers":[
        {
            "category":"Organizations",
            "subcategory":"Religious Organization",
            "type":"Services"
        }
    ],
    "sg:phone":"+1 504 821 9399",
    "sg:postcode":"70125",
    "sg:province":"LA",
    "sg:tags":[
        "church"
    ],
    "wof:name":"Jehovah's Witnesses",
    "wof:placetype":"venue"
},
  "geometry": {"coordinates":[-90.10164899999999,29.947609],"type":"Point"}
}