{
  "type": "Feature",
  "properties": {
    "iso:country":"US",
    "sg:address":"1001 Washington St",
    "sg:city":"Franklinton",
    "sg:classifiers":[
        {
            "category":"Banks & Credit Unions",
            "subcategory":"Bank",
            "type":"Services"
        }
    ],
    "sg:phone":"+1 985 839 3512",
    "sg:postcode":"70438",
    "sg:province":"LA",
    "sg:tags":[
        "financing"
    ],
    "wof:name":"Magee Financial",
    "wof:placetype":"venue"
},
  "geometry": {"coordinates":[-90.154573,30.84539],"type":"Point"}
}