{
  "type": "Feature",
  "properties": {
    "iso:country":"US",
    "sg:address":"541 Chandler Rd",
    "sg:city":"Ruston",
    "sg:classifiers":[
        {
            "category":"Organizations",
            "subcategory":"Professional Association",
            "type":"Services"
        }
    ],
    "sg:phone":"+1 318 768 2224",
    "sg:postcode":"71270",
    "sg:province":"LA",
    "sg:tags":[
        "business"
    ],
    "wof:name":"Assocted Prvailing Wage Contrs",
    "wof:placetype":"venue"
},
  "geometry": {"coordinates":[-92.560396,32.549841],"type":"Point"}
}