{
  "type": "Feature",
  "properties": {
    "addr:full":"9384 Florida Blvd Walker LA 70785",
    "addr:housenumber":"9384",
    "addr:postcode":"70785",
    "addr:street":"Florida Blvd",
    "iso:country":"US",
    "sg:address":"9384 Florida Blvd",
    "sg:city":"Walker",
    "sg:classifiers":[
        {
            "category":"Shopping",
            "subcategory":"Musical Instruments",
            "type":"Retail Goods"
        }
    ],
    "sg:phone":"+1 225 665 0796",
    "sg:postcode":"70785",
    "sg:province":"LA",
    "wof:name":"Music Mans Music Mart South La",
    "wof:placetype":"venue"
},
  "geometry": {"coordinates":[-90.922926,30.48264],"type":"Point"}
}