{
  "type": "Feature",
  "properties": {
    "iso:country":"US",
    "sg:address":"104 W 2nd St",
    "sg:city":"Belle Chasse",
    "sg:classifiers":[
        {
            "category":"Professional",
            "subcategory":"Business Services",
            "type":"Services"
        }
    ],
    "sg:phone":"+1 504 392 3165",
    "sg:postcode":"70037",
    "sg:province":"LA",
    "sg:tags":[
        "volunteer"
    ],
    "wof:name":"Carrie G Matirne",
    "wof:placetype":"venue"
},
  "geometry": {"coordinates":[-89.98855399999999,29.852402],"type":"Point"}
}