{
  "type": "Feature",
  "properties": {
    "addr:full":"1525 E Bridge St Breaux Bridge LA 70517",
    "addr:housenumber":"1525",
    "addr:postcode":"70517",
    "addr:street":"E Bridge St",
    "iso:country":"US",
    "sg:address":"1525 E Bridge St",
    "sg:city":"Breaux Bridge",
    "sg:classifiers":[
        {
            "category":"Health Services",
            "subcategory":"Doctor",
            "type":"Services"
        }
    ],
    "sg:phone":"+1 337 332 4473",
    "sg:postcode":"70517",
    "sg:province":"LA",
    "sg:tags":[
        "physician",
        "surgeon"
    ],
    "wof:name":"Guidry Eye Clinic",
    "wof:placetype":"venue"
},
  "geometry": {"coordinates":[-91.887056,30.282618],"type":"Point"}
}