{
  "type": "Feature",
  "properties": {
    "addr:full":"839 Kings Hwy Shreveport LA 71104",
    "addr:housenumber":"839",
    "addr:postcode":"71104",
    "addr:street":"Kings Hwy",
    "iso:country":"US",
    "sg:address":"839 Kings Hwy",
    "sg:city":"Shreveport",
    "sg:classifiers":[
        {
            "category":"Shopping",
            "subcategory":"Bicycles & Sporting Goods",
            "type":"Retail Goods"
        }
    ],
    "sg:phone":"+1 318 429 0660",
    "sg:postcode":"71104",
    "sg:province":"LA",
    "wof:name":"Shreveport Regional Sports",
    "wof:placetype":"venue"
},
  "geometry": {"coordinates":[-93.74683899999999,32.481287],"type":"Point"}
}