{
  "type": "Feature",
  "properties": {
    "iso:country":"US",
    "sg:address":"1898 Macarthur Dr",
    "sg:city":"Alexandria",
    "sg:classifiers":[
        {
            "category":"Freight",
            "type":"Transportation"
        }
    ],
    "sg:phone":"+1 318 449 4680",
    "sg:postcode":"71301",
    "sg:province":"LA",
    "sg:tags":[
        "warehouse"
    ],
    "wof:name":"Work Boot Warehouse & Safety",
    "wof:placetype":"venue"
},
  "geometry": {"coordinates":[-92.471407,31.276933],"type":"Point"}
}