{
  "type": "Feature",
  "properties": {
    "addr:full":"120 Park Center Dr Broussard LA 70518",
    "addr:housenumber":"120",
    "addr:postcode":"70518",
    "addr:street":"Park Center Dr",
    "iso:country":"US",
    "sg:address":"120 Park Center Dr",
    "sg:city":"Broussard",
    "sg:classifiers":[
        {
            "category":"Mining & Drilling",
            "type":"Manufacturing & Wholesale Goods"
        }
    ],
    "sg:phone":"+1 337 267 3113",
    "sg:postcode":"70518",
    "sg:province":"LA",
    "sg:tags":[
        "field",
        "oil"
    ],
    "wof:name":"Drillchem Drilling Solutions",
    "wof:placetype":"venue"
},
  "geometry": {"coordinates":[-91.97451700000001,30.16375],"type":"Point"}
}