{
  "type": "Feature",
  "properties": {
    "addr:full":"3556 Youree Dr Shreveport LA 71105",
    "addr:housenumber":"3556",
    "addr:postcode":"71105",
    "addr:street":"Youree Dr",
    "iso:country":"US",
    "sg:address":"3556 Youree Dr",
    "sg:city":"Shreveport",
    "sg:classifiers":[
        {
            "category":"Professional",
            "subcategory":"Engineering",
            "type":"Services"
        }
    ],
    "sg:phone":"+1 318 869 2088",
    "sg:postcode":"71105",
    "sg:province":"LA",
    "sg:tags":[
        "refining",
        "engineer"
    ],
    "wof:name":"Robert E Mc Dowell",
    "wof:placetype":"venue"
},
  "geometry": {"coordinates":[-93.722295,32.475697],"type":"Point"}
}