{
  "type": "Feature",
  "properties": {
    "iso:country":"US",
    "sg:address":"3643 Progress Church Rd",
    "sg:city":"Pleasant Hill",
    "sg:classifiers":[
        {
            "category":"Organizations",
            "subcategory":"Religious Organization",
            "type":"Services"
        }
    ],
    "sg:phone":"+1 318 796 3725",
    "sg:postcode":"71065",
    "sg:province":"LA",
    "sg:tags":[
        "church"
    ],
    "wof:name":"Progress Church",
    "wof:placetype":"venue"
},
  "geometry": {"coordinates":[-93.55291699999999,31.789163],"type":"Point"}
}