{
  "type": "Feature",
  "properties": {
    "iso:country":"US",
    "sg:address":"403 E Union St",
    "sg:city":"Minden",
    "sg:classifiers":[
        {
            "category":"Personal",
            "subcategory":"Barber",
            "type":"Services"
        }
    ],
    "sg:phone":"+1 318 377 9876",
    "sg:postcode":"71055",
    "sg:province":"LA",
    "sg:tags":[
        "shop"
    ],
    "wof:name":"Lewis Barber Shop",
    "wof:placetype":"venue"
},
  "geometry": {"coordinates":[-93.280737,32.612421],"type":"Point"}
}