{
  "type": "Feature",
  "properties": {
    "iso:country":"US",
    "sg:address":"840 Poydras St",
    "sg:city":"New Orleans",
    "sg:classifiers":[
        {
            "category":"Professional",
            "subcategory":"Computer Services",
            "type":"Services"
        }
    ],
    "sg:phone":"+1 504 524 1010",
    "sg:postcode":"70112",
    "sg:province":"LA",
    "sg:tags":[
        "internet"
    ],
    "wof:name":"Backup USA",
    "wof:placetype":"venue"
},
  "geometry": {"coordinates":[-90.07298400000001,29.950263],"type":"Point"}
}