{
  "type": "Feature",
  "properties": {
    "iso:country":"US",
    "sg:address":"41061 State Rte 933",
    "sg:city":"Prairieville",
    "sg:classifiers":[
        {
            "category":"Retail",
            "subcategory":"Veterinary Services",
            "type":"Services"
        }
    ],
    "sg:phone":"+1 225 622 6443",
    "sg:postcode":"70769",
    "sg:province":"LA",
    "sg:tags":[
        "veterinarian"
    ],
    "wof:name":"Galvez Veterinary Clinic",
    "wof:placetype":"venue"
},
  "geometry": {"coordinates":[-90.91855099999999,30.313709],"type":"Point"}
}