{
  "type": "Feature",
  "properties": {
    "addr:full":"512 Pujo St Lake Charles LA 70601",
    "addr:housenumber":"512",
    "addr:postcode":"70601",
    "addr:street":"Pujo St",
    "iso:country":"US",
    "sg:address":"512 Pujo St",
    "sg:city":"Lake Charles",
    "sg:classifiers":[
        {
            "category":"Professional",
            "subcategory":"Lawyer & Legal Services",
            "type":"Services"
        }
    ],
    "sg:phone":"+1 337 439 7616",
    "sg:postcode":"70601",
    "sg:province":"LA",
    "sg:tags":[
        "attorney"
    ],
    "wof:name":"Kathleen Kay",
    "wof:placetype":"venue"
},
  "geometry": {"coordinates":[-93.213438,30.227095],"type":"Point"}
}