{
  "type": "Feature",
  "properties": {
    "iso:country":"US",
    "sg:address":"12734 Mansfield Rd",
    "sg:city":"Keithville",
    "sg:classifiers":[
        {
            "category":"Retail",
            "subcategory":"Auto Repair",
            "type":"Services"
        }
    ],
    "sg:phone":"+1 318 925 9192",
    "sg:postcode":"71047",
    "sg:province":"LA",
    "sg:tags":[
        "repairing",
        "automobile"
    ],
    "wof:name":"Stonewall Transmission",
    "wof:placetype":"venue"
},
  "geometry": {"coordinates":[-93.83049200000001,32.317612],"type":"Point"}
}