{
  "type": "Feature",
  "properties": {
    "iso:country":"US",
    "sg:address":"3520 Anthony Ferry Rd",
    "sg:city":"Sulphur",
    "sg:classifiers":[
        {
            "category":"Restaurant",
            "type":"Food & Drink"
        }
    ],
    "sg:phone":"+1 337 527 8254",
    "sg:postcode":"70663",
    "sg:province":"LA",
    "sg:tags":[
        "eating"
    ],
    "wof:name":"Rtm Services Inc",
    "wof:placetype":"venue"
},
  "geometry": {"coordinates":[-93.32567400000001,30.31515],"type":"Point"}
}