{
  "type": "Feature",
  "properties": {
    "addr:full":"506C Lafayette St Youngsville LA 70592",
    "addr:housenumber":"506c",
    "addr:postcode":"70592",
    "addr:street":"Lafayette St",
    "iso:country":"US",
    "sg:address":"506C Lafayette St",
    "sg:city":"Youngsville",
    "sg:classifiers":[
        {
            "category":"Education",
            "subcategory":"Library",
            "type":"Public Place"
        }
    ],
    "sg:phone":"+1 337 856 9385",
    "sg:postcode":"70592",
    "sg:province":"LA",
    "wof:name":"Youngsville Branch Library",
    "wof:placetype":"venue"
},
  "geometry": {"coordinates":[-91.990527,30.108998],"type":"Point"}
}