{
  "type": "Feature",
  "properties": {
    "iso:country":"US",
    "sg:address":"4525 Burke Dr",
    "sg:city":"Metairie",
    "sg:classifiers":[
        {
            "category":"Building & Trades",
            "subcategory":"Construction",
            "type":"Services"
        },
        {
            "category":"Home & Garden",
            "subcategory":"Home Furnishings",
            "type":"Retail Goods"
        }
    ],
    "sg:phone":"+1 504 887 4609",
    "sg:postcode":"70003",
    "sg:province":"LA",
    "sg:tags":[
        "venetian",
        "blind",
        "contractor"
    ],
    "wof:name":"Custom Window Creation LLC",
    "wof:placetype":"venue"
},
  "geometry": {"coordinates":[-90.217281,30.020558],"type":"Point"}
}