{
  "type": "Feature",
  "properties": {
    "iso:country":"US",
    "sg:address":"219 W Oak Ln",
    "sg:city":"Lake Charles",
    "sg:classifiers":[
        {
            "category":"Professional",
            "subcategory":"Business Services",
            "type":"Services"
        }
    ],
    "sg:phone":"+1 337 436 5917",
    "sg:postcode":"70605",
    "sg:province":"LA",
    "sg:tags":[
        "recording",
        "studio"
    ],
    "wof:name":"Magnolia Music",
    "wof:placetype":"venue"
},
  "geometry": {"coordinates":[-93.222953,30.189066],"type":"Point"}
}