{
  "type": "Feature",
  "properties": {
    "addr:full":"14 Egret St New Orleans LA 70124",
    "addr:housenumber":"14",
    "addr:postcode":"70124",
    "addr:street":"Egret St",
    "iso:country":"US",
    "sg:address":"14 Egret St",
    "sg:city":"New Orleans",
    "sg:classifiers":[
        {
            "category":"Building & Trades",
            "subcategory":"Plumbing",
            "type":"Services"
        }
    ],
    "sg:phone":"+1 504 415 3087",
    "sg:postcode":"70124",
    "sg:province":"LA",
    "sg:tags":[
        "conditioning",
        "air",
        "system",
        "contractor"
    ],
    "wof:name":"Corcoran Services",
    "wof:placetype":"venue"
},
  "geometry": {"coordinates":[-90.091825,30.0219],"type":"Point"}
}