{
  "type": "Feature",
  "properties": {
    "addr:full":"858 Benton Rd Bossier City LA 71111",
    "addr:housenumber":"858",
    "addr:postcode":"71111",
    "addr:street":"Benton Rd",
    "iso:country":"US",
    "sg:address":"858 Benton Rd",
    "sg:city":"Bossier City",
    "sg:classifiers":[
        {
            "category":"Shopping",
            "subcategory":"Musical Instruments",
            "type":"Retail Goods"
        }
    ],
    "sg:phone":"+1 318 746 6417",
    "sg:postcode":"71111",
    "sg:province":"LA",
    "sg:website":"www.thestringshop.com",
    "wof:name":"String Shop",
    "wof:placetype":"venue"
},
  "geometry": {"coordinates":[-93.71805999999999,32.527203],"type":"Point"}
}