{
  "type": "Feature",
  "properties": {
    "addr:full":"1314 Hoadley St Shreveport LA 71104",
    "addr:housenumber":"1314",
    "addr:postcode":"71104",
    "addr:street":"Hoadley St",
    "iso:country":"US",
    "sg:address":"1314 Hoadley St",
    "sg:city":"Shreveport",
    "sg:classifiers":[
        {
            "category":"Building & Trades",
            "subcategory":"Equipment Rental",
            "type":"Services"
        }
    ],
    "sg:phone":"+1 318 222 0702",
    "sg:postcode":"71104",
    "sg:province":"LA",
    "sg:tags":[
        "scaffolding"
    ],
    "sg:website":"www.nonstopscaffolding.com",
    "wof:name":"Non-Stop Scaffolding Co",
    "wof:placetype":"venue"
},
  "geometry": {"coordinates":[-93.75573900000001,32.491839],"type":"Point"}
}