{
  "type": "Feature",
  "properties": {
    "iso:country":"US",
    "sg:address":"807 Royal St",
    "sg:city":"New Orleans",
    "sg:classifiers":[
        {
            "category":"Shopping",
            "subcategory":"Shoes",
            "type":"Retail Goods"
        }
    ],
    "sg:phone":"+1 504 524 3522",
    "sg:postcode":"70116",
    "sg:province":"LA",
    "wof:name":"Shoe-Nami",
    "wof:placetype":"venue"
},
  "geometry": {"coordinates":[-90.063366,29.959635],"type":"Point"}
}