{
  "type": "Feature",
  "properties": {
    "iso:country":"US",
    "sg:address":"873 Lamar Ave",
    "sg:city":"Gretna",
    "sg:classifiers":[
        {
            "category":"Autos & Motor Vehicles",
            "subcategory":"Auto Supplies",
            "type":"Retail Goods"
        }
    ],
    "sg:phone":"+1 504 392 9808",
    "sg:postcode":"70056",
    "sg:province":"LA",
    "sg:tags":[
        "automobile",
        "alarm"
    ],
    "wof:name":"Pro Tech Svc",
    "wof:placetype":"venue"
},
  "geometry": {"coordinates":[-90.028807,29.894216],"type":"Point"}
}