{
  "type": "Feature",
  "properties": {
    "iso:country":"US",
    "sg:address":"719 Esplanade Ave",
    "sg:city":"New Orleans",
    "sg:classifiers":[
        {
            "category":"Travel",
            "subcategory":"Hotels & Motels",
            "type":"Entertainment"
        }
    ],
    "sg:phone":"+1 504 948 9328",
    "sg:postcode":"70116",
    "sg:province":"LA",
    "sg:tags":[
        "breakfast",
        "accommodation",
        "bed"
    ],
    "sg:website":"www.quarteresplanade.com",
    "wof:name":"A Quarter Esplanade",
    "wof:placetype":"venue"
},
  "geometry": {"coordinates":[-90.060616,29.963997],"type":"Point"}
}