{
  "type": "Feature",
  "properties": {
    "iso:country":"US",
    "sg:address":"3046 Barataria Blvd",
    "sg:city":"Marrero",
    "sg:classifiers":[
        {
            "category":"Retail",
            "subcategory":"Auto Repair",
            "type":"Services"
        }
    ],
    "sg:phone":"+1 504 348 1642",
    "sg:postcode":"70072",
    "sg:province":"LA",
    "sg:tags":[
        "repairing",
        "automobile"
    ],
    "wof:name":"Quality Auto Repair & Sales",
    "wof:placetype":"venue"
},
  "geometry": {"coordinates":[-90.11685799999999,29.848374],"type":"Point"}
}