{
  "type": "Feature",
  "properties": {
    "iso:country":"US",
    "sg:address":"23855 Eden St",
    "sg:city":"Plaquemine",
    "sg:classifiers":[
        {
            "category":"Health Services",
            "subcategory":"Optometrist",
            "type":"Services"
        }
    ],
    "sg:phone":"+1 225 687 2026",
    "sg:postcode":"70764",
    "sg:province":"LA",
    "wof:name":"Southern Eye Ctr",
    "wof:placetype":"venue"
},
  "geometry": {"coordinates":[-91.232913,30.286857],"type":"Point"}
}