{
  "type": "Feature",
  "properties": {
    "iso:country":"US",
    "sg:address":"305 E Main St",
    "sg:city":"Oak Grove",
    "sg:classifiers":[
        {
            "category":"Government",
            "subcategory":"Office",
            "type":"Public Place"
        }
    ],
    "sg:phone":"+1 318 428 2371",
    "sg:postcode":"71263",
    "sg:province":"LA",
    "wof:name":"West Carroll Assessor's Office",
    "wof:placetype":"venue"
},
  "geometry": {"coordinates":[-91.387613,32.861025],"type":"Point"}
}