{
  "type": "Feature",
  "properties": {
    "addr:full":"1209 Wiegand Dr Bridge City LA 70094",
    "addr:housenumber":"1209",
    "addr:postcode":"70094",
    "addr:street":"Wiegand Dr Bridge",
    "iso:country":"US",
    "sg:address":"1209 Wiegand Dr",
    "sg:city":"Bridge City",
    "sg:classifiers":[
        {
            "category":"Retail",
            "subcategory":"Repair Shop",
            "type":"Services"
        },
        {
            "category":"Building & Trades",
            "subcategory":"Construction",
            "type":"Services"
        }
    ],
    "sg:phone":"+1 504 436 7372",
    "sg:postcode":"70094",
    "sg:province":"LA",
    "sg:tags":[
        "welding",
        "contractor"
    ],
    "wof:name":"Premium Welding",
    "wof:placetype":"venue"
},
  "geometry": {"coordinates":[-90.16199,29.931235],"type":"Point"}
}