{
  "type": "Feature",
  "properties": {
    "addr:full":"117 Heymann Blvd Lafayette LA 70503",
    "addr:housenumber":"117",
    "addr:postcode":"70503",
    "addr:street":"Heymann Blvd",
    "iso:country":"US",
    "sg:address":"117 Heymann Blvd",
    "sg:city":"Lafayette",
    "sg:classifiers":[
        {
            "category":"Professional",
            "type":"Services"
        }
    ],
    "sg:phone":"+1 337 234 5222",
    "sg:postcode":"70503",
    "sg:province":"LA",
    "sg:tags":[
        "consultant",
        "geological"
    ],
    "wof:name":"Arthur Christy",
    "wof:placetype":"venue"
},
  "geometry": {"coordinates":[-92.013966,30.206613],"type":"Point"}
}