{
  "type": "Feature",
  "properties": {
    "addr:full":"486 W Prien Lake Rd Lake Charles LA 70601",
    "addr:housenumber":"486",
    "addr:postcode":"70601",
    "addr:street":"W Prien Lake Rd",
    "iso:country":"US",
    "sg:address":"486 W Prien Lake Rd",
    "sg:city":"Lake Charles",
    "sg:classifiers":[
        {
            "category":"Government",
            "subcategory":"Police Station",
            "type":"Public Place"
        }
    ],
    "sg:phone":"+1 337 491 8630",
    "sg:postcode":"70601",
    "sg:province":"LA",
    "sg:tags":[
        "department"
    ],
    "wof:name":"Lake Charles Police Community",
    "wof:placetype":"venue"
},
  "geometry": {"coordinates":[-93.225325,30.198175],"type":"Point"}
}