{
  "type": "Feature",
  "properties": {
    "iso:country":"US",
    "sg:address":"317 3rd St",
    "sg:city":"Kenner",
    "sg:classifiers":[
        {
            "category":"Freight",
            "type":"Transportation"
        },
        {
            "category":"Retail",
            "subcategory":"Repair Shop",
            "type":"Services"
        }
    ],
    "sg:phone":"+1 504 466 7116",
    "sg:postcode":"70062",
    "sg:province":"LA",
    "sg:tags":[
        "operator",
        "grease",
        "local",
        "trap",
        "trucking"
    ],
    "wof:name":"Airport Vacuum Truck Service",
    "wof:placetype":"venue"
},
  "geometry": {"coordinates":[-90.267037,29.976604],"type":"Point"}
}