{
  "type": "Feature",
  "properties": {
    "iso:country":"US",
    "sg:address":"150 Freestate Blvd",
    "sg:city":"Shreveport",
    "sg:classifiers":[
        {
            "category":"Banks & Credit Unions",
            "subcategory":"Bank",
            "type":"Services"
        }
    ],
    "sg:phone":"+1 318 226 2709",
    "sg:postcode":"71107",
    "sg:province":"LA",
    "wof:name":"Bank One",
    "wof:placetype":"venue"
},
  "geometry": {"coordinates":[-93.765035,32.537027],"type":"Point"}
}