{
  "type": "Feature",
  "properties": {
    "iso:country":"US",
    "sg:address":"1204 Shreveport Rd",
    "sg:city":"Minden",
    "sg:classifiers":[
        {
            "category":"Restaurant",
            "type":"Food & Drink"
        }
    ],
    "sg:phone":"+1 318 371 2771",
    "sg:postcode":"71055",
    "sg:province":"LA",
    "sg:tags":[
        "barbecue"
    ],
    "wof:name":"J R's Bbq",
    "wof:placetype":"venue"
},
  "geometry": {"coordinates":[-93.304244,32.60679],"type":"Point"}
}