{
  "type": "Feature",
  "properties": {
    "addr:full":"2183 Highland Rd Baton Rouge LA 70802",
    "addr:housenumber":"2183",
    "addr:postcode":"70802",
    "addr:street":"Highland Rd",
    "iso:country":"US",
    "sg:address":"2183 Highland Rd",
    "sg:city":"Baton Rouge",
    "sg:classifiers":[
        {
            "category":"Bars & Pubs",
            "type":"Food & Drink"
        }
    ],
    "sg:phone":"+1 225 242 9491",
    "sg:postcode":"70802",
    "sg:province":"LA",
    "sg:tags":[
        "club",
        "night"
    ],
    "wof:name":"SPLASH",
    "wof:placetype":"venue"
},
  "geometry": {"coordinates":[-91.18065199999999,30.427326],"type":"Point"}
}