{
  "type": "Feature",
  "properties": {
    "iso:country":"US",
    "sg:address":"6535 Line Ave",
    "sg:city":"Shreveport",
    "sg:classifiers":[
        {
            "category":"Restaurant",
            "type":"Food & Drink"
        }
    ],
    "sg:phone":"+1 318 868 8866",
    "sg:postcode":"71106",
    "sg:province":"LA",
    "wof:name":"Chianti Restaurant",
    "wof:placetype":"venue"
},
  "geometry": {"coordinates":[-93.74591700000001,32.446837],"type":"Point"}
}