{
  "type": "Feature",
  "properties": {
    "addr:full":"3127 Broadway St New Orleans LA 70125",
    "addr:housenumber":"3127",
    "addr:postcode":"70125",
    "addr:street":"Broadway St",
    "iso:country":"US",
    "sg:address":"3127 Broadway St",
    "sg:city":"New Orleans",
    "sg:classifiers":[
        {
            "category":"Bars & Pubs",
            "type":"Food & Drink"
        }
    ],
    "sg:phone":"+1 504 866 0004",
    "sg:postcode":"70125",
    "sg:province":"LA",
    "sg:tags":[
        "lounge",
        "cocktail"
    ],
    "wof:name":"Jackson Lounge",
    "wof:placetype":"venue"
},
  "geometry": {"coordinates":[-90.110393,29.958123],"type":"Point"}
}