{
  "type": "Feature",
  "properties": {
    "addr:full":"3701 Plank Rd Baton Rouge LA 70805",
    "addr:housenumber":"3701",
    "addr:postcode":"70805",
    "addr:street":"Plank Rd",
    "iso:country":"US",
    "sg:address":"3701 Plank Rd",
    "sg:city":"Baton Rouge",
    "sg:classifiers":[
        {
            "category":"Organizations",
            "subcategory":"Religious Organization",
            "type":"Services"
        }
    ],
    "sg:phone":"+1 225 358 0200",
    "sg:postcode":"70805",
    "sg:province":"LA",
    "sg:tags":[
        "church"
    ],
    "wof:name":"Healing Waters Ministry Otrch",
    "wof:placetype":"venue"
},
  "geometry": {"coordinates":[-91.15927600000001,30.482108],"type":"Point"}
}