{
  "type": "Feature",
  "properties": {
    "iso:country":"US",
    "sg:address":"2238 Martin Luther King Jr Blvd",
    "sg:city":"New Orleans",
    "sg:classifiers":[
        {
            "category":"Food & Beverages",
            "subcategory":"Groceries & Convenience Stores",
            "type":"Retail Goods"
        }
    ],
    "sg:phone":"+1 504 586 1762",
    "sg:postcode":"70113",
    "sg:province":"LA",
    "sg:tags":[
        "grocer"
    ],
    "wof:name":"Project Food Store",
    "wof:placetype":"venue"
},
  "geometry": {"coordinates":[-90.082322,29.942693],"type":"Point"}
}