{
  "type": "Feature",
  "properties": {
    "iso:country":"US",
    "sg:address":"131 Gillis Cutoff",
    "sg:city":"Lake Charles",
    "sg:classifiers":[
        {
            "category":"Food & Beverages",
            "subcategory":"Meat & Fish",
            "type":"Retail Goods"
        }
    ],
    "sg:phone":"+1 337 855 4806",
    "sg:postcode":"70611",
    "sg:province":"LA",
    "wof:name":"Gillis Meat Processing",
    "wof:placetype":"venue"
},
  "geometry": {"coordinates":[-93.206272,30.373718],"type":"Point"}
}