{
  "type": "Feature",
  "properties": {
    "addr:full":"601 W Branche St Rayne LA 70578",
    "addr:housenumber":"601",
    "addr:postcode":"70578",
    "addr:street":"W Branche St",
    "iso:country":"US",
    "sg:address":"601 W Branche St",
    "sg:city":"Rayne",
    "sg:classifiers":[
        {
            "category":"Restaurant",
            "type":"Food & Drink"
        }
    ],
    "sg:phone":"+1 337 334 4727",
    "sg:postcode":"70578",
    "sg:province":"LA",
    "wof:name":"Brousse's Drive Inn",
    "wof:placetype":"venue"
},
  "geometry": {"coordinates":[-92.27425599999999,30.227318],"type":"Point"}
}