{
  "type": "Feature",
  "properties": {
    "addr:full":"6415 Quinn Dr Baton Rouge LA 70817",
    "addr:housenumber":"6415",
    "addr:postcode":"70817",
    "addr:street":"Quinn Dr",
    "iso:country":"US",
    "sg:address":"6415 Quinn Dr",
    "sg:city":"Baton Rouge",
    "sg:classifiers":[
        {
            "category":"Professional",
            "subcategory":"Engineering",
            "type":"Services"
        }
    ],
    "sg:phone":"+1 225 751 9251",
    "sg:postcode":"70817",
    "sg:province":"LA",
    "sg:tags":[
        "engineer"
    ],
    "wof:name":"Lee Consulting Svc",
    "wof:placetype":"venue"
},
  "geometry": {"coordinates":[-91.034302,30.393455],"type":"Point"}
}