{
  "type": "Feature",
  "properties": {
    "iso:country":"US",
    "sg:address":"3100 Ridgelake Dr",
    "sg:city":"Metairie",
    "sg:classifiers":[
        {
            "category":"Building & Trades",
            "subcategory":"Construction",
            "type":"Services"
        }
    ],
    "sg:phone":"+1 504 832 6653",
    "sg:postcode":"70002",
    "sg:province":"LA",
    "sg:tags":[
        "fire",
        "restoration",
        "damage"
    ],
    "wof:name":"Mold Testing & Remediation",
    "wof:placetype":"venue"
},
  "geometry": {"coordinates":[-90.15342699999999,30.007134],"type":"Point"}
}