{
  "type": "Feature",
  "properties": {
    "iso:country":"US",
    "sg:address":"2307 Whitney Ave",
    "sg:city":"Gretna",
    "sg:classifiers":[
        {
            "category":"Shopping",
            "subcategory":"Florist",
            "type":"Retail Goods"
        }
    ],
    "sg:phone":"+1 504 304 6148",
    "sg:postcode":"70056",
    "sg:province":"LA",
    "wof:name":"Irmalila",
    "wof:placetype":"venue"
},
  "geometry": {"coordinates":[-90.042911,29.915908],"type":"Point"}
}