{
  "type": "Feature",
  "properties": {
    "iso:country":"US",
    "sg:address":"926 Taft Pl",
    "sg:city":"New Orleans",
    "sg:classifiers":[
        {
            "category":"Professional",
            "type":"Services"
        }
    ],
    "sg:phone":"+1 504 896 2582",
    "sg:postcode":"70119",
    "sg:province":"LA",
    "wof:name":"Palmetto Pictures Inc",
    "wof:placetype":"venue"
},
  "geometry": {"coordinates":[-90.091652,29.980687],"type":"Point"}
}