{
  "type": "Feature",
  "properties": {
    "iso:country":"US",
    "sg:address":"641 E Madison Ave",
    "sg:city":"Bastrop",
    "sg:classifiers":[
        {
            "category":"Shopping",
            "subcategory":"Gifts & Souvenirs",
            "type":"Retail Goods"
        }
    ],
    "sg:phone":"+1 318 281 1927",
    "sg:postcode":"71220",
    "sg:province":"LA",
    "sg:tags":[
        "shop"
    ],
    "wof:name":"Rodgers Hallmark",
    "wof:placetype":"venue"
},
  "geometry": {"coordinates":[-91.906029,32.778791],"type":"Point"}
}