{
  "type": "Feature",
  "properties": {
    "addr:full":"3708 Severn Ave Metairie LA 70002",
    "addr:housenumber":"3708",
    "addr:postcode":"70002",
    "addr:street":"Severn Ave",
    "iso:country":"US",
    "sg:address":"3708 Severn Ave",
    "sg:city":"Metairie",
    "sg:classifiers":[
        {
            "category":"Wholesale",
            "subcategory":"Durable Goods & Equipment",
            "type":"Manufacturing & Wholesale Goods"
        }
    ],
    "sg:phone":"+1 504 888 7947",
    "sg:postcode":"70002",
    "sg:province":"LA",
    "sg:tags":[
        "representative",
        "manufacturer"
    ],
    "wof:name":"James E Berrigan Inc",
    "wof:placetype":"venue"
},
  "geometry": {"coordinates":[-90.159139,30.015631],"type":"Point"}
}