{
  "type": "Feature",
  "properties": {
    "iso:country":"US",
    "sg:address":"28760 Juban Rd",
    "sg:city":"Denham Springs",
    "sg:classifiers":[
        {
            "category":"Real Estate",
            "subcategory":"Real Estate Operator",
            "type":"Services"
        }
    ],
    "sg:phone":"+1 225 665 0455",
    "sg:postcode":"70726",
    "sg:province":"LA",
    "sg:tags":[
        "mobile",
        "home",
        "community"
    ],
    "wof:name":"Seven Oaks Mobile Home Park",
    "wof:placetype":"venue"
},
  "geometry": {"coordinates":[-90.91885600000001,30.4724],"type":"Point"}
}