{
  "type": "Feature",
  "properties": {
    "iso:country":"US",
    "sg:address":"117 S Vine St",
    "sg:city":"Bastrop",
    "sg:classifiers":[
        {
            "category":"Personal",
            "subcategory":"Beauty Salon",
            "type":"Services"
        }
    ],
    "sg:phone":"+1 318 281 8652",
    "sg:postcode":"71220",
    "sg:province":"LA",
    "sg:tags":[
        "school"
    ],
    "wof:name":"Bastrop Beauty School",
    "wof:placetype":"venue"
},
  "geometry": {"coordinates":[-91.91554499999999,32.778087],"type":"Point"}
}