{
  "type": "Feature",
  "properties": {
    "iso:country":"US",
    "sg:address":"8128 Willow St",
    "sg:city":"New Orleans",
    "sg:classifiers":[
        {
            "category":"Retail",
            "subcategory":"Laundry & Dry Cleaning",
            "type":"Services"
        }
    ],
    "sg:phone":"+1 504 861 7812",
    "sg:postcode":"70118",
    "sg:province":"LA",
    "sg:tags":[
        "cleaners"
    ],
    "wof:name":"Liberto Cleaners",
    "wof:placetype":"venue"
},
  "geometry": {"coordinates":[-90.12899299999999,29.949238],"type":"Point"}
}