{
  "type": "Feature",
  "properties": {
    "addr:full":"64107 Hwy 41 Pearl River LA 70452",
    "addr:housenumber":"64107",
    "addr:postcode":"70452",
    "addr:street":"Hwy 41",
    "iso:country":"US",
    "sg:address":"64107 Hwy 41",
    "sg:city":"Pearl River",
    "sg:classifiers":[
        {
            "category":"Restaurant",
            "type":"Food & Drink"
        }
    ],
    "sg:phone":"+1 985 863 8841",
    "sg:postcode":"70452",
    "sg:province":"LA",
    "wof:name":"Sonic Drive-In",
    "wof:placetype":"venue"
},
  "geometry": {"coordinates":[-89.752797,30.361792],"type":"Point"}
}