{
  "type": "Feature",
  "properties": {
    "iso:country":"US",
    "sg:address":"127 S Bienville St",
    "sg:city":"Lafayette",
    "sg:classifiers":[
        {
            "category":"Building & Trades",
            "subcategory":"Construction",
            "type":"Services"
        }
    ],
    "sg:phone":"+1 337 232 6448",
    "sg:postcode":"70501",
    "sg:province":"LA",
    "sg:tags":[
        "roofing",
        "contractor"
    ],
    "wof:name":"Simon Roofing",
    "wof:placetype":"venue"
},
  "geometry": {"coordinates":[-92.023903,30.2332],"type":"Point"}
}