{
  "type": "Feature",
  "properties": {
    "iso:country":"US",
    "sg:address":"200 Main St",
    "sg:city":"Colfax",
    "sg:classifiers":[
        {
            "category":"Government",
            "subcategory":"Court House",
            "type":"Public Place"
        }
    ],
    "sg:phone":"+1 318 627 3246",
    "sg:postcode":"71417",
    "sg:province":"LA",
    "sg:tags":[
        "county"
    ],
    "wof:name":"Grant Parish Clerk Of Court",
    "wof:placetype":"venue"
},
  "geometry": {"coordinates":[-92.712373,31.516942],"type":"Point"}
}