{
  "type": "Feature",
  "properties": {
    "addr:full":"110 Little Beaver Ln New Iberia LA 70560",
    "addr:housenumber":"110",
    "addr:postcode":"70560",
    "addr:street":"Little Beaver Ln",
    "iso:country":"US",
    "sg:address":"110 Little Beaver Ln",
    "sg:city":"New Iberia",
    "sg:classifiers":[
        {
            "category":"Wholesale",
            "subcategory":"Machinery & Supplies",
            "type":"Manufacturing & Wholesale Goods"
        }
    ],
    "sg:phone":"+1 337 364 3025",
    "sg:postcode":"70560",
    "sg:province":"LA",
    "sg:tags":[
        "field",
        "oil"
    ],
    "wof:name":"Well Service & Supply",
    "wof:placetype":"venue"
},
  "geometry": {"coordinates":[-91.873442,30.05628],"type":"Point"}
}