{
  "type": "Feature",
  "properties": {
    "addr:full":"406 Ambassador Caffery Pkwy Scott LA 70583",
    "addr:housenumber":"406",
    "addr:postcode":"70583",
    "addr:street":"Ambassador Caffery Pkwy",
    "iso:country":"US",
    "sg:address":"406 Ambassador Caffery Pkwy",
    "sg:city":"Scott",
    "sg:classifiers":[
        {
            "category":"Food & Beverages",
            "subcategory":"Groceries & Convenience Stores",
            "type":"Retail Goods"
        }
    ],
    "sg:phone":"+1 337 235 8277",
    "sg:postcode":"70583",
    "sg:province":"LA",
    "sg:website":"www.crackerbarrel.com",
    "wof:name":"Cracker Barrel",
    "wof:placetype":"venue"
},
  "geometry": {"coordinates":[-92.06607,30.24004],"type":"Point"}
}