{
  "type": "Feature",
  "properties": {
    "iso:country":"US",
    "sg:address":"3125 Valcour Aime St",
    "sg:city":"Vacherie",
    "sg:classifiers":[
        {
            "category":"Education",
            "subcategory":"School",
            "type":"Public Place"
        }
    ],
    "sg:phone":"+1 225 265 3042",
    "sg:postcode":"70090",
    "sg:province":"LA",
    "wof:name":"St James Parish Science & Math",
    "wof:placetype":"venue"
},
  "geometry": {"coordinates":[-90.753606,30.005449],"type":"Point"}
}