{
  "type": "Feature",
  "properties": {
    "iso:country":"US",
    "sg:address":"107 Leeward Loop",
    "sg:city":"Carencro",
    "sg:classifiers":[
        {
            "category":"Professional",
            "subcategory":"Research",
            "type":"Services"
        }
    ],
    "sg:phone":"+1 337 896 7268",
    "sg:postcode":"70520",
    "sg:province":"LA",
    "sg:tags":[
        "environmental",
        "ecological"
    ],
    "wof:name":"KJN Enviroserv",
    "wof:placetype":"venue"
},
  "geometry": {"coordinates":[-92.073087,30.317521],"type":"Point"}
}