{
  "type": "Feature",
  "properties": {
    "iso:country":"US",
    "sg:address":"401 E Maggie St",
    "sg:city":"Leesville",
    "sg:classifiers":[
        {
            "category":"Retail",
            "subcategory":"Laundry & Dry Cleaning",
            "type":"Services"
        }
    ],
    "sg:phone":"+1 337 238 0062",
    "sg:postcode":"71446",
    "sg:province":"LA",
    "sg:tags":[
        "cleaners"
    ],
    "wof:name":"City Cleaners",
    "wof:placetype":"venue"
},
  "geometry": {"coordinates":[-93.25999,31.14134],"type":"Point"}
}