{
  "type": "Feature",
  "properties": {
    "iso:country":"US",
    "sg:address":"550 Nighthawk Rd",
    "sg:city":"Morse",
    "sg:classifiers":[
        {
            "category":"Education",
            "subcategory":"Special Training",
            "type":"Public Place"
        }
    ],
    "sg:phone":"+1 337 783 9318",
    "sg:postcode":"70534",
    "sg:province":"LA",
    "sg:tags":[
        "aircraft",
        "school"
    ],
    "wof:name":"A J Aviation Aerial Patrol",
    "wof:placetype":"venue"
},
  "geometry": {"coordinates":[-92.481331,30.16777],"type":"Point"}
}