{
  "type": "Feature",
  "properties": {
    "iso:country":"US",
    "sg:address":"1630 Metro Dr",
    "sg:city":"Alexandria",
    "sg:classifiers":[
        {
            "category":"Professional",
            "subcategory":"Lawyer & Legal Services",
            "type":"Services"
        }
    ],
    "sg:phone":"+1 318 473 0052",
    "sg:postcode":"71301",
    "sg:province":"LA",
    "sg:tags":[
        "attorney"
    ],
    "wof:name":"Brian K Thompson",
    "wof:placetype":"venue"
},
  "geometry": {"coordinates":[-92.47104299999999,31.27596],"type":"Point"}
}