{
  "type": "Feature",
  "properties": {
    "addr:full":"505 N 18th St Monroe LA 71201",
    "addr:housenumber":"505",
    "addr:postcode":"71201",
    "addr:street":"N 18Th St",
    "iso:country":"US",
    "sg:address":"505 N 18th St",
    "sg:city":"Monroe",
    "sg:classifiers":[
        {
            "category":"Banks & Credit Unions",
            "subcategory":"Bank",
            "type":"Services"
        }
    ],
    "sg:phone":"+1 318 322 8100",
    "sg:postcode":"71201",
    "sg:province":"LA",
    "sg:tags":[
        "loan"
    ],
    "wof:name":"Century Loans",
    "wof:placetype":"venue"
},
  "geometry": {"coordinates":[-92.10564100000001,32.515854],"type":"Point"}
}