{
  "type": "Feature",
  "properties": {
    "addr:full":"2751 Vidrine Rd Ville Platte LA 70586",
    "addr:housenumber":"2751",
    "addr:postcode":"70586",
    "addr:street":"Vidrine Rd",
    "iso:country":"US",
    "sg:address":"2751 Vidrine Rd",
    "sg:city":"Ville Platte",
    "sg:classifiers":[
        {
            "category":"Retail",
            "subcategory":"Veterinary Services",
            "type":"Services"
        }
    ],
    "sg:phone":"+1 337 363 8032",
    "sg:postcode":"70586",
    "sg:province":"LA",
    "sg:tags":[
        "hospital",
        "animal"
    ],
    "wof:name":"Town & Country Animal Clinic",
    "wof:placetype":"venue"
},
  "geometry": {"coordinates":[-92.322495,30.701187],"type":"Point"}
}