{
  "type": "Feature",
  "properties": {
    "iso:country":"US",
    "sg:address":"15510 W Club Deluxe Rd",
    "sg:city":"Hammond",
    "sg:classifiers":[
        {
            "category":"Real Estate",
            "subcategory":"Real Estate Operator",
            "type":"Services"
        }
    ],
    "sg:phone":"+1 985 542 4825",
    "sg:postcode":"70403",
    "sg:province":"LA",
    "sg:tags":[
        "apartment"
    ],
    "wof:name":"Hammond Square Apartments",
    "wof:placetype":"venue"
},
  "geometry": {"coordinates":[-90.46990099999999,30.475545],"type":"Point"}
}