{
  "type": "Feature",
  "properties": {
    "iso:country":"US",
    "sg:address":"3102 Elysian Fields Ave",
    "sg:city":"New Orleans",
    "sg:classifiers":[
        {
            "category":"Fast Food",
            "type":"Food & Drink"
        },
        {
            "category":"Food & Beverages",
            "subcategory":"Meat & Fish",
            "type":"Retail Goods"
        }
    ],
    "sg:phone":"+1 504 943 0891",
    "sg:postcode":"70122",
    "sg:province":"LA",
    "sg:tags":[
        "burger",
        "hot",
        "dog"
    ],
    "sg:website":"www.burgerking.com",
    "wof:name":"Burger King Llc",
    "wof:placetype":"venue"
},
  "geometry": {"coordinates":[-90.05879,29.989832],"type":"Point"}
}