{
  "type": "Feature",
  "properties": {
    "addr:full":"784 Elmer Rd Elmer LA 71424",
    "addr:housenumber":"784",
    "addr:postcode":"71424",
    "addr:street":"Elmer Rd",
    "iso:country":"US",
    "sg:address":"784 Elmer Rd",
    "sg:city":"Elmer",
    "sg:classifiers":[
        {
            "category":"Personal",
            "subcategory":"Beauty Salon",
            "type":"Services"
        }
    ],
    "sg:phone":"+1 318 659 4859",
    "sg:postcode":"71424",
    "sg:province":"LA",
    "wof:name":"Mechele's Hair Nail & Tanning",
    "wof:placetype":"venue"
},
  "geometry": {"coordinates":[-92.711219,31.090184],"type":"Point"}
}