{
  "type": "Feature",
  "properties": {
    "iso:country":"US",
    "sg:address":"1000 Lafargue St",
    "sg:city":"Sulphur",
    "sg:classifiers":[
        {
            "category":"Manufacturing",
            "subcategory":"Metals",
            "type":"Manufacturing & Wholesale Goods"
        }
    ],
    "sg:phone":"+1 337 528 2282",
    "sg:postcode":"70663",
    "sg:province":"LA",
    "sg:tags":[
        "plating"
    ],
    "wof:name":"Cajun Chrome & Plating",
    "wof:placetype":"venue"
},
  "geometry": {"coordinates":[-93.378129,30.229841],"type":"Point"}
}