{
  "type": "Feature",
  "properties": {
    "iso:country":"US",
    "sg:address":"18615 S Harrells Ferry Rd",
    "sg:city":"Baton Rouge",
    "sg:classifiers":[
        {
            "category":"Building & Trades",
            "subcategory":"Construction",
            "type":"Services"
        }
    ],
    "sg:phone":"+1 225 753 4445",
    "sg:postcode":"70816",
    "sg:province":"LA",
    "sg:tags":[
        "downspouts",
        "gutter"
    ],
    "wof:name":"Gutters & More",
    "wof:placetype":"venue"
},
  "geometry": {"coordinates":[-90.98068600000001,30.418826],"type":"Point"}
}