{
  "type": "Feature",
  "properties": {
    "iso:country":"US",
    "sg:address":"104 Ehret Pl",
    "sg:city":"Marrero",
    "sg:classifiers":[
        {
            "category":"Professional",
            "subcategory":"Business Services",
            "type":"Services"
        }
    ],
    "sg:phone":"+1 504 340 4166",
    "sg:postcode":"70072",
    "sg:province":"LA",
    "wof:name":"McEvers Enterprises",
    "wof:placetype":"venue"
},
  "geometry": {"coordinates":[-90.10647899999999,29.862027],"type":"Point"}
}