{
  "type": "Feature",
  "properties": {
    "addr:full":"152 Banks Ave Lafayette LA 70506",
    "addr:housenumber":"152",
    "addr:postcode":"70506",
    "addr:street":"Banks Ave",
    "iso:country":"US",
    "sg:address":"152 Banks Ave",
    "sg:city":"Lafayette",
    "sg:classifiers":[
        {
            "category":"Retail",
            "subcategory":"Repair Shop",
            "type":"Services"
        }
    ],
    "sg:phone":"+1 337 893 8838",
    "sg:postcode":"70506",
    "sg:province":"LA",
    "sg:tags":[
        "key"
    ],
    "sg:website":"www.palsecure.com",
    "wof:name":"Pop-A-Lock",
    "wof:placetype":"venue"
},
  "geometry": {"coordinates":[-92.060664,30.227553],"type":"Point"}
}