{
  "type": "Feature",
  "properties": {
    "iso:country":"US",
    "sg:address":"1801 A P Tureaud Ave",
    "sg:city":"New Orleans",
    "sg:classifiers":[
        {
            "category":"Organizations",
            "subcategory":"Religious Organization",
            "type":"Services"
        }
    ],
    "sg:phone":"+1 504 948 4516",
    "sg:postcode":"70116",
    "sg:province":"LA",
    "wof:name":"Cedar Grove Baptist Church",
    "wof:placetype":"venue"
},
  "geometry": {"coordinates":[-90.06684,29.976073],"type":"Point"}
}