{
  "type": "Feature",
  "properties": {
    "iso:country":"US",
    "sg:address":"253 Cheniere Baptist Church Rd",
    "sg:city":"West Monroe",
    "sg:classifiers":[
        {
            "category":"Retail",
            "subcategory":"Repair Shop",
            "type":"Services"
        }
    ],
    "sg:phone":"+1 318 396 2953",
    "sg:postcode":"71292",
    "sg:province":"LA",
    "sg:tags":[
        "equipment",
        "hydraulic"
    ],
    "wof:name":"Hydraulic Rebuilders",
    "wof:placetype":"venue"
},
  "geometry": {"coordinates":[-92.244563,32.501668],"type":"Point"}
}