{
  "type": "Feature",
  "properties": {
    "iso:country":"US",
    "sg:address":"176 Bryant Rd",
    "sg:city":"Montgomery",
    "sg:classifiers":[
        {
            "category":"Organizations",
            "subcategory":"Community Association",
            "type":"Services"
        }
    ],
    "sg:phone":"+1 318 646 2861",
    "sg:postcode":"71454",
    "sg:province":"LA",
    "wof:name":"Veterans of Foreign Wars of US",
    "wof:placetype":"venue"
},
  "geometry": {"coordinates":[-92.801322,31.696727],"type":"Point"}
}