{
  "type": "Feature",
  "properties": {
    "addr:full":"3025 Elysian Fields Ave New Orleans LA 70122",
    "addr:housenumber":"3025",
    "addr:postcode":"70122",
    "addr:street":"Elysian Fields Ave",
    "iso:country":"US",
    "sg:address":"3025 Elysian Fields Ave",
    "sg:city":"New Orleans",
    "sg:classifiers":[
        {
            "category":"Restaurant",
            "type":"Food & Drink"
        }
    ],
    "sg:menulink":"http://www.allmenus.com/la/new-orleans/188410-mcdonalds/menu/",
    "sg:postcode":"70122",
    "sg:province":"LA",
    "sg:tags":[
        "burger",
        "american"
    ],
    "wof:name":"McDonald's",
    "wof:placetype":"venue"
},
  "geometry": {"coordinates":[-90.05828200000001,29.989079],"type":"Point"}
}