{
  "type": "Feature",
  "properties": {
    "iso:country":"US",
    "sg:address":"3620 de la Ronde Dr",
    "sg:city":"Chalmette",
    "sg:classifiers":[
        {
            "category":"Health Services",
            "subcategory":"Health Practitioner",
            "type":"Services"
        }
    ],
    "sg:phone":"+1 504 271 6778",
    "sg:postcode":"70043",
    "sg:province":"LA",
    "sg:tags":[
        "therapist",
        "physical"
    ],
    "wof:name":"St Bernard Physical Therapy",
    "wof:placetype":"venue"
},
  "geometry": {"coordinates":[-89.970434,29.957766],"type":"Point"}
}