{
  "type": "Feature",
  "properties": {
    "addr:full":"1402 N Acadian Throughway W Baton Rouge LA 70802",
    "addr:housenumber":"1402",
    "addr:postcode":"70802",
    "addr:street":"N Acadian Throughway W",
    "iso:country":"US",
    "sg:address":"1402 N Acadian Throughway W",
    "sg:city":"Baton Rouge",
    "sg:classifiers":[
        {
            "category":"Organizations",
            "subcategory":"Religious Organization",
            "type":"Services"
        }
    ],
    "sg:phone":"+1 225 357 3300",
    "sg:postcode":"70802",
    "sg:province":"LA",
    "sg:tags":[
        "church"
    ],
    "wof:name":"In Christ We Trust Fellowship",
    "wof:placetype":"venue"
},
  "geometry": {"coordinates":[-91.156021,30.461366],"type":"Point"}
}