{
  "type": "Feature",
  "properties": {
    "iso:country":"US",
    "sg:address":"3775 Hemlock St",
    "sg:city":"Zachary",
    "sg:classifiers":[
        {
            "category":"Education",
            "subcategory":"School",
            "type":"Public Place"
        }
    ],
    "sg:phone":"+1 225 654 4036",
    "sg:postcode":"70791",
    "sg:province":"LA",
    "wof:name":"Zachary Elementary School",
    "wof:placetype":"venue"
},
  "geometry": {"coordinates":[-91.16788099999999,30.640787],"type":"Point"}
}