{
  "type": "Feature",
  "properties": {
    "iso:country":"US",
    "sg:address":"78461 Hwy 437",
    "sg:city":"Covington",
    "sg:classifiers":[
        {
            "category":"Restaurant",
            "type":"Food & Drink"
        }
    ],
    "sg:phone":"+1 985 892 8744",
    "sg:postcode":"70435",
    "sg:province":"LA",
    "wof:name":"Lily Bean's",
    "wof:placetype":"venue"
},
  "geometry": {"coordinates":[-90.07568499999999,30.573999],"type":"Point"}
}