{
  "type": "Feature",
  "properties": {
    "iso:country":"US",
    "sg:address":"219 N Range Ave",
    "sg:city":"Denham Springs",
    "sg:classifiers":[
        {
            "category":"Shopping",
            "subcategory":"Used Merchandise",
            "type":"Retail Goods"
        }
    ],
    "sg:phone":"+1 225 667 5454",
    "sg:postcode":"70726",
    "sg:province":"LA",
    "wof:name":"Downtown Antiques",
    "wof:placetype":"venue"
},
  "geometry": {"coordinates":[-90.95620599999999,30.485815],"type":"Point"}
}