{
  "type": "Feature",
  "properties": {
    "iso:country":"US",
    "sg:address":"146 Jodie Williams Rd",
    "sg:city":"Deridder",
    "sg:phone":"+1 337 462 3183",
    "sg:postcode":"70634",
    "sg:province":"LA",
    "sg:tags":[
        "distributor",
        "oil",
        "marketer"
    ],
    "wof:name":"Eastex Crude Co",
    "wof:placetype":"venue"
},
  "geometry": {"coordinates":[-93.293708,30.909125],"type":"Point"}
}