{
  "type": "Feature",
  "properties": {
    "iso:country":"US",
    "sg:address":"12903 State Rte 1",
    "sg:city":"Oil City",
    "sg:classifiers":[
        {
            "category":"Wholesale",
            "subcategory":"Machinery & Supplies",
            "type":"Manufacturing & Wholesale Goods"
        }
    ],
    "sg:phone":"+1 318 995 7006",
    "sg:postcode":"71061",
    "sg:province":"LA",
    "sg:tags":[
        "equipment",
        "railroad"
    ],
    "wof:name":"Railway Equipment Svc",
    "wof:placetype":"venue"
},
  "geometry": {"coordinates":[-93.979696,32.77158],"type":"Point"}
}