{
  "type": "Feature",
  "properties": {
    "iso:country":"US",
    "sg:address":"8846 S Choctaw Dr",
    "sg:city":"Baton Rouge",
    "sg:classifiers":[
        {
            "category":"Professional",
            "subcategory":"Research",
            "type":"Services"
        }
    ],
    "sg:phone":"+1 225 927 4187",
    "sg:postcode":"70815",
    "sg:province":"LA",
    "sg:tags":[
        "environmental",
        "ecological"
    ],
    "wof:name":"Evans Equipment & Environment",
    "wof:placetype":"venue"
},
  "geometry": {"coordinates":[-91.091527,30.471459],"type":"Point"}
}