{
  "type": "Feature",
  "properties": {
    "iso:country":"US",
    "sg:address":"3035 Mc Connell Dr",
    "sg:city":"Baton Rouge",
    "sg:classifiers":[
        {
            "category":"Professional",
            "type":"Services"
        }
    ],
    "sg:phone":"+1 225 925 8216",
    "sg:postcode":"70809",
    "sg:province":"LA",
    "wof:name":"Betty D Cunningham Designs",
    "wof:placetype":"venue"
},
  "geometry": {"coordinates":[-91.11253000000001,30.421956],"type":"Point"}
}