{
  "type": "Feature",
  "properties": {
    "iso:country":"US",
    "sg:address":"2704 Wooddale Blvd",
    "sg:city":"Baton Rouge",
    "sg:classifiers":[
        {
            "category":"Professional",
            "subcategory":"Lawyer & Legal Services",
            "type":"Services"
        }
    ],
    "sg:phone":"+1 225 925 8884",
    "sg:postcode":"70805",
    "sg:province":"LA",
    "sg:tags":[
        "clinic"
    ],
    "wof:name":"Advocacy Ctr-Elderly Disabled",
    "wof:placetype":"venue"
},
  "geometry": {"coordinates":[-91.115909,30.473493],"type":"Point"}
}