{
  "type": "Feature",
  "properties": {
    "addr:full":"608 Parent St New Roads LA 70760",
    "addr:housenumber":"608",
    "addr:postcode":"70760",
    "addr:street":"Parent St",
    "iso:country":"US",
    "sg:address":"608 Parent St",
    "sg:city":"New Roads",
    "sg:classifiers":[
        {
            "category":"Autos & Motor Vehicles",
            "subcategory":"Automobile Sales",
            "type":"Retail Goods"
        }
    ],
    "sg:phone":"+1 225 638 9041",
    "sg:postcode":"70760",
    "sg:province":"LA",
    "sg:tags":[
        "car",
        "dealer"
    ],
    "wof:name":"New Roads Motor Co Inc",
    "wof:placetype":"venue"
},
  "geometry": {"coordinates":[-91.440521,30.700667],"type":"Point"}
}