{
  "type": "Feature",
  "properties": {
    "addr:full":"42480 State Rte 23 Venice LA 70091",
    "addr:housenumber":"42480",
    "addr:postcode":"70091",
    "addr:street":"State Rte 23",
    "iso:country":"US",
    "sg:address":"42480 State Rte 23",
    "sg:city":"Venice",
    "sg:classifiers":[
        {
            "category":"Shopping",
            "subcategory":"Bicycles & Sporting Goods",
            "type":"Retail Goods"
        }
    ],
    "sg:phone":"+1 985 534 7799",
    "sg:postcode":"70091",
    "sg:province":"LA",
    "sg:tags":[
        "bait",
        "fishing"
    ],
    "wof:name":"Barney's Bait Shop",
    "wof:placetype":"venue"
},
  "geometry": {"coordinates":[-89.36386400000001,29.284684],"type":"Point"}
}