{
  "type": "Feature",
  "properties": {
    "addr:full":"184 Thibodeaux Rd Florien LA 71429",
    "addr:housenumber":"184",
    "addr:postcode":"71429",
    "addr:street":"Thibodeaux Rd",
    "iso:country":"US",
    "sg:address":"184 Thibodeaux Rd",
    "sg:city":"Florien",
    "sg:classifiers":[
        {
            "category":"Building & Trades",
            "subcategory":"Construction",
            "type":"Services"
        }
    ],
    "sg:phone":"+1 318 586 0007",
    "sg:postcode":"71429",
    "sg:province":"LA",
    "sg:tags":[
        "contractor"
    ],
    "wof:name":"Sacco Improvements",
    "wof:placetype":"venue"
},
  "geometry": {"coordinates":[-93.33956000000001,31.448045],"type":"Point"}
}