{
  "type": "Feature",
  "properties": {
    "addr:full":"424 Airport Rd Mansura LA 71350",
    "addr:housenumber":"424",
    "addr:postcode":"71350",
    "addr:street":"Airport Rd",
    "iso:country":"US",
    "sg:address":"424 Airport Rd",
    "sg:city":"Mansura",
    "sg:classifiers":[
        {
            "category":"Building & Trades",
            "subcategory":"Plumbing",
            "type":"Services"
        }
    ],
    "sg:phone":"+1 318 253 8218",
    "sg:postcode":"71350",
    "sg:province":"LA",
    "sg:tags":[
        "contractor"
    ],
    "wof:name":"Quebedeauxs AC & Htg",
    "wof:placetype":"venue"
},
  "geometry": {"coordinates":[-92.062192,31.098527],"type":"Point"}
}