{
  "type": "Feature",
  "properties": {
    "addr:full":"3966 Lakeshore Dr Shreveport LA 71109",
    "addr:housenumber":"3966",
    "addr:postcode":"71109",
    "addr:street":"Lakeshore Dr",
    "iso:country":"US",
    "sg:address":"3966 Lakeshore Dr",
    "sg:city":"Shreveport",
    "sg:classifiers":[
        {
            "category":"Shopping",
            "subcategory":"Florist",
            "type":"Retail Goods"
        }
    ],
    "sg:phone":"+1 318 635 2160",
    "sg:postcode":"71109",
    "sg:province":"LA",
    "wof:name":"Pat's Elegant Florist",
    "wof:placetype":"venue"
},
  "geometry": {"coordinates":[-93.8032,32.490196],"type":"Point"}
}