{
  "type": "Feature",
  "properties": {
    "iso:country":"US",
    "sg:address":"11914 Justice Ave",
    "sg:city":"Baton Rouge",
    "sg:classifiers":[
        {
            "category":"Professional",
            "subcategory":"Management & Consulting",
            "type":"Services"
        }
    ],
    "sg:phone":"+1 225 293 1387",
    "sg:postcode":"70816",
    "sg:province":"LA",
    "sg:tags":[
        "consultant",
        "business"
    ],
    "wof:name":"PSI Inc",
    "wof:placetype":"venue"
},
  "geometry": {"coordinates":[-91.049952,30.424069],"type":"Point"}
}