{
  "type": "Feature",
  "properties": {
    "iso:country":"US",
    "sg:address":"4702 Toulouse St",
    "sg:city":"New Orleans",
    "sg:classifiers":[
        {
            "category":"Professional",
            "subcategory":"Engineering",
            "type":"Services"
        }
    ],
    "sg:phone":"+1 504 488 1442",
    "sg:postcode":"70119",
    "sg:province":"LA",
    "sg:tags":[
        "engineer"
    ],
    "wof:name":"Zehner & Bouchon Consulting",
    "wof:placetype":"venue"
},
  "geometry": {"coordinates":[-90.1044,29.98319],"type":"Point"}
}