{
  "type": "Feature",
  "properties": {
    "iso:country":"US",
    "sg:address":"5119 Interest Rd",
    "sg:city":"New Iberia",
    "sg:classifiers":[
        {
            "category":"Wholesale",
            "subcategory":"Metals & Minerals",
            "type":"Manufacturing & Wholesale Goods"
        }
    ],
    "sg:phone":"+1 337 365 0390",
    "sg:postcode":"70560",
    "sg:province":"LA",
    "sg:tags":[
        "pipe"
    ],
    "wof:name":"Acadian Fiberglass Inc",
    "wof:placetype":"venue"
},
  "geometry": {"coordinates":[-91.872992,29.94959],"type":"Point"}
}