{
  "type": "Feature",
  "properties": {
    "addr:full":"166 Nixon Rd Kinder LA 70648",
    "addr:housenumber":"166",
    "addr:postcode":"70648",
    "addr:street":"Nixon Rd",
    "iso:country":"US",
    "sg:address":"166 Nixon Rd",
    "sg:city":"Kinder",
    "sg:classifiers":[
        {
            "category":"Freight",
            "type":"Transportation"
        }
    ],
    "sg:phone":"+1 337 738 2219",
    "sg:postcode":"70648",
    "sg:province":"LA",
    "sg:tags":[
        "hauling",
        "trucking"
    ],
    "wof:name":"Wade Savant Trucking",
    "wof:placetype":"venue"
},
  "geometry": {"coordinates":[-92.97372300000001,30.445514],"type":"Point"}
}