{
  "type": "Feature",
  "properties": {
    "iso:country":"US",
    "sg:address":"2433 Midway St",
    "sg:city":"Shreveport",
    "sg:classifiers":[
        {
            "category":"Retail",
            "subcategory":"Repair Shop",
            "type":"Services"
        }
    ],
    "sg:phone":"+1 318 631 7800",
    "sg:postcode":"71108",
    "sg:province":"LA",
    "wof:name":"Ilias Uptholstery",
    "wof:placetype":"venue"
},
  "geometry": {"coordinates":[-93.77510599999999,32.470876],"type":"Point"}
}