{
  "type": "Feature",
  "properties": {
    "iso:country":"US",
    "sg:address":"1600 Peach St",
    "sg:city":"Monroe",
    "sg:classifiers":[
        {
            "category":"Organizations",
            "subcategory":"Religious Organization",
            "type":"Services"
        }
    ],
    "sg:phone":"+1 318 387 6839",
    "sg:postcode":"71202",
    "sg:province":"LA",
    "wof:name":"St Mary Mssonary Baptst Church",
    "wof:placetype":"venue"
},
  "geometry": {"coordinates":[-92.0949,32.49581],"type":"Point"}
}