{
  "type": "Feature",
  "properties": {
    "iso:country":"US",
    "sg:address":"14841 Bluff Creek Dr",
    "sg:city":"Baker",
    "sg:classifiers":[
        {
            "category":"Freight",
            "type":"Transportation"
        }
    ],
    "sg:phone":"+1 225 775 1695",
    "sg:postcode":"70714",
    "sg:province":"LA",
    "sg:tags":[
        "operator",
        "trucking"
    ],
    "wof:name":"Michael S Pualk",
    "wof:placetype":"venue"
},
  "geometry": {"coordinates":[-91.121156,30.581234],"type":"Point"}
}