{
  "type": "Feature",
  "properties": {
    "addr:full":"5349 Choctaw Dr Baton Rouge LA 70805",
    "addr:housenumber":"5349",
    "addr:postcode":"70805",
    "addr:street":"Choctaw Dr",
    "iso:country":"US",
    "sg:address":"5349 Choctaw Dr",
    "sg:city":"Baton Rouge",
    "sg:classifiers":[
        {
            "category":"Retail",
            "subcategory":"Auto Repair",
            "type":"Services"
        }
    ],
    "sg:phone":"+1 225 355 7200",
    "sg:postcode":"70805",
    "sg:province":"LA",
    "sg:tags":[
        "glass",
        "coating",
        "tinting"
    ],
    "wof:name":"Tint Doctor",
    "wof:placetype":"venue"
},
  "geometry": {"coordinates":[-91.137595,30.470756],"type":"Point"}
}