{
  "type": "Feature",
  "properties": {
    "addr:full":"555 N Parkview Pl Baton Rouge LA 70815",
    "addr:housenumber":"555",
    "addr:postcode":"70815",
    "addr:street":"N Parkview Pl",
    "iso:country":"US",
    "sg:address":"555 N Parkview Pl",
    "sg:city":"Baton Rouge",
    "sg:classifiers":[
        {
            "category":"Professional",
            "subcategory":"Business Services",
            "type":"Services"
        }
    ],
    "sg:phone":"+1 225 664 2321",
    "sg:postcode":"70815",
    "sg:province":"LA",
    "sg:tags":[
        "appraiser"
    ],
    "wof:name":"Property Damage Appraisers Inc",
    "wof:placetype":"venue"
},
  "geometry": {"coordinates":[-91.079621,30.448237],"type":"Point"}
}