{
  "type": "Feature",
  "properties": {
    "iso:country":"US",
    "sg:address":"213 Amanda Dr",
    "sg:city":"Lafayette",
    "sg:classifiers":[
        {
            "category":"Retail",
            "subcategory":"Car Wash",
            "type":"Services"
        }
    ],
    "sg:phone":"+1 337 235 3637",
    "sg:postcode":"70507",
    "sg:province":"LA",
    "wof:name":"Ronnie's Car Care Center",
    "wof:placetype":"venue"
},
  "geometry": {"coordinates":[-92.013578,30.288495],"type":"Point"}
}