{
  "type": "Feature",
  "properties": {
    "iso:country":"US",
    "sg:address":"9251 Mansfield Rd",
    "sg:city":"Shreveport",
    "sg:classifiers":[
        {
            "category":"Retail",
            "subcategory":"Auto Repair",
            "type":"Services"
        }
    ],
    "sg:phone":"+1 318 212 0198",
    "sg:postcode":"71118",
    "sg:province":"LA",
    "sg:tags":[
        "repairing",
        "automobile",
        "truck"
    ],
    "sg:website":"http://clickserve.dartsearch.net/link/click?lid=43000000313869391&ds_s_kwgid=58000000006820725&ds_e_matchtype={MatchType}&ds_e_kwdid={OrderItemId}&ds_e_adid={AdId}&ds_url_v=2",
    "wof:name":"Summer Grove Auto Care",
    "wof:placetype":"venue"
},
  "geometry": {"coordinates":[-93.805948,32.40004],"type":"Point"}
}