{
  "type": "Feature",
  "properties": {
    "addr:full":"4847 Revere Ave Baton Rouge LA 70808",
    "addr:housenumber":"4847",
    "addr:postcode":"70808",
    "addr:street":"Revere Ave",
    "iso:country":"US",
    "sg:address":"4847 Revere Ave",
    "sg:city":"Baton Rouge",
    "sg:classifiers":[
        {
            "category":"Organizations",
            "subcategory":"Non-profit Organization",
            "type":"Services"
        }
    ],
    "sg:phone":"+1 225 925 9041",
    "sg:postcode":"70808",
    "sg:province":"LA",
    "sg:website":"www.lmha.com",
    "wof:name":"Louisiana Manufactured Housing",
    "wof:placetype":"venue"
},
  "geometry": {"coordinates":[-91.137547,30.416783],"type":"Point"}
}