{
  "type": "Feature",
  "properties": {
    "iso:country":"US",
    "sg:address":"4821 Veterans Memorial Blvd",
    "sg:city":"Metairie",
    "sg:classifiers":[
        {
            "category":"Food & Beverages",
            "subcategory":"Bakery",
            "type":"Retail Goods"
        }
    ],
    "sg:phone":"+1 504 885 7500",
    "sg:postcode":"70006",
    "sg:province":"LA",
    "sg:tags":[
        "baker",
        "eating",
        "mfg"
    ],
    "wof:name":"Gambino's Bakeries Inc",
    "wof:placetype":"venue"
},
  "geometry": {"coordinates":[-90.192305,30.005895],"type":"Point"}
}