{
  "type": "Feature",
  "properties": {
    "addr:full":"307 Pecan Grove Rd Scott LA 70583",
    "addr:housenumber":"307",
    "addr:postcode":"70583",
    "addr:street":"Pecan Grove Rd",
    "iso:country":"US",
    "sg:address":"307 Pecan Grove Rd",
    "sg:city":"Scott",
    "sg:classifiers":[
        {
            "category":"Real Estate",
            "subcategory":"Real Estate Operator",
            "type":"Services"
        }
    ],
    "sg:phone":"+1 337 233 3614",
    "sg:postcode":"70583",
    "sg:province":"LA",
    "sg:tags":[
        "mobile",
        "home",
        "site"
    ],
    "wof:name":"G & R Mobile Park",
    "wof:placetype":"venue"
},
  "geometry": {"coordinates":[-92.07199799999999,30.235681],"type":"Point"}
}