{
  "type": "Feature",
  "properties": {
    "iso:country":"US",
    "sg:address":"1112 US Hwy 90",
    "sg:city":"New Iberia",
    "sg:classifiers":[
        {
            "category":"Home & Garden",
            "subcategory":"Mobile Homes",
            "type":"Retail Goods"
        }
    ],
    "sg:phone":"+1 337 364 1863",
    "sg:postcode":"70560",
    "sg:province":"LA",
    "wof:name":"American Homestar Mortgage",
    "wof:placetype":"venue"
},
  "geometry": {"coordinates":[-91.840197,29.970385],"type":"Point"}
}