{
  "type": "Feature",
  "properties": {
    "addr:full":"174 Sunset Strip Sunset LA 70584",
    "addr:housenumber":"174",
    "addr:postcode":"70584",
    "addr:street":"Sunset Strip",
    "iso:country":"US",
    "sg:address":"174 Sunset Strip",
    "sg:city":"Sunset",
    "sg:classifiers":[
        {
            "category":"Government",
            "subcategory":"Office",
            "type":"Public Place"
        }
    ],
    "sg:phone":"+1 337 662 3235",
    "sg:postcode":"70584",
    "sg:province":"LA",
    "sg:tags":[
        "county",
        "resource"
    ],
    "wof:name":"St Landry Parish Aging Council",
    "wof:placetype":"venue"
},
  "geometry": {"coordinates":[-92.071747,30.411725],"type":"Point"}
}