{
  "type": "Feature",
  "properties": {
    "iso:country":"US",
    "sg:address":"7802 State Rte 182",
    "sg:city":"Morgan City",
    "sg:classifiers":[
        {
            "category":"Restaurant",
            "type":"Food & Drink"
        }
    ],
    "sg:phone":"+1 985 384 6828",
    "sg:postcode":"70380",
    "sg:province":"LA",
    "wof:name":"Bingo's Seafood",
    "wof:placetype":"venue"
},
  "geometry": {"coordinates":[-91.174459,29.693189],"type":"Point"}
}