{
  "type": "Feature",
  "properties": {
    "iso:country":"US",
    "sg:address":"439 Brenda Dr",
    "sg:city":"Denham Springs",
    "sg:classifiers":[
        {
            "category":"Shopping",
            "subcategory":"Beauty & Cosmetics",
            "type":"Retail Goods"
        }
    ],
    "sg:phone":"+1 225 665 4501",
    "sg:postcode":"70726",
    "sg:province":"LA",
    "sg:tags":[
        "merchandise"
    ],
    "wof:name":"Mary Kay Cosmetics",
    "wof:placetype":"venue"
},
  "geometry": {"coordinates":[-90.946247,30.502255],"type":"Point"}
}