{
  "type": "Feature",
  "properties": {
    "iso:country":"US",
    "sg:address":"1137 US Hwy 171",
    "sg:city":"Stonewall",
    "sg:classifiers":[
        {
            "category":"Retail",
            "subcategory":"Portrait Studio",
            "type":"Services"
        }
    ],
    "sg:phone":"+1 318 925 3533",
    "sg:postcode":"71078",
    "sg:province":"LA",
    "sg:tags":[
        "photographer"
    ],
    "wof:name":"Rachelle Photography",
    "wof:placetype":"venue"
},
  "geometry": {"coordinates":[-93.819203,32.272752],"type":"Point"}
}