{
  "type": "Feature",
  "properties": {
    "iso:country":"US",
    "sg:address":"6411 Masonic Dr",
    "sg:city":"Alexandria",
    "sg:classifiers":[
        {
            "category":"Banks & Credit Unions",
            "subcategory":"Investment Brokerage",
            "type":"Services"
        }
    ],
    "sg:phone":"+1 318 448 0979",
    "sg:postcode":"71301",
    "sg:province":"LA",
    "sg:tags":[
        "merger",
        "acquisition"
    ],
    "wof:name":"National Acquisition Group Inc",
    "wof:placetype":"venue"
},
  "geometry": {"coordinates":[-92.48244200000001,31.250194],"type":"Point"}
}