{
  "type": "Feature",
  "properties": {
    "iso:country":"US",
    "sg:address":"900 North Blvd",
    "sg:city":"Baton Rouge",
    "sg:classifiers":[
        {
            "category":"Professional",
            "subcategory":"Lawyer & Legal Services",
            "type":"Services"
        }
    ],
    "sg:phone":"+1 225 383 9703",
    "sg:postcode":"70802",
    "sg:province":"LA",
    "sg:tags":[
        "attorney"
    ],
    "sg:website":"www.manassehandgillplc.com",
    "wof:name":"Manasseh Gill Joubert",
    "wof:placetype":"venue"
},
  "geometry": {"coordinates":[-91.180509,30.447166],"type":"Point"}
}