{
  "type": "Feature",
  "properties": {
    "addr:full":"1520 Haring Rd Metairie LA 70001",
    "addr:housenumber":"1520",
    "addr:postcode":"70001",
    "addr:street":"Haring Rd",
    "iso:country":"US",
    "sg:address":"1520 Haring Rd",
    "sg:city":"Metairie",
    "sg:classifiers":[
        {
            "category":"Professional",
            "subcategory":"Business Services",
            "type":"Services"
        }
    ],
    "sg:phone":"+1 504 887 8874",
    "sg:postcode":"70001",
    "sg:province":"LA",
    "sg:tags":[
        "interior",
        "designer"
    ],
    "wof:name":"James Anthony W Dsign Cnslting",
    "wof:placetype":"venue"
},
  "geometry": {"coordinates":[-90.19323300000001,29.986913],"type":"Point"}
}