{
  "type": "Feature",
  "properties": {
    "iso:country":"US",
    "sg:address":"2659 N Causeway Blvd",
    "sg:city":"Mandeville",
    "sg:classifiers":[
        {
            "category":"Health Services",
            "subcategory":"Nursing And Care Facility",
            "type":"Services"
        }
    ],
    "sg:phone":"+1 985 871 9272",
    "sg:postcode":"70471",
    "sg:province":"LA",
    "sg:tags":[
        "hospice"
    ],
    "wof:name":"Lakeshore Hospice",
    "wof:placetype":"venue"
},
  "geometry": {"coordinates":[-90.089164,30.3905],"type":"Point"}
}