{
  "type": "Feature",
  "properties": {
    "iso:country":"US",
    "sg:address":"332 River Oaks Dr",
    "sg:city":"Destrehan",
    "sg:classifiers":[
        {
            "category":"Professional",
            "type":"Services"
        }
    ],
    "sg:phone":"+1 985 764 8989",
    "sg:postcode":"70047",
    "sg:province":"LA",
    "sg:tags":[
        "establishment"
    ],
    "wof:name":"Affirmative Solutions",
    "wof:placetype":"venue"
},
  "geometry": {"coordinates":[-90.37876300000001,29.953787],"type":"Point"}
}