{
  "type": "Feature",
  "properties": {
    "addr:full":"5557 Government St Baton Rouge LA 70806",
    "addr:housenumber":"5557",
    "addr:postcode":"70806",
    "addr:street":"Government St",
    "iso:country":"US",
    "sg:address":"5557 Government St",
    "sg:city":"Baton Rouge",
    "sg:classifiers":[
        {
            "category":"Personal",
            "subcategory":"Beauty Salon",
            "type":"Services"
        }
    ],
    "sg:phone":"+1 225 926 2112",
    "sg:postcode":"70806",
    "sg:province":"LA",
    "sg:tags":[
        "spa",
        "day"
    ],
    "wof:name":"Sanctuary Spa",
    "wof:placetype":"venue"
},
  "geometry": {"coordinates":[-91.132096,30.444738],"type":"Point"}
}