{
  "type": "Feature",
  "properties": {
    "addr:full":"462 E 70th St Shreveport LA 71106",
    "addr:housenumber":"462",
    "addr:postcode":"71106",
    "addr:street":"E 70Th St",
    "iso:country":"US",
    "sg:address":"462 E 70th St",
    "sg:city":"Shreveport",
    "sg:classifiers":[
        {
            "category":"Professional",
            "subcategory":"Detective & Security Services",
            "type":"Services"
        }
    ],
    "sg:phone":"+1 318 861 1339",
    "sg:postcode":"71106",
    "sg:province":"LA",
    "sg:tags":[
        "investigator"
    ],
    "wof:name":"CID Investigative & Srvllnc",
    "wof:placetype":"venue"
},
  "geometry": {"coordinates":[-93.749251,32.441925],"type":"Point"}
}