{
  "type": "Feature",
  "properties": {
    "addr:full":"1546 4th St Jonesville LA 71343",
    "addr:housenumber":"1546",
    "addr:postcode":"71343",
    "addr:street":"4Th St",
    "iso:country":"US",
    "sg:address":"1546 4th St",
    "sg:city":"Jonesville",
    "sg:classifiers":[
        {
            "category":"Retail",
            "subcategory":"Auto Repair",
            "type":"Services"
        }
    ],
    "sg:phone":"+1 318 339 6005",
    "sg:postcode":"71343",
    "sg:province":"LA",
    "sg:tags":[
        "automobile",
        "lubrication"
    ],
    "wof:name":"Jonesville Oil & Detail Ctr",
    "wof:placetype":"venue"
},
  "geometry": {"coordinates":[-91.82796,31.629464],"type":"Point"}
}