{
  "type": "Feature",
  "properties": {
    "addr:full":"3406 College St Jackson LA 70748",
    "addr:housenumber":"3406",
    "addr:postcode":"70748",
    "addr:street":"College St",
    "iso:country":"US",
    "sg:address":"3406 College St",
    "sg:city":"Jackson",
    "sg:classifiers":[
        {
            "category":"Social Services",
            "type":"Services"
        }
    ],
    "sg:phone":"+1 225 634 5040",
    "sg:postcode":"70748",
    "sg:province":"LA",
    "sg:tags":[
        "probation"
    ],
    "wof:name":"East Feliciana Probation Ofc",
    "wof:placetype":"venue"
},
  "geometry": {"coordinates":[-91.213414,30.840246],"type":"Point"}
}