{
  "type": "Feature",
  "properties": {
    "addr:full":"225 Morgan St New Orleans LA 70114",
    "addr:housenumber":"225",
    "addr:postcode":"70114",
    "addr:street":"Morgan St",
    "iso:country":"US",
    "sg:address":"225 Morgan St",
    "sg:city":"New Orleans",
    "sg:classifiers":[
        {
            "category":"Government",
            "subcategory":"Court House",
            "type":"Public Place"
        }
    ],
    "sg:phone":"+1 504 364 4060",
    "sg:postcode":"70114",
    "sg:province":"LA",
    "sg:tags":[
        "city"
    ],
    "wof:name":"New Orleans Traffic Court",
    "wof:placetype":"venue"
},
  "geometry": {"coordinates":[-90.05386900000001,29.953958],"type":"Point"}
}