{
  "type": "Feature",
  "properties": {
    "iso:country":"US",
    "sg:address":"13653 Devall Rd",
    "sg:city":"Baton Rouge",
    "sg:classifiers":[
        {
            "category":"Building & Trades",
            "subcategory":"Construction",
            "type":"Services"
        }
    ],
    "sg:phone":"+1 225 262 1980",
    "sg:postcode":"70818",
    "sg:province":"LA",
    "sg:tags":[
        "roofing",
        "contractor"
    ],
    "wof:name":"Blanco Roofing",
    "wof:placetype":"venue"
},
  "geometry": {"coordinates":[-91.03246799999999,30.570591],"type":"Point"}
}