{
  "type": "Feature",
  "properties": {
    "iso:country":"US",
    "sg:address":"1749 Bertrand Dr",
    "sg:city":"Lafayette",
    "sg:classifiers":[
        {
            "category":"Professional",
            "type":"Services"
        }
    ],
    "sg:phone":"+1 337 289 1671",
    "sg:postcode":"70506",
    "sg:province":"LA",
    "sg:tags":[
        "establishment"
    ],
    "wof:name":"KTD",
    "wof:placetype":"venue"
},
  "geometry": {"coordinates":[-92.05825,30.225806],"type":"Point"}
}