{
  "type": "Feature",
  "properties": {
    "addr:full":"1347 Rue Desiree Baton Rouge LA 70810",
    "addr:housenumber":"1347",
    "addr:postcode":"70810",
    "addr:street":"Rue Desiree",
    "iso:country":"US",
    "sg:address":"1347 Rue Desiree",
    "sg:city":"Baton Rouge",
    "sg:classifiers":[
        {
            "category":"Building & Trades",
            "subcategory":"Plumbing",
            "type":"Services"
        }
    ],
    "sg:phone":"+1 225 766 3065",
    "sg:postcode":"70810",
    "sg:province":"LA",
    "sg:tags":[
        "conditioning",
        "air",
        "system",
        "contractor"
    ],
    "wof:name":"Pro Temp Svc Inc",
    "wof:placetype":"venue"
},
  "geometry": {"coordinates":[-91.091555,30.36703],"type":"Point"}
}