{
  "type": "Feature",
  "properties": {
    "addr:full":"315 Convention St Baton Rouge LA 70801",
    "addr:housenumber":"315",
    "addr:postcode":"70801",
    "addr:street":"Convention St",
    "iso:country":"US",
    "sg:address":"315 Convention St",
    "sg:city":"Baton Rouge",
    "sg:classifiers":[
        {
            "category":"Organizations",
            "subcategory":"Community Association",
            "type":"Services"
        }
    ],
    "sg:phone":"+1 225 344 7658",
    "sg:postcode":"70801",
    "sg:province":"LA",
    "sg:tags":[
        "fraternal"
    ],
    "wof:name":"Masonic Lodge",
    "wof:placetype":"venue"
},
  "geometry": {"coordinates":[-91.18716499999999,30.448354],"type":"Point"}
}