{
  "type": "Feature",
  "properties": {
    "addr:full":"1113 Aurora Ave Metairie LA 70005",
    "addr:housenumber":"1113",
    "addr:postcode":"70005",
    "addr:street":"Aurora Ave",
    "iso:country":"US",
    "sg:address":"1113 Aurora Ave",
    "sg:city":"Metairie",
    "sg:classifiers":[
        {
            "category":"Professional",
            "subcategory":"Business Services",
            "type":"Services"
        }
    ],
    "sg:phone":"+1 504 834 8464",
    "sg:postcode":"70005",
    "sg:province":"LA",
    "sg:tags":[
        "interior",
        "designer"
    ],
    "wof:name":"Frank Gambino Interiors",
    "wof:placetype":"venue"
},
  "geometry": {"coordinates":[-90.13964900000001,30.010909],"type":"Point"}
}