{
  "type": "Feature",
  "properties": {
    "iso:country":"US",
    "sg:address":"35024 Highway 30",
    "sg:city":"Geismar",
    "sg:classifiers":[
        {
            "category":"Building & Trades",
            "subcategory":"Construction",
            "type":"Services"
        }
    ],
    "sg:phone":"+1 225 673 2293",
    "sg:postcode":"70734",
    "sg:province":"LA",
    "sg:tags":[
        "contractor"
    ],
    "wof:name":"S & B Engineers & Construction",
    "wof:placetype":"venue"
},
  "geometry": {"coordinates":[-91.047997,30.2414],"type":"Point"}
}