{
  "type": "Feature",
  "properties": {
    "addr:full":"800 Sterlington Rd Monroe LA 71203",
    "addr:housenumber":"800",
    "addr:postcode":"71203",
    "addr:street":"Sterlington Rd",
    "iso:country":"US",
    "sg:address":"800 Sterlington Rd",
    "sg:city":"Monroe",
    "sg:classifiers":[
        {
            "category":"Banks & Credit Unions",
            "subcategory":"Bank",
            "type":"Services"
        }
    ],
    "sg:phone":"+1 318 329 2751",
    "sg:postcode":"71203",
    "sg:province":"LA",
    "wof:name":"Hibernia National Bank",
    "wof:placetype":"venue"
},
  "geometry": {"coordinates":[-92.08068900000001,32.52989],"type":"Point"}
}