{
  "type": "Feature",
  "properties": {
    "iso:country":"US",
    "sg:address":"3001 Willow Ln",
    "sg:city":"Madisonville",
    "sg:classifiers":[
        {
            "category":"Home & Garden",
            "subcategory":"Household Appliances",
            "type":"Retail Goods"
        }
    ],
    "sg:phone":"+1 504 731 7531",
    "sg:postcode":"70447",
    "sg:province":"LA",
    "wof:name":"Oreck Floor Care Center",
    "wof:placetype":"venue"
},
  "geometry": {"coordinates":[-90.17580700000001,30.439944],"type":"Point"}
}