{
  "type": "Feature",
  "properties": {
    "iso:country":"US",
    "sg:address":"1420 Greenlaw St",
    "sg:city":"Franklinton",
    "sg:classifiers":[
        {
            "category":"Retail",
            "subcategory":"Auto Repair",
            "type":"Services"
        }
    ],
    "sg:phone":"+1 985 839 3024",
    "sg:postcode":"70438",
    "sg:province":"LA",
    "sg:tags":[
        "repairing",
        "automobile"
    ],
    "wof:name":"Triple X Auto Parts & Svc",
    "wof:placetype":"venue"
},
  "geometry": {"coordinates":[-90.14926699999999,30.849455],"type":"Point"}
}