{
  "type": "Feature",
  "properties": {
    "addr:full":"7520 Old State Hwy 1 Addis LA 70710",
    "addr:housenumber":"7520",
    "addr:postcode":"70710",
    "addr:street":"Old State Hwy 1 Addis",
    "iso:country":"US",
    "sg:address":"7520 Old State Hwy 1",
    "sg:city":"Addis",
    "sg:classifiers":[
        {
            "category":"Building & Trades",
            "subcategory":"Electrical",
            "type":"Services"
        }
    ],
    "sg:phone":"+1 225 338 1522",
    "sg:postcode":"70710",
    "sg:province":"LA",
    "sg:tags":[
        "electric",
        "contractor"
    ],
    "wof:name":"Riley Electrical Supply Inc",
    "wof:placetype":"venue"
},
  "geometry": {"coordinates":[-91.264848,30.35821],"type":"Point"}
}