{
  "type": "Feature",
  "properties": {
    "iso:country":"US",
    "sg:address":"107 Emma St",
    "sg:city":"Houma",
    "sg:classifiers":[
        {
            "category":"Wholesale",
            "subcategory":"Machinery & Supplies",
            "type":"Manufacturing & Wholesale Goods"
        }
    ],
    "sg:phone":"+1 985 857 8356",
    "sg:postcode":"70363",
    "sg:province":"LA",
    "sg:tags":[
        "cleaning"
    ],
    "wof:name":"Cantrelle's Screening",
    "wof:placetype":"venue"
},
  "geometry": {"coordinates":[-90.702415,29.591372],"type":"Point"}
}