{
  "type": "Feature",
  "properties": {
    "addr:full":"1005 Roper Rd Scott LA 70583",
    "addr:housenumber":"1005",
    "addr:postcode":"70583",
    "addr:street":"Roper Rd",
    "iso:country":"US",
    "sg:address":"1005 Roper Rd",
    "sg:city":"Scott",
    "sg:classifiers":[
        {
            "category":"Retail",
            "subcategory":"Auto Repair",
            "type":"Services"
        }
    ],
    "sg:phone":"+1 337 235 1945",
    "sg:postcode":"70583",
    "sg:province":"LA",
    "sg:tags":[
        "repairing",
        "automobile"
    ],
    "wof:name":"Hebert's Automotive Repairs",
    "wof:placetype":"venue"
},
  "geometry": {"coordinates":[-92.059669,30.264147],"type":"Point"}
}