{
  "type": "Feature",
  "properties": {
    "addr:full":"3820 Magazine St New Orleans LA 70115",
    "addr:housenumber":"3820",
    "addr:postcode":"70115",
    "addr:street":"Magazine St",
    "iso:country":"US",
    "sg:address":"3820 Magazine St",
    "sg:city":"New Orleans",
    "sg:classifiers":[
        {
            "category":"Shopping",
            "type":"Retail Goods"
        }
    ],
    "sg:phone":"+1 504 891 2525",
    "sg:postcode":"70115",
    "sg:province":"LA",
    "sg:tags":[
        "merchandise"
    ],
    "wof:name":"D K Clay Inc",
    "wof:placetype":"venue"
},
  "geometry": {"coordinates":[-90.09479,29.921254],"type":"Point"}
}