{
  "type": "Feature",
  "properties": {
    "iso:country":"US",
    "sg:address":"213 Service Rd",
    "sg:city":"Rayne",
    "sg:classifiers":[
        {
            "category":"Autos & Motor Vehicles",
            "subcategory":"Auto Supplies",
            "type":"Retail Goods"
        }
    ],
    "sg:phone":"+1 337 334 0344",
    "sg:postcode":"70578",
    "sg:province":"LA",
    "sg:tags":[
        "equipment",
        "racing",
        "car",
        "automobile"
    ],
    "wof:name":"A 1 Speed & Accessories Inc",
    "wof:placetype":"venue"
},
  "geometry": {"coordinates":[-92.271708,30.252842],"type":"Point"}
}