{
  "type": "Feature",
  "properties": {
    "addr:full":"625 E Lincoln Rd Ville Platte LA 70586",
    "addr:housenumber":"625",
    "addr:postcode":"70586",
    "addr:street":"E Lincoln Rd",
    "iso:country":"US",
    "sg:address":"625 E Lincoln Rd",
    "sg:city":"Ville Platte",
    "sg:classifiers":[
        {
            "category":"Shopping",
            "subcategory":"Computers & Home Electronics",
            "type":"Retail Goods"
        }
    ],
    "sg:phone":"+1 337 363 0046",
    "sg:postcode":"70586",
    "sg:province":"LA",
    "sg:tags":[
        "equipment",
        "electronic",
        "supply"
    ],
    "wof:name":"Radio Shack",
    "wof:placetype":"venue"
},
  "geometry": {"coordinates":[-92.263662,30.693601],"type":"Point"}
}