{
  "type": "Feature",
  "properties": {
    "iso:country":"US",
    "sg:address":"900 McDonald Ave",
    "sg:city":"Ruston",
    "sg:classifiers":[
        {
            "category":"Social Services",
            "subcategory":"Child Care",
            "type":"Services"
        }
    ],
    "sg:phone":"+1 318 255 7082",
    "sg:postcode":"71270",
    "sg:province":"LA",
    "wof:name":"Candieland Day Care Ctr",
    "wof:placetype":"venue"
},
  "geometry": {"coordinates":[-92.62566,32.525692],"type":"Point"}
}