{
  "type": "Feature",
  "properties": {
    "addr:full":"10473 Lindsey Ln St Francisville LA 70775",
    "addr:housenumber":"10473",
    "addr:postcode":"70775",
    "addr:street":"Lindsey Ln St",
    "iso:country":"US",
    "sg:address":"10473 Lindsey Ln",
    "sg:city":"St Francisville",
    "sg:classifiers":[
        {
            "category":"Travel",
            "subcategory":"Hotels & Motels",
            "type":"Entertainment"
        }
    ],
    "sg:phone":"+1 225 635 3176",
    "sg:postcode":"70775",
    "sg:province":"LA",
    "sg:tags":[
        "breakfast",
        "accommodation",
        "bed"
    ],
    "sg:website":"www.lakerosemoundinn.com",
    "wof:name":"Lake Rosemound Inn",
    "wof:placetype":"venue"
},
  "geometry": {"coordinates":[-91.362793,30.98701],"type":"Point"}
}