{
  "type": "Feature",
  "properties": {
    "iso:country":"US",
    "sg:address":"301 Pacific Ave",
    "sg:city":"New Orleans",
    "sg:classifiers":[
        {
            "category":"Wholesale",
            "subcategory":"Medical Equipment & Supplies",
            "type":"Manufacturing & Wholesale Goods"
        }
    ],
    "sg:phone":"+1 504 263 2611",
    "sg:postcode":"70114",
    "sg:province":"LA",
    "sg:tags":[
        "hospital"
    ],
    "wof:name":"Tri-State Hospital Supply Corp",
    "wof:placetype":"venue"
},
  "geometry": {"coordinates":[-90.045923,29.951974],"type":"Point"}
}