{
  "type": "Feature",
  "properties": {
    "addr:full":"3432 Monroe Hwy Pineville LA 71360",
    "addr:housenumber":"3432",
    "addr:postcode":"71360",
    "addr:street":"Monroe Hwy",
    "iso:country":"US",
    "sg:address":"3432 Monroe Hwy",
    "sg:city":"Pineville",
    "sg:classifiers":[
        {
            "category":"Food & Beverages",
            "subcategory":"Groceries & Convenience Stores",
            "type":"Retail Goods"
        }
    ],
    "sg:phone":"+1 318 640 8846",
    "sg:postcode":"71360",
    "sg:province":"LA",
    "wof:name":"Circle K",
    "wof:placetype":"venue"
},
  "geometry": {"coordinates":[-92.411908,31.362931],"type":"Point"}
}