{
  "type": "Feature",
  "properties": {
    "iso:country":"US",
    "sg:address":"5598 Shreveport Hwy",
    "sg:city":"Pineville",
    "sg:classifiers":[
        {
            "category":"Food & Beverages",
            "subcategory":"Groceries & Convenience Stores",
            "type":"Retail Goods"
        }
    ],
    "sg:phone":"+1 318 641 0037",
    "sg:postcode":"71360",
    "sg:province":"LA",
    "wof:name":"Big Dubs Grocery",
    "wof:placetype":"venue"
},
  "geometry": {"coordinates":[-92.44255099999999,31.398204],"type":"Point"}
}