{
  "type": "Feature",
  "properties": {
    "iso:country":"US",
    "sg:address":"7006 Read Ln",
    "sg:city":"New Orleans",
    "sg:classifiers":[
        {
            "category":"Retail",
            "subcategory":"Veterinary Services",
            "type":"Services"
        }
    ],
    "sg:phone":"+1 504 242 4200",
    "sg:postcode":"70127",
    "sg:province":"LA",
    "sg:tags":[
        "veterinarian"
    ],
    "wof:name":"Gentilly Veterinary Hospital",
    "wof:placetype":"venue"
},
  "geometry": {"coordinates":[-89.97669399999999,30.039888],"type":"Point"}
}