{
  "type": "Feature",
  "properties": {
    "iso:country":"US",
    "sg:address":"4422 Airline Dr",
    "sg:city":"Metairie",
    "sg:classifiers":[
        {
            "category":"Home & Garden",
            "subcategory":"Building Materials",
            "type":"Retail Goods"
        }
    ],
    "sg:phone":"+1 504 836 0010",
    "sg:postcode":"70001",
    "sg:province":"LA",
    "sg:tags":[
        "glass",
        "window",
        "plate"
    ],
    "wof:name":"Glass Masters",
    "wof:placetype":"venue"
},
  "geometry": {"coordinates":[-90.176985,29.975247],"type":"Point"}
}