{
  "type": "Feature",
  "properties": {
    "iso:country":"US",
    "sg:address":"215 N Vine St",
    "sg:city":"Bastrop",
    "sg:classifiers":[
        {
            "category":"Shopping",
            "subcategory":"Gifts & Souvenirs",
            "type":"Retail Goods"
        }
    ],
    "sg:phone":"+1 318 283 2233",
    "sg:postcode":"71220",
    "sg:province":"LA",
    "sg:tags":[
        "shop"
    ],
    "wof:name":"New Beginning Christian Shop",
    "wof:placetype":"venue"
},
  "geometry": {"coordinates":[-91.91571399999999,32.779692],"type":"Point"}
}