{
  "type": "Feature",
  "properties": {
    "iso:country":"US",
    "sg:address":"740 Jordan St",
    "sg:city":"Shreveport",
    "sg:classifiers":[
        {
            "category":"Health Services",
            "subcategory":"Doctor",
            "type":"Services"
        }
    ],
    "sg:phone":"+1 318 424 9240",
    "sg:postcode":"71101",
    "sg:province":"LA",
    "sg:tags":[
        "physician",
        "surgeon"
    ],
    "wof:name":"Arthritis & Rheumatology",
    "wof:placetype":"venue"
},
  "geometry": {"coordinates":[-93.745947,32.498226],"type":"Point"}
}