{
  "type": "Feature",
  "properties": {
    "addr:full":"8736 Greenwell Springs Rd Baton Rouge LA 70814",
    "addr:housenumber":"8736",
    "addr:postcode":"70814",
    "addr:street":"Greenwell Springs Rd",
    "iso:country":"US",
    "sg:address":"8736 Greenwell Springs Rd",
    "sg:city":"Baton Rouge",
    "sg:classifiers":[
        {
            "category":"Retail",
            "subcategory":"Auto Repair",
            "type":"Services"
        }
    ],
    "sg:phone":"+1 225 925 2511",
    "sg:postcode":"70814",
    "sg:province":"LA",
    "sg:tags":[
        "repairing",
        "automobile"
    ],
    "wof:name":"John-T's Auto Repair",
    "wof:placetype":"venue"
},
  "geometry": {"coordinates":[-91.095484,30.481987],"type":"Point"}
}