{
  "type": "Feature",
  "properties": {
    "iso:country":"US",
    "sg:address":"404 Azalea Dr",
    "sg:city":"Westwego",
    "sg:classifiers":[
        {
            "category":"Government",
            "subcategory":"Fire Station",
            "type":"Public Place"
        }
    ],
    "sg:phone":"+1 504 431 7092",
    "sg:postcode":"70094",
    "sg:province":"LA",
    "sg:tags":[
        "department"
    ],
    "wof:name":"Live Oak Manor Volunteer Fire",
    "wof:placetype":"venue"
},
  "geometry": {"coordinates":[-90.23977499999999,29.948624],"type":"Point"}
}