{
  "type": "Feature",
  "properties": {
    "iso:country":"US",
    "sg:address":"719 East St",
    "sg:city":"Minden",
    "sg:classifiers":[
        {
            "category":"Organizations",
            "subcategory":"Religious Organization",
            "type":"Services"
        }
    ],
    "sg:phone":"+1 318 377 9974",
    "sg:postcode":"71055",
    "sg:province":"LA",
    "sg:tags":[
        "church"
    ],
    "wof:name":"Feltus Temple Church Of God",
    "wof:placetype":"venue"
},
  "geometry": {"coordinates":[-93.28460099999999,32.605736],"type":"Point"}
}