{
  "type": "Feature",
  "properties": {
    "iso:country":"US",
    "sg:address":"260 Alexander St",
    "sg:city":"Bossier City",
    "sg:classifiers":[
        {
            "category":"Retail",
            "subcategory":"Auto Repair",
            "type":"Services"
        }
    ],
    "sg:phone":"+1 318 929 2174",
    "sg:postcode":"71111",
    "sg:province":"LA",
    "sg:tags":[
        "repairing",
        "automobile"
    ],
    "wof:name":"Treadaway's Auto Supply & Rpr",
    "wof:placetype":"venue"
},
  "geometry": {"coordinates":[-93.737987,32.517585],"type":"Point"}
}