{
  "type": "Feature",
  "properties": {
    "iso:country":"US",
    "sg:address":"195 Strawberry St",
    "sg:city":"Slidell",
    "sg:classifiers":[
        {
            "category":"Wholesale",
            "subcategory":"Office Equipment",
            "type":"Manufacturing & Wholesale Goods"
        }
    ],
    "sg:phone":"+1 985 781 9376",
    "sg:postcode":"70460",
    "sg:province":"LA",
    "sg:tags":[
        "machine",
        "duplicating",
        "copying"
    ],
    "wof:name":"Xpress Imaging LLC",
    "wof:placetype":"venue"
},
  "geometry": {"coordinates":[-89.780232,30.290739],"type":"Point"}
}