{
  "type": "Feature",
  "properties": {
    "iso:country":"US",
    "sg:address":"102 Dolphus St",
    "sg:city":"Bastrop",
    "sg:classifiers":[
        {
            "category":"Restaurant",
            "type":"Food & Drink"
        }
    ],
    "sg:phone":"+1 318 281 6440",
    "sg:postcode":"71220",
    "sg:province":"LA",
    "wof:name":"O'Boy Bar B Que",
    "wof:placetype":"venue"
},
  "geometry": {"coordinates":[-91.93352400000001,32.77647],"type":"Point"}
}