{
  "type": "Feature",
  "properties": {
    "addr:full":"54078 Hwy 1062 Loranger LA 70446",
    "addr:housenumber":"54078",
    "addr:postcode":"1062;70446",
    "addr:street":"Hwy",
    "iso:country":"US",
    "sg:address":"54078 Hwy 1062",
    "sg:city":"Loranger",
    "sg:classifiers":[
        {
            "category":"Organizations",
            "subcategory":"Religious Organization",
            "type":"Services"
        }
    ],
    "sg:phone":"+1 985 878 4718",
    "sg:postcode":"70446",
    "sg:province":"LA",
    "sg:tags":[
        "church"
    ],
    "wof:name":"Loranger Baptist Church",
    "wof:placetype":"venue"
},
  "geometry": {"coordinates":[-90.398369,30.63902],"type":"Point"}
}