{
  "type": "Feature",
  "properties": {
    "iso:country":"US",
    "sg:address":"6026 Paris Ave",
    "sg:city":"New Orleans",
    "sg:classifiers":[
        {
            "category":"Education",
            "subcategory":"School",
            "type":"Public Place"
        }
    ],
    "sg:phone":"+1 504 286 2710",
    "sg:postcode":"70122",
    "sg:province":"LA",
    "wof:name":"H C Schaumburg Elem School",
    "wof:placetype":"venue"
},
  "geometry": {"coordinates":[-90.07555000000001,30.019524],"type":"Point"}
}