{
  "type": "Feature",
  "properties": {
    "iso:country":"US",
    "sg:address":"1695 Tara Blvd",
    "sg:city":"Baton Rouge",
    "sg:classifiers":[
        {
            "category":"Organizations",
            "subcategory":"Community Association",
            "type":"Services"
        }
    ],
    "sg:phone":"+1 225 925 5552",
    "sg:postcode":"70806",
    "sg:province":"LA",
    "sg:tags":[
        "club"
    ],
    "wof:name":"Tara Club Office",
    "wof:placetype":"venue"
},
  "geometry": {"coordinates":[-91.091182,30.432293],"type":"Point"}
}