{
  "type": "Feature",
  "properties": {
    "addr:full":"749 Aurora Dr New Orleans LA 70131",
    "addr:housenumber":"749",
    "addr:postcode":"70131",
    "addr:street":"Aurora Dr",
    "iso:country":"US",
    "sg:address":"749 Aurora Dr",
    "sg:city":"New Orleans",
    "sg:classifiers":[
        {
            "category":"Banks & Credit Unions",
            "subcategory":"Investment Brokerage",
            "type":"Services"
        }
    ],
    "sg:phone":"+1 504 828 5887",
    "sg:postcode":"70131",
    "sg:province":"LA",
    "sg:tags":[
        "security"
    ],
    "wof:name":"Edward Jones Co",
    "wof:placetype":"venue"
},
  "geometry": {"coordinates":[-89.98820499999999,29.920375],"type":"Point"}
}