{
  "type": "Feature",
  "properties": {
    "iso:country":"US",
    "sg:address":"301 3rd St",
    "sg:city":"Bridge City",
    "sg:classifiers":[
        {
            "category":"Education",
            "subcategory":"School",
            "type":"Public Place"
        }
    ],
    "sg:phone":"+1 504 349 5473",
    "sg:postcode":"70094",
    "sg:province":"LA",
    "wof:name":"Bridge City Head Start",
    "wof:placetype":"venue"
},
  "geometry": {"coordinates":[-90.165008,29.933235],"type":"Point"}
}