{
  "type": "Feature",
  "properties": {
    "iso:country":"US",
    "sg:address":"10257 Boswell St",
    "sg:city":"Bastrop",
    "sg:classifiers":[
        {
            "category":"Personal",
            "subcategory":"Beauty Salon",
            "type":"Services"
        }
    ],
    "sg:phone":"+1 318 283 8321",
    "sg:postcode":"71220",
    "sg:province":"LA",
    "wof:name":"Shear Impressions",
    "wof:placetype":"venue"
},
  "geometry": {"coordinates":[-91.89212000000001,32.788528],"type":"Point"}
}