{
  "type": "Feature",
  "properties": {
    "iso:country":"US",
    "sg:address":"24985 Merchant Rd",
    "sg:city":"Denham Springs",
    "sg:classifiers":[
        {
            "category":"Organizations",
            "subcategory":"Religious Organization",
            "type":"Services"
        }
    ],
    "sg:phone":"+1 225 665 3560",
    "sg:postcode":"70726",
    "sg:province":"LA",
    "sg:tags":[
        "church"
    ],
    "wof:name":"Baton Rouge Friends Meeting",
    "wof:placetype":"venue"
},
  "geometry": {"coordinates":[-90.90580199999999,30.433737],"type":"Point"}
}