{
  "type": "Feature",
  "properties": {
    "addr:full":"282 Brick St Breaux Bridge LA 70517",
    "addr:housenumber":"282",
    "addr:postcode":"70517",
    "addr:street":"Brick St;Bridge",
    "iso:country":"US",
    "sg:address":"282 Brick St",
    "sg:city":"Breaux Bridge",
    "sg:classifiers":[
        {
            "category":"Education",
            "subcategory":"Special Training",
            "type":"Public Place"
        }
    ],
    "sg:phone":"+1 337 332 6636",
    "sg:postcode":"70517",
    "sg:province":"LA",
    "wof:name":"Southwest Safety Training",
    "wof:placetype":"venue"
},
  "geometry": {"coordinates":[-91.907566,30.276087],"type":"Point"}
}