{
  "type": "Feature",
  "properties": {
    "iso:country":"US",
    "sg:address":"2215 Worley Dr",
    "sg:city":"Alexandria",
    "sg:classifiers":[
        {
            "category":"Shopping",
            "subcategory":"Used Merchandise",
            "type":"Retail Goods"
        }
    ],
    "sg:phone":"+1 318 445 3305",
    "sg:postcode":"71301",
    "sg:province":"LA",
    "sg:tags":[
        "book",
        "rare",
        "dealer"
    ],
    "wof:name":"Book Inn",
    "wof:placetype":"venue"
},
  "geometry": {"coordinates":[-92.46491,31.276093],"type":"Point"}
}