{
  "type": "Feature",
  "properties": {
    "iso:country":"US",
    "sg:address":"8680 Bluebonnet Blvd",
    "sg:city":"Baton Rouge",
    "sg:classifiers":[
        {
            "category":"Professional",
            "subcategory":"Management & Consulting",
            "type":"Services"
        }
    ],
    "sg:phone":"+1 225 767 7742",
    "sg:postcode":"70810",
    "sg:province":"LA",
    "sg:tags":[
        "consultant",
        "business"
    ],
    "wof:name":"Renaissance Executive Forums",
    "wof:placetype":"venue"
},
  "geometry": {"coordinates":[-91.101984,30.370751],"type":"Point"}
}