{
  "type": "Feature",
  "properties": {
    "iso:country":"US",
    "sg:address":"900 S College Rd",
    "sg:city":"Lafayette",
    "sg:classifiers":[
        {
            "category":"Real Estate",
            "subcategory":"Real Estate Agent",
            "type":"Services"
        }
    ],
    "sg:phone":"+1 337 267 4016",
    "sg:postcode":"70503",
    "sg:province":"LA",
    "wof:name":"Jeanette D Conrad",
    "wof:placetype":"venue"
},
  "geometry": {"coordinates":[-92.029647,30.201397],"type":"Point"}
}