{
  "type": "Feature",
  "properties": {
    "addr:full":"454 Heymann Blvd Lafayette LA 70503",
    "addr:housenumber":"454",
    "addr:postcode":"70503",
    "addr:street":"Heymann Blvd",
    "iso:country":"US",
    "sg:address":"454 Heymann Blvd",
    "sg:city":"Lafayette",
    "sg:classifiers":[
        {
            "category":"Food & Beverages",
            "subcategory":"Groceries & Convenience Stores",
            "type":"Retail Goods"
        }
    ],
    "sg:phone":"+1 337 235 4114",
    "sg:postcode":"70503",
    "sg:province":"LA",
    "sg:tags":[
        "grocer"
    ],
    "wof:name":"Champagnes Market",
    "wof:placetype":"venue"
},
  "geometry": {"coordinates":[-92.016254,30.203097],"type":"Point"}
}