{
  "type": "Feature",
  "properties": {
    "iso:country":"US",
    "sg:address":"14399 Hwy 21 S",
    "sg:city":"Bogalusa",
    "sg:classifiers":[
        {
            "category":"Retail",
            "subcategory":"Veterinary Services",
            "type":"Services"
        }
    ],
    "sg:phone":"+1 985 732 7460",
    "sg:postcode":"70427",
    "sg:province":"LA",
    "sg:tags":[
        "veterinarian"
    ],
    "wof:name":"Animal Medical Clinic",
    "wof:placetype":"venue"
},
  "geometry": {"coordinates":[-89.852238,30.731488],"type":"Point"}
}