{
  "type": "Feature",
  "properties": {
    "iso:country":"US",
    "sg:address":"504 N Main St",
    "sg:city":"Farmerville",
    "sg:classifiers":[
        {
            "category":"Banks & Credit Unions",
            "subcategory":"Investment Brokerage",
            "type":"Services"
        }
    ],
    "sg:phone":"+1 318 368 2421",
    "sg:postcode":"71241",
    "sg:province":"LA",
    "sg:tags":[
        "clothing",
        "commodity",
        "contract"
    ],
    "wof:name":"Ellawee Fashions",
    "wof:placetype":"venue"
},
  "geometry": {"coordinates":[-92.40536899999999,32.77791],"type":"Point"}
}