{
  "type": "Feature",
  "properties": {
    "iso:country":"US",
    "sg:address":"11868 Jefferson Hwy",
    "sg:city":"Baton Rouge",
    "sg:classifiers":[
        {
            "category":"Retail",
            "subcategory":"Auto Repair",
            "type":"Services"
        }
    ],
    "sg:phone":"+1 225 753 8473",
    "sg:postcode":"70816",
    "sg:province":"LA",
    "sg:tags":[
        "repairing",
        "automobile"
    ],
    "wof:name":"Jefferson Car Care",
    "wof:placetype":"venue"
},
  "geometry": {"coordinates":[-91.047769,30.395205],"type":"Point"}
}