{
  "type": "Feature",
  "properties": {
    "iso:country":"US",
    "sg:address":"101 Bocage Dr",
    "sg:city":"Donaldsonville",
    "sg:classifiers":[
        {
            "category":"Organizations",
            "subcategory":"Professional Association",
            "type":"Services"
        }
    ],
    "sg:phone":"+1 225 473 3789",
    "sg:postcode":"70346",
    "sg:province":"LA",
    "sg:tags":[
        "business",
        "trade"
    ],
    "wof:name":"Ascension Parish Council-Aging",
    "wof:placetype":"venue"
},
  "geometry": {"coordinates":[-91.003783,30.089616],"type":"Point"}
}