{
  "type": "Feature",
  "properties": {
    "iso:country":"US",
    "sg:address":"1401 Hwy 1183",
    "sg:city":"Simmesport",
    "sg:phone":"+1 318 941 2879",
    "sg:postcode":"71369",
    "sg:province":"LA",
    "sg:tags":[
        "farm",
        "soybean"
    ],
    "wof:name":"Edward Calliham",
    "wof:placetype":"venue"
},
  "geometry": {"coordinates":[-91.84269500000001,30.961135],"type":"Point"}
}