{
  "type": "Feature",
  "properties": {
    "iso:country":"US",
    "sg:address":"401 E Ridge Dr",
    "sg:city":"Pineville",
    "sg:classifiers":[
        {
            "category":"Building & Trades",
            "subcategory":"Construction",
            "type":"Services"
        }
    ],
    "sg:phone":"+1 318 484 2958",
    "sg:postcode":"71360",
    "sg:province":"LA",
    "sg:tags":[
        "painter"
    ],
    "wof:name":"JCE Paint Co",
    "wof:placetype":"venue"
},
  "geometry": {"coordinates":[-92.33147099999999,31.347328],"type":"Point"}
}