{
  "type": "Feature",
  "properties": {
    "addr:full":"3311 Mohican St Baton Rouge LA 70805",
    "addr:housenumber":"3311",
    "addr:postcode":"70805",
    "addr:street":"Mohican St",
    "iso:country":"US",
    "sg:address":"3311 Mohican St",
    "sg:city":"Baton Rouge",
    "sg:classifiers":[
        {
            "category":"Personal",
            "subcategory":"Beauty Salon",
            "type":"Services"
        }
    ],
    "sg:phone":"+1 225 357 9442",
    "sg:postcode":"70805",
    "sg:province":"LA",
    "wof:name":"Hair Boxx Unlimited",
    "wof:placetype":"venue"
},
  "geometry": {"coordinates":[-91.155406,30.484674],"type":"Point"}
}