{
  "type": "Feature",
  "properties": {
    "iso:country":"US",
    "sg:address":"11802 Cloverland Ave",
    "sg:city":"Baton Rouge",
    "sg:classifiers":[
        {
            "category":"Building & Trades",
            "subcategory":"Construction",
            "type":"Services"
        }
    ],
    "sg:phone":"+1 225 751 7503",
    "sg:postcode":"70809",
    "sg:province":"LA",
    "sg:tags":[
        "general",
        "contractor"
    ],
    "wof:name":"Fred R Matthews Gen Contractor",
    "wof:placetype":"venue"
},
  "geometry": {"coordinates":[-91.049763,30.390118],"type":"Point"}
}