{
  "type": "Feature",
  "properties": {
    "iso:country":"US",
    "sg:address":"21490 Koop Rd",
    "sg:city":"Mandeville",
    "sg:classifiers":[
        {
            "category":"Government",
            "subcategory":"Office",
            "type":"Public Place"
        }
    ],
    "sg:phone":"+1 985 898 2532",
    "sg:postcode":"70471",
    "sg:province":"LA",
    "wof:name":"St Tammany Parish Addressing",
    "wof:placetype":"venue"
},
  "geometry": {"coordinates":[-90.043965,30.41851],"type":"Point"}
}