{
  "type": "Feature",
  "properties": {
    "addr:full":"170 Remington Dr Mandeville LA 70448",
    "addr:housenumber":"170",
    "addr:postcode":"70448",
    "addr:street":"Remington Dr",
    "iso:country":"US",
    "sg:address":"170 Remington Dr",
    "sg:city":"Mandeville",
    "sg:classifiers":[
        {
            "category":"Communications",
            "type":"Services"
        }
    ],
    "sg:phone":"+1 985 727 4431",
    "sg:postcode":"70448",
    "sg:province":"LA",
    "sg:tags":[
        "communication"
    ],
    "wof:name":"Communication Application",
    "wof:placetype":"venue"
},
  "geometry": {"coordinates":[-90.052666,30.379328],"type":"Point"}
}