{
  "type": "Feature",
  "properties": {
    "addr:full":"934 E Napoleon St Sulphur LA 70663",
    "addr:housenumber":"934",
    "addr:postcode":"70663",
    "addr:street":"E Napoleon St",
    "iso:country":"US",
    "sg:address":"934 E Napoleon St",
    "sg:city":"Sulphur",
    "sg:classifiers":[
        {
            "category":"Food & Beverages",
            "subcategory":"Bakery",
            "type":"Retail Goods"
        }
    ],
    "sg:phone":"+1 337 527 3177",
    "sg:postcode":"70663",
    "sg:province":"LA",
    "sg:tags":[
        "doughnut"
    ],
    "wof:name":"Vee's Donuts",
    "wof:placetype":"venue"
},
  "geometry": {"coordinates":[-93.36744299999999,30.236734],"type":"Point"}
}