{
  "type": "Feature",
  "properties": {
    "addr:full":"322 Heymann Blvd Lafayette LA 70503",
    "addr:housenumber":"322",
    "addr:postcode":"70503",
    "addr:street":"Heymann Blvd",
    "iso:country":"US",
    "sg:address":"322 Heymann Blvd",
    "sg:city":"Lafayette",
    "sg:classifiers":[
        {
            "category":"Insurance",
            "subcategory":"Insurance Agent",
            "type":"Services"
        }
    ],
    "sg:phone":"+1 337 232 2200",
    "sg:postcode":"70503",
    "sg:province":"LA",
    "wof:name":"Equitable Life Assurance Soc",
    "wof:placetype":"venue"
},
  "geometry": {"coordinates":[-92.015444,30.204407],"type":"Point"}
}