{
  "type": "Feature",
  "properties": {
    "iso:country":"US",
    "sg:address":"126 Crip Ln",
    "sg:city":"Duson",
    "sg:classifiers":[
        {
            "category":"Professional",
            "subcategory":"Management & Consulting",
            "type":"Services"
        }
    ],
    "sg:phone":"+1 337 993 3643",
    "sg:postcode":"70529",
    "sg:province":"LA",
    "sg:tags":[
        "consultant",
        "automation"
    ],
    "wof:name":"Acadiana Measurement Control",
    "wof:placetype":"venue"
},
  "geometry": {"coordinates":[-92.13559100000001,30.183349],"type":"Point"}
}