{
  "type": "Feature",
  "properties": {
    "addr:full":"1200 Homer Rd Minden LA 71055",
    "addr:housenumber":"1200",
    "addr:postcode":"71055",
    "addr:street":"Homer Rd",
    "iso:country":"US",
    "sg:address":"1200 Homer Rd",
    "sg:city":"Minden",
    "sg:classifiers":[
        {
            "category":"Government",
            "subcategory":"Office",
            "type":"Public Place"
        }
    ],
    "sg:phone":"+1 318 371 3030",
    "sg:postcode":"71055",
    "sg:province":"LA",
    "wof:name":"Health Unit",
    "wof:placetype":"venue"
},
  "geometry": {"coordinates":[-93.25292899999999,32.624902],"type":"Point"}
}