{
  "type": "Feature",
  "properties": {
    "addr:full":"5710 Wright Rd New Orleans LA 70128",
    "addr:housenumber":"5710",
    "addr:postcode":"70128",
    "addr:street":"Wright Rd",
    "iso:country":"US",
    "sg:address":"5710 Wright Rd",
    "sg:city":"New Orleans",
    "sg:classifiers":[
        {
            "category":"Health Services",
            "subcategory":"Podiatrist",
            "type":"Services"
        }
    ],
    "sg:phone":"+1 504 242 1177",
    "sg:postcode":"70128",
    "sg:province":"LA",
    "wof:name":"For Feet Sake LLC",
    "wof:placetype":"venue"
},
  "geometry": {"coordinates":[-89.961889,30.034994],"type":"Point"}
}