{
  "type": "Feature",
  "properties": {
    "addr:full":"3945 Old Marksville Hwy Pineville LA 71360",
    "addr:housenumber":"3945",
    "addr:postcode":"71360",
    "addr:street":"Old Marksville Hwy",
    "iso:country":"US",
    "sg:address":"3945 Old Marksville Hwy",
    "sg:city":"Pineville",
    "sg:classifiers":[
        {
            "category":"Building & Trades",
            "subcategory":"Construction",
            "type":"Services"
        }
    ],
    "sg:phone":"+1 318 619 9439",
    "sg:postcode":"71360",
    "sg:province":"LA",
    "sg:tags":[
        "excavating",
        "contractor"
    ],
    "wof:name":"Bolton Backhoe Svc",
    "wof:placetype":"venue"
},
  "geometry": {"coordinates":[-92.33596300000001,31.296451],"type":"Point"}
}