{
  "type": "Feature",
  "properties": {
    "iso:country":"US",
    "sg:address":"2860 State Rte 3226",
    "sg:city":"Deridder",
    "sg:classifiers":[
        {
            "category":"Building & Trades",
            "subcategory":"Plumbing",
            "type":"Services"
        }
    ],
    "sg:phone":"+1 337 462 4899",
    "sg:postcode":"70653",
    "sg:province":"LA",
    "sg:tags":[
        "mechanic"
    ],
    "wof:name":"Scott Lemmon",
    "wof:placetype":"venue"
},
  "geometry": {"coordinates":[-93.353561,30.869239],"type":"Point"}
}