{
  "type": "Feature",
  "properties": {
    "iso:country":"US",
    "sg:address":"1909 Engineers Rd",
    "sg:city":"Belle Chasse",
    "sg:classifiers":[
        {
            "category":"Building & Trades",
            "subcategory":"Construction",
            "type":"Services"
        }
    ],
    "sg:phone":"+1 504 393 6359",
    "sg:postcode":"70037",
    "sg:province":"LA",
    "sg:tags":[
        "painter"
    ],
    "wof:name":"Delta Coatings Inc",
    "wof:placetype":"venue"
},
  "geometry": {"coordinates":[-90.020897,29.8578],"type":"Point"}
}