{
  "type": "Feature",
  "properties": {
    "addr:full":"1201 Burgundy St New Orleans LA 70116",
    "addr:housenumber":"1201",
    "addr:postcode":"70116",
    "addr:street":"Burgundy St",
    "iso:country":"US",
    "sg:address":"1201 Burgundy St",
    "sg:city":"New Orleans",
    "sg:classifiers":[
        {
            "category":"Bars & Pubs",
            "subcategory":"Nightclub",
            "type":"Food & Drink"
        }
    ],
    "sg:phone":"+1 504 522 9715",
    "sg:postcode":"70116",
    "sg:province":"LA",
    "sg:tags":[
        "nightlife"
    ],
    "wof:name":"Cosimo's",
    "wof:placetype":"venue"
},
  "geometry": {"coordinates":[-90.06390399999999,29.964001],"type":"Point"}
}