{
  "type": "Feature",
  "properties": {
    "iso:country":"US",
    "sg:address":"5101 Westwood Park Dr",
    "sg:city":"Shreveport",
    "sg:classifiers":[
        {
            "category":"Travel",
            "subcategory":"Hotels & Motels",
            "type":"Entertainment"
        }
    ],
    "sg:phone":"+1 318 631 2000",
    "sg:postcode":"71109",
    "sg:province":"LA",
    "wof:name":"Holiday Inn Express Shreveport",
    "wof:placetype":"venue"
},
  "geometry": {"coordinates":[-93.82569599999999,32.463585],"type":"Point"}
}