{
  "type": "Feature",
  "properties": {
    "addr:full":"81174 Jim Loyd Rd Folsom LA 70437",
    "addr:housenumber":"81174",
    "addr:postcode":"70437",
    "addr:street":"Jim Loyd Rd",
    "iso:country":"US",
    "sg:address":"81174 Jim Loyd Rd",
    "sg:city":"Folsom",
    "sg:classifiers":[
        {
            "category":"Professional",
            "subcategory":"Lawyer & Legal Services",
            "type":"Services"
        }
    ],
    "sg:phone":"+1 985 796 8710",
    "sg:postcode":"70437",
    "sg:province":"LA",
    "sg:tags":[
        "attorney"
    ],
    "wof:name":"John F Dillon",
    "wof:placetype":"venue"
},
  "geometry": {"coordinates":[-90.19846800000001,30.609375],"type":"Point"}
}