{
  "type": "Feature",
  "properties": {
    "iso:country":"US",
    "sg:address":"533 2nd St",
    "sg:city":"Natchitoches",
    "sg:classifiers":[
        {
            "category":"Organizations",
            "subcategory":"Religious Organization",
            "type":"Services"
        }
    ],
    "sg:phone":"+1 318 352 3110",
    "sg:postcode":"71457",
    "sg:province":"LA",
    "sg:tags":[
        "church"
    ],
    "wof:name":"Trinity Episcopal Daycare",
    "wof:placetype":"venue"
},
  "geometry": {"coordinates":[-93.08793,31.759807],"type":"Point"}
}