{
  "type": "Feature",
  "properties": {
    "iso:country":"US",
    "sg:address":"201 W Palmetto Ave",
    "sg:city":"Plain Dealing",
    "sg:phone":"+1 318 326 4756",
    "sg:postcode":"71064",
    "sg:province":"LA",
    "sg:tags":[
        "oil",
        "gasoline"
    ],
    "wof:name":"Curtis Allen Oil Inc",
    "wof:placetype":"venue"
},
  "geometry": {"coordinates":[-93.701638,32.905517],"type":"Point"}
}