{
  "type": "Feature",
  "properties": {
    "addr:full":"6660 Riverside Dr New Orleans LA 70123",
    "addr:housenumber":"6660",
    "addr:postcode":"70123",
    "addr:street":"Riverside Dr",
    "iso:country":"US",
    "sg:address":"6660 Riverside Dr",
    "sg:city":"New Orleans",
    "sg:classifiers":[
        {
            "category":"Health Services",
            "subcategory":"Health Practitioner",
            "type":"Services"
        }
    ],
    "sg:phone":"+1 504 780 7651",
    "sg:postcode":"70123",
    "sg:province":"LA",
    "sg:tags":[
        "psychologist"
    ],
    "wof:name":"Lynn Brayton",
    "wof:placetype":"venue"
},
  "geometry": {"coordinates":[-90.193428,29.933629],"type":"Point"}
}