{
  "type": "Feature",
  "properties": {
    "iso:country":"US",
    "sg:address":"7811 Airline Hwy",
    "sg:city":"Baton Rouge",
    "sg:classifiers":[
        {
            "category":"Autos & Motor Vehicles",
            "subcategory":"Automobile Sales",
            "type":"Retail Goods"
        }
    ],
    "sg:phone":"+1 225 924 6472",
    "sg:postcode":"70815",
    "sg:province":"LA",
    "sg:tags":[
        "car",
        "dealer"
    ],
    "wof:name":"Superior Pre-Owned Auto Sales",
    "wof:placetype":"venue"
},
  "geometry": {"coordinates":[-91.10649600000001,30.468149],"type":"Point"}
}