{
  "type": "Feature",
  "properties": {
    "iso:country":"US",
    "sg:address":"8471 Blake St",
    "sg:city":"Greenwood",
    "sg:classifiers":[
        {
            "category":"Professional",
            "subcategory":"Business Services",
            "type":"Services"
        }
    ],
    "sg:phone":"+1 318 938 8210",
    "sg:postcode":"71033",
    "sg:province":"LA",
    "wof:name":"Susan M Wolfe",
    "wof:placetype":"venue"
},
  "geometry": {"coordinates":[-93.949372,32.422158],"type":"Point"}
}