{
  "type": "Feature",
  "properties": {
    "iso:country":"US",
    "sg:address":"6618 Highland Rd",
    "sg:city":"Baton Rouge",
    "sg:classifiers":[
        {
            "category":"Professional",
            "type":"Services"
        }
    ],
    "sg:phone":"+1 225 769 9761",
    "sg:postcode":"70808",
    "sg:province":"LA",
    "wof:name":"Andrew J McPhate",
    "wof:placetype":"venue"
},
  "geometry": {"coordinates":[-91.145943,30.383544],"type":"Point"}
}