{
  "type": "Feature",
  "properties": {
    "addr:full":"5757 Corporate Blvd Baton Rouge LA 70808",
    "addr:housenumber":"5757",
    "addr:postcode":"70808",
    "addr:street":"Corporate Blvd",
    "iso:country":"US",
    "sg:address":"5757 Corporate Blvd",
    "sg:city":"Baton Rouge",
    "sg:classifiers":[
        {
            "category":"Professional",
            "subcategory":"Lawyer & Legal Services",
            "type":"Services"
        }
    ],
    "sg:phone":"+1 225 927 5495",
    "sg:postcode":"70808",
    "sg:province":"LA",
    "sg:tags":[
        "attorney"
    ],
    "wof:name":"LA Branche & Le Jeune",
    "wof:placetype":"venue"
},
  "geometry": {"coordinates":[-91.130572,30.425242],"type":"Point"}
}