{
  "type": "Feature",
  "properties": {
    "addr:full":"205 N Trenton St Ruston LA 71270",
    "addr:housenumber":"205",
    "addr:postcode":"71270",
    "addr:street":"N Trenton St",
    "iso:country":"US",
    "sg:address":"205 N Trenton St",
    "sg:city":"Ruston",
    "sg:classifiers":[
        {
            "category":"Shopping",
            "subcategory":"Clothing, Apparel, & Fashions",
            "type":"Retail Goods"
        }
    ],
    "sg:phone":"+1 318 251 3732",
    "sg:postcode":"71270",
    "sg:province":"LA",
    "wof:name":"Factory Connection",
    "wof:placetype":"venue"
},
  "geometry": {"coordinates":[-92.639127,32.530163],"type":"Point"}
}