{
  "type": "Feature",
  "properties": {
    "addr:full":"26720 Persimmon Rd Denham Springs LA 70726",
    "addr:housenumber":"26720",
    "addr:postcode":"70726",
    "addr:street":"Persimmon Rd",
    "iso:country":"US",
    "sg:address":"26720 Persimmon Rd",
    "sg:city":"Denham Springs",
    "sg:classifiers":[
        {
            "category":"Autos & Motor Vehicles",
            "subcategory":"Automobile Sales",
            "type":"Retail Goods"
        }
    ],
    "sg:phone":"+1 225 667 9166",
    "sg:postcode":"70726",
    "sg:province":"LA",
    "sg:tags":[
        "car",
        "dealer"
    ],
    "wof:name":"Brokash Motors",
    "wof:placetype":"venue"
},
  "geometry": {"coordinates":[-90.869928,30.454893],"type":"Point"}
}