{
  "type": "Feature",
  "properties": {
    "addr:full":"306 3rd St Kentwood LA 70444",
    "addr:housenumber":"306",
    "addr:postcode":"70444",
    "addr:street":"3Rd St",
    "iso:country":"US",
    "sg:address":"306 3rd St",
    "sg:city":"Kentwood",
    "sg:classifiers":[
        {
            "category":"Social Services",
            "subcategory":"Child Care",
            "type":"Services"
        }
    ],
    "sg:phone":"+1 985 229 4141",
    "sg:postcode":"70444",
    "sg:province":"LA",
    "sg:tags":[
        "kindergarten",
        "academic",
        "school"
    ],
    "wof:name":"New Hope Learning Ctr",
    "wof:placetype":"venue"
},
  "geometry": {"coordinates":[-90.508932,30.941625],"type":"Point"}
}