{
  "type": "Feature",
  "properties": {
    "iso:country":"US",
    "sg:address":"104 N 2nd St",
    "sg:city":"Eunice",
    "sg:classifiers":[
        {
            "category":"Health Services",
            "subcategory":"Chiropractor",
            "type":"Services"
        }
    ],
    "sg:phone":"+1 337 546 0143",
    "sg:postcode":"70535",
    "sg:province":"LA",
    "wof:name":"Le Jeune Chiropractic Clinic",
    "wof:placetype":"venue"
},
  "geometry": {"coordinates":[-92.416219,30.495874],"type":"Point"}
}