{
  "type": "Feature",
  "properties": {
    "iso:country":"US",
    "sg:address":"3101 Kentucky Ave",
    "sg:city":"Kenner",
    "sg:classifiers":[
        {
            "category":"Building & Trades",
            "subcategory":"Construction",
            "type":"Services"
        }
    ],
    "sg:phone":"+1 504 466 9604",
    "sg:postcode":"70065",
    "sg:province":"LA",
    "sg:tags":[
        "contractor"
    ],
    "wof:name":"Golden Painting & Remodeling",
    "wof:placetype":"venue"
},
  "geometry": {"coordinates":[-90.23299299999999,30.013778],"type":"Point"}
}