{
  "type": "Feature",
  "properties": {
    "iso:country":"US",
    "sg:address":"2630 Veterans Memorial Blvd",
    "sg:city":"Kenner",
    "sg:classifiers":[
        {
            "category":"Autos & Motor Vehicles",
            "subcategory":"Automobile Sales",
            "type":"Retail Goods"
        }
    ],
    "sg:phone":"+1 504 469 6165",
    "sg:postcode":"70062",
    "sg:province":"LA",
    "sg:tags":[
        "car",
        "dealer"
    ],
    "sg:website":"www.peakebmw.com",
    "wof:name":"Peake Bmw",
    "wof:placetype":"venue"
},
  "geometry": {"coordinates":[-90.23186099999999,30.006184],"type":"Point"}
}