{
  "type": "Feature",
  "properties": {
    "iso:country":"US",
    "sg:address":"365 N 4th St",
    "sg:city":"Baton Rouge",
    "sg:classifiers":[
        {
            "category":"Social Services",
            "type":"Services"
        }
    ],
    "sg:phone":"+1 225 383 7899",
    "sg:postcode":"70801",
    "sg:province":"LA",
    "sg:tags":[
        "organization",
        "welfare"
    ],
    "wof:name":"Best Buddies Intl Inc",
    "wof:placetype":"venue"
},
  "geometry": {"coordinates":[-91.18714300000001,30.449717],"type":"Point"}
}