{
  "type": "Feature",
  "properties": {
    "iso:country":"US",
    "sg:address":"259 Belle Terre Blvd",
    "sg:city":"La Place",
    "sg:classifiers":[
        {
            "category":"Professional",
            "subcategory":"Business Services",
            "type":"Services"
        }
    ],
    "sg:phone":"+1 985 653 8608",
    "sg:postcode":"70068",
    "sg:province":"LA",
    "sg:tags":[
        "sewing",
        "contractor"
    ],
    "wof:name":"Sewing Innovations",
    "wof:placetype":"venue"
},
  "geometry": {"coordinates":[-90.500885,30.074845],"type":"Point"}
}