{
  "type": "Feature",
  "properties": {
    "iso:country":"US",
    "sg:address":"2420 Music St",
    "sg:city":"New Orleans",
    "sg:classifiers":[
        {
            "category":"Retail",
            "subcategory":"Auto Repair",
            "type":"Services"
        }
    ],
    "sg:phone":"+1 504 947 8735",
    "sg:postcode":"70117",
    "sg:province":"LA",
    "sg:tags":[
        "wrecker"
    ],
    "wof:name":"Terry's Wrecker Svc",
    "wof:placetype":"venue"
},
  "geometry": {"coordinates":[-90.052183,29.982882],"type":"Point"}
}