{
  "type": "Feature",
  "properties": {
    "iso:country":"US",
    "sg:address":"2041 White Myrtle Dr",
    "sg:city":"Madisonville",
    "sg:classifiers":[
        {
            "category":"Building & Trades",
            "subcategory":"Construction",
            "type":"Services"
        }
    ],
    "sg:phone":"+1 985 792 1955",
    "sg:postcode":"70447",
    "sg:province":"LA",
    "sg:tags":[
        "contractor"
    ],
    "wof:name":"Exterior Stucco Finish",
    "wof:placetype":"venue"
},
  "geometry": {"coordinates":[-90.173012,30.440917],"type":"Point"}
}