{
  "type": "Feature",
  "properties": {
    "iso:country":"US",
    "sg:address":"21305 State Rte 77",
    "sg:city":"Grosse Tete",
    "sg:classifiers":[
        {
            "category":"Wholesale",
            "subcategory":"Meat",
            "type":"Manufacturing & Wholesale Goods"
        }
    ],
    "sg:phone":"+1 225 648 2551",
    "sg:postcode":"70740",
    "sg:province":"LA",
    "sg:tags":[
        "product"
    ],
    "wof:name":"Bayou's Edge Game Processing",
    "wof:placetype":"venue"
},
  "geometry": {"coordinates":[-91.398298,30.367873],"type":"Point"}
}