{
  "type": "Feature",
  "properties": {
    "iso:country":"US",
    "sg:address":"7436 Bult Rd",
    "sg:city":"Lake Charles",
    "sg:classifiers":[
        {
            "category":"Shopping",
            "subcategory":"Hobbies, Toys, & Games",
            "type":"Retail Goods"
        }
    ],
    "sg:phone":"+1 337 478 2082",
    "sg:postcode":"70607",
    "sg:province":"LA",
    "wof:name":"Kurts Welding Shop",
    "wof:placetype":"venue"
},
  "geometry": {"coordinates":[-93.19581700000001,30.127384],"type":"Point"}
}