{
  "type": "Feature",
  "properties": {
    "iso:country":"US",
    "sg:address":"1955 Surgi Dr",
    "sg:city":"Mandeville",
    "sg:classifiers":[
        {
            "category":"Retail",
            "subcategory":"Repair Shop",
            "type":"Services"
        }
    ],
    "sg:phone":"+1 985 951 8807",
    "sg:postcode":"70448",
    "sg:province":"LA",
    "sg:tags":[
        "equipment",
        "hydraulic"
    ],
    "wof:name":"Hydraulic Industries",
    "wof:placetype":"venue"
},
  "geometry": {"coordinates":[-90.046278,30.379006],"type":"Point"}
}