{
  "type": "Feature",
  "properties": {
    "iso:country":"US",
    "sg:address":"3798 Sloan Rd",
    "sg:city":"Mansfield",
    "sg:classifiers":[
        {
            "category":"Organizations",
            "subcategory":"Religious Organization",
            "type":"Services"
        }
    ],
    "sg:phone":"+1 318 872 6427",
    "sg:postcode":"71052",
    "sg:province":"LA",
    "sg:tags":[
        "church"
    ],
    "wof:name":"Trinity Missionary Baptist Chr",
    "wof:placetype":"venue"
},
  "geometry": {"coordinates":[-93.605363,32.136189],"type":"Point"}
}