{
  "type": "Feature",
  "properties": {
    "iso:country":"US",
    "sg:address":"307 Chisum St",
    "sg:city":"Sicily Island",
    "sg:classifiers":[
        {
            "category":"Health Services",
            "subcategory":"Doctor",
            "type":"Services"
        }
    ],
    "sg:phone":"+1 318 389 5727",
    "sg:postcode":"71368",
    "sg:province":"LA",
    "sg:tags":[
        "clinic"
    ],
    "wof:name":"Medical Center",
    "wof:placetype":"venue"
},
  "geometry": {"coordinates":[-91.662183,31.854193],"type":"Point"}
}