{
  "type": "Feature",
  "properties": {
    "iso:country":"US",
    "sg:address":"2810 Armand St",
    "sg:city":"Monroe",
    "sg:classifiers":[
        {
            "category":"Health Services",
            "subcategory":"Doctor",
            "type":"Services"
        }
    ],
    "sg:phone":"+1 318 322 5864",
    "sg:postcode":"71201",
    "sg:province":"LA",
    "sg:tags":[
        "physician",
        "surgeon"
    ],
    "wof:name":"Irby Pulmonary Clinic",
    "wof:placetype":"venue"
},
  "geometry": {"coordinates":[-92.092861,32.529047],"type":"Point"}
}