{
  "type": "Feature",
  "properties": {
    "iso:country":"US",
    "sg:address":"3060 Wimberly Dr",
    "sg:city":"Vinton",
    "sg:classifiers":[
        {
            "category":"Retail",
            "subcategory":"Auto Repair",
            "type":"Services"
        }
    ],
    "sg:phone":"+1 337 589 0446",
    "sg:postcode":"70668",
    "sg:province":"LA",
    "sg:tags":[
        "transmission"
    ],
    "wof:name":"Florida Gas Transmission",
    "wof:placetype":"venue"
},
  "geometry": {"coordinates":[-93.648583,30.183234],"type":"Point"}
}