{
  "type": "Feature",
  "properties": {
    "addr:full":"306 Chartres St New Orleans LA 70130",
    "addr:housenumber":"306",
    "addr:postcode":"70130",
    "addr:street":"Chartres St",
    "iso:country":"US",
    "sg:address":"306 Chartres St",
    "sg:city":"New Orleans",
    "sg:classifiers":[
        {
            "category":"Shopping",
            "subcategory":"Jewelry",
            "type":"Retail Goods"
        }
    ],
    "sg:phone":"+1 504 581 1348",
    "sg:postcode":"70130",
    "sg:province":"LA",
    "wof:name":"Earth Odyssey Llc",
    "wof:placetype":"venue"
},
  "geometry": {"coordinates":[-90.06647,29.954224],"type":"Point"}
}