{
  "type": "Feature",
  "properties": {
    "iso:country":"US",
    "sg:address":"5179 Plank Rd",
    "sg:city":"Baton Rouge",
    "sg:classifiers":[
        {
            "category":"Cafe",
            "type":"Food & Drink"
        }
    ],
    "sg:menulink":"http://www.allmenus.com/la/baton-rouge/234204-piccadilly-cafeteria/menu/",
    "sg:phone":"+1 225 355 4387",
    "sg:postcode":"70805",
    "sg:province":"LA",
    "sg:tags":[
        "american",
        "southwestern"
    ],
    "wof:name":"Piccadilly Cafeteria",
    "wof:placetype":"venue"
},
  "geometry": {"coordinates":[-91.15427200000001,30.496333],"type":"Point"}
}