{
  "type": "Feature",
  "properties": {
    "addr:full":"82286 Hwy 25 Folsom LA 70437",
    "addr:housenumber":"82286",
    "addr:postcode":"70437",
    "addr:street":"Hwy 25",
    "iso:country":"US",
    "sg:address":"82286 Hwy 25",
    "sg:city":"Folsom",
    "sg:classifiers":[
        {
            "category":"Autos & Motor Vehicles",
            "subcategory":"Auto Supplies",
            "type":"Retail Goods"
        }
    ],
    "sg:phone":"+1 985 796 0505",
    "sg:postcode":"70437",
    "sg:province":"LA",
    "sg:tags":[
        "automobile",
        "parts"
    ],
    "wof:name":"Southern Motor Sports",
    "wof:placetype":"venue"
},
  "geometry": {"coordinates":[-90.186849,30.627746],"type":"Point"}
}