{
  "type": "Feature",
  "properties": {
    "addr:full":"802 Julia St Rayville LA 71269",
    "addr:housenumber":"802",
    "addr:postcode":"71269",
    "addr:street":"Julia St",
    "iso:country":"US",
    "sg:address":"802 Julia St",
    "sg:city":"Rayville",
    "sg:classifiers":[
        {
            "category":"Professional",
            "subcategory":"Lawyer & Legal Services",
            "type":"Services"
        }
    ],
    "sg:phone":"+1 318 728 4413",
    "sg:postcode":"71269",
    "sg:province":"LA",
    "sg:tags":[
        "attorney"
    ],
    "wof:name":"Myrt T Hales Jr Law Office",
    "wof:placetype":"venue"
},
  "geometry": {"coordinates":[-91.758897,32.474525],"type":"Point"}
}