{
  "type": "Feature",
  "properties": {
    "addr:full":"762 Austin Pl Shreveport LA 71101",
    "addr:housenumber":"762",
    "addr:postcode":"71101",
    "addr:street":"Austin Pl",
    "iso:country":"US",
    "sg:address":"762 Austin Pl",
    "sg:city":"Shreveport",
    "sg:classifiers":[
        {
            "category":"Manufacturing",
            "subcategory":"Metals",
            "type":"Manufacturing & Wholesale Goods"
        }
    ],
    "sg:phone":"+1 318 425 4839",
    "sg:postcode":"71101",
    "sg:province":"LA",
    "sg:tags":[
        "tool"
    ],
    "wof:name":"Snap-On Tools",
    "wof:placetype":"venue"
},
  "geometry": {"coordinates":[-93.753271,32.505636],"type":"Point"}
}