{
  "type": "Feature",
  "properties": {
    "iso:country":"US",
    "sg:address":"930 Center St",
    "sg:city":"Lafayette",
    "sg:classifiers":[
        {
            "category":"Local Transit",
            "type":"Transportation"
        }
    ],
    "sg:phone":"+1 337 235 8976",
    "sg:postcode":"70501",
    "sg:province":"LA",
    "wof:name":"Acadiana Medical Svc",
    "wof:placetype":"venue"
},
  "geometry": {"coordinates":[-91.990477,30.238638],"type":"Point"}
}