{
  "type": "Feature",
  "properties": {
    "addr:full":"100 Park West Dr Scott LA 70583",
    "addr:housenumber":"100",
    "addr:postcode":"70583",
    "addr:street":"Park West Dr",
    "iso:country":"US",
    "sg:address":"100 Park West Dr",
    "sg:city":"Scott",
    "sg:classifiers":[
        {
            "category":"Building & Trades",
            "subcategory":"Equipment Rental",
            "type":"Services"
        }
    ],
    "sg:phone":"+1 337 233 4226",
    "sg:postcode":"70583",
    "sg:province":"LA",
    "sg:tags":[
        "tightening",
        "bolt"
    ],
    "wof:name":"Hydratight Sweeney Pdts Corp",
    "wof:placetype":"venue"
},
  "geometry": {"coordinates":[-92.10091799999999,30.244072],"type":"Point"}
}