{
  "type": "Feature",
  "properties": {
    "iso:country":"US",
    "sg:address":"2250 Gause Blvd E",
    "sg:city":"Slidell",
    "sg:classifiers":[
        {
            "category":"Shopping",
            "subcategory":"Computers & Home Electronics",
            "type":"Retail Goods"
        }
    ],
    "sg:phone":"+1 985 781 6606",
    "sg:postcode":"70461",
    "sg:province":"LA",
    "sg:tags":[
        "software"
    ],
    "wof:name":"CWS Group Inc",
    "wof:placetype":"venue"
},
  "geometry": {"coordinates":[-89.73622,30.28682],"type":"Point"}
}