{
  "type": "Feature",
  "properties": {
    "iso:country":"US",
    "sg:address":"37043 Geismar Dr",
    "sg:city":"Geismar",
    "sg:classifiers":[
        {
            "category":"Food & Beverages",
            "subcategory":"Groceries & Convenience Stores",
            "type":"Retail Goods"
        }
    ],
    "sg:phone":"+1 225 673 2922",
    "sg:postcode":"70734",
    "sg:province":"LA",
    "wof:name":"J & L Convenience Store",
    "wof:placetype":"venue"
},
  "geometry": {"coordinates":[-90.987748,30.242603],"type":"Point"}
}