{
  "type": "Feature",
  "properties": {
    "addr:full":"9742 State Rte 23 Belle Chasse LA 70037",
    "addr:housenumber":"9742",
    "addr:postcode":"70037",
    "addr:street":"State Rte 23",
    "iso:country":"US",
    "sg:address":"9742 State Rte 23",
    "sg:city":"Belle Chasse",
    "sg:classifiers":[
        {
            "category":"Manufacturing",
            "subcategory":"Tools & Machinery",
            "type":"Manufacturing & Wholesale Goods"
        }
    ],
    "sg:phone":"+1 504 398 1183",
    "sg:postcode":"70037",
    "sg:province":"LA",
    "sg:tags":[
        "machine",
        "shop"
    ],
    "wof:name":"BAC Enterprises",
    "wof:placetype":"venue"
},
  "geometry": {"coordinates":[-90.006563,29.821143],"type":"Point"}
}