{
  "type": "Feature",
  "properties": {
    "iso:country":"US",
    "sg:address":"3528 Youree Dr",
    "sg:city":"Shreveport",
    "sg:classifiers":[
        {
            "category":"Health Services",
            "subcategory":"Chiropractor",
            "type":"Services"
        }
    ],
    "sg:phone":"+1 318 865 4875",
    "sg:postcode":"71105",
    "sg:province":"LA",
    "wof:name":"Barksdale Chiropractic Clinic",
    "wof:placetype":"venue"
},
  "geometry": {"coordinates":[-93.72229400000001,32.47516],"type":"Point"}
}