{
  "type": "Feature",
  "properties": {
    "iso:country":"US",
    "sg:address":"9562 Bonneydune Dr",
    "sg:city":"Shreveport",
    "sg:classifiers":[
        {
            "category":"Building & Trades",
            "subcategory":"Plumbing",
            "type":"Services"
        }
    ],
    "sg:phone":"+1 318 687 9295",
    "sg:postcode":"71106",
    "sg:province":"LA",
    "sg:tags":[
        "tank",
        "septic"
    ],
    "wof:name":"T & T Construction",
    "wof:placetype":"venue"
},
  "geometry": {"coordinates":[-93.76075299999999,32.38502],"type":"Point"}
}