{
  "type": "Feature",
  "properties": {
    "iso:country":"US",
    "sg:address":"2101 Lafitte St",
    "sg:city":"New Orleans",
    "sg:classifiers":[
        {
            "category":"Real Estate",
            "subcategory":"Real Estate Agent",
            "type":"Services"
        }
    ],
    "sg:phone":"+1 504 822 5383",
    "sg:postcode":"70112",
    "sg:province":"LA",
    "sg:tags":[
        "authorities",
        "housing"
    ],
    "wof:name":"Lafitte Housing Development",
    "wof:placetype":"venue"
},
  "geometry": {"coordinates":[-90.07859999999999,29.966027],"type":"Point"}
}