{
  "type": "Feature",
  "properties": {
    "iso:country":"US",
    "sg:address":"7025 Pines Rd",
    "sg:city":"Shreveport",
    "sg:classifiers":[
        {
            "category":"Retail",
            "subcategory":"Veterinary Services",
            "type":"Services"
        }
    ],
    "sg:phone":"+1 318 688 0642",
    "sg:postcode":"71129",
    "sg:province":"LA",
    "sg:tags":[
        "veterinarian"
    ],
    "wof:name":"Companion Animal Medical Ctr",
    "wof:placetype":"venue"
},
  "geometry": {"coordinates":[-93.861746,32.441933],"type":"Point"}
}