{
  "type": "Feature",
  "properties": {
    "addr:full":"435 Failla Rd Lafayette LA 70508",
    "addr:housenumber":"435",
    "addr:postcode":"70508",
    "addr:street":"Failla Rd",
    "iso:country":"US",
    "sg:address":"435 Failla Rd",
    "sg:city":"Lafayette",
    "sg:classifiers":[
        {
            "category":"Retail",
            "subcategory":"Auto Repair",
            "type":"Services"
        }
    ],
    "sg:phone":"+1 337 984 5448",
    "sg:postcode":"70508",
    "sg:province":"LA",
    "sg:tags":[
        "repairing",
        "automobile"
    ],
    "wof:name":"Larry's Automotive",
    "wof:placetype":"venue"
},
  "geometry": {"coordinates":[-92.01636999999999,30.14888],"type":"Point"}
}