{
  "type": "Feature",
  "properties": {
    "addr:full":"1875 N Market St Shreveport LA 71107",
    "addr:housenumber":"1875",
    "addr:postcode":"71107",
    "addr:street":"N Market St",
    "iso:country":"US",
    "sg:address":"1875 N Market St",
    "sg:city":"Shreveport",
    "sg:classifiers":[
        {
            "category":"Autos & Motor Vehicles",
            "subcategory":"Auto Supplies",
            "type":"Retail Goods"
        }
    ],
    "sg:phone":"+1 318 227 1195",
    "sg:postcode":"71107",
    "sg:province":"LA",
    "sg:tags":[
        "automobile",
        "parts"
    ],
    "wof:name":"Autozone",
    "wof:placetype":"venue"
},
  "geometry": {"coordinates":[-93.773915,32.540431],"type":"Point"}
}