{
  "type": "Feature",
  "properties": {
    "addr:full":"5875 Main St Zachary LA 70791",
    "addr:housenumber":"5875",
    "addr:postcode":"70791",
    "addr:street":"Main St",
    "iso:country":"US",
    "sg:address":"5875 Main St",
    "sg:city":"Zachary",
    "sg:classifiers":[
        {
            "category":"Cinema",
            "subcategory":"Movie Rental",
            "type":"Entertainment"
        }
    ],
    "sg:phone":"+1 225 654 5758",
    "sg:postcode":"70791",
    "sg:province":"LA",
    "sg:tags":[
        "leasing",
        "video",
        "disc",
        "tape"
    ],
    "sg:website":"www.blockbuster.com",
    "wof:name":"Blockbuster Video",
    "wof:placetype":"venue"
},
  "geometry": {"coordinates":[-91.14173,30.649094],"type":"Point"}
}