{
  "type": "Feature",
  "properties": {
    "iso:country":"US",
    "sg:address":"105 Metairie Hammond Hwy",
    "sg:city":"Metairie",
    "sg:classifiers":[
        {
            "category":"Restaurant",
            "type":"Food & Drink"
        }
    ],
    "sg:menulink":"http://www.allmenus.com/la/metairie/235645-2-tonys-italian-restaurant-/menu/",
    "sg:phone":"+1 504 831 0999",
    "sg:postcode":"70005",
    "sg:province":"LA",
    "sg:tags":[
        "italian"
    ],
    "wof:name":"2 Tony's Italian Restaurant ",
    "wof:placetype":"venue"
},
  "geometry": {"coordinates":[-90.122028,30.020099],"type":"Point"}
}