{
  "type": "Feature",
  "properties": {
    "iso:country":"US",
    "sg:address":"1316 Lee St",
    "sg:city":"Minden",
    "sg:classifiers":[
        {
            "category":"Restaurant",
            "type":"Food & Drink"
        }
    ],
    "sg:phone":"+1 318 377 5370",
    "sg:postcode":"71055",
    "sg:province":"LA",
    "wof:name":"Golden Biscuit Restaurant",
    "wof:placetype":"venue"
},
  "geometry": {"coordinates":[-93.287541,32.597833],"type":"Point"}
}