{
  "type": "Feature",
  "properties": {
    "addr:full":"12850 Florida Blvd Baton Rouge LA 70815",
    "addr:housenumber":"12850",
    "addr:postcode":"70815",
    "addr:street":"Florida Blvd",
    "iso:country":"US",
    "sg:address":"12850 Florida Blvd",
    "sg:city":"Baton Rouge",
    "sg:classifiers":[
        {
            "category":"Freight",
            "type":"Transportation"
        }
    ],
    "sg:phone":"+1 225 272 5887",
    "sg:postcode":"70815",
    "sg:province":"LA",
    "sg:tags":[
        "commercial",
        "storage"
    ],
    "wof:name":"Sunbelt Mini-Storage",
    "wof:placetype":"venue"
},
  "geometry": {"coordinates":[-91.044158,30.461045],"type":"Point"}
}