{
  "type": "Feature",
  "properties": {
    "iso:country":"US",
    "sg:address":"1602 S 4th St",
    "sg:city":"Monroe",
    "sg:classifiers":[
        {
            "category":"Retail",
            "subcategory":"Repair Shop",
            "type":"Services"
        }
    ],
    "sg:phone":"+1 318 322 4371",
    "sg:postcode":"71202",
    "sg:province":"LA",
    "wof:name":"Northside Upholstery Inc",
    "wof:placetype":"venue"
},
  "geometry": {"coordinates":[-92.097335,32.483979],"type":"Point"}
}