{
  "type": "Feature",
  "properties": {
    "addr:full":"8700 Booker St Baton Rouge LA 70807",
    "addr:housenumber":"8700",
    "addr:postcode":"70807",
    "addr:street":"Booker St",
    "iso:country":"US",
    "sg:address":"8700 Booker St",
    "sg:city":"Baton Rouge",
    "sg:classifiers":[
        {
            "category":"Organizations",
            "subcategory":"Community Association",
            "type":"Services"
        }
    ],
    "sg:phone":"+1 225 775 1234",
    "sg:postcode":"70807",
    "sg:province":"LA",
    "sg:tags":[
        "fraternal"
    ],
    "wof:name":"Elks Lodge",
    "wof:placetype":"venue"
},
  "geometry": {"coordinates":[-91.18155899999999,30.526798],"type":"Point"}
}