{
  "type": "Feature",
  "properties": {
    "iso:country":"US",
    "sg:address":"603 Hwy 665",
    "sg:city":"Montegut",
    "sg:classifiers":[
        {
            "category":"Professional",
            "type":"Services"
        }
    ],
    "sg:phone":"+1 985 594 5632",
    "sg:postcode":"70377",
    "sg:province":"LA",
    "wof:name":"Cecil A Neal",
    "wof:placetype":"venue"
},
  "geometry": {"coordinates":[-90.53837900000001,29.505966],"type":"Point"}
}