{
  "type": "Feature",
  "properties": {
    "iso:country":"US",
    "sg:address":"824 Distributors Row",
    "sg:city":"Harahan",
    "sg:classifiers":[
        {
            "category":"Manufacturing",
            "subcategory":"Food",
            "type":"Manufacturing & Wholesale Goods"
        }
    ],
    "sg:phone":"+1 504 731 3500",
    "sg:postcode":"70123",
    "sg:province":"LA",
    "sg:tags":[
        "spice"
    ],
    "sg:website":"www.chefpaul.com",
    "wof:name":"Magic Seasoning Blends",
    "wof:placetype":"venue"
},
  "geometry": {"coordinates":[-90.18858899999999,29.953362],"type":"Point"}
}