{
  "type": "Feature",
  "properties": {
    "addr:full":"2414 S 5th St Leesville LA 71446",
    "addr:housenumber":"2414",
    "addr:postcode":"71446",
    "addr:street":"S 5Th St",
    "iso:country":"US",
    "sg:address":"2414 S 5th St",
    "sg:city":"Leesville",
    "sg:classifiers":[
        {
            "category":"Shopping",
            "subcategory":"Clothing, Apparel, & Fashions",
            "type":"Retail Goods"
        }
    ],
    "sg:phone":"+1 337 392 1008",
    "sg:postcode":"71446",
    "sg:province":"LA",
    "wof:name":"Cato",
    "wof:placetype":"venue"
},
  "geometry": {"coordinates":[-93.269473,31.119058],"type":"Point"}
}