{
  "type": "Feature",
  "properties": {
    "iso:country":"US",
    "sg:address":"1019 Baronne St",
    "sg:city":"New Orleans",
    "sg:classifiers":[
        {
            "category":"Retail",
            "subcategory":"Auto Rental",
            "type":"Services"
        }
    ],
    "sg:phone":"+1 504 593 9068",
    "sg:postcode":"70113",
    "sg:province":"LA",
    "sg:tags":[
        "renting",
        "automobile"
    ],
    "wof:name":"Enterprise Rent-A-Car",
    "wof:placetype":"venue"
},
  "geometry": {"coordinates":[-90.075371,29.944074],"type":"Point"}
}