{
  "type": "Feature",
  "properties": {
    "iso:country":"US",
    "sg:address":"630 Bayard St",
    "sg:city":"New Iberia",
    "sg:classifiers":[
        {
            "category":"Freight",
            "type":"Transportation"
        }
    ],
    "sg:phone":"+1 337 369 6225",
    "sg:postcode":"70560",
    "sg:province":"LA",
    "sg:tags":[
        "field",
        "oil",
        "hauling"
    ],
    "wof:name":"Truck-It",
    "wof:placetype":"venue"
},
  "geometry": {"coordinates":[-91.803298,29.980981],"type":"Point"}
}