{
  "type": "Feature",
  "properties": {
    "iso:country":"US",
    "sg:address":"2733 Eddie Williams Ave",
    "sg:city":"Alexandria",
    "sg:classifiers":[
        {
            "category":"Real Estate",
            "subcategory":"Developer",
            "type":"Services"
        }
    ],
    "sg:phone":"+1 318 445 8550",
    "sg:postcode":"71302",
    "sg:province":"LA",
    "sg:tags":[
        "cemetery"
    ],
    "wof:name":"Garden Of Memories",
    "wof:placetype":"venue"
},
  "geometry": {"coordinates":[-92.439897,31.285974],"type":"Point"}
}