{
  "type": "Feature",
  "properties": {
    "addr:full":"16385 Hwy 102 Jennings LA 70546",
    "addr:housenumber":"16385",
    "addr:postcode":"70546",
    "addr:street":"Hwy 102",
    "iso:country":"US",
    "sg:address":"16385 Hwy 102",
    "sg:city":"Jennings",
    "sg:classifiers":[
        {
            "category":"Food & Beverages",
            "subcategory":"Groceries & Convenience Stores",
            "type":"Retail Goods"
        }
    ],
    "sg:phone":"+1 337 824 6090",
    "sg:postcode":"70546",
    "sg:province":"LA",
    "wof:name":"Country Mile Store",
    "wof:placetype":"venue"
},
  "geometry": {"coordinates":[-92.65526300000001,30.264454],"type":"Point"}
}