{
  "type": "Feature",
  "properties": {
    "iso:country":"US",
    "sg:address":"23151 State Rte 20",
    "sg:city":"Vacherie",
    "sg:classifiers":[
        {
            "category":"Building & Trades",
            "subcategory":"Plumbing",
            "type":"Services"
        }
    ],
    "sg:phone":"+1 225 265 2450",
    "sg:postcode":"70090",
    "sg:province":"LA",
    "sg:tags":[
        "contractor"
    ],
    "wof:name":"Rodney Tabor Sr Plumbing",
    "wof:placetype":"venue"
},
  "geometry": {"coordinates":[-90.704403,29.941136],"type":"Point"}
}