{
  "type": "Feature",
  "properties": {
    "iso:country":"US",
    "sg:address":"4117 David Dr",
    "sg:city":"Metairie",
    "sg:classifiers":[
        {
            "category":"Building & Trades",
            "subcategory":"Construction",
            "type":"Services"
        }
    ],
    "sg:phone":"+1 504 889 1855",
    "sg:postcode":"70003",
    "sg:province":"LA",
    "sg:tags":[
        "house"
    ],
    "wof:name":"Mvp Remodeling",
    "wof:placetype":"venue"
},
  "geometry": {"coordinates":[-90.22557500000001,30.01852],"type":"Point"}
}