{
  "type": "Feature",
  "properties": {
    "addr:full":"8917 Jefferson Hwy New Orleans LA 70123",
    "addr:housenumber":"8917",
    "addr:postcode":"70123",
    "addr:street":"Jefferson Hwy",
    "iso:country":"US",
    "sg:address":"8917 Jefferson Hwy",
    "sg:city":"New Orleans",
    "sg:classifiers":[
        {
            "category":"Professional",
            "subcategory":"Lawyer & Legal Services",
            "type":"Services"
        }
    ],
    "sg:phone":"+1 504 737 3232",
    "sg:postcode":"70123",
    "sg:province":"LA",
    "sg:tags":[
        "attorney"
    ],
    "wof:name":"Vandenweghe Lawfirm",
    "wof:placetype":"venue"
},
  "geometry": {"coordinates":[-90.213178,29.9446],"type":"Point"}
}