{
  "type": "Feature",
  "properties": {
    "iso:country":"US",
    "sg:address":"1742 Stumpf Blvd",
    "sg:city":"Terrytown",
    "sg:classifiers":[
        {
            "category":"Shopping",
            "subcategory":"Clothing, Apparel, & Fashions",
            "type":"Retail Goods"
        }
    ],
    "sg:phone":"+1 504 366 6887",
    "sg:postcode":"70056",
    "sg:province":"LA",
    "sg:tags":[
        "children's",
        "clothing"
    ],
    "wof:name":"J & L Uniforms & Apparel",
    "wof:placetype":"venue"
},
  "geometry": {"coordinates":[-90.037598,29.911501],"type":"Point"}
}