{
  "type": "Feature",
  "properties": {
    "iso:country":"US",
    "sg:address":"3993 Pontchartrain Dr",
    "sg:city":"Slidell",
    "sg:classifiers":[
        {
            "category":"Shopping",
            "subcategory":"Gifts & Souvenirs",
            "type":"Retail Goods"
        }
    ],
    "sg:phone":"+1 985 781 1315",
    "sg:postcode":"70458",
    "sg:province":"LA",
    "sg:tags":[
        "shop"
    ],
    "wof:name":"Accessory Warehouse",
    "wof:placetype":"venue"
},
  "geometry": {"coordinates":[-89.791673,30.25161],"type":"Point"}
}