{
  "type": "Feature",
  "properties": {
    "addr:full":"3437 Prytania St New Orleans LA 70115",
    "addr:housenumber":"3437",
    "addr:postcode":"70115",
    "addr:street":"Prytania St",
    "iso:country":"US",
    "sg:address":"3437 Prytania St",
    "sg:city":"New Orleans",
    "sg:classifiers":[
        {
            "category":"Health Services",
            "subcategory":"Doctor",
            "type":"Services"
        }
    ],
    "sg:phone":"+1 504 883 5395",
    "sg:postcode":"70115",
    "sg:province":"LA",
    "sg:tags":[
        "physician",
        "surgeon",
        "radiology",
        "outpatient",
        "facility"
    ],
    "wof:name":"Diagnostic Imaging Services",
    "wof:placetype":"venue"
},
  "geometry": {"coordinates":[-90.09114,29.926886],"type":"Point"}
}