{
  "type": "Feature",
  "properties": {
    "iso:country":"US",
    "sg:address":"16718 Centurion Ave",
    "sg:city":"Baton Rouge",
    "sg:classifiers":[
        {
            "category":"Building & Trades",
            "subcategory":"Construction",
            "type":"Services"
        }
    ],
    "sg:phone":"+1 225 273 8978",
    "sg:postcode":"70816",
    "sg:province":"LA",
    "sg:tags":[
        "house"
    ],
    "wof:name":"Flemings & Flemings Constructi",
    "wof:placetype":"venue"
},
  "geometry": {"coordinates":[-91.00044200000001,30.452095],"type":"Point"}
}