{
  "type": "Feature",
  "properties": {
    "iso:country":"US",
    "sg:address":"2906 Neco Town Rd",
    "sg:city":"New Iberia",
    "sg:classifiers":[
        {
            "category":"Retail",
            "subcategory":"Animal Services",
            "type":"Services"
        }
    ],
    "sg:phone":"+1 337 367 7836",
    "sg:postcode":"70560",
    "sg:province":"LA",
    "wof:name":"Tammys Professional Grooming",
    "wof:placetype":"venue"
},
  "geometry": {"coordinates":[-91.783208,29.944337],"type":"Point"}
}