{
  "type": "Feature",
  "properties": {
    "addr:full":"780 E Port Hudson Plains Rd Zachary LA 70791",
    "addr:housenumber":"780",
    "addr:postcode":"70791",
    "addr:street":"E Port;Plains Rd",
    "iso:country":"US",
    "sg:address":"780 E Port Hudson Plains Rd",
    "sg:city":"Zachary",
    "sg:classifiers":[
        {
            "category":"Shopping",
            "subcategory":"Beauty & Cosmetics",
            "type":"Retail Goods"
        }
    ],
    "sg:phone":"+1 225 654 8424",
    "sg:postcode":"70791",
    "sg:province":"LA",
    "sg:tags":[
        "merchandise"
    ],
    "wof:name":"Mary Kay Cosmetics",
    "wof:placetype":"venue"
},
  "geometry": {"coordinates":[-91.24118900000001,30.680339],"type":"Point"}
}