{
  "type": "Feature",
  "properties": {
    "iso:country":"US",
    "sg:address":"1307 Lyons St",
    "sg:city":"New Orleans",
    "sg:classifiers":[
        {
            "category":"Bars & Pubs",
            "type":"Food & Drink"
        }
    ],
    "sg:phone":"+1 504 891 2373",
    "sg:postcode":"70115",
    "sg:province":"LA",
    "sg:tags":[
        "lounge",
        "cocktail"
    ],
    "sg:website":"www.kingpinbar.com",
    "wof:name":"Kingpin",
    "wof:placetype":"venue"
},
  "geometry": {"coordinates":[-90.107544,29.924538],"type":"Point"}
}