{
  "type": "Feature",
  "properties": {
    "addr:full":"17050 Medical Center Dr Baton Rouge LA 70816",
    "addr:housenumber":"17050",
    "addr:postcode":"70816",
    "addr:street":"Medical Center Dr",
    "iso:country":"US",
    "sg:address":"17050 Medical Center Dr",
    "sg:city":"Baton Rouge",
    "sg:classifiers":[
        {
            "category":"Personal",
            "subcategory":"Beauty Salon",
            "type":"Services"
        }
    ],
    "sg:phone":"+1 225 906 2620",
    "sg:postcode":"70816",
    "sg:province":"LA",
    "sg:tags":[
        "treatment",
        "skin"
    ],
    "wof:name":"Simply Beautiful Laser Ctr",
    "wof:placetype":"venue"
},
  "geometry": {"coordinates":[-91.007367,30.439716],"type":"Point"}
}