{
  "type": "Feature",
  "properties": {
    "addr:full":"3030 Colquitt Rd Shreveport LA 71118",
    "addr:housenumber":"3030",
    "addr:postcode":"71118",
    "addr:street":"Colquitt Rd",
    "iso:country":"US",
    "sg:address":"3030 Colquitt Rd",
    "sg:city":"Shreveport",
    "sg:classifiers":[
        {
            "category":"Organizations",
            "subcategory":"Religious Organization",
            "type":"Services"
        }
    ],
    "sg:phone":"+1 318 686 3870",
    "sg:postcode":"71118",
    "sg:province":"LA",
    "sg:tags":[
        "church"
    ],
    "wof:name":"John Calvin Presbyterian Chr",
    "wof:placetype":"venue"
},
  "geometry": {"coordinates":[-93.813524,32.39511],"type":"Point"}
}