{
  "type": "Feature",
  "properties": {
    "addr:full":"1345 Youngs Rd Morgan City LA 70380",
    "addr:housenumber":"1345",
    "addr:postcode":"70380",
    "addr:street":"Youngs Rd",
    "iso:country":"US",
    "sg:address":"1345 Youngs Rd",
    "sg:city":"Morgan City",
    "sg:classifiers":[
        {
            "category":"Mining & Drilling",
            "type":"Manufacturing & Wholesale Goods"
        }
    ],
    "sg:phone":"+1 985 380 2778",
    "sg:postcode":"70380",
    "sg:province":"LA",
    "sg:tags":[
        "field",
        "oil",
        "gas"
    ],
    "wof:name":"Training Department",
    "wof:placetype":"venue"
},
  "geometry": {"coordinates":[-91.18992799999999,29.689178],"type":"Point"}
}