{
  "type": "Feature",
  "properties": {
    "iso:country":"US",
    "sg:address":"16587 Airline Hwy",
    "sg:city":"Prairieville",
    "sg:classifiers":[
        {
            "category":"Building & Trades",
            "subcategory":"Construction",
            "type":"Services"
        }
    ],
    "sg:phone":"+1 225 673 8996",
    "sg:postcode":"70769",
    "sg:province":"LA",
    "sg:tags":[
        "maker",
        "cabinet"
    ],
    "wof:name":"Creative Woodworks",
    "wof:placetype":"venue"
},
  "geometry": {"coordinates":[-90.97745999999999,30.316223],"type":"Point"}
}