{
  "type": "Feature",
  "properties": {
    "iso:country":"US",
    "sg:address":"2902 Lake St",
    "sg:city":"Lake Charles",
    "sg:classifiers":[
        {
            "category":"Autos & Motor Vehicles",
            "subcategory":"Fuel & Gas Station",
            "type":"Retail Goods"
        }
    ],
    "sg:phone":"+1 337 478 2880",
    "sg:postcode":"70601",
    "sg:province":"LA",
    "sg:tags":[
        "oil"
    ],
    "wof:name":"Khan Petroleum Inc",
    "wof:placetype":"venue"
},
  "geometry": {"coordinates":[-93.232432,30.205101],"type":"Point"}
}