{
  "type": "Feature",
  "properties": {
    "iso:country":"US",
    "sg:address":"1421 S Washington St",
    "sg:city":"Bastrop",
    "sg:classifiers":[
        {
            "category":"Retail",
            "subcategory":"Auto Repair",
            "type":"Services"
        }
    ],
    "sg:phone":"+1 318 281 2529",
    "sg:postcode":"71220",
    "sg:province":"LA",
    "sg:tags":[
        "repairing",
        "automobile"
    ],
    "wof:name":"S S Automotive Repair",
    "wof:placetype":"venue"
},
  "geometry": {"coordinates":[-91.91224699999999,32.765654],"type":"Point"}
}