{
  "type": "Feature",
  "properties": {
    "addr:full":"553 State Rte 495 Cloutierville LA 71416",
    "addr:housenumber":"553",
    "addr:postcode":"71416",
    "addr:street":"State Rte 495 Cloutierville",
    "iso:country":"US",
    "sg:address":"553 State Rte 495",
    "sg:city":"Cloutierville",
    "sg:classifiers":[
        {
            "category":"Building & Trades",
            "subcategory":"Construction",
            "type":"Services"
        }
    ],
    "sg:phone":"+1 318 379 9100",
    "sg:postcode":"71416",
    "sg:province":"LA",
    "sg:tags":[
        "roofing",
        "contractor"
    ],
    "wof:name":"A Jones Roofing",
    "wof:placetype":"venue"
},
  "geometry": {"coordinates":[-92.890973,31.551671],"type":"Point"}
}