{
  "type": "Feature",
  "properties": {
    "iso:country":"US",
    "sg:address":"4410 Highland Rd",
    "sg:city":"Baton Rouge",
    "sg:classifiers":[
        {
            "category":"Personal",
            "subcategory":"Beauty Salon",
            "type":"Services"
        }
    ],
    "sg:phone":"+1 225 769 7993",
    "sg:postcode":"70808",
    "sg:province":"LA",
    "sg:tags":[
        "shop"
    ],
    "wof:name":"Lockworks Hair Skin & Nails",
    "wof:placetype":"venue"
},
  "geometry": {"coordinates":[-91.17152,30.402954],"type":"Point"}
}