{
  "type": "Feature",
  "properties": {
    "iso:country":"US",
    "sg:address":"2816 Lake Villa Dr",
    "sg:city":"Metairie",
    "sg:classifiers":[
        {
            "category":"Health Services",
            "subcategory":"Doctor",
            "type":"Services"
        }
    ],
    "sg:phone":"+1 504 885 3255",
    "sg:postcode":"70002",
    "sg:province":"LA",
    "sg:tags":[
        "dentist"
    ],
    "wof:name":"Raul F Ramirez DDS",
    "wof:placetype":"venue"
},
  "geometry": {"coordinates":[-90.176226,30.000464],"type":"Point"}
}