{
  "type": "Feature",
  "properties": {
    "iso:country":"US",
    "sg:address":"3434 Louisa St",
    "sg:city":"New Orleans",
    "sg:classifiers":[
        {
            "category":"Bars & Pubs",
            "type":"Food & Drink"
        }
    ],
    "sg:phone":"+1 504 947 3193",
    "sg:postcode":"70126",
    "sg:province":"LA",
    "wof:name":"H & M Inc",
    "wof:placetype":"venue"
},
  "geometry": {"coordinates":[-90.03488400000001,29.992739],"type":"Point"}
}