{
  "type": "Feature",
  "properties": {
    "iso:country":"US",
    "sg:address":"31007 Old Baton Rouge Hwy",
    "sg:city":"Hammond",
    "sg:classifiers":[
        {
            "category":"Manufacturing",
            "subcategory":"Signs",
            "type":"Manufacturing & Wholesale Goods"
        }
    ],
    "sg:phone":"+1 225 567 3646",
    "sg:postcode":"70403",
    "sg:province":"LA",
    "wof:name":"C & S Framing Shop",
    "wof:placetype":"venue"
},
  "geometry": {"coordinates":[-90.56089,30.48358],"type":"Point"}
}