{
  "type": "Feature",
  "properties": {
    "addr:full":"1438 S Carrollton Ave New Orleans LA 70118",
    "addr:housenumber":"1438",
    "addr:postcode":"70118",
    "addr:street":"S Carrollton Ave",
    "iso:country":"US",
    "sg:address":"1438 S Carrollton Ave",
    "sg:city":"New Orleans",
    "sg:classifiers":[
        {
            "category":"Restaurant",
            "type":"Food & Drink"
        }
    ],
    "sg:phone":"+1 504 862 9001",
    "sg:postcode":"70118",
    "sg:province":"LA",
    "wof:name":"Basil Leaf",
    "wof:placetype":"venue"
},
  "geometry": {"coordinates":[-90.12782199999999,29.949282],"type":"Point"}
}