{
  "type": "Feature",
  "properties": {
    "iso:country":"US",
    "sg:address":"2305 Choctaw Dr",
    "sg:city":"Baton Rouge",
    "sg:classifiers":[
        {
            "category":"Organizations",
            "subcategory":"Religious Organization",
            "type":"Services"
        }
    ],
    "sg:phone":"+1 225 358 0493",
    "sg:postcode":"70805",
    "sg:province":"LA",
    "wof:name":"Vietnamese Apostolate CCD",
    "wof:placetype":"venue"
},
  "geometry": {"coordinates":[-91.16551200000001,30.469994],"type":"Point"}
}