{
  "type": "Feature",
  "properties": {
    "addr:full":"2644 S Sherwood Forest Blvd Baton Rouge LA 70816",
    "addr:housenumber":"2644",
    "addr:postcode":"70816",
    "addr:street":"S Sherwood Forest Blvd",
    "iso:country":"US",
    "sg:address":"2644 S Sherwood Forest Blvd",
    "sg:city":"Baton Rouge",
    "sg:classifiers":[
        {
            "category":"Insurance",
            "subcategory":"Insurance Agent",
            "type":"Services"
        }
    ],
    "sg:phone":"+1 225 292 2176",
    "sg:postcode":"70816",
    "sg:province":"LA",
    "wof:name":"Liberty National",
    "wof:placetype":"venue"
},
  "geometry": {"coordinates":[-91.05550700000001,30.427459],"type":"Point"}
}