{
  "type": "Feature",
  "properties": {
    "addr:full":"7603 Touchet Ln Broussard LA 70518",
    "addr:postcode":"7603;70518",
    "addr:street":"Touchet Ln",
    "iso:country":"US",
    "sg:address":"7603 Touchet Ln",
    "sg:city":"Broussard",
    "sg:classifiers":[
        {
            "category":"Arts & Performance",
            "subcategory":"Theater",
            "type":"Entertainment"
        }
    ],
    "sg:phone":"+1 337 519 8944",
    "sg:postcode":"70518",
    "sg:province":"LA",
    "sg:tags":[
        "group"
    ],
    "wof:name":"Double TT Disc Jockey Service",
    "wof:placetype":"venue"
},
  "geometry": {"coordinates":[-91.928691,30.065378],"type":"Point"}
}