{
  "type": "Feature",
  "properties": {
    "addr:full":"19411 Helenberg Rd Covington LA 70433",
    "addr:postcode":"19411;70433",
    "addr:street":"Helenberg Rd",
    "iso:country":"US",
    "sg:address":"19411 Helenberg Rd",
    "sg:city":"Covington",
    "sg:classifiers":[
        {
            "category":"Professional",
            "subcategory":"Business Services",
            "type":"Services"
        }
    ],
    "sg:phone":"+1 985 809 2162",
    "sg:postcode":"70433",
    "sg:province":"LA",
    "sg:tags":[
        "appraiser"
    ],
    "wof:name":"Murphy Appraisal Svc",
    "wof:placetype":"venue"
},
  "geometry": {"coordinates":[-90.080927,30.431565],"type":"Point"}
}