{
  "type": "Feature",
  "properties": {
    "iso:country":"US",
    "sg:address":"8648 State Rte 23",
    "sg:city":"Belle Chasse",
    "sg:classifiers":[
        {
            "category":"Personal",
            "subcategory":"Beauty Salon",
            "type":"Services"
        }
    ],
    "sg:phone":"+1 504 433 4331",
    "sg:postcode":"70037",
    "sg:province":"LA",
    "wof:name":"Lisa Harris Salon",
    "wof:placetype":"venue"
},
  "geometry": {"coordinates":[-89.991224,29.848077],"type":"Point"}
}