{
  "type": "Feature",
  "properties": {
    "addr:full":"1201 Sams Ave New Orleans LA 70123",
    "addr:housenumber":"1201",
    "addr:postcode":"70123",
    "addr:street":"Sams Ave",
    "iso:country":"US",
    "sg:address":"1201 Sams Ave",
    "sg:city":"New Orleans",
    "sg:classifiers":[
        {
            "category":"Social Services",
            "type":"Services"
        }
    ],
    "sg:phone":"+1 504 734 1322",
    "sg:postcode":"70123",
    "sg:province":"LA",
    "sg:tags":[
        "food",
        "banks"
    ],
    "sg:website":"www.nohunger.org",
    "wof:name":"Second Harvesters Food Bank",
    "wof:placetype":"venue"
},
  "geometry": {"coordinates":[-90.196899,29.956851],"type":"Point"}
}