{
  "type": "Feature",
  "properties": {
    "iso:country":"US",
    "sg:address":"5632 Hera St",
    "sg:city":"Alexandria",
    "sg:classifiers":[
        {
            "category":"Professional",
            "subcategory":"Business Services",
            "type":"Services"
        }
    ],
    "sg:phone":"+1 318 445 5262",
    "sg:postcode":"71303",
    "sg:province":"LA",
    "wof:name":"Reggie Humbles Enterprise",
    "wof:placetype":"venue"
},
  "geometry": {"coordinates":[-92.49372,31.26997],"type":"Point"}
}