{
  "type": "Feature",
  "properties": {
    "addr:full":"4460 State Rte 485 Robeline LA 71469",
    "addr:housenumber":"4460",
    "addr:postcode":"71469",
    "addr:street":"State Rte 485",
    "iso:country":"US",
    "sg:address":"4460 State Rte 485",
    "sg:city":"Robeline",
    "sg:classifiers":[
        {
            "category":"Professional",
            "type":"Services"
        }
    ],
    "sg:phone":"+1 318 472 1007",
    "sg:postcode":"71469",
    "sg:province":"LA",
    "sg:tags":[
        "establishment"
    ],
    "wof:name":"Adai Caddo Tribal Living",
    "wof:placetype":"venue"
},
  "geometry": {"coordinates":[-93.28381,31.7805],"type":"Point"}
}