{
  "type": "Feature",
  "properties": {
    "iso:country":"US",
    "sg:address":"7280 Corporate Blvd",
    "sg:city":"Baton Rouge",
    "sg:classifiers":[
        {
            "category":"Shopping",
            "subcategory":"Clothing, Apparel, & Fashions",
            "type":"Retail Goods"
        }
    ],
    "sg:phone":"+1 225 927 3227",
    "sg:postcode":"70809",
    "sg:province":"LA",
    "sg:tags":[
        "sportswear"
    ],
    "wof:name":"Athletique LLC",
    "wof:placetype":"venue"
},
  "geometry": {"coordinates":[-91.123705,30.424744],"type":"Point"}
}