{
  "type": "Feature",
  "properties": {
    "addr:full":"1800 E Judge Perez Dr Ste C Chalmette LA 70043",
    "addr:housenumber":"1800",
    "addr:postcode":"70043",
    "addr:street":"E Judge Perez Dr Ste C Chalmette",
    "iso:country":"US",
    "sg:address":"1800 E Judge Perez Dr Ste C",
    "sg:city":"Chalmette",
    "sg:classifiers":[
        {
            "category":"Personal",
            "subcategory":"Tanning Parlor",
            "type":"Services"
        }
    ],
    "sg:phone":"+1 504 278 8990",
    "sg:postcode":"70043",
    "sg:province":"LA",
    "wof:name":"Planet Beach Tanning Salon",
    "wof:placetype":"venue"
},
  "geometry": {"coordinates":[-89.94835500000001,29.937357],"type":"Point"}
}