{
  "type": "Feature",
  "properties": {
    "addr:full":"3258 Lanier Dr Baton Rouge LA 70814",
    "addr:housenumber":"3258",
    "addr:postcode":"70814",
    "addr:street":"Lanier Dr",
    "iso:country":"US",
    "sg:address":"3258 Lanier Dr",
    "sg:city":"Baton Rouge",
    "sg:classifiers":[
        {
            "category":"Wholesale",
            "subcategory":"Durable Goods & Equipment",
            "type":"Manufacturing & Wholesale Goods"
        }
    ],
    "sg:phone":"+1 225 929 9525",
    "sg:postcode":"70814",
    "sg:province":"LA",
    "sg:tags":[
        "exporter"
    ],
    "wof:name":"Global Business Network",
    "wof:placetype":"venue"
},
  "geometry": {"coordinates":[-91.109182,30.483849],"type":"Point"}
}