{
  "type": "Feature",
  "properties": {
    "addr:full":"1517 E Bert Kouns Industrial Loop Shreveport LA 71105",
    "addr:housenumber":"1517",
    "addr:postcode":"71105",
    "addr:street":"E Bert Kouns Industrial Loop",
    "iso:country":"US",
    "sg:address":"1517 E Bert Kouns Industrial Loop",
    "sg:city":"Shreveport",
    "sg:classifiers":[
        {
            "category":"Restaurant",
            "type":"Food & Drink"
        }
    ],
    "sg:menulink":"http://www.allmenus.com/la/shreveport/82255-applebees/menu/",
    "sg:phone":"+1 318 795 9595",
    "sg:postcode":"71105",
    "sg:province":"LA",
    "sg:tags":[
        "burger",
        "american",
        "sandwich",
        "soup"
    ],
    "wof:name":"Applebee's",
    "wof:placetype":"venue"
},
  "geometry": {"coordinates":[-93.71796999999999,32.42696],"type":"Point"}
}