{
  "type": "Feature",
  "properties": {
    "addr:full":"600 E Flournoy Lucas Rd Shreveport LA 71115",
    "addr:housenumber":"600",
    "addr:postcode":"71115",
    "addr:street":"E Flournoy Lucas Rd",
    "iso:country":"US",
    "sg:address":"600 E Flournoy Lucas Rd",
    "sg:city":"Shreveport",
    "sg:classifiers":[
        {
            "category":"Health Services",
            "subcategory":"Nursing And Care Facility",
            "type":"Services"
        }
    ],
    "sg:phone":"+1 318 797 1900",
    "sg:postcode":"71115",
    "sg:province":"LA",
    "sg:tags":[
        "home",
        "convalescent"
    ],
    "wof:name":"Live Oak Retirement Community",
    "wof:placetype":"venue"
},
  "geometry": {"coordinates":[-93.70643699999999,32.400942],"type":"Point"}
}