{
  "type": "Feature",
  "properties": {
    "iso:country":"US",
    "sg:address":"1727 Jackson Ave",
    "sg:city":"New Orleans",
    "sg:classifiers":[
        {
            "category":"Wholesale",
            "subcategory":"Non-durable Goods",
            "type":"Manufacturing & Wholesale Goods"
        }
    ],
    "sg:phone":"+1 504 524 6888",
    "sg:postcode":"70113",
    "sg:province":"LA",
    "wof:name":"Sidney Broussard Ltd",
    "wof:placetype":"venue"
},
  "geometry": {"coordinates":[-90.081362,29.935042],"type":"Point"}
}