{
  "type": "Feature",
  "properties": {
    "iso:country":"US",
    "sg:address":"1511 E Tunnel Blvd",
    "sg:city":"Houma",
    "sg:classifiers":[
        {
            "category":"Shopping",
            "subcategory":"Pharmacy",
            "type":"Retail Goods"
        }
    ],
    "sg:phone":"+1 985 873 5913",
    "sg:postcode":"70363",
    "sg:province":"LA",
    "sg:website":"www.walgreens.com",
    "wof:name":"Walgreens",
    "wof:placetype":"venue"
},
  "geometry": {"coordinates":[-90.706563,29.587773],"type":"Point"}
}