{
  "type": "Feature",
  "properties": {
    "addr:full":"712 Sara Dr Leesville LA 71446",
    "addr:housenumber":"712",
    "addr:postcode":"71446",
    "addr:street":"Sara Dr",
    "iso:country":"US",
    "sg:address":"712 Sara Dr",
    "sg:city":"Leesville",
    "sg:classifiers":[
        {
            "category":"Retail",
            "subcategory":"Animal Services",
            "type":"Services"
        }
    ],
    "sg:phone":"+1 337 238 1018",
    "sg:postcode":"71446",
    "sg:province":"LA",
    "wof:name":"Mildred Owens",
    "wof:placetype":"venue"
},
  "geometry": {"coordinates":[-93.29132799999999,31.139085],"type":"Point"}
}