{
  "type": "Feature",
  "properties": {
    "addr:full":"14621 Shady Grove Ln Wilson LA 70761",
    "addr:housenumber":"14621",
    "addr:postcode":"70761",
    "addr:street":"Shady Grove Ln",
    "iso:country":"US",
    "sg:address":"14621 Shady Grove Ln",
    "sg:city":"Wilson",
    "sg:classifiers":[
        {
            "category":"Home & Garden",
            "subcategory":"Building Materials",
            "type":"Retail Goods"
        }
    ],
    "sg:phone":"+1 225 629 9400",
    "sg:postcode":"70761",
    "sg:province":"LA",
    "sg:tags":[
        "lumber"
    ],
    "wof:name":"J & J Millworks",
    "wof:placetype":"venue"
},
  "geometry": {"coordinates":[-91.11476399999999,30.987652],"type":"Point"}
}