{
  "type": "Feature",
  "properties": {
    "iso:country":"US",
    "sg:address":"871 Sam Houston Jones Pkwy",
    "sg:city":"Lake Charles",
    "sg:classifiers":[
        {
            "category":"Personal",
            "subcategory":"Beauty Salon",
            "type":"Services"
        }
    ],
    "sg:phone":"+1 337 217 0320",
    "sg:postcode":"70611",
    "sg:province":"LA",
    "sg:tags":[
        "manicuring"
    ],
    "wof:name":"Klassy Nails",
    "wof:placetype":"venue"
},
  "geometry": {"coordinates":[-93.21138999999999,30.300712],"type":"Point"}
}