{
  "type": "Feature",
  "properties": {
    "iso:country":"US",
    "sg:address":"540 Court St",
    "sg:city":"Port Allen",
    "sg:classifiers":[
        {
            "category":"Personal",
            "subcategory":"Beauty Salon",
            "type":"Services"
        }
    ],
    "sg:phone":"+1 225 336 9022",
    "sg:postcode":"70767",
    "sg:province":"LA",
    "sg:tags":[
        "shop",
        "manicuring"
    ],
    "wof:name":"Anita' Nail Salon",
    "wof:placetype":"venue"
},
  "geometry": {"coordinates":[-91.206182,30.452558],"type":"Point"}
}