{
  "type": "Feature",
  "properties": {
    "iso:country":"US",
    "sg:address":"106 Ashland Ct",
    "sg:city":"Lafayette",
    "sg:classifiers":[
        {
            "category":"Professional",
            "subcategory":"Detective & Security Services",
            "type":"Services"
        }
    ],
    "sg:phone":"+1 337 267 7326",
    "sg:postcode":"70508",
    "sg:province":"LA",
    "sg:tags":[
        "investigator"
    ],
    "wof:name":"Dan Snow Fire Investigations",
    "wof:placetype":"venue"
},
  "geometry": {"coordinates":[-92.005763,30.164237],"type":"Point"}
}