{
  "type": "Feature",
  "properties": {
    "iso:country":"US",
    "sg:address":"2001 Oak Park Blvd",
    "sg:city":"Lake Charles",
    "sg:classifiers":[
        {
            "category":"Restaurant",
            "type":"Food & Drink"
        }
    ],
    "sg:phone":"+1 337 477 9759",
    "sg:postcode":"70601",
    "sg:province":"LA",
    "wof:name":"Cotten's Famous Hamburgers",
    "wof:placetype":"venue"
},
  "geometry": {"coordinates":[-93.18924,30.203405],"type":"Point"}
}