{
  "type": "Feature",
  "properties": {
    "iso:country":"US",
    "sg:address":"703 Aero Dr",
    "sg:city":"Shreveport",
    "sg:classifiers":[
        {
            "category":"Manufacturing",
            "subcategory":"Signs",
            "type":"Manufacturing & Wholesale Goods"
        }
    ],
    "sg:phone":"+1 318 222 3355",
    "sg:postcode":"71107",
    "sg:province":"LA",
    "wof:name":"Banner Sign & Barricade",
    "wof:placetype":"venue"
},
  "geometry": {"coordinates":[-93.768451,32.528838],"type":"Point"}
}