{
  "type": "Feature",
  "properties": {
    "iso:country":"US",
    "sg:address":"14885 W Main St",
    "sg:city":"Cut Off",
    "sg:classifiers":[
        {
            "category":"Professional",
            "subcategory":"Accounting & Tax Preparation",
            "type":"Services"
        }
    ],
    "sg:phone":"+1 985 632 3305",
    "sg:postcode":"70345",
    "sg:province":"LA",
    "sg:tags":[
        "return",
        "filing"
    ],
    "wof:name":"Curole Bookkeeping",
    "wof:placetype":"venue"
},
  "geometry": {"coordinates":[-90.335717,29.52645],"type":"Point"}
}