{
  "type": "Feature",
  "properties": {
    "iso:country":"US",
    "sg:address":"200 Sierra Ct",
    "sg:city":"Metairie",
    "sg:classifiers":[
        {
            "category":"Professional",
            "subcategory":"Lawyer & Legal Services",
            "type":"Services"
        }
    ],
    "sg:phone":"+1 504 832 0800",
    "sg:postcode":"70001",
    "sg:province":"LA",
    "sg:tags":[
        "attorney"
    ],
    "wof:name":"Fleischmann Law Firm",
    "wof:placetype":"venue"
},
  "geometry": {"coordinates":[-90.15542499999999,29.97883],"type":"Point"}
}