{
  "type": "Feature",
  "properties": {
    "iso:country":"US",
    "sg:address":"174 Diddle Babbs Rd",
    "sg:city":"Glenmora",
    "sg:classifiers":[
        {
            "category":"Organizations",
            "subcategory":"Religious Organization",
            "type":"Services"
        }
    ],
    "sg:phone":"+1 318 748 8662",
    "sg:postcode":"71433",
    "sg:province":"LA",
    "wof:name":"United Pentecostal Church",
    "wof:placetype":"venue"
},
  "geometry": {"coordinates":[-92.56026,30.921302],"type":"Point"}
}