{
  "type": "Feature",
  "properties": {
    "iso:country":"US",
    "sg:address":"2002 Anita Blvd",
    "sg:city":"Hammond",
    "sg:classifiers":[
        {
            "category":"Personal",
            "subcategory":"Beauty Salon",
            "type":"Services"
        }
    ],
    "sg:phone":"+1 985 429 1188",
    "sg:postcode":"70403",
    "sg:province":"LA",
    "sg:tags":[
        "shop"
    ],
    "wof:name":"Michalles",
    "wof:placetype":"venue"
},
  "geometry": {"coordinates":[-90.482736,30.492495],"type":"Point"}
}