{
  "type": "Feature",
  "properties": {
    "addr:full":"1082 Huval St Henderson LA 70517",
    "addr:housenumber":"1082",
    "addr:postcode":"70517",
    "addr:street":"Huval St",
    "iso:country":"US",
    "sg:address":"1082 Huval St",
    "sg:city":"Henderson",
    "sg:classifiers":[
        {
            "category":"Shopping",
            "subcategory":"Clothing, Apparel, & Fashions",
            "type":"Retail Goods"
        }
    ],
    "sg:phone":"+1 337 228 1198",
    "sg:postcode":"70517",
    "sg:province":"LA",
    "sg:tags":[
        "alteration"
    ],
    "wof:name":"Alterations By Maggie",
    "wof:placetype":"venue"
},
  "geometry": {"coordinates":[-91.798529,30.315841],"type":"Point"}
}