{
  "type": "Feature",
  "properties": {
    "addr:full":"38 Boogaerts Rd Boyce LA 71409",
    "addr:housenumber":"38",
    "addr:postcode":"71409",
    "addr:street":"Boogaerts Rd",
    "iso:country":"US",
    "sg:address":"38 Boogaerts Rd",
    "sg:city":"Boyce",
    "sg:classifiers":[
        {
            "category":"Building & Trades",
            "subcategory":"Electrical",
            "type":"Services"
        }
    ],
    "sg:phone":"+1 318 487 8009",
    "sg:postcode":"71409",
    "sg:province":"LA",
    "sg:tags":[
        "installation"
    ],
    "wof:name":"Red River Satellites",
    "wof:placetype":"venue"
},
  "geometry": {"coordinates":[-92.583252,31.36792],"type":"Point"}
}