{
  "type": "Feature",
  "properties": {
    "addr:full":"3000 Downs Blvd Metairie LA 70003",
    "addr:housenumber":"3000",
    "addr:postcode":"70003",
    "addr:street":"Downs Blvd",
    "iso:country":"US",
    "sg:address":"3000 Downs Blvd",
    "sg:city":"Metairie",
    "sg:classifiers":[
        {
            "category":"Recreation",
            "type":"Entertainment"
        }
    ],
    "sg:phone":"+1 504 838 4389",
    "sg:postcode":"70003",
    "sg:province":"LA",
    "sg:tags":[
        "parks"
    ],
    "wof:name":"Lafreniere Park",
    "wof:placetype":"venue"
},
  "geometry": {"coordinates":[-90.21339399999999,30.003919],"type":"Point"}
}