{
  "type": "Feature",
  "properties": {
    "addr:full":"1006 N Lake Arthur Ave Jennings LA 70546",
    "addr:housenumber":"1006",
    "addr:postcode":"70546",
    "addr:street":"N Lake Arthur Ave",
    "iso:country":"US",
    "sg:address":"1006 N Lake Arthur Ave",
    "sg:city":"Jennings",
    "sg:classifiers":[
        {
            "category":"Education",
            "subcategory":"College",
            "type":"Public Place"
        }
    ],
    "sg:phone":"+1 337 824 1773",
    "sg:postcode":"70546",
    "sg:province":"LA",
    "wof:name":"Louisiana State University",
    "wof:placetype":"venue"
},
  "geometry": {"coordinates":[-92.66330600000001,30.231549],"type":"Point"}
}