{
  "type": "Feature",
  "properties": {
    "addr:full":"11257 General Ott Rd Hammond LA 70403",
    "addr:housenumber":"11257",
    "addr:postcode":"70403",
    "addr:street":"General Ott Rd",
    "iso:country":"US",
    "sg:address":"11257 General Ott Rd",
    "sg:city":"Hammond",
    "sg:classifiers":[
        {
            "category":"Professional",
            "subcategory":"Business Services",
            "type":"Services"
        }
    ],
    "sg:phone":"+1 225 567 5779",
    "sg:postcode":"70403",
    "sg:province":"LA",
    "wof:name":"Internet Solutions Inc",
    "wof:placetype":"venue"
},
  "geometry": {"coordinates":[-90.541676,30.475312],"type":"Point"}
}