{
  "type": "Feature",
  "properties": {
    "iso:country":"US",
    "sg:address":"254 Pacific St",
    "sg:city":"Port Barre",
    "sg:classifiers":[
        {
            "category":"Organizations",
            "subcategory":"Religious Organization",
            "type":"Services"
        }
    ],
    "sg:phone":"+1 337 585 7605",
    "sg:postcode":"70577",
    "sg:province":"LA",
    "sg:tags":[
        "church"
    ],
    "wof:name":"House Of Prayer",
    "wof:placetype":"venue"
},
  "geometry": {"coordinates":[-91.951724,30.567669],"type":"Point"}
}