{
  "type": "Feature",
  "properties": {
    "iso:country":"US",
    "sg:address":"111 N Court St",
    "sg:city":"Opelousas",
    "sg:classifiers":[
        {
            "category":"Professional",
            "subcategory":"Lawyer & Legal Services",
            "type":"Services"
        }
    ],
    "sg:phone":"+1 337 948 8006",
    "sg:postcode":"70570",
    "sg:province":"LA",
    "wof:name":"Kimberly Jones Attorney",
    "wof:placetype":"venue"
},
  "geometry": {"coordinates":[-92.082712,30.535078],"type":"Point"}
}