{
  "type": "Feature",
  "properties": {
    "addr:full":"123 Wright St Lafayette LA 70507",
    "addr:housenumber":"123",
    "addr:postcode":"70507",
    "addr:street":"Wright St",
    "iso:country":"US",
    "sg:address":"123 Wright St",
    "sg:city":"Lafayette",
    "sg:classifiers":[
        {
            "category":"Retail",
            "subcategory":"Auto Repair",
            "type":"Services"
        }
    ],
    "sg:phone":"+1 337 233 3948",
    "sg:postcode":"70507",
    "sg:province":"LA",
    "sg:tags":[
        "body",
        "automobile",
        "painting"
    ],
    "wof:name":"Monte's Repair Shop",
    "wof:placetype":"venue"
},
  "geometry": {"coordinates":[-92.047178,30.277987],"type":"Point"}
}