{
  "type": "Feature",
  "properties": {
    "iso:country":"US",
    "sg:address":"519 McCreight St",
    "sg:city":"Bastrop",
    "sg:classifiers":[
        {
            "category":"Food & Beverages",
            "subcategory":"Bakery",
            "type":"Retail Goods"
        }
    ],
    "sg:phone":"+1 318 281 0253",
    "sg:postcode":"71220",
    "sg:province":"LA",
    "sg:tags":[
        "baker"
    ],
    "wof:name":"Cotton's Holsum Baking Co",
    "wof:placetype":"venue"
},
  "geometry": {"coordinates":[-91.902843,32.783856],"type":"Point"}
}