{
  "type": "Feature",
  "properties": {
    "addr:full":"9001 Cortana Pl Baton Rouge LA 70815",
    "addr:housenumber":"9001",
    "addr:postcode":"70815",
    "addr:street":"Cortana Pl",
    "iso:country":"US",
    "sg:address":"9001 Cortana Pl",
    "sg:city":"Baton Rouge",
    "sg:classifiers":[
        {
            "category":"Shopping",
            "subcategory":"Department Store",
            "type":"Retail Goods"
        }
    ],
    "sg:phone":"+1 225 922 5295",
    "sg:postcode":"70815",
    "sg:province":"LA",
    "wof:name":"Sears Roebuck & Co",
    "wof:placetype":"venue"
},
  "geometry": {"coordinates":[-91.08994300000001,30.45568],"type":"Point"}
}