{
  "type": "Feature",
  "properties": {
    "iso:country":"US",
    "sg:address":"5654 Main St",
    "sg:city":"Zachary",
    "sg:classifiers":[
        {
            "category":"Insurance",
            "subcategory":"Insurance Agent",
            "type":"Services"
        }
    ],
    "sg:phone":"+1 225 654 7817",
    "sg:postcode":"70791",
    "sg:province":"LA",
    "wof:name":"Allstate Insurance",
    "wof:placetype":"venue"
},
  "geometry": {"coordinates":[-91.13966600000001,30.649754],"type":"Point"}
}