{
  "type": "Feature",
  "properties": {
    "iso:country":"US",
    "sg:address":"4350 US Hwy 90",
    "sg:city":"Broussard",
    "sg:classifiers":[
        {
            "category":"Retail",
            "subcategory":"Repair Shop",
            "type":"Services"
        }
    ],
    "sg:phone":"+1 337 261 0355",
    "sg:postcode":"70518",
    "sg:province":"LA",
    "sg:tags":[
        "welding"
    ],
    "wof:name":"Taylor Made Contract Wldng Svc",
    "wof:placetype":"venue"
},
  "geometry": {"coordinates":[-91.95464200000001,30.151593],"type":"Point"}
}