{
  "type": "Feature",
  "properties": {
    "addr:full":"1250 Carmel Ave Lafayette LA 70501",
    "addr:housenumber":"1250",
    "addr:postcode":"70501",
    "addr:street":"Carmel Ave",
    "iso:country":"US",
    "sg:address":"1250 Carmel Ave",
    "sg:city":"Lafayette",
    "sg:classifiers":[
        {
            "category":"Organizations",
            "subcategory":"Religious Organization",
            "type":"Services"
        }
    ],
    "sg:phone":"+1 337 232 4651",
    "sg:postcode":"70501",
    "sg:province":"LA",
    "sg:tags":[
        "church"
    ],
    "wof:name":"Carmelite Monastery",
    "wof:placetype":"venue"
},
  "geometry": {"coordinates":[-91.990084,30.233082],"type":"Point"}
}