{
  "type": "Feature",
  "properties": {
    "addr:full":"625 State Rte 182 Houma LA 70364",
    "addr:housenumber":"625",
    "addr:postcode":"70364",
    "addr:street":"State Rte 182",
    "iso:country":"US",
    "sg:address":"625 State Rte 182",
    "sg:city":"Houma",
    "sg:classifiers":[
        {
            "category":"Autos & Motor Vehicles",
            "subcategory":"Auto Supplies",
            "type":"Retail Goods"
        }
    ],
    "sg:phone":"+1 985 868 1965",
    "sg:postcode":"70364",
    "sg:province":"LA",
    "sg:tags":[
        "tire"
    ],
    "wof:name":"Superior Tire Svc",
    "wof:placetype":"venue"
},
  "geometry": {"coordinates":[-90.714218,29.607736],"type":"Point"}
}