{
  "type": "Feature",
  "properties": {
    "addr:full":"9864 Professional Blvd Baton Rouge LA 70809",
    "addr:housenumber":"9864",
    "addr:postcode":"70809",
    "addr:street":"Professional Blvd",
    "iso:country":"US",
    "sg:address":"9864 Professional Blvd",
    "sg:city":"Baton Rouge",
    "sg:classifiers":[
        {
            "category":"Manufacturing",
            "subcategory":"Printing",
            "type":"Manufacturing & Wholesale Goods"
        }
    ],
    "sg:phone":"+1 225 293 2900",
    "sg:postcode":"70809",
    "sg:province":"LA",
    "sg:tags":[
        "printer"
    ],
    "wof:name":"Connelly Press & Copy Inc",
    "wof:placetype":"venue"
},
  "geometry": {"coordinates":[-91.074883,30.415969],"type":"Point"}
}