{
  "type": "Feature",
  "properties": {
    "addr:full":"7931 Chef Menteur Hwy New Orleans LA 70126",
    "addr:housenumber":"7931",
    "addr:postcode":"70126",
    "addr:street":"Chef Menteur Hwy",
    "iso:country":"US",
    "sg:address":"7931 Chef Menteur Hwy",
    "sg:city":"New Orleans",
    "sg:classifiers":[
        {
            "category":"Organizations",
            "subcategory":"Religious Organization",
            "type":"Services"
        }
    ],
    "sg:phone":"+1 504 246 3545",
    "sg:postcode":"70126",
    "sg:province":"LA",
    "sg:tags":[
        "church"
    ],
    "wof:name":"Victory Gospel Chapel Intl",
    "wof:placetype":"venue"
},
  "geometry": {"coordinates":[-89.993161,30.013491],"type":"Point"}
}