{
  "type": "Feature",
  "properties": {
    "addr:full":"4153 Hwy 1 Port Allen LA 70767",
    "addr:housenumber":"4153",
    "addr:postcode":"70767",
    "addr:street":"Hwy 1",
    "iso:country":"US",
    "sg:address":"4153 Hwy 1",
    "sg:city":"Port Allen",
    "sg:classifiers":[
        {
            "category":"Insurance",
            "subcategory":"Insurance Agent",
            "type":"Services"
        }
    ],
    "sg:phone":"+1 225 749 4100",
    "sg:postcode":"70767",
    "sg:province":"LA",
    "wof:name":"Farm Bureau Insurance",
    "wof:placetype":"venue"
},
  "geometry": {"coordinates":[-91.22581099999999,30.412365],"type":"Point"}
}