{
  "type": "Feature",
  "properties": {
    "addr:full":"465 W Cypress Ave Bastrop LA 71220",
    "addr:housenumber":"465",
    "addr:postcode":"71220",
    "addr:street":"W Cypress Ave",
    "iso:country":"US",
    "sg:address":"465 W Cypress Ave",
    "sg:city":"Bastrop",
    "sg:classifiers":[
        {
            "category":"Organizations",
            "subcategory":"Religious Organization",
            "type":"Services"
        }
    ],
    "sg:phone":"+1 318 281 2764",
    "sg:postcode":"71220",
    "sg:province":"LA",
    "sg:tags":[
        "church"
    ],
    "wof:name":"Magnolia Baptist Church",
    "wof:placetype":"venue"
},
  "geometry": {"coordinates":[-91.920165,32.780064],"type":"Point"}
}