{
  "type": "Feature",
  "properties": {
    "iso:country":"US",
    "sg:address":"3704 Page Dr",
    "sg:city":"Metairie",
    "sg:classifiers":[
        {
            "category":"Personal",
            "type":"Services"
        }
    ],
    "sg:phone":"+1 504 885 0015",
    "sg:postcode":"70003",
    "sg:province":"LA",
    "wof:name":"Pontchartrain Sales & Leasing",
    "wof:placetype":"venue"
},
  "geometry": {"coordinates":[-90.20363399999999,30.010272],"type":"Point"}
}