{
  "type": "Feature",
  "properties": {
    "iso:country":"US",
    "sg:address":"79139 Jessie Hyatt Rd",
    "sg:city":"Covington",
    "sg:classifiers":[
        {
            "category":"Building & Trades",
            "subcategory":"Construction",
            "type":"Services"
        }
    ],
    "sg:phone":"+1 985 893 8923",
    "sg:postcode":"70435",
    "sg:province":"LA",
    "sg:tags":[
        "siding",
        "contractor"
    ],
    "wof:name":"Custom Vinyl Siding",
    "wof:placetype":"venue"
},
  "geometry": {"coordinates":[-90.12674800000001,30.577804],"type":"Point"}
}