{
  "type": "Feature",
  "properties": {
    "iso:country":"US",
    "sg:address":"7887 Walmsley Ave",
    "sg:city":"New Orleans",
    "sg:classifiers":[
        {
            "category":"Organizations",
            "subcategory":"Religious Organization",
            "type":"Services"
        }
    ],
    "sg:phone":"+1 504 861 9521",
    "sg:postcode":"70125",
    "sg:province":"LA",
    "sg:website":"www.arno-sbe.org",
    "wof:name":"Archdiocese Of New Orleans",
    "wof:placetype":"venue"
},
  "geometry": {"coordinates":[-90.115027,29.95701],"type":"Point"}
}