{
  "type": "Feature",
  "properties": {
    "addr:full":"310 Ella St Lafayette LA 70506",
    "addr:housenumber":"310",
    "addr:postcode":"70506",
    "addr:street":"Ella St",
    "iso:country":"US",
    "sg:address":"310 Ella St",
    "sg:city":"Lafayette",
    "sg:classifiers":[
        {
            "category":"Retail",
            "subcategory":"Portrait Studio",
            "type":"Services"
        }
    ],
    "sg:phone":"+1 337 237 1970",
    "sg:postcode":"70506",
    "sg:province":"LA",
    "sg:tags":[
        "photographer"
    ],
    "wof:name":"Snapshots Of Acadiana",
    "wof:placetype":"venue"
},
  "geometry": {"coordinates":[-92.05302399999999,30.214942],"type":"Point"}
}