{
  "type": "Feature",
  "properties": {
    "addr:full":"5362 Old Hwy 6 Natchitoches LA 71457",
    "addr:housenumber":"5362",
    "addr:postcode":"71457",
    "addr:street":"Old Hwy 6",
    "iso:country":"US",
    "sg:address":"5362 Old Hwy 6",
    "sg:city":"Natchitoches",
    "sg:classifiers":[
        {
            "category":"Travel",
            "subcategory":"Hotels & Motels",
            "type":"Entertainment"
        }
    ],
    "sg:phone":"+1 318 352 7500",
    "sg:postcode":"71457",
    "sg:province":"LA",
    "wof:name":"Comfort Inn",
    "wof:placetype":"venue"
},
  "geometry": {"coordinates":[-93.173159,31.719353],"type":"Point"}
}