{
  "type": "Feature",
  "properties": {
    "iso:country":"US",
    "sg:address":"3704 Rue Chardonnay",
    "sg:city":"Metairie",
    "sg:classifiers":[
        {
            "category":"Organizations",
            "subcategory":"Religious Organization",
            "type":"Services"
        }
    ],
    "sg:phone":"+1 504 454 3286",
    "sg:postcode":"70002",
    "sg:province":"LA",
    "wof:name":"Word of Truth Ministries",
    "wof:placetype":"venue"
},
  "geometry": {"coordinates":[-90.165396,30.019816],"type":"Point"}
}