{
  "type": "Feature",
  "properties": {
    "iso:country":"US",
    "sg:address":"3214 N Roman St",
    "sg:city":"New Orleans",
    "sg:classifiers":[
        {
            "category":"Professional",
            "subcategory":"Advertising",
            "type":"Services"
        }
    ],
    "sg:phone":"+1 504 836 0525",
    "sg:postcode":"70117",
    "sg:province":"LA",
    "wof:name":"Augie Leopold Advertising",
    "wof:placetype":"venue"
},
  "geometry": {"coordinates":[-90.039564,29.974145],"type":"Point"}
}