{
  "type": "Feature",
  "properties": {
    "iso:country":"US",
    "sg:address":"200 Broadway St",
    "sg:city":"New Orleans",
    "sg:classifiers":[
        {
            "category":"Professional",
            "subcategory":"Business Services",
            "type":"Services"
        }
    ],
    "sg:phone":"+1 504 861 0060",
    "sg:postcode":"70118",
    "sg:province":"LA",
    "wof:name":"UPS Stores The",
    "wof:placetype":"venue"
},
  "geometry": {"coordinates":[-90.132182,29.930535],"type":"Point"}
}