{
  "type": "Feature",
  "properties": {
    "addr:full":"31501 Sanford Rd Franklinton LA 70438",
    "addr:housenumber":"31501",
    "addr:postcode":"70438",
    "addr:street":"Sanford Rd",
    "iso:country":"US",
    "sg:address":"31501 Sanford Rd",
    "sg:city":"Franklinton",
    "sg:classifiers":[
        {
            "category":"Retail",
            "subcategory":"Auto Repair",
            "type":"Services"
        }
    ],
    "sg:phone":"+1 985 839 2304",
    "sg:postcode":"70438",
    "sg:province":"LA",
    "sg:tags":[
        "body",
        "automobile",
        "painting"
    ],
    "wof:name":"Sanford & Son Body Shop",
    "wof:placetype":"venue"
},
  "geometry": {"coordinates":[-90.180508,30.97716],"type":"Point"}
}