{
  "type": "Feature",
  "properties": {
    "addr:full":"8013 Dalton St Metairie LA 70003",
    "addr:housenumber":"8013",
    "addr:postcode":"70003",
    "addr:street":"Dalton St",
    "iso:country":"US",
    "sg:address":"8013 Dalton St",
    "sg:city":"Metairie",
    "sg:classifiers":[
        {
            "category":"Shopping",
            "subcategory":"Hobbies, Toys, & Games",
            "type":"Retail Goods"
        }
    ],
    "sg:phone":"+1 504 469 2189",
    "sg:postcode":"70003",
    "sg:province":"LA",
    "wof:name":"Bees Amusement",
    "wof:placetype":"venue"
},
  "geometry": {"coordinates":[-90.21985599999999,29.987577],"type":"Point"}
}