{
  "type": "Feature",
  "properties": {
    "iso:country":"US",
    "sg:address":"708 1st St",
    "sg:city":"Duson",
    "sg:classifiers":[
        {
            "category":"Education",
            "subcategory":"Library",
            "type":"Public Place"
        }
    ],
    "sg:phone":"+1 337 873 3521",
    "sg:postcode":"70529",
    "sg:province":"LA",
    "wof:name":"Duson Library",
    "wof:placetype":"venue"
},
  "geometry": {"coordinates":[-92.178862,30.235867],"type":"Point"}
}