{
  "type": "Feature",
  "properties": {
    "iso:country":"US",
    "sg:address":"205 Cornwell St",
    "sg:city":"Lafayette",
    "sg:classifiers":[
        {
            "category":"Freight",
            "type":"Transportation"
        }
    ],
    "sg:phone":"+1 337 234 1447",
    "sg:postcode":"70507",
    "sg:province":"LA",
    "sg:tags":[
        "field",
        "oil"
    ],
    "wof:name":"Dixie Vacuum Trucks Inc",
    "wof:placetype":"venue"
},
  "geometry": {"coordinates":[-92.009754,30.287951],"type":"Point"}
}