{
  "type": "Feature",
  "properties": {
    "iso:country":"US",
    "sg:address":"5216 Sanford St",
    "sg:city":"Metairie",
    "sg:classifiers":[
        {
            "category":"Home & Garden",
            "subcategory":"Building Materials",
            "type":"Retail Goods"
        }
    ],
    "sg:phone":"+1 504 887 1182",
    "sg:postcode":"70006",
    "sg:province":"LA",
    "sg:tags":[
        "glass",
        "window",
        "plate"
    ],
    "wof:name":"Glass Glazing Spec Inc",
    "wof:placetype":"venue"
},
  "geometry": {"coordinates":[-90.198588,30.002902],"type":"Point"}
}