{
  "type": "Feature",
  "properties": {
    "iso:country":"US",
    "sg:address":"454 Bayou Dr",
    "sg:city":"Pierre Part",
    "sg:classifiers":[
        {
            "category":"Building & Trades",
            "subcategory":"Construction",
            "type":"Services"
        }
    ],
    "sg:phone":"+1 985 252 9900",
    "sg:postcode":"70339",
    "sg:province":"LA",
    "sg:tags":[
        "nonresidential"
    ],
    "wof:name":"Millet Contractors",
    "wof:placetype":"venue"
},
  "geometry": {"coordinates":[-91.19911399999999,29.985168],"type":"Point"}
}