{
  "type": "Feature",
  "properties": {
    "iso:country":"US",
    "sg:address":"301 Jefferson St",
    "sg:city":"New Iberia",
    "sg:classifiers":[
        {
            "category":"Wholesale",
            "subcategory":"Machinery & Supplies",
            "type":"Manufacturing & Wholesale Goods"
        }
    ],
    "sg:phone":"+1 337 367 9212",
    "sg:postcode":"70560",
    "sg:province":"LA",
    "sg:tags":[
        "pipe",
        "fitting"
    ],
    "sg:website":"www.coburns.com",
    "wof:name":"Coburn Supply Co",
    "wof:placetype":"venue"
},
  "geometry": {"coordinates":[-91.823279,30.006877],"type":"Point"}
}