{
  "type": "Feature",
  "properties": {
    "iso:country":"US",
    "sg:address":"198 David Dr",
    "sg:city":"Thibodaux",
    "sg:classifiers":[
        {
            "category":"Government",
            "subcategory":"Office",
            "type":"Public Place"
        }
    ],
    "sg:phone":"+1 985 446 7234",
    "sg:postcode":"70301",
    "sg:province":"LA",
    "sg:tags":[
        "village"
    ],
    "wof:name":"Thibodaux Sewage Plant",
    "wof:placetype":"venue"
},
  "geometry": {"coordinates":[-90.769756,29.769343],"type":"Point"}
}