{
  "type": "Feature",
  "properties": {
    "iso:country":"US",
    "sg:address":"427 Hoffpauir Rd",
    "sg:city":"Ragley",
    "sg:classifiers":[
        {
            "category":"Wholesale",
            "subcategory":"Farm Supplies",
            "type":"Manufacturing & Wholesale Goods"
        }
    ],
    "sg:phone":"+1 337 725 3343",
    "sg:postcode":"70657",
    "sg:province":"LA",
    "wof:name":"Hoffpauir Farm Ranch",
    "wof:placetype":"venue"
},
  "geometry": {"coordinates":[-93.265849,30.482728],"type":"Point"}
}