{
  "type": "Feature",
  "properties": {
    "iso:country":"US",
    "sg:address":"421 Burdette St",
    "sg:city":"New Orleans",
    "sg:classifiers":[
        {
            "category":"Education",
            "subcategory":"School",
            "type":"Public Place"
        }
    ],
    "sg:phone":"+1 504 862 5157",
    "sg:postcode":"70118",
    "sg:province":"LA",
    "wof:name":"Benjamin Banneker",
    "wof:placetype":"venue"
},
  "geometry": {"coordinates":[-90.13261900000001,29.940155],"type":"Point"}
}