{
  "type": "Feature",
  "properties": {
    "iso:country":"US",
    "sg:address":"16090 Hwy 16",
    "sg:city":"French Settlemnt",
    "sg:classifiers":[
        {
            "category":"Autos & Motor Vehicles",
            "subcategory":"Fuel & Gas Station",
            "type":"Retail Goods"
        }
    ],
    "sg:phone":"+1 225 698 9627",
    "sg:postcode":"70733",
    "sg:province":"LA",
    "sg:tags":[
        "oil"
    ],
    "wof:name":"Khalsa International Inc",
    "wof:placetype":"venue"
},
  "geometry": {"coordinates":[-90.79951,30.301884],"type":"Point"}
}