{
  "type": "Feature",
  "properties": {
    "addr:full":"7310 Memorial Rd Cloutierville LA 70659",
    "addr:housenumber":"7310",
    "addr:postcode":"70659",
    "addr:street":"Memorial Rd",
    "iso:country":"US",
    "sg:address":"7310 Memorial Rd",
    "sg:city":"Cloutierville",
    "sg:classifiers":[
        {
            "category":"Professional",
            "subcategory":"Management & Consulting",
            "type":"Services"
        },
        {
            "category":"Manufacturing",
            "subcategory":"Lumber",
            "type":"Manufacturing & Wholesale Goods"
        }
    ],
    "sg:phone":"+1 337 462 5105",
    "sg:postcode":"70659",
    "sg:province":"LA",
    "sg:tags":[
        "forester",
        "business"
    ],
    "wof:name":"Tim Cooper Forestry Consultant",
    "wof:placetype":"venue"
},
  "geometry": {"coordinates":[-93.291704,30.934099],"type":"Point"}
}