{
  "type": "Feature",
  "properties": {
    "iso:country":"US",
    "sg:address":"200 Crofton Rd",
    "sg:city":"Kenner",
    "sg:classifiers":[
        {
            "category":"Freight",
            "type":"Transportation"
        }
    ],
    "sg:phone":"+1 504 468 2712",
    "sg:postcode":"70062",
    "sg:province":"LA",
    "sg:tags":[
        "broker",
        "customs"
    ],
    "wof:name":"Robert W Cisco",
    "wof:placetype":"venue"
},
  "geometry": {"coordinates":[-90.270625,29.98536],"type":"Point"}
}