{
  "type": "Feature",
  "properties": {
    "addr:full":"5228 Greenwood Rd Shreveport LA 71109",
    "addr:housenumber":"5228",
    "addr:postcode":"71109",
    "addr:street":"Greenwood Rd",
    "iso:country":"US",
    "sg:address":"5228 Greenwood Rd",
    "sg:city":"Shreveport",
    "sg:classifiers":[
        {
            "category":"Professional",
            "subcategory":"Business Services",
            "type":"Services"
        },
        {
            "category":"Government",
            "subcategory":"Department Of Motor Vehicles",
            "type":"Public Place"
        }
    ],
    "sg:phone":"+1 318 550 0417",
    "sg:postcode":"71109",
    "sg:province":"LA",
    "sg:tags":[
        "tags-vehicle",
        "license"
    ],
    "wof:name":"Anc Auto Title",
    "wof:placetype":"venue"
},
  "geometry": {"coordinates":[-93.837298,32.465408],"type":"Point"}
}