{
  "type": "Feature",
  "properties": {
    "iso:country":"US",
    "sg:address":"414 N 4th St",
    "sg:city":"Baton Rouge",
    "sg:classifiers":[
        {
            "category":"Government",
            "subcategory":"Office",
            "type":"Public Place"
        }
    ],
    "sg:phone":"+1 225 342 2512",
    "sg:postcode":"70802",
    "sg:province":"LA",
    "wof:name":"Quality Assurance Div",
    "wof:placetype":"venue"
},
  "geometry": {"coordinates":[-91.187059,30.451311],"type":"Point"}
}