{
  "type": "Feature",
  "properties": {
    "iso:country":"US",
    "sg:address":"5640 Airline Hwy",
    "sg:city":"Baton Rouge",
    "sg:classifiers":[
        {
            "category":"Banks & Credit Unions",
            "subcategory":"Bank",
            "type":"Services"
        }
    ],
    "sg:phone":"+1 225 248 7186",
    "sg:postcode":"70805",
    "sg:province":"LA",
    "wof:name":"Hancock Bank",
    "wof:placetype":"venue"
},
  "geometry": {"coordinates":[-91.13245999999999,30.503807],"type":"Point"}
}