{
  "type": "Feature",
  "properties": {
    "iso:country":"US",
    "sg:address":"6115 Johnston St",
    "sg:city":"Lafayette",
    "sg:classifiers":[
        {
            "category":"Building & Trades",
            "subcategory":"Construction",
            "type":"Services"
        }
    ],
    "sg:phone":"+1 337 983 0301",
    "sg:postcode":"70503",
    "sg:province":"LA",
    "sg:tags":[
        "general",
        "contractor"
    ],
    "wof:name":"Kas Construction",
    "wof:placetype":"venue"
},
  "geometry": {"coordinates":[-92.083501,30.164826],"type":"Point"}
}