{
  "type": "Feature",
  "properties": {
    "addr:full":"570 Ave A Westwego LA 70094",
    "addr:housenumber":"570",
    "addr:postcode":"70094",
    "addr:street":"Ave A Westwego",
    "iso:country":"US",
    "sg:address":"570 Ave A",
    "sg:city":"Westwego",
    "sg:classifiers":[
        {
            "category":"Social Services",
            "subcategory":"Child Care",
            "type":"Services"
        }
    ],
    "sg:phone":"+1 504 340 7093",
    "sg:postcode":"70094",
    "sg:province":"LA",
    "wof:name":"A-Bear's Day Care Ctr Inc",
    "wof:placetype":"venue"
},
  "geometry": {"coordinates":[-90.145308,29.908924],"type":"Point"}
}