{
  "type": "Feature",
  "properties": {
    "iso:country":"US",
    "sg:address":"2552 Airline Dr",
    "sg:city":"Bossier City",
    "sg:classifiers":[
        {
            "category":"Autos & Motor Vehicles",
            "subcategory":"Fuel & Gas Station",
            "type":"Retail Goods"
        }
    ],
    "sg:phone":"+1 318 549 1985",
    "sg:postcode":"71111",
    "sg:province":"LA",
    "sg:tags":[
        "oil"
    ],
    "wof:name":"Murphy USA",
    "wof:placetype":"venue"
},
  "geometry": {"coordinates":[-93.70832799999999,32.541266],"type":"Point"}
}