{
  "type": "Feature",
  "properties": {
    "iso:country":"US",
    "sg:address":"327 Meadow St",
    "sg:city":"Jena",
    "sg:classifiers":[
        {
            "category":"Shopping",
            "subcategory":"Florist",
            "type":"Retail Goods"
        }
    ],
    "sg:phone":"+1 318 992 5450",
    "sg:postcode":"71360",
    "sg:province":"LA",
    "wof:name":"D J's Cermaics & Flowers",
    "wof:placetype":"venue"
},
  "geometry": {"coordinates":[-92.41248,31.325568],"type":"Point"}
}