{
  "type": "Feature",
  "properties": {
    "iso:country":"US",
    "sg:address":"3547 Hwy 190",
    "sg:city":"Mandeville",
    "sg:classifiers":[
        {
            "category":"Home & Garden",
            "subcategory":"Home Furnishings",
            "type":"Retail Goods"
        }
    ],
    "sg:phone":"+1 985 727 9368",
    "sg:postcode":"70471",
    "sg:province":"LA",
    "sg:tags":[
        "lamp",
        "shades"
    ],
    "wof:name":"Lighting Inc",
    "wof:placetype":"venue"
},
  "geometry": {"coordinates":[-90.088303,30.393763],"type":"Point"}
}