{
  "type": "Feature",
  "properties": {
    "iso:country":"US",
    "sg:address":"140 Northeast Rd",
    "sg:city":"Monroe",
    "sg:classifiers":[
        {
            "category":"Building & Trades",
            "subcategory":"Landscaping Services",
            "type":"Services"
        }
    ],
    "sg:phone":"+1 318 323 4234",
    "sg:postcode":"71202",
    "sg:province":"LA",
    "sg:tags":[
        "tree"
    ],
    "wof:name":"Northeast LA Tree Svc Inc",
    "wof:placetype":"venue"
},
  "geometry": {"coordinates":[-92.047904,32.511886],"type":"Point"}
}