{
  "type": "Feature",
  "properties": {
    "addr:full":"7211 Weeks Island Rd New Iberia LA 70560",
    "addr:housenumber":"7211",
    "addr:postcode":"70560",
    "addr:street":"Weeks Island Rd",
    "iso:country":"US",
    "sg:address":"7211 Weeks Island Rd",
    "sg:city":"New Iberia",
    "sg:classifiers":[
        {
            "category":"Organizations",
            "subcategory":"Religious Organization",
            "type":"Services"
        }
    ],
    "sg:phone":"+1 337 364 8557",
    "sg:postcode":"70560",
    "sg:province":"LA",
    "sg:tags":[
        "church"
    ],
    "wof:name":"United Pentecostal Church",
    "wof:placetype":"venue"
},
  "geometry": {"coordinates":[-91.78830499999999,29.845716],"type":"Point"}
}