{
  "type": "Feature",
  "properties": {
    "iso:country":"US",
    "sg:address":"1521 Corporate Dr",
    "sg:city":"Shreveport",
    "sg:classifiers":[
        {
            "category":"Professional",
            "subcategory":"Detective & Security Services",
            "type":"Services"
        }
    ],
    "sg:phone":"+1 318 425 3201",
    "sg:postcode":"71107",
    "sg:province":"LA",
    "sg:tags":[
        "car",
        "armored"
    ],
    "sg:website":"www.loomisfargo.com",
    "wof:name":"Loomis Fargo & Co",
    "wof:placetype":"venue"
},
  "geometry": {"coordinates":[-93.777961,32.535718],"type":"Point"}
}