{
  "type": "Feature",
  "properties": {
    "addr:full":"1140 Choctaw Rd Thibodaux LA 70301",
    "addr:housenumber":"1140",
    "addr:postcode":"70301",
    "addr:street":"Choctaw Rd",
    "iso:country":"US",
    "sg:address":"1140 Choctaw Rd",
    "sg:city":"Thibodaux",
    "sg:classifiers":[
        {
            "category":"Building & Trades",
            "subcategory":"Plumbing",
            "type":"Services"
        }
    ],
    "sg:phone":"+1 985 633 2038",
    "sg:postcode":"70301",
    "sg:province":"LA",
    "sg:tags":[
        "conditioning",
        "air",
        "system",
        "contractor"
    ],
    "wof:name":"Alton's Heating & Air",
    "wof:placetype":"venue"
},
  "geometry": {"coordinates":[-90.779742,29.880856],"type":"Point"}
}