{
  "type": "Feature",
  "properties": {
    "iso:country":"US",
    "sg:address":"436 Ave G",
    "sg:city":"Port Allen",
    "sg:classifiers":[
        {
            "category":"Building & Trades",
            "subcategory":"Construction",
            "type":"Services"
        }
    ],
    "sg:phone":"+1 225 383 7748",
    "sg:postcode":"70767",
    "sg:province":"LA",
    "sg:tags":[
        "general",
        "contractor"
    ],
    "wof:name":"Tri-J UNLIMITED LLC",
    "wof:placetype":"venue"
},
  "geometry": {"coordinates":[-91.20361200000001,30.44686],"type":"Point"}
}