{
  "type": "Feature",
  "properties": {
    "iso:country":"US",
    "sg:address":"11638 Timber Ridge Dr",
    "sg:city":"Keithville",
    "sg:classifiers":[
        {
            "category":"Building & Trades",
            "subcategory":"Construction",
            "type":"Services"
        }
    ],
    "sg:phone":"+1 318 925 3089",
    "sg:postcode":"71047",
    "sg:province":"LA",
    "sg:tags":[
        "house"
    ],
    "wof:name":"D & W Construction Inc",
    "wof:placetype":"venue"
},
  "geometry": {"coordinates":[-93.93504900000001,32.311844],"type":"Point"}
}