{
  "type": "Feature",
  "properties": {
    "iso:country":"US",
    "sg:address":"10501 E Kings Hwy",
    "sg:city":"Shreveport",
    "sg:classifiers":[
        {
            "category":"Personal",
            "subcategory":"Beauty Salon",
            "type":"Services"
        }
    ],
    "sg:phone":"+1 318 797 9459",
    "sg:postcode":"71115",
    "sg:province":"LA",
    "wof:name":"Rapusnsel Beauty Shop",
    "wof:placetype":"venue"
},
  "geometry": {"coordinates":[-93.691411,32.410876],"type":"Point"}
}