{
  "type": "Feature",
  "properties": {
    "iso:country":"US",
    "sg:address":"218 N Domingue Ave",
    "sg:city":"Lafayette",
    "sg:classifiers":[
        {
            "category":"Social Services",
            "subcategory":"Child Care",
            "type":"Services"
        }
    ],
    "sg:phone":"+1 337 988 0137",
    "sg:postcode":"70506",
    "sg:province":"LA",
    "wof:name":"Sarah's Day Care Ctr",
    "wof:placetype":"venue"
},
  "geometry": {"coordinates":[-92.083651,30.198377],"type":"Point"}
}