{
  "type": "Feature",
  "properties": {
    "iso:country":"US",
    "sg:address":"2106 Red Cut Rd",
    "sg:city":"West Monroe",
    "sg:classifiers":[
        {
            "category":"Professional",
            "type":"Services"
        }
    ],
    "sg:phone":"+1 318 388 0314",
    "sg:postcode":"71292",
    "sg:province":"LA",
    "sg:tags":[
        "establishment"
    ],
    "wof:name":"Memorial Designs Inc",
    "wof:placetype":"venue"
},
  "geometry": {"coordinates":[-92.179726,32.364535],"type":"Point"}
}