{
  "type": "Feature",
  "properties": {
    "iso:country":"US",
    "sg:address":"3703 Arkansas Ave",
    "sg:city":"Kenner",
    "sg:classifiers":[
        {
            "category":"Building & Trades",
            "subcategory":"Construction",
            "type":"Services"
        }
    ],
    "sg:phone":"+1 504 467 5635",
    "sg:postcode":"70065",
    "sg:province":"LA",
    "sg:tags":[
        "house"
    ],
    "wof:name":"Casanova Construction LLC",
    "wof:placetype":"venue"
},
  "geometry": {"coordinates":[-90.244857,30.025543],"type":"Point"}
}