{
  "type": "Feature",
  "properties": {
    "addr:full":"3127 Transcontinental Dr Metairie LA 70006",
    "addr:postcode":"3127;70006",
    "addr:street":"Transcontinental Dr",
    "iso:country":"US",
    "sg:address":"3127 Transcontinental Dr",
    "sg:city":"Metairie",
    "sg:classifiers":[
        {
            "category":"Real Estate",
            "subcategory":"Real Estate Operator",
            "type":"Services"
        }
    ],
    "sg:phone":"+1 504 455 4222",
    "sg:postcode":"70006",
    "sg:province":"LA",
    "sg:tags":[
        "apartment"
    ],
    "wof:name":"Canterbury Square",
    "wof:placetype":"venue"
},
  "geometry": {"coordinates":[-90.194267,30.003943],"type":"Point"}
}