{
  "type": "Feature",
  "properties": {
    "iso:country":"US",
    "sg:address":"10761 Bank St",
    "sg:city":"Clinton",
    "sg:classifiers":[
        {
            "category":"Retail",
            "subcategory":"Funeral Services",
            "type":"Services"
        }
    ],
    "sg:phone":"+1 225 683 5176",
    "sg:postcode":"70722",
    "sg:province":"LA",
    "sg:tags":[
        "director"
    ],
    "wof:name":"Charlet Funeral Home Inc",
    "wof:placetype":"venue"
},
  "geometry": {"coordinates":[-91.018986,30.859054],"type":"Point"}
}