{
  "type": "Feature",
  "properties": {
    "addr:full":"4724 Lakewood Dr Metairie LA 70002",
    "addr:housenumber":"4724",
    "addr:postcode":"70002",
    "addr:street":"Lakewood Dr",
    "iso:country":"US",
    "sg:address":"4724 Lakewood Dr",
    "sg:city":"Metairie",
    "sg:classifiers":[
        {
            "category":"Professional",
            "type":"Services"
        }
    ],
    "sg:phone":"+1 504 888 3005",
    "sg:postcode":"70002",
    "sg:province":"LA",
    "wof:name":"R F Lusky",
    "wof:placetype":"venue"
},
  "geometry": {"coordinates":[-90.178381,30.020503],"type":"Point"}
}