{
  "type": "Feature",
  "properties": {
    "addr:full":"28105 Hwy 190 Lacombe LA 70445",
    "addr:housenumber":"28105",
    "addr:postcode":"70445",
    "addr:street":"Hwy 190",
    "iso:country":"US",
    "sg:address":"28105 Hwy 190",
    "sg:city":"Lacombe",
    "sg:classifiers":[
        {
            "category":"Personal",
            "subcategory":"Barber",
            "type":"Services"
        }
    ],
    "sg:phone":"+1 985 882 2313",
    "sg:postcode":"70445",
    "sg:province":"LA",
    "wof:name":"Kneal's Barber Shop",
    "wof:placetype":"venue"
},
  "geometry": {"coordinates":[-89.94054,30.312519],"type":"Point"}
}