{
  "type": "Feature",
  "properties": {
    "iso:country":"US",
    "sg:address":"3145 Ohio St",
    "sg:city":"Kenner",
    "sg:classifiers":[
        {
            "category":"Professional",
            "type":"Services"
        }
    ],
    "sg:phone":"+1 504 305 1168",
    "sg:postcode":"70065",
    "sg:province":"LA",
    "wof:name":"Dunlap & Dunlap Inc",
    "wof:placetype":"venue"
},
  "geometry": {"coordinates":[-90.250995,30.012458],"type":"Point"}
}