{
  "type": "Feature",
  "properties": {
    "iso:country":"US",
    "sg:address":"105 N Main St",
    "sg:city":"Marksville",
    "sg:classifiers":[
        {
            "category":"Manufacturing",
            "subcategory":"Printing",
            "type":"Manufacturing & Wholesale Goods"
        }
    ],
    "sg:phone":"+1 318 253 9247",
    "sg:postcode":"71351",
    "sg:province":"LA",
    "sg:tags":[
        "newspaper"
    ],
    "wof:name":"Weekly News",
    "wof:placetype":"venue"
},
  "geometry": {"coordinates":[-92.066839,31.126712],"type":"Point"}
}