{
  "type": "Feature",
  "properties": {
    "addr:full":"12346 Kingston Dr Baton Rouge LA 70807",
    "addr:housenumber":"12346",
    "addr:postcode":"70807",
    "addr:street":"Kingston Dr",
    "iso:country":"US",
    "sg:address":"12346 Kingston Dr",
    "sg:city":"Baton Rouge",
    "sg:classifiers":[
        {
            "category":"Professional",
            "subcategory":"Management & Consulting",
            "type":"Services"
        }
    ],
    "sg:phone":"+1 225 778 9900",
    "sg:postcode":"70807",
    "sg:province":"LA",
    "sg:tags":[
        "business"
    ],
    "wof:name":"Selders Automotive Transp",
    "wof:placetype":"venue"
},
  "geometry": {"coordinates":[-91.161646,30.556474],"type":"Point"}
}