{
  "type": "Feature",
  "properties": {
    "iso:country":"US",
    "sg:address":"620 Markham Dr",
    "sg:city":"Slidell",
    "sg:classifiers":[
        {
            "category":"Building & Trades",
            "subcategory":"Plumbing",
            "type":"Services"
        }
    ],
    "sg:phone":"+1 985 643 1089",
    "sg:postcode":"70458",
    "sg:province":"LA",
    "sg:tags":[
        "conditioning",
        "air",
        "system",
        "contractor"
    ],
    "wof:name":"Steele Air Conditioning & Heat",
    "wof:placetype":"venue"
},
  "geometry": {"coordinates":[-89.780492,30.250157],"type":"Point"}
}