{
  "type": "Feature",
  "properties": {
    "iso:country":"US",
    "sg:address":"318 W 18th St",
    "sg:city":"Lake Charles",
    "sg:classifiers":[
        {
            "category":"Professional",
            "subcategory":"Business Services",
            "type":"Services"
        }
    ],
    "sg:phone":"+1 337 439 8070",
    "sg:postcode":"70601",
    "sg:province":"LA",
    "wof:name":"Betty Smith",
    "wof:placetype":"venue"
},
  "geometry": {"coordinates":[-93.22514200000001,30.205697],"type":"Point"}
}