{
  "type": "Feature",
  "properties": {
    "iso:country":"US",
    "sg:address":"1939 Hickory Ave",
    "sg:city":"Harahan",
    "sg:classifiers":[
        {
            "category":"Professional",
            "subcategory":"Lawyer & Legal Services",
            "type":"Services"
        }
    ],
    "sg:phone":"+1 504 738 2849",
    "sg:postcode":"70123",
    "sg:province":"LA",
    "sg:tags":[
        "attorney"
    ],
    "wof:name":"Zoe O Fleming",
    "wof:placetype":"venue"
},
  "geometry": {"coordinates":[-90.20809,29.970763],"type":"Point"}
}