{
  "type": "Feature",
  "properties": {
    "iso:country":"US",
    "sg:address":"650 N Ardenwood Dr",
    "sg:city":"Baton Rouge",
    "sg:classifiers":[
        {
            "category":"Personal",
            "subcategory":"Beauty Salon",
            "type":"Services"
        }
    ],
    "sg:phone":"+1 225 201 0600",
    "sg:postcode":"70806",
    "sg:province":"LA",
    "wof:name":"Doris Beauty & Style",
    "wof:placetype":"venue"
},
  "geometry": {"coordinates":[-91.12732200000001,30.451443],"type":"Point"}
}