{
  "type": "Feature",
  "properties": {
    "iso:country":"US",
    "sg:address":"10129 Hyde Pl",
    "sg:city":"River Ridge",
    "sg:classifiers":[
        {
            "category":"Professional",
            "subcategory":"Business Services",
            "type":"Services"
        }
    ],
    "sg:phone":"+1 504 737 8383",
    "sg:postcode":"70123",
    "sg:province":"LA",
    "wof:name":"Organize It",
    "wof:placetype":"venue"
},
  "geometry": {"coordinates":[-90.21375999999999,29.96891],"type":"Point"}
}