{
  "type": "Feature",
  "properties": {
    "addr:full":"107 W Tampico St New Iberia LA 70563",
    "addr:housenumber":"107",
    "addr:postcode":"70563",
    "addr:street":"W Tampico St",
    "iso:country":"US",
    "sg:address":"107 W Tampico St",
    "sg:city":"New Iberia",
    "sg:classifiers":[
        {
            "category":"Insurance",
            "subcategory":"Hazard Insurance",
            "type":"Services"
        }
    ],
    "sg:phone":"+1 337 367 9993",
    "sg:postcode":"70563",
    "sg:province":"LA",
    "sg:tags":[
        "bond"
    ],
    "wof:name":"A-Able Bonding Co",
    "wof:placetype":"venue"
},
  "geometry": {"coordinates":[-91.814843,30.026187],"type":"Point"}
}