{
  "type": "Feature",
  "properties": {
    "iso:country":"US",
    "sg:address":"250 Holt St",
    "sg:city":"Bastrop",
    "sg:classifiers":[
        {
            "category":"Social Services",
            "subcategory":"Job Training",
            "type":"Services"
        }
    ],
    "sg:phone":"+1 318 283 0849",
    "sg:postcode":"71220",
    "sg:province":"LA",
    "sg:tags":[
        "rehab",
        "government"
    ],
    "sg:website":"www.laworks.net",
    "wof:name":"Employment Office",
    "wof:placetype":"venue"
},
  "geometry": {"coordinates":[-91.88969400000001,32.779597],"type":"Point"}
}