{
  "type": "Feature",
  "properties": {
    "addr:full":"2500 Lapalco Blvd Ste 7 Harvey LA 70058",
    "addr:housenumber":"2500",
    "addr:postcode":"70058",
    "addr:street":"Lapalco Blvd Ste 7 Harvey",
    "iso:country":"US",
    "sg:address":"2500 Lapalco Blvd Ste 7",
    "sg:city":"Harvey",
    "sg:classifiers":[
        {
            "category":"Arts & Performance",
            "subcategory":"Music",
            "type":"Entertainment"
        }
    ],
    "sg:phone":"+1 504 366 2900",
    "sg:postcode":"70058",
    "sg:province":"LA",
    "sg:tags":[
        "dj"
    ],
    "sg:website":"www.adventagencies.com",
    "wof:name":"Advent Agencies",
    "wof:placetype":"venue"
},
  "geometry": {"coordinates":[-90.06059,29.873327],"type":"Point"}
}