{
  "type": "Feature",
  "properties": {
    "iso:country":"US",
    "sg:address":"4101 Hollywood Ave",
    "sg:city":"Shreveport",
    "sg:classifiers":[
        {
            "category":"Food & Beverages",
            "subcategory":"Groceries & Convenience Stores",
            "type":"Retail Goods"
        }
    ],
    "sg:phone":"+1 318 631 3671",
    "sg:postcode":"71109",
    "sg:province":"LA",
    "sg:tags":[
        "grocer"
    ],
    "wof:name":"R & W Consumer Grocery",
    "wof:placetype":"venue"
},
  "geometry": {"coordinates":[-93.80692500000001,32.456562],"type":"Point"}
}