{
  "type": "Feature",
  "properties": {
    "iso:country":"US",
    "sg:address":"7734 Hwy 1",
    "sg:city":"Mansura",
    "sg:classifiers":[
        {
            "category":"Manufacturing",
            "subcategory":"Metals",
            "type":"Manufacturing & Wholesale Goods"
        }
    ],
    "sg:phone":"+1 318 253 9907",
    "sg:postcode":"71350",
    "sg:province":"LA",
    "sg:tags":[
        "valve"
    ],
    "wof:name":"Kerotest Manufacturing Corp",
    "wof:placetype":"venue"
},
  "geometry": {"coordinates":[-92.055386,31.083165],"type":"Point"}
}