{
  "type": "Feature",
  "properties": {
    "iso:country":"US",
    "sg:address":"5956 Magazine St",
    "sg:city":"New Orleans",
    "sg:classifiers":[
        {
            "category":"Education",
            "subcategory":"Dance Studio",
            "type":"Public Place"
        }
    ],
    "sg:phone":"+1 504 899 3780",
    "sg:postcode":"70115",
    "sg:province":"LA",
    "sg:tags":[
        "instruction",
        "dancing"
    ],
    "wof:name":"New Orleans Dance Academy",
    "wof:placetype":"venue"
},
  "geometry": {"coordinates":[-90.120741,29.921829],"type":"Point"}
}