{
  "type": "Feature",
  "properties": {
    "addr:full":"145 Robert E Lee Blvd New Orleans LA 70124",
    "addr:housenumber":"145",
    "addr:postcode":"70124",
    "addr:street":"Robert E Lee Blvd",
    "iso:country":"US",
    "sg:address":"145 Robert E Lee Blvd",
    "sg:city":"New Orleans",
    "sg:classifiers":[
        {
            "category":"Health Services",
            "subcategory":"Doctor",
            "type":"Services"
        }
    ],
    "sg:phone":"+1 504 282 5398",
    "sg:postcode":"70124",
    "sg:province":"LA",
    "sg:tags":[
        "physician",
        "surgeon"
    ],
    "wof:name":"Frank Monte MD",
    "wof:placetype":"venue"
},
  "geometry": {"coordinates":[-90.11192200000001,30.020179],"type":"Point"}
}