{
  "type": "Feature",
  "properties": {
    "iso:country":"US",
    "sg:address":"10001 Lake Forest Blvd",
    "sg:city":"New Orleans",
    "sg:classifiers":[
        {
            "category":"Banks & Credit Unions",
            "subcategory":"Investment Brokerage",
            "type":"Services"
        }
    ],
    "sg:phone":"+1 504 245 2326",
    "sg:postcode":"70127",
    "sg:province":"LA",
    "sg:tags":[
        "advisory",
        "financial"
    ],
    "wof:name":"Complete Financial Svc LLC",
    "wof:placetype":"venue"
},
  "geometry": {"coordinates":[-89.975769,30.031112],"type":"Point"}
}