{
  "type": "Feature",
  "properties": {
    "iso:country":"US",
    "sg:address":"1000 Wildcat Dr",
    "sg:city":"Abbeville",
    "sg:classifiers":[
        {
            "category":"Health Services",
            "subcategory":"Chiropractor",
            "type":"Services"
        }
    ],
    "sg:phone":"+1 337 893 5252",
    "sg:postcode":"70510",
    "sg:province":"LA",
    "wof:name":"Chauvin Chiropractic Clinic",
    "wof:placetype":"venue"
},
  "geometry": {"coordinates":[-92.106267,29.980123],"type":"Point"}
}