{
  "type": "Feature",
  "properties": {
    "addr:full":"707 N Montgomery Ave Kaplan LA 70548",
    "addr:housenumber":"707",
    "addr:postcode":"70548",
    "addr:street":"N Montgomery Ave Kaplan La",
    "iso:country":"US",
    "sg:address":"707 N Montgomery Ave",
    "sg:city":"Kaplan",
    "sg:classifiers":[
        {
            "category":"Health Services",
            "subcategory":"Chiropractor",
            "type":"Services"
        }
    ],
    "sg:phone":"+1 337 643 6546",
    "sg:postcode":"70548",
    "sg:province":"LA",
    "wof:name":"Chiropractic Pain Management",
    "wof:placetype":"venue"
},
  "geometry": {"coordinates":[-92.29601099999999,30.008114],"type":"Point"}
}