{
  "type": "Feature",
  "properties": {
    "addr:full":"201 Westmark Blvd Lafayette LA 70506",
    "addr:housenumber":"201",
    "addr:postcode":"70506",
    "addr:street":"Westmark Blvd",
    "iso:country":"US",
    "sg:address":"201 Westmark Blvd",
    "sg:city":"Lafayette",
    "sg:classifiers":[
        {
            "category":"Shopping",
            "type":"Retail Goods"
        }
    ],
    "sg:phone":"+1 337 981 1758",
    "sg:postcode":"70506",
    "sg:province":"LA",
    "sg:tags":[
        "aquarium"
    ],
    "sg:website":"www.tropicalfishbowl.com",
    "wof:name":"Tropical Fish Bowl",
    "wof:placetype":"venue"
},
  "geometry": {"coordinates":[-92.074979,30.184396],"type":"Point"}
}