{
  "type": "Feature",
  "properties": {
    "iso:country":"US",
    "sg:address":"304 E Morris Ave",
    "sg:city":"Hammond",
    "sg:classifiers":[
        {
            "category":"Shopping",
            "subcategory":"Florist",
            "type":"Retail Goods"
        }
    ],
    "sg:phone":"+1 985 345 0525",
    "sg:postcode":"70403",
    "sg:province":"LA",
    "wof:name":"Carol's Flowers Crafts & Gifts",
    "wof:placetype":"venue"
},
  "geometry": {"coordinates":[-90.45719699999999,30.503833],"type":"Point"}
}