{
  "type": "Feature",
  "properties": {
    "iso:country":"US",
    "sg:address":"3116 College Dr",
    "sg:city":"Baton Rouge",
    "sg:classifiers":[
        {
            "category":"Shopping",
            "subcategory":"Stationery & Office Supplies",
            "type":"Retail Goods"
        }
    ],
    "sg:phone":"+1 225 927 0034",
    "sg:postcode":"70808",
    "sg:province":"LA",
    "sg:website":"www.officedepot.com",
    "wof:name":"Office Depot",
    "wof:placetype":"venue"
},
  "geometry": {"coordinates":[-91.14075200000001,30.420754],"type":"Point"}
}