{
  "type": "Feature",
  "properties": {
    "iso:country":"US",
    "sg:address":"3229 Ambassador Caffery Pkwy",
    "sg:city":"Lafayette",
    "sg:classifiers":[
        {
            "category":"Shopping",
            "subcategory":"Clothing, Apparel, & Fashions",
            "type":"Retail Goods"
        }
    ],
    "sg:phone":"+1 337 981 7946",
    "sg:postcode":"70506",
    "sg:province":"LA",
    "sg:tags":[
        "swimwear",
        "accessory"
    ],
    "sg:website":"www.getwetshop.com",
    "wof:name":"Get Wet",
    "wof:placetype":"venue"
},
  "geometry": {"coordinates":[-92.074889,30.182838],"type":"Point"}
}