{
  "type": "Feature",
  "properties": {
    "iso:country":"US",
    "sg:address":"806 Roberts Ave",
    "sg:city":"Jennings",
    "sg:classifiers":[
        {
            "category":"Utilities",
            "type":"Services"
        }
    ],
    "sg:phone":"+1 337 824 3497",
    "sg:postcode":"70546",
    "sg:province":"LA",
    "sg:tags":[
        "management"
    ],
    "wof:name":"American Meter Svc",
    "wof:placetype":"venue"
},
  "geometry": {"coordinates":[-92.647582,30.233949],"type":"Point"}
}