{
  "type": "Feature",
  "properties": {
    "iso:country":"US",
    "sg:address":"707 S Main St",
    "sg:city":"Springhill",
    "sg:classifiers":[
        {
            "category":"Utilities",
            "subcategory":"Mobile Phone",
            "type":"Services"
        }
    ],
    "sg:phone":"+1 318 539 4261",
    "sg:postcode":"71075",
    "sg:province":"LA",
    "sg:tags":[
        "telephone",
        "cellular"
    ],
    "wof:name":"Russell Cellular & Satellite",
    "wof:placetype":"venue"
},
  "geometry": {"coordinates":[-93.461184,32.995003],"type":"Point"}
}