{
  "type": "Feature",
  "properties": {
    "iso:country":"US",
    "sg:address":"930 Tunica Dr E",
    "sg:city":"Marksville",
    "sg:classifiers":[
        {
            "category":"Wholesale",
            "subcategory":"Auto Parts",
            "type":"Manufacturing & Wholesale Goods"
        }
    ],
    "sg:phone":"+1 318 253 7253",
    "sg:postcode":"71351",
    "sg:province":"LA",
    "sg:tags":[
        "automobile",
        "rebuilt"
    ],
    "wof:name":"Lemoine's Auto Parts",
    "wof:placetype":"venue"
},
  "geometry": {"coordinates":[-92.06410700000001,31.110172],"type":"Point"}
}