{
  "type": "Feature",
  "properties": {
    "addr:full":"3316 Transcontinental Dr Metairie LA 70006",
    "addr:housenumber":"3316",
    "addr:postcode":"70006",
    "addr:street":"Transcontinental Dr",
    "iso:country":"US",
    "sg:address":"3316 Transcontinental Dr",
    "sg:city":"Metairie",
    "sg:classifiers":[
        {
            "category":"Personal",
            "subcategory":"Beauty Salon",
            "type":"Services"
        }
    ],
    "sg:phone":"+1 504 887 7518",
    "sg:postcode":"70006",
    "sg:province":"LA",
    "sg:tags":[
        "manicuring"
    ],
    "wof:name":"Dulce's Beauty Ctr",
    "wof:placetype":"venue"
},
  "geometry": {"coordinates":[-90.19550599999999,30.006744],"type":"Point"}
}