{
  "type": "Feature",
  "properties": {
    "addr:full":"4605 W Congress St Lafayette LA 70506",
    "addr:housenumber":"4605",
    "addr:postcode":"70506",
    "addr:street":"W Congress St",
    "iso:country":"US",
    "sg:address":"4605 W Congress St",
    "sg:city":"Lafayette",
    "sg:classifiers":[
        {
            "category":"Retail",
            "subcategory":"Auto Repair",
            "type":"Services"
        }
    ],
    "sg:phone":"+1 337 988 6677",
    "sg:postcode":"70506",
    "sg:province":"LA",
    "sg:tags":[
        "repairing",
        "automobile"
    ],
    "sg:website":"www.zimstires.com",
    "wof:name":"Zim's Alignment Automotive",
    "wof:placetype":"venue"
},
  "geometry": {"coordinates":[-92.08399199999999,30.195768],"type":"Point"}
}