{
  "type": "Feature",
  "properties": {
    "iso:country":"US",
    "sg:address":"278 Ozia Skyline",
    "sg:city":"Houma",
    "sg:classifiers":[
        {
            "category":"Organizations",
            "subcategory":"Religious Organization",
            "type":"Services"
        }
    ],
    "sg:phone":"+1 985 876 4358",
    "sg:postcode":"70364",
    "sg:province":"LA",
    "wof:name":"Magnolia Evangelism Inc",
    "wof:placetype":"venue"
},
  "geometry": {"coordinates":[-90.687815,29.652667],"type":"Point"}
}