{
  "type": "Feature",
  "properties": {
    "iso:country":"US",
    "sg:address":"607 E Askew St",
    "sg:city":"Tallulah",
    "sg:classifiers":[
        {
            "category":"Professional",
            "subcategory":"Lawyer & Legal Services",
            "type":"Services"
        }
    ],
    "sg:phone":"+1 318 574 3133",
    "sg:postcode":"71282",
    "sg:province":"LA",
    "sg:tags":[
        "attorney"
    ],
    "wof:name":"Sevier Yerger & Bishop",
    "wof:placetype":"venue"
},
  "geometry": {"coordinates":[-91.18509400000001,32.408813],"type":"Point"}
}