{
  "type": "Feature",
  "properties": {
    "iso:country":"US",
    "sg:address":"108 W Simcoe St",
    "sg:city":"Lafayette",
    "sg:classifiers":[
        {
            "category":"Autos & Motor Vehicles",
            "subcategory":"Automobile Sales",
            "type":"Retail Goods"
        }
    ],
    "sg:phone":"+1 337 234 6826",
    "sg:postcode":"70501",
    "sg:province":"LA",
    "sg:tags":[
        "used"
    ],
    "wof:name":"Creole Motors",
    "wof:placetype":"venue"
},
  "geometry": {"coordinates":[-92.016525,30.231261],"type":"Point"}
}