{
  "type": "Feature",
  "properties": {
    "addr:full":"5334 Evangeline St Baton Rouge LA 70805",
    "addr:housenumber":"5334",
    "addr:postcode":"70805",
    "addr:street":"Evangeline St",
    "iso:country":"US",
    "sg:address":"5334 Evangeline St",
    "sg:city":"Baton Rouge",
    "sg:classifiers":[
        {
            "category":"Retail",
            "subcategory":"Auto Repair",
            "type":"Services"
        }
    ],
    "sg:phone":"+1 225 356 7850",
    "sg:postcode":"70805",
    "sg:province":"LA",
    "sg:tags":[
        "repairing",
        "automobile"
    ],
    "wof:name":"American Imports",
    "wof:placetype":"venue"
},
  "geometry": {"coordinates":[-91.137776,30.493202],"type":"Point"}
}