{
  "type": "Feature",
  "properties": {
    "iso:country":"US",
    "sg:address":"1901 Stafford St",
    "sg:city":"Gretna",
    "sg:classifiers":[
        {
            "category":"Retail",
            "subcategory":"Portrait Studio",
            "type":"Services"
        }
    ],
    "sg:phone":"+1 504 366 4505",
    "sg:postcode":"70053",
    "sg:province":"LA",
    "sg:tags":[
        "identification",
        "card"
    ],
    "wof:name":"Ident-A-Kid Svc",
    "wof:placetype":"venue"
},
  "geometry": {"coordinates":[-90.056877,29.902765],"type":"Point"}
}