{
  "type": "Feature",
  "properties": {
    "iso:country":"US",
    "sg:address":"100 Grand Ave",
    "sg:city":"Milton",
    "sg:classifiers":[
        {
            "category":"Wholesale",
            "subcategory":"Non-durable Goods",
            "type":"Manufacturing & Wholesale Goods"
        }
    ],
    "sg:phone":"+1 337 857 1300",
    "sg:postcode":"70592",
    "sg:province":"LA",
    "sg:tags":[
        "interior"
    ],
    "wof:name":"Prints Charming",
    "wof:placetype":"venue"
},
  "geometry": {"coordinates":[-92.07426599999999,30.104667],"type":"Point"}
}