{
  "type": "Feature",
  "properties": {
    "iso:country":"US",
    "sg:address":"4900 4th St",
    "sg:city":"Marrero",
    "sg:classifiers":[
        {
            "category":"Health Services",
            "subcategory":"Medical Lab",
            "type":"Services"
        }
    ],
    "sg:phone":"+1 504 341 9181",
    "sg:postcode":"70072",
    "sg:province":"LA",
    "sg:tags":[
        "laboratory"
    ],
    "wof:name":"Trafficano Dental Laboratory",
    "wof:placetype":"venue"
},
  "geometry": {"coordinates":[-90.10093500000001,29.903171],"type":"Point"}
}