{
  "type": "Feature",
  "properties": {
    "addr:full":"121 Hammett Rd Rayville LA 71269",
    "addr:housenumber":"121",
    "addr:postcode":"71269",
    "addr:street":"Hammett Rd",
    "iso:country":"US",
    "sg:address":"121 Hammett Rd",
    "sg:city":"Rayville",
    "sg:classifiers":[
        {
            "category":"Retail",
            "subcategory":"Auto Repair",
            "type":"Services"
        }
    ],
    "sg:phone":"+1 318 728 4070",
    "sg:postcode":"71269",
    "sg:province":"LA",
    "sg:tags":[
        "repairing",
        "automobile"
    ],
    "wof:name":"Hammett Well Svc Inc",
    "wof:placetype":"venue"
},
  "geometry": {"coordinates":[-91.779927,32.483769],"type":"Point"}
}