{
  "type": "Feature",
  "properties": {
    "iso:country":"US",
    "sg:address":"301 E Kaliste Saloom Rd",
    "sg:city":"Lafayette",
    "sg:classifiers":[
        {
            "category":"Insurance",
            "subcategory":"Hazard Insurance",
            "type":"Services"
        }
    ],
    "sg:phone":"+1 337 266 9626",
    "sg:postcode":"70508",
    "sg:province":"LA",
    "sg:tags":[
        "profit",
        "sharing",
        "pension",
        "plan"
    ],
    "wof:name":"Thurlow & Assoc Inc",
    "wof:placetype":"venue"
},
  "geometry": {"coordinates":[-92.00835499999999,30.194724],"type":"Point"}
}