{
  "type": "Feature",
  "properties": {
    "addr:full":"1196 State Rte 137 Rayville LA 71269",
    "addr:housenumber":"1196",
    "addr:postcode":"71269",
    "addr:street":"State Rte 137 Rayville",
    "iso:country":"US",
    "sg:address":"1196 State Rte 137",
    "sg:city":"Rayville",
    "sg:classifiers":[
        {
            "category":"Wholesale",
            "subcategory":"Machinery & Supplies",
            "type":"Manufacturing & Wholesale Goods"
        }
    ],
    "sg:phone":"+1 318 728 6423",
    "sg:postcode":"71269",
    "sg:province":"LA",
    "sg:tags":[
        "farm",
        "equipment"
    ],
    "wof:name":"Delta Ridge Implement Inc",
    "wof:placetype":"venue"
},
  "geometry": {"coordinates":[-91.759361,32.471639],"type":"Point"}
}