{
  "type": "Feature",
  "properties": {
    "addr:full":"2452 Murphy St Bossier City LA 71112",
    "addr:housenumber":"2452",
    "addr:postcode":"71112",
    "addr:street":"Murphy St",
    "iso:country":"US",
    "sg:address":"2452 Murphy St",
    "sg:city":"Bossier City",
    "sg:classifiers":[
        {
            "category":"Manufacturing",
            "subcategory":"Tools & Machinery",
            "type":"Manufacturing & Wholesale Goods"
        }
    ],
    "sg:phone":"+1 318 747 4301",
    "sg:postcode":"71112",
    "sg:province":"LA",
    "sg:tags":[
        "equipment",
        "dental",
        "supply"
    ],
    "wof:name":"Dee Dental Co",
    "wof:placetype":"venue"
},
  "geometry": {"coordinates":[-93.69471799999999,32.50842],"type":"Point"}
}