{
  "type": "Feature",
  "properties": {
    "iso:country":"US",
    "sg:address":"3748 N Causeway Blvd",
    "sg:city":"Metairie",
    "sg:classifiers":[
        {
            "category":"Professional",
            "subcategory":"Management & Consulting",
            "type":"Services"
        }
    ],
    "sg:phone":"+1 504 838 7222",
    "sg:postcode":"70002",
    "sg:province":"LA",
    "sg:tags":[
        "town",
        "city",
        "regional",
        "planner"
    ],
    "wof:name":"Master Planning Consortium",
    "wof:placetype":"venue"
},
  "geometry": {"coordinates":[-90.154417,30.016458],"type":"Point"}
}