{
  "type": "Feature",
  "properties": {
    "addr:full":"1216 11th St Lake Charles LA 70601",
    "addr:housenumber":"1216",
    "addr:postcode":"70601",
    "addr:street":"11Th St",
    "iso:country":"US",
    "sg:address":"1216 11th St",
    "sg:city":"Lake Charles",
    "sg:classifiers":[
        {
            "category":"Retail",
            "subcategory":"Animal Services",
            "type":"Services"
        }
    ],
    "sg:phone":"+1 337 436 2255",
    "sg:postcode":"70601",
    "sg:province":"LA",
    "sg:tags":[
        "pet",
        "boarding",
        "sitting"
    ],
    "wof:name":"Carole's Caring Touch Pet",
    "wof:placetype":"venue"
},
  "geometry": {"coordinates":[-93.20174,30.214139],"type":"Point"}
}