{
  "type": "Feature",
  "properties": {
    "iso:country":"US",
    "sg:address":"3131 Cameron St",
    "sg:city":"Lafayette",
    "sg:classifiers":[
        {
            "category":"Professional",
            "subcategory":"Research",
            "type":"Services"
        }
    ],
    "sg:phone":"+1 337 269 9114",
    "sg:postcode":"70506",
    "sg:province":"LA",
    "sg:tags":[
        "environmental",
        "ecological"
    ],
    "sg:website":"www.kourco.com",
    "wof:name":"Kourco Environmental",
    "wof:placetype":"venue"
},
  "geometry": {"coordinates":[-92.05616499999999,30.232509],"type":"Point"}
}