{
  "type": "Feature",
  "properties": {
    "addr:full":"1010 N 9th St Swartz LA 71291",
    "addr:housenumber":"1010",
    "addr:postcode":"71291",
    "addr:street":"N 9Th St",
    "iso:country":"US",
    "sg:address":"1010 N 9th St",
    "sg:city":"Swartz",
    "sg:classifiers":[
        {
            "category":"Insurance",
            "subcategory":"Insurance Agent",
            "type":"Services"
        }
    ],
    "sg:phone":"+1 318 361 4703",
    "sg:postcode":"71291",
    "sg:province":"LA",
    "wof:name":"Joe P Farr",
    "wof:placetype":"venue"
},
  "geometry": {"coordinates":[-92.136877,32.500734],"type":"Point"}
}