{
  "type": "Feature",
  "properties": {
    "addr:full":"6984 Modesto Ave Baton Rouge LA 70811",
    "addr:housenumber":"6984",
    "addr:postcode":"70811",
    "addr:street":"Modesto Ave",
    "iso:country":"US",
    "sg:address":"6984 Modesto Ave",
    "sg:city":"Baton Rouge",
    "sg:classifiers":[
        {
            "category":"Shopping",
            "subcategory":"Clothing, Apparel, & Fashions",
            "type":"Retail Goods"
        }
    ],
    "sg:phone":"+1 225 356 7738",
    "sg:postcode":"70811",
    "sg:province":"LA",
    "sg:tags":[
        "woman"
    ],
    "wof:name":"Total Image",
    "wof:placetype":"venue"
},
  "geometry": {"coordinates":[-91.11975099999999,30.521013],"type":"Point"}
}