{
  "type": "Feature",
  "properties": {
    "iso:country":"US",
    "sg:address":"712 Newton St",
    "sg:city":"Lake Charles",
    "sg:classifiers":[
        {
            "category":"Real Estate",
            "subcategory":"Surveying",
            "type":"Services"
        }
    ],
    "sg:phone":"+1 337 477 9387",
    "sg:postcode":"70607",
    "sg:province":"LA",
    "wof:name":"O Neil Herbert Land Surveyor",
    "wof:placetype":"venue"
},
  "geometry": {"coordinates":[-93.209981,30.145462],"type":"Point"}
}