{
  "type": "Feature",
  "properties": {
    "iso:country":"US",
    "sg:address":"2020 W Pinhook Rd",
    "sg:city":"Lafayette",
    "sg:classifiers":[
        {
            "category":"Manufacturing",
            "subcategory":"Printing",
            "type":"Manufacturing & Wholesale Goods"
        }
    ],
    "sg:phone":"+1 337 232 4831",
    "sg:postcode":"70508",
    "sg:province":"LA",
    "sg:tags":[
        "publisher",
        "guide"
    ],
    "sg:website":"www.yellowbook.com",
    "wof:name":"Yellow Book USA",
    "wof:placetype":"venue"
},
  "geometry": {"coordinates":[-92.01058500000001,30.185682],"type":"Point"}
}