{
  "type": "Feature",
  "properties": {
    "addr:full":"117 Macarthur Dr Alexandria LA 71303",
    "addr:housenumber":"117",
    "addr:postcode":"71303",
    "addr:street":"Macarthur Dr",
    "iso:country":"US",
    "sg:address":"117 Macarthur Dr",
    "sg:city":"Alexandria",
    "sg:classifiers":[
        {
            "category":"Professional",
            "subcategory":"Accounting & Tax Preparation",
            "type":"Services"
        }
    ],
    "sg:phone":"+1 318 445 7555",
    "sg:postcode":"71303",
    "sg:province":"LA",
    "sg:tags":[
        "return",
        "filing"
    ],
    "sg:website":"www.hrblock.com",
    "wof:name":"H & R Block Tax Svc",
    "wof:placetype":"venue"
},
  "geometry": {"coordinates":[-92.47945300000001,31.300706],"type":"Point"}
}