{
  "type": "Feature",
  "properties": {
    "addr:full":"904 Tate Cove Rd Ville Platte LA 70586",
    "addr:housenumber":"904",
    "addr:postcode":"70586",
    "addr:street":"Tate Cove Rd",
    "iso:country":"US",
    "sg:address":"904 Tate Cove Rd",
    "sg:city":"Ville Platte",
    "sg:classifiers":[
        {
            "category":"Personal",
            "subcategory":"Beauty Salon",
            "type":"Services"
        }
    ],
    "sg:phone":"+1 337 363 4339",
    "sg:postcode":"70586",
    "sg:province":"LA",
    "wof:name":"Juanita's Beauty Shop",
    "wof:placetype":"venue"
},
  "geometry": {"coordinates":[-92.262019,30.692999],"type":"Point"}
}