{
  "type": "Feature",
  "properties": {
    "iso:country":"US",
    "sg:address":"608 N Ave K",
    "sg:city":"Crowley",
    "sg:classifiers":[
        {
            "category":"Health Services",
            "subcategory":"Doctor",
            "type":"Services"
        }
    ],
    "sg:phone":"+1 337 788 0677",
    "sg:postcode":"70526",
    "sg:province":"LA",
    "sg:tags":[
        "dentist"
    ],
    "sg:website":"www.acadianasmiles.com",
    "wof:name":"Taylor & Broussard",
    "wof:placetype":"venue"
},
  "geometry": {"coordinates":[-92.369113,30.218566],"type":"Point"}
}