{
  "type": "Feature",
  "properties": {
    "iso:country":"US",
    "sg:address":"3422 Cleary Ave",
    "sg:city":"Metairie",
    "sg:classifiers":[
        {
            "category":"Professional",
            "subcategory":"Management & Consulting",
            "type":"Services"
        }
    ],
    "sg:phone":"+1 504 888 2733",
    "sg:postcode":"70002",
    "sg:province":"LA",
    "sg:tags":[
        "consultant",
        "business"
    ],
    "wof:name":"Client Services Unlimited",
    "wof:placetype":"venue"
},
  "geometry": {"coordinates":[-90.17273900000001,30.006113],"type":"Point"}
}