{
  "type": "Feature",
  "properties": {
    "iso:country":"US",
    "sg:address":"7600 Youree Dr",
    "sg:city":"Shreveport",
    "sg:classifiers":[
        {
            "category":"Autos & Motor Vehicles",
            "subcategory":"Auto Supplies",
            "type":"Retail Goods"
        }
    ],
    "sg:phone":"+1 318 797 8045",
    "sg:postcode":"71105",
    "sg:province":"LA",
    "sg:tags":[
        "automobile",
        "stereo",
        "radio"
    ],
    "sg:website":"www.wrightssoundgallery.com",
    "wof:name":"Wright's Sound Gallery Inc",
    "wof:placetype":"venue"
},
  "geometry": {"coordinates":[-93.711997,32.43181],"type":"Point"}
}