{
  "type": "Feature",
  "properties": {
    "iso:country":"US",
    "sg:address":"19130 Million Dollar Rd",
    "sg:city":"Covington",
    "sg:classifiers":[
        {
            "category":"Shopping",
            "subcategory":"Gifts & Souvenirs",
            "type":"Retail Goods"
        }
    ],
    "sg:phone":"+1 985 809 7511",
    "sg:postcode":"70435",
    "sg:province":"LA",
    "sg:tags":[
        "basket",
        "parcel"
    ],
    "wof:name":"Angelworks",
    "wof:placetype":"venue"
},
  "geometry": {"coordinates":[-90.08131899999999,30.577513],"type":"Point"}
}