{
  "type": "Feature",
  "properties": {
    "addr:full":"7701 Dwyer Rd New Orleans LA 70126",
    "addr:housenumber":"7701",
    "addr:postcode":"70126",
    "addr:street":"Dwyer Rd",
    "iso:country":"US",
    "sg:address":"7701 Dwyer Rd",
    "sg:city":"New Orleans",
    "sg:classifiers":[
        {
            "category":"Wholesale",
            "subcategory":"Drugs",
            "type":"Manufacturing & Wholesale Goods"
        }
    ],
    "sg:phone":"+1 504 242 0457",
    "sg:postcode":"70126",
    "sg:province":"LA",
    "sg:tags":[
        "perfume"
    ],
    "wof:name":"Saba Scents Intl Inc",
    "wof:placetype":"venue"
},
  "geometry": {"coordinates":[-89.998369,30.02238],"type":"Point"}
}