{
  "type": "Feature",
  "properties": {
    "addr:full":"4705 Conlin St Metairie LA 70006",
    "addr:housenumber":"4705",
    "addr:postcode":"70006",
    "addr:street":"Conlin St",
    "iso:country":"US",
    "sg:address":"4705 Conlin St",
    "sg:city":"Metairie",
    "sg:classifiers":[
        {
            "category":"Building & Trades",
            "subcategory":"Construction",
            "type":"Services"
        }
    ],
    "sg:phone":"+1 504 455 3706",
    "sg:postcode":"70006",
    "sg:province":"LA",
    "sg:tags":[
        "house"
    ],
    "wof:name":"Edward Enterprise Construction",
    "wof:placetype":"venue"
},
  "geometry": {"coordinates":[-90.19887300000001,30.023764],"type":"Point"}
}