{
  "type": "Feature",
  "properties": {
    "addr:full":"1258 Emmanuel Rd Cloutierville LA 71416",
    "addr:housenumber":"1258",
    "addr:postcode":"71416",
    "addr:street":"Emmanuel Rd",
    "iso:country":"US",
    "sg:address":"1258 Emmanuel Rd",
    "sg:city":"Cloutierville",
    "sg:classifiers":[
        {
            "category":"Utilities",
            "subcategory":"Refuse",
            "type":"Services"
        }
    ],
    "sg:phone":"+1 318 379 1344",
    "sg:postcode":"71416",
    "sg:province":"LA",
    "sg:tags":[
        "disposal",
        "waste"
    ],
    "wof:name":"Household Waste",
    "wof:placetype":"venue"
},
  "geometry": {"coordinates":[-92.929339,31.498772],"type":"Point"}
}