{
  "type": "Feature",
  "properties": {
    "iso:country":"US",
    "sg:address":"1122 Comanche Trl",
    "sg:city":"West Monroe",
    "sg:classifiers":[
        {
            "category":"Real Estate",
            "subcategory":"Real Estate Agent",
            "type":"Services"
        }
    ],
    "sg:phone":"+1 318 396 8820",
    "sg:postcode":"71291",
    "sg:province":"LA",
    "wof:name":"Safari Ventures",
    "wof:placetype":"venue"
},
  "geometry": {"coordinates":[-92.232303,32.560422],"type":"Point"}
}