{
  "type": "Feature",
  "properties": {
    "iso:country":"US",
    "sg:address":"3535 Nicholson Dr",
    "sg:city":"Baton Rouge",
    "sg:classifiers":[
        {
            "category":"Banks & Credit Unions",
            "subcategory":"Bank",
            "type":"Services"
        }
    ],
    "sg:phone":"+1 225 769 8841",
    "sg:postcode":"70802",
    "sg:province":"LA",
    "wof:name":"Campus Federal Credit Union",
    "wof:placetype":"venue"
},
  "geometry": {"coordinates":[-91.187376,30.415853],"type":"Point"}
}