{
  "type": "Feature",
  "properties": {
    "iso:country":"US",
    "sg:address":"306 New Natchitoches Rd",
    "sg:city":"West Monroe",
    "sg:classifiers":[
        {
            "category":"Building & Trades",
            "subcategory":"Construction",
            "type":"Services"
        }
    ],
    "sg:phone":"+1 318 322 1221",
    "sg:postcode":"71292",
    "sg:province":"LA",
    "sg:tags":[
        "roofing",
        "contractor"
    ],
    "wof:name":"Central Roofing Inc",
    "wof:placetype":"venue"
},
  "geometry": {"coordinates":[-92.165125,32.491914],"type":"Point"}
}