{
  "type": "Feature",
  "properties": {
    "iso:country":"US",
    "sg:address":"708 Natchez Blvd",
    "sg:city":"Opelousas",
    "sg:classifiers":[
        {
            "category":"Health Services",
            "subcategory":"Hospital",
            "type":"Services"
        }
    ],
    "sg:phone":"+1 337 594 9067",
    "sg:postcode":"70570",
    "sg:province":"LA",
    "wof:name":"Opelousas General Hospital",
    "wof:placetype":"venue"
},
  "geometry": {"coordinates":[-92.07437299999999,30.545739],"type":"Point"}
}