{
  "type": "Feature",
  "properties": {
    "addr:full":"5236 York St Metairie LA 70001",
    "addr:housenumber":"5236",
    "addr:postcode":"70001",
    "addr:street":"York St",
    "iso:country":"US",
    "sg:address":"5236 York St",
    "sg:city":"Metairie",
    "sg:classifiers":[
        {
            "category":"Building & Trades",
            "subcategory":"Construction",
            "type":"Services"
        }
    ],
    "sg:phone":"+1 504 460 0099",
    "sg:postcode":"70001",
    "sg:province":"LA",
    "sg:tags":[
        "carpentry",
        "contractor"
    ],
    "wof:name":"Yourcarpenter Quality Woodwork",
    "wof:placetype":"venue"
},
  "geometry": {"coordinates":[-90.195431,29.996763],"type":"Point"}
}