{
  "type": "Feature",
  "properties": {
    "addr:full":"407 Cincinnati St Delhi LA 71232",
    "addr:housenumber":"407",
    "addr:postcode":"71232",
    "addr:street":"Cincinnati St",
    "iso:country":"US",
    "sg:address":"407 Cincinnati St",
    "sg:city":"Delhi",
    "sg:classifiers":[
        {
            "category":"Health Services",
            "subcategory":"Doctor",
            "type":"Services"
        }
    ],
    "sg:phone":"+1 318 878 9340",
    "sg:postcode":"71232",
    "sg:province":"LA",
    "sg:tags":[
        "clinic"
    ],
    "wof:name":"Delhi Clinic Kidmed",
    "wof:placetype":"venue"
},
  "geometry": {"coordinates":[-91.49398600000001,32.453694],"type":"Point"}
}