{
  "type": "Feature",
  "properties": {
    "iso:country":"US",
    "sg:address":"9010 River Rd",
    "sg:city":"Chalmette",
    "sg:classifiers":[
        {
            "category":"Wholesale",
            "subcategory":"Sporting Goods",
            "type":"Manufacturing & Wholesale Goods"
        }
    ],
    "sg:phone":"+1 504 279 0683",
    "sg:postcode":"70094",
    "sg:province":"LA",
    "sg:tags":[
        "tackle",
        "fishing"
    ],
    "wof:name":"Realures Direct Distributing",
    "wof:placetype":"venue"
},
  "geometry": {"coordinates":[-90.239423,29.959542],"type":"Point"}
}