{
  "type": "Feature",
  "properties": {
    "iso:country":"US",
    "sg:address":"1508 W Pinhook Rd",
    "sg:city":"Lafayette",
    "sg:classifiers":[
        {
            "category":"Restaurant",
            "type":"Food & Drink"
        }
    ],
    "sg:phone":"+1 337 237 2860",
    "sg:postcode":"70503",
    "sg:province":"LA",
    "wof:name":"Guidry's Reef",
    "wof:placetype":"venue"
},
  "geometry": {"coordinates":[-92.01631,30.195486],"type":"Point"}
}