{
  "type": "Feature",
  "properties": {
    "addr:full":"2393 Hwy 18 Edgard LA 70049",
    "addr:housenumber":"2393",
    "addr:postcode":"70049",
    "addr:street":"Hwy 18 Edgard La",
    "iso:country":"US",
    "sg:address":"2393 Hwy 18",
    "sg:city":"Edgard",
    "sg:classifiers":[
        {
            "category":"Professional",
            "subcategory":"Lawyer & Legal Services",
            "type":"Services"
        }
    ],
    "sg:phone":"+1 985 497 5909",
    "sg:postcode":"70049",
    "sg:province":"LA",
    "sg:tags":[
        "attorney"
    ],
    "wof:name":"John Crumb Dist Atty Office",
    "wof:placetype":"venue"
},
  "geometry": {"coordinates":[-90.57242599999999,30.046346],"type":"Point"}
}