{
  "type": "Feature",
  "properties": {
    "addr:full":"418 Bilbo St Deridder LA 70634",
    "addr:housenumber":"418",
    "addr:postcode":"70634",
    "addr:street":"Bilbo St",
    "iso:country":"US",
    "sg:address":"418 Bilbo St",
    "sg:city":"Deridder",
    "sg:classifiers":[
        {
            "category":"Insurance",
            "subcategory":"Insurance Agent",
            "type":"Services"
        }
    ],
    "sg:phone":"+1 337 463 6813",
    "sg:postcode":"70634",
    "sg:province":"LA",
    "wof:name":"American National Insurance Co",
    "wof:placetype":"venue"
},
  "geometry": {"coordinates":[-93.289956,30.850302],"type":"Point"}
}