{
  "type": "Feature",
  "properties": {
    "iso:country":"US",
    "sg:address":"1075 Spring Creek Rd",
    "sg:city":"Ruston",
    "sg:classifiers":[
        {
            "category":"Professional",
            "subcategory":"Business Services",
            "type":"Services"
        }
    ],
    "sg:phone":"+1 318 247 8100",
    "sg:postcode":"71270",
    "sg:province":"LA",
    "sg:tags":[
        "interior",
        "consultant",
        "design",
        "decorator"
    ],
    "wof:name":"J Rainey & Co",
    "wof:placetype":"venue"
},
  "geometry": {"coordinates":[-92.710252,32.584215],"type":"Point"}
}