{
  "type": "Feature",
  "properties": {
    "addr:full":"1133 W Houston River Rd Sulphur LA 70663",
    "addr:housenumber":"1133",
    "addr:postcode":"70663",
    "addr:street":"W Houston River Rd",
    "iso:country":"US",
    "sg:address":"1133 W Houston River Rd",
    "sg:city":"Sulphur",
    "sg:classifiers":[
        {
            "category":"Organizations",
            "subcategory":"Religious Organization",
            "type":"Services"
        }
    ],
    "sg:phone":"+1 337 527 5808",
    "sg:postcode":"70663",
    "sg:province":"LA",
    "sg:tags":[
        "church"
    ],
    "wof:name":"Beth Shalom",
    "wof:placetype":"venue"
},
  "geometry": {"coordinates":[-93.391283,30.285675],"type":"Point"}
}