{
  "type": "Feature",
  "properties": {
    "iso:country":"US",
    "sg:address":"68 Belle Helene Dr",
    "sg:city":"Destrehan",
    "sg:classifiers":[
        {
            "category":"Professional",
            "type":"Services"
        }
    ],
    "sg:phone":"+1 985 725 0162",
    "sg:postcode":"70047",
    "sg:province":"LA",
    "sg:tags":[
        "establishment"
    ],
    "wof:name":"Marketing Dynamics",
    "wof:placetype":"venue"
},
  "geometry": {"coordinates":[-90.368303,29.980801],"type":"Point"}
}