{
  "type": "Feature",
  "properties": {
    "addr:full":"622 Rue Conti New Orleans LA 70130",
    "addr:housenumber":"622",
    "addr:postcode":"70130",
    "addr:street":"Rue Conti",
    "iso:country":"US",
    "sg:address":"622 Rue Conti",
    "sg:city":"New Orleans",
    "sg:classifiers":[
        {
            "category":"Shopping",
            "subcategory":"Beauty & Cosmetics",
            "type":"Retail Goods"
        }
    ],
    "sg:phone":"+1 888 581 4999",
    "sg:postcode":"70130",
    "sg:province":"LA",
    "sg:tags":[
        "supply"
    ],
    "sg:website":"www.shinedayspa.com",
    "wof:name":"SHINE Spa & Specialties",
    "wof:placetype":"venue"
},
  "geometry": {"coordinates":[-90.066208,29.955194],"type":"Point"}
}