{
  "type": "Feature",
  "properties": {
    "iso:country":"US",
    "sg:address":"9999 Burbank Dr",
    "sg:city":"Baton Rouge",
    "sg:classifiers":[
        {
            "category":"Shopping",
            "subcategory":"Department Store",
            "type":"Retail Goods"
        }
    ],
    "sg:phone":"+1 225 766 2485",
    "sg:postcode":"70810",
    "sg:province":"LA",
    "sg:tags":[
        "shop"
    ],
    "wof:name":"Family Dollar Store",
    "wof:placetype":"venue"
},
  "geometry": {"coordinates":[-91.11700999999999,30.357004],"type":"Point"}
}