{
  "type": "Feature",
  "properties": {
    "iso:country":"US",
    "sg:address":"1001 Alfred St",
    "sg:city":"Scott",
    "sg:classifiers":[
        {
            "category":"Retail",
            "subcategory":"Auto Repair",
            "type":"Services"
        }
    ],
    "sg:phone":"+1 337 232 0100",
    "sg:postcode":"70583",
    "sg:province":"LA",
    "wof:name":"Troy's Auto Repair",
    "wof:placetype":"venue"
},
  "geometry": {"coordinates":[-92.093681,30.234408],"type":"Point"}
}