{
  "type": "Feature",
  "properties": {
    "addr:full":"3017 Magazine St New Orleans LA 70115",
    "addr:housenumber":"3017",
    "addr:postcode":"70115",
    "addr:street":"Magazine St",
    "iso:country":"US",
    "sg:address":"3017 Magazine St",
    "sg:city":"New Orleans",
    "sg:classifiers":[
        {
            "category":"Real Estate",
            "subcategory":"Real Estate Operator",
            "type":"Services"
        }
    ],
    "sg:phone":"+1 504 896 9994",
    "sg:postcode":"70115",
    "sg:province":"LA",
    "sg:tags":[
        "mall",
        "shopping",
        "center"
    ],
    "wof:name":"Magazine Antique Mall",
    "wof:placetype":"venue"
},
  "geometry": {"coordinates":[-90.085296,29.924721],"type":"Point"}
}