{
  "type": "Feature",
  "properties": {
    "iso:country":"US",
    "sg:address":"2393 Hwy 18",
    "sg:city":"Edgard",
    "sg:classifiers":[
        {
            "category":"Government",
            "subcategory":"Office",
            "type":"Public Place"
        }
    ],
    "sg:phone":"+1 985 497 3311",
    "sg:postcode":"70049",
    "sg:province":"LA",
    "sg:tags":[
        "federal"
    ],
    "wof:name":"US Consolidated Farm Svc Agcy",
    "wof:placetype":"venue"
},
  "geometry": {"coordinates":[-90.57242599999999,30.046346],"type":"Point"}
}