{
  "type": "Feature",
  "properties": {
    "iso:country":"US",
    "sg:address":"4224 Magazine St",
    "sg:city":"New Orleans",
    "sg:classifiers":[
        {
            "category":"Shopping",
            "subcategory":"Clothing, Apparel, & Fashions",
            "type":"Retail Goods"
        }
    ],
    "sg:phone":"+1 504 895 1720",
    "sg:postcode":"70115",
    "sg:province":"LA",
    "wof:name":"For Mone",
    "wof:placetype":"venue"
},
  "geometry": {"coordinates":[-90.099937,29.92085],"type":"Point"}
}