{
  "type": "Feature",
  "properties": {
    "iso:country":"US",
    "sg:address":"211 E Verot School Rd",
    "sg:city":"Lafayette",
    "sg:classifiers":[
        {
            "category":"Retail",
            "subcategory":"Car Wash",
            "type":"Services"
        }
    ],
    "sg:phone":"+1 337 268 4005",
    "sg:postcode":"70508",
    "sg:province":"LA",
    "sg:tags":[
        "automobile",
        "detail",
        "clean"
    ],
    "wof:name":"Washtub",
    "wof:placetype":"venue"
},
  "geometry": {"coordinates":[-91.993909,30.181148],"type":"Point"}
}