{
  "type": "Feature",
  "properties": {
    "addr:full":"45404 Stringer Bridge Rd St Amant LA 70774",
    "addr:postcode":"45404;70774",
    "addr:street":"Stringer Bridge Rd St",
    "iso:country":"US",
    "sg:address":"45404 Stringer Bridge Rd",
    "sg:city":"St Amant",
    "sg:classifiers":[
        {
            "category":"Government",
            "subcategory":"Office",
            "type":"Public Place"
        }
    ],
    "sg:phone":"+1 225 621 5744",
    "sg:postcode":"70774",
    "sg:province":"LA",
    "wof:name":"Ascension Parish Mosquito Cntl",
    "wof:placetype":"venue"
},
  "geometry": {"coordinates":[-90.840126,30.2407],"type":"Point"}
}