{
  "type": "Feature",
  "properties": {
    "iso:country":"US",
    "sg:address":"9301 Hwy 339",
    "sg:city":"Abbeville",
    "sg:classifiers":[
        {
            "category":"Building & Trades",
            "subcategory":"Construction",
            "type":"Services"
        }
    ],
    "sg:phone":"+1 337 937 5696",
    "sg:postcode":"70510",
    "sg:province":"LA",
    "sg:tags":[
        "house"
    ],
    "wof:name":"Suire Home Builders",
    "wof:placetype":"venue"
},
  "geometry": {"coordinates":[-92.023166,30.012613],"type":"Point"}
}