{
  "type": "Feature",
  "properties": {
    "addr:full":"312 Aycock St Arabi LA 70032",
    "addr:housenumber":"312",
    "addr:postcode":"70032",
    "addr:street":"Aycock St",
    "iso:country":"US",
    "sg:address":"312 Aycock St",
    "sg:city":"Arabi",
    "sg:classifiers":[
        {
            "category":"Manufacturing",
            "subcategory":"Chemicals & Compounds",
            "type":"Manufacturing & Wholesale Goods"
        }
    ],
    "sg:phone":"+1 504 271 6110",
    "sg:postcode":"70032",
    "sg:province":"LA",
    "sg:tags":[
        "cleaning"
    ],
    "sg:website":"www.dab-a-do.com",
    "wof:name":"Diversified Chemicals & Prods",
    "wof:placetype":"venue"
},
  "geometry": {"coordinates":[-90.005751,29.951855],"type":"Point"}
}