{
  "type": "Feature",
  "properties": {
    "iso:country":"US",
    "sg:address":"114 W Vermilion St",
    "sg:city":"Lafayette",
    "sg:classifiers":[
        {
            "category":"Social Services",
            "subcategory":"Adult Care",
            "type":"Services"
        }
    ],
    "sg:phone":"+1 337 236 9111",
    "sg:postcode":"70501",
    "sg:province":"LA",
    "sg:tags":[
        "home",
        "residential"
    ],
    "wof:name":"Leading Health Care-Louisiana",
    "wof:placetype":"venue"
},
  "geometry": {"coordinates":[-92.01967500000001,30.224],"type":"Point"}
}