{
  "type": "Feature",
  "properties": {
    "addr:full":"431 W Landry St Opelousas LA 70570",
    "addr:housenumber":"431",
    "addr:postcode":"70570",
    "addr:street":"W Landry St",
    "iso:country":"US",
    "sg:address":"431 W Landry St",
    "sg:city":"Opelousas",
    "sg:classifiers":[
        {
            "category":"Personal",
            "subcategory":"Barber",
            "type":"Services"
        }
    ],
    "sg:phone":"+1 337 407 1966",
    "sg:postcode":"70570",
    "sg:province":"LA",
    "wof:name":"Bowman's Barber Shop",
    "wof:placetype":"venue"
},
  "geometry": {"coordinates":[-92.08782100000001,30.533611],"type":"Point"}
}