{
  "type": "Feature",
  "properties": {
    "addr:full":"230 Washington St West Monroe LA 71292",
    "addr:housenumber":"230",
    "addr:postcode":"71292",
    "addr:street":"Washington St West",
    "iso:country":"US",
    "sg:address":"230 Washington St",
    "sg:city":"West Monroe",
    "sg:classifiers":[
        {
            "category":"Organizations",
            "subcategory":"Religious Organization",
            "type":"Services"
        }
    ],
    "sg:phone":"+1 318 325 5981",
    "sg:postcode":"71292",
    "sg:province":"LA",
    "sg:tags":[
        "church"
    ],
    "wof:name":"Bethel Baptist Church",
    "wof:placetype":"venue"
},
  "geometry": {"coordinates":[-92.175262,32.489206],"type":"Point"}
}