{
  "type": "Feature",
  "properties": {
    "iso:country":"US",
    "sg:address":"3146 Louisville Ave",
    "sg:city":"Monroe",
    "sg:classifiers":[
        {
            "category":"Shopping",
            "subcategory":"Department Store",
            "type":"Retail Goods"
        }
    ],
    "sg:phone":"+1 318 388 2730",
    "sg:postcode":"71201",
    "sg:province":"LA",
    "sg:tags":[
        "shop"
    ],
    "wof:name":"Dollar General",
    "wof:placetype":"venue"
},
  "geometry": {"coordinates":[-92.085735,32.522677],"type":"Point"}
}