{
  "type": "Feature",
  "properties": {
    "iso:country":"US",
    "sg:address":"2213 Riverland Dr",
    "sg:city":"Chalmette",
    "sg:classifiers":[
        {
            "category":"Professional",
            "subcategory":"Accounting & Tax Preparation",
            "type":"Services"
        }
    ],
    "sg:phone":"+1 504 277 3696",
    "sg:postcode":"70043",
    "sg:province":"LA",
    "wof:name":"Charles R Capdepon Jr CPA",
    "wof:placetype":"venue"
},
  "geometry": {"coordinates":[-89.952578,29.935316],"type":"Point"}
}