{
  "type": "Feature",
  "properties": {
    "addr:full":"1017 16th St Lake Charles LA 70601",
    "addr:housenumber":"1017",
    "addr:postcode":"70601",
    "addr:street":"16Th St",
    "iso:country":"US",
    "sg:address":"1017 16th St",
    "sg:city":"Lake Charles",
    "sg:classifiers":[
        {
            "category":"Shopping",
            "subcategory":"Gifts & Souvenirs",
            "type":"Retail Goods"
        }
    ],
    "sg:phone":"+1 337 436 4317",
    "sg:postcode":"70601",
    "sg:province":"LA",
    "wof:name":"Triangle Gifts",
    "wof:placetype":"venue"
},
  "geometry": {"coordinates":[-93.20571700000001,30.208507],"type":"Point"}
}