{
  "type": "Feature",
  "properties": {
    "iso:country":"US",
    "sg:address":"191 E 44th St",
    "sg:city":"Cut Off",
    "sg:classifiers":[
        {
            "category":"Education",
            "subcategory":"Special Training",
            "type":"Public Place"
        }
    ],
    "sg:phone":"+1 985 632 4823",
    "sg:postcode":"70345",
    "sg:province":"LA",
    "wof:name":"Individual Learing Academy",
    "wof:placetype":"venue"
},
  "geometry": {"coordinates":[-90.33350799999999,29.523873],"type":"Point"}
}