{
  "type": "Feature",
  "properties": {
    "iso:country":"US",
    "sg:address":"2724 Manley Ave",
    "sg:city":"Metairie",
    "sg:classifiers":[
        {
            "category":"Building & Trades",
            "subcategory":"Landscaping Services",
            "type":"Services"
        }
    ],
    "sg:phone":"+1 504 833 1176",
    "sg:postcode":"70001",
    "sg:province":"LA",
    "sg:tags":[
        "landscape",
        "contractor"
    ],
    "wof:name":"Darlene's Garden Creations",
    "wof:placetype":"venue"
},
  "geometry": {"coordinates":[-90.152008,29.975505],"type":"Point"}
}