{
  "type": "Feature",
  "properties": {
    "addr:full":"122 Lock Dam Rd Marksville LA 71351",
    "addr:housenumber":"122",
    "addr:postcode":"71351",
    "addr:street":"Lock Dam Rd",
    "iso:country":"US",
    "sg:address":"122 Lock Dam Rd",
    "sg:city":"Marksville",
    "sg:classifiers":[
        {
            "category":"Building & Trades",
            "subcategory":"Plumbing",
            "type":"Services"
        }
    ],
    "sg:phone":"+1 318 240 9980",
    "sg:postcode":"71351",
    "sg:province":"LA",
    "sg:tags":[
        "conditioning",
        "air",
        "system",
        "contractor"
    ],
    "wof:name":"Polar Air & Electrical",
    "wof:placetype":"venue"
},
  "geometry": {"coordinates":[-91.960052,31.23891],"type":"Point"}
}