{
  "type": "Feature",
  "properties": {
    "iso:country":"US",
    "sg:address":"4817 Garden St",
    "sg:city":"Metairie",
    "sg:classifiers":[
        {
            "category":"Retail",
            "subcategory":"Repair Shop",
            "type":"Services"
        }
    ],
    "sg:phone":"+1 504 455 1166",
    "sg:postcode":"70001",
    "sg:province":"LA",
    "sg:tags":[
        "lock",
        "locksmith"
    ],
    "wof:name":"Champion Locksmith",
    "wof:placetype":"venue"
},
  "geometry": {"coordinates":[-90.186992,29.985519],"type":"Point"}
}