{
  "type": "Feature",
  "properties": {
    "addr:full":"2139 Stumpf Blvd Ste J Terrytown LA 70056",
    "addr:housenumber":"2139",
    "addr:postcode":"70056",
    "addr:street":"Stumpf Blvd Ste J",
    "iso:country":"US",
    "sg:address":"2139 Stumpf Blvd Ste J",
    "sg:city":"Terrytown",
    "sg:classifiers":[
        {
            "category":"Personal",
            "subcategory":"Nail Salon",
            "type":"Services"
        }
    ],
    "sg:phone":"+1 504 361 3366",
    "sg:postcode":"70056",
    "sg:province":"LA",
    "wof:name":"Kimberly's Nail Salon",
    "wof:placetype":"venue"
},
  "geometry": {"coordinates":[-90.024902,29.9095],"type":"Point"}
}