{
  "type": "Feature",
  "properties": {
    "iso:country":"US",
    "sg:address":"905 Loree St",
    "sg:city":"Vinton",
    "sg:classifiers":[
        {
            "category":"Manufacturing",
            "subcategory":"Printing",
            "type":"Manufacturing & Wholesale Goods"
        }
    ],
    "sg:phone":"+1 337 589 7650",
    "sg:postcode":"70668",
    "sg:province":"LA",
    "sg:tags":[
        "newspaper"
    ],
    "wof:name":"Vinton News",
    "wof:placetype":"venue"
},
  "geometry": {"coordinates":[-93.57253799999999,30.188781],"type":"Point"}
}