{
  "type": "Feature",
  "properties": {
    "iso:country":"US",
    "sg:address":"201 Longfellow Rd",
    "sg:city":"Mansura",
    "sg:classifiers":[
        {
            "category":"Education",
            "subcategory":"School",
            "type":"Public Place"
        }
    ],
    "sg:phone":"+1 318 240 8285",
    "sg:postcode":"71350",
    "sg:province":"LA",
    "wof:name":"Avoylles Public Charter School",
    "wof:placetype":"venue"
},
  "geometry": {"coordinates":[-92.04770499999999,31.080609],"type":"Point"}
}