{
  "type": "Feature",
  "properties": {
    "addr:full":"1007 Westgate Dr Bossier City LA 71112",
    "addr:housenumber":"1007",
    "addr:postcode":"71112",
    "addr:street":"Westgate Dr",
    "iso:country":"US",
    "sg:address":"1007 Westgate Dr",
    "sg:city":"Bossier City",
    "sg:classifiers":[
        {
            "category":"Home & Garden",
            "subcategory":"Building Materials",
            "type":"Retail Goods"
        }
    ],
    "sg:phone":"+1 318 746 2436",
    "sg:postcode":"71112",
    "sg:province":"LA",
    "sg:tags":[
        "glass",
        "window",
        "plate"
    ],
    "wof:name":"Snell's Glass Svc",
    "wof:placetype":"venue"
},
  "geometry": {"coordinates":[-93.691441,32.498001],"type":"Point"}
}