{
  "type": "Feature",
  "properties": {
    "iso:country":"US",
    "sg:address":"1425 Cross St",
    "sg:city":"Marrero",
    "sg:classifiers":[
        {
            "category":"Education",
            "subcategory":"School",
            "type":"Public Place"
        }
    ],
    "sg:phone":"+1 504 349 5185",
    "sg:postcode":"70072",
    "sg:province":"LA",
    "wof:name":"Westbank Headstart",
    "wof:placetype":"venue"
},
  "geometry": {"coordinates":[-90.111693,29.889415],"type":"Point"}
}