{
  "type": "Feature",
  "properties": {
    "iso:country":"US",
    "sg:address":"1339 SE Evangeline Thruway",
    "sg:city":"Broussard",
    "sg:classifiers":[
        {
            "category":"Restaurant",
            "type":"Food & Drink"
        },
        {
            "category":"Food & Beverages",
            "subcategory":"Groceries & Convenience Stores",
            "type":"Retail Goods"
        }
    ],
    "sg:phone":"+1 337 369 1957",
    "sg:postcode":"70518",
    "sg:province":"LA",
    "wof:name":"St Martin Truckstop",
    "wof:placetype":"venue"
},
  "geometry": {"coordinates":[-91.924599,30.1001],"type":"Point"}
}