{
  "type": "Feature",
  "properties": {
    "addr:full":"601 Cypress St West Monroe LA 71291",
    "addr:housenumber":"601",
    "addr:postcode":"71291",
    "addr:street":"Cypress St West",
    "iso:country":"US",
    "sg:address":"601 Cypress St",
    "sg:city":"West Monroe",
    "sg:classifiers":[
        {
            "category":"Personal",
            "subcategory":"Beauty Salon",
            "type":"Services"
        }
    ],
    "sg:phone":"+1 318 340 9111",
    "sg:postcode":"71291",
    "sg:province":"LA",
    "sg:tags":[
        "manicuring"
    ],
    "wof:name":"Natural Nails",
    "wof:placetype":"venue"
},
  "geometry": {"coordinates":[-92.1297,32.505359],"type":"Point"}
}