{
  "type": "Feature",
  "properties": {
    "addr:full":"608 E Church St Church Point LA 70525",
    "addr:housenumber":"608",
    "addr:postcode":"70525",
    "addr:street":"E Church St",
    "iso:country":"US",
    "sg:address":"608 E Church St",
    "sg:city":"Church Point",
    "sg:classifiers":[
        {
            "category":"Retail",
            "subcategory":"Portrait Studio",
            "type":"Services"
        }
    ],
    "sg:phone":"+1 337 668 4874",
    "sg:postcode":"70525",
    "sg:province":"LA",
    "sg:tags":[
        "photo"
    ],
    "wof:name":"In His Image Photography",
    "wof:placetype":"venue"
},
  "geometry": {"coordinates":[-92.21444099999999,30.407253],"type":"Point"}
}