{
  "type": "Feature",
  "properties": {
    "iso:country":"US",
    "sg:address":"67296 Hwy 41",
    "sg:city":"Pearl River",
    "sg:classifiers":[
        {
            "category":"Autos & Motor Vehicles",
            "subcategory":"Automobile Sales",
            "type":"Retail Goods"
        }
    ],
    "sg:phone":"+1 985 863 3888",
    "sg:postcode":"70452",
    "sg:province":"LA",
    "sg:tags":[
        "sport",
        "trailer",
        "utility"
    ],
    "wof:name":"Northshore Trailer Sales",
    "wof:placetype":"venue"
},
  "geometry": {"coordinates":[-89.766592,30.403931],"type":"Point"}
}