{
  "type": "Feature",
  "properties": {
    "iso:country":"US",
    "sg:address":"2636 Dougherty Dr",
    "sg:city":"Baton Rouge",
    "sg:classifiers":[
        {
            "category":"Building & Trades",
            "subcategory":"Construction",
            "type":"Services"
        }
    ],
    "sg:phone":"+1 225 355 5611",
    "sg:postcode":"70805",
    "sg:province":"LA",
    "sg:tags":[
        "paving",
        "contractor"
    ],
    "wof:name":"Barber Brothers Contracting Co",
    "wof:placetype":"venue"
},
  "geometry": {"coordinates":[-91.135105,30.470934],"type":"Point"}
}