{
  "type": "Feature",
  "properties": {
    "iso:country":"US",
    "sg:address":"2925 S Vernon Dr",
    "sg:city":"Zachary",
    "sg:classifiers":[
        {
            "category":"Social Services",
            "subcategory":"Child Care",
            "type":"Services"
        }
    ],
    "sg:phone":"+1 225 654 9539",
    "sg:postcode":"70791",
    "sg:province":"LA",
    "sg:tags":[
        "day"
    ],
    "wof:name":"Keith H Day",
    "wof:placetype":"venue"
},
  "geometry": {"coordinates":[-91.169197,30.689532],"type":"Point"}
}