{
  "type": "Feature",
  "properties": {
    "iso:country":"US",
    "sg:address":"828 E 1st St",
    "sg:city":"Deridder",
    "sg:classifiers":[
        {
            "category":"Personal",
            "subcategory":"Beauty Salon",
            "type":"Services"
        }
    ],
    "sg:phone":"+1 337 463 3591",
    "sg:postcode":"70634",
    "sg:province":"LA",
    "wof:name":"Brenda's Hair Care",
    "wof:placetype":"venue"
},
  "geometry": {"coordinates":[-93.270762,30.846777],"type":"Point"}
}