{
  "type": "Feature",
  "properties": {
    "addr:full":"70202 9th St Covington LA 70433",
    "addr:housenumber":"70202",
    "addr:postcode":"70433",
    "addr:street":"9Th St",
    "iso:country":"US",
    "sg:address":"70202 9th St",
    "sg:city":"Covington",
    "sg:classifiers":[
        {
            "category":"Professional",
            "subcategory":"Business Services",
            "type":"Services"
        }
    ],
    "sg:phone":"+1 985 871 8046",
    "sg:postcode":"70433",
    "sg:province":"LA",
    "wof:name":"La Center For Art & Technology",
    "wof:placetype":"venue"
},
  "geometry": {"coordinates":[-90.059479,30.453951],"type":"Point"}
}