{
  "type": "Feature",
  "properties": {
    "addr:full":"630 Saint Ann St New Orleans LA 70116",
    "addr:housenumber":"630",
    "addr:postcode":"70116",
    "addr:street":"Saint Ann St",
    "iso:country":"US",
    "sg:address":"630 Saint Ann St",
    "sg:city":"New Orleans",
    "sg:classifiers":[
        {
            "category":"Shopping",
            "subcategory":"Clothing, Apparel, & Fashions",
            "type":"Retail Goods"
        }
    ],
    "sg:phone":"+1 504 568 1018",
    "sg:postcode":"70116",
    "sg:province":"LA",
    "sg:tags":[
        "costume"
    ],
    "wof:name":"Maskarade",
    "wof:placetype":"venue"
},
  "geometry": {"coordinates":[-90.06349899999999,29.9587],"type":"Point"}
}