{
  "type": "Feature",
  "properties": {
    "addr:full":"1051 Gause Blvd Slidell LA 70458",
    "addr:housenumber":"1051",
    "addr:postcode":"70458",
    "addr:street":"Gause Blvd",
    "iso:country":"US",
    "sg:address":"1051 Gause Blvd",
    "sg:city":"Slidell",
    "sg:classifiers":[
        {
            "category":"Building & Trades",
            "subcategory":"Equipment Rental",
            "type":"Services"
        }
    ],
    "sg:phone":"+1 985 649 8786",
    "sg:postcode":"70458",
    "sg:province":"LA",
    "sg:tags":[
        "leasing"
    ],
    "wof:name":"Camellia Leasing Corp Inc",
    "wof:placetype":"venue"
},
  "geometry": {"coordinates":[-89.76972000000001,30.284636],"type":"Point"}
}