{
  "type": "Feature",
  "properties": {
    "iso:country":"US",
    "sg:address":"301 Lafayette St",
    "sg:city":"Youngsville",
    "sg:classifiers":[
        {
            "category":"Food & Beverages",
            "subcategory":"Groceries & Convenience Stores",
            "type":"Retail Goods"
        }
    ],
    "sg:phone":"+1 337 856 8848",
    "sg:postcode":"70592",
    "sg:province":"LA",
    "wof:name":"6-Pak Plus Food Mart",
    "wof:placetype":"venue"
},
  "geometry": {"coordinates":[-91.990573,30.100192],"type":"Point"}
}