{
  "type": "Feature",
  "properties": {
    "iso:country":"US",
    "sg:address":"4121 Eagle St",
    "sg:city":"New Orleans",
    "sg:classifiers":[
        {
            "category":"Personal",
            "subcategory":"Beauty Salon",
            "type":"Services"
        }
    ],
    "sg:phone":"+1 504 488 4579",
    "sg:postcode":"70118",
    "sg:province":"LA",
    "sg:tags":[
        "shop"
    ],
    "wof:name":"Joyces Hair Care",
    "wof:placetype":"venue"
},
  "geometry": {"coordinates":[-90.11277800000001,29.97331],"type":"Point"}
}