{
  "type": "Feature",
  "properties": {
    "addr:full":"921 Harding St Lafayette LA 70503",
    "addr:housenumber":"921",
    "addr:postcode":"70503",
    "addr:street":"Harding St",
    "iso:country":"US",
    "sg:address":"921 Harding St",
    "sg:city":"Lafayette",
    "sg:classifiers":[
        {
            "category":"Real Estate",
            "subcategory":"Architect",
            "type":"Services"
        }
    ],
    "sg:phone":"+1 337 235 3208",
    "sg:postcode":"70503",
    "sg:province":"LA",
    "wof:name":"Hamilton & Assoc",
    "wof:placetype":"venue"
},
  "geometry": {"coordinates":[-92.016265,30.206697],"type":"Point"}
}