{
  "type": "Feature",
  "properties": {
    "iso:country":"US",
    "sg:address":"2237 Airline Dr",
    "sg:city":"Bossier City",
    "sg:classifiers":[
        {
            "category":"Retail",
            "subcategory":"Laundry & Dry Cleaning",
            "type":"Services"
        }
    ],
    "sg:phone":"+1 318 742 4898",
    "sg:postcode":"71111",
    "sg:province":"LA",
    "sg:tags":[
        "cleaners"
    ],
    "wof:name":"Porter's Fine Dry Cleaning",
    "wof:placetype":"venue"
},
  "geometry": {"coordinates":[-93.70416899999999,32.530553],"type":"Point"}
}