{
  "type": "Feature",
  "properties": {
    "addr:full":"2810 Louisville Ave Monroe LA 71201",
    "addr:housenumber":"2810",
    "addr:postcode":"71201",
    "addr:street":"Louisville Ave",
    "iso:country":"US",
    "sg:address":"2810 Louisville Ave",
    "sg:city":"Monroe",
    "sg:classifiers":[
        {
            "category":"Food & Beverages",
            "subcategory":"Groceries & Convenience Stores",
            "type":"Retail Goods"
        }
    ],
    "sg:phone":"+1 318 387 0687",
    "sg:postcode":"71201",
    "sg:province":"LA",
    "wof:name":"Delta Mini Mart",
    "wof:placetype":"venue"
},
  "geometry": {"coordinates":[-92.09153999999999,32.524427],"type":"Point"}
}