{
  "type": "Feature",
  "properties": {
    "addr:full":"414 Pueblo Ln Shreveport LA 71106",
    "addr:housenumber":"414",
    "addr:postcode":"71106",
    "addr:street":"Pueblo Ln",
    "iso:country":"US",
    "sg:address":"414 Pueblo Ln",
    "sg:city":"Shreveport",
    "sg:classifiers":[
        {
            "category":"Building & Trades",
            "subcategory":"Plumbing",
            "type":"Services"
        }
    ],
    "sg:phone":"+1 318 797 2586",
    "sg:postcode":"71106",
    "sg:province":"LA",
    "sg:tags":[
        "contractor"
    ],
    "wof:name":"Alpine Air",
    "wof:placetype":"venue"
},
  "geometry": {"coordinates":[-93.706355,32.344769],"type":"Point"}
}