{
  "type": "Feature",
  "properties": {
    "iso:country":"US",
    "sg:address":"1703 N Airline Hwy",
    "sg:city":"Gonzales",
    "sg:classifiers":[
        {
            "category":"Restaurant",
            "type":"Food & Drink"
        }
    ],
    "sg:menulink":"http://www.allmenus.com/la/modeste/180405-jack-in-the-box/menu/",
    "sg:phone":"+1 225 647 3603",
    "sg:postcode":"70737",
    "sg:province":"LA",
    "sg:tags":[
        "burger",
        "american"
    ],
    "wof:name":"Jack in the Box",
    "wof:placetype":"venue"
},
  "geometry": {"coordinates":[-90.92155200000001,30.246977],"type":"Point"}
}