{
  "type": "Feature",
  "properties": {
    "addr:full":"1614 Kayouchee St Lake Charles LA 70615",
    "addr:housenumber":"1614",
    "addr:postcode":"70615",
    "addr:street":"Kayouchee St",
    "iso:country":"US",
    "sg:address":"1614 Kayouchee St",
    "sg:city":"Lake Charles",
    "sg:classifiers":[
        {
            "category":"Personal",
            "subcategory":"Beauty Salon",
            "type":"Services"
        }
    ],
    "sg:phone":"+1 337 433 8245",
    "sg:postcode":"70615",
    "sg:province":"LA",
    "sg:tags":[
        "shop"
    ],
    "wof:name":"Lulas Carousel",
    "wof:placetype":"venue"
},
  "geometry": {"coordinates":[-93.173001,30.218006],"type":"Point"}
}