{
  "type": "Feature",
  "properties": {
    "iso:country":"US",
    "sg:address":"145 4th St",
    "sg:city":"Singer",
    "sg:classifiers":[
        {
            "category":"Organizations",
            "subcategory":"Religious Organization",
            "type":"Services"
        }
    ],
    "sg:phone":"+1 337 786 5802",
    "sg:postcode":"70660",
    "sg:province":"LA",
    "sg:tags":[
        "church"
    ],
    "wof:name":"Oretta Pentecostal Church",
    "wof:placetype":"venue"
},
  "geometry": {"coordinates":[-93.44081199999999,30.527128],"type":"Point"}
}