{
  "type": "Feature",
  "properties": {
    "iso:country":"US",
    "sg:address":"167 Peart Rd",
    "sg:city":"Alexandria",
    "sg:classifiers":[
        {
            "category":"Personal",
            "type":"Services"
        }
    ],
    "sg:phone":"+1 318 473 0028",
    "sg:postcode":"71302",
    "sg:province":"LA",
    "wof:name":"Jackie Jofferion",
    "wof:placetype":"venue"
},
  "geometry": {"coordinates":[-92.29231799999999,31.154453],"type":"Point"}
}