{
  "type": "Feature",
  "properties": {
    "iso:country":"US",
    "sg:address":"6140 Westbank Expy",
    "sg:city":"Marrero",
    "sg:classifiers":[
        {
            "category":"Restaurant",
            "type":"Food & Drink"
        }
    ],
    "sg:menulink":"http://www.allmenus.com/la/avondale/188376-mcdonalds/menu/",
    "sg:postcode":"70072",
    "sg:province":"LA",
    "sg:tags":[
        "burger",
        "american"
    ],
    "wof:name":"McDonald's",
    "wof:placetype":"venue"
},
  "geometry": {"coordinates":[-90.11287299999999,29.894335],"type":"Point"}
}