{
  "type": "Feature",
  "properties": {
    "iso:country":"US",
    "sg:address":"629 Farrington Dr",
    "sg:city":"Marrero",
    "sg:classifiers":[
        {
            "category":"Building & Trades",
            "subcategory":"Plumbing",
            "type":"Services"
        }
    ],
    "sg:phone":"+1 504 341 8526",
    "sg:postcode":"70072",
    "sg:province":"LA",
    "sg:tags":[
        "conditioning",
        "air",
        "system",
        "contractor"
    ],
    "wof:name":"Quality Comfort Systems",
    "wof:placetype":"venue"
},
  "geometry": {"coordinates":[-90.090942,29.900161],"type":"Point"}
}