{
  "type": "Feature",
  "properties": {
    "addr:full":"13080 W Main St Larose LA 70373",
    "addr:housenumber":"13080",
    "addr:postcode":"70373",
    "addr:street":"W Main St Larose",
    "iso:country":"US",
    "sg:address":"13080 W Main St",
    "sg:city":"Larose",
    "sg:classifiers":[
        {
            "category":"Recreation",
            "type":"Entertainment"
        }
    ],
    "sg:phone":"+1 985 798 7607",
    "sg:postcode":"70373",
    "sg:province":"LA",
    "sg:tags":[
        "charter",
        "boat"
    ],
    "sg:website":"www.kgmarine.com",
    "wof:name":"Kevin Gros Consulting & Marine",
    "wof:placetype":"venue"
},
  "geometry": {"coordinates":[-90.365718,29.564842],"type":"Point"}
}