{
  "type": "Feature",
  "properties": {
    "iso:country":"US",
    "sg:address":"7698 Goodwood Blvd",
    "sg:city":"Baton Rouge",
    "sg:classifiers":[
        {
            "category":"Health Services",
            "subcategory":"Doctor",
            "type":"Services"
        }
    ],
    "sg:phone":"+1 225 927 8141",
    "sg:postcode":"70806",
    "sg:province":"LA",
    "sg:tags":[
        "physician",
        "surgeon"
    ],
    "wof:name":"Vitreoretinal Institute",
    "wof:placetype":"venue"
},
  "geometry": {"coordinates":[-91.10501499999999,30.442399],"type":"Point"}
}