{
  "type": "Feature",
  "properties": {
    "iso:country":"US",
    "sg:address":"4950 Dauphine St",
    "sg:city":"New Orleans",
    "sg:classifiers":[
        {
            "category":"Education",
            "subcategory":"School",
            "type":"Public Place"
        }
    ],
    "sg:phone":"+1 504 942 3100",
    "sg:postcode":"70117",
    "sg:province":"LA",
    "sg:tags":[
        "elementary"
    ],
    "sg:website":"www.holycrosstigers.com",
    "wof:name":"Holy Cross School",
    "wof:placetype":"venue"
},
  "geometry": {"coordinates":[-90.02469600000001,29.9597],"type":"Point"}
}