{
  "type": "Feature",
  "properties": {
    "addr:full":"201 Pontchartrain Dr Slidell LA 70458",
    "addr:housenumber":"201",
    "addr:postcode":"70458",
    "addr:street":"Pontchartrain Dr",
    "iso:country":"US",
    "sg:address":"201 Pontchartrain Dr",
    "sg:city":"Slidell",
    "sg:classifiers":[
        {
            "category":"Retail",
            "subcategory":"Car Wash",
            "type":"Services"
        }
    ],
    "sg:phone":"+1 985 781 0500",
    "sg:postcode":"70458",
    "sg:province":"LA",
    "sg:tags":[
        "polishing",
        "washing"
    ],
    "wof:name":"Magic Glow Car Wash & Xpress",
    "wof:placetype":"venue"
},
  "geometry": {"coordinates":[-89.787525,30.267241],"type":"Point"}
}