{
  "type": "Feature",
  "properties": {
    "addr:full":"400 Travis St Shreveport LA 71101",
    "addr:housenumber":"400",
    "addr:postcode":"71101",
    "addr:street":"Travis St",
    "iso:country":"US",
    "sg:address":"400 Travis St",
    "sg:city":"Shreveport",
    "sg:classifiers":[
        {
            "category":"Professional",
            "subcategory":"Lawyer & Legal Services",
            "type":"Services"
        }
    ],
    "sg:phone":"+1 318 222 1700",
    "sg:postcode":"71101",
    "sg:province":"LA",
    "sg:tags":[
        "personal",
        "injury",
        "attorney",
        "criminal",
        "law"
    ],
    "sg:website":"http://www.theharvillelawfirm.com",
    "wof:name":"Harville Law Firm LLC The",
    "wof:placetype":"venue"
},
  "geometry": {"coordinates":[-93.74954200000001,32.514408],"type":"Point"}
}