{
  "type": "Feature",
  "properties": {
    "addr:full":"1156 McVeigh Rd Arnaudville LA 70512",
    "addr:housenumber":"1156",
    "addr:postcode":"70512",
    "addr:street":"Mcveigh Rd",
    "iso:country":"US",
    "sg:address":"1156 McVeigh Rd",
    "sg:city":"Arnaudville",
    "sg:classifiers":[
        {
            "category":"Retail",
            "subcategory":"Animal Services",
            "type":"Services"
        }
    ],
    "sg:phone":"+1 337 754 7884",
    "sg:postcode":"70512",
    "sg:province":"LA",
    "sg:tags":[
        "breeder",
        "horse"
    ],
    "wof:name":"Dixieland Horse Farm",
    "wof:placetype":"venue"
},
  "geometry": {"coordinates":[-91.92706699999999,30.364159],"type":"Point"}
}