{
  "type": "Feature",
  "properties": {
    "iso:country":"US",
    "sg:address":"1470 Urania St",
    "sg:city":"New Orleans",
    "sg:classifiers":[
        {
            "category":"Professional",
            "subcategory":"Advertising",
            "type":"Services"
        }
    ],
    "sg:phone":"+1 504 525 0932",
    "sg:postcode":"70130",
    "sg:province":"LA",
    "sg:tags":[
        "counselor"
    ],
    "wof:name":"Marketing Center",
    "wof:placetype":"venue"
},
  "geometry": {"coordinates":[-90.07533599999999,29.934659],"type":"Point"}
}