{
  "type": "Feature",
  "properties": {
    "iso:country":"US",
    "sg:address":"404 Church",
    "sg:city":"Columbia",
    "sg:classifiers":[
        {
            "category":"Organizations",
            "subcategory":"Religious Organization",
            "type":"Services"
        }
    ],
    "sg:phone":"+1 318 649 2202",
    "sg:postcode":"71418",
    "sg:province":"LA",
    "sg:tags":[
        "church"
    ],
    "wof:name":"First Baptist Church",
    "wof:placetype":"venue"
},
  "geometry": {"coordinates":[-92.073589,32.102749],"type":"Point"}
}