{
  "type": "Feature",
  "properties": {
    "iso:country":"US",
    "sg:address":"134 S 3rd St",
    "sg:city":"Eunice",
    "sg:classifiers":[
        {
            "category":"Banks & Credit Unions",
            "subcategory":"Bank",
            "type":"Services"
        }
    ],
    "sg:phone":"+1 337 457 5444",
    "sg:postcode":"70535",
    "sg:province":"LA",
    "sg:tags":[
        "financing"
    ],
    "wof:name":"Tigerland Finance Of Eunice",
    "wof:placetype":"venue"
},
  "geometry": {"coordinates":[-92.41743,30.494552],"type":"Point"}
}