{
  "type": "Feature",
  "properties": {
    "iso:country":"US",
    "sg:address":"710 Olinde St",
    "sg:city":"New Roads",
    "sg:classifiers":[
        {
            "category":"Shopping",
            "subcategory":"Used Merchandise",
            "type":"Retail Goods"
        }
    ],
    "sg:phone":"+1 225 638 6304",
    "sg:postcode":"70760",
    "sg:province":"LA",
    "sg:tags":[
        "shop",
        "thrift"
    ],
    "wof:name":"St Vincent De Paul",
    "wof:placetype":"venue"
},
  "geometry": {"coordinates":[-91.44213999999999,30.697188],"type":"Point"}
}