{
  "type": "Feature",
  "properties": {
    "iso:country":"US",
    "sg:address":"2622 College Dr",
    "sg:city":"Baton Rouge",
    "sg:classifiers":[
        {
            "category":"Organizations",
            "subcategory":"Religious Organization",
            "type":"Services"
        }
    ],
    "sg:phone":"+1 225 766 1510",
    "sg:postcode":"70808",
    "sg:province":"LA",
    "sg:tags":[
        "church"
    ],
    "wof:name":"Greater Morning Star Baptist",
    "wof:placetype":"venue"
},
  "geometry": {"coordinates":[-91.139481,30.423268],"type":"Point"}
}