{
  "type": "Feature",
  "properties": {
    "addr:full":"979 Oneal Ln Baton Rouge LA 70816",
    "addr:housenumber":"979",
    "addr:postcode":"70816",
    "addr:street":"Oneal Ln",
    "iso:country":"US",
    "sg:address":"979 Oneal Ln",
    "sg:city":"Baton Rouge",
    "sg:classifiers":[
        {
            "category":"Real Estate",
            "subcategory":"Real Estate Agent",
            "type":"Services"
        }
    ],
    "sg:phone":"+1 225 272 0611",
    "sg:postcode":"70816",
    "sg:province":"LA",
    "wof:name":"B D Commercial Property",
    "wof:placetype":"venue"
},
  "geometry": {"coordinates":[-91.008292,30.455074],"type":"Point"}
}