{
  "type": "Feature",
  "properties": {
    "iso:country":"US",
    "sg:address":"44179 Conway St",
    "sg:city":"Sorrento",
    "sg:classifiers":[
        {
            "category":"Retail",
            "subcategory":"Auto Repair",
            "type":"Services"
        }
    ],
    "sg:phone":"+1 225 675 8357",
    "sg:postcode":"70778",
    "sg:province":"LA",
    "sg:tags":[
        "wrecker"
    ],
    "wof:name":"Tullier's Towing",
    "wof:placetype":"venue"
},
  "geometry": {"coordinates":[-90.865702,30.17505],"type":"Point"}
}