{
  "type": "Feature",
  "properties": {
    "addr:full":"205 Kennedy Dr Montegut LA 70377",
    "addr:housenumber":"205",
    "addr:postcode":"70377",
    "addr:street":"Kennedy Dr Montegut",
    "iso:country":"US",
    "sg:address":"205 Kennedy Dr",
    "sg:city":"Montegut",
    "sg:classifiers":[
        {
            "category":"Local Transit",
            "type":"Transportation"
        }
    ],
    "sg:phone":"+1 985 594 6506",
    "sg:postcode":"70377",
    "sg:province":"LA",
    "sg:tags":[
        "limousine"
    ],
    "wof:name":"Sam's Limo Svc Inc",
    "wof:placetype":"venue"
},
  "geometry": {"coordinates":[-90.55471300000001,29.470441],"type":"Point"}
}