{
  "type": "Feature",
  "properties": {
    "iso:country":"US",
    "sg:address":"6745 Bayou Black Dr",
    "sg:city":"Gibson",
    "sg:classifiers":[
        {
            "category":"Building & Trades",
            "subcategory":"Construction",
            "type":"Services"
        }
    ],
    "sg:phone":"+1 985 851 2215",
    "sg:postcode":"70356",
    "sg:province":"LA",
    "sg:tags":[
        "field",
        "oil",
        "contractor"
    ],
    "wof:name":"Max Welders Inc",
    "wof:placetype":"venue"
},
  "geometry": {"coordinates":[-91.04335399999999,29.664737],"type":"Point"}
}