{
  "type": "Feature",
  "properties": {
    "iso:country":"US",
    "sg:address":"513 S Court St",
    "sg:city":"Opelousas",
    "sg:classifiers":[
        {
            "category":"Personal",
            "subcategory":"Beauty Salon",
            "type":"Services"
        }
    ],
    "sg:phone":"+1 337 942 7770",
    "sg:postcode":"70570",
    "sg:province":"LA",
    "wof:name":"Des Amis",
    "wof:placetype":"venue"
},
  "geometry": {"coordinates":[-92.08361499999999,30.529844],"type":"Point"}
}