{
  "type": "Feature",
  "properties": {
    "iso:country":"US",
    "sg:address":"116 S Jefferson Davis Pkwy",
    "sg:city":"New Orleans",
    "sg:classifiers":[
        {
            "category":"Health Services",
            "subcategory":"Podiatrist",
            "type":"Services"
        }
    ],
    "sg:phone":"+1 504 827 0555",
    "sg:postcode":"70119",
    "sg:province":"LA",
    "wof:name":"Soul Butterfly Foot Care Ctr",
    "wof:placetype":"venue"
},
  "geometry": {"coordinates":[-90.094486,29.969111],"type":"Point"}
}