{
  "type": "Feature",
  "properties": {
    "addr:full":"660 Government St Baton Rouge LA 70802",
    "addr:housenumber":"660",
    "addr:postcode":"70802",
    "addr:street":"Government St",
    "iso:country":"US",
    "sg:address":"660 Government St",
    "sg:city":"Baton Rouge",
    "sg:classifiers":[
        {
            "category":"Communications",
            "subcategory":"Film & Video Production",
            "type":"Services"
        }
    ],
    "sg:phone":"+1 225 383 0900",
    "sg:postcode":"70802",
    "sg:province":"LA",
    "sg:tags":[
        "motion",
        "picture",
        "studio",
        "producer"
    ],
    "wof:name":"Hollywood Productions",
    "wof:placetype":"venue"
},
  "geometry": {"coordinates":[-91.185013,30.443321],"type":"Point"}
}