{
  "type": "Feature",
  "properties": {
    "iso:country":"US",
    "sg:address":"103 S Landry Dr",
    "sg:city":"New Iberia",
    "sg:classifiers":[
        {
            "category":"Retail",
            "subcategory":"Self-service Laundry",
            "type":"Services"
        }
    ],
    "sg:phone":"+1 337 367 1144",
    "sg:postcode":"70560",
    "sg:province":"LA",
    "wof:name":"Clean Scene",
    "wof:placetype":"venue"
},
  "geometry": {"coordinates":[-91.83324,30.02179],"type":"Point"}
}