{
  "type": "Feature",
  "properties": {
    "iso:country":"US",
    "sg:address":"5703 Read Blvd",
    "sg:city":"New Orleans",
    "sg:classifiers":[
        {
            "category":"Retail",
            "subcategory":"Repair Shop",
            "type":"Services"
        }
    ],
    "sg:phone":"+1 504 241 6042",
    "sg:postcode":"70127",
    "sg:province":"LA",
    "sg:tags":[
        "television",
        "radio"
    ],
    "wof:name":"Video Vision Electronics",
    "wof:placetype":"venue"
},
  "geometry": {"coordinates":[-89.97336,30.033635],"type":"Point"}
}