{
  "type": "Feature",
  "properties": {
    "addr:full":"104 Ozone St West Monroe LA 71291",
    "addr:housenumber":"104",
    "addr:postcode":"71291",
    "addr:street":"Ozone St West",
    "iso:country":"US",
    "sg:address":"104 Ozone St",
    "sg:city":"West Monroe",
    "sg:classifiers":[
        {
            "category":"Mining & Drilling",
            "type":"Manufacturing & Wholesale Goods"
        }
    ],
    "sg:phone":"+1 318 325 3393",
    "sg:postcode":"71291",
    "sg:province":"LA",
    "sg:tags":[
        "perforating",
        "well",
        "oil",
        "logging"
    ],
    "wof:name":"Southern Mud Logging Inc",
    "wof:placetype":"venue"
},
  "geometry": {"coordinates":[-92.153846,32.519068],"type":"Point"}
}