{
  "type": "Feature",
  "properties": {
    "iso:country":"US",
    "sg:address":"250 Barringer Dr",
    "sg:city":"Ponchatoula",
    "sg:classifiers":[
        {
            "category":"Education",
            "subcategory":"Special Training",
            "type":"Public Place"
        }
    ],
    "sg:phone":"+1 985 386 2233",
    "sg:postcode":"70454",
    "sg:province":"LA",
    "sg:tags":[
        "tutoring"
    ],
    "wof:name":"After The Bell",
    "wof:placetype":"venue"
},
  "geometry": {"coordinates":[-90.452445,30.446623],"type":"Point"}
}