{
  "type": "Feature",
  "properties": {
    "addr:full":"4346 Shreveport Blanchard Hwy Shreveport LA 71107",
    "addr:postcode":"4346;71107",
    "addr:street":"Blanchard Hwy",
    "iso:country":"US",
    "sg:address":"4346 Shreveport Blanchard Hwy",
    "sg:city":"Shreveport",
    "sg:classifiers":[
        {
            "category":"Manufacturing",
            "subcategory":"Metals",
            "type":"Manufacturing & Wholesale Goods"
        }
    ],
    "sg:phone":"+1 318 424 3237",
    "sg:postcode":"71107",
    "sg:province":"LA",
    "sg:tags":[
        "steel"
    ],
    "wof:name":"S & W Steel Fabricator Inc",
    "wof:placetype":"venue"
},
  "geometry": {"coordinates":[-93.82616299999999,32.529069],"type":"Point"}
}