{
  "type": "Feature",
  "properties": {
    "iso:country":"US",
    "sg:address":"11568 Mercantile Dr",
    "sg:city":"Baton Rouge",
    "sg:classifiers":[
        {
            "category":"Manufacturing",
            "subcategory":"Tools & Machinery",
            "type":"Manufacturing & Wholesale Goods"
        }
    ],
    "sg:phone":"+1 225 293 7594",
    "sg:postcode":"70809",
    "sg:province":"LA",
    "sg:tags":[
        "equipment",
        "electric"
    ],
    "wof:name":"Eaton Electrical",
    "wof:placetype":"venue"
},
  "geometry": {"coordinates":[-91.049452,30.376476],"type":"Point"}
}