{
  "type": "Feature",
  "properties": {
    "iso:country":"US",
    "sg:address":"7825 Old Monroe Rd",
    "sg:city":"Bastrop",
    "sg:classifiers":[
        {
            "category":"Freight",
            "type":"Transportation"
        }
    ],
    "sg:phone":"+1 318 281 3898",
    "sg:postcode":"71220",
    "sg:province":"LA",
    "sg:tags":[
        "building",
        "house",
        "mover"
    ],
    "wof:name":"W K Porter & Sons House Moving",
    "wof:placetype":"venue"
},
  "geometry": {"coordinates":[-91.916771,32.737585],"type":"Point"}
}