{
  "type": "Feature",
  "properties": {
    "addr:full":"8227 Scenic Hwy Baton Rouge LA 70807",
    "addr:housenumber":"8227",
    "addr:postcode":"70807",
    "addr:street":"Scenic Hwy",
    "iso:country":"US",
    "sg:address":"8227 Scenic Hwy",
    "sg:city":"Baton Rouge",
    "sg:classifiers":[
        {
            "category":"Government",
            "subcategory":"Police Station",
            "type":"Public Place"
        }
    ],
    "sg:phone":"+1 225 389 3033",
    "sg:postcode":"70807",
    "sg:province":"LA",
    "sg:tags":[
        "department"
    ],
    "wof:name":"Baton Rouge Police Dept",
    "wof:placetype":"venue"
},
  "geometry": {"coordinates":[-91.180538,30.522659],"type":"Point"}
}