{
  "type": "Feature",
  "properties": {
    "iso:country":"US",
    "sg:address":"2038 Hwy 80",
    "sg:city":"Haughton",
    "sg:classifiers":[
        {
            "category":"Personal",
            "subcategory":"Beauty Salon",
            "type":"Services"
        }
    ],
    "sg:phone":"+1 318 949 9666",
    "sg:postcode":"71037",
    "sg:province":"LA",
    "wof:name":"Back Room LTD",
    "wof:placetype":"venue"
},
  "geometry": {"coordinates":[-93.603577,32.555823],"type":"Point"}
}