{
  "type": "Feature",
  "properties": {
    "iso:country":"US",
    "sg:address":"1717 Macarthur Dr",
    "sg:city":"Alexandria",
    "sg:classifiers":[
        {
            "category":"Education",
            "subcategory":"Special Training",
            "type":"Public Place"
        }
    ],
    "sg:phone":"+1 318 443 6289",
    "sg:postcode":"71301",
    "sg:province":"LA",
    "sg:tags":[
        "school",
        "instruction",
        "art"
    ],
    "wof:name":"Rapid Frames",
    "wof:placetype":"venue"
},
  "geometry": {"coordinates":[-92.47232099999999,31.281135],"type":"Point"}
}