{
  "type": "Feature",
  "properties": {
    "iso:country":"US",
    "sg:address":"107 W 76th St",
    "sg:city":"Cut Off",
    "sg:classifiers":[
        {
            "category":"Real Estate",
            "subcategory":"Real Estate Operator",
            "type":"Services"
        }
    ],
    "sg:phone":"+1 985 632 5292",
    "sg:postcode":"70345",
    "sg:province":"LA",
    "sg:tags":[
        "building",
        "apartment"
    ],
    "wof:name":"Country Home Apts",
    "wof:placetype":"venue"
},
  "geometry": {"coordinates":[-90.334384,29.516438],"type":"Point"}
}