{
  "type": "Feature",
  "properties": {
    "addr:full":"11911 Ferdinand St St Francisville LA 70775",
    "addr:housenumber":"11911",
    "addr:postcode":"70775",
    "addr:street":"Ferdinand St",
    "iso:country":"US",
    "sg:address":"11911 Ferdinand St",
    "sg:city":"St Francisville",
    "sg:classifiers":[
        {
            "category":"Personal",
            "type":"Services"
        }
    ],
    "sg:phone":"+1 225 784 2838",
    "sg:postcode":"70775",
    "sg:province":"LA",
    "sg:tags":[
        "therapist",
        "massage"
    ],
    "wof:name":"Massage Clinic",
    "wof:placetype":"venue"
},
  "geometry": {"coordinates":[-91.383387,30.776912],"type":"Point"}
}