{
  "type": "Feature",
  "properties": {
    "iso:country":"US",
    "sg:address":"2884 Manning St",
    "sg:city":"Port Arthur",
    "sg:classifiers":[
        {
            "category":"Building & Trades",
            "subcategory":"Cleaning & Sanitation",
            "type":"Services"
        }
    ],
    "sg:phone":"+1 409 736 3439",
    "sg:postcode":"77640",
    "sg:province":"TX",
    "sg:tags":[
        "maintenance"
    ],
    "wof:name":"A To Z Bonded Cleaning",
    "wof:placetype":"venue"
},
  "geometry": {"coordinates":[-94.034811,29.889893],"type":"Point"}
}