{
  "type": "Feature",
  "properties": {
    "iso:country":"US",
    "sg:address":"189 Power Blvd",
    "sg:city":"Reserve",
    "sg:classifiers":[
        {
            "category":"Freight",
            "type":"Transportation"
        }
    ],
    "sg:phone":"+1 985 479 2443",
    "sg:postcode":"70084",
    "sg:province":"LA",
    "sg:tags":[
        "hauling",
        "trucking"
    ],
    "wof:name":"Linden Bulk Transport",
    "wof:placetype":"venue"
},
  "geometry": {"coordinates":[-90.567931,30.074255],"type":"Point"}
}