{
  "type": "Feature",
  "properties": {
    "iso:country":"US",
    "sg:address":"5235 Florida Blvd",
    "sg:city":"Baton Rouge",
    "sg:classifiers":[
        {
            "category":"Banks & Credit Unions",
            "subcategory":"Bank",
            "type":"Services"
        }
    ],
    "sg:phone":"+1 225 930 0700",
    "sg:postcode":"70806",
    "sg:province":"LA",
    "sg:tags":[
        "financing"
    ],
    "wof:name":"Ready Financial Svc Inc",
    "wof:placetype":"venue"
},
  "geometry": {"coordinates":[-91.13474600000001,30.451117],"type":"Point"}
}