{
  "type": "Feature",
  "properties": {
    "iso:country":"US",
    "sg:address":"5207 Essen Ln",
    "sg:city":"Baton Rouge",
    "sg:classifiers":[
        {
            "category":"Wholesale",
            "subcategory":"Medical Equipment & Supplies",
            "type":"Manufacturing & Wholesale Goods"
        }
    ],
    "sg:phone":"+1 225 819 1417",
    "sg:postcode":"70809",
    "sg:province":"LA",
    "sg:tags":[
        "physician",
        "surgeon"
    ],
    "wof:name":"United Medical Supply LLC",
    "wof:placetype":"venue"
},
  "geometry": {"coordinates":[-91.106951,30.3995],"type":"Point"}
}