{
  "type": "Feature",
  "properties": {
    "addr:full":"751 Chartres St New Orleans LA 70116",
    "addr:housenumber":"751",
    "addr:postcode":"70116",
    "addr:street":"Chartres St",
    "iso:country":"US",
    "sg:address":"751 Chartres St",
    "sg:city":"New Orleans",
    "sg:classifiers":[
        {
            "category":"Museum",
            "type":"Entertainment"
        }
    ],
    "sg:phone":"+1 504 568 6972",
    "sg:postcode":"70116",
    "sg:province":"LA",
    "wof:name":"Louisiana State Museum",
    "wof:placetype":"venue"
},
  "geometry": {"coordinates":[-90.06303699999999,29.95823],"type":"Point"}
}