{
  "type": "Feature",
  "properties": {
    "iso:country":"US",
    "sg:address":"1603 E Lafayette St",
    "sg:city":"Winnfield",
    "sg:classifiers":[
        {
            "category":"Social Services",
            "subcategory":"Child Care",
            "type":"Services"
        }
    ],
    "sg:phone":"+1 318 648 7090",
    "sg:postcode":"71483",
    "sg:province":"LA",
    "wof:name":"Yaweh Pleasant Playland Daycr",
    "wof:placetype":"venue"
},
  "geometry": {"coordinates":[-92.62579599999999,31.924821],"type":"Point"}
}