{
  "type": "Feature",
  "properties": {
    "addr:full":"1101 E Ardoin St Eunice LA 70535",
    "addr:housenumber":"1101",
    "addr:postcode":"70535",
    "addr:street":"E Ardoin St",
    "iso:country":"US",
    "sg:address":"1101 E Ardoin St",
    "sg:city":"Eunice",
    "sg:classifiers":[
        {
            "category":"Mining & Drilling",
            "type":"Manufacturing & Wholesale Goods"
        }
    ],
    "sg:phone":"+1 337 457 4803",
    "sg:postcode":"70535",
    "sg:province":"LA",
    "sg:tags":[
        "field",
        "contractor"
    ],
    "wof:name":"Slick Construction Co",
    "wof:placetype":"venue"
},
  "geometry": {"coordinates":[-92.41434599999999,30.478412],"type":"Point"}
}