{
  "type": "Feature",
  "properties": {
    "iso:country":"US",
    "sg:address":"5081 State Rte 397",
    "sg:city":"Bell City",
    "sg:classifiers":[
        {
            "category":"Organizations",
            "subcategory":"Religious Organization",
            "type":"Services"
        }
    ],
    "sg:phone":"+1 337 598 1000",
    "sg:postcode":"70630",
    "sg:province":"LA",
    "wof:name":"Sweetlake Untd Methdst Church",
    "wof:placetype":"venue"
},
  "geometry": {"coordinates":[-93.10881500000001,30.067289],"type":"Point"}
}