{
  "type": "Feature",
  "properties": {
    "iso:country":"US",
    "sg:address":"802 1st St",
    "sg:city":"Jonesville",
    "sg:classifiers":[
        {
            "category":"Farming",
            "subcategory":"Farm & Veterinary Services",
            "type":"Manufacturing & Wholesale Goods"
        }
    ],
    "sg:phone":"+1 318 339 9075",
    "sg:postcode":"71343",
    "sg:province":"LA",
    "sg:tags":[
        "gin",
        "cotton"
    ],
    "sg:website":"www.jonesville.com",
    "wof:name":"Jonesville Four Rivers Gin LLC",
    "wof:placetype":"venue"
},
  "geometry": {"coordinates":[-91.817134,31.629608],"type":"Point"}
}