{
  "type": "Feature",
  "properties": {
    "iso:country":"US",
    "sg:address":"7840 US Hwy 165",
    "sg:city":"Columbia",
    "sg:classifiers":[
        {
            "category":"Banks & Credit Unions",
            "subcategory":"Bank",
            "type":"Services"
        }
    ],
    "sg:phone":"+1 318 649 6124",
    "sg:postcode":"71418",
    "sg:province":"LA",
    "wof:name":"Homeland FSB",
    "wof:placetype":"venue"
},
  "geometry": {"coordinates":[-92.093671,32.081017],"type":"Point"}
}