{
  "type": "Feature",
  "properties": {
    "addr:full":"127 Clipper Cove Lafayette LA 70508",
    "addr:housenumber":"127",
    "addr:postcode":"70508",
    "addr:street":"Clipper Cove",
    "iso:country":"US",
    "sg:address":"127 Clipper Cove",
    "sg:city":"Lafayette",
    "sg:classifiers":[
        {
            "category":"Professional",
            "subcategory":"Engineering",
            "type":"Services"
        }
    ],
    "sg:phone":"+1 337 984 3822",
    "sg:postcode":"70508",
    "sg:province":"LA",
    "wof:name":"Breaux Engineering Inc",
    "wof:placetype":"venue"
},
  "geometry": {"coordinates":[-92.057672,30.154595],"type":"Point"}
}