{
  "type": "Feature",
  "properties": {
    "iso:country":"US",
    "sg:address":"2900 Hwy 122",
    "sg:city":"Atlanta",
    "sg:classifiers":[
        {
            "category":"Utilities",
            "subcategory":"Water",
            "type":"Services"
        }
    ],
    "sg:phone":"+1 318 646 2539",
    "sg:postcode":"71404",
    "sg:province":"LA",
    "sg:tags":[
        "company",
        "sewage"
    ],
    "wof:name":"West Grant Water Assn",
    "wof:placetype":"venue"
},
  "geometry": {"coordinates":[-92.76537,31.693005],"type":"Point"}
}