{
  "type": "Feature",
  "properties": {
    "addr:full":"1450 N Market St Shreveport LA 71107",
    "addr:housenumber":"1450",
    "addr:postcode":"71107",
    "addr:street":"N Market St",
    "iso:country":"US",
    "sg:address":"1450 N Market St",
    "sg:city":"Shreveport",
    "sg:classifiers":[
        {
            "category":"Manufacturing",
            "subcategory":"Metals",
            "type":"Manufacturing & Wholesale Goods"
        }
    ],
    "sg:phone":"+1 318 424 1146",
    "sg:postcode":"71107",
    "sg:province":"LA",
    "sg:tags":[
        "steel"
    ],
    "wof:name":"Alpha Welding & Fabrication",
    "wof:placetype":"venue"
},
  "geometry": {"coordinates":[-93.769397,32.536043],"type":"Point"}
}