{
  "type": "Feature",
  "properties": {
    "addr:full":"688 Sam Houston Jones Pkwy Lake Charles LA 70611",
    "addr:housenumber":"688",
    "addr:postcode":"70611",
    "addr:street":"Sam Houston Jones Pkwy",
    "iso:country":"US",
    "sg:address":"688 Sam Houston Jones Pkwy",
    "sg:city":"Lake Charles",
    "sg:classifiers":[
        {
            "category":"Food & Beverages",
            "subcategory":"Meat & Fish",
            "type":"Retail Goods"
        }
    ],
    "sg:phone":"+1 337 855 0206",
    "sg:postcode":"70611",
    "sg:province":"LA",
    "sg:tags":[
        "seafood"
    ],
    "wof:name":"Hot Spot",
    "wof:placetype":"venue"
},
  "geometry": {"coordinates":[-93.207677,30.300556],"type":"Point"}
}