{
  "type": "Feature",
  "properties": {
    "iso:country":"US",
    "sg:address":"1603 N 19th St",
    "sg:city":"Monroe",
    "sg:classifiers":[
        {
            "category":"Utilities",
            "subcategory":"Mobile Phone",
            "type":"Services"
        }
    ],
    "sg:phone":"+1 318 807 9473",
    "sg:postcode":"71201",
    "sg:province":"LA",
    "sg:tags":[
        "telephone",
        "cellular"
    ],
    "wof:name":"Wireless Workplace",
    "wof:placetype":"venue"
},
  "geometry": {"coordinates":[-92.11183,32.526655],"type":"Point"}
}