{
  "type": "Feature",
  "properties": {
    "iso:country":"US",
    "sg:address":"3326 Front St",
    "sg:city":"Winnsboro",
    "sg:classifiers":[
        {
            "category":"Health Services",
            "subcategory":"Doctor",
            "type":"Services"
        }
    ],
    "sg:phone":"+1 318 435 7333",
    "sg:postcode":"71295",
    "sg:province":"LA",
    "sg:tags":[
        "physician",
        "surgeon"
    ],
    "wof:name":"Winnsboro Medical Clinic",
    "wof:placetype":"venue"
},
  "geometry": {"coordinates":[-91.726787,32.181964],"type":"Point"}
}