{
  "type": "Feature",
  "properties": {
    "iso:country":"US",
    "sg:address":"3466 Charlie Moss Rd",
    "sg:city":"Sulphur",
    "sg:classifiers":[
        {
            "category":"Recreation",
            "type":"Entertainment"
        }
    ],
    "sg:phone":"+1 337 583 2363",
    "sg:postcode":"70665",
    "sg:province":"LA",
    "sg:tags":[
        "club",
        "membership",
        "guide"
    ],
    "wof:name":"Game Management Inc",
    "wof:placetype":"venue"
},
  "geometry": {"coordinates":[-93.464269,30.099596],"type":"Point"}
}