{
  "type": "Feature",
  "properties": {
    "addr:full":"3215 Knight St Shreveport LA 71105",
    "addr:housenumber":"3215",
    "addr:postcode":"71105",
    "addr:street":"Knight St",
    "iso:country":"US",
    "sg:address":"3215 Knight St",
    "sg:city":"Shreveport",
    "sg:classifiers":[
        {
            "category":"Wholesale",
            "subcategory":"Construction Materials",
            "type":"Manufacturing & Wholesale Goods"
        }
    ],
    "sg:phone":"+1 318 226 1201",
    "sg:postcode":"71105",
    "sg:province":"LA",
    "sg:tags":[
        "pallet",
        "skid"
    ],
    "wof:name":"Done Right Pallet Co",
    "wof:placetype":"venue"
},
  "geometry": {"coordinates":[-93.701342,32.479725],"type":"Point"}
}