{
  "type": "Feature",
  "properties": {
    "addr:full":"1416 Kenilworth Pkwy Baton Rouge LA 70808",
    "addr:housenumber":"1416",
    "addr:postcode":"70808",
    "addr:street":"Kenilworth Pkwy",
    "iso:country":"US",
    "sg:address":"1416 Kenilworth Pkwy",
    "sg:city":"Baton Rouge",
    "sg:classifiers":[
        {
            "category":"Real Estate",
            "subcategory":"Real Estate Agent",
            "type":"Services"
        }
    ],
    "sg:phone":"+1 225 766 5667",
    "sg:postcode":"70808",
    "sg:province":"LA",
    "wof:name":"Raghunath P Yadav",
    "wof:placetype":"venue"
},
  "geometry": {"coordinates":[-91.126254,30.388451],"type":"Point"}
}