{
  "type": "Feature",
  "properties": {
    "iso:country":"US",
    "sg:address":"106 Burgess Dr",
    "sg:city":"Broussard",
    "sg:classifiers":[
        {
            "category":"Professional",
            "type":"Services"
        },
        {
            "category":"Building & Trades",
            "subcategory":"Construction",
            "type":"Services"
        }
    ],
    "sg:phone":"+1 337 234 3990",
    "sg:postcode":"70518",
    "sg:province":"LA",
    "sg:tags":[
        "boring",
        "establishment",
        "drilling",
        "contractor"
    ],
    "wof:name":"Integrated Directional Rsrcs",
    "wof:placetype":"venue"
},
  "geometry": {"coordinates":[-91.95974699999999,30.154423],"type":"Point"}
}