{
  "type": "Feature",
  "properties": {
    "iso:country":"US",
    "sg:address":"215 Staring Ln",
    "sg:city":"Baton Rouge",
    "sg:classifiers":[
        {
            "category":"Banks & Credit Unions",
            "subcategory":"Bank",
            "type":"Services"
        }
    ],
    "sg:phone":"+1 225 766 9316",
    "sg:postcode":"70810",
    "sg:province":"LA",
    "sg:tags":[
        "national",
        "commercial"
    ],
    "wof:name":"Bank One National Assn Chicago",
    "wof:placetype":"venue"
},
  "geometry": {"coordinates":[-91.121511,30.37148],"type":"Point"}
}