{
  "type": "Feature",
  "properties": {
    "iso:country":"US",
    "sg:address":"854 Texas Ave",
    "sg:city":"Shreveport",
    "sg:classifiers":[
        {
            "category":"Wholesale",
            "subcategory":"Electrical",
            "type":"Manufacturing & Wholesale Goods"
        }
    ],
    "sg:phone":"+1 318 222 7474",
    "sg:postcode":"71101",
    "sg:province":"LA",
    "sg:tags":[
        "equipment",
        "electric",
        "supply"
    ],
    "wof:name":"CRJ",
    "wof:placetype":"venue"
},
  "geometry": {"coordinates":[-93.75190499999999,32.507831],"type":"Point"}
}