{
  "type": "Feature",
  "properties": {
    "iso:country":"US",
    "sg:address":"1619 Sampson St",
    "sg:city":"Westlake",
    "sg:classifiers":[
        {
            "category":"Banks & Credit Unions",
            "subcategory":"Bank",
            "type":"Services"
        }
    ],
    "sg:phone":"+1 337 436 8994",
    "sg:postcode":"70669",
    "sg:province":"LA",
    "sg:tags":[
        "loan"
    ],
    "wof:name":"Louisiana Title Loans Inc",
    "wof:placetype":"venue"
},
  "geometry": {"coordinates":[-93.258178,30.253346],"type":"Point"}
}