{
  "type": "Feature",
  "properties": {
    "iso:country":"US",
    "sg:address":"1811 Roselawn Ave",
    "sg:city":"Monroe",
    "sg:classifiers":[
        {
            "category":"Freight",
            "type":"Transportation"
        }
    ],
    "sg:phone":"+1 318 387 8871",
    "sg:postcode":"71201",
    "sg:province":"LA",
    "wof:name":"Shipping Systems Inc",
    "wof:placetype":"venue"
},
  "geometry": {"coordinates":[-92.109943,32.521585],"type":"Point"}
}