{
  "type": "Feature",
  "properties": {
    "iso:country":"US",
    "sg:address":"1011 24th St",
    "sg:city":"Kenner",
    "sg:classifiers":[
        {
            "category":"Professional",
            "subcategory":"Business Services",
            "type":"Services"
        }
    ],
    "sg:phone":"+1 504 454 7204",
    "sg:postcode":"70062",
    "sg:province":"LA",
    "wof:name":"Convention Plant Designs Inc",
    "wof:placetype":"venue"
},
  "geometry": {"coordinates":[-90.254502,29.99998],"type":"Point"}
}