{
  "type": "Feature",
  "properties": {
    "iso:country":"US",
    "sg:address":"1330 3rd St",
    "sg:city":"Alexandria",
    "sg:classifiers":[
        {
            "category":"Professional",
            "subcategory":"Lawyer & Legal Services",
            "type":"Services"
        }
    ],
    "sg:phone":"+1 318 448 8301",
    "sg:postcode":"71301",
    "sg:province":"LA",
    "sg:tags":[
        "attorney"
    ],
    "wof:name":"Sooter & Assoc LLC",
    "wof:placetype":"venue"
},
  "geometry": {"coordinates":[-92.44291,31.309832],"type":"Point"}
}