{
  "type": "Feature",
  "properties": {
    "iso:country":"US",
    "sg:address":"4825 US Hwy 90",
    "sg:city":"Broussard",
    "sg:classifiers":[
        {
            "category":"Wholesale",
            "subcategory":"Machinery & Supplies",
            "type":"Manufacturing & Wholesale Goods"
        }
    ],
    "sg:phone":"+1 337 837 8862",
    "sg:postcode":"70518",
    "sg:province":"LA",
    "sg:tags":[
        "pump"
    ],
    "wof:name":"Arlan Enterprises Inc",
    "wof:placetype":"venue"
},
  "geometry": {"coordinates":[-91.94507299999999,30.139301],"type":"Point"}
}