{
  "type": "Feature",
  "properties": {
    "iso:country":"US",
    "sg:address":"4015 Texas Hwy",
    "sg:city":"Many",
    "sg:classifiers":[
        {
            "category":"Farming",
            "subcategory":"Farm",
            "type":"Manufacturing & Wholesale Goods"
        }
    ],
    "sg:phone":"+1 318 256 5991",
    "sg:postcode":"71449",
    "sg:province":"LA",
    "sg:tags":[
        "crop",
        "general"
    ],
    "wof:name":"Gentrys Cricket Farm",
    "wof:placetype":"venue"
},
  "geometry": {"coordinates":[-93.540199,31.535064],"type":"Point"}
}