{
  "type": "Feature",
  "properties": {
    "addr:full":"517 W 67th St Shreveport LA 71106",
    "addr:housenumber":"517",
    "addr:postcode":"71106",
    "addr:street":"W 67Th St",
    "iso:country":"US",
    "sg:address":"517 W 67th St",
    "sg:city":"Shreveport",
    "sg:classifiers":[
        {
            "category":"Freight",
            "type":"Transportation"
        }
    ],
    "sg:phone":"+1 318 865 8889",
    "sg:postcode":"71106",
    "sg:province":"LA",
    "sg:tags":[
        "delivery"
    ],
    "wof:name":"ASAP Express Delivery",
    "wof:placetype":"venue"
},
  "geometry": {"coordinates":[-93.765198,32.444466],"type":"Point"}
}