{
  "type": "Feature",
  "properties": {
    "iso:country":"US",
    "sg:address":"4817 Plank Rd",
    "sg:city":"Baton Rouge",
    "sg:classifiers":[
        {
            "category":"Organizations",
            "subcategory":"Religious Organization",
            "type":"Services"
        }
    ],
    "sg:phone":"+1 225 355 0035",
    "sg:postcode":"70805",
    "sg:province":"LA",
    "sg:tags":[
        "church"
    ],
    "wof:name":"Harvest Time Fellowship",
    "wof:placetype":"venue"
},
  "geometry": {"coordinates":[-91.154978,30.494514],"type":"Point"}
}