{
  "type": "Feature",
  "properties": {
    "addr:full":"1922 1st St Slidell LA 70458",
    "addr:housenumber":"1922",
    "addr:postcode":"70458",
    "addr:street":"1St St",
    "iso:country":"US",
    "sg:address":"1922 1st St",
    "sg:city":"Slidell",
    "sg:classifiers":[
        {
            "category":"Shopping",
            "subcategory":"Used Merchandise",
            "type":"Retail Goods"
        }
    ],
    "sg:phone":"+1 985 781 2020",
    "sg:postcode":"70458",
    "sg:province":"LA",
    "wof:name":"Lisieux Antiques",
    "wof:placetype":"venue"
},
  "geometry": {"coordinates":[-89.782678,30.277299],"type":"Point"}
}