{
  "type": "Feature",
  "properties": {
    "iso:country":"US",
    "sg:address":"19274 Antenor St",
    "sg:city":"Mandeville",
    "sg:classifiers":[
        {
            "category":"Building & Trades",
            "subcategory":"Construction",
            "type":"Services"
        }
    ],
    "sg:phone":"+1 985 875 0910",
    "sg:postcode":"70471",
    "sg:province":"LA",
    "sg:tags":[
        "painter"
    ],
    "wof:name":"Certa Pro Painters",
    "wof:placetype":"venue"
},
  "geometry": {"coordinates":[-90.077969,30.402077],"type":"Point"}
}