{
  "type": "Feature",
  "properties": {
    "iso:country":"US",
    "sg:address":"1313 Louise St",
    "sg:city":"Alexandria",
    "sg:classifiers":[
        {
            "category":"Retail",
            "subcategory":"Auto Repair",
            "type":"Services"
        }
    ],
    "sg:phone":"+1 318 442 7147",
    "sg:postcode":"71303",
    "sg:province":"LA",
    "sg:tags":[
        "wrecker"
    ],
    "wof:name":"Drewett Towing",
    "wof:placetype":"venue"
},
  "geometry": {"coordinates":[-92.48103999999999,31.310506],"type":"Point"}
}