{
  "type": "Feature",
  "properties": {
    "addr:full":"2171 Oneal Ln Baton Rouge LA 70816",
    "addr:housenumber":"2171",
    "addr:postcode":"70816",
    "addr:street":"Oneal Ln",
    "iso:country":"US",
    "sg:address":"2171 Oneal Ln",
    "sg:city":"Baton Rouge",
    "sg:classifiers":[
        {
            "category":"Professional",
            "subcategory":"Accounting & Tax Preparation",
            "type":"Services"
        }
    ],
    "sg:phone":"+1 225 293 1040",
    "sg:postcode":"70816",
    "sg:province":"LA",
    "sg:tags":[
        "return",
        "filing"
    ],
    "wof:name":"Jackson Hewitt Tax Svc",
    "wof:placetype":"venue"
},
  "geometry": {"coordinates":[-91.007632,30.43673],"type":"Point"}
}