{
  "type": "Feature",
  "properties": {
    "iso:country":"US",
    "sg:address":"2150 Westbank Expy",
    "sg:city":"Harvey",
    "sg:classifiers":[
        {
            "category":"Social Services",
            "type":"Services"
        }
    ],
    "sg:phone":"+1 504 361 6700",
    "sg:postcode":"70058",
    "sg:province":"LA",
    "sg:tags":[
        "government"
    ],
    "wof:name":"Corrections-Youth Svc Div",
    "wof:placetype":"venue"
},
  "geometry": {"coordinates":[-90.071859,29.900882],"type":"Point"}
}