{
  "type": "Feature",
  "properties": {
    "iso:country":"US",
    "sg:address":"4242 Bayouside Dr",
    "sg:city":"Houma",
    "sg:classifiers":[
        {
            "category":"Professional",
            "type":"Services"
        }
    ],
    "sg:phone":"+1 504 594 9307",
    "sg:postcode":"70363",
    "sg:province":"LA",
    "wof:name":"Coco Village Inc",
    "wof:placetype":"venue"
},
  "geometry": {"coordinates":[-90.618544,29.537393],"type":"Point"}
}