{
  "type": "Feature",
  "properties": {
    "iso:country":"US",
    "sg:address":"117 Oak St",
    "sg:city":"Rayne",
    "sg:classifiers":[
        {
            "category":"Health Services",
            "subcategory":"Chiropractor",
            "type":"Services"
        }
    ],
    "sg:phone":"+1 337 334 4100",
    "sg:postcode":"70578",
    "sg:province":"LA",
    "wof:name":"Menard Chiropractic Clinic",
    "wof:placetype":"venue"
},
  "geometry": {"coordinates":[-92.267871,30.247778],"type":"Point"}
}