{
  "type": "Feature",
  "properties": {
    "iso:country":"US",
    "sg:address":"2767 Tulane Ave",
    "sg:city":"New Orleans",
    "sg:classifiers":[
        {
            "category":"Insurance",
            "subcategory":"Hazard Insurance",
            "type":"Services"
        }
    ],
    "sg:phone":"+1 504 822 9666",
    "sg:postcode":"70119",
    "sg:province":"LA",
    "sg:tags":[
        "bond"
    ],
    "wof:name":"Blair's Bail Bonds",
    "wof:placetype":"venue"
},
  "geometry": {"coordinates":[-90.092144,29.962615],"type":"Point"}
}