{
  "type": "Feature",
  "properties": {
    "iso:country":"US",
    "sg:address":"873 US Hwy 90",
    "sg:city":"Morgan City",
    "sg:classifiers":[
        {
            "category":"Shopping",
            "subcategory":"Department Store",
            "type":"Retail Goods"
        }
    ],
    "sg:phone":"+1 985 399 9699",
    "sg:postcode":"70380",
    "sg:province":"LA",
    "sg:tags":[
        "shop"
    ],
    "wof:name":"Burke's Outlet",
    "wof:placetype":"venue"
},
  "geometry": {"coordinates":[-91.27168399999999,29.680852],"type":"Point"}
}