{
  "type": "Feature",
  "properties": {
    "iso:country":"US",
    "sg:address":"904 E 4th St",
    "sg:city":"Dequincy",
    "sg:classifiers":[
        {
            "category":"Autos & Motor Vehicles",
            "subcategory":"Auto Supplies",
            "type":"Retail Goods"
        }
    ],
    "sg:phone":"+1 337 786 7304",
    "sg:postcode":"70633",
    "sg:province":"LA",
    "sg:tags":[
        "automobile",
        "parts"
    ],
    "wof:name":"Treme Auto Supply",
    "wof:placetype":"venue"
},
  "geometry": {"coordinates":[-93.425152,30.451092],"type":"Point"}
}