{
  "type": "Feature",
  "properties": {
    "iso:country":"US",
    "sg:address":"120 Cedar Dr",
    "sg:city":"Belle Chasse",
    "sg:classifiers":[
        {
            "category":"Building & Trades",
            "subcategory":"Cleaning & Sanitation",
            "type":"Services"
        }
    ],
    "sg:phone":"+1 504 656 9675",
    "sg:postcode":"70037",
    "sg:province":"LA",
    "sg:tags":[
        "equipment",
        "maintenance"
    ],
    "wof:name":"Belle Chasse Team Clean",
    "wof:placetype":"venue"
},
  "geometry": {"coordinates":[-90.021063,29.794763],"type":"Point"}
}