{
  "type": "Feature",
  "properties": {
    "iso:country":"US",
    "sg:address":"2115 Belle Chasse Hwy",
    "sg:city":"Terrytown",
    "sg:classifiers":[
        {
            "category":"Retail",
            "subcategory":"Animal Services",
            "type":"Services"
        }
    ],
    "sg:phone":"+1 504 433 0595",
    "sg:postcode":"70056",
    "sg:province":"LA",
    "sg:tags":[
        "pet",
        "grooming",
        "washing"
    ],
    "wof:name":"Jazzy Pets Grooming",
    "wof:placetype":"venue"
},
  "geometry": {"coordinates":[-90.031131,29.888838],"type":"Point"}
}