{
  "type": "Feature",
  "properties": {
    "addr:full":"716 6th St Mamou LA 70554",
    "addr:housenumber":"716",
    "addr:postcode":"70554",
    "addr:street":"6Th St",
    "iso:country":"US",
    "sg:address":"716 6th St",
    "sg:city":"Mamou",
    "sg:classifiers":[
        {
            "category":"Organizations",
            "subcategory":"Religious Organization",
            "type":"Services"
        }
    ],
    "sg:phone":"+1 337 468 3159",
    "sg:postcode":"70554",
    "sg:province":"LA",
    "sg:tags":[
        "church"
    ],
    "wof:name":"St Ann Catholic Church",
    "wof:placetype":"venue"
},
  "geometry": {"coordinates":[-92.419483,30.633875],"type":"Point"}
}