{
  "type": "Feature",
  "properties": {
    "iso:country":"US",
    "sg:address":"6387 Highway 93",
    "sg:city":"Sunset",
    "sg:classifiers":[
        {
            "category":"Retail",
            "subcategory":"Animal Services",
            "type":"Services"
        }
    ],
    "sg:phone":"+1 337 662 3222",
    "sg:postcode":"70584",
    "sg:province":"LA",
    "sg:tags":[
        "pet"
    ],
    "wof:name":"Southern Equine Stables",
    "wof:placetype":"venue"
},
  "geometry": {"coordinates":[-92.074203,30.3813],"type":"Point"}
}