{
  "type": "Feature",
  "properties": {
    "iso:country":"US",
    "sg:address":"1253 1st Ave",
    "sg:city":"Harvey",
    "sg:classifiers":[
        {
            "category":"Professional",
            "type":"Services"
        }
    ],
    "sg:phone":"+1 504 328 2103",
    "sg:postcode":"70058",
    "sg:province":"LA",
    "sg:tags":[
        "establishment"
    ],
    "wof:name":"Aquatic Technologies Unltd LLC",
    "wof:placetype":"venue"
},
  "geometry": {"coordinates":[-90.08195499999999,29.896295],"type":"Point"}
}