{
  "type": "Feature",
  "properties": {
    "iso:country":"US",
    "sg:address":"416 Bertrand Dr",
    "sg:city":"Lafayette",
    "sg:classifiers":[
        {
            "category":"Retail",
            "subcategory":"Auto Repair",
            "type":"Services"
        }
    ],
    "sg:phone":"+1 337 235 9745",
    "sg:postcode":"70506",
    "sg:province":"LA",
    "sg:tags":[
        "repairing",
        "automobile"
    ],
    "wof:name":"Bertinot's Automotive Inc",
    "wof:placetype":"venue"
},
  "geometry": {"coordinates":[-92.04395599999999,30.21056],"type":"Point"}
}