{
  "type": "Feature",
  "properties": {
    "iso:country":"US",
    "sg:address":"6904 Asher St",
    "sg:city":"Metairie",
    "sg:classifiers":[
        {
            "category":"Social Services",
            "type":"Services"
        }
    ],
    "sg:phone":"+1 504 888 0269",
    "sg:postcode":"70003",
    "sg:province":"LA",
    "wof:name":"Sun Light Counseling",
    "wof:placetype":"venue"
},
  "geometry": {"coordinates":[-90.217906,30.012914],"type":"Point"}
}