{
  "type": "Feature",
  "properties": {
    "addr:full":"3001 Ormond Blvd Destrehan LA 70047",
    "addr:housenumber":"3001",
    "addr:postcode":"70047",
    "addr:street":"Ormond Blvd Destrehan",
    "iso:country":"US",
    "sg:address":"3001 Ormond Blvd",
    "sg:city":"Destrehan",
    "sg:classifiers":[
        {
            "category":"Bars & Pubs",
            "type":"Food & Drink"
        }
    ],
    "sg:phone":"+1 985 764 1100",
    "sg:postcode":"70047",
    "sg:province":"LA",
    "wof:name":"Sport's Pub & Grill Inc",
    "wof:placetype":"venue"
},
  "geometry": {"coordinates":[-90.36415700000001,29.977529],"type":"Point"}
}