{
  "type": "Feature",
  "properties": {
    "iso:country":"US",
    "sg:address":"304 Ward Ln",
    "sg:city":"Sulphur",
    "sg:classifiers":[
        {
            "category":"Building & Trades",
            "subcategory":"Landscaping Services",
            "type":"Services"
        }
    ],
    "sg:phone":"+1 337 625 3117",
    "sg:postcode":"70663",
    "sg:province":"LA",
    "sg:tags":[
        "tree"
    ],
    "wof:name":"Burns & Mc Lachlan Tree Surg",
    "wof:placetype":"venue"
},
  "geometry": {"coordinates":[-93.330181,30.219899],"type":"Point"}
}