{
  "type": "Feature",
  "properties": {
    "iso:country":"US",
    "sg:address":"2932 General Degaulle Dr",
    "sg:city":"New Orleans",
    "sg:classifiers":[
        {
            "category":"Utilities",
            "subcategory":"Telephone",
            "type":"Services"
        }
    ],
    "sg:phone":"+1 504 368 8546",
    "sg:postcode":"70114",
    "sg:province":"LA",
    "sg:tags":[
        "company"
    ],
    "wof:name":"ATI Alternative Telecomm",
    "wof:placetype":"venue"
},
  "geometry": {"coordinates":[-90.02856199999999,29.928401],"type":"Point"}
}