{
  "type": "Feature",
  "properties": {
    "iso:country":"US",
    "sg:address":"2602 Linda Ln",
    "sg:city":"Coushatta",
    "sg:classifiers":[
        {
            "category":"Professional",
            "type":"Services"
        }
    ],
    "sg:phone":"+1 318 932 0811",
    "sg:postcode":"71019",
    "sg:province":"LA",
    "sg:tags":[
        "establishment"
    ],
    "wof:name":"Gipson Enterprise",
    "wof:placetype":"venue"
},
  "geometry": {"coordinates":[-93.29932599999999,32.007381],"type":"Point"}
}