{
  "type": "Feature",
  "properties": {
    "iso:country":"US",
    "sg:address":"1475 Fremaux Ave",
    "sg:city":"Slidell",
    "sg:classifiers":[
        {
            "category":"Organizations",
            "subcategory":"Religious Organization",
            "type":"Services"
        }
    ],
    "sg:phone":"+1 985 641 2094",
    "sg:postcode":"70458",
    "sg:province":"LA",
    "sg:tags":[
        "church"
    ],
    "wof:name":"Kingdom Halls Of Jehovah's",
    "wof:placetype":"venue"
},
  "geometry": {"coordinates":[-89.762756,30.277516],"type":"Point"}
}