{
  "type": "Feature",
  "properties": {
    "iso:country":"US",
    "sg:address":"15790 Paul Vega M D",
    "sg:city":"Hammond",
    "sg:classifiers":[
        {
            "category":"Health Services",
            "subcategory":"Doctor",
            "type":"Services"
        }
    ],
    "sg:phone":"+1 985 230 6601",
    "sg:postcode":"70403",
    "sg:province":"LA",
    "sg:tags":[
        "physician",
        "surgeon"
    ],
    "wof:name":"Scully Sartin & Glaudi",
    "wof:placetype":"venue"
},
  "geometry": {"coordinates":[-90.462114,30.466202],"type":"Point"}
}