{
  "type": "Feature",
  "properties": {
    "iso:country":"US",
    "sg:address":"9442 Burbank Dr",
    "sg:city":"Baton Rouge",
    "sg:classifiers":[
        {
            "category":"Retail",
            "subcategory":"Repair Shop",
            "type":"Services"
        }
    ],
    "sg:phone":"+1 225 763 5969",
    "sg:postcode":"70810",
    "sg:province":"LA",
    "sg:tags":[
        "repairing",
        "lawn",
        "mower"
    ],
    "wof:name":"Baton Rouge Small Engine Rpr",
    "wof:placetype":"venue"
},
  "geometry": {"coordinates":[-91.120048,30.358343],"type":"Point"}
}