{
  "type": "Feature",
  "properties": {
    "iso:country":"US",
    "sg:address":"2021 E Napoleon St",
    "sg:city":"Sulphur",
    "sg:classifiers":[
        {
            "category":"Real Estate",
            "subcategory":"Real Estate Agent",
            "type":"Services"
        }
    ],
    "sg:phone":"+1 337 625 4291",
    "sg:postcode":"70663",
    "sg:province":"LA",
    "wof:name":"Dolan Real Estate Inc",
    "wof:placetype":"venue"
},
  "geometry": {"coordinates":[-93.354992,30.236662],"type":"Point"}
}