{
  "type": "Feature",
  "properties": {
    "iso:country":"US",
    "sg:address":"614 Bernard St",
    "sg:city":"Carencro",
    "sg:classifiers":[
        {
            "category":"Autos & Motor Vehicles",
            "subcategory":"Automobile Sales",
            "type":"Retail Goods"
        }
    ],
    "sg:phone":"+1 337 280 4703",
    "sg:postcode":"70520",
    "sg:province":"LA",
    "sg:tags":[
        "car",
        "dealer"
    ],
    "wof:name":"Dean's Auto Sales",
    "wof:placetype":"venue"
},
  "geometry": {"coordinates":[-92.042821,30.321718],"type":"Point"}
}