{
  "type": "Feature",
  "properties": {
    "iso:country":"US",
    "sg:address":"604 Robert Blvd",
    "sg:city":"Slidell",
    "sg:classifiers":[
        {
            "category":"Food & Beverages",
            "subcategory":"Groceries & Convenience Stores",
            "type":"Retail Goods"
        }
    ],
    "sg:phone":"+1 985 641 6920",
    "sg:postcode":"70458",
    "sg:province":"LA",
    "wof:name":"G G's Drink Stop",
    "wof:placetype":"venue"
},
  "geometry": {"coordinates":[-89.76063600000001,30.297773],"type":"Point"}
}