{
  "type": "Feature",
  "properties": {
    "addr:full":"10744 Linkwood Ct Baton Rouge LA 70810",
    "addr:housenumber":"10744",
    "addr:postcode":"70810",
    "addr:street":"Linkwood Ct",
    "iso:country":"US",
    "sg:address":"10744 Linkwood Ct",
    "sg:city":"Baton Rouge",
    "sg:classifiers":[
        {
            "category":"Professional",
            "subcategory":"Lawyer & Legal Services",
            "type":"Services"
        }
    ],
    "sg:phone":"+1 225 927 5871",
    "sg:postcode":"70810",
    "sg:province":"LA",
    "sg:tags":[
        "attorney"
    ],
    "wof:name":"Downs & Saffiotti",
    "wof:placetype":"venue"
},
  "geometry": {"coordinates":[-91.099057,30.374837],"type":"Point"}
}