{
  "type": "Feature",
  "properties": {
    "addr:full":"6001 Main St Zachary LA 70791",
    "addr:housenumber":"6001",
    "addr:postcode":"70791",
    "addr:street":"Main St",
    "iso:country":"US",
    "sg:address":"6001 Main St",
    "sg:city":"Zachary",
    "sg:classifiers":[
        {
            "category":"Government",
            "subcategory":"Post Office",
            "type":"Public Place"
        }
    ],
    "sg:phone":"+1 225 654 4538",
    "sg:postcode":"70791",
    "sg:province":"LA",
    "wof:name":"US Post Office",
    "wof:placetype":"venue"
},
  "geometry": {"coordinates":[-91.142776,30.64864],"type":"Point"}
}