{
  "type": "Feature",
  "properties": {
    "iso:country":"US",
    "sg:address":"7000 Bullard Ave",
    "sg:city":"New Orleans",
    "sg:classifiers":[
        {
            "category":"Restaurant",
            "type":"Food & Drink"
        }
    ],
    "sg:phone":"+1 504 246 7892",
    "sg:postcode":"70128",
    "sg:province":"LA",
    "wof:name":"Pizza Hut",
    "wof:placetype":"venue"
},
  "geometry": {"coordinates":[-89.96268499999999,30.047863],"type":"Point"}
}