{
  "type": "Feature",
  "properties": {
    "iso:country":"US",
    "sg:address":"303 Hammond Hwy",
    "sg:city":"New Orleans",
    "sg:classifiers":[
        {
            "category":"Professional",
            "type":"Services"
        },
        {
            "category":"Professional",
            "subcategory":"Research",
            "type":"Services"
        }
    ],
    "sg:phone":"+1 504 288 8503",
    "sg:postcode":"70124",
    "sg:province":"LA",
    "sg:tags":[
        "environmental",
        "ecological"
    ],
    "sg:website":"www.hollywoodcuts.com",
    "wof:name":"Kindred Environmental Svc",
    "wof:placetype":"venue"
},
  "geometry": {"coordinates":[-90.11672799999999,30.019475],"type":"Point"}
}