{
  "type": "Feature",
  "properties": {
    "iso:country":"US",
    "sg:address":"2804 Ambassador Caffery Pkwy",
    "sg:city":"Lafayette",
    "sg:classifiers":[
        {
            "category":"Health Services",
            "subcategory":"Doctor",
            "type":"Services"
        }
    ],
    "sg:phone":"+1 337 233 1542",
    "sg:postcode":"70506",
    "sg:province":"LA",
    "sg:tags":[
        "physician",
        "surgeon"
    ],
    "wof:name":"Arcadiana Renal Physicians Amc",
    "wof:placetype":"venue"
},
  "geometry": {"coordinates":[-92.075332,30.197828],"type":"Point"}
}