{
  "type": "Feature",
  "properties": {
    "addr:full":"711 N Main St Jennings LA 70546",
    "addr:housenumber":"711",
    "addr:postcode":"70546",
    "addr:street":"N Main St",
    "iso:country":"US",
    "sg:address":"711 N Main St",
    "sg:city":"Jennings",
    "sg:classifiers":[
        {
            "category":"Health Services",
            "subcategory":"Doctor",
            "type":"Services"
        }
    ],
    "sg:phone":"+1 337 824 2002",
    "sg:postcode":"70546",
    "sg:province":"LA",
    "sg:tags":[
        "clinic"
    ],
    "wof:name":"Shirley Medical Clinic",
    "wof:placetype":"venue"
},
  "geometry": {"coordinates":[-92.65808800000001,30.22721],"type":"Point"}
}