{
  "type": "Feature",
  "properties": {
    "addr:full":"308 Althea Dr Duson LA 70529",
    "addr:housenumber":"308",
    "addr:postcode":"70529",
    "addr:street":"Althea Dr Duson",
    "iso:country":"US",
    "sg:address":"308 Althea Dr",
    "sg:city":"Duson",
    "sg:classifiers":[
        {
            "category":"Building & Trades",
            "subcategory":"Construction",
            "type":"Services"
        }
    ],
    "sg:phone":"+1 337 873 4946",
    "sg:postcode":"70529",
    "sg:province":"LA",
    "sg:tags":[
        "roofing",
        "contractor"
    ],
    "wof:name":"Berard's Roofing",
    "wof:placetype":"venue"
},
  "geometry": {"coordinates":[-92.147431,30.206564],"type":"Point"}
}