{
  "type": "Feature",
  "properties": {
    "iso:country":"US",
    "sg:address":"2226 Walnut Rd",
    "sg:city":"Springhill",
    "sg:classifiers":[
        {
            "category":"Animal Shelter",
            "type":"Public Place"
        },
        {
            "category":"Retail",
            "subcategory":"Pet Boarding",
            "type":"Services"
        },
        {
            "category":"Retail",
            "subcategory":"Animal Services",
            "type":"Services"
        }
    ],
    "sg:phone":"+1 318 994 2668",
    "sg:postcode":"71075",
    "sg:province":"LA",
    "sg:tags":[
        "exercising",
        "kennel",
        "sitting"
    ],
    "sg:website":"http://www.circlejkennels.com",
    "wof:name":"Circle J Kennels",
    "wof:placetype":"venue"
},
  "geometry": {"coordinates":[-93.433966,32.96804],"type":"Point"}
}