{
  "type": "Feature",
  "properties": {
    "iso:country":"US",
    "sg:address":"10050 Morrison Rd",
    "sg:city":"New Orleans",
    "sg:classifiers":[
        {
            "category":"Personal",
            "subcategory":"Beauty Salon",
            "type":"Services"
        }
    ],
    "sg:phone":"+1 504 241 3343",
    "sg:postcode":"70127",
    "sg:province":"LA",
    "wof:name":"Too Tuff Hair Salon",
    "wof:placetype":"venue"
},
  "geometry": {"coordinates":[-89.979885,30.043041],"type":"Point"}
}