{
  "type": "Feature",
  "properties": {
    "iso:country":"US",
    "sg:address":"3017 Bell St",
    "sg:city":"New Orleans",
    "sg:classifiers":[
        {
            "category":"Professional",
            "type":"Services"
        }
    ],
    "sg:phone":"+1 504 486 0990",
    "sg:postcode":"70119",
    "sg:province":"LA",
    "wof:name":"Complete Property Services",
    "wof:placetype":"venue"
},
  "geometry": {"coordinates":[-90.084176,29.977351],"type":"Point"}
}