{
  "type": "Feature",
  "properties": {
    "iso:country":"US",
    "sg:address":"106 Jane St",
    "sg:city":"Slidell",
    "sg:classifiers":[
        {
            "category":"Education",
            "subcategory":"College",
            "type":"Public Place"
        }
    ],
    "sg:phone":"+1 985 726 9600",
    "sg:postcode":"70461",
    "sg:province":"LA",
    "sg:tags":[
        "school",
        "theological"
    ],
    "wof:name":"Slidell Baptist Seminary",
    "wof:placetype":"venue"
},
  "geometry": {"coordinates":[-89.726124,30.298717],"type":"Point"}
}