{
  "type": "Feature",
  "properties": {
    "addr:full":"2240 Oneal Ln Baton Rouge LA 70816",
    "addr:housenumber":"2240",
    "addr:postcode":"70816",
    "addr:street":"Oneal Ln",
    "iso:country":"US",
    "sg:address":"2240 Oneal Ln",
    "sg:city":"Baton Rouge",
    "sg:classifiers":[
        {
            "category":"Utilities",
            "subcategory":"Mobile Phone",
            "type":"Services"
        }
    ],
    "sg:phone":"+1 225 753 8660",
    "sg:postcode":"70816",
    "sg:province":"LA",
    "sg:tags":[
        "telephone",
        "cellular"
    ],
    "wof:name":"Radio Shack",
    "wof:placetype":"venue"
},
  "geometry": {"coordinates":[-91.007614,30.437644],"type":"Point"}
}