{
  "type": "Feature",
  "properties": {
    "iso:country":"US",
    "sg:address":"117 Lafitte Ave",
    "sg:city":"Lafayette",
    "sg:classifiers":[
        {
            "category":"Professional",
            "type":"Services"
        }
    ],
    "sg:phone":"+1 337 962 8600",
    "sg:postcode":"70506",
    "sg:province":"LA",
    "sg:tags":[
        "indoor",
        "testing"
    ],
    "wof:name":"Lafitte Avenue LLC",
    "wof:placetype":"venue"
},
  "geometry": {"coordinates":[-92.04067000000001,30.211965],"type":"Point"}
}