{
  "type": "Feature",
  "properties": {
    "iso:country":"US",
    "sg:address":"1704 Duson Ave",
    "sg:city":"Opelousas",
    "sg:classifiers":[
        {
            "category":"Taxi",
            "type":"Transportation"
        }
    ],
    "sg:phone":"+1 337 942 2515",
    "sg:postcode":"70570",
    "sg:province":"LA",
    "sg:tags":[
        "taxicab"
    ],
    "wof:name":"Lil' Richard's Express Taxi",
    "wof:placetype":"venue"
},
  "geometry": {"coordinates":[-92.102486,30.530965],"type":"Point"}
}