{
  "type": "Feature",
  "properties": {
    "addr:full":"1750 Ryan St Lake Charles LA 70601",
    "addr:housenumber":"1750",
    "addr:postcode":"70601",
    "addr:street":"Ryan St",
    "iso:country":"US",
    "sg:address":"1750 Ryan St",
    "sg:city":"Lake Charles",
    "sg:classifiers":[
        {
            "category":"Health Services",
            "subcategory":"Doctor",
            "type":"Services"
        }
    ],
    "sg:phone":"+1 337 433 3001",
    "sg:postcode":"70601",
    "sg:province":"LA",
    "sg:tags":[
        "clinic"
    ],
    "wof:name":"Louisiana Pet Imaging",
    "wof:placetype":"venue"
},
  "geometry": {"coordinates":[-93.219213,30.216326],"type":"Point"}
}