{
  "type": "Feature",
  "properties": {
    "addr:full":"503 E 1st St Kaplan LA 70548",
    "addr:housenumber":"503",
    "addr:postcode":"70548",
    "addr:street":"E 1St St",
    "iso:country":"US",
    "sg:address":"503 E 1st St",
    "sg:city":"Kaplan",
    "sg:classifiers":[
        {
            "category":"Restaurant",
            "type":"Food & Drink"
        }
    ],
    "sg:phone":"+1 337 643 8110",
    "sg:postcode":"70548",
    "sg:province":"LA",
    "wof:name":"Mc Donald's",
    "wof:placetype":"venue"
},
  "geometry": {"coordinates":[-92.28115099999999,29.996795],"type":"Point"}
}