{
  "type": "Feature",
  "properties": {
    "iso:country":"US",
    "sg:address":"151 Industrial Dr",
    "sg:city":"Slidell",
    "sg:classifiers":[
        {
            "category":"Wholesale",
            "subcategory":"Scrap",
            "type":"Manufacturing & Wholesale Goods"
        }
    ],
    "sg:phone":"+1 985 649 2940",
    "sg:postcode":"70460",
    "sg:province":"LA",
    "sg:tags":[
        "recycling",
        "center"
    ],
    "wof:name":"Ellis Recycling Co",
    "wof:placetype":"venue"
},
  "geometry": {"coordinates":[-89.777503,30.315764],"type":"Point"}
}