{
  "type": "Feature",
  "properties": {
    "iso:country":"US",
    "sg:address":"35055 Old State Hwy 16",
    "sg:city":"Denham Springs",
    "sg:classifiers":[
        {
            "category":"Restaurant",
            "type":"Food & Drink"
        }
    ],
    "sg:phone":"+1 225 667 2884",
    "sg:postcode":"70706",
    "sg:province":"LA",
    "sg:tags":[
        "parlor",
        "ice",
        "cream"
    ],
    "wof:name":"Kaleidoscoops",
    "wof:placetype":"venue"
},
  "geometry": {"coordinates":[-90.95292499999999,30.57715],"type":"Point"}
}