{
  "type": "Feature",
  "properties": {
    "addr:full":"100 W Walnut Ave Eunice LA 70535",
    "addr:housenumber":"100",
    "addr:postcode":"70535",
    "addr:street":"W Walnut Ave",
    "iso:country":"US",
    "sg:address":"100 W Walnut Ave",
    "sg:city":"Eunice",
    "sg:classifiers":[
        {
            "category":"Home & Garden",
            "subcategory":"Building Materials",
            "type":"Retail Goods"
        }
    ],
    "sg:phone":"+1 337 457 5273",
    "sg:postcode":"70535",
    "sg:province":"LA",
    "sg:tags":[
        "paint"
    ],
    "wof:name":"City Auto Supply Inc",
    "wof:placetype":"venue"
},
  "geometry": {"coordinates":[-92.416285,30.493895],"type":"Point"}
}