{
  "type": "Feature",
  "properties": {
    "iso:country":"US",
    "sg:address":"115 Payne St",
    "sg:city":"Cullen",
    "sg:classifiers":[
        {
            "category":"Organizations",
            "subcategory":"Religious Organization",
            "type":"Services"
        }
    ],
    "sg:phone":"+1 318 994 2144",
    "sg:postcode":"71021",
    "sg:province":"LA",
    "sg:tags":[
        "church"
    ],
    "wof:name":"Holy Temple First Church-God",
    "wof:placetype":"venue"
},
  "geometry": {"coordinates":[-93.44893500000001,32.972135],"type":"Point"}
}