{
  "type": "Feature",
  "properties": {
    "iso:country":"US",
    "sg:address":"3041 E Causeway Approach",
    "sg:city":"Mandeville",
    "sg:classifiers":[
        {
            "category":"Health Services",
            "subcategory":"Chiropractor",
            "type":"Services"
        }
    ],
    "sg:phone":"+1 985 624 2971",
    "sg:postcode":"70448",
    "sg:province":"LA",
    "wof:name":"Northshore Chiropractic",
    "wof:placetype":"venue"
},
  "geometry": {"coordinates":[-90.08944700000001,30.373915],"type":"Point"}
}