{
  "type": "Feature",
  "properties": {
    "iso:country":"US",
    "sg:address":"25050 State Rte 1",
    "sg:city":"Plaquemine",
    "sg:classifiers":[
        {
            "category":"Organizations",
            "subcategory":"Community Association",
            "type":"Services"
        }
    ],
    "sg:phone":"+1 225 687 3208",
    "sg:postcode":"70764",
    "sg:province":"LA",
    "sg:tags":[
        "military"
    ],
    "wof:name":"American Legion",
    "wof:placetype":"venue"
},
  "geometry": {"coordinates":[-91.22381900000001,30.276294],"type":"Point"}
}