{
  "type": "Feature",
  "properties": {
    "iso:country":"US",
    "sg:address":"7225 Airline Hwy",
    "sg:city":"Baton Rouge",
    "sg:classifiers":[
        {
            "category":"Wholesale",
            "subcategory":"Auto Parts",
            "type":"Manufacturing & Wholesale Goods"
        }
    ],
    "sg:phone":"+1 225 356 3800",
    "sg:postcode":"70805",
    "sg:province":"LA",
    "sg:tags":[
        "shaft",
        "drive"
    ],
    "wof:name":"Driveline Of Baton Rouge Inc",
    "wof:placetype":"venue"
},
  "geometry": {"coordinates":[-91.11556899999999,30.480778],"type":"Point"}
}