{
  "type": "Feature",
  "properties": {
    "iso:country":"US",
    "sg:address":"389 Black River Dr",
    "sg:city":"Madisonville",
    "sg:classifiers":[
        {
            "category":"Wholesale",
            "subcategory":"Construction Materials",
            "type":"Manufacturing & Wholesale Goods"
        }
    ],
    "sg:phone":"+1 985 542 5126",
    "sg:postcode":"70447",
    "sg:province":"LA",
    "sg:tags":[
        "fence"
    ],
    "wof:name":"Leyrer Fence & Deck",
    "wof:placetype":"venue"
},
  "geometry": {"coordinates":[-90.183329,30.428077],"type":"Point"}
}