{
  "type": "Feature",
  "properties": {
    "addr:full":"24970 State Rte 1 Plaquemine LA 70764",
    "addr:housenumber":"24970",
    "addr:postcode":"70764",
    "addr:street":"State Rte 1 Plaquemine",
    "iso:country":"US",
    "sg:address":"24970 State Rte 1",
    "sg:city":"Plaquemine",
    "sg:classifiers":[
        {
            "category":"Recreation",
            "type":"Entertainment"
        }
    ],
    "sg:phone":"+1 225 687 7900",
    "sg:postcode":"70764",
    "sg:province":"LA",
    "sg:tags":[
        "parks"
    ],
    "wof:name":"Iberville Parks & Recreation",
    "wof:placetype":"venue"
},
  "geometry": {"coordinates":[-91.22413,30.277046],"type":"Point"}
}