{
  "type": "Feature",
  "properties": {
    "iso:country":"US",
    "sg:address":"2750 Country Club Rd",
    "sg:city":"Lake Charles",
    "sg:classifiers":[
        {
            "category":"Restaurant",
            "type":"Food & Drink"
        }
    ],
    "sg:menulink":"http://www.allmenus.com/la/lake-charles/106974-soup-man/menu/",
    "sg:phone":"+1 337 480 0424",
    "sg:postcode":"70605",
    "sg:province":"LA",
    "sg:tags":[
        "soup",
        "american",
        "salad"
    ],
    "wof:name":"Soup Man",
    "wof:placetype":"venue"
},
  "geometry": {"coordinates":[-93.26522799999999,30.16862],"type":"Point"}
}