{
  "type": "Feature",
  "properties": {
    "iso:country":"US",
    "sg:address":"3350 Ridgelake Dr",
    "sg:city":"Metairie",
    "sg:classifiers":[
        {
            "category":"Professional",
            "subcategory":"Accounting & Tax Preparation",
            "type":"Services"
        }
    ],
    "sg:phone":"+1 504 835 5599",
    "sg:postcode":"70002",
    "sg:province":"LA",
    "sg:tags":[
        "accountant"
    ],
    "wof:name":"Patrick J Gros",
    "wof:placetype":"venue"
},
  "geometry": {"coordinates":[-90.153367,30.010268],"type":"Point"}
}