{
  "type": "Feature",
  "properties": {
    "iso:country":"US",
    "sg:address":"781 Jump Basin Rd",
    "sg:city":"Venice",
    "sg:phone":"+1 985 534 2220",
    "sg:postcode":"70091",
    "sg:province":"LA",
    "sg:tags":[
        "oil"
    ],
    "wof:name":"Martin Midstream",
    "wof:placetype":"venue"
},
  "geometry": {"coordinates":[-89.35434600000001,29.266012],"type":"Point"}
}