{
  "type": "Feature",
  "properties": {
    "iso:country":"US",
    "sg:address":"9930 Lake Forest Blvd",
    "sg:city":"New Orleans",
    "sg:classifiers":[
        {
            "category":"Bars & Pubs",
            "type":"Food & Drink"
        }
    ],
    "sg:phone":"+1 504 241 9963",
    "sg:postcode":"70127",
    "sg:province":"LA",
    "sg:tags":[
        "lounge",
        "cocktail"
    ],
    "wof:name":"Sports Bar Daiquiri & Grill",
    "wof:placetype":"venue"
},
  "geometry": {"coordinates":[-89.976073,30.03094],"type":"Point"}
}