{
  "type": "Feature",
  "properties": {
    "addr:full":"3733 Blanchard Dr Chalmette LA 70043",
    "addr:housenumber":"3733",
    "addr:postcode":"70043",
    "addr:street":"Blanchard Dr Chalmette",
    "iso:country":"US",
    "sg:address":"3733 Blanchard Dr",
    "sg:city":"Chalmette",
    "sg:classifiers":[
        {
            "category":"Retail",
            "subcategory":"Repair Shop",
            "type":"Services"
        }
    ],
    "sg:phone":"+1 504 309 3736",
    "sg:postcode":"70043",
    "sg:province":"LA",
    "wof:name":"Steam Tech Cleaning Service",
    "wof:placetype":"venue"
},
  "geometry": {"coordinates":[-89.939781,29.947406],"type":"Point"}
}