{
  "type": "Feature",
  "properties": {
    "addr:full":"3422 Cleary Ave Metairie LA 70002",
    "addr:housenumber":"3422",
    "addr:postcode":"70002",
    "addr:street":"Cleary Ave",
    "iso:country":"US",
    "sg:address":"3422 Cleary Ave",
    "sg:city":"Metairie",
    "sg:classifiers":[
        {
            "category":"Social Services",
            "type":"Services"
        }
    ],
    "sg:phone":"+1 504 455 7058",
    "sg:postcode":"70002",
    "sg:province":"LA",
    "wof:name":"Sylvia Hodges LPC",
    "wof:placetype":"venue"
},
  "geometry": {"coordinates":[-90.17273900000001,30.006113],"type":"Point"}
}