{
  "type": "Feature",
  "properties": {
    "addr:full":"4036 Camphor St Marrero LA 70072",
    "addr:housenumber":"4036",
    "addr:postcode":"70072",
    "addr:street":"Camphor St Marrero",
    "iso:country":"US",
    "sg:address":"4036 Camphor St",
    "sg:city":"Marrero",
    "sg:classifiers":[
        {
            "category":"Freight",
            "type":"Transportation"
        }
    ],
    "sg:phone":"+1 504 347 3818",
    "sg:postcode":"70072",
    "sg:province":"LA",
    "sg:tags":[
        "local",
        "storage",
        "trucking"
    ],
    "wof:name":"Picou Trucking Company",
    "wof:placetype":"venue"
},
  "geometry": {"coordinates":[-90.088095,29.883637],"type":"Point"}
}