{
  "type": "Feature",
  "properties": {
    "iso:country":"US",
    "sg:address":"3936 Berot Dr",
    "sg:city":"Metairie",
    "sg:classifiers":[
        {
            "category":"Professional",
            "subcategory":"Business Services",
            "type":"Services"
        }
    ],
    "sg:phone":"+1 504 887 5681",
    "sg:postcode":"70002",
    "sg:province":"LA",
    "sg:tags":[
        "monogramming"
    ],
    "wof:name":"KS Monogramming",
    "wof:placetype":"venue"
},
  "geometry": {"coordinates":[-90.174751,30.012725],"type":"Point"}
}