{
  "type": "Feature",
  "properties": {
    "addr:full":"1044 Michigan Ave Port Allen LA 70767",
    "addr:housenumber":"1044",
    "addr:postcode":"70767",
    "addr:street":"Michigan Ave",
    "iso:country":"US",
    "sg:address":"1044 Michigan Ave",
    "sg:city":"Port Allen",
    "sg:classifiers":[
        {
            "category":"Banks & Credit Unions",
            "subcategory":"Bank",
            "type":"Services"
        }
    ],
    "sg:phone":"+1 225 344 0318",
    "sg:postcode":"70767",
    "sg:province":"LA",
    "wof:name":"West Baton Rouge Teachers CU",
    "wof:placetype":"venue"
},
  "geometry": {"coordinates":[-91.21313000000001,30.459064],"type":"Point"}
}