{
  "type": "Feature",
  "properties": {
    "iso:country":"US",
    "sg:address":"321 Dugas Ln",
    "sg:city":"Melville",
    "sg:classifiers":[
        {
            "category":"Wholesale",
            "subcategory":"Construction Materials",
            "type":"Manufacturing & Wholesale Goods"
        }
    ],
    "sg:phone":"+1 337 623 4252",
    "sg:postcode":"71353",
    "sg:province":"LA",
    "sg:tags":[
        "fence"
    ],
    "wof:name":"Dugas Fence Co",
    "wof:placetype":"venue"
},
  "geometry": {"coordinates":[-91.736278,30.69645],"type":"Point"}
}