{
  "type": "Feature",
  "properties": {
    "iso:country":"US",
    "sg:address":"3826 Peters Rd",
    "sg:city":"Harvey",
    "sg:classifiers":[
        {
            "category":"Building & Trades",
            "subcategory":"Construction",
            "type":"Services"
        }
    ],
    "sg:phone":"+1 504 368 2500",
    "sg:postcode":"70058",
    "sg:province":"LA",
    "sg:tags":[
        "general",
        "contractor"
    ],
    "wof:name":"Trinity Construction",
    "wof:placetype":"venue"
},
  "geometry": {"coordinates":[-90.057198,29.850317],"type":"Point"}
}