{
  "type": "Feature",
  "properties": {
    "iso:country":"US",
    "sg:address":"1308 Distributors Row",
    "sg:city":"New Orleans",
    "sg:classifiers":[
        {
            "category":"Wholesale",
            "subcategory":"Auto Parts",
            "type":"Manufacturing & Wholesale Goods"
        }
    ],
    "sg:phone":"+1 504 734 0307",
    "sg:postcode":"70123",
    "sg:province":"LA",
    "sg:tags":[
        "automobile",
        "supply"
    ],
    "wof:name":"LA Engines",
    "wof:placetype":"venue"
},
  "geometry": {"coordinates":[-90.190561,29.959061],"type":"Point"}
}