{
  "type": "Feature",
  "properties": {
    "iso:country":"US",
    "sg:address":"1275 Springwood Ln",
    "sg:city":"Shreveport",
    "sg:classifiers":[
        {
            "category":"Building & Trades",
            "subcategory":"Construction",
            "type":"Services"
        }
    ],
    "sg:phone":"+1 318 929 9305",
    "sg:postcode":"71107",
    "sg:province":"LA",
    "sg:tags":[
        "general",
        "contractor"
    ],
    "wof:name":"V & G Construction",
    "wof:placetype":"venue"
},
  "geometry": {"coordinates":[-93.965419,32.551834],"type":"Point"}
}