{
  "type": "Feature",
  "properties": {
    "addr:full":"143 Kass St Gretna LA 70056",
    "addr:housenumber":"143",
    "addr:postcode":"70056",
    "addr:street":"Kass St",
    "iso:country":"US",
    "sg:address":"143 Kass St",
    "sg:city":"Gretna",
    "sg:classifiers":[
        {
            "category":"Building & Trades",
            "subcategory":"Construction",
            "type":"Services"
        }
    ],
    "sg:phone":"+1 504 366 3208",
    "sg:postcode":"70056",
    "sg:province":"LA",
    "sg:tags":[
        "contractor"
    ],
    "wof:name":"Royal Roofing Co Inc",
    "wof:placetype":"venue"
},
  "geometry": {"coordinates":[-90.042382,29.912683],"type":"Point"}
}