{
  "type": "Feature",
  "properties": {
    "iso:country":"US",
    "sg:address":"6716 Hwy 190 W",
    "sg:city":"Port Allen",
    "sg:classifiers":[
        {
            "category":"Building & Trades",
            "subcategory":"Construction",
            "type":"Services"
        }
    ],
    "sg:phone":"+1 225 387 9199",
    "sg:postcode":"70767",
    "sg:province":"LA",
    "sg:tags":[
        "general",
        "contractor"
    ],
    "wof:name":"Clark Construction Ent LLC",
    "wof:placetype":"venue"
},
  "geometry": {"coordinates":[-91.307502,30.499413],"type":"Point"}
}