{
  "type": "Feature",
  "properties": {
    "addr:full":"1750 W Prien Lake Rd Lake Charles LA 70601",
    "addr:housenumber":"1750",
    "addr:postcode":"70601",
    "addr:street":"W Prien Lake Rd",
    "iso:country":"US",
    "sg:address":"1750 W Prien Lake Rd",
    "sg:city":"Lake Charles",
    "sg:classifiers":[
        {
            "category":"Shopping",
            "subcategory":"Computers & Home Electronics",
            "type":"Retail Goods"
        }
    ],
    "sg:phone":"+1 337 478 6133",
    "sg:postcode":"70601",
    "sg:province":"LA",
    "sg:tags":[
        "game",
        "video"
    ],
    "wof:name":"EB Games",
    "wof:placetype":"venue"
},
  "geometry": {"coordinates":[-93.24636700000001,30.197664],"type":"Point"}
}