{
  "type": "Feature",
  "properties": {
    "iso:country":"US",
    "sg:address":"330 Moosa Blvd",
    "sg:city":"Eunice",
    "sg:classifiers":[
        {
            "category":"Utilities",
            "subcategory":"Cable",
            "type":"Services"
        }
    ],
    "sg:phone":"+1 337 948 6767",
    "sg:postcode":"70535",
    "sg:province":"LA",
    "sg:tags":[
        "television"
    ],
    "wof:name":"TWI Cable Inc",
    "wof:placetype":"venue"
},
  "geometry": {"coordinates":[-92.404794,30.495573],"type":"Point"}
}