{
  "type": "Feature",
  "properties": {
    "iso:country":"US",
    "sg:address":"2001 Soniat St",
    "sg:city":"New Orleans",
    "sg:classifiers":[
        {
            "category":"Manufacturing",
            "subcategory":"Metals",
            "type":"Manufacturing & Wholesale Goods"
        }
    ],
    "sg:phone":"+1 504 949 2103",
    "sg:postcode":"70115",
    "sg:province":"LA",
    "sg:tags":[
        "steel"
    ],
    "wof:name":"Resteel Supply Corp",
    "wof:placetype":"venue"
},
  "geometry": {"coordinates":[-90.10943399999999,29.933056],"type":"Point"}
}