{
  "type": "Feature",
  "properties": {
    "iso:country":"US",
    "sg:address":"9088 Mansfield Rd",
    "sg:city":"Shreveport",
    "sg:classifiers":[
        {
            "category":"Restaurant",
            "type":"Food & Drink"
        }
    ],
    "sg:menulink":"http://www.allmenus.com/la/shreveport/82259-applebees/menu/",
    "sg:phone":"+1 318 688 7235",
    "sg:postcode":"71118",
    "sg:province":"LA",
    "sg:tags":[
        "burger",
        "american",
        "sandwich",
        "soup"
    ],
    "wof:name":"Applebee's",
    "wof:placetype":"venue"
},
  "geometry": {"coordinates":[-93.79850399999999,32.408197],"type":"Point"}
}