{
  "type": "Feature",
  "properties": {
    "addr:full":"701 Metairie Rd Metairie LA 70005",
    "addr:housenumber":"701",
    "addr:postcode":"70005",
    "addr:street":"Metairie Rd",
    "iso:country":"US",
    "sg:address":"701 Metairie Rd",
    "sg:city":"Metairie",
    "sg:classifiers":[
        {
            "category":"Professional",
            "subcategory":"Business Services",
            "type":"Services"
        }
    ],
    "sg:phone":"+1 504 831 2668",
    "sg:postcode":"70005",
    "sg:province":"LA",
    "sg:tags":[
        "interior",
        "consultant",
        "design",
        "decorator"
    ],
    "wof:name":"N B Interiors",
    "wof:placetype":"venue"
},
  "geometry": {"coordinates":[-90.13162800000001,29.988531],"type":"Point"}
}