{
  "type": "Feature",
  "properties": {
    "iso:country":"US",
    "sg:address":"1500 Gold St",
    "sg:city":"Natchitoches",
    "sg:classifiers":[
        {
            "category":"Education",
            "subcategory":"School",
            "type":"Public Place"
        }
    ],
    "sg:phone":"+1 318 352 6170",
    "sg:postcode":"71457",
    "sg:province":"LA",
    "wof:name":"Special Education",
    "wof:placetype":"venue"
},
  "geometry": {"coordinates":[-93.098418,31.778855],"type":"Point"}
}