{
  "type": "Feature",
  "properties": {
    "iso:country":"US",
    "sg:address":"714 Caffin Ave",
    "sg:city":"New Orleans",
    "sg:classifiers":[
        {
            "category":"Organizations",
            "subcategory":"Religious Organization",
            "type":"Services"
        }
    ],
    "sg:phone":"+1 504 949 4957",
    "sg:postcode":"70117",
    "sg:province":"LA",
    "wof:name":"Golden Gate Missionary Ba",
    "wof:placetype":"venue"
},
  "geometry": {"coordinates":[-90.01695100000001,29.957913],"type":"Point"}
}