{
  "type": "Feature",
  "properties": {
    "iso:country":"US",
    "sg:address":"19715 Plank Rd",
    "sg:city":"Zachary",
    "sg:classifiers":[
        {
            "category":"Retail",
            "subcategory":"Repair Shop",
            "type":"Services"
        }
    ],
    "sg:phone":"+1 225 654 0897",
    "sg:postcode":"70791",
    "sg:province":"LA",
    "wof:name":"Chris T V",
    "wof:placetype":"venue"
},
  "geometry": {"coordinates":[-91.10829200000001,30.638823],"type":"Point"}
}