{
  "type": "Feature",
  "properties": {
    "iso:country":"US",
    "sg:address":"188 Elvie Ct",
    "sg:city":"Westwego",
    "sg:classifiers":[
        {
            "category":"Travel",
            "subcategory":"Travel Agent",
            "type":"Entertainment"
        }
    ],
    "sg:phone":"+1 504 436 1832",
    "sg:postcode":"70094",
    "sg:province":"LA",
    "sg:tags":[
        "operator",
        "tour"
    ],
    "wof:name":"Jutta Woods Tour Guide",
    "wof:placetype":"venue"
},
  "geometry": {"coordinates":[-90.21086200000001,29.899079],"type":"Point"}
}