{
  "type": "Feature",
  "properties": {
    "addr:full":"20119 Tv Tower Rd Fenton LA 70648",
    "addr:postcode":"20119;70648",
    "addr:street":"Tv Tower Rd",
    "iso:country":"US",
    "sg:address":"20119 Tv Tower Rd",
    "sg:city":"Fenton",
    "sg:classifiers":[
        {
            "category":"Professional",
            "subcategory":"Management & Consulting",
            "type":"Services"
        }
    ],
    "sg:phone":"+1 337 756 2665",
    "sg:postcode":"70648",
    "sg:province":"LA",
    "sg:tags":[
        "consultant",
        "energy",
        "conservation"
    ],
    "wof:name":"H S Resources",
    "wof:placetype":"venue"
},
  "geometry": {"coordinates":[-92.913432,30.379673],"type":"Point"}
}