{
  "type": "Feature",
  "properties": {
    "iso:country":"US",
    "sg:address":"145 Woodland Dr",
    "sg:city":"La Place",
    "sg:classifiers":[
        {
            "category":"Freight",
            "type":"Transportation"
        }
    ],
    "sg:phone":"+1 985 652 7225",
    "sg:postcode":"70068",
    "sg:province":"LA",
    "sg:tags":[
        "trucking"
    ],
    "wof:name":"Direct Transport Agency Inc",
    "wof:placetype":"venue"
},
  "geometry": {"coordinates":[-90.450401,30.086123],"type":"Point"}
}