{
  "type": "Feature",
  "properties": {
    "addr:full":"1802 S Arkansas St Springhill LA 71075",
    "addr:housenumber":"1802",
    "addr:postcode":"71075",
    "addr:street":"S Arkansas St",
    "iso:country":"US",
    "sg:address":"1802 S Arkansas St",
    "sg:city":"Springhill",
    "sg:phone":"+1 318 539 2594",
    "sg:postcode":"71075",
    "sg:province":"LA",
    "sg:tags":[
        "oil",
        "gasoline"
    ],
    "sg:website":"www.smithssouth-central.com",
    "wof:name":"Smiths South-Central Sales Co",
    "wof:placetype":"venue"
},
  "geometry": {"coordinates":[-93.460086,32.986468],"type":"Point"}
}