{
  "type": "Feature",
  "properties": {
    "iso:country":"US",
    "sg:address":"3417 Paris Rd",
    "sg:city":"Chalmette",
    "sg:classifiers":[
        {
            "category":"Retail",
            "subcategory":"Auto Repair",
            "type":"Services"
        }
    ],
    "sg:phone":"+1 504 271 7365",
    "sg:postcode":"70043",
    "sg:province":"LA",
    "sg:tags":[
        "automobile",
        "inspection"
    ],
    "wof:name":"St Bernard Motor Vehicle",
    "wof:placetype":"venue"
},
  "geometry": {"coordinates":[-89.959796,29.950268],"type":"Point"}
}