{
  "type": "Feature",
  "properties": {
    "addr:full":"2215 Cleary Ave Metairie LA 70001",
    "addr:housenumber":"2215",
    "addr:postcode":"70001",
    "addr:street":"Cleary Ave",
    "iso:country":"US",
    "sg:address":"2215 Cleary Ave",
    "sg:city":"Metairie",
    "sg:classifiers":[
        {
            "category":"Organizations",
            "subcategory":"Community Association",
            "type":"Services"
        }
    ],
    "sg:phone":"+1 504 888 8152",
    "sg:postcode":"70001",
    "sg:province":"LA",
    "sg:tags":[
        "fraternal"
    ],
    "wof:name":"Elks Lodge",
    "wof:placetype":"venue"
},
  "geometry": {"coordinates":[-90.17135,29.994208],"type":"Point"}
}