{
  "type": "Feature",
  "properties": {
    "iso:country":"US",
    "sg:address":"520 City Park Ave",
    "sg:city":"New Orleans",
    "sg:classifiers":[
        {
            "category":"Restaurant",
            "type":"Food & Drink"
        }
    ],
    "sg:phone":"+1 504 488 3622",
    "sg:postcode":"70119",
    "sg:province":"LA",
    "sg:tags":[
        "eating"
    ],
    "wof:name":"City Park Cafe",
    "wof:placetype":"venue"
},
  "geometry": {"coordinates":[-90.105431,29.983545],"type":"Point"}
}