{
  "type": "Feature",
  "properties": {
    "addr:full":"6600 Franklin Ave New Orleans LA 70122",
    "addr:housenumber":"6600",
    "addr:postcode":"70122",
    "addr:street":"Franklin Ave",
    "iso:country":"US",
    "sg:address":"6600 Franklin Ave",
    "sg:city":"New Orleans",
    "sg:classifiers":[
        {
            "category":"Banks & Credit Unions",
            "subcategory":"Bank",
            "type":"Services"
        }
    ],
    "sg:phone":"+1 504 282 1445",
    "sg:postcode":"70122",
    "sg:province":"LA",
    "sg:tags":[
        "loan",
        "real estate"
    ],
    "wof:name":"Wells Fargo Financial Accptnce",
    "wof:placetype":"venue"
},
  "geometry": {"coordinates":[-90.05239899999999,30.028067],"type":"Point"}
}