{
  "type": "Feature",
  "properties": {
    "addr:full":"1116 E Kent Dr Sulphur LA 70663",
    "addr:housenumber":"1116",
    "addr:postcode":"70663",
    "addr:street":"E Kent Dr",
    "iso:country":"US",
    "sg:address":"1116 E Kent Dr",
    "sg:city":"Sulphur",
    "sg:classifiers":[
        {
            "category":"Health Services",
            "subcategory":"Doctor",
            "type":"Services"
        }
    ],
    "sg:phone":"+1 337 527 7095",
    "sg:postcode":"70663",
    "sg:province":"LA",
    "sg:tags":[
        "clinic"
    ],
    "wof:name":"Sulphur Prenatal Clinic",
    "wof:placetype":"venue"
},
  "geometry": {"coordinates":[-93.370391,30.228924],"type":"Point"}
}