{
  "type": "Feature",
  "properties": {
    "iso:country":"US",
    "sg:address":"355 N Talens Landing Rd",
    "sg:city":"Gueydan",
    "sg:classifiers":[
        {
            "category":"Travel",
            "subcategory":"Hotels & Motels",
            "type":"Entertainment"
        }
    ],
    "sg:phone":"+1 337 536 7066",
    "sg:postcode":"70542",
    "sg:province":"LA",
    "sg:tags":[
        "operation"
    ],
    "wof:name":"La Maison Des Chenes",
    "wof:placetype":"venue"
},
  "geometry": {"coordinates":[-92.63770700000001,30.037408],"type":"Point"}
}