{
  "type": "Feature",
  "properties": {
    "iso:country":"US",
    "sg:address":"204 S Burnside Ave",
    "sg:city":"Gonzales",
    "sg:classifiers":[
        {
            "category":"Food & Beverages",
            "subcategory":"Bakery",
            "type":"Retail Goods"
        }
    ],
    "sg:phone":"+1 225 644 4578",
    "sg:postcode":"70737",
    "sg:province":"LA",
    "sg:tags":[
        "baker"
    ],
    "wof:name":"Cal's Bakery",
    "wof:placetype":"venue"
},
  "geometry": {"coordinates":[-90.920601,30.23198],"type":"Point"}
}