{
  "type": "Feature",
  "properties": {
    "addr:full":"2029 N Acadian Thruway W Baton Rouge LA 70802",
    "addr:housenumber":"2029",
    "addr:postcode":"70802",
    "addr:street":"N Acadian Thruway W",
    "iso:country":"US",
    "sg:address":"2029 N Acadian Thruway W",
    "sg:city":"Baton Rouge",
    "sg:classifiers":[
        {
            "category":"Restaurant",
            "type":"Food & Drink"
        }
    ],
    "sg:menulink":"http://www.allmenus.com/la/baton-rouge/13216-churchs-chicken/menu/",
    "sg:phone":"+1 225 387 1174",
    "sg:postcode":"70802",
    "sg:province":"LA",
    "sg:tags":[
        "chicken",
        "wing"
    ],
    "wof:name":"Church's Chicken",
    "wof:placetype":"venue"
},
  "geometry": {"coordinates":[-91.156594,30.466755],"type":"Point"}
}