{
  "type": "Feature",
  "properties": {
    "addr:full":"217 Faye Dr Converse LA 71065",
    "addr:housenumber":"217",
    "addr:postcode":"71065",
    "addr:street":"Faye Dr",
    "iso:country":"US",
    "sg:address":"217 Faye Dr",
    "sg:city":"Converse",
    "sg:classifiers":[
        {
            "category":"Insurance",
            "subcategory":"Insurance Agent",
            "type":"Services"
        }
    ],
    "sg:phone":"+1 318 796 3488",
    "sg:postcode":"71065",
    "sg:province":"LA",
    "wof:name":"Modern Woodmen of America",
    "wof:placetype":"venue"
},
  "geometry": {"coordinates":[-93.627121,31.7777],"type":"Point"}
}