{
  "type": "Feature",
  "properties": {
    "iso:country":"US",
    "sg:address":"4535 Magazine St",
    "sg:city":"New Orleans",
    "sg:classifiers":[
        {
            "category":"Shopping",
            "type":"Retail Goods"
        }
    ],
    "sg:phone":"+1 504 896 9198",
    "sg:postcode":"70115",
    "sg:province":"LA",
    "sg:tags":[
        "art",
        "gallery",
        "dealer"
    ],
    "wof:name":"Martin Luke Gallery",
    "wof:placetype":"venue"
},
  "geometry": {"coordinates":[-90.103498,29.920713],"type":"Point"}
}