{
  "type": "Feature",
  "properties": {
    "addr:full":"326 Heymann Blvd Lafayette LA 70503",
    "addr:housenumber":"326",
    "addr:postcode":"70503",
    "addr:street":"Heymann Blvd",
    "iso:country":"US",
    "sg:address":"326 Heymann Blvd",
    "sg:city":"Lafayette",
    "sg:classifiers":[
        {
            "category":"Shopping",
            "subcategory":"Gifts & Souvenirs",
            "type":"Retail Goods"
        }
    ],
    "sg:phone":"+1 337 235 9557",
    "sg:postcode":"70503",
    "sg:province":"LA",
    "sg:tags":[
        "shop"
    ],
    "wof:name":"Nest",
    "wof:placetype":"venue"
},
  "geometry": {"coordinates":[-92.01541899999999,30.204456],"type":"Point"}
}