{
  "type": "Feature",
  "properties": {
    "iso:country":"US",
    "sg:address":"800 Central Ave",
    "sg:city":"Jefferson",
    "sg:classifiers":[
        {
            "category":"Wholesale",
            "subcategory":"Medical Equipment & Supplies",
            "type":"Manufacturing & Wholesale Goods"
        }
    ],
    "sg:phone":"+1 504 733 9729",
    "sg:postcode":"70121",
    "sg:province":"LA",
    "sg:tags":[
        "repair",
        "sales",
        "apparatus",
        "x"
    ],
    "wof:name":"Medical Imaging Solutions Inc",
    "wof:placetype":"venue"
},
  "geometry": {"coordinates":[-90.17364499999999,29.969934],"type":"Point"}
}