{
  "type": "Feature",
  "properties": {
    "addr:full":"8088 Hawks Rd Leesville LA 71459",
    "addr:housenumber":"8088",
    "addr:postcode":"71459",
    "addr:street":"Hawks Rd",
    "iso:country":"US",
    "sg:address":"8088 Hawks Rd",
    "sg:city":"Leesville",
    "sg:classifiers":[
        {
            "category":"Social Services",
            "subcategory":"Job Training",
            "type":"Services"
        }
    ],
    "sg:phone":"+1 337 462 8880",
    "sg:postcode":"71459",
    "sg:province":"LA",
    "sg:tags":[
        "rehabilitation"
    ],
    "wof:name":"Tri Parish Rehabilitation Hosp",
    "wof:placetype":"venue"
},
  "geometry": {"coordinates":[-93.300838,30.94145],"type":"Point"}
}