{
  "type": "Feature",
  "properties": {
    "addr:full":"11179 Florida Blvd Baton Rouge LA 70815",
    "addr:housenumber":"11179",
    "addr:postcode":"70815",
    "addr:street":"Florida Blvd",
    "iso:country":"US",
    "sg:address":"11179 Florida Blvd",
    "sg:city":"Baton Rouge",
    "sg:classifiers":[
        {
            "category":"Autos & Motor Vehicles",
            "subcategory":"Automobile Sales",
            "type":"Retail Goods"
        }
    ],
    "sg:phone":"+1 225 274 1774",
    "sg:postcode":"70815",
    "sg:province":"LA",
    "sg:tags":[
        "car",
        "dealer"
    ],
    "wof:name":"Auto South",
    "wof:placetype":"venue"
},
  "geometry": {"coordinates":[-91.06250900000001,30.458224],"type":"Point"}
}