{
  "type": "Feature",
  "properties": {
    "iso:country":"US",
    "sg:address":"1402 Lewis St",
    "sg:city":"Sulphur",
    "sg:classifiers":[
        {
            "category":"Building & Trades",
            "subcategory":"Construction",
            "type":"Services"
        }
    ],
    "sg:phone":"+1 337 527 7632",
    "sg:postcode":"70663",
    "sg:province":"LA",
    "sg:tags":[
        "maker",
        "cabinet"
    ],
    "wof:name":"Cryer Custom Woodworking",
    "wof:placetype":"venue"
},
  "geometry": {"coordinates":[-93.367902,30.259165],"type":"Point"}
}