{
  "type": "Feature",
  "properties": {
    "addr:full":"4417 Transcontinental Dr Metairie LA 70006",
    "addr:housenumber":"4417",
    "addr:postcode":"70006",
    "addr:street":"Transcontinental Dr",
    "iso:country":"US",
    "sg:address":"4417 Transcontinental Dr",
    "sg:city":"Metairie",
    "sg:classifiers":[
        {
            "category":"Banks & Credit Unions",
            "subcategory":"Investment Brokerage",
            "type":"Services"
        }
    ],
    "sg:phone":"+1 504 456 7303",
    "sg:postcode":"70006",
    "sg:province":"LA",
    "sg:tags":[
        "stock",
        "bond"
    ],
    "wof:name":"Edward Jones Co",
    "wof:placetype":"venue"
},
  "geometry": {"coordinates":[-90.198571,30.017574],"type":"Point"}
}