{
  "type": "Feature",
  "properties": {
    "iso:country":"US",
    "sg:address":"809 Julia St",
    "sg:city":"Rayville",
    "sg:classifiers":[
        {
            "category":"Insurance",
            "subcategory":"Insurance Agent",
            "type":"Services"
        }
    ],
    "sg:phone":"+1 318 728 3304",
    "sg:postcode":"71269",
    "sg:province":"LA",
    "wof:name":"Shelter Insurance",
    "wof:placetype":"venue"
},
  "geometry": {"coordinates":[-91.758899,32.474504],"type":"Point"}
}