{
  "type": "Feature",
  "properties": {
    "iso:country":"US",
    "sg:address":"1528 Molitor St",
    "sg:city":"Mandeville",
    "sg:classifiers":[
        {
            "category":"Wholesale",
            "subcategory":"Electrical",
            "type":"Manufacturing & Wholesale Goods"
        }
    ],
    "sg:phone":"+1 985 727 2963",
    "sg:postcode":"70448",
    "sg:province":"LA",
    "sg:tags":[
        "alarm",
        "burglar",
        "system"
    ],
    "wof:name":"Alpha Systems",
    "wof:placetype":"venue"
},
  "geometry": {"coordinates":[-90.038066,30.362744],"type":"Point"}
}