{
  "type": "Feature",
  "properties": {
    "iso:country":"US",
    "sg:address":"6403 General Meyer Ave",
    "sg:city":"New Orleans",
    "sg:classifiers":[
        {
            "category":"Professional",
            "subcategory":"Business Services",
            "type":"Services"
        }
    ],
    "sg:phone":"+1 504 393 9893",
    "sg:postcode":"70131",
    "sg:province":"LA",
    "sg:tags":[
        "recording",
        "studio"
    ],
    "wof:name":"Golden Money Recording Studio",
    "wof:placetype":"venue"
},
  "geometry": {"coordinates":[-89.984675,29.923669],"type":"Point"}
}