{
  "type": "Feature",
  "properties": {
    "iso:country":"US",
    "sg:address":"3218 Line Ave",
    "sg:city":"Shreveport",
    "sg:classifiers":[
        {
            "category":"Real Estate",
            "subcategory":"Surveying",
            "type":"Services"
        }
    ],
    "sg:phone":"+1 318 226 0100",
    "sg:postcode":"71104",
    "sg:province":"LA",
    "sg:tags":[
        "surveyor"
    ],
    "wof:name":"Landpoint Surveys Inc",
    "wof:placetype":"venue"
},
  "geometry": {"coordinates":[-93.746117,32.479467],"type":"Point"}
}