{
  "type": "Feature",
  "properties": {
    "addr:full":"840 E Laurel Ave Eunice LA 70535",
    "addr:housenumber":"840",
    "addr:postcode":"70535",
    "addr:street":"E Laurel Ave",
    "iso:country":"US",
    "sg:address":"840 E Laurel Ave",
    "sg:city":"Eunice",
    "sg:classifiers":[
        {
            "category":"Banks & Credit Unions",
            "subcategory":"Bank",
            "type":"Services"
        }
    ],
    "sg:phone":"+1 337 457 9585",
    "sg:postcode":"70535",
    "sg:province":"LA",
    "sg:tags":[
        "loan",
        "real estate"
    ],
    "wof:name":"Teche Federal Bank",
    "wof:placetype":"venue"
},
  "geometry": {"coordinates":[-92.40505,30.494945],"type":"Point"}
}