{
  "type": "Feature",
  "properties": {
    "iso:country":"US",
    "sg:address":"338 Edwards Ave",
    "sg:city":"New Orleans",
    "sg:classifiers":[
        {
            "category":"Communications",
            "subcategory":"Film & Video Production",
            "type":"Services"
        }
    ],
    "sg:phone":"+1 504 304 7345",
    "sg:postcode":"70123",
    "sg:province":"LA",
    "sg:tags":[
        "taping"
    ],
    "wof:name":"Cox-10 Productions",
    "wof:placetype":"venue"
},
  "geometry": {"coordinates":[-90.188964,29.947805],"type":"Point"}
}