{
  "type": "Feature",
  "properties": {
    "iso:country":"US",
    "sg:address":"3421 Esplanade Ave",
    "sg:city":"New Orleans",
    "sg:classifiers":[
        {
            "category":"Real Estate",
            "subcategory":"Developer",
            "type":"Services"
        }
    ],
    "sg:phone":"+1 504 482 5065",
    "sg:postcode":"70119",
    "sg:province":"LA",
    "sg:tags":[
        "cemetery"
    ],
    "wof:name":"St Louis Cemeteries",
    "wof:placetype":"venue"
},
  "geometry": {"coordinates":[-90.08855,29.983201],"type":"Point"}
}