{
  "type": "Feature",
  "properties": {
    "iso:country":"US",
    "sg:address":"2612 Metairie Rd",
    "sg:city":"Metairie",
    "sg:classifiers":[
        {
            "category":"Health Services",
            "subcategory":"Chiropractor",
            "type":"Services"
        }
    ],
    "sg:phone":"+1 504 833 5363",
    "sg:postcode":"70001",
    "sg:province":"LA",
    "wof:name":"Metairie Chiropractic Clinic",
    "wof:placetype":"venue"
},
  "geometry": {"coordinates":[-90.151796,29.97988],"type":"Point"}
}