{
  "type": "Feature",
  "properties": {
    "iso:country":"US",
    "sg:address":"708 Barataria Blvd",
    "sg:city":"Marrero",
    "sg:classifiers":[
        {
            "category":"Recreation",
            "type":"Entertainment"
        },
        {
            "category":"Building & Trades",
            "subcategory":"Construction",
            "type":"Services"
        }
    ],
    "sg:phone":"+1 504 348 1770",
    "sg:postcode":"70072",
    "sg:province":"LA",
    "sg:tags":[
        "spa",
        "house",
        "contractor",
        "sauna",
        "bath"
    ],
    "wof:name":"Southern Refinishing LLC",
    "wof:placetype":"venue"
},
  "geometry": {"coordinates":[-90.100582,29.898624],"type":"Point"}
}