{
  "type": "Feature",
  "properties": {
    "addr:full":"1902 Midway St Shreveport LA 71108",
    "addr:housenumber":"1902",
    "addr:postcode":"71108",
    "addr:street":"Midway St",
    "iso:country":"US",
    "sg:address":"1902 Midway St",
    "sg:city":"Shreveport",
    "sg:classifiers":[
        {
            "category":"Professional",
            "subcategory":"Accounting & Tax Preparation",
            "type":"Services"
        }
    ],
    "sg:phone":"+1 318 636 5864",
    "sg:postcode":"71108",
    "sg:province":"LA",
    "sg:tags":[
        "bookkeeping",
        "general"
    ],
    "wof:name":"Beverly's Tax & Elec Filing",
    "wof:placetype":"venue"
},
  "geometry": {"coordinates":[-93.77032800000001,32.471014],"type":"Point"}
}