{
  "type": "Feature",
  "properties": {
    "iso:country":"US",
    "sg:address":"2200 Tanger Blvd",
    "sg:city":"Gonzales",
    "sg:classifiers":[
        {
            "category":"Shopping",
            "type":"Retail Goods"
        }
    ],
    "sg:phone":"+1 225 647 5890",
    "sg:postcode":"70737",
    "sg:province":"LA",
    "sg:tags":[
        "factory",
        "outlet"
    ],
    "wof:name":"Factory Brand Shoes",
    "wof:placetype":"venue"
},
  "geometry": {"coordinates":[-90.95169799999999,30.214813],"type":"Point"}
}