{
  "type": "Feature",
  "properties": {
    "iso:country":"US",
    "sg:address":"236 US Hwy 171",
    "sg:city":"Lake Charles",
    "sg:classifiers":[
        {
            "category":"Retail",
            "subcategory":"Repair Shop",
            "type":"Services"
        }
    ],
    "sg:phone":"+1 337 217 3317",
    "sg:postcode":"70611",
    "sg:province":"LA",
    "sg:tags":[
        "taxidermist"
    ],
    "wof:name":"Backwoods Taxidermy",
    "wof:placetype":"venue"
},
  "geometry": {"coordinates":[-93.194897,30.306361],"type":"Point"}
}