{
  "type": "Feature",
  "properties": {
    "addr:full":"4201 Forsythe Ave Monroe LA 71201",
    "addr:housenumber":"4201",
    "addr:postcode":"71201",
    "addr:street":"Forsythe Ave",
    "iso:country":"US",
    "sg:address":"4201 Forsythe Ave",
    "sg:city":"Monroe",
    "sg:classifiers":[
        {
            "category":"Organizations",
            "subcategory":"Religious Organization",
            "type":"Services"
        }
    ],
    "sg:phone":"+1 318 325 8689",
    "sg:postcode":"71201",
    "sg:province":"LA",
    "sg:tags":[
        "church"
    ],
    "wof:name":"Messiah Lutheran Church",
    "wof:placetype":"venue"
},
  "geometry": {"coordinates":[-92.07952899999999,32.543079],"type":"Point"}
}