{
  "type": "Feature",
  "properties": {
    "iso:country":"US",
    "sg:address":"8056 State Rte 23",
    "sg:city":"Belle Chasse",
    "sg:classifiers":[
        {
            "category":"Professional",
            "subcategory":"Management & Consulting",
            "type":"Services"
        }
    ],
    "sg:phone":"+1 504 433 3851",
    "sg:postcode":"70037",
    "sg:province":"LA",
    "sg:tags":[
        "field",
        "oil",
        "consultant"
    ],
    "wof:name":"Garney Williamson Consulting",
    "wof:placetype":"venue"
},
  "geometry": {"coordinates":[-89.99141299999999,29.859558],"type":"Point"}
}