{
  "type": "Feature",
  "properties": {
    "iso:country":"US",
    "sg:address":"2113 S Bayou Dr",
    "sg:city":"Golden Meadow",
    "sg:classifiers":[
        {
            "category":"Shopping",
            "subcategory":"Music",
            "type":"Retail Goods"
        }
    ],
    "sg:phone":"+1 985 475 6644",
    "sg:postcode":"70357",
    "sg:province":"LA",
    "sg:tags":[
        "video",
        "disc",
        "tape",
        "cassette"
    ],
    "wof:name":"Debra's Movie World",
    "wof:placetype":"venue"
},
  "geometry": {"coordinates":[-90.259597,29.376289],"type":"Point"}
}