{
  "type": "Feature",
  "properties": {
    "iso:country":"US",
    "sg:address":"400 Bubby Dr",
    "sg:city":"Houma",
    "sg:classifiers":[
        {
            "category":"Freight",
            "type":"Transportation"
        }
    ],
    "sg:phone":"+1 985 851 6614",
    "sg:postcode":"70360",
    "sg:province":"LA",
    "sg:tags":[
        "operator",
        "local",
        "trucking"
    ],
    "wof:name":"Leon Veral Trucking",
    "wof:placetype":"venue"
},
  "geometry": {"coordinates":[-90.802736,29.619392],"type":"Point"}
}