{
  "type": "Feature",
  "properties": {
    "iso:country":"US",
    "sg:address":"41028 State Rte 621",
    "sg:city":"Gonzales",
    "sg:classifiers":[
        {
            "category":"Retail",
            "subcategory":"Auto Repair",
            "type":"Services"
        }
    ],
    "sg:phone":"+1 225 644 2889",
    "sg:postcode":"70737",
    "sg:province":"LA",
    "sg:tags":[
        "repairing",
        "automobile"
    ],
    "wof:name":"Professional Car Care-Gonzales",
    "wof:placetype":"venue"
},
  "geometry": {"coordinates":[-90.920481,30.269333],"type":"Point"}
}