{
  "type": "Feature",
  "properties": {
    "iso:country":"US",
    "sg:address":"9119 World Ministry Ave",
    "sg:city":"Baton Rouge",
    "sg:classifiers":[
        {
            "category":"Retail",
            "subcategory":"Repair Shop",
            "type":"Services"
        }
    ],
    "sg:phone":"+1 225 769 2011",
    "sg:postcode":"70810",
    "sg:province":"LA",
    "sg:tags":[
        "welding"
    ],
    "wof:name":"Quality Welding LLC",
    "wof:placetype":"venue"
},
  "geometry": {"coordinates":[-91.09402900000001,30.383918],"type":"Point"}
}