{
  "type": "Feature",
  "properties": {
    "addr:full":"160 Bud Walker Rd Dry Prong LA 71423",
    "addr:housenumber":"160",
    "addr:postcode":"71423",
    "addr:street":"Bud Walker Rd",
    "iso:country":"US",
    "sg:address":"160 Bud Walker Rd",
    "sg:city":"Dry Prong",
    "sg:classifiers":[
        {
            "category":"Communications",
            "subcategory":"Radio Station",
            "type":"Services"
        }
    ],
    "sg:phone":"+1 318 899 5837",
    "sg:postcode":"71423",
    "sg:province":"LA",
    "sg:tags":[
        "company",
        "broadcasting"
    ],
    "wof:name":"KVDP",
    "wof:placetype":"venue"
},
  "geometry": {"coordinates":[-92.515081,31.58773],"type":"Point"}
}