{
  "type": "Feature",
  "properties": {
    "addr:full":"231 N Columbia St Covington LA 70433",
    "addr:housenumber":"231",
    "addr:postcode":"70433",
    "addr:street":"N",
    "iso:country":"US",
    "sg:address":"231 N Columbia St",
    "sg:city":"Covington",
    "sg:classifiers":[
        {
            "category":"Shopping",
            "subcategory":"Clothing, Apparel, & Fashions",
            "type":"Retail Goods"
        }
    ],
    "sg:phone":"+1 985 871 4155",
    "sg:postcode":"70433",
    "sg:province":"LA",
    "sg:tags":[
        "t"
    ],
    "wof:name":"Ichabod's",
    "wof:placetype":"venue"
},
  "geometry": {"coordinates":[-90.094217,30.474823],"type":"Point"}
}