{
  "type": "Feature",
  "properties": {
    "addr:full":"4500 Desiard St Monroe LA 71203",
    "addr:housenumber":"4500",
    "addr:postcode":"71203",
    "addr:street":"Desiard St",
    "iso:country":"US",
    "sg:address":"4500 Desiard St",
    "sg:city":"Monroe",
    "sg:classifiers":[
        {
            "category":"Real Estate",
            "subcategory":"Real Estate Agent",
            "type":"Services"
        }
    ],
    "sg:phone":"+1 318 345 0125",
    "sg:postcode":"71203",
    "sg:province":"LA",
    "sg:tags":[
        "agency",
        "rental"
    ],
    "wof:name":"North American Land Dvlpmnt",
    "wof:placetype":"venue"
},
  "geometry": {"coordinates":[-92.065409,32.526005],"type":"Point"}
}