{
  "type": "Feature",
  "properties": {
    "addr:full":"3401 Jean Lafitte Pkwy Chalmette LA 70043",
    "addr:housenumber":"3401",
    "addr:postcode":"70043",
    "addr:street":"Jean Lafitte Pkwy Chalmette",
    "iso:country":"US",
    "sg:address":"3401 Jean Lafitte Pkwy",
    "sg:city":"Chalmette",
    "sg:classifiers":[
        {
            "category":"Health Services",
            "subcategory":"Health Practitioner",
            "type":"Services"
        }
    ],
    "sg:phone":"+1 504 279 5111",
    "sg:postcode":"70043",
    "sg:province":"LA",
    "sg:tags":[
        "therapist",
        "physical"
    ],
    "wof:name":"Metro Physical Therapy",
    "wof:placetype":"venue"
},
  "geometry": {"coordinates":[-89.978292,29.957508],"type":"Point"}
}