{
  "type": "Feature",
  "properties": {
    "iso:country":"US",
    "sg:address":"1015 Central Ave",
    "sg:city":"Metairie",
    "sg:classifiers":[
        {
            "category":"Professional",
            "subcategory":"Business Services",
            "type":"Services"
        }
    ],
    "sg:phone":"+1 504 620 1485",
    "sg:postcode":"70001",
    "sg:province":"LA",
    "wof:name":"Small Business Accounting",
    "wof:placetype":"venue"
},
  "geometry": {"coordinates":[-90.174459,29.974767],"type":"Point"}
}