{
  "type": "Feature",
  "properties": {
    "addr:full":"1173 W Airline Hwy La Place LA 70068",
    "addr:housenumber":"1173",
    "addr:postcode":"70068",
    "addr:street":"W Airline Hwy La Place",
    "iso:country":"US",
    "sg:address":"1173 W Airline Hwy",
    "sg:city":"La Place",
    "sg:classifiers":[
        {
            "category":"Food & Beverages",
            "subcategory":"Groceries & Convenience Stores",
            "type":"Retail Goods"
        }
    ],
    "sg:phone":"+1 985 652 5032",
    "sg:postcode":"70068",
    "sg:province":"LA",
    "sg:tags":[
        "grocer"
    ],
    "wof:name":"Holmes Food Mart",
    "wof:placetype":"venue"
},
  "geometry": {"coordinates":[-90.490487,30.071215],"type":"Point"}
}