{
  "type": "Feature",
  "properties": {
    "iso:country":"US",
    "sg:address":"123 Credeur Rd",
    "sg:city":"Scott",
    "sg:classifiers":[
        {
            "category":"Farming",
            "subcategory":"Livestock Farm",
            "type":"Manufacturing & Wholesale Goods"
        }
    ],
    "sg:phone":"+1 337 873 3569",
    "sg:postcode":"70583",
    "sg:province":"LA",
    "sg:tags":[
        "specialty",
        "animal"
    ],
    "wof:name":"Jacques Crocs",
    "wof:placetype":"venue"
},
  "geometry": {"coordinates":[-92.15667999999999,30.270652],"type":"Point"}
}