{
  "type": "Feature",
  "properties": {
    "addr:full":"2009 Enterprise Blvd Lake Charles LA 70601",
    "addr:housenumber":"2009",
    "addr:postcode":"70601",
    "addr:street":"Enterprise Blvd",
    "iso:country":"US",
    "sg:address":"2009 Enterprise Blvd",
    "sg:city":"Lake Charles",
    "sg:classifiers":[
        {
            "category":"Restaurant",
            "type":"Food & Drink"
        }
    ],
    "sg:phone":"+1 337 494 0062",
    "sg:postcode":"70601",
    "sg:province":"LA",
    "sg:tags":[
        "eating"
    ],
    "wof:name":"Aladdin Lebanese Restaurant",
    "wof:placetype":"venue"
},
  "geometry": {"coordinates":[-93.204234,30.212944],"type":"Point"}
}