{
  "type": "Feature",
  "properties": {
    "iso:country":"US",
    "sg:address":"1123 Garrett Rd",
    "sg:city":"Monroe",
    "sg:classifiers":[
        {
            "category":"Food & Beverages",
            "subcategory":"Groceries & Convenience Stores",
            "type":"Retail Goods"
        }
    ],
    "sg:phone":"+1 318 343 9241",
    "sg:postcode":"71203",
    "sg:province":"LA",
    "wof:name":"Moore Oil 9",
    "wof:placetype":"venue"
},
  "geometry": {"coordinates":[-92.054355,32.499024],"type":"Point"}
}