{
  "type": "Feature",
  "properties": {
    "iso:country":"US",
    "sg:address":"11429 Ferdinand St",
    "sg:city":"St Francisville",
    "sg:classifiers":[
        {
            "category":"Restaurant",
            "type":"Food & Drink"
        }
    ],
    "sg:phone":"+1 225 784 0161",
    "sg:postcode":"70775",
    "sg:province":"LA",
    "wof:name":"Que Pasa Inc",
    "wof:placetype":"venue"
},
  "geometry": {"coordinates":[-91.388975,30.774563],"type":"Point"}
}