{
  "type": "Feature",
  "properties": {
    "iso:country":"US",
    "sg:address":"200 Hudson Ln",
    "sg:city":"Monroe",
    "sg:classifiers":[
        {
            "category":"Personal",
            "subcategory":"Beauty Salon",
            "type":"Services"
        }
    ],
    "sg:phone":"+1 318 387 3600",
    "sg:postcode":"71201",
    "sg:province":"LA",
    "wof:name":"Danny's Hair Studio",
    "wof:placetype":"venue"
},
  "geometry": {"coordinates":[-92.12165,32.51003],"type":"Point"}
}