{
  "type": "Feature",
  "properties": {
    "iso:country":"US",
    "sg:address":"413 S Main St",
    "sg:city":"Springhill",
    "sg:classifiers":[
        {
            "category":"Autos & Motor Vehicles",
            "subcategory":"Auto Supplies",
            "type":"Retail Goods"
        }
    ],
    "sg:phone":"+1 318 539 5483",
    "sg:postcode":"71075",
    "sg:province":"LA",
    "sg:tags":[
        "tire"
    ],
    "wof:name":"Keith's 66 & Tire Center",
    "wof:placetype":"venue"
},
  "geometry": {"coordinates":[-93.461127,32.998036],"type":"Point"}
}