{
  "type": "Feature",
  "properties": {
    "iso:country":"US",
    "sg:address":"3101 Old Sterlington Rd",
    "sg:city":"Monroe",
    "sg:classifiers":[
        {
            "category":"Building & Trades",
            "subcategory":"Electrical",
            "type":"Services"
        }
    ],
    "sg:phone":"+1 318 343 8454",
    "sg:postcode":"71203",
    "sg:province":"LA",
    "sg:tags":[
        "booth",
        "equipment",
        "telephone",
        "pay"
    ],
    "wof:name":"Phone Booth",
    "wof:placetype":"venue"
},
  "geometry": {"coordinates":[-92.064453,32.553719],"type":"Point"}
}