{
  "type": "Feature",
  "properties": {
    "addr:full":"645 Codifer St Slidell LA 70458",
    "addr:housenumber":"645",
    "addr:postcode":"70458",
    "addr:street":"Codifer St",
    "iso:country":"US",
    "sg:address":"645 Codifer St",
    "sg:city":"Slidell",
    "sg:classifiers":[
        {
            "category":"Utilities",
            "type":"Services"
        }
    ],
    "sg:phone":"+1 985 781 0804",
    "sg:postcode":"70458",
    "sg:province":"LA",
    "sg:tags":[
        "oil",
        "up",
        "clean",
        "spill"
    ],
    "wof:name":"O'Brien's Oil Pollution SVCS",
    "wof:placetype":"venue"
},
  "geometry": {"coordinates":[-89.78206900000001,30.264307],"type":"Point"}
}