{
  "type": "Feature",
  "properties": {
    "iso:country":"US",
    "sg:address":"4124 E Jevon Ln",
    "sg:city":"Lake Charles",
    "sg:classifiers":[
        {
            "category":"Education",
            "subcategory":"Special Training",
            "type":"Public Place"
        }
    ],
    "sg:phone":"+1 337 474 3474",
    "sg:postcode":"70605",
    "sg:province":"LA",
    "wof:name":"Meeraj Inc",
    "wof:placetype":"venue"
},
  "geometry": {"coordinates":[-93.24222899999999,30.183034],"type":"Point"}
}