{
  "type": "Feature",
  "properties": {
    "iso:country":"US",
    "sg:address":"9707 Exxon Rd",
    "sg:city":"Abbeville",
    "sg:classifiers":[
        {
            "category":"Mining & Drilling",
            "type":"Manufacturing & Wholesale Goods"
        }
    ],
    "sg:phone":"+1 337 893 0429",
    "sg:postcode":"70510",
    "sg:province":"LA",
    "sg:tags":[
        "field",
        "oil"
    ],
    "wof:name":"Intracoastal Liquid Mud Inc",
    "wof:placetype":"venue"
},
  "geometry": {"coordinates":[-92.137773,29.826228],"type":"Point"}
}