{
  "type": "Feature",
  "properties": {
    "addr:full":"2324 Severn Ave Metairie LA 70001",
    "addr:housenumber":"2324",
    "addr:postcode":"70001",
    "addr:street":"Severn Ave",
    "iso:country":"US",
    "sg:address":"2324 Severn Ave",
    "sg:city":"Metairie",
    "sg:classifiers":[
        {
            "category":"Professional",
            "subcategory":"Management & Consulting",
            "type":"Services"
        }
    ],
    "sg:phone":"+1 504 834 0151",
    "sg:postcode":"70001",
    "sg:province":"LA",
    "sg:tags":[
        "construction"
    ],
    "wof:name":"2nd Opinion Inc",
    "wof:placetype":"venue"
},
  "geometry": {"coordinates":[-90.15996800000001,29.994541],"type":"Point"}
}