{
  "type": "Feature",
  "properties": {
    "addr:full":"430 Memorial Dr Donaldsonville LA 70346",
    "addr:housenumber":"430",
    "addr:postcode":"70346",
    "addr:street":"Memorial Dr",
    "iso:country":"US",
    "sg:address":"430 Memorial Dr",
    "sg:city":"Donaldsonville",
    "sg:classifiers":[
        {
            "category":"Organizations",
            "subcategory":"Religious Organization",
            "type":"Services"
        }
    ],
    "sg:phone":"+1 225 473 3787",
    "sg:postcode":"70346",
    "sg:province":"LA",
    "sg:tags":[
        "church"
    ],
    "wof:name":"Counsel Of God Ministries",
    "wof:placetype":"venue"
},
  "geometry": {"coordinates":[-91.002771,30.087414],"type":"Point"}
}