{
  "type": "Feature",
  "properties": {
    "iso:country":"US",
    "sg:address":"2400 Tiger Dr",
    "sg:city":"Morgan City",
    "sg:classifiers":[
        {
            "category":"Education",
            "subcategory":"School",
            "type":"Public Place"
        }
    ],
    "sg:phone":"+1 985 384 1754",
    "sg:postcode":"70380",
    "sg:province":"LA",
    "sg:tags":[
        "high",
        "senior"
    ],
    "wof:name":"Morgan City Senior High School",
    "wof:placetype":"venue"
},
  "geometry": {"coordinates":[-91.20537,29.71754],"type":"Point"}
}