{
  "type": "Feature",
  "properties": {
    "addr:full":"6641 S Meadow Lark Dr Lake Charles LA 70607",
    "addr:housenumber":"6641",
    "addr:postcode":"70607",
    "addr:street":"S Meadow Lark Dr",
    "iso:country":"US",
    "sg:address":"6641 S Meadow Lark Dr",
    "sg:city":"Lake Charles",
    "sg:classifiers":[
        {
            "category":"Home & Garden",
            "subcategory":"Furniture",
            "type":"Retail Goods"
        }
    ],
    "sg:phone":"+1 337 477 1515",
    "sg:postcode":"70607",
    "sg:province":"LA",
    "wof:name":"Palm Huts & More",
    "wof:placetype":"venue"
},
  "geometry": {"coordinates":[-93.161813,30.142175],"type":"Point"}
}