{
  "type": "Feature",
  "properties": {
    "iso:country":"US",
    "sg:address":"800 Navarre Ave",
    "sg:city":"New Orleans",
    "sg:classifiers":[
        {
            "category":"Restaurant",
            "type":"Food & Drink"
        }
    ],
    "sg:phone":"+1 504 488 9267",
    "sg:postcode":"70124",
    "sg:province":"LA",
    "sg:tags":[
        "sandwich"
    ],
    "wof:name":"Weaver's Po Boy Sandwiches",
    "wof:placetype":"venue"
},
  "geometry": {"coordinates":[-90.10684999999999,29.989589],"type":"Point"}
}