{
  "type": "Feature",
  "properties": {
    "iso:country":"US",
    "sg:address":"6737 Corbina Rd",
    "sg:city":"Lake Charles",
    "sg:classifiers":[
        {
            "category":"Organizations",
            "subcategory":"Religious Organization",
            "type":"Services"
        }
    ],
    "sg:phone":"+1 337 474 3758",
    "sg:postcode":"70607",
    "sg:province":"LA",
    "sg:tags":[
        "church"
    ],
    "wof:name":"Faith Bible Church",
    "wof:placetype":"venue"
},
  "geometry": {"coordinates":[-93.162724,30.140863],"type":"Point"}
}