{
  "type": "Feature",
  "properties": {
    "iso:country":"US",
    "sg:address":"1800 Corbin Rd",
    "sg:city":"Hammond",
    "sg:classifiers":[
        {
            "category":"Organizations",
            "subcategory":"Religious Organization",
            "type":"Services"
        }
    ],
    "sg:phone":"+1 985 345 7123",
    "sg:postcode":"70403",
    "sg:province":"LA",
    "sg:tags":[
        "church"
    ],
    "wof:name":"Pear Ridge Church-Christ",
    "wof:placetype":"venue"
},
  "geometry": {"coordinates":[-90.48051,30.49734],"type":"Point"}
}