{
  "type": "Feature",
  "properties": {
    "iso:country":"US",
    "sg:address":"2216 N 39th St",
    "sg:city":"Baton Rouge",
    "sg:classifiers":[
        {
            "category":"Building & Trades",
            "subcategory":"Landscaping Services",
            "type":"Services"
        }
    ],
    "sg:phone":"+1 225 356 1487",
    "sg:postcode":"70802",
    "sg:province":"LA",
    "wof:name":"Green Glove Lawn Maintenance",
    "wof:placetype":"venue"
},
  "geometry": {"coordinates":[-91.151336,30.467875],"type":"Point"}
}