{
  "type": "Feature",
  "properties": {
    "iso:country":"US",
    "sg:address":"141 Hwy 22 E",
    "sg:city":"Madisonville",
    "sg:classifiers":[
        {
            "category":"Wholesale",
            "subcategory":"Apparel",
            "type":"Manufacturing & Wholesale Goods"
        }
    ],
    "sg:phone":"+1 985 845 2709",
    "sg:postcode":"70447",
    "sg:province":"LA",
    "sg:tags":[
        "footwear"
    ],
    "wof:name":"Jimmy Cole LLC",
    "wof:placetype":"venue"
},
  "geometry": {"coordinates":[-90.151763,30.404324],"type":"Point"}
}