{
  "type": "Feature",
  "properties": {
    "iso:country":"US",
    "sg:address":"320 W Thomas St",
    "sg:city":"Hammond",
    "sg:classifiers":[
        {
            "category":"Real Estate",
            "subcategory":"Real Estate Agent",
            "type":"Services"
        }
    ],
    "sg:phone":"+1 985 542 6886",
    "sg:postcode":"70401",
    "sg:province":"LA",
    "sg:tags":[
        "agency",
        "rental"
    ],
    "wof:name":"Superior Rent To Own",
    "wof:placetype":"venue"
},
  "geometry": {"coordinates":[-90.46370400000001,30.503559],"type":"Point"}
}