{
  "type": "Feature",
  "properties": {
    "addr:full":"2500 S Prieur St New Orleans LA 70125",
    "addr:housenumber":"2500",
    "addr:postcode":"70125",
    "addr:street":"S Prieur St",
    "iso:country":"US",
    "sg:address":"2500 S Prieur St",
    "sg:city":"New Orleans",
    "sg:classifiers":[
        {
            "category":"Food & Beverages",
            "subcategory":"Groceries & Convenience Stores",
            "type":"Retail Goods"
        }
    ],
    "sg:phone":"+1 504 821 4768",
    "sg:postcode":"70125",
    "sg:province":"LA",
    "wof:name":"G & G Grocery",
    "wof:placetype":"venue"
},
  "geometry": {"coordinates":[-90.094742,29.945876],"type":"Point"}
}