{
  "type": "Feature",
  "properties": {
    "iso:country":"US",
    "sg:address":"47119 Tantillo Ln",
    "sg:city":"Hammond",
    "sg:classifiers":[
        {
            "category":"Building & Trades",
            "subcategory":"Cleaning & Sanitation",
            "type":"Services"
        }
    ],
    "sg:phone":"+1 985 542 9525",
    "sg:postcode":"70401",
    "sg:province":"LA",
    "sg:tags":[
        "maintenance"
    ],
    "wof:name":"Joanne Laprimes Cleaning",
    "wof:placetype":"venue"
},
  "geometry": {"coordinates":[-90.49897799999999,30.535795],"type":"Point"}
}