{
  "type": "Feature",
  "properties": {
    "iso:country":"US",
    "sg:address":"1850 Lapalco Blvd",
    "sg:city":"Harvey",
    "sg:classifiers":[
        {
            "category":"Freight",
            "type":"Transportation"
        }
    ],
    "sg:phone":"+1 504 227 2470",
    "sg:postcode":"70058",
    "sg:province":"LA",
    "sg:tags":[
        "warehouse",
        "mini"
    ],
    "wof:name":"Manhattan Mini Storage",
    "wof:placetype":"venue"
},
  "geometry": {"coordinates":[-90.05197800000001,29.874072],"type":"Point"}
}