{
  "type": "Feature",
  "properties": {
    "iso:country":"US",
    "sg:address":"3230 Barksdale Blvd",
    "sg:city":"Bossier City",
    "sg:classifiers":[
        {
            "category":"Food & Beverages",
            "subcategory":"Bakery",
            "type":"Retail Goods"
        }
    ],
    "sg:phone":"+1 318 741 1003",
    "sg:postcode":"71112",
    "sg:province":"LA",
    "sg:tags":[
        "doughnut"
    ],
    "wof:name":"Southern Maid Donut Shop",
    "wof:placetype":"venue"
},
  "geometry": {"coordinates":[-93.684455,32.488964],"type":"Point"}
}