{
  "type": "Feature",
  "properties": {
    "iso:country":"US",
    "sg:address":"372 Colonial Club Dr",
    "sg:city":"New Orleans",
    "sg:classifiers":[
        {
            "category":"Health Services",
            "subcategory":"Health Practitioner",
            "type":"Services"
        }
    ],
    "sg:phone":"+1 504 738 7819",
    "sg:postcode":"70123",
    "sg:province":"LA",
    "wof:name":"Habilitation Therapy Rpt",
    "wof:placetype":"venue"
},
  "geometry": {"coordinates":[-90.2056,29.939186],"type":"Point"}
}