{
  "type": "Feature",
  "properties": {
    "addr:full":"5830 Willow St New Orleans LA 70115",
    "addr:housenumber":"5830",
    "addr:postcode":"70115",
    "addr:street":"Willow St",
    "iso:country":"US",
    "sg:address":"5830 Willow St",
    "sg:city":"New Orleans",
    "sg:classifiers":[
        {
            "category":"Professional",
            "subcategory":"Accounting & Tax Preparation",
            "type":"Services"
        }
    ],
    "sg:phone":"+1 504 866 5621",
    "sg:postcode":"70115",
    "sg:province":"LA",
    "sg:tags":[
        "accountant"
    ],
    "wof:name":"J V Leclere Krentel",
    "wof:placetype":"venue"
},
  "geometry": {"coordinates":[-90.11454000000001,29.939723],"type":"Point"}
}