{
  "type": "Feature",
  "properties": {
    "addr:full":"916 Hwy 20 Thibodaux LA 70301",
    "addr:housenumber":"916",
    "addr:postcode":"70301",
    "addr:street":"Hwy 20",
    "iso:country":"US",
    "sg:address":"916 Hwy 20",
    "sg:city":"Thibodaux",
    "sg:classifiers":[
        {
            "category":"Building & Trades",
            "subcategory":"Construction",
            "type":"Services"
        }
    ],
    "sg:phone":"+1 985 633 5134",
    "sg:postcode":"70301",
    "sg:province":"LA",
    "sg:tags":[
        "contractor"
    ],
    "wof:name":"Red Express Construction LLC",
    "wof:placetype":"venue"
},
  "geometry": {"coordinates":[-90.77481,29.902915],"type":"Point"}
}