{
  "type": "Feature",
  "properties": {
    "iso:country":"US",
    "sg:address":"4400 Ambassador Caffery Pkwy",
    "sg:city":"Lafayette",
    "sg:classifiers":[
        {
            "category":"Restaurant",
            "type":"Food & Drink"
        }
    ],
    "sg:menulink":"http://www.allmenus.com/la/broadmoor/228720-juliens-po-boys-cajun-style/menu/",
    "sg:phone":"+1 337 981 8162",
    "sg:postcode":"70508",
    "sg:province":"LA",
    "sg:tags":[
        "american",
        "creole",
        "cajun"
    ],
    "wof:name":"Julien's Po-boys Cajun Style",
    "wof:placetype":"venue"
},
  "geometry": {"coordinates":[-92.050802,30.158473],"type":"Point"}
}