{
  "type": "Feature",
  "properties": {
    "iso:country":"US",
    "sg:address":"19504 Hwy 440",
    "sg:city":"Kentwood",
    "sg:classifiers":[
        {
            "category":"Retail",
            "subcategory":"Auto Repair",
            "type":"Services"
        }
    ],
    "sg:phone":"+1 985 229 5309",
    "sg:postcode":"70444",
    "sg:province":"LA",
    "sg:tags":[
        "body"
    ],
    "wof:name":"Tates Paint Body Shop",
    "wof:placetype":"venue"
},
  "geometry": {"coordinates":[-90.3997,30.869001],"type":"Point"}
}