{
  "type": "Feature",
  "properties": {
    "iso:country":"US",
    "sg:address":"4535 Choctaw Dr",
    "sg:city":"Baton Rouge",
    "sg:classifiers":[
        {
            "category":"Wholesale",
            "subcategory":"Hardware",
            "type":"Manufacturing & Wholesale Goods"
        }
    ],
    "sg:phone":"+1 225 356 0158",
    "sg:postcode":"70805",
    "sg:province":"LA",
    "sg:tags":[
        "nut",
        "bolt"
    ],
    "sg:website":"www.indscrew.com",
    "wof:name":"Industrial Screw & Supply Co",
    "wof:placetype":"venue"
},
  "geometry": {"coordinates":[-91.140258,30.470648],"type":"Point"}
}