{
  "type": "Feature",
  "properties": {
    "iso:country":"US",
    "sg:address":"329 Oak Tree Rd",
    "sg:city":"Belle Chasse",
    "sg:classifiers":[
        {
            "category":"Building & Trades",
            "subcategory":"Construction",
            "type":"Services"
        }
    ],
    "sg:phone":"+1 504 391 9091",
    "sg:postcode":"70037",
    "sg:province":"LA",
    "sg:tags":[
        "hanging",
        "contractor"
    ],
    "wof:name":"Boyer Painting",
    "wof:placetype":"venue"
},
  "geometry": {"coordinates":[-89.99363700000001,29.850162],"type":"Point"}
}