{
  "type": "Feature",
  "properties": {
    "iso:country":"US",
    "sg:address":"128 Demanade Blvd",
    "sg:city":"Lafayette",
    "sg:classifiers":[
        {
            "category":"Banks & Credit Unions",
            "subcategory":"Bank",
            "type":"Services"
        }
    ],
    "sg:phone":"+1 337 234 1711",
    "sg:postcode":"70503",
    "sg:province":"LA",
    "sg:tags":[
        "loan",
        "real estate"
    ],
    "wof:name":"Mynex Investments Inc",
    "wof:placetype":"venue"
},
  "geometry": {"coordinates":[-92.012624,30.202933],"type":"Point"}
}