{
  "type": "Feature",
  "properties": {
    "addr:full":"11396 Spellman Rd Geismar LA 70734",
    "addr:housenumber":"11396",
    "addr:postcode":"70734",
    "addr:street":"Spellman Rd",
    "iso:country":"US",
    "sg:address":"11396 Spellman Rd",
    "sg:city":"Geismar",
    "sg:classifiers":[
        {
            "category":"Professional",
            "subcategory":"Business Services",
            "type":"Services"
        }
    ],
    "sg:phone":"+1 225 673 5499",
    "sg:postcode":"70734",
    "sg:province":"LA",
    "wof:name":"Thompson Enterprises",
    "wof:placetype":"venue"
},
  "geometry": {"coordinates":[-90.98969700000001,30.230993],"type":"Point"}
}