{
  "type": "Feature",
  "properties": {
    "addr:full":"14759 Denham Rd Pride LA 70770",
    "addr:postcode":"14759;70770",
    "addr:street":"Denham Rd",
    "iso:country":"US",
    "sg:address":"14759 Denham Rd",
    "sg:city":"Pride",
    "sg:classifiers":[
        {
            "category":"Organizations",
            "subcategory":"Religious Organization",
            "type":"Services"
        }
    ],
    "sg:phone":"+1 225 261 8233",
    "sg:postcode":"70770",
    "sg:province":"LA",
    "sg:tags":[
        "church"
    ],
    "wof:name":"Community Christian Ctr",
    "wof:placetype":"venue"
},
  "geometry": {"coordinates":[-91.023512,30.587969],"type":"Point"}
}