{
  "type": "Feature",
  "properties": {
    "iso:country":"US",
    "sg:address":"4800 Dawn St",
    "sg:city":"Alexandria",
    "sg:classifiers":[
        {
            "category":"Education",
            "subcategory":"School",
            "type":"Public Place"
        }
    ],
    "sg:phone":"+1 318 443 3688",
    "sg:postcode":"71301",
    "sg:province":"LA",
    "wof:name":"S M Brame Jr High School",
    "wof:placetype":"venue"
},
  "geometry": {"coordinates":[-92.47378999999999,31.27218],"type":"Point"}
}