{
  "type": "Feature",
  "properties": {
    "iso:country":"US",
    "sg:address":"202 Longwood Dr",
    "sg:city":"Thibodaux",
    "sg:classifiers":[
        {
            "category":"Building & Trades",
            "subcategory":"Equipment Rental",
            "type":"Services"
        }
    ],
    "sg:phone":"+1 985 446 3297",
    "sg:postcode":"70301",
    "sg:province":"LA",
    "sg:tags":[
        "yard"
    ],
    "wof:name":"Welcome To My Party",
    "wof:placetype":"venue"
},
  "geometry": {"coordinates":[-90.813883,29.801525],"type":"Point"}
}