{
  "type": "Feature",
  "properties": {
    "addr:full":"625 Main St Logansport LA 71049",
    "addr:housenumber":"625",
    "addr:postcode":"71049",
    "addr:street":"Main St",
    "iso:country":"US",
    "sg:address":"625 Main St",
    "sg:city":"Logansport",
    "sg:classifiers":[
        {
            "category":"Shopping",
            "subcategory":"Department Store",
            "type":"Retail Goods"
        }
    ],
    "sg:phone":"+1 318 697 5958",
    "sg:postcode":"71049",
    "sg:province":"LA",
    "sg:tags":[
        "shop"
    ],
    "wof:name":"Family Dollar Store",
    "wof:placetype":"venue"
},
  "geometry": {"coordinates":[-93.99995800000001,31.974756],"type":"Point"}
}