{
  "type": "Feature",
  "properties": {
    "iso:country":"US",
    "sg:address":"2037 Darlington Ct",
    "sg:city":"Shreveport",
    "sg:classifiers":[
        {
            "category":"Manufacturing",
            "subcategory":"Apparel",
            "type":"Manufacturing & Wholesale Goods"
        }
    ],
    "sg:phone":"+1 318 688 1051",
    "sg:postcode":"71118",
    "sg:province":"LA",
    "sg:tags":[
        "mfg"
    ],
    "wof:name":"Wanda Knapp ACC & Gifts",
    "wof:placetype":"venue"
},
  "geometry": {"coordinates":[-93.791399,32.384261],"type":"Point"}
}