{
  "type": "Feature",
  "properties": {
    "iso:country":"US",
    "sg:address":"9113 Bellegrove Pl",
    "sg:city":"New Orleans",
    "sg:classifiers":[
        {
            "category":"Professional",
            "subcategory":"Lawyer & Legal Services",
            "type":"Services"
        }
    ],
    "sg:phone":"+1 504 737 4868",
    "sg:postcode":"70123",
    "sg:province":"LA",
    "sg:tags":[
        "attorney"
    ],
    "wof:name":"Carol K Accardo",
    "wof:placetype":"venue"
},
  "geometry": {"coordinates":[-90.207104,29.956645],"type":"Point"}
}