{
  "type": "Feature",
  "properties": {
    "iso:country":"US",
    "sg:address":"888 Tara Blvd",
    "sg:city":"Baton Rouge",
    "sg:classifiers":[
        {
            "category":"Health Services",
            "subcategory":"Doctor",
            "type":"Services"
        }
    ],
    "sg:phone":"+1 225 926 4400",
    "sg:postcode":"70806",
    "sg:province":"LA",
    "sg:tags":[
        "physician",
        "surgeon"
    ],
    "wof:name":"Pediatric Clinic",
    "wof:placetype":"venue"
},
  "geometry": {"coordinates":[-91.095972,30.441766],"type":"Point"}
}