{
  "type": "Feature",
  "properties": {
    "addr:full":"4648 S I- 10 Svc Rd W Metairie LA 70001",
    "addr:housenumber":"4648;10",
    "addr:postcode":"70001",
    "addr:street":"S I;Svc Rd W",
    "iso:country":"US",
    "sg:address":"4648 S I- 10 Svc Rd W",
    "sg:city":"Metairie",
    "sg:classifiers":[
        {
            "category":"Health Services",
            "subcategory":"Medical Lab",
            "type":"Services"
        }
    ],
    "sg:phone":"+1 504 889 2307",
    "sg:postcode":"70001",
    "sg:province":"LA",
    "sg:tags":[
        "laboratory"
    ],
    "sg:website":"www.questdiagnostics.com",
    "wof:name":"Quest Diagnostics Inc",
    "wof:placetype":"venue"
},
  "geometry": {"coordinates":[-90.182855,29.996476],"type":"Point"}
}