{
  "type": "Feature",
  "properties": {
    "addr:full":"8020 Downman Rd New Orleans LA 70126",
    "addr:housenumber":"8020",
    "addr:postcode":"70126",
    "addr:street":"Downman Rd",
    "iso:country":"US",
    "sg:address":"8020 Downman Rd",
    "sg:city":"New Orleans",
    "sg:classifiers":[
        {
            "category":"Food & Beverages",
            "subcategory":"Groceries & Convenience Stores",
            "type":"Retail Goods"
        }
    ],
    "sg:phone":"+1 504 241 3365",
    "sg:postcode":"70126",
    "sg:province":"LA",
    "wof:name":"Speed Racer",
    "wof:placetype":"venue"
},
  "geometry": {"coordinates":[-90.026799,30.032365],"type":"Point"}
}