{
  "type": "Feature",
  "properties": {
    "iso:country":"US",
    "sg:address":"603 Harrington St",
    "sg:city":"Jennings",
    "sg:classifiers":[
        {
            "category":"Building & Trades",
            "subcategory":"Construction",
            "type":"Services"
        }
    ],
    "sg:phone":"+1 337 824 3943",
    "sg:postcode":"70546",
    "sg:province":"LA",
    "sg:tags":[
        "house"
    ],
    "wof:name":"Richard Lynn Construction",
    "wof:placetype":"venue"
},
  "geometry": {"coordinates":[-92.649773,30.217577],"type":"Point"}
}