{
  "type": "Feature",
  "properties": {
    "iso:country":"US",
    "sg:address":"3514 Hamilton St",
    "sg:city":"New Orleans",
    "sg:classifiers":[
        {
            "category":"Building & Trades",
            "subcategory":"Construction",
            "type":"Services"
        }
    ],
    "sg:phone":"+1 504 488 0369",
    "sg:postcode":"70118",
    "sg:province":"LA",
    "sg:tags":[
        "house"
    ],
    "wof:name":"Thaddeaus Griffin Contractor",
    "wof:placetype":"venue"
},
  "geometry": {"coordinates":[-90.11978999999999,29.971178],"type":"Point"}
}