{
  "type": "Feature",
  "properties": {
    "addr:full":"3939 Gentilly Blvd New Orleans LA 70126",
    "addr:housenumber":"3939",
    "addr:postcode":"70126",
    "addr:street":"Gentilly Blvd",
    "iso:country":"US",
    "sg:address":"3939 Gentilly Blvd",
    "sg:city":"New Orleans",
    "sg:classifiers":[
        {
            "category":"Communications",
            "subcategory":"Radio Station",
            "type":"Services"
        }
    ],
    "sg:phone":"+1 504 816 8000",
    "sg:postcode":"70126",
    "sg:province":"LA",
    "wof:name":"Wbsn Fm Radio Station",
    "wof:placetype":"venue"
},
  "geometry": {"coordinates":[-90.0438,30.0026],"type":"Point"}
}