{
  "type": "Feature",
  "properties": {
    "iso:country":"US",
    "sg:address":"10503 N Oak Hills Pkwy",
    "sg:city":"Baton Rouge",
    "sg:classifiers":[
        {
            "category":"Government",
            "subcategory":"Office",
            "type":"Public Place"
        }
    ],
    "sg:phone":"+1 225 757 8905",
    "sg:postcode":"70810",
    "sg:province":"LA",
    "wof:name":"Bluebonnett Swamp Nature Ctr",
    "wof:placetype":"venue"
},
  "geometry": {"coordinates":[-91.10274200000001,30.369748],"type":"Point"}
}