{
  "type": "Feature",
  "properties": {
    "iso:country":"US",
    "sg:address":"6220 Hollyfield Dr",
    "sg:city":"Baton Rouge",
    "sg:classifiers":[
        {
            "category":"Retail",
            "subcategory":"Repair Shop",
            "type":"Services"
        }
    ],
    "sg:phone":"+1 225 751 6912",
    "sg:postcode":"70809",
    "sg:province":"LA",
    "sg:tags":[
        "equipment",
        "conditioning",
        "air"
    ],
    "wof:name":"Eagle Refrigeration & Mech LLC",
    "wof:placetype":"venue"
},
  "geometry": {"coordinates":[-91.05319299999999,30.389423],"type":"Point"}
}