{
  "type": "Feature",
  "properties": {
    "addr:full":"8225 Summa Ave Baton Rouge LA 70809",
    "addr:postcode":"8225;70809",
    "addr:street":"Summa Ave",
    "iso:country":"US",
    "sg:address":"8225 Summa Ave",
    "sg:city":"Baton Rouge",
    "sg:classifiers":[
        {
            "category":"Health Services",
            "subcategory":"Nursing And Care Facility",
            "type":"Services"
        }
    ],
    "sg:phone":"+1 225 766 0130",
    "sg:postcode":"70809",
    "sg:province":"LA",
    "sg:tags":[
        "home",
        "convalescent"
    ],
    "wof:name":"Lakewood Quarters Rehab Hosp",
    "wof:placetype":"venue"
},
  "geometry": {"coordinates":[-91.100235,30.398928],"type":"Point"}
}