{
  "type": "Feature",
  "properties": {
    "iso:country":"US",
    "sg:address":"112 Old Oak Dr",
    "sg:city":"Montegut",
    "sg:classifiers":[
        {
            "category":"Personal",
            "subcategory":"Beauty Salon",
            "type":"Services"
        }
    ],
    "sg:phone":"+1 985 594 6210",
    "sg:postcode":"70377",
    "sg:province":"LA",
    "wof:name":"Look Beauty Salon",
    "wof:placetype":"venue"
},
  "geometry": {"coordinates":[-90.55625000000001,29.472534],"type":"Point"}
}