{
  "type": "Feature",
  "properties": {
    "iso:country":"US",
    "sg:address":"551 S Van Ave",
    "sg:city":"Houma",
    "sg:classifiers":[
        {
            "category":"Food & Beverages",
            "subcategory":"Groceries & Convenience Stores",
            "type":"Retail Goods"
        }
    ],
    "sg:phone":"+1 985 580 3339",
    "sg:postcode":"70363",
    "sg:province":"LA",
    "wof:name":"Gaubert Oil Co",
    "wof:placetype":"venue"
},
  "geometry": {"coordinates":[-90.709969,29.578442],"type":"Point"}
}