{
  "type": "Feature",
  "properties": {
    "addr:full":"2112 Pratt St Gretna LA 70053",
    "addr:housenumber":"2112",
    "addr:postcode":"70053",
    "addr:street":"Pratt St",
    "iso:country":"US",
    "sg:address":"2112 Pratt St",
    "sg:city":"Gretna",
    "sg:classifiers":[
        {
            "category":"Restaurant",
            "type":"Food & Drink"
        }
    ],
    "sg:phone":"+1 504 362 9870",
    "sg:postcode":"70053",
    "sg:province":"LA",
    "wof:name":"LA Pointe Restaurante Inc",
    "wof:placetype":"venue"
},
  "geometry": {"coordinates":[-90.044659,29.916985],"type":"Point"}
}