{
  "type": "Feature",
  "properties": {
    "addr:full":"130 Ellis Rd Deridder LA 70634",
    "addr:housenumber":"130",
    "addr:postcode":"70634",
    "addr:street":"Ellis Rd",
    "iso:country":"US",
    "sg:address":"130 Ellis Rd",
    "sg:city":"Deridder",
    "sg:classifiers":[
        {
            "category":"Social Services",
            "subcategory":"Child Care",
            "type":"Services"
        }
    ],
    "sg:phone":"+1 337 463 7478",
    "sg:postcode":"70634",
    "sg:province":"LA",
    "wof:name":"Mother Goose Day Care",
    "wof:placetype":"venue"
},
  "geometry": {"coordinates":[-93.309876,30.850331],"type":"Point"}
}