{
  "type": "Feature",
  "properties": {
    "addr:full":"530 Helios Ave Metairie LA 70005",
    "addr:housenumber":"530",
    "addr:postcode":"70005",
    "addr:street":"Helios Ave",
    "iso:country":"US",
    "sg:address":"530 Helios Ave",
    "sg:city":"Metairie",
    "sg:classifiers":[
        {
            "category":"Retail",
            "subcategory":"Portrait Studio",
            "type":"Services"
        }
    ],
    "sg:phone":"+1 504 831 0450",
    "sg:postcode":"70005",
    "sg:province":"LA",
    "sg:tags":[
        "photographer"
    ],
    "wof:name":"Louisiana Children's Studio",
    "wof:placetype":"venue"
},
  "geometry": {"coordinates":[-90.144397,29.995687],"type":"Point"}
}