{
  "type": "Feature",
  "properties": {
    "addr:full":"3203 3rd St Alexandria LA 71302",
    "addr:housenumber":"3203",
    "addr:postcode":"71302",
    "addr:street":"3Rd St",
    "iso:country":"US",
    "sg:address":"3203 3rd St",
    "sg:city":"Alexandria",
    "sg:classifiers":[
        {
            "category":"Food & Beverages",
            "subcategory":"Groceries & Convenience Stores",
            "type":"Retail Goods"
        }
    ],
    "sg:phone":"+1 318 442 5995",
    "sg:postcode":"71302",
    "sg:province":"LA",
    "wof:name":"Rnb Foods",
    "wof:placetype":"venue"
},
  "geometry": {"coordinates":[-92.42576699999999,31.297327],"type":"Point"}
}