{
  "type": "Feature",
  "properties": {
    "iso:country":"US",
    "sg:address":"5412 Joor Rd",
    "sg:city":"Baton Rouge",
    "sg:classifiers":[
        {
            "category":"Social Services",
            "subcategory":"Child Care",
            "type":"Services"
        }
    ],
    "sg:phone":"+1 225 926 5558",
    "sg:postcode":"70811",
    "sg:province":"LA",
    "sg:tags":[
        "day"
    ],
    "wof:name":"Country Kids DC & Lrng Ctr",
    "wof:placetype":"venue"
},
  "geometry": {"coordinates":[-91.087486,30.501261],"type":"Point"}
}