{
  "type": "Feature",
  "properties": {
    "addr:full":"554 State Rte 178 Church Point LA 70525",
    "addr:housenumber":"554",
    "addr:postcode":"70525",
    "addr:street":"State Rte 178",
    "iso:country":"US",
    "sg:address":"554 State Rte 178",
    "sg:city":"Church Point",
    "sg:classifiers":[
        {
            "category":"Building & Trades",
            "subcategory":"Plumbing",
            "type":"Services"
        }
    ],
    "sg:phone":"+1 337 684 2628",
    "sg:postcode":"70525",
    "sg:province":"LA",
    "sg:tags":[
        "conditioning",
        "air",
        "system",
        "contractor"
    ],
    "wof:name":"Pat's Air Conditioning & Htg",
    "wof:placetype":"venue"
},
  "geometry": {"coordinates":[-92.214316,30.407353],"type":"Point"}
}