{
  "type": "Feature",
  "properties": {
    "addr:full":"804 E Cornerview St Gonzales LA 70737",
    "addr:housenumber":"804",
    "addr:postcode":"70737",
    "addr:street":"E Cornerview St",
    "iso:country":"US",
    "sg:address":"804 E Cornerview St",
    "sg:city":"Gonzales",
    "sg:classifiers":[
        {
            "category":"Professional",
            "subcategory":"Lawyer & Legal Services",
            "type":"Services"
        }
    ],
    "sg:phone":"+1 225 647 4441",
    "sg:postcode":"70737",
    "sg:province":"LA",
    "sg:tags":[
        "attorney"
    ],
    "wof:name":"Lloyd A Capello Jr",
    "wof:placetype":"venue"
},
  "geometry": {"coordinates":[-90.912468,30.232981],"type":"Point"}
}