{
  "type": "Feature",
  "properties": {
    "iso:country":"US",
    "sg:address":"1834 Alexander Ave",
    "sg:city":"Arabi",
    "sg:classifiers":[
        {
            "category":"Building & Trades",
            "subcategory":"Plumbing",
            "type":"Services"
        }
    ],
    "sg:phone":"+1 504 277 5733",
    "sg:postcode":"70032",
    "sg:province":"LA",
    "sg:tags":[
        "contractor"
    ],
    "wof:name":"Perrien Leroy F Plumbing & Htg",
    "wof:placetype":"venue"
},
  "geometry": {"coordinates":[-89.995496,29.969372],"type":"Point"}
}