{
  "type": "Feature",
  "properties": {
    "iso:country":"US",
    "sg:address":"723 S Lewis St",
    "sg:city":"New Iberia",
    "sg:classifiers":[
        {
            "category":"Restaurant",
            "type":"Food & Drink"
        }
    ],
    "sg:phone":"+1 337 367 3171",
    "sg:postcode":"70560",
    "sg:province":"LA",
    "wof:name":"Piccadilly Classic Amer Ckng",
    "wof:placetype":"venue"
},
  "geometry": {"coordinates":[-91.809466,29.993832],"type":"Point"}
}