{
  "type": "Feature",
  "properties": {
    "iso:country":"US",
    "sg:address":"1940 N Pine St",
    "sg:city":"Deridder",
    "sg:classifiers":[
        {
            "category":"Autos & Motor Vehicles",
            "subcategory":"Recreational Vehicle Sales",
            "type":"Retail Goods"
        }
    ],
    "sg:phone":"+1 337 494 0927",
    "sg:postcode":"70634",
    "sg:province":"LA",
    "wof:name":"Kite Brothers Motors Co",
    "wof:placetype":"venue"
},
  "geometry": {"coordinates":[-93.28482,30.881511],"type":"Point"}
}