{
  "type": "Feature",
  "properties": {
    "iso:country":"US",
    "sg:address":"6139 San Juan Dr",
    "sg:city":"Baton Rouge",
    "sg:classifiers":[
        {
            "category":"Insurance",
            "subcategory":"Insurance Agent",
            "type":"Services"
        }
    ],
    "sg:phone":"+1 225 744 4743",
    "sg:postcode":"70811",
    "sg:province":"LA",
    "wof:name":"Olinde's Insurance Of LA LLC",
    "wof:placetype":"venue"
},
  "geometry": {"coordinates":[-91.131652,30.522686],"type":"Point"}
}