{
  "type": "Feature",
  "properties": {
    "iso:country":"US",
    "sg:address":"7040 Colfax Dr",
    "sg:city":"Baker",
    "sg:classifiers":[
        {
            "category":"Building & Trades",
            "subcategory":"Construction",
            "type":"Services"
        }
    ],
    "sg:phone":"+1 225 774 7449",
    "sg:postcode":"70714",
    "sg:province":"LA",
    "sg:tags":[
        "steel"
    ],
    "wof:name":"Allan Carroll & Assoc",
    "wof:placetype":"venue"
},
  "geometry": {"coordinates":[-91.117841,30.59033],"type":"Point"}
}