{
  "type": "Feature",
  "properties": {
    "iso:country":"US",
    "sg:address":"821 Baronne St",
    "sg:city":"New Orleans",
    "sg:classifiers":[
        {
            "category":"Professional",
            "subcategory":"Lawyer & Legal Services",
            "type":"Services"
        }
    ],
    "sg:phone":"+1 504 679 6151",
    "sg:postcode":"70113",
    "sg:province":"LA",
    "sg:tags":[
        "attorney"
    ],
    "wof:name":"Stacey W Marcel",
    "wof:placetype":"venue"
},
  "geometry": {"coordinates":[-90.074603,29.945271],"type":"Point"}
}