{
  "type": "Feature",
  "properties": {
    "iso:country":"US",
    "sg:address":"6700 Jefferson Paige Rd",
    "sg:city":"Shreveport",
    "sg:classifiers":[
        {
            "category":"Wholesale",
            "subcategory":"Machinery & Supplies",
            "type":"Manufacturing & Wholesale Goods"
        }
    ],
    "sg:phone":"+1 318 635 5454",
    "sg:postcode":"71119",
    "sg:province":"LA",
    "sg:tags":[
        "equipment",
        "safety",
        "clothing"
    ],
    "sg:website":"www.ldlunitedunion.com",
    "wof:name":"LDL United Union Inc",
    "wof:placetype":"venue"
},
  "geometry": {"coordinates":[-93.88207,32.478709],"type":"Point"}
}