{
  "type": "Feature",
  "properties": {
    "addr:full":"433 Plaza St Franklinton LA 70427",
    "addr:housenumber":"433",
    "addr:postcode":"70427",
    "addr:street":"Plaza St",
    "iso:country":"US",
    "sg:address":"433 Plaza St",
    "sg:city":"Franklinton",
    "sg:classifiers":[
        {
            "category":"Professional",
            "subcategory":"Computer Services",
            "type":"Services"
        }
    ],
    "sg:phone":"+1 985 839 9197",
    "sg:postcode":"70427",
    "sg:province":"LA",
    "sg:tags":[
        "internet"
    ],
    "wof:name":"Verio Inc",
    "wof:placetype":"venue"
},
  "geometry": {"coordinates":[-89.867893,30.779155],"type":"Point"}
}