{
  "type": "Feature",
  "properties": {
    "iso:country":"US",
    "sg:address":"9650 Airline Hwy",
    "sg:city":"Baton Rouge",
    "sg:classifiers":[
        {
            "category":"Restaurant",
            "type":"Food & Drink"
        }
    ],
    "sg:menulink":"http://www.allmenus.com/la/baton-rouge/106961-soup-man/menu/",
    "sg:phone":"+1 225 926 9304",
    "sg:postcode":"70815",
    "sg:province":"LA",
    "sg:tags":[
        "soup",
        "american",
        "salad"
    ],
    "wof:name":"Soup Man",
    "wof:placetype":"venue"
},
  "geometry": {"coordinates":[-91.082999,30.432266],"type":"Point"}
}