{
  "type": "Feature",
  "properties": {
    "iso:country":"US",
    "sg:address":"22 Purser St",
    "sg:city":"Pineville",
    "sg:classifiers":[
        {
            "category":"Real Estate",
            "subcategory":"Real Estate Agent",
            "type":"Services"
        }
    ],
    "sg:phone":"+1 318 443 4274",
    "sg:postcode":"71360",
    "sg:province":"LA",
    "wof:name":"Whatley Properties",
    "wof:placetype":"venue"
},
  "geometry": {"coordinates":[-92.41816,31.330399],"type":"Point"}
}