{
  "type": "Feature",
  "properties": {
    "iso:country":"US",
    "sg:address":"731 E Landry St",
    "sg:city":"Opelousas",
    "sg:classifiers":[
        {
            "category":"Autos & Motor Vehicles",
            "subcategory":"Fuel & Gas Station",
            "type":"Retail Goods"
        }
    ],
    "sg:phone":"+1 337 942 2770",
    "sg:postcode":"70570",
    "sg:province":"LA",
    "sg:tags":[
        "oil"
    ],
    "wof:name":"Tommy's Enterprise Inc",
    "wof:placetype":"venue"
},
  "geometry": {"coordinates":[-92.075924,30.532085],"type":"Point"}
}