{
  "type": "Feature",
  "properties": {
    "iso:country":"US",
    "sg:address":"1000 Hwy 190",
    "sg:city":"Covington",
    "sg:classifiers":[
        {
            "category":"Autos & Motor Vehicles",
            "subcategory":"Automobile Sales",
            "type":"Retail Goods"
        }
    ],
    "sg:phone":"+1 985 871 5052",
    "sg:postcode":"70433",
    "sg:province":"LA",
    "sg:tags":[
        "used"
    ],
    "wof:name":"Diamond Auto Sales",
    "wof:placetype":"venue"
},
  "geometry": {"coordinates":[-90.082027,30.445551],"type":"Point"}
}