{
  "type": "Feature",
  "properties": {
    "addr:full":"4792 Johnston St Lafayette LA 70503",
    "addr:housenumber":"4792",
    "addr:postcode":"70503",
    "addr:street":"Johnston St",
    "iso:country":"US",
    "sg:address":"4792 Johnston St",
    "sg:city":"Lafayette",
    "sg:classifiers":[
        {
            "category":"Restaurant",
            "type":"Food & Drink"
        }
    ],
    "sg:menulink":"http://www.allmenus.com/la/lafayette/201439-sonic/menu/",
    "sg:phone":"+1 337 981 1212",
    "sg:postcode":"70503",
    "sg:province":"LA",
    "sg:tags":[
        "burger",
        "american"
    ],
    "wof:name":"Sonic",
    "wof:placetype":"venue"
},
  "geometry": {"coordinates":[-92.065831,30.186741],"type":"Point"}
}