{
  "type": "Feature",
  "properties": {
    "iso:country":"US",
    "sg:address":"219 Griffin Rd",
    "sg:city":"Youngsville",
    "sg:classifiers":[
        {
            "category":"Mining & Drilling",
            "type":"Manufacturing & Wholesale Goods"
        }
    ],
    "sg:phone":"+1 337 856 5965",
    "sg:postcode":"70592",
    "sg:province":"LA",
    "sg:tags":[
        "field",
        "oil"
    ],
    "sg:website":"www.mwdsi.com",
    "wof:name":"MWD Svc",
    "wof:placetype":"venue"
},
  "geometry": {"coordinates":[-91.981899,30.109174],"type":"Point"}
}