{
  "type": "Feature",
  "properties": {
    "iso:country":"US",
    "sg:address":"2401 Comet St",
    "sg:city":"New Orleans",
    "sg:classifiers":[
        {
            "category":"Professional",
            "subcategory":"Research",
            "type":"Services"
        }
    ],
    "sg:phone":"+1 504 394 6705",
    "sg:postcode":"70131",
    "sg:province":"LA",
    "sg:tags":[
        "commercial",
        "physical"
    ],
    "wof:name":"Crabarray Inc",
    "wof:placetype":"venue"
},
  "geometry": {"coordinates":[-90.01008899999999,29.928248],"type":"Point"}
}