{
  "type": "Feature",
  "properties": {
    "addr:full":"104 W Hutchinson Ave Crowley LA 70526",
    "addr:housenumber":"104",
    "addr:postcode":"70526",
    "addr:street":"W Hutchinson Ave",
    "iso:country":"US",
    "sg:address":"104 W Hutchinson Ave",
    "sg:city":"Crowley",
    "sg:classifiers":[
        {
            "category":"Government",
            "subcategory":"Fire Station",
            "type":"Public Place"
        }
    ],
    "sg:phone":"+1 337 788 4106",
    "sg:postcode":"70526",
    "sg:province":"LA",
    "sg:tags":[
        "department"
    ],
    "wof:name":"Crowley City Fire Dept",
    "wof:placetype":"venue"
},
  "geometry": {"coordinates":[-92.374825,30.214144],"type":"Point"}
}