{
  "type": "Feature",
  "properties": {
    "addr:full":"330 N Ardenwood Dr Baton Rouge LA 70806",
    "addr:housenumber":"330",
    "addr:postcode":"70806",
    "addr:street":"N Ardenwood Dr",
    "iso:country":"US",
    "sg:address":"330 N Ardenwood Dr",
    "sg:city":"Baton Rouge",
    "sg:classifiers":[
        {
            "category":"Government",
            "subcategory":"Office",
            "type":"Public Place"
        }
    ],
    "sg:phone":"+1 225 925 3606",
    "sg:postcode":"70806",
    "sg:province":"LA",
    "wof:name":"Audit Review Div",
    "wof:placetype":"venue"
},
  "geometry": {"coordinates":[-91.127351,30.453952],"type":"Point"}
}