{
  "type": "Feature",
  "properties": {
    "iso:country":"US",
    "sg:address":"6154 Pine Tree Loop",
    "sg:city":"Shreveport",
    "sg:classifiers":[
        {
            "category":"Building & Trades",
            "subcategory":"Construction",
            "type":"Services"
        }
    ],
    "sg:phone":"+1 318 929 3782",
    "sg:postcode":"71107",
    "sg:province":"LA",
    "sg:tags":[
        "system",
        "contractor",
        "air conditioning"
    ],
    "wof:name":"Lisa A Bamburg",
    "wof:placetype":"venue"
},
  "geometry": {"coordinates":[-93.88342799999999,32.635809],"type":"Point"}
}