{
  "type": "Feature",
  "properties": {
    "addr:full":"418 Lancaster Dr Houma LA 70360",
    "addr:housenumber":"418",
    "addr:postcode":"70360",
    "addr:street":"Lancaster Dr",
    "iso:country":"US",
    "sg:address":"418 Lancaster Dr",
    "sg:city":"Houma",
    "sg:classifiers":[
        {
            "category":"Building & Trades",
            "subcategory":"Plumbing",
            "type":"Services"
        }
    ],
    "sg:phone":"+1 985 580 2317",
    "sg:postcode":"70360",
    "sg:province":"LA",
    "sg:tags":[
        "plumbing",
        "contractor"
    ],
    "wof:name":"Lecompte's Plumbing Inc",
    "wof:placetype":"venue"
},
  "geometry": {"coordinates":[-90.75957,29.579084],"type":"Point"}
}