{
  "type": "Feature",
  "properties": {
    "iso:country":"US",
    "sg:address":"1700 Abadie Ave",
    "sg:city":"Metairie",
    "sg:classifiers":[
        {
            "category":"Professional",
            "type":"Services"
        }
    ],
    "sg:phone":"+1 504 454 1242",
    "sg:postcode":"70003",
    "sg:province":"LA",
    "wof:name":"Wesley Clark",
    "wof:placetype":"venue"
},
  "geometry": {"coordinates":[-90.208027,29.991472],"type":"Point"}
}