{
  "type": "Feature",
  "properties": {
    "iso:country":"US",
    "sg:address":"8110 Oak Ridge Rd",
    "sg:city":"Mer Rouge",
    "sg:classifiers":[
        {
            "category":"Organizations",
            "subcategory":"Religious Organization",
            "type":"Services"
        }
    ],
    "sg:phone":"+1 318 647 3709",
    "sg:postcode":"71261",
    "sg:province":"LA",
    "wof:name":"Eudora Baptist Church",
    "wof:placetype":"venue"
},
  "geometry": {"coordinates":[-91.782999,32.734212],"type":"Point"}
}