{
  "type": "Feature",
  "properties": {
    "addr:full":"3009 College Dr Baton Rouge LA 70808",
    "addr:housenumber":"3009",
    "addr:postcode":"70808",
    "addr:street":"College Dr",
    "iso:country":"US",
    "sg:address":"3009 College Dr",
    "sg:city":"Baton Rouge",
    "sg:classifiers":[
        {
            "category":"Coffee & Tea",
            "type":"Food & Drink"
        }
    ],
    "sg:menulink":"http://www.allmenus.com/la/baton-rouge/113658-starbucks-coffee/menu/",
    "sg:phone":"+1 225 216 7880",
    "sg:postcode":"70808",
    "sg:province":"LA",
    "sg:tags":[
        "american"
    ],
    "wof:name":"Starbucks Coffee",
    "wof:placetype":"venue"
},
  "geometry": {"coordinates":[-91.140691,30.420644],"type":"Point"}
}