{
  "type": "Feature",
  "properties": {
    "iso:country":"US",
    "sg:address":"3652 Main Hwy",
    "sg:city":"Breaux Bridge",
    "sg:classifiers":[
        {
            "category":"Wholesale",
            "subcategory":"Auto Parts",
            "type":"Manufacturing & Wholesale Goods"
        }
    ],
    "sg:phone":"+1 337 332 2205",
    "sg:postcode":"70517",
    "sg:province":"LA",
    "sg:tags":[
        "automobile",
        "supply"
    ],
    "wof:name":"Picard's Auto Truck & Ind",
    "wof:placetype":"venue"
},
  "geometry": {"coordinates":[-91.92926300000001,30.288493],"type":"Point"}
}