{
  "type": "Feature",
  "properties": {
    "addr:full":"6262 Fleur de Lis Dr New Orleans LA 70124",
    "addr:housenumber":"6262",
    "addr:postcode":"70124",
    "addr:street":"Fleur De Lis Dr",
    "iso:country":"US",
    "sg:address":"6262 Fleur de Lis Dr",
    "sg:city":"New Orleans",
    "sg:classifiers":[
        {
            "category":"Restaurant",
            "type":"Food & Drink"
        }
    ],
    "sg:phone":"+1 504 488 0888",
    "sg:postcode":"70124",
    "sg:province":"LA",
    "wof:name":"Tony Angello's Restaurant",
    "wof:placetype":"venue"
},
  "geometry": {"coordinates":[-90.11893499999999,30.004918],"type":"Point"}
}