{
  "type": "Feature",
  "properties": {
    "addr:full":"13000 Justice Ave Baton Rouge LA 70816",
    "addr:housenumber":"13000",
    "addr:postcode":"70816",
    "addr:street":"Justice Ave",
    "iso:country":"US",
    "sg:address":"13000 Justice Ave",
    "sg:city":"Baton Rouge",
    "sg:classifiers":[
        {
            "category":"Health Services",
            "subcategory":"Clinic",
            "type":"Services"
        }
    ],
    "sg:phone":"+1 225 292 9690",
    "sg:postcode":"70816",
    "sg:province":"LA",
    "sg:tags":[
        "organization",
        "medical",
        "surgical"
    ],
    "wof:name":"Examination Management Svc",
    "wof:placetype":"venue"
},
  "geometry": {"coordinates":[-91.04769,30.424086],"type":"Point"}
}