{
  "type": "Feature",
  "properties": {
    "iso:country":"US",
    "sg:address":"305 E Main St",
    "sg:city":"Oak Grove",
    "sg:classifiers":[
        {
            "category":"Professional",
            "subcategory":"Lawyer & Legal Services",
            "type":"Services"
        }
    ],
    "sg:phone":"+1 318 428 3213",
    "sg:postcode":"71263",
    "sg:province":"LA",
    "sg:tags":[
        "attorney"
    ],
    "wof:name":"West Carroll District Attorney",
    "wof:placetype":"venue"
},
  "geometry": {"coordinates":[-91.387613,32.861025],"type":"Point"}
}