{
  "type": "Feature",
  "properties": {
    "addr:full":"3509 Loop Rd Monroe LA 71201",
    "addr:housenumber":"3509",
    "addr:postcode":"71201",
    "addr:street":"Loop Rd",
    "iso:country":"US",
    "sg:address":"3509 Loop Rd",
    "sg:city":"Monroe",
    "sg:classifiers":[
        {
            "category":"Social Services",
            "type":"Services"
        }
    ],
    "sg:phone":"+1 318 325 4484",
    "sg:postcode":"71201",
    "sg:province":"LA",
    "wof:name":"East Street Shelter",
    "wof:placetype":"venue"
},
  "geometry": {"coordinates":[-92.093734,32.542553],"type":"Point"}
}