{
  "type": "Feature",
  "properties": {
    "iso:country":"US",
    "sg:address":"2315 N Woodlawn Ave",
    "sg:city":"Metairie",
    "sg:classifiers":[
        {
            "category":"Professional",
            "subcategory":"Engineering",
            "type":"Services"
        }
    ],
    "sg:phone":"+1 504 454 1710",
    "sg:postcode":"70001",
    "sg:province":"LA",
    "sg:tags":[
        "engineer"
    ],
    "wof:name":"GSE Assoc Inc",
    "wof:placetype":"venue"
},
  "geometry": {"coordinates":[-90.180916,29.995805],"type":"Point"}
}