{
  "type": "Feature",
  "properties": {
    "iso:country":"US",
    "sg:address":"739 Jackson Ave",
    "sg:city":"New Orleans",
    "sg:classifiers":[
        {
            "category":"Retail",
            "subcategory":"Laundry & Dry Cleaning",
            "type":"Services"
        }
    ],
    "sg:phone":"+1 504 523 2448",
    "sg:postcode":"70130",
    "sg:province":"LA",
    "sg:tags":[
        "cleaners"
    ],
    "wof:name":"One Hour Cleaners",
    "wof:placetype":"venue"
},
  "geometry": {"coordinates":[-90.074313,29.926959],"type":"Point"}
}