{
  "type": "Feature",
  "properties": {
    "addr:full":"3519 Patrick St Lake Charles LA 70605",
    "addr:housenumber":"3519",
    "addr:postcode":"70605",
    "addr:street":"Patrick St",
    "iso:country":"US",
    "sg:address":"3519 Patrick St",
    "sg:city":"Lake Charles",
    "sg:classifiers":[
        {
            "category":"Social Services",
            "type":"Services"
        }
    ],
    "sg:phone":"+1 337 477 2407",
    "sg:postcode":"70605",
    "sg:province":"LA",
    "sg:tags":[
        "worker"
    ],
    "wof:name":"Helping Hands Counseling",
    "wof:placetype":"venue"
},
  "geometry": {"coordinates":[-93.21704699999999,30.19241],"type":"Point"}
}