{
  "type": "Feature",
  "properties": {
    "iso:country":"US",
    "sg:address":"327 Bourbon St",
    "sg:city":"New Orleans",
    "sg:classifiers":[
        {
            "category":"Bars & Pubs",
            "type":"Food & Drink"
        }
    ],
    "sg:phone":"+1 504 525 3836",
    "sg:postcode":"70130",
    "sg:province":"LA",
    "wof:name":"Fais Deaux Deaux",
    "wof:placetype":"venue"
},
  "geometry": {"coordinates":[-90.06793999999999,29.9561],"type":"Point"}
}