{
  "type": "Feature",
  "properties": {
    "addr:full":"2130 Wooddale Blvd Baton Rouge LA 70806",
    "addr:housenumber":"2130",
    "addr:postcode":"70806",
    "addr:street":"Wooddale Blvd",
    "iso:country":"US",
    "sg:address":"2130 Wooddale Blvd",
    "sg:city":"Baton Rouge",
    "sg:classifiers":[
        {
            "category":"Building & Trades",
            "subcategory":"Construction",
            "type":"Services"
        }
    ],
    "sg:phone":"+1 225 927 7112",
    "sg:postcode":"70806",
    "sg:province":"LA",
    "sg:tags":[
        "tile",
        "dealer"
    ],
    "wof:name":"T & L Distributing Co",
    "wof:placetype":"venue"
},
  "geometry": {"coordinates":[-91.11515900000001,30.4685],"type":"Point"}
}