{
  "type": "Feature",
  "properties": {
    "iso:country":"US",
    "sg:address":"7618 Old Hammond Hwy",
    "sg:city":"Baton Rouge",
    "sg:classifiers":[
        {
            "category":"Shopping",
            "subcategory":"Gifts & Souvenirs",
            "type":"Retail Goods"
        }
    ],
    "sg:phone":"+1 225 926 8505",
    "sg:postcode":"70809",
    "sg:province":"LA",
    "sg:tags":[
        "shop"
    ],
    "wof:name":"Bath Junkie",
    "wof:placetype":"venue"
},
  "geometry": {"coordinates":[-91.10708099999999,30.43103],"type":"Point"}
}