{
  "type": "Feature",
  "properties": {
    "iso:country":"US",
    "sg:address":"327 E Union St",
    "sg:city":"Minden",
    "sg:classifiers":[
        {
            "category":"Shopping",
            "subcategory":"Clothing, Apparel, & Fashions",
            "type":"Retail Goods"
        }
    ],
    "sg:phone":"+1 318 377 1243",
    "sg:postcode":"71055",
    "sg:province":"LA",
    "wof:name":"Jessica's Fashions",
    "wof:placetype":"venue"
},
  "geometry": {"coordinates":[-93.281899,32.612428],"type":"Point"}
}