{
  "type": "Feature",
  "properties": {
    "iso:country":"US",
    "sg:address":"650 N Ardenwood Dr",
    "sg:city":"Baton Rouge",
    "sg:classifiers":[
        {
            "category":"Real Estate",
            "subcategory":"Real Estate Operator",
            "type":"Services"
        }
    ],
    "sg:phone":"+1 225 924 7223",
    "sg:postcode":"70806",
    "sg:province":"LA",
    "sg:tags":[
        "apartment"
    ],
    "wof:name":"Ardenwood Park Apartments",
    "wof:placetype":"venue"
},
  "geometry": {"coordinates":[-91.12732200000001,30.451443],"type":"Point"}
}