{
  "type": "Feature",
  "properties": {
    "addr:full":"4414 Government St Baton Rouge LA 70806",
    "addr:housenumber":"4414",
    "addr:postcode":"70806",
    "addr:street":"Government St",
    "iso:country":"US",
    "sg:address":"4414 Government St",
    "sg:city":"Baton Rouge",
    "sg:classifiers":[
        {
            "category":"Personal",
            "subcategory":"Barber",
            "type":"Services"
        }
    ],
    "sg:phone":"+1 225 343 9217",
    "sg:postcode":"70806",
    "sg:province":"LA",
    "wof:name":"Wayne's Hair Styling & Barber",
    "wof:placetype":"venue"
},
  "geometry": {"coordinates":[-91.14382000000001,30.444336],"type":"Point"}
}