{
  "type": "Feature",
  "properties": {
    "iso:country":"US",
    "sg:address":"641 W Prien Lake Rd",
    "sg:city":"Lake Charles",
    "sg:classifiers":[
        {
            "category":"Banks & Credit Unions",
            "subcategory":"Investment Brokerage",
            "type":"Services"
        },
        {
            "category":"Real Estate",
            "subcategory":"Real Estate Agent",
            "type":"Services"
        }
    ],
    "sg:phone":"+1 337 480 3799",
    "sg:postcode":"70601",
    "sg:province":"LA",
    "sg:tags":[
        "co",
        "holding"
    ],
    "wof:name":"Tower Land Co Inc",
    "wof:placetype":"venue"
},
  "geometry": {"coordinates":[-93.22962699999999,30.19832],"type":"Point"}
}