{
  "type": "Feature",
  "properties": {
    "addr:full":"2117 Rose St Zwolle LA 71486",
    "addr:housenumber":"2117",
    "addr:postcode":"71486",
    "addr:street":"Rose St",
    "iso:country":"US",
    "sg:address":"2117 Rose St",
    "sg:city":"Zwolle",
    "sg:classifiers":[
        {
            "category":"Education",
            "subcategory":"School",
            "type":"Public Place"
        }
    ],
    "sg:phone":"+1 318 645 6369",
    "sg:postcode":"71486",
    "sg:province":"LA",
    "sg:tags":[
        "k-",
        "private"
    ],
    "sg:website":"http://www.sabine.k12.la.us",
    "wof:name":"Zwolle Intermediate School",
    "wof:placetype":"venue"
},
  "geometry": {"coordinates":[-93.647002,31.633034],"type":"Point"}
}