{
  "type": "Feature",
  "properties": {
    "iso:country":"US",
    "sg:address":"105 Philomine St",
    "sg:city":"Lafayette",
    "sg:classifiers":[
        {
            "category":"Manufacturing",
            "subcategory":"Chemicals & Compounds",
            "type":"Manufacturing & Wholesale Goods"
        }
    ],
    "sg:phone":"+1 337 234 1469",
    "sg:postcode":"70506",
    "sg:province":"LA",
    "wof:name":"Buffalo Chemical Co Inc",
    "wof:placetype":"venue"
},
  "geometry": {"coordinates":[-92.033635,30.237734],"type":"Point"}
}