{
  "type": "Feature",
  "properties": {
    "iso:country":"US",
    "sg:address":"1990 W 21st Ave",
    "sg:city":"Covington",
    "sg:classifiers":[
        {
            "category":"Shopping",
            "subcategory":"Used Merchandise",
            "type":"Retail Goods"
        }
    ],
    "sg:phone":"+1 985 898 2257",
    "sg:postcode":"70433",
    "sg:province":"LA",
    "sg:tags":[
        "antique"
    ],
    "wof:name":"Robert Pool Furniture Design",
    "wof:placetype":"venue"
},
  "geometry": {"coordinates":[-90.118166,30.48504],"type":"Point"}
}