{
  "type": "Feature",
  "properties": {
    "addr:full":"2707 W 70th St Shreveport LA 71108",
    "addr:housenumber":"2707",
    "addr:postcode":"71108",
    "addr:street":"W 70Th St",
    "iso:country":"US",
    "sg:address":"2707 W 70th St",
    "sg:city":"Shreveport",
    "sg:classifiers":[
        {
            "category":"Home & Garden",
            "subcategory":"Household Appliances",
            "type":"Retail Goods"
        },
        {
            "category":"Home & Garden",
            "subcategory":"Home Furnishings",
            "type":"Retail Goods"
        },
        {
            "category":"Home & Garden",
            "subcategory":"Carpets & Floor Coverings",
            "type":"Retail Goods"
        }
    ],
    "sg:phone":"+1 318 671 7950",
    "sg:postcode":"71108",
    "sg:province":"LA",
    "sg:tags":[
        "bedroom",
        "major",
        "set",
        "bed",
        "mattress"
    ],
    "wof:name":"Mattress And More",
    "wof:placetype":"venue"
},
  "geometry": {"coordinates":[-93.781387,32.441917],"type":"Point"}
}