{
  "type": "Feature",
  "properties": {
    "iso:country":"US",
    "sg:address":"501 Saint Peter St",
    "sg:city":"Donaldsonville",
    "sg:classifiers":[
        {
            "category":"Professional",
            "type":"Services"
        }
    ],
    "sg:phone":"+1 225 473 7527",
    "sg:postcode":"70392",
    "sg:province":"LA",
    "sg:tags":[
        "establishment"
    ],
    "wof:name":"Nichols Studios",
    "wof:placetype":"venue"
},
  "geometry": {"coordinates":[-91.302757,29.687015],"type":"Point"}
}