{
  "type": "Feature",
  "properties": {
    "iso:country":"US",
    "sg:address":"4941 W Napoleon Ave",
    "sg:city":"Metairie",
    "sg:classifiers":[
        {
            "category":"Shopping",
            "type":"Retail Goods"
        }
    ],
    "sg:phone":"+1 504 455 0010",
    "sg:postcode":"70001",
    "sg:province":"LA",
    "sg:tags":[
        "picture",
        "frame"
    ],
    "wof:name":"Cannon Framing & Artworks",
    "wof:placetype":"venue"
},
  "geometry": {"coordinates":[-90.19273200000001,29.994739],"type":"Point"}
}