{
  "type": "Feature",
  "properties": {
    "iso:country":"US",
    "sg:address":"2019 Ruth St",
    "sg:city":"Sulphur",
    "sg:classifiers":[
        {
            "category":"Organizations",
            "subcategory":"Religious Organization",
            "type":"Services"
        }
    ],
    "sg:phone":"+1 337 527 6556",
    "sg:postcode":"70663",
    "sg:province":"LA",
    "sg:tags":[
        "church"
    ],
    "wof:name":"Covenant Presbyterian Church",
    "wof:placetype":"venue"
},
  "geometry": {"coordinates":[-93.37633099999999,30.219726],"type":"Point"}
}