{
  "type": "Feature",
  "properties": {
    "iso:country":"US",
    "sg:address":"2150 Westbank Expy",
    "sg:city":"Harvey",
    "sg:classifiers":[
        {
            "category":"Social Services",
            "type":"Services"
        }
    ],
    "sg:phone":"+1 504 362 6708",
    "sg:postcode":"70058",
    "sg:province":"LA",
    "sg:tags":[
        "organization",
        "welfare"
    ],
    "wof:name":"United Cerebral Palsy",
    "wof:placetype":"venue"
},
  "geometry": {"coordinates":[-90.071859,29.900882],"type":"Point"}
}