{
  "type": "Feature",
  "properties": {
    "addr:full":"911 W Jefferson St Oak Grove LA 71263",
    "addr:housenumber":"911",
    "addr:postcode":"71263",
    "addr:street":"W Jefferson St",
    "iso:country":"US",
    "sg:address":"911 W Jefferson St",
    "sg:city":"Oak Grove",
    "sg:classifiers":[
        {
            "category":"Freight",
            "type":"Transportation"
        }
    ],
    "sg:phone":"+1 318 428 5500",
    "sg:postcode":"71263",
    "sg:province":"LA",
    "sg:tags":[
        "consultant"
    ],
    "wof:name":"Gunter Brokerage Svc Inc",
    "wof:placetype":"venue"
},
  "geometry": {"coordinates":[-91.404365,32.860632],"type":"Point"}
}