{
  "type": "Feature",
  "properties": {
    "iso:country":"US",
    "sg:address":"4041 Williams Blvd",
    "sg:city":"Kenner",
    "sg:classifiers":[
        {
            "category":"Personal",
            "subcategory":"Beauty Salon",
            "type":"Services"
        }
    ],
    "sg:phone":"+1 504 443 6117",
    "sg:postcode":"70065",
    "sg:province":"LA",
    "sg:tags":[
        "manicuring"
    ],
    "wof:name":"Lkd Nail & Skin Care",
    "wof:placetype":"venue"
},
  "geometry": {"coordinates":[-90.238845,30.027513],"type":"Point"}
}