{
  "type": "Feature",
  "properties": {
    "addr:full":"7475 Jefferson Hwy Baton Rouge LA 70806",
    "addr:housenumber":"7475",
    "addr:postcode":"70806",
    "addr:street":"Jefferson Hwy",
    "iso:country":"US",
    "sg:address":"7475 Jefferson Hwy",
    "sg:city":"Baton Rouge",
    "sg:classifiers":[
        {
            "category":"Food & Beverages",
            "subcategory":"Groceries & Convenience Stores",
            "type":"Retail Goods"
        }
    ],
    "sg:phone":"+1 225 926 3841",
    "sg:postcode":"70806",
    "sg:province":"LA",
    "wof:name":"Circle K",
    "wof:placetype":"venue"
},
  "geometry": {"coordinates":[-91.113156,30.43407],"type":"Point"}
}