{
  "type": "Feature",
  "properties": {
    "addr:full":"13524 River Rd Edgard LA 70070",
    "addr:housenumber":"13524",
    "addr:postcode":"70070",
    "addr:street":"River Rd",
    "iso:country":"US",
    "sg:address":"13524 River Rd",
    "sg:city":"Edgard",
    "sg:classifiers":[
        {
            "category":"Banks & Credit Unions",
            "subcategory":"Bank",
            "type":"Services"
        }
    ],
    "sg:phone":"+1 985 497 3326",
    "sg:postcode":"70070",
    "sg:province":"LA",
    "wof:name":"Hibernia National Bank",
    "wof:placetype":"venue"
},
  "geometry": {"coordinates":[-90.366463,29.934737],"type":"Point"}
}