{
  "type": "Feature",
  "properties": {
    "iso:country":"US",
    "sg:address":"26 Reynolds St",
    "sg:city":"Springhill",
    "sg:classifiers":[
        {
            "category":"Banks & Credit Unions",
            "subcategory":"Investment Brokerage",
            "type":"Services"
        }
    ],
    "sg:phone":"+1 318 539 2020",
    "sg:postcode":"71075",
    "sg:province":"LA",
    "sg:tags":[
        "advisory",
        "financial"
    ],
    "wof:name":"G R Financial Designs Inc",
    "wof:placetype":"venue"
},
  "geometry": {"coordinates":[-93.46104699999999,33.002253],"type":"Point"}
}