{
  "type": "Feature",
  "properties": {
    "iso:country":"US",
    "sg:address":"1602 N University Ave",
    "sg:city":"Lafayette",
    "sg:classifiers":[
        {
            "category":"Restaurant",
            "type":"Food & Drink"
        }
    ],
    "sg:phone":"+1 337 267 3449",
    "sg:postcode":"70506",
    "sg:province":"LA",
    "wof:name":"Taco Torro",
    "wof:placetype":"venue"
},
  "geometry": {"coordinates":[-92.035743,30.250718],"type":"Point"}
}