{
  "type": "Feature",
  "properties": {
    "iso:country":"US",
    "sg:address":"2705 Ingrid Ln",
    "sg:city":"Metairie",
    "sg:classifiers":[
        {
            "category":"Wholesale",
            "subcategory":"Chemicals & Plastics",
            "type":"Manufacturing & Wholesale Goods"
        }
    ],
    "sg:phone":"+1 504 456 0873",
    "sg:postcode":"70003",
    "sg:province":"LA",
    "sg:tags":[
        "oxygen"
    ],
    "wof:name":"Oxymed Inc",
    "wof:placetype":"venue"
},
  "geometry": {"coordinates":[-90.20501400000001,29.998501],"type":"Point"}
}