{
  "type": "Feature",
  "properties": {
    "addr:full":"1255 N Hearne Ave Shreveport LA 71107",
    "addr:housenumber":"1255",
    "addr:postcode":"71107",
    "addr:street":"N Hearne Ave",
    "iso:country":"US",
    "sg:address":"1255 N Hearne Ave",
    "sg:city":"Shreveport",
    "sg:classifiers":[
        {
            "category":"Home & Garden",
            "subcategory":"Garden Supply",
            "type":"Retail Goods"
        }
    ],
    "sg:phone":"+1 318 222 3871",
    "sg:postcode":"71107",
    "sg:province":"LA",
    "sg:tags":[
        "lawn",
        "mower"
    ],
    "sg:website":"www.enginessw.com",
    "wof:name":"Engines Southwest Inc",
    "wof:placetype":"venue"
},
  "geometry": {"coordinates":[-93.76209299999999,32.538553],"type":"Point"}
}