{
  "type": "Feature",
  "properties": {
    "addr:full":"29790 S Range Rd Livingston LA 70754",
    "addr:housenumber":"29790",
    "addr:postcode":"70754",
    "addr:street":"S Range Rd",
    "iso:country":"US",
    "sg:address":"29790 S Range Rd",
    "sg:city":"Livingston",
    "sg:classifiers":[
        {
            "category":"Wholesale",
            "subcategory":"Motor Vehicles",
            "type":"Manufacturing & Wholesale Goods"
        }
    ],
    "sg:phone":"+1 225 686 0301",
    "sg:postcode":"70754",
    "sg:province":"LA",
    "sg:tags":[
        "auction",
        "automobile"
    ],
    "wof:name":"Copart Inc",
    "wof:placetype":"venue"
},
  "geometry": {"coordinates":[-90.75296899999999,30.50169],"type":"Point"}
}