{
  "type": "Feature",
  "properties": {
    "iso:country":"US",
    "sg:address":"1266 Grimmett Dr",
    "sg:city":"Shreveport",
    "sg:classifiers":[
        {
            "category":"Food & Beverages",
            "subcategory":"Groceries & Convenience Stores",
            "type":"Retail Goods"
        }
    ],
    "sg:phone":"+1 318 226 2580",
    "sg:postcode":"71107",
    "sg:province":"LA",
    "wof:name":"GRIMMET Drive Groc",
    "wof:placetype":"venue"
},
  "geometry": {"coordinates":[-93.76381000000001,32.534204],"type":"Point"}
}