{
  "type": "Feature",
  "properties": {
    "iso:country":"US",
    "sg:address":"9702 Airline Hwy",
    "sg:city":"Baton Rouge",
    "sg:classifiers":[
        {
            "category":"Restaurant",
            "type":"Food & Drink"
        }
    ],
    "sg:menulink":"http://www.allmenus.com/la/baton-rouge/82264-applebees/menu/",
    "sg:phone":"+1 225 924 3001",
    "sg:postcode":"70816",
    "sg:province":"LA",
    "sg:tags":[
        "burger",
        "american",
        "sandwich",
        "soup"
    ],
    "wof:name":"Applebee's",
    "wof:placetype":"venue"
},
  "geometry": {"coordinates":[-91.08049699999999,30.431222],"type":"Point"}
}