{
  "type": "Feature",
  "properties": {
    "addr:full":"813 S Carrollton Ave New Orleans LA 70118",
    "addr:housenumber":"813",
    "addr:postcode":"70118",
    "addr:street":"S Carrollton Ave",
    "iso:country":"US",
    "sg:address":"813 S Carrollton Ave",
    "sg:city":"New Orleans",
    "sg:classifiers":[
        {
            "category":"Professional",
            "subcategory":"Lawyer & Legal Services",
            "type":"Services"
        }
    ],
    "sg:phone":"+1 504 861 0008",
    "sg:postcode":"70118",
    "sg:province":"LA",
    "sg:tags":[
        "attorney"
    ],
    "wof:name":"Carol A Newman",
    "wof:placetype":"venue"
},
  "geometry": {"coordinates":[-90.131923,29.945004],"type":"Point"}
}