{
  "type": "Feature",
  "properties": {
    "addr:full":"4469 Perkins Rd Baton Rouge LA 70808",
    "addr:housenumber":"4469",
    "addr:postcode":"70808",
    "addr:street":"Perkins Rd",
    "iso:country":"US",
    "sg:address":"4469 Perkins Rd",
    "sg:city":"Baton Rouge",
    "sg:classifiers":[
        {
            "category":"Autos & Motor Vehicles",
            "subcategory":"Auto Supplies",
            "type":"Retail Goods"
        }
    ],
    "sg:phone":"+1 225 387 3500",
    "sg:postcode":"70808",
    "sg:province":"LA",
    "sg:tags":[
        "automobile",
        "parts"
    ],
    "sg:website":"www.autozone.com",
    "wof:name":"Autozone",
    "wof:placetype":"venue"
},
  "geometry": {"coordinates":[-91.144248,30.416997],"type":"Point"}
}