{
  "type": "Feature",
  "properties": {
    "iso:country":"US",
    "sg:address":"733 Bourg Larose Hwy",
    "sg:city":"Bourg",
    "sg:classifiers":[
        {
            "category":"Manufacturing",
            "subcategory":"Metals",
            "type":"Manufacturing & Wholesale Goods"
        }
    ],
    "sg:phone":"+1 985 594 9678",
    "sg:postcode":"70343",
    "sg:province":"LA",
    "sg:tags":[
        "fabricator",
        "sheet"
    ],
    "wof:name":"Intracoastal Iron Works",
    "wof:placetype":"venue"
},
  "geometry": {"coordinates":[-90.533394,29.552172],"type":"Point"}
}