{
  "type": "Feature",
  "properties": {
    "addr:full":"560 Burwin Curry Rd Gilbert LA 71336",
    "addr:housenumber":"560",
    "addr:postcode":"71336",
    "addr:street":"Burwin Curry Rd",
    "iso:country":"US",
    "sg:address":"560 Burwin Curry Rd",
    "sg:city":"Gilbert",
    "sg:classifiers":[
        {
            "category":"Farming",
            "subcategory":"Farm",
            "type":"Manufacturing & Wholesale Goods"
        }
    ],
    "sg:phone":"+1 318 435 7645",
    "sg:postcode":"71336",
    "sg:province":"LA",
    "sg:tags":[
        "crop",
        "general"
    ],
    "wof:name":"Curry B E Farm G",
    "wof:placetype":"venue"
},
  "geometry": {"coordinates":[-91.52428,32.057956],"type":"Point"}
}