{
  "type": "Feature",
  "properties": {
    "addr:full":"750 Florida St Baton Rouge LA 70801",
    "addr:housenumber":"750",
    "addr:postcode":"70801",
    "addr:street":"Florida St",
    "iso:country":"US",
    "sg:address":"750 Florida St",
    "sg:city":"Baton Rouge",
    "sg:classifiers":[
        {
            "category":"Government",
            "subcategory":"Office",
            "type":"Public Place"
        }
    ],
    "sg:phone":"+1 225 389 0390",
    "sg:postcode":"70801",
    "sg:province":"LA",
    "wof:name":"US Motor Carriers Ofc",
    "wof:placetype":"venue"
},
  "geometry": {"coordinates":[-91.182154,30.449418],"type":"Point"}
}