{
  "type": "Feature",
  "properties": {
    "addr:full":"2135 Saint Charles Ave New Orleans LA 70130",
    "addr:housenumber":"2135",
    "addr:postcode":"70130",
    "addr:street":"Saint Charles Ave",
    "iso:country":"US",
    "sg:address":"2135 Saint Charles Ave",
    "sg:city":"New Orleans",
    "sg:classifiers":[
        {
            "category":"Restaurant",
            "type":"Food & Drink"
        }
    ],
    "sg:phone":"+1 504 522 6602",
    "sg:postcode":"70130",
    "sg:province":"LA",
    "wof:name":"Igor's Garlic Clove Restaurant",
    "wof:placetype":"venue"
},
  "geometry": {"coordinates":[-90.080395,29.934448],"type":"Point"}
}