{
  "type": "Feature",
  "properties": {
    "iso:country":"US",
    "sg:address":"7299 State Rte 182",
    "sg:city":"Morgan City",
    "sg:classifiers":[
        {
            "category":"Restaurant",
            "type":"Food & Drink"
        }
    ],
    "sg:phone":"+1 985 385 3661",
    "sg:postcode":"70380",
    "sg:province":"LA",
    "wof:name":"Pizza Hut",
    "wof:placetype":"venue"
},
  "geometry": {"coordinates":[-91.187637,29.693944],"type":"Point"}
}