{
  "type": "Feature",
  "properties": {
    "addr:full":"5409 Airline Hwy Baton Rouge LA 70805",
    "addr:housenumber":"5409",
    "addr:postcode":"70805",
    "addr:street":"Airline Hwy",
    "iso:country":"US",
    "sg:address":"5409 Airline Hwy",
    "sg:city":"Baton Rouge",
    "sg:classifiers":[
        {
            "category":"Recreation",
            "subcategory":"Amusement Park",
            "type":"Entertainment"
        }
    ],
    "sg:phone":"+1 225 355 6735",
    "sg:postcode":"70805",
    "sg:province":"LA",
    "wof:name":"Bingo Center",
    "wof:placetype":"venue"
},
  "geometry": {"coordinates":[-91.13666000000001,30.507128],"type":"Point"}
}