{
  "type": "Feature",
  "properties": {
    "iso:country":"US",
    "sg:address":"225 Bellot St",
    "sg:city":"Lafayette",
    "sg:classifiers":[
        {
            "category":"Wholesale",
            "subcategory":"Electrical",
            "type":"Manufacturing & Wholesale Goods"
        }
    ],
    "sg:phone":"+1 337 232 8601",
    "sg:postcode":"70501",
    "sg:province":"LA",
    "sg:tags":[
        "electric",
        "motor"
    ],
    "wof:name":"Jeff's Electric Motor Sales",
    "wof:placetype":"venue"
},
  "geometry": {"coordinates":[-92.01548699999999,30.2368],"type":"Point"}
}