{
  "type": "Feature",
  "properties": {
    "addr:full":"1709 Badt Ave Thibodaux LA 70301",
    "addr:housenumber":"1709",
    "addr:postcode":"70301",
    "addr:street":"Badt Ave",
    "iso:country":"US",
    "sg:address":"1709 Badt Ave",
    "sg:city":"Thibodaux",
    "sg:classifiers":[
        {
            "category":"Real Estate",
            "subcategory":"Real Estate Operator",
            "type":"Services"
        }
    ],
    "sg:phone":"+1 985 449 4152",
    "sg:postcode":"70301",
    "sg:province":"LA",
    "sg:tags":[
        "apartment"
    ],
    "wof:name":"Garden Apartments",
    "wof:placetype":"venue"
},
  "geometry": {"coordinates":[-90.82572999999999,29.776272],"type":"Point"}
}