{
  "type": "Feature",
  "properties": {
    "iso:country":"US",
    "sg:address":"119 Charter St",
    "sg:city":"Delhi",
    "sg:classifiers":[
        {
            "category":"Education",
            "subcategory":"School",
            "type":"Public Place"
        }
    ],
    "sg:phone":"+1 318 878 2508",
    "sg:postcode":"71232",
    "sg:province":"LA",
    "sg:tags":[
        "academic",
        "special"
    ],
    "wof:name":"Richland Training Ctr",
    "wof:placetype":"venue"
},
  "geometry": {"coordinates":[-91.493681,32.463065],"type":"Point"}
}