{
  "type": "Feature",
  "properties": {
    "addr:full":"2138 Louisiana Ave New Orleans LA 70115",
    "addr:housenumber":"2138",
    "addr:postcode":"70115",
    "addr:street":"Louisiana Ave",
    "iso:country":"US",
    "sg:address":"2138 Louisiana Ave",
    "sg:city":"New Orleans",
    "sg:classifiers":[
        {
            "category":"Food & Beverages",
            "subcategory":"Groceries & Convenience Stores",
            "type":"Retail Goods"
        }
    ],
    "sg:phone":"+1 504 895 3311",
    "sg:postcode":"70115",
    "sg:province":"LA",
    "sg:tags":[
        "grocer"
    ],
    "wof:name":"Le's Discount Supermarket",
    "wof:placetype":"venue"
},
  "geometry": {"coordinates":[-90.09406,29.933304],"type":"Point"}
}