{
  "type": "Feature",
  "properties": {
    "iso:country":"US",
    "sg:address":"1641 Poland Ave",
    "sg:city":"New Orleans",
    "sg:classifiers":[
        {
            "category":"Real Estate",
            "subcategory":"Real Estate Agent",
            "type":"Services"
        }
    ],
    "sg:phone":"+1 504 944 2244",
    "sg:postcode":"70117",
    "sg:province":"LA",
    "wof:name":"Turn Key Realty LLC",
    "wof:placetype":"venue"
},
  "geometry": {"coordinates":[-90.029797,29.969858],"type":"Point"}
}