{
  "type": "Feature",
  "properties": {
    "iso:country":"US",
    "sg:address":"548 Clayton Dr",
    "sg:city":"Norco",
    "sg:classifiers":[
        {
            "category":"Building & Trades",
            "subcategory":"Construction",
            "type":"Services"
        }
    ],
    "sg:phone":"+1 985 764 9239",
    "sg:postcode":"70079",
    "sg:province":"LA",
    "sg:tags":[
        "hanging",
        "contractor"
    ],
    "wof:name":"Loupes Painting Plus Inc",
    "wof:placetype":"venue"
},
  "geometry": {"coordinates":[-90.410532,30.009235],"type":"Point"}
}