{
  "type": "Feature",
  "properties": {
    "iso:country":"US",
    "sg:address":"316 Madison St",
    "sg:city":"Gretna",
    "sg:classifiers":[
        {
            "category":"Professional",
            "subcategory":"Business Services",
            "type":"Services"
        }
    ],
    "sg:phone":"+1 504 361 3909",
    "sg:postcode":"70053",
    "sg:province":"LA",
    "sg:tags":[
        "decorating",
        "contractor"
    ],
    "wof:name":"Unique Events Inc",
    "wof:placetype":"venue"
},
  "geometry": {"coordinates":[-90.05273699999999,29.936079],"type":"Point"}
}