{
  "type": "Feature",
  "properties": {
    "iso:country":"US",
    "sg:address":"7120 Jewella Ave",
    "sg:city":"Shreveport",
    "sg:classifiers":[
        {
            "category":"Retail",
            "subcategory":"Auto Repair",
            "type":"Services"
        }
    ],
    "sg:phone":"+1 318 688 2844",
    "sg:postcode":"71108",
    "sg:province":"LA",
    "sg:tags":[
        "body",
        "painting",
        "repairing",
        "automobile"
    ],
    "wof:name":"Twin City Paint and Body",
    "wof:placetype":"venue"
},
  "geometry": {"coordinates":[-93.79742899999999,32.439701],"type":"Point"}
}