{
  "type": "Feature",
  "properties": {
    "iso:country":"US",
    "sg:address":"1109 Cypress St",
    "sg:city":"West Monroe",
    "sg:classifiers":[
        {
            "category":"Retail",
            "subcategory":"Auto Repair",
            "type":"Services"
        }
    ],
    "sg:phone":"+1 318 361 9700",
    "sg:postcode":"71291",
    "sg:province":"LA",
    "sg:tags":[
        "body",
        "automobile",
        "painting"
    ],
    "wof:name":"Sanchez Auto Body",
    "wof:placetype":"venue"
},
  "geometry": {"coordinates":[-92.133184,32.509258],"type":"Point"}
}