{
  "type": "Feature",
  "properties": {
    "iso:country":"US",
    "sg:address":"3140 E Prien Lake Rd",
    "sg:city":"Lake Charles",
    "sg:classifiers":[
        {
            "category":"Shopping",
            "subcategory":"Gifts & Souvenirs",
            "type":"Retail Goods"
        }
    ],
    "sg:phone":"+1 337 480 1988",
    "sg:postcode":"70615",
    "sg:province":"LA",
    "sg:tags":[
        "party",
        "supply"
    ],
    "wof:name":"Party City",
    "wof:placetype":"venue"
},
  "geometry": {"coordinates":[-93.170489,30.198198],"type":"Point"}
}