{
  "type": "Feature",
  "properties": {
    "addr:full":"6106 Scenic Hwy Baton Rouge LA 70805",
    "addr:housenumber":"6106",
    "addr:postcode":"70805",
    "addr:street":"Scenic Hwy",
    "iso:country":"US",
    "sg:address":"6106 Scenic Hwy",
    "sg:city":"Baton Rouge",
    "sg:classifiers":[
        {
            "category":"Autos & Motor Vehicles",
            "subcategory":"Auto Supplies",
            "type":"Retail Goods"
        }
    ],
    "sg:phone":"+1 225 775 8195",
    "sg:postcode":"70805",
    "sg:province":"LA",
    "sg:tags":[
        "tire"
    ],
    "wof:name":"Ready To Roll Used Auto & Tire",
    "wof:placetype":"venue"
},
  "geometry": {"coordinates":[-91.17058299999999,30.505653],"type":"Point"}
}