{
  "type": "Feature",
  "properties": {
    "addr:full":"12114 Industriplex Blvd Baton Rouge LA 70809",
    "addr:housenumber":"12114",
    "addr:postcode":"70809",
    "addr:street":"Industriplex Blvd",
    "iso:country":"US",
    "sg:address":"12114 Industriplex Blvd",
    "sg:city":"Baton Rouge",
    "sg:classifiers":[
        {
            "category":"Professional",
            "type":"Services"
        }
    ],
    "sg:phone":"+1 225 755 7100",
    "sg:postcode":"70809",
    "sg:province":"LA",
    "wof:name":"Sears Product Svc",
    "wof:placetype":"venue"
},
  "geometry": {"coordinates":[-91.04329,30.384126],"type":"Point"}
}