{
  "type": "Feature",
  "properties": {
    "iso:country":"US",
    "sg:address":"806 Hilton St",
    "sg:city":"Monroe",
    "sg:classifiers":[
        {
            "category":"Professional",
            "subcategory":"Advertising",
            "type":"Services"
        }
    ],
    "sg:phone":"+1 318 325 5748",
    "sg:postcode":"71201",
    "sg:province":"LA",
    "sg:tags":[
        "counselor"
    ],
    "wof:name":"Robertson Design Group",
    "wof:placetype":"venue"
},
  "geometry": {"coordinates":[-92.12251500000001,32.522852],"type":"Point"}
}