{
  "type": "Feature",
  "properties": {
    "iso:country":"US",
    "sg:address":"2216 W Willow St",
    "sg:city":"Scott",
    "sg:classifiers":[
        {
            "category":"Professional",
            "subcategory":"Testing Lab",
            "type":"Services"
        }
    ],
    "sg:phone":"+1 337 234 6789",
    "sg:postcode":"70583",
    "sg:province":"LA",
    "sg:tags":[
        "laboratory"
    ],
    "wof:name":"South Testing & Inspection Inc",
    "wof:placetype":"venue"
},
  "geometry": {"coordinates":[-92.066721,30.243293],"type":"Point"}
}