{
  "type": "Feature",
  "properties": {
    "iso:country":"US",
    "sg:address":"71599 Leveson St",
    "sg:city":"Abita Springs",
    "sg:classifiers":[
        {
            "category":"Building & Trades",
            "subcategory":"Construction",
            "type":"Services"
        }
    ],
    "sg:phone":"+1 985 892 5551",
    "sg:postcode":"70420",
    "sg:province":"LA",
    "sg:tags":[
        "general",
        "contractor"
    ],
    "wof:name":"Abita Baths",
    "wof:placetype":"venue"
},
  "geometry": {"coordinates":[-90.038877,30.476428],"type":"Point"}
}