{
  "type": "Feature",
  "properties": {
    "iso:country":"US",
    "sg:address":"2634 Gendarme Rd",
    "sg:city":"Carencro",
    "sg:classifiers":[
        {
            "category":"Bars & Pubs",
            "type":"Food & Drink"
        }
    ],
    "sg:phone":"+1 337 896 0651",
    "sg:postcode":"70520",
    "sg:province":"LA",
    "wof:name":"Emfinger Inc",
    "wof:placetype":"venue"
},
  "geometry": {"coordinates":[-92.085735,30.325612],"type":"Point"}
}