{
  "type": "Feature",
  "properties": {
    "addr:full":"8325 Oak St New Orleans LA 70118",
    "addr:housenumber":"8325",
    "addr:postcode":"70118",
    "addr:street":"Oak St",
    "iso:country":"US",
    "sg:address":"8325 Oak St",
    "sg:city":"New Orleans",
    "sg:classifiers":[
        {
            "category":"Wholesale",
            "subcategory":"Machinery & Supplies",
            "type":"Manufacturing & Wholesale Goods"
        }
    ],
    "sg:phone":"+1 504 866 2626",
    "sg:postcode":"70118",
    "sg:province":"LA",
    "sg:tags":[
        "salon",
        "beauty"
    ],
    "wof:name":"Armstrong Mc Call Beauty Supl",
    "wof:placetype":"venue"
},
  "geometry": {"coordinates":[-90.132131,29.949325],"type":"Point"}
}