{
  "type": "Feature",
  "properties": {
    "iso:country":"US",
    "sg:address":"1240 Hwy 594",
    "sg:city":"Monroe",
    "sg:classifiers":[
        {
            "category":"Government",
            "subcategory":"Office",
            "type":"Public Place"
        }
    ],
    "sg:phone":"+1 318 362 4595",
    "sg:postcode":"71203",
    "sg:province":"LA",
    "wof:name":"Monroe Narcotic's Unit",
    "wof:placetype":"venue"
},
  "geometry": {"coordinates":[-91.990495,32.524146],"type":"Point"}
}