{
  "type": "Feature",
  "properties": {
    "iso:country":"US",
    "sg:address":"2882 Hwy 865",
    "sg:city":"Winnsboro",
    "sg:classifiers":[
        {
            "category":"Recreation",
            "type":"Entertainment"
        }
    ],
    "sg:phone":"+1 318 435 4983",
    "sg:postcode":"71295",
    "sg:province":"LA",
    "sg:tags":[
        "amusement"
    ],
    "wof:name":"Winnsboro Gun Club Inc",
    "wof:placetype":"venue"
},
  "geometry": {"coordinates":[-91.723189,32.124446],"type":"Point"}
}