{
  "type": "Feature",
  "properties": {
    "iso:country":"US",
    "sg:address":"4424 Venus St",
    "sg:city":"New Orleans",
    "sg:classifiers":[
        {
            "category":"Real Estate",
            "subcategory":"Real Estate Agent",
            "type":"Services"
        }
    ],
    "sg:phone":"+1 504 288 6775",
    "sg:postcode":"70122",
    "sg:province":"LA",
    "wof:name":"Inner City RE Dev Corp",
    "wof:placetype":"venue"
},
  "geometry": {"coordinates":[-90.051475,30.004885],"type":"Point"}
}