{
  "type": "Feature",
  "properties": {
    "addr:full":"1020 N Cumberland St Metairie LA 70003",
    "addr:housenumber":"1020",
    "addr:postcode":"70003",
    "addr:street":"N Cumberland St",
    "iso:country":"US",
    "sg:address":"1020 N Cumberland St",
    "sg:city":"Metairie",
    "sg:classifiers":[
        {
            "category":"Freight",
            "type":"Transportation"
        }
    ],
    "sg:phone":"+1 504 464 8848",
    "sg:postcode":"70003",
    "sg:province":"LA",
    "sg:tags":[
        "delivery"
    ],
    "wof:name":"Riverbend Delivery Svc Inc",
    "wof:placetype":"venue"
},
  "geometry": {"coordinates":[-90.225646,29.988752],"type":"Point"}
}