{
  "type": "Feature",
  "properties": {
    "addr:full":"311 Chamberlain Rd Rayne LA 70578",
    "addr:housenumber":"311",
    "addr:postcode":"70578",
    "addr:street":"Chamberlain Rd",
    "iso:country":"US",
    "sg:address":"311 Chamberlain Rd",
    "sg:city":"Rayne",
    "sg:classifiers":[
        {
            "category":"Farming",
            "subcategory":"Farm",
            "type":"Manufacturing & Wholesale Goods"
        }
    ],
    "sg:phone":"+1 337 334 4616",
    "sg:postcode":"70578",
    "sg:province":"LA",
    "wof:name":"Indian Ridge Farm",
    "wof:placetype":"venue"
},
  "geometry": {"coordinates":[-92.243212,30.156989],"type":"Point"}
}