{
  "type": "Feature",
  "properties": {
    "addr:full":"3710 Jolly Dr Baton Rouge LA 70808",
    "addr:housenumber":"3710",
    "addr:postcode":"70808",
    "addr:street":"Jolly Dr",
    "iso:country":"US",
    "sg:address":"3710 Jolly Dr",
    "sg:city":"Baton Rouge",
    "sg:classifiers":[
        {
            "category":"Professional",
            "type":"Services"
        }
    ],
    "sg:phone":"+1 225 383 2813",
    "sg:postcode":"70808",
    "sg:province":"LA",
    "wof:name":"Jabez Foundation Inc",
    "wof:placetype":"venue"
},
  "geometry": {"coordinates":[-91.15535800000001,30.410484],"type":"Point"}
}