{
  "type": "Feature",
  "properties": {
    "addr:full":"201 E Louisiana Ave Rayne LA 70578",
    "addr:housenumber":"201",
    "addr:postcode":"70578",
    "addr:street":"E Louisiana Ave",
    "iso:country":"US",
    "sg:address":"201 E Louisiana Ave",
    "sg:city":"Rayne",
    "sg:classifiers":[
        {
            "category":"Health Services",
            "subcategory":"Clinic",
            "type":"Services"
        }
    ],
    "sg:phone":"+1 337 334 8200",
    "sg:postcode":"70578",
    "sg:province":"LA",
    "wof:name":"Revival Health Care",
    "wof:placetype":"venue"
},
  "geometry": {"coordinates":[-92.26782300000001,30.235885],"type":"Point"}
}