{
  "type": "Feature",
  "properties": {
    "iso:country":"US",
    "sg:address":"5560 Buncombe Rd",
    "sg:city":"Shreveport",
    "sg:classifiers":[
        {
            "category":"Organizations",
            "subcategory":"Religious Organization",
            "type":"Services"
        }
    ],
    "sg:phone":"+1 318 687 8272",
    "sg:postcode":"71129",
    "sg:province":"LA",
    "sg:tags":[
        "church"
    ],
    "wof:name":"Rose Park Baptist Church",
    "wof:placetype":"venue"
},
  "geometry": {"coordinates":[-93.843638,32.448177],"type":"Point"}
}