{
  "type": "Feature",
  "properties": {
    "addr:full":"4525 Glendale St Metairie LA 70006",
    "addr:housenumber":"4525",
    "addr:postcode":"70006",
    "addr:street":"Glendale St",
    "iso:country":"US",
    "sg:address":"4525 Glendale St",
    "sg:city":"Metairie",
    "sg:classifiers":[
        {
            "category":"Organizations",
            "subcategory":"Community Association",
            "type":"Services"
        }
    ],
    "sg:phone":"+1 504 888 4033",
    "sg:postcode":"70006",
    "sg:province":"LA",
    "wof:name":"Krewe Du Vieux Carre",
    "wof:placetype":"venue"
},
  "geometry": {"coordinates":[-90.18744599999999,30.014259],"type":"Point"}
}