{
  "type": "Feature",
  "properties": {
    "addr:full":"13674 Glen Ellis Rd Walker LA 70785",
    "addr:housenumber":"13674",
    "addr:postcode":"70785",
    "addr:street":"Glen Ellis Rd",
    "iso:country":"US",
    "sg:address":"13674 Glen Ellis Rd",
    "sg:city":"Walker",
    "sg:classifiers":[
        {
            "category":"Real Estate",
            "subcategory":"Real Estate Operator",
            "type":"Services"
        }
    ],
    "sg:phone":"+1 225 664 3384",
    "sg:postcode":"70785",
    "sg:province":"LA",
    "sg:tags":[
        "mobile",
        "home",
        "site"
    ],
    "wof:name":"AD Mobile Home Park",
    "wof:placetype":"venue"
},
  "geometry": {"coordinates":[-90.859869,30.459225],"type":"Point"}
}