{
  "type": "Feature",
  "properties": {
    "addr:full":"207 Louisville Ave Monroe LA 71201",
    "addr:housenumber":"207",
    "addr:postcode":"71201",
    "addr:street":"Louisville Ave",
    "iso:country":"US",
    "sg:address":"207 Louisville Ave",
    "sg:city":"Monroe",
    "sg:classifiers":[
        {
            "category":"Government",
            "subcategory":"Office",
            "type":"Public Place"
        }
    ],
    "sg:phone":"+1 318 340 0800",
    "sg:postcode":"71201",
    "sg:province":"LA",
    "wof:name":"Representative Kay K KATZ",
    "wof:placetype":"venue"
},
  "geometry": {"coordinates":[-92.122632,32.507426],"type":"Point"}
}