{
  "type": "Feature",
  "properties": {
    "iso:country":"US",
    "sg:address":"6759 Steamboat Ln",
    "sg:city":"Maurice",
    "sg:classifiers":[
        {
            "category":"Building & Trades",
            "subcategory":"Plumbing",
            "type":"Services"
        }
    ],
    "sg:phone":"+1 337 898 2205",
    "sg:postcode":"70555",
    "sg:province":"LA",
    "sg:tags":[
        "conditioning",
        "air",
        "system",
        "contractor"
    ],
    "wof:name":"Kole's Air Cond & Electric",
    "wof:placetype":"venue"
},
  "geometry": {"coordinates":[-92.08942,30.110595],"type":"Point"}
}