{
  "type": "Feature",
  "properties": {
    "iso:country":"US",
    "sg:address":"2156 Denley Rd",
    "sg:city":"Houma",
    "sg:classifiers":[
        {
            "category":"Mining & Drilling",
            "type":"Manufacturing & Wholesale Goods"
        }
    ],
    "sg:phone":"+1 985 851 5300",
    "sg:postcode":"70363",
    "sg:province":"LA",
    "sg:tags":[
        "field",
        "oil"
    ],
    "sg:website":"www.deltainspection.com",
    "wof:name":"Delta Inspection Co Of Houma",
    "wof:placetype":"venue"
},
  "geometry": {"coordinates":[-90.68351199999999,29.551148],"type":"Point"}
}