{
  "type": "Feature",
  "properties": {
    "addr:full":"2701 Opelousas St Lake Charles LA 70615",
    "addr:housenumber":"2701",
    "addr:postcode":"70615",
    "addr:street":"Opelousas St",
    "iso:country":"US",
    "sg:address":"2701 Opelousas St",
    "sg:city":"Lake Charles",
    "sg:classifiers":[
        {
            "category":"Real Estate",
            "subcategory":"Developer",
            "type":"Services"
        }
    ],
    "sg:phone":"+1 337 436 0514",
    "sg:postcode":"70615",
    "sg:province":"LA",
    "sg:tags":[
        "cemetery"
    ],
    "wof:name":"Combre Memorial Park",
    "wof:placetype":"venue"
},
  "geometry": {"coordinates":[-93.175472,30.242317],"type":"Point"}
}