{
  "type": "Feature",
  "properties": {
    "iso:country":"US",
    "sg:address":"310 Main St",
    "sg:city":"Grambling",
    "sg:classifiers":[
        {
            "category":"Shopping",
            "subcategory":"Clothing, Apparel, & Fashions",
            "type":"Retail Goods"
        }
    ],
    "sg:phone":"+1 318 247 6151",
    "sg:postcode":"71245",
    "sg:province":"LA",
    "sg:tags":[
        "furnishing"
    ],
    "wof:name":"Collegiate Shoppe",
    "wof:placetype":"venue"
},
  "geometry": {"coordinates":[-92.714258,32.526646],"type":"Point"}
}