{
  "type": "Feature",
  "properties": {
    "iso:country":"US",
    "sg:address":"5828 Line Ave",
    "sg:city":"Shreveport",
    "sg:classifiers":[
        {
            "category":"Food & Beverages",
            "subcategory":"Groceries & Convenience Stores",
            "type":"Retail Goods"
        }
    ],
    "sg:phone":"+1 318 869 3545",
    "sg:postcode":"71106",
    "sg:province":"LA",
    "sg:tags":[
        "grocer"
    ],
    "wof:name":"Brookshire's",
    "wof:placetype":"venue"
},
  "geometry": {"coordinates":[-93.74612,32.455972],"type":"Point"}
}