{
  "type": "Feature",
  "properties": {
    "iso:country":"US",
    "sg:address":"500 Verona St",
    "sg:city":"Newellton",
    "sg:classifiers":[
        {
            "category":"Education",
            "subcategory":"School",
            "type":"Public Place"
        }
    ],
    "sg:phone":"+1 318 467 5109",
    "sg:postcode":"71357",
    "sg:province":"LA",
    "wof:name":"Newellton High School",
    "wof:placetype":"venue"
},
  "geometry": {"coordinates":[-91.243511,32.072205],"type":"Point"}
}