{
  "type": "Feature",
  "properties": {
    "iso:country":"US",
    "sg:address":"4728 Cleary Ave",
    "sg:city":"Metairie",
    "sg:classifiers":[
        {
            "category":"Retail",
            "subcategory":"Repair Shop",
            "type":"Services"
        }
    ],
    "sg:phone":"+1 504 887 3575",
    "sg:postcode":"70002",
    "sg:province":"LA",
    "sg:tags":[
        "appliance"
    ],
    "wof:name":"K C Repairs",
    "wof:placetype":"venue"
},
  "geometry": {"coordinates":[-90.174138,30.019533],"type":"Point"}
}