{
  "type": "Feature",
  "properties": {
    "iso:country":"US",
    "sg:address":"102 W 91st St",
    "sg:city":"Galliano",
    "sg:classifiers":[
        {
            "category":"Government",
            "subcategory":"Office",
            "type":"Public Place"
        }
    ],
    "sg:phone":"+1 985 632 6933",
    "sg:postcode":"70345",
    "sg:province":"LA",
    "sg:tags":[
        "county",
        "taxation"
    ],
    "wof:name":"Lafourche Parish Assessor",
    "wof:placetype":"venue"
},
  "geometry": {"coordinates":[-90.32958000000001,29.501392],"type":"Point"}
}