{
  "type": "Feature",
  "properties": {
    "iso:country":"US",
    "sg:address":"9010 State Rte 182",
    "sg:city":"Morgan City",
    "sg:classifiers":[
        {
            "category":"Building & Trades",
            "subcategory":"Construction",
            "type":"Services"
        }
    ],
    "sg:phone":"+1 985 384 3870",
    "sg:postcode":"70380",
    "sg:province":"LA",
    "sg:tags":[
        "designer",
        "marine",
        "contractor"
    ],
    "wof:name":"South Louisiana Fab Inc",
    "wof:placetype":"venue"
},
  "geometry": {"coordinates":[-91.14418000000001,29.682416],"type":"Point"}
}