{
  "type": "Feature",
  "properties": {
    "iso:country":"US",
    "sg:address":"2825 S Macarthur Dr",
    "sg:city":"Alexandria",
    "sg:classifiers":[
        {
            "category":"Retail",
            "subcategory":"Auto Repair",
            "type":"Services"
        }
    ],
    "sg:phone":"+1 318 473 1553",
    "sg:postcode":"71301",
    "sg:province":"LA",
    "sg:tags":[
        "body",
        "automobile",
        "painting"
    ],
    "wof:name":"John Abshires Auto Body Repair",
    "wof:placetype":"venue"
},
  "geometry": {"coordinates":[-92.461601,31.270915],"type":"Point"}
}