{
  "type": "Feature",
  "properties": {
    "addr:full":"2023 E Madison Ave Bastrop LA 71220",
    "addr:housenumber":"2023",
    "addr:postcode":"71220",
    "addr:street":"E Madison Ave",
    "iso:country":"US",
    "sg:address":"2023 E Madison Ave",
    "sg:city":"Bastrop",
    "sg:classifiers":[
        {
            "category":"Restaurant",
            "type":"Food & Drink"
        }
    ],
    "sg:menulink":"http://www.allmenus.com/la/bastrop/173709-wendys/menu/",
    "sg:phone":"+1 318 556 3818",
    "sg:postcode":"71220",
    "sg:province":"LA",
    "sg:tags":[
        "burger",
        "american",
        "soup"
    ],
    "wof:name":"Wendy's",
    "wof:placetype":"venue"
},
  "geometry": {"coordinates":[-91.885682,32.777168],"type":"Point"}
}