{
  "type": "Feature",
  "properties": {
    "addr:full":"477 Moroni Rd Winnsboro LA 71295",
    "addr:housenumber":"477",
    "addr:postcode":"71295",
    "addr:street":"Moroni Rd",
    "iso:country":"US",
    "sg:address":"477 Moroni Rd",
    "sg:city":"Winnsboro",
    "sg:classifiers":[
        {
            "category":"Farming",
            "subcategory":"Farm",
            "type":"Manufacturing & Wholesale Goods"
        }
    ],
    "sg:phone":"+1 318 435 3236",
    "sg:postcode":"71295",
    "sg:province":"LA",
    "wof:name":"Moroni Brothers Farm",
    "wof:placetype":"venue"
},
  "geometry": {"coordinates":[-91.58824799999999,32.125263],"type":"Point"}
}