{
  "type": "Feature",
  "properties": {
    "iso:country":"US",
    "sg:address":"38211 Buillion Switch Rd",
    "sg:city":"Prairieville",
    "sg:classifiers":[
        {
            "category":"Wholesale",
            "subcategory":"Machinery & Supplies",
            "type":"Manufacturing & Wholesale Goods"
        }
    ],
    "sg:phone":"+1 225 677 7838",
    "sg:postcode":"70769",
    "sg:province":"LA",
    "sg:tags":[
        "contractor"
    ],
    "sg:website":"www.clmequipment.com",
    "wof:name":"CLM Equipment Co Inc",
    "wof:placetype":"venue"
},
  "geometry": {"coordinates":[-90.966307,30.296908],"type":"Point"}
}