{
  "type": "Feature",
  "properties": {
    "iso:country":"US",
    "sg:address":"204 Sam St",
    "sg:city":"Kilbourne",
    "sg:classifiers":[
        {
            "category":"Food & Beverages",
            "subcategory":"Specialty",
            "type":"Retail Goods"
        }
    ],
    "sg:phone":"+1 318 428 3613",
    "sg:postcode":"71263",
    "sg:province":"LA",
    "sg:tags":[
        "water",
        "bulk",
        "company"
    ],
    "wof:name":"New Carroll Water System",
    "wof:placetype":"venue"
},
  "geometry": {"coordinates":[-91.29947199999999,32.996904],"type":"Point"}
}