{
  "type": "Feature",
  "properties": {
    "addr:full":"7662 Percy Ave Baton Rouge LA 70812",
    "addr:housenumber":"7662",
    "addr:postcode":"70812",
    "addr:street":"Percy Ave",
    "iso:country":"US",
    "sg:address":"7662 Percy Ave",
    "sg:city":"Baton Rouge",
    "sg:classifiers":[
        {
            "category":"Freight",
            "type":"Transportation"
        }
    ],
    "sg:phone":"+1 225 354 0608",
    "sg:postcode":"70812",
    "sg:province":"LA",
    "sg:tags":[
        "special"
    ],
    "wof:name":"Herme & Son Trucking",
    "wof:placetype":"venue"
},
  "geometry": {"coordinates":[-91.112769,30.501045],"type":"Point"}
}