{
  "type": "Feature",
  "properties": {
    "iso:country":"US",
    "sg:address":"1280 S Flannery Rd",
    "sg:city":"Baton Rouge",
    "sg:classifiers":[
        {
            "category":"Personal",
            "subcategory":"Barber",
            "type":"Services"
        }
    ],
    "sg:phone":"+1 225 273 0636",
    "sg:postcode":"70815",
    "sg:province":"LA",
    "wof:name":"El Hombre Hair Designers",
    "wof:placetype":"venue"
},
  "geometry": {"coordinates":[-91.03447199999999,30.445941],"type":"Point"}
}