{
  "type": "Feature",
  "properties": {
    "iso:country":"US",
    "sg:address":"110 Grove St",
    "sg:city":"Lake Charles",
    "sg:classifiers":[
        {
            "category":"Building & Trades",
            "subcategory":"Electrical",
            "type":"Services"
        }
    ],
    "sg:phone":"+1 337 558 6803",
    "sg:postcode":"70601",
    "sg:province":"LA",
    "sg:tags":[
        "electric",
        "contractor"
    ],
    "wof:name":"Phoenix Electric",
    "wof:placetype":"venue"
},
  "geometry": {"coordinates":[-93.22185399999999,30.218713],"type":"Point"}
}