{
  "type": "Feature",
  "properties": {
    "addr:full":"2347 Justin Ln Harvey LA 70058",
    "addr:housenumber":"2347",
    "addr:postcode":"70058",
    "addr:street":"Justin Ln",
    "iso:country":"US",
    "sg:address":"2347 Justin Ln",
    "sg:city":"Harvey",
    "sg:classifiers":[
        {
            "category":"Retail",
            "subcategory":"Auto Repair",
            "type":"Services"
        }
    ],
    "sg:phone":"+1 504 615 4654",
    "sg:postcode":"70058",
    "sg:province":"LA",
    "sg:tags":[
        "automobile",
        "installation",
        "glass"
    ],
    "wof:name":"K C's Windshield Repair Svc",
    "wof:placetype":"venue"
},
  "geometry": {"coordinates":[-90.047791,29.880476],"type":"Point"}
}