{
  "type": "Feature",
  "properties": {
    "iso:country":"US",
    "sg:address":"11860 Airline Hwy",
    "sg:city":"Baton Rouge",
    "sg:classifiers":[
        {
            "category":"Autos & Motor Vehicles",
            "subcategory":"Auto Supplies",
            "type":"Retail Goods"
        }
    ],
    "sg:phone":"+1 225 292 4430",
    "sg:postcode":"70817",
    "sg:province":"LA",
    "sg:tags":[
        "automobile",
        "parts"
    ],
    "wof:name":"Genuine Parts Co",
    "wof:placetype":"venue"
},
  "geometry": {"coordinates":[-91.049347,30.393721],"type":"Point"}
}