{
  "type": "Feature",
  "properties": {
    "iso:country":"US",
    "sg:address":"705 Marie St",
    "sg:city":"Scott",
    "sg:classifiers":[
        {
            "category":"Retail",
            "subcategory":"Funeral Services",
            "type":"Services"
        }
    ],
    "sg:phone":"+1 337 235 9445",
    "sg:postcode":"70583",
    "sg:province":"LA",
    "sg:tags":[
        "cemetery"
    ],
    "wof:name":"Delhomme Funeral Homes",
    "wof:placetype":"venue"
},
  "geometry": {"coordinates":[-92.0923,30.2314],"type":"Point"}
}