{
  "type": "Feature",
  "properties": {
    "addr:full":"555 Goodhope St Norco LA 70079",
    "addr:housenumber":"555",
    "addr:postcode":"70079",
    "addr:street":"Goodhope St",
    "iso:country":"US",
    "sg:address":"555 Goodhope St",
    "sg:city":"Norco",
    "sg:classifiers":[
        {
            "category":"Social Services",
            "type":"Services"
        }
    ],
    "sg:phone":"+1 985 764 9696",
    "sg:postcode":"70079",
    "sg:province":"LA",
    "sg:tags":[
        "organization",
        "welfare"
    ],
    "wof:name":"Norco Civic Assn",
    "wof:placetype":"venue"
},
  "geometry": {"coordinates":[-90.408095,30.008405],"type":"Point"}
}