{
  "type": "Feature",
  "properties": {
    "addr:full":"101 Stonehill Rd Lafayette LA 70508",
    "addr:housenumber":"101",
    "addr:postcode":"70508",
    "addr:street":"Stonehill Rd",
    "iso:country":"US",
    "sg:address":"101 Stonehill Rd",
    "sg:city":"Lafayette",
    "sg:classifiers":[
        {
            "category":"Building & Trades",
            "subcategory":"Construction",
            "type":"Services"
        }
    ],
    "sg:phone":"+1 337 993 1791",
    "sg:postcode":"70508",
    "sg:province":"LA",
    "sg:tags":[
        "contractor"
    ],
    "wof:name":"Stonehenge Builders",
    "wof:placetype":"venue"
},
  "geometry": {"coordinates":[-92.038991,30.175492],"type":"Point"}
}