{
  "type": "Feature",
  "properties": {
    "iso:country":"US",
    "sg:address":"5095 W Main St",
    "sg:city":"Houma",
    "sg:classifiers":[
        {
            "category":"Shopping",
            "subcategory":"Used Merchandise",
            "type":"Retail Goods"
        }
    ],
    "sg:phone":"+1 985 873 8892",
    "sg:postcode":"70360",
    "sg:province":"LA",
    "sg:tags":[
        "furniture"
    ],
    "wof:name":"Andy's Used Furniture",
    "wof:placetype":"venue"
},
  "geometry": {"coordinates":[-90.76746799999999,29.656122],"type":"Point"}
}