{
  "type": "Feature",
  "properties": {
    "iso:country":"US",
    "sg:address":"1000 Barataria Ave",
    "sg:city":"Houma",
    "sg:classifiers":[
        {
            "category":"Home & Garden",
            "subcategory":"Building Materials",
            "type":"Retail Goods"
        }
    ],
    "sg:phone":"+1 985 872 1431",
    "sg:postcode":"70360",
    "sg:province":"LA",
    "sg:tags":[
        "equipment",
        "electric",
        "supply"
    ],
    "wof:name":"Valley Supply Co Of Houma",
    "wof:placetype":"venue"
},
  "geometry": {"coordinates":[-90.726399,29.590351],"type":"Point"}
}