{
  "type": "Feature",
  "properties": {
    "addr:full":"8735 W Judge Perez Dr Chalmette LA 70043",
    "addr:housenumber":"8735",
    "addr:postcode":"70043",
    "addr:street":"W Judge Perez Dr Chalmette",
    "iso:country":"US",
    "sg:address":"8735 W Judge Perez Dr",
    "sg:city":"Chalmette",
    "sg:classifiers":[
        {
            "category":"Personal",
            "subcategory":"Beauty Salon",
            "type":"Services"
        }
    ],
    "sg:phone":"+1 504 279 9600",
    "sg:postcode":"70043",
    "sg:province":"LA",
    "wof:name":"A New U",
    "wof:placetype":"venue"
},
  "geometry": {"coordinates":[-89.97227700000001,29.950549],"type":"Point"}
}