{
  "type": "Feature",
  "properties": {
    "iso:country":"US",
    "sg:address":"4000 Metropolitan St",
    "sg:city":"New Orleans",
    "sg:classifiers":[
        {
            "category":"Retail",
            "subcategory":"Auto Repair",
            "type":"Services"
        }
    ],
    "sg:phone":"+1 504 947 9807",
    "sg:postcode":"70126",
    "sg:province":"LA",
    "sg:tags":[
        "transmission",
        "general"
    ],
    "wof:name":"Dependable Automatic Transm",
    "wof:placetype":"venue"
},
  "geometry": {"coordinates":[-90.036102,30.001814],"type":"Point"}
}