{
  "type": "Feature",
  "properties": {
    "iso:country":"US",
    "sg:address":"723 1st Ave",
    "sg:city":"Harvey",
    "sg:classifiers":[
        {
            "category":"Autos & Motor Vehicles",
            "subcategory":"Boat Sales",
            "type":"Retail Goods"
        }
    ],
    "sg:phone":"+1 504 347 2892",
    "sg:postcode":"70058",
    "sg:province":"LA",
    "sg:tags":[
        "equipment",
        "marine",
        "supply"
    ],
    "wof:name":"Block One Marine Inc",
    "wof:placetype":"venue"
},
  "geometry": {"coordinates":[-90.08332299999999,29.900373],"type":"Point"}
}