{
  "type": "Feature",
  "properties": {
    "addr:full":"8058 E Park Ave Houma LA 70364",
    "addr:housenumber":"8058",
    "addr:postcode":"70364",
    "addr:street":"E Park Ave",
    "iso:country":"US",
    "sg:address":"8058 E Park Ave",
    "sg:city":"Houma",
    "sg:classifiers":[
        {
            "category":"Restaurant",
            "type":"Food & Drink"
        }
    ],
    "sg:phone":"+1 985 857 8822",
    "sg:postcode":"70364",
    "sg:province":"LA",
    "wof:name":"Subway Sandwiches & Salads",
    "wof:placetype":"venue"
},
  "geometry": {"coordinates":[-90.71656900000001,29.599581],"type":"Point"}
}