{
  "type": "Feature",
  "properties": {
    "addr:full":"1878 Belfield Rd Lake Charles LA 70611",
    "addr:housenumber":"1878",
    "addr:postcode":"70611",
    "addr:street":"Belfield Rd",
    "iso:country":"US",
    "sg:address":"1878 Belfield Rd",
    "sg:city":"Lake Charles",
    "sg:classifiers":[
        {
            "category":"Building & Trades",
            "subcategory":"Construction",
            "type":"Services"
        }
    ],
    "sg:phone":"+1 337 855 4133",
    "sg:postcode":"70611",
    "sg:province":"LA",
    "sg:tags":[
        "painter"
    ],
    "wof:name":"Ace Painting Svc",
    "wof:placetype":"venue"
},
  "geometry": {"coordinates":[-93.214533,30.333871],"type":"Point"}
}