{
  "type": "Feature",
  "properties": {
    "addr:full":"518 Leontine St New Orleans LA 70115",
    "addr:housenumber":"518",
    "addr:postcode":"70115",
    "addr:street":"Leontine St",
    "iso:country":"US",
    "sg:address":"518 Leontine St",
    "sg:city":"New Orleans",
    "sg:classifiers":[
        {
            "category":"Social Services",
            "type":"Services"
        }
    ],
    "sg:phone":"+1 504 897 0498",
    "sg:postcode":"70115",
    "sg:province":"LA",
    "wof:name":"Kris ORourke Msw Lcsw",
    "wof:placetype":"venue"
},
  "geometry": {"coordinates":[-90.11437599999999,29.917398],"type":"Point"}
}