{
  "type": "Feature",
  "properties": {
    "addr:full":"3078 Mount Olive Church Donaldsonville LA 70346",
    "addr:housenumber":"3078",
    "addr:postcode":"70346",
    "addr:street":"Mount;Donaldsonville",
    "iso:country":"US",
    "sg:address":"3078 Mount Olive Church",
    "sg:city":"Donaldsonville",
    "sg:classifiers":[
        {
            "category":"Organizations",
            "subcategory":"Religious Organization",
            "type":"Services"
        }
    ],
    "sg:phone":"+1 225 473 9223",
    "sg:postcode":"70346",
    "sg:province":"LA",
    "sg:tags":[
        "church"
    ],
    "wof:name":"Second Mt Olive Baptist Church",
    "wof:placetype":"venue"
},
  "geometry": {"coordinates":[-91.008785,30.107205],"type":"Point"}
}