{
  "type": "Feature",
  "properties": {
    "iso:country":"US",
    "sg:address":"3955 Government St",
    "sg:city":"Baton Rouge",
    "sg:classifiers":[
        {
            "category":"Social Services",
            "type":"Services"
        }
    ],
    "sg:phone":"+1 225 383 0681",
    "sg:postcode":"70806",
    "sg:province":"LA",
    "sg:tags":[
        "organization",
        "welfare"
    ],
    "sg:website":"www.ywca-br.org",
    "wof:name":"YWCA",
    "wof:placetype":"venue"
},
  "geometry": {"coordinates":[-91.149158,30.444366],"type":"Point"}
}