{
  "type": "Feature",
  "properties": {
    "iso:country":"US",
    "sg:address":"1308 S 5th St",
    "sg:city":"Leesville",
    "sg:classifiers":[
        {
            "category":"Restaurant",
            "type":"Food & Drink"
        }
    ],
    "sg:phone":"+1 337 238 3510",
    "sg:postcode":"71446",
    "sg:province":"LA",
    "wof:name":"Cadillac Jack's",
    "wof:placetype":"venue"
},
  "geometry": {"coordinates":[-93.265934,31.132437],"type":"Point"}
}