{
  "type": "Feature",
  "properties": {
    "iso:country":"US",
    "sg:address":"250 Katherine Dr",
    "sg:city":"Crowley",
    "sg:classifiers":[
        {
            "category":"Social Services",
            "subcategory":"Child Care",
            "type":"Services"
        }
    ],
    "sg:phone":"+1 337 788 2322",
    "sg:postcode":"70526",
    "sg:province":"LA",
    "wof:name":"Room To Grow Daycare",
    "wof:placetype":"venue"
},
  "geometry": {"coordinates":[-92.332683,30.192522],"type":"Point"}
}