{
  "type": "Feature",
  "properties": {
    "iso:country":"US",
    "sg:address":"11838 S Harrells Ferry Rd",
    "sg:city":"Baton Rouge",
    "sg:classifiers":[
        {
            "category":"Professional",
            "subcategory":"Management & Consulting",
            "type":"Services"
        }
    ],
    "sg:phone":"+1 225 275 7940",
    "sg:postcode":"70816",
    "sg:province":"LA",
    "sg:tags":[
        "marketing",
        "consultant"
    ],
    "wof:name":"Southern Marketing Group",
    "wof:placetype":"venue"
},
  "geometry": {"coordinates":[-91.051879,30.430861],"type":"Point"}
}