{
  "type": "Feature",
  "properties": {
    "iso:country":"US",
    "sg:address":"5927 Lapalco Blvd",
    "sg:city":"Marrero",
    "sg:classifiers":[
        {
            "category":"Shopping",
            "subcategory":"Florist",
            "type":"Retail Goods"
        }
    ],
    "sg:phone":"+1 504 348 4266",
    "sg:postcode":"70072",
    "sg:province":"LA",
    "wof:name":"Best Choice B & F",
    "wof:placetype":"venue"
},
  "geometry": {"coordinates":[-90.11154000000001,29.875199],"type":"Point"}
}