{
  "type": "Feature",
  "properties": {
    "iso:country":"US",
    "sg:address":"2119 Ryan St",
    "sg:city":"Lake Charles",
    "sg:classifiers":[
        {
            "category":"Autos & Motor Vehicles",
            "subcategory":"Auto Supplies",
            "type":"Retail Goods"
        }
    ],
    "sg:phone":"+1 337 436 2929",
    "sg:postcode":"70601",
    "sg:province":"LA",
    "sg:tags":[
        "automobile",
        "parts"
    ],
    "wof:name":"Advance Auto Parts",
    "wof:placetype":"venue"
},
  "geometry": {"coordinates":[-93.218559,30.211977],"type":"Point"}
}