{
  "type": "Feature",
  "properties": {
    "iso:country":"US",
    "sg:address":"13318 Hwy 40",
    "sg:city":"Folsom",
    "sg:classifiers":[
        {
            "category":"Real Estate",
            "subcategory":"Real Estate Operator",
            "type":"Services"
        }
    ],
    "sg:phone":"+1 985 796 9447",
    "sg:postcode":"70437",
    "sg:province":"LA",
    "sg:tags":[
        "apartment"
    ],
    "wof:name":"Cottonwood Apartments",
    "wof:placetype":"venue"
},
  "geometry": {"coordinates":[-90.18928,30.627567],"type":"Point"}
}