{
  "type": "Feature",
  "properties": {
    "iso:country":"US",
    "sg:address":"11939 Bricksome Ave",
    "sg:city":"Baton Rouge",
    "sg:classifiers":[
        {
            "category":"Banks & Credit Unions",
            "subcategory":"Investment Brokerage",
            "type":"Services"
        }
    ],
    "sg:phone":"+1 225 292 0608",
    "sg:postcode":"70816",
    "sg:province":"LA",
    "sg:tags":[
        "security"
    ],
    "wof:name":"Securities America",
    "wof:placetype":"venue"
},
  "geometry": {"coordinates":[-91.04858,30.425852],"type":"Point"}
}