{
  "type": "Feature",
  "properties": {
    "addr:full":"4416 Johnston St Lafayette LA 70503",
    "addr:housenumber":"4416",
    "addr:postcode":"70503",
    "addr:street":"Johnston St",
    "iso:country":"US",
    "sg:address":"4416 Johnston St",
    "sg:city":"Lafayette",
    "sg:classifiers":[
        {
            "category":"Real Estate",
            "subcategory":"Real Estate Services",
            "type":"Services"
        }
    ],
    "sg:phone":"+1 337 993 1800",
    "sg:postcode":"70503",
    "sg:province":"LA",
    "sg:tags":[
        "company",
        "title"
    ],
    "wof:name":"Auto Title Express",
    "wof:placetype":"venue"
},
  "geometry": {"coordinates":[-92.058609,30.193877],"type":"Point"}
}