{
  "type": "Feature",
  "properties": {
    "addr:full":"5992 Mer Rouge Rd Bastrop LA 71220",
    "addr:housenumber":"5992",
    "addr:postcode":"71220",
    "addr:street":"Mer Rouge Rd",
    "iso:country":"US",
    "sg:address":"5992 Mer Rouge Rd",
    "sg:city":"Bastrop",
    "sg:classifiers":[
        {
            "category":"Personal",
            "subcategory":"Tanning Parlor",
            "type":"Services"
        }
    ],
    "sg:phone":"+1 318 556 8267",
    "sg:postcode":"71220",
    "sg:province":"LA",
    "sg:tags":[
        "salon"
    ],
    "wof:name":"Sun-Kissed Tans",
    "wof:placetype":"venue"
},
  "geometry": {"coordinates":[-91.873608,32.773319],"type":"Point"}
}