{
  "type": "Feature",
  "properties": {
    "addr:full":"500 N Beglis Pkwy Sulphur LA 70663",
    "addr:housenumber":"500",
    "addr:postcode":"70663",
    "addr:street":"N Beglis Pkwy",
    "iso:country":"US",
    "sg:address":"500 N Beglis Pkwy",
    "sg:city":"Sulphur",
    "sg:classifiers":[
        {
            "category":"Autos & Motor Vehicles",
            "subcategory":"Fuel & Gas Station",
            "type":"Retail Goods"
        }
    ],
    "sg:phone":"+1 337 528 3156",
    "sg:postcode":"70663",
    "sg:province":"LA",
    "sg:tags":[
        "oil"
    ],
    "wof:name":"5th Wheel Conoco",
    "wof:placetype":"venue"
},
  "geometry": {"coordinates":[-93.35937199999999,30.242009],"type":"Point"}
}