{
  "type": "Feature",
  "properties": {
    "addr:full":"12198 US Hwy 165 Glenmora LA 71433",
    "addr:postcode":"12198;71433",
    "addr:street":"Us Hwy 165 Glenmora",
    "iso:country":"US",
    "sg:address":"12198 US Hwy 165",
    "sg:city":"Glenmora",
    "sg:classifiers":[
        {
            "category":"Food & Beverages",
            "subcategory":"Groceries & Convenience Stores",
            "type":"Retail Goods"
        }
    ],
    "sg:phone":"+1 318 748 4958",
    "sg:postcode":"71433",
    "sg:province":"LA",
    "sg:tags":[
        "grocer"
    ],
    "wof:name":"Dalton's Grocery",
    "wof:placetype":"venue"
},
  "geometry": {"coordinates":[-92.57247,30.997923],"type":"Point"}
}