{
  "type": "Feature",
  "properties": {
    "iso:country":"US",
    "sg:address":"201 Cindy St",
    "sg:city":"Thibodaux",
    "sg:classifiers":[
        {
            "category":"Professional",
            "subcategory":"Advertising",
            "type":"Services"
        }
    ],
    "sg:phone":"+1 985 448 0211",
    "sg:postcode":"70301",
    "sg:province":"LA",
    "sg:tags":[
        "guide"
    ],
    "wof:name":"Trans Western Publishing",
    "wof:placetype":"venue"
},
  "geometry": {"coordinates":[-90.949826,29.834258],"type":"Point"}
}