{
  "type": "Feature",
  "properties": {
    "iso:country":"US",
    "sg:address":"11535 Sullivan Rd",
    "sg:city":"Baton Rouge",
    "sg:classifiers":[
        {
            "category":"Retail",
            "subcategory":"Laundry & Dry Cleaning",
            "type":"Services"
        }
    ],
    "sg:phone":"+1 225 261 3518",
    "sg:postcode":"70818",
    "sg:province":"LA",
    "sg:tags":[
        "cleaners"
    ],
    "wof:name":"Kean's The Cleaner",
    "wof:placetype":"venue"
},
  "geometry": {"coordinates":[-91.03888999999999,30.556916],"type":"Point"}
}