{
  "type": "Feature",
  "properties": {
    "iso:country":"US",
    "sg:address":"324 Haydite Ave",
    "sg:city":"Lafayette",
    "sg:classifiers":[
        {
            "category":"Organizations",
            "subcategory":"Religious Organization",
            "type":"Services"
        }
    ],
    "sg:phone":"+1 337 232 3157",
    "sg:postcode":"70507",
    "sg:province":"LA",
    "wof:name":"The Family Church",
    "wof:placetype":"venue"
},
  "geometry": {"coordinates":[-92.033401,30.253799],"type":"Point"}
}