{
  "type": "Feature",
  "properties": {
    "iso:country":"US",
    "sg:address":"2103 NW Evangeline Trwy",
    "sg:city":"Lafayette",
    "sg:classifiers":[
        {
            "category":"Food & Beverages",
            "subcategory":"Groceries & Convenience Stores",
            "type":"Retail Goods"
        }
    ],
    "sg:phone":"+1 337 234 5773",
    "sg:postcode":"70501",
    "sg:province":"LA",
    "sg:website":"www.crackerbarrel.com",
    "wof:name":"Cracker Barrel",
    "wof:placetype":"venue"
},
  "geometry": {"coordinates":[-92.014,30.2519],"type":"Point"}
}