{
  "type": "Feature",
  "properties": {
    "addr:full":"7065 Magnolia Beach Rd Denham Springs LA 70706",
    "addr:housenumber":"7065",
    "addr:postcode":"70706",
    "addr:street":"Magnolia Beach Rd",
    "iso:country":"US",
    "sg:address":"7065 Magnolia Beach Rd",
    "sg:city":"Denham Springs",
    "sg:classifiers":[
        {
            "category":"Wholesale",
            "subcategory":"Toys & Hobbies",
            "type":"Manufacturing & Wholesale Goods"
        }
    ],
    "sg:phone":"+1 225 791 4044",
    "sg:postcode":"70706",
    "sg:province":"LA",
    "sg:tags":[
        "firework"
    ],
    "wof:name":"Red Rocket Fireworks Co",
    "wof:placetype":"venue"
},
  "geometry": {"coordinates":[-90.96559600000001,30.533983],"type":"Point"}
}