{
  "type": "Feature",
  "properties": {
    "iso:country":"US",
    "sg:address":"1925 N Stevendale Rd",
    "sg:city":"Baton Rouge",
    "sg:classifiers":[
        {
            "category":"Autos & Motor Vehicles",
            "subcategory":"Automobile Sales",
            "type":"Retail Goods"
        }
    ],
    "sg:phone":"+1 225 274 9023",
    "sg:postcode":"70819",
    "sg:province":"LA",
    "sg:tags":[
        "car",
        "dealer"
    ],
    "wof:name":"H & R Used Cars",
    "wof:placetype":"venue"
},
  "geometry": {"coordinates":[-91.002622,30.47047],"type":"Point"}
}