{
  "type": "Feature",
  "properties": {
    "iso:country":"US",
    "sg:address":"132 E Moreau St",
    "sg:city":"Chalmette",
    "sg:classifiers":[
        {
            "category":"Wholesale",
            "subcategory":"Auto Parts",
            "type":"Manufacturing & Wholesale Goods"
        }
    ],
    "sg:phone":"+1 504 271 8007",
    "sg:postcode":"70043",
    "sg:province":"LA",
    "sg:tags":[
        "equipment",
        "truck"
    ],
    "wof:name":"Bulldog Spray On Bedliners",
    "wof:placetype":"venue"
},
  "geometry": {"coordinates":[-89.96517900000001,29.93738],"type":"Point"}
}