{
  "type": "Feature",
  "properties": {
    "addr:full":"3700 Orleans Ave New Orleans LA 70119",
    "addr:housenumber":"3700",
    "addr:postcode":"70119",
    "addr:street":"Orleans Ave",
    "iso:country":"US",
    "sg:address":"3700 Orleans Ave",
    "sg:city":"New Orleans",
    "sg:classifiers":[
        {
            "category":"Restaurant",
            "type":"Food & Drink"
        }
    ],
    "sg:phone":"+1 504 934 1192",
    "sg:postcode":"70119",
    "sg:province":"LA",
    "sg:tags":[
        "shop",
        "coffee"
    ],
    "wof:name":"P J's Coffee House",
    "wof:placetype":"venue"
},
  "geometry": {"coordinates":[-90.093052,29.977407],"type":"Point"}
}