{
  "type": "Feature",
  "properties": {
    "iso:country":"US",
    "sg:address":"206 S Washington St",
    "sg:city":"Bastrop",
    "sg:classifiers":[
        {
            "category":"Shopping",
            "type":"Retail Goods"
        }
    ],
    "sg:phone":"+1 318 281 8212",
    "sg:postcode":"71220",
    "sg:province":"LA",
    "sg:tags":[
        "cosmetic",
        "perfume"
    ],
    "wof:name":"Hair Care Beauty Supply",
    "wof:placetype":"venue"
},
  "geometry": {"coordinates":[-91.914494,32.777219],"type":"Point"}
}