{
  "type": "Feature",
  "properties": {
    "iso:country":"US",
    "sg:address":"257 Bergeron St",
    "sg:city":"Houma",
    "sg:classifiers":[
        {
            "category":"Food & Beverages",
            "subcategory":"Specialty",
            "type":"Retail Goods"
        }
    ],
    "sg:phone":"+1 985 879 3444",
    "sg:postcode":"70364",
    "sg:province":"LA",
    "sg:tags":[
        "american",
        "latin",
        "mexican",
        "product"
    ],
    "wof:name":"Mickey Brown Inc",
    "wof:placetype":"venue"
},
  "geometry": {"coordinates":[-90.716589,29.602476],"type":"Point"}
}