{
  "type": "Feature",
  "properties": {
    "iso:country":"US",
    "sg:address":"1731 Martin Luther King Blvd",
    "sg:city":"Houma",
    "sg:classifiers":[
        {
            "category":"Cafe",
            "type":"Food & Drink"
        }
    ],
    "sg:menulink":"http://www.allmenus.com/la/houma/155741-wow-cafe--wingery/menu/",
    "sg:phone":"+1 985 876 4969",
    "sg:postcode":"70360",
    "sg:province":"LA",
    "sg:tags":[
        "american"
    ],
    "wof:name":"Wow Cafe & Wingery",
    "wof:placetype":"venue"
},
  "geometry": {"coordinates":[-90.754643,29.611779],"type":"Point"}
}