{
  "type": "Feature",
  "properties": {
    "iso:country":"US",
    "sg:address":"5421 Durham Dr",
    "sg:city":"New Orleans",
    "sg:classifiers":[
        {
            "category":"Building & Trades",
            "subcategory":"Landscaping Services",
            "type":"Services"
        }
    ],
    "sg:phone":"+1 504 433 0401",
    "sg:postcode":"70131",
    "sg:province":"LA",
    "wof:name":"Lofton Lawn Care",
    "wof:placetype":"venue"
},
  "geometry": {"coordinates":[-89.997855,29.920154],"type":"Point"}
}