{
  "type": "Feature",
  "properties": {
    "addr:full":"83 Louisiana St Westwego LA 70094",
    "addr:housenumber":"83",
    "addr:postcode":"70094",
    "addr:street":"Louisiana St",
    "iso:country":"US",
    "sg:address":"83 Louisiana St",
    "sg:city":"Westwego",
    "sg:classifiers":[
        {
            "category":"Building & Trades",
            "subcategory":"Construction",
            "type":"Services"
        }
    ],
    "sg:phone":"+1 504 341 7217",
    "sg:postcode":"70094",
    "sg:province":"LA",
    "sg:tags":[
        "general",
        "contractor"
    ],
    "wof:name":"Jacobsen Specialty Svc",
    "wof:placetype":"venue"
},
  "geometry": {"coordinates":[-90.14645299999999,29.911008],"type":"Point"}
}