{
  "type": "Feature",
  "properties": {
    "addr:full":"39 Sandpiper Dr La Place LA 70068",
    "addr:housenumber":"39",
    "addr:postcode":"70068",
    "addr:street":"Sandpiper Dr La Place",
    "iso:country":"US",
    "sg:address":"39 Sandpiper Dr",
    "sg:city":"La Place",
    "sg:classifiers":[
        {
            "category":"Local Transit",
            "type":"Transportation"
        }
    ],
    "sg:phone":"+1 985 652 5466",
    "sg:postcode":"70068",
    "sg:province":"LA",
    "sg:tags":[
        "limousine"
    ],
    "wof:name":"Al's Royal Coach Limousine Svc",
    "wof:placetype":"venue"
},
  "geometry": {"coordinates":[-90.46241499999999,30.087062],"type":"Point"}
}