{
  "type": "Feature",
  "properties": {
    "iso:country":"US",
    "sg:address":"827 Magazine St",
    "sg:city":"New Orleans",
    "sg:classifiers":[
        {
            "category":"Professional",
            "subcategory":"Business Services",
            "type":"Services"
        }
    ],
    "sg:phone":"+1 504 524 6066",
    "sg:postcode":"70130",
    "sg:province":"LA",
    "sg:tags":[
        "convention",
        "meeting",
        "facility"
    ],
    "sg:website":"www.conventionplant.com",
    "wof:name":"Convention Plant Creations",
    "wof:placetype":"venue"
},
  "geometry": {"coordinates":[-90.06960100000001,29.944228],"type":"Point"}
}