{
  "type": "Feature",
  "properties": {
    "addr:full":"6224 Isabell Ln Alexandria LA 71303",
    "addr:postcode":"6224;71303",
    "addr:street":"Isabell Ln",
    "iso:country":"US",
    "sg:address":"6224 Isabell Ln",
    "sg:city":"Alexandria",
    "sg:classifiers":[
        {
            "category":"Retail",
            "subcategory":"Animal Services",
            "type":"Services"
        }
    ],
    "sg:phone":"+1 318 448 9862",
    "sg:postcode":"71303",
    "sg:province":"LA",
    "sg:tags":[
        "pet",
        "boarding",
        "sitting"
    ],
    "wof:name":"Pawticulars Pet Sitting",
    "wof:placetype":"venue"
},
  "geometry": {"coordinates":[-92.506942,31.263918],"type":"Point"}
}