{
  "type": "Feature",
  "properties": {
    "iso:country":"US",
    "sg:address":"101 S Main St",
    "sg:city":"Church Point",
    "sg:classifiers":[
        {
            "category":"Wholesale",
            "subcategory":"Machinery & Supplies",
            "type":"Manufacturing & Wholesale Goods"
        },
        {
            "category":"Personal",
            "subcategory":"Beauty Salon",
            "type":"Services"
        }
    ],
    "sg:phone":"+1 337 684 3751",
    "sg:postcode":"70525",
    "sg:province":"LA",
    "sg:tags":[
        "shop",
        "equipment",
        "establishment"
    ],
    "wof:name":"Han's Beauty Supply",
    "wof:placetype":"venue"
},
  "geometry": {"coordinates":[-92.21707600000001,30.405533],"type":"Point"}
}