{
  "type": "Feature",
  "properties": {
    "iso:country":"US",
    "sg:address":"4536 Plank Rd",
    "sg:city":"Baton Rouge",
    "sg:classifiers":[
        {
            "category":"Food & Beverages",
            "subcategory":"Groceries & Convenience Stores",
            "type":"Retail Goods"
        }
    ],
    "sg:phone":"+1 225 358 0086",
    "sg:postcode":"70805",
    "sg:province":"LA",
    "wof:name":"Circle K",
    "wof:placetype":"venue"
},
  "geometry": {"coordinates":[-91.15621,30.490819],"type":"Point"}
}