{
  "type": "Feature",
  "properties": {
    "iso:country":"US",
    "sg:address":"772 Country Club Rd",
    "sg:city":"Winnfield",
    "sg:classifiers":[
        {
            "category":"Organizations",
            "subcategory":"Religious Organization",
            "type":"Services"
        }
    ],
    "sg:phone":"+1 318 628 2561",
    "sg:postcode":"71483",
    "sg:province":"LA",
    "sg:tags":[
        "church"
    ],
    "wof:name":"Our Lady Of Lourdes",
    "wof:placetype":"venue"
},
  "geometry": {"coordinates":[-92.648971,31.906697],"type":"Point"}
}