{
  "type": "Feature",
  "properties": {
    "iso:country":"US",
    "sg:address":"2175 W Laurel Ave",
    "sg:city":"Eunice",
    "sg:classifiers":[
        {
            "category":"Autos & Motor Vehicles",
            "subcategory":"Automobile Sales",
            "type":"Retail Goods"
        }
    ],
    "sg:phone":"+1 337 457 8825",
    "sg:postcode":"70535",
    "sg:province":"LA",
    "sg:tags":[
        "used",
        "dealer"
    ],
    "wof:name":"Eunice Auto Sales",
    "wof:placetype":"venue"
},
  "geometry": {"coordinates":[-92.437884,30.494936],"type":"Point"}
}