{
  "type": "Feature",
  "properties": {
    "addr:full":"4002 Desiard St Monroe LA 71203",
    "addr:housenumber":"4002",
    "addr:postcode":"71203",
    "addr:street":"Desiard St",
    "iso:country":"US",
    "sg:address":"4002 Desiard St",
    "sg:city":"Monroe",
    "sg:classifiers":[
        {
            "category":"Shopping",
            "subcategory":"Department Store",
            "type":"Retail Goods"
        }
    ],
    "sg:phone":"+1 318 345 2495",
    "sg:postcode":"71203",
    "sg:province":"LA",
    "wof:name":"Greek Dreams",
    "wof:placetype":"venue"
},
  "geometry": {"coordinates":[-92.073233,32.525584],"type":"Point"}
}