{
  "type": "Feature",
  "properties": {
    "addr:full":"8377 W el Cajon Dr Baton Rouge LA 70815",
    "addr:housenumber":"8377",
    "addr:postcode":"70815",
    "addr:street":"W El Cajon Dr",
    "iso:country":"US",
    "sg:address":"8377 W el Cajon Dr",
    "sg:city":"Baton Rouge",
    "sg:classifiers":[
        {
            "category":"Autos & Motor Vehicles",
            "subcategory":"Auto Supplies",
            "type":"Retail Goods"
        }
    ],
    "sg:phone":"+1 225 922 9294",
    "sg:postcode":"70815",
    "sg:province":"LA",
    "sg:tags":[
        "automobile",
        "parts"
    ],
    "wof:name":"Scroggins Trans-Parts",
    "wof:placetype":"venue"
},
  "geometry": {"coordinates":[-91.09983099999999,30.469188],"type":"Point"}
}