{
  "type": "Feature",
  "properties": {
    "iso:country":"US",
    "sg:address":"1624 Newton St",
    "sg:city":"New Orleans",
    "sg:classifiers":[
        {
            "category":"Restaurant",
            "type":"Food & Drink"
        }
    ],
    "sg:phone":"+1 504 362 1010",
    "sg:postcode":"70114",
    "sg:province":"LA",
    "wof:name":"Church's Chicken",
    "wof:placetype":"venue"
},
  "geometry": {"coordinates":[-90.039986,29.945191],"type":"Point"}
}