{
  "type": "Feature",
  "properties": {
    "addr:full":"438 Fortson St Shreveport LA 71107",
    "addr:housenumber":"438",
    "addr:postcode":"71107",
    "addr:street":"Fortson St",
    "iso:country":"US",
    "sg:address":"438 Fortson St",
    "sg:city":"Shreveport",
    "sg:phone":"+1 318 222 3287",
    "sg:postcode":"71107",
    "sg:province":"LA",
    "sg:tags":[
        "bulk",
        "gas"
    ],
    "wof:name":"Aeriform Corp",
    "wof:placetype":"venue"
},
  "geometry": {"coordinates":[-93.762328,32.526509],"type":"Point"}
}