{
  "type": "Feature",
  "properties": {
    "iso:country":"US",
    "sg:address":"325 Royal St",
    "sg:city":"New Orleans",
    "sg:classifiers":[
        {
            "category":"Shopping",
            "subcategory":"Used Merchandise",
            "type":"Retail Goods"
        }
    ],
    "sg:phone":"+1 504 522 4552",
    "sg:postcode":"70130",
    "sg:province":"LA",
    "sg:tags":[
        "antique"
    ],
    "wof:name":"Royal Co",
    "wof:placetype":"venue"
},
  "geometry": {"coordinates":[-90.06702199999999,29.955502],"type":"Point"}
}