{
  "type": "Feature",
  "properties": {
    "addr:full":"602 Woodward Ave Ruston LA 71270",
    "addr:housenumber":"602",
    "addr:postcode":"71270",
    "addr:street":"Woodward Ave",
    "iso:country":"US",
    "sg:address":"602 Woodward Ave",
    "sg:city":"Ruston",
    "sg:classifiers":[
        {
            "category":"Wholesale",
            "subcategory":"Hardware",
            "type":"Manufacturing & Wholesale Goods"
        }
    ],
    "sg:phone":"+1 318 255 6324",
    "sg:postcode":"71270",
    "sg:province":"LA",
    "sg:tags":[
        "plumbing",
        "fixture",
        "supply"
    ],
    "wof:name":"Coburn Supply Co",
    "wof:placetype":"venue"
},
  "geometry": {"coordinates":[-92.64581800000001,32.540808],"type":"Point"}
}