{
  "type": "Feature",
  "properties": {
    "addr:full":"4699 Hwy 80 Haughton LA 71037",
    "addr:housenumber":"4699",
    "addr:postcode":"71037",
    "addr:street":"Hwy 80",
    "iso:country":"US",
    "sg:address":"4699 Hwy 80",
    "sg:city":"Haughton",
    "sg:classifiers":[
        {
            "category":"Banks & Credit Unions",
            "subcategory":"Bank",
            "type":"Services"
        }
    ],
    "sg:phone":"+1 318 226 2725",
    "sg:postcode":"71037",
    "sg:province":"LA",
    "wof:name":"Bank One",
    "wof:placetype":"venue"
},
  "geometry": {"coordinates":[-93.567685,32.55621],"type":"Point"}
}