{
  "type": "Feature",
  "properties": {
    "addr:full":"5000 River Rd Marrero LA 70072",
    "addr:housenumber":"5000",
    "addr:postcode":"70072",
    "addr:street":"River Rd Marrero",
    "iso:country":"US",
    "sg:address":"5000 River Rd",
    "sg:city":"Marrero",
    "sg:classifiers":[
        {
            "category":"Autos & Motor Vehicles",
            "subcategory":"Fuel & Gas Station",
            "type":"Retail Goods"
        }
    ],
    "sg:phone":"+1 504 680 6800",
    "sg:postcode":"70072",
    "sg:province":"LA",
    "sg:tags":[
        "oil"
    ],
    "wof:name":"Shell",
    "wof:placetype":"venue"
},
  "geometry": {"coordinates":[-90.101731,29.905278],"type":"Point"}
}