{
  "type": "Feature",
  "properties": {
    "addr:full":"1049 W Airline Hwy La Place LA 70068",
    "addr:housenumber":"1049",
    "addr:postcode":"70068",
    "addr:street":"W Airline Hwy La Place",
    "iso:country":"US",
    "sg:address":"1049 W Airline Hwy",
    "sg:city":"La Place",
    "sg:classifiers":[
        {
            "category":"Retail",
            "subcategory":"Auto Repair",
            "type":"Services"
        }
    ],
    "sg:phone":"+1 985 652 9329",
    "sg:postcode":"70068",
    "sg:province":"LA",
    "sg:tags":[
        "wrecker"
    ],
    "wof:name":"Clement's Towing",
    "wof:placetype":"venue"
},
  "geometry": {"coordinates":[-90.48812700000001,30.07043],"type":"Point"}
}