{
  "type": "Feature",
  "properties": {
    "iso:country":"US",
    "sg:address":"40810 Hayes Rd",
    "sg:city":"Slidell",
    "sg:classifiers":[
        {
            "category":"Building & Trades",
            "subcategory":"Construction",
            "type":"Services"
        }
    ],
    "sg:phone":"+1 985 643 9632",
    "sg:postcode":"70461",
    "sg:province":"LA",
    "sg:tags":[
        "masonry",
        "contractor"
    ],
    "wof:name":"Ross Masonry",
    "wof:placetype":"venue"
},
  "geometry": {"coordinates":[-89.719191,30.28189],"type":"Point"}
}