{
  "type": "Feature",
  "properties": {
    "iso:country":"US",
    "sg:address":"2401 Camelot Ct",
    "sg:city":"Metairie",
    "sg:classifiers":[
        {
            "category":"Building & Trades",
            "subcategory":"Construction",
            "type":"Services"
        }
    ],
    "sg:phone":"+1 504 779 3568",
    "sg:postcode":"70001",
    "sg:province":"LA",
    "sg:tags":[
        "painter"
    ],
    "wof:name":"Wright's Painting LLC",
    "wof:placetype":"venue"
},
  "geometry": {"coordinates":[-90.165359,29.996063],"type":"Point"}
}