{
  "type": "Feature",
  "properties": {
    "iso:country":"US",
    "sg:address":"343 US Hwy 80",
    "sg:city":"Tallulah",
    "sg:classifiers":[
        {
            "category":"Wholesale",
            "subcategory":"Chemicals & Plastics",
            "type":"Manufacturing & Wholesale Goods"
        }
    ],
    "sg:phone":"+1 318 574 2333",
    "sg:postcode":"71282",
    "sg:province":"LA",
    "sg:website":"www.uap.com",
    "wof:name":"UAP Delta",
    "wof:placetype":"venue"
},
  "geometry": {"coordinates":[-91.19394800000001,32.411595],"type":"Point"}
}