{
  "type": "Feature",
  "properties": {
    "addr:full":"708 W 70th St Shreveport LA 71106",
    "addr:housenumber":"708",
    "addr:postcode":"71106",
    "addr:street":"W 70Th St",
    "iso:country":"US",
    "sg:address":"708 W 70th St",
    "sg:city":"Shreveport",
    "sg:classifiers":[
        {
            "category":"Personal",
            "subcategory":"Beauty Salon",
            "type":"Services"
        }
    ],
    "sg:phone":"+1 318 868 6789",
    "sg:postcode":"71106",
    "sg:province":"LA",
    "sg:tags":[
        "manicuring"
    ],
    "wof:name":"Lovey Nails",
    "wof:placetype":"venue"
},
  "geometry": {"coordinates":[-93.77143599999999,32.442064],"type":"Point"}
}