{
  "type": "Feature",
  "properties": {
    "iso:country":"US",
    "sg:address":"411 Texas St",
    "sg:city":"Natchitoches",
    "sg:classifiers":[
        {
            "category":"Autos & Motor Vehicles",
            "subcategory":"Automobile Sales",
            "type":"Retail Goods"
        }
    ],
    "sg:phone":"+1 318 354 6578",
    "sg:postcode":"71457",
    "sg:province":"LA",
    "sg:tags":[
        "car",
        "dealer"
    ],
    "wof:name":"Best Deal's Auto Sales",
    "wof:placetype":"venue"
},
  "geometry": {"coordinates":[-93.090841,31.76733],"type":"Point"}
}