{
  "type": "Feature",
  "properties": {
    "addr:full":"122 Guillot St Pierre Part LA 70339",
    "addr:housenumber":"122",
    "addr:postcode":"70339",
    "addr:street":"Guillot St",
    "iso:country":"US",
    "sg:address":"122 Guillot St",
    "sg:city":"Pierre Part",
    "sg:classifiers":[
        {
            "category":"Professional",
            "subcategory":"Business Services",
            "type":"Services"
        }
    ],
    "sg:phone":"+1 985 252 9794",
    "sg:postcode":"70339",
    "sg:province":"LA",
    "wof:name":"Uncle Sams Trucking LLC",
    "wof:placetype":"venue"
},
  "geometry": {"coordinates":[-91.19120599999999,29.994123],"type":"Point"}
}