{
  "type": "Feature",
  "properties": {
    "addr:full":"10527 S Mall Dr Baton Rouge LA 70809",
    "addr:housenumber":"10527",
    "addr:postcode":"70809",
    "addr:street":"S Mall Dr",
    "iso:country":"US",
    "sg:address":"10527 S Mall Dr",
    "sg:city":"Baton Rouge",
    "sg:classifiers":[
        {
            "category":"Shopping",
            "type":"Retail Goods"
        }
    ],
    "sg:phone":"+1 225 292 0479",
    "sg:postcode":"70809",
    "sg:province":"LA",
    "sg:tags":[
        "pet",
        "shop"
    ],
    "wof:name":"Petsmart",
    "wof:placetype":"venue"
},
  "geometry": {"coordinates":[-91.06442,30.376686],"type":"Point"}
}