{
  "type": "Feature",
  "properties": {
    "addr:full":"1953 Prospect Blvd Houma LA 70363",
    "addr:housenumber":"1953",
    "addr:postcode":"70363",
    "addr:street":"Prospect Blvd",
    "iso:country":"US",
    "sg:address":"1953 Prospect Blvd",
    "sg:city":"Houma",
    "sg:classifiers":[
        {
            "category":"Sports & Exercise",
            "subcategory":"Gym",
            "type":"Entertainment"
        }
    ],
    "sg:phone":"+1 985 873 0097",
    "sg:postcode":"70363",
    "sg:province":"LA",
    "sg:tags":[
        "club",
        "health",
        "studio",
        "gymnasium"
    ],
    "wof:name":"Body Elite Fitness Ctr East",
    "wof:placetype":"venue"
},
  "geometry": {"coordinates":[-90.68446400000001,29.582763],"type":"Point"}
}