{
  "type": "Feature",
  "properties": {
    "iso:country":"US",
    "sg:address":"2610 Washington St",
    "sg:city":"Monroe",
    "sg:classifiers":[
        {
            "category":"Insurance",
            "subcategory":"Insurance Agent",
            "type":"Services"
        }
    ],
    "sg:phone":"+1 318 322 7132",
    "sg:postcode":"71201",
    "sg:province":"LA",
    "wof:name":"Acclaim Insurance",
    "wof:placetype":"venue"
},
  "geometry": {"coordinates":[-92.09706799999999,32.520825],"type":"Point"}
}