{
  "type": "Feature",
  "properties": {
    "iso:country":"US",
    "sg:address":"40195 Macedonia Rd",
    "sg:city":"Hammond",
    "sg:classifiers":[
        {
            "category":"Wholesale",
            "subcategory":"Electrical",
            "type":"Manufacturing & Wholesale Goods"
        }
    ],
    "sg:phone":"+1 225 294 7297",
    "sg:postcode":"70403",
    "sg:province":"LA",
    "sg:tags":[
        "control",
        "security",
        "system"
    ],
    "wof:name":"Edwards Security",
    "wof:placetype":"venue"
},
  "geometry": {"coordinates":[-90.53559199999999,30.441074],"type":"Point"}
}