{
  "type": "Feature",
  "properties": {
    "addr:full":"3801 Hwy 70 Pierre Part LA 70339",
    "addr:housenumber":"3801",
    "addr:postcode":"70339",
    "addr:street":"Hwy 70 Pierre Part",
    "iso:country":"US",
    "sg:address":"3801 Hwy 70",
    "sg:city":"Pierre Part",
    "sg:classifiers":[
        {
            "category":"Shopping",
            "subcategory":"Gifts & Souvenirs",
            "type":"Retail Goods"
        }
    ],
    "sg:phone":"+1 985 252 8810",
    "sg:postcode":"70339",
    "sg:province":"LA",
    "sg:tags":[
        "shop"
    ],
    "wof:name":"Christina's Closet",
    "wof:placetype":"venue"
},
  "geometry": {"coordinates":[-91.21290500000001,29.94644],"type":"Point"}
}