{
  "type": "Feature",
  "properties": {
    "iso:country":"US",
    "sg:address":"1217 N Causeway Blvd",
    "sg:city":"Metairie",
    "sg:classifiers":[
        {
            "category":"Shopping",
            "subcategory":"Clothing, Apparel, & Fashions",
            "type":"Retail Goods"
        }
    ],
    "sg:phone":"+1 504 834 8990",
    "sg:postcode":"70001",
    "sg:province":"LA",
    "sg:tags":[
        "baby",
        "accessory"
    ],
    "wof:name":"Baby's Room Inc",
    "wof:placetype":"venue"
},
  "geometry": {"coordinates":[-90.155676,29.984303],"type":"Point"}
}