{
  "type": "Feature",
  "properties": {
    "addr:full":"318 N Court St Opelousas LA 70570",
    "addr:housenumber":"318",
    "addr:postcode":"70570",
    "addr:street":"N Court St",
    "iso:country":"US",
    "sg:address":"318 N Court St",
    "sg:city":"Opelousas",
    "sg:classifiers":[
        {
            "category":"Government",
            "subcategory":"Office",
            "type":"Public Place"
        }
    ],
    "sg:phone":"+1 337 948 2583",
    "sg:postcode":"70570",
    "sg:province":"LA",
    "sg:tags":[
        "village"
    ],
    "wof:name":"Opelousas Code Enforcement",
    "wof:placetype":"venue"
},
  "geometry": {"coordinates":[-92.082245,30.536889],"type":"Point"}
}