{
  "type": "Feature",
  "properties": {
    "addr:full":"7231 Mickens Rd Baton Rouge LA 70811",
    "addr:housenumber":"7231",
    "addr:postcode":"70811",
    "addr:street":"Mickens Rd",
    "iso:country":"US",
    "sg:address":"7231 Mickens Rd",
    "sg:city":"Baton Rouge",
    "sg:classifiers":[
        {
            "category":"Freight",
            "type":"Transportation"
        }
    ],
    "sg:phone":"+1 225 358 1502",
    "sg:postcode":"70811",
    "sg:province":"LA",
    "wof:name":"Latosh Co Transportation LLC",
    "wof:placetype":"venue"
},
  "geometry": {"coordinates":[-91.118696,30.517388],"type":"Point"}
}