{
  "type": "Feature",
  "properties": {
    "iso:country":"US",
    "sg:address":"18939 Saint Clare Ct",
    "sg:city":"Baton Rouge",
    "sg:classifiers":[
        {
            "category":"Professional",
            "subcategory":"Management & Consulting",
            "type":"Services"
        }
    ],
    "sg:phone":"+1 225 752 0134",
    "sg:postcode":"70810",
    "sg:province":"LA",
    "sg:tags":[
        "consultant"
    ],
    "wof:name":"Dick Lea & Assoc Inc",
    "wof:placetype":"venue"
},
  "geometry": {"coordinates":[-91.032932,30.340729],"type":"Point"}
}