{
  "type": "Feature",
  "properties": {
    "iso:country":"US",
    "sg:address":"287 Sligo Rd",
    "sg:city":"Bossier City",
    "sg:classifiers":[
        {
            "category":"Farming",
            "subcategory":"Livestock Farm",
            "type":"Manufacturing & Wholesale Goods"
        }
    ],
    "sg:phone":"+1 318 742 3541",
    "sg:postcode":"71112",
    "sg:province":"LA",
    "sg:tags":[
        "keeping",
        "supply",
        "sales",
        "bee",
        "honey",
        "production"
    ],
    "wof:name":"Hummer & Son Honey Farm",
    "wof:placetype":"venue"
},
  "geometry": {"coordinates":[-93.637694,32.439443],"type":"Point"}
}