{
  "type": "Feature",
  "properties": {
    "addr:full":"15525 Crossett Rd Bastrop LA 71220",
    "addr:housenumber":"15525",
    "addr:postcode":"71220",
    "addr:street":"Crossett Rd",
    "iso:country":"US",
    "sg:address":"15525 Crossett Rd",
    "sg:city":"Bastrop",
    "sg:classifiers":[
        {
            "category":"Utilities",
            "subcategory":"Water",
            "type":"Services"
        }
    ],
    "sg:phone":"+1 318 281 0057",
    "sg:postcode":"71220",
    "sg:province":"LA",
    "sg:tags":[
        "company-utility",
        "system",
        "supply"
    ],
    "wof:name":"Beekman Water Systems",
    "wof:placetype":"venue"
},
  "geometry": {"coordinates":[-91.885419,32.923413],"type":"Point"}
}