{
  "type": "Feature",
  "properties": {
    "iso:country":"US",
    "sg:address":"4948 Chef Menteur Hwy",
    "sg:city":"New Orleans",
    "sg:classifiers":[
        {
            "category":"Building & Trades",
            "subcategory":"Pest Control",
            "type":"Services"
        }
    ],
    "sg:phone":"+1 504 949 7378",
    "sg:postcode":"70126",
    "sg:province":"LA",
    "wof:name":"Rodent Guard Pest Extrmntn",
    "wof:placetype":"venue"
},
  "geometry": {"coordinates":[-90.031643,30.00698],"type":"Point"}
}