{
  "type": "Feature",
  "properties": {
    "iso:country":"US",
    "sg:address":"1031 Parker Rd",
    "sg:city":"Sondheimer",
    "sg:classifiers":[
        {
            "category":"Real Estate",
            "subcategory":"Surveying",
            "type":"Services"
        }
    ],
    "sg:phone":"+1 318 552 6368",
    "sg:postcode":"71202",
    "sg:province":"LA",
    "wof:name":"Precision Land Leveling Co",
    "wof:placetype":"venue"
},
  "geometry": {"coordinates":[-92.042749,32.485125],"type":"Point"}
}