{
  "type": "Feature",
  "properties": {
    "addr:full":"757 Professional Dr N Shreveport LA 71105",
    "addr:housenumber":"757",
    "addr:postcode":"71105",
    "addr:street":"Professional Dr N",
    "iso:country":"US",
    "sg:address":"757 Professional Dr N",
    "sg:city":"Shreveport",
    "sg:classifiers":[
        {
            "category":"Building & Trades",
            "subcategory":"Construction",
            "type":"Services"
        }
    ],
    "sg:phone":"+1 318 795 0845",
    "sg:postcode":"71105",
    "sg:province":"LA",
    "sg:tags":[
        "general",
        "contractor"
    ],
    "wof:name":"Smith Martin Builders Inc",
    "wof:placetype":"venue"
},
  "geometry": {"coordinates":[-93.725543,32.414444],"type":"Point"}
}