{
  "type": "Feature",
  "properties": {
    "iso:country":"US",
    "sg:address":"801 E University Ave",
    "sg:city":"Lafayette",
    "sg:classifiers":[
        {
            "category":"Building & Trades",
            "subcategory":"Construction",
            "type":"Services"
        }
    ],
    "sg:phone":"+1 337 233 9716",
    "sg:postcode":"70503",
    "sg:province":"LA",
    "sg:tags":[
        "general",
        "contractor"
    ],
    "wof:name":"Gomez Design Group",
    "wof:placetype":"venue"
},
  "geometry": {"coordinates":[-92.01156400000001,30.211757],"type":"Point"}
}