{
  "type": "Feature",
  "properties": {
    "iso:country":"US",
    "sg:address":"3330 Barksdale Blvd",
    "sg:city":"Bossier City",
    "sg:classifiers":[
        {
            "category":"Health Services",
            "subcategory":"Doctor",
            "type":"Services"
        }
    ],
    "sg:phone":"+1 318 742 4700",
    "sg:postcode":"71112",
    "sg:province":"LA",
    "sg:tags":[
        "dentist"
    ],
    "wof:name":"Robert K Hill DDS",
    "wof:placetype":"venue"
},
  "geometry": {"coordinates":[-93.68629900000001,32.491663],"type":"Point"}
}