{
  "type": "Feature",
  "properties": {
    "iso:country":"US",
    "sg:address":"941 Austin Rd",
    "sg:city":"Youngsville",
    "sg:classifiers":[
        {
            "category":"Building & Trades",
            "subcategory":"Landscaping Services",
            "type":"Services"
        }
    ],
    "sg:phone":"+1 337 856 2181",
    "sg:postcode":"70592",
    "sg:province":"LA",
    "wof:name":"Ryan Lopez Lawn Services",
    "wof:placetype":"venue"
},
  "geometry": {"coordinates":[-91.98148,30.042339],"type":"Point"}
}