{
  "type": "Feature",
  "properties": {
    "addr:full":"15668 Fischers Ln Ponchatoula LA 70454",
    "addr:postcode":"15668;70454",
    "addr:street":"Fischers Ln",
    "iso:country":"US",
    "sg:address":"15668 Fischers Ln",
    "sg:city":"Ponchatoula",
    "sg:classifiers":[
        {
            "category":"Organizations",
            "subcategory":"Religious Organization",
            "type":"Services"
        }
    ],
    "sg:phone":"+1 985 386 8685",
    "sg:postcode":"70454",
    "sg:province":"LA",
    "sg:tags":[
        "church"
    ],
    "wof:name":"First United Pentecostal Chr",
    "wof:placetype":"venue"
},
  "geometry": {"coordinates":[-90.460877,30.442744],"type":"Point"}
}