{
  "type": "Feature",
  "properties": {
    "iso:country":"US",
    "sg:address":"5918 Elysian Fields Ave",
    "sg:city":"New Orleans",
    "sg:classifiers":[
        {
            "category":"Real Estate",
            "subcategory":"Real Estate Agent",
            "type":"Services"
        }
    ],
    "sg:phone":"+1 504 282 1030",
    "sg:postcode":"70122",
    "sg:province":"LA",
    "wof:name":"Irving & Assoc",
    "wof:placetype":"venue"
},
  "geometry": {"coordinates":[-90.061047,30.01887],"type":"Point"}
}