{
  "type": "Feature",
  "properties": {
    "iso:country":"US",
    "sg:address":"3328 Bienville St",
    "sg:city":"New Orleans",
    "sg:classifiers":[
        {
            "category":"Professional",
            "type":"Services"
        }
    ],
    "sg:phone":"+1 504 827 9998",
    "sg:postcode":"70119",
    "sg:province":"LA",
    "wof:name":"Pudd Inc",
    "wof:placetype":"venue"
},
  "geometry": {"coordinates":[-90.092122,29.971401],"type":"Point"}
}