{
  "type": "Feature",
  "properties": {
    "iso:country":"US",
    "sg:address":"2114 Paris Rd",
    "sg:city":"Chalmette",
    "sg:classifiers":[
        {
            "category":"Social Services",
            "subcategory":"Child Care",
            "type":"Services"
        }
    ],
    "sg:phone":"+1 504 277 7790",
    "sg:postcode":"70043",
    "sg:province":"LA",
    "wof:name":"Children's Academy",
    "wof:placetype":"venue"
},
  "geometry": {"coordinates":[-89.965616,29.938547],"type":"Point"}
}