{
  "type": "Feature",
  "properties": {
    "addr:full":"4824 Cleveland Ave New Orleans LA 70119",
    "addr:housenumber":"4824",
    "addr:postcode":"70119",
    "addr:street":"Cleveland Ave",
    "iso:country":"US",
    "sg:address":"4824 Cleveland Ave",
    "sg:city":"New Orleans",
    "sg:classifiers":[
        {
            "category":"Professional",
            "subcategory":"Computer Services",
            "type":"Services"
        }
    ],
    "sg:phone":"+1 504 780 2946",
    "sg:postcode":"70119",
    "sg:province":"LA",
    "wof:name":"Baseline Technologies",
    "wof:placetype":"venue"
},
  "geometry": {"coordinates":[-90.10911400000001,29.978711],"type":"Point"}
}