{
  "type": "Feature",
  "properties": {
    "iso:country":"US",
    "sg:address":"1014 Pierremont Rd",
    "sg:city":"Shreveport",
    "sg:classifiers":[
        {
            "category":"Professional",
            "type":"Services"
        }
    ],
    "sg:phone":"+1 318 868 6041",
    "sg:postcode":"71106",
    "sg:province":"LA",
    "sg:tags":[
        "establishment"
    ],
    "wof:name":"J & E Sales",
    "wof:placetype":"venue"
},
  "geometry": {"coordinates":[-93.751062,32.454805],"type":"Point"}
}