{
  "type": "Feature",
  "properties": {
    "iso:country":"US",
    "sg:address":"932 Mulberry St",
    "sg:city":"Westlake",
    "sg:classifiers":[
        {
            "category":"Organizations",
            "subcategory":"Religious Organization",
            "type":"Services"
        }
    ],
    "sg:phone":"+1 337 439 8388",
    "sg:postcode":"70669",
    "sg:province":"LA",
    "sg:tags":[
        "church"
    ],
    "wof:name":"Pentecostals Of Westlake",
    "wof:placetype":"venue"
},
  "geometry": {"coordinates":[-93.260577,30.253248],"type":"Point"}
}