{
  "type": "Feature",
  "properties": {
    "iso:country":"US",
    "sg:address":"5451 W 70th St",
    "sg:city":"Shreveport",
    "sg:classifiers":[
        {
            "category":"Education",
            "subcategory":"Dance Studio",
            "type":"Public Place"
        }
    ],
    "sg:phone":"+1 318 629 1138",
    "sg:postcode":"71129",
    "sg:province":"LA",
    "sg:tags":[
        "instruction",
        "dancing"
    ],
    "wof:name":"Rhema Word Sch-Worship Dance",
    "wof:placetype":"venue"
},
  "geometry": {"coordinates":[-93.843711,32.441999],"type":"Point"}
}