{
  "type": "Feature",
  "properties": {
    "iso:country":"US",
    "sg:address":"20 Memory Ln",
    "sg:city":"West Monroe",
    "sg:classifiers":[
        {
            "category":"Building & Trades",
            "subcategory":"Cleaning & Sanitation",
            "type":"Services"
        }
    ],
    "sg:phone":"+1 318 396 6489",
    "sg:postcode":"71291",
    "sg:province":"LA",
    "sg:tags":[
        "maintenance"
    ],
    "wof:name":"Morris Cleaning Service",
    "wof:placetype":"venue"
},
  "geometry": {"coordinates":[-92.18025,32.534552],"type":"Point"}
}