{
  "type": "Feature",
  "properties": {
    "addr:full":"701 E 4th St Dequincy LA 70633",
    "addr:housenumber":"701",
    "addr:postcode":"70633",
    "addr:street":"E 4Th St",
    "iso:country":"US",
    "sg:address":"701 E 4th St",
    "sg:city":"Dequincy",
    "sg:classifiers":[
        {
            "category":"Banks & Credit Unions",
            "subcategory":"Bank",
            "type":"Services"
        }
    ],
    "sg:phone":"+1 337 786 7922",
    "sg:postcode":"70633",
    "sg:province":"LA",
    "sg:tags":[
        "loan",
        "broker",
        "financing"
    ],
    "wof:name":"Cinco Financial Services Inc",
    "wof:placetype":"venue"
},
  "geometry": {"coordinates":[-93.42853100000001,30.450971],"type":"Point"}
}