{
  "type": "Feature",
  "properties": {
    "addr:full":"165 Chevron Rd Golden Meadow LA 70357",
    "addr:housenumber":"165",
    "addr:postcode":"70357",
    "addr:street":"Chevron Rd;Meadow",
    "iso:country":"US",
    "sg:address":"165 Chevron Rd",
    "sg:city":"Golden Meadow",
    "sg:classifiers":[
        {
            "category":"Wholesale",
            "subcategory":"Petroleum",
            "type":"Manufacturing & Wholesale Goods"
        }
    ],
    "sg:phone":"+1 504 592 7713",
    "sg:postcode":"70357",
    "sg:province":"LA",
    "sg:tags":[
        "pipe",
        "line",
        "company"
    ],
    "wof:name":"Chevron Pipeline Co",
    "wof:placetype":"venue"
},
  "geometry": {"coordinates":[-90.18861,29.106197],"type":"Point"}
}