{
  "type": "Feature",
  "properties": {
    "iso:country":"US",
    "sg:address":"2016 Clearview Pkwy",
    "sg:city":"Metairie",
    "sg:classifiers":[
        {
            "category":"Personal",
            "subcategory":"Beauty Salon",
            "type":"Services"
        }
    ],
    "sg:phone":"+1 504 455 1517",
    "sg:postcode":"70001",
    "sg:province":"LA",
    "wof:name":"Salon Bella",
    "wof:placetype":"venue"
},
  "geometry": {"coordinates":[-90.18133899999999,29.991168],"type":"Point"}
}