{
  "type": "Feature",
  "properties": {
    "iso:country":"US",
    "sg:address":"801 Brindley Rd",
    "sg:city":"Oakdale",
    "sg:classifiers":[
        {
            "category":"Government",
            "subcategory":"Police Station",
            "type":"Public Place"
        }
    ],
    "sg:phone":"+1 318 335 0534",
    "sg:postcode":"71463",
    "sg:province":"LA",
    "sg:tags":[
        "protection"
    ],
    "wof:name":"Sheriffs Office",
    "wof:placetype":"venue"
},
  "geometry": {"coordinates":[-92.658674,30.805758],"type":"Point"}
}