{
  "type": "Feature",
  "properties": {
    "iso:country":"US",
    "sg:address":"5901 Main St",
    "sg:city":"Zachary",
    "sg:classifiers":[
        {
            "category":"Shopping",
            "subcategory":"Department Store",
            "type":"Retail Goods"
        }
    ],
    "sg:phone":"+1 225 654 0313",
    "sg:postcode":"70791",
    "sg:province":"LA",
    "sg:website":"www.walmart.com",
    "wof:name":"Wal-Mart Supercenter",
    "wof:placetype":"venue"
},
  "geometry": {"coordinates":[-91.141946,30.649],"type":"Point"}
}