{
  "type": "Feature",
  "properties": {
    "addr:full":"1737 W Sale Rd Lake Charles LA 70605",
    "addr:housenumber":"1737",
    "addr:postcode":"70605",
    "addr:street":"W Sale Rd",
    "iso:country":"US",
    "sg:address":"1737 W Sale Rd",
    "sg:city":"Lake Charles",
    "sg:classifiers":[
        {
            "category":"Restaurant",
            "type":"Food & Drink"
        }
    ],
    "sg:phone":"+1 337 477 9033",
    "sg:postcode":"70605",
    "sg:province":"LA",
    "wof:name":"Big Daddy's Sports Grill",
    "wof:placetype":"venue"
},
  "geometry": {"coordinates":[-93.2486,30.183555],"type":"Point"}
}