{
  "type": "Feature",
  "properties": {
    "iso:country":"US",
    "sg:address":"17397 Tiger Rd",
    "sg:city":"Prairieville",
    "sg:classifiers":[
        {
            "category":"Social Services",
            "type":"Services"
        }
    ],
    "sg:phone":"+1 225 622 1017",
    "sg:postcode":"70769",
    "sg:province":"LA",
    "wof:name":"Lorraine F Landry Med LPC",
    "wof:placetype":"venue"
},
  "geometry": {"coordinates":[-90.89766,30.32381],"type":"Point"}
}