{
  "type": "Feature",
  "properties": {
    "iso:country":"US",
    "sg:address":"2134 Hwy 308",
    "sg:city":"Raceland",
    "sg:classifiers":[
        {
            "category":"Education",
            "subcategory":"School",
            "type":"Public Place"
        }
    ],
    "sg:phone":"+1 985 446 0947",
    "sg:postcode":"70394",
    "sg:province":"LA",
    "wof:name":"Top North Even Start",
    "wof:placetype":"venue"
},
  "geometry": {"coordinates":[-90.712057,29.751386],"type":"Point"}
}