{
  "type": "Feature",
  "properties": {
    "addr:full":"918 Virgil St Gretna LA 70053",
    "addr:housenumber":"918",
    "addr:postcode":"70053",
    "addr:street":"Virgil St",
    "iso:country":"US",
    "sg:address":"918 Virgil St",
    "sg:city":"Gretna",
    "sg:classifiers":[
        {
            "category":"Banks & Credit Unions",
            "subcategory":"Bank",
            "type":"Services"
        }
    ],
    "sg:phone":"+1 504 368 1533",
    "sg:postcode":"70053",
    "sg:province":"LA",
    "sg:tags":[
        "cashing",
        "check"
    ],
    "wof:name":"Cash Flow Management",
    "wof:placetype":"venue"
},
  "geometry": {"coordinates":[-90.04817799999999,29.926239],"type":"Point"}
}