{
  "type": "Feature",
  "properties": {
    "addr:full":"107 Fairway Dr La Place LA 70068",
    "addr:housenumber":"107",
    "addr:postcode":"70068",
    "addr:street":"Fairway Dr La Place",
    "iso:country":"US",
    "sg:address":"107 Fairway Dr",
    "sg:city":"La Place",
    "sg:classifiers":[
        {
            "category":"Real Estate",
            "subcategory":"Real Estate Agent",
            "type":"Services"
        }
    ],
    "sg:phone":"+1 985 651 3007",
    "sg:postcode":"70068",
    "sg:province":"LA",
    "sg:website":"www.landcrafthomes.com",
    "wof:name":"Landcraft Inc",
    "wof:placetype":"venue"
},
  "geometry": {"coordinates":[-90.497134,30.085725],"type":"Point"}
}