{
  "type": "Feature",
  "properties": {
    "iso:country":"US",
    "sg:address":"8710 State Rte 23",
    "sg:city":"Belle Chasse",
    "sg:classifiers":[
        {
            "category":"Government",
            "subcategory":"Post Office",
            "type":"Public Place"
        }
    ],
    "sg:phone":"+1 504 000 1111",
    "sg:postcode":"70037",
    "sg:province":"LA",
    "wof:name":"US Post Office",
    "wof:placetype":"venue"
},
  "geometry": {"coordinates":[-89.992192,29.847155],"type":"Point"}
}