{
  "type": "Feature",
  "properties": {
    "addr:full":"619 Homer Rd Minden LA 71055",
    "addr:housenumber":"619",
    "addr:postcode":"71055",
    "addr:street":"Homer Rd",
    "iso:country":"US",
    "sg:address":"619 Homer Rd",
    "sg:city":"Minden",
    "sg:classifiers":[
        {
            "category":"Professional",
            "subcategory":"Accounting & Tax Preparation",
            "type":"Services"
        }
    ],
    "sg:phone":"+1 318 377 6129",
    "sg:postcode":"71055",
    "sg:province":"LA",
    "sg:tags":[
        "return",
        "filing"
    ],
    "wof:name":"H & R Block Tax Svc",
    "wof:placetype":"venue"
},
  "geometry": {"coordinates":[-93.269446,32.621479],"type":"Point"}
}