{
  "type": "Feature",
  "properties": {
    "iso:country":"US",
    "sg:address":"11575 Sullivan Rd",
    "sg:city":"Baton Rouge",
    "sg:classifiers":[
        {
            "category":"Retail",
            "subcategory":"Auto Repair",
            "type":"Services"
        }
    ],
    "sg:phone":"+1 225 261 9558",
    "sg:postcode":"70818",
    "sg:province":"LA",
    "sg:tags":[
        "repairing",
        "automobile"
    ],
    "wof:name":"B P Full Svc Station",
    "wof:placetype":"venue"
},
  "geometry": {"coordinates":[-91.03876,30.556708],"type":"Point"}
}