{
  "type": "Feature",
  "properties": {
    "iso:country":"US",
    "sg:address":"603 Center St",
    "sg:city":"New Iberia",
    "sg:classifiers":[
        {
            "category":"Government",
            "subcategory":"Office",
            "type":"Public Place"
        }
    ],
    "sg:phone":"+1 337 364 5948",
    "sg:postcode":"70560",
    "sg:province":"LA",
    "wof:name":"Iberia Jtpa OFFICE",
    "wof:placetype":"venue"
},
  "geometry": {"coordinates":[-91.821332,29.999303],"type":"Point"}
}