{
  "type": "Feature",
  "properties": {
    "iso:country":"US",
    "sg:address":"100 Downs St",
    "sg:city":"New Orleans",
    "sg:classifiers":[
        {
            "category":"Building & Trades",
            "subcategory":"Cleaning & Sanitation",
            "type":"Services"
        }
    ],
    "sg:phone":"+1 985 845 4440",
    "sg:postcode":"70124",
    "sg:province":"LA",
    "sg:tags":[
        "janitor"
    ],
    "wof:name":"Art's Professional Janitoral",
    "wof:placetype":"venue"
},
  "geometry": {"coordinates":[-90.112861,30.015556],"type":"Point"}
}