{
  "type": "Feature",
  "properties": {
    "addr:full":"551 Sligo Rd Bossier City LA 71112",
    "addr:housenumber":"551",
    "addr:postcode":"71112",
    "addr:street":"Sligo Rd",
    "iso:country":"US",
    "sg:address":"551 Sligo Rd",
    "sg:city":"Bossier City",
    "sg:classifiers":[
        {
            "category":"Building & Trades",
            "subcategory":"Construction",
            "type":"Services"
        }
    ],
    "sg:phone":"+1 318 747 3140",
    "sg:postcode":"71112",
    "sg:province":"LA",
    "sg:tags":[
        "paving",
        "contractor"
    ],
    "wof:name":"Dale's Paving Inc",
    "wof:placetype":"venue"
},
  "geometry": {"coordinates":[-93.63113300000001,32.439036],"type":"Point"}
}