{
  "type": "Feature",
  "properties": {
    "addr:full":"1005 Veterans Memorial Blvd Kenner LA 70062",
    "addr:housenumber":"1005",
    "addr:postcode":"70062",
    "addr:street":"Veterans Memorial Blvd",
    "iso:country":"US",
    "sg:address":"1005 Veterans Memorial Blvd",
    "sg:city":"Kenner",
    "sg:classifiers":[
        {
            "category":"Professional",
            "subcategory":"Credit Reporting & Collection",
            "type":"Services"
        }
    ],
    "sg:phone":"+1 504 467 5116",
    "sg:postcode":"70062",
    "sg:province":"LA",
    "sg:tags":[
        "agency"
    ],
    "wof:name":"Morgan Stone & Assoc",
    "wof:placetype":"venue"
},
  "geometry": {"coordinates":[-90.254015,30.006316],"type":"Point"}
}