{
  "type": "Feature",
  "properties": {
    "addr:full":"400 S Capitol St Many LA 71449",
    "addr:housenumber":"400",
    "addr:postcode":"71449",
    "addr:street":"S Capitol St",
    "iso:country":"US",
    "sg:address":"400 S Capitol St",
    "sg:city":"Many",
    "sg:classifiers":[
        {
            "category":"Government",
            "subcategory":"Office",
            "type":"Public Place"
        }
    ],
    "sg:phone":"+1 318 256 2675",
    "sg:postcode":"71449",
    "sg:province":"LA",
    "sg:tags":[
        "civil",
        "defense",
        "agency"
    ],
    "wof:name":"Civil Defense",
    "wof:placetype":"venue"
},
  "geometry": {"coordinates":[-93.48417999999999,31.56719],"type":"Point"}
}