{
  "type": "Feature",
  "properties": {
    "iso:country":"US",
    "sg:address":"365 Canal St",
    "sg:city":"New Orleans",
    "sg:classifiers":[
        {
            "category":"Professional",
            "subcategory":"Lawyer & Legal Services",
            "type":"Services"
        }
    ],
    "sg:phone":"+1 504 212 8820",
    "sg:postcode":"70130",
    "sg:province":"LA",
    "wof:name":"Maestri Rachel A",
    "wof:placetype":"venue"
},
  "geometry": {"coordinates":[-90.065708,29.951212],"type":"Point"}
}