{
  "type": "Feature",
  "properties": {
    "addr:full":"2224 20th St Lake Charles LA 70601",
    "addr:housenumber":"2224",
    "addr:postcode":"70601",
    "addr:street":"20Th St",
    "iso:country":"US",
    "sg:address":"2224 20th St",
    "sg:city":"Lake Charles",
    "sg:classifiers":[
        {
            "category":"Arts & Performance",
            "subcategory":"Theater",
            "type":"Entertainment"
        }
    ],
    "sg:phone":"+1 337 478 3578",
    "sg:postcode":"70601",
    "sg:province":"LA",
    "sg:tags":[
        "group"
    ],
    "wof:name":"Donna P Vanchiere",
    "wof:placetype":"venue"
},
  "geometry": {"coordinates":[-93.185576,30.202211],"type":"Point"}
}