{
  "type": "Feature",
  "properties": {
    "iso:country":"US",
    "sg:address":"100 Mississippi St",
    "sg:city":"Donaldsonville",
    "sg:classifiers":[
        {
            "category":"Utilities",
            "subcategory":"Water",
            "type":"Services"
        }
    ],
    "sg:phone":"+1 225 473 7539",
    "sg:postcode":"70346",
    "sg:province":"LA",
    "sg:tags":[
        "system",
        "supply"
    ],
    "wof:name":"Bayou Lafourche Fresh Water",
    "wof:placetype":"venue"
},
  "geometry": {"coordinates":[-90.990323,30.107539],"type":"Point"}
}