{
  "type": "Feature",
  "properties": {
    "addr:full":"608 W Court St Winnfield LA 71483",
    "addr:housenumber":"608",
    "addr:postcode":"71483",
    "addr:street":"W Court St",
    "iso:country":"US",
    "sg:address":"608 W Court St",
    "sg:city":"Winnfield",
    "sg:classifiers":[
        {
            "category":"Food & Beverages",
            "subcategory":"Groceries & Convenience Stores",
            "type":"Retail Goods"
        }
    ],
    "sg:phone":"+1 318 628 4568",
    "sg:postcode":"71483",
    "sg:province":"LA",
    "wof:name":"E Z Mart Stores",
    "wof:placetype":"venue"
},
  "geometry": {"coordinates":[-92.64745600000001,31.925927],"type":"Point"}
}