{
  "type": "Feature",
  "properties": {
    "iso:country":"US",
    "sg:address":"1095 San Antonio Ave",
    "sg:city":"Many",
    "sg:classifiers":[
        {
            "category":"Autos & Motor Vehicles",
            "subcategory":"Automobile Sales",
            "type":"Retail Goods"
        }
    ],
    "sg:phone":"+1 318 256 2066",
    "sg:postcode":"71449",
    "sg:province":"LA",
    "sg:tags":[
        "car",
        "dealer"
    ],
    "sg:website":"www.foymotors.com",
    "wof:name":"Julian Foy Motors Inc",
    "wof:placetype":"venue"
},
  "geometry": {"coordinates":[-93.480048,31.568777],"type":"Point"}
}