{
  "type": "Feature",
  "properties": {
    "iso:country":"US",
    "sg:address":"606 E Prien Lake Rd",
    "sg:city":"Lake Charles",
    "sg:classifiers":[
        {
            "category":"Shopping",
            "subcategory":"Computers & Home Electronics",
            "type":"Retail Goods"
        }
    ],
    "sg:phone":"+1 337 474 2675",
    "sg:postcode":"70601",
    "sg:province":"LA",
    "sg:tags":[
        "audio"
    ],
    "wof:name":"Jay's Audio",
    "wof:placetype":"venue"
},
  "geometry": {"coordinates":[-93.21404,30.198268],"type":"Point"}
}