{
  "type": "Feature",
  "properties": {
    "addr:full":"438 Airport Rd Galliano LA 70354",
    "addr:housenumber":"438",
    "addr:postcode":"70354",
    "addr:street":"Airport Rd",
    "iso:country":"US",
    "sg:address":"438 Airport Rd",
    "sg:city":"Galliano",
    "sg:classifiers":[
        {
            "category":"Government",
            "subcategory":"Office",
            "type":"Public Place"
        }
    ],
    "sg:phone":"+1 985 475 5280",
    "sg:postcode":"70354",
    "sg:province":"LA",
    "sg:tags":[
        "federal"
    ],
    "wof:name":"Natural Resources Conservation",
    "wof:placetype":"venue"
},
  "geometry": {"coordinates":[-90.272154,29.433493],"type":"Point"}
}