{
  "type": "Feature",
  "properties": {
    "iso:country":"US",
    "sg:address":"610 Haynes Ave",
    "sg:city":"Shreveport",
    "sg:classifiers":[
        {
            "category":"Organizations",
            "subcategory":"Religious Organization",
            "type":"Services"
        }
    ],
    "sg:phone":"+1 318 865 2307",
    "sg:postcode":"71105",
    "sg:province":"LA",
    "sg:tags":[
        "church"
    ],
    "wof:name":"Haynes Avenue Baptist Church",
    "wof:placetype":"venue"
},
  "geometry": {"coordinates":[-93.700535,32.457124],"type":"Point"}
}