{
  "type": "Feature",
  "properties": {
    "iso:country":"US",
    "sg:address":"7722 Office Park Blvd",
    "sg:city":"Baton Rouge",
    "sg:classifiers":[
        {
            "category":"Government",
            "subcategory":"Office",
            "type":"Public Place"
        }
    ],
    "sg:phone":"+1 225 929 7411",
    "sg:postcode":"70809",
    "sg:province":"LA",
    "sg:tags":[
        "state",
        "resource"
    ],
    "sg:website":"www.lampers.org",
    "wof:name":"Retirement Systems",
    "wof:placetype":"venue"
},
  "geometry": {"coordinates":[-91.103407,30.41905],"type":"Point"}
}