{
  "type": "Feature",
  "properties": {
    "iso:country":"US",
    "sg:address":"9150 Bereford Dr",
    "sg:city":"Baton Rouge",
    "sg:classifiers":[
        {
            "category":"Education",
            "subcategory":"School",
            "type":"Public Place"
        }
    ],
    "sg:phone":"+1 225 923 2068",
    "sg:postcode":"70809",
    "sg:province":"LA",
    "sg:website":"www.brighton-academy.org",
    "wof:name":"Brighton Academy",
    "wof:placetype":"venue"
},
  "geometry": {"coordinates":[-91.081857,30.417899],"type":"Point"}
}