{
  "type": "Feature",
  "properties": {
    "addr:full":"217 N Broad St New Orleans LA 70119",
    "addr:housenumber":"217",
    "addr:postcode":"70119",
    "addr:street":"N Broad St",
    "iso:country":"US",
    "sg:address":"217 N Broad St",
    "sg:city":"New Orleans",
    "sg:classifiers":[
        {
            "category":"Food & Beverages",
            "subcategory":"Groceries & Convenience Stores",
            "type":"Retail Goods"
        }
    ],
    "sg:phone":"+1 504 822 1030",
    "sg:postcode":"70119",
    "sg:province":"LA",
    "wof:name":"E Z Discount Store",
    "wof:placetype":"venue"
},
  "geometry": {"coordinates":[-90.08609,29.967251],"type":"Point"}
}