{
  "type": "Feature",
  "properties": {
    "iso:country":"US",
    "sg:address":"144 E Washington St",
    "sg:city":"Shreveport",
    "sg:classifiers":[
        {
            "category":"Organizations",
            "subcategory":"Community Association",
            "type":"Services"
        }
    ],
    "sg:phone":"+1 318 868 5360",
    "sg:postcode":"71104",
    "sg:province":"LA",
    "sg:tags":[
        "fraternal"
    ],
    "wof:name":"Kappa Sigma Fraternity",
    "wof:placetype":"venue"
},
  "geometry": {"coordinates":[-93.728753,32.484896],"type":"Point"}
}