{
  "type": "Feature",
  "properties": {
    "addr:full":"8201 Tennis Court Ln Shreveport LA 71106",
    "addr:housenumber":"8201",
    "addr:postcode":"71106",
    "addr:street":"Tennis Court Ln",
    "iso:country":"US",
    "sg:address":"8201 Tennis Court Ln",
    "sg:city":"Shreveport",
    "sg:classifiers":[
        {
            "category":"Recreation",
            "type":"Entertainment"
        }
    ],
    "sg:phone":"+1 318 869 3303",
    "sg:postcode":"71106",
    "sg:province":"LA",
    "sg:tags":[
        "tennis",
        "court"
    ],
    "wof:name":"Racket Club Indoors",
    "wof:placetype":"venue"
},
  "geometry": {"coordinates":[-93.73942700000001,32.430892],"type":"Point"}
}