{
  "type": "Feature",
  "properties": {
    "addr:full":"232 W Prien Lake Rd Lake Charles LA 70601",
    "addr:housenumber":"232",
    "addr:postcode":"70601",
    "addr:street":"W Prien Lake Rd",
    "iso:country":"US",
    "sg:address":"232 W Prien Lake Rd",
    "sg:city":"Lake Charles",
    "sg:classifiers":[
        {
            "category":"Professional",
            "type":"Services"
        }
    ],
    "sg:phone":"+1 337 477 7935",
    "sg:postcode":"70601",
    "sg:province":"LA",
    "wof:name":"Manpower Temporary Svc",
    "wof:placetype":"venue"
},
  "geometry": {"coordinates":[-93.221287,30.198183],"type":"Point"}
}