{
  "type": "Feature",
  "properties": {
    "addr:full":"2631 Donahue Ferry Rd Pineville LA 71360",
    "addr:housenumber":"2631",
    "addr:postcode":"71360",
    "addr:street":"Donahue Ferry Rd",
    "iso:country":"US",
    "sg:address":"2631 Donahue Ferry Rd",
    "sg:city":"Pineville",
    "sg:classifiers":[
        {
            "category":"Health Services",
            "subcategory":"Health Practitioner",
            "type":"Services"
        }
    ],
    "sg:phone":"+1 318 641 0800",
    "sg:postcode":"71360",
    "sg:province":"LA",
    "sg:tags":[
        "psychologist"
    ],
    "wof:name":"Consulting Psychologists Inc",
    "wof:placetype":"venue"
},
  "geometry": {"coordinates":[-92.404332,31.350239],"type":"Point"}
}