{
  "type": "Feature",
  "properties": {
    "iso:country":"US",
    "sg:address":"2500 Scenic Hwy",
    "sg:city":"Baton Rouge",
    "sg:classifiers":[
        {
            "category":"Food & Beverages",
            "subcategory":"Meat & Fish",
            "type":"Retail Goods"
        }
    ],
    "sg:phone":"+1 225 356 6377",
    "sg:postcode":"70805",
    "sg:province":"LA",
    "sg:tags":[
        "seafood"
    ],
    "wof:name":"V's Cafe & Seafood Market Inc",
    "wof:placetype":"venue"
},
  "geometry": {"coordinates":[-91.16825,30.471078],"type":"Point"}
}