{
  "type": "Feature",
  "properties": {
    "iso:country":"US",
    "sg:address":"129 Freestate Blvd",
    "sg:city":"Shreveport",
    "sg:classifiers":[
        {
            "category":"Wholesale",
            "subcategory":"Machinery & Supplies",
            "type":"Manufacturing & Wholesale Goods"
        }
    ],
    "sg:phone":"+1 318 424 7860",
    "sg:postcode":"71107",
    "sg:province":"LA",
    "sg:tags":[
        "equipment"
    ],
    "wof:name":"Harbison Fischer Mfg Co",
    "wof:placetype":"venue"
},
  "geometry": {"coordinates":[-93.765039,32.537237],"type":"Point"}
}