{
  "type": "Feature",
  "properties": {
    "iso:country":"US",
    "sg:address":"6892 Hooper Rd",
    "sg:city":"Baton Rouge",
    "sg:classifiers":[
        {
            "category":"Organizations",
            "subcategory":"Religious Organization",
            "type":"Services"
        }
    ],
    "sg:phone":"+1 225 357 0205",
    "sg:postcode":"70811",
    "sg:province":"LA",
    "sg:tags":[
        "church"
    ],
    "wof:name":"Apostolic Christian Temple",
    "wof:placetype":"venue"
},
  "geometry": {"coordinates":[-91.11097100000001,30.52848],"type":"Point"}
}