{
  "type": "Feature",
  "properties": {
    "iso:country":"US",
    "sg:address":"2500 E Simcoe St",
    "sg:city":"Lafayette",
    "sg:classifiers":[
        {
            "category":"Health Services",
            "subcategory":"Nursing And Care Facility",
            "type":"Services"
        }
    ],
    "sg:phone":"+1 337 233 7115",
    "sg:postcode":"70501",
    "sg:province":"LA",
    "sg:tags":[
        "home",
        "convalescent"
    ],
    "wof:name":"River Oaks Retirement Manor",
    "wof:placetype":"venue"
},
  "geometry": {"coordinates":[-91.990166,30.222572],"type":"Point"}
}