{
  "type": "Feature",
  "properties": {
    "addr:full":"9504 Mansfield Rd Shreveport LA 71118",
    "addr:housenumber":"9504",
    "addr:postcode":"71118",
    "addr:street":"Mansfield Rd",
    "iso:country":"US",
    "sg:address":"9504 Mansfield Rd",
    "sg:city":"Shreveport",
    "sg:classifiers":[
        {
            "category":"Wholesale",
            "subcategory":"Construction Materials",
            "type":"Manufacturing & Wholesale Goods"
        }
    ],
    "sg:phone":"+1 318 686 0707",
    "sg:postcode":"71118",
    "sg:province":"LA",
    "sg:tags":[
        "fencing",
        "supply"
    ],
    "wof:name":"Berry Sales",
    "wof:placetype":"venue"
},
  "geometry": {"coordinates":[-93.817117,32.386208],"type":"Point"}
}