{
  "type": "Feature",
  "properties": {
    "addr:full":"409 Legardeur Dr Slidell LA 70460",
    "addr:housenumber":"409",
    "addr:postcode":"70460",
    "addr:street":"Legardeur Dr",
    "iso:country":"US",
    "sg:address":"409 Legardeur Dr",
    "sg:city":"Slidell",
    "sg:classifiers":[
        {
            "category":"Wholesale",
            "subcategory":"Sporting Goods",
            "type":"Manufacturing & Wholesale Goods"
        }
    ],
    "sg:phone":"+1 985 649 0693",
    "sg:postcode":"70460",
    "sg:province":"LA",
    "sg:tags":[
        "gun",
        "gunsmith"
    ],
    "wof:name":"GDL Enterprises",
    "wof:placetype":"venue"
},
  "geometry": {"coordinates":[-89.83498,30.26055],"type":"Point"}
}