{
  "type": "Feature",
  "properties": {
    "iso:country":"US",
    "sg:address":"28180 Pine Cone Rd",
    "sg:city":"Abita Springs",
    "sg:classifiers":[
        {
            "category":"Building & Trades",
            "subcategory":"Cleaning & Sanitation",
            "type":"Services"
        }
    ],
    "sg:phone":"+1 985 809 3857",
    "sg:postcode":"70420",
    "sg:province":"LA",
    "sg:tags":[
        "house"
    ],
    "wof:name":"All Star Maid Svc",
    "wof:placetype":"venue"
},
  "geometry": {"coordinates":[-89.937882,30.50179],"type":"Point"}
}