{
  "type": "Feature",
  "properties": {
    "iso:country":"US",
    "sg:address":"3405 Saint Claude Ave",
    "sg:city":"New Orleans",
    "sg:classifiers":[
        {
            "category":"Health Services",
            "subcategory":"Doctor",
            "type":"Services"
        }
    ],
    "sg:phone":"+1 504 943 9578",
    "sg:postcode":"70117",
    "sg:province":"LA",
    "sg:tags":[
        "cardiologist"
    ],
    "wof:name":"Dyer Farere Dr",
    "wof:placetype":"venue"
},
  "geometry": {"coordinates":[-90.040397,29.966929],"type":"Point"}
}