{
  "type": "Feature",
  "properties": {
    "iso:country":"US",
    "sg:address":"1913 N Morrison Blvd",
    "sg:city":"Hammond",
    "sg:classifiers":[
        {
            "category":"Restaurant",
            "type":"Food & Drink"
        }
    ],
    "sg:menulink":"http://www.allmenus.com/la/hammond/185282-mcdonalds/menu/",
    "sg:postcode":"70401",
    "sg:province":"LA",
    "sg:tags":[
        "burger",
        "american"
    ],
    "wof:name":"McDonald's",
    "wof:placetype":"venue"
},
  "geometry": {"coordinates":[-90.482784,30.517437],"type":"Point"}
}