{
  "type": "Feature",
  "properties": {
    "addr:full":"306 S Main St Saint Martinville LA 70582",
    "addr:housenumber":"306",
    "addr:postcode":"70582",
    "addr:street":"S Main St",
    "iso:country":"US",
    "sg:address":"306 S Main St",
    "sg:city":"Saint Martinville",
    "sg:classifiers":[
        {
            "category":"Health Services",
            "subcategory":"Doctor",
            "type":"Services"
        }
    ],
    "sg:phone":"+1 337 394 3768",
    "sg:postcode":"70582",
    "sg:province":"LA",
    "sg:tags":[
        "surgeon",
        "oral"
    ],
    "wof:name":"Beyt Gerard M DDS",
    "wof:placetype":"venue"
},
  "geometry": {"coordinates":[-91.829697,30.121799],"type":"Point"}
}