{
  "type": "Feature",
  "properties": {
    "iso:country":"US",
    "sg:address":"3200 Monroe Hwy",
    "sg:city":"Pineville",
    "sg:classifiers":[
        {
            "category":"Professional",
            "type":"Services"
        }
    ],
    "sg:phone":"+1 318 640 1984",
    "sg:postcode":"71360",
    "sg:province":"LA",
    "sg:tags":[
        "establishment"
    ],
    "wof:name":"St Frances Cabrini Office",
    "wof:placetype":"venue"
},
  "geometry": {"coordinates":[-92.41413799999999,31.36083],"type":"Point"}
}