{
  "type": "Feature",
  "properties": {
    "iso:country":"US",
    "sg:address":"5928 US Hwy 84",
    "sg:city":"Vidalia",
    "sg:classifiers":[
        {
            "category":"Professional",
            "subcategory":"Business Services",
            "type":"Services"
        }
    ],
    "sg:phone":"+1 318 757 3423",
    "sg:postcode":"71373",
    "sg:province":"LA",
    "wof:name":"Hammett House Movers",
    "wof:placetype":"venue"
},
  "geometry": {"coordinates":[-91.51772699999999,31.603367],"type":"Point"}
}