{
  "type": "Feature",
  "properties": {
    "iso:country":"US",
    "sg:address":"10838 Greenwell Springs Rd",
    "sg:city":"Baton Rouge",
    "sg:classifiers":[
        {
            "category":"Freight",
            "type":"Transportation"
        }
    ],
    "sg:phone":"+1 225 275 2023",
    "sg:postcode":"70814",
    "sg:province":"LA",
    "sg:tags":[
        "commercial",
        "storage"
    ],
    "wof:name":"Storage Center",
    "wof:placetype":"venue"
},
  "geometry": {"coordinates":[-91.063723,30.493717],"type":"Point"}
}