{
  "type": "Feature",
  "properties": {
    "iso:country":"US",
    "sg:address":"601 Behrman Hwy Ste 3",
    "sg:city":"Terrytown",
    "sg:classifiers":[
        {
            "category":"Food & Beverages",
            "subcategory":"Ethnic Foods",
            "type":"Retail Goods"
        },
        {
            "category":"Food & Beverages",
            "subcategory":"Groceries & Convenience Stores",
            "type":"Retail Goods"
        }
    ],
    "sg:phone":"+1 504 394 7358",
    "sg:postcode":"70056",
    "sg:province":"LA",
    "wof:name":"Pinoy Food Mart",
    "wof:placetype":"venue"
},
  "geometry": {"coordinates":[-90.01842000000001,29.902964],"type":"Point"}
}