{
  "type": "Feature",
  "properties": {
    "iso:country":"US",
    "sg:address":"4949 Stumberg Ln",
    "sg:city":"Baton Rouge",
    "sg:classifiers":[
        {
            "category":"Professional",
            "subcategory":"Management & Consulting",
            "type":"Services"
        }
    ],
    "sg:phone":"+1 225 756 2127",
    "sg:postcode":"70816",
    "sg:province":"LA",
    "wof:name":"Huff Marketing",
    "wof:placetype":"venue"
},
  "geometry": {"coordinates":[-91.037274,30.404657],"type":"Point"}
}