{
  "type": "Feature",
  "properties": {
    "iso:country":"US",
    "sg:address":"7200 Jewella Ave Ofc",
    "sg:city":"Shreveport",
    "sg:classifiers":[
        {
            "category":"Real Estate",
            "subcategory":"Real Estate Services",
            "type":"Services"
        },
        {
            "category":"Real Estate",
            "subcategory":"Real Estate Operator",
            "type":"Services"
        }
    ],
    "sg:phone":"+1 318 687 1787",
    "sg:postcode":"71108",
    "sg:province":"LA",
    "sg:tags":[
        "vacancy",
        "apartment",
        "rental",
        "finder",
        "listing"
    ],
    "wof:name":"Tiffany Square Apartments",
    "wof:placetype":"venue"
},
  "geometry": {"coordinates":[-93.797417,32.438511],"type":"Point"}
}