{
  "type": "Feature",
  "properties": {
    "iso:country":"US",
    "sg:address":"2910 Old Minden Rd",
    "sg:city":"Bossier City",
    "sg:classifiers":[
        {
            "category":"Autos & Motor Vehicles",
            "subcategory":"Automobile Sales",
            "type":"Retail Goods"
        }
    ],
    "sg:phone":"+1 318 742 2075",
    "sg:postcode":"71112",
    "sg:province":"LA",
    "sg:tags":[
        "car",
        "dealer"
    ],
    "wof:name":"Bailiff's Auto Sales Inc",
    "wof:placetype":"venue"
},
  "geometry": {"coordinates":[-93.694547,32.521724],"type":"Point"}
}