{
  "type": "Feature",
  "properties": {
    "iso:country":"US",
    "sg:address":"8018 State Rte 23",
    "sg:city":"Belle Chasse",
    "sg:classifiers":[
        {
            "category":"Government",
            "subcategory":"Office",
            "type":"Public Place"
        }
    ],
    "sg:phone":"+1 504 393 5649",
    "sg:postcode":"70037",
    "sg:province":"LA",
    "wof:name":"Representative Ernest D Wooten",
    "wof:placetype":"venue"
},
  "geometry": {"coordinates":[-89.992257,29.859837],"type":"Point"}
}