{
  "type": "Feature",
  "properties": {
    "addr:full":"119 Aberdeen Dr Slidell LA 70461",
    "addr:housenumber":"119",
    "addr:postcode":"70461",
    "addr:street":"Aberdeen Dr",
    "iso:country":"US",
    "sg:address":"119 Aberdeen Dr",
    "sg:city":"Slidell",
    "sg:classifiers":[
        {
            "category":"Social Services",
            "type":"Services"
        }
    ],
    "sg:phone":"+1 985 641 7400",
    "sg:postcode":"70461",
    "sg:province":"LA",
    "sg:tags":[
        "counselor",
        "marriage",
        "family"
    ],
    "wof:name":"Cindy C D Mc Nitt",
    "wof:placetype":"venue"
},
  "geometry": {"coordinates":[-89.728758,30.295918],"type":"Point"}
}