{
  "type": "Feature",
  "properties": {
    "iso:country":"US",
    "sg:address":"1023 Barrow St",
    "sg:city":"Houma",
    "sg:classifiers":[
        {
            "category":"Restaurant",
            "type":"Food & Drink"
        }
    ],
    "sg:phone":"+1 985 868 4125",
    "sg:postcode":"70360",
    "sg:province":"LA",
    "wof:name":"Sunrise Fried Chicken",
    "wof:placetype":"venue"
},
  "geometry": {"coordinates":[-90.720266,29.590235],"type":"Point"}
}