{
  "type": "Feature",
  "properties": {
    "addr:full":"6237 Pasteur Blvd New Orleans LA 70122",
    "addr:housenumber":"6237",
    "addr:postcode":"70122",
    "addr:street":"Pasteur Blvd",
    "iso:country":"US",
    "sg:address":"6237 Pasteur Blvd",
    "sg:city":"New Orleans",
    "sg:classifiers":[
        {
            "category":"Professional",
            "subcategory":"Art Services",
            "type":"Services"
        }
    ],
    "sg:phone":"+1 504 288 6143",
    "sg:postcode":"70122",
    "sg:province":"LA",
    "sg:tags":[
        "commercial",
        "design"
    ],
    "wof:name":"Advanced Document Management S",
    "wof:placetype":"venue"
},
  "geometry": {"coordinates":[-90.063185,30.022365],"type":"Point"}
}