{
  "type": "Feature",
  "properties": {
    "addr:full":"820 Rafe Meyer Rd Baton Rouge LA 70807",
    "addr:housenumber":"820",
    "addr:postcode":"70807",
    "addr:street":"Rafe Meyer Rd",
    "iso:country":"US",
    "sg:address":"820 Rafe Meyer Rd",
    "sg:city":"Baton Rouge",
    "sg:classifiers":[
        {
            "category":"Organizations",
            "subcategory":"Religious Organization",
            "type":"Services"
        }
    ],
    "sg:phone":"+1 225 775 9756",
    "sg:postcode":"70807",
    "sg:province":"LA",
    "sg:tags":[
        "church"
    ],
    "wof:name":"St John Baptist Church",
    "wof:placetype":"venue"
},
  "geometry": {"coordinates":[-91.19432399999999,30.567638],"type":"Point"}
}