{
  "type": "Feature",
  "properties": {
    "iso:country":"US",
    "sg:address":"1638 Ryan St",
    "sg:city":"Lake Charles",
    "sg:classifiers":[
        {
            "category":"Professional",
            "subcategory":"Computer Services",
            "type":"Services"
        }
    ],
    "sg:phone":"+1 337 433 8957",
    "sg:postcode":"70601",
    "sg:province":"LA",
    "sg:tags":[
        "repair"
    ],
    "wof:name":"Micro Solution",
    "wof:placetype":"venue"
},
  "geometry": {"coordinates":[-93.219252,30.218036],"type":"Point"}
}