{
  "type": "Feature",
  "properties": {
    "iso:country":"US",
    "sg:address":"12610 Airline Hwy",
    "sg:city":"Gonzales",
    "sg:classifiers":[
        {
            "category":"Manufacturing",
            "subcategory":"Metals",
            "type":"Manufacturing & Wholesale Goods"
        }
    ],
    "sg:phone":"+1 225 644 3639",
    "sg:postcode":"70737",
    "sg:province":"LA",
    "sg:tags":[
        "pipe",
        "bending",
        "fabricating"
    ],
    "wof:name":"E & E Ind Svc Inc",
    "wof:placetype":"venue"
},
  "geometry": {"coordinates":[-90.928358,30.254441],"type":"Point"}
}