{
  "type": "Feature",
  "properties": {
    "iso:country":"US",
    "sg:address":"1018 Main St",
    "sg:city":"Franklinton",
    "sg:classifiers":[
        {
            "category":"Insurance",
            "subcategory":"Insurance Agent",
            "type":"Services"
        }
    ],
    "sg:phone":"+1 985 839 4495",
    "sg:postcode":"70438",
    "sg:province":"LA",
    "wof:name":"Moore & Jenkins Insurance",
    "wof:placetype":"venue"
},
  "geometry": {"coordinates":[-90.155405,30.843853],"type":"Point"}
}