{
  "type": "Feature",
  "properties": {
    "addr:full":"3202 Franklin St Monroe LA 71201",
    "addr:housenumber":"3202",
    "addr:postcode":"71201",
    "addr:street":"Franklin St",
    "iso:country":"US",
    "sg:address":"3202 Franklin St",
    "sg:city":"Monroe",
    "sg:classifiers":[
        {
            "category":"Education",
            "subcategory":"School",
            "type":"Public Place"
        }
    ],
    "sg:phone":"+1 318 387 1851",
    "sg:postcode":"71201",
    "sg:province":"LA",
    "sg:website":"www.fatimaschool.org",
    "wof:name":"Our Lady Of Fatima School",
    "wof:placetype":"venue"
},
  "geometry": {"coordinates":[-92.08313800000001,32.5247],"type":"Point"}
}