{
  "type": "Feature",
  "properties": {
    "iso:country":"US",
    "sg:address":"207 W 2nd St",
    "sg:city":"Deridder",
    "sg:classifiers":[
        {
            "category":"Professional",
            "subcategory":"Lawyer & Legal Services",
            "type":"Services"
        }
    ],
    "sg:phone":"+1 337 463 8692",
    "sg:postcode":"70634",
    "sg:province":"LA",
    "sg:tags":[
        "attorney"
    ],
    "wof:name":"Hall Lestage & Landreneau",
    "wof:placetype":"venue"
},
  "geometry": {"coordinates":[-93.289008,30.845778],"type":"Point"}
}