{
  "type": "Feature",
  "properties": {
    "iso:country":"US",
    "sg:address":"320 3rd St",
    "sg:city":"Baton Rouge",
    "sg:classifiers":[
        {
            "category":"Professional",
            "subcategory":"Research",
            "type":"Services"
        }
    ],
    "sg:phone":"+1 225 346 6740",
    "sg:postcode":"70801",
    "sg:province":"LA",
    "sg:tags":[
        "organization",
        "noncommercial"
    ],
    "wof:name":"Louisana Ind Cllege Foundation",
    "wof:placetype":"venue"
},
  "geometry": {"coordinates":[-91.188202,30.450152],"type":"Point"}
}