{
  "type": "Feature",
  "properties": {
    "addr:full":"14529 Old Baton Rouge Hwy Hammond LA 70403",
    "addr:housenumber":"14529",
    "addr:postcode":"70403",
    "addr:street":"Old Baton Rouge Hwy",
    "iso:country":"US",
    "sg:address":"14529 Old Baton Rouge Hwy",
    "sg:city":"Hammond",
    "sg:classifiers":[
        {
            "category":"Bars & Pubs",
            "type":"Food & Drink"
        }
    ],
    "sg:phone":"+1 985 429 1324",
    "sg:postcode":"70403",
    "sg:province":"LA",
    "wof:name":"Jakie's Of Hammond Sportsbar",
    "wof:placetype":"venue"
},
  "geometry": {"coordinates":[-90.578002,30.481487],"type":"Point"}
}