{
  "type": "Feature",
  "properties": {
    "iso:country":"US",
    "sg:address":"151 Industrial Pkwy",
    "sg:city":"Lafayette",
    "sg:classifiers":[
        {
            "category":"Building & Trades",
            "subcategory":"Construction",
            "type":"Services"
        }
    ],
    "sg:phone":"+1 337 232 7224",
    "sg:postcode":"70508",
    "sg:province":"LA",
    "sg:tags":[
        "home",
        "builder"
    ],
    "wof:name":"Venus Construction Corp",
    "wof:placetype":"venue"
},
  "geometry": {"coordinates":[-92.00960499999999,30.18571],"type":"Point"}
}