{
  "type": "Feature",
  "properties": {
    "addr:full":"3843 W Main St Gray LA 70359",
    "addr:housenumber":"3843",
    "addr:postcode":"70359",
    "addr:street":"W Main St",
    "iso:country":"US",
    "sg:address":"3843 W Main St",
    "sg:city":"Gray",
    "sg:classifiers":[
        {
            "category":"Home & Garden",
            "subcategory":"Building Materials",
            "type":"Retail Goods"
        }
    ],
    "sg:phone":"+1 985 853 1385",
    "sg:postcode":"70359",
    "sg:province":"LA",
    "wof:name":"K G Building Supplies",
    "wof:placetype":"venue"
},
  "geometry": {"coordinates":[-90.784873,29.682441],"type":"Point"}
}