{
  "type": "Feature",
  "properties": {
    "addr:full":"8680 Airline Hwy Baton Rouge LA 70815",
    "addr:housenumber":"8680",
    "addr:postcode":"70815",
    "addr:street":"Airline Hwy",
    "iso:country":"US",
    "sg:address":"8680 Airline Hwy",
    "sg:city":"Baton Rouge",
    "sg:classifiers":[
        {
            "category":"Shopping",
            "subcategory":"Bicycles & Sporting Goods",
            "type":"Retail Goods"
        }
    ],
    "sg:phone":"+1 225 930 3022",
    "sg:postcode":"70815",
    "sg:province":"LA",
    "wof:name":"Sports Authority",
    "wof:placetype":"venue"
},
  "geometry": {"coordinates":[-91.09408999999999,30.450441],"type":"Point"}
}