{
  "type": "Feature",
  "properties": {
    "iso:country":"US",
    "sg:address":"10 Roxanne Dr",
    "sg:city":"Youngsville",
    "sg:classifiers":[
        {
            "category":"Home & Garden",
            "subcategory":"Building Materials",
            "type":"Retail Goods"
        }
    ],
    "sg:phone":"+1 337 856 9740",
    "sg:postcode":"70592",
    "sg:province":"LA",
    "sg:tags":[
        "glass",
        "leaded"
    ],
    "wof:name":"Inspirational Stained Glass",
    "wof:placetype":"venue"
},
  "geometry": {"coordinates":[-92.02810599999999,30.065437],"type":"Point"}
}