{
  "type": "Feature",
  "properties": {
    "iso:country":"US",
    "sg:address":"222 Railroad Ave",
    "sg:city":"Donaldsonville",
    "sg:classifiers":[
        {
            "category":"Shopping",
            "subcategory":"Used Merchandise",
            "type":"Retail Goods"
        }
    ],
    "sg:phone":"+1 225 474 6575",
    "sg:postcode":"70346",
    "sg:province":"LA",
    "sg:tags":[
        "shop",
        "thrift"
    ],
    "wof:name":"Thrift Shop",
    "wof:placetype":"venue"
},
  "geometry": {"coordinates":[-90.987968,30.105012],"type":"Point"}
}