{
  "type": "Feature",
  "properties": {
    "iso:country":"US",
    "sg:address":"751 S 9th St",
    "sg:city":"Eunice",
    "sg:classifiers":[
        {
            "category":"Government",
            "subcategory":"Office",
            "type":"Public Place"
        }
    ],
    "sg:phone":"+1 337 457 3280",
    "sg:postcode":"70535",
    "sg:province":"LA",
    "sg:tags":[
        "state",
        "security"
    ],
    "wof:name":"National Guard",
    "wof:placetype":"venue"
},
  "geometry": {"coordinates":[-92.42435999999999,30.48821],"type":"Point"}
}