{
  "type": "Feature",
  "properties": {
    "addr:full":"607 E 1st St Kaplan LA 70548",
    "addr:housenumber":"607",
    "addr:postcode":"70548",
    "addr:street":"E 1St St",
    "iso:country":"US",
    "sg:address":"607 E 1st St",
    "sg:city":"Kaplan",
    "sg:classifiers":[
        {
            "category":"Home & Garden",
            "subcategory":"Hardware",
            "type":"Retail Goods"
        }
    ],
    "sg:phone":"+1 337 643 7851",
    "sg:postcode":"70548",
    "sg:province":"LA",
    "wof:name":"Cajun Hardware",
    "wof:placetype":"venue"
},
  "geometry": {"coordinates":[-92.280058,29.996471],"type":"Point"}
}