{
  "type": "Feature",
  "properties": {
    "iso:country":"US",
    "sg:address":"300 Canton St",
    "sg:city":"Berwick",
    "sg:classifiers":[
        {
            "category":"Banks & Credit Unions",
            "subcategory":"Bank",
            "type":"Services"
        }
    ],
    "sg:phone":"+1 985 384 6444",
    "sg:postcode":"70342",
    "sg:province":"LA",
    "wof:name":"Whitney National Bank",
    "wof:placetype":"venue"
},
  "geometry": {"coordinates":[-91.21754,29.693226],"type":"Point"}
}