{
  "type": "Feature",
  "properties": {
    "iso:country":"US",
    "sg:address":"1132 Sena Dr",
    "sg:city":"Metairie",
    "sg:classifiers":[
        {
            "category":"Real Estate",
            "subcategory":"Real Estate Agent",
            "type":"Services"
        }
    ],
    "sg:phone":"+1 504 838 8343",
    "sg:postcode":"70005",
    "sg:province":"LA",
    "wof:name":"Daniel J Craven",
    "wof:placetype":"venue"
},
  "geometry": {"coordinates":[-90.13473999999999,30.01255],"type":"Point"}
}