{
  "type": "Feature",
  "properties": {
    "addr:full":"3630 State Rte 78 Livonia LA 70755",
    "addr:housenumber":"3630",
    "addr:postcode":"70755",
    "addr:street":"State Rte 78",
    "iso:country":"US",
    "sg:address":"3630 State Rte 78",
    "sg:city":"Livonia",
    "sg:classifiers":[
        {
            "category":"Food & Beverages",
            "subcategory":"Groceries & Convenience Stores",
            "type":"Retail Goods"
        }
    ],
    "sg:phone":"+1 225 637 2614",
    "sg:postcode":"70755",
    "sg:province":"LA",
    "wof:name":"Cashio's Quick Stop",
    "wof:placetype":"venue"
},
  "geometry": {"coordinates":[-91.54753599999999,30.56946],"type":"Point"}
}