{
  "type": "Feature",
  "properties": {
    "iso:country":"US",
    "sg:address":"134 Daisy St",
    "sg:city":"Garyville",
    "sg:classifiers":[
        {
            "category":"Retail",
            "subcategory":"Funeral Services",
            "type":"Services"
        }
    ],
    "sg:phone":"+1 985 535 2516",
    "sg:postcode":"70051",
    "sg:province":"LA",
    "sg:tags":[
        "director"
    ],
    "wof:name":"Hobson Brown Funeral Home",
    "wof:placetype":"venue"
},
  "geometry": {"coordinates":[-90.614762,30.053542],"type":"Point"}
}