{
  "type": "Feature",
  "properties": {
    "addr:full":"2908 Engineers Rd Belle Chasse LA 70037",
    "addr:housenumber":"2908",
    "addr:postcode":"70037",
    "addr:street":"Engineers Rd",
    "iso:country":"US",
    "sg:address":"2908 Engineers Rd",
    "sg:city":"Belle Chasse",
    "sg:classifiers":[
        {
            "category":"Local Transit",
            "type":"Transportation"
        }
    ],
    "sg:phone":"+1 504 391 2683",
    "sg:postcode":"70037",
    "sg:province":"LA",
    "sg:tags":[
        "passenger"
    ],
    "wof:name":"Hollywood Limo",
    "wof:placetype":"venue"
},
  "geometry": {"coordinates":[-90.048699,29.837247],"type":"Point"}
}