{
  "type": "Feature",
  "properties": {
    "iso:country":"US",
    "sg:address":"128 2nd St",
    "sg:city":"Colfax",
    "sg:classifiers":[
        {
            "category":"Retail",
            "subcategory":"Funeral Services",
            "type":"Services"
        }
    ],
    "sg:phone":"+1 318 627 3511",
    "sg:postcode":"71417",
    "sg:province":"LA",
    "wof:name":"Kramer Funeral Home",
    "wof:placetype":"venue"
},
  "geometry": {"coordinates":[-92.701065,31.506544],"type":"Point"}
}