{
  "type": "Feature",
  "properties": {
    "iso:country":"US",
    "sg:address":"3511 NW Evangeline Throughway",
    "sg:city":"Carencro",
    "sg:classifiers":[
        {
            "category":"Restaurant",
            "type":"Food & Drink"
        }
    ],
    "sg:phone":"+1 337 896 2604",
    "sg:postcode":"70520",
    "sg:province":"LA",
    "wof:name":"Angele's Restaurant",
    "wof:placetype":"venue"
},
  "geometry": {"coordinates":[-92.030418,30.309922],"type":"Point"}
}