{
  "type": "Feature",
  "properties": {
    "iso:country":"US",
    "sg:address":"313 E Martin Luther King Jr Dr",
    "sg:city":"Grand Coteau",
    "sg:classifiers":[
        {
            "category":"Organizations",
            "subcategory":"Religious Organization",
            "type":"Services"
        }
    ],
    "sg:phone":"+1 337 662 5251",
    "sg:postcode":"70541",
    "sg:province":"LA",
    "sg:tags":[
        "house",
        "retreat"
    ],
    "wof:name":"Jesuit Spirituality Ctr",
    "wof:placetype":"venue"
},
  "geometry": {"coordinates":[-92.046254,30.418112],"type":"Point"}
}