{
  "type": "Feature",
  "properties": {
    "iso:country":"US",
    "sg:address":"3624 Cleveland Ave",
    "sg:city":"New Orleans",
    "sg:classifiers":[
        {
            "category":"Professional",
            "subcategory":"Lawyer & Legal Services",
            "type":"Services"
        }
    ],
    "sg:phone":"+1 504 482 8130",
    "sg:postcode":"70119",
    "sg:province":"LA",
    "sg:tags":[
        "attorney"
    ],
    "wof:name":"Susan G Guidry Law Offices",
    "wof:placetype":"venue"
},
  "geometry": {"coordinates":[-90.09749100000001,29.970824],"type":"Point"}
}