{
  "type": "Feature",
  "properties": {
    "iso:country":"US",
    "sg:address":"206 W Alabama Ave",
    "sg:city":"Ruston",
    "sg:classifiers":[
        {
            "category":"Banks & Credit Unions",
            "subcategory":"Bank",
            "type":"Services"
        }
    ],
    "sg:phone":"+1 318 255 8654",
    "sg:postcode":"71270",
    "sg:province":"LA",
    "sg:tags":[
        "loan"
    ],
    "wof:name":"World Finance Corp",
    "wof:placetype":"venue"
},
  "geometry": {"coordinates":[-92.640322,32.530592],"type":"Point"}
}