{
  "type": "Feature",
  "properties": {
    "iso:country":"US",
    "sg:address":"82355 Hwy 25",
    "sg:city":"Folsom",
    "sg:classifiers":[
        {
            "category":"Organizations",
            "subcategory":"Professional Association",
            "type":"Services"
        }
    ],
    "sg:phone":"+1 985 796 0606",
    "sg:postcode":"70437",
    "sg:province":"LA",
    "wof:name":"Bethesda Community Programs",
    "wof:placetype":"venue"
},
  "geometry": {"coordinates":[-90.188008,30.631145],"type":"Point"}
}