{
  "type": "Feature",
  "properties": {
    "iso:country":"US",
    "sg:address":"411 Incarnate Word Dr",
    "sg:city":"Kenner",
    "sg:classifiers":[
        {
            "category":"Professional",
            "subcategory":"Testing Lab",
            "type":"Services"
        }
    ],
    "sg:phone":"+1 504 466 5255",
    "sg:postcode":"70065",
    "sg:province":"LA",
    "sg:tags":[
        "laboratory"
    ],
    "wof:name":"Mobile Calibration Svc",
    "wof:placetype":"venue"
},
  "geometry": {"coordinates":[-90.26461999999999,30.015026],"type":"Point"}
}