{
  "type": "Feature",
  "properties": {
    "iso:country":"US",
    "sg:address":"1001 Bertrand Dr",
    "sg:city":"Lafayette",
    "sg:classifiers":[
        {
            "category":"Shopping",
            "subcategory":"Crafts & Fabrics",
            "type":"Retail Goods"
        }
    ],
    "sg:phone":"+1 337 232 1515",
    "sg:postcode":"70506",
    "sg:province":"LA",
    "sg:tags":[
        "shop"
    ],
    "wof:name":"Fancy Fabrics",
    "wof:placetype":"venue"
},
  "geometry": {"coordinates":[-92.049273,30.218244],"type":"Point"}
}