{
  "type": "Feature",
  "properties": {
    "iso:country":"US",
    "sg:address":"197 Crocker Rd",
    "sg:city":"Choudrant",
    "sg:classifiers":[
        {
            "category":"Shopping",
            "type":"Retail Goods"
        }
    ],
    "sg:phone":"+1 318 768 4551",
    "sg:postcode":"71227",
    "sg:province":"LA",
    "sg:tags":[
        "monument"
    ],
    "wof:name":"JWT Cemetery Svc",
    "wof:placetype":"venue"
},
  "geometry": {"coordinates":[-92.435001,32.514389],"type":"Point"}
}