{
  "type": "Feature",
  "properties": {
    "iso:country":"US",
    "sg:address":"1111 N 28th St",
    "sg:city":"Baton Rouge",
    "sg:classifiers":[
        {
            "category":"Education",
            "subcategory":"School",
            "type":"Public Place"
        }
    ],
    "sg:phone":"+1 225 344 2152",
    "sg:postcode":"70802",
    "sg:province":"LA",
    "wof:name":"New Horizon Head Start",
    "wof:placetype":"venue"
},
  "geometry": {"coordinates":[-91.16072200000001,30.459185],"type":"Point"}
}