{
  "type": "Feature",
  "properties": {
    "addr:full":"62 Charles Gilley Rd Mangham LA 71259",
    "addr:housenumber":"62",
    "addr:postcode":"71259",
    "addr:street":"Charles Gilley Rd",
    "iso:country":"US",
    "sg:address":"62 Charles Gilley Rd",
    "sg:city":"Mangham",
    "sg:classifiers":[
        {
            "category":"Freight",
            "type":"Transportation"
        }
    ],
    "sg:phone":"+1 318 248 3733",
    "sg:postcode":"71259",
    "sg:province":"LA",
    "sg:tags":[
        "operator",
        "local",
        "trucking"
    ],
    "wof:name":"Gilley Trucking",
    "wof:placetype":"venue"
},
  "geometry": {"coordinates":[-91.898129,32.276443],"type":"Point"}
}