{
  "type": "Feature",
  "properties": {
    "addr:full":"115 E Saint Peter St New Iberia LA 70560",
    "addr:housenumber":"115",
    "addr:postcode":"70560",
    "addr:street":"E Saint Peter St",
    "iso:country":"US",
    "sg:address":"115 E Saint Peter St",
    "sg:city":"New Iberia",
    "sg:classifiers":[
        {
            "category":"Personal",
            "subcategory":"Beauty Salon",
            "type":"Services"
        }
    ],
    "sg:phone":"+1 337 365 1444",
    "sg:postcode":"70560",
    "sg:province":"LA",
    "sg:tags":[
        "shop",
        "barber"
    ],
    "wof:name":"A Salon by Rachel",
    "wof:placetype":"venue"
},
  "geometry": {"coordinates":[-91.81909899999999,30.0051],"type":"Point"}
}