{
  "type": "Feature",
  "properties": {
    "iso:country":"US",
    "sg:address":"123 Theta St",
    "sg:city":"Belle Chasse",
    "sg:classifiers":[
        {
            "category":"Building & Trades",
            "subcategory":"Landscaping Services",
            "type":"Services"
        }
    ],
    "sg:phone":"+1 504 391 0178",
    "sg:postcode":"70037",
    "sg:province":"LA",
    "wof:name":"Joe S Lawn Service",
    "wof:placetype":"venue"
},
  "geometry": {"coordinates":[-90.008848,29.864865],"type":"Point"}
}