{
  "type": "Feature",
  "properties": {
    "addr:full":"1704 Houma Blvd Metairie LA 70001",
    "addr:housenumber":"1704",
    "addr:postcode":"70001",
    "addr:street":"Houma Blvd",
    "iso:country":"US",
    "sg:address":"1704 Houma Blvd",
    "sg:city":"Metairie",
    "sg:classifiers":[
        {
            "category":"Banks & Credit Unions",
            "subcategory":"Investment Brokerage",
            "type":"Services"
        }
    ],
    "sg:phone":"+1 504 888 5200",
    "sg:postcode":"70001",
    "sg:province":"LA",
    "sg:tags":[
        "security"
    ],
    "wof:name":"Domino Holdings",
    "wof:placetype":"venue"
},
  "geometry": {"coordinates":[-90.177223,29.990389],"type":"Point"}
}