{
  "type": "Feature",
  "properties": {
    "iso:country":"US",
    "sg:address":"1108 Canal Blvd",
    "sg:city":"Thibodaux",
    "sg:classifiers":[
        {
            "category":"Retail",
            "subcategory":"Auto Repair",
            "type":"Services"
        }
    ],
    "sg:phone":"+1 985 446 2777",
    "sg:postcode":"70301",
    "sg:province":"LA",
    "sg:tags":[
        "repairing",
        "automobile"
    ],
    "wof:name":"Chabill's Tire Traxx",
    "wof:placetype":"venue"
},
  "geometry": {"coordinates":[-90.821851,29.789953],"type":"Point"}
}