{
  "type": "Feature",
  "properties": {
    "iso:country":"US",
    "sg:address":"3001 Veterans Memorial Dr",
    "sg:city":"Abbeville",
    "sg:classifiers":[
        {
            "category":"Shopping",
            "subcategory":"Shoes",
            "type":"Retail Goods"
        }
    ],
    "sg:phone":"+1 337 893 7545",
    "sg:postcode":"70510",
    "sg:province":"LA",
    "wof:name":"Hibbett Sporting Goods Inc",
    "wof:placetype":"venue"
},
  "geometry": {"coordinates":[-92.096329,29.970427],"type":"Point"}
}