{
  "type": "Feature",
  "properties": {
    "addr:full":"11756 Florida Blvd Baton Rouge LA 70815",
    "addr:housenumber":"11756",
    "addr:postcode":"70815",
    "addr:street":"Florida Blvd",
    "iso:country":"US",
    "sg:address":"11756 Florida Blvd",
    "sg:city":"Baton Rouge",
    "sg:classifiers":[
        {
            "category":"Freight",
            "type":"Transportation"
        }
    ],
    "sg:phone":"+1 225 275 6909",
    "sg:postcode":"70815",
    "sg:province":"LA",
    "sg:tags":[
        "commercial",
        "storage"
    ],
    "wof:name":"Sherwood Mini Storage Inc",
    "wof:placetype":"venue"
},
  "geometry": {"coordinates":[-91.05634999999999,30.459106],"type":"Point"}
}