{
  "type": "Feature",
  "properties": {
    "iso:country":"US",
    "sg:address":"502 Railroad Ave",
    "sg:city":"Donaldsonville",
    "sg:classifiers":[
        {
            "category":"Shopping",
            "subcategory":"Department Store",
            "type":"Retail Goods"
        }
    ],
    "sg:phone":"+1 225 473 8230",
    "sg:postcode":"70346",
    "sg:province":"LA",
    "wof:name":"Shaheen's Department Store",
    "wof:placetype":"venue"
},
  "geometry": {"coordinates":[-90.989795,30.102502],"type":"Point"}
}