{
  "type": "Feature",
  "properties": {
    "iso:country":"US",
    "sg:address":"555 Lapalco Blvd Ste 106",
    "sg:city":"Gretna",
    "sg:classifiers":[
        {
            "category":"Personal",
            "subcategory":"Barber",
            "type":"Services"
        }
    ],
    "sg:phone":"+1 504 393 2904",
    "sg:postcode":"70056",
    "sg:province":"LA",
    "sg:website":"www.fantasticsams.com",
    "wof:name":"Fantastic Sam's",
    "wof:placetype":"venue"
},
  "geometry": {"coordinates":[-90.033897,29.879101],"type":"Point"}
}