{
  "type": "Feature",
  "properties": {
    "iso:country":"US",
    "sg:address":"2655 N Foster Dr",
    "sg:city":"Baton Rouge",
    "sg:classifiers":[
        {
            "category":"Wholesale",
            "subcategory":"Metals & Minerals",
            "type":"Manufacturing & Wholesale Goods"
        }
    ],
    "sg:phone":"+1 225 356 4631",
    "sg:postcode":"70805",
    "sg:province":"LA",
    "sg:tags":[
        "steel",
        "warehouse"
    ],
    "wof:name":"Capitol Steel Inc",
    "wof:placetype":"venue"
},
  "geometry": {"coordinates":[-91.140294,30.471153],"type":"Point"}
}