{
  "type": "Feature",
  "properties": {
    "iso:country":"US",
    "sg:address":"6556 Airline Hwy",
    "sg:city":"Baton Rouge",
    "sg:classifiers":[
        {
            "category":"Bars & Pubs",
            "type":"Food & Drink"
        }
    ],
    "sg:phone":"+1 225 356 9152",
    "sg:postcode":"70805",
    "sg:province":"LA",
    "sg:tags":[
        "lounge",
        "cocktail"
    ],
    "wof:name":"Ruby's Lounge",
    "wof:placetype":"venue"
},
  "geometry": {"coordinates":[-91.121639,30.489032],"type":"Point"}
}