{
  "type": "Feature",
  "properties": {
    "iso:country":"US",
    "sg:address":"610 Tate Cove Rd",
    "sg:city":"Ville Platte",
    "sg:classifiers":[
        {
            "category":"Retail",
            "subcategory":"Auto Repair",
            "type":"Services"
        }
    ],
    "sg:phone":"+1 337 363 7771",
    "sg:postcode":"70586",
    "sg:province":"LA",
    "sg:tags":[
        "repairing",
        "automobile"
    ],
    "wof:name":"Western Auto",
    "wof:placetype":"venue"
},
  "geometry": {"coordinates":[-92.263722,30.689667],"type":"Point"}
}