{
  "type": "Feature",
  "properties": {
    "addr:full":"101 E Reynolds Dr Ruston LA 71270",
    "addr:housenumber":"101",
    "addr:postcode":"71270",
    "addr:street":"E Reynolds Dr",
    "iso:country":"US",
    "sg:address":"101 E Reynolds Dr",
    "sg:city":"Ruston",
    "sg:classifiers":[
        {
            "category":"Insurance",
            "subcategory":"Insurance Agent",
            "type":"Services"
        }
    ],
    "sg:phone":"+1 318 255 3353",
    "sg:postcode":"71270",
    "sg:province":"LA",
    "wof:name":"Modern Woodmen Of America",
    "wof:placetype":"venue"
},
  "geometry": {"coordinates":[-92.633124,32.544782],"type":"Point"}
}