{
  "type": "Feature",
  "properties": {
    "iso:country":"US",
    "sg:address":"1916 Kansas Ave",
    "sg:city":"Kenner",
    "sg:classifiers":[
        {
            "category":"Arts & Performance",
            "subcategory":"Theater",
            "type":"Entertainment"
        }
    ],
    "sg:phone":"+1 504 469 8383",
    "sg:postcode":"70062",
    "sg:province":"LA",
    "sg:tags":[
        "group"
    ],
    "wof:name":"Royal Entertainment",
    "wof:placetype":"venue"
},
  "geometry": {"coordinates":[-90.23578000000001,29.991494],"type":"Point"}
}