{
  "type": "Feature",
  "properties": {
    "iso:country":"US",
    "sg:address":"3918 Benton Dr",
    "sg:city":"Bourg",
    "sg:classifiers":[
        {
            "category":"Wholesale",
            "subcategory":"Machinery & Supplies",
            "type":"Manufacturing & Wholesale Goods"
        }
    ],
    "sg:phone":"+1 985 876 9669",
    "sg:postcode":"70343",
    "sg:province":"LA",
    "wof:name":"Laitram Machinery",
    "wof:placetype":"venue"
},
  "geometry": {"coordinates":[-90.64430900000001,29.562521],"type":"Point"}
}