{
  "type": "Feature",
  "properties": {
    "iso:country":"US",
    "sg:address":"55226 Hwy 424",
    "sg:city":"Franklinton",
    "sg:classifiers":[
        {
            "category":"Retail",
            "subcategory":"Repair Shop",
            "type":"Services"
        }
    ],
    "sg:phone":"+1 985 848 5902",
    "sg:postcode":"70438",
    "sg:province":"LA",
    "sg:tags":[
        "con",
        "electrical",
        "welding",
        "contractor"
    ],
    "wof:name":"Seals Welding & Metal Work",
    "wof:placetype":"venue"
},
  "geometry": {"coordinates":[-89.971639,30.993623],"type":"Point"}
}