{
  "type": "Feature",
  "properties": {
    "iso:country":"US",
    "sg:address":"1400 W Tunnel Blvd",
    "sg:city":"Houma",
    "sg:classifiers":[
        {
            "category":"Restaurant",
            "type":"Food & Drink"
        }
    ],
    "sg:phone":"+1 985 873 8740",
    "sg:postcode":"70360",
    "sg:province":"LA",
    "wof:name":"Spahr's Seafood Co",
    "wof:placetype":"venue"
},
  "geometry": {"coordinates":[-90.745974,29.604405],"type":"Point"}
}