{
  "type": "Feature",
  "properties": {
    "iso:country":"US",
    "sg:address":"8131 Oak St",
    "sg:city":"New Orleans",
    "sg:classifiers":[
        {
            "category":"Wholesale",
            "subcategory":"Durable Goods & Equipment",
            "type":"Manufacturing & Wholesale Goods"
        }
    ],
    "sg:phone":"+1 504 864 1169",
    "sg:postcode":"70118",
    "sg:province":"LA",
    "sg:tags":[
        "exporter"
    ],
    "wof:name":"Express Oilfield Supply Inc",
    "wof:placetype":"venue"
},
  "geometry": {"coordinates":[-90.130405,29.947906],"type":"Point"}
}