{
  "type": "Feature",
  "properties": {
    "addr:full":"1115 Jack Wells Blvd Shreveport LA 71107",
    "addr:housenumber":"1115",
    "addr:postcode":"71107",
    "addr:street":"Jack Wells Blvd",
    "iso:country":"US",
    "sg:address":"1115 Jack Wells Blvd",
    "sg:city":"Shreveport",
    "sg:classifiers":[
        {
            "category":"Government",
            "subcategory":"Office",
            "type":"Public Place"
        }
    ],
    "sg:phone":"+1 318 221 7433",
    "sg:postcode":"71107",
    "sg:province":"LA",
    "sg:tags":[
        "city",
        "program"
    ],
    "wof:name":"Sportran-City Transit System",
    "wof:placetype":"venue"
},
  "geometry": {"coordinates":[-93.75848999999999,32.537437],"type":"Point"}
}