{
  "type": "Feature",
  "properties": {
    "iso:country":"US",
    "sg:address":"2204 N 10th St",
    "sg:city":"Monroe",
    "sg:classifiers":[
        {
            "category":"Organizations",
            "subcategory":"Religious Organization",
            "type":"Services"
        }
    ],
    "sg:phone":"+1 318 329 9298",
    "sg:postcode":"71201",
    "sg:province":"LA",
    "sg:tags":[
        "church"
    ],
    "wof:name":"Parkview Baptist Church",
    "wof:placetype":"venue"
},
  "geometry": {"coordinates":[-92.125457,32.526498],"type":"Point"}
}