{
  "type": "Feature",
  "properties": {
    "addr:full":"12120 Brown Rd Denham Springs LA 70726",
    "addr:housenumber":"12120",
    "addr:postcode":"70726",
    "addr:street":"Brown Rd",
    "iso:country":"US",
    "sg:address":"12120 Brown Rd",
    "sg:city":"Denham Springs",
    "sg:classifiers":[
        {
            "category":"Food & Beverages",
            "subcategory":"Groceries & Convenience Stores",
            "type":"Retail Goods"
        }
    ],
    "sg:phone":"+1 225 791 0309",
    "sg:postcode":"70726",
    "sg:province":"LA",
    "wof:name":"Fontenot Grocery",
    "wof:placetype":"venue"
},
  "geometry": {"coordinates":[-90.90105,30.429879],"type":"Point"}
}