{
  "type": "Feature",
  "properties": {
    "iso:country":"US",
    "sg:address":"3900 Cypress St",
    "sg:city":"West Monroe",
    "sg:classifiers":[
        {
            "category":"Autos & Motor Vehicles",
            "subcategory":"Automobile Sales",
            "type":"Retail Goods"
        }
    ],
    "sg:phone":"+1 318 396 1100",
    "sg:postcode":"71291",
    "sg:province":"LA",
    "sg:tags":[
        "sport",
        "trailer",
        "utility"
    ],
    "wof:name":"Fowler Truck & Trailer",
    "wof:placetype":"venue"
},
  "geometry": {"coordinates":[-92.169292,32.517254],"type":"Point"}
}