{
  "type": "Feature",
  "properties": {
    "addr:full":"4110 Greenwood Rd Shreveport LA 71109",
    "addr:housenumber":"4110",
    "addr:postcode":"71109",
    "addr:street":"Greenwood Rd",
    "iso:country":"US",
    "sg:address":"4110 Greenwood Rd",
    "sg:city":"Shreveport",
    "sg:classifiers":[
        {
            "category":"Food & Beverages",
            "subcategory":"Groceries & Convenience Stores",
            "type":"Retail Goods"
        }
    ],
    "sg:phone":"+1 318 636 0256",
    "sg:postcode":"71109",
    "sg:province":"LA",
    "sg:tags":[
        "grocer"
    ],
    "wof:name":"A & W Food Mart",
    "wof:placetype":"venue"
},
  "geometry": {"coordinates":[-93.81277799999999,32.471313],"type":"Point"}
}