{
  "type": "Feature",
  "properties": {
    "iso:country":"US",
    "sg:address":"2242 N Claiborne Ave",
    "sg:city":"New Orleans",
    "sg:classifiers":[
        {
            "category":"Government",
            "subcategory":"Office",
            "type":"Public Place"
        }
    ],
    "sg:phone":"+1 504 941 4436",
    "sg:postcode":"70117",
    "sg:province":"LA",
    "sg:tags":[
        "city",
        "program",
        "health"
    ],
    "wof:name":"Katherine Benson Health Ctr",
    "wof:placetype":"venue"
},
  "geometry": {"coordinates":[-90.054815,29.973678],"type":"Point"}
}