{
  "type": "Feature",
  "properties": {
    "iso:country":"US",
    "sg:address":"2308 Washington St",
    "sg:city":"Monroe",
    "sg:classifiers":[
        {
            "category":"Building & Trades",
            "subcategory":"Construction",
            "type":"Services"
        }
    ],
    "sg:phone":"+1 318 325 8353",
    "sg:postcode":"71201",
    "sg:province":"LA",
    "sg:tags":[
        "general",
        "contractor"
    ],
    "wof:name":"E R Lawrence",
    "wof:placetype":"venue"
},
  "geometry": {"coordinates":[-92.09903799999999,32.518937],"type":"Point"}
}