{
  "type": "Feature",
  "properties": {
    "iso:country":"US",
    "sg:address":"7415 Corporate Blvd",
    "sg:city":"Baton Rouge",
    "sg:classifiers":[
        {
            "category":"Coffee & Tea",
            "type":"Food & Drink"
        }
    ],
    "sg:menulink":"http://www.allmenus.com/la/baton-rouge/113633-starbucks-coffee/menu/",
    "sg:phone":"+1 225 218 1042",
    "sg:postcode":"70809",
    "sg:province":"LA",
    "sg:tags":[
        "american"
    ],
    "wof:name":"Starbucks Coffee",
    "wof:placetype":"venue"
},
  "geometry": {"coordinates":[-91.112617,30.430783],"type":"Point"}
}