{
  "type": "Feature",
  "properties": {
    "addr:full":"8521 General Chennault Dr Baton Rouge LA 70807",
    "addr:housenumber":"8521",
    "addr:postcode":"70807",
    "addr:street":"General Chennault Dr",
    "iso:country":"US",
    "sg:address":"8521 General Chennault Dr",
    "sg:city":"Baton Rouge",
    "sg:classifiers":[
        {
            "category":"Government",
            "subcategory":"Office",
            "type":"Public Place"
        }
    ],
    "sg:phone":"+1 225 356 1327",
    "sg:postcode":"70807",
    "sg:province":"LA",
    "sg:tags":[
        "federal",
        "security"
    ],
    "wof:name":"US Marine Corps",
    "wof:placetype":"venue"
},
  "geometry": {"coordinates":[-91.16018099999999,30.528054],"type":"Point"}
}