{
  "type": "Feature",
  "properties": {
    "iso:country":"US",
    "sg:address":"40249 Bren Way",
    "sg:city":"Ponchatoula",
    "sg:classifiers":[
        {
            "category":"Shopping",
            "subcategory":"Gifts & Souvenirs",
            "type":"Retail Goods"
        }
    ],
    "sg:phone":"+1 225 294 2528",
    "sg:postcode":"70454",
    "sg:province":"LA",
    "sg:tags":[
        "jewelry"
    ],
    "wof:name":"T & K Jewelry & Gifts",
    "wof:placetype":"venue"
},
  "geometry": {"coordinates":[-90.515271,30.444245],"type":"Point"}
}