{
  "type": "Feature",
  "properties": {
    "addr:full":"1570 Susek Dr Pineville LA 71360",
    "addr:housenumber":"1570",
    "addr:postcode":"71360",
    "addr:street":"Susek Dr",
    "iso:country":"US",
    "sg:address":"1570 Susek Dr",
    "sg:city":"Pineville",
    "sg:classifiers":[
        {
            "category":"Building & Trades",
            "subcategory":"Landscaping Services",
            "type":"Services"
        }
    ],
    "sg:phone":"+1 318 640 2258",
    "sg:postcode":"71360",
    "sg:province":"LA",
    "sg:tags":[
        "lawn",
        "maintenance",
        "grounds"
    ],
    "wof:name":"Ferguson Nursery & Landscape",
    "wof:placetype":"venue"
},
  "geometry": {"coordinates":[-92.38591,31.344143],"type":"Point"}
}