{
  "type": "Feature",
  "properties": {
    "addr:full":"1348 Main St Baker LA 70714",
    "addr:housenumber":"1348",
    "addr:postcode":"70714",
    "addr:street":"Main St",
    "iso:country":"US",
    "sg:address":"1348 Main St",
    "sg:city":"Baker",
    "sg:classifiers":[
        {
            "category":"Retail",
            "subcategory":"Laundry & Dry Cleaning",
            "type":"Services"
        },
        {
            "category":"Shopping",
            "subcategory":"Clothing, Apparel, & Fashions",
            "type":"Retail Goods"
        }
    ],
    "sg:phone":"+1 225 774 1827",
    "sg:postcode":"70714",
    "sg:province":"LA",
    "sg:tags":[
        "alteration"
    ],
    "wof:name":"Kay's Alteration & Tailoring",
    "wof:placetype":"venue"
},
  "geometry": {"coordinates":[-91.167807,30.589521],"type":"Point"}
}