{
  "type": "Feature",
  "properties": {
    "addr:full":"681 Horseshoe Lake Rd Monroe LA 71203",
    "addr:housenumber":"681",
    "addr:postcode":"71203",
    "addr:street":"Horseshoe Lake Rd",
    "iso:country":"US",
    "sg:address":"681 Horseshoe Lake Rd",
    "sg:city":"Monroe",
    "sg:classifiers":[
        {
            "category":"Retail",
            "subcategory":"Auto Repair",
            "type":"Services"
        }
    ],
    "sg:phone":"+1 318 322 0644",
    "sg:postcode":"71203",
    "sg:province":"LA",
    "sg:tags":[
        "repairing",
        "automobile"
    ],
    "wof:name":"Reeves Auto Repair Inc",
    "wof:placetype":"venue"
},
  "geometry": {"coordinates":[-92.073798,32.582444],"type":"Point"}
}