{
  "type": "Feature",
  "properties": {
    "iso:country":"US",
    "sg:address":"3405 Palmisano Blvd",
    "sg:city":"Chalmette",
    "sg:classifiers":[
        {
            "category":"Building & Trades",
            "subcategory":"Construction",
            "type":"Services"
        }
    ],
    "sg:phone":"+1 504 271 6956",
    "sg:postcode":"70043",
    "sg:province":"LA",
    "sg:tags":[
        "project"
    ],
    "wof:name":"Anthony R Fradella Inc",
    "wof:placetype":"venue"
},
  "geometry": {"coordinates":[-89.946958,29.948287],"type":"Point"}
}