{
  "type": "Feature",
  "properties": {
    "iso:country":"US",
    "sg:address":"133 Maxwell Dr",
    "sg:city":"Rayville",
    "sg:classifiers":[
        {
            "category":"Retail",
            "subcategory":"Car Wash",
            "type":"Services"
        }
    ],
    "sg:phone":"+1 318 728 9031",
    "sg:postcode":"71247",
    "sg:province":"LA",
    "sg:tags":[
        "carwash"
    ],
    "wof:name":"Rayville Car Wash",
    "wof:placetype":"venue"
},
  "geometry": {"coordinates":[-92.714895,32.285886],"type":"Point"}
}