{
  "type": "Feature",
  "properties": {
    "iso:country":"US",
    "sg:address":"4625 Parkoaks Dr",
    "sg:city":"Baton Rouge",
    "sg:classifiers":[
        {
            "category":"Retail",
            "subcategory":"Auto Repair",
            "type":"Services"
        }
    ],
    "sg:phone":"+1 225 744 4537",
    "sg:postcode":"70816",
    "sg:province":"LA",
    "sg:tags":[
        "automotive"
    ],
    "wof:name":"Leighs Notary Service",
    "wof:placetype":"venue"
},
  "geometry": {"coordinates":[-91.043809,30.409849],"type":"Point"}
}