{
  "type": "Feature",
  "properties": {
    "iso:country":"US",
    "sg:address":"11949 Bricksome Ave",
    "sg:city":"Baton Rouge",
    "sg:classifiers":[
        {
            "category":"Building & Trades",
            "subcategory":"Construction",
            "type":"Services"
        }
    ],
    "sg:phone":"+1 225 293 1940",
    "sg:postcode":"70816",
    "sg:province":"LA",
    "sg:tags":[
        "general",
        "contractor"
    ],
    "wof:name":"Record & Assoc Construction Co",
    "wof:placetype":"venue"
},
  "geometry": {"coordinates":[-91.04867299999999,30.425946],"type":"Point"}
}