{
  "type": "Feature",
  "properties": {
    "addr:full":"420 4th St Natchitoches LA 71457",
    "addr:housenumber":"420",
    "addr:postcode":"71457",
    "addr:street":"4Th St",
    "iso:country":"US",
    "sg:address":"420 4th St",
    "sg:city":"Natchitoches",
    "sg:classifiers":[
        {
            "category":"Government",
            "subcategory":"Office",
            "type":"Public Place"
        }
    ],
    "sg:phone":"+1 318 357 3838",
    "sg:postcode":"71457",
    "sg:province":"LA",
    "sg:tags":[
        "city",
        "planning",
        "dev"
    ],
    "wof:name":"Natchitoches Community Dev",
    "wof:placetype":"venue"
},
  "geometry": {"coordinates":[-93.09080299999999,31.758324],"type":"Point"}
}