{
  "type": "Feature",
  "properties": {
    "iso:country":"US",
    "sg:address":"2106 Hollywood Ave",
    "sg:city":"Shreveport",
    "sg:classifiers":[
        {
            "category":"Personal",
            "subcategory":"Beauty Salon",
            "type":"Services"
        }
    ],
    "sg:phone":"+1 318 636 3936",
    "sg:postcode":"71108",
    "sg:province":"LA",
    "wof:name":"Flora's New Image Beauty Salon",
    "wof:placetype":"venue"
},
  "geometry": {"coordinates":[-93.77547800000001,32.456557],"type":"Point"}
}