{
  "type": "Feature",
  "properties": {
    "addr:full":"230 L Roshong Rd Leesville LA 71446",
    "addr:housenumber":"230",
    "addr:postcode":"71446",
    "addr:street":"Roshong Rd",
    "iso:country":"US",
    "sg:address":"230 L Roshong Rd",
    "sg:city":"Leesville",
    "sg:classifiers":[
        {
            "category":"Freight",
            "type":"Transportation"
        }
    ],
    "sg:phone":"+1 337 238 4826",
    "sg:postcode":"71446",
    "sg:province":"LA",
    "sg:tags":[
        "mobile",
        "home"
    ],
    "wof:name":"D & S Mobile Home Movers",
    "wof:placetype":"venue"
},
  "geometry": {"coordinates":[-93.246472,31.070955],"type":"Point"}
}