{
  "type": "Feature",
  "properties": {
    "iso:country":"US",
    "sg:address":"408 Jefferson St",
    "sg:city":"New Iberia",
    "sg:classifiers":[
        {
            "category":"Insurance",
            "subcategory":"Insurance Agent",
            "type":"Services"
        }
    ],
    "sg:phone":"+1 337 367 7234",
    "sg:postcode":"70560",
    "sg:province":"LA",
    "wof:name":"Iberia Parish Farm Bureau",
    "wof:placetype":"venue"
},
  "geometry": {"coordinates":[-91.824516,30.006202],"type":"Point"}
}