{
  "type": "Feature",
  "properties": {
    "iso:country":"US",
    "sg:address":"2113 38th St",
    "sg:city":"Kenner",
    "sg:classifiers":[
        {
            "category":"Professional",
            "subcategory":"Engineering",
            "type":"Services"
        }
    ],
    "sg:phone":"+1 504 443 5481",
    "sg:postcode":"70065",
    "sg:province":"LA",
    "sg:tags":[
        "engineer"
    ],
    "sg:website":"www.edi-nola.com",
    "wof:name":"Engineering Dynamics Inc",
    "wof:placetype":"venue"
},
  "geometry": {"coordinates":[-90.238013,30.025064],"type":"Point"}
}