{
  "type": "Feature",
  "properties": {
    "iso:country":"US",
    "sg:address":"56673 Behrman St",
    "sg:city":"Slidell",
    "sg:classifiers":[
        {
            "category":"Building & Trades",
            "subcategory":"Electrical",
            "type":"Services"
        }
    ],
    "sg:phone":"+1 985 643 9358",
    "sg:postcode":"70458",
    "sg:province":"LA",
    "sg:tags":[
        "electric",
        "contractor"
    ],
    "wof:name":"Kastner Electric Inc",
    "wof:placetype":"venue"
},
  "geometry": {"coordinates":[-89.764025,30.253036],"type":"Point"}
}