{
  "type": "Feature",
  "properties": {
    "addr:full":"9001 Lake Forest Blvd New Orleans LA 70127",
    "addr:housenumber":"9001",
    "addr:postcode":"70127",
    "addr:street":"Lake Forest Blvd",
    "iso:country":"US",
    "sg:address":"9001 Lake Forest Blvd",
    "sg:city":"New Orleans",
    "sg:classifiers":[
        {
            "category":"Real Estate",
            "subcategory":"Real Estate Operator",
            "type":"Services"
        }
    ],
    "sg:phone":"+1 504 241 2941",
    "sg:postcode":"70127",
    "sg:province":"LA",
    "sg:tags":[
        "apartment"
    ],
    "wof:name":"Cedar Creek Apartments",
    "wof:placetype":"venue"
},
  "geometry": {"coordinates":[-89.985877,30.028684],"type":"Point"}
}