{
  "type": "Feature",
  "properties": {
    "iso:country":"US",
    "sg:address":"4739 Utica Ave",
    "sg:city":"Metairie",
    "sg:classifiers":[
        {
            "category":"Insurance",
            "subcategory":"Insurance Agent",
            "type":"Services"
        }
    ],
    "sg:phone":"+1 504 885 0700",
    "sg:postcode":"70006",
    "sg:province":"LA",
    "sg:tags":[
        "adjuster"
    ],
    "wof:name":"Tom Kellum & Assoc",
    "wof:placetype":"venue"
},
  "geometry": {"coordinates":[-90.18759900000001,30.000341],"type":"Point"}
}