{
  "type": "Feature",
  "properties": {
    "addr:full":"624 Opelousas St Donaldsonville LA 70346",
    "addr:housenumber":"624",
    "addr:postcode":"70346",
    "addr:street":"Opelousas St",
    "iso:country":"US",
    "sg:address":"624 Opelousas St",
    "sg:city":"Donaldsonville",
    "sg:classifiers":[
        {
            "category":"Shopping",
            "type":"Retail Goods"
        }
    ],
    "sg:phone":"+1 225 473 9472",
    "sg:postcode":"70346",
    "sg:province":"LA",
    "sg:tags":[
        "monument"
    ],
    "wof:name":"Donaldsonville Marble Co",
    "wof:placetype":"venue"
},
  "geometry": {"coordinates":[-90.986637,30.102009],"type":"Point"}
}