{
  "type": "Feature",
  "properties": {
    "addr:full":"1418 Edwards Ave New Orleans LA 70123",
    "addr:housenumber":"1418",
    "addr:postcode":"70123",
    "addr:street":"Edwards Ave",
    "iso:country":"US",
    "sg:address":"1418 Edwards Ave",
    "sg:city":"New Orleans",
    "sg:classifiers":[
        {
            "category":"Building & Trades",
            "subcategory":"Construction",
            "type":"Services"
        }
    ],
    "sg:phone":"+1 504 733 0330",
    "sg:postcode":"70123",
    "sg:province":"LA",
    "sg:tags":[
        "general",
        "contractor"
    ],
    "wof:name":"Joseph R Labadot Constr Inc",
    "wof:placetype":"venue"
},
  "geometry": {"coordinates":[-90.19506,29.960794],"type":"Point"}
}