{
  "type": "Feature",
  "properties": {
    "addr:full":"7907 Hwy 10 Ethel LA 70730",
    "addr:housenumber":"7907",
    "addr:postcode":"70730",
    "addr:street":"Hwy 10 Ethel La",
    "iso:country":"US",
    "sg:address":"7907 Hwy 10",
    "sg:city":"Ethel",
    "sg:classifiers":[
        {
            "category":"Retail",
            "subcategory":"Auto Repair",
            "type":"Services"
        }
    ],
    "sg:phone":"+1 225 683 5253",
    "sg:postcode":"70730",
    "sg:province":"LA",
    "sg:tags":[
        "repairing",
        "automobile"
    ],
    "wof:name":"Shane's Mechanic Svc",
    "wof:placetype":"venue"
},
  "geometry": {"coordinates":[-91.12373599999999,30.838193],"type":"Point"}
}