{
  "type": "Feature",
  "properties": {
    "iso:country":"US",
    "sg:address":"6904 Downman Rd",
    "sg:city":"New Orleans",
    "sg:classifiers":[
        {
            "category":"Utilities",
            "subcategory":"Telephone",
            "type":"Services"
        }
    ],
    "sg:phone":"+1 504 821 3663",
    "sg:postcode":"70126",
    "sg:province":"LA",
    "sg:tags":[
        "company"
    ],
    "wof:name":"Speedy Reconnect",
    "wof:placetype":"venue"
},
  "geometry": {"coordinates":[-90.023273,30.022592],"type":"Point"}
}