{
  "type": "Feature",
  "properties": {
    "addr:full":"2723 W Pinhook Rd Lafayette LA 70508",
    "addr:housenumber":"2723",
    "addr:postcode":"70508",
    "addr:street":"W Pinhook Rd",
    "iso:country":"US",
    "sg:address":"2723 W Pinhook Rd",
    "sg:city":"Lafayette",
    "sg:classifiers":[
        {
            "category":"Banks & Credit Unions",
            "subcategory":"Bank",
            "type":"Services"
        }
    ],
    "sg:phone":"+1 337 232 8686",
    "sg:postcode":"70508",
    "sg:province":"LA",
    "wof:name":"Iberiabank",
    "wof:placetype":"venue"
},
  "geometry": {"coordinates":[-92.002565,30.177363],"type":"Point"}
}