{
  "type": "Feature",
  "properties": {
    "addr:full":"8645 US Hwy 165 Woodworth LA 71485",
    "addr:housenumber":"8645",
    "addr:postcode":"71485",
    "addr:street":"Us Hwy 165",
    "iso:country":"US",
    "sg:address":"8645 US Hwy 165",
    "sg:city":"Woodworth",
    "sg:classifiers":[
        {
            "category":"Personal",
            "subcategory":"Beauty Salon",
            "type":"Services"
        }
    ],
    "sg:phone":"+1 318 443 3322",
    "sg:postcode":"71485",
    "sg:province":"LA",
    "sg:tags":[
        "spa",
        "day"
    ],
    "sg:website":"www.thenestspa.com",
    "wof:name":"Nest",
    "wof:placetype":"venue"
},
  "geometry": {"coordinates":[-92.506838,31.212838],"type":"Point"}
}