{
  "type": "Feature",
  "properties": {
    "addr:full":"649 Beltz Rd Leesville LA 71446",
    "addr:housenumber":"649",
    "addr:postcode":"71446",
    "addr:street":"Beltz Rd",
    "iso:country":"US",
    "sg:address":"649 Beltz Rd",
    "sg:city":"Leesville",
    "sg:classifiers":[
        {
            "category":"Retail",
            "subcategory":"Laundry & Dry Cleaning",
            "type":"Services"
        }
    ],
    "sg:phone":"+1 337 537 2026",
    "sg:postcode":"71446",
    "sg:province":"LA",
    "wof:name":"Chafield Suk",
    "wof:placetype":"venue"
},
  "geometry": {"coordinates":[-93.259317,31.097267],"type":"Point"}
}