{
  "type": "Feature",
  "properties": {
    "addr:full":"100 Walker Dr Pineville LA 71360",
    "addr:housenumber":"100",
    "addr:postcode":"71360",
    "addr:street":"Walker Dr",
    "iso:country":"US",
    "sg:address":"100 Walker Dr",
    "sg:city":"Pineville",
    "sg:classifiers":[
        {
            "category":"Retail",
            "subcategory":"Animal Services",
            "type":"Services"
        }
    ],
    "sg:phone":"+1 318 641 0100",
    "sg:postcode":"71360",
    "sg:province":"LA",
    "sg:tags":[
        "pet",
        "grooming",
        "washing"
    ],
    "wof:name":"A-1 Pet Grooming By Storm",
    "wof:placetype":"venue"
},
  "geometry": {"coordinates":[-92.396512,31.353444],"type":"Point"}
}