{
  "type": "Feature",
  "properties": {
    "iso:country":"US",
    "sg:address":"431 Oak Ridge Dr",
    "sg:city":"Benton",
    "sg:classifiers":[
        {
            "category":"Wholesale",
            "subcategory":"Scrap",
            "type":"Manufacturing & Wholesale Goods"
        }
    ],
    "sg:phone":"+1 318 965 2694",
    "sg:postcode":"71006",
    "sg:province":"LA",
    "sg:tags":[
        "material"
    ],
    "wof:name":"Benton Salvage",
    "wof:placetype":"venue"
},
  "geometry": {"coordinates":[-93.74073799999999,32.702274],"type":"Point"}
}