{
  "type": "Feature",
  "properties": {
    "iso:country":"US",
    "sg:address":"4860 General Meyer Ave",
    "sg:city":"New Orleans",
    "sg:classifiers":[
        {
            "category":"Health Services",
            "subcategory":"Dentist",
            "type":"Services"
        }
    ],
    "sg:phone":"+1 504 398 3004",
    "sg:postcode":"70131",
    "sg:province":"LA",
    "wof:name":"Family Dentistry",
    "wof:placetype":"venue"
},
  "geometry": {"coordinates":[-90.00362800000001,29.932316],"type":"Point"}
}