{
  "type": "Feature",
  "properties": {
    "iso:country":"US",
    "sg:address":"1530 Lapalco Blvd Ste 4",
    "sg:city":"Harvey",
    "sg:classifiers":[
        {
            "category":"Personal",
            "type":"Services"
        },
        {
            "category":"Retail",
            "subcategory":"Laundry & Dry Cleaning",
            "type":"Services"
        }
    ],
    "sg:phone":"+1 504 365 8383",
    "sg:postcode":"70058",
    "sg:province":"LA",
    "sg:tags":[
        "sewing",
        "alteration"
    ],
    "wof:name":"T & A Tailor and Dry Cleaners",
    "wof:placetype":"venue"
},
  "geometry": {"coordinates":[-90.049103,29.875299],"type":"Point"}
}