{
  "type": "Feature",
  "properties": {
    "addr:full":"2105 Hwy 563 Simsboro LA 71275",
    "addr:housenumber":"2105",
    "addr:postcode":"71275",
    "addr:street":"Hwy 563 Simsboro",
    "iso:country":"US",
    "sg:address":"2105 Hwy 563",
    "sg:city":"Simsboro",
    "sg:classifiers":[
        {
            "category":"Retail",
            "subcategory":"Repair Shop",
            "type":"Services"
        }
    ],
    "sg:phone":"+1 318 247 3432",
    "sg:postcode":"71275",
    "sg:province":"LA",
    "sg:tags":[
        "repairing",
        "piano",
        "refinishing"
    ],
    "wof:name":"Woodard Piano Svc",
    "wof:placetype":"venue"
},
  "geometry": {"coordinates":[-92.76001599999999,32.617309],"type":"Point"}
}