{
  "type": "Feature",
  "properties": {
    "iso:country":"US",
    "sg:address":"232 Tiger Creek Rd",
    "sg:city":"Farmerville",
    "sg:classifiers":[
        {
            "category":"Building & Trades",
            "subcategory":"Construction",
            "type":"Services"
        }
    ],
    "sg:phone":"+1 318 368 9241",
    "sg:postcode":"71241",
    "sg:province":"LA",
    "sg:tags":[
        "excavating",
        "contractor"
    ],
    "wof:name":"J & N Backhoe & Dozer",
    "wof:placetype":"venue"
},
  "geometry": {"coordinates":[-92.34668000000001,32.743053],"type":"Point"}
}