{
  "type": "Feature",
  "properties": {
    "addr:full":"3322 Lake St Baton Rouge LA 70802",
    "addr:housenumber":"3322",
    "addr:postcode":"70802",
    "addr:street":"Lake St",
    "iso:country":"US",
    "sg:address":"3322 Lake St",
    "sg:city":"Baton Rouge",
    "sg:classifiers":[
        {
            "category":"Restaurant",
            "type":"Food & Drink"
        }
    ],
    "sg:menulink":"http://www.allmenus.com/la/baton-rouge/173681-wendys/menu/",
    "sg:phone":"+1 225 383 1151",
    "sg:postcode":"70802",
    "sg:province":"LA",
    "sg:tags":[
        "burger",
        "american",
        "soup"
    ],
    "wof:name":"Wendy's",
    "wof:placetype":"venue"
},
  "geometry": {"coordinates":[-91.17929100000001,30.418115],"type":"Point"}
}