{
  "type": "Feature",
  "properties": {
    "iso:country":"US",
    "sg:address":"15202 S Choctaw Dr Exd",
    "sg:city":"Baton Rouge",
    "sg:classifiers":[
        {
            "category":"Professional",
            "type":"Services"
        }
    ],
    "sg:phone":"+1 225 273 9635",
    "sg:postcode":"70819",
    "sg:province":"LA",
    "sg:tags":[
        "establishment"
    ],
    "wof:name":"Ebr Dept Of Public Works",
    "wof:placetype":"venue"
},
  "geometry": {"coordinates":[-91.01733,30.47039],"type":"Point"}
}