{
  "type": "Feature",
  "properties": {
    "iso:country":"US",
    "sg:address":"154 W McNeese St",
    "sg:city":"Lake Charles",
    "sg:classifiers":[
        {
            "category":"Professional",
            "subcategory":"Computer Services",
            "type":"Services"
        }
    ],
    "sg:phone":"+1 337 479 0810",
    "sg:postcode":"70605",
    "sg:province":"LA",
    "sg:tags":[
        "repair"
    ],
    "wof:name":"Business Center Inc",
    "wof:placetype":"venue"
},
  "geometry": {"coordinates":[-93.219571,30.17624],"type":"Point"}
}