{
  "type": "Feature",
  "properties": {
    "addr:full":"109 Cason Rd Broussard LA 70518",
    "addr:housenumber":"109",
    "addr:postcode":"70518",
    "addr:street":"Cason Rd",
    "iso:country":"US",
    "sg:address":"109 Cason Rd",
    "sg:city":"Broussard",
    "sg:classifiers":[
        {
            "category":"Professional",
            "type":"Services"
        }
    ],
    "sg:phone":"+1 337 837 2466",
    "sg:postcode":"70518",
    "sg:province":"LA",
    "sg:tags":[
        "pipe",
        "equipment",
        "line"
    ],
    "sg:website":"www.pricesupply.net",
    "wof:name":"Price Supply Inc",
    "wof:placetype":"venue"
},
  "geometry": {"coordinates":[-91.97135900000001,30.164221],"type":"Point"}
}