{
  "type": "Feature",
  "properties": {
    "iso:country":"US",
    "sg:address":"25238 Teal Rd",
    "sg:city":"Abbeville",
    "sg:classifiers":[
        {
            "category":"Autos & Motor Vehicles",
            "subcategory":"Fuel & Gas Station",
            "type":"Retail Goods"
        }
    ],
    "sg:phone":"+1 337 893 1211",
    "sg:postcode":"70510",
    "sg:province":"LA",
    "sg:tags":[
        "oil"
    ],
    "wof:name":"Morgan Shell Landing Inc",
    "wof:placetype":"venue"
},
  "geometry": {"coordinates":[-92.15586,29.784011],"type":"Point"}
}