{
  "type": "Feature",
  "properties": {
    "iso:country":"US",
    "sg:address":"4137 Dowd Rd",
    "sg:city":"Collinston",
    "sg:classifiers":[
        {
            "category":"Professional",
            "subcategory":"Accounting & Tax Preparation",
            "type":"Services"
        }
    ],
    "sg:phone":"+1 318 874 9455",
    "sg:postcode":"71229",
    "sg:province":"LA",
    "sg:tags":[
        "accountant"
    ],
    "wof:name":"Ann's Tax Svc",
    "wof:placetype":"venue"
},
  "geometry": {"coordinates":[-91.90254899999999,32.71701],"type":"Point"}
}