{
  "type": "Feature",
  "properties": {
    "iso:country":"US",
    "sg:address":"2746 Oneal Ln",
    "sg:city":"Baton Rouge",
    "sg:classifiers":[
        {
            "category":"Retail",
            "subcategory":"Car Wash",
            "type":"Services"
        }
    ],
    "sg:phone":"+1 225 751 8771",
    "sg:postcode":"70816",
    "sg:province":"LA",
    "sg:tags":[
        "automobile",
        "detail",
        "clean"
    ],
    "wof:name":"Extreme Clean Car Wash",
    "wof:placetype":"venue"
},
  "geometry": {"coordinates":[-91.007632,30.428618],"type":"Point"}
}