{
  "type": "Feature",
  "properties": {
    "iso:country":"US",
    "sg:address":"516 N Jefferson Ave",
    "sg:city":"Covington",
    "sg:classifiers":[
        {
            "category":"Retail",
            "subcategory":"Auto Repair",
            "type":"Services"
        }
    ],
    "sg:phone":"+1 985 892 0242",
    "sg:postcode":"70433",
    "sg:province":"LA",
    "sg:tags":[
        "repairing",
        "automobile"
    ],
    "wof:name":"H & K Automotive Svc",
    "wof:placetype":"venue"
},
  "geometry": {"coordinates":[-90.09745700000001,30.479688],"type":"Point"}
}