{
  "type": "Feature",
  "properties": {
    "addr:full":"11810 Lake Charles Hwy Leesville LA 71446",
    "addr:housenumber":"11810",
    "addr:postcode":"71446",
    "addr:street":"Lake Charles Hwy",
    "iso:country":"US",
    "sg:address":"11810 Lake Charles Hwy",
    "sg:city":"Leesville",
    "sg:classifiers":[
        {
            "category":"Wholesale",
            "subcategory":"Electrical",
            "type":"Manufacturing & Wholesale Goods"
        }
    ],
    "sg:phone":"+1 337 238 4400",
    "sg:postcode":"71446",
    "sg:province":"LA",
    "sg:tags":[
        "equipment",
        "electric",
        "supply"
    ],
    "wof:name":"Rexel Southern",
    "wof:placetype":"venue"
},
  "geometry": {"coordinates":[-93.26947,31.020659],"type":"Point"}
}