{
  "type": "Feature",
  "properties": {
    "iso:country":"US",
    "sg:address":"408 N 6th St",
    "sg:city":"West Monroe",
    "sg:classifiers":[
        {
            "category":"Health Services",
            "subcategory":"Health Practitioner",
            "type":"Services"
        }
    ],
    "sg:phone":"+1 318 340 9877",
    "sg:postcode":"71291",
    "sg:province":"LA",
    "sg:tags":[
        "therapist",
        "physical"
    ],
    "wof:name":"Core Wellness Physical",
    "wof:placetype":"venue"
},
  "geometry": {"coordinates":[-92.13217299999999,32.500703],"type":"Point"}
}