{
  "type": "Feature",
  "properties": {
    "iso:country":"US",
    "sg:address":"400 S Jefferson Davis Pkwy",
    "sg:city":"New Orleans",
    "sg:classifiers":[
        {
            "category":"Real Estate",
            "subcategory":"Architect",
            "type":"Services"
        }
    ],
    "sg:phone":"+1 504 821 1556",
    "sg:postcode":"70119",
    "sg:province":"LA",
    "wof:name":"Ron Domin Architects",
    "wof:placetype":"venue"
},
  "geometry": {"coordinates":[-90.09694399999999,29.96642],"type":"Point"}
}