{
  "type": "Feature",
  "properties": {
    "iso:country":"US",
    "sg:address":"5342 Saint Charles Ave",
    "sg:city":"New Orleans",
    "sg:classifiers":[
        {
            "category":"Organizations",
            "subcategory":"Non-profit Organization",
            "type":"Services"
        }
    ],
    "sg:phone":"+1 504 897 0143",
    "sg:postcode":"70115",
    "sg:province":"LA",
    "sg:website":"www.nojcc.com",
    "wof:name":"Jewish Community Ctr",
    "wof:placetype":"venue"
},
  "geometry": {"coordinates":[-90.111797,29.927829],"type":"Point"}
}