{
  "type": "Feature",
  "properties": {
    "addr:full":"4415 Shores Dr Metairie LA 70006",
    "addr:housenumber":"4415",
    "addr:postcode":"70006",
    "addr:street":"Shores Dr",
    "iso:country":"US",
    "sg:address":"4415 Shores Dr",
    "sg:city":"Metairie",
    "sg:classifiers":[
        {
            "category":"Utilities",
            "subcategory":"Telephone",
            "type":"Services"
        }
    ],
    "sg:phone":"+1 504 457 0300",
    "sg:postcode":"70006",
    "sg:province":"LA",
    "sg:tags":[
        "communications"
    ],
    "wof:name":"Evercom Systems",
    "wof:placetype":"venue"
},
  "geometry": {"coordinates":[-90.189387,30.018851],"type":"Point"}
}