{
  "type": "Feature",
  "properties": {
    "addr:full":"1002 Highland Ave Shreveport LA 71101",
    "addr:housenumber":"1002",
    "addr:postcode":"71101",
    "addr:street":"Highland Ave",
    "iso:country":"US",
    "sg:address":"1002 Highland Ave",
    "sg:city":"Shreveport",
    "sg:classifiers":[
        {
            "category":"Health Services",
            "subcategory":"Doctor",
            "type":"Services"
        }
    ],
    "sg:phone":"+1 318 222 6226",
    "sg:postcode":"71101",
    "sg:province":"LA",
    "sg:tags":[
        "clinic"
    ],
    "wof:name":"Brentwood Outpatient Ctr",
    "wof:placetype":"venue"
},
  "geometry": {"coordinates":[-93.73969700000001,32.501804],"type":"Point"}
}