{
  "type": "Feature",
  "properties": {
    "iso:country":"US",
    "sg:address":"2912 David Dr",
    "sg:city":"Metairie",
    "sg:classifiers":[
        {
            "category":"Retail",
            "subcategory":"Laundry & Dry Cleaning",
            "type":"Services"
        }
    ],
    "sg:phone":"+1 504 455 5000",
    "sg:postcode":"70003",
    "sg:province":"LA",
    "sg:tags":[
        "cleaners"
    ],
    "wof:name":"Super Cleaners Inc",
    "wof:placetype":"venue"
},
  "geometry": {"coordinates":[-90.220343,30.003762],"type":"Point"}
}