{
  "type": "Feature",
  "properties": {
    "iso:country":"US",
    "sg:address":"8210 Kurthwood Rd",
    "sg:city":"Leesville",
    "sg:classifiers":[
        {
            "category":"Bars & Pubs",
            "type":"Food & Drink"
        }
    ],
    "sg:phone":"+1 337 239 0125",
    "sg:postcode":"71446",
    "sg:province":"LA",
    "wof:name":"Gamemasters Bar",
    "wof:placetype":"venue"
},
  "geometry": {"coordinates":[-93.256445,31.164848],"type":"Point"}
}