{
  "type": "Feature",
  "properties": {
    "addr:full":"2426 Mistletoe St New Orleans LA 70118",
    "addr:housenumber":"2426",
    "addr:postcode":"70118",
    "addr:street":"Mistletoe St",
    "iso:country":"US",
    "sg:address":"2426 Mistletoe St",
    "sg:city":"New Orleans",
    "sg:classifiers":[
        {
            "category":"Building & Trades",
            "subcategory":"Construction",
            "type":"Services"
        }
    ],
    "sg:phone":"+1 504 861 0082",
    "sg:postcode":"70118",
    "sg:province":"LA",
    "sg:tags":[
        "general",
        "contractor"
    ],
    "wof:name":"Slambeaux Construction Inc",
    "wof:placetype":"venue"
},
  "geometry": {"coordinates":[-90.128975,29.963995],"type":"Point"}
}