{
  "type": "Feature",
  "properties": {
    "iso:country":"US",
    "sg:address":"2729 Lee Dr",
    "sg:city":"Pierre Part",
    "sg:classifiers":[
        {
            "category":"Sports & Exercise",
            "subcategory":"Gym",
            "type":"Entertainment"
        }
    ],
    "sg:phone":"+1 985 252 3533",
    "sg:postcode":"70339",
    "sg:province":"LA",
    "sg:tags":[
        "club",
        "health",
        "studio",
        "gymnasium"
    ],
    "wof:name":"Le Physique Fitness Ctr",
    "wof:placetype":"venue"
},
  "geometry": {"coordinates":[-91.19765700000001,29.983145],"type":"Point"}
}