{
  "type": "Feature",
  "properties": {
    "addr:full":"4400 State Rte 153 Creston LA 71070",
    "addr:housenumber":"4400",
    "addr:postcode":"71070",
    "addr:street":"State Rte 153",
    "iso:country":"US",
    "sg:address":"4400 State Rte 153",
    "sg:city":"Creston",
    "sg:classifiers":[
        {
            "category":"Government",
            "subcategory":"Fire Station",
            "type":"Public Place"
        }
    ],
    "sg:phone":"+1 318 875 2191",
    "sg:postcode":"71070",
    "sg:province":"LA",
    "sg:tags":[
        "department"
    ],
    "wof:name":"Creston Fire Dept",
    "wof:placetype":"venue"
},
  "geometry": {"coordinates":[-93.085835,32.024738],"type":"Point"}
}