{
  "type": "Feature",
  "properties": {
    "iso:country":"US",
    "sg:address":"5825 Florida Blvd",
    "sg:city":"Baton Rouge",
    "sg:classifiers":[
        {
            "category":"Government",
            "subcategory":"Office",
            "type":"Public Place"
        }
    ],
    "sg:phone":"+1 225 922 1346",
    "sg:postcode":"70806",
    "sg:province":"LA",
    "sg:website":"www.ldaf.state.la.us",
    "wof:name":"Dairy Stabilization",
    "wof:placetype":"venue"
},
  "geometry": {"coordinates":[-91.130427,30.451262],"type":"Point"}
}