{
  "type": "Feature",
  "properties": {
    "iso:country":"US",
    "sg:address":"122 Mark Dr",
    "sg:city":"Des Allemands",
    "sg:classifiers":[
        {
            "category":"Home & Garden",
            "subcategory":"Home Furnishings",
            "type":"Retail Goods"
        }
    ],
    "sg:phone":"+1 985 758 7184",
    "sg:postcode":"70030",
    "sg:province":"LA",
    "sg:tags":[
        "curtain",
        "made",
        "drapery"
    ],
    "wof:name":"Windows Of Elegance",
    "wof:placetype":"venue"
},
  "geometry": {"coordinates":[-90.425453,29.809257],"type":"Point"}
}