{
  "type": "Feature",
  "properties": {
    "iso:country":"US",
    "sg:address":"395 Hudson Rd",
    "sg:city":"Farmerville",
    "sg:classifiers":[
        {
            "category":"Building & Trades",
            "subcategory":"Pest Control",
            "type":"Services"
        }
    ],
    "sg:phone":"+1 318 368 9036",
    "sg:postcode":"71241",
    "sg:province":"LA",
    "wof:name":"D'Arbonne Pest Control",
    "wof:placetype":"venue"
},
  "geometry": {"coordinates":[-92.37273999999999,32.788979],"type":"Point"}
}