{
  "type": "Feature",
  "properties": {
    "iso:country":"US",
    "sg:address":"8701 Airline Dr",
    "sg:city":"Metairie",
    "sg:classifiers":[
        {
            "category":"Food & Beverages",
            "subcategory":"Groceries & Convenience Stores",
            "type":"Retail Goods"
        }
    ],
    "sg:phone":"+1 504 467 9634",
    "sg:postcode":"70003",
    "sg:province":"LA",
    "wof:name":"Airport Convenience Store",
    "wof:placetype":"venue"
},
  "geometry": {"coordinates":[-90.23269500000001,29.979229],"type":"Point"}
}