{
  "type": "Feature",
  "properties": {
    "addr:full":"1124 Huey P Long Ave Gretna LA 70053",
    "addr:housenumber":"1124;p",
    "addr:postcode":"70053",
    "addr:street":"Huey;Long Ave",
    "iso:country":"US",
    "sg:address":"1124 Huey P Long Ave",
    "sg:city":"Gretna",
    "sg:classifiers":[
        {
            "category":"Banks & Credit Unions",
            "subcategory":"Financial Services",
            "type":"Services"
        }
    ],
    "sg:phone":"+1 504 367 6670",
    "sg:postcode":"70053",
    "sg:province":"LA",
    "sg:tags":[
        "broker",
        "mortgage"
    ],
    "wof:name":"Assured Mortgage Co & Financial Services Inc",
    "wof:placetype":"venue"
},
  "geometry": {"coordinates":[-90.059898,29.9097],"type":"Point"}
}