{
  "type": "Feature",
  "properties": {
    "iso:country":"US",
    "sg:address":"4100 North Blvd",
    "sg:city":"Baton Rouge",
    "sg:classifiers":[
        {
            "category":"Health Services",
            "subcategory":"Nursing And Care Facility",
            "type":"Services"
        }
    ],
    "sg:phone":"+1 225 387 6704",
    "sg:postcode":"70806",
    "sg:province":"LA",
    "sg:tags":[
        "home",
        "convalescent"
    ],
    "wof:name":"Hillhaven Nursing Ctr",
    "wof:placetype":"venue"
},
  "geometry": {"coordinates":[-91.14632,30.448487],"type":"Point"}
}