{
  "type": "Feature",
  "properties": {
    "iso:country":"US",
    "sg:address":"4610 South Dr",
    "sg:city":"Jefferson",
    "sg:classifiers":[
        {
            "category":"Building & Trades",
            "subcategory":"Electrical",
            "type":"Services"
        }
    ],
    "sg:phone":"+1 504 734 7062",
    "sg:postcode":"70121",
    "sg:province":"LA",
    "sg:tags":[
        "electric",
        "contractor"
    ],
    "wof:name":"Foto Electric",
    "wof:placetype":"venue"
},
  "geometry": {"coordinates":[-90.173652,29.954021],"type":"Point"}
}