{
  "type": "Feature",
  "properties": {
    "addr:full":"2720 State Rte 182 Morgan City LA 70380",
    "addr:housenumber":"2720",
    "addr:postcode":"70380",
    "addr:street":"State Rte 182 Morgan",
    "iso:country":"US",
    "sg:address":"2720 State Rte 182",
    "sg:city":"Morgan City",
    "sg:classifiers":[
        {
            "category":"Professional",
            "subcategory":"Accounting & Tax Preparation",
            "type":"Services"
        }
    ],
    "sg:phone":"+1 985 395 9311",
    "sg:postcode":"70380",
    "sg:province":"LA",
    "sg:tags":[
        "bookkeeping",
        "general"
    ],
    "wof:name":"Mayon's Accounting & Tax Svc",
    "wof:placetype":"venue"
},
  "geometry": {"coordinates":[-91.26373100000001,29.704293],"type":"Point"}
}