{
  "type": "Feature",
  "properties": {
    "iso:country":"US",
    "sg:address":"120 S State St",
    "sg:city":"Abbeville",
    "sg:classifiers":[
        {
            "category":"Real Estate",
            "subcategory":"Real Estate Services",
            "type":"Services"
        }
    ],
    "sg:phone":"+1 337 740 3673",
    "sg:postcode":"70510",
    "sg:province":"LA",
    "wof:name":"Todd Dore Inc",
    "wof:placetype":"venue"
},
  "geometry": {"coordinates":[-92.13576500000001,29.973807],"type":"Point"}
}