{
  "type": "Feature",
  "properties": {
    "iso:country":"US",
    "sg:address":"207 W Worthy St",
    "sg:city":"Gonzales",
    "sg:classifiers":[
        {
            "category":"Manufacturing",
            "subcategory":"Printing",
            "type":"Manufacturing & Wholesale Goods"
        }
    ],
    "sg:phone":"+1 225 647 2625",
    "sg:postcode":"70737",
    "sg:province":"LA",
    "sg:tags":[
        "printer"
    ],
    "wof:name":"Sprint Print",
    "wof:placetype":"venue"
},
  "geometry": {"coordinates":[-90.921581,30.225494],"type":"Point"}
}