{
  "type": "Feature",
  "properties": {
    "iso:country":"US",
    "sg:address":"7840 Florida Blvd",
    "sg:city":"Baton Rouge",
    "sg:classifiers":[
        {
            "category":"Personal",
            "subcategory":"Shoe Repair & Shine",
            "type":"Services"
        }
    ],
    "sg:phone":"+1 225 926 9842",
    "sg:postcode":"70806",
    "sg:province":"LA",
    "sg:tags":[
        "repairing",
        "boot"
    ],
    "wof:name":"Edgewood Shoe Svc",
    "wof:placetype":"venue"
},
  "geometry": {"coordinates":[-91.106521,30.451889],"type":"Point"}
}