{
  "type": "Feature",
  "properties": {
    "iso:country":"US",
    "sg:address":"200 Trotter St",
    "sg:city":"New Iberia",
    "sg:classifiers":[
        {
            "category":"Freight",
            "type":"Transportation"
        }
    ],
    "sg:phone":"+1 337 364 2898",
    "sg:postcode":"70563",
    "sg:province":"LA",
    "sg:tags":[
        "packing",
        "crating"
    ],
    "wof:name":"Industrial Wood Products Of LA",
    "wof:placetype":"venue"
},
  "geometry": {"coordinates":[-91.808149,30.012169],"type":"Point"}
}