{
  "type": "Feature",
  "properties": {
    "iso:country":"US",
    "sg:address":"400 Skipper St",
    "sg:city":"Breaux Bridge",
    "sg:classifiers":[
        {
            "category":"Shopping",
            "subcategory":"Clothing, Apparel, & Fashions",
            "type":"Retail Goods"
        }
    ],
    "sg:phone":"+1 337 332 5358",
    "sg:postcode":"70517",
    "sg:province":"LA",
    "wof:name":"Candys Fashions Custom Tlrg",
    "wof:placetype":"venue"
},
  "geometry": {"coordinates":[-91.90003900000001,30.266772],"type":"Point"}
}