{
  "type": "Feature",
  "properties": {
    "iso:country":"US",
    "sg:address":"2722 Savage Forks Rd",
    "sg:city":"Leesville",
    "sg:classifiers":[
        {
            "category":"Building & Trades",
            "subcategory":"Landscaping Services",
            "type":"Services"
        }
    ],
    "sg:phone":"+1 337 239 3126",
    "sg:postcode":"71446",
    "sg:province":"LA",
    "wof:name":"Rogers Tree Svc & Ldscp Contr",
    "wof:placetype":"venue"
},
  "geometry": {"coordinates":[-93.31191200000001,31.079743],"type":"Point"}
}