{
  "type": "Feature",
  "properties": {
    "addr:full":"41452 Fritchie Ln Slidell LA 70461",
    "addr:postcode":"41452;70461",
    "addr:street":"Fritchie Ln",
    "iso:country":"US",
    "sg:address":"41452 Fritchie Ln",
    "sg:city":"Slidell",
    "sg:classifiers":[
        {
            "category":"Professional",
            "type":"Services"
        }
    ],
    "sg:phone":"+1 985 649 6933",
    "sg:postcode":"70461",
    "sg:province":"LA",
    "sg:tags":[
        "establishment"
    ],
    "wof:name":"Hernandez & Hernandez",
    "wof:placetype":"venue"
},
  "geometry": {"coordinates":[-89.709312,30.301119],"type":"Point"}
}