{
  "type": "Feature",
  "properties": {
    "iso:country":"US",
    "sg:address":"1869 Ames Blvd",
    "sg:city":"Marrero",
    "sg:classifiers":[
        {
            "category":"Government",
            "subcategory":"Office",
            "type":"Public Place"
        }
    ],
    "sg:phone":"+1 504 349 5111",
    "sg:postcode":"70072",
    "sg:province":"LA",
    "wof:name":"Jefferson Parish Anmal Shelter",
    "wof:placetype":"venue"
},
  "geometry": {"coordinates":[-90.11405499999999,29.881465],"type":"Point"}
}