{
  "type": "Feature",
  "properties": {
    "addr:full":"315 Neal St Ruston LA 71270",
    "addr:housenumber":"315",
    "addr:postcode":"71270",
    "addr:street":"Neal St",
    "iso:country":"US",
    "sg:address":"315 Neal St",
    "sg:city":"Ruston",
    "sg:classifiers":[
        {
            "category":"Retail",
            "subcategory":"Auto Repair",
            "type":"Services"
        }
    ],
    "sg:phone":"+1 318 255 9467",
    "sg:postcode":"71270",
    "sg:province":"LA",
    "sg:tags":[
        "truck"
    ],
    "wof:name":"Truck Service Corp",
    "wof:placetype":"venue"
},
  "geometry": {"coordinates":[-92.62373100000001,32.529602],"type":"Point"}
}