{
  "type": "Feature",
  "properties": {
    "iso:country":"US",
    "sg:address":"1204 W 21st Ave",
    "sg:city":"Covington",
    "sg:classifiers":[
        {
            "category":"Restaurant",
            "type":"Food & Drink"
        }
    ],
    "sg:phone":"+1 985 892 3287",
    "sg:postcode":"70433",
    "sg:province":"LA",
    "sg:tags":[
        "caterer"
    ],
    "wof:name":"Catering By Don",
    "wof:placetype":"venue"
},
  "geometry": {"coordinates":[-90.11193,30.481855],"type":"Point"}
}