{
  "type": "Feature",
  "properties": {
    "iso:country":"US",
    "sg:address":"1329 Grant Ave",
    "sg:city":"Breaux Bridge",
    "sg:classifiers":[
        {
            "category":"Health Services",
            "subcategory":"Doctor",
            "type":"Services"
        }
    ],
    "sg:phone":"+1 337 332 2412",
    "sg:postcode":"70517",
    "sg:province":"LA",
    "sg:tags":[
        "dentist"
    ],
    "wof:name":"Family & Cosmetic Dental Ctr",
    "wof:placetype":"venue"
},
  "geometry": {"coordinates":[-91.887393,30.276827],"type":"Point"}
}