{
  "type": "Feature",
  "properties": {
    "iso:country":"US",
    "sg:address":"403 Museum St",
    "sg:city":"Oil City",
    "sg:classifiers":[
        {
            "category":"Autos & Motor Vehicles",
            "subcategory":"Automobile Sales",
            "type":"Retail Goods"
        }
    ],
    "sg:phone":"+1 318 995 0903",
    "sg:postcode":"71061",
    "sg:province":"LA",
    "sg:tags":[
        "car",
        "dealer"
    ],
    "wof:name":"Poindexter Auto Sales",
    "wof:placetype":"venue"
},
  "geometry": {"coordinates":[-93.97617,32.75172],"type":"Point"}
}