{
  "type": "Feature",
  "properties": {
    "addr:full":"6600 Spanish Fort Blvd New Orleans LA 70124",
    "addr:housenumber":"6600",
    "addr:postcode":"70124",
    "addr:street":"Spanish Fort Blvd",
    "iso:country":"US",
    "sg:address":"6600 Spanish Fort Blvd",
    "sg:city":"New Orleans",
    "sg:classifiers":[
        {
            "category":"Education",
            "subcategory":"School",
            "type":"Public Place"
        }
    ],
    "sg:phone":"+1 504 282 2811",
    "sg:postcode":"70124",
    "sg:province":"LA",
    "sg:website":"www.spxmensclub.org",
    "wof:name":"St Pius X School",
    "wof:placetype":"venue"
},
  "geometry": {"coordinates":[-90.090619,30.023155],"type":"Point"}
}