{
  "type": "Feature",
  "properties": {
    "iso:country":"US",
    "sg:address":"603 W Admiral Doyle Dr # F",
    "sg:city":"New Iberia",
    "sg:classifiers":[
        {
            "category":"Professional",
            "subcategory":"Lawyer & Legal Services",
            "type":"Services"
        },
        {
            "category":"Home & Garden",
            "subcategory":"Carpets & Floor Coverings",
            "type":"Retail Goods"
        }
    ],
    "sg:phone":"+1 337 365 6657",
    "sg:postcode":"70560",
    "sg:province":"LA",
    "sg:tags":[
        "notary",
        "mattress"
    ],
    "wof:name":"Fremin's Food & Furniture",
    "wof:placetype":"venue"
},
  "geometry": {"coordinates":[-91.8424,30.001699],"type":"Point"}
}