{
  "type": "Feature",
  "properties": {
    "addr:full":"1035 Oma St Natchitoches LA 71457",
    "addr:housenumber":"1035",
    "addr:postcode":"71457",
    "addr:street":"Oma St",
    "iso:country":"US",
    "sg:address":"1035 Oma St",
    "sg:city":"Natchitoches",
    "sg:classifiers":[
        {
            "category":"Professional",
            "subcategory":"Business Services",
            "type":"Services"
        }
    ],
    "sg:phone":"+1 318 352 5734",
    "sg:postcode":"71457",
    "sg:province":"LA",
    "wof:name":"Triple M Enterprises Inc",
    "wof:placetype":"venue"
},
  "geometry": {"coordinates":[-93.08255800000001,31.768891],"type":"Point"}
}