{
  "type": "Feature",
  "properties": {
    "addr:full":"207 Mary Ann St St Martinville LA 70582",
    "addr:housenumber":"207",
    "addr:postcode":"70582",
    "addr:street":"Mary Ann St St",
    "iso:country":"US",
    "sg:address":"207 Mary Ann St",
    "sg:city":"St Martinville",
    "sg:classifiers":[
        {
            "category":"Building & Trades",
            "subcategory":"Landscaping Services",
            "type":"Services"
        }
    ],
    "sg:phone":"+1 337 394 3224",
    "sg:postcode":"70582",
    "sg:province":"LA",
    "sg:tags":[
        "lawn",
        "maintenance",
        "grounds"
    ],
    "wof:name":"Donald's Lawn Svc",
    "wof:placetype":"venue"
},
  "geometry": {"coordinates":[-91.837738,30.110926],"type":"Point"}
}