{
  "type": "Feature",
  "properties": {
    "iso:country":"US",
    "sg:address":"136 S Broad St",
    "sg:city":"New Orleans",
    "sg:classifiers":[
        {
            "category":"Restaurant",
            "type":"Food & Drink"
        }
    ],
    "sg:phone":"+1 504 827 0220",
    "sg:postcode":"70119",
    "sg:province":"LA",
    "wof:name":"Subway Sandwiches & Salads",
    "wof:placetype":"venue"
},
  "geometry": {"coordinates":[-90.087577,29.96511],"type":"Point"}
}