{
  "type": "Feature",
  "properties": {
    "addr:full":"8460 US Hwy 190 Merryville LA 70653",
    "addr:housenumber":"8460",
    "addr:postcode":"70653",
    "addr:street":"Us Hwy 190",
    "iso:country":"US",
    "sg:address":"8460 US Hwy 190",
    "sg:city":"Merryville",
    "sg:classifiers":[
        {
            "category":"Food & Beverages",
            "subcategory":"Groceries & Convenience Stores",
            "type":"Retail Goods"
        }
    ],
    "sg:phone":"+1 337 825 6922",
    "sg:postcode":"70653",
    "sg:province":"LA",
    "sg:tags":[
        "grocer"
    ],
    "wof:name":"Junction Grocery",
    "wof:placetype":"venue"
},
  "geometry": {"coordinates":[-93.510372,30.833054],"type":"Point"}
}