{
  "type": "Feature",
  "properties": {
    "iso:country":"US",
    "sg:address":"2250 Myrtle Ave",
    "sg:city":"Baton Rouge",
    "sg:classifiers":[
        {
            "category":"Professional",
            "subcategory":"Lawyer & Legal Services",
            "type":"Services"
        }
    ],
    "sg:phone":"+1 225 344 7651",
    "sg:postcode":"70806",
    "sg:province":"LA",
    "sg:tags":[
        "attorney"
    ],
    "wof:name":"W Scott Maxwell",
    "wof:placetype":"venue"
},
  "geometry": {"coordinates":[-91.16427400000001,30.438565],"type":"Point"}
}