{
  "type": "Feature",
  "properties": {
    "addr:full":"139 Creek St Trout LA 71378",
    "addr:housenumber":"139",
    "addr:postcode":"71378",
    "addr:street":"Creek St",
    "iso:country":"US",
    "sg:address":"139 Creek St",
    "sg:city":"Trout",
    "sg:classifiers":[
        {
            "category":"Organizations",
            "subcategory":"Religious Organization",
            "type":"Services"
        }
    ],
    "sg:phone":"+1 318 992 5806",
    "sg:postcode":"71378",
    "sg:province":"LA",
    "wof:name":"Antioch Free Methodist Church",
    "wof:placetype":"venue"
},
  "geometry": {"coordinates":[-91.653098,31.985014],"type":"Point"}
}