{
  "type": "Feature",
  "properties": {
    "iso:country":"US",
    "sg:address":"369 Cope Dr",
    "sg:city":"Shreveport",
    "sg:classifiers":[
        {
            "category":"Professional",
            "subcategory":"Business Services",
            "type":"Services"
        }
    ],
    "sg:phone":"+1 318 797 6837",
    "sg:postcode":"71106",
    "sg:province":"LA",
    "sg:tags":[
        "plant",
        "design",
        "maintenance"
    ],
    "wof:name":"Living Interiors",
    "wof:placetype":"venue"
},
  "geometry": {"coordinates":[-93.69565,32.361455],"type":"Point"}
}