{
  "type": "Feature",
  "properties": {
    "iso:country":"US",
    "sg:address":"103 S Monroe St",
    "sg:city":"Minden",
    "sg:classifiers":[
        {
            "category":"Communications",
            "type":"Services"
        }
    ],
    "sg:phone":"+1 318 000 1111",
    "sg:postcode":"71055",
    "sg:province":"LA",
    "wof:name":"Webster Communication District",
    "wof:placetype":"venue"
},
  "geometry": {"coordinates":[-93.288579,32.616124],"type":"Point"}
}