{
  "type": "Feature",
  "properties": {
    "iso:country":"US",
    "sg:address":"1222 Barrow St",
    "sg:city":"Houma",
    "sg:classifiers":[
        {
            "category":"Building & Trades",
            "subcategory":"Construction",
            "type":"Services"
        }
    ],
    "sg:phone":"+1 985 879 1501",
    "sg:postcode":"70360",
    "sg:province":"LA",
    "sg:tags":[
        "contractor"
    ],
    "wof:name":"National Building & Contr Co",
    "wof:placetype":"venue"
},
  "geometry": {"coordinates":[-90.720815,29.587429],"type":"Point"}
}