{
  "type": "Feature",
  "properties": {
    "addr:full":"1026 Ave A Marrero LA 70072",
    "addr:housenumber":"1026",
    "addr:postcode":"70072",
    "addr:street":"Ave A Marrero",
    "iso:country":"US",
    "sg:address":"1026 Ave A",
    "sg:city":"Marrero",
    "sg:classifiers":[
        {
            "category":"Bars & Pubs",
            "type":"Food & Drink"
        }
    ],
    "sg:phone":"+1 504 328 1116",
    "sg:postcode":"70072",
    "sg:province":"LA",
    "wof:name":"Whitney's Fishing Hole",
    "wof:placetype":"venue"
},
  "geometry": {"coordinates":[-90.092681,29.892746],"type":"Point"}
}