{
  "type": "Feature",
  "properties": {
    "addr:full":"5801 Main St Zachary LA 70791",
    "addr:housenumber":"5801",
    "addr:postcode":"70791",
    "addr:street":"Main St",
    "iso:country":"US",
    "sg:address":"5801 Main St",
    "sg:city":"Zachary",
    "sg:classifiers":[
        {
            "category":"Restaurant",
            "type":"Food & Drink"
        }
    ],
    "sg:menulink":"http://www.allmenus.com/la/zachary/132122-subway/menu/",
    "sg:phone":"+1 225 658 5815",
    "sg:postcode":"70791",
    "sg:province":"LA",
    "sg:tags":[
        "american",
        "sandwich"
    ],
    "wof:name":"Subway",
    "wof:placetype":"venue"
},
  "geometry": {"coordinates":[-91.14425300000001,30.648094],"type":"Point"}
}