{
  "type": "Feature",
  "properties": {
    "addr:full":"18510 Perkins Oak Rd Prairieville LA 70769",
    "addr:housenumber":"18510",
    "addr:postcode":"70769",
    "addr:street":"Perkins Oak Rd",
    "iso:country":"US",
    "sg:address":"18510 Perkins Oak Rd",
    "sg:city":"Prairieville",
    "sg:classifiers":[
        {
            "category":"Manufacturing",
            "subcategory":"Tools & Machinery",
            "type":"Manufacturing & Wholesale Goods"
        }
    ],
    "sg:phone":"+1 225 673 6285",
    "sg:postcode":"70769",
    "sg:province":"LA",
    "sg:tags":[
        "machine",
        "shop"
    ],
    "wof:name":"Salco Inc",
    "wof:placetype":"venue"
},
  "geometry": {"coordinates":[-90.990354,30.336017],"type":"Point"}
}