{
  "type": "Feature",
  "properties": {
    "addr:full":"2505 E Prien Lake Rd Lake Charles LA 70601",
    "addr:housenumber":"2505",
    "addr:postcode":"70601",
    "addr:street":"E Prien Lake Rd",
    "iso:country":"US",
    "sg:address":"2505 E Prien Lake Rd",
    "sg:city":"Lake Charles",
    "sg:classifiers":[
        {
            "category":"Food & Beverages",
            "subcategory":"Groceries & Convenience Stores",
            "type":"Retail Goods"
        }
    ],
    "sg:phone":"+1 337 478 7698",
    "sg:postcode":"70601",
    "sg:province":"LA",
    "wof:name":"Circle K",
    "wof:placetype":"venue"
},
  "geometry": {"coordinates":[-93.185125,30.198247],"type":"Point"}
}