{
  "type": "Feature",
  "properties": {
    "iso:country":"US",
    "sg:address":"801 New Natchitoches Rd",
    "sg:city":"West Monroe",
    "sg:classifiers":[
        {
            "category":"Food & Beverages",
            "subcategory":"Groceries & Convenience Stores",
            "type":"Retail Goods"
        }
    ],
    "sg:phone":"+1 318 651 9900",
    "sg:postcode":"71292",
    "sg:province":"LA",
    "sg:tags":[
        "grocer"
    ],
    "wof:name":"Singh Grocery",
    "wof:placetype":"venue"
},
  "geometry": {"coordinates":[-92.17541,32.49225],"type":"Point"}
}