{
  "type": "Feature",
  "properties": {
    "iso:country":"US",
    "sg:address":"4441 Burbank Dr",
    "sg:city":"Baton Rouge",
    "sg:classifiers":[
        {
            "category":"Building & Trades",
            "subcategory":"Construction",
            "type":"Services"
        }
    ],
    "sg:phone":"+1 225 769 0380",
    "sg:postcode":"70820",
    "sg:province":"LA",
    "sg:tags":[
        "contractor"
    ],
    "wof:name":"Baronne's Construction",
    "wof:placetype":"venue"
},
  "geometry": {"coordinates":[-91.17302599999999,30.399321],"type":"Point"}
}