{
  "type": "Feature",
  "properties": {
    "iso:country":"US",
    "sg:address":"905 Live Oak St",
    "sg:city":"Lake Charles",
    "sg:classifiers":[
        {
            "category":"Arts & Performance",
            "subcategory":"Theater",
            "type":"Entertainment"
        }
    ],
    "sg:phone":"+1 337 436 7149",
    "sg:postcode":"70601",
    "sg:province":"LA",
    "sg:tags":[
        "group"
    ],
    "wof:name":"Big South Entertainment",
    "wof:placetype":"venue"
},
  "geometry": {"coordinates":[-93.208586,30.210177],"type":"Point"}
}