{
  "type": "Feature",
  "properties": {
    "addr:full":"3375 Weber Dr Vacherie LA 70090",
    "addr:housenumber":"3375",
    "addr:postcode":"70090",
    "addr:street":"Weber Dr",
    "iso:country":"US",
    "sg:address":"3375 Weber Dr",
    "sg:city":"Vacherie",
    "sg:classifiers":[
        {
            "category":"Building & Trades",
            "subcategory":"Construction",
            "type":"Services"
        }
    ],
    "sg:phone":"+1 225 265 4511",
    "sg:postcode":"70090",
    "sg:province":"LA",
    "sg:tags":[
        "general",
        "contractor"
    ],
    "wof:name":"Housing Authority",
    "wof:placetype":"venue"
},
  "geometry": {"coordinates":[-90.783447,29.9929],"type":"Point"}
}