{
  "type": "Feature",
  "properties": {
    "addr:full":"6206 Mansfield Rd Shreveport LA 71108",
    "addr:housenumber":"6206",
    "addr:postcode":"71108",
    "addr:street":"Mansfield Rd",
    "iso:country":"US",
    "sg:address":"6206 Mansfield Rd",
    "sg:city":"Shreveport",
    "sg:classifiers":[
        {
            "category":"Professional",
            "subcategory":"Business Services",
            "type":"Services"
        }
    ],
    "sg:phone":"+1 318 636 0662",
    "sg:postcode":"71108",
    "sg:province":"LA",
    "sg:tags":[
        "recording",
        "studio"
    ],
    "wof:name":"Gospel Unlimited Bookstore",
    "wof:placetype":"venue"
},
  "geometry": {"coordinates":[-93.778963,32.44929],"type":"Point"}
}