{
  "type": "Feature",
  "properties": {
    "iso:country":"US",
    "sg:address":"2964 Plank Rd",
    "sg:city":"Baton Rouge",
    "sg:classifiers":[
        {
            "category":"Professional",
            "type":"Services"
        }
    ],
    "sg:phone":"+1 225 355 3318",
    "sg:postcode":"70805",
    "sg:province":"LA",
    "wof:name":"Doan Inc MAI B T",
    "wof:placetype":"venue"
},
  "geometry": {"coordinates":[-91.16191999999999,30.474605],"type":"Point"}
}