{
  "type": "Feature",
  "properties": {
    "iso:country":"US",
    "sg:address":"3810 Veterans Memorial Blvd",
    "sg:city":"Metairie",
    "sg:classifiers":[
        {
            "category":"Freight",
            "type":"Transportation"
        }
    ],
    "sg:phone":"+1 504 885 4544",
    "sg:postcode":"70006",
    "sg:province":"LA",
    "sg:tags":[
        "mover"
    ],
    "wof:name":"New Orleans Shipping & Pckgng",
    "wof:placetype":"venue"
},
  "geometry": {"coordinates":[-90.169318,30.00443],"type":"Point"}
}