{
  "type": "Feature",
  "properties": {
    "iso:country":"US",
    "sg:address":"5057 Osborne Ave",
    "sg:city":"Baton Rouge",
    "sg:classifiers":[
        {
            "category":"Building & Trades",
            "subcategory":"Construction",
            "type":"Services"
        }
    ],
    "sg:phone":"+1 225 389 9612",
    "sg:postcode":"70805",
    "sg:province":"LA",
    "sg:tags":[
        "waterproofing",
        "contractor"
    ],
    "wof:name":"Associated Waterproofing Corp",
    "wof:placetype":"venue"
},
  "geometry": {"coordinates":[-91.135772,30.473146],"type":"Point"}
}