{
  "type": "Feature",
  "properties": {
    "iso:country":"US",
    "sg:address":"2179 State Rte 182",
    "sg:city":"Raceland",
    "sg:classifiers":[
        {
            "category":"Insurance",
            "subcategory":"Insurance Agent",
            "type":"Services"
        }
    ],
    "sg:phone":"+1 985 537 9616",
    "sg:postcode":"70394",
    "sg:province":"LA",
    "wof:name":"Jones Insurance Svc LLC",
    "wof:placetype":"venue"
},
  "geometry": {"coordinates":[-90.612472,29.72123],"type":"Point"}
}