{
  "type": "Feature",
  "properties": {
    "addr:full":"1020 Lee Rd Morgan City LA 70380",
    "addr:housenumber":"1020",
    "addr:postcode":"70380",
    "addr:street":"Lee Rd",
    "iso:country":"US",
    "sg:address":"1020 Lee Rd",
    "sg:city":"Morgan City",
    "sg:classifiers":[
        {
            "category":"Manufacturing",
            "subcategory":"Metals",
            "type":"Manufacturing & Wholesale Goods"
        }
    ],
    "sg:phone":"+1 985 631 4949",
    "sg:postcode":"70380",
    "sg:province":"LA",
    "wof:name":"Royal Eagle Svc LLC",
    "wof:placetype":"venue"
},
  "geometry": {"coordinates":[-91.122471,29.661686],"type":"Point"}
}