{
  "type": "Feature",
  "properties": {
    "iso:country":"US",
    "sg:address":"1616 S Columbia St",
    "sg:city":"Bogalusa",
    "sg:classifiers":[
        {
            "category":"Arts & Performance",
            "subcategory":"Theater",
            "type":"Entertainment"
        }
    ],
    "sg:phone":"+1 985 732 2211",
    "sg:postcode":"70427",
    "sg:province":"LA",
    "sg:tags":[
        "dance",
        "company"
    ],
    "wof:name":"All That Jazz With Ashley",
    "wof:placetype":"venue"
},
  "geometry": {"coordinates":[-89.851146,30.758882],"type":"Point"}
}