{
  "type": "Feature",
  "properties": {
    "addr:full":"919 Granada Dr New Iberia LA 70560",
    "addr:housenumber":"919",
    "addr:postcode":"70560",
    "addr:street":"Granada Dr",
    "iso:country":"US",
    "sg:address":"919 Granada Dr",
    "sg:city":"New Iberia",
    "sg:classifiers":[
        {
            "category":"Manufacturing",
            "subcategory":"Tools & Machinery",
            "type":"Manufacturing & Wholesale Goods"
        }
    ],
    "sg:phone":"+1 337 364 9890",
    "sg:postcode":"70560",
    "sg:province":"LA",
    "sg:tags":[
        "machine",
        "shop"
    ],
    "wof:name":"Port Machine Shop",
    "wof:placetype":"venue"
},
  "geometry": {"coordinates":[-91.84252499999999,29.967833],"type":"Point"}
}