{
  "type": "Feature",
  "properties": {
    "addr:full":"711 Enterprise Blvd Lake Charles LA 70601",
    "addr:housenumber":"711",
    "addr:postcode":"70601",
    "addr:street":"Enterprise Blvd",
    "iso:country":"US",
    "sg:address":"711 Enterprise Blvd",
    "sg:city":"Lake Charles",
    "sg:classifiers":[
        {
            "category":"Autos & Motor Vehicles",
            "subcategory":"Auto Supplies",
            "type":"Retail Goods"
        }
    ],
    "sg:phone":"+1 337 433 0584",
    "sg:postcode":"70601",
    "sg:province":"LA",
    "sg:tags":[
        "automobile",
        "parts"
    ],
    "wof:name":"Bumper To Bumper",
    "wof:placetype":"venue"
},
  "geometry": {"coordinates":[-93.204195,30.22853],"type":"Point"}
}