{
  "type": "Feature",
  "properties": {
    "iso:country":"US",
    "sg:address":"1501 8th St",
    "sg:city":"Harvey",
    "sg:classifiers":[
        {
            "category":"Manufacturing",
            "subcategory":"Printing",
            "type":"Manufacturing & Wholesale Goods"
        }
    ],
    "sg:phone":"+1 504 368 3327",
    "sg:postcode":"70058",
    "sg:province":"LA",
    "sg:tags":[
        "printer"
    ],
    "wof:name":"Dumag Printing & Snap Out Frms",
    "wof:placetype":"venue"
},
  "geometry": {"coordinates":[-90.067832,29.906216],"type":"Point"}
}