{
  "type": "Feature",
  "properties": {
    "iso:country":"US",
    "sg:address":"2749 Toulouse St",
    "sg:city":"New Orleans",
    "sg:classifiers":[
        {
            "category":"Professional",
            "subcategory":"Management & Consulting",
            "type":"Services"
        }
    ],
    "sg:phone":"+1 504 488 1300",
    "sg:postcode":"70119",
    "sg:province":"LA",
    "sg:tags":[
        "consultant",
        "business"
    ],
    "wof:name":"Major Services Inc",
    "wof:placetype":"venue"
},
  "geometry": {"coordinates":[-90.08396399999999,29.969607],"type":"Point"}
}