{
  "type": "Feature",
  "properties": {
    "iso:country":"US",
    "sg:address":"406 Woodvale Ave",
    "sg:city":"Lafayette",
    "sg:classifiers":[
        {
            "category":"Professional",
            "subcategory":"Management & Consulting",
            "type":"Services"
        }
    ],
    "sg:phone":"+1 337 981 3829",
    "sg:postcode":"70503",
    "sg:province":"LA",
    "sg:tags":[
        "business"
    ],
    "wof:name":"Kenny Consultants William H",
    "wof:placetype":"venue"
},
  "geometry": {"coordinates":[-92.04698999999999,30.197325],"type":"Point"}
}