{
  "type": "Feature",
  "properties": {
    "addr:full":"2360 Kingston St Kenner LA 70062",
    "addr:housenumber":"2360",
    "addr:postcode":"70062",
    "addr:street":"Kingston St",
    "iso:country":"US",
    "sg:address":"2360 Kingston St",
    "sg:city":"Kenner",
    "sg:classifiers":[
        {
            "category":"Retail",
            "subcategory":"Auto Repair",
            "type":"Services"
        }
    ],
    "sg:phone":"+1 504 469 2005",
    "sg:postcode":"70062",
    "sg:province":"LA",
    "sg:tags":[
        "body",
        "automobile",
        "painting"
    ],
    "wof:name":"Don's Unique Auto Inc",
    "wof:placetype":"venue"
},
  "geometry": {"coordinates":[-90.26956,30.000282],"type":"Point"}
}