{
  "type": "Feature",
  "properties": {
    "iso:country":"US",
    "sg:address":"515 E Washington St",
    "sg:city":"Shreveport",
    "sg:classifiers":[
        {
            "category":"Insurance",
            "subcategory":"Insurance Agent",
            "type":"Services"
        }
    ],
    "sg:phone":"+1 318 865 5600",
    "sg:postcode":"71104",
    "sg:province":"LA",
    "wof:name":"Mid South Measurements",
    "wof:placetype":"venue"
},
  "geometry": {"coordinates":[-93.72195600000001,32.484675],"type":"Point"}
}