{
  "type": "Feature",
  "properties": {
    "iso:country":"US",
    "sg:address":"39730 Les Rois Rd",
    "sg:city":"Gueydan",
    "sg:classifiers":[
        {
            "category":"Professional",
            "subcategory":"Management & Consulting",
            "type":"Services"
        }
    ],
    "sg:phone":"+1 337 774 5240",
    "sg:postcode":"70542",
    "sg:province":"LA",
    "wof:name":"Robert G Linscombe",
    "wof:placetype":"venue"
},
  "geometry": {"coordinates":[-92.638848,30.038106],"type":"Point"}
}