{
  "type": "Feature",
  "properties": {
    "iso:country":"US",
    "sg:address":"5817 Common St",
    "sg:city":"Lake Charles",
    "sg:classifiers":[
        {
            "category":"Autos & Motor Vehicles",
            "subcategory":"Boat Sales",
            "type":"Retail Goods"
        }
    ],
    "sg:phone":"+1 337 478 1291",
    "sg:postcode":"70607",
    "sg:province":"LA",
    "sg:tags":[
        "dealer",
        "sales"
    ],
    "wof:name":"DHP Enterprises",
    "wof:placetype":"venue"
},
  "geometry": {"coordinates":[-93.213722,30.154766],"type":"Point"}
}