{
  "type": "Feature",
  "properties": {
    "iso:country":"US",
    "sg:address":"2860 NE Evangeline Throughway",
    "sg:city":"Lafayette",
    "sg:classifiers":[
        {
            "category":"Freight",
            "type":"Transportation"
        }
    ],
    "sg:phone":"+1 337 264 9090",
    "sg:postcode":"70507",
    "sg:province":"LA",
    "sg:tags":[
        "commercial",
        "storage"
    ],
    "wof:name":"Evangeline Self Storage",
    "wof:placetype":"venue"
},
  "geometry": {"coordinates":[-92.01945499999999,30.278053],"type":"Point"}
}