{
  "type": "Feature",
  "properties": {
    "addr:full":"121 Oak Ave Bridge City LA 70094",
    "addr:housenumber":"121",
    "addr:postcode":"70094",
    "addr:street":"Oak Ave Bridge",
    "iso:country":"US",
    "sg:address":"121 Oak Ave",
    "sg:city":"Bridge City",
    "sg:classifiers":[
        {
            "category":"Professional",
            "subcategory":"Business Services",
            "type":"Services"
        }
    ],
    "sg:phone":"+1 504 436 7775",
    "sg:postcode":"70094",
    "sg:province":"LA",
    "sg:tags":[
        "diver"
    ],
    "wof:name":"Independent Diving Svc",
    "wof:placetype":"venue"
},
  "geometry": {"coordinates":[-90.153547,29.943701],"type":"Point"}
}