{
  "type": "Feature",
  "properties": {
    "addr:full":"113 E Gloria Switch Rd Lafayette LA 70507",
    "addr:housenumber":"113",
    "addr:postcode":"70507",
    "addr:street":"E Gloria Switch Rd",
    "iso:country":"US",
    "sg:address":"113 E Gloria Switch Rd",
    "sg:city":"Lafayette",
    "sg:classifiers":[
        {
            "category":"Professional",
            "type":"Services"
        }
    ],
    "sg:phone":"+1 337 267 4684",
    "sg:postcode":"70507",
    "sg:province":"LA",
    "sg:tags":[
        "establishment"
    ],
    "wof:name":"Elhelou Faycal",
    "wof:placetype":"venue"
},
  "geometry": {"coordinates":[-92.022462,30.295622],"type":"Point"}
}