{
  "type": "Feature",
  "properties": {
    "iso:country":"US",
    "sg:address":"173 Hwy 22 E",
    "sg:city":"Madisonville",
    "sg:classifiers":[
        {
            "category":"Autos & Motor Vehicles",
            "subcategory":"Fuel & Gas Station",
            "type":"Retail Goods"
        }
    ],
    "sg:phone":"+1 985 845 3993",
    "sg:postcode":"70447",
    "sg:province":"LA",
    "sg:tags":[
        "oil"
    ],
    "wof:name":"Riverbend Spur",
    "wof:placetype":"venue"
},
  "geometry": {"coordinates":[-90.142691,30.40654],"type":"Point"}
}