{
  "type": "Feature",
  "properties": {
    "addr:full":"5425 Lapalco Blvd Marrero LA 70072",
    "addr:housenumber":"5425",
    "addr:postcode":"70072",
    "addr:street":"Lapalco Blvd Marrero",
    "iso:country":"US",
    "sg:address":"5425 Lapalco Blvd",
    "sg:city":"Marrero",
    "sg:classifiers":[
        {
            "category":"Personal",
            "subcategory":"Barber",
            "type":"Services"
        }
    ],
    "sg:phone":"+1 504 328 7288",
    "sg:postcode":"70072",
    "sg:province":"LA",
    "wof:name":"Rob's Barber Shop",
    "wof:placetype":"venue"
},
  "geometry": {"coordinates":[-90.108294,29.875284],"type":"Point"}
}