{
  "type": "Feature",
  "properties": {
    "iso:country":"US",
    "sg:address":"101 Machen Dr",
    "sg:city":"Springhill",
    "sg:classifiers":[
        {
            "category":"Government",
            "subcategory":"Office",
            "type":"Public Place"
        }
    ],
    "sg:phone":"+1 318 539 5936",
    "sg:postcode":"71075",
    "sg:province":"LA",
    "sg:tags":[
        "village"
    ],
    "wof:name":"Criminal Clerk",
    "wof:placetype":"venue"
},
  "geometry": {"coordinates":[-93.460543,33.005795],"type":"Point"}
}