{
  "type": "Feature",
  "properties": {
    "addr:full":"2533 Munster Blvd Meraux LA 70075",
    "addr:housenumber":"2533",
    "addr:postcode":"70075",
    "addr:street":"Munster Blvd Meraux",
    "iso:country":"US",
    "sg:address":"2533 Munster Blvd",
    "sg:city":"Meraux",
    "sg:classifiers":[
        {
            "category":"Government",
            "subcategory":"Office",
            "type":"Public Place"
        }
    ],
    "sg:phone":"+1 504 278 7446",
    "sg:postcode":"70075",
    "sg:province":"LA",
    "sg:tags":[
        "state"
    ],
    "wof:name":"Elections & Registration Dept",
    "wof:placetype":"venue"
},
  "geometry": {"coordinates":[-89.93340600000001,29.936618],"type":"Point"}
}