{
  "type": "Feature",
  "properties": {
    "addr:full":"146 Acacia Dr Lafayette LA 70508",
    "addr:housenumber":"146",
    "addr:postcode":"70508",
    "addr:street":"Acacia Dr",
    "iso:country":"US",
    "sg:address":"146 Acacia Dr",
    "sg:city":"Lafayette",
    "sg:classifiers":[
        {
            "category":"Building & Trades",
            "subcategory":"Construction",
            "type":"Services"
        }
    ],
    "sg:phone":"+1 337 232 5547",
    "sg:postcode":"70508",
    "sg:province":"LA",
    "sg:tags":[
        "floor",
        "laying",
        "contractor"
    ],
    "wof:name":"Steven Woodlock",
    "wof:placetype":"venue"
},
  "geometry": {"coordinates":[-92.027492,30.19168],"type":"Point"}
}