{
  "type": "Feature",
  "properties": {
    "iso:country":"US",
    "sg:address":"403 Homalot Dr",
    "sg:city":"Shreveport",
    "sg:classifiers":[
        {
            "category":"Building & Trades",
            "subcategory":"Plumbing",
            "type":"Services"
        }
    ],
    "sg:phone":"+1 318 671 8071",
    "sg:postcode":"71106",
    "sg:province":"LA",
    "sg:tags":[
        "plumbing",
        "contractor"
    ],
    "wof:name":"Faires Plumbing",
    "wof:placetype":"venue"
},
  "geometry": {"coordinates":[-93.764329,32.385175],"type":"Point"}
}