{
  "type": "Feature",
  "properties": {
    "iso:country":"US",
    "sg:address":"3203 Lavey Ln",
    "sg:city":"Baker",
    "sg:classifiers":[
        {
            "category":"Banks & Credit Unions",
            "subcategory":"Bank",
            "type":"Services"
        }
    ],
    "sg:phone":"+1 225 775 2860",
    "sg:postcode":"70714",
    "sg:province":"LA",
    "sg:tags":[
        "loan"
    ],
    "wof:name":"American Mortgage & Loan Inc",
    "wof:placetype":"venue"
},
  "geometry": {"coordinates":[-91.167107,30.575404],"type":"Point"}
}