{
  "type": "Feature",
  "properties": {
    "addr:full":"117 West St Franklinton LA 70438",
    "addr:housenumber":"117",
    "addr:postcode":"70438",
    "addr:street":"West St",
    "iso:country":"US",
    "sg:address":"117 West St",
    "sg:city":"Franklinton",
    "sg:classifiers":[
        {
            "category":"Professional",
            "subcategory":"Computer Services",
            "type":"Services"
        }
    ],
    "sg:phone":"+1 985 795 1300",
    "sg:postcode":"70438",
    "sg:province":"LA",
    "wof:name":"Cross Communications",
    "wof:placetype":"venue"
},
  "geometry": {"coordinates":[-90.17644,30.816221],"type":"Point"}
}