{
  "type": "Feature",
  "properties": {
    "addr:full":"418 Newton St Gretna LA 70053",
    "addr:housenumber":"418",
    "addr:postcode":"70053",
    "addr:street":"Newton St",
    "iso:country":"US",
    "sg:address":"418 Newton St",
    "sg:city":"Gretna",
    "sg:phone":"+1 504 361 0403",
    "sg:postcode":"70053",
    "sg:province":"LA",
    "sg:tags":[
        "fuel",
        "diesel"
    ],
    "wof:name":"RPL Oil Distr",
    "wof:placetype":"venue"
},
  "geometry": {"coordinates":[-90.06320599999999,29.915524],"type":"Point"}
}