{
  "type": "Feature",
  "properties": {
    "iso:country":"US",
    "sg:address":"513 Kostmayer Ave",
    "sg:city":"Slidell",
    "sg:classifiers":[
        {
            "category":"Shopping",
            "subcategory":"Clothing, Apparel, & Fashions",
            "type":"Retail Goods"
        }
    ],
    "sg:phone":"+1 985 690 4160",
    "sg:postcode":"70458",
    "sg:province":"LA",
    "sg:tags":[
        "dressmaker"
    ],
    "wof:name":"Sandy Myles Seamstress",
    "wof:placetype":"venue"
},
  "geometry": {"coordinates":[-89.788353,30.259531],"type":"Point"}
}