{
  "type": "Feature",
  "properties": {
    "addr:full":"205 S Lacarpe Cir Houma LA 70360",
    "addr:housenumber":"205",
    "addr:postcode":"70360",
    "addr:street":"S Lacarpe Cir",
    "iso:country":"US",
    "sg:address":"205 S Lacarpe Cir",
    "sg:city":"Houma",
    "sg:classifiers":[
        {
            "category":"Food & Beverages",
            "subcategory":"Groceries & Convenience Stores",
            "type":"Retail Goods"
        }
    ],
    "sg:phone":"+1 985 879 1211",
    "sg:postcode":"70360",
    "sg:province":"LA",
    "sg:tags":[
        "product",
        "snack"
    ],
    "wof:name":"Fisher Snacks Inc",
    "wof:placetype":"venue"
},
  "geometry": {"coordinates":[-90.74857900000001,29.595436],"type":"Point"}
}