{
  "type": "Feature",
  "properties": {
    "iso:country":"US",
    "sg:address":"820 Jordan St",
    "sg:city":"Shreveport",
    "sg:classifiers":[
        {
            "category":"Retail",
            "subcategory":"Repair Shop",
            "type":"Services"
        }
    ],
    "sg:phone":"+1 318 741 0003",
    "sg:postcode":"71101",
    "sg:province":"LA",
    "sg:tags":[
        "equipment",
        "medical"
    ],
    "wof:name":"Kinetic Biomedical Svc",
    "wof:placetype":"venue"
},
  "geometry": {"coordinates":[-93.74635000000001,32.498226],"type":"Point"}
}