{
  "type": "Feature",
  "properties": {
    "addr:full":"4401 Maplewood Dr Sulphur LA 70663",
    "addr:housenumber":"4401",
    "addr:postcode":"70663",
    "addr:street":"Maplewood Dr",
    "iso:country":"US",
    "sg:address":"4401 Maplewood Dr",
    "sg:city":"Sulphur",
    "sg:classifiers":[
        {
            "category":"Education",
            "subcategory":"School",
            "type":"Public Place"
        }
    ],
    "sg:phone":"+1 337 625 3457",
    "sg:postcode":"70663",
    "sg:province":"LA",
    "sg:website":"www.cpsb.org",
    "wof:name":"Maplewood Middle School",
    "wof:placetype":"venue"
},
  "geometry": {"coordinates":[-93.31613900000001,30.227839],"type":"Point"}
}