{
  "type": "Feature",
  "properties": {
    "iso:country":"US",
    "sg:address":"1010 N Miro St",
    "sg:city":"New Orleans",
    "sg:classifiers":[
        {
            "category":"Manufacturing",
            "subcategory":"Rubber & Plastics",
            "type":"Manufacturing & Wholesale Goods"
        }
    ],
    "sg:phone":"+1 504 522 9613",
    "sg:postcode":"70119",
    "sg:province":"LA",
    "sg:tags":[
        "gasket"
    ],
    "sg:website":"www.gbggasket.com",
    "wof:name":"G B & G Die & Gasket Co",
    "wof:placetype":"venue"
},
  "geometry": {"coordinates":[-90.075822,29.970867],"type":"Point"}
}