{
  "type": "Feature",
  "properties": {
    "iso:country":"US",
    "sg:address":"1426 N Parkerson Ave",
    "sg:city":"Crowley",
    "sg:classifiers":[
        {
            "category":"Restaurant",
            "type":"Food & Drink"
        }
    ],
    "sg:phone":"+1 337 788 0507",
    "sg:postcode":"70526",
    "sg:province":"LA",
    "wof:name":"Burger Zone",
    "wof:placetype":"venue"
},
  "geometry": {"coordinates":[-92.378608,30.2236],"type":"Point"}
}