{
  "type": "Feature",
  "properties": {
    "iso:country":"US",
    "sg:address":"4954 Pete Nation Rd",
    "sg:city":"Starks",
    "sg:classifiers":[
        {
            "category":"Retail",
            "subcategory":"Car Wash",
            "type":"Services"
        }
    ],
    "sg:phone":"+1 337 743 6320",
    "sg:postcode":"70661",
    "sg:province":"LA",
    "sg:tags":[
        "carwash"
    ],
    "wof:name":"Starks Car Wash",
    "wof:placetype":"venue"
},
  "geometry": {"coordinates":[-93.68218400000001,30.256346],"type":"Point"}
}