{
  "type": "Feature",
  "properties": {
    "iso:country":"US",
    "sg:address":"4936 Groom Rd",
    "sg:city":"Baker",
    "sg:classifiers":[
        {
            "category":"Retail",
            "subcategory":"Veterinary Services",
            "type":"Services"
        }
    ],
    "sg:phone":"+1 225 775 8815",
    "sg:postcode":"70714",
    "sg:province":"LA",
    "sg:tags":[
        "veterinarian"
    ],
    "wof:name":"Baker Animal Hospital",
    "wof:placetype":"venue"
},
  "geometry": {"coordinates":[-91.147119,30.586737],"type":"Point"}
}