{
  "type": "Feature",
  "properties": {
    "iso:country":"US",
    "sg:address":"1002 E Polk St",
    "sg:city":"Baton Rouge",
    "sg:classifiers":[
        {
            "category":"Organizations",
            "subcategory":"Religious Organization",
            "type":"Services"
        }
    ],
    "sg:phone":"+1 225 343 5615",
    "sg:postcode":"70802",
    "sg:province":"LA",
    "sg:tags":[
        "church"
    ],
    "wof:name":"Greater Beulah Baptist Church",
    "wof:placetype":"venue"
},
  "geometry": {"coordinates":[-91.17301399999999,30.427053],"type":"Point"}
}