{
  "type": "Feature",
  "properties": {
    "addr:full":"3640 Williams Blvd Kenner LA 70065",
    "addr:housenumber":"3640",
    "addr:postcode":"70065",
    "addr:street":"Williams Blvd",
    "iso:country":"US",
    "sg:address":"3640 Williams Blvd",
    "sg:city":"Kenner",
    "sg:classifiers":[
        {
            "category":"Shopping",
            "subcategory":"Bicycles & Sporting Goods",
            "type":"Retail Goods"
        }
    ],
    "sg:phone":"+1 504 469 5543",
    "sg:postcode":"70065",
    "sg:province":"LA",
    "sg:tags":[
        "apparel",
        "bowling",
        "accessory"
    ],
    "wof:name":"Striketime Trophy & Bowling",
    "wof:placetype":"venue"
},
  "geometry": {"coordinates":[-90.238981,30.022347],"type":"Point"}
}