{
  "type": "Feature",
  "properties": {
    "iso:country":"US",
    "sg:address":"738 E Bridge St",
    "sg:city":"St Martinville",
    "sg:classifiers":[
        {
            "category":"Retail",
            "subcategory":"Car Wash",
            "type":"Services"
        }
    ],
    "sg:phone":"+1 337 394 4123",
    "sg:postcode":"70582",
    "sg:province":"LA",
    "sg:tags":[
        "polishing",
        "washing"
    ],
    "wof:name":"Twin Pines Carwash",
    "wof:placetype":"venue"
},
  "geometry": {"coordinates":[-91.822157,30.121957],"type":"Point"}
}