{
  "type": "Feature",
  "properties": {
    "addr:full":"1002 Broussard Dr Breaux Bridge LA 70517",
    "addr:housenumber":"1002",
    "addr:postcode":"la 70517",
    "addr:street":"Broussard Dr",
    "iso:country":"US",
    "sg:address":"1002 Broussard Dr",
    "sg:city":"Breaux Bridge",
    "sg:classifiers":[
        {
            "category":"Personal",
            "subcategory":"Beauty Salon",
            "type":"Services"
        },
        {
            "category":"Personal",
            "subcategory":"Barber",
            "type":"Services"
        }
    ],
    "sg:phone":"+1 337 332 4415",
    "sg:postcode":"70517",
    "sg:province":"LA",
    "sg:tags":[
        "shop"
    ],
    "wof:name":"Judy's Hair Design",
    "wof:placetype":"venue"
},
  "geometry": {"coordinates":[-91.87460400000001,30.251243],"type":"Point"}
}