{
  "type": "Feature",
  "properties": {
    "addr:full":"11203 Darryl Dr Baton Rouge LA 70815",
    "addr:housenumber":"11203",
    "addr:postcode":"70815",
    "addr:street":"Darryl Dr",
    "iso:country":"US",
    "sg:address":"11203 Darryl Dr",
    "sg:city":"Baton Rouge",
    "sg:classifiers":[
        {
            "category":"Professional",
            "subcategory":"Research",
            "type":"Services"
        }
    ],
    "sg:phone":"+1 225 275 7966",
    "sg:postcode":"70815",
    "sg:province":"LA",
    "sg:tags":[
        "environmental",
        "ecological"
    ],
    "wof:name":"Whitcomb Environmental Cnsltng",
    "wof:placetype":"venue"
},
  "geometry": {"coordinates":[-91.066327,30.470912],"type":"Point"}
}