{
  "type": "Feature",
  "properties": {
    "addr:full":"313 Royal St New Orleans LA 70130",
    "addr:housenumber":"313",
    "addr:postcode":"70130",
    "addr:street":"Royal St",
    "iso:country":"US",
    "sg:address":"313 Royal St",
    "sg:city":"New Orleans",
    "sg:classifiers":[
        {
            "category":"Shopping",
            "subcategory":"Used Merchandise",
            "type":"Retail Goods"
        }
    ],
    "sg:phone":"+1 504 522 4124",
    "sg:postcode":"70130",
    "sg:province":"LA",
    "sg:tags":[
        "antique"
    ],
    "wof:name":"Windsor Collection",
    "wof:placetype":"venue"
},
  "geometry": {"coordinates":[-90.066947,29.955602],"type":"Point"}
}