{
  "type": "Feature",
  "properties": {
    "addr:full":"4900 Knight Dr New Orleans LA 70127",
    "addr:housenumber":"4900",
    "addr:postcode":"70127",
    "addr:street":"Knight Dr",
    "iso:country":"US",
    "sg:address":"4900 Knight Dr",
    "sg:city":"New Orleans",
    "sg:classifiers":[
        {
            "category":"Local Transit",
            "type":"Transportation"
        }
    ],
    "sg:phone":"+1 504 324 6340",
    "sg:postcode":"70127",
    "sg:province":"LA",
    "sg:tags":[
        "passenger"
    ],
    "wof:name":"Cajun Transportation",
    "wof:placetype":"venue"
},
  "geometry": {"coordinates":[-89.98340399999999,30.023049],"type":"Point"}
}