{
  "type": "Feature",
  "properties": {
    "iso:country":"US",
    "sg:address":"1535 Franklin Ave",
    "sg:city":"New Orleans",
    "sg:classifiers":[
        {
            "category":"Food & Beverages",
            "subcategory":"Meat & Fish",
            "type":"Retail Goods"
        }
    ],
    "sg:phone":"+1 504 948 8628",
    "sg:postcode":"70117",
    "sg:province":"LA",
    "sg:tags":[
        "shop"
    ],
    "wof:name":"Quicky's Meat",
    "wof:placetype":"venue"
},
  "geometry": {"coordinates":[-90.04879800000001,29.974001],"type":"Point"}
}