{
  "type": "Feature",
  "properties": {
    "iso:country":"US",
    "sg:address":"2108 Oak Grove Dr",
    "sg:city":"Vinton",
    "sg:classifiers":[
        {
            "category":"Retail",
            "subcategory":"Laundry & Dry Cleaning",
            "type":"Services"
        }
    ],
    "sg:phone":"+1 337 302 2469",
    "sg:postcode":"70668",
    "sg:province":"LA",
    "sg:tags":[
        "cleaner",
        "rug",
        "carpet"
    ],
    "wof:name":"Jani-King",
    "wof:placetype":"venue"
},
  "geometry": {"coordinates":[-93.62597,30.164668],"type":"Point"}
}