{
  "type": "Feature",
  "properties": {
    "iso:country":"US",
    "sg:address":"2307 Veterans Memorial Dr",
    "sg:city":"Abbeville",
    "sg:classifiers":[
        {
            "category":"Restaurant",
            "type":"Food & Drink"
        }
    ],
    "sg:menulink":"http://www.allmenus.com/la/abbeville/173657-wendys/menu/",
    "sg:phone":"+1 337 893 8938",
    "sg:postcode":"70510",
    "sg:province":"LA",
    "sg:tags":[
        "burger",
        "american",
        "soup"
    ],
    "wof:name":"Wendy's",
    "wof:placetype":"venue"
},
  "geometry": {"coordinates":[-92.109262,29.979001],"type":"Point"}
}