{
  "type": "Feature",
  "properties": {
    "iso:country":"US",
    "sg:address":"3105 State Rte 75",
    "sg:city":"St Gabriel",
    "sg:classifiers":[
        {
            "category":"Banks & Credit Unions",
            "subcategory":"Bank",
            "type":"Services"
        }
    ],
    "sg:phone":"+1 225 642 1548",
    "sg:postcode":"70776",
    "sg:province":"LA",
    "sg:tags":[
        "federally",
        "chartered"
    ],
    "wof:name":"C G Fcu",
    "wof:placetype":"venue"
},
  "geometry": {"coordinates":[-91.107288,30.264611],"type":"Point"}
}