{
  "type": "Feature",
  "properties": {
    "iso:country":"US",
    "sg:address":"3486 Drusilla Ln",
    "sg:city":"Baton Rouge",
    "sg:classifiers":[
        {
            "category":"Food & Beverages",
            "subcategory":"Bakery",
            "type":"Retail Goods"
        }
    ],
    "sg:phone":"+1 225 930 0085",
    "sg:postcode":"70809",
    "sg:province":"LA",
    "sg:tags":[
        "doughnut"
    ],
    "wof:name":"Mary Lee Do-Nuts",
    "wof:placetype":"venue"
},
  "geometry": {"coordinates":[-91.088624,30.419602],"type":"Point"}
}