{
  "type": "Feature",
  "properties": {
    "iso:country":"US",
    "sg:address":"223 Elizabeth St",
    "sg:city":"Many",
    "sg:classifiers":[
        {
            "category":"Food & Beverages",
            "subcategory":"Groceries & Convenience Stores",
            "type":"Retail Goods"
        }
    ],
    "sg:phone":"+1 318 256 2045",
    "sg:postcode":"71449",
    "sg:province":"LA",
    "sg:tags":[
        "grocer"
    ],
    "wof:name":"Brookshire Brothers",
    "wof:placetype":"venue"
},
  "geometry": {"coordinates":[-93.48803700000001,31.566487],"type":"Point"}
}