{
  "type": "Feature",
  "properties": {
    "iso:country":"US",
    "sg:address":"1400 N Foster Dr",
    "sg:city":"Baton Rouge",
    "sg:classifiers":[
        {
            "category":"Organizations",
            "subcategory":"Religious Organization",
            "type":"Services"
        }
    ],
    "sg:phone":"+1 225 925 3133",
    "sg:postcode":"70806",
    "sg:province":"LA",
    "sg:tags":[
        "church"
    ],
    "wof:name":"Star Hill Baptist Church",
    "wof:placetype":"venue"
},
  "geometry": {"coordinates":[-91.13929400000001,30.461289],"type":"Point"}
}