{
  "type": "Feature",
  "properties": {
    "iso:country":"US",
    "sg:address":"135 Northshore Blvd",
    "sg:city":"Slidell",
    "sg:classifiers":[
        {
            "category":"Shopping",
            "subcategory":"Department Store",
            "type":"Retail Goods"
        }
    ],
    "sg:phone":"+1 985 646 0505",
    "sg:postcode":"70460",
    "sg:province":"LA",
    "wof:name":"Dollar Values",
    "wof:placetype":"venue"
},
  "geometry": {"coordinates":[-89.82580799999999,30.308671],"type":"Point"}
}