{
  "type": "Feature",
  "properties": {
    "iso:country":"US",
    "sg:address":"3091 Hwy 80 W",
    "sg:city":"Calhoun",
    "sg:classifiers":[
        {
            "category":"Restaurant",
            "type":"Food & Drink"
        }
    ],
    "sg:phone":"+1 318 644 9995",
    "sg:postcode":"71225",
    "sg:province":"LA",
    "wof:name":"Chief's Hideaway",
    "wof:placetype":"venue"
},
  "geometry": {"coordinates":[-92.362289,32.512444],"type":"Point"}
}