{
  "type": "Feature",
  "properties": {
    "addr:full":"830 Enterprise Blvd Lake Charles LA 70601",
    "addr:housenumber":"830",
    "addr:postcode":"70601",
    "addr:street":"Enterprise Blvd",
    "iso:country":"US",
    "sg:address":"830 Enterprise Blvd",
    "sg:city":"Lake Charles",
    "sg:classifiers":[
        {
            "category":"Government",
            "subcategory":"Police Station",
            "type":"Public Place"
        }
    ],
    "sg:phone":"+1 337 491 1311",
    "sg:postcode":"70601",
    "sg:province":"LA",
    "sg:tags":[
        "department"
    ],
    "wof:name":"Lake Charles Police Dept",
    "wof:placetype":"venue"
},
  "geometry": {"coordinates":[-93.204387,30.226412],"type":"Point"}
}