{
  "type": "Feature",
  "properties": {
    "iso:country":"US",
    "sg:address":"101 Tivoli St",
    "sg:city":"Abbeville",
    "sg:classifiers":[
        {
            "category":"Personal",
            "subcategory":"Beauty Salon",
            "type":"Services"
        }
    ],
    "sg:phone":"+1 337 893 2040",
    "sg:postcode":"70510",
    "sg:province":"LA",
    "wof:name":"Salon De'Ville",
    "wof:placetype":"venue"
},
  "geometry": {"coordinates":[-92.134485,29.97412],"type":"Point"}
}