{
  "type": "Feature",
  "properties": {
    "addr:full":"6219 W Park Ave Houma LA 70364",
    "addr:housenumber":"6219",
    "addr:postcode":"70364",
    "addr:street":"W Park Ave",
    "iso:country":"US",
    "sg:address":"6219 W Park Ave",
    "sg:city":"Houma",
    "sg:classifiers":[
        {
            "category":"Restaurant",
            "type":"Food & Drink"
        }
    ],
    "sg:phone":"+1 985 868 6593",
    "sg:postcode":"70364",
    "sg:province":"LA",
    "wof:name":"Mc Donald's",
    "wof:placetype":"venue"
},
  "geometry": {"coordinates":[-90.752256,29.626716],"type":"Point"}
}