{
  "type": "Feature",
  "properties": {
    "iso:country":"US",
    "sg:address":"135 Jane Dr",
    "sg:city":"Slidell",
    "sg:classifiers":[
        {
            "category":"Railroad",
            "type":"Transportation"
        }
    ],
    "sg:phone":"+1 985 649 1584",
    "sg:postcode":"70460",
    "sg:province":"LA",
    "sg:tags":[
        "rail",
        "datum"
    ],
    "wof:name":"Enterprise Unlimited",
    "wof:placetype":"venue"
},
  "geometry": {"coordinates":[-89.83417799999999,30.263621],"type":"Point"}
}