{
  "type": "Feature",
  "properties": {
    "iso:country":"US",
    "sg:address":"10560 State Rte 431",
    "sg:city":"St Amant",
    "sg:classifiers":[
        {
            "category":"Wholesale",
            "subcategory":"Machinery & Supplies",
            "type":"Manufacturing & Wholesale Goods"
        }
    ],
    "sg:phone":"+1 225 675 6775",
    "sg:postcode":"70774",
    "sg:province":"LA",
    "sg:tags":[
        "equipment",
        "industrial"
    ],
    "wof:name":"J L Browne & Assoc",
    "wof:placetype":"venue"
},
  "geometry": {"coordinates":[-90.869562,30.222354],"type":"Point"}
}