{
  "type": "Feature",
  "properties": {
    "iso:country":"US",
    "sg:address":"105 Dartmouth Cir",
    "sg:city":"Youngsville",
    "sg:classifiers":[
        {
            "category":"Professional",
            "subcategory":"Testing Lab",
            "type":"Services"
        }
    ],
    "sg:phone":"+1 337 856 0707",
    "sg:postcode":"70592",
    "sg:province":"LA",
    "sg:tags":[
        "x"
    ],
    "wof:name":"Quality Control Specialists",
    "wof:placetype":"venue"
},
  "geometry": {"coordinates":[-91.988372,30.098956],"type":"Point"}
}