{
  "type": "Feature",
  "properties": {
    "iso:country":"US",
    "sg:address":"3433 Monroe Hwy",
    "sg:city":"Pineville",
    "sg:classifiers":[
        {
            "category":"Restaurant",
            "type":"Food & Drink"
        }
    ],
    "sg:phone":"+1 318 640 7115",
    "sg:postcode":"71360",
    "sg:province":"LA",
    "sg:tags":[
        "delicatessen"
    ],
    "wof:name":"King Stop",
    "wof:placetype":"venue"
},
  "geometry": {"coordinates":[-92.41203,31.363019],"type":"Point"}
}