{
  "type": "Feature",
  "properties": {
    "addr:full":"560 State Rte 397 Lake Charles LA 70615",
    "addr:housenumber":"560",
    "addr:postcode":"70615",
    "addr:street":"State Rte 397",
    "iso:country":"US",
    "sg:address":"560 State Rte 397",
    "sg:city":"Lake Charles",
    "sg:classifiers":[
        {
            "category":"Autos & Motor Vehicles",
            "subcategory":"Fuel & Gas Station",
            "type":"Retail Goods"
        }
    ],
    "sg:phone":"+1 337 433 1366",
    "sg:postcode":"70615",
    "sg:province":"LA",
    "sg:tags":[
        "plaza",
        "truck",
        "stops"
    ],
    "wof:name":"Chardele Auto & Truck Plaza",
    "wof:placetype":"venue"
},
  "geometry": {"coordinates":[-93.129273,30.231033],"type":"Point"}
}