{
  "type": "Feature",
  "properties": {
    "addr:full":"4630 Orleans Ave New Orleans LA 70119",
    "addr:housenumber":"4630",
    "addr:postcode":"70119",
    "addr:street":"Orleans Ave",
    "iso:country":"US",
    "sg:address":"4630 Orleans Ave",
    "sg:city":"New Orleans",
    "sg:classifiers":[
        {
            "category":"Professional",
            "subcategory":"Computer Services",
            "type":"Services"
        }
    ],
    "sg:phone":"+1 504 488 8280",
    "sg:postcode":"70119",
    "sg:province":"LA",
    "sg:tags":[
        "internet"
    ],
    "sg:website":"www.louisianachess.com",
    "wof:name":"Superior Alarms",
    "wof:placetype":"venue"
},
  "geometry": {"coordinates":[-90.10174000000001,29.983328],"type":"Point"}
}