{
  "type": "Feature",
  "properties": {
    "iso:country":"US",
    "sg:address":"119 Nolan Rd",
    "sg:city":"Broussard",
    "sg:classifiers":[
        {
            "category":"Wholesale",
            "subcategory":"Machinery & Supplies",
            "type":"Manufacturing & Wholesale Goods"
        }
    ],
    "sg:phone":"+1 337 837 2701",
    "sg:postcode":"70518",
    "sg:province":"LA",
    "sg:tags":[
        "pump"
    ],
    "sg:website":"www.candbsales.com",
    "wof:name":"C & B Sales & Svc Inc",
    "wof:placetype":"venue"
},
  "geometry": {"coordinates":[-91.97315,30.164013],"type":"Point"}
}