{
  "type": "Feature",
  "properties": {
    "iso:country":"US",
    "sg:address":"11125 Darryl Dr",
    "sg:city":"Baton Rouge",
    "sg:phone":"+1 225 272 4915",
    "sg:postcode":"70815",
    "sg:province":"LA",
    "sg:tags":[
        "bulk",
        "gas"
    ],
    "wof:name":"Gas Analytical Svc Inc",
    "wof:placetype":"venue"
},
  "geometry": {"coordinates":[-91.065483,30.470993],"type":"Point"}
}