{
  "type": "Feature",
  "properties": {
    "iso:country":"US",
    "sg:address":"1901 Roselawn Ave",
    "sg:city":"Monroe",
    "sg:classifiers":[
        {
            "category":"Shopping",
            "subcategory":"Clothing, Apparel, & Fashions",
            "type":"Retail Goods"
        }
    ],
    "sg:phone":"+1 318 410 0082",
    "sg:postcode":"71201",
    "sg:province":"LA",
    "sg:tags":[
        "t"
    ],
    "wof:name":"T-Shirts Express",
    "wof:placetype":"venue"
},
  "geometry": {"coordinates":[-92.10674899999999,32.52333],"type":"Point"}
}