{
  "type": "Feature",
  "properties": {
    "iso:country":"US",
    "sg:address":"1007 Hawkins St",
    "sg:city":"Gretna",
    "sg:classifiers":[
        {
            "category":"Organizations",
            "subcategory":"Religious Organization",
            "type":"Services"
        }
    ],
    "sg:phone":"+1 504 366 3182",
    "sg:postcode":"70053",
    "sg:province":"LA",
    "wof:name":"Faith Hope & Love Healing",
    "wof:placetype":"venue"
},
  "geometry": {"coordinates":[-90.043071,29.913585],"type":"Point"}
}