{
  "type": "Feature",
  "properties": {
    "iso:country":"US",
    "sg:address":"1237 Grand Caillou Rd",
    "sg:city":"Houma",
    "sg:classifiers":[
        {
            "category":"Shopping",
            "subcategory":"Musical Instruments",
            "type":"Retail Goods"
        }
    ],
    "sg:phone":"+1 985 872 4280",
    "sg:postcode":"70363",
    "sg:province":"LA",
    "wof:name":"Dusenbery's Music",
    "wof:placetype":"venue"
},
  "geometry": {"coordinates":[-90.68906800000001,29.577911],"type":"Point"}
}