{
  "type": "Feature",
  "properties": {
    "iso:country":"US",
    "sg:address":"216 Hidden Springs Ln",
    "sg:city":"Covington",
    "sg:classifiers":[
        {
            "category":"Professional",
            "subcategory":"Advertising",
            "type":"Services"
        }
    ],
    "sg:phone":"+1 985 898 6359",
    "sg:postcode":"70433",
    "sg:province":"LA",
    "wof:name":"P R Advertising",
    "wof:placetype":"venue"
},
  "geometry": {"coordinates":[-90.073774,30.436857],"type":"Point"}
}