{
  "type": "Feature",
  "properties": {
    "iso:country":"US",
    "sg:address":"17606 Carlisle Ave",
    "sg:city":"Baton Rouge",
    "sg:classifiers":[
        {
            "category":"Utilities",
            "type":"Services"
        }
    ],
    "sg:phone":"+1 225 752 7463",
    "sg:postcode":"70817",
    "sg:province":"LA",
    "sg:tags":[
        "sweeping"
    ],
    "wof:name":"Woodlawn Development Inc",
    "wof:placetype":"venue"
},
  "geometry": {"coordinates":[-90.992103,30.37837],"type":"Point"}
}