{
  "type": "Feature",
  "properties": {
    "iso:country":"US",
    "sg:address":"701 David Dr",
    "sg:city":"Metairie",
    "sg:classifiers":[
        {
            "category":"Shopping",
            "subcategory":"Florist",
            "type":"Retail Goods"
        }
    ],
    "sg:phone":"+1 504 818 2644",
    "sg:postcode":"70003",
    "sg:province":"LA",
    "wof:name":"Kori's Floral Boutique",
    "wof:placetype":"venue"
},
  "geometry": {"coordinates":[-90.21219000000001,29.982014],"type":"Point"}
}