{
  "type": "Feature",
  "properties": {
    "iso:country":"US",
    "sg:address":"955 Sycamore St",
    "sg:city":"Cottonport",
    "sg:classifiers":[
        {
            "category":"Government",
            "subcategory":"Post Office",
            "type":"Public Place"
        }
    ],
    "sg:phone":"+1 318 876 2205",
    "sg:postcode":"71327",
    "sg:province":"LA",
    "wof:name":"US Post Office",
    "wof:placetype":"venue"
},
  "geometry": {"coordinates":[-92.052267,30.983894],"type":"Point"}
}