{
  "type": "Feature",
  "properties": {
    "addr:full":"24 Jana Dr Monroe LA 71203",
    "addr:postcode":"71203",
    "addr:street":"Jana Dr",
    "iso:country":"US",
    "sg:address":"24 Jana Dr",
    "sg:city":"Monroe",
    "sg:classifiers":[
        {
            "category":"Wholesale",
            "subcategory":"Farm Supplies",
            "type":"Manufacturing & Wholesale Goods"
        }
    ],
    "sg:phone":"+1 318 343 2513",
    "sg:postcode":"71203",
    "sg:province":"LA",
    "sg:tags":[
        "chemical",
        "agricultural"
    ],
    "wof:name":"Bayer Corporation",
    "wof:placetype":"venue"
},
  "geometry": {"coordinates":[-92.06410200000001,32.553363],"type":"Point"}
}