{
  "type": "Feature",
  "properties": {
    "iso:country":"US",
    "sg:address":"7988 Hwy 79",
    "sg:city":"Haynesville",
    "sg:classifiers":[
        {
            "category":"Building & Trades",
            "subcategory":"Electrical",
            "type":"Services"
        }
    ],
    "sg:phone":"+1 318 624 2022",
    "sg:postcode":"71038",
    "sg:province":"LA",
    "sg:tags":[
        "electrical",
        "contractor"
    ],
    "wof:name":"Hines Forestry",
    "wof:placetype":"venue"
},
  "geometry": {"coordinates":[-93.121066,32.945009],"type":"Point"}
}