{
  "type": "Feature",
  "properties": {
    "iso:country":"US",
    "sg:address":"9391 Ellerbe Rd",
    "sg:city":"Shreveport",
    "sg:classifiers":[
        {
            "category":"Organizations",
            "subcategory":"Religious Organization",
            "type":"Services"
        }
    ],
    "sg:phone":"+1 318 861 3166",
    "sg:postcode":"71106",
    "sg:province":"LA",
    "sg:tags":[
        "church"
    ],
    "wof:name":"Anglican Church Of Epiphany",
    "wof:placetype":"venue"
},
  "geometry": {"coordinates":[-93.735775,32.401708],"type":"Point"}
}