{
  "type": "Feature",
  "properties": {
    "iso:country":"US",
    "sg:address":"6725 Siegen Ln",
    "sg:city":"Baton Rouge",
    "sg:classifiers":[
        {
            "category":"Shopping",
            "subcategory":"Computers & Home Electronics",
            "type":"Retail Goods"
        }
    ],
    "sg:phone":"+1 225 295 0669",
    "sg:postcode":"70809",
    "sg:province":"LA",
    "sg:tags":[
        "game",
        "video"
    ],
    "wof:name":"Gamestop",
    "wof:placetype":"venue"
},
  "geometry": {"coordinates":[-91.062955,30.38728],"type":"Point"}
}