{
  "type": "Feature",
  "properties": {
    "iso:country":"US",
    "sg:address":"830 Ockley Dr",
    "sg:city":"Shreveport",
    "sg:classifiers":[
        {
            "category":"Health Services",
            "subcategory":"Doctor",
            "type":"Services"
        }
    ],
    "sg:phone":"+1 318 868 8324",
    "sg:postcode":"71106",
    "sg:province":"LA",
    "sg:tags":[
        "medical"
    ],
    "wof:name":"Carolyn N Gibson MD A Pro",
    "wof:placetype":"venue"
},
  "geometry": {"coordinates":[-93.747709,32.469452],"type":"Point"}
}