{
  "type": "Feature",
  "properties": {
    "iso:country":"US",
    "sg:address":"994 Marina Dr",
    "sg:city":"Slidell",
    "sg:classifiers":[
        {
            "category":"Manufacturing",
            "subcategory":"Toys & Sporting Goods",
            "type":"Manufacturing & Wholesale Goods"
        }
    ],
    "sg:phone":"+1 985 607 0112",
    "sg:postcode":"70458",
    "sg:province":"LA",
    "sg:tags":[
        "tackle",
        "fishing"
    ],
    "wof:name":"Heads Or Tails Inc",
    "wof:placetype":"venue"
},
  "geometry": {"coordinates":[-89.789795,30.219182],"type":"Point"}
}