{
  "type": "Feature",
  "properties": {
    "iso:country":"US",
    "sg:address":"435 Calhoun St",
    "sg:city":"New Orleans",
    "sg:classifiers":[
        {
            "category":"Wholesale",
            "subcategory":"Machinery & Supplies",
            "type":"Manufacturing & Wholesale Goods"
        }
    ],
    "sg:phone":"+1 504 891 6222",
    "sg:postcode":"70118",
    "sg:province":"LA",
    "sg:tags":[
        "equipment",
        "welding"
    ],
    "wof:name":"Production Fastening Systems",
    "wof:placetype":"venue"
},
  "geometry": {"coordinates":[-90.12687699999999,29.920606],"type":"Point"}
}