{
  "type": "Feature",
  "properties": {
    "addr:full":"900 S 6th St Leesville LA 71446",
    "addr:housenumber":"900",
    "addr:postcode":"71446",
    "addr:street":"S 6Th St",
    "iso:country":"US",
    "sg:address":"900 S 6th St",
    "sg:city":"Leesville",
    "sg:classifiers":[
        {
            "category":"Social Services",
            "subcategory":"Job Training",
            "type":"Services"
        }
    ],
    "sg:phone":"+1 337 392 8118",
    "sg:postcode":"71446",
    "sg:province":"LA",
    "sg:tags":[
        "rehabilitation"
    ],
    "wof:name":"Leesville Rehab Hospital LLC",
    "wof:placetype":"venue"
},
  "geometry": {"coordinates":[-93.265693,31.136222],"type":"Point"}
}