{
  "type": "Feature",
  "properties": {
    "iso:country":"US",
    "sg:address":"165 Industrial Pkwy",
    "sg:city":"Lafayette",
    "sg:classifiers":[
        {
            "category":"Manufacturing",
            "subcategory":"Tools & Machinery",
            "type":"Manufacturing & Wholesale Goods"
        }
    ],
    "sg:phone":"+1 337 266 5864",
    "sg:postcode":"70508",
    "sg:province":"LA",
    "sg:tags":[
        "field",
        "oil",
        "equipment"
    ],
    "wof:name":"Vermilion River Tool & Eqpt Co",
    "wof:placetype":"venue"
},
  "geometry": {"coordinates":[-92.006152,30.188358],"type":"Point"}
}