{
  "type": "Feature",
  "properties": {
    "addr:full":"58026 Fort St Plaquemine LA 70764",
    "addr:housenumber":"58026",
    "addr:postcode":"70764",
    "addr:street":"Fort St",
    "iso:country":"US",
    "sg:address":"58026 Fort St",
    "sg:city":"Plaquemine",
    "sg:classifiers":[
        {
            "category":"Food & Beverages",
            "subcategory":"Meat & Fish",
            "type":"Retail Goods"
        }
    ],
    "sg:phone":"+1 225 685 0049",
    "sg:postcode":"70764",
    "sg:province":"LA",
    "sg:tags":[
        "seafood"
    ],
    "wof:name":"Seafood Shoppe",
    "wof:placetype":"venue"
},
  "geometry": {"coordinates":[-91.23398400000001,30.28358],"type":"Point"}
}