{
  "type": "Feature",
  "properties": {
    "addr:full":"9539 Chef Menteur Hwy New Orleans LA 70127",
    "addr:housenumber":"9539",
    "addr:postcode":"70127",
    "addr:street":"Chef Menteur Hwy",
    "iso:country":"US",
    "sg:address":"9539 Chef Menteur Hwy",
    "sg:city":"New Orleans",
    "sg:classifiers":[
        {
            "category":"Bars & Pubs",
            "type":"Food & Drink"
        }
    ],
    "sg:phone":"+1 504 241 8012",
    "sg:postcode":"70127",
    "sg:province":"LA",
    "sg:tags":[
        "lounge",
        "cocktail"
    ],
    "wof:name":"Surf 90",
    "wof:placetype":"venue"
},
  "geometry": {"coordinates":[-89.973062,30.017417],"type":"Point"}
}