{
  "type": "Feature",
  "properties": {
    "addr:full":"1800 Line Ave Shreveport LA 71101",
    "addr:housenumber":"1800",
    "addr:postcode":"71101",
    "addr:street":"Line Ave",
    "iso:country":"US",
    "sg:address":"1800 Line Ave",
    "sg:city":"Shreveport",
    "sg:classifiers":[
        {
            "category":"Education",
            "subcategory":"College",
            "type":"Public Place"
        }
    ],
    "sg:phone":"+1 318 677 3100",
    "sg:postcode":"71101",
    "sg:province":"LA",
    "sg:tags":[
        "academic",
        "school"
    ],
    "sg:website":"www.nsula.edu",
    "wof:name":"Northwestern State University",
    "wof:placetype":"venue"
},
  "geometry": {"coordinates":[-93.74603999999999,32.492686],"type":"Point"}
}