{
  "type": "Feature",
  "properties": {
    "iso:country":"US",
    "sg:address":"1432 Fournet St",
    "sg:city":"Lake Charles",
    "sg:classifiers":[
        {
            "category":"Health Services",
            "subcategory":"Doctor",
            "type":"Services"
        }
    ],
    "sg:phone":"+1 337 439 4220",
    "sg:postcode":"70601",
    "sg:province":"LA",
    "sg:tags":[
        "physician",
        "surgeon"
    ],
    "wof:name":"M & M Family Center",
    "wof:placetype":"venue"
},
  "geometry": {"coordinates":[-93.200507,30.240908],"type":"Point"}
}