{
  "type": "Feature",
  "properties": {
    "addr:full":"2040 Belle Chasse Hwy Gretna LA 70053",
    "addr:housenumber":"2040",
    "addr:postcode":"70053",
    "addr:street":"Belle Chasse Hwy",
    "iso:country":"US",
    "sg:address":"2040 Belle Chasse Hwy",
    "sg:city":"Gretna",
    "sg:classifiers":[
        {
            "category":"Insurance",
            "subcategory":"Insurance Agent",
            "type":"Services"
        }
    ],
    "sg:phone":"+1 504 366 8394",
    "sg:postcode":"70053",
    "sg:province":"LA",
    "wof:name":"Prudential",
    "wof:placetype":"venue"
},
  "geometry": {"coordinates":[-90.052021,29.904203],"type":"Point"}
}