{
  "type": "Feature",
  "properties": {
    "iso:country":"US",
    "sg:address":"301 S 2nd St",
    "sg:city":"Eunice",
    "sg:classifiers":[
        {
            "category":"Health Services",
            "subcategory":"Optometrist",
            "type":"Services"
        }
    ],
    "sg:phone":"+1 337 457 2376",
    "sg:postcode":"70535",
    "sg:province":"LA",
    "wof:name":"Fink & Moser",
    "wof:placetype":"venue"
},
  "geometry": {"coordinates":[-92.41633,30.492663],"type":"Point"}
}