{
  "type": "Feature",
  "properties": {
    "iso:country":"US",
    "sg:address":"197 Westbank Expy",
    "sg:city":"Gretna",
    "sg:classifiers":[
        {
            "category":"Shopping",
            "subcategory":"Music",
            "type":"Retail Goods"
        }
    ],
    "sg:phone":"+1 504 367 2445",
    "sg:postcode":"70053",
    "sg:province":"LA",
    "sg:tags":[
        "compact",
        "record",
        "disc",
        "tape"
    ],
    "wof:name":"Fye",
    "wof:placetype":"venue"
},
  "geometry": {"coordinates":[-90.05331099999999,29.912077],"type":"Point"}
}