{
  "type": "Feature",
  "properties": {
    "addr:full":"1728 N Claiborne Ave New Orleans LA 70116",
    "addr:housenumber":"1728",
    "addr:postcode":"70116",
    "addr:street":"N Claiborne Ave",
    "iso:country":"US",
    "sg:address":"1728 N Claiborne Ave",
    "sg:city":"New Orleans",
    "sg:classifiers":[
        {
            "category":"Autos & Motor Vehicles",
            "subcategory":"Automobile Sales",
            "type":"Retail Goods"
        }
    ],
    "sg:phone":"+1 504 943 6622",
    "sg:postcode":"70116",
    "sg:province":"LA",
    "sg:tags":[
        "limo"
    ],
    "wof:name":"Rhodes Limousine Service",
    "wof:placetype":"venue"
},
  "geometry": {"coordinates":[-90.062676,29.972795],"type":"Point"}
}