{
  "type": "Feature",
  "properties": {
    "iso:country":"US",
    "sg:address":"205 N Church St",
    "sg:city":"Carencro",
    "sg:classifiers":[
        {
            "category":"Restaurant",
            "type":"Food & Drink"
        }
    ],
    "sg:phone":"+1 337 896 5556",
    "sg:postcode":"70520",
    "sg:province":"LA",
    "sg:tags":[
        "parlor",
        "ice",
        "cream"
    ],
    "wof:name":"Monnie's Snow Shack",
    "wof:placetype":"venue"
},
  "geometry": {"coordinates":[-92.04668100000001,30.319113],"type":"Point"}
}