{
  "type": "Feature",
  "properties": {
    "iso:country":"US",
    "sg:address":"4747 W Napoleon Ave",
    "sg:city":"Metairie",
    "sg:classifiers":[
        {
            "category":"Restaurant",
            "type":"Food & Drink"
        }
    ],
    "sg:phone":"+1 504 888 0601",
    "sg:postcode":"70001",
    "sg:province":"LA",
    "sg:tags":[
        "shop",
        "coffee"
    ],
    "wof:name":"Chateau Coffee Cafe",
    "wof:placetype":"venue"
},
  "geometry": {"coordinates":[-90.184451,29.993802],"type":"Point"}
}