{
  "type": "Feature",
  "properties": {
    "iso:country":"US",
    "sg:address":"1210 Florida Ave SE",
    "sg:city":"Denham Springs",
    "sg:classifiers":[
        {
            "category":"Travel",
            "subcategory":"Hotels & Motels",
            "type":"Entertainment"
        }
    ],
    "sg:phone":"+1 225 664 7893",
    "sg:postcode":"70726",
    "sg:province":"LA",
    "wof:name":"Village Inn",
    "wof:placetype":"venue"
},
  "geometry": {"coordinates":[-90.939644,30.484165],"type":"Point"}
}