{
  "type": "Feature",
  "properties": {
    "iso:country":"US",
    "sg:address":"227 N Kirkland Dr",
    "sg:city":"Brusly",
    "sg:classifiers":[
        {
            "category":"Banks & Credit Unions",
            "subcategory":"Bank",
            "type":"Services"
        }
    ],
    "sg:phone":"+1 225 749 9050",
    "sg:postcode":"70719",
    "sg:province":"LA",
    "sg:tags":[
        "company",
        "trust"
    ],
    "wof:name":"Holtrachem Liquidating Trust",
    "wof:placetype":"venue"
},
  "geometry": {"coordinates":[-91.233273,30.387639],"type":"Point"}
}