{
  "type": "Feature",
  "properties": {
    "iso:country":"US",
    "sg:address":"901 Ridgefield Rd",
    "sg:city":"Thibodaux",
    "sg:classifiers":[
        {
            "category":"Professional",
            "subcategory":"Accounting & Tax Preparation",
            "type":"Services"
        }
    ],
    "sg:phone":"+1 985 446 0994",
    "sg:postcode":"70301",
    "sg:province":"LA",
    "sg:tags":[
        "accountant"
    ],
    "wof:name":"Ann T Hebert CPA",
    "wof:placetype":"venue"
},
  "geometry": {"coordinates":[-90.82732799999999,29.792239],"type":"Point"}
}