{
  "type": "Feature",
  "properties": {
    "addr:full":"209 Marcon Dr Lafayette LA 70507",
    "addr:housenumber":"209",
    "addr:postcode":"70507",
    "addr:street":"Marcon Dr",
    "iso:country":"US",
    "sg:address":"209 Marcon Dr",
    "sg:city":"Lafayette",
    "sg:classifiers":[
        {
            "category":"Mining & Drilling",
            "type":"Manufacturing & Wholesale Goods"
        }
    ],
    "sg:phone":"+1 337 593 9987",
    "sg:postcode":"70507",
    "sg:province":"LA",
    "sg:tags":[
        "field",
        "oil"
    ],
    "wof:name":"Flow Petroleum Svc Inc",
    "wof:placetype":"venue"
},
  "geometry": {"coordinates":[-92.045896,30.259264],"type":"Point"}
}