{
  "type": "Feature",
  "properties": {
    "addr:full":"2095 N Hearne Ave Shreveport LA 71107",
    "addr:housenumber":"2095",
    "addr:postcode":"71107",
    "addr:street":"N Hearne Ave",
    "iso:country":"US",
    "sg:address":"2095 N Hearne Ave",
    "sg:city":"Shreveport",
    "sg:classifiers":[
        {
            "category":"Wholesale",
            "subcategory":"Electrical",
            "type":"Manufacturing & Wholesale Goods"
        }
    ],
    "sg:phone":"+1 318 227 8006",
    "sg:postcode":"71107",
    "sg:province":"LA",
    "sg:tags":[
        "transmission",
        "equipment",
        "power"
    ],
    "wof:name":"Conveyco Sales Of Alabama Inc",
    "wof:placetype":"venue"
},
  "geometry": {"coordinates":[-93.775809,32.532865],"type":"Point"}
}