{
  "type": "Feature",
  "properties": {
    "iso:country":"US",
    "sg:address":"411 S Main St",
    "sg:city":"St Martinville",
    "sg:classifiers":[
        {
            "category":"Banks & Credit Unions",
            "subcategory":"Bank",
            "type":"Services"
        }
    ],
    "sg:phone":"+1 337 394 5014",
    "sg:postcode":"70582",
    "sg:province":"LA",
    "sg:tags":[
        "loan"
    ],
    "wof:name":"First Community Credit",
    "wof:placetype":"venue"
},
  "geometry": {"coordinates":[-91.830164,30.120266],"type":"Point"}
}