{
  "type": "Feature",
  "properties": {
    "iso:country":"US",
    "sg:address":"3821 Franklin Ave",
    "sg:city":"New Orleans",
    "sg:classifiers":[
        {
            "category":"Education",
            "subcategory":"School",
            "type":"Public Place"
        }
    ],
    "sg:phone":"+1 504 942 3634",
    "sg:postcode":"70122",
    "sg:province":"LA",
    "sg:tags":[
        "high",
        "middle",
        "elementary"
    ],
    "wof:name":"Orleans Parish School Board",
    "wof:placetype":"venue"
},
  "geometry": {"coordinates":[-90.049677,29.997851],"type":"Point"}
}