{
  "type": "Feature",
  "properties": {
    "iso:country":"US",
    "sg:address":"1438 Clinton Dr",
    "sg:city":"Denham Springs",
    "sg:classifiers":[
        {
            "category":"Building & Trades",
            "subcategory":"Electrical",
            "type":"Services"
        }
    ],
    "sg:phone":"+1 225 665 3358",
    "sg:postcode":"70726",
    "sg:province":"LA",
    "sg:tags":[
        "electric",
        "contractor"
    ],
    "wof:name":"ATCO Electric",
    "wof:placetype":"venue"
},
  "geometry": {"coordinates":[-90.95208700000001,30.503019],"type":"Point"}
}