{
  "type": "Feature",
  "properties": {
    "addr:full":"4201 Moss St Lafayette LA 70507",
    "addr:housenumber":"4201",
    "addr:postcode":"70507",
    "addr:street":"Moss St",
    "iso:country":"US",
    "sg:address":"4201 Moss St",
    "sg:city":"Lafayette",
    "sg:classifiers":[
        {
            "category":"Education",
            "subcategory":"School",
            "type":"Public Place"
        }
    ],
    "sg:phone":"+1 337 233 2496",
    "sg:postcode":"70507",
    "sg:province":"LA",
    "sg:tags":[
        "high",
        "middle",
        "elementary"
    ],
    "wof:name":"Middle Schools",
    "wof:placetype":"venue"
},
  "geometry": {"coordinates":[-92.00659899999999,30.2845],"type":"Point"}
}