{
  "type": "Feature",
  "properties": {
    "iso:country":"US",
    "sg:address":"728 W 11th Ave",
    "sg:city":"Covington",
    "sg:classifiers":[
        {
            "category":"Health Services",
            "subcategory":"Doctor",
            "type":"Services"
        }
    ],
    "sg:phone":"+1 985 893 3395",
    "sg:postcode":"70433",
    "sg:province":"LA",
    "sg:tags":[
        "physician",
        "surgeon"
    ],
    "wof:name":"Northlake Pediatrics",
    "wof:placetype":"venue"
},
  "geometry": {"coordinates":[-90.113868,30.470272],"type":"Point"}
}