{
  "type": "Feature",
  "properties": {
    "iso:country":"US",
    "sg:address":"807 4th St",
    "sg:city":"Jonesville",
    "sg:phone":"+1 318 339 9281",
    "sg:postcode":"71343",
    "sg:province":"LA",
    "sg:tags":[
        "oil"
    ],
    "wof:name":"Cloutier Oil Co",
    "wof:placetype":"venue"
},
  "geometry": {"coordinates":[-91.82198200000001,31.628603],"type":"Point"}
}