{
  "type": "Feature",
  "properties": {
    "iso:country":"US",
    "sg:address":"2041 Silverside Dr",
    "sg:city":"Baton Rouge",
    "sg:classifiers":[
        {
            "category":"Social Services",
            "type":"Services"
        }
    ],
    "sg:phone":"+1 225 765 5273",
    "sg:postcode":"70808",
    "sg:province":"LA",
    "sg:tags":[
        "care",
        "center",
        "day"
    ],
    "wof:name":"Our Lady Of The Lake Regional",
    "wof:placetype":"venue"
},
  "geometry": {"coordinates":[-91.112044,30.395975],"type":"Point"}
}