{
  "type": "Feature",
  "properties": {
    "iso:country":"US",
    "sg:address":"7119 Prairie Rd",
    "sg:city":"Winnsboro",
    "sg:classifiers":[
        {
            "category":"Insurance",
            "subcategory":"Health Insurance",
            "type":"Services"
        }
    ],
    "sg:phone":"+1 318 435 4709",
    "sg:postcode":"71295",
    "sg:province":"LA",
    "sg:tags":[
        "carrier"
    ],
    "wof:name":"Select Benefits Services",
    "wof:placetype":"venue"
},
  "geometry": {"coordinates":[-91.72524799999999,32.158171],"type":"Point"}
}