{
  "type": "Feature",
  "properties": {
    "iso:country":"US",
    "sg:address":"629 N Spring St",
    "sg:city":"Shreveport",
    "sg:classifiers":[
        {
            "category":"Organizations",
            "subcategory":"Professional Association",
            "type":"Services"
        }
    ],
    "sg:phone":"+1 318 221 5233",
    "sg:postcode":"71101",
    "sg:province":"LA",
    "wof:name":"Red River Valley Assn",
    "wof:placetype":"venue"
},
  "geometry": {"coordinates":[-93.74524,32.513582],"type":"Point"}
}