{
  "type": "Feature",
  "properties": {
    "iso:country":"US",
    "sg:address":"5925 Line Ave",
    "sg:city":"Shreveport",
    "sg:classifiers":[
        {
            "category":"Real Estate",
            "subcategory":"Architect",
            "type":"Services"
        }
    ],
    "sg:phone":"+1 318 861 7669",
    "sg:postcode":"71106",
    "sg:province":"LA",
    "wof:name":"Ben Patterson",
    "wof:placetype":"venue"
},
  "geometry": {"coordinates":[-93.745955,32.45402],"type":"Point"}
}