{
  "type": "Feature",
  "properties": {
    "iso:country":"US",
    "sg:address":"4123 Woodland Dr",
    "sg:city":"New Orleans",
    "sg:classifiers":[
        {
            "category":"Education",
            "subcategory":"University",
            "type":"Public Place"
        }
    ],
    "sg:phone":"+1 504 394 7744",
    "sg:postcode":"70131",
    "sg:province":"LA",
    "sg:tags":[
        "college"
    ],
    "sg:website":"www.olhcc.edu",
    "wof:name":"Our Lady of Holy Cross College",
    "wof:placetype":"venue"
},
  "geometry": {"coordinates":[-89.993202,29.9097],"type":"Point"}
}