{
  "type": "Feature",
  "properties": {
    "iso:country":"US",
    "sg:address":"4900 State Rte 311",
    "sg:city":"Houma",
    "sg:classifiers":[
        {
            "category":"Restaurant",
            "type":"Food & Drink"
        }
    ],
    "sg:phone":"+1 985 223 4441",
    "sg:postcode":"70360",
    "sg:province":"LA",
    "sg:tags":[
        "delicatessen"
    ],
    "wof:name":"Bali's Deli",
    "wof:placetype":"venue"
},
  "geometry": {"coordinates":[-90.758651,29.599361],"type":"Point"}
}