{
  "type": "Feature",
  "properties": {
    "iso:country":"US",
    "sg:address":"309 W 3rd St",
    "sg:city":"Thibodaux",
    "sg:classifiers":[
        {
            "category":"Government",
            "subcategory":"Office",
            "type":"Public Place"
        }
    ],
    "sg:phone":"+1 985 448 1291",
    "sg:postcode":"70301",
    "sg:province":"LA",
    "wof:name":"Honorable Bruce Simpson",
    "wof:placetype":"venue"
},
  "geometry": {"coordinates":[-90.81994899999999,29.797414],"type":"Point"}
}