{
  "type": "Feature",
  "properties": {
    "addr:full":"1800 South Ln Mandeville LA 70471",
    "addr:housenumber":"1800",
    "addr:postcode":"70471",
    "addr:street":"South Ln",
    "iso:country":"US",
    "sg:address":"1800 South Ln",
    "sg:city":"Mandeville",
    "sg:classifiers":[
        {
            "category":"Professional",
            "type":"Services"
        }
    ],
    "sg:phone":"+1 985 898 2221",
    "sg:postcode":"70471",
    "sg:province":"LA",
    "sg:tags":[
        "establishment"
    ],
    "wof:name":"Phoenix Snow Group",
    "wof:placetype":"venue"
},
  "geometry": {"coordinates":[-90.03397200000001,30.427166],"type":"Point"}
}