{
  "type": "Feature",
  "properties": {
    "iso:country":"US",
    "sg:address":"120 E Peck Blvd",
    "sg:city":"Lafayette",
    "sg:classifiers":[
        {
            "category":"Professional",
            "subcategory":"Accounting & Tax Preparation",
            "type":"Services"
        }
    ],
    "sg:phone":"+1 337 984 6913",
    "sg:postcode":"70508",
    "sg:province":"LA",
    "wof:name":"Walter Gaudet",
    "wof:placetype":"venue"
},
  "geometry": {"coordinates":[-92.05759500000001,30.145744],"type":"Point"}
}