{
  "type": "Feature",
  "properties": {
    "addr:full":"3300 Metairie Rd Metairie LA 70001",
    "addr:postcode":"3300;70001",
    "addr:street":"Metairie Rd",
    "iso:country":"US",
    "sg:address":"3300 Metairie Rd",
    "sg:city":"Metairie",
    "sg:classifiers":[
        {
            "category":"Government",
            "subcategory":"Police Station",
            "type":"Public Place"
        }
    ],
    "sg:phone":"+1 504 832 2300",
    "sg:postcode":"70001",
    "sg:province":"LA",
    "sg:tags":[
        "sheriff"
    ],
    "wof:name":"Jefferson Parish Sheriff's Ofc",
    "wof:placetype":"venue"
},
  "geometry": {"coordinates":[-90.158332,29.975841],"type":"Point"}
}