{
  "type": "Feature",
  "properties": {
    "addr:full":"3578 State Rte 359 Washington LA 70589",
    "addr:housenumber":"3578",
    "addr:postcode":"70589",
    "addr:street":"State Rte 359",
    "iso:country":"US",
    "sg:address":"3578 State Rte 359",
    "sg:city":"Washington",
    "sg:classifiers":[
        {
            "category":"Organizations",
            "subcategory":"Membership Organization",
            "type":"Services"
        }
    ],
    "sg:phone":"+1 337 826 7035",
    "sg:postcode":"70589",
    "sg:province":"LA",
    "wof:name":"Louisiana Quarter Horse Assn",
    "wof:placetype":"venue"
},
  "geometry": {"coordinates":[-91.96489800000001,30.671473],"type":"Point"}
}