{
  "type": "Feature",
  "properties": {
    "iso:country":"US",
    "sg:address":"801 Hickory St",
    "sg:city":"Thibodaux",
    "sg:classifiers":[
        {
            "category":"Retail",
            "subcategory":"Auto Repair",
            "type":"Services"
        }
    ],
    "sg:phone":"+1 985 446 0573",
    "sg:postcode":"70301",
    "sg:province":"LA",
    "sg:tags":[
        "general"
    ],
    "wof:name":"Steves Auto Care Inc",
    "wof:placetype":"venue"
},
  "geometry": {"coordinates":[-90.83429,29.790657],"type":"Point"}
}