{
  "type": "Feature",
  "properties": {
    "addr:full":"301 Davis Dr Pineville LA 71360",
    "addr:housenumber":"301",
    "addr:postcode":"71360",
    "addr:street":"Davis Dr",
    "iso:country":"US",
    "sg:address":"301 Davis Dr",
    "sg:city":"Pineville",
    "sg:classifiers":[
        {
            "category":"Autos & Motor Vehicles",
            "subcategory":"Fuel & Gas Station",
            "type":"Retail Goods"
        }
    ],
    "sg:phone":"+1 318 487 6963",
    "sg:postcode":"71360",
    "sg:province":"LA",
    "sg:tags":[
        "automotive",
        "station",
        "gasoline",
        "oil"
    ],
    "wof:name":"Bordelon's Cenla Towing",
    "wof:placetype":"venue"
},
  "geometry": {"coordinates":[-92.40658999999999,31.327916],"type":"Point"}
}