{
  "type": "Feature",
  "properties": {
    "iso:country":"US",
    "sg:address":"2316 Bessie St",
    "sg:city":"Shreveport",
    "sg:classifiers":[
        {
            "category":"Organizations",
            "subcategory":"Religious Organization",
            "type":"Services"
        }
    ],
    "sg:phone":"+1 318 425 7270",
    "sg:postcode":"71103",
    "sg:province":"LA",
    "sg:tags":[
        "church"
    ],
    "wof:name":"Midway Baptist Church No 1",
    "wof:placetype":"venue"
},
  "geometry": {"coordinates":[-93.775739,32.486244],"type":"Point"}
}