{
  "type": "Feature",
  "properties": {
    "iso:country":"US",
    "sg:address":"534 Queen Anne Dr",
    "sg:city":"Slidell",
    "sg:classifiers":[
        {
            "category":"Shopping",
            "subcategory":"Computers & Home Electronics",
            "type":"Retail Goods"
        }
    ],
    "sg:phone":"+1 985 781 2063",
    "sg:postcode":"70460",
    "sg:province":"LA",
    "sg:tags":[
        "product",
        "electronic"
    ],
    "wof:name":"Northshore Logistics LLC",
    "wof:placetype":"venue"
},
  "geometry": {"coordinates":[-89.815358,30.29281],"type":"Point"}
}