{
  "type": "Feature",
  "properties": {
    "iso:country":"US",
    "sg:address":"8400 W Judge Perez Dr",
    "sg:city":"Chalmette",
    "sg:classifiers":[
        {
            "category":"Banks & Credit Unions",
            "subcategory":"Bank",
            "type":"Services"
        }
    ],
    "sg:phone":"+1 504 279 5441",
    "sg:postcode":"70043",
    "sg:province":"LA",
    "sg:tags":[
        "cashing",
        "check"
    ],
    "wof:name":"Cash Tyme",
    "wof:placetype":"venue"
},
  "geometry": {"coordinates":[-89.979119,29.953279],"type":"Point"}
}