{
  "type": "Feature",
  "properties": {
    "iso:country":"US",
    "sg:address":"2325 Middle Creek Blvd",
    "sg:city":"Bossier City",
    "sg:classifiers":[
        {
            "category":"Recreation",
            "subcategory":"Amusement Park",
            "type":"Entertainment"
        }
    ],
    "sg:phone":"+1 318 635 4887",
    "sg:postcode":"71111",
    "sg:province":"LA",
    "wof:name":"Six Flags",
    "wof:placetype":"venue"
},
  "geometry": {"coordinates":[-93.638623,32.570421],"type":"Point"}
}