{
  "type": "Feature",
  "properties": {
    "iso:country":"US",
    "sg:address":"100 W Texas Ave",
    "sg:city":"Ruston",
    "sg:classifiers":[
        {
            "category":"Professional",
            "subcategory":"Lawyer & Legal Services",
            "type":"Services"
        }
    ],
    "sg:phone":"+1 318 251 5100",
    "sg:postcode":"71270",
    "sg:province":"LA",
    "sg:tags":[
        "attorney"
    ],
    "wof:name":"Lincoln Parish District Atty",
    "wof:placetype":"venue"
},
  "geometry": {"coordinates":[-92.639442,32.526725],"type":"Point"}
}