{
  "type": "Feature",
  "properties": {
    "addr:full":"19404 Hwy 16 Amite LA 70422",
    "addr:housenumber":"19404",
    "addr:postcode":"70422",
    "addr:street":"Hwy 16 Amite",
    "iso:country":"US",
    "sg:address":"19404 Hwy 16",
    "sg:city":"Amite",
    "sg:classifiers":[
        {
            "category":"Restaurant",
            "type":"Food & Drink"
        }
    ],
    "sg:phone":"+1 985 747 2100",
    "sg:postcode":"70422",
    "sg:province":"LA",
    "wof:name":"Neighborhood Cafe",
    "wof:placetype":"venue"
},
  "geometry": {"coordinates":[-90.402021,30.744355],"type":"Point"}
}