{
  "type": "Feature",
  "properties": {
    "iso:country":"US",
    "sg:address":"1575 Parks Rd",
    "sg:city":"Benton",
    "sg:classifiers":[
        {
            "category":"Building & Trades",
            "subcategory":"Construction",
            "type":"Services"
        }
    ],
    "sg:phone":"+1 318 965 0015",
    "sg:postcode":"71006",
    "sg:province":"LA",
    "sg:tags":[
        "utility",
        "contractor"
    ],
    "wof:name":"Cypress Bay Utility Svc Inc",
    "wof:placetype":"venue"
},
  "geometry": {"coordinates":[-93.64625700000001,32.657439],"type":"Point"}
}