{
  "type": "Feature",
  "properties": {
    "iso:country":"US",
    "sg:address":"16330 US Hwy 371",
    "sg:city":"Minden",
    "sg:classifiers":[
        {
            "category":"Organizations",
            "subcategory":"Religious Organization",
            "type":"Services"
        }
    ],
    "sg:phone":"+1 318 377 5775",
    "sg:postcode":"71055",
    "sg:province":"LA",
    "wof:name":"Whispering Pine MB Church",
    "wof:placetype":"venue"
},
  "geometry": {"coordinates":[-93.37205,32.672246],"type":"Point"}
}