{
  "type": "Feature",
  "properties": {
    "iso:country":"US",
    "sg:address":"500 Juliette Pl",
    "sg:city":"Lafayette",
    "sg:classifiers":[
        {
            "category":"Health Services",
            "subcategory":"Doctor",
            "type":"Services"
        }
    ],
    "sg:phone":"+1 337 232 2520",
    "sg:postcode":"70506",
    "sg:province":"LA",
    "sg:tags":[
        "physician",
        "surgeon"
    ],
    "wof:name":"Acadiana Medical Oncology",
    "wof:placetype":"venue"
},
  "geometry": {"coordinates":[-92.028837,30.215895],"type":"Point"}
}