{
  "type": "Feature",
  "properties": {
    "addr:full":"604 Canal St New Orleans LA 70130",
    "addr:housenumber":"604",
    "addr:postcode":"70130",
    "addr:street":"Canal St",
    "iso:country":"US",
    "sg:address":"604 Canal St",
    "sg:city":"New Orleans",
    "sg:classifiers":[
        {
            "category":"Shopping",
            "subcategory":"Luggage & Leather Goods",
            "type":"Retail Goods"
        }
    ],
    "sg:phone":"+1 504 568 1953",
    "sg:postcode":"70130",
    "sg:province":"LA",
    "sg:website":"www.rapps.com",
    "wof:name":"Rapp's Luggage & Gifts",
    "wof:placetype":"venue"
},
  "geometry": {"coordinates":[-90.068415,29.952991],"type":"Point"}
}