{
  "type": "Feature",
  "properties": {
    "addr:full":"1201 E Burton St Sulphur LA 70663",
    "addr:housenumber":"1201",
    "addr:postcode":"70663",
    "addr:street":"E Burton St",
    "iso:country":"US",
    "sg:address":"1201 E Burton St",
    "sg:city":"Sulphur",
    "sg:classifiers":[
        {
            "category":"Education",
            "subcategory":"School",
            "type":"Public Place"
        }
    ],
    "sg:phone":"+1 337 527 7566",
    "sg:postcode":"70663",
    "sg:province":"LA",
    "wof:name":"E K Key Elementary School",
    "wof:placetype":"venue"
},
  "geometry": {"coordinates":[-93.36784900000001,30.242002],"type":"Point"}
}