{
  "type": "Feature",
  "properties": {
    "iso:country":"US",
    "sg:address":"2720 Independence St",
    "sg:city":"Metairie",
    "sg:classifiers":[
        {
            "category":"Building & Trades",
            "subcategory":"Construction",
            "type":"Services"
        }
    ],
    "sg:phone":"+1 504 456 1111",
    "sg:postcode":"70006",
    "sg:province":"LA",
    "sg:tags":[
        "insulation",
        "heat",
        "contractor"
    ],
    "wof:name":"Quality Thermal",
    "wof:placetype":"venue"
},
  "geometry": {"coordinates":[-90.178004,30.000148],"type":"Point"}
}