{
  "type": "Feature",
  "properties": {
    "iso:country":"US",
    "sg:address":"615 Exposition Blvd",
    "sg:city":"New Orleans",
    "sg:classifiers":[
        {
            "category":"Education",
            "subcategory":"Dance Studio",
            "type":"Public Place"
        }
    ],
    "sg:phone":"+1 504 897 1269",
    "sg:postcode":"70118",
    "sg:province":"LA",
    "sg:tags":[
        "instruction",
        "dancing"
    ],
    "wof:name":"Do The Zyedco",
    "wof:placetype":"venue"
},
  "geometry": {"coordinates":[-90.12700700000001,29.923052],"type":"Point"}
}