{
  "type": "Feature",
  "properties": {
    "addr:full":"2320 Commercial Dr Port Allen LA 70767",
    "addr:housenumber":"2320",
    "addr:postcode":"70767",
    "addr:street":"Commercial Dr",
    "iso:country":"US",
    "sg:address":"2320 Commercial Dr",
    "sg:city":"Port Allen",
    "sg:classifiers":[
        {
            "category":"Real Estate",
            "subcategory":"Real Estate Operator",
            "type":"Services"
        }
    ],
    "sg:phone":"+1 225 334 0225",
    "sg:postcode":"70767",
    "sg:province":"LA",
    "sg:tags":[
        "apartment"
    ],
    "wof:name":"Allen Courts Apartments II",
    "wof:placetype":"venue"
},
  "geometry": {"coordinates":[-91.23249800000001,30.448007],"type":"Point"}
}