{
  "type": "Feature",
  "properties": {
    "iso:country":"US",
    "sg:address":"3854 American Way",
    "sg:city":"Baton Rouge",
    "sg:classifiers":[
        {
            "category":"Real Estate",
            "subcategory":"Real Estate Agent",
            "type":"Services"
        }
    ],
    "sg:phone":"+1 225 292 2686",
    "sg:postcode":"70816",
    "sg:province":"LA",
    "sg:tags":[
        "management"
    ],
    "wof:name":"Security National Properties",
    "wof:placetype":"venue"
},
  "geometry": {"coordinates":[-91.05357100000001,30.417256],"type":"Point"}
}