{
  "type": "Feature",
  "properties": {
    "iso:country":"US",
    "sg:address":"2121 Banks St",
    "sg:city":"New Orleans",
    "sg:classifiers":[
        {
            "category":"Autos & Motor Vehicles",
            "subcategory":"Auto Supplies",
            "type":"Retail Goods"
        }
    ],
    "sg:phone":"+1 504 523 5607",
    "sg:postcode":"70119",
    "sg:province":"LA",
    "sg:tags":[
        "automobile",
        "parts"
    ],
    "wof:name":"Broadmoor Auto Parts Inc",
    "wof:placetype":"venue"
},
  "geometry": {"coordinates":[-90.08429700000001,29.959375],"type":"Point"}
}