{
  "type": "Feature",
  "properties": {
    "addr:full":"1849 Octavia Dr Mandeville LA 70448",
    "addr:housenumber":"1849",
    "addr:postcode":"70448",
    "addr:street":"Octavia Dr",
    "iso:country":"US",
    "sg:address":"1849 Octavia Dr",
    "sg:city":"Mandeville",
    "sg:classifiers":[
        {
            "category":"Real Estate",
            "subcategory":"Architect",
            "type":"Services"
        },
        {
            "category":"Professional",
            "subcategory":"Business Services",
            "type":"Services"
        }
    ],
    "sg:phone":"+1 985 626 5396",
    "sg:postcode":"70448",
    "sg:province":"LA",
    "sg:tags":[
        "home",
        "planning",
        "design"
    ],
    "wof:name":"Jay M Fiorello Inc",
    "wof:placetype":"venue"
},
  "geometry": {"coordinates":[-90.024456,30.376888],"type":"Point"}
}