{
  "type": "Feature",
  "properties": {
    "iso:country":"US",
    "sg:address":"101 Oak St",
    "sg:city":"Donner",
    "sg:classifiers":[
        {
            "category":"Professional",
            "type":"Services"
        }
    ],
    "sg:phone":"+1 985 448 0541",
    "sg:postcode":"70356",
    "sg:province":"LA",
    "wof:name":"Beverly McDonald",
    "wof:placetype":"venue"
},
  "geometry": {"coordinates":[-90.950936,29.69428],"type":"Point"}
}