{
  "type": "Feature",
  "properties": {
    "iso:country":"US",
    "sg:address":"124 Bertrand Dr",
    "sg:city":"Lafayette",
    "sg:classifiers":[
        {
            "category":"Home & Garden",
            "subcategory":"Household Appliances",
            "type":"Retail Goods"
        }
    ],
    "sg:phone":"+1 337 262 0602",
    "sg:postcode":"70506",
    "sg:province":"LA",
    "wof:name":"Conn's Appliances",
    "wof:placetype":"venue"
},
  "geometry": {"coordinates":[-92.04154200000001,30.207016],"type":"Point"}
}