{
  "type": "Feature",
  "properties": {
    "iso:country":"US",
    "sg:address":"16060 Joe Sevario Rd",
    "sg:city":"Prairieville",
    "sg:classifiers":[
        {
            "category":"Autos & Motor Vehicles",
            "subcategory":"Automobile Sales",
            "type":"Retail Goods"
        }
    ],
    "sg:phone":"+1 225 622 7589",
    "sg:postcode":"70769",
    "sg:province":"LA",
    "sg:tags":[
        "car",
        "dealer"
    ],
    "wof:name":"Galvez Motorcars",
    "wof:placetype":"venue"
},
  "geometry": {"coordinates":[-90.904723,30.300374],"type":"Point"}
}