{
  "type": "Feature",
  "properties": {
    "iso:country":"US",
    "sg:address":"630 Orange St",
    "sg:city":"Lake Charles",
    "sg:classifiers":[
        {
            "category":"Retail",
            "subcategory":"Auto Repair",
            "type":"Services"
        }
    ],
    "sg:phone":"+1 337 437 7653",
    "sg:postcode":"70601",
    "sg:province":"LA",
    "sg:tags":[
        "repairing",
        "tire"
    ],
    "wof:name":"Jeff Wilder Tire Svc",
    "wof:placetype":"venue"
},
  "geometry": {"coordinates":[-93.212524,30.20414],"type":"Point"}
}