{
  "type": "Feature",
  "properties": {
    "iso:country":"US",
    "sg:address":"3400 Ames Blvd",
    "sg:city":"Marrero",
    "sg:classifiers":[
        {
            "category":"Real Estate",
            "subcategory":"Real Estate Operator",
            "type":"Services"
        }
    ],
    "sg:phone":"+1 504 341 6540",
    "sg:postcode":"70072",
    "sg:province":"LA",
    "sg:tags":[
        "mobile",
        "home",
        "site"
    ],
    "wof:name":"Sievers Trailer Court",
    "wof:placetype":"venue"
},
  "geometry": {"coordinates":[-90.10943899999999,29.855845],"type":"Point"}
}