{
  "type": "Feature",
  "properties": {
    "addr:full":"717 Gulf St Lake Charles LA 70601",
    "addr:housenumber":"717",
    "addr:postcode":"70601",
    "addr:street":"Gulf St",
    "iso:country":"US",
    "sg:address":"717 Gulf St",
    "sg:city":"Lake Charles",
    "sg:classifiers":[
        {
            "category":"Building & Trades",
            "subcategory":"Pest Control",
            "type":"Services"
        }
    ],
    "sg:phone":"+1 337 478 7826",
    "sg:postcode":"70601",
    "sg:province":"LA",
    "sg:website":"www.mckenziepestcontrol.com",
    "wof:name":"Mc Kenzie Pest Control",
    "wof:placetype":"venue"
},
  "geometry": {"coordinates":[-93.210097,30.202619],"type":"Point"}
}