{
  "type": "Feature",
  "properties": {
    "iso:country":"US",
    "sg:address":"13491 US Hwy 90",
    "sg:city":"Boutte",
    "sg:classifiers":[
        {
            "category":"Building & Trades",
            "subcategory":"Equipment Rental",
            "type":"Services"
        }
    ],
    "sg:phone":"+1 985 331 2289",
    "sg:postcode":"70039",
    "sg:province":"LA",
    "sg:tags":[
        "scaffolding"
    ],
    "wof:name":"Miken Specialties",
    "wof:placetype":"venue"
},
  "geometry": {"coordinates":[-90.37750699999999,29.904607],"type":"Point"}
}