{
  "type": "Feature",
  "properties": {
    "iso:country":"US",
    "sg:address":"1206 Marion Hwy",
    "sg:city":"Farmerville",
    "sg:classifiers":[
        {
            "category":"Education",
            "subcategory":"School",
            "type":"Public Place"
        }
    ],
    "sg:phone":"+1 318 368 2437",
    "sg:postcode":"71241",
    "sg:province":"LA",
    "wof:name":"Union Parish Special Education",
    "wof:placetype":"venue"
},
  "geometry": {"coordinates":[-92.38829,32.794037],"type":"Point"}
}