{
  "type": "Feature",
  "properties": {
    "addr:full":"901 Wilson St Lafayette LA 70503",
    "addr:housenumber":"901",
    "addr:postcode":"70503",
    "addr:street":"Wilson St",
    "iso:country":"US",
    "sg:address":"901 Wilson St",
    "sg:city":"Lafayette",
    "sg:classifiers":[
        {
            "category":"Health Services",
            "subcategory":"Medical Lab",
            "type":"Services"
        }
    ],
    "sg:phone":"+1 337 269 5552",
    "sg:postcode":"70503",
    "sg:province":"LA",
    "sg:tags":[
        "resonance",
        "magnetic",
        "imaging"
    ],
    "wof:name":"Advanced Imaging Of Lafayette",
    "wof:placetype":"venue"
},
  "geometry": {"coordinates":[-92.017206,30.207096],"type":"Point"}
}