{
  "type": "Feature",
  "properties": {
    "iso:country":"US",
    "sg:address":"16 Professional Dr",
    "sg:city":"Houma",
    "sg:classifiers":[
        {
            "category":"Professional",
            "subcategory":"Accounting & Tax Preparation",
            "type":"Services"
        }
    ],
    "sg:phone":"+1 985 868 4056",
    "sg:postcode":"70360",
    "sg:province":"LA",
    "sg:tags":[
        "accountant"
    ],
    "wof:name":"Guidry & Guidry",
    "wof:placetype":"venue"
},
  "geometry": {"coordinates":[-90.735964,29.593341],"type":"Point"}
}