{
  "type": "Feature",
  "properties": {
    "iso:country":"US",
    "sg:address":"16339 George Oneal Rd",
    "sg:city":"Baton Rouge",
    "sg:classifiers":[
        {
            "category":"Wholesale",
            "subcategory":"Construction Materials",
            "type":"Manufacturing & Wholesale Goods"
        }
    ],
    "sg:phone":"+1 225 753 1314",
    "sg:postcode":"70817",
    "sg:province":"LA",
    "wof:name":"Beveleed GL Designs of The S",
    "wof:placetype":"venue"
},
  "geometry": {"coordinates":[-91.005152,30.407266],"type":"Point"}
}