{
  "type": "Feature",
  "properties": {
    "iso:country":"US",
    "sg:address":"713 N Chataignier St",
    "sg:city":"Ville Platte",
    "sg:classifiers":[
        {
            "category":"Retail",
            "subcategory":"Auto Repair",
            "type":"Services"
        }
    ],
    "sg:phone":"+1 337 363 4341",
    "sg:postcode":"70586",
    "sg:province":"LA",
    "sg:tags":[
        "general"
    ],
    "wof:name":"General Repair Shop",
    "wof:placetype":"venue"
},
  "geometry": {"coordinates":[-92.268947,30.693197],"type":"Point"}
}