{
  "type": "Feature",
  "properties": {
    "iso:country":"US",
    "sg:address":"900 Pierremont Rd",
    "sg:city":"Shreveport",
    "sg:classifiers":[
        {
            "category":"Banks & Credit Unions",
            "subcategory":"Investment Brokerage",
            "type":"Services"
        },
        {
            "category":"Professional",
            "subcategory":"Management & Consulting",
            "type":"Services"
        }
    ],
    "sg:phone":"+1 318 219 4188",
    "sg:postcode":"71106",
    "sg:province":"LA",
    "sg:tags":[
        "consultant",
        "planning",
        "financial"
    ],
    "wof:name":"Chris Harbuck Chartered Financ",
    "wof:placetype":"venue"
},
  "geometry": {"coordinates":[-93.748164,32.454704],"type":"Point"}
}