{
  "type": "Feature",
  "properties": {
    "iso:country":"US",
    "sg:address":"530 N 4th St",
    "sg:city":"Eunice",
    "sg:classifiers":[
        {
            "category":"Personal",
            "subcategory":"Beauty Salon",
            "type":"Services"
        }
    ],
    "sg:phone":"+1 337 457 4489",
    "sg:postcode":"70535",
    "sg:province":"LA",
    "wof:name":"Cobb's Beauty Salon",
    "wof:placetype":"venue"
},
  "geometry": {"coordinates":[-92.4188,30.499228],"type":"Point"}
}