{
  "type": "Feature",
  "properties": {
    "addr:full":"606 US Hwy 90 Jennings LA 70546",
    "addr:housenumber":"606",
    "addr:postcode":"70546",
    "addr:street":"Us Hwy 90",
    "iso:country":"US",
    "sg:address":"606 US Hwy 90",
    "sg:city":"Jennings",
    "sg:classifiers":[
        {
            "category":"Building & Trades",
            "subcategory":"Construction",
            "type":"Services"
        }
    ],
    "sg:phone":"+1 337 616 8137",
    "sg:postcode":"70546",
    "sg:province":"LA",
    "sg:tags":[
        "repairing",
        "remodeling",
        "contractor"
    ],
    "wof:name":"West Remodeling",
    "wof:placetype":"venue"
},
  "geometry": {"coordinates":[-92.652474,30.216487],"type":"Point"}
}