{
  "type": "Feature",
  "properties": {
    "iso:country":"US",
    "sg:address":"3122 Louisville Ave",
    "sg:city":"Monroe",
    "sg:classifiers":[
        {
            "category":"Communications",
            "subcategory":"Radio Station",
            "type":"Services"
        }
    ],
    "sg:phone":"+1 318 323 5953",
    "sg:postcode":"71201",
    "sg:province":"LA",
    "sg:tags":[
        "company",
        "broadcasting"
    ],
    "wof:name":"KOUS",
    "wof:placetype":"venue"
},
  "geometry": {"coordinates":[-92.085296,32.522547],"type":"Point"}
}