{
  "type": "Feature",
  "properties": {
    "iso:country":"US",
    "sg:address":"125 W Broad St",
    "sg:city":"Lake Charles",
    "sg:classifiers":[
        {
            "category":"Restaurant",
            "type":"Food & Drink"
        }
    ],
    "sg:menulink":"http://www.allmenus.com/la/lake-charles/173668-wendys/menu/",
    "sg:phone":"+1 337 433 8852",
    "sg:postcode":"70601",
    "sg:province":"LA",
    "sg:tags":[
        "burger",
        "american",
        "soup"
    ],
    "wof:name":"Wendy's",
    "wof:placetype":"venue"
},
  "geometry": {"coordinates":[-93.217589,30.229373],"type":"Point"}
}