{
  "type": "Feature",
  "properties": {
    "addr:full":"3701 Magazine St New Orleans LA 70115",
    "addr:housenumber":"3701",
    "addr:postcode":"70115",
    "addr:street":"Magazine St",
    "iso:country":"US",
    "sg:address":"3701 Magazine St",
    "sg:city":"New Orleans",
    "sg:classifiers":[
        {
            "category":"Home & Garden",
            "subcategory":"Furniture",
            "type":"Retail Goods"
        }
    ],
    "sg:phone":"+1 504 895 9880",
    "sg:postcode":"70115",
    "sg:province":"LA",
    "wof:name":"Latitudes Show Room & Gallery",
    "wof:placetype":"venue"
},
  "geometry": {"coordinates":[-90.094093,29.921457],"type":"Point"}
}