{
  "type": "Feature",
  "properties": {
    "addr:full":"2913 Jackson St Alexandria LA 71301",
    "addr:housenumber":"2913",
    "addr:postcode":"71301",
    "addr:street":"Jackson St",
    "iso:country":"US",
    "sg:address":"2913 Jackson St",
    "sg:city":"Alexandria",
    "sg:classifiers":[
        {
            "category":"Insurance",
            "subcategory":"Insurance Agent",
            "type":"Services"
        }
    ],
    "sg:phone":"+1 318 561 2250",
    "sg:postcode":"71301",
    "sg:province":"LA",
    "wof:name":"Janell Robinson",
    "wof:placetype":"venue"
},
  "geometry": {"coordinates":[-92.468205,31.292171],"type":"Point"}
}