{
  "type": "Feature",
  "properties": {
    "iso:country":"US",
    "sg:address":"200 James Dr W",
    "sg:city":"St Rose",
    "sg:classifiers":[
        {
            "category":"Manufacturing",
            "subcategory":"Apparel",
            "type":"Manufacturing & Wholesale Goods"
        }
    ],
    "sg:phone":"+1 504 712 7100",
    "sg:postcode":"70047",
    "sg:province":"LA",
    "wof:name":"Wemco Inc",
    "wof:placetype":"venue"
},
  "geometry": {"coordinates":[-90.34686600000001,29.940013],"type":"Point"}
}