{
  "type": "Feature",
  "properties": {
    "addr:full":"45511 Hwy 1072 Franklinton LA 70438",
    "addr:housenumber":"45511",
    "addr:postcode":"1072;70438",
    "addr:street":"Hwy",
    "iso:country":"US",
    "sg:address":"45511 Hwy 1072",
    "sg:city":"Franklinton",
    "sg:classifiers":[
        {
            "category":"Retail",
            "subcategory":"Repair Shop",
            "type":"Services"
        }
    ],
    "sg:phone":"+1 985 839 3835",
    "sg:postcode":"70438",
    "sg:province":"LA",
    "sg:tags":[
        "upholsterer"
    ],
    "wof:name":"Buddy's Trim Shop",
    "wof:placetype":"venue"
},
  "geometry": {"coordinates":[-90.13330499999999,30.825525],"type":"Point"}
}