{
  "type": "Feature",
  "properties": {
    "iso:country":"US",
    "sg:address":"2836 E Main St",
    "sg:city":"Hessmer",
    "sg:classifiers":[
        {
            "category":"Restaurant",
            "type":"Food & Drink"
        }
    ],
    "sg:menulink":"http://www.allmenus.com/la/marksville/66743-pizza-pro/menu/",
    "sg:phone":"+1 318 563 8400",
    "sg:postcode":"71341",
    "sg:province":"LA",
    "sg:tags":[
        "american",
        "pizza"
    ],
    "wof:name":"Pizza Pro",
    "wof:placetype":"venue"
},
  "geometry": {"coordinates":[-92.122604,31.054532],"type":"Point"}
}