{
  "type": "Feature",
  "properties": {
    "iso:country":"US",
    "sg:address":"9799 Cortana Pl",
    "sg:city":"Baton Rouge",
    "sg:classifiers":[
        {
            "category":"Autos & Motor Vehicles",
            "subcategory":"Auto Supplies",
            "type":"Retail Goods"
        }
    ],
    "sg:phone":"+1 225 231 7103",
    "sg:postcode":"70815",
    "sg:province":"LA",
    "sg:tags":[
        "tire"
    ],
    "wof:name":"Tire Town Team",
    "wof:placetype":"venue"
},
  "geometry": {"coordinates":[-91.096885,30.458153],"type":"Point"}
}