{
  "type": "Feature",
  "properties": {
    "iso:country":"US",
    "sg:address":"524 Royal St",
    "sg:city":"New Orleans",
    "sg:classifiers":[
        {
            "category":"Shopping",
            "subcategory":"Clothing, Apparel, & Fashions",
            "type":"Retail Goods"
        }
    ],
    "sg:phone":"+1 504 568 0001",
    "sg:postcode":"70130",
    "sg:province":"LA",
    "sg:tags":[
        "accessory"
    ],
    "sg:website":"www.RazzleDazzle.com",
    "wof:name":"Razzle Dazzle",
    "wof:placetype":"venue"
},
  "geometry": {"coordinates":[-90.065805,29.95678],"type":"Point"}
}