{
  "type": "Feature",
  "properties": {
    "addr:full":"1800 Parkview Dr Monroe LA 71202",
    "addr:housenumber":"1800",
    "addr:postcode":"71202",
    "addr:street":"Parkview Dr",
    "iso:country":"US",
    "sg:address":"1800 Parkview Dr",
    "sg:city":"Monroe",
    "sg:classifiers":[
        {
            "category":"Organizations",
            "subcategory":"Religious Organization",
            "type":"Services"
        }
    ],
    "sg:phone":"+1 318 322 7446",
    "sg:postcode":"71202",
    "sg:province":"LA",
    "wof:name":"Bethel Church Of God In Christ",
    "wof:placetype":"venue"
},
  "geometry": {"coordinates":[-92.08901,32.487029],"type":"Point"}
}