{
  "type": "Feature",
  "properties": {
    "addr:full":"5420 Lapalco Blvd Marrero LA 70072",
    "addr:housenumber":"5420",
    "addr:postcode":"70072",
    "addr:street":"Lapalco Blvd Marrero",
    "iso:country":"US",
    "sg:address":"5420 Lapalco Blvd",
    "sg:city":"Marrero",
    "sg:classifiers":[
        {
            "category":"Home & Garden",
            "subcategory":"Garden Supply",
            "type":"Retail Goods"
        }
    ],
    "sg:phone":"+1 504 347 8777",
    "sg:postcode":"70072",
    "sg:province":"LA",
    "sg:tags":[
        "center"
    ],
    "wof:name":"Rose Garden & Pet Store",
    "wof:placetype":"venue"
},
  "geometry": {"coordinates":[-90.10833700000001,29.875282],"type":"Point"}
}