{
  "type": "Feature",
  "properties": {
    "iso:country":"US",
    "sg:address":"901 Crepe Myrtle St",
    "sg:city":"Pineville",
    "sg:classifiers":[
        {
            "category":"Education",
            "subcategory":"School",
            "type":"Public Place"
        }
    ],
    "sg:phone":"+1 318 487 9648",
    "sg:postcode":"71360",
    "sg:province":"LA",
    "wof:name":"Slocum School",
    "wof:placetype":"venue"
},
  "geometry": {"coordinates":[-92.42527,31.311044],"type":"Point"}
}