{
  "type": "Feature",
  "properties": {
    "iso:country":"US",
    "sg:address":"253 W Phelps Ave",
    "sg:city":"Shreveport",
    "sg:classifiers":[
        {
            "category":"Building & Trades",
            "subcategory":"Construction",
            "type":"Services"
        }
    ],
    "sg:phone":"+1 318 929 1352",
    "sg:postcode":"71107",
    "sg:province":"LA",
    "sg:tags":[
        "wallcoverings-installation",
        "wallpaper",
        "painting",
        "contractor"
    ],
    "wof:name":"Stavag Painting Mike",
    "wof:placetype":"venue"
},
  "geometry": {"coordinates":[-93.896544,32.581905],"type":"Point"}
}