{
  "type": "Feature",
  "properties": {
    "iso:country":"US",
    "sg:address":"3082 Hwy 562",
    "sg:city":"Wisner",
    "sg:classifiers":[
        {
            "category":"Freight",
            "type":"Transportation"
        }
    ],
    "sg:phone":"+1 318 724 6696",
    "sg:postcode":"71378",
    "sg:province":"LA",
    "sg:tags":[
        "grain",
        "elevator"
    ],
    "wof:name":"Wisner Elevator Co Inc",
    "wof:placetype":"venue"
},
  "geometry": {"coordinates":[-91.65344,31.986123],"type":"Point"}
}