{
  "type": "Feature",
  "properties": {
    "iso:country":"US",
    "sg:address":"6007 Financial Plz",
    "sg:city":"Shreveport",
    "sg:classifiers":[
        {
            "category":"Professional",
            "subcategory":"Management & Consulting",
            "type":"Services"
        }
    ],
    "sg:phone":"+1 318 688 6986",
    "sg:postcode":"71129",
    "sg:province":"LA",
    "sg:tags":[
        "home",
        "nursing"
    ],
    "sg:website":"www.hccci.com",
    "wof:name":"Health Care Capital Inc",
    "wof:placetype":"venue"
},
  "geometry": {"coordinates":[-93.858204,32.451437],"type":"Point"}
}