{
  "type": "Feature",
  "properties": {
    "iso:country":"US",
    "sg:address":"7632 Hwy 99",
    "sg:city":"Welsh",
    "sg:classifiers":[
        {
            "category":"Building & Trades",
            "subcategory":"Plumbing",
            "type":"Services"
        }
    ],
    "sg:phone":"+1 337 587 2222",
    "sg:postcode":"70591",
    "sg:province":"LA",
    "sg:tags":[
        "product",
        "management",
        "energy",
        "system"
    ],
    "wof:name":"Noble Energy Inc",
    "wof:placetype":"venue"
},
  "geometry": {"coordinates":[-92.816948,30.13396],"type":"Point"}
}