{
  "type": "Feature",
  "properties": {
    "addr:full":"1715 N Causeway Blvd Mandeville LA 70471",
    "addr:housenumber":"1715",
    "addr:postcode":"70471",
    "addr:street":"N Causeway Blvd",
    "iso:country":"US",
    "sg:address":"1715 N Causeway Blvd",
    "sg:city":"Mandeville",
    "sg:classifiers":[
        {
            "category":"Government",
            "subcategory":"Office",
            "type":"Public Place"
        }
    ],
    "sg:phone":"+1 985 624 4445",
    "sg:postcode":"70471",
    "sg:province":"LA",
    "sg:tags":[
        "state",
        "program"
    ],
    "wof:name":"Motor Vehicle Dept",
    "wof:placetype":"venue"
},
  "geometry": {"coordinates":[-90.08991399999999,30.386162],"type":"Point"}
}