{
  "type": "Feature",
  "properties": {
    "iso:country":"US",
    "sg:address":"11017 Perkins Rd",
    "sg:city":"Baton Rouge",
    "sg:classifiers":[
        {
            "category":"Freight",
            "type":"Transportation"
        }
    ],
    "sg:phone":"+1 225 757 1990",
    "sg:postcode":"70810",
    "sg:province":"LA",
    "sg:tags":[
        "trucking"
    ],
    "wof:name":"River City Transport",
    "wof:placetype":"venue"
},
  "geometry": {"coordinates":[-91.08900800000001,30.373859],"type":"Point"}
}