{
  "type": "Feature",
  "properties": {
    "iso:country":"US",
    "sg:address":"3919 Houston River Rd",
    "sg:city":"Westlake",
    "sg:classifiers":[
        {
            "category":"Travel",
            "subcategory":"Campground",
            "type":"Entertainment"
        }
    ],
    "sg:phone":"+1 337 433 9922",
    "sg:postcode":"70669",
    "sg:province":"LA",
    "wof:name":"Big Oaks Rv Park",
    "wof:placetype":"venue"
},
  "geometry": {"coordinates":[-93.308438,30.277787],"type":"Point"}
}