{
  "type": "Feature",
  "properties": {
    "iso:country":"US",
    "sg:address":"6865 Magnolia Beach Rd",
    "sg:city":"Denham Springs",
    "sg:classifiers":[
        {
            "category":"Professional",
            "type":"Services"
        }
    ],
    "sg:phone":"+1 225 791 2587",
    "sg:postcode":"70706",
    "sg:province":"LA",
    "sg:tags":[
        "establishment"
    ],
    "wof:name":"Fat Frog's Snowball",
    "wof:placetype":"venue"
},
  "geometry": {"coordinates":[-90.964416,30.532261],"type":"Point"}
}