{
  "type": "Feature",
  "properties": {
    "iso:country":"US",
    "sg:address":"1616 Veterans Memorial Dr",
    "sg:city":"Abbeville",
    "sg:classifiers":[
        {
            "category":"Retail",
            "subcategory":"Animal Services",
            "type":"Services"
        }
    ],
    "sg:phone":"+1 337 893 7388",
    "sg:postcode":"70510",
    "sg:province":"LA",
    "sg:tags":[
        "shelter"
    ],
    "wof:name":"Animal Aid For Vermilion Area",
    "wof:placetype":"venue"
},
  "geometry": {"coordinates":[-92.120239,29.981227],"type":"Point"}
}