{
  "type": "Feature",
  "properties": {
    "iso:country":"US",
    "sg:address":"7700 Chef Menteur Hwy",
    "sg:city":"New Orleans",
    "sg:classifiers":[
        {
            "category":"Travel",
            "subcategory":"Hotels & Motels",
            "type":"Entertainment"
        }
    ],
    "sg:phone":"+1 504 244 9108",
    "sg:postcode":"70126",
    "sg:province":"LA",
    "wof:name":"Jack's Motel",
    "wof:placetype":"venue"
},
  "geometry": {"coordinates":[-89.996911,30.012455],"type":"Point"}
}