{
  "type": "Feature",
  "properties": {
    "addr:full":"6505 Masonic Dr Alexandria LA 71301",
    "addr:housenumber":"6505",
    "addr:postcode":"71301",
    "addr:street":"Masonic Dr",
    "iso:country":"US",
    "sg:address":"6505 Masonic Dr",
    "sg:city":"Alexandria",
    "sg:classifiers":[
        {
            "category":"Retail",
            "subcategory":"Auto Repair",
            "type":"Services"
        }
    ],
    "sg:phone":"+1 318 487 1886",
    "sg:postcode":"71301",
    "sg:province":"LA",
    "sg:tags":[
        "transmission"
    ],
    "wof:name":"Alexandria Transmission Co",
    "wof:placetype":"venue"
},
  "geometry": {"coordinates":[-92.481357,31.251989],"type":"Point"}
}