{
  "type": "Feature",
  "properties": {
    "addr:full":"611 Main St Minden LA 71055",
    "addr:housenumber":"611",
    "addr:postcode":"71055",
    "addr:street":"Main St",
    "iso:country":"US",
    "sg:address":"611 Main St",
    "sg:city":"Minden",
    "sg:classifiers":[
        {
            "category":"Professional",
            "subcategory":"Accounting & Tax Preparation",
            "type":"Services"
        }
    ],
    "sg:phone":"+1 318 377 0858",
    "sg:postcode":"71055",
    "sg:province":"LA",
    "sg:tags":[
        "accountant"
    ],
    "wof:name":"Moore & LA Bruyere",
    "wof:placetype":"venue"
},
  "geometry": {"coordinates":[-93.287246,32.615154],"type":"Point"}
}