{
  "type": "Feature",
  "properties": {
    "iso:country":"US",
    "sg:address":"197 Antigua Dr",
    "sg:city":"Lafayette",
    "sg:classifiers":[
        {
            "category":"Arts & Performance",
            "subcategory":"Theater",
            "type":"Entertainment"
        }
    ],
    "sg:phone":"+1 337 984 5814",
    "sg:postcode":"70503",
    "sg:province":"LA",
    "sg:tags":[
        "group"
    ],
    "wof:name":"Acadian Society Entertainment",
    "wof:placetype":"venue"
},
  "geometry": {"coordinates":[-92.058482,30.179902],"type":"Point"}
}