{
  "type": "Feature",
  "properties": {
    "addr:full":"216 W Thomas St Hammond LA 70401",
    "addr:housenumber":"216",
    "addr:postcode":"70401",
    "addr:street":"W Thomas St",
    "iso:country":"US",
    "sg:address":"216 W Thomas St",
    "sg:city":"Hammond",
    "sg:classifiers":[
        {
            "category":"Health Services",
            "subcategory":"Hospital",
            "type":"Services"
        }
    ],
    "sg:phone":"+1 985 340 1999",
    "sg:postcode":"70401",
    "sg:province":"LA",
    "sg:tags":[
        "mental"
    ],
    "wof:name":"Winning In Life Coaching",
    "wof:placetype":"venue"
},
  "geometry": {"coordinates":[-90.46251700000001,30.503818],"type":"Point"}
}