{
  "type": "Feature",
  "properties": {
    "iso:country":"US",
    "sg:address":"602 Brashear Ave",
    "sg:city":"Morgan City",
    "sg:classifiers":[
        {
            "category":"Shopping",
            "subcategory":"Used Merchandise",
            "type":"Retail Goods"
        }
    ],
    "sg:phone":"+1 985 384 1434",
    "sg:postcode":"70380",
    "sg:province":"LA",
    "sg:tags":[
        "shop",
        "consignment"
    ],
    "wof:name":"Thelma's Dis N' Dat",
    "wof:placetype":"venue"
},
  "geometry": {"coordinates":[-91.204791,29.700399],"type":"Point"}
}