{
  "type": "Feature",
  "properties": {
    "addr:full":"6851 Island Rd Jarreau LA 70749",
    "addr:housenumber":"6851",
    "addr:postcode":"70749",
    "addr:street":"Island Rd",
    "iso:country":"US",
    "sg:address":"6851 Island Rd",
    "sg:city":"Jarreau",
    "sg:classifiers":[
        {
            "category":"Building & Trades",
            "subcategory":"Construction",
            "type":"Services"
        }
    ],
    "sg:phone":"+1 225 627 5877",
    "sg:postcode":"70749",
    "sg:province":"LA",
    "sg:tags":[
        "contractor"
    ],
    "wof:name":"Sonnier's Construction",
    "wof:placetype":"venue"
},
  "geometry": {"coordinates":[-91.45293599999999,30.621005],"type":"Point"}
}