{
  "type": "Feature",
  "properties": {
    "addr:full":"225 N College Rd Lafayette LA 70506",
    "addr:housenumber":"225",
    "addr:postcode":"70506",
    "addr:street":"N College Rd",
    "iso:country":"US",
    "sg:address":"225 N College Rd",
    "sg:city":"Lafayette",
    "sg:classifiers":[
        {
            "category":"Health Services",
            "subcategory":"Optometrist",
            "type":"Services"
        }
    ],
    "sg:phone":"+1 337 233 3727",
    "sg:postcode":"70506",
    "sg:province":"LA",
    "wof:name":"Acadian Vision Assoc",
    "wof:placetype":"venue"
},
  "geometry": {"coordinates":[-92.04352,30.211417],"type":"Point"}
}