{
  "type": "Feature",
  "properties": {
    "iso:country":"US",
    "sg:address":"127 Tison Rd",
    "sg:city":"Carencro",
    "sg:classifiers":[
        {
            "category":"Manufacturing",
            "subcategory":"Lumber",
            "type":"Manufacturing & Wholesale Goods"
        }
    ],
    "sg:phone":"+1 337 896 0357",
    "sg:postcode":"70520",
    "sg:province":"LA",
    "sg:tags":[
        "forester"
    ],
    "wof:name":"Willis & Taylor Forest Conslnt",
    "wof:placetype":"venue"
},
  "geometry": {"coordinates":[-92.043648,30.308533],"type":"Point"}
}