{
  "type": "Feature",
  "properties": {
    "iso:country":"US",
    "sg:address":"15042 River Rd",
    "sg:city":"Hahnville",
    "sg:classifiers":[
        {
            "category":"Autos & Motor Vehicles",
            "subcategory":"Automobile Sales",
            "type":"Retail Goods"
        }
    ],
    "sg:phone":"+1 985 783 6611",
    "sg:postcode":"70057",
    "sg:province":"LA",
    "sg:tags":[
        "car",
        "dealer"
    ],
    "wof:name":"Madere's Garage Inc",
    "wof:placetype":"venue"
},
  "geometry": {"coordinates":[-90.403583,29.963603],"type":"Point"}
}