{
  "type": "Feature",
  "properties": {
    "iso:country":"US",
    "sg:address":"1354 Horridge St",
    "sg:city":"Vinton",
    "sg:classifiers":[
        {
            "category":"Government",
            "subcategory":"Post Office",
            "type":"Public Place"
        }
    ],
    "sg:phone":"+1 337 000 1111",
    "sg:postcode":"70668",
    "sg:province":"LA",
    "wof:name":"US Post Office",
    "wof:placetype":"venue"
},
  "geometry": {"coordinates":[-93.58142599999999,30.189879],"type":"Point"}
}