{
  "type": "Feature",
  "properties": {
    "iso:country":"US",
    "sg:address":"3211 Petro Dr",
    "sg:city":"Sulphur",
    "sg:classifiers":[
        {
            "category":"Building & Trades",
            "subcategory":"Equipment Rental",
            "type":"Services"
        }
    ],
    "sg:phone":"+1 337 708 0040",
    "sg:postcode":"70665",
    "sg:province":"LA",
    "sg:tags":[
        "crane"
    ],
    "wof:name":"Louisiana Crane LLC",
    "wof:placetype":"venue"
},
  "geometry": {"coordinates":[-93.328233,30.204435],"type":"Point"}
}