{
  "type": "Feature",
  "properties": {
    "iso:country":"US",
    "sg:address":"4609 Gus Young Ave",
    "sg:city":"Baton Rouge",
    "sg:classifiers":[
        {
            "category":"Shopping",
            "subcategory":"Music",
            "type":"Retail Goods"
        }
    ],
    "sg:phone":"+1 225 924 6054",
    "sg:postcode":"70802",
    "sg:province":"LA",
    "sg:tags":[
        "compact",
        "record",
        "disc",
        "tape"
    ],
    "wof:name":"Capital Records & Tapes",
    "wof:placetype":"venue"
},
  "geometry": {"coordinates":[-91.142932,30.462253],"type":"Point"}
}