{
  "type": "Feature",
  "properties": {
    "iso:country":"US",
    "sg:address":"110 Verot School Rd",
    "sg:city":"Lafayette",
    "sg:classifiers":[
        {
            "category":"Autos & Motor Vehicles",
            "subcategory":"Auto Supplies",
            "type":"Retail Goods"
        }
    ],
    "sg:phone":"+1 337 354 0003",
    "sg:postcode":"70508",
    "sg:province":"LA",
    "sg:tags":[
        "tire"
    ],
    "wof:name":"Chabill's",
    "wof:placetype":"venue"
},
  "geometry": {"coordinates":[-92.001031,30.177375],"type":"Point"}
}