{
  "type": "Feature",
  "properties": {
    "iso:country":"US",
    "sg:address":"3499 Hwy 165 Byp",
    "sg:city":"Monroe",
    "sg:classifiers":[
        {
            "category":"Home & Garden",
            "subcategory":"Mobile Homes",
            "type":"Retail Goods"
        }
    ],
    "sg:phone":"+1 318 387 9898",
    "sg:postcode":"71202",
    "sg:province":"LA",
    "wof:name":"C & L Homes",
    "wof:placetype":"venue"
},
  "geometry": {"coordinates":[-92.08275399999999,32.469653],"type":"Point"}
}