{
  "type": "Feature",
  "properties": {
    "iso:country":"US",
    "sg:address":"17830 Lavo Ln",
    "sg:city":"Baton Rouge",
    "sg:classifiers":[
        {
            "category":"Building & Trades",
            "subcategory":"Pest Control",
            "type":"Services"
        }
    ],
    "sg:phone":"+1 225 654 2252",
    "sg:postcode":"70810",
    "sg:province":"LA",
    "sg:website":"www.terminix.com",
    "wof:name":"Terminix International",
    "wof:placetype":"venue"
},
  "geometry": {"coordinates":[-91.0274,30.342381],"type":"Point"}
}