{
  "type": "Feature",
  "properties": {
    "iso:country":"US",
    "sg:address":"909 N 33rd St",
    "sg:city":"Monroe",
    "sg:classifiers":[
        {
            "category":"Personal",
            "type":"Services"
        }
    ],
    "sg:phone":"+1 318 322 7009",
    "sg:postcode":"71201",
    "sg:province":"LA",
    "sg:tags":[
        "genealogist"
    ],
    "wof:name":"Family History Ctr",
    "wof:placetype":"venue"
},
  "geometry": {"coordinates":[-92.085903,32.532766],"type":"Point"}
}