{
  "type": "Feature",
  "properties": {
    "iso:country":"US",
    "sg:address":"1400 Canal St",
    "sg:city":"New Orleans",
    "sg:classifiers":[
        {
            "category":"Health Services",
            "subcategory":"Doctor",
            "type":"Services"
        }
    ],
    "sg:phone":"+1 504 593 9895",
    "sg:postcode":"70112",
    "sg:province":"LA",
    "sg:tags":[
        "clinic"
    ],
    "wof:name":"Dialysis Clinic Inc",
    "wof:placetype":"venue"
},
  "geometry": {"coordinates":[-90.07541500000001,29.957324],"type":"Point"}
}