{
  "type": "Feature",
  "properties": {
    "addr:full":"5540 Swift Plant Rd Lake Charles LA 70615",
    "addr:housenumber":"5540",
    "addr:postcode":"70615",
    "addr:street":"Swift Plant Rd",
    "iso:country":"US",
    "sg:address":"5540 Swift Plant Rd",
    "sg:city":"Lake Charles",
    "sg:classifiers":[
        {
            "category":"Recreation",
            "type":"Entertainment"
        }
    ],
    "sg:phone":"+1 337 437 3650",
    "sg:postcode":"70615",
    "sg:province":"LA",
    "sg:tags":[
        "parks"
    ],
    "wof:name":"Calcasieu Parish Public Works",
    "wof:placetype":"venue"
},
  "geometry": {"coordinates":[-93.13433999999999,30.227622],"type":"Point"}
}