{
  "type": "Feature",
  "properties": {
    "addr:full":"2031 Oriole St Slidell LA 70460",
    "addr:housenumber":"2031",
    "addr:postcode":"70460",
    "addr:street":"Oriole St",
    "iso:country":"US",
    "sg:address":"2031 Oriole St",
    "sg:city":"Slidell",
    "sg:classifiers":[
        {
            "category":"Home & Garden",
            "subcategory":"Carpets & Floor Coverings",
            "type":"Retail Goods"
        }
    ],
    "sg:phone":"+1 504 430 7227",
    "sg:postcode":"70460",
    "sg:province":"LA",
    "wof:name":"Richwood Floors",
    "wof:placetype":"venue"
},
  "geometry": {"coordinates":[-89.840093,30.289727],"type":"Point"}
}