{
  "type": "Feature",
  "properties": {
    "iso:country":"US",
    "sg:address":"4336 Jeannie Marie Pl",
    "sg:city":"New Orleans",
    "sg:classifiers":[
        {
            "category":"Arts & Performance",
            "subcategory":"Theater",
            "type":"Entertainment"
        }
    ],
    "sg:phone":"+1 504 288 8974",
    "sg:postcode":"70122",
    "sg:province":"LA",
    "sg:tags":[
        "group"
    ],
    "wof:name":"Black Mask Entertainment LLc",
    "wof:placetype":"venue"
},
  "geometry": {"coordinates":[-90.076852,30.001778],"type":"Point"}
}