{
  "type": "Feature",
  "properties": {
    "iso:country":"US",
    "sg:address":"3100 Andover St",
    "sg:city":"New Orleans",
    "sg:classifiers":[
        {
            "category":"Mining & Drilling",
            "type":"Manufacturing & Wholesale Goods"
        }
    ],
    "sg:phone":"+1 504 837 1511",
    "sg:postcode":"70121",
    "sg:province":"LA",
    "sg:tags":[
        "stone"
    ],
    "wof:name":"Tuscan Stone Imports",
    "wof:placetype":"venue"
},
  "geometry": {"coordinates":[-90.16067,29.966231],"type":"Point"}
}