{
  "type": "Feature",
  "properties": {
    "iso:country":"US",
    "sg:address":"244 April Dr",
    "sg:city":"Florien",
    "sg:classifiers":[
        {
            "category":"Building & Trades",
            "subcategory":"Cleaning & Sanitation",
            "type":"Services"
        }
    ],
    "sg:phone":"+1 318 565 4253",
    "sg:postcode":"71429",
    "sg:province":"LA",
    "sg:tags":[
        "maintenance"
    ],
    "wof:name":"Adams Janitorial Service",
    "wof:placetype":"venue"
},
  "geometry": {"coordinates":[-93.586403,31.261789],"type":"Point"}
}