{
  "type": "Feature",
  "properties": {
    "iso:country":"US",
    "sg:address":"5609 Salmen Ave",
    "sg:city":"New Orleans",
    "sg:classifiers":[
        {
            "category":"Wholesale",
            "subcategory":"Machinery & Supplies",
            "type":"Manufacturing & Wholesale Goods"
        }
    ],
    "sg:phone":"+1 504 734 8900",
    "sg:postcode":"70123",
    "sg:province":"LA",
    "sg:tags":[
        "janitor"
    ],
    "wof:name":"Wessex Inc",
    "wof:placetype":"venue"
},
  "geometry": {"coordinates":[-90.192902,29.961428],"type":"Point"}
}