{
  "type": "Feature",
  "properties": {
    "addr:full":"1202 Veterans Memorial Dr Abbeville LA 70510",
    "addr:housenumber":"1202",
    "addr:postcode":"70510",
    "addr:street":"Veterans Memorial Dr",
    "iso:country":"US",
    "sg:address":"1202 Veterans Memorial Dr",
    "sg:city":"Abbeville",
    "sg:classifiers":[
        {
            "category":"Banks & Credit Unions",
            "subcategory":"Bank",
            "type":"Services"
        }
    ],
    "sg:phone":"+1 337 893 3240",
    "sg:postcode":"70510",
    "sg:province":"LA",
    "sg:tags":[
        "loan"
    ],
    "wof:name":"Allday Payday Loans",
    "wof:placetype":"venue"
},
  "geometry": {"coordinates":[-92.123374,29.981515],"type":"Point"}
}