{
  "type": "Feature",
  "properties": {
    "addr:full":"83 Rains St Pleasant Hill LA 71065",
    "addr:housenumber":"83",
    "addr:postcode":"71065",
    "addr:street":"Rains St",
    "iso:country":"US",
    "sg:address":"83 Rains St",
    "sg:city":"Pleasant Hill",
    "sg:classifiers":[
        {
            "category":"Real Estate",
            "subcategory":"Real Estate Operator",
            "type":"Services"
        }
    ],
    "sg:phone":"+1 318 796 2575",
    "sg:postcode":"71065",
    "sg:province":"LA",
    "sg:tags":[
        "building",
        "apartment"
    ],
    "wof:name":"Calhoun Property Managment",
    "wof:placetype":"venue"
},
  "geometry": {"coordinates":[-93.510031,31.810947],"type":"Point"}
}