{
  "type": "Feature",
  "properties": {
    "addr:full":"4301 Main St La Place LA 70068",
    "addr:housenumber":"4301",
    "addr:postcode":"70068",
    "addr:street":"Main St La Place",
    "iso:country":"US",
    "sg:address":"4301 Main St",
    "sg:city":"La Place",
    "sg:classifiers":[
        {
            "category":"Food & Beverages",
            "subcategory":"Groceries & Convenience Stores",
            "type":"Retail Goods"
        }
    ],
    "sg:phone":"+1 985 652 4141",
    "sg:postcode":"70068",
    "sg:province":"LA",
    "sg:tags":[
        "grocer"
    ],
    "wof:name":"Ecol Inc",
    "wof:placetype":"venue"
},
  "geometry": {"coordinates":[-90.45263,30.082455],"type":"Point"}
}