{
  "type": "Feature",
  "properties": {
    "addr:full":"1619 Jackson Ave New Orleans LA 70130",
    "addr:housenumber":"1619",
    "addr:postcode":"70130",
    "addr:street":"Jackson Ave",
    "iso:country":"US",
    "sg:address":"1619 Jackson Ave",
    "sg:city":"New Orleans",
    "sg:classifiers":[
        {
            "category":"Personal",
            "subcategory":"Beauty Salon",
            "type":"Services"
        }
    ],
    "sg:phone":"+1 504 596 6880",
    "sg:postcode":"70130",
    "sg:province":"LA",
    "sg:tags":[
        "manicuring"
    ],
    "wof:name":"Nature Nails",
    "wof:placetype":"venue"
},
  "geometry": {"coordinates":[-90.081136,29.934852],"type":"Point"}
}