{
  "type": "Feature",
  "properties": {
    "iso:country":"US",
    "sg:address":"107 Short St",
    "sg:city":"Taylor",
    "sg:classifiers":[
        {
            "category":"Government",
            "subcategory":"Post Office",
            "type":"Public Place"
        }
    ],
    "sg:phone":"+1 318 843 6666",
    "sg:postcode":"71028",
    "sg:province":"LA",
    "wof:name":"US Post Office",
    "wof:placetype":"venue"
},
  "geometry": {"coordinates":[-93.14354400000001,32.546694],"type":"Point"}
}