{
  "type": "Feature",
  "properties": {
    "addr:full":"408 Cedar St Farmerville LA 71241",
    "addr:housenumber":"408",
    "addr:postcode":"71241",
    "addr:street":"Cedar St",
    "iso:country":"US",
    "sg:address":"408 Cedar St",
    "sg:city":"Farmerville",
    "sg:classifiers":[
        {
            "category":"Building & Trades",
            "subcategory":"Construction",
            "type":"Services"
        }
    ],
    "sg:phone":"+1 318 368 2622",
    "sg:postcode":"71241",
    "sg:province":"LA",
    "sg:tags":[
        "contractor"
    ],
    "wof:name":"Don M Barron Contractor Inc",
    "wof:placetype":"venue"
},
  "geometry": {"coordinates":[-92.400958,32.771308],"type":"Point"}
}