{
  "type": "Feature",
  "properties": {
    "iso:country":"US",
    "sg:address":"1401 Florida St",
    "sg:city":"Mandeville",
    "sg:classifiers":[
        {
            "category":"Health Services",
            "subcategory":"Nursing And Care Facility",
            "type":"Services"
        }
    ],
    "sg:phone":"+1 985 626 8581",
    "sg:postcode":"70448",
    "sg:province":"LA",
    "sg:tags":[
        "home",
        "convalescent"
    ],
    "wof:name":"Pontchartrain Health Care Ctr",
    "wof:placetype":"venue"
},
  "geometry": {"coordinates":[-90.053291,30.359326],"type":"Point"}
}