{
  "type": "Feature",
  "properties": {
    "iso:country":"US",
    "sg:address":"3113 Orleans Ave",
    "sg:city":"New Orleans",
    "sg:classifiers":[
        {
            "category":"Social Services",
            "subcategory":"Child Care",
            "type":"Services"
        }
    ],
    "sg:phone":"+1 504 482 1477",
    "sg:postcode":"70119",
    "sg:province":"LA",
    "wof:name":"Clark's Child Dev Ctr",
    "wof:placetype":"venue"
},
  "geometry": {"coordinates":[-90.088083,29.974473],"type":"Point"}
}