{
  "type": "Feature",
  "properties": {
    "addr:full":"2011 Hudson Ln Monroe LA 71201",
    "addr:housenumber":"2011",
    "addr:postcode":"71201",
    "addr:street":"Hudson Ln",
    "iso:country":"US",
    "sg:address":"2011 Hudson Ln",
    "sg:city":"Monroe",
    "sg:classifiers":[
        {
            "category":"Professional",
            "subcategory":"Lawyer & Legal Services",
            "type":"Services"
        }
    ],
    "sg:phone":"+1 318 325 7577",
    "sg:postcode":"71201",
    "sg:province":"LA",
    "sg:tags":[
        "attorney"
    ],
    "wof:name":"Loomis & Dement",
    "wof:placetype":"venue"
},
  "geometry": {"coordinates":[-92.105862,32.520207],"type":"Point"}
}