{
  "type": "Feature",
  "properties": {
    "iso:country":"US",
    "sg:address":"110 W Hill St",
    "sg:city":"Farmerville",
    "sg:classifiers":[
        {
            "category":"Education",
            "subcategory":"School",
            "type":"Public Place"
        }
    ],
    "sg:phone":"+1 318 368 8890",
    "sg:postcode":"71241",
    "sg:province":"LA",
    "wof:name":"Union Christian Academy",
    "wof:placetype":"venue"
},
  "geometry": {"coordinates":[-92.406161,32.770319],"type":"Point"}
}