{
  "type": "Feature",
  "properties": {
    "iso:country":"US",
    "sg:address":"1701 W Court St",
    "sg:city":"Winnfield",
    "sg:classifiers":[
        {
            "category":"Professional",
            "subcategory":"Engineering",
            "type":"Services"
        }
    ],
    "sg:phone":"+1 318 628 7200",
    "sg:postcode":"71483",
    "sg:province":"LA",
    "sg:tags":[
        "engineer"
    ],
    "wof:name":"Kennedy Engineering",
    "wof:placetype":"venue"
},
  "geometry": {"coordinates":[-92.653425,31.933514],"type":"Point"}
}