{
  "type": "Feature",
  "properties": {
    "addr:full":"1742 W Laurel Ave Eunice LA 70535",
    "addr:housenumber":"1742",
    "addr:postcode":"70535",
    "addr:street":"W Laurel Ave",
    "iso:country":"US",
    "sg:address":"1742 W Laurel Ave",
    "sg:city":"Eunice",
    "sg:classifiers":[
        {
            "category":"Shopping",
            "subcategory":"Computers & Home Electronics",
            "type":"Retail Goods"
        }
    ],
    "sg:phone":"+1 337 457 5230",
    "sg:postcode":"70535",
    "sg:province":"LA",
    "sg:tags":[
        "equipment",
        "electronic",
        "supply"
    ],
    "wof:name":"Radio Shack",
    "wof:placetype":"venue"
},
  "geometry": {"coordinates":[-92.433605,30.495046],"type":"Point"}
}