{
  "type": "Feature",
  "properties": {
    "iso:country":"US",
    "sg:address":"10339 Mammoth Ave",
    "sg:city":"Baton Rouge",
    "sg:classifiers":[
        {
            "category":"Building & Trades",
            "subcategory":"Plumbing",
            "type":"Services"
        }
    ],
    "sg:phone":"+1 225 928 0943",
    "sg:postcode":"70814",
    "sg:province":"LA",
    "sg:tags":[
        "conditioning",
        "air",
        "system",
        "contractor"
    ],
    "wof:name":"Peterson's Air Cond & Refrig",
    "wof:placetype":"venue"
},
  "geometry": {"coordinates":[-91.074572,30.475963],"type":"Point"}
}