{
  "type": "Feature",
  "properties": {
    "iso:country":"US",
    "sg:address":"1001 N Hwy 190",
    "sg:city":"Covington",
    "sg:classifiers":[
        {
            "category":"Professional",
            "subcategory":"Accounting & Tax Preparation",
            "type":"Services"
        }
    ],
    "sg:phone":"+1 985 893 2440",
    "sg:postcode":"70433",
    "sg:province":"LA",
    "sg:tags":[
        "accountant"
    ],
    "wof:name":"Hyperbaric Oxygen Inc",
    "wof:placetype":"venue"
},
  "geometry": {"coordinates":[-90.08230399999999,30.445988],"type":"Point"}
}