{
  "type": "Feature",
  "properties": {
    "addr:full":"1906 Cooper Lake Rd Bastrop LA 71220",
    "addr:housenumber":"1906",
    "addr:postcode":"71220",
    "addr:street":"Cooper Lake Rd",
    "iso:country":"US",
    "sg:address":"1906 Cooper Lake Rd",
    "sg:city":"Bastrop",
    "sg:classifiers":[
        {
            "category":"Social Services",
            "subcategory":"Child Care",
            "type":"Services"
        }
    ],
    "sg:phone":"+1 318 281 8819",
    "sg:postcode":"71220",
    "sg:province":"LA",
    "wof:name":"PREP Ctr",
    "wof:placetype":"venue"
},
  "geometry": {"coordinates":[-91.890958,32.784313],"type":"Point"}
}