{
  "type": "Feature",
  "properties": {
    "addr:full":"216 E Bayou Narcisse St Gonzales LA 70737",
    "addr:housenumber":"216",
    "addr:postcode":"70737",
    "addr:street":"E Bayou Narcisse St",
    "iso:country":"US",
    "sg:address":"216 E Bayou Narcisse St",
    "sg:city":"Gonzales",
    "sg:classifiers":[
        {
            "category":"Banks & Credit Unions",
            "subcategory":"Bank",
            "type":"Services"
        }
    ],
    "sg:phone":"+1 225 644 0058",
    "sg:postcode":"70737",
    "sg:province":"LA",
    "sg:tags":[
        "loan"
    ],
    "wof:name":"Ascension Loans LLC",
    "wof:placetype":"venue"
},
  "geometry": {"coordinates":[-90.918824,30.247418],"type":"Point"}
}