{
  "type": "Feature",
  "properties": {
    "iso:country":"US",
    "sg:address":"430 S Woodlake Way",
    "sg:city":"Slidell",
    "sg:classifiers":[
        {
            "category":"Professional",
            "type":"Services"
        }
    ],
    "sg:phone":"+1 985 781 6668",
    "sg:postcode":"70452",
    "sg:province":"LA",
    "sg:tags":[
        "establishment"
    ],
    "wof:name":"Resmed",
    "wof:placetype":"venue"
},
  "geometry": {"coordinates":[-89.741089,30.32568],"type":"Point"}
}