{
  "type": "Feature",
  "properties": {
    "iso:country":"US",
    "sg:address":"1863 Rue de Cotton",
    "sg:city":"Ville Platte",
    "sg:classifiers":[
        {
            "category":"Shopping",
            "subcategory":"Computers & Home Electronics",
            "type":"Retail Goods"
        }
    ],
    "sg:phone":"+1 337 363 5320",
    "sg:postcode":"70586",
    "sg:province":"LA",
    "sg:tags":[
        "equipment",
        "dealer"
    ],
    "wof:name":"Orion Computer Svc Inc",
    "wof:placetype":"venue"
},
  "geometry": {"coordinates":[-92.222855,30.744335],"type":"Point"}
}