{
  "type": "Feature",
  "properties": {
    "addr:full":"6116 W Calhoun Dr Alexandria LA 71303",
    "addr:housenumber":"6116",
    "addr:postcode":"71303",
    "addr:street":"W Calhoun Dr",
    "iso:country":"US",
    "sg:address":"6116 W Calhoun Dr",
    "sg:city":"Alexandria",
    "sg:classifiers":[
        {
            "category":"Travel",
            "subcategory":"Hotels & Motels",
            "type":"Entertainment"
        }
    ],
    "sg:phone":"+1 318 442 3700",
    "sg:postcode":"71303",
    "sg:province":"LA",
    "wof:name":"LA Quinta Inn",
    "wof:placetype":"venue"
},
  "geometry": {"coordinates":[-92.52240500000001,31.345927],"type":"Point"}
}