{
  "type": "Feature",
  "properties": {
    "addr:full":"74219 Hwy 1054 Kentwood LA 70444",
    "addr:housenumber":"74219",
    "addr:postcode":"1054;70444",
    "addr:street":"Hwy",
    "iso:country":"US",
    "sg:address":"74219 Hwy 1054",
    "sg:city":"Kentwood",
    "sg:classifiers":[
        {
            "category":"Wholesale",
            "subcategory":"Farm Supplies",
            "type":"Manufacturing & Wholesale Goods"
        }
    ],
    "sg:phone":"+1 985 229 4401",
    "sg:postcode":"70444",
    "sg:province":"LA",
    "sg:tags":[
        "feed"
    ],
    "wof:name":"Spring Creek Milling Co-Op",
    "wof:placetype":"venue"
},
  "geometry": {"coordinates":[-90.447896,30.935683],"type":"Point"}
}