{
  "type": "Feature",
  "properties": {
    "addr:full":"104 Hwy 55 Bourg LA 70343",
    "addr:housenumber":"104",
    "addr:postcode":"70343",
    "addr:street":"Hwy 55 Bourg La",
    "iso:country":"US",
    "sg:address":"104 Hwy 55",
    "sg:city":"Bourg",
    "sg:classifiers":[
        {
            "category":"Personal",
            "subcategory":"Beauty Salon",
            "type":"Services"
        }
    ],
    "sg:phone":"+1 985 594 6002",
    "sg:postcode":"70343",
    "sg:province":"LA",
    "sg:tags":[
        "manicuring"
    ],
    "wof:name":"Rochelle's Nail Salon",
    "wof:placetype":"venue"
},
  "geometry": {"coordinates":[-90.587008,29.547234],"type":"Point"}
}