{
  "type": "Feature",
  "properties": {
    "iso:country":"US",
    "sg:address":"1921 S Cutting Ave",
    "sg:city":"Jennings",
    "sg:classifiers":[
        {
            "category":"Organizations",
            "subcategory":"Religious Organization",
            "type":"Services"
        }
    ],
    "sg:phone":"+1 337 824 2900",
    "sg:postcode":"70546",
    "sg:province":"LA",
    "wof:name":"Hope & Faith Outreach Prayer",
    "wof:placetype":"venue"
},
  "geometry": {"coordinates":[-92.65515499999999,30.201084],"type":"Point"}
}