{
  "type": "Feature",
  "properties": {
    "iso:country":"US",
    "sg:address":"416 McCormick St",
    "sg:city":"Bossier City",
    "sg:classifiers":[
        {
            "category":"Organizations",
            "subcategory":"Religious Organization",
            "type":"Services"
        }
    ],
    "sg:phone":"+1 318 221 0730",
    "sg:postcode":"71111",
    "sg:province":"LA",
    "wof:name":"Director For Religious Educatn",
    "wof:placetype":"venue"
},
  "geometry": {"coordinates":[-93.727752,32.517625],"type":"Point"}
}