{
  "type": "Feature",
  "properties": {
    "addr:full":"725 W 8th Ave Covington LA 70433",
    "addr:housenumber":"725",
    "addr:postcode":"70433",
    "addr:street":"W 8Th Ave",
    "iso:country":"US",
    "sg:address":"725 W 8th Ave",
    "sg:city":"Covington",
    "sg:classifiers":[
        {
            "category":"Health Services",
            "subcategory":"Doctor",
            "type":"Services"
        }
    ],
    "sg:phone":"+1 985 892 2434",
    "sg:postcode":"70433",
    "sg:province":"LA",
    "sg:tags":[
        "physician",
        "surgeon"
    ],
    "wof:name":"Doctors For Women Medical Ctr",
    "wof:placetype":"venue"
},
  "geometry": {"coordinates":[-90.11543399999999,30.467245],"type":"Point"}
}