{
  "type": "Feature",
  "properties": {
    "iso:country":"US",
    "sg:address":"809 Carter St",
    "sg:city":"Vidalia",
    "sg:classifiers":[
        {
            "category":"Banks & Credit Unions",
            "subcategory":"Bank",
            "type":"Services"
        }
    ],
    "sg:phone":"+1 318 336 9200",
    "sg:postcode":"71373",
    "sg:province":"LA",
    "sg:tags":[
        "cashing",
        "check"
    ],
    "wof:name":"Cash Express",
    "wof:placetype":"venue"
},
  "geometry": {"coordinates":[-91.434606,31.568834],"type":"Point"}
}