{
  "type": "Feature",
  "properties": {
    "iso:country":"US",
    "sg:address":"6007 Financial Plz",
    "sg:city":"Shreveport",
    "sg:classifiers":[
        {
            "category":"Real Estate",
            "subcategory":"Real Estate Agent",
            "type":"Services"
        }
    ],
    "sg:phone":"+1 318 683 3946",
    "sg:postcode":"71129",
    "sg:province":"LA",
    "sg:tags":[
        "finding",
        "apartment",
        "rental"
    ],
    "wof:name":"Apartment Directory",
    "wof:placetype":"venue"
},
  "geometry": {"coordinates":[-93.858204,32.451437],"type":"Point"}
}