{
  "type": "Feature",
  "properties": {
    "iso:country":"US",
    "sg:address":"9550 Mansfield Rd",
    "sg:city":"Shreveport",
    "sg:classifiers":[
        {
            "category":"Restaurant",
            "type":"Food & Drink"
        }
    ],
    "sg:menulink":"http://www.allmenus.com/la/keithville/132128-subway/menu/",
    "sg:phone":"+1 318 686 8220",
    "sg:postcode":"71118",
    "sg:province":"LA",
    "sg:tags":[
        "american",
        "sandwich"
    ],
    "wof:name":"Subway",
    "wof:placetype":"venue"
},
  "geometry": {"coordinates":[-93.815872,32.388246],"type":"Point"}
}