{
  "type": "Feature",
  "properties": {
    "iso:country":"US",
    "sg:address":"1435 Frasier St",
    "sg:city":"Haynesville",
    "sg:classifiers":[
        {
            "category":"Place Of Worship",
            "subcategory":"Church",
            "type":"Public Place"
        },
        {
            "category":"Place Of Worship",
            "type":"Public Place"
        }
    ],
    "sg:phone":"+1 318 624 2704",
    "sg:postcode":"71038",
    "sg:province":"LA",
    "sg:tags":[
        "churches-baptist-general",
        "churches-baptist-southern",
        "churches-baptist"
    ],
    "wof:name":"Family Life Center",
    "wof:placetype":"venue"
},
  "geometry": {"coordinates":[-93.137817,32.962216],"type":"Point"}
}