{
  "type": "Feature",
  "properties": {
    "iso:country":"US",
    "sg:address":"287 Inspiration Park Dr",
    "sg:city":"Kentwood",
    "sg:classifiers":[
        {
            "category":"Travel",
            "subcategory":"Campground",
            "type":"Entertainment"
        }
    ],
    "sg:phone":"+1 985 229 7194",
    "sg:postcode":"70444",
    "sg:province":"LA",
    "wof:name":"Garden",
    "wof:placetype":"venue"
},
  "geometry": {"coordinates":[-90.567339,30.927421],"type":"Point"}
}