{
  "type": "Feature",
  "properties": {
    "iso:country":"US",
    "sg:address":"59295 Pierre Ln",
    "sg:city":"Lacombe",
    "sg:classifiers":[
        {
            "category":"Real Estate",
            "subcategory":"Real Estate Agent",
            "type":"Services"
        }
    ],
    "sg:phone":"+1 504 578 7670",
    "sg:postcode":"70445",
    "sg:province":"LA",
    "sg:tags":[
        "agency",
        "rental"
    ],
    "wof:name":"Partytime Inflatables",
    "wof:placetype":"venue"
},
  "geometry": {"coordinates":[-89.91143099999999,30.294394],"type":"Point"}
}