{
  "type": "Feature",
  "properties": {
    "addr:full":"301 E Saint Peter St New Iberia LA 70560",
    "addr:housenumber":"301",
    "addr:postcode":"70560",
    "addr:street":"E Saint Peter St",
    "iso:country":"US",
    "sg:address":"301 E Saint Peter St",
    "sg:city":"New Iberia",
    "sg:classifiers":[
        {
            "category":"Social Services",
            "type":"Services"
        }
    ],
    "sg:phone":"+1 337 365 1800",
    "sg:postcode":"70560",
    "sg:province":"LA",
    "sg:tags":[
        "organization",
        "welfare"
    ],
    "wof:name":"Family Resource Ctr",
    "wof:placetype":"venue"
},
  "geometry": {"coordinates":[-91.81694299999999,30.002584],"type":"Point"}
}