{
  "type": "Feature",
  "properties": {
    "iso:country":"US",
    "sg:address":"1502 S Huntington St",
    "sg:city":"Sulphur",
    "sg:classifiers":[
        {
            "category":"Real Estate",
            "subcategory":"Architect",
            "type":"Services"
        }
    ],
    "sg:phone":"+1 337 527 8137",
    "sg:postcode":"70663",
    "sg:province":"LA",
    "wof:name":"H Curtis Vincent Architects",
    "wof:placetype":"venue"
},
  "geometry": {"coordinates":[-93.377268,30.226503],"type":"Point"}
}