{
  "type": "Feature",
  "properties": {
    "iso:country":"US",
    "sg:address":"2221 Louisville Ave",
    "sg:city":"Monroe",
    "sg:classifiers":[
        {
            "category":"Utilities",
            "subcategory":"Mobile Phone",
            "type":"Services"
        }
    ],
    "sg:phone":"+1 318 323 7468",
    "sg:postcode":"71201",
    "sg:province":"LA",
    "sg:tags":[
        "telephone",
        "cellular"
    ],
    "wof:name":"Radio Shack",
    "wof:placetype":"venue"
},
  "geometry": {"coordinates":[-92.102115,32.520543],"type":"Point"}
}