{
  "type": "Feature",
  "properties": {
    "addr:full":"2416 Harveys Barber Shop Rd Dubberly LA 71024",
    "addr:housenumber":"2416",
    "addr:postcode":"71024",
    "addr:street":"Rd",
    "iso:country":"US",
    "sg:address":"2416 Harveys Barber Shop Rd",
    "sg:city":"Dubberly",
    "sg:classifiers":[
        {
            "category":"Retail",
            "subcategory":"Auto Repair",
            "type":"Services"
        }
    ],
    "sg:phone":"+1 318 377 3507",
    "sg:postcode":"71024",
    "sg:province":"LA",
    "sg:tags":[
        "car",
        "lubrication"
    ],
    "wof:name":"Oil Butler",
    "wof:placetype":"venue"
},
  "geometry": {"coordinates":[-93.219688,32.536431],"type":"Point"}
}