{
  "type": "Feature",
  "properties": {
    "iso:country":"US",
    "sg:address":"3700 Jackson St Exd",
    "sg:city":"Alexandria",
    "sg:classifiers":[
        {
            "category":"Professional",
            "subcategory":"Lawyer & Legal Services",
            "type":"Services"
        }
    ],
    "sg:phone":"+1 318 443 4009",
    "sg:postcode":"71303",
    "sg:province":"LA",
    "sg:tags":[
        "attorney"
    ],
    "wof:name":"Elder Law & Estate Planning",
    "wof:placetype":"venue"
},
  "geometry": {"coordinates":[-92.47685199999999,31.283879],"type":"Point"}
}