{
  "type": "Feature",
  "properties": {
    "addr:full":"1020 Primrose St Luling LA 70070",
    "addr:housenumber":"1020",
    "addr:postcode":"70070",
    "addr:street":"Primrose St",
    "iso:country":"US",
    "sg:address":"1020 Primrose St",
    "sg:city":"Luling",
    "sg:classifiers":[
        {
            "category":"Shopping",
            "subcategory":"Clothing, Apparel, & Fashions",
            "type":"Retail Goods"
        }
    ],
    "sg:phone":"+1 985 331 1170",
    "sg:postcode":"70070",
    "sg:province":"LA",
    "sg:tags":[
        "swim",
        "dance",
        "wear"
    ],
    "wof:name":"Frog In A Tutu",
    "wof:placetype":"venue"
},
  "geometry": {"coordinates":[-90.36639599999999,29.903042],"type":"Point"}
}