{
  "type": "Feature",
  "properties": {
    "addr:full":"1620 N University Ave Lafayette LA 70506",
    "addr:housenumber":"1620",
    "addr:postcode":"70506",
    "addr:street":"N University Ave",
    "iso:country":"US",
    "sg:address":"1620 N University Ave",
    "sg:city":"Lafayette",
    "sg:classifiers":[
        {
            "category":"Education",
            "subcategory":"Kindergarten",
            "type":"Public Place"
        }
    ],
    "sg:phone":"+1 337 237 9345",
    "sg:postcode":"70506",
    "sg:province":"LA",
    "sg:tags":[
        "school",
        "driving"
    ],
    "sg:website":"www.firstchoicedriversed.com",
    "wof:name":"First Choice Driving School",
    "wof:placetype":"venue"
},
  "geometry": {"coordinates":[-92.035132,30.249685],"type":"Point"}
}