{
  "type": "Feature",
  "properties": {
    "addr:full":"2614 Drusilla Ln Baton Rouge LA 70809",
    "addr:postcode":"2614;70809",
    "addr:street":"Drusilla Ln",
    "iso:country":"US",
    "sg:address":"2614 Drusilla Ln",
    "sg:city":"Baton Rouge",
    "sg:classifiers":[
        {
            "category":"Wholesale",
            "subcategory":"Electrical",
            "type":"Manufacturing & Wholesale Goods"
        }
    ],
    "sg:phone":"+1 225 928 8411",
    "sg:postcode":"70809",
    "sg:province":"LA",
    "sg:tags":[
        "fire",
        "alarm",
        "system"
    ],
    "wof:name":"Qubic Technology LLC",
    "wof:placetype":"venue"
},
  "geometry": {"coordinates":[-91.084113,30.42766],"type":"Point"}
}