{
  "type": "Feature",
  "properties": {
    "iso:country":"US",
    "sg:address":"6770 Johnston St",
    "sg:city":"Lafayette",
    "sg:classifiers":[
        {
            "category":"Mining & Drilling",
            "type":"Manufacturing & Wholesale Goods"
        }
    ],
    "sg:phone":"+1 337 989 8495",
    "sg:postcode":"70503",
    "sg:province":"LA",
    "sg:tags":[
        "field",
        "oil"
    ],
    "sg:website":"www.cudd.com",
    "wof:name":"Cudd Pressure Control Inc",
    "wof:placetype":"venue"
},
  "geometry": {"coordinates":[-92.092928,30.151671],"type":"Point"}
}