{
  "type": "Feature",
  "properties": {
    "addr:full":"130 Orchard Rd New Orleans LA 70123",
    "addr:housenumber":"130",
    "addr:postcode":"70123",
    "addr:street":"Orchard Rd",
    "iso:country":"US",
    "sg:address":"130 Orchard Rd",
    "sg:city":"New Orleans",
    "sg:classifiers":[
        {
            "category":"Freight",
            "type":"Transportation"
        }
    ],
    "sg:phone":"+1 504 738 7611",
    "sg:postcode":"70123",
    "sg:province":"LA",
    "sg:tags":[
        "mobile",
        "home",
        "intrastate",
        "transport"
    ],
    "wof:name":"Humphries Transport Inc",
    "wof:placetype":"venue"
},
  "geometry": {"coordinates":[-90.218063,29.948922],"type":"Point"}
}