{
  "type": "Feature",
  "properties": {
    "iso:country":"US",
    "sg:address":"200 Greenleaves Blvd",
    "sg:city":"Mandeville",
    "sg:classifiers":[
        {
            "category":"Professional",
            "subcategory":"Accounting & Tax Preparation",
            "type":"Services"
        }
    ],
    "sg:phone":"+1 985 626 7273",
    "sg:postcode":"70448",
    "sg:province":"LA",
    "sg:tags":[
        "accountant"
    ],
    "wof:name":"Dillard Jeanfreau & Winters",
    "wof:placetype":"venue"
},
  "geometry": {"coordinates":[-90.075976,30.377841],"type":"Point"}
}