{
  "type": "Feature",
  "properties": {
    "iso:country":"US",
    "sg:address":"1006 Spruce St",
    "sg:city":"Morgan City",
    "sg:classifiers":[
        {
            "category":"Shopping",
            "subcategory":"Gifts & Souvenirs",
            "type":"Retail Goods"
        }
    ],
    "sg:phone":"+1 985 384 0675",
    "sg:postcode":"70380",
    "sg:province":"LA",
    "sg:tags":[
        "shop"
    ],
    "wof:name":"Judy's Boutique & Gifts",
    "wof:placetype":"venue"
},
  "geometry": {"coordinates":[-91.202918,29.708822],"type":"Point"}
}