{
  "type": "Feature",
  "properties": {
    "addr:full":"2712 Village Ln Bossier City LA 71112",
    "addr:housenumber":"2712",
    "addr:postcode":"71112",
    "addr:street":"Village Ln",
    "iso:country":"US",
    "sg:address":"2712 Village Ln",
    "sg:city":"Bossier City",
    "sg:classifiers":[
        {
            "category":"Restaurant",
            "type":"Food & Drink"
        }
    ],
    "sg:phone":"+1 318 747 1644",
    "sg:postcode":"71112",
    "sg:province":"LA",
    "wof:name":"Catfish King",
    "wof:placetype":"venue"
},
  "geometry": {"coordinates":[-93.69953,32.523174],"type":"Point"}
}