{
  "type": "Feature",
  "properties": {
    "iso:country":"US",
    "sg:address":"877 Friendship Rd",
    "sg:city":"Frierson",
    "sg:classifiers":[
        {
            "category":"Building & Trades",
            "subcategory":"Construction",
            "type":"Services"
        }
    ],
    "sg:phone":"+1 318 798 6743",
    "sg:postcode":"71027",
    "sg:province":"LA",
    "sg:tags":[
        "culvert"
    ],
    "wof:name":"Tri-State Pipe & Culverts",
    "wof:placetype":"venue"
},
  "geometry": {"coordinates":[-93.674193,32.228493],"type":"Point"}
}