{
  "type": "Feature",
  "properties": {
    "iso:country":"US",
    "sg:address":"3555 Ambassador Caffery Pkwy",
    "sg:city":"Lafayette",
    "sg:classifiers":[
        {
            "category":"Restaurant",
            "type":"Food & Drink"
        }
    ],
    "sg:menulink":"http://www.allmenus.com/la/broadmoor/64283-chuck-e-cheeses/menu/",
    "sg:phone":"+1 337 216 9550",
    "sg:postcode":"70503",
    "sg:province":"LA",
    "sg:tags":[
        "american",
        "pizza"
    ],
    "wof:name":"Chuck E. Cheese's",
    "wof:placetype":"venue"
},
  "geometry": {"coordinates":[-92.072003,30.175986],"type":"Point"}
}