{
  "type": "Feature",
  "properties": {
    "iso:country":"US",
    "sg:address":"1409 Canal St",
    "sg:city":"New Orleans",
    "sg:classifiers":[
        {
            "category":"Personal",
            "type":"Services"
        }
    ],
    "sg:phone":"+1 504 527 5988",
    "sg:postcode":"70112",
    "sg:province":"LA",
    "wof:name":"Ink-A-Bink",
    "wof:placetype":"venue"
},
  "geometry": {"coordinates":[-90.075397,29.957216],"type":"Point"}
}