{
  "type": "Feature",
  "properties": {
    "addr:full":"18169 Lee Rd Franklinton LA 70438",
    "addr:housenumber":"18169",
    "addr:postcode":"70438",
    "addr:street":"Lee Rd",
    "iso:country":"US",
    "sg:address":"18169 Lee Rd",
    "sg:city":"Franklinton",
    "sg:classifiers":[
        {
            "category":"Utilities",
            "subcategory":"Natural Gas",
            "type":"Services"
        }
    ],
    "sg:phone":"+1 985 839 4721",
    "sg:postcode":"70438",
    "sg:province":"LA",
    "wof:name":"Florida Gas Transmission Co",
    "wof:placetype":"venue"
},
  "geometry": {"coordinates":[-90.05815699999999,30.784789],"type":"Point"}
}