{
  "type": "Feature",
  "properties": {
    "iso:country":"US",
    "sg:address":"5800 Perkins Rd",
    "sg:city":"Baton Rouge",
    "sg:classifiers":[
        {
            "category":"Real Estate",
            "subcategory":"Real Estate Agent",
            "type":"Services"
        }
    ],
    "sg:phone":"+1 225 767 0220",
    "sg:postcode":"70808",
    "sg:province":"LA",
    "wof:name":"Persac Properties",
    "wof:placetype":"venue"
},
  "geometry": {"coordinates":[-91.13055900000001,30.41013],"type":"Point"}
}