{
  "type": "Feature",
  "properties": {
    "addr:full":"9818 Bluebonnet Blvd Baton Rouge LA 70810",
    "addr:housenumber":"9818",
    "addr:postcode":"70810",
    "addr:street":"Bluebonnet Blvd",
    "iso:country":"US",
    "sg:address":"9818 Bluebonnet Blvd",
    "sg:city":"Baton Rouge",
    "sg:classifiers":[
        {
            "category":"Insurance",
            "subcategory":"Insurance Agent",
            "type":"Services"
        }
    ],
    "sg:phone":"+1 225 819 8007",
    "sg:postcode":"70810",
    "sg:province":"LA",
    "wof:name":"Independent Insurance Agents",
    "wof:placetype":"venue"
},
  "geometry": {"coordinates":[-91.109498,30.355448],"type":"Point"}
}