{
  "type": "Feature",
  "properties": {
    "addr:full":"3008 20th St Metairie LA 70002",
    "addr:housenumber":"3008",
    "addr:postcode":"70002",
    "addr:street":"20Th St",
    "iso:country":"US",
    "sg:address":"3008 20th St",
    "sg:city":"Metairie",
    "sg:classifiers":[
        {
            "category":"Professional",
            "subcategory":"Business Services",
            "type":"Services"
        }
    ],
    "sg:phone":"+1 504 835 3453",
    "sg:postcode":"70002",
    "sg:province":"LA",
    "sg:tags":[
        "record",
        "medical"
    ],
    "sg:website":"www.velfile.com",
    "wof:name":"MTT Enterprises",
    "wof:placetype":"venue"
},
  "geometry": {"coordinates":[-90.15335899999999,30.00663],"type":"Point"}
}