{
  "type": "Feature",
  "properties": {
    "addr:full":"218 S Mall St Lafayette LA 70503",
    "addr:housenumber":"218",
    "addr:postcode":"70503",
    "addr:street":"S Mall St",
    "iso:country":"US",
    "sg:address":"218 S Mall St",
    "sg:city":"Lafayette",
    "sg:classifiers":[
        {
            "category":"Personal",
            "type":"Services"
        }
    ],
    "sg:phone":"+1 337 232 5015",
    "sg:postcode":"70503",
    "sg:province":"LA",
    "wof:name":"Katherine Bennett Lmt",
    "wof:placetype":"venue"
},
  "geometry": {"coordinates":[-92.009888,30.205927],"type":"Point"}
}