{
  "type": "Feature",
  "properties": {
    "iso:country":"US",
    "sg:address":"401 Whitney Ave",
    "sg:city":"Gretna",
    "sg:classifiers":[
        {
            "category":"Retail",
            "subcategory":"Laundry & Dry Cleaning",
            "type":"Services"
        }
    ],
    "sg:phone":"+1 504 364 0701",
    "sg:postcode":"70056",
    "sg:province":"LA",
    "sg:tags":[
        "cleaner",
        "rug",
        "carpet"
    ],
    "wof:name":"Carpet Keepers",
    "wof:placetype":"venue"
},
  "geometry": {"coordinates":[-90.042297,29.919901],"type":"Point"}
}