{
  "type": "Feature",
  "properties": {
    "iso:country":"US",
    "sg:address":"132 16th St",
    "sg:city":"Golden Meadow",
    "sg:classifiers":[
        {
            "category":"Professional",
            "type":"Services"
        }
    ],
    "sg:phone":"+1 985 396 2005",
    "sg:postcode":"70357",
    "sg:province":"LA",
    "sg:tags":[
        "establishment"
    ],
    "wof:name":"Expert Riser Solutions LLC",
    "wof:placetype":"venue"
},
  "geometry": {"coordinates":[-90.200362,29.120546],"type":"Point"}
}