{
  "type": "Feature",
  "properties": {
    "iso:country":"US",
    "sg:address":"19970 Highland Rd",
    "sg:city":"Baton Rouge",
    "sg:classifiers":[
        {
            "category":"Professional",
            "subcategory":"Advertising",
            "type":"Services"
        }
    ],
    "sg:phone":"+1 225 752 1140",
    "sg:postcode":"70809",
    "sg:province":"LA",
    "sg:tags":[
        "mailing",
        "shipping"
    ],
    "wof:name":"Fed Ex",
    "wof:placetype":"venue"
},
  "geometry": {"coordinates":[-91.015473,30.355241],"type":"Point"}
}