{
  "type": "Feature",
  "properties": {
    "iso:country":"US",
    "sg:address":"4019 Johnston St",
    "sg:city":"Lafayette",
    "sg:classifiers":[
        {
            "category":"Banks & Credit Unions",
            "subcategory":"Bank",
            "type":"Services"
        }
    ],
    "sg:phone":"+1 337 993 1209",
    "sg:postcode":"70503",
    "sg:province":"LA",
    "sg:tags":[
        "loan"
    ],
    "wof:name":"Fast Auto & Payday Loans Inc",
    "wof:placetype":"venue"
},
  "geometry": {"coordinates":[-92.056392,30.197426],"type":"Point"}
}