{
  "type": "Feature",
  "properties": {
    "addr:full":"5958 Jamison St New Orleans LA 70126",
    "addr:housenumber":"5958",
    "addr:postcode":"70126",
    "addr:street":"Jamison St",
    "iso:country":"US",
    "sg:address":"5958 Jamison St",
    "sg:city":"New Orleans",
    "sg:classifiers":[
        {
            "category":"Building & Trades",
            "subcategory":"Cleaning & Sanitation",
            "type":"Services"
        }
    ],
    "sg:phone":"+1 504 244 0027",
    "sg:postcode":"70126",
    "sg:province":"LA",
    "sg:tags":[
        "janitor",
        "maintenance"
    ],
    "wof:name":"Thompson Cleaning Service",
    "wof:placetype":"venue"
},
  "geometry": {"coordinates":[-90.021102,30.01556],"type":"Point"}
}