{
  "type": "Feature",
  "properties": {
    "iso:country":"US",
    "sg:address":"1613 Ruth St",
    "sg:city":"Sulphur",
    "sg:classifiers":[
        {
            "category":"Restaurant",
            "type":"Food & Drink"
        }
    ],
    "sg:phone":"+1 337 527 8297",
    "sg:postcode":"70663",
    "sg:province":"LA",
    "wof:name":"Popeyes Chicken & Biscuits",
    "wof:placetype":"venue"
},
  "geometry": {"coordinates":[-93.37638699999999,30.224404],"type":"Point"}
}