{
  "type": "Feature",
  "properties": {
    "iso:country":"US",
    "sg:address":"1063 Joey Dr",
    "sg:city":"Breaux Bridge",
    "sg:classifiers":[
        {
            "category":"Autos & Motor Vehicles",
            "subcategory":"Automobile Sales",
            "type":"Retail Goods"
        }
    ],
    "sg:phone":"+1 337 332 2369",
    "sg:postcode":"70517",
    "sg:province":"LA",
    "sg:tags":[
        "car",
        "dealer"
    ],
    "wof:name":"D & D Auto Sales",
    "wof:placetype":"venue"
},
  "geometry": {"coordinates":[-91.94823599999999,30.288841],"type":"Point"}
}