{
  "type": "Feature",
  "properties": {
    "addr:full":"6131 Dauphine St New Orleans LA 70117",
    "addr:housenumber":"6131",
    "addr:postcode":"70117",
    "addr:street":"Dauphine St",
    "iso:country":"US",
    "sg:address":"6131 Dauphine St",
    "sg:city":"New Orleans",
    "sg:classifiers":[
        {
            "category":"Wholesale",
            "subcategory":"Construction Materials",
            "type":"Manufacturing & Wholesale Goods"
        }
    ],
    "sg:phone":"+1 504 277 8704",
    "sg:postcode":"70117",
    "sg:province":"LA",
    "sg:tags":[
        "fence"
    ],
    "wof:name":"Budget Fence Co",
    "wof:placetype":"venue"
},
  "geometry": {"coordinates":[-90.011793,29.956681],"type":"Point"}
}