{
  "type": "Feature",
  "properties": {
    "iso:country":"US",
    "sg:address":"252 Stone Rd",
    "sg:city":"Slidell",
    "sg:classifiers":[
        {
            "category":"Freight",
            "type":"Transportation"
        }
    ],
    "sg:phone":"+1 985 649 8090",
    "sg:postcode":"70460",
    "sg:province":"LA",
    "sg:tags":[
        "delivery"
    ],
    "wof:name":"Velocity Express Inc",
    "wof:placetype":"venue"
},
  "geometry": {"coordinates":[-89.78101599999999,30.301983],"type":"Point"}
}