{
  "type": "Feature",
  "properties": {
    "iso:country":"US",
    "sg:address":"210 W Florida Ave",
    "sg:city":"Ruston",
    "sg:classifiers":[
        {
            "category":"Professional",
            "subcategory":"Lawyer & Legal Services",
            "type":"Services"
        }
    ],
    "sg:phone":"+1 318 254 8200",
    "sg:postcode":"71270",
    "sg:province":"LA",
    "sg:tags":[
        "attorney"
    ],
    "wof:name":"Coyle & Green",
    "wof:placetype":"venue"
},
  "geometry": {"coordinates":[-92.64049,32.532615],"type":"Point"}
}