{
  "type": "Feature",
  "properties": {
    "iso:country":"US",
    "sg:address":"104 Philhurst St",
    "sg:city":"Lafayette",
    "sg:classifiers":[
        {
            "category":"Home & Garden",
            "subcategory":"Garden Supply",
            "type":"Retail Goods"
        }
    ],
    "sg:phone":"+1 337 288 0477",
    "sg:postcode":"70503",
    "sg:province":"LA",
    "sg:tags":[
        "machinery"
    ],
    "wof:name":"Callais Irrigation",
    "wof:placetype":"venue"
},
  "geometry": {"coordinates":[-92.060616,30.189464],"type":"Point"}
}