{
  "type": "Feature",
  "properties": {
    "iso:country":"US",
    "sg:address":"2811 Toulouse St",
    "sg:city":"New Orleans",
    "sg:classifiers":[
        {
            "category":"Wholesale",
            "subcategory":"Groceries",
            "type":"Manufacturing & Wholesale Goods"
        }
    ],
    "sg:phone":"+1 504 299 9403",
    "sg:postcode":"70119",
    "sg:province":"LA",
    "sg:tags":[
        "beverage"
    ],
    "wof:name":"Crown Beverage Co",
    "wof:placetype":"venue"
},
  "geometry": {"coordinates":[-90.086018,29.971064],"type":"Point"}
}