{
  "type": "Feature",
  "properties": {
    "iso:country":"US",
    "sg:address":"13541 Tiger Bend Rd",
    "sg:city":"Baton Rouge",
    "sg:classifiers":[
        {
            "category":"Professional",
            "subcategory":"Lawyer & Legal Services",
            "type":"Services"
        }
    ],
    "sg:phone":"+1 225 755 0707",
    "sg:postcode":"70817",
    "sg:province":"LA",
    "sg:tags":[
        "attorney"
    ],
    "wof:name":"Hawkins Law Office",
    "wof:placetype":"venue"
},
  "geometry": {"coordinates":[-91.034009,30.392104],"type":"Point"}
}