{
  "type": "Feature",
  "properties": {
    "addr:full":"6139 S 1st St Chataignier LA 70524",
    "addr:housenumber":"6139",
    "addr:postcode":"70524",
    "addr:street":"S 1St St",
    "iso:country":"US",
    "sg:address":"6139 S 1st St",
    "sg:city":"Chataignier",
    "sg:classifiers":[
        {
            "category":"Organizations",
            "subcategory":"Religious Organization",
            "type":"Services"
        }
    ],
    "sg:phone":"+1 337 885 3397",
    "sg:postcode":"70524",
    "sg:province":"LA",
    "sg:tags":[
        "church"
    ],
    "wof:name":"First Baptist Church",
    "wof:placetype":"venue"
},
  "geometry": {"coordinates":[-92.32204299999999,30.566528],"type":"Point"}
}