{
  "type": "Feature",
  "properties": {
    "addr:full":"2317 Manhattan Blvd Harvey LA 70058",
    "addr:housenumber":"2317",
    "addr:postcode":"70058",
    "addr:street":"Manhattan Blvd",
    "iso:country":"US",
    "sg:address":"2317 Manhattan Blvd",
    "sg:city":"Harvey",
    "sg:classifiers":[
        {
            "category":"Personal",
            "subcategory":"Beauty Salon",
            "type":"Services"
        }
    ],
    "sg:phone":"+1 504 361 8494",
    "sg:postcode":"70058",
    "sg:province":"LA",
    "sg:tags":[
        "nail",
        "manicuring"
    ],
    "wof:name":"Natural Nails",
    "wof:placetype":"venue"
},
  "geometry": {"coordinates":[-90.05100299999999,29.880199],"type":"Point"}
}