{
  "type": "Feature",
  "properties": {
    "iso:country":"US",
    "sg:address":"7551 Horizon Dr",
    "sg:city":"New Orleans",
    "sg:classifiers":[
        {
            "category":"Shopping",
            "type":"Retail Goods"
        }
    ],
    "sg:phone":"+1 504 524 3146",
    "sg:postcode":"70129",
    "sg:province":"LA",
    "sg:tags":[
        "regalia",
        "fraternal",
        "supply"
    ],
    "wof:name":"Temple Shop",
    "wof:placetype":"venue"
},
  "geometry": {"coordinates":[-89.926997,30.058191],"type":"Point"}
}