{
  "type": "Feature",
  "properties": {
    "iso:country":"US",
    "sg:address":"7207 Desiard St",
    "sg:city":"Monroe",
    "sg:classifiers":[
        {
            "category":"Arts & Performance",
            "subcategory":"Theater",
            "type":"Entertainment"
        }
    ],
    "sg:phone":"+1 318 998 1274",
    "sg:postcode":"71203",
    "sg:province":"LA",
    "sg:tags":[
        "bureau"
    ],
    "wof:name":"Dynasty Entertainment",
    "wof:placetype":"venue"
},
  "geometry": {"coordinates":[-92.049373,32.525637],"type":"Point"}
}