{
  "type": "Feature",
  "properties": {
    "addr:full":"2121 Airline Dr Metairie LA 70001",
    "addr:housenumber":"2121",
    "addr:postcode":"70001",
    "addr:street":"Airline Dr",
    "iso:country":"US",
    "sg:address":"2121 Airline Dr",
    "sg:city":"Metairie",
    "sg:classifiers":[
        {
            "category":"Government",
            "subcategory":"Police Station",
            "type":"Public Place"
        }
    ],
    "sg:phone":"+1 504 838 5660",
    "sg:postcode":"70001",
    "sg:province":"LA",
    "sg:tags":[
        "state"
    ],
    "wof:name":"State Police",
    "wof:placetype":"venue"
},
  "geometry": {"coordinates":[-90.150953,29.974358],"type":"Point"}
}