{
  "type": "Feature",
  "properties": {
    "addr:full":"127 Camp St New Orleans LA 70130",
    "addr:housenumber":"127",
    "addr:postcode":"70130",
    "addr:street":"Camp St",
    "iso:country":"US",
    "sg:address":"127 Camp St",
    "sg:city":"New Orleans",
    "sg:classifiers":[
        {
            "category":"Professional",
            "subcategory":"Lawyer & Legal Services",
            "type":"Services"
        }
    ],
    "sg:phone":"+1 504 568 1112",
    "sg:postcode":"70130",
    "sg:province":"LA",
    "sg:tags":[
        "attorney"
    ],
    "wof:name":"Wessel & Assoc",
    "wof:placetype":"venue"
},
  "geometry": {"coordinates":[-90.068573,29.952015],"type":"Point"}
}