{
  "type": "Feature",
  "properties": {
    "iso:country":"US",
    "sg:address":"28194 S Satsuma Rd",
    "sg:city":"Livingston",
    "sg:classifiers":[
        {
            "category":"Professional",
            "subcategory":"Management & Consulting",
            "type":"Services"
        }
    ],
    "sg:phone":"+1 225 686 8738",
    "sg:postcode":"70754",
    "sg:province":"LA",
    "sg:tags":[
        "communications",
        "consultant"
    ],
    "wof:name":"Mesa Communications Group",
    "wof:placetype":"venue"
},
  "geometry": {"coordinates":[-90.79410900000001,30.482903],"type":"Point"}
}