{
  "type": "Feature",
  "properties": {
    "iso:country":"US",
    "sg:address":"2595 N Sherwood Forest Dr",
    "sg:city":"Baton Rouge",
    "sg:classifiers":[
        {
            "category":"Health Services",
            "subcategory":"Chiropractor",
            "type":"Services"
        }
    ],
    "sg:phone":"+1 225 272 1974",
    "sg:postcode":"70815",
    "sg:province":"LA",
    "wof:name":"Booth Chiropractic Clinic",
    "wof:placetype":"venue"
},
  "geometry": {"coordinates":[-91.057912,30.471311],"type":"Point"}
}