{
  "type": "Feature",
  "properties": {
    "iso:country":"US",
    "sg:address":"4606 Jones Creek Rd",
    "sg:city":"Baton Rouge",
    "sg:classifiers":[
        {
            "category":"Building & Trades",
            "subcategory":"Pest Control",
            "type":"Services"
        }
    ],
    "sg:phone":"+1 225 751 8688",
    "sg:postcode":"70817",
    "sg:province":"LA",
    "wof:name":"Baton Rouge Pest Control Inc",
    "wof:placetype":"venue"
},
  "geometry": {"coordinates":[-91.01546500000001,30.412064],"type":"Point"}
}