{
  "type": "Feature",
  "properties": {
    "addr:full":"1811 W Laurel Ave Eunice LA 70535",
    "addr:housenumber":"1811",
    "addr:postcode":"70535",
    "addr:street":"W Laurel Ave",
    "iso:country":"US",
    "sg:address":"1811 W Laurel Ave",
    "sg:city":"Eunice",
    "sg:classifiers":[
        {
            "category":"Banks & Credit Unions",
            "subcategory":"Investment Brokerage",
            "type":"Services"
        }
    ],
    "sg:phone":"+1 337 457 1721",
    "sg:postcode":"70535",
    "sg:province":"LA",
    "sg:tags":[
        "security"
    ],
    "wof:name":"Edward Jones Co",
    "wof:placetype":"venue"
},
  "geometry": {"coordinates":[-92.434994,30.494908],"type":"Point"}
}