{
  "type": "Feature",
  "properties": {
    "iso:country":"US",
    "sg:address":"5303 E Texas St",
    "sg:city":"Bossier City",
    "sg:classifiers":[
        {
            "category":"Building & Trades",
            "subcategory":"Landscaping Services",
            "type":"Services"
        }
    ],
    "sg:phone":"+1 318 742 0562",
    "sg:postcode":"71111",
    "sg:province":"LA",
    "sg:tags":[
        "lawn",
        "maintenance",
        "grounds"
    ],
    "wof:name":"Yard Boy",
    "wof:placetype":"venue"
},
  "geometry": {"coordinates":[-93.661952,32.536924],"type":"Point"}
}