{
  "type": "Feature",
  "properties": {
    "addr:full":"2055 Metairie Rd Metairie LA 70005",
    "addr:housenumber":"2055",
    "addr:postcode":"70005",
    "addr:street":"Metairie Rd",
    "iso:country":"US",
    "sg:address":"2055 Metairie Rd",
    "sg:city":"Metairie",
    "sg:classifiers":[
        {
            "category":"Social Services",
            "subcategory":"Child Care",
            "type":"Services"
        }
    ],
    "sg:phone":"+1 504 838 7979",
    "sg:postcode":"70005",
    "sg:province":"LA",
    "sg:tags":[
        "kindergarten",
        "academic",
        "school"
    ],
    "wof:name":"Little Red School House",
    "wof:placetype":"venue"
},
  "geometry": {"coordinates":[-90.146776,29.985101],"type":"Point"}
}