{
  "type": "Feature",
  "properties": {
    "iso:country":"US",
    "sg:address":"2911 Milam St",
    "sg:city":"Shreveport",
    "sg:classifiers":[
        {
            "category":"Restaurant",
            "type":"Food & Drink"
        }
    ],
    "sg:phone":"+1 318 424 3900",
    "sg:postcode":"71103",
    "sg:province":"LA",
    "wof:name":"New Nat Cafe",
    "wof:placetype":"venue"
},
  "geometry": {"coordinates":[-93.78643,32.503513],"type":"Point"}
}