{
  "type": "Feature",
  "properties": {
    "iso:country":"US",
    "sg:address":"212 6th St",
    "sg:city":"Lafayette",
    "sg:classifiers":[
        {
            "category":"Organizations",
            "subcategory":"Religious Organization",
            "type":"Services"
        }
    ],
    "sg:phone":"+1 337 235 2407",
    "sg:postcode":"70501",
    "sg:province":"LA",
    "sg:tags":[
        "church"
    ],
    "wof:name":"Salvation Army",
    "wof:placetype":"venue"
},
  "geometry": {"coordinates":[-92.011692,30.226896],"type":"Point"}
}