{
  "type": "Feature",
  "properties": {
    "addr:full":"1623 State Rte 30 Gonzales LA 70737",
    "addr:housenumber":"1623",
    "addr:postcode":"70737",
    "addr:street":"State Rte 30 Gonzales La",
    "iso:country":"US",
    "sg:address":"1623 State Rte 30",
    "sg:city":"Gonzales",
    "sg:classifiers":[
        {
            "category":"Retail",
            "subcategory":"Repair Shop",
            "type":"Services"
        }
    ],
    "sg:phone":"+1 225 644 3837",
    "sg:postcode":"70737",
    "sg:province":"LA",
    "sg:tags":[
        "lighting",
        "fixture"
    ],
    "wof:name":"Ascension Lighting Svc",
    "wof:placetype":"venue"
},
  "geometry": {"coordinates":[-90.90036600000001,30.21113],"type":"Point"}
}