{
  "type": "Feature",
  "properties": {
    "iso:country":"US",
    "sg:address":"4900 Bissonet Dr",
    "sg:city":"Metairie",
    "sg:classifiers":[
        {
            "category":"Freight",
            "type":"Transportation"
        }
    ],
    "sg:phone":"+1 504 454 7558",
    "sg:postcode":"70003",
    "sg:province":"LA",
    "sg:tags":[
        "fixed",
        "motor",
        "facility"
    ],
    "wof:name":"Cargo Surveyors Inc",
    "wof:placetype":"venue"
},
  "geometry": {"coordinates":[-90.212384,30.023488],"type":"Point"}
}