{
  "type": "Feature",
  "properties": {
    "addr:full":"15063 E Main St Cut Off LA 70345",
    "addr:housenumber":"15063",
    "addr:postcode":"70345",
    "addr:street":"E Main St Cut Off",
    "iso:country":"US",
    "sg:address":"15063 E Main St",
    "sg:city":"Cut Off",
    "sg:classifiers":[
        {
            "category":"Professional",
            "subcategory":"Lawyer & Legal Services",
            "type":"Services"
        }
    ],
    "sg:phone":"+1 985 632 1275",
    "sg:postcode":"70345",
    "sg:province":"LA",
    "sg:tags":[
        "attorney"
    ],
    "wof:name":"Ray L Rhymes Law Office",
    "wof:placetype":"venue"
},
  "geometry": {"coordinates":[-90.32553299999999,29.489252],"type":"Point"}
}