{
  "type": "Feature",
  "properties": {
    "iso:country":"US",
    "sg:address":"1924 W Laurel Ave",
    "sg:city":"Eunice",
    "sg:classifiers":[
        {
            "category":"Shopping",
            "subcategory":"Clothing, Apparel, & Fashions",
            "type":"Retail Goods"
        }
    ],
    "sg:phone":"+1 337 457 7431",
    "sg:postcode":"70535",
    "sg:province":"LA",
    "wof:name":"Deshotel's Junior & Missy Shop",
    "wof:placetype":"venue"
},
  "geometry": {"coordinates":[-92.43636100000001,30.495072],"type":"Point"}
}