{
  "type": "Feature",
  "properties": {
    "iso:country":"US",
    "sg:address":"200 3rd St",
    "sg:city":"Rayne",
    "sg:classifiers":[
        {
            "category":"Government",
            "subcategory":"Office",
            "type":"Public Place"
        }
    ],
    "sg:phone":"+1 337 334 6670",
    "sg:postcode":"70578",
    "sg:province":"LA",
    "sg:tags":[
        "village"
    ],
    "wof:name":"Rayne Power Plant",
    "wof:placetype":"venue"
},
  "geometry": {"coordinates":[-92.271807,30.235111],"type":"Point"}
}