{
  "type": "Feature",
  "properties": {
    "addr:full":"512 Chickasaw Dr Opelousas LA 70570",
    "addr:housenumber":"512",
    "addr:postcode":"70570",
    "addr:street":"Chickasaw Dr",
    "iso:country":"US",
    "sg:address":"512 Chickasaw Dr",
    "sg:city":"Opelousas",
    "sg:classifiers":[
        {
            "category":"Banks & Credit Unions",
            "subcategory":"Bank",
            "type":"Services"
        }
    ],
    "sg:phone":"+1 337 948 0128",
    "sg:postcode":"70570",
    "sg:province":"LA",
    "wof:name":"Fernandez Kandy Banks",
    "wof:placetype":"venue"
},
  "geometry": {"coordinates":[-92.075357,30.5467],"type":"Point"}
}