{
  "type": "Feature",
  "properties": {
    "iso:country":"US",
    "sg:address":"5401 Robeline Dr",
    "sg:city":"Metairie",
    "sg:classifiers":[
        {
            "category":"Retail",
            "subcategory":"Portrait Studio",
            "type":"Services"
        }
    ],
    "sg:phone":"+1 504 454 8424",
    "sg:postcode":"70003",
    "sg:province":"LA",
    "sg:tags":[
        "photographer"
    ],
    "sg:website":"www.sansonephotography.com",
    "wof:name":"Sansone Photography",
    "wof:placetype":"venue"
},
  "geometry": {"coordinates":[-90.22143800000001,30.031223],"type":"Point"}
}