{
  "type": "Feature",
  "properties": {
    "iso:country":"US",
    "sg:address":"3428 Jefferson Hwy",
    "sg:city":"Jefferson",
    "sg:classifiers":[
        {
            "category":"Retail",
            "subcategory":"Repair Shop",
            "type":"Services"
        }
    ],
    "sg:phone":"+1 504 831 8400",
    "sg:postcode":"70121",
    "sg:province":"LA",
    "sg:tags":[
        "television",
        "radio"
    ],
    "wof:name":"Phil's TV Svc",
    "wof:placetype":"venue"
},
  "geometry": {"coordinates":[-90.15982,29.962955],"type":"Point"}
}