{
  "type": "Feature",
  "properties": {
    "addr:full":"1604 Military Hwy Pineville LA 71360",
    "addr:housenumber":"1604",
    "addr:postcode":"71360",
    "addr:street":"Military Hwy",
    "iso:country":"US",
    "sg:address":"1604 Military Hwy",
    "sg:city":"Pineville",
    "sg:classifiers":[
        {
            "category":"Shopping",
            "subcategory":"Department Store",
            "type":"Retail Goods"
        }
    ],
    "sg:phone":"+1 318 445 3746",
    "sg:postcode":"71360",
    "sg:province":"LA",
    "sg:tags":[
        "shop"
    ],
    "wof:name":"Family Dollar Store",
    "wof:placetype":"venue"
},
  "geometry": {"coordinates":[-92.42787199999999,31.334956],"type":"Point"}
}