{
  "type": "Feature",
  "properties": {
    "iso:country":"US",
    "sg:address":"7758 Bluebonnet Blvd",
    "sg:city":"Baton Rouge",
    "sg:classifiers":[
        {
            "category":"Retail",
            "subcategory":"Laundry & Dry Cleaning",
            "type":"Services"
        }
    ],
    "sg:phone":"+1 225 766 7090",
    "sg:postcode":"70810",
    "sg:province":"LA",
    "sg:tags":[
        "cleaners"
    ],
    "wof:name":"Trinity Cleaners",
    "wof:placetype":"venue"
},
  "geometry": {"coordinates":[-91.09760900000001,30.379609],"type":"Point"}
}