{
  "type": "Feature",
  "properties": {
    "addr:full":"306 N Adams St Welsh LA 70591",
    "addr:housenumber":"306",
    "addr:postcode":"70591",
    "addr:street":"N Adams St",
    "iso:country":"US",
    "sg:address":"306 N Adams St",
    "sg:city":"Welsh",
    "sg:classifiers":[
        {
            "category":"Organizations",
            "subcategory":"Religious Organization",
            "type":"Services"
        }
    ],
    "sg:phone":"+1 337 734 2043",
    "sg:postcode":"70591",
    "sg:province":"LA",
    "sg:tags":[
        "church"
    ],
    "wof:name":"First United Methodist Church",
    "wof:placetype":"venue"
},
  "geometry": {"coordinates":[-92.821569,30.241327],"type":"Point"}
}