{
  "type": "Feature",
  "properties": {
    "iso:country":"US",
    "sg:address":"8700 Old Hammond Hwy",
    "sg:city":"Baton Rouge",
    "sg:classifiers":[
        {
            "category":"Organizations",
            "subcategory":"Professional Association",
            "type":"Services"
        }
    ],
    "sg:phone":"+1 225 216 3990",
    "sg:postcode":"70809",
    "sg:province":"LA",
    "wof:name":"Cove Subdivision Assn",
    "wof:placetype":"venue"
},
  "geometry": {"coordinates":[-91.092703,30.43098],"type":"Point"}
}