{
  "type": "Feature",
  "properties": {
    "iso:country":"US",
    "sg:address":"2143 Wooddale Blvd",
    "sg:city":"Baton Rouge",
    "sg:classifiers":[
        {
            "category":"Building & Trades",
            "subcategory":"Construction",
            "type":"Services"
        }
    ],
    "sg:phone":"+1 225 274 8400",
    "sg:postcode":"70806",
    "sg:province":"LA",
    "sg:tags":[
        "home",
        "improvement"
    ],
    "wof:name":"A 1 Home Improvements",
    "wof:placetype":"venue"
},
  "geometry": {"coordinates":[-91.11525,30.468358],"type":"Point"}
}