{
  "type": "Feature",
  "properties": {
    "addr:full":"801 Ramon St Mandeville LA 70448",
    "addr:housenumber":"801",
    "addr:postcode":"70448",
    "addr:street":"Ramon St",
    "iso:country":"US",
    "sg:address":"801 Ramon St",
    "sg:city":"Mandeville",
    "sg:classifiers":[
        {
            "category":"Retail",
            "subcategory":"Auto Repair",
            "type":"Services"
        }
    ],
    "sg:phone":"+1 985 626 9876",
    "sg:postcode":"70448",
    "sg:province":"LA",
    "sg:tags":[
        "wrecker"
    ],
    "wof:name":"Keith's Towing Svc",
    "wof:placetype":"venue"
},
  "geometry": {"coordinates":[-90.07038900000001,30.367936],"type":"Point"}
}