{
  "type": "Feature",
  "properties": {
    "iso:country":"US",
    "sg:address":"760 Pailet Ave",
    "sg:city":"Harvey",
    "sg:classifiers":[
        {
            "category":"Professional",
            "subcategory":"Business Services",
            "type":"Services"
        }
    ],
    "sg:phone":"+1 504 366 9044",
    "sg:postcode":"70058",
    "sg:province":"LA",
    "wof:name":"P & P Group Incorporated",
    "wof:placetype":"venue"
},
  "geometry": {"coordinates":[-90.076131,29.90186],"type":"Point"}
}