{
  "type": "Feature",
  "properties": {
    "iso:country":"US",
    "sg:address":"6030 Line Ave",
    "sg:city":"Shreveport",
    "sg:classifiers":[
        {
            "category":"Professional",
            "subcategory":"Advertising",
            "type":"Services"
        }
    ],
    "sg:phone":"+1 318 868 1776",
    "sg:postcode":"71106",
    "sg:province":"LA",
    "sg:tags":[
        "mailing",
        "shipping"
    ],
    "wof:name":"Pack & Wrap",
    "wof:placetype":"venue"
},
  "geometry": {"coordinates":[-93.7461,32.453306],"type":"Point"}
}