{
  "type": "Feature",
  "properties": {
    "iso:country":"US",
    "sg:address":"25908 New Hope Ave",
    "sg:city":"Denham Springs",
    "sg:classifiers":[
        {
            "category":"Health Services",
            "subcategory":"Doctor",
            "type":"Services"
        }
    ],
    "sg:phone":"+1 225 665 2703",
    "sg:postcode":"70726",
    "sg:province":"LA",
    "sg:tags":[
        "physician",
        "surgeon"
    ],
    "wof:name":"David C Kemp MD",
    "wof:placetype":"venue"
},
  "geometry": {"coordinates":[-90.95432,30.443862],"type":"Point"}
}