{
  "type": "Feature",
  "properties": {
    "iso:country":"US",
    "sg:address":"4266 Front St",
    "sg:city":"Winnsboro",
    "sg:classifiers":[
        {
            "category":"Organizations",
            "subcategory":"Community Association",
            "type":"Services"
        }
    ],
    "sg:phone":"+1 318 412 0472",
    "sg:postcode":"71295",
    "sg:province":"LA",
    "sg:tags":[
        "environmental",
        "org"
    ],
    "wof:name":"Nature Concervancy",
    "wof:placetype":"venue"
},
  "geometry": {"coordinates":[-91.7086,32.153128],"type":"Point"}
}