{
  "type": "Feature",
  "properties": {
    "iso:country":"US",
    "sg:address":"7388 Highland Rd",
    "sg:city":"Baton Rouge",
    "sg:classifiers":[
        {
            "category":"Professional",
            "subcategory":"Engineering",
            "type":"Services"
        }
    ],
    "sg:phone":"+1 225 766 7154",
    "sg:postcode":"70808",
    "sg:province":"LA",
    "sg:tags":[
        "engineer"
    ],
    "sg:website":"www.albertyandassociates.com",
    "wof:name":"Alberty & Assoc",
    "wof:placetype":"venue"
},
  "geometry": {"coordinates":[-91.139736,30.378906],"type":"Point"}
}