{
  "type": "Feature",
  "properties": {
    "iso:country":"US",
    "sg:address":"517 Metairie Rd",
    "sg:city":"Metairie",
    "sg:classifiers":[
        {
            "category":"Shopping",
            "subcategory":"Optical Goods",
            "type":"Retail Goods"
        }
    ],
    "sg:phone":"+1 504 837 1555",
    "sg:postcode":"70005",
    "sg:province":"LA",
    "wof:name":"Barnett Optical Corporation",
    "wof:placetype":"venue"
},
  "geometry": {"coordinates":[-90.129639,29.986644],"type":"Point"}
}