{
  "type": "Feature",
  "properties": {
    "iso:country":"US",
    "sg:address":"3000 Hwy 10",
    "sg:city":"Jackson",
    "sg:classifiers":[
        {
            "category":"Shopping",
            "subcategory":"Department Store",
            "type":"Retail Goods"
        }
    ],
    "sg:phone":"+1 225 634 3372",
    "sg:postcode":"70748",
    "sg:province":"LA",
    "sg:tags":[
        "shop"
    ],
    "wof:name":"Family Dollar Store",
    "wof:placetype":"venue"
},
  "geometry": {"coordinates":[-91.186881,30.83507],"type":"Point"}
}