{
  "type": "Feature",
  "properties": {
    "iso:country":"US",
    "sg:address":"7184 US Hwy 165",
    "sg:city":"Columbia",
    "sg:classifiers":[
        {
            "category":"Organizations",
            "subcategory":"Religious Organization",
            "type":"Services"
        }
    ],
    "sg:phone":"+1 318 649 2227",
    "sg:postcode":"71418",
    "sg:province":"LA",
    "sg:tags":[
        "church"
    ],
    "wof:name":"Crossroads Baptist Church",
    "wof:placetype":"venue"
},
  "geometry": {"coordinates":[-92.09063399999999,32.086202],"type":"Point"}
}