{
  "type": "Feature",
  "properties": {
    "addr:full":"5632 Estelle Dr Baton Rouge LA 70817",
    "addr:housenumber":"5632",
    "addr:postcode":"70817",
    "addr:street":"Estelle Dr",
    "iso:country":"US",
    "sg:address":"5632 Estelle Dr",
    "sg:city":"Baton Rouge",
    "sg:classifiers":[
        {
            "category":"Insurance",
            "subcategory":"Insurance Agent",
            "type":"Services"
        }
    ],
    "sg:phone":"+1 225 293 5100",
    "sg:postcode":"70817",
    "sg:province":"LA",
    "wof:name":"New York Life",
    "wof:placetype":"venue"
},
  "geometry": {"coordinates":[-91.013411,30.40317],"type":"Point"}
}