{
  "type": "Feature",
  "properties": {
    "iso:country":"US",
    "sg:address":"3400 N Galvez St",
    "sg:city":"New Orleans",
    "sg:classifiers":[
        {
            "category":"Retail",
            "subcategory":"Laundry & Dry Cleaning",
            "type":"Services"
        }
    ],
    "sg:phone":"+1 504 940 2222",
    "sg:postcode":"70117",
    "sg:province":"LA",
    "sg:tags":[
        "cleaners"
    ],
    "wof:name":"M & M Dry Cleaners",
    "wof:placetype":"venue"
},
  "geometry": {"coordinates":[-90.036551,29.976857],"type":"Point"}
}