{
  "type": "Feature",
  "properties": {
    "iso:country":"US",
    "sg:address":"508 E Bayou Dr",
    "sg:city":"Tallulah",
    "sg:classifiers":[
        {
            "category":"Social Services",
            "type":"Services"
        }
    ],
    "sg:phone":"+1 318 574 3552",
    "sg:postcode":"71282",
    "sg:province":"LA",
    "sg:tags":[
        "government"
    ],
    "wof:name":"Youth Service Div",
    "wof:placetype":"venue"
},
  "geometry": {"coordinates":[-91.18097299999999,32.407718],"type":"Point"}
}