{
  "type": "Feature",
  "properties": {
    "iso:country":"US",
    "sg:address":"3702 Louisiana Ave",
    "sg:city":"Lake Charles",
    "sg:classifiers":[
        {
            "category":"Personal",
            "subcategory":"Beauty Salon",
            "type":"Services"
        }
    ],
    "sg:phone":"+1 337 478 0586",
    "sg:postcode":"70607",
    "sg:province":"LA",
    "wof:name":"Ruth & Naomi",
    "wof:placetype":"venue"
},
  "geometry": {"coordinates":[-93.205589,30.190652],"type":"Point"}
}