{
  "type": "Feature",
  "properties": {
    "addr:full":"227 Laird St West Monroe LA 71291",
    "addr:housenumber":"227",
    "addr:postcode":"71291",
    "addr:street":"Laird St West",
    "iso:country":"US",
    "sg:address":"227 Laird St",
    "sg:city":"West Monroe",
    "sg:classifiers":[
        {
            "category":"Manufacturing",
            "subcategory":"Food",
            "type":"Manufacturing & Wholesale Goods"
        }
    ],
    "sg:phone":"+1 318 396 8355",
    "sg:postcode":"71291",
    "sg:province":"LA",
    "sg:tags":[
        "syrup"
    ],
    "wof:name":"Norris Syrup Co",
    "wof:placetype":"venue"
},
  "geometry": {"coordinates":[-92.186233,32.520086],"type":"Point"}
}