{
  "type": "Feature",
  "properties": {
    "iso:country":"US",
    "sg:address":"6012 Frederick Dr",
    "sg:city":"Baton Rouge",
    "sg:classifiers":[
        {
            "category":"Professional",
            "subcategory":"Business Services",
            "type":"Services"
        }
    ],
    "sg:phone":"+1 225 753 5421",
    "sg:postcode":"70817",
    "sg:province":"LA",
    "wof:name":"Soniats Jeff Studio For Fine",
    "wof:placetype":"venue"
},
  "geometry": {"coordinates":[-90.99945099999999,30.396284],"type":"Point"}
}