{
  "type": "Feature",
  "properties": {
    "iso:country":"US",
    "sg:address":"906 Homer Rd",
    "sg:city":"Minden",
    "sg:classifiers":[
        {
            "category":"Health Services",
            "subcategory":"Health Practitioner",
            "type":"Services"
        }
    ],
    "sg:phone":"+1 318 377 4028",
    "sg:postcode":"71055",
    "sg:province":"LA",
    "sg:tags":[
        "therapist",
        "physical"
    ],
    "wof:name":"Physical Therapy Assoc",
    "wof:placetype":"venue"
},
  "geometry": {"coordinates":[-93.266113,32.621699],"type":"Point"}
}