{
  "type": "Feature",
  "properties": {
    "iso:country":"US",
    "sg:address":"415 Goode St",
    "sg:city":"Houma",
    "sg:classifiers":[
        {
            "category":"Professional",
            "subcategory":"Lawyer & Legal Services",
            "type":"Services"
        }
    ],
    "sg:phone":"+1 985 872 6531",
    "sg:postcode":"70360",
    "sg:province":"LA",
    "sg:tags":[
        "attorney"
    ],
    "wof:name":"Elton A Darsey",
    "wof:placetype":"venue"
},
  "geometry": {"coordinates":[-90.721946,29.595414],"type":"Point"}
}