{
  "type": "Feature",
  "properties": {
    "addr:full":"222 Louise St Baton Rouge LA 70802",
    "addr:housenumber":"222",
    "addr:postcode":"70802",
    "addr:street":"Louise St",
    "iso:country":"US",
    "sg:address":"222 Louise St",
    "sg:city":"Baton Rouge",
    "sg:classifiers":[
        {
            "category":"Professional",
            "subcategory":"Lawyer & Legal Services",
            "type":"Services"
        }
    ],
    "sg:phone":"+1 225 266 4372",
    "sg:postcode":"70802",
    "sg:province":"LA",
    "sg:tags":[
        "attorney"
    ],
    "wof:name":"Robert H Abbott III",
    "wof:placetype":"venue"
},
  "geometry": {"coordinates":[-91.182574,30.433972],"type":"Point"}
}