{
  "type": "Feature",
  "properties": {
    "addr:full":"4021 Najolia St Meraux LA 70075",
    "addr:housenumber":"4021",
    "addr:postcode":"70075",
    "addr:street":"Najolia St",
    "iso:country":"US",
    "sg:address":"4021 Najolia St",
    "sg:city":"Meraux",
    "sg:classifiers":[
        {
            "category":"Building & Trades",
            "subcategory":"Plumbing",
            "type":"Services"
        }
    ],
    "sg:phone":"+1 504 277 0407",
    "sg:postcode":"70075",
    "sg:province":"LA",
    "sg:tags":[
        "conditioning",
        "air",
        "system",
        "contractor"
    ],
    "wof:name":"City-Wide Air Conditioning",
    "wof:placetype":"venue"
},
  "geometry": {"coordinates":[-89.92135500000001,29.939139],"type":"Point"}
}