{
  "type": "Feature",
  "properties": {
    "addr:full":"7913 Desiard St Monroe LA 71203",
    "addr:housenumber":"7913",
    "addr:postcode":"71203",
    "addr:street":"Desiard St",
    "iso:country":"US",
    "sg:address":"7913 Desiard St",
    "sg:city":"Monroe",
    "sg:classifiers":[
        {
            "category":"Communications",
            "subcategory":"Film & Video Production",
            "type":"Services"
        }
    ],
    "sg:phone":"+1 318 345 2503",
    "sg:postcode":"71203",
    "sg:province":"LA",
    "sg:tags":[
        "taping"
    ],
    "wof:name":"Advent Video Productions",
    "wof:placetype":"venue"
},
  "geometry": {"coordinates":[-92.042884,32.526129],"type":"Point"}
}