{
  "type": "Feature",
  "properties": {
    "iso:country":"US",
    "sg:address":"3566 S Carrollton Ave",
    "sg:city":"New Orleans",
    "sg:classifiers":[
        {
            "category":"Shopping",
            "subcategory":"Discount & Variety Stores",
            "type":"Retail Goods"
        }
    ],
    "sg:phone":"+1 504 482 5112",
    "sg:postcode":"70118",
    "sg:province":"LA",
    "wof:name":"Wig World",
    "wof:placetype":"venue"
},
  "geometry": {"coordinates":[-90.11154500000001,29.964469],"type":"Point"}
}