{
  "type": "Feature",
  "properties": {
    "addr:full":"10966 Crossett Rd Bastrop LA 71220",
    "addr:housenumber":"10966",
    "addr:postcode":"71220",
    "addr:street":"Crossett Rd",
    "iso:country":"US",
    "sg:address":"10966 Crossett Rd",
    "sg:city":"Bastrop",
    "sg:classifiers":[
        {
            "category":"Farming",
            "subcategory":"Farm",
            "type":"Manufacturing & Wholesale Goods"
        }
    ],
    "sg:phone":"+1 318 283 0673",
    "sg:postcode":"71220",
    "sg:province":"LA",
    "sg:tags":[
        "crop",
        "general"
    ],
    "wof:name":"Hawkins Terrell",
    "wof:placetype":"venue"
},
  "geometry": {"coordinates":[-91.892425,32.817948],"type":"Point"}
}