{
  "type": "Feature",
  "properties": {
    "iso:country":"US",
    "sg:address":"1739 Willow Point Dr",
    "sg:city":"Shreveport",
    "sg:classifiers":[
        {
            "category":"Professional",
            "subcategory":"Accounting & Tax Preparation",
            "type":"Services"
        }
    ],
    "sg:phone":"+1 318 747 1000",
    "sg:postcode":"71119",
    "sg:province":"LA",
    "sg:tags":[
        "return",
        "filing"
    ],
    "wof:name":"Gilbert L Sibley Jr Inc",
    "wof:placetype":"venue"
},
  "geometry": {"coordinates":[-93.82356299999999,32.496346],"type":"Point"}
}