{
  "type": "Feature",
  "properties": {
    "addr:full":"113 Elm St Thibodaux LA 70301",
    "addr:housenumber":"113",
    "addr:postcode":"70301",
    "addr:street":"Elm St",
    "iso:country":"US",
    "sg:address":"113 Elm St",
    "sg:city":"Thibodaux",
    "sg:classifiers":[
        {
            "category":"Personal",
            "subcategory":"Beauty Salon",
            "type":"Services"
        }
    ],
    "sg:phone":"+1 985 446 9112",
    "sg:postcode":"70301",
    "sg:province":"LA",
    "sg:tags":[
        "shop"
    ],
    "wof:name":"Allie Beauty Salon",
    "wof:placetype":"venue"
},
  "geometry": {"coordinates":[-90.825829,29.798506],"type":"Point"}
}