{
  "type": "Feature",
  "properties": {
    "iso:country":"US",
    "sg:address":"624 Porteous St",
    "sg:city":"New Orleans",
    "sg:classifiers":[
        {
            "category":"Professional",
            "subcategory":"Advertising",
            "type":"Services"
        }
    ],
    "sg:phone":"+1 504 586 1609",
    "sg:postcode":"70124",
    "sg:province":"LA",
    "sg:tags":[
        "counselor"
    ],
    "wof:name":"Rosemary James & Assoc",
    "wof:placetype":"venue"
},
  "geometry": {"coordinates":[-90.107788,30.010383],"type":"Point"}
}