{
  "type": "Feature",
  "properties": {
    "iso:country":"US",
    "sg:address":"222 E California Ave",
    "sg:city":"Vivian",
    "sg:classifiers":[
        {
            "category":"Building & Trades",
            "subcategory":"Electrical",
            "type":"Services"
        }
    ],
    "sg:phone":"+1 318 375 3031",
    "sg:postcode":"71082",
    "sg:province":"LA",
    "sg:tags":[
        "electric",
        "contractor"
    ],
    "wof:name":"Edwards Electric & Air Cond",
    "wof:placetype":"venue"
},
  "geometry": {"coordinates":[-93.985832,32.868015],"type":"Point"}
}