{
  "type": "Feature",
  "properties": {
    "iso:country":"US",
    "sg:address":"23525 Eden St",
    "sg:city":"Plaquemine",
    "sg:classifiers":[
        {
            "category":"Manufacturing",
            "subcategory":"Printing",
            "type":"Manufacturing & Wholesale Goods"
        }
    ],
    "sg:phone":"+1 225 687 9711",
    "sg:postcode":"70764",
    "sg:province":"LA",
    "sg:tags":[
        "commercial"
    ],
    "sg:website":"www.vicknairprinting.com",
    "wof:name":"Vicknair Printing Inc",
    "wof:placetype":"venue"
},
  "geometry": {"coordinates":[-91.234965,30.289816],"type":"Point"}
}