{
  "type": "Feature",
  "properties": {
    "iso:country":"US",
    "sg:address":"6901 W Bert Kouns Industrial Loop",
    "sg:city":"Shreveport",
    "sg:classifiers":[
        {
            "category":"Autos & Motor Vehicles",
            "subcategory":"Fuel & Gas Station",
            "type":"Retail Goods"
        }
    ],
    "sg:phone":"+1 318 688 0654",
    "sg:postcode":"71129",
    "sg:province":"LA",
    "sg:tags":[
        "plaza",
        "truck",
        "stops"
    ],
    "wof:name":"Pilot Travel Ctr",
    "wof:placetype":"venue"
},
  "geometry": {"coordinates":[-93.89993699999999,32.442436],"type":"Point"}
}