{
  "type": "Feature",
  "properties": {
    "iso:country":"US",
    "sg:address":"5 Serenity Dr",
    "sg:city":"Mandeville",
    "sg:classifiers":[
        {
            "category":"Wholesale",
            "subcategory":"Medical Equipment & Supplies",
            "type":"Manufacturing & Wholesale Goods"
        }
    ],
    "sg:phone":"+1 985 626 1926",
    "sg:postcode":"70471",
    "sg:province":"LA",
    "sg:tags":[
        "physician",
        "surgeon"
    ],
    "wof:name":"Moore Medical Inc",
    "wof:placetype":"venue"
},
  "geometry": {"coordinates":[-90.11418,30.38635],"type":"Point"}
}