{
  "type": "Feature",
  "properties": {
    "iso:country":"US",
    "sg:address":"28736 State Rte 82",
    "sg:city":"Kaplan",
    "sg:classifiers":[
        {
            "category":"Education",
            "subcategory":"Library",
            "type":"Public Place"
        }
    ],
    "sg:phone":"+1 337 737 2510",
    "sg:postcode":"70548",
    "sg:province":"LA",
    "wof:name":"Vermilion Parish Library",
    "wof:placetype":"venue"
},
  "geometry": {"coordinates":[-92.57343899999999,29.670644],"type":"Point"}
}