{
  "type": "Feature",
  "properties": {
    "iso:country":"US",
    "sg:address":"11274 Stevenson Rd",
    "sg:city":"Geismar",
    "sg:classifiers":[
        {
            "category":"Food & Beverages",
            "subcategory":"Specialty",
            "type":"Retail Goods"
        }
    ],
    "sg:phone":"+1 225 677 8753",
    "sg:postcode":"70734",
    "sg:province":"LA",
    "sg:tags":[
        "spice"
    ],
    "wof:name":"Mama Dude's Creole Seasonings",
    "wof:placetype":"venue"
},
  "geometry": {"coordinates":[-90.98632600000001,30.231202],"type":"Point"}
}