{
  "type": "Feature",
  "properties": {
    "iso:country":"US",
    "sg:address":"307 France St",
    "sg:city":"Baton Rouge",
    "sg:classifiers":[
        {
            "category":"Health Services",
            "subcategory":"Clinic",
            "type":"Services"
        }
    ],
    "sg:phone":"+1 225 381 9959",
    "sg:postcode":"70802",
    "sg:province":"LA",
    "sg:tags":[
        "home"
    ],
    "wof:name":"Homecare Providers Inc",
    "wof:placetype":"venue"
},
  "geometry": {"coordinates":[-91.186543,30.442923],"type":"Point"}
}