{
  "type": "Feature",
  "properties": {
    "iso:country":"US",
    "sg:address":"3928 N Arnoult Rd",
    "sg:city":"Metairie",
    "sg:classifiers":[
        {
            "category":"Real Estate",
            "subcategory":"Architect",
            "type":"Services"
        }
    ],
    "sg:phone":"+1 504 454 1970",
    "sg:postcode":"70002",
    "sg:province":"LA",
    "sg:tags":[
        "architectural"
    ],
    "wof:name":"Ernst Dorfi Architect Co",
    "wof:placetype":"venue"
},
  "geometry": {"coordinates":[-90.16006400000001,30.019777],"type":"Point"}
}