{
  "type": "Feature",
  "properties": {
    "iso:country":"US",
    "sg:address":"521 NW Court Cir",
    "sg:city":"Crowley",
    "sg:classifiers":[
        {
            "category":"Professional",
            "subcategory":"Lawyer & Legal Services",
            "type":"Services"
        }
    ],
    "sg:phone":"+1 337 785 0098",
    "sg:postcode":"70526",
    "sg:province":"LA",
    "sg:tags":[
        "attorney"
    ],
    "wof:name":"Red Drum Investments",
    "wof:placetype":"venue"
},
  "geometry": {"coordinates":[-92.373974,30.213874],"type":"Point"}
}