{
  "type": "Feature",
  "properties": {
    "iso:country":"US",
    "sg:address":"145 W Hickory St",
    "sg:city":"Ponchatoula",
    "sg:classifiers":[
        {
            "category":"Wholesale",
            "subcategory":"Chemicals & Plastics",
            "type":"Manufacturing & Wholesale Goods"
        }
    ],
    "sg:phone":"+1 985 386 4760",
    "sg:postcode":"70454",
    "sg:province":"LA",
    "sg:tags":[
        "oxygen"
    ],
    "wof:name":"Quality Home Oxygen",
    "wof:placetype":"venue"
},
  "geometry": {"coordinates":[-90.442452,30.43988],"type":"Point"}
}