{
  "type": "Feature",
  "properties": {
    "iso:country":"US",
    "sg:address":"414 N Causeway Blvd",
    "sg:city":"Mandeville",
    "sg:classifiers":[
        {
            "category":"Professional",
            "subcategory":"Credit Reporting & Collection",
            "type":"Services"
        }
    ],
    "sg:phone":"+1 985 626 1963",
    "sg:postcode":"70448",
    "sg:province":"LA",
    "sg:tags":[
        "agency"
    ],
    "wof:name":"Revenue Assurance Partners LLC",
    "wof:placetype":"venue"
},
  "geometry": {"coordinates":[-90.091759,30.375105],"type":"Point"}
}