{
  "type": "Feature",
  "properties": {
    "addr:full":"3810 E Texas St Bossier City LA 71111",
    "addr:housenumber":"3810",
    "addr:postcode":"71111",
    "addr:street":"E Texas St",
    "iso:country":"US",
    "sg:address":"3810 E Texas St",
    "sg:city":"Bossier City",
    "sg:classifiers":[
        {
            "category":"Restaurant",
            "type":"Food & Drink"
        }
    ],
    "sg:phone":"+1 318 629 9070",
    "sg:postcode":"71111",
    "sg:province":"LA",
    "wof:name":"Fonzy's Diner",
    "wof:placetype":"venue"
},
  "geometry": {"coordinates":[-93.68386,32.529859],"type":"Point"}
}