{
  "type": "Feature",
  "properties": {
    "iso:country":"US",
    "sg:address":"722 E Creole Rd",
    "sg:city":"Creole",
    "sg:classifiers":[
        {
            "category":"Retail",
            "subcategory":"Portrait Studio",
            "type":"Services"
        }
    ],
    "sg:phone":"+1 337 542 4413",
    "sg:postcode":"70632",
    "sg:province":"LA",
    "sg:tags":[
        "photo"
    ],
    "wof:name":"Images Photography",
    "wof:placetype":"venue"
},
  "geometry": {"coordinates":[-93.082137,29.815705],"type":"Point"}
}