{
  "type": "Feature",
  "properties": {
    "iso:country":"US",
    "sg:address":"1911 Georgia St",
    "sg:city":"Baton Rouge",
    "sg:classifiers":[
        {
            "category":"Organizations",
            "subcategory":"Religious Organization",
            "type":"Services"
        }
    ],
    "sg:phone":"+1 225 387 2396",
    "sg:postcode":"70802",
    "sg:province":"LA",
    "sg:tags":[
        "church"
    ],
    "wof:name":"Calvary Third Baptist Church",
    "wof:placetype":"venue"
},
  "geometry": {"coordinates":[-91.175287,30.429462],"type":"Point"}
}