{
  "type": "Feature",
  "properties": {
    "iso:country":"US",
    "sg:address":"1101 Busby St",
    "sg:city":"Shreveport",
    "sg:classifiers":[
        {
            "category":"Shopping",
            "subcategory":"Florist",
            "type":"Retail Goods"
        }
    ],
    "sg:phone":"+1 318 425 1982",
    "sg:postcode":"71101",
    "sg:province":"LA",
    "wof:name":"Rose-Neath Flowers Shop",
    "wof:placetype":"venue"
},
  "geometry": {"coordinates":[-93.738547,32.499975],"type":"Point"}
}