{
  "type": "Feature",
  "properties": {
    "addr:full":"5905 Florida Blvd Baton Rouge LA 70806",
    "addr:housenumber":"5905",
    "addr:postcode":"70806",
    "addr:street":"Florida Blvd",
    "iso:country":"US",
    "sg:address":"5905 Florida Blvd",
    "sg:city":"Baton Rouge",
    "sg:classifiers":[
        {
            "category":"Government",
            "subcategory":"Office",
            "type":"Public Place"
        }
    ],
    "sg:phone":"+1 225 925 4397",
    "sg:postcode":"70806",
    "sg:province":"LA",
    "wof:name":"Disability Determinations Svc",
    "wof:placetype":"venue"
},
  "geometry": {"coordinates":[-91.127455,30.451362],"type":"Point"}
}