{
  "type": "Feature",
  "properties": {
    "addr:full":"1330 Irish Bend Rd Franklin LA 70538",
    "addr:housenumber":"1330",
    "addr:postcode":"70538",
    "addr:street":"Irish Bend Rd",
    "iso:country":"US",
    "sg:address":"1330 Irish Bend Rd",
    "sg:city":"Franklin",
    "sg:classifiers":[
        {
            "category":"Organizations",
            "subcategory":"Community Association",
            "type":"Services"
        }
    ],
    "sg:phone":"+1 337 828 1357",
    "sg:postcode":"70538",
    "sg:province":"LA",
    "sg:tags":[
        "military"
    ],
    "wof:name":"American Legion",
    "wof:placetype":"venue"
},
  "geometry": {"coordinates":[-91.48008799999999,29.80553],"type":"Point"}
}