{
  "type": "Feature",
  "properties": {
    "addr:full":"3831 Louisa St New Orleans LA 70126",
    "addr:housenumber":"3831",
    "addr:postcode":"70126",
    "addr:street":"Louisa St",
    "iso:country":"US",
    "sg:address":"3831 Louisa St",
    "sg:city":"New Orleans",
    "sg:classifiers":[
        {
            "category":"Retail",
            "subcategory":"Laundry & Dry Cleaning",
            "type":"Services"
        }
    ],
    "sg:phone":"+1 504 947 0657",
    "sg:postcode":"70126",
    "sg:province":"LA",
    "sg:tags":[
        "linen",
        "supply"
    ],
    "sg:website":"www.nationallinen.com",
    "wof:name":"National Linen Svc",
    "wof:placetype":"venue"
},
  "geometry": {"coordinates":[-90.03479299999999,29.997901],"type":"Point"}
}