{
  "type": "Feature",
  "properties": {
    "addr:full":"6717 Masonic Dr Alexandria LA 71301",
    "addr:housenumber":"6717",
    "addr:postcode":"71301",
    "addr:street":"Masonic Dr",
    "iso:country":"US",
    "sg:address":"6717 Masonic Dr",
    "sg:city":"Alexandria",
    "sg:classifiers":[
        {
            "category":"Wholesale",
            "subcategory":"Vending Machines",
            "type":"Manufacturing & Wholesale Goods"
        }
    ],
    "sg:phone":"+1 318 443 4699",
    "sg:postcode":"71301",
    "sg:province":"LA",
    "wof:name":"Kay's Gourmet Catering",
    "wof:placetype":"venue"
},
  "geometry": {"coordinates":[-92.48416899999999,31.247532],"type":"Point"}
}