{
  "type": "Feature",
  "properties": {
    "iso:country":"US",
    "sg:address":"3423 Jackson St",
    "sg:city":"Alexandria",
    "sg:classifiers":[
        {
            "category":"Restaurant",
            "type":"Food & Drink"
        }
    ],
    "sg:phone":"+1 318 443 9568",
    "sg:postcode":"71301",
    "sg:province":"LA",
    "wof:name":"Chinese Kitchen",
    "wof:placetype":"venue"
},
  "geometry": {"coordinates":[-92.47430199999999,31.286613],"type":"Point"}
}