{
  "type": "Feature",
  "properties": {
    "iso:country":"US",
    "sg:address":"4613 Palm St",
    "sg:city":"Baton Rouge",
    "sg:classifiers":[
        {
            "category":"Organizations",
            "subcategory":"Religious Organization",
            "type":"Services"
        }
    ],
    "sg:phone":"+1 225 926 3259",
    "sg:postcode":"70808",
    "sg:province":"LA",
    "sg:tags":[
        "church"
    ],
    "wof:name":"Southside Baptist Church",
    "wof:placetype":"venue"
},
  "geometry": {"coordinates":[-91.146,30.410257],"type":"Point"}
}