{
  "type": "Feature",
  "properties": {
    "iso:country":"US",
    "sg:address":"2201 Judy Dr",
    "sg:city":"Meraux",
    "sg:classifiers":[
        {
            "category":"Wholesale",
            "subcategory":"Hardware",
            "type":"Manufacturing & Wholesale Goods"
        }
    ],
    "sg:phone":"+1 504 279 9473",
    "sg:postcode":"70075",
    "sg:province":"LA",
    "sg:tags":[
        "machine",
        "making",
        "ice",
        "equipment"
    ],
    "wof:name":"USA Svc Co",
    "wof:placetype":"venue"
},
  "geometry": {"coordinates":[-89.930639,29.934555],"type":"Point"}
}