{
  "type": "Feature",
  "properties": {
    "iso:country":"US",
    "sg:address":"9300 Mansfield Rd",
    "sg:city":"Shreveport",
    "sg:classifiers":[
        {
            "category":"Real Estate",
            "subcategory":"Real Estate Agent",
            "type":"Services"
        }
    ],
    "sg:phone":"+1 318 687 2811",
    "sg:postcode":"71118",
    "sg:province":"LA",
    "sg:website":"www.oscarcloyd.com",
    "wof:name":"Prudential Preferred Prprts",
    "wof:placetype":"venue"
},
  "geometry": {"coordinates":[-93.81035799999999,32.395932],"type":"Point"}
}