{
  "type": "Feature",
  "properties": {
    "iso:country":"US",
    "sg:address":"209 N Adams Ave",
    "sg:city":"Rayne",
    "sg:classifiers":[
        {
            "category":"Restaurant",
            "type":"Food & Drink"
        }
    ],
    "sg:phone":"+1 337 334 7217",
    "sg:postcode":"70578",
    "sg:province":"LA",
    "sg:tags":[
        "pizza"
    ],
    "wof:name":"Mr Gatti's Pizza",
    "wof:placetype":"venue"
},
  "geometry": {"coordinates":[-92.26888700000001,30.237813],"type":"Point"}
}