{
  "type": "Feature",
  "properties": {
    "addr:full":"872 Harrison Ave New Orleans LA 70124",
    "addr:housenumber":"872",
    "addr:postcode":"70124",
    "addr:street":"Harrison Ave",
    "iso:country":"US",
    "sg:address":"872 Harrison Ave",
    "sg:city":"New Orleans",
    "sg:classifiers":[
        {
            "category":"Restaurant",
            "type":"Food & Drink"
        }
    ],
    "sg:phone":"+1 504 482 4616",
    "sg:postcode":"70124",
    "sg:province":"LA",
    "wof:name":"Lovecchio's Deli",
    "wof:placetype":"venue"
},
  "geometry": {"coordinates":[-90.104366,30.004193],"type":"Point"}
}