{
  "type": "Feature",
  "properties": {
    "iso:country":"US",
    "sg:address":"209 E Saint Victor St",
    "sg:city":"Abbeville",
    "sg:classifiers":[
        {
            "category":"Professional",
            "subcategory":"Lawyer & Legal Services",
            "type":"Services"
        }
    ],
    "sg:phone":"+1 337 893 1705",
    "sg:postcode":"70510",
    "sg:province":"LA",
    "sg:tags":[
        "attorney"
    ],
    "wof:name":"Bart A Broussard",
    "wof:placetype":"venue"
},
  "geometry": {"coordinates":[-92.134204,29.975019],"type":"Point"}
}