{
  "type": "Feature",
  "properties": {
    "iso:country":"US",
    "sg:address":"3027 Magazine St",
    "sg:city":"New Orleans",
    "sg:classifiers":[
        {
            "category":"Retail",
            "subcategory":"Repair Shop",
            "type":"Services"
        }
    ],
    "sg:phone":"+1 504 895 5346",
    "sg:postcode":"70115",
    "sg:province":"LA",
    "sg:tags":[
        "lock",
        "locksmith"
    ],
    "wof:name":"H Rault Locksmiths",
    "wof:placetype":"venue"
},
  "geometry": {"coordinates":[-90.08523099999999,29.924763],"type":"Point"}
}