{
  "type": "Feature",
  "properties": {
    "addr:full":"6584 Mer Rouge Rd Bastrop LA 71220",
    "addr:housenumber":"6584",
    "addr:postcode":"71220",
    "addr:street":"Mer Rouge Rd",
    "iso:country":"US",
    "sg:address":"6584 Mer Rouge Rd",
    "sg:city":"Bastrop",
    "sg:classifiers":[
        {
            "category":"Government",
            "subcategory":"Office",
            "type":"Public Place"
        }
    ],
    "sg:phone":"+1 318 283 0815",
    "sg:postcode":"71220",
    "sg:province":"LA",
    "sg:tags":[
        "state",
        "program"
    ],
    "wof:name":"Transportation Dept Mntnc",
    "wof:placetype":"venue"
},
  "geometry": {"coordinates":[-91.85514000000001,32.772883],"type":"Point"}
}