{
  "type": "Feature",
  "properties": {
    "addr:full":"903 E Morris Ave Hammond LA 70403",
    "addr:housenumber":"903",
    "addr:postcode":"70403",
    "addr:street":"E Morris Ave",
    "iso:country":"US",
    "sg:address":"903 E Morris Ave",
    "sg:city":"Hammond",
    "sg:classifiers":[
        {
            "category":"Restaurant",
            "type":"Food & Drink"
        }
    ],
    "sg:menulink":"http://www.allmenus.com/la/hammond/228208-jacmel-inn/menu/",
    "sg:phone":"+1 985 542 0043",
    "sg:postcode":"70403",
    "sg:province":"LA",
    "sg:tags":[
        "american",
        "creole",
        "cajun"
    ],
    "wof:name":"Jacmel Inn",
    "wof:placetype":"venue"
},
  "geometry": {"coordinates":[-90.451615,30.505183],"type":"Point"}
}