{
  "type": "Feature",
  "properties": {
    "addr:full":"10978 W Robin Hood Dr Baton Rouge LA 70815",
    "addr:housenumber":"10978",
    "addr:postcode":"70815",
    "addr:street":"W Robin Hood Dr",
    "iso:country":"US",
    "sg:address":"10978 W Robin Hood Dr",
    "sg:city":"Baton Rouge",
    "sg:classifiers":[
        {
            "category":"Personal",
            "subcategory":"Barber",
            "type":"Services"
        }
    ],
    "sg:phone":"+1 225 272 6050",
    "sg:postcode":"70815",
    "sg:province":"LA",
    "wof:name":"King's Room Barber",
    "wof:placetype":"venue"
},
  "geometry": {"coordinates":[-91.06450100000001,30.455573],"type":"Point"}
}