{
  "type": "Feature",
  "properties": {
    "addr:full":"1914 Cedarwood Ave Gretna LA 70056",
    "addr:housenumber":"1914",
    "addr:postcode":"70056",
    "addr:street":"Cedarwood Ave",
    "iso:country":"US",
    "sg:address":"1914 Cedarwood Ave",
    "sg:city":"Gretna",
    "sg:classifiers":[
        {
            "category":"Farming",
            "subcategory":"Fish & Marine Products",
            "type":"Manufacturing & Wholesale Goods"
        }
    ],
    "sg:phone":"+1 504 368 9717",
    "sg:postcode":"70056",
    "sg:province":"LA",
    "sg:tags":[
        "shellfish",
        "fishing"
    ],
    "wof:name":"John R Upchurch",
    "wof:placetype":"venue"
},
  "geometry": {"coordinates":[-90.03138300000001,29.909488],"type":"Point"}
}