{
  "type": "Feature",
  "properties": {
    "addr:full":"3627 Robertson St Metairie LA 70001",
    "addr:housenumber":"3627",
    "addr:postcode":"70001",
    "addr:street":"Robertson St",
    "iso:country":"US",
    "sg:address":"3627 Robertson St",
    "sg:city":"Metairie",
    "sg:classifiers":[
        {
            "category":"Building & Trades",
            "subcategory":"Landscaping Services",
            "type":"Services"
        }
    ],
    "sg:phone":"+1 504 831 3151",
    "sg:postcode":"70001",
    "sg:province":"LA",
    "sg:tags":[
        "lawn",
        "maintenance",
        "grounds"
    ],
    "wof:name":"Tebbe's Professional Lawn Care",
    "wof:placetype":"venue"
},
  "geometry": {"coordinates":[-90.16301,29.974502],"type":"Point"}
}