{
  "type": "Feature",
  "properties": {
    "iso:country":"US",
    "sg:address":"606 Sandi Ln",
    "sg:city":"Lake Charles",
    "sg:classifiers":[
        {
            "category":"Social Services",
            "subcategory":"Child Care",
            "type":"Services"
        }
    ],
    "sg:phone":"+1 337 436 2531",
    "sg:postcode":"70658",
    "sg:province":"LA",
    "sg:tags":[
        "day"
    ],
    "wof:name":"Sharon/Roe Day Care",
    "wof:placetype":"venue"
},
  "geometry": {"coordinates":[-93.12059499999999,30.431981],"type":"Point"}
}