{
  "type": "Feature",
  "properties": {
    "addr:full":"6080 Oberlin Rd Mamou LA 70554",
    "addr:housenumber":"6080",
    "addr:postcode":"70554",
    "addr:street":"Oberlin Rd",
    "iso:country":"US",
    "sg:address":"6080 Oberlin Rd",
    "sg:city":"Mamou",
    "sg:classifiers":[
        {
            "category":"Farming",
            "subcategory":"Farm",
            "type":"Manufacturing & Wholesale Goods"
        }
    ],
    "sg:phone":"+1 337 457 9551",
    "sg:postcode":"70554",
    "sg:province":"LA",
    "sg:tags":[
        "crop",
        "general"
    ],
    "wof:name":"Keith Heinen",
    "wof:placetype":"venue"
},
  "geometry": {"coordinates":[-92.55972300000001,30.579695],"type":"Point"}
}