{
  "type": "Feature",
  "properties": {
    "iso:country":"US",
    "sg:address":"925 Decatur St",
    "sg:city":"New Orleans",
    "sg:classifiers":[
        {
            "category":"Arts & Performance",
            "subcategory":"Art Gallery",
            "type":"Entertainment"
        }
    ],
    "sg:phone":"+1 504 522 3478",
    "sg:postcode":"70116",
    "sg:province":"LA",
    "wof:name":"Crabnet the",
    "wof:placetype":"venue"
},
  "geometry": {"coordinates":[-90.060997,29.9589],"type":"Point"}
}