{
  "type": "Feature",
  "properties": {
    "iso:country":"US",
    "sg:address":"6326 Memphis St",
    "sg:city":"New Orleans",
    "sg:classifiers":[
        {
            "category":"Education",
            "subcategory":"School",
            "type":"Public Place"
        }
    ],
    "sg:phone":"+1 504 482 4123",
    "sg:postcode":"70124",
    "sg:province":"LA",
    "wof:name":"St Dominic School",
    "wof:placetype":"venue"
},
  "geometry": {"coordinates":[-90.105704,30.006102],"type":"Point"}
}