{
  "type": "Feature",
  "properties": {
    "addr:full":"1010 Contractors Cir Bossier City LA 71111",
    "addr:housenumber":"1010",
    "addr:postcode":"71111",
    "addr:street":"Contractors Cir",
    "iso:country":"US",
    "sg:address":"1010 Contractors Cir",
    "sg:city":"Bossier City",
    "sg:classifiers":[
        {
            "category":"Manufacturing",
            "subcategory":"Textiles",
            "type":"Manufacturing & Wholesale Goods"
        }
    ],
    "sg:phone":"+1 318 752 9301",
    "sg:postcode":"71111",
    "sg:province":"LA",
    "sg:tags":[
        "screen",
        "printing"
    ],
    "wof:name":"Image Wear",
    "wof:placetype":"venue"
},
  "geometry": {"coordinates":[-93.72093099999999,32.531105],"type":"Point"}
}