{
  "type": "Feature",
  "properties": {
    "addr:full":"130 W 4th St Dequincy LA 70633",
    "addr:housenumber":"130",
    "addr:postcode":"70633",
    "addr:street":"W 4Th St",
    "iso:country":"US",
    "sg:address":"130 W 4th St",
    "sg:city":"Dequincy",
    "sg:classifiers":[
        {
            "category":"Local Transit",
            "type":"Transportation"
        }
    ],
    "sg:phone":"+1 337 786 2528",
    "sg:postcode":"70633",
    "sg:province":"LA",
    "sg:tags":[
        "ambulance"
    ],
    "wof:name":"Acadian Ambulance",
    "wof:placetype":"venue"
},
  "geometry": {"coordinates":[-93.437774,30.45191],"type":"Point"}
}