{
  "type": "Feature",
  "properties": {
    "iso:country":"US",
    "sg:address":"6305 W Main St",
    "sg:city":"Houma",
    "sg:classifiers":[
        {
            "category":"Retail",
            "subcategory":"Auto Repair",
            "type":"Services"
        }
    ],
    "sg:phone":"+1 985 879 1503",
    "sg:postcode":"70360",
    "sg:province":"LA",
    "sg:tags":[
        "repairing",
        "automotive",
        "automobile",
        "general"
    ],
    "wof:name":"Witty's Automotive Repair",
    "wof:placetype":"venue"
},
  "geometry": {"coordinates":[-90.751374,29.624014],"type":"Point"}
}