{
  "type": "Feature",
  "properties": {
    "iso:country":"US",
    "sg:address":"102 S Monroe St",
    "sg:city":"West Monroe",
    "sg:classifiers":[
        {
            "category":"Health Services",
            "subcategory":"Clinic",
            "type":"Services"
        }
    ],
    "sg:phone":"+1 318 329 3737",
    "sg:postcode":"71270",
    "sg:province":"LA",
    "sg:tags":[
        "home"
    ],
    "sg:website":"www.lahcg.com",
    "wof:name":"Glenwood Home Health",
    "wof:placetype":"venue"
},
  "geometry": {"coordinates":[-92.640846,32.528418],"type":"Point"}
}