{
  "type": "Feature",
  "properties": {
    "addr:full":"103 Douglas Dr Houma LA 70364",
    "addr:housenumber":"103",
    "addr:postcode":"70364",
    "addr:street":"Douglas Dr",
    "iso:country":"US",
    "sg:address":"103 Douglas Dr",
    "sg:city":"Houma",
    "sg:classifiers":[
        {
            "category":"Bars & Pubs",
            "type":"Food & Drink"
        }
    ],
    "sg:phone":"+1 985 872 5744",
    "sg:postcode":"70364",
    "sg:province":"LA",
    "sg:tags":[
        "lounge",
        "bar",
        "cocktail"
    ],
    "wof:name":"Phantom's Tavern",
    "wof:placetype":"venue"
},
  "geometry": {"coordinates":[-90.751711,29.628845],"type":"Point"}
}