{
  "type": "Feature",
  "properties": {
    "iso:country":"US",
    "sg:address":"314 Nashua Dr",
    "sg:city":"Carencro",
    "sg:classifiers":[
        {
            "category":"Restaurant",
            "type":"Food & Drink"
        }
    ],
    "sg:phone":"+1 337 886 2855",
    "sg:postcode":"70520",
    "sg:province":"LA",
    "sg:tags":[
        "eating"
    ],
    "wof:name":"Cajun Kitchen",
    "wof:placetype":"venue"
},
  "geometry": {"coordinates":[-92.074235,30.302221],"type":"Point"}
}