{
  "type": "Feature",
  "properties": {
    "iso:country":"US",
    "sg:address":"10349 Sullivan Rd",
    "sg:city":"Baton Rouge",
    "sg:classifiers":[
        {
            "category":"Professional",
            "subcategory":"Management & Consulting",
            "type":"Services"
        },
        {
            "category":"Government",
            "subcategory":"Office",
            "type":"Public Place"
        }
    ],
    "sg:phone":"+1 225 261 7382",
    "sg:postcode":"70818",
    "sg:province":"LA",
    "sg:tags":[
        "business"
    ],
    "wof:name":"Donald Ray Kennard",
    "wof:placetype":"venue"
},
  "geometry": {"coordinates":[-91.02825300000001,30.540892],"type":"Point"}
}