{
  "type": "Feature",
  "properties": {
    "iso:country":"US",
    "sg:address":"1703 Gause Blvd",
    "sg:city":"Slidell",
    "sg:classifiers":[
        {
            "category":"Food & Beverages",
            "subcategory":"Groceries & Convenience Stores",
            "type":"Retail Goods"
        }
    ],
    "sg:phone":"+1 985 646 1234",
    "sg:postcode":"70458",
    "sg:province":"LA",
    "wof:name":"Speedy G's",
    "wof:placetype":"venue"
},
  "geometry": {"coordinates":[-89.74970500000001,30.284789],"type":"Point"}
}