{
  "type": "Feature",
  "properties": {
    "iso:country":"US",
    "sg:address":"2200 4th St",
    "sg:city":"Harvey",
    "sg:classifiers":[
        {
            "category":"Restaurant",
            "type":"Food & Drink"
        }
    ],
    "sg:phone":"+1 504 227 0402",
    "sg:postcode":"70058",
    "sg:province":"LA",
    "sg:tags":[
        "eating"
    ],
    "wof:name":"Kim's Seafood",
    "wof:placetype":"venue"
},
  "geometry": {"coordinates":[-90.07708599999999,29.909345],"type":"Point"}
}