{
  "type": "Feature",
  "properties": {
    "iso:country":"US",
    "sg:address":"117 Blue Lake Dr",
    "sg:city":"Crowley",
    "sg:classifiers":[
        {
            "category":"Health Services",
            "subcategory":"Doctor",
            "type":"Services"
        }
    ],
    "sg:phone":"+1 337 783 3321",
    "sg:postcode":"70526",
    "sg:province":"LA",
    "sg:tags":[
        "dentist"
    ],
    "wof:name":"James C Richey DDS",
    "wof:placetype":"venue"
},
  "geometry": {"coordinates":[-92.38412599999999,30.230235],"type":"Point"}
}