{
  "type": "Feature",
  "properties": {
    "addr:full":"4000 Jurgens St Metairie LA 70002",
    "addr:postcode":"4000;70002",
    "addr:street":"Jurgens St",
    "iso:country":"US",
    "sg:address":"4000 Jurgens St",
    "sg:city":"Metairie",
    "sg:classifiers":[
        {
            "category":"Retail",
            "subcategory":"Auto Rental",
            "type":"Services"
        }
    ],
    "sg:phone":"+1 504 455 7755",
    "sg:postcode":"70002",
    "sg:province":"LA",
    "sg:tags":[
        "trailer",
        "utility"
    ],
    "wof:name":"T C S Enterprise Inc",
    "wof:placetype":"venue"
},
  "geometry": {"coordinates":[-90.174193,30.010843],"type":"Point"}
}