{
  "type": "Feature",
  "properties": {
    "iso:country":"US",
    "sg:address":"4344 Earhart Blvd",
    "sg:city":"New Orleans",
    "sg:classifiers":[
        {
            "category":"Manufacturing",
            "subcategory":"Building Materials",
            "type":"Manufacturing & Wholesale Goods"
        },
        {
            "category":"Home & Garden",
            "subcategory":"Furniture",
            "type":"Retail Goods"
        }
    ],
    "sg:phone":"+1 504 822 8708",
    "sg:postcode":"70125",
    "sg:province":"LA",
    "sg:tags":[
        "household",
        "mfg",
        "appliance",
        "cabinet"
    ],
    "wof:name":"Top's Woodwork & Supply Inc",
    "wof:placetype":"venue"
},
  "geometry": {"coordinates":[-90.10138499999999,29.957358],"type":"Point"}
}