{
  "type": "Feature",
  "properties": {
    "iso:country":"US",
    "sg:address":"7122 Main St",
    "sg:city":"Houma",
    "sg:classifiers":[
        {
            "category":"Retail",
            "subcategory":"Car Wash",
            "type":"Services"
        }
    ],
    "sg:phone":"+1 985 223 0075",
    "sg:postcode":"70360",
    "sg:province":"LA",
    "sg:tags":[
        "automobile",
        "detail",
        "clean"
    ],
    "wof:name":"E D Auto Detail",
    "wof:placetype":"venue"
},
  "geometry": {"coordinates":[-90.738789,29.601675],"type":"Point"}
}