{
  "type": "Feature",
  "properties": {
    "addr:full":"3420 Highway 190 Mandeville LA 70471",
    "addr:housenumber":"3420",
    "addr:postcode":"70471",
    "addr:street":"Highway 190",
    "iso:country":"US",
    "sg:address":"3420 Highway 190",
    "sg:city":"Mandeville",
    "sg:classifiers":[
        {
            "category":"Restaurant",
            "type":"Food & Drink"
        }
    ],
    "sg:menulink":"http://www.allmenus.com/la/mandeville/28766-chilis/menu/",
    "sg:phone":"+1 985 727 2771",
    "sg:postcode":"70471",
    "sg:province":"LA",
    "sg:tags":[
        "burger",
        "american",
        "sandwich",
        "tex-mex",
        "soup"
    ],
    "wof:name":"Chili's",
    "wof:placetype":"venue"
},
  "geometry": {"coordinates":[-90.085069,30.392732],"type":"Point"}
}