{
  "type": "Feature",
  "properties": {
    "iso:country":"US",
    "sg:address":"4739 Hwy 10",
    "sg:city":"Jackson",
    "sg:classifiers":[
        {
            "category":"Restaurant",
            "type":"Food & Drink"
        }
    ],
    "sg:phone":"+1 225 634 7429",
    "sg:postcode":"70748",
    "sg:province":"LA",
    "wof:name":"LA War Veterans Canteen",
    "wof:placetype":"venue"
},
  "geometry": {"coordinates":[-91.14193,30.833371],"type":"Point"}
}