{
  "type": "Feature",
  "properties": {
    "addr:full":"3935 E Texas St Bossier City LA 71111",
    "addr:housenumber":"3935",
    "addr:postcode":"71111",
    "addr:street":"E Texas St",
    "iso:country":"US",
    "sg:address":"3935 E Texas St",
    "sg:city":"Bossier City",
    "sg:classifiers":[
        {
            "category":"Manufacturing",
            "subcategory":"Buildings",
            "type":"Manufacturing & Wholesale Goods"
        }
    ],
    "sg:phone":"+1 318 741 0036",
    "sg:postcode":"71111",
    "sg:province":"LA",
    "sg:tags":[
        "prefab"
    ],
    "wof:name":"J V Holding",
    "wof:placetype":"venue"
},
  "geometry": {"coordinates":[-93.682475,32.530438],"type":"Point"}
}