{
  "type": "Feature",
  "properties": {
    "iso:country":"US",
    "sg:address":"181 Central Ave",
    "sg:city":"Reserve",
    "sg:classifiers":[
        {
            "category":"Manufacturing",
            "subcategory":"Printing",
            "type":"Manufacturing & Wholesale Goods"
        }
    ],
    "sg:phone":"+1 985 536 2435",
    "sg:postcode":"70084",
    "sg:province":"LA",
    "sg:tags":[
        "printer"
    ],
    "wof:name":"Madere's Printing Svc",
    "wof:placetype":"venue"
},
  "geometry": {"coordinates":[-90.55167299999999,30.057371],"type":"Point"}
}