{
  "type": "Feature",
  "properties": {
    "iso:country":"US",
    "sg:address":"3020 Madonna Dr",
    "sg:city":"Alexandria",
    "sg:classifiers":[
        {
            "category":"Building & Trades",
            "subcategory":"Construction",
            "type":"Services"
        }
    ],
    "sg:phone":"+1 318 443 6034",
    "sg:postcode":"71301",
    "sg:province":"LA",
    "sg:tags":[
        "painter"
    ],
    "wof:name":"A-Ok Painters Alan Skluzacek",
    "wof:placetype":"venue"
},
  "geometry": {"coordinates":[-92.472292,31.295624],"type":"Point"}
}