{
  "type": "Feature",
  "properties": {
    "addr:full":"408 Broadway St Minden LA 71055",
    "addr:housenumber":"408",
    "addr:postcode":"71055",
    "addr:street":"Broadway St",
    "iso:country":"US",
    "sg:address":"408 Broadway St",
    "sg:city":"Minden",
    "sg:classifiers":[
        {
            "category":"Professional",
            "subcategory":"Accounting & Tax Preparation",
            "type":"Services"
        }
    ],
    "sg:phone":"+1 318 371 1200",
    "sg:postcode":"71055",
    "sg:province":"LA",
    "sg:tags":[
        "return",
        "filing"
    ],
    "wof:name":"Sunbelt Credit",
    "wof:placetype":"venue"
},
  "geometry": {"coordinates":[-93.287493,32.614095],"type":"Point"}
}