{
  "type": "Feature",
  "properties": {
    "addr:full":"630 Brashear Ave Morgan City LA 70380",
    "addr:housenumber":"630",
    "addr:postcode":"70380",
    "addr:street":"Brashear Ave",
    "iso:country":"US",
    "sg:address":"630 Brashear Ave",
    "sg:city":"Morgan City",
    "sg:classifiers":[
        {
            "category":"Restaurant",
            "type":"Food & Drink"
        }
    ],
    "sg:phone":"+1 985 384 6747",
    "sg:postcode":"70380",
    "sg:province":"LA",
    "wof:name":"Church's Chicken",
    "wof:placetype":"venue"
},
  "geometry": {"coordinates":[-91.205127,29.700241],"type":"Point"}
}