{
  "type": "Feature",
  "properties": {
    "iso:country":"US",
    "sg:address":"2126 Constance St",
    "sg:city":"New Orleans",
    "sg:classifiers":[
        {
            "category":"Social Services",
            "subcategory":"Child Care",
            "type":"Services"
        }
    ],
    "sg:phone":"+1 504 522 2725",
    "sg:postcode":"70130",
    "sg:province":"LA",
    "wof:name":"Leslie Day Care",
    "wof:placetype":"venue"
},
  "geometry": {"coordinates":[-90.07570800000001,29.928906],"type":"Point"}
}