{
  "type": "Feature",
  "properties": {
    "iso:country":"US",
    "sg:address":"425 Roussell St",
    "sg:city":"Houma",
    "sg:classifiers":[
        {
            "category":"Professional",
            "subcategory":"Computer Services",
            "type":"Services"
        }
    ],
    "sg:phone":"+1 985 223 1200",
    "sg:postcode":"70360",
    "sg:province":"LA",
    "sg:tags":[
        "internet"
    ],
    "wof:name":"Internet 8",
    "wof:placetype":"venue"
},
  "geometry": {"coordinates":[-90.721042,29.595392],"type":"Point"}
}