{
  "type": "Feature",
  "properties": {
    "iso:country":"US",
    "sg:address":"901 S 3rd St",
    "sg:city":"Leesville",
    "sg:classifiers":[
        {
            "category":"Railroad",
            "type":"Transportation"
        }
    ],
    "sg:phone":"+1 337 239 1563",
    "sg:postcode":"71446",
    "sg:province":"LA",
    "wof:name":"Kansas City Southern Railway",
    "wof:placetype":"venue"
},
  "geometry": {"coordinates":[-93.26244800000001,31.135316],"type":"Point"}
}