{
  "type": "Feature",
  "properties": {
    "addr:full":"105 Al-Ida Dr Hammond LA 70403",
    "addr:housenumber":"105",
    "addr:postcode":"70403",
    "addr:street":"Al-Ida Dr",
    "iso:country":"US",
    "sg:address":"105 Al-Ida Dr",
    "sg:city":"Hammond",
    "sg:classifiers":[
        {
            "category":"Personal",
            "subcategory":"Beauty Salon",
            "type":"Services"
        }
    ],
    "sg:phone":"+1 985 340 0097",
    "sg:postcode":"70403",
    "sg:province":"LA",
    "wof:name":"Highway 190 Car Care Salon",
    "wof:placetype":"venue"
},
  "geometry": {"coordinates":[-90.510542,30.50425],"type":"Point"}
}