{
  "type": "Feature",
  "properties": {
    "iso:country":"US",
    "sg:address":"5005 Florida Blvd",
    "sg:city":"Baton Rouge",
    "sg:classifiers":[
        {
            "category":"Personal",
            "subcategory":"Beauty Salon",
            "type":"Services"
        }
    ],
    "sg:phone":"+1 225 927 7976",
    "sg:postcode":"70806",
    "sg:province":"LA",
    "sg:tags":[
        "manicuring"
    ],
    "wof:name":"Pretty Nails",
    "wof:placetype":"venue"
},
  "geometry": {"coordinates":[-91.13757200000001,30.451035],"type":"Point"}
}