{
  "type": "Feature",
  "properties": {
    "addr:full":"805 Royal St New Orleans LA 70116",
    "addr:housenumber":"805",
    "addr:postcode":"70116",
    "addr:street":"Royal St",
    "iso:country":"US",
    "sg:address":"805 Royal St",
    "sg:city":"New Orleans",
    "sg:classifiers":[
        {
            "category":"Shopping",
            "type":"Retail Goods"
        }
    ],
    "sg:phone":"+1 504 523 2964",
    "sg:postcode":"70116",
    "sg:province":"LA",
    "sg:tags":[
        "art",
        "gallery",
        "dealer"
    ],
    "wof:name":"Barlow Art Gallery",
    "wof:placetype":"venue"
},
  "geometry": {"coordinates":[-90.063354,29.95965],"type":"Point"}
}