{
  "type": "Feature",
  "properties": {
    "iso:country":"US",
    "sg:address":"1665 Jonesboro Rd",
    "sg:city":"Arcadia",
    "sg:classifiers":[
        {
            "category":"Personal",
            "subcategory":"Beauty Salon",
            "type":"Services"
        }
    ],
    "sg:phone":"+1 318 263 8382",
    "sg:postcode":"71001",
    "sg:province":"LA",
    "wof:name":"James Ballance Beauty Shop",
    "wof:placetype":"venue"
},
  "geometry": {"coordinates":[-92.91878800000001,32.539934],"type":"Point"}
}