{
  "type": "Feature",
  "properties": {
    "iso:country":"US",
    "sg:address":"332 E Farrel Rd",
    "sg:city":"Lafayette",
    "sg:classifiers":[
        {
            "category":"Professional",
            "subcategory":"Management & Consulting",
            "type":"Services"
        }
    ],
    "sg:phone":"+1 337 988 5758",
    "sg:postcode":"70508",
    "sg:province":"LA",
    "sg:tags":[
        "business"
    ],
    "wof:name":"Lanier Evaluation & Lrng Ctr",
    "wof:placetype":"venue"
},
  "geometry": {"coordinates":[-92.03823300000001,30.145348],"type":"Point"}
}