{
  "type": "Feature",
  "properties": {
    "iso:country":"US",
    "sg:address":"619 Baird Dr",
    "sg:city":"Baton Rouge",
    "sg:classifiers":[
        {
            "category":"Personal",
            "type":"Services"
        }
    ],
    "sg:phone":"+1 225 761 9268",
    "sg:postcode":"70808",
    "sg:province":"LA",
    "wof:name":"Knead Knot",
    "wof:placetype":"venue"
},
  "geometry": {"coordinates":[-91.12042099999999,30.385141],"type":"Point"}
}