{
  "type": "Feature",
  "properties": {
    "iso:country":"US",
    "sg:address":"633 Walker Rd",
    "sg:city":"Choudrant",
    "sg:classifiers":[
        {
            "category":"Retail",
            "subcategory":"Auto Repair",
            "type":"Services"
        }
    ],
    "sg:phone":"+1 318 768 3232",
    "sg:postcode":"71227",
    "sg:province":"LA",
    "sg:tags":[
        "repairing",
        "automobile"
    ],
    "wof:name":"Rick's Auto Repair",
    "wof:placetype":"venue"
},
  "geometry": {"coordinates":[-92.482041,32.518476],"type":"Point"}
}