{
  "type": "Feature",
  "properties": {
    "iso:country":"US",
    "sg:address":"1809 England Dr",
    "sg:city":"Alexandria",
    "sg:classifiers":[
        {
            "category":"Autos & Motor Vehicles",
            "subcategory":"Auto Supplies",
            "type":"Retail Goods"
        }
    ],
    "sg:phone":"+1 318 442 1223",
    "sg:postcode":"71303",
    "sg:province":"LA",
    "sg:tags":[
        "tire"
    ],
    "wof:name":"Southland Tires & Rims",
    "wof:placetype":"venue"
},
  "geometry": {"coordinates":[-92.482259,31.315835],"type":"Point"}
}