{
  "type": "Feature",
  "properties": {
    "addr:full":"1740 Bordeaux St New Orleans LA 70115",
    "addr:housenumber":"1740",
    "addr:postcode":"70115",
    "addr:street":"Bordeaux St",
    "iso:country":"US",
    "sg:address":"1740 Bordeaux St",
    "sg:city":"New Orleans",
    "sg:classifiers":[
        {
            "category":"Professional",
            "type":"Services"
        }
    ],
    "sg:phone":"+1 504 899 1373",
    "sg:postcode":"70115",
    "sg:province":"LA",
    "wof:name":"Voulez Vous Inc",
    "wof:placetype":"venue"
},
  "geometry": {"coordinates":[-90.10693499999999,29.927774],"type":"Point"}
}