{
  "type": "Feature",
  "properties": {
    "iso:country":"US",
    "sg:address":"826 Bee Tree St",
    "sg:city":"Westlake",
    "sg:classifiers":[
        {
            "category":"Retail",
            "subcategory":"Auto Repair",
            "type":"Services"
        }
    ],
    "sg:phone":"+1 337 494 1999",
    "sg:postcode":"70669",
    "sg:province":"LA",
    "sg:tags":[
        "repairing",
        "automobile"
    ],
    "wof:name":"B & B Svc",
    "wof:placetype":"venue"
},
  "geometry": {"coordinates":[-93.25490000000001,30.257976],"type":"Point"}
}