{
  "type": "Feature",
  "properties": {
    "addr:full":"235 N Main St Breaux Bridge LA 70517",
    "addr:housenumber":"235",
    "addr:postcode":"70517",
    "addr:street":"N Main St",
    "iso:country":"US",
    "sg:address":"235 N Main St",
    "sg:city":"Breaux Bridge",
    "sg:classifiers":[
        {
            "category":"Personal",
            "subcategory":"Barber",
            "type":"Services"
        }
    ],
    "sg:phone":"+1 337 332 1898",
    "sg:postcode":"70517",
    "sg:province":"LA",
    "sg:tags":[
        "shop"
    ],
    "wof:name":"Jim's Barber Shop",
    "wof:placetype":"venue"
},
  "geometry": {"coordinates":[-91.90071500000001,30.274473],"type":"Point"}
}