{
  "type": "Feature",
  "properties": {
    "iso:country":"US",
    "sg:address":"400 Travis St",
    "sg:city":"Shreveport",
    "sg:classifiers":[
        {
            "category":"Manufacturing",
            "subcategory":"Printing",
            "type":"Manufacturing & Wholesale Goods"
        }
    ],
    "sg:phone":"+1 318 676 8855",
    "sg:postcode":"71101",
    "sg:province":"LA",
    "sg:tags":[
        "printer"
    ],
    "wof:name":"QDM Printing",
    "wof:placetype":"venue"
},
  "geometry": {"coordinates":[-93.75053200000001,32.513689],"type":"Point"}
}