{
  "type": "Feature",
  "properties": {
    "iso:country":"US",
    "sg:address":"343 Fruge St",
    "sg:city":"Mermentau",
    "sg:classifiers":[
        {
            "category":"Railroad",
            "type":"Transportation"
        }
    ],
    "sg:phone":"+1 337 824 4202",
    "sg:postcode":"70556",
    "sg:province":"LA",
    "wof:name":"Burlington Northern Santa Fe",
    "wof:placetype":"venue"
},
  "geometry": {"coordinates":[-92.58801099999999,30.188081],"type":"Point"}
}