{
  "type": "Feature",
  "properties": {
    "iso:country":"US",
    "sg:address":"9250 Dean Rd",
    "sg:city":"Shreveport",
    "sg:classifiers":[
        {
            "category":"Real Estate",
            "subcategory":"Real Estate Operator",
            "type":"Services"
        }
    ],
    "sg:phone":"+1 318 688 7720",
    "sg:postcode":"71118",
    "sg:province":"LA",
    "sg:tags":[
        "apartment"
    ],
    "sg:website":"http://www.fairfieldmanagement.com",
    "wof:name":"Hillside Apartments",
    "wof:placetype":"venue"
},
  "geometry": {"coordinates":[-93.831873,32.39995],"type":"Point"}
}