{
  "type": "Feature",
  "properties": {
    "iso:country":"US",
    "sg:address":"13345 Woodridge Ave",
    "sg:city":"Baton Rouge",
    "sg:classifiers":[
        {
            "category":"Wholesale",
            "subcategory":"Machinery & Supplies",
            "type":"Manufacturing & Wholesale Goods"
        }
    ],
    "sg:phone":"+1 225 755 1150",
    "sg:postcode":"70809",
    "sg:province":"LA",
    "sg:tags":[
        "equipment",
        "industrial"
    ],
    "wof:name":"Radco Industrial Supply",
    "wof:placetype":"venue"
},
  "geometry": {"coordinates":[-91.036913,30.3742],"type":"Point"}
}