{
  "type": "Feature",
  "properties": {
    "iso:country":"US",
    "sg:address":"1019 8th St",
    "sg:city":"Morgan City",
    "sg:classifiers":[
        {
            "category":"Organizations",
            "subcategory":"Religious Organization",
            "type":"Services"
        }
    ],
    "sg:phone":"+1 985 384 3489",
    "sg:postcode":"70380",
    "sg:province":"LA",
    "sg:tags":[
        "church"
    ],
    "wof:name":"Church Of Christ",
    "wof:placetype":"venue"
},
  "geometry": {"coordinates":[-91.202263,29.703914],"type":"Point"}
}