{
  "type": "Feature",
  "properties": {
    "iso:country":"US",
    "sg:address":"1770 Hwy 59",
    "sg:city":"Mandeville",
    "sg:classifiers":[
        {
            "category":"Food & Beverages",
            "subcategory":"Meat & Fish",
            "type":"Retail Goods"
        }
    ],
    "sg:phone":"+1 985 624 8552",
    "sg:postcode":"70448",
    "sg:province":"LA",
    "sg:tags":[
        "seafood"
    ],
    "wof:name":"Mandeville Seafood",
    "wof:placetype":"venue"
},
  "geometry": {"coordinates":[-90.054333,30.375511],"type":"Point"}
}