{
  "type": "Feature",
  "properties": {
    "iso:country":"US",
    "sg:address":"700 Dublin St",
    "sg:city":"New Orleans",
    "sg:classifiers":[
        {
            "category":"Real Estate",
            "subcategory":"Real Estate Agent",
            "type":"Services"
        }
    ],
    "sg:phone":"+1 504 862 0100",
    "sg:postcode":"70118",
    "sg:province":"LA",
    "wof:name":"Keller Williams Realtors",
    "wof:placetype":"venue"
},
  "geometry": {"coordinates":[-90.13368199999999,29.945235],"type":"Point"}
}