{
  "type": "Feature",
  "properties": {
    "iso:country":"US",
    "sg:address":"605 E Lasalle St",
    "sg:city":"Ville Platte",
    "sg:classifiers":[
        {
            "category":"Insurance",
            "subcategory":"Insurance Agent",
            "type":"Services"
        }
    ],
    "sg:phone":"+1 337 363 7737",
    "sg:postcode":"70586",
    "sg:province":"LA",
    "wof:name":"State Farm Insurance",
    "wof:placetype":"venue"
},
  "geometry": {"coordinates":[-92.267038,30.68757],"type":"Point"}
}