{
  "type": "Feature",
  "properties": {
    "addr:full":"8549 United Plaza Blvd Baton Rouge LA 70809",
    "addr:housenumber":"8549",
    "addr:postcode":"70809",
    "addr:street":"United Plaza Blvd",
    "iso:country":"US",
    "sg:address":"8549 United Plaza Blvd",
    "sg:city":"Baton Rouge",
    "sg:classifiers":[
        {
            "category":"Restaurant",
            "type":"Food & Drink"
        }
    ],
    "sg:phone":"+1 225 927 1072",
    "sg:postcode":"70809",
    "sg:province":"LA",
    "wof:name":"Subway Sandwiches & Salads",
    "wof:placetype":"venue"
},
  "geometry": {"coordinates":[-91.09587000000001,30.409558],"type":"Point"}
}