{
  "type": "Feature",
  "properties": {
    "iso:country":"US",
    "sg:address":"2621 Timber Ln",
    "sg:city":"Lake Charles",
    "sg:classifiers":[
        {
            "category":"Retail",
            "subcategory":"Repair Shop",
            "type":"Services"
        }
    ],
    "sg:phone":"+1 337 478 3007",
    "sg:postcode":"70605",
    "sg:province":"LA",
    "sg:tags":[
        "sharpening",
        "tool",
        "saw",
        "hand"
    ],
    "wof:name":"Saw Thibson Shop",
    "wof:placetype":"venue"
},
  "geometry": {"coordinates":[-93.26366899999999,30.18701],"type":"Point"}
}