{
  "type": "Feature",
  "properties": {
    "iso:country":"US",
    "sg:address":"205 Edenborn St",
    "sg:city":"Campti",
    "sg:classifiers":[
        {
            "category":"Wholesale",
            "subcategory":"Construction Materials",
            "type":"Manufacturing & Wholesale Goods"
        }
    ],
    "sg:phone":"+1 318 476 2299",
    "sg:postcode":"71411",
    "sg:province":"LA",
    "sg:tags":[
        "timberland",
        "company",
        "timber"
    ],
    "wof:name":"Young Estate",
    "wof:placetype":"venue"
},
  "geometry": {"coordinates":[-93.11511900000001,31.8893],"type":"Point"}
}