{
  "type": "Feature",
  "properties": {
    "iso:country":"US",
    "sg:address":"1521 Netherlin Dr",
    "sg:city":"Pineville",
    "sg:classifiers":[
        {
            "category":"Professional",
            "type":"Services"
        }
    ],
    "sg:phone":"+1 318 640 0696",
    "sg:postcode":"71360",
    "sg:province":"LA",
    "sg:tags":[
        "establishment"
    ],
    "wof:name":"Directions Of Louisiana",
    "wof:placetype":"venue"
},
  "geometry": {"coordinates":[-92.440855,31.397317],"type":"Point"}
}