{
  "type": "Feature",
  "properties": {
    "iso:country":"US",
    "sg:address":"1447 Hwy 20",
    "sg:city":"Thibodaux",
    "sg:classifiers":[
        {
            "category":"Shopping",
            "subcategory":"Department Store",
            "type":"Retail Goods"
        }
    ],
    "sg:phone":"+1 985 633 8682",
    "sg:postcode":"70301",
    "sg:province":"LA",
    "sg:tags":[
        "shop"
    ],
    "wof:name":"Dollar General",
    "wof:placetype":"venue"
},
  "geometry": {"coordinates":[-90.737044,29.896413],"type":"Point"}
}