{
  "type": "Feature",
  "properties": {
    "iso:country":"US",
    "sg:address":"326 Marrero Rd",
    "sg:city":"Marrero",
    "sg:classifiers":[
        {
            "category":"Wholesale",
            "subcategory":"Construction Materials",
            "type":"Manufacturing & Wholesale Goods"
        }
    ],
    "sg:phone":"+1 504 340 2300",
    "sg:postcode":"70072",
    "sg:province":"LA",
    "sg:tags":[
        "fence"
    ],
    "wof:name":"Automated Gate Div",
    "wof:placetype":"venue"
},
  "geometry": {"coordinates":[-90.109611,29.89921],"type":"Point"}
}