{
  "type": "Feature",
  "properties": {
    "addr:full":"1143 Aberdeen Dr Harvey LA 70058",
    "addr:housenumber":"1143",
    "addr:postcode":"70058",
    "addr:street":"Aberdeen Dr",
    "iso:country":"US",
    "sg:address":"1143 Aberdeen Dr",
    "sg:city":"Harvey",
    "sg:classifiers":[
        {
            "category":"Building & Trades",
            "subcategory":"Cleaning & Sanitation",
            "type":"Services"
        }
    ],
    "sg:phone":"+1 504 368 0422",
    "sg:postcode":"70058",
    "sg:province":"LA",
    "sg:tags":[
        "house"
    ],
    "wof:name":"It's All About You",
    "wof:placetype":"venue"
},
  "geometry": {"coordinates":[-90.069131,29.895609],"type":"Point"}
}