{
  "type": "Feature",
  "properties": {
    "addr:full":"148 Schexnayder Rd Palmetto LA 71358",
    "addr:housenumber":"148",
    "addr:postcode":"71358",
    "addr:street":"Schexnayder Rd",
    "iso:country":"US",
    "sg:address":"148 Schexnayder Rd",
    "sg:city":"Palmetto",
    "sg:phone":"+1 337 623 4708",
    "sg:postcode":"71358",
    "sg:province":"LA",
    "sg:tags":[
        "farm",
        "beet"
    ],
    "wof:name":"Troy Leger",
    "wof:placetype":"venue"
},
  "geometry": {"coordinates":[-91.86180299999999,30.755163],"type":"Point"}
}