{
  "type": "Feature",
  "properties": {
    "iso:country":"US",
    "sg:address":"394 Bridges Rd",
    "sg:city":"Downsville",
    "sg:classifiers":[
        {
            "category":"Building & Trades",
            "subcategory":"Construction",
            "type":"Services"
        }
    ],
    "sg:phone":"+1 318 982 5500",
    "sg:postcode":"71234",
    "sg:province":"LA",
    "sg:tags":[
        "crop",
        "contractor"
    ],
    "wof:name":"3 B Farms",
    "wof:placetype":"venue"
},
  "geometry": {"coordinates":[-92.31171500000001,32.644613],"type":"Point"}
}