{
  "type": "Feature",
  "properties": {
    "addr:full":"408 3rd St Oberlin LA 70655",
    "addr:housenumber":"408",
    "addr:postcode":"70655",
    "addr:street":"3Rd St",
    "iso:country":"US",
    "sg:address":"408 3rd St",
    "sg:city":"Oberlin",
    "sg:classifiers":[
        {
            "category":"Home & Garden",
            "subcategory":"Building Materials",
            "type":"Retail Goods"
        }
    ],
    "sg:phone":"+1 337 639 2473",
    "sg:postcode":"70655",
    "sg:province":"LA",
    "sg:tags":[
        "lumber"
    ],
    "wof:name":"Oberlin Building Supplies",
    "wof:placetype":"venue"
},
  "geometry": {"coordinates":[-92.76477300000001,30.61436],"type":"Point"}
}