{
  "type": "Feature",
  "properties": {
    "iso:country":"US",
    "sg:address":"111 Centerville St NE",
    "sg:city":"Denham Springs",
    "sg:classifiers":[
        {
            "category":"Wholesale",
            "subcategory":"Sporting Goods",
            "type":"Manufacturing & Wholesale Goods"
        }
    ],
    "sg:phone":"+1 225 664 0900",
    "sg:postcode":"70726",
    "sg:province":"LA",
    "wof:name":"Raas Racing",
    "wof:placetype":"venue"
},
  "geometry": {"coordinates":[-90.956019,30.487014],"type":"Point"}
}