{
  "type": "Feature",
  "properties": {
    "iso:country":"US",
    "sg:address":"2013 S Claiborne Ave",
    "sg:city":"New Orleans",
    "sg:classifiers":[
        {
            "category":"Food & Beverages",
            "subcategory":"Groceries & Convenience Stores",
            "type":"Retail Goods"
        }
    ],
    "sg:phone":"+1 504 522 6328",
    "sg:postcode":"70125",
    "sg:province":"LA",
    "sg:tags":[
        "grocer"
    ],
    "wof:name":"Wagner's",
    "wof:placetype":"venue"
},
  "geometry": {"coordinates":[-90.08885600000001,29.946317],"type":"Point"}
}