{
  "type": "Feature",
  "properties": {
    "iso:country":"US",
    "sg:address":"3100 Royal St",
    "sg:city":"New Orleans",
    "sg:classifiers":[
        {
            "category":"Building & Trades",
            "subcategory":"Plumbing",
            "type":"Services"
        }
    ],
    "sg:phone":"+1 504 945 5160",
    "sg:postcode":"70117",
    "sg:province":"LA",
    "sg:tags":[
        "contractor"
    ],
    "wof:name":"Phils Sheet Metal",
    "wof:placetype":"venue"
},
  "geometry": {"coordinates":[-90.04369199999999,29.963086],"type":"Point"}
}