{
  "type": "Feature",
  "properties": {
    "iso:country":"US",
    "sg:address":"35927 State Rte 23",
    "sg:city":"Buras",
    "sg:classifiers":[
        {
            "category":"Restaurant",
            "type":"Food & Drink"
        }
    ],
    "sg:phone":"+1 985 657 9323",
    "sg:postcode":"70041",
    "sg:province":"LA",
    "wof:name":"River Baron's Bar & Grill",
    "wof:placetype":"venue"
},
  "geometry": {"coordinates":[-89.522299,29.34556],"type":"Point"}
}