{
  "type": "Feature",
  "properties": {
    "addr:full":"60288 Dollar Rd Angie LA 70426",
    "addr:postcode":"60288;70426",
    "addr:street":"Dollar Rd",
    "iso:country":"US",
    "sg:address":"60288 Dollar Rd",
    "sg:city":"Angie",
    "sg:classifiers":[
        {
            "category":"Building & Trades",
            "subcategory":"Pest Control",
            "type":"Services"
        }
    ],
    "sg:phone":"+1 985 730 4385",
    "sg:postcode":"70426",
    "sg:province":"LA",
    "wof:name":"Zap A Bug",
    "wof:placetype":"venue"
},
  "geometry": {"coordinates":[-89.882823,30.88215],"type":"Point"}
}