{
  "type": "Feature",
  "properties": {
    "addr:full":"124 Church St Minden LA 71055",
    "addr:housenumber":"124",
    "addr:postcode":"71055",
    "addr:street":"Church St",
    "iso:country":"US",
    "sg:address":"124 Church St",
    "sg:city":"Minden",
    "sg:classifiers":[
        {
            "category":"Organizations",
            "subcategory":"Religious Organization",
            "type":"Services"
        }
    ],
    "sg:phone":"+1 318 377 7079",
    "sg:postcode":"71055",
    "sg:province":"LA",
    "sg:tags":[
        "church"
    ],
    "wof:name":"Heflin Methodist Church",
    "wof:placetype":"venue"
},
  "geometry": {"coordinates":[-93.275812,32.612353],"type":"Point"}
}