{
  "type": "Feature",
  "properties": {
    "iso:country":"US",
    "sg:address":"1201 Canal St",
    "sg:city":"New Orleans",
    "sg:classifiers":[
        {
            "category":"Real Estate",
            "subcategory":"Real Estate Operator",
            "type":"Services"
        }
    ],
    "sg:phone":"+1 504 525 0333",
    "sg:postcode":"70112",
    "sg:province":"LA",
    "sg:tags":[
        "condominium"
    ],
    "wof:name":"1201 Canal St Condominiums",
    "wof:placetype":"venue"
},
  "geometry": {"coordinates":[-90.074067,29.956332],"type":"Point"}
}