{
  "type": "Feature",
  "properties": {
    "iso:country":"US",
    "sg:address":"30082 Hwy 21",
    "sg:city":"Angie",
    "sg:classifiers":[
        {
            "category":"Freight",
            "type":"Transportation"
        }
    ],
    "sg:phone":"+1 985 986 2648",
    "sg:postcode":"70426",
    "sg:province":"LA",
    "sg:tags":[
        "commercial",
        "storage"
    ],
    "wof:name":"Pioneer Food Store & Mini",
    "wof:placetype":"venue"
},
  "geometry": {"coordinates":[-89.81222,30.959059],"type":"Point"}
}