{
  "type": "Feature",
  "properties": {
    "iso:country":"US",
    "sg:address":"11715 Bricksome Ave",
    "sg:city":"Baton Rouge",
    "sg:classifiers":[
        {
            "category":"Wholesale",
            "subcategory":"Office Equipment",
            "type":"Manufacturing & Wholesale Goods"
        }
    ],
    "sg:phone":"+1 225 291 8777",
    "sg:postcode":"70816",
    "sg:province":"LA",
    "sg:tags":[
        "credit"
    ],
    "wof:name":"Global Merchant Solutions",
    "wof:placetype":"venue"
},
  "geometry": {"coordinates":[-91.052109,30.426388],"type":"Point"}
}