{
  "type": "Feature",
  "properties": {
    "addr:full":"3505 Lee St Alexandria LA 71302",
    "addr:housenumber":"3505",
    "addr:postcode":"71302",
    "addr:street":"Lee St",
    "iso:country":"US",
    "sg:address":"3505 Lee St",
    "sg:city":"Alexandria",
    "sg:classifiers":[
        {
            "category":"Autos & Motor Vehicles",
            "subcategory":"Auto Supplies",
            "type":"Retail Goods"
        }
    ],
    "sg:phone":"+1 318 561 0332",
    "sg:postcode":"71302",
    "sg:province":"LA",
    "sg:tags":[
        "automobile",
        "parts"
    ],
    "sg:website":"www.autozone.com",
    "wof:name":"Autozone",
    "wof:placetype":"venue"
},
  "geometry": {"coordinates":[-92.44586200000001,31.275149],"type":"Point"}
}