{
  "type": "Feature",
  "properties": {
    "iso:country":"US",
    "sg:address":"13880 Hayne Blvd",
    "sg:city":"New Orleans",
    "sg:classifiers":[
        {
            "category":"Social Services",
            "subcategory":"Child Care",
            "type":"Services"
        }
    ],
    "sg:phone":"+1 504 240 2099",
    "sg:postcode":"70128",
    "sg:province":"LA",
    "wof:name":"Mothers Little Angels",
    "wof:placetype":"venue"
},
  "geometry": {"coordinates":[-89.95415300000001,30.067485],"type":"Point"}
}