{
  "type": "Feature",
  "properties": {
    "addr:full":"1338 Gause Blvd Slidell LA 70458",
    "addr:housenumber":"1338",
    "addr:postcode":"70458",
    "addr:street":"Gause Blvd",
    "iso:country":"US",
    "sg:address":"1338 Gause Blvd",
    "sg:city":"Slidell",
    "sg:classifiers":[
        {
            "category":"Personal",
            "type":"Services"
        }
    ],
    "sg:phone":"+1 985 641 4158",
    "sg:postcode":"70458",
    "sg:province":"LA",
    "sg:tags":[
        "credit",
        "debt",
        "counseling"
    ],
    "wof:name":"Consumer Credit Counseling Svc",
    "wof:placetype":"venue"
},
  "geometry": {"coordinates":[-89.764093,30.284863],"type":"Point"}
}