{
  "type": "Feature",
  "properties": {
    "iso:country":"US",
    "sg:address":"1087 Oscar Guidry Rd",
    "sg:city":"Saint Martinville",
    "sg:classifiers":[
        {
            "category":"Professional",
            "subcategory":"Business Services",
            "type":"Services"
        }
    ],
    "sg:phone":"+1 337 228 2912",
    "sg:postcode":"70582",
    "sg:province":"LA",
    "sg:tags":[
        "seafood"
    ],
    "wof:name":"Seafood International",
    "wof:placetype":"venue"
},
  "geometry": {"coordinates":[-91.814256,30.233025],"type":"Point"}
}