{
  "type": "Feature",
  "properties": {
    "addr:full":"1201 Capitol Access Rd Baton Rouge LA 70802",
    "addr:housenumber":"1201",
    "addr:postcode":"70802",
    "addr:street":"Capitol Access Rd",
    "iso:country":"US",
    "sg:address":"1201 Capitol Access Rd",
    "sg:city":"Baton Rouge",
    "sg:classifiers":[
        {
            "category":"Government",
            "subcategory":"Office",
            "type":"Public Place"
        }
    ],
    "sg:phone":"+1 225 342 8274",
    "sg:postcode":"70802",
    "sg:province":"LA",
    "sg:tags":[
        "state"
    ],
    "wof:name":"Personnel Management Div",
    "wof:placetype":"venue"
},
  "geometry": {"coordinates":[-91.17763600000001,30.45825],"type":"Point"}
}