{
  "type": "Feature",
  "properties": {
    "iso:country":"US",
    "sg:address":"1833 Sterkx Rd",
    "sg:city":"Alexandria",
    "sg:classifiers":[
        {
            "category":"Building & Trades",
            "subcategory":"Construction",
            "type":"Services"
        }
    ],
    "sg:phone":"+1 318 442 3392",
    "sg:postcode":"71301",
    "sg:province":"LA",
    "sg:tags":[
        "general",
        "contractor"
    ],
    "wof:name":"Westerchil Construction Co",
    "wof:placetype":"venue"
},
  "geometry": {"coordinates":[-92.448939,31.276815],"type":"Point"}
}