{
  "type": "Feature",
  "properties": {
    "addr:full":"1003 Wendy Dr St Martinville LA 70582",
    "addr:housenumber":"1003",
    "addr:postcode":"70582",
    "addr:street":"Wendy Dr St",
    "iso:country":"US",
    "sg:address":"1003 Wendy Dr",
    "sg:city":"St Martinville",
    "sg:classifiers":[
        {
            "category":"Insurance",
            "subcategory":"Hazard Insurance",
            "type":"Services"
        }
    ],
    "sg:phone":"+1 337 394 9487",
    "sg:postcode":"70582",
    "sg:province":"LA",
    "sg:tags":[
        "bond"
    ],
    "wof:name":"St Martin Bonding Co",
    "wof:placetype":"venue"
},
  "geometry": {"coordinates":[-91.837143,30.103261],"type":"Point"}
}