{
  "type": "Feature",
  "properties": {
    "addr:full":"3515 N I- 10 Svc Rd W Metairie LA 70002",
    "addr:housenumber":"3515;10",
    "addr:postcode":"70002",
    "addr:street":"N I;Svc Rd W",
    "iso:country":"US",
    "sg:address":"3515 N I- 10 Svc Rd W",
    "sg:city":"Metairie",
    "sg:classifiers":[
        {
            "category":"Organizations",
            "subcategory":"Labor Organization",
            "type":"Services"
        }
    ],
    "sg:phone":"+1 504 885 3054",
    "sg:postcode":"70002",
    "sg:province":"LA",
    "wof:name":"Plumbers Marine & Steamfitters",
    "wof:placetype":"venue"
},
  "geometry": {"coordinates":[-90.159767,29.998058],"type":"Point"}
}