{
  "type": "Feature",
  "properties": {
    "iso:country":"US",
    "sg:address":"2041 Hospital Rd",
    "sg:city":"New Roads",
    "sg:classifiers":[
        {
            "category":"Wholesale",
            "subcategory":"Chemicals & Plastics",
            "type":"Manufacturing & Wholesale Goods"
        }
    ],
    "sg:phone":"+1 225 638 7056",
    "sg:postcode":"70760",
    "sg:province":"LA",
    "wof:name":"Helena Chemical Co",
    "wof:placetype":"venue"
},
  "geometry": {"coordinates":[-91.464562,30.685263],"type":"Point"}
}