{
  "type": "Feature",
  "properties": {
    "iso:country":"US",
    "sg:address":"2316 Dauphine St",
    "sg:city":"New Orleans",
    "sg:classifiers":[
        {
            "category":"Travel",
            "subcategory":"Bed & Breakfast",
            "type":"Entertainment"
        }
    ],
    "sg:phone":"+1 504 948 2217",
    "sg:postcode":"70117",
    "sg:province":"LA",
    "sg:website":"www.ladauphine.com",
    "wof:name":"La Dauphine B&B",
    "wof:placetype":"venue"
},
  "geometry": {"coordinates":[-90.054821,29.965672],"type":"Point"}
}