{
  "type": "Feature",
  "properties": {
    "iso:country":"US",
    "sg:address":"1200 S Clearview Pkwy",
    "sg:city":"New Orleans",
    "sg:classifiers":[
        {
            "category":"Wholesale",
            "subcategory":"Machinery & Supplies",
            "type":"Manufacturing & Wholesale Goods"
        }
    ],
    "sg:phone":"+1 504 734 0463",
    "sg:postcode":"70123",
    "sg:province":"LA",
    "sg:tags":[
        "salon",
        "beauty"
    ],
    "wof:name":"Sally Beauty Supply",
    "wof:placetype":"venue"
},
  "geometry": {"coordinates":[-90.18474000000001,29.962441],"type":"Point"}
}