{
  "type": "Feature",
  "properties": {
    "iso:country":"US",
    "sg:address":"6135 Fairfield Ave",
    "sg:city":"Shreveport",
    "sg:classifiers":[
        {
            "category":"Health Services",
            "subcategory":"Medical Lab",
            "type":"Services"
        }
    ],
    "sg:phone":"+1 318 868 9779",
    "sg:postcode":"71106",
    "sg:province":"LA",
    "sg:tags":[
        "resonance",
        "magnetic",
        "imaging"
    ],
    "sg:website":"www.ibtcorp.net",
    "wof:name":"Integrated Business Techs",
    "wof:placetype":"venue"
},
  "geometry": {"coordinates":[-93.75017800000001,32.449333],"type":"Point"}
}