{
  "type": "Feature",
  "properties": {
    "iso:country":"US",
    "sg:address":"105 E Oak St",
    "sg:city":"Amite",
    "sg:classifiers":[
        {
            "category":"Banks & Credit Unions",
            "subcategory":"Bank",
            "type":"Services"
        }
    ],
    "sg:phone":"+1 985 748 5949",
    "sg:postcode":"70422",
    "sg:province":"LA",
    "sg:tags":[
        "financing"
    ],
    "wof:name":"Advantage Financial Svc",
    "wof:placetype":"venue"
},
  "geometry": {"coordinates":[-90.508247,30.726738],"type":"Point"}
}