{
  "type": "Feature",
  "properties": {
    "iso:country":"US",
    "sg:address":"5940 Cameron St",
    "sg:city":"Scott",
    "sg:classifiers":[
        {
            "category":"Manufacturing",
            "subcategory":"Leather Goods",
            "type":"Manufacturing & Wholesale Goods"
        }
    ],
    "sg:phone":"+1 337 234 8233",
    "sg:postcode":"70583",
    "sg:province":"LA",
    "wof:name":"Leather Station Llc",
    "wof:placetype":"venue"
},
  "geometry": {"coordinates":[-92.096362,30.233663],"type":"Point"}
}