{
  "type": "Feature",
  "properties": {
    "iso:country":"US",
    "sg:address":"7777 Bluebonnet Blvd",
    "sg:city":"Baton Rouge",
    "sg:classifiers":[
        {
            "category":"Coffee & Tea",
            "type":"Food & Drink"
        }
    ],
    "sg:menulink":"http://www.allmenus.com/la/baton-rouge/113634-starbucks-coffee/menu/",
    "sg:phone":"+1 225 766 2784",
    "sg:postcode":"70810",
    "sg:province":"LA",
    "sg:tags":[
        "american"
    ],
    "wof:name":"Starbucks Coffee",
    "wof:placetype":"venue"
},
  "geometry": {"coordinates":[-91.097759,30.379261],"type":"Point"}
}