{
  "type": "Feature",
  "properties": {
    "iso:country":"US",
    "sg:address":"9282 Scotland Ave",
    "sg:city":"Baton Rouge",
    "sg:classifiers":[
        {
            "category":"Health Services",
            "subcategory":"Doctor",
            "type":"Services"
        }
    ],
    "sg:phone":"+1 225 775 4640",
    "sg:postcode":"70807",
    "sg:province":"LA",
    "sg:tags":[
        "dentist"
    ],
    "wof:name":"Joseph M Dyer DDS",
    "wof:placetype":"venue"
},
  "geometry": {"coordinates":[-91.179129,30.531114],"type":"Point"}
}