{
  "type": "Feature",
  "properties": {
    "addr:full":"1300 W Landry St Opelousas LA 70570",
    "addr:housenumber":"1300",
    "addr:postcode":"70570",
    "addr:street":"W Landry St",
    "iso:country":"US",
    "sg:address":"1300 W Landry St",
    "sg:city":"Opelousas",
    "sg:classifiers":[
        {
            "category":"Building & Trades",
            "subcategory":"Equipment Rental",
            "type":"Services"
        }
    ],
    "sg:phone":"+1 337 948 7711",
    "sg:postcode":"70570",
    "sg:province":"LA",
    "sg:tags":[
        "yard"
    ],
    "wof:name":"Saucier's Equipment Rental Str",
    "wof:placetype":"venue"
},
  "geometry": {"coordinates":[-92.0973,30.534847],"type":"Point"}
}