{
  "type": "Feature",
  "properties": {
    "iso:country":"US",
    "sg:address":"8127 Oak St",
    "sg:city":"New Orleans",
    "sg:classifiers":[
        {
            "category":"Shopping",
            "subcategory":"Clothing, Apparel, & Fashions",
            "type":"Retail Goods"
        }
    ],
    "sg:phone":"+1 504 866 0991",
    "sg:postcode":"70118",
    "sg:province":"LA",
    "wof:name":"Beatrice Shop Inc",
    "wof:placetype":"venue"
},
  "geometry": {"coordinates":[-90.130437,29.947935],"type":"Point"}
}