{
  "type": "Feature",
  "properties": {
    "iso:country":"US",
    "sg:address":"58521 Meriam St",
    "sg:city":"Plaquemine",
    "sg:classifiers":[
        {
            "category":"Organizations",
            "subcategory":"Religious Organization",
            "type":"Services"
        }
    ],
    "sg:phone":"+1 225 687 2445",
    "sg:postcode":"70764",
    "sg:province":"LA",
    "sg:tags":[
        "church"
    ],
    "wof:name":"Church Of God",
    "wof:placetype":"venue"
},
  "geometry": {"coordinates":[-91.244697,30.282066],"type":"Point"}
}