{
  "type": "Feature",
  "properties": {
    "iso:country":"US",
    "sg:address":"202 Winterpark Dr",
    "sg:city":"West Monroe",
    "sg:classifiers":[
        {
            "category":"Organizations",
            "subcategory":"Religious Organization",
            "type":"Services"
        }
    ],
    "sg:phone":"+1 318 396 6671",
    "sg:postcode":"71292",
    "sg:province":"LA",
    "sg:tags":[
        "church"
    ],
    "wof:name":"Seventh-Day Adventist Church",
    "wof:placetype":"venue"
},
  "geometry": {"coordinates":[-92.230277,32.505504],"type":"Point"}
}