{
  "type": "Feature",
  "properties": {
    "addr:full":"419 W Cypress Ave Bastrop LA 71220",
    "addr:housenumber":"419",
    "addr:postcode":"71220",
    "addr:street":"W Cypress Ave",
    "iso:country":"US",
    "sg:address":"419 W Cypress Ave",
    "sg:city":"Bastrop",
    "sg:classifiers":[
        {
            "category":"Shopping",
            "subcategory":"Used Merchandise",
            "type":"Retail Goods"
        }
    ],
    "sg:phone":"+1 318 281 1967",
    "sg:postcode":"71220",
    "sg:province":"LA",
    "sg:tags":[
        "appliance"
    ],
    "wof:name":"Don's Appliance",
    "wof:placetype":"venue"
},
  "geometry": {"coordinates":[-91.919023,32.780137],"type":"Point"}
}