{
  "type": "Feature",
  "properties": {
    "addr:full":"129 Keating Dr Belle Chasse LA 70037",
    "addr:housenumber":"129",
    "addr:postcode":"70037",
    "addr:street":"Keating Dr",
    "iso:country":"US",
    "sg:address":"129 Keating Dr",
    "sg:city":"Belle Chasse",
    "sg:classifiers":[
        {
            "category":"Building & Trades",
            "subcategory":"Construction",
            "type":"Services"
        }
    ],
    "sg:phone":"+1 504 391 1815",
    "sg:postcode":"70037",
    "sg:province":"LA",
    "sg:tags":[
        "home",
        "improvement"
    ],
    "wof:name":"Home Creations Inc",
    "wof:placetype":"venue"
},
  "geometry": {"coordinates":[-89.98512100000001,29.903248],"type":"Point"}
}