{
  "type": "Feature",
  "properties": {
    "addr:full":"16204 N Gallaugher Rd Jennings LA 70546",
    "addr:housenumber":"16204",
    "addr:postcode":"70546",
    "addr:street":"N Gallaugher Rd",
    "iso:country":"US",
    "sg:address":"16204 N Gallaugher Rd",
    "sg:city":"Jennings",
    "sg:classifiers":[
        {
            "category":"Building & Trades",
            "subcategory":"Electrical",
            "type":"Services"
        }
    ],
    "sg:phone":"+1 337 824 0438",
    "sg:postcode":"70546",
    "sg:province":"LA",
    "sg:tags":[
        "electric",
        "contractor"
    ],
    "wof:name":"Crochet Electric",
    "wof:placetype":"venue"
},
  "geometry": {"coordinates":[-92.647685,30.269526],"type":"Point"}
}