{
  "type": "Feature",
  "properties": {
    "iso:country":"US",
    "sg:address":"3820 Monroe Hwy",
    "sg:city":"Pineville",
    "sg:classifiers":[
        {
            "category":"Retail",
            "subcategory":"Auto Repair",
            "type":"Services"
        }
    ],
    "sg:phone":"+1 318 641 1004",
    "sg:postcode":"71360",
    "sg:province":"LA",
    "sg:tags":[
        "repairing",
        "automobile"
    ],
    "wof:name":"Bo's Auto Repair & Svc",
    "wof:placetype":"venue"
},
  "geometry": {"coordinates":[-92.409043,31.369299],"type":"Point"}
}