{
  "type": "Feature",
  "properties": {
    "iso:country":"US",
    "sg:address":"9666 Ferry Rd",
    "sg:city":"New Roads",
    "sg:classifiers":[
        {
            "category":"Retail",
            "subcategory":"Repair Shop",
            "type":"Services"
        }
    ],
    "sg:phone":"+1 225 638 6853",
    "sg:postcode":"70760",
    "sg:province":"LA",
    "sg:tags":[
        "refinishing",
        "furniture"
    ],
    "wof:name":"John T's Furniture Restoration",
    "wof:placetype":"venue"
},
  "geometry": {"coordinates":[-91.404763,30.745913],"type":"Point"}
}