{
  "type": "Feature",
  "properties": {
    "iso:country":"US",
    "sg:address":"306 Rue Dauphine",
    "sg:city":"Eunice",
    "sg:classifiers":[
        {
            "category":"Personal",
            "subcategory":"Beauty Salon",
            "type":"Services"
        }
    ],
    "sg:phone":"+1 337 457 1975",
    "sg:postcode":"70535",
    "sg:province":"LA",
    "wof:name":"Joann's Originals",
    "wof:placetype":"venue"
},
  "geometry": {"coordinates":[-92.40746300000001,30.454278],"type":"Point"}
}