{
  "type": "Feature",
  "properties": {
    "iso:country":"US",
    "sg:address":"2515 Southside Dr",
    "sg:city":"Shreveport",
    "sg:classifiers":[
        {
            "category":"Health Services",
            "subcategory":"Doctor",
            "type":"Services"
        }
    ],
    "sg:phone":"+1 318 686 6411",
    "sg:postcode":"71118",
    "sg:province":"LA",
    "sg:tags":[
        "dentist"
    ],
    "wof:name":"Melvin De Soto Professional",
    "wof:placetype":"venue"
},
  "geometry": {"coordinates":[-93.796539,32.412883],"type":"Point"}
}