{
  "type": "Feature",
  "properties": {
    "addr:full":"220 E Stephenson St Shreveport LA 71104",
    "addr:housenumber":"220",
    "addr:postcode":"71104",
    "addr:street":"E Stephenson St",
    "iso:country":"US",
    "sg:address":"220 E Stephenson St",
    "sg:city":"Shreveport",
    "sg:classifiers":[
        {
            "category":"Organizations",
            "subcategory":"Community Association",
            "type":"Services"
        }
    ],
    "sg:phone":"+1 318 865 3306",
    "sg:postcode":"71104",
    "sg:province":"LA",
    "wof:name":"Knights Of Columbus",
    "wof:placetype":"venue"
},
  "geometry": {"coordinates":[-93.728672,32.478155],"type":"Point"}
}