{
  "type": "Feature",
  "properties": {
    "iso:country":"US",
    "sg:address":"1903 W Church St",
    "sg:city":"Hammond",
    "sg:classifiers":[
        {
            "category":"Education",
            "subcategory":"School",
            "type":"Public Place"
        }
    ],
    "sg:phone":"+1 985 345 0081",
    "sg:postcode":"70401",
    "sg:province":"LA",
    "wof:name":"Hammond Adult Education",
    "wof:placetype":"venue"
},
  "geometry": {"coordinates":[-90.482542,30.50449],"type":"Point"}
}