{
  "type": "Feature",
  "properties": {
    "addr:full":"7121 Colquitt Rd Keithville LA 71047",
    "addr:housenumber":"7121",
    "addr:postcode":"71047",
    "addr:street":"Colquitt Rd",
    "iso:country":"US",
    "sg:address":"7121 Colquitt Rd",
    "sg:city":"Keithville",
    "sg:classifiers":[
        {
            "category":"Personal",
            "subcategory":"Beauty Salon",
            "type":"Services"
        }
    ],
    "sg:phone":"+1 318 925 2177",
    "sg:postcode":"71047",
    "sg:province":"LA",
    "sg:tags":[
        "shop"
    ],
    "wof:name":"Salone Jr Blanchard",
    "wof:placetype":"venue"
},
  "geometry": {"coordinates":[-93.908314,32.3316],"type":"Point"}
}