{
  "type": "Feature",
  "properties": {
    "iso:country":"US",
    "sg:address":"369 Lamourie Rd",
    "sg:city":"Lecompte",
    "sg:classifiers":[
        {
            "category":"Professional",
            "subcategory":"Lawyer & Legal Services",
            "type":"Services"
        }
    ],
    "sg:phone":"+1 318 776 4836",
    "sg:postcode":"71346",
    "sg:province":"LA",
    "sg:tags":[
        "attorney"
    ],
    "wof:name":"Van Hoof Law Firm",
    "wof:placetype":"venue"
},
  "geometry": {"coordinates":[-92.35530199999999,31.124944],"type":"Point"}
}