{
  "type": "Feature",
  "properties": {
    "iso:country":"US",
    "sg:address":"1100 Cook St",
    "sg:city":"Gretna",
    "sg:classifiers":[
        {
            "category":"Organizations",
            "subcategory":"Community Association",
            "type":"Services"
        }
    ],
    "sg:phone":"+1 504 366 5144",
    "sg:postcode":"70053",
    "sg:province":"LA",
    "sg:tags":[
        "fraternal"
    ],
    "wof:name":"Oscar J Dunn Lodge 85 F & AM",
    "wof:placetype":"venue"
},
  "geometry": {"coordinates":[-90.045188,29.92411],"type":"Point"}
}