{
  "type": "Feature",
  "properties": {
    "iso:country":"US",
    "sg:address":"16415 Florida Blvd",
    "sg:city":"Baton Rouge",
    "sg:classifiers":[
        {
            "category":"Autos & Motor Vehicles",
            "subcategory":"Recreational Vehicle Sales",
            "type":"Retail Goods"
        }
    ],
    "sg:phone":"+1 225 272 2222",
    "sg:postcode":"70819",
    "sg:province":"LA",
    "sg:website":"www.dixierv.com",
    "wof:name":"Dixie RV Superstores",
    "wof:placetype":"venue"
},
  "geometry": {"coordinates":[-91.0073,30.467027],"type":"Point"}
}