{
  "type": "Feature",
  "properties": {
    "iso:country":"US",
    "sg:address":"511 15th St",
    "sg:city":"Lake Charles",
    "sg:classifiers":[
        {
            "category":"Retail",
            "subcategory":"Auto Repair",
            "type":"Services"
        }
    ],
    "sg:phone":"+1 337 436 7314",
    "sg:postcode":"70601",
    "sg:province":"LA",
    "sg:tags":[
        "repairing",
        "automobile"
    ],
    "wof:name":"Jensen's Alignment Svc",
    "wof:placetype":"venue"
},
  "geometry": {"coordinates":[-93.215873,30.20933],"type":"Point"}
}