{
  "type": "Feature",
  "properties": {
    "iso:country":"US",
    "sg:address":"1824 Felicity St",
    "sg:city":"New Orleans",
    "sg:classifiers":[
        {
            "category":"Shopping",
            "subcategory":"Used Merchandise",
            "type":"Retail Goods"
        }
    ],
    "sg:phone":"+1 504 523 2702",
    "sg:postcode":"70113",
    "sg:province":"LA",
    "sg:tags":[
        "antique"
    ],
    "wof:name":"Bank",
    "wof:placetype":"venue"
},
  "geometry": {"coordinates":[-90.08053200000001,29.938739],"type":"Point"}
}