{
  "type": "Feature",
  "properties": {
    "iso:country":"US",
    "sg:address":"226 W 63rd St",
    "sg:city":"Shreveport",
    "sg:classifiers":[
        {
            "category":"Professional",
            "subcategory":"Business Services",
            "type":"Services"
        }
    ],
    "sg:phone":"+1 318 219 3838",
    "sg:postcode":"71106",
    "sg:province":"LA",
    "sg:tags":[
        "event"
    ],
    "wof:name":"Events At Hand",
    "wof:placetype":"venue"
},
  "geometry": {"coordinates":[-93.760991,32.448673],"type":"Point"}
}