{
  "type": "Feature",
  "properties": {
    "iso:country":"US",
    "sg:address":"332 Bayou Liberty Rd",
    "sg:city":"Slidell",
    "sg:classifiers":[
        {
            "category":"Autos & Motor Vehicles",
            "subcategory":"Boat Sales",
            "type":"Retail Goods"
        }
    ],
    "sg:phone":"+1 985 645 0480",
    "sg:postcode":"70458",
    "sg:province":"LA",
    "sg:tags":[
        "yacht"
    ],
    "wof:name":"Mayer Yachts Sales",
    "wof:placetype":"venue"
},
  "geometry": {"coordinates":[-89.790657,30.269334],"type":"Point"}
}