{
  "type": "Feature",
  "properties": {
    "iso:country":"US",
    "sg:address":"5104 Mansfield Rd",
    "sg:city":"Shreveport",
    "sg:classifiers":[
        {
            "category":"Real Estate",
            "subcategory":"Real Estate Agent",
            "type":"Services"
        }
    ],
    "sg:phone":"+1 318 631 4582",
    "sg:postcode":"71108",
    "sg:province":"LA",
    "wof:name":"Scheen & Assoc Inc",
    "wof:placetype":"venue"
},
  "geometry": {"coordinates":[-93.776062,32.463489],"type":"Point"}
}