{
  "type": "Feature",
  "properties": {
    "addr:full":"42445 Weber City Rd Gonzales LA 70737",
    "addr:housenumber":"42445",
    "addr:postcode":"70737",
    "addr:street":"Weber City Rd",
    "iso:country":"US",
    "sg:address":"42445 Weber City Rd",
    "sg:city":"Gonzales",
    "sg:classifiers":[
        {
            "category":"Professional",
            "subcategory":"Business Services",
            "type":"Services"
        }
    ],
    "sg:phone":"+1 225 644 0619",
    "sg:postcode":"70737",
    "sg:province":"LA",
    "sg:tags":[
        "conference",
        "coordinator",
        "seminar"
    ],
    "wof:name":"Conference Central",
    "wof:placetype":"venue"
},
  "geometry": {"coordinates":[-90.889996,30.230849],"type":"Point"}
}