{
  "type": "Feature",
  "properties": {
    "iso:country":"US",
    "sg:address":"1921 Manor Heights Dr",
    "sg:city":"Marrero",
    "sg:classifiers":[
        {
            "category":"Retail",
            "subcategory":"Laundry & Dry Cleaning",
            "type":"Services"
        }
    ],
    "sg:phone":"+1 504 341 5840",
    "sg:postcode":"70072",
    "sg:province":"LA",
    "wof:name":"Trang Tailor & Alterations",
    "wof:placetype":"venue"
},
  "geometry": {"coordinates":[-90.10853400000001,29.876579],"type":"Point"}
}