{
  "type": "Feature",
  "properties": {
    "iso:country":"US",
    "sg:address":"3936 Plank Rd",
    "sg:city":"Baton Rouge",
    "sg:classifiers":[
        {
            "category":"Social Services",
            "subcategory":"Child Care",
            "type":"Services"
        }
    ],
    "sg:phone":"+1 225 355 5594",
    "sg:postcode":"70805",
    "sg:province":"LA",
    "wof:name":"Heidi & Mikey's Learning Ctr",
    "wof:placetype":"venue"
},
  "geometry": {"coordinates":[-91.157991,30.485527],"type":"Point"}
}