{
  "type": "Feature",
  "properties": {
    "iso:country":"US",
    "sg:address":"837 S Clearview Pkwy",
    "sg:city":"Jefferson",
    "sg:classifiers":[
        {
            "category":"Health Services",
            "subcategory":"Optometrist",
            "type":"Services"
        }
    ],
    "sg:phone":"+1 504 733 0406",
    "sg:postcode":"70121",
    "sg:province":"LA",
    "wof:name":"St Charles Vision Contact Lens",
    "wof:placetype":"venue"
},
  "geometry": {"coordinates":[-90.1832,29.959122],"type":"Point"}
}