{
  "type": "Feature",
  "properties": {
    "addr:full":"1706 Jackson St Alexandria LA 71301",
    "addr:housenumber":"1706",
    "addr:postcode":"71301",
    "addr:street":"Jackson St",
    "iso:country":"US",
    "sg:address":"1706 Jackson St",
    "sg:city":"Alexandria",
    "sg:classifiers":[
        {
            "category":"Personal",
            "subcategory":"Beauty Salon",
            "type":"Services"
        }
    ],
    "sg:phone":"+1 318 442 0670",
    "sg:postcode":"71301",
    "sg:province":"LA",
    "wof:name":"Hair Co",
    "wof:placetype":"venue"
},
  "geometry": {"coordinates":[-92.45657199999999,31.302948],"type":"Point"}
}