{
  "type": "Feature",
  "properties": {
    "iso:country":"US",
    "sg:address":"3655 Oneal Ln",
    "sg:city":"Baton Rouge",
    "sg:classifiers":[
        {
            "category":"Travel",
            "subcategory":"Hotels & Motels",
            "type":"Entertainment"
        }
    ],
    "sg:phone":"+1 225 751 6978",
    "sg:postcode":"70816",
    "sg:province":"LA",
    "sg:tags":[
        "operation"
    ],
    "wof:name":"Courtyard By Marriott",
    "wof:placetype":"venue"
},
  "geometry": {"coordinates":[-91.007729,30.419601],"type":"Point"}
}