{
  "type": "Feature",
  "properties": {
    "iso:country":"US",
    "sg:address":"36330 Jefferson St",
    "sg:city":"Slidell",
    "sg:classifiers":[
        {
            "category":"Building & Trades",
            "subcategory":"Plumbing",
            "type":"Services"
        }
    ],
    "sg:phone":"+1 985 781 5445",
    "sg:postcode":"70460",
    "sg:province":"LA",
    "sg:tags":[
        "conditioning",
        "air",
        "system",
        "contractor"
    ],
    "wof:name":"Air Conditioning & Heat",
    "wof:placetype":"venue"
},
  "geometry": {"coordinates":[-89.789502,30.297446],"type":"Point"}
}