{
  "type": "Feature",
  "properties": {
    "iso:country":"US",
    "sg:address":"1200 St Roch Avenue",
    "sg:city":"New Orleans",
    "sg:classifiers":[
        {
            "category":"Bars & Pubs",
            "type":"Food & Drink"
        }
    ],
    "sg:phone":"+1 504 945 0194",
    "sg:postcode":"70117",
    "sg:province":"LA",
    "wof:name":"St Roch Tavern",
    "wof:placetype":"venue"
},
  "geometry": {"coordinates":[-90.052322,29.969824],"type":"Point"}
}