{
  "type": "Feature",
  "properties": {
    "iso:country":"US",
    "sg:address":"15651 Club Deluxe Rd",
    "sg:city":"Hammond",
    "sg:classifiers":[
        {
            "category":"Organizations",
            "subcategory":"Religious Organization",
            "type":"Services"
        }
    ],
    "sg:phone":"+1 985 542 4187",
    "sg:postcode":"70403",
    "sg:province":"LA",
    "sg:tags":[
        "church"
    ],
    "wof:name":"Second Rose Hill Baptist Chr",
    "wof:placetype":"venue"
},
  "geometry": {"coordinates":[-90.45032,30.475541],"type":"Point"}
}