{
  "type": "Feature",
  "properties": {
    "iso:country":"US",
    "sg:address":"850 Kansas Ln",
    "sg:city":"Monroe",
    "sg:classifiers":[
        {
            "category":"Wholesale",
            "subcategory":"Durable Goods & Equipment",
            "type":"Manufacturing & Wholesale Goods"
        }
    ],
    "sg:phone":"+1 318 699 9100",
    "sg:postcode":"71203",
    "sg:province":"LA",
    "sg:tags":[
        "importer"
    ],
    "sg:website":"www.abs-link.com",
    "wof:name":"Allied Building Stores Inc",
    "wof:placetype":"venue"
},
  "geometry": {"coordinates":[-92.055696,32.507575],"type":"Point"}
}