{
  "type": "Feature",
  "properties": {
    "iso:country":"US",
    "sg:address":"253 Belle Terre Blvd",
    "sg:city":"La Place",
    "sg:classifiers":[
        {
            "category":"Insurance",
            "subcategory":"Insurance Agent",
            "type":"Services"
        }
    ],
    "sg:phone":"+1 985 651 9388",
    "sg:postcode":"70068",
    "sg:province":"LA",
    "sg:tags":[
        "adjuster"
    ],
    "wof:name":"Crump Southern & Assoc",
    "wof:placetype":"venue"
},
  "geometry": {"coordinates":[-90.500885,30.074845],"type":"Point"}
}