{
  "type": "Feature",
  "properties": {
    "iso:country":"US",
    "sg:address":"1064 Macon Front Rd",
    "sg:city":"Oak Grove",
    "sg:classifiers":[
        {
            "category":"Building & Trades",
            "subcategory":"Plumbing",
            "type":"Services"
        }
    ],
    "sg:phone":"+1 318 428 3822",
    "sg:postcode":"71263",
    "sg:province":"LA",
    "sg:tags":[
        "conditioning",
        "air",
        "system",
        "contractor"
    ],
    "wof:name":"Jerry's Heating & Air Cond",
    "wof:placetype":"venue"
},
  "geometry": {"coordinates":[-91.339856,32.875268],"type":"Point"}
}