{
  "type": "Feature",
  "properties": {
    "iso:country":"US",
    "sg:address":"1611 W Sale Rd",
    "sg:city":"Lake Charles",
    "sg:classifiers":[
        {
            "category":"Organizations",
            "subcategory":"Religious Organization",
            "type":"Services"
        }
    ],
    "sg:phone":"+1 337 477 3463",
    "sg:postcode":"70605",
    "sg:province":"LA",
    "sg:tags":[
        "church"
    ],
    "sg:website":"www.salestreet.org",
    "wof:name":"Sale Street Baptist Church",
    "wof:placetype":"venue"
},
  "geometry": {"coordinates":[-93.24435699999999,30.183543],"type":"Point"}
}