{
  "type": "Feature",
  "properties": {
    "addr:full":"1910 W Thomas St Hammond LA 70401",
    "addr:housenumber":"1910",
    "addr:postcode":"70401",
    "addr:street":"W Thomas St",
    "iso:country":"US",
    "sg:address":"1910 W Thomas St",
    "sg:city":"Hammond",
    "sg:classifiers":[
        {
            "category":"Shopping",
            "subcategory":"Pharmacy",
            "type":"Retail Goods"
        }
    ],
    "sg:phone":"+1 985 345 1602",
    "sg:postcode":"70401",
    "sg:province":"LA",
    "wof:name":"Walgreens",
    "wof:placetype":"venue"
},
  "geometry": {"coordinates":[-90.481174,30.500844],"type":"Point"}
}