{
  "type": "Feature",
  "properties": {
    "iso:country":"US",
    "sg:address":"9704 Royal St",
    "sg:city":"St Francisville",
    "sg:classifiers":[
        {
            "category":"Travel",
            "subcategory":"Hotels & Motels",
            "type":"Entertainment"
        }
    ],
    "sg:phone":"+1 225 635 6116",
    "sg:postcode":"70775",
    "sg:province":"LA",
    "sg:tags":[
        "breakfast",
        "accommodation",
        "bed"
    ],
    "sg:website":"www.shadetreeinn.com",
    "wof:name":"Shadetree Bed & Breakfast",
    "wof:placetype":"venue"
},
  "geometry": {"coordinates":[-91.388975,30.774563],"type":"Point"}
}