{
  "type": "Feature",
  "properties": {
    "iso:country":"US",
    "sg:address":"2100 Rue Simone",
    "sg:city":"Hammond",
    "sg:classifiers":[
        {
            "category":"Professional",
            "subcategory":"Business Services",
            "type":"Services"
        },
        {
            "category":"Real Estate",
            "subcategory":"Real Estate Services",
            "type":"Services"
        }
    ],
    "sg:phone":"+1 985 542 4422",
    "sg:postcode":"70403",
    "sg:province":"LA",
    "sg:tags":[
        "company",
        "title"
    ],
    "wof:name":"Hammond Title Co Inc",
    "wof:placetype":"venue"
},
  "geometry": {"coordinates":[-90.48385,30.488274],"type":"Point"}
}