{
  "type": "Feature",
  "properties": {
    "iso:country":"US",
    "sg:address":"3437 Masonic Dr",
    "sg:city":"Alexandria",
    "sg:classifiers":[
        {
            "category":"Shopping",
            "subcategory":"Clothing, Apparel, & Fashions",
            "type":"Retail Goods"
        }
    ],
    "sg:phone":"+1 318 443 1735",
    "sg:postcode":"71301",
    "sg:province":"LA",
    "sg:tags":[
        "t"
    ],
    "wof:name":"Airbrush LA",
    "wof:placetype":"venue"
},
  "geometry": {"coordinates":[-92.462433,31.280551],"type":"Point"}
}