{
  "type": "Feature",
  "properties": {
    "iso:country":"US",
    "sg:address":"542 S Columbia St",
    "sg:city":"Bogalusa",
    "sg:classifiers":[
        {
            "category":"Health Services",
            "subcategory":"Hospital",
            "type":"Services"
        }
    ],
    "sg:phone":"+1 985 735 9448",
    "sg:postcode":"70427",
    "sg:province":"LA",
    "sg:tags":[
        "mental"
    ],
    "wof:name":"Wenbe LLC",
    "wof:placetype":"venue"
},
  "geometry": {"coordinates":[-89.854049,30.773848],"type":"Point"}
}