{
  "type": "Feature",
  "properties": {
    "iso:country":"US",
    "sg:address":"822 Hwy 1178",
    "sg:city":"Evergreen",
    "sg:phone":"+1 318 346 7885",
    "sg:postcode":"71333",
    "sg:province":"LA",
    "sg:tags":[
        "farm",
        "soybean"
    ],
    "wof:name":"Redmon Milby Farm",
    "wof:placetype":"venue"
},
  "geometry": {"coordinates":[-92.109393,30.933687],"type":"Point"}
}