{
  "type": "Feature",
  "properties": {
    "addr:full":"1000 McKeen Pl Monroe LA 71201",
    "addr:housenumber":"1000",
    "addr:postcode":"71201",
    "addr:street":"Mckeen Pl",
    "iso:country":"US",
    "sg:address":"1000 McKeen Pl",
    "sg:city":"Monroe",
    "sg:classifiers":[
        {
            "category":"Health Services",
            "subcategory":"Nursing And Care Facility",
            "type":"Services"
        }
    ],
    "sg:phone":"+1 318 387 5300",
    "sg:postcode":"71201",
    "sg:province":"LA",
    "sg:tags":[
        "home",
        "convalescent"
    ],
    "wof:name":"Oaks",
    "wof:placetype":"venue"
},
  "geometry": {"coordinates":[-92.11985,32.52218],"type":"Point"}
}