{
  "type": "Feature",
  "properties": {
    "iso:country":"US",
    "sg:address":"1519 State Rte 182",
    "sg:city":"Morgan City",
    "sg:classifiers":[
        {
            "category":"Government",
            "subcategory":"Office",
            "type":"Public Place"
        }
    ],
    "sg:phone":"+1 985 395 4653",
    "sg:postcode":"70380",
    "sg:province":"LA",
    "wof:name":"St Mary Narcotics Div",
    "wof:placetype":"venue"
},
  "geometry": {"coordinates":[-91.271411,29.689819],"type":"Point"}
}