{
  "type": "Feature",
  "properties": {
    "addr:full":"202 Cavalier Dr Mansfield LA 71052",
    "addr:housenumber":"202",
    "addr:postcode":"71052",
    "addr:street":"Cavalier Dr",
    "iso:country":"US",
    "sg:address":"202 Cavalier Dr",
    "sg:city":"Mansfield",
    "sg:classifiers":[
        {
            "category":"Organizations",
            "subcategory":"Community Association",
            "type":"Services"
        }
    ],
    "sg:phone":"+1 318 872 1873",
    "sg:postcode":"71052",
    "sg:province":"LA",
    "sg:tags":[
        "club"
    ],
    "wof:name":"Cavalier's Men Club",
    "wof:placetype":"venue"
},
  "geometry": {"coordinates":[-93.72904,32.00544],"type":"Point"}
}