{
  "type": "Feature",
  "properties": {
    "iso:country":"US",
    "sg:address":"14514 W Main St",
    "sg:city":"Cut Off",
    "sg:classifiers":[
        {
            "category":"Professional",
            "subcategory":"Lawyer & Legal Services",
            "type":"Services"
        }
    ],
    "sg:phone":"+1 985 632 2778",
    "sg:postcode":"70345",
    "sg:province":"LA",
    "sg:tags":[
        "attorney"
    ],
    "wof:name":"Cheramie & Stentz Law Offices",
    "wof:placetype":"venue"
},
  "geometry": {"coordinates":[-90.335984,29.539636],"type":"Point"}
}