{
  "type": "Feature",
  "properties": {
    "iso:country":"US",
    "sg:address":"136 Slaughterhouse Rd",
    "sg:city":"Bunkie",
    "sg:classifiers":[
        {
            "category":"Food & Beverages",
            "subcategory":"Meat & Fish",
            "type":"Retail Goods"
        }
    ],
    "sg:phone":"+1 318 346 7201",
    "sg:postcode":"71322",
    "sg:province":"LA",
    "wof:name":"Hardy's Slaughter House",
    "wof:placetype":"venue"
},
  "geometry": {"coordinates":[-92.162813,30.953521],"type":"Point"}
}