{
  "type": "Feature",
  "properties": {
    "iso:country":"US",
    "sg:address":"238 Gabasse St",
    "sg:city":"Houma",
    "sg:classifiers":[
        {
            "category":"Real Estate",
            "subcategory":"Real Estate Agent",
            "type":"Services"
        }
    ],
    "sg:phone":"+1 985 879 1019",
    "sg:postcode":"70360",
    "sg:province":"LA",
    "wof:name":"Baker Real Estate",
    "wof:placetype":"venue"
},
  "geometry": {"coordinates":[-90.717814,29.59717],"type":"Point"}
}