{
  "type": "Feature",
  "properties": {
    "iso:country":"US",
    "sg:address":"2100 Federal Ave",
    "sg:city":"Morgan City",
    "sg:classifiers":[
        {
            "category":"Food & Beverages",
            "subcategory":"Groceries & Convenience Stores",
            "type":"Retail Goods"
        }
    ],
    "sg:phone":"+1 985 385 5758",
    "sg:postcode":"70380",
    "sg:province":"LA",
    "wof:name":"Johnny's Food Mart",
    "wof:placetype":"venue"
},
  "geometry": {"coordinates":[-91.214562,29.713178],"type":"Point"}
}