{
  "type": "Feature",
  "properties": {
    "addr:full":"4209 Pro St Shreveport LA 71109",
    "addr:housenumber":"4209",
    "addr:postcode":"71109",
    "addr:street":"Pro St",
    "iso:country":"US",
    "sg:address":"4209 Pro St",
    "sg:city":"Shreveport",
    "sg:classifiers":[
        {
            "category":"Autos & Motor Vehicles",
            "subcategory":"Auto Supplies",
            "type":"Retail Goods"
        }
    ],
    "sg:phone":"+1 318 632 0021",
    "sg:postcode":"71109",
    "sg:province":"LA",
    "sg:tags":[
        "automobile",
        "parts"
    ],
    "wof:name":"American Engine",
    "wof:placetype":"venue"
},
  "geometry": {"coordinates":[-93.813939,32.469227],"type":"Point"}
}