{
  "type": "Feature",
  "properties": {
    "addr:full":"1701 Duane St Baton Rouge LA 70802",
    "addr:housenumber":"1701",
    "addr:postcode":"70802",
    "addr:street":"Duane St",
    "iso:country":"US",
    "sg:address":"1701 Duane St",
    "sg:city":"Baton Rouge",
    "sg:classifiers":[
        {
            "category":"Real Estate",
            "subcategory":"Real Estate Agent",
            "type":"Services"
        }
    ],
    "sg:phone":"+1 225 377 2014",
    "sg:postcode":"70802",
    "sg:province":"LA",
    "sg:tags":[
        "authorities",
        "housing"
    ],
    "wof:name":"Baton Rouge Housing Authority",
    "wof:placetype":"venue"
},
  "geometry": {"coordinates":[-91.18536400000001,30.430878],"type":"Point"}
}