{
  "type": "Feature",
  "properties": {
    "addr:full":"7809 Airline Dr Metairie LA 70003",
    "addr:housenumber":"7809",
    "addr:postcode":"70003",
    "addr:street":"Airline Dr",
    "iso:country":"US",
    "sg:address":"7809 Airline Dr",
    "sg:city":"Metairie",
    "sg:classifiers":[
        {
            "category":"Building & Trades",
            "subcategory":"Construction",
            "type":"Services"
        }
    ],
    "sg:phone":"+1 504 739 9992",
    "sg:postcode":"70003",
    "sg:province":"LA",
    "sg:tags":[
        "home",
        "builder"
    ],
    "wof:name":"C Lemoine Builders",
    "wof:placetype":"venue"
},
  "geometry": {"coordinates":[-90.220603,29.978518],"type":"Point"}
}