{
  "type": "Feature",
  "properties": {
    "iso:country":"US",
    "sg:address":"201 S Bevill St",
    "sg:city":"Winnfield",
    "sg:classifiers":[
        {
            "category":"Government",
            "subcategory":"Post Office",
            "type":"Public Place"
        }
    ],
    "sg:phone":"+1 318 000 1111",
    "sg:postcode":"71483",
    "sg:province":"LA",
    "wof:name":"US Post Office",
    "wof:placetype":"venue"
},
  "geometry": {"coordinates":[-92.637547,31.925832],"type":"Point"}
}