{
  "type": "Feature",
  "properties": {
    "iso:country":"US",
    "sg:address":"323 N Columbia St",
    "sg:city":"Covington",
    "sg:classifiers":[
        {
            "category":"Shopping",
            "subcategory":"Hobbies, Toys, & Games",
            "type":"Retail Goods"
        }
    ],
    "sg:phone":"+1 985 809 6854",
    "sg:postcode":"70433",
    "sg:province":"LA",
    "sg:tags":[
        "craft",
        "supply"
    ],
    "wof:name":"Mo's Art Supply & Framing",
    "wof:placetype":"venue"
},
  "geometry": {"coordinates":[-90.09446800000001,30.475925],"type":"Point"}
}