{
  "type": "Feature",
  "properties": {
    "iso:country":"US",
    "sg:address":"117 Oak St",
    "sg:city":"Rayne",
    "sg:classifiers":[
        {
            "category":"Restaurant",
            "type":"Food & Drink"
        }
    ],
    "sg:phone":"+1 337 334 3299",
    "sg:postcode":"70578",
    "sg:province":"LA",
    "wof:name":"Smoothies 'n More",
    "wof:placetype":"venue"
},
  "geometry": {"coordinates":[-92.267871,30.247778],"type":"Point"}
}