{
  "type": "Feature",
  "properties": {
    "addr:full":"5921 Bellingham Pl Metairie LA 70003",
    "addr:postcode":"5921;70003",
    "addr:street":"Pl",
    "iso:country":"US",
    "sg:address":"5921 Bellingham Pl",
    "sg:city":"Metairie",
    "sg:classifiers":[
        {
            "category":"Home & Garden",
            "subcategory":"Building Materials",
            "type":"Retail Goods"
        }
    ],
    "sg:phone":"+1 504 818 2800",
    "sg:postcode":"70003",
    "sg:province":"LA",
    "sg:tags":[
        "windows"
    ],
    "wof:name":"Gordon Home Improvement",
    "wof:placetype":"venue"
},
  "geometry": {"coordinates":[-90.198987,29.981052],"type":"Point"}
}