{
  "type": "Feature",
  "properties": {
    "addr:full":"2 Canal St New Orleans LA 70130",
    "addr:housenumber":"2",
    "addr:postcode":"70130",
    "addr:street":"Canal St",
    "iso:country":"US",
    "sg:address":"2 Canal St",
    "sg:city":"New Orleans",
    "sg:classifiers":[
        {
            "category":"Travel",
            "subcategory":"Travel Agent",
            "type":"Entertainment"
        }
    ],
    "sg:phone":"+1 504 523 1923",
    "sg:postcode":"70130",
    "sg:province":"LA",
    "sg:tags":[
        "agency",
        "steamship"
    ],
    "wof:name":"Gulfship Maritime Inc",
    "wof:placetype":"venue"
},
  "geometry": {"coordinates":[-90.064413,29.950375],"type":"Point"}
}