{
  "type": "Feature",
  "properties": {
    "addr:full":"4942 Laine Ave New Orleans LA 70126",
    "addr:housenumber":"4942",
    "addr:postcode":"70126",
    "addr:street":"Laine Ave",
    "iso:country":"US",
    "sg:address":"4942 Laine Ave",
    "sg:city":"New Orleans",
    "sg:classifiers":[
        {
            "category":"Social Services",
            "subcategory":"Child Care",
            "type":"Services"
        }
    ],
    "sg:phone":"+1 504 242 6458",
    "sg:postcode":"70126",
    "sg:province":"LA",
    "sg:tags":[
        "day"
    ],
    "wof:name":"Christian Day Private Pre-Sch",
    "wof:placetype":"venue"
},
  "geometry": {"coordinates":[-89.990968,30.021659],"type":"Point"}
}