{
  "type": "Feature",
  "properties": {
    "iso:country":"US",
    "sg:address":"255 Hickory Ave",
    "sg:city":"New Orleans",
    "sg:classifiers":[
        {
            "category":"Professional",
            "type":"Services"
        }
    ],
    "sg:phone":"+1 504 737 0350",
    "sg:postcode":"70123",
    "sg:province":"LA",
    "sg:tags":[
        "establishment"
    ],
    "wof:name":"Kim Lord High Tech",
    "wof:placetype":"venue"
},
  "geometry": {"coordinates":[-90.194176,29.94013],"type":"Point"}
}