{
  "type": "Feature",
  "properties": {
    "iso:country":"US",
    "sg:address":"800 Metairie Rd",
    "sg:city":"Metairie",
    "sg:classifiers":[
        {
            "category":"Insurance",
            "subcategory":"Insurance Agent",
            "type":"Services"
        }
    ],
    "sg:phone":"+1 504 832 4127",
    "sg:postcode":"70005",
    "sg:province":"LA",
    "wof:name":"Ab Flynt Insurance",
    "wof:placetype":"venue"
},
  "geometry": {"coordinates":[-90.13205600000001,29.988802],"type":"Point"}
}