{
  "type": "Feature",
  "properties": {
    "addr:full":"6056 Pontchartrain Blvd New Orleans LA 70124",
    "addr:housenumber":"6056",
    "addr:postcode":"70124",
    "addr:street":"Pontchartrain Blvd",
    "iso:country":"US",
    "sg:address":"6056 Pontchartrain Blvd",
    "sg:city":"New Orleans",
    "sg:classifiers":[
        {
            "category":"Organizations",
            "subcategory":"Religious Organization",
            "type":"Services"
        }
    ],
    "sg:phone":"+1 504 488 3236",
    "sg:postcode":"70124",
    "sg:province":"LA",
    "sg:tags":[
        "church"
    ],
    "wof:name":"New Way Christian Center",
    "wof:placetype":"venue"
},
  "geometry": {"coordinates":[-90.116196,30.001279],"type":"Point"}
}