{
  "type": "Feature",
  "properties": {
    "addr:full":"199 Ebenezer Rd Haughton LA 71051",
    "addr:housenumber":"199",
    "addr:postcode":"71051",
    "addr:street":"Ebenezer Rd",
    "iso:country":"US",
    "sg:address":"199 Ebenezer Rd",
    "sg:city":"Haughton",
    "sg:classifiers":[
        {
            "category":"Organizations",
            "subcategory":"Religious Organization",
            "type":"Services"
        }
    ],
    "sg:phone":"+1 318 987 2112",
    "sg:postcode":"71051",
    "sg:province":"LA",
    "wof:name":"Ebernezer Baptist Church",
    "wof:placetype":"venue"
},
  "geometry": {"coordinates":[-93.545879,32.420663],"type":"Point"}
}