{
  "type": "Feature",
  "properties": {
    "addr:full":"3528 Montford St Jefferson LA 70121",
    "addr:postcode":"3528;70121",
    "addr:street":"Montford St",
    "iso:country":"US",
    "sg:address":"3528 Montford St",
    "sg:city":"Jefferson",
    "sg:classifiers":[
        {
            "category":"Education",
            "subcategory":"School",
            "type":"Public Place"
        }
    ],
    "sg:phone":"+1 504 836 0808",
    "sg:postcode":"70121",
    "sg:province":"LA",
    "wof:name":"Jefferson Community School",
    "wof:placetype":"venue"
},
  "geometry": {"coordinates":[-90.16192700000001,29.967853],"type":"Point"}
}