{
  "type": "Feature",
  "properties": {
    "addr:full":"7009 US Hwy 165 Columbia LA 71418",
    "addr:housenumber":"7009",
    "addr:postcode":"71418",
    "addr:street":"Us Hwy 165",
    "iso:country":"US",
    "sg:address":"7009 US Hwy 165",
    "sg:city":"Columbia",
    "sg:classifiers":[
        {
            "category":"Home & Garden",
            "subcategory":"Household Appliances",
            "type":"Retail Goods"
        }
    ],
    "sg:phone":"+1 318 649 2301",
    "sg:postcode":"71418",
    "sg:province":"LA",
    "wof:name":"Aarons Sales & Lease Ownership",
    "wof:placetype":"venue"
},
  "geometry": {"coordinates":[-92.09042599999999,32.086545],"type":"Point"}
}