{
  "type": "Feature",
  "properties": {
    "addr:full":"1000 Parkview Dr Ste 3 New Iberia LA 70563",
    "addr:housenumber":"1000",
    "addr:postcode":"70563",
    "addr:street":"Parkview Dr Ste 3",
    "iso:country":"US",
    "sg:address":"1000 Parkview Dr Ste 3",
    "sg:city":"New Iberia",
    "sg:classifiers":[
        {
            "category":"Sports & Exercise",
            "subcategory":"Gym",
            "type":"Entertainment"
        },
        {
            "category":"Arena",
            "subcategory":"Sports Club",
            "type":"Entertainment"
        }
    ],
    "sg:phone":"+1 337 367 0386",
    "sg:postcode":"70563",
    "sg:province":"LA",
    "sg:tags":[
        "martial art"
    ],
    "wof:name":"Acadiana Karate",
    "wof:placetype":"venue"
},
  "geometry": {"coordinates":[-91.803101,30.003099],"type":"Point"}
}