{
  "type": "Feature",
  "properties": {
    "addr:full":"1401 Ryan St Lake Charles LA 70601",
    "addr:housenumber":"1401",
    "addr:postcode":"70601",
    "addr:street":"Ryan St",
    "iso:country":"US",
    "sg:address":"1401 Ryan St",
    "sg:city":"Lake Charles",
    "sg:classifiers":[
        {
            "category":"Wholesale",
            "subcategory":"Construction Materials",
            "type":"Manufacturing & Wholesale Goods"
        }
    ],
    "sg:phone":"+1 337 439 7500",
    "sg:postcode":"70601",
    "sg:province":"LA",
    "sg:tags":[
        "timberland",
        "company",
        "timber"
    ],
    "wof:name":"PWK Timberland Corp",
    "wof:placetype":"venue"
},
  "geometry": {"coordinates":[-93.21902300000001,30.220266],"type":"Point"}
}