{
  "type": "Feature",
  "properties": {
    "addr:full":"2530 Tanger Blvd Gonzales LA 70737",
    "addr:housenumber":"2530",
    "addr:postcode":"70737",
    "addr:street":"Tanger Blvd Gonzales La",
    "iso:country":"US",
    "sg:address":"2530 Tanger Blvd",
    "sg:city":"Gonzales",
    "sg:classifiers":[
        {
            "category":"Restaurant",
            "type":"Food & Drink"
        }
    ],
    "sg:phone":"+1 225 647 7679",
    "sg:postcode":"70737",
    "sg:province":"LA",
    "sg:tags":[
        "shop",
        "coffee"
    ],
    "wof:name":"Starbucks",
    "wof:placetype":"venue"
},
  "geometry": {"coordinates":[-90.950537,30.211423],"type":"Point"}
}