{
  "type": "Feature",
  "properties": {
    "addr:full":"4437 Chef Menteur Hwy New Orleans LA 70126",
    "addr:housenumber":"4437",
    "addr:postcode":"70126",
    "addr:street":"Chef Menteur Hwy",
    "iso:country":"US",
    "sg:address":"4437 Chef Menteur Hwy",
    "sg:city":"New Orleans",
    "sg:classifiers":[
        {
            "category":"Shopping",
            "subcategory":"Clothing, Apparel, & Fashions",
            "type":"Retail Goods"
        }
    ],
    "sg:phone":"+1 504 283 1593",
    "sg:postcode":"70126",
    "sg:province":"LA",
    "sg:tags":[
        "furnishing"
    ],
    "wof:name":"Step N Style Fashions",
    "wof:placetype":"venue"
},
  "geometry": {"coordinates":[-90.03661200000001,30.005369],"type":"Point"}
}