{
  "type": "Feature",
  "properties": {
    "addr:full":"485 Brick St Breaux Bridge LA 70517",
    "addr:housenumber":"485",
    "addr:postcode":"70517",
    "addr:street":"Brick St;Bridge",
    "iso:country":"US",
    "sg:address":"485 Brick St",
    "sg:city":"Breaux Bridge",
    "sg:classifiers":[
        {
            "category":"Banks & Credit Unions",
            "subcategory":"Financial Services",
            "type":"Services"
        }
    ],
    "sg:phone":"+1 337 332 5960",
    "sg:postcode":"70517",
    "sg:province":"LA",
    "sg:tags":[
        "company",
        "holding"
    ],
    "wof:name":"First Bankshares-St Martin LTD",
    "wof:placetype":"venue"
},
  "geometry": {"coordinates":[-91.909509,30.274628],"type":"Point"}
}