{
  "type": "Feature",
  "properties": {
    "iso:country":"US",
    "sg:address":"2170 Oneal Ln",
    "sg:city":"Baton Rouge",
    "sg:classifiers":[
        {
            "category":"Shopping",
            "subcategory":"Department Store",
            "type":"Retail Goods"
        }
    ],
    "sg:phone":"+1 225 751 5123",
    "sg:postcode":"70816",
    "sg:province":"LA",
    "sg:tags":[
        "shop"
    ],
    "wof:name":"Dollar Tree",
    "wof:placetype":"venue"
},
  "geometry": {"coordinates":[-91.007632,30.436717],"type":"Point"}
}