{
  "type": "Feature",
  "properties": {
    "iso:country":"US",
    "sg:address":"201 S 19th St",
    "sg:city":"Baton Rouge",
    "sg:classifiers":[
        {
            "category":"Personal",
            "subcategory":"Beauty Salon",
            "type":"Services"
        }
    ],
    "sg:phone":"+1 225 381 7210",
    "sg:postcode":"70806",
    "sg:province":"LA",
    "wof:name":"Elaine's Magic Touch Hair",
    "wof:placetype":"venue"
},
  "geometry": {"coordinates":[-91.169151,30.445774],"type":"Point"}
}