{
  "type": "Feature",
  "properties": {
    "iso:country":"US",
    "sg:address":"1400 S Orange St",
    "sg:city":"Lafayette",
    "sg:classifiers":[
        {
            "category":"Education",
            "subcategory":"School",
            "type":"Public Place"
        }
    ],
    "sg:phone":"+1 337 234 2313",
    "sg:postcode":"70501",
    "sg:province":"LA",
    "wof:name":"Paul Breaux Middle School",
    "wof:placetype":"venue"
},
  "geometry": {"coordinates":[-91.996105,30.218125],"type":"Point"}
}