{
  "type": "Feature",
  "properties": {
    "iso:country":"US",
    "sg:address":"708 N 7th St",
    "sg:city":"Thibodaux",
    "sg:classifiers":[
        {
            "category":"Home & Garden",
            "subcategory":"Garden Supply",
            "type":"Retail Goods"
        }
    ],
    "sg:phone":"+1 985 447 8514",
    "sg:postcode":"70301",
    "sg:province":"LA",
    "sg:tags":[
        "lawn",
        "mower"
    ],
    "wof:name":"Tom's Bike Shop",
    "wof:placetype":"venue"
},
  "geometry": {"coordinates":[-90.82299500000001,29.801363],"type":"Point"}
}