{
  "type": "Feature",
  "properties": {
    "iso:country":"US",
    "sg:address":"4407 Fisher St",
    "sg:city":"Westlake",
    "sg:classifiers":[
        {
            "category":"Insurance",
            "subcategory":"Hazard Insurance",
            "type":"Services"
        }
    ],
    "sg:phone":"+1 337 882 8077",
    "sg:postcode":"70663",
    "sg:province":"LA",
    "sg:tags":[
        "bond"
    ],
    "wof:name":"Ms Dot's Bail Bonding",
    "wof:placetype":"venue"
},
  "geometry": {"coordinates":[-93.307665,30.245671],"type":"Point"}
}