{
  "type": "Feature",
  "properties": {
    "addr:full":"1111 Center St New Iberia LA 70560",
    "addr:housenumber":"1111",
    "addr:postcode":"70560",
    "addr:street":"Center St",
    "iso:country":"US",
    "sg:address":"1111 Center St",
    "sg:city":"New Iberia",
    "sg:classifiers":[
        {
            "category":"Building & Trades",
            "subcategory":"Electrical",
            "type":"Services"
        }
    ],
    "sg:phone":"+1 337 364 7973",
    "sg:postcode":"70560",
    "sg:province":"LA",
    "sg:tags":[
        "electric",
        "contractor"
    ],
    "wof:name":"Control Devices Inc",
    "wof:placetype":"venue"
},
  "geometry": {"coordinates":[-91.827675,29.994595],"type":"Point"}
}