{
  "type": "Feature",
  "properties": {
    "addr:full":"1223 Fancher St Vinton LA 70668",
    "addr:housenumber":"1223",
    "addr:postcode":"70668",
    "addr:street":"Fancher St",
    "iso:country":"US",
    "sg:address":"1223 Fancher St",
    "sg:city":"Vinton",
    "sg:classifiers":[
        {
            "category":"Social Services",
            "subcategory":"Adult Care",
            "type":"Services"
        }
    ],
    "sg:phone":"+1 337 589 9386",
    "sg:postcode":"70668",
    "sg:province":"LA",
    "sg:tags":[
        "home",
        "group"
    ],
    "wof:name":"Calcasiu Group Home V",
    "wof:placetype":"venue"
},
  "geometry": {"coordinates":[-93.58442700000001,30.191802],"type":"Point"}
}