{
  "type": "Feature",
  "properties": {
    "iso:country":"US",
    "sg:address":"2600 Greenwood Rd",
    "sg:city":"Shreveport",
    "sg:classifiers":[
        {
            "category":"Health Services",
            "subcategory":"Health Practitioner",
            "type":"Services"
        }
    ],
    "sg:phone":"+1 318 212 4720",
    "sg:postcode":"71103",
    "sg:province":"LA",
    "sg:tags":[
        "therapist",
        "physical"
    ],
    "sg:website":"www.wkmc.com",
    "wof:name":"Willis-Knighton Medical Ctr",
    "wof:placetype":"venue"
},
  "geometry": {"coordinates":[-93.780091,32.483385],"type":"Point"}
}