{
  "type": "Feature",
  "properties": {
    "iso:country":"US",
    "sg:address":"1026 Homestead Ave",
    "sg:city":"Metairie",
    "sg:classifiers":[
        {
            "category":"Professional",
            "subcategory":"Lawyer & Legal Services",
            "type":"Services"
        }
    ],
    "sg:phone":"+1 504 838 8568",
    "sg:postcode":"70005",
    "sg:province":"LA",
    "sg:tags":[
        "attorney"
    ],
    "wof:name":"Jeanne T Cresson",
    "wof:placetype":"venue"
},
  "geometry": {"coordinates":[-90.137727,30.00823],"type":"Point"}
}