{
  "type": "Feature",
  "properties": {
    "addr:full":"3301 Wall Blvd Terrytown LA 70056",
    "addr:housenumber":"3301",
    "addr:postcode":"70056",
    "addr:street":"Wall Blvd",
    "iso:country":"US",
    "sg:address":"3301 Wall Blvd",
    "sg:city":"Terrytown",
    "sg:classifiers":[
        {
            "category":"Government",
            "subcategory":"Fire Station",
            "type":"Public Place"
        }
    ],
    "sg:phone":"+1 504 349 5554",
    "sg:postcode":"70056",
    "sg:province":"LA",
    "sg:tags":[
        "department"
    ],
    "wof:name":"Terrytown Volunteer Fire Dept",
    "wof:placetype":"venue"
},
  "geometry": {"coordinates":[-90.03246900000001,29.864613],"type":"Point"}
}