{
  "type": "Feature",
  "properties": {
    "addr:full":"1091 Swan Ave Baton Rouge LA 70807",
    "addr:housenumber":"1091",
    "addr:postcode":"70807",
    "addr:street":"Swan Ave",
    "iso:country":"US",
    "sg:address":"1091 Swan Ave",
    "sg:city":"Baton Rouge",
    "sg:classifiers":[
        {
            "category":"Shopping",
            "subcategory":"Clothing, Apparel, & Fashions",
            "type":"Retail Goods"
        }
    ],
    "sg:phone":"+1 225 775 7542",
    "sg:postcode":"70807",
    "sg:province":"LA",
    "sg:tags":[
        "lettering"
    ],
    "wof:name":"College Sports & Urban Wear",
    "wof:placetype":"venue"
},
  "geometry": {"coordinates":[-91.18322999999999,30.523716],"type":"Point"}
}