{
  "type": "Feature",
  "properties": {
    "iso:country":"US",
    "sg:address":"5800 Coubra Dr",
    "sg:city":"Marrero",
    "sg:classifiers":[
        {
            "category":"Wholesale",
            "subcategory":"Machinery & Supplies",
            "type":"Manufacturing & Wholesale Goods"
        }
    ],
    "sg:phone":"+1 504 347 0880",
    "sg:postcode":"70072",
    "sg:province":"LA",
    "sg:tags":[
        "engine"
    ],
    "wof:name":"Delhomme Industries Inc",
    "wof:placetype":"venue"
},
  "geometry": {"coordinates":[-90.115409,29.862364],"type":"Point"}
}