{
  "type": "Feature",
  "properties": {
    "iso:country":"US",
    "sg:address":"235 Devon Rd",
    "sg:city":"La Place",
    "sg:classifiers":[
        {
            "category":"Professional",
            "subcategory":"Business Services",
            "type":"Services"
        }
    ],
    "sg:phone":"+1 985 652 2006",
    "sg:postcode":"70068",
    "sg:province":"LA",
    "wof:name":"R Waguespack",
    "wof:placetype":"venue"
},
  "geometry": {"coordinates":[-90.449888,30.059449],"type":"Point"}
}