{
  "type": "Feature",
  "properties": {
    "addr:full":"113 Arnould Blvd Lafayette LA 70506",
    "addr:housenumber":"113",
    "addr:postcode":"70506",
    "addr:street":"Arnould Blvd",
    "iso:country":"US",
    "sg:address":"113 Arnould Blvd",
    "sg:city":"Lafayette",
    "sg:classifiers":[
        {
            "category":"Shopping",
            "subcategory":"Gifts & Souvenirs",
            "type":"Retail Goods"
        }
    ],
    "sg:phone":"+1 337 984 3263",
    "sg:postcode":"70506",
    "sg:province":"LA",
    "sg:tags":[
        "shop"
    ],
    "wof:name":"Caroline & Co",
    "wof:placetype":"venue"
},
  "geometry": {"coordinates":[-92.054541,30.203325],"type":"Point"}
}