{
  "type": "Feature",
  "properties": {
    "iso:country":"US",
    "sg:address":"3012 Old Minden Rd",
    "sg:city":"Bossier City",
    "sg:classifiers":[
        {
            "category":"Education",
            "subcategory":"Special Training",
            "type":"Public Place"
        }
    ],
    "sg:phone":"+1 318 746 0750",
    "sg:postcode":"71112",
    "sg:province":"LA",
    "sg:tags":[
        "center"
    ],
    "wof:name":"V & T's Learning Ctr",
    "wof:placetype":"venue"
},
  "geometry": {"coordinates":[-93.69576000000001,32.521358],"type":"Point"}
}