{
  "type": "Feature",
  "properties": {
    "iso:country":"US",
    "sg:address":"7041 State Rte 531",
    "sg:city":"Heflin",
    "sg:classifiers":[
        {
            "category":"Education",
            "subcategory":"Library",
            "type":"Public Place"
        }
    ],
    "sg:phone":"+1 318 371 1027",
    "sg:postcode":"71039",
    "sg:province":"LA",
    "wof:name":"Webster Library",
    "wof:placetype":"venue"
},
  "geometry": {"coordinates":[-93.263999,32.456196],"type":"Point"}
}