{
  "type": "Feature",
  "properties": {
    "addr:full":"2047 E Texas St Bossier City LA 71111",
    "addr:housenumber":"2047",
    "addr:postcode":"71111",
    "addr:street":"E Texas St",
    "iso:country":"US",
    "sg:address":"2047 E Texas St",
    "sg:city":"Bossier City",
    "sg:classifiers":[
        {
            "category":"Building & Trades",
            "subcategory":"Plumbing",
            "type":"Services"
        }
    ],
    "sg:phone":"+1 318 746 7867",
    "sg:postcode":"71111",
    "sg:province":"LA",
    "sg:tags":[
        "septic"
    ],
    "wof:name":"Enviro-Vac",
    "wof:placetype":"venue"
},
  "geometry": {"coordinates":[-93.721087,32.528006],"type":"Point"}
}