{
  "type": "Feature",
  "properties": {
    "iso:country":"US",
    "sg:address":"1051 Grimmett Dr",
    "sg:city":"Shreveport",
    "sg:classifiers":[
        {
            "category":"Retail",
            "subcategory":"Auto Repair",
            "type":"Services"
        }
    ],
    "sg:phone":"+1 318 222 2383",
    "sg:postcode":"71107",
    "sg:province":"LA",
    "sg:tags":[
        "body",
        "automobile",
        "painting"
    ],
    "wof:name":"Burnom's Auto Body Repair",
    "wof:placetype":"venue"
},
  "geometry": {"coordinates":[-93.75790499999999,32.529467],"type":"Point"}
}