{
  "type": "Feature",
  "properties": {
    "iso:country":"US",
    "sg:address":"4112 Driftwood Rd",
    "sg:city":"Crowley",
    "sg:classifiers":[
        {
            "category":"Professional",
            "subcategory":"Business Services",
            "type":"Services"
        }
    ],
    "sg:phone":"+1 337 783 0835",
    "sg:postcode":"70526",
    "sg:province":"LA",
    "wof:name":"Jude Lagrange",
    "wof:placetype":"venue"
},
  "geometry": {"coordinates":[-92.344587,30.094533],"type":"Point"}
}