{
  "type": "Feature",
  "properties": {
    "addr:full":"3213 17th St Metairie LA 70002",
    "addr:housenumber":"3213",
    "addr:postcode":"70002",
    "addr:street":"17Th St",
    "iso:country":"US",
    "sg:address":"3213 17th St",
    "sg:city":"Metairie",
    "sg:classifiers":[
        {
            "category":"Shopping",
            "subcategory":"Optical Goods",
            "type":"Retail Goods"
        }
    ],
    "sg:phone":"+1 504 837 3622",
    "sg:postcode":"70002",
    "sg:province":"LA",
    "wof:name":"National Optical Warehouse",
    "wof:placetype":"venue"
},
  "geometry": {"coordinates":[-90.157854,30.009341],"type":"Point"}
}