{
  "type": "Feature",
  "properties": {
    "iso:country":"US",
    "sg:address":"3259 Chippewa St",
    "sg:city":"New Orleans",
    "sg:classifiers":[
        {
            "category":"Restaurant",
            "type":"Food & Drink"
        }
    ],
    "sg:phone":"+1 504 866 6644",
    "sg:postcode":"70115",
    "sg:province":"LA",
    "sg:tags":[
        "caterer"
    ],
    "wof:name":"Southern Hospitality Systems",
    "wof:placetype":"venue"
},
  "geometry": {"coordinates":[-90.085511,29.919689],"type":"Point"}
}