{
  "type": "Feature",
  "properties": {
    "iso:country":"US",
    "sg:address":"4205 Elm St",
    "sg:city":"Monroe",
    "sg:classifiers":[
        {
            "category":"Real Estate",
            "subcategory":"Real Estate Operator",
            "type":"Services"
        }
    ],
    "sg:phone":"+1 318 325 0907",
    "sg:postcode":"71203",
    "sg:province":"LA",
    "sg:tags":[
        "apartment"
    ],
    "wof:name":"Kingsway Apartments",
    "wof:placetype":"venue"
},
  "geometry": {"coordinates":[-92.068636,32.512051],"type":"Point"}
}