{
  "type": "Feature",
  "properties": {
    "addr:full":"8736 W Judge Perez Dr Chalmette LA 70043",
    "addr:housenumber":"8736",
    "addr:postcode":"70043",
    "addr:street":"W Judge Perez Dr Chalmette",
    "iso:country":"US",
    "sg:address":"8736 W Judge Perez Dr",
    "sg:city":"Chalmette",
    "sg:classifiers":[
        {
            "category":"Shopping",
            "subcategory":"Department Store",
            "type":"Retail Goods"
        }
    ],
    "sg:phone":"+1 504 278 4545",
    "sg:postcode":"70043",
    "sg:province":"LA",
    "sg:tags":[
        "shop"
    ],
    "wof:name":"99 Cents Always",
    "wof:placetype":"venue"
},
  "geometry": {"coordinates":[-89.97260199999999,29.950255],"type":"Point"}
}