{
  "type": "Feature",
  "properties": {
    "iso:country":"US",
    "sg:address":"309 Roselawn Blvd",
    "sg:city":"Lafayette",
    "sg:classifiers":[
        {
            "category":"Professional",
            "subcategory":"Management & Consulting",
            "type":"Services"
        }
    ],
    "sg:phone":"+1 337 984 9700",
    "sg:postcode":"70503",
    "sg:province":"LA",
    "sg:tags":[
        "business"
    ],
    "wof:name":"Womack & Assoc",
    "wof:placetype":"venue"
},
  "geometry": {"coordinates":[-92.048219,30.197038],"type":"Point"}
}