{
  "type": "Feature",
  "properties": {
    "addr:full":"119 E Church St Church Point LA 70525",
    "addr:housenumber":"119",
    "addr:postcode":"70525",
    "addr:street":"E Church St",
    "iso:country":"US",
    "sg:address":"119 E Church St",
    "sg:city":"Church Point",
    "sg:classifiers":[
        {
            "category":"Social Services",
            "subcategory":"Child Care",
            "type":"Services"
        }
    ],
    "sg:phone":"+1 337 684 5437",
    "sg:postcode":"70525",
    "sg:province":"LA",
    "wof:name":"Noah's Ark Daycare",
    "wof:placetype":"venue"
},
  "geometry": {"coordinates":[-92.21477899999999,30.406934],"type":"Point"}
}