{
  "type": "Feature",
  "properties": {
    "iso:country":"US",
    "sg:address":"125 Broad St",
    "sg:city":"Lake Charles",
    "sg:classifiers":[
        {
            "category":"Professional",
            "type":"Services"
        }
    ],
    "sg:phone":"+1 337 436 3575",
    "sg:postcode":"70601",
    "sg:province":"LA",
    "sg:tags":[
        "consultant",
        "geological"
    ],
    "wof:name":"Stanley N Warburton",
    "wof:placetype":"venue"
},
  "geometry": {"coordinates":[-93.217251,30.229536],"type":"Point"}
}