{
  "type": "Feature",
  "properties": {
    "iso:country":"US",
    "sg:address":"1011 N Causeway Blvd",
    "sg:city":"Mandeville",
    "sg:classifiers":[
        {
            "category":"Insurance",
            "subcategory":"Insurance Agent",
            "type":"Services"
        }
    ],
    "sg:phone":"+1 985 626 4497",
    "sg:postcode":"70471",
    "sg:province":"LA",
    "wof:name":"Eustis Insurance Satellite Off",
    "wof:placetype":"venue"
},
  "geometry": {"coordinates":[-90.090924,30.380479],"type":"Point"}
}