{
  "type": "Feature",
  "properties": {
    "iso:country":"US",
    "sg:address":"1820 W Pinhook Rd",
    "sg:city":"Lafayette",
    "sg:classifiers":[
        {
            "category":"Autos & Motor Vehicles",
            "subcategory":"Automobile Sales",
            "type":"Retail Goods"
        }
    ],
    "sg:phone":"+1 337 769 1539",
    "sg:postcode":"70508",
    "sg:province":"LA",
    "sg:tags":[
        "car",
        "dealer"
    ],
    "wof:name":"Cars R Us",
    "wof:placetype":"venue"
},
  "geometry": {"coordinates":[-92.015676,30.190675],"type":"Point"}
}