{
  "type": "Feature",
  "properties": {
    "iso:country":"US",
    "sg:address":"2121 Clearview Pkwy",
    "sg:city":"Metairie",
    "sg:classifiers":[
        {
            "category":"Autos & Motor Vehicles",
            "subcategory":"Automobile Sales",
            "type":"Retail Goods"
        }
    ],
    "sg:phone":"+1 504 455 6666",
    "sg:postcode":"70001",
    "sg:province":"LA",
    "sg:tags":[
        "car",
        "dealer"
    ],
    "sg:website":"www.crownbuickgmc.com",
    "wof:name":"Crown Buick GMC Truck Inc",
    "wof:placetype":"venue"
},
  "geometry": {"coordinates":[-90.181313,29.992974],"type":"Point"}
}