{
  "type": "Feature",
  "properties": {
    "iso:country":"US",
    "sg:address":"5083 Radcliff St",
    "sg:city":"Marrero",
    "sg:classifiers":[
        {
            "category":"Building & Trades",
            "subcategory":"Construction",
            "type":"Services"
        }
    ],
    "sg:phone":"+1 504 341 1698",
    "sg:postcode":"70072",
    "sg:province":"LA",
    "sg:tags":[
        "house"
    ],
    "wof:name":"Kents Int/EXT Construction",
    "wof:placetype":"venue"
},
  "geometry": {"coordinates":[-90.11863,29.852215],"type":"Point"}
}