{
  "type": "Feature",
  "properties": {
    "iso:country":"US",
    "sg:address":"1202 Johnson St",
    "sg:city":"Franklinton",
    "sg:classifiers":[
        {
            "category":"Building & Trades",
            "subcategory":"Electrical",
            "type":"Services"
        }
    ],
    "sg:phone":"+1 985 839 6419",
    "sg:postcode":"70438",
    "sg:province":"LA",
    "sg:tags":[
        "electrical",
        "contractor"
    ],
    "wof:name":"Fair City Electric",
    "wof:placetype":"venue"
},
  "geometry": {"coordinates":[-90.14638100000001,30.837899],"type":"Point"}
}