{
  "type": "Feature",
  "properties": {
    "addr:full":"6305 Elysian Fields Ave New Orleans LA 70122",
    "addr:housenumber":"6305",
    "addr:postcode":"70122",
    "addr:street":"Elysian Fields Ave",
    "iso:country":"US",
    "sg:address":"6305 Elysian Fields Ave",
    "sg:city":"New Orleans",
    "sg:classifiers":[
        {
            "category":"Building & Trades",
            "subcategory":"Construction",
            "type":"Services"
        }
    ],
    "sg:phone":"+1 504 286 2421",
    "sg:postcode":"70122",
    "sg:province":"LA",
    "sg:tags":[
        "contractor"
    ],
    "wof:name":"Courseault Commercial Inc",
    "wof:placetype":"venue"
},
  "geometry": {"coordinates":[-90.06082499999999,30.023181],"type":"Point"}
}