{
  "type": "Feature",
  "properties": {
    "iso:country":"US",
    "sg:address":"3240 Dalrymple Dr",
    "sg:city":"Baton Rouge",
    "sg:classifiers":[
        {
            "category":"Social Services",
            "subcategory":"Child Care",
            "type":"Services"
        }
    ],
    "sg:phone":"+1 225 344 8077",
    "sg:postcode":"70802",
    "sg:province":"LA",
    "sg:tags":[
        "kindergarten",
        "academic",
        "school"
    ],
    "wof:name":"University Presbyterian School",
    "wof:placetype":"venue"
},
  "geometry": {"coordinates":[-91.171587,30.418879],"type":"Point"}
}