{
  "type": "Feature",
  "properties": {
    "iso:country":"US",
    "sg:address":"4524 Shores Dr",
    "sg:city":"Metairie",
    "sg:classifiers":[
        {
            "category":"Personal",
            "subcategory":"Beauty Salon",
            "type":"Services"
        }
    ],
    "sg:phone":"+1 504 456 9847",
    "sg:postcode":"70006",
    "sg:province":"LA",
    "sg:tags":[
        "manicuring"
    ],
    "wof:name":"Donna Nails",
    "wof:placetype":"venue"
},
  "geometry": {"coordinates":[-90.189307,30.017522],"type":"Point"}
}