{
  "type": "Feature",
  "properties": {
    "iso:country":"US",
    "sg:address":"350 Jordan St",
    "sg:city":"Shreveport",
    "sg:classifiers":[
        {
            "category":"Social Services",
            "subcategory":"Job Training",
            "type":"Services"
        }
    ],
    "sg:phone":"+1 318 220 7334",
    "sg:postcode":"71101",
    "sg:province":"LA",
    "sg:tags":[
        "rehabilitation"
    ],
    "wof:name":"Rehabilitation Concepts Inc",
    "wof:placetype":"venue"
},
  "geometry": {"coordinates":[-93.73654999999999,32.498217],"type":"Point"}
}