{
  "type": "Feature",
  "properties": {
    "addr:full":"2820 Piedmont St Kenner LA 70062",
    "addr:housenumber":"2820",
    "addr:postcode":"70062",
    "addr:street":"Piedmont St",
    "iso:country":"US",
    "sg:address":"2820 Piedmont St",
    "sg:city":"Kenner",
    "sg:classifiers":[
        {
            "category":"Manufacturing",
            "subcategory":"Rubber & Plastics",
            "type":"Manufacturing & Wholesale Goods"
        }
    ],
    "sg:phone":"+1 504 461 8747",
    "sg:postcode":"70062",
    "sg:province":"LA",
    "wof:name":"Kajun Plastics Inc",
    "wof:placetype":"venue"
},
  "geometry": {"coordinates":[-90.27175200000001,30.006549],"type":"Point"}
}