{
  "type": "Feature",
  "properties": {
    "iso:country":"US",
    "sg:address":"3428 Karen Dr",
    "sg:city":"Chalmette",
    "sg:classifiers":[
        {
            "category":"Professional",
            "type":"Services"
        }
    ],
    "sg:phone":"+1 504 271 8067",
    "sg:postcode":"70043",
    "sg:province":"LA",
    "wof:name":"Crescent Ship Svc of St Rose",
    "wof:placetype":"venue"
},
  "geometry": {"coordinates":[-89.94833800000001,29.948082],"type":"Point"}
}