{
  "type": "Feature",
  "properties": {
    "iso:country":"US",
    "sg:address":"619 Cresswell Ln",
    "sg:city":"Opelousas",
    "sg:classifiers":[
        {
            "category":"Shopping",
            "subcategory":"Department Store",
            "type":"Retail Goods"
        }
    ],
    "sg:phone":"+1 337 594 1057",
    "sg:postcode":"70570",
    "sg:province":"LA",
    "wof:name":"Goody's",
    "wof:placetype":"venue"
},
  "geometry": {"coordinates":[-92.07914,30.519834],"type":"Point"}
}