{
  "type": "Feature",
  "properties": {
    "iso:country":"US",
    "sg:address":"5700 Johnston St",
    "sg:city":"Lafayette",
    "sg:classifiers":[
        {
            "category":"Shopping",
            "subcategory":"Gifts & Souvenirs",
            "type":"Retail Goods"
        }
    ],
    "sg:phone":"+1 337 993 5700",
    "sg:postcode":"70503",
    "sg:province":"LA",
    "sg:tags":[
        "party",
        "supply"
    ],
    "wof:name":"Party City",
    "wof:placetype":"venue"
},
  "geometry": {"coordinates":[-92.077156,30.175445],"type":"Point"}
}