{
  "type": "Feature",
  "properties": {
    "iso:country":"US",
    "sg:address":"2809 US Hwy 51",
    "sg:city":"La Place",
    "sg:classifiers":[
        {
            "category":"Real Estate",
            "subcategory":"Real Estate Agent",
            "type":"Services"
        }
    ],
    "sg:phone":"+1 985 652 3900",
    "sg:postcode":"70068",
    "sg:province":"LA",
    "wof:name":"Re/Max Real Estate Partners",
    "wof:placetype":"venue"
},
  "geometry": {"coordinates":[-90.47702,30.07073],"type":"Point"}
}