{
  "type": "Feature",
  "properties": {
    "iso:country":"US",
    "sg:address":"245 S Gentilly Rd",
    "sg:city":"Lafayette",
    "sg:classifiers":[
        {
            "category":"Wholesale",
            "subcategory":"Machinery & Supplies",
            "type":"Manufacturing & Wholesale Goods"
        }
    ],
    "sg:phone":"+1 337 231 0086",
    "sg:postcode":"70507",
    "sg:province":"LA",
    "sg:tags":[
        "contractor"
    ],
    "wof:name":"TIC Equipment Co",
    "wof:placetype":"venue"
},
  "geometry": {"coordinates":[-92.050141,30.254012],"type":"Point"}
}