{
  "type": "Feature",
  "properties": {
    "addr:full":"1500 Milton St New Orleans LA 70122",
    "addr:housenumber":"1500",
    "addr:postcode":"70122",
    "addr:street":"Milton St",
    "iso:country":"US",
    "sg:address":"1500 Milton St",
    "sg:city":"New Orleans",
    "sg:classifiers":[
        {
            "category":"Government",
            "subcategory":"Police Station",
            "type":"Public Place"
        }
    ],
    "sg:phone":"+1 504 282 0287",
    "sg:postcode":"70122",
    "sg:province":"LA",
    "sg:tags":[
        "protection"
    ],
    "wof:name":"Police Dept",
    "wof:placetype":"venue"
},
  "geometry": {"coordinates":[-90.07476200000001,29.99596],"type":"Point"}
}