{
  "type": "Feature",
  "properties": {
    "addr:full":"1521 Lena Rd Boyce LA 71447",
    "addr:housenumber":"1521",
    "addr:postcode":"71447",
    "addr:street":"Lena Rd",
    "iso:country":"US",
    "sg:address":"1521 Lena Rd",
    "sg:city":"Boyce",
    "sg:classifiers":[
        {
            "category":"Organizations",
            "subcategory":"Religious Organization",
            "type":"Services"
        }
    ],
    "sg:phone":"+1 318 793 9191",
    "sg:postcode":"71447",
    "sg:province":"LA",
    "sg:tags":[
        "church"
    ],
    "wof:name":"Damascus Baptist Church",
    "wof:placetype":"venue"
},
  "geometry": {"coordinates":[-92.773539,31.462715],"type":"Point"}
}