{
  "type": "Feature",
  "properties": {
    "iso:country":"US",
    "sg:address":"817 Horseshoe Dr",
    "sg:city":"Cottonport",
    "sg:classifiers":[
        {
            "category":"Personal",
            "subcategory":"Beauty Salon",
            "type":"Services"
        }
    ],
    "sg:phone":"+1 318 876 2224",
    "sg:postcode":"71327",
    "sg:province":"LA",
    "sg:tags":[
        "shop"
    ],
    "wof:name":"Armand M Theodise",
    "wof:placetype":"venue"
},
  "geometry": {"coordinates":[-92.05139200000001,30.999534],"type":"Point"}
}