{
  "type": "Feature",
  "properties": {
    "addr:full":"15655 Airline Hwy Prairieville LA 70769",
    "addr:housenumber":"15655",
    "addr:postcode":"70769",
    "addr:street":"Airline Hwy Prairieville",
    "iso:country":"US",
    "sg:address":"15655 Airline Hwy",
    "sg:city":"Prairieville",
    "sg:classifiers":[
        {
            "category":"Government",
            "subcategory":"Post Office",
            "type":"Public Place"
        }
    ],
    "sg:phone":"+1 225 673 8117",
    "sg:postcode":"70769",
    "sg:province":"LA",
    "wof:name":"US Post Office",
    "wof:placetype":"venue"
},
  "geometry": {"coordinates":[-90.962384,30.291684],"type":"Point"}
}