{
  "type": "Feature",
  "properties": {
    "addr:full":"4979 Jones Creek Rd Baton Rouge LA 70817",
    "addr:housenumber":"4979",
    "addr:postcode":"70817",
    "addr:street":"Jones Creek Rd",
    "iso:country":"US",
    "sg:address":"4979 Jones Creek Rd",
    "sg:city":"Baton Rouge",
    "sg:classifiers":[
        {
            "category":"Restaurant",
            "type":"Food & Drink"
        }
    ],
    "sg:menulink":"http://www.allmenus.com/la/baton-rouge/188262-mcdonalds/menu/",
    "sg:postcode":"70817",
    "sg:province":"LA",
    "sg:tags":[
        "burger",
        "american"
    ],
    "wof:name":"McDonald's",
    "wof:placetype":"venue"
},
  "geometry": {"coordinates":[-91.01558199999999,30.408934],"type":"Point"}
}