{
  "type": "Feature",
  "properties": {
    "iso:country":"US",
    "sg:address":"2740 Ridgefield Rd",
    "sg:city":"Gretna",
    "sg:classifiers":[
        {
            "category":"Shopping",
            "subcategory":"Computers & Home Electronics",
            "type":"Retail Goods"
        }
    ],
    "sg:phone":"+1 504 394 4268",
    "sg:postcode":"70056",
    "sg:province":"LA",
    "wof:name":"Tip-Ems Air Conditioning & Htg",
    "wof:placetype":"venue"
},
  "geometry": {"coordinates":[-90.033096,29.871179],"type":"Point"}
}