{
  "type": "Feature",
  "properties": {
    "addr:full":"632 Dumaine St New Orleans LA 70116",
    "addr:housenumber":"632",
    "addr:postcode":"70116",
    "addr:street":"Dumaine St",
    "iso:country":"US",
    "sg:address":"632 Dumaine St",
    "sg:city":"New Orleans",
    "sg:classifiers":[
        {
            "category":"Government",
            "subcategory":"Office",
            "type":"Public Place"
        }
    ],
    "sg:phone":"+1 504 599 1147",
    "sg:postcode":"70116",
    "sg:province":"LA",
    "sg:tags":[
        "state"
    ],
    "wof:name":"Lieutenant Governor Office",
    "wof:placetype":"venue"
},
  "geometry": {"coordinates":[-90.063059,29.959381],"type":"Point"}
}