{
  "type": "Feature",
  "properties": {
    "iso:country":"US",
    "sg:address":"416 N 5th St",
    "sg:city":"Monroe",
    "sg:classifiers":[
        {
            "category":"Autos & Motor Vehicles",
            "subcategory":"Automobile Sales",
            "type":"Retail Goods"
        }
    ],
    "sg:phone":"+1 318 324 9200",
    "sg:postcode":"71201",
    "sg:province":"LA",
    "sg:tags":[
        "car",
        "dealer"
    ],
    "wof:name":"John Brodnax LLC",
    "wof:placetype":"venue"
},
  "geometry": {"coordinates":[-92.116694,32.507541],"type":"Point"}
}