{
  "type": "Feature",
  "properties": {
    "addr:full":"705 Spring St Farmerville LA 71241",
    "addr:housenumber":"705",
    "addr:postcode":"71241",
    "addr:street":"Spring St",
    "iso:country":"US",
    "sg:address":"705 Spring St",
    "sg:city":"Farmerville",
    "sg:classifiers":[
        {
            "category":"Manufacturing",
            "subcategory":"Buildings",
            "type":"Manufacturing & Wholesale Goods"
        }
    ],
    "sg:phone":"+1 318 368 0657",
    "sg:postcode":"71241",
    "sg:province":"LA",
    "sg:tags":[
        "prefab"
    ],
    "wof:name":"T & R Investments Inc",
    "wof:placetype":"venue"
},
  "geometry": {"coordinates":[-92.401475,32.781074],"type":"Point"}
}