{
  "type": "Feature",
  "properties": {
    "iso:country":"US",
    "sg:address":"3009 Avery Island Rd",
    "sg:city":"New Iberia",
    "sg:classifiers":[
        {
            "category":"Shopping",
            "subcategory":"Clothing, Apparel, & Fashions",
            "type":"Retail Goods"
        }
    ],
    "sg:phone":"+1 337 365 8793",
    "sg:postcode":"70560",
    "sg:province":"LA",
    "sg:tags":[
        "woman"
    ],
    "wof:name":"Carolyns Fashions",
    "wof:placetype":"venue"
},
  "geometry": {"coordinates":[-91.85562299999999,29.974533],"type":"Point"}
}