{
  "type": "Feature",
  "properties": {
    "iso:country":"US",
    "sg:address":"1815 Military Hwy",
    "sg:city":"Pineville",
    "sg:classifiers":[
        {
            "category":"Professional",
            "subcategory":"Accounting & Tax Preparation",
            "type":"Services"
        }
    ],
    "sg:phone":"+1 318 443 5444",
    "sg:postcode":"71360",
    "sg:province":"LA",
    "sg:tags":[
        "accountant"
    ],
    "wof:name":"William E Hughes Jr CPA",
    "wof:placetype":"venue"
},
  "geometry": {"coordinates":[-92.426591,31.336878],"type":"Point"}
}