{
  "type": "Feature",
  "properties": {
    "iso:country":"US",
    "sg:address":"3401 Jefferson Hwy",
    "sg:city":"Jefferson",
    "sg:classifiers":[
        {
            "category":"Travel",
            "subcategory":"Hotels & Motels",
            "type":"Entertainment"
        }
    ],
    "sg:phone":"+1 504 838 9442",
    "sg:postcode":"70121",
    "sg:province":"LA",
    "wof:name":"Inn Motel",
    "wof:placetype":"venue"
},
  "geometry": {"coordinates":[-90.16010900000001,29.963205],"type":"Point"}
}