{
  "type": "Feature",
  "properties": {
    "addr:full":"113 E Lafayette Dr West Monroe LA 71291",
    "addr:housenumber":"113",
    "addr:postcode":"71291",
    "addr:street":"E Lafayette Dr West",
    "iso:country":"US",
    "sg:address":"113 E Lafayette Dr",
    "sg:city":"West Monroe",
    "sg:classifiers":[
        {
            "category":"Professional",
            "type":"Services"
        }
    ],
    "sg:phone":"+1 318 396 6322",
    "sg:postcode":"71291",
    "sg:province":"LA",
    "sg:tags":[
        "establishment"
    ],
    "wof:name":"LA Gas Svc",
    "wof:placetype":"venue"
},
  "geometry": {"coordinates":[-92.17133800000001,32.560388],"type":"Point"}
}