{
  "type": "Feature",
  "properties": {
    "iso:country":"US",
    "sg:address":"1037 N 12th St",
    "sg:city":"Eunice",
    "sg:classifiers":[
        {
            "category":"Social Services",
            "type":"Services"
        }
    ],
    "sg:phone":"+1 337 457 1230",
    "sg:postcode":"70535",
    "sg:province":"LA",
    "wof:name":"Fruge Jacqueline Ncc LPC",
    "wof:placetype":"venue"
},
  "geometry": {"coordinates":[-92.427626,30.504739],"type":"Point"}
}