{
  "type": "Feature",
  "properties": {
    "iso:country":"US",
    "sg:address":"101 Greathouse St",
    "sg:city":"Jena",
    "sg:classifiers":[
        {
            "category":"Government",
            "subcategory":"Court House",
            "type":"Public Place"
        }
    ],
    "sg:phone":"+1 318 992 2158",
    "sg:postcode":"71334",
    "sg:province":"LA",
    "sg:tags":[
        "county"
    ],
    "wof:name":"LA Salle Clerk Of Court",
    "wof:placetype":"venue"
},
  "geometry": {"coordinates":[-91.549661,31.630649],"type":"Point"}
}