{
  "type": "Feature",
  "properties": {
    "addr:full":"218 Leslie St Denham Springs LA 70726",
    "addr:housenumber":"218",
    "addr:postcode":"70726",
    "addr:street":"Leslie St",
    "iso:country":"US",
    "sg:address":"218 Leslie St",
    "sg:city":"Denham Springs",
    "sg:classifiers":[
        {
            "category":"Building & Trades",
            "subcategory":"Construction",
            "type":"Services"
        }
    ],
    "sg:phone":"+1 225 665 7847",
    "sg:postcode":"70726",
    "sg:province":"LA",
    "sg:tags":[
        "dry wall",
        "contractor"
    ],
    "wof:name":"Anthony Snead Drywall Contrctr",
    "wof:placetype":"venue"
},
  "geometry": {"coordinates":[-90.95784,30.492243],"type":"Point"}
}