{
  "type": "Feature",
  "properties": {
    "iso:country":"US",
    "sg:address":"324 W Pinhook Rd",
    "sg:city":"Lafayette",
    "sg:classifiers":[
        {
            "category":"Bus Charters",
            "type":"Transportation"
        }
    ],
    "sg:phone":"+1 337 291 6071",
    "sg:postcode":"70501",
    "sg:province":"LA",
    "sg:tags":[
        "rental"
    ],
    "sg:website":"www.acadianacrewchange.com",
    "wof:name":"Acadiana Coaches",
    "wof:placetype":"venue"
},
  "geometry": {"coordinates":[-92.009125,30.21177],"type":"Point"}
}