{
  "type": "Feature",
  "properties": {
    "iso:country":"US",
    "sg:address":"619 Decatur St",
    "sg:city":"New Orleans",
    "sg:classifiers":[
        {
            "category":"Shopping",
            "subcategory":"Pharmacy",
            "type":"Retail Goods"
        }
    ],
    "sg:phone":"+1 504 525 7263",
    "sg:postcode":"70130",
    "sg:province":"LA",
    "sg:tags":[
        "drugstore"
    ],
    "sg:website":"www.walgreens.com/",
    "wof:name":"Walgreens",
    "wof:placetype":"venue"
},
  "geometry": {"coordinates":[-90.06335199999999,29.956584],"type":"Point"}
}