{
  "type": "Feature",
  "properties": {
    "addr:full":"920 N Alexander Ave Port Allen LA 70767",
    "addr:housenumber":"920",
    "addr:postcode":"70767",
    "addr:street":"N Alexander Ave",
    "iso:country":"US",
    "sg:address":"920 N Alexander Ave",
    "sg:city":"Port Allen",
    "sg:classifiers":[
        {
            "category":"Food & Beverages",
            "subcategory":"Groceries & Convenience Stores",
            "type":"Retail Goods"
        }
    ],
    "sg:phone":"+1 225 383 1865",
    "sg:postcode":"70767",
    "sg:province":"LA",
    "sg:tags":[
        "grocer"
    ],
    "wof:name":"Bro's Food Store",
    "wof:placetype":"venue"
},
  "geometry": {"coordinates":[-91.21093399999999,30.462023],"type":"Point"}
}