{
  "type": "Feature",
  "properties": {
    "iso:country":"US",
    "sg:address":"4860 W Green Ridge Dr",
    "sg:city":"Baton Rouge",
    "sg:classifiers":[
        {
            "category":"Shopping",
            "subcategory":"Musical Instruments",
            "type":"Retail Goods"
        }
    ],
    "sg:phone":"+1 225 272 1989",
    "sg:postcode":"70814",
    "sg:province":"LA",
    "wof:name":"Music Time",
    "wof:placetype":"venue"
},
  "geometry": {"coordinates":[-91.059569,30.496259],"type":"Point"}
}