{
  "type": "Feature",
  "properties": {
    "iso:country":"US",
    "sg:address":"10155 Mammoth Ave",
    "sg:city":"Baton Rouge",
    "sg:classifiers":[
        {
            "category":"Manufacturing",
            "subcategory":"Tools & Machinery",
            "type":"Manufacturing & Wholesale Goods"
        }
    ],
    "sg:phone":"+1 225 926 3667",
    "sg:postcode":"70814",
    "sg:province":"LA",
    "sg:tags":[
        "equipment",
        "laboratory",
        "supply"
    ],
    "sg:website":"www.tek-lab.com",
    "wof:name":"Teklab Inc",
    "wof:placetype":"venue"
},
  "geometry": {"coordinates":[-91.072746,30.477139],"type":"Point"}
}