{
  "type": "Feature",
  "properties": {
    "iso:country":"US",
    "sg:address":"304 Tunica Dr W",
    "sg:city":"Marksville",
    "sg:classifiers":[
        {
            "category":"Banks & Credit Unions",
            "subcategory":"Bank",
            "type":"Services"
        }
    ],
    "sg:phone":"+1 318 240 7007",
    "sg:postcode":"71351",
    "sg:province":"LA",
    "sg:tags":[
        "loan"
    ],
    "wof:name":"First Franklin Financial Corp",
    "wof:placetype":"venue"
},
  "geometry": {"coordinates":[-92.07141900000001,31.12529],"type":"Point"}
}