{
  "type": "Feature",
  "properties": {
    "iso:country":"US",
    "sg:address":"909 Causeway Blvd",
    "sg:city":"Jefferson",
    "sg:classifiers":[
        {
            "category":"Building & Trades",
            "subcategory":"Construction",
            "type":"Services"
        }
    ],
    "sg:phone":"+1 504 841 2827",
    "sg:postcode":"70121",
    "sg:province":"LA",
    "sg:tags":[
        "concrete",
        "contractor"
    ],
    "wof:name":"Tekcrete Inc",
    "wof:placetype":"venue"
},
  "geometry": {"coordinates":[-90.156454,29.965236],"type":"Point"}
}