{
  "type": "Feature",
  "properties": {
    "iso:country":"US",
    "sg:address":"1315 Estalote Ave",
    "sg:city":"Harvey",
    "sg:classifiers":[
        {
            "category":"Organizations",
            "subcategory":"Religious Organization",
            "type":"Services"
        }
    ],
    "sg:phone":"+1 504 361 1570",
    "sg:postcode":"70058",
    "sg:province":"LA",
    "wof:name":"White Chapel Baptist Church",
    "wof:placetype":"venue"
},
  "geometry": {"coordinates":[-90.07196399999999,29.893242],"type":"Point"}
}