{
  "type": "Feature",
  "properties": {
    "addr:full":"2405 Court St Port Allen LA 70767",
    "addr:housenumber":"2405",
    "addr:postcode":"70767",
    "addr:street":"Court St",
    "iso:country":"US",
    "sg:address":"2405 Court St",
    "sg:city":"Port Allen",
    "sg:classifiers":[
        {
            "category":"Autos & Motor Vehicles",
            "subcategory":"Automobile Sales",
            "type":"Retail Goods"
        }
    ],
    "sg:phone":"+1 225 343 3576",
    "sg:postcode":"70767",
    "sg:province":"LA",
    "sg:tags":[
        "car",
        "dealer"
    ],
    "wof:name":"Pappy's Used Cars",
    "wof:placetype":"venue"
},
  "geometry": {"coordinates":[-91.235553,30.451005],"type":"Point"}
}