{
  "type": "Feature",
  "properties": {
    "iso:country":"US",
    "sg:address":"3715 Williams Blvd",
    "sg:city":"Kenner",
    "sg:classifiers":[
        {
            "category":"Health Services",
            "subcategory":"Doctor",
            "type":"Services"
        }
    ],
    "sg:phone":"+1 504 305 3812",
    "sg:postcode":"70065",
    "sg:province":"LA",
    "sg:tags":[
        "physician",
        "surgeon"
    ],
    "wof:name":"Pediatric Medical Clinic",
    "wof:placetype":"venue"
},
  "geometry": {"coordinates":[-90.239107,30.024434],"type":"Point"}
}