{
  "type": "Feature",
  "properties": {
    "iso:country":"US",
    "sg:address":"123 E Saint Peter St",
    "sg:city":"New Iberia",
    "sg:classifiers":[
        {
            "category":"Real Estate",
            "subcategory":"Real Estate Agent",
            "type":"Services"
        }
    ],
    "sg:phone":"+1 337 367 2563",
    "sg:postcode":"70560",
    "sg:province":"LA",
    "wof:name":"James Real Estate",
    "wof:placetype":"venue"
},
  "geometry": {"coordinates":[-91.81909899999999,30.004999],"type":"Point"}
}