{
  "type": "Feature",
  "properties": {
    "iso:country":"US",
    "sg:address":"4147 Old Hwy 6",
    "sg:city":"Natchitoches",
    "sg:classifiers":[
        {
            "category":"Autos & Motor Vehicles",
            "subcategory":"Automobile Sales",
            "type":"Retail Goods"
        }
    ],
    "sg:phone":"+1 318 356 0040",
    "sg:postcode":"71457",
    "sg:province":"LA",
    "sg:tags":[
        "used"
    ],
    "wof:name":"3 D Motors",
    "wof:placetype":"venue"
},
  "geometry": {"coordinates":[-93.172392,31.720002],"type":"Point"}
}