{
  "type": "Feature",
  "properties": {
    "iso:country":"US",
    "sg:address":"1307 Old Jeanerette Rd",
    "sg:city":"New Iberia",
    "sg:classifiers":[
        {
            "category":"Health Services",
            "subcategory":"Doctor",
            "type":"Services"
        }
    ],
    "sg:phone":"+1 337 364 3000",
    "sg:postcode":"70563",
    "sg:province":"LA",
    "sg:tags":[
        "physician",
        "surgeon"
    ],
    "wof:name":"William A Cenac MD",
    "wof:placetype":"venue"
},
  "geometry": {"coordinates":[-91.79710300000001,30.000104],"type":"Point"}
}