{
  "type": "Feature",
  "properties": {
    "iso:country":"US",
    "sg:address":"314 W 1st St",
    "sg:city":"Kaplan",
    "sg:classifiers":[
        {
            "category":"Personal",
            "subcategory":"Barber",
            "type":"Services"
        }
    ],
    "sg:phone":"+1 337 643 2163",
    "sg:postcode":"70548",
    "sg:province":"LA",
    "sg:tags":[
        "shop"
    ],
    "wof:name":"Bert's Barber Shop",
    "wof:placetype":"venue"
},
  "geometry": {"coordinates":[-92.288597,29.999158],"type":"Point"}
}