{
  "type": "Feature",
  "properties": {
    "addr:full":"7135 Benson Ct New Orleans LA 70127",
    "addr:housenumber":"7135",
    "addr:postcode":"70127",
    "addr:street":"Benson Ct",
    "iso:country":"US",
    "sg:address":"7135 Benson Ct",
    "sg:city":"New Orleans",
    "sg:classifiers":[
        {
            "category":"Health Services",
            "subcategory":"Doctor",
            "type":"Services"
        }
    ],
    "sg:phone":"+1 504 588 5414",
    "sg:postcode":"70127",
    "sg:province":"LA",
    "sg:tags":[
        "medical"
    ],
    "wof:name":"Social Policy Research Group",
    "wof:placetype":"venue"
},
  "geometry": {"coordinates":[-89.991463,30.03427],"type":"Point"}
}