{
  "type": "Feature",
  "properties": {
    "addr:full":"6105 Milton Dr New Iberia LA 70560",
    "addr:housenumber":"6105",
    "addr:postcode":"70560",
    "addr:street":"Milton Dr",
    "iso:country":"US",
    "sg:address":"6105 Milton Dr",
    "sg:city":"New Iberia",
    "sg:classifiers":[
        {
            "category":"Personal",
            "type":"Services"
        }
    ],
    "sg:phone":"+1 337 224 0700",
    "sg:postcode":"70560",
    "sg:province":"LA",
    "wof:name":"Le Parsait Jour",
    "wof:placetype":"venue"
},
  "geometry": {"coordinates":[-91.912132,29.966102],"type":"Point"}
}