{
  "type": "Feature",
  "properties": {
    "addr:full":"2611 N Dumont Dr Baton Rouge LA 70814",
    "addr:housenumber":"2611",
    "addr:postcode":"70814",
    "addr:street":"N Dumont Dr",
    "iso:country":"US",
    "sg:address":"2611 N Dumont Dr",
    "sg:city":"Baton Rouge",
    "sg:classifiers":[
        {
            "category":"Manufacturing",
            "subcategory":"Tools & Machinery",
            "type":"Manufacturing & Wholesale Goods"
        }
    ],
    "sg:phone":"+1 225 275 9914",
    "sg:postcode":"70814",
    "sg:province":"LA",
    "sg:tags":[
        "equipment",
        "lighting"
    ],
    "wof:name":"Jon Bajon Inc",
    "wof:placetype":"venue"
},
  "geometry": {"coordinates":[-91.05095,30.473773],"type":"Point"}
}