{
  "type": "Feature",
  "properties": {
    "iso:country":"US",
    "sg:address":"101 Advent St",
    "sg:city":"Sulphur",
    "sg:classifiers":[
        {
            "category":"Health Services",
            "subcategory":"Podiatrist",
            "type":"Services"
        }
    ],
    "sg:phone":"+1 337 625 7604",
    "sg:postcode":"70663",
    "sg:province":"LA",
    "wof:name":"Foot Specialist Of Sulphur",
    "wof:placetype":"venue"
},
  "geometry": {"coordinates":[-93.32714799999999,30.227999],"type":"Point"}
}