{
  "type": "Feature",
  "properties": {
    "iso:country":"US",
    "sg:address":"18370 Hwy 190",
    "sg:city":"Reeves",
    "sg:classifiers":[
        {
            "category":"Government",
            "subcategory":"Office",
            "type":"Public Place"
        }
    ],
    "sg:phone":"+1 337 666 2613",
    "sg:postcode":"70658",
    "sg:province":"LA",
    "sg:tags":[
        "city"
    ],
    "wof:name":"Reeves City Hall",
    "wof:placetype":"venue"
},
  "geometry": {"coordinates":[-93.047381,30.519509],"type":"Point"}
}