{
  "type": "Feature",
  "properties": {
    "iso:country":"US",
    "sg:address":"7527 Town South Ave",
    "sg:city":"Baton Rouge",
    "sg:classifiers":[
        {
            "category":"Personal",
            "type":"Services"
        }
    ],
    "sg:phone":"+1 225 767 0555",
    "sg:postcode":"70808",
    "sg:province":"LA",
    "sg:tags":[
        "hair",
        "replacement"
    ],
    "wof:name":"American Hairlines",
    "wof:placetype":"venue"
},
  "geometry": {"coordinates":[-91.112059,30.390573],"type":"Point"}
}