{
  "type": "Feature",
  "properties": {
    "iso:country":"US",
    "sg:address":"3201 Delille St",
    "sg:city":"Chalmette",
    "sg:classifiers":[
        {
            "category":"Insurance",
            "subcategory":"Insurance Agent",
            "type":"Services"
        }
    ],
    "sg:phone":"+1 504 279 2118",
    "sg:postcode":"70043",
    "sg:province":"LA",
    "wof:name":"Hugh Hauck",
    "wof:placetype":"venue"
},
  "geometry": {"coordinates":[-89.96343899999999,29.950557],"type":"Point"}
}