{
  "type": "Feature",
  "properties": {
    "iso:country":"US",
    "sg:address":"213 Miller St",
    "sg:city":"Lafayette",
    "sg:classifiers":[
        {
            "category":"Shopping",
            "subcategory":"Computers & Home Electronics",
            "type":"Retail Goods"
        }
    ],
    "sg:phone":"+1 337 235 3620",
    "sg:postcode":"70503",
    "sg:province":"LA",
    "sg:tags":[
        "system"
    ],
    "wof:name":"Acadian Custom Installations",
    "wof:placetype":"venue"
},
  "geometry": {"coordinates":[-92.01022500000001,30.198489],"type":"Point"}
}