{
  "type": "Feature",
  "properties": {
    "iso:country":"US",
    "sg:address":"5253 Rebelle Ln",
    "sg:city":"Port Allen",
    "sg:classifiers":[
        {
            "category":"Retail",
            "subcategory":"Repair Shop",
            "type":"Services"
        }
    ],
    "sg:phone":"+1 225 383 8402",
    "sg:postcode":"70767",
    "sg:province":"LA",
    "sg:tags":[
        "equipment",
        "conditioning",
        "air"
    ],
    "wof:name":"Mike Blanchard's AC & Heating",
    "wof:placetype":"venue"
},
  "geometry": {"coordinates":[-91.281284,30.461016],"type":"Point"}
}