{
  "type": "Feature",
  "properties": {
    "addr:full":"109 E Bert Kouns Industrial Loop Shreveport LA 71106",
    "addr:housenumber":"109",
    "addr:postcode":"71106",
    "addr:street":"E Bert Kouns Industrial Loop",
    "iso:country":"US",
    "sg:address":"109 E Bert Kouns Industrial Loop",
    "sg:city":"Shreveport",
    "sg:classifiers":[
        {
            "category":"Autos & Motor Vehicles",
            "subcategory":"Fuel & Gas Station",
            "type":"Retail Goods"
        }
    ],
    "sg:phone":"+1 318 688 9663",
    "sg:postcode":"71106",
    "sg:province":"LA",
    "sg:tags":[
        "oil"
    ],
    "wof:name":"Chevron",
    "wof:placetype":"venue"
},
  "geometry": {"coordinates":[-93.738614,32.399167],"type":"Point"}
}