{
  "type": "Feature",
  "properties": {
    "iso:country":"US",
    "sg:address":"1701 Sgt Alfred Dr",
    "sg:city":"Slidell",
    "sg:classifiers":[
        {
            "category":"Wholesale",
            "subcategory":"Medical Equipment & Supplies",
            "type":"Manufacturing & Wholesale Goods"
        }
    ],
    "sg:phone":"+1 985 649 6525",
    "sg:postcode":"70458",
    "sg:province":"LA",
    "sg:tags":[
        "physician",
        "surgeon"
    ],
    "wof:name":"Summit Medical Svc Inc",
    "wof:placetype":"venue"
},
  "geometry": {"coordinates":[-89.78049799999999,30.279653],"type":"Point"}
}