{
  "type": "Feature",
  "properties": {
    "addr:full":"1200 Cooktown Rd Ruston LA 71270",
    "addr:housenumber":"1200",
    "addr:postcode":"71270",
    "addr:street":"Cooktown Rd",
    "iso:country":"US",
    "sg:address":"1200 Cooktown Rd",
    "sg:city":"Ruston",
    "sg:classifiers":[
        {
            "category":"Coffee & Tea",
            "type":"Food & Drink"
        }
    ],
    "sg:menulink":"http://www.allmenus.com/la/ruston/113645-starbucks-coffee/menu/",
    "sg:phone":"+1 318 255 9219",
    "sg:postcode":"71270",
    "sg:province":"LA",
    "sg:tags":[
        "american"
    ],
    "wof:name":"Starbucks Coffee",
    "wof:placetype":"venue"
},
  "geometry": {"coordinates":[-92.652973,32.537658],"type":"Point"}
}