{
  "type": "Feature",
  "properties": {
    "iso:country":"US",
    "sg:address":"4639 Magazine St",
    "sg:city":"New Orleans",
    "sg:classifiers":[
        {
            "category":"Retail",
            "subcategory":"Self-service Laundry",
            "type":"Services"
        }
    ],
    "sg:phone":"+1 504 894 8887",
    "sg:postcode":"70115",
    "sg:province":"LA",
    "wof:name":"Magazine Laundromat",
    "wof:placetype":"venue"
},
  "geometry": {"coordinates":[-90.104603,29.920625],"type":"Point"}
}