{
  "type": "Feature",
  "properties": {
    "iso:country":"US",
    "sg:address":"3136 Paris Ave",
    "sg:city":"New Orleans",
    "sg:classifiers":[
        {
            "category":"Shopping",
            "subcategory":"Hobbies, Toys, & Games",
            "type":"Retail Goods"
        }
    ],
    "sg:phone":"+1 504 940 6000",
    "sg:postcode":"70119",
    "sg:province":"LA",
    "sg:tags":[
        "supply"
    ],
    "wof:name":"Games New Orleans Inc",
    "wof:placetype":"venue"
},
  "geometry": {"coordinates":[-90.073161,29.989993],"type":"Point"}
}