{
  "type": "Feature",
  "properties": {
    "iso:country":"US",
    "sg:address":"4037 Dickinson St",
    "sg:city":"Lakeland",
    "sg:classifiers":[
        {
            "category":"Organizations",
            "subcategory":"Community Association",
            "type":"Services"
        }
    ],
    "sg:phone":"+1 225 627 4188",
    "sg:postcode":"70752",
    "sg:province":"LA",
    "wof:name":"Kiwanis International Inc",
    "wof:placetype":"venue"
},
  "geometry": {"coordinates":[-91.41733499999999,30.57798],"type":"Point"}
}