{
  "type": "Feature",
  "properties": {
    "addr:full":"2805 Buffon St Chalmette LA 70043",
    "addr:housenumber":"2805",
    "addr:postcode":"70043",
    "addr:street":"Buffon St",
    "iso:country":"US",
    "sg:address":"2805 Buffon St",
    "sg:city":"Chalmette",
    "sg:classifiers":[
        {
            "category":"Home & Garden",
            "subcategory":"Garden Supply",
            "type":"Retail Goods"
        }
    ],
    "sg:phone":"+1 504 271 6798",
    "sg:postcode":"70043",
    "sg:province":"LA",
    "sg:tags":[
        "sprinkler"
    ],
    "wof:name":"Advanced Sprinkler & Landscpng",
    "wof:placetype":"venue"
},
  "geometry": {"coordinates":[-89.961089,29.944868],"type":"Point"}
}