{
  "type": "Feature",
  "properties": {
    "iso:country":"US",
    "sg:address":"6861 Klug Pines Rd",
    "sg:city":"Shreveport",
    "sg:classifiers":[
        {
            "category":"Building & Trades",
            "subcategory":"Construction",
            "type":"Services"
        }
    ],
    "sg:phone":"+1 318 688 4649",
    "sg:postcode":"71129",
    "sg:province":"LA",
    "sg:tags":[
        "hanging",
        "contractor"
    ],
    "wof:name":"Rawls Painting Co",
    "wof:placetype":"venue"
},
  "geometry": {"coordinates":[-93.869263,32.445259],"type":"Point"}
}