{
  "type": "Feature",
  "properties": {
    "addr:full":"2524 Airbase Rd Alexandria LA 71303",
    "addr:housenumber":"2524",
    "addr:postcode":"71303",
    "addr:street":"Airbase Rd",
    "iso:country":"US",
    "sg:address":"2524 Airbase Rd",
    "sg:city":"Alexandria",
    "sg:classifiers":[
        {
            "category":"Home & Garden",
            "subcategory":"Building Materials",
            "type":"Retail Goods"
        }
    ],
    "sg:phone":"+1 318 448 2278",
    "sg:postcode":"71303",
    "sg:province":"LA",
    "sg:tags":[
        "glass",
        "window",
        "plate"
    ],
    "wof:name":"Shield & Star",
    "wof:placetype":"venue"
},
  "geometry": {"coordinates":[-92.524444,31.327993],"type":"Point"}
}