{
  "type": "Feature",
  "properties": {
    "addr:full":"20700 Old Scenic Hwy Zachary LA 70791",
    "addr:housenumber":"20700",
    "addr:postcode":"70791",
    "addr:street":"Old Scenic Hwy Zachary",
    "iso:country":"US",
    "sg:address":"20700 Old Scenic Hwy",
    "sg:city":"Zachary",
    "sg:classifiers":[
        {
            "category":"Restaurant",
            "type":"Food & Drink"
        }
    ],
    "sg:phone":"+1 225 658 5858",
    "sg:postcode":"70791",
    "sg:province":"LA",
    "wof:name":"Rogers Steak & Seafood",
    "wof:placetype":"venue"
},
  "geometry": {"coordinates":[-91.19227100000001,30.659859],"type":"Point"}
}