{
  "type": "Feature",
  "properties": {
    "iso:country":"US",
    "sg:address":"7711 US Hwy 167",
    "sg:city":"Turkey Creek",
    "sg:classifiers":[
        {
            "category":"Government",
            "subcategory":"Office",
            "type":"Public Place"
        }
    ],
    "sg:phone":"+1 337 461 2212",
    "sg:postcode":"70585",
    "sg:province":"LA",
    "sg:tags":[
        "city"
    ],
    "wof:name":"Turkey Creek City Hall",
    "wof:placetype":"venue"
},
  "geometry": {"coordinates":[-92.39647600000001,30.864428],"type":"Point"}
}