{
  "type": "Feature",
  "properties": {
    "iso:country":"US",
    "sg:address":"1234 E Pont Des Mouton Rd",
    "sg:city":"Lafayette",
    "sg:classifiers":[
        {
            "category":"Organizations",
            "subcategory":"Membership Organization",
            "type":"Services"
        }
    ],
    "sg:phone":"+1 337 233 8044",
    "sg:postcode":"70507",
    "sg:province":"LA",
    "sg:tags":[
        "athletic",
        "gym"
    ],
    "wof:name":"Brown Park Athletics",
    "wof:placetype":"venue"
},
  "geometry": {"coordinates":[-91.992104,30.2722],"type":"Point"}
}