{
  "type": "Feature",
  "properties": {
    "iso:country":"US",
    "sg:address":"9836 Florida Blvd",
    "sg:city":"Baton Rouge",
    "sg:classifiers":[
        {
            "category":"Restaurant",
            "type":"Food & Drink"
        }
    ],
    "sg:phone":"+1 225 218 0391",
    "sg:postcode":"70815",
    "sg:province":"LA",
    "sg:tags":[
        "barbecue"
    ],
    "wof:name":"Port A Pit Barbecue",
    "wof:placetype":"venue"
},
  "geometry": {"coordinates":[-91.075746,30.456021],"type":"Point"}
}