{
  "type": "Feature",
  "properties": {
    "addr:full":"621 Prairie St Winnsboro LA 71295",
    "addr:housenumber":"621",
    "addr:postcode":"71295",
    "addr:street":"Prairie St",
    "iso:country":"US",
    "sg:address":"621 Prairie St",
    "sg:city":"Winnsboro",
    "sg:classifiers":[
        {
            "category":"Personal",
            "subcategory":"Beauty Salon",
            "type":"Services"
        }
    ],
    "sg:phone":"+1 318 435 5277",
    "sg:postcode":"71295",
    "sg:province":"LA",
    "wof:name":"New You Salon",
    "wof:placetype":"venue"
},
  "geometry": {"coordinates":[-91.71841000000001,32.1643],"type":"Point"}
}