{
  "type": "Feature",
  "properties": {
    "addr:full":"4330 Dumaine St New Orleans LA 70119",
    "addr:housenumber":"4330",
    "addr:postcode":"70119",
    "addr:street":"Dumaine St",
    "iso:country":"US",
    "sg:address":"4330 Dumaine St",
    "sg:city":"New Orleans",
    "sg:classifiers":[
        {
            "category":"Professional",
            "subcategory":"Lawyer & Legal Services",
            "type":"Services"
        }
    ],
    "sg:phone":"+1 504 488 8802",
    "sg:postcode":"70119",
    "sg:province":"LA",
    "sg:tags":[
        "attorney"
    ],
    "wof:name":"Ladouceur & Ladouceur",
    "wof:placetype":"venue"
},
  "geometry": {"coordinates":[-90.098113,29.983171],"type":"Point"}
}