{
  "type": "Feature",
  "properties": {
    "iso:country":"US",
    "sg:address":"74009 Hwy 25",
    "sg:city":"Covington",
    "sg:classifiers":[
        {
            "category":"Wholesale",
            "subcategory":"Construction Materials",
            "type":"Manufacturing & Wholesale Goods"
        }
    ],
    "sg:phone":"+1 985 892 3130",
    "sg:postcode":"70435",
    "sg:province":"LA",
    "sg:tags":[
        "sand",
        "gravel"
    ],
    "wof:name":"Tammany Haulers",
    "wof:placetype":"venue"
},
  "geometry": {"coordinates":[-90.110905,30.504985],"type":"Point"}
}