{
  "type": "Feature",
  "properties": {
    "iso:country":"US",
    "sg:address":"2310 N Main St",
    "sg:city":"Saint Martinville",
    "sg:classifiers":[
        {
            "category":"Shopping",
            "subcategory":"Department Store",
            "type":"Retail Goods"
        }
    ],
    "sg:phone":"+1 337 837 8886",
    "sg:postcode":"70582",
    "sg:province":"LA",
    "sg:website":"www.walmart.com",
    "wof:name":"Wal-Mart",
    "wof:placetype":"venue"
},
  "geometry": {"coordinates":[-91.8228,30.145599],"type":"Point"}
}