{
  "type": "Feature",
  "properties": {
    "iso:country":"US",
    "sg:address":"279 Mora Rd",
    "sg:city":"Mora",
    "sg:classifiers":[
        {
            "category":"Organizations",
            "subcategory":"Religious Organization",
            "type":"Services"
        }
    ],
    "sg:phone":"+1 318 793 8359",
    "sg:postcode":"71455",
    "sg:province":"LA",
    "wof:name":"Spanish Branch Baptist Church",
    "wof:placetype":"venue"
},
  "geometry": {"coordinates":[-92.917669,31.348085],"type":"Point"}
}