{
  "type": "Feature",
  "properties": {
    "iso:country":"US",
    "sg:address":"1887 Ames Blvd",
    "sg:city":"Marrero",
    "sg:classifiers":[
        {
            "category":"Government",
            "subcategory":"Office",
            "type":"Public Place"
        }
    ],
    "sg:phone":"+1 504 349 5360",
    "sg:postcode":"70072",
    "sg:province":"LA",
    "wof:name":"Jefferson Parish Emergency Ctr",
    "wof:placetype":"venue"
},
  "geometry": {"coordinates":[-90.114051,29.881731],"type":"Point"}
}