{
  "type": "Feature",
  "properties": {
    "iso:country":"US",
    "sg:address":"116 Rebecca Dr",
    "sg:city":"Jonesville",
    "sg:classifiers":[
        {
            "category":"Freight",
            "type":"Transportation"
        }
    ],
    "sg:phone":"+1 318 339 7377",
    "sg:postcode":"71343",
    "sg:province":"LA",
    "sg:tags":[
        "courier"
    ],
    "wof:name":"Wesley Corporation",
    "wof:placetype":"venue"
},
  "geometry": {"coordinates":[-91.825898,31.622736],"type":"Point"}
}