{
  "type": "Feature",
  "properties": {
    "addr:full":"1064 Highland Park Dr Baton Rouge LA 70808",
    "addr:housenumber":"1064",
    "addr:postcode":"70808",
    "addr:street":"Highland Park Dr",
    "iso:country":"US",
    "sg:address":"1064 Highland Park Dr",
    "sg:city":"Baton Rouge",
    "sg:classifiers":[
        {
            "category":"Professional",
            "subcategory":"Management & Consulting",
            "type":"Services"
        }
    ],
    "sg:phone":"+1 225 766 1698",
    "sg:postcode":"70808",
    "sg:province":"LA",
    "sg:tags":[
        "consultant",
        "resource"
    ],
    "wof:name":"Max Forbes Inc",
    "wof:placetype":"venue"
},
  "geometry": {"coordinates":[-91.133731,30.388944],"type":"Point"}
}