{
  "type": "Feature",
  "properties": {
    "addr:full":"140 Teema Rd Carencro LA 70520",
    "addr:housenumber":"140",
    "addr:postcode":"70520",
    "addr:street":"Teema Rd",
    "iso:country":"US",
    "sg:address":"140 Teema Rd",
    "sg:city":"Carencro",
    "sg:classifiers":[
        {
            "category":"Personal",
            "subcategory":"Beauty Salon",
            "type":"Services"
        }
    ],
    "sg:phone":"+1 337 896 7296",
    "sg:postcode":"70520",
    "sg:province":"LA",
    "wof:name":"T & K's Perfection",
    "wof:placetype":"venue"
},
  "geometry": {"coordinates":[-92.04195300000001,30.320209],"type":"Point"}
}