{
  "type": "Feature",
  "properties": {
    "iso:country":"US",
    "sg:address":"1001 Loyola Ave",
    "sg:city":"New Orleans",
    "sg:classifiers":[
        {
            "category":"Restaurant",
            "type":"Food & Drink"
        }
    ],
    "sg:menulink":"http://www.allmenus.com/la/new-orleans/89254-subway/menu/",
    "sg:phone":"+1 504 523 6501",
    "sg:postcode":"70113",
    "sg:province":"LA",
    "sg:tags":[
        "american",
        "sandwich"
    ],
    "wof:name":"Subway",
    "wof:placetype":"venue"
},
  "geometry": {"coordinates":[-90.077742,29.94503],"type":"Point"}
}