{
  "type": "Feature",
  "properties": {
    "iso:country":"US",
    "sg:address":"531 Ave A",
    "sg:city":"Westwego",
    "sg:classifiers":[
        {
            "category":"Education",
            "subcategory":"School",
            "type":"Public Place"
        }
    ],
    "sg:phone":"+1 504 341 9505",
    "sg:postcode":"70094",
    "sg:province":"LA",
    "wof:name":"Our Lady Of Prompt Succor",
    "wof:placetype":"venue"
},
  "geometry": {"coordinates":[-90.14557499999999,29.908207],"type":"Point"}
}