{
  "type": "Feature",
  "properties": {
    "iso:country":"US",
    "sg:address":"6767 Perkins Rd",
    "sg:city":"Baton Rouge",
    "sg:classifiers":[
        {
            "category":"Organizations",
            "subcategory":"Professional Association",
            "type":"Services"
        }
    ],
    "sg:phone":"+1 225 763 8500",
    "sg:postcode":"70808",
    "sg:province":"LA",
    "sg:website":"www.lsms.org",
    "wof:name":"LA State Medical Society",
    "wof:placetype":"venue"
},
  "geometry": {"coordinates":[-91.120012,30.402504],"type":"Point"}
}