{
  "type": "Feature",
  "properties": {
    "iso:country":"US",
    "sg:address":"1134 Barrow St",
    "sg:city":"Houma",
    "sg:classifiers":[
        {
            "category":"Communications",
            "type":"Services"
        }
    ],
    "sg:phone":"+1 985 868 9696",
    "sg:postcode":"70360",
    "sg:province":"LA",
    "sg:tags":[
        "carrier"
    ],
    "wof:name":"Beeper World",
    "wof:placetype":"venue"
},
  "geometry": {"coordinates":[-90.72065600000001,29.588385],"type":"Point"}
}