{
  "type": "Feature",
  "properties": {
    "iso:country":"US",
    "sg:address":"3510 Drusilla Ln",
    "sg:city":"Baton Rouge",
    "sg:classifiers":[
        {
            "category":"Restaurant",
            "type":"Food & Drink"
        }
    ],
    "sg:menulink":"http://www.allmenus.com/la/baton-rouge/214335-voodoo-bbq--grill/menu/",
    "sg:phone":"+1 225 926 3003",
    "sg:postcode":"70809",
    "sg:province":"LA",
    "sg:tags":[
        "barbecue",
        "american"
    ],
    "wof:name":"Voodoo Bbq & Grill",
    "wof:placetype":"venue"
},
  "geometry": {"coordinates":[-91.08903599999999,30.418716],"type":"Point"}
}