{
  "type": "Feature",
  "properties": {
    "iso:country":"US",
    "sg:address":"741 Point St",
    "sg:city":"Houma",
    "sg:classifiers":[
        {
            "category":"Retail",
            "subcategory":"Portrait Studio",
            "type":"Services"
        }
    ],
    "sg:phone":"+1 985 868 0700",
    "sg:postcode":"70360",
    "sg:province":"LA",
    "sg:tags":[
        "photographer",
        "photo"
    ],
    "wof:name":"James Pitre Photography",
    "wof:placetype":"venue"
},
  "geometry": {"coordinates":[-90.71897800000001,29.59256],"type":"Point"}
}