{
  "type": "Feature",
  "properties": {
    "addr:full":"8820 Plum St New Orleans LA 70118",
    "addr:housenumber":"8820",
    "addr:postcode":"70118",
    "addr:street":"Plum St",
    "iso:country":"US",
    "sg:address":"8820 Plum St",
    "sg:city":"New Orleans",
    "sg:classifiers":[
        {
            "category":"Organizations",
            "subcategory":"Community Association",
            "type":"Services"
        }
    ],
    "sg:phone":"+1 504 866 5533",
    "sg:postcode":"70118",
    "sg:province":"LA",
    "sg:tags":[
        "club"
    ],
    "wof:name":"Krewe Of Carrollton",
    "wof:placetype":"venue"
},
  "geometry": {"coordinates":[-90.13555599999999,29.953235],"type":"Point"}
}