{
  "type": "Feature",
  "properties": {
    "iso:country":"US",
    "sg:address":"5611 Perez Rd",
    "sg:city":"Lydia",
    "sg:classifiers":[
        {
            "category":"Retail",
            "subcategory":"Repair Shop",
            "type":"Services"
        }
    ],
    "sg:phone":"+1 337 367 5102",
    "sg:postcode":"70560",
    "sg:province":"LA",
    "sg:tags":[
        "outboard",
        "motor"
    ],
    "wof:name":"Perez Marine Svc",
    "wof:placetype":"venue"
},
  "geometry": {"coordinates":[-91.786592,29.921689],"type":"Point"}
}