{
  "type": "Feature",
  "properties": {
    "iso:country":"US",
    "sg:address":"3300 Eton St",
    "sg:city":"New Orleans",
    "sg:classifiers":[
        {
            "category":"Organizations",
            "subcategory":"Religious Organization",
            "type":"Services"
        }
    ],
    "sg:phone":"+1 504 394 5483",
    "sg:postcode":"70131",
    "sg:province":"LA",
    "sg:tags":[
        "elementary",
        "school",
        "church"
    ],
    "sg:website":"www.auroraumc.com",
    "wof:name":"Aurora United Methodist Church",
    "wof:placetype":"venue"
},
  "geometry": {"coordinates":[-89.997902,29.9193],"type":"Point"}
}