{
  "type": "Feature",
  "properties": {
    "iso:country":"US",
    "sg:address":"4515 Feliciana Dr",
    "sg:city":"New Orleans",
    "sg:classifiers":[
        {
            "category":"Freight",
            "type":"Transportation"
        }
    ],
    "sg:phone":"+1 504 283 0326",
    "sg:postcode":"70126",
    "sg:province":"LA",
    "sg:tags":[
        "mover"
    ],
    "wof:name":"C Delandro & Son Moving",
    "wof:placetype":"venue"
},
  "geometry": {"coordinates":[-90.040237,30.009685],"type":"Point"}
}