{
  "type": "Feature",
  "properties": {
    "addr:full":"3688 Clayton Dr Baton Rouge LA 70805",
    "addr:housenumber":"3688",
    "addr:postcode":"70805",
    "addr:street":"Clayton Dr",
    "iso:country":"US",
    "sg:address":"3688 Clayton Dr",
    "sg:city":"Baton Rouge",
    "sg:classifiers":[
        {
            "category":"Organizations",
            "subcategory":"Religious Organization",
            "type":"Services"
        }
    ],
    "sg:phone":"+1 225 357 2029",
    "sg:postcode":"70805",
    "sg:province":"LA",
    "sg:tags":[
        "church"
    ],
    "wof:name":"Harvest Life Ctr",
    "wof:placetype":"venue"
},
  "geometry": {"coordinates":[-91.155933,30.490748],"type":"Point"}
}