{
  "type": "Feature",
  "properties": {
    "iso:country":"US",
    "sg:address":"100 Rowley Blvd",
    "sg:city":"Arabi",
    "sg:classifiers":[
        {
            "category":"Real Estate",
            "subcategory":"Developer",
            "type":"Services"
        }
    ],
    "sg:phone":"+1 504 279 0421",
    "sg:postcode":"70032",
    "sg:province":"LA",
    "wof:name":"Fred J Sigur Realty Co",
    "wof:placetype":"venue"
},
  "geometry": {"coordinates":[-89.995136,29.954096],"type":"Point"}
}