{
  "type": "Feature",
  "properties": {
    "iso:country":"US",
    "sg:address":"506 N Kinney Ave",
    "sg:city":"Iowa",
    "sg:classifiers":[
        {
            "category":"Social Services",
            "subcategory":"Adult Care",
            "type":"Services"
        }
    ],
    "sg:phone":"+1 337 582 1592",
    "sg:postcode":"70647",
    "sg:province":"LA",
    "sg:tags":[
        "organization",
        "senior",
        "citizen"
    ],
    "wof:name":"Town Of Iowa",
    "wof:placetype":"venue"
},
  "geometry": {"coordinates":[-93.01221,30.243583],"type":"Point"}
}