{
  "type": "Feature",
  "properties": {
    "addr:full":"804 E Saint Mary Blvd Lafayette LA 70503",
    "addr:housenumber":"804",
    "addr:postcode":"70503",
    "addr:street":"E Saint Mary Blvd",
    "iso:country":"US",
    "sg:address":"804 E Saint Mary Blvd",
    "sg:city":"Lafayette",
    "sg:classifiers":[
        {
            "category":"Organizations",
            "subcategory":"Professional Association",
            "type":"Services"
        }
    ],
    "sg:phone":"+1 337 233 2705",
    "sg:postcode":"70503",
    "sg:province":"LA",
    "sg:tags":[
        "chambers",
        "commerce"
    ],
    "sg:website":"www.lafchamber.org",
    "wof:name":"Greater Lafayette Chamber",
    "wof:placetype":"venue"
},
  "geometry": {"coordinates":[-92.01447400000001,30.208898],"type":"Point"}
}