{
  "type": "Feature",
  "properties": {
    "addr:full":"1304 Bertrand Dr Lafayette LA 70506",
    "addr:housenumber":"1304",
    "addr:postcode":"70506",
    "addr:street":"Bertrand Dr",
    "iso:country":"US",
    "sg:address":"1304 Bertrand Dr",
    "sg:city":"Lafayette",
    "sg:classifiers":[
        {
            "category":"Professional",
            "subcategory":"Business Services",
            "type":"Services"
        }
    ],
    "sg:phone":"+1 337 232 5664",
    "sg:postcode":"70506",
    "sg:province":"LA",
    "sg:tags":[
        "transcribing",
        "disc"
    ],
    "wof:name":"Transcription Express Inc",
    "wof:placetype":"venue"
},
  "geometry": {"coordinates":[-92.051439,30.22153],"type":"Point"}
}