{
  "type": "Feature",
  "properties": {
    "iso:country":"US",
    "sg:address":"817 Common St",
    "sg:city":"New Orleans",
    "sg:classifiers":[
        {
            "category":"Travel",
            "subcategory":"Hotels & Motels",
            "type":"Entertainment"
        }
    ],
    "sg:phone":"+1 504 525 1111",
    "sg:postcode":"70130",
    "sg:province":"LA",
    "sg:website":"www.marriott.com",
    "wof:name":"Renaissance Pere Marquette",
    "wof:placetype":"venue"
},
  "geometry": {"coordinates":[-90.071782,29.953288],"type":"Point"}
}