{
  "type": "Feature",
  "properties": {
    "iso:country":"US",
    "sg:address":"1050 Robert Blvd",
    "sg:city":"Slidell",
    "sg:classifiers":[
        {
            "category":"Education",
            "subcategory":"School",
            "type":"Public Place"
        }
    ],
    "sg:phone":"+1 985 643 4612",
    "sg:postcode":"70458",
    "sg:province":"LA",
    "sg:website":"www.saintmm.org",
    "wof:name":"St Margaret Mary School",
    "wof:placetype":"venue"
},
  "geometry": {"coordinates":[-89.77070500000001,30.288907],"type":"Point"}
}