{
  "type": "Feature",
  "properties": {
    "iso:country":"US",
    "sg:address":"107 Georgetown Loop",
    "sg:city":"Lafayette",
    "sg:classifiers":[
        {
            "category":"Professional",
            "subcategory":"Management & Consulting",
            "type":"Services"
        }
    ],
    "sg:phone":"+1 337 984 4940",
    "sg:postcode":"70506",
    "sg:province":"LA",
    "sg:tags":[
        "research"
    ],
    "wof:name":"Judith Angers",
    "wof:placetype":"venue"
},
  "geometry": {"coordinates":[-92.09790700000001,30.211031],"type":"Point"}
}