{
  "type": "Feature",
  "properties": {
    "iso:country":"US",
    "sg:address":"2058 Hwy 139",
    "sg:city":"Monroe",
    "sg:classifiers":[
        {
            "category":"Food & Beverages",
            "subcategory":"Groceries & Convenience Stores",
            "type":"Retail Goods"
        }
    ],
    "sg:phone":"+1 318 345 0275",
    "sg:postcode":"71203",
    "sg:province":"LA",
    "sg:tags":[
        "grocer"
    ],
    "wof:name":"Dave's U-Pack-It",
    "wof:placetype":"venue"
},
  "geometry": {"coordinates":[-91.98959600000001,32.58029],"type":"Point"}
}