{
  "type": "Feature",
  "properties": {
    "addr:full":"1101 Abraham Roy St New Iberia LA 70560",
    "addr:housenumber":"1101",
    "addr:postcode":"70560",
    "addr:street":"Abraham Roy St",
    "iso:country":"US",
    "sg:address":"1101 Abraham Roy St",
    "sg:city":"New Iberia",
    "sg:classifiers":[
        {
            "category":"Food & Beverages",
            "subcategory":"Groceries & Convenience Stores",
            "type":"Retail Goods"
        }
    ],
    "sg:phone":"+1 337 365 8735",
    "sg:postcode":"70560",
    "sg:province":"LA",
    "wof:name":"Moss Convenience Store",
    "wof:placetype":"venue"
},
  "geometry": {"coordinates":[-91.83243299999999,30.011799],"type":"Point"}
}