{
  "type": "Feature",
  "properties": {
    "addr:full":"8132 Lockhart Rd Denham Springs LA 70726",
    "addr:housenumber":"8132",
    "addr:postcode":"70726",
    "addr:street":"Lockhart Rd",
    "iso:country":"US",
    "sg:address":"8132 Lockhart Rd",
    "sg:city":"Denham Springs",
    "sg:classifiers":[
        {
            "category":"Building & Trades",
            "subcategory":"Pest Control",
            "type":"Services"
        }
    ],
    "sg:phone":"+1 225 664 4621",
    "sg:postcode":"70726",
    "sg:province":"LA",
    "wof:name":"Willie's Pest Control Inc",
    "wof:placetype":"venue"
},
  "geometry": {"coordinates":[-90.95399399999999,30.527364],"type":"Point"}
}