{
  "type": "Feature",
  "properties": {
    "iso:country":"US",
    "sg:address":"4877 State Rte 15",
    "sg:city":"Winnsboro",
    "sg:phone":"+1 318 435 5605",
    "sg:postcode":"71295",
    "sg:province":"LA",
    "sg:tags":[
        "gas"
    ],
    "wof:name":"Herring Gas Co",
    "wof:placetype":"venue"
},
  "geometry": {"coordinates":[-91.705704,32.129488],"type":"Point"}
}