{
  "type": "Feature",
  "properties": {
    "iso:country":"US",
    "sg:address":"3825 Hessmer Ave",
    "sg:city":"Metairie",
    "sg:classifiers":[
        {
            "category":"Retail",
            "subcategory":"Veterinary Services",
            "type":"Services"
        }
    ],
    "sg:phone":"+1 504 834 2023",
    "sg:postcode":"70002",
    "sg:province":"LA",
    "sg:tags":[
        "veterinarian"
    ],
    "wof:name":"Natural Pet Care",
    "wof:placetype":"venue"
},
  "geometry": {"coordinates":[-90.163298,30.009731],"type":"Point"}
}