{
  "type": "Feature",
  "properties": {
    "iso:country":"US",
    "sg:address":"1901 Manhattan Blvd",
    "sg:city":"Harvey",
    "sg:classifiers":[
        {
            "category":"Building & Trades",
            "subcategory":"Construction",
            "type":"Services"
        }
    ],
    "sg:phone":"+1 504 644 4025",
    "sg:postcode":"70058",
    "sg:province":"LA",
    "sg:tags":[
        "contractor"
    ],
    "wof:name":"Cetco Oil Field Services",
    "wof:placetype":"venue"
},
  "geometry": {"coordinates":[-90.055114,29.886811],"type":"Point"}
}