{
  "type": "Feature",
  "properties": {
    "iso:country":"US",
    "sg:address":"213 S Doyle St",
    "sg:city":"Jennings",
    "sg:classifiers":[
        {
            "category":"Organizations",
            "subcategory":"Religious Organization",
            "type":"Services"
        }
    ],
    "sg:phone":"+1 337 824 4432",
    "sg:postcode":"70546",
    "sg:province":"LA",
    "sg:tags":[
        "church"
    ],
    "wof:name":"Faith Tabernacle",
    "wof:placetype":"venue"
},
  "geometry": {"coordinates":[-92.661359,30.219606],"type":"Point"}
}