{
  "type": "Feature",
  "properties": {
    "iso:country":"US",
    "sg:address":"9513 Amanda Dr",
    "sg:city":"Greenwood",
    "sg:classifiers":[
        {
            "category":"Retail",
            "subcategory":"Repair Shop",
            "type":"Services"
        }
    ],
    "sg:phone":"+1 318 938 4207",
    "sg:postcode":"71033",
    "sg:province":"LA",
    "sg:tags":[
        "taxidermist"
    ],
    "wof:name":"Nature's Creations Taxidermy",
    "wof:placetype":"venue"
},
  "geometry": {"coordinates":[-94.010105,32.446855],"type":"Point"}
}