{
  "type": "Feature",
  "properties": {
    "iso:country":"US",
    "sg:address":"122 Buckingham St",
    "sg:city":"La Place",
    "sg:classifiers":[
        {
            "category":"Professional",
            "subcategory":"Business Services",
            "type":"Services"
        }
    ],
    "sg:phone":"+1 985 651 3875",
    "sg:postcode":"70068",
    "sg:province":"LA",
    "wof:name":"R&R Foresight Enterprise LLC",
    "wof:placetype":"venue"
},
  "geometry": {"coordinates":[-90.43317399999999,30.060008],"type":"Point"}
}