{
  "type": "Feature",
  "properties": {
    "iso:country":"US",
    "sg:address":"510 Pine St",
    "sg:city":"Monroe",
    "sg:classifiers":[
        {
            "category":"Personal",
            "subcategory":"Beauty Salon",
            "type":"Services"
        }
    ],
    "sg:phone":"+1 318 699 0555",
    "sg:postcode":"71201",
    "sg:province":"LA",
    "sg:tags":[
        "shop"
    ],
    "wof:name":"Eclipse Salon",
    "wof:placetype":"venue"
},
  "geometry": {"coordinates":[-92.116495,32.50883],"type":"Point"}
}