{
  "type": "Feature",
  "properties": {
    "iso:country":"US",
    "sg:address":"3062 E Texas St",
    "sg:city":"Bossier City",
    "sg:classifiers":[
        {
            "category":"Retail",
            "subcategory":"Auto Repair",
            "type":"Services"
        }
    ],
    "sg:phone":"+1 318 742 3778",
    "sg:postcode":"71111",
    "sg:province":"LA",
    "sg:tags":[
        "muffler",
        "exhaust",
        "system"
    ],
    "wof:name":"Midas Auto Svc Experts",
    "wof:placetype":"venue"
},
  "geometry": {"coordinates":[-93.694005,32.528663],"type":"Point"}
}