{
  "type": "Feature",
  "properties": {
    "addr:full":"2401 Louisville Ave Monroe LA 71201",
    "addr:housenumber":"2401",
    "addr:postcode":"71201",
    "addr:street":"Louisville Ave",
    "iso:country":"US",
    "sg:address":"2401 Louisville Ave",
    "sg:city":"Monroe",
    "sg:classifiers":[
        {
            "category":"Restaurant",
            "type":"Food & Drink"
        }
    ],
    "sg:menulink":"http://www.allmenus.com/la/monroe/197545-burger-king/menu/",
    "sg:phone":"+1 318 322 3723",
    "sg:postcode":"71201",
    "sg:province":"LA",
    "sg:tags":[
        "burger",
        "american"
    ],
    "wof:name":"Burger King",
    "wof:placetype":"venue"
},
  "geometry": {"coordinates":[-92.09963,32.522049],"type":"Point"}
}