{
  "type": "Feature",
  "properties": {
    "iso:country":"US",
    "sg:address":"725 Cotton St",
    "sg:city":"Shreveport",
    "sg:classifiers":[
        {
            "category":"Organizations",
            "subcategory":"Community Association",
            "type":"Services"
        }
    ],
    "sg:phone":"+1 318 221 9713",
    "sg:postcode":"71101",
    "sg:province":"LA",
    "sg:tags":[
        "fraternal"
    ],
    "wof:name":"Scottish Rite Temple",
    "wof:placetype":"venue"
},
  "geometry": {"coordinates":[-93.749865,32.508427],"type":"Point"}
}