{
  "type": "Feature",
  "properties": {
    "iso:country":"US",
    "sg:address":"1722 Common St",
    "sg:city":"Lake Charles",
    "sg:classifiers":[
        {
            "category":"Wholesale",
            "subcategory":"Electrical",
            "type":"Manufacturing & Wholesale Goods"
        }
    ],
    "sg:phone":"+1 337 439 2431",
    "sg:postcode":"70601",
    "sg:province":"LA",
    "sg:tags":[
        "equipment",
        "electronic",
        "supply"
    ],
    "wof:name":"Menard Electronics Inc",
    "wof:placetype":"venue"
},
  "geometry": {"coordinates":[-93.214097,30.216936],"type":"Point"}
}