{
  "type": "Feature",
  "properties": {
    "iso:country":"US",
    "sg:address":"9320 Burbank Dr",
    "sg:city":"Baton Rouge",
    "sg:classifiers":[
        {
            "category":"Restaurant",
            "type":"Food & Drink"
        }
    ],
    "sg:phone":"+1 225 767 8766",
    "sg:postcode":"70820",
    "sg:province":"LA",
    "sg:tags":[
        "barbecue"
    ],
    "wof:name":"Cou Yons Fatru Texas Bbq",
    "wof:placetype":"venue"
},
  "geometry": {"coordinates":[-91.123999,30.360253],"type":"Point"}
}