{
  "type": "Feature",
  "properties": {
    "iso:country":"US",
    "sg:address":"543 E Plaquemine St",
    "sg:city":"Jennings",
    "sg:classifiers":[
        {
            "category":"Personal",
            "subcategory":"Beauty Salon",
            "type":"Services"
        }
    ],
    "sg:phone":"+1 337 824 4357",
    "sg:postcode":"70546",
    "sg:province":"LA",
    "sg:tags":[
        "shop"
    ],
    "wof:name":"Head Lines Hair Designs",
    "wof:placetype":"venue"
},
  "geometry": {"coordinates":[-92.651779,30.22255],"type":"Point"}
}