{
  "type": "Feature",
  "properties": {
    "iso:country":"US",
    "sg:address":"401 Spruce St",
    "sg:city":"Norco",
    "sg:classifiers":[
        {
            "category":"Organizations",
            "subcategory":"Religious Organization",
            "type":"Services"
        }
    ],
    "sg:phone":"+1 985 764 6503",
    "sg:postcode":"70079",
    "sg:province":"LA",
    "sg:tags":[
        "church"
    ],
    "sg:website":"www.sacredheartchurchnorco.org",
    "wof:name":"Sacred Heart Of Jesus",
    "wof:placetype":"venue"
},
  "geometry": {"coordinates":[-90.417182,30.006376],"type":"Point"}
}