{
  "type": "Feature",
  "properties": {
    "addr:full":"3005 Harvard Ave Metairie LA 70006",
    "addr:housenumber":"3005",
    "addr:postcode":"70006",
    "addr:street":"Harvard Ave",
    "iso:country":"US",
    "sg:address":"3005 Harvard Ave",
    "sg:city":"Metairie",
    "sg:classifiers":[
        {
            "category":"Health Services",
            "subcategory":"Clinic",
            "type":"Services"
        }
    ],
    "sg:phone":"+1 504 455 3726",
    "sg:postcode":"70006",
    "sg:province":"LA",
    "sg:tags":[
        "organization",
        "dentist"
    ],
    "wof:name":"Gulf Coast Dental Plan Inc",
    "wof:placetype":"venue"
},
  "geometry": {"coordinates":[-90.189691,30.003334],"type":"Point"}
}