{
  "type": "Feature",
  "properties": {
    "iso:country":"US",
    "sg:address":"3640 W Esplanade Ave S",
    "sg:city":"Metairie",
    "sg:classifiers":[
        {
            "category":"Retail",
            "subcategory":"Veterinary Services",
            "type":"Services"
        }
    ],
    "sg:phone":"+1 504 455 6386",
    "sg:postcode":"70002",
    "sg:province":"LA",
    "sg:tags":[
        "veterinarian"
    ],
    "sg:website":"www.gregrichdvm.com",
    "wof:name":"West Esplanade Veterinary Clnc",
    "wof:placetype":"venue"
},
  "geometry": {"coordinates":[-90.16365500000001,30.014534],"type":"Point"}
}