{
  "type": "Feature",
  "properties": {
    "addr:full":"3218 Timberlane Dr Shreveport LA 71107",
    "addr:housenumber":"3218",
    "addr:postcode":"71107",
    "addr:street":"Timberlane Dr",
    "iso:country":"US",
    "sg:address":"3218 Timberlane Dr",
    "sg:city":"Shreveport",
    "sg:classifiers":[
        {
            "category":"Professional",
            "subcategory":"Business Services",
            "type":"Services"
        }
    ],
    "sg:phone":"+1 318 222 7088",
    "sg:postcode":"71107",
    "sg:province":"LA",
    "sg:tags":[
        "notary"
    ],
    "wof:name":"Hall Notary",
    "wof:placetype":"venue"
},
  "geometry": {"coordinates":[-93.78157400000001,32.564359],"type":"Point"}
}