{
  "type": "Feature",
  "properties": {
    "iso:country":"US",
    "sg:address":"829 Saint Charles Ave",
    "sg:city":"New Orleans",
    "sg:classifiers":[
        {
            "category":"Professional",
            "subcategory":"Advertising",
            "type":"Services"
        }
    ],
    "sg:phone":"+1 504 558 3940",
    "sg:postcode":"70130",
    "sg:province":"LA",
    "wof:name":"EMERILS'S.COM",
    "wof:placetype":"venue"
},
  "geometry": {"coordinates":[-90.072079,29.944839],"type":"Point"}
}