{
  "type": "Feature",
  "properties": {
    "iso:country":"US",
    "sg:address":"28665 Cowart Rd",
    "sg:city":"Holden",
    "sg:classifiers":[
        {
            "category":"Retail",
            "subcategory":"Repair Shop",
            "type":"Services"
        }
    ],
    "sg:phone":"+1 225 567 2239",
    "sg:postcode":"70744",
    "sg:province":"LA",
    "wof:name":"Charles De Mars TV & Elec",
    "wof:placetype":"venue"
},
  "geometry": {"coordinates":[-90.604995,30.485335],"type":"Point"}
}