{
  "type": "Feature",
  "properties": {
    "iso:country":"US",
    "sg:address":"175 Porter St",
    "sg:city":"New Iberia",
    "sg:classifiers":[
        {
            "category":"Education",
            "subcategory":"School",
            "type":"Public Place"
        }
    ],
    "sg:phone":"+1 337 369 6764",
    "sg:postcode":"70560",
    "sg:province":"LA",
    "wof:name":"St Edward Catholic School",
    "wof:placetype":"venue"
},
  "geometry": {"coordinates":[-91.82530300000001,30.002403],"type":"Point"}
}