{
  "type": "Feature",
  "properties": {
    "iso:country":"US",
    "sg:address":"2223 Old Minden Rd",
    "sg:city":"Bossier City",
    "sg:classifiers":[
        {
            "category":"Banks & Credit Unions",
            "subcategory":"Investment Brokerage",
            "type":"Services"
        }
    ],
    "sg:phone":"+1 318 741 0085",
    "sg:postcode":"71112",
    "sg:province":"LA",
    "sg:tags":[
        "stock",
        "bond"
    ],
    "wof:name":"Edward Jones Co",
    "wof:placetype":"venue"
},
  "geometry": {"coordinates":[-93.704064,32.519329],"type":"Point"}
}