{
  "type": "Feature",
  "properties": {
    "addr:full":"10222 Oliphant Rd Baton Rouge LA 70809",
    "addr:housenumber":"10222",
    "addr:postcode":"70809",
    "addr:street":"Oliphant Rd",
    "iso:country":"US",
    "sg:address":"10222 Oliphant Rd",
    "sg:city":"Baton Rouge",
    "sg:classifiers":[
        {
            "category":"Building & Trades",
            "subcategory":"Construction",
            "type":"Services"
        }
    ],
    "sg:phone":"+1 225 292 7233",
    "sg:postcode":"70809",
    "sg:province":"LA",
    "sg:tags":[
        "house"
    ],
    "wof:name":"Portias Properties Inc",
    "wof:placetype":"venue"
},
  "geometry": {"coordinates":[-91.070346,30.402678],"type":"Point"}
}