{
  "type": "Feature",
  "properties": {
    "iso:country":"US",
    "sg:address":"946 Jefferson Hwy",
    "sg:city":"Jefferson",
    "sg:classifiers":[
        {
            "category":"Organizations",
            "subcategory":"Community Association",
            "type":"Services"
        }
    ],
    "sg:phone":"+1 504 833 5117",
    "sg:postcode":"70121",
    "sg:province":"LA",
    "sg:tags":[
        "fraternal"
    ],
    "wof:name":"952 Corp",
    "wof:placetype":"venue"
},
  "geometry": {"coordinates":[-90.13825799999999,29.96528],"type":"Point"}
}