{
  "type": "Feature",
  "properties": {
    "addr:full":"2100 Ames Blvd Marrero LA 70072",
    "addr:housenumber":"2100",
    "addr:postcode":"70072",
    "addr:street":"Ames Blvd Marrero",
    "iso:country":"US",
    "sg:address":"2100 Ames Blvd",
    "sg:city":"Marrero",
    "sg:classifiers":[
        {
            "category":"Organizations",
            "subcategory":"Religious Organization",
            "type":"Services"
        }
    ],
    "sg:phone":"+1 504 244 6800",
    "sg:postcode":"70072",
    "sg:province":"LA",
    "sg:tags":[
        "church"
    ],
    "wof:name":"Greater St Stephen Full Gospel",
    "wof:placetype":"venue"
},
  "geometry": {"coordinates":[-90.110969,29.866581],"type":"Point"}
}