{
  "type": "Feature",
  "properties": {
    "addr:full":"1621 Generes Dr New Orleans LA 70123",
    "addr:housenumber":"1621",
    "addr:postcode":"70123",
    "addr:street":"Generes Dr",
    "iso:country":"US",
    "sg:address":"1621 Generes Dr",
    "sg:city":"New Orleans",
    "sg:classifiers":[
        {
            "category":"Building & Trades",
            "subcategory":"Plumbing",
            "type":"Services"
        }
    ],
    "sg:phone":"+1 504 305 3405",
    "sg:postcode":"70123",
    "sg:province":"LA",
    "sg:tags":[
        "sheet",
        "work",
        "metal",
        "contractor"
    ],
    "wof:name":"National Sheet Metal Svc",
    "wof:placetype":"venue"
},
  "geometry": {"coordinates":[-90.2062,29.962397],"type":"Point"}
}