{
  "type": "Feature",
  "properties": {
    "iso:country":"US",
    "sg:address":"4611 Lawndale Dr",
    "sg:city":"Benton",
    "sg:classifiers":[
        {
            "category":"Wholesale",
            "subcategory":"Machinery & Supplies",
            "type":"Manufacturing & Wholesale Goods"
        }
    ],
    "sg:phone":"+1 318 965 2265",
    "sg:postcode":"71006",
    "sg:province":"LA",
    "sg:tags":[
        "field",
        "oil"
    ],
    "wof:name":"Rockbit International Inc",
    "wof:placetype":"venue"
},
  "geometry": {"coordinates":[-93.716346,32.652806],"type":"Point"}
}