{
  "type": "Feature",
  "properties": {
    "iso:country":"US",
    "sg:address":"13974 Tech Dr",
    "sg:city":"Baton Rouge",
    "sg:classifiers":[
        {
            "category":"Building & Trades",
            "subcategory":"Electrical",
            "type":"Services"
        }
    ],
    "sg:phone":"+1 225 937 4587",
    "sg:postcode":"70818",
    "sg:province":"LA",
    "sg:tags":[
        "electrical",
        "contractor"
    ],
    "wof:name":"Ty Electric LLC",
    "wof:placetype":"venue"
},
  "geometry": {"coordinates":[-91.036906,30.556749],"type":"Point"}
}