{
  "type": "Feature",
  "properties": {
    "iso:country":"US",
    "sg:address":"312 Live Oak St",
    "sg:city":"Metairie",
    "sg:classifiers":[
        {
            "category":"Building & Trades",
            "subcategory":"Construction",
            "type":"Services"
        }
    ],
    "sg:phone":"+1 504 837 9111",
    "sg:postcode":"70005",
    "sg:province":"LA",
    "sg:tags":[
        "general",
        "contractor"
    ],
    "wof:name":"Jay Louvier Construction Co",
    "wof:placetype":"venue"
},
  "geometry": {"coordinates":[-90.124803,30.018139],"type":"Point"}
}