{
  "type": "Feature",
  "properties": {
    "addr:full":"2180 N Lobdell Ave Baton Rouge LA 70806",
    "addr:housenumber":"2180",
    "addr:postcode":"70806",
    "addr:street":"N Lobdell Ave",
    "iso:country":"US",
    "sg:address":"2180 N Lobdell Ave",
    "sg:city":"Baton Rouge",
    "sg:classifiers":[
        {
            "category":"Food & Beverages",
            "subcategory":"Groceries & Convenience Stores",
            "type":"Retail Goods"
        }
    ],
    "sg:phone":"+1 225 927 1366",
    "sg:postcode":"70806",
    "sg:province":"LA",
    "wof:name":"Circle K",
    "wof:placetype":"venue"
},
  "geometry": {"coordinates":[-91.117525,30.464141],"type":"Point"}
}