{
  "type": "Feature",
  "properties": {
    "iso:country":"US",
    "sg:address":"3629 Lake Aspen Dr W",
    "sg:city":"Gretna",
    "sg:classifiers":[
        {
            "category":"Professional",
            "subcategory":"Business Services",
            "type":"Services"
        }
    ],
    "sg:phone":"+1 504 394 2322",
    "sg:postcode":"70056",
    "sg:province":"LA",
    "wof:name":"Sumrall Studio",
    "wof:placetype":"venue"
},
  "geometry": {"coordinates":[-90.03308199999999,29.85559],"type":"Point"}
}