{
  "type": "Feature",
  "properties": {
    "addr:full":"1501 Flood St New Orleans LA 70117",
    "addr:housenumber":"1501",
    "addr:postcode":"70117",
    "addr:street":"Flood St",
    "iso:country":"US",
    "sg:address":"1501 Flood St",
    "sg:city":"New Orleans",
    "sg:classifiers":[
        {
            "category":"Professional",
            "subcategory":"Employment Agencies",
            "type":"Services"
        }
    ],
    "sg:phone":"+1 504 616 5215",
    "sg:postcode":"70117",
    "sg:province":"LA",
    "wof:name":"Unlimited Services Employment",
    "wof:placetype":"venue"
},
  "geometry": {"coordinates":[-90.015277,29.966143],"type":"Point"}
}