{
  "type": "Feature",
  "properties": {
    "addr:full":"501 E Texas Ave Ruston LA 71270",
    "addr:housenumber":"501",
    "addr:postcode":"71270",
    "addr:street":"E Texas Ave",
    "iso:country":"US",
    "sg:address":"501 E Texas Ave",
    "sg:city":"Ruston",
    "sg:classifiers":[
        {
            "category":"Professional",
            "type":"Services"
        }
    ],
    "sg:phone":"+1 318 251 2806",
    "sg:postcode":"71270",
    "sg:province":"LA",
    "sg:tags":[
        "establishment"
    ],
    "wof:name":"Aber Lee Ofc",
    "wof:placetype":"venue"
},
  "geometry": {"coordinates":[-92.632244,32.526354],"type":"Point"}
}