{
  "type": "Feature",
  "properties": {
    "addr:full":"17510 W Main St Galliano LA 70354",
    "addr:housenumber":"17510",
    "addr:postcode":"70354",
    "addr:street":"W Main St",
    "iso:country":"US",
    "sg:address":"17510 W Main St",
    "sg:city":"Galliano",
    "sg:classifiers":[
        {
            "category":"Retail",
            "subcategory":"Car Wash",
            "type":"Services"
        }
    ],
    "sg:phone":"+1 985 632 8197",
    "sg:postcode":"70354",
    "sg:province":"LA",
    "sg:tags":[
        "polishing",
        "washing"
    ],
    "wof:name":"L A Detailing",
    "wof:placetype":"venue"
},
  "geometry": {"coordinates":[-90.303658,29.448729],"type":"Point"}
}