{
  "type": "Feature",
  "properties": {
    "iso:country":"US",
    "sg:address":"7235 Jefferson Hwy",
    "sg:city":"Baton Rouge",
    "sg:classifiers":[
        {
            "category":"Professional",
            "subcategory":"Lawyer & Legal Services",
            "type":"Services"
        }
    ],
    "sg:phone":"+1 225 928 1112",
    "sg:postcode":"70806",
    "sg:province":"LA",
    "sg:tags":[
        "attorney"
    ],
    "wof:name":"Law Office",
    "wof:placetype":"venue"
},
  "geometry": {"coordinates":[-91.116106,30.434053],"type":"Point"}
}