{
  "type": "Feature",
  "properties": {
    "addr:full":"329 Florida St Baton Rouge LA 70801",
    "addr:housenumber":"329",
    "addr:postcode":"70801",
    "addr:street":"Florida St",
    "iso:country":"US",
    "sg:address":"329 Florida St",
    "sg:city":"Baton Rouge",
    "sg:classifiers":[
        {
            "category":"Cafe",
            "type":"Food & Drink"
        },
        {
            "category":"Restaurant",
            "type":"Food & Drink"
        }
    ],
    "sg:menulink":"http://www.allmenus.com/la/baton-rouge/21746-harringtons-cafe/menu/",
    "sg:phone":"+1 225 343 2626",
    "sg:postcode":"70801",
    "sg:province":"LA",
    "sg:tags":[
        "american",
        "southern"
    ],
    "wof:name":"Harrington's Cafe",
    "wof:placetype":"venue"
},
  "geometry": {"coordinates":[-91.18786900000001,30.44931],"type":"Point"}
}