{
  "type": "Feature",
  "properties": {
    "iso:country":"US",
    "sg:address":"231 Sunset Ave",
    "sg:city":"Houma",
    "sg:classifiers":[
        {
            "category":"Retail",
            "subcategory":"Auto Repair",
            "type":"Services"
        }
    ],
    "sg:phone":"+1 985 876 9918",
    "sg:postcode":"70360",
    "sg:province":"LA",
    "sg:tags":[
        "repairing",
        "automobile"
    ],
    "wof:name":"Bow 2 Stern Svc",
    "wof:placetype":"venue"
},
  "geometry": {"coordinates":[-90.72495000000001,29.586408],"type":"Point"}
}