{
  "type": "Feature",
  "properties": {
    "addr:full":"5924 Common St Lake Charles LA 70607",
    "addr:housenumber":"5924",
    "addr:postcode":"70607",
    "addr:street":"Common St",
    "iso:country":"US",
    "sg:address":"5924 Common St",
    "sg:city":"Lake Charles",
    "sg:classifiers":[
        {
            "category":"Professional",
            "subcategory":"Business Services",
            "type":"Services"
        }
    ],
    "sg:phone":"+1 337 477 2502",
    "sg:postcode":"70607",
    "sg:province":"LA",
    "sg:tags":[
        "notary"
    ],
    "wof:name":"B Smart Notary Svc",
    "wof:placetype":"venue"
},
  "geometry": {"coordinates":[-93.213841,30.15359],"type":"Point"}
}