{
  "type": "Feature",
  "properties": {
    "addr:full":"823 Decatur St New Orleans LA 70116",
    "addr:housenumber":"823",
    "addr:postcode":"70116",
    "addr:street":"Decatur St",
    "iso:country":"US",
    "sg:address":"823 Decatur St",
    "sg:city":"New Orleans",
    "sg:classifiers":[
        {
            "category":"Restaurant",
            "type":"Food & Drink"
        }
    ],
    "sg:phone":"+1 504 525 8676",
    "sg:postcode":"70116",
    "sg:province":"LA",
    "sg:tags":[
        "cajun/creole"
    ],
    "sg:website":"www.tujaguesrestaurant.com/",
    "wof:name":"Tujague's Restaurant",
    "wof:placetype":"venue"
},
  "geometry": {"coordinates":[-90.0616,29.958099],"type":"Point"}
}