{
  "type": "Feature",
  "properties": {
    "addr:full":"602 W Prien Lake Rd Lake Charles LA 70601",
    "addr:housenumber":"602",
    "addr:postcode":"70601",
    "addr:street":"W Prien Lake Rd",
    "iso:country":"US",
    "sg:address":"602 W Prien Lake Rd",
    "sg:city":"Lake Charles",
    "sg:classifiers":[
        {
            "category":"Building & Trades",
            "subcategory":"Construction",
            "type":"Services"
        }
    ],
    "sg:phone":"+1 337 433 6883",
    "sg:postcode":"70601",
    "sg:province":"LA",
    "sg:tags":[
        "general",
        "contractor"
    ],
    "wof:name":"Abshire Contracting Svc Inc",
    "wof:placetype":"venue"
},
  "geometry": {"coordinates":[-93.23058399999999,30.198169],"type":"Point"}
}