{
  "type": "Feature",
  "properties": {
    "iso:country":"US",
    "sg:address":"3152 Hwy 1",
    "sg:city":"Grand Isle",
    "sg:classifiers":[
        {
            "category":"Restaurant",
            "type":"Food & Drink"
        }
    ],
    "sg:phone":"+1 985 787 2000",
    "sg:postcode":"70358",
    "sg:province":"LA",
    "wof:name":"Beav's Bar B Que",
    "wof:placetype":"venue"
},
  "geometry": {"coordinates":[-89.998718,29.230432],"type":"Point"}
}