{
  "type": "Feature",
  "properties": {
    "addr:full":"120 Reagan St Pineville LA 71360",
    "addr:housenumber":"120",
    "addr:postcode":"71360",
    "addr:street":"Reagan St",
    "iso:country":"US",
    "sg:address":"120 Reagan St",
    "sg:city":"Pineville",
    "sg:classifiers":[
        {
            "category":"Shopping",
            "type":"Retail Goods"
        }
    ],
    "sg:phone":"+1 318 443 3889",
    "sg:postcode":"71360",
    "sg:province":"LA",
    "sg:tags":[
        "miscellaneous",
        "store"
    ],
    "wof:name":"Blue Bead Alterations",
    "wof:placetype":"venue"
},
  "geometry": {"coordinates":[-92.43228000000001,31.323534],"type":"Point"}
}