{
  "type": "Feature",
  "properties": {
    "addr:full":"1050 Bert Kouns Industrial Loop Shreveport LA 71118",
    "addr:housenumber":"1050",
    "addr:postcode":"71118",
    "addr:street":"Bert Kouns Industrial Loop",
    "iso:country":"US",
    "sg:address":"1050 Bert Kouns Industrial Loop",
    "sg:city":"Shreveport",
    "sg:classifiers":[
        {
            "category":"Place Of Worship",
            "subcategory":"Church",
            "type":"Public Place"
        }
    ],
    "sg:phone":"+1 318 687 5121",
    "sg:postcode":"71118",
    "sg:province":"LA",
    "sg:tags":[
        "churches-catholic"
    ],
    "sg:website":"http://www.stmops.org",
    "wof:name":"Saint Mary Of The Pines Catholic Church",
    "wof:placetype":"venue"
},
  "geometry": {"coordinates":[-93.780736,32.401513],"type":"Point"}
}