{
  "type": "Feature",
  "properties": {
    "iso:country":"US",
    "sg:address":"303 Bienville St",
    "sg:city":"Natchitoches",
    "sg:classifiers":[
        {
            "category":"Social Services",
            "subcategory":"Job Training",
            "type":"Services"
        }
    ],
    "sg:phone":"+1 318 357 3145",
    "sg:postcode":"71457",
    "sg:province":"LA",
    "sg:tags":[
        "rehab",
        "government"
    ],
    "wof:name":"Employment Security Office",
    "wof:placetype":"venue"
},
  "geometry": {"coordinates":[-93.082504,31.752022],"type":"Point"}
}