{
  "type": "Feature",
  "properties": {
    "addr:full":"1038 Main St Baton Rouge LA 70802",
    "addr:housenumber":"1038",
    "addr:postcode":"70802",
    "addr:street":"Main St",
    "iso:country":"US",
    "sg:address":"1038 Main St",
    "sg:city":"Baton Rouge",
    "sg:classifiers":[
        {
            "category":"Local Transit",
            "type":"Transportation"
        }
    ],
    "sg:phone":"+1 225 267 6566",
    "sg:postcode":"70802",
    "sg:province":"LA",
    "sg:tags":[
        "handicapped"
    ],
    "wof:name":"Express Mobility",
    "wof:placetype":"venue"
},
  "geometry": {"coordinates":[-91.178894,30.451623],"type":"Point"}
}