{
  "type": "Feature",
  "properties": {
    "addr:full":"2622 Johnston St Lafayette LA 70503",
    "addr:housenumber":"2622",
    "addr:postcode":"70503",
    "addr:street":"Johnston St",
    "iso:country":"US",
    "sg:address":"2622 Johnston St",
    "sg:city":"Lafayette",
    "sg:classifiers":[
        {
            "category":"Restaurant",
            "type":"Food & Drink"
        }
    ],
    "sg:menulink":"http://www.allmenus.com/la/lafayette/65414-cicis-pizza-buffet/menu/",
    "sg:phone":"+1 337 237 6466",
    "sg:postcode":"70503",
    "sg:province":"LA",
    "sg:tags":[
        "american",
        "pizza"
    ],
    "wof:name":"CiCi's Pizza Buffet",
    "wof:placetype":"venue"
},
  "geometry": {"coordinates":[-92.036922,30.208156],"type":"Point"}
}