{
  "type": "Feature",
  "properties": {
    "iso:country":"US",
    "sg:address":"14897 State Rte 417",
    "sg:city":"Batchelor",
    "sg:classifiers":[
        {
            "category":"Organizations",
            "subcategory":"Religious Organization",
            "type":"Services"
        }
    ],
    "sg:phone":"+1 225 492 2629",
    "sg:postcode":"70715",
    "sg:province":"LA",
    "sg:tags":[
        "church"
    ],
    "wof:name":"Mt Maria Baptist Church",
    "wof:placetype":"venue"
},
  "geometry": {"coordinates":[-91.71360199999999,30.840559],"type":"Point"}
}