{
  "type": "Feature",
  "properties": {
    "iso:country":"US",
    "sg:address":"26832 James Chapel Rd N",
    "sg:city":"Holden",
    "sg:classifiers":[
        {
            "category":"Wholesale",
            "subcategory":"Machinery & Supplies",
            "type":"Manufacturing & Wholesale Goods"
        }
    ],
    "sg:phone":"+1 225 567 5564",
    "sg:postcode":"70744",
    "sg:province":"LA",
    "sg:tags":[
        "pump"
    ],
    "wof:name":"Davidson-Swett Pumps & Supls",
    "wof:placetype":"venue"
},
  "geometry": {"coordinates":[-90.63654,30.476239],"type":"Point"}
}