{
  "type": "Feature",
  "properties": {
    "iso:country":"US",
    "sg:address":"211 River Woods Dr",
    "sg:city":"Lafayette",
    "sg:classifiers":[
        {
            "category":"Building & Trades",
            "subcategory":"Construction",
            "type":"Services"
        }
    ],
    "sg:phone":"+1 337 856 6640",
    "sg:postcode":"70508",
    "sg:province":"LA",
    "sg:tags":[
        "insulation",
        "heat",
        "contractor"
    ],
    "wof:name":"Jax Service LLC",
    "wof:placetype":"venue"
},
  "geometry": {"coordinates":[-92.065577,30.122088],"type":"Point"}
}