{
  "type": "Feature",
  "properties": {
    "iso:country":"US",
    "sg:address":"1800 Arts St",
    "sg:city":"New Orleans",
    "sg:classifiers":[
        {
            "category":"Organizations",
            "subcategory":"Religious Organization",
            "type":"Services"
        }
    ],
    "sg:phone":"+1 504 947 3705",
    "sg:postcode":"70117",
    "sg:province":"LA",
    "sg:tags":[
        "church"
    ],
    "wof:name":"Abundant Life Ministries",
    "wof:placetype":"venue"
},
  "geometry": {"coordinates":[-90.05052000000001,29.977072],"type":"Point"}
}