{
  "type": "Feature",
  "properties": {
    "iso:country":"US",
    "sg:address":"107 NE Railroad Ave",
    "sg:city":"Ville Platte",
    "sg:classifiers":[
        {
            "category":"Retail",
            "subcategory":"Repair Shop",
            "type":"Services"
        }
    ],
    "sg:phone":"+1 337 363 1979",
    "sg:postcode":"70586",
    "sg:province":"LA",
    "sg:tags":[
        "appliance"
    ],
    "wof:name":"City Appliance Of Ville Platte",
    "wof:placetype":"venue"
},
  "geometry": {"coordinates":[-92.273408,30.688449],"type":"Point"}
}