{
  "type": "Feature",
  "properties": {
    "iso:country":"US",
    "sg:address":"1086 Hwy 113",
    "sg:city":"Glenmora",
    "sg:classifiers":[
        {
            "category":"Retail",
            "subcategory":"Auto Repair",
            "type":"Services"
        }
    ],
    "sg:phone":"+1 318 748 6088",
    "sg:postcode":"71433",
    "sg:province":"LA",
    "sg:tags":[
        "body"
    ],
    "wof:name":"Cenla Trucks",
    "wof:placetype":"venue"
},
  "geometry": {"coordinates":[-92.655686,30.994837],"type":"Point"}
}