{
  "type": "Feature",
  "properties": {
    "addr:full":"4941 Parkforest Dr Baton Rouge LA 70816",
    "addr:housenumber":"4941",
    "addr:postcode":"70816",
    "addr:street":"Parkforest Dr",
    "iso:country":"US",
    "sg:address":"4941 Parkforest Dr",
    "sg:city":"Baton Rouge",
    "sg:classifiers":[
        {
            "category":"Organizations",
            "subcategory":"Religious Organization",
            "type":"Services"
        }
    ],
    "sg:phone":"+1 225 753 3319",
    "sg:postcode":"70816",
    "sg:province":"LA",
    "wof:name":"Phillip Willis Evangelist",
    "wof:placetype":"venue"
},
  "geometry": {"coordinates":[-91.04308,30.407878],"type":"Point"}
}