{
  "type": "Feature",
  "properties": {
    "addr:full":"1169 Robert Blvd Slidell LA 70458",
    "addr:housenumber":"1169",
    "addr:postcode":"70458",
    "addr:street":"Robert Blvd",
    "iso:country":"US",
    "sg:address":"1169 Robert Blvd",
    "sg:city":"Slidell",
    "sg:classifiers":[
        {
            "category":"Personal",
            "type":"Services"
        }
    ],
    "sg:phone":"+1 985 646 1117",
    "sg:postcode":"70458",
    "sg:province":"LA",
    "sg:tags":[
        "hair",
        "replacement"
    ],
    "wof:name":"On Stage Hair Studio",
    "wof:placetype":"venue"
},
  "geometry": {"coordinates":[-89.771162,30.286946],"type":"Point"}
}