{
  "type": "Feature",
  "properties": {
    "addr:full":"810 Jefferson St New Iberia LA 70560",
    "addr:housenumber":"810",
    "addr:postcode":"70560",
    "addr:street":"Jefferson St",
    "iso:country":"US",
    "sg:address":"810 Jefferson St",
    "sg:city":"New Iberia",
    "sg:classifiers":[
        {
            "category":"Banks & Credit Unions",
            "subcategory":"Bank",
            "type":"Services"
        }
    ],
    "sg:phone":"+1 337 365 8522",
    "sg:postcode":"70560",
    "sg:province":"LA",
    "sg:tags":[
        "loan"
    ],
    "wof:name":"Cinco Financial Svc",
    "wof:placetype":"venue"
},
  "geometry": {"coordinates":[-91.82817300000001,30.003793],"type":"Point"}
}