{
  "type": "Feature",
  "properties": {
    "addr:full":"544 Main St Baton Rouge LA 70801",
    "addr:housenumber":"544",
    "addr:postcode":"70801",
    "addr:street":"Main St",
    "iso:country":"US",
    "sg:address":"544 Main St",
    "sg:city":"Baton Rouge",
    "sg:classifiers":[
        {
            "category":"Government",
            "subcategory":"Office",
            "type":"Public Place"
        }
    ],
    "sg:phone":"+1 225 342 3822",
    "sg:postcode":"70801",
    "sg:province":"LA",
    "sg:tags":[
        "state",
        "taxation"
    ],
    "wof:name":"Management & Budget Div",
    "wof:placetype":"venue"
},
  "geometry": {"coordinates":[-91.18523500000001,30.451441],"type":"Point"}
}