{
  "type": "Feature",
  "properties": {
    "iso:country":"US",
    "sg:address":"1138 Barrow St",
    "sg:city":"Houma",
    "sg:classifiers":[
        {
            "category":"Manufacturing",
            "subcategory":"Metals",
            "type":"Manufacturing & Wholesale Goods"
        }
    ],
    "sg:phone":"+1 985 868 2761",
    "sg:postcode":"70360",
    "sg:province":"LA",
    "sg:tags":[
        "fabricator",
        "sheet"
    ],
    "wof:name":"H & P Sheet Metal Works",
    "wof:placetype":"venue"
},
  "geometry": {"coordinates":[-90.720648,29.588436],"type":"Point"}
}