{
  "type": "Feature",
  "properties": {
    "iso:country":"US",
    "sg:address":"1549 Fairmont St",
    "sg:city":"Baton Rouge",
    "sg:classifiers":[
        {
            "category":"Shopping",
            "type":"Retail Goods"
        }
    ],
    "sg:phone":"+1 225 389 0050",
    "sg:postcode":"70808",
    "sg:province":"LA",
    "sg:tags":[
        "pet",
        "food",
        "supply"
    ],
    "wof:name":"Organic Pet Foods Inc",
    "wof:placetype":"venue"
},
  "geometry": {"coordinates":[-91.162694,30.435358],"type":"Point"}
}