{
  "type": "Feature",
  "properties": {
    "addr:full":"3600 W Congress St Lafayette LA 70506",
    "addr:housenumber":"3600",
    "addr:postcode":"70506",
    "addr:street":"W Congress St",
    "iso:country":"US",
    "sg:address":"3600 W Congress St",
    "sg:city":"Lafayette",
    "sg:classifiers":[
        {
            "category":"Insurance",
            "subcategory":"Insurance Agent",
            "type":"Services"
        }
    ],
    "sg:phone":"+1 337 981 4990",
    "sg:postcode":"70506",
    "sg:province":"LA",
    "wof:name":"Don Higginbotham Insurance",
    "wof:placetype":"venue"
},
  "geometry": {"coordinates":[-92.063042,30.202973],"type":"Point"}
}