{
  "type": "Feature",
  "properties": {
    "iso:country":"US",
    "sg:address":"1206 Park Dr",
    "sg:city":"Mandeville",
    "sg:classifiers":[
        {
            "category":"Professional",
            "subcategory":"Accounting & Tax Preparation",
            "type":"Services"
        }
    ],
    "sg:phone":"+1 985 624 5100",
    "sg:postcode":"70471",
    "sg:province":"LA",
    "sg:tags":[
        "payroll"
    ],
    "wof:name":"Time Plus Payroll Svc",
    "wof:placetype":"venue"
},
  "geometry": {"coordinates":[-90.088947,30.383572],"type":"Point"}
}