{
  "type": "Feature",
  "properties": {
    "addr:full":"5827 Youree Dr Shreveport LA 71105",
    "addr:housenumber":"5827",
    "addr:postcode":"71105",
    "addr:street":"Youree Dr",
    "iso:country":"US",
    "sg:address":"5827 Youree Dr",
    "sg:city":"Shreveport",
    "sg:classifiers":[
        {
            "category":"Shopping",
            "subcategory":"Gifts & Souvenirs",
            "type":"Retail Goods"
        }
    ],
    "sg:phone":"+1 318 219 3100",
    "sg:postcode":"71105",
    "sg:province":"LA",
    "sg:tags":[
        "shop"
    ],
    "wof:name":"Uniquely Yours Interiors",
    "wof:placetype":"venue"
},
  "geometry": {"coordinates":[-93.721977,32.455112],"type":"Point"}
}