{
  "type": "Feature",
  "properties": {
    "iso:country":"US",
    "sg:address":"4345 Greenwood Rd",
    "sg:city":"Shreveport",
    "sg:classifiers":[
        {
            "category":"Home & Garden",
            "subcategory":"Mobile Homes",
            "type":"Retail Goods"
        }
    ],
    "sg:phone":"+1 318 635 9711",
    "sg:postcode":"71109",
    "sg:province":"LA",
    "wof:name":"Foster Mobile Home Sales",
    "wof:placetype":"venue"
},
  "geometry": {"coordinates":[-93.817384,32.471357],"type":"Point"}
}