{
  "type": "Feature",
  "properties": {
    "addr:full":"836 Shirley Rd Bunkie LA 71322",
    "addr:housenumber":"836",
    "addr:postcode":"71322",
    "addr:street":"Shirley Rd",
    "iso:country":"US",
    "sg:address":"836 Shirley Rd",
    "sg:city":"Bunkie",
    "sg:classifiers":[
        {
            "category":"Banks & Credit Unions",
            "subcategory":"Bank",
            "type":"Services"
        }
    ],
    "sg:phone":"+1 318 346 6265",
    "sg:postcode":"71322",
    "sg:province":"LA",
    "wof:name":"Hibernia National Bank",
    "wof:placetype":"venue"
},
  "geometry": {"coordinates":[-92.194594,30.959553],"type":"Point"}
}