{
  "type": "Feature",
  "properties": {
    "addr:full":"807 Mays St Ruston LA 71270",
    "addr:housenumber":"807",
    "addr:postcode":"71270",
    "addr:street":"Mays St",
    "iso:country":"US",
    "sg:address":"807 Mays St",
    "sg:city":"Ruston",
    "sg:classifiers":[
        {
            "category":"Restaurant",
            "type":"Food & Drink"
        }
    ],
    "sg:phone":"+1 318 255 0269",
    "sg:postcode":"71270",
    "sg:province":"LA",
    "sg:tags":[
        "eating"
    ],
    "wof:name":"Barbara Canada",
    "wof:placetype":"venue"
},
  "geometry": {"coordinates":[-92.64261,32.521155],"type":"Point"}
}