{
  "type": "Feature",
  "properties": {
    "iso:country":"US",
    "sg:address":"7340 Union Ave",
    "sg:city":"Shreveport",
    "sg:classifiers":[
        {
            "category":"Organizations",
            "subcategory":"Religious Organization",
            "type":"Services"
        }
    ],
    "sg:phone":"+1 318 687 7929",
    "sg:postcode":"71106",
    "sg:province":"LA",
    "sg:tags":[
        "church"
    ],
    "wof:name":"Fountain Of Life Christian Ctr",
    "wof:placetype":"venue"
},
  "geometry": {"coordinates":[-93.77166699999999,32.438303],"type":"Point"}
}