{
  "type": "Feature",
  "properties": {
    "iso:country":"US",
    "sg:address":"9101 State Rte 936",
    "sg:city":"Saint Amant",
    "sg:classifiers":[
        {
            "category":"Farming",
            "subcategory":"Livestock Farm",
            "type":"Manufacturing & Wholesale Goods"
        }
    ],
    "sg:phone":"+1 225 675 6364",
    "sg:postcode":"70774",
    "sg:province":"LA",
    "sg:tags":[
        "horse"
    ],
    "wof:name":"Dean Williams",
    "wof:placetype":"venue"
},
  "geometry": {"coordinates":[-90.83406600000001,30.198638],"type":"Point"}
}