{
  "type": "Feature",
  "properties": {
    "iso:country":"US",
    "sg:address":"111 Pauls Ln",
    "sg:city":"Port Sulphur",
    "sg:classifiers":[
        {
            "category":"Bars & Pubs",
            "type":"Food & Drink"
        }
    ],
    "sg:phone":"+1 985 564 2203",
    "sg:postcode":"70083",
    "sg:province":"LA",
    "sg:tags":[
        "lounge",
        "cocktail"
    ],
    "wof:name":"T J's Sports Bar Inc",
    "wof:placetype":"venue"
},
  "geometry": {"coordinates":[-89.645762,29.452645],"type":"Point"}
}