{
  "type": "Feature",
  "properties": {
    "iso:country":"US",
    "sg:address":"213 Spyglass Ln",
    "sg:city":"Youngsville",
    "sg:classifiers":[
        {
            "category":"Health Services",
            "subcategory":"Health Practitioner",
            "type":"Services"
        }
    ],
    "sg:phone":"+1 337 857 9629",
    "sg:postcode":"70518",
    "sg:province":"LA",
    "sg:tags":[
        "pathologist",
        "speech"
    ],
    "wof:name":"Acadiana Speech Therapy LLC",
    "wof:placetype":"venue"
},
  "geometry": {"coordinates":[-91.950472,30.093592],"type":"Point"}
}