{
  "type": "Feature",
  "properties": {
    "iso:country":"US",
    "sg:address":"1968 Barataria Blvd",
    "sg:city":"Marrero",
    "sg:classifiers":[
        {
            "category":"Restaurant",
            "type":"Food & Drink"
        }
    ],
    "sg:menulink":"http://www.allmenus.com/la/avondale/91680-shoneys-restaurant/menu/",
    "sg:phone":"+1 504 348 4888",
    "sg:postcode":"70072",
    "sg:province":"LA",
    "sg:tags":[
        "american"
    ],
    "wof:name":"Shoney's Restaurant",
    "wof:placetype":"venue"
},
  "geometry": {"coordinates":[-90.098271,29.873116],"type":"Point"}
}