{
  "type": "Feature",
  "properties": {
    "iso:country":"US",
    "sg:address":"6306 State Rte 81",
    "sg:city":"Lottie",
    "sg:classifiers":[
        {
            "category":"Health Services",
            "subcategory":"Doctor",
            "type":"Services"
        }
    ],
    "sg:phone":"+1 225 637 3901",
    "sg:postcode":"70756",
    "sg:province":"LA",
    "sg:tags":[
        "physician",
        "surgeon"
    ],
    "wof:name":"Neal Smith III MD",
    "wof:placetype":"venue"
},
  "geometry": {"coordinates":[-91.624272,30.548358],"type":"Point"}
}