{
  "type": "Feature",
  "properties": {
    "addr:full":"316 N Walnut St Tallulah LA 71282",
    "addr:housenumber":"316",
    "addr:postcode":"71282",
    "addr:street":"N Walnut St",
    "iso:country":"US",
    "sg:address":"316 N Walnut St",
    "sg:city":"Tallulah",
    "sg:classifiers":[
        {
            "category":"Organizations",
            "subcategory":"Religious Organization",
            "type":"Services"
        }
    ],
    "sg:phone":"+1 318 574 2974",
    "sg:postcode":"71282",
    "sg:province":"LA",
    "sg:tags":[
        "church"
    ],
    "wof:name":"Greater Mt Olive Baptist Chr",
    "wof:placetype":"venue"
},
  "geometry": {"coordinates":[-91.18768300000001,32.410977],"type":"Point"}
}