{
  "type": "Feature",
  "properties": {
    "iso:country":"US",
    "sg:address":"1001 Marigny St",
    "sg:city":"New Orleans",
    "sg:classifiers":[
        {
            "category":"Travel",
            "subcategory":"Hotels & Motels",
            "type":"Entertainment"
        }
    ],
    "sg:phone":"+1 504 949 5815",
    "sg:postcode":"70117",
    "sg:province":"LA",
    "sg:website":"www.frenchquarteraccommodations.com",
    "wof:name":"French Quarter Accommodations",
    "wof:placetype":"venue"
},
  "geometry": {"coordinates":[-90.055603,29.967699],"type":"Point"}
}