{
  "type": "Feature",
  "properties": {
    "addr:full":"4223 Greenbriar Dr Shreveport LA 71109",
    "addr:housenumber":"4223",
    "addr:postcode":"71109",
    "addr:street":"Greenbriar Dr",
    "iso:country":"US",
    "sg:address":"4223 Greenbriar Dr",
    "sg:city":"Shreveport",
    "sg:classifiers":[
        {
            "category":"Government",
            "subcategory":"Office",
            "type":"Public Place"
        }
    ],
    "sg:phone":"+1 318 635 4615",
    "sg:postcode":"71109",
    "sg:province":"LA",
    "sg:tags":[
        "housing",
        "program",
        "village"
    ],
    "wof:name":"Briarwood Villiage",
    "wof:placetype":"venue"
},
  "geometry": {"coordinates":[-93.815952,32.466764],"type":"Point"}
}