{
  "type": "Feature",
  "properties": {
    "addr:full":"4936 Veterans Memorial Blvd Metairie LA 70006",
    "addr:housenumber":"4936",
    "addr:postcode":"70006",
    "addr:street":"Veterans Memorial Blvd",
    "iso:country":"US",
    "sg:address":"4936 Veterans Memorial Blvd",
    "sg:city":"Metairie",
    "sg:classifiers":[
        {
            "category":"Shopping",
            "subcategory":"Pharmacy",
            "type":"Retail Goods"
        }
    ],
    "sg:phone":"+1 504 883 5616",
    "sg:postcode":"70006",
    "sg:province":"LA",
    "sg:website":"www.riteaid.com",
    "wof:name":"Rite Aid Pharmacy",
    "wof:placetype":"venue"
},
  "geometry": {"coordinates":[-90.19381,30.005987],"type":"Point"}
}