{
  "type": "Feature",
  "properties": {
    "addr:full":"102 S Monroe St West Monroe LA 71270",
    "addr:housenumber":"102",
    "addr:postcode":"71270",
    "addr:street":"S Monroe St West",
    "iso:country":"US",
    "sg:address":"102 S Monroe St",
    "sg:city":"West Monroe",
    "sg:classifiers":[
        {
            "category":"Wholesale",
            "subcategory":"Medical Equipment & Supplies",
            "type":"Manufacturing & Wholesale Goods"
        }
    ],
    "sg:phone":"+1 318 338 3550",
    "sg:postcode":"71270",
    "sg:province":"LA",
    "sg:tags":[
        "hospital"
    ],
    "wof:name":"Respiratory Therapist Equip",
    "wof:placetype":"venue"
},
  "geometry": {"coordinates":[-92.640846,32.528418],"type":"Point"}
}