{
  "type": "Feature",
  "properties": {
    "iso:country":"US",
    "sg:address":"1733 Staring Ln",
    "sg:city":"Baton Rouge",
    "sg:classifiers":[
        {
            "category":"Autos & Motor Vehicles",
            "subcategory":"Auto Supplies",
            "type":"Retail Goods"
        }
    ],
    "sg:phone":"+1 225 769 6660",
    "sg:postcode":"70810",
    "sg:province":"LA",
    "sg:tags":[
        "automobile",
        "parts"
    ],
    "wof:name":"O'Reilly Auto Parts",
    "wof:placetype":"venue"
},
  "geometry": {"coordinates":[-91.111931,30.390041],"type":"Point"}
}