{
  "type": "Feature",
  "properties": {
    "iso:country":"US",
    "sg:address":"2 Westside Shopping Ctr",
    "sg:city":"Gretna",
    "sg:classifiers":[
        {
            "category":"Banks & Credit Unions",
            "subcategory":"Bank",
            "type":"Services"
        }
    ],
    "sg:phone":"+1 504 533 3779",
    "sg:postcode":"70053",
    "sg:province":"LA",
    "sg:website":"www.capitalone.com",
    "wof:name":"Capital One",
    "wof:placetype":"venue"
},
  "geometry": {"coordinates":[-90.051754,29.913583],"type":"Point"}
}