{
  "type": "Feature",
  "properties": {
    "iso:country":"US",
    "sg:address":"13880 Hayne Blvd",
    "sg:city":"New Orleans",
    "sg:classifiers":[
        {
            "category":"Food & Beverages",
            "subcategory":"Meat & Fish",
            "type":"Retail Goods"
        }
    ],
    "sg:phone":"+1 504 241 5288",
    "sg:postcode":"70128",
    "sg:province":"LA",
    "wof:name":"Tania Meat Market",
    "wof:placetype":"venue"
},
  "geometry": {"coordinates":[-89.95415300000001,30.067485],"type":"Point"}
}