{
  "type": "Feature",
  "properties": {
    "iso:country":"US",
    "sg:address":"104 Village St",
    "sg:city":"Slidell",
    "sg:classifiers":[
        {
            "category":"Banks & Credit Unions",
            "subcategory":"Investment Brokerage",
            "type":"Services"
        }
    ],
    "sg:phone":"+1 985 643 2802",
    "sg:postcode":"70458",
    "sg:province":"LA",
    "sg:tags":[
        "consultant",
        "planning",
        "financial"
    ],
    "wof:name":"Thomas F O'Connor Certified",
    "wof:placetype":"venue"
},
  "geometry": {"coordinates":[-89.746498,30.30982],"type":"Point"}
}