{
  "type": "Feature",
  "properties": {
    "iso:country":"US",
    "sg:address":"10928 S Choctaw Dr",
    "sg:city":"Baton Rouge",
    "sg:classifiers":[
        {
            "category":"Manufacturing",
            "subcategory":"Tools & Machinery",
            "type":"Manufacturing & Wholesale Goods"
        }
    ],
    "sg:phone":"+1 225 275 7696",
    "sg:postcode":"70815",
    "sg:province":"LA",
    "sg:tags":[
        "disposal",
        "reduction",
        "waste"
    ],
    "sg:website":"www.shamrocktools.com",
    "wof:name":"Shamrock Pipe Tools",
    "wof:placetype":"venue"
},
  "geometry": {"coordinates":[-91.064379,30.472187],"type":"Point"}
}