{
  "type": "Feature",
  "properties": {
    "addr:full":"5424 Lapalco Blvd Marrero LA 70072",
    "addr:housenumber":"5424",
    "addr:postcode":"70072",
    "addr:street":"Lapalco Blvd Marrero",
    "iso:country":"US",
    "sg:address":"5424 Lapalco Blvd",
    "sg:city":"Marrero",
    "sg:classifiers":[
        {
            "category":"Autos & Motor Vehicles",
            "subcategory":"Automobile Sales",
            "type":"Retail Goods"
        }
    ],
    "sg:phone":"+1 504 348 2277",
    "sg:postcode":"70072",
    "sg:province":"LA",
    "sg:tags":[
        "car",
        "dealer"
    ],
    "wof:name":"Lapalco Motors",
    "wof:placetype":"venue"
},
  "geometry": {"coordinates":[-90.10830199999999,29.875284],"type":"Point"}
}