{
  "type": "Feature",
  "properties": {
    "addr:full":"12728 Jefferson Hwy Baton Rouge LA 70816",
    "addr:housenumber":"12728",
    "addr:postcode":"70816",
    "addr:street":"Jefferson Hwy",
    "iso:country":"US",
    "sg:address":"12728 Jefferson Hwy",
    "sg:city":"Baton Rouge",
    "sg:classifiers":[
        {
            "category":"Government",
            "subcategory":"Office",
            "type":"Public Place"
        }
    ],
    "sg:phone":"+1 225 751 8265",
    "sg:postcode":"70816",
    "sg:province":"LA",
    "wof:name":"Steven E Sanders Justice-Peace",
    "wof:placetype":"venue"
},
  "geometry": {"coordinates":[-91.044382,30.394523],"type":"Point"}
}