{
  "type": "Feature",
  "properties": {
    "addr:full":"824 Elmwood Park Blvd New Orleans LA 70123",
    "addr:housenumber":"824",
    "addr:postcode":"70123",
    "addr:street":"Elmwood Park Blvd",
    "iso:country":"US",
    "sg:address":"824 Elmwood Park Blvd",
    "sg:city":"New Orleans",
    "sg:classifiers":[
        {
            "category":"Professional",
            "subcategory":"Computer Services",
            "type":"Services"
        }
    ],
    "sg:phone":"+1 504 818 0463",
    "sg:postcode":"70123",
    "sg:province":"LA",
    "wof:name":"Axxes-It",
    "wof:placetype":"venue"
},
  "geometry": {"coordinates":[-90.18633699999999,29.954313],"type":"Point"}
}