{
  "type": "Feature",
  "properties": {
    "iso:country":"US",
    "sg:address":"1725 Metro Dr",
    "sg:city":"Alexandria",
    "sg:classifiers":[
        {
            "category":"Restaurant",
            "type":"Food & Drink"
        }
    ],
    "sg:menulink":"http://www.allmenus.com/la/alexandria/64279-chuck-e-cheeses/menu/",
    "sg:phone":"+1 318 445 9843",
    "sg:postcode":"71301",
    "sg:province":"LA",
    "sg:tags":[
        "american",
        "pizza"
    ],
    "wof:name":"Chuck E. Cheese's",
    "wof:placetype":"venue"
},
  "geometry": {"coordinates":[-92.47336199999999,31.27574],"type":"Point"}
}