{
  "type": "Feature",
  "properties": {
    "iso:country":"US",
    "sg:address":"755 Airline Dr",
    "sg:city":"Kenner",
    "sg:classifiers":[
        {
            "category":"Building & Trades",
            "subcategory":"Equipment Rental",
            "type":"Services"
        }
    ],
    "sg:phone":"+1 504 468 6766",
    "sg:postcode":"70062",
    "sg:province":"LA",
    "sg:tags":[
        "leasing",
        "furniture"
    ],
    "sg:website":"www.ctsf.com",
    "wof:name":"Cort Trade Show Furnishings",
    "wof:placetype":"venue"
},
  "geometry": {"coordinates":[-90.261572,29.983153],"type":"Point"}
}