{
  "type": "Feature",
  "properties": {
    "iso:country":"US",
    "sg:address":"4796 Pontchartrain Dr",
    "sg:city":"Slidell",
    "sg:classifiers":[
        {
            "category":"Wholesale",
            "subcategory":"Electrical",
            "type":"Manufacturing & Wholesale Goods"
        }
    ],
    "sg:phone":"+1 985 641 7480",
    "sg:postcode":"70458",
    "sg:province":"LA",
    "sg:tags":[
        "control"
    ],
    "sg:website":"www.midsouthsalesco.com",
    "wof:name":"Mid-South Sales Co",
    "wof:placetype":"venue"
},
  "geometry": {"coordinates":[-89.818372,30.223738],"type":"Point"}
}