{
  "type": "Feature",
  "properties": {
    "iso:country":"US",
    "sg:address":"1953 Hobbiton Rd",
    "sg:city":"Baton Rouge",
    "sg:classifiers":[
        {
            "category":"Wholesale",
            "subcategory":"Electrical",
            "type":"Manufacturing & Wholesale Goods"
        }
    ],
    "sg:phone":"+1 225 752 9395",
    "sg:postcode":"70810",
    "sg:province":"LA",
    "sg:tags":[
        "equipment",
        "electric",
        "supply"
    ],
    "wof:name":"Panduit Corp",
    "wof:placetype":"venue"
},
  "geometry": {"coordinates":[-91.065635,30.363055],"type":"Point"}
}