{
  "type": "Feature",
  "properties": {
    "iso:country":"US",
    "sg:address":"10495 Airline Hwy",
    "sg:city":"Baton Rouge",
    "sg:classifiers":[
        {
            "category":"Autos & Motor Vehicles",
            "subcategory":"Automobile Sales",
            "type":"Retail Goods"
        }
    ],
    "sg:phone":"+1 225 292 5400",
    "sg:postcode":"70816",
    "sg:province":"LA",
    "sg:tags":[
        "car",
        "dealer"
    ],
    "wof:name":"Rock & Roll Motors Inc",
    "wof:placetype":"venue"
},
  "geometry": {"coordinates":[-91.067498,30.413683],"type":"Point"}
}