{
  "type": "Feature",
  "properties": {
    "iso:country":"US",
    "sg:address":"908 Williams Blvd",
    "sg:city":"Kenner",
    "sg:classifiers":[
        {
            "category":"Professional",
            "subcategory":"Lawyer & Legal Services",
            "type":"Services"
        }
    ],
    "sg:phone":"+1 504 469 4358",
    "sg:postcode":"70062",
    "sg:province":"LA",
    "sg:tags":[
        "attorney"
    ],
    "wof:name":"Stephen V Vallot",
    "wof:placetype":"venue"
},
  "geometry": {"coordinates":[-90.244331,29.980824],"type":"Point"}
}