{
  "type": "Feature",
  "properties": {
    "iso:country":"US",
    "sg:address":"3126 Edenborn Ave",
    "sg:city":"Metairie",
    "sg:classifiers":[
        {
            "category":"Professional",
            "subcategory":"Business Services",
            "type":"Services"
        }
    ],
    "sg:phone":"+1 504 779 9858",
    "sg:postcode":"70002",
    "sg:province":"LA",
    "wof:name":"Crown Financial Services",
    "wof:placetype":"venue"
},
  "geometry": {"coordinates":[-90.162055,30.007041],"type":"Point"}
}