{
  "type": "Feature",
  "properties": {
    "addr:full":"300 N 10th St Baton Rouge LA 70802",
    "addr:housenumber":"300",
    "addr:postcode":"70802",
    "addr:street":"N 10Th St",
    "iso:country":"US",
    "sg:address":"300 N 10th St",
    "sg:city":"Baton Rouge",
    "sg:classifiers":[
        {
            "category":"Government",
            "subcategory":"Office",
            "type":"Public Place"
        }
    ],
    "sg:phone":"+1 225 389 3105",
    "sg:postcode":"70802",
    "sg:province":"LA",
    "sg:tags":[
        "village"
    ],
    "sg:website":"www.brgov.com",
    "wof:name":"Baton Rouge Commercial Plan",
    "wof:placetype":"venue"
},
  "geometry": {"coordinates":[-91.17982499999999,30.450623],"type":"Point"}
}