{
  "type": "Feature",
  "properties": {
    "iso:country":"US",
    "sg:address":"4520 Clearview Pkwy",
    "sg:city":"Metairie",
    "sg:classifiers":[
        {
            "category":"Health Services",
            "subcategory":"Doctor",
            "type":"Services"
        }
    ],
    "sg:phone":"+1 504 885 0177",
    "sg:postcode":"70006",
    "sg:province":"LA",
    "sg:tags":[
        "dentist"
    ],
    "sg:website":"www.neworleansendo.com",
    "wof:name":"Endodontic Specialists",
    "wof:placetype":"venue"
},
  "geometry": {"coordinates":[-90.18843,30.017484],"type":"Point"}
}