{
  "type": "Feature",
  "properties": {
    "iso:country":"US",
    "sg:address":"1111 Janice Dr",
    "sg:city":"Springhill",
    "sg:classifiers":[
        {
            "category":"Wholesale",
            "subcategory":"Meat",
            "type":"Manufacturing & Wholesale Goods"
        },
        {
            "category":"Professional",
            "type":"Services"
        },
        {
            "category":"Food & Beverages",
            "subcategory":"Meat & Fish",
            "type":"Retail Goods"
        }
    ],
    "sg:phone":"+1 318 539 5000",
    "sg:postcode":"71075",
    "sg:province":"LA",
    "sg:tags":[
        "meat-wholesale",
        "market",
        "caterer"
    ],
    "wof:name":"French Market Specialty Meats",
    "wof:placetype":"venue"
},
  "geometry": {"coordinates":[-93.478294,33.013508],"type":"Point"}
}