{
  "type": "Feature",
  "properties": {
    "addr:full":"422 5th Ave Harvey LA 70058",
    "addr:housenumber":"422",
    "addr:postcode":"70058",
    "addr:street":"5Th Ave",
    "iso:country":"US",
    "sg:address":"422 5th Ave",
    "sg:city":"Harvey",
    "sg:classifiers":[
        {
            "category":"Recreation",
            "type":"Entertainment"
        }
    ],
    "sg:phone":"+1 504 341 4633",
    "sg:postcode":"70058",
    "sg:province":"LA",
    "sg:tags":[
        "amusement"
    ],
    "wof:name":"Snoballs R Us",
    "wof:placetype":"venue"
},
  "geometry": {"coordinates":[-90.08869199999999,29.904981],"type":"Point"}
}