{
  "type": "Feature",
  "properties": {
    "iso:country":"US",
    "sg:address":"327 Iberia St",
    "sg:city":"Youngsville",
    "sg:classifiers":[
        {
            "category":"Health Services",
            "subcategory":"Optometrist",
            "type":"Services"
        },
        {
            "category":"Shopping",
            "subcategory":"Optician",
            "type":"Retail Goods"
        }
    ],
    "sg:phone":"+1 337 857 5567",
    "sg:postcode":"70592",
    "sg:province":"LA",
    "sg:tags":[
        "ophthalmologist",
        "eyewear"
    ],
    "wof:name":"Young Eyes LLC",
    "wof:placetype":"venue"
},
  "geometry": {"coordinates":[-91.993415,30.101568],"type":"Point"}
}