{
  "type": "Feature",
  "properties": {
    "iso:country":"US",
    "sg:address":"10404 Tallowwood Ave",
    "sg:city":"Baker",
    "sg:classifiers":[
        {
            "category":"Building & Trades",
            "subcategory":"Construction",
            "type":"Services"
        }
    ],
    "sg:phone":"+1 225 261 4245",
    "sg:postcode":"70714",
    "sg:province":"LA",
    "sg:tags":[
        "carpentry",
        "contractor"
    ],
    "wof:name":"Leblanc & Sons Wood Work Inc",
    "wof:placetype":"venue"
},
  "geometry": {"coordinates":[-91.07096900000001,30.554657],"type":"Point"}
}