{
  "type": "Feature",
  "properties": {
    "iso:country":"US",
    "sg:address":"1206 J W Davis Dr",
    "sg:city":"Hammond",
    "sg:classifiers":[
        {
            "category":"Banks & Credit Unions",
            "subcategory":"Investment Brokerage",
            "type":"Services"
        }
    ],
    "sg:phone":"+1 985 419 9842",
    "sg:postcode":"70403",
    "sg:province":"LA",
    "wof:name":"Shapiro Baines & Assoc",
    "wof:placetype":"venue"
},
  "geometry": {"coordinates":[-90.469791,30.487128],"type":"Point"}
}