{
  "type": "Feature",
  "properties": {
    "addr:full":"400 Lapalco Blvd Gretna LA 70056",
    "addr:housenumber":"400",
    "addr:postcode":"70056",
    "addr:street":"Lapalco Blvd",
    "iso:country":"US",
    "sg:address":"400 Lapalco Blvd",
    "sg:city":"Gretna",
    "sg:classifiers":[
        {
            "category":"Personal",
            "subcategory":"Beauty Salon",
            "type":"Services"
        }
    ],
    "sg:phone":"+1 504 391 0803",
    "sg:postcode":"70056",
    "sg:province":"LA",
    "wof:name":"Beauty Sense",
    "wof:placetype":"venue"
},
  "geometry": {"coordinates":[-90.02637300000001,29.881224],"type":"Point"}
}