{
  "type": "Feature",
  "properties": {
    "iso:country":"US",
    "sg:address":"13301 Chef Menteur Hwy",
    "sg:city":"New Orleans",
    "sg:phone":"+1 504 254 8984",
    "sg:postcode":"70129",
    "sg:province":"LA",
    "sg:tags":[
        "product",
        "petroleum"
    ],
    "wof:name":"Chevron Products Co",
    "wof:placetype":"venue"
},
  "geometry": {"coordinates":[-89.930302,30.030275],"type":"Point"}
}