{
  "type": "Feature",
  "properties": {
    "addr:full":"210 Terrace Ave Baton Rouge LA 70802",
    "addr:housenumber":"210",
    "addr:postcode":"70802",
    "addr:street":"Terrace Ave",
    "iso:country":"US",
    "sg:address":"210 Terrace Ave",
    "sg:city":"Baton Rouge",
    "sg:classifiers":[
        {
            "category":"Organizations",
            "subcategory":"Professional Association",
            "type":"Services"
        }
    ],
    "sg:phone":"+1 225 383 1023",
    "sg:postcode":"70802",
    "sg:province":"LA",
    "sg:tags":[
        "business"
    ],
    "wof:name":"American Subcontractors Assn",
    "wof:placetype":"venue"
},
  "geometry": {"coordinates":[-91.188079,30.436224],"type":"Point"}
}