{
  "type": "Feature",
  "properties": {
    "iso:country":"US",
    "sg:address":"7539 Jefferson Hwy",
    "sg:city":"Baton Rouge",
    "sg:classifiers":[
        {
            "category":"Home & Garden",
            "subcategory":"Hardware",
            "type":"Retail Goods"
        }
    ],
    "sg:phone":"+1 225 926 0040",
    "sg:postcode":"70806",
    "sg:province":"LA",
    "wof:name":"Goodwood Hardware & Outdoors",
    "wof:placetype":"venue"
},
  "geometry": {"coordinates":[-91.109678,30.431646],"type":"Point"}
}