{
  "type": "Feature",
  "properties": {
    "iso:country":"US",
    "sg:address":"6570 Youree Dr",
    "sg:city":"Shreveport",
    "sg:classifiers":[
        {
            "category":"Insurance",
            "subcategory":"Insurance Agent",
            "type":"Services"
        }
    ],
    "sg:phone":"+1 318 797 0262",
    "sg:postcode":"71105",
    "sg:province":"LA",
    "wof:name":"AAA Insurance",
    "wof:placetype":"venue"
},
  "geometry": {"coordinates":[-93.720116,32.445717],"type":"Point"}
}