{
  "type": "Feature",
  "properties": {
    "iso:country":"US",
    "sg:address":"3631 State Rte 78",
    "sg:city":"Livonia",
    "sg:classifiers":[
        {
            "category":"Organizations",
            "subcategory":"Religious Organization",
            "type":"Services"
        }
    ],
    "sg:phone":"+1 225 637 3730",
    "sg:postcode":"70755",
    "sg:province":"LA",
    "sg:tags":[
        "church"
    ],
    "wof:name":"Place Of Refuge Ministries",
    "wof:placetype":"venue"
},
  "geometry": {"coordinates":[-91.543055,30.57538],"type":"Point"}
}