{
  "type": "Feature",
  "properties": {
    "iso:country":"US",
    "sg:address":"2201 Williams Blvd",
    "sg:city":"Kenner",
    "sg:classifiers":[
        {
            "category":"Retail",
            "subcategory":"Self-service Laundry",
            "type":"Services"
        }
    ],
    "sg:phone":"+1 504 466 8588",
    "sg:postcode":"70062",
    "sg:province":"LA",
    "wof:name":"Laundry Basket",
    "wof:placetype":"venue"
},
  "geometry": {"coordinates":[-90.24131,29.997617],"type":"Point"}
}