{
  "type": "Feature",
  "properties": {
    "iso:country":"US",
    "sg:address":"104 N Corner St",
    "sg:city":"Delcambre",
    "sg:classifiers":[
        {
            "category":"Utilities",
            "subcategory":"Telephone",
            "type":"Services"
        }
    ],
    "sg:phone":"+1 337 685 2311",
    "sg:postcode":"70528",
    "sg:province":"LA",
    "sg:tags":[
        "company"
    ],
    "sg:website":"www.delcambre.net",
    "wof:name":"Delcambre Telephone Co",
    "wof:placetype":"venue"
},
  "geometry": {"coordinates":[-91.98924599999999,29.949124],"type":"Point"}
}