{
  "type": "Feature",
  "properties": {
    "addr:full":"14427 Airline Hwy Gonzales LA 70737",
    "addr:housenumber":"14427",
    "addr:postcode":"70737",
    "addr:street":"Airline Hwy Gonzales La",
    "iso:country":"US",
    "sg:address":"14427 Airline Hwy",
    "sg:city":"Gonzales",
    "sg:classifiers":[
        {
            "category":"Autos & Motor Vehicles",
            "subcategory":"Automobile Sales",
            "type":"Retail Goods"
        }
    ],
    "sg:phone":"+1 225 673 6272",
    "sg:postcode":"70737",
    "sg:province":"LA",
    "sg:tags":[
        "car",
        "dealer"
    ],
    "wof:name":"S & W Auto Sales",
    "wof:placetype":"venue"
},
  "geometry": {"coordinates":[-90.949077,30.27716],"type":"Point"}
}