{
  "type": "Feature",
  "properties": {
    "addr:full":"1127 Forsythe Ave Monroe LA 71201",
    "addr:housenumber":"1127",
    "addr:postcode":"71201",
    "addr:street":"Forsythe Ave",
    "iso:country":"US",
    "sg:address":"1127 Forsythe Ave",
    "sg:city":"Monroe",
    "sg:classifiers":[
        {
            "category":"Shopping",
            "subcategory":"Gifts & Souvenirs",
            "type":"Retail Goods"
        }
    ],
    "sg:phone":"+1 318 398 3298",
    "sg:postcode":"71201",
    "sg:province":"LA",
    "sg:tags":[
        "shop"
    ],
    "wof:name":"Bedbugs",
    "wof:placetype":"venue"
},
  "geometry": {"coordinates":[-92.122288,32.525794],"type":"Point"}
}