{
  "type": "Feature",
  "properties": {
    "addr:full":"336 Wren St Morgan City LA 70380",
    "addr:housenumber":"336",
    "addr:postcode":"70380",
    "addr:street":"Wren St",
    "iso:country":"US",
    "sg:address":"336 Wren St",
    "sg:city":"Morgan City",
    "sg:classifiers":[
        {
            "category":"Real Estate",
            "subcategory":"Real Estate Agent",
            "type":"Services"
        }
    ],
    "sg:phone":"+1 985 384 5118",
    "sg:postcode":"70380",
    "sg:province":"LA",
    "sg:tags":[
        "authorities",
        "housing"
    ],
    "wof:name":"US Housing Authority",
    "wof:placetype":"venue"
},
  "geometry": {"coordinates":[-91.195868,29.715579],"type":"Point"}
}