{
  "type": "Feature",
  "properties": {
    "addr:full":"1624 Shannon Rd Alexandria LA 71301",
    "addr:housenumber":"1624",
    "addr:postcode":"71301",
    "addr:street":"Shannon Rd",
    "iso:country":"US",
    "sg:address":"1624 Shannon Rd",
    "sg:city":"Alexandria",
    "sg:classifiers":[
        {
            "category":"Shopping",
            "subcategory":"Pharmacy",
            "type":"Retail Goods"
        }
    ],
    "sg:phone":"+1 318 448 3374",
    "sg:postcode":"71301",
    "sg:province":"LA",
    "sg:tags":[
        "aid",
        "first",
        "supply"
    ],
    "wof:name":"First Aid & Safety Supply Co",
    "wof:placetype":"venue"
},
  "geometry": {"coordinates":[-92.479848,31.269102],"type":"Point"}
}