{
  "type": "Feature",
  "properties": {
    "iso:country":"US",
    "sg:address":"100 Stone Rd",
    "sg:city":"Slidell",
    "sg:classifiers":[
        {
            "category":"Freight",
            "type":"Transportation"
        }
    ],
    "sg:phone":"+1 985 646 4957",
    "sg:postcode":"70460",
    "sg:province":"LA",
    "sg:tags":[
        "warehouse"
    ],
    "wof:name":"St Tammany Parish School Board",
    "wof:placetype":"venue"
},
  "geometry": {"coordinates":[-89.78095500000001,30.303306],"type":"Point"}
}