{
  "type": "Feature",
  "properties": {
    "addr:full":"1360 Salem Rd Farmerville LA 71241",
    "addr:housenumber":"1360",
    "addr:postcode":"71241",
    "addr:street":"Salem Rd",
    "iso:country":"US",
    "sg:address":"1360 Salem Rd",
    "sg:city":"Farmerville",
    "sg:classifiers":[
        {
            "category":"Building & Trades",
            "subcategory":"Landscaping Services",
            "type":"Services"
        }
    ],
    "sg:phone":"+1 318 368 7923",
    "sg:postcode":"71241",
    "sg:province":"LA",
    "sg:tags":[
        "landscape",
        "contractor"
    ],
    "wof:name":"Albritton Lawn & Irrigation",
    "wof:placetype":"venue"
},
  "geometry": {"coordinates":[-92.347568,32.834237],"type":"Point"}
}