{
  "type": "Feature",
  "properties": {
    "iso:country":"US",
    "sg:address":"1013 N Pine St",
    "sg:city":"Deridder",
    "sg:classifiers":[
        {
            "category":"Banks & Credit Unions",
            "subcategory":"Bank",
            "type":"Services"
        }
    ],
    "sg:phone":"+1 337 463 4290",
    "sg:postcode":"70634",
    "sg:province":"LA",
    "sg:tags":[
        "cashing",
        "check"
    ],
    "wof:name":"Advance America",
    "wof:placetype":"venue"
},
  "geometry": {"coordinates":[-93.284998,30.86694],"type":"Point"}
}