{
  "type": "Feature",
  "properties": {
    "iso:country":"US",
    "sg:address":"12905 Hammack Rd",
    "sg:city":"Denham Springs",
    "sg:classifiers":[
        {
            "category":"Building & Trades",
            "subcategory":"Construction",
            "type":"Services"
        }
    ],
    "sg:phone":"+1 225 665 1926",
    "sg:postcode":"70726",
    "sg:province":"LA",
    "sg:tags":[
        "contractor"
    ],
    "wof:name":"R Coleman Contracting Inc",
    "wof:placetype":"venue"
},
  "geometry": {"coordinates":[-90.87119,30.393592],"type":"Point"}
}