{
  "type": "Feature",
  "properties": {
    "addr:full":"317 Tunica Dr W Marksville LA 71351",
    "addr:housenumber":"317",
    "addr:postcode":"71351",
    "addr:street":"Tunica Dr W Marksville",
    "iso:country":"US",
    "sg:address":"317 Tunica Dr W",
    "sg:city":"Marksville",
    "sg:classifiers":[
        {
            "category":"Restaurant",
            "type":"Food & Drink"
        }
    ],
    "sg:menulink":"http://www.allmenus.com/la/marksville/72930-pizza-hut/menu/",
    "sg:phone":"+1 318 253 4561",
    "sg:postcode":"71351",
    "sg:province":"LA",
    "sg:tags":[
        "american",
        "pizza"
    ],
    "wof:name":"Pizza Hut",
    "wof:placetype":"venue"
},
  "geometry": {"coordinates":[-92.073245,31.125816],"type":"Point"}
}