{
  "type": "Feature",
  "properties": {
    "addr:full":"2628 Delaware Ave Kenner LA 70062",
    "addr:housenumber":"2628",
    "addr:postcode":"70062",
    "addr:street":"Delaware Ave",
    "iso:country":"US",
    "sg:address":"2628 Delaware Ave",
    "sg:city":"Kenner",
    "sg:classifiers":[
        {
            "category":"Manufacturing",
            "subcategory":"Metals",
            "type":"Manufacturing & Wholesale Goods"
        }
    ],
    "sg:phone":"+1 504 472 9888",
    "sg:postcode":"70062",
    "sg:province":"LA",
    "sg:tags":[
        "coating",
        "powder"
    ],
    "wof:name":"Armadillo Coating Co",
    "wof:placetype":"venue"
},
  "geometry": {"coordinates":[-90.242592,30.004638],"type":"Point"}
}