{
  "type": "Feature",
  "properties": {
    "iso:country":"US",
    "sg:address":"1506 S Morrison Blvd",
    "sg:city":"Hammond",
    "sg:classifiers":[
        {
            "category":"Banks & Credit Unions",
            "subcategory":"Bank",
            "type":"Services"
        }
    ],
    "sg:phone":"+1 985 902 1500",
    "sg:postcode":"70403",
    "sg:province":"LA",
    "wof:name":"Hibernia National Bank",
    "wof:placetype":"venue"
},
  "geometry": {"coordinates":[-90.482776,30.485298],"type":"Point"}
}