{
  "type": "Feature",
  "properties": {
    "iso:country":"US",
    "sg:address":"4539 N I- 10 Svc Rd W",
    "sg:city":"Metairie",
    "sg:classifiers":[
        {
            "category":"Communications",
            "subcategory":"Radio Station",
            "type":"Services"
        }
    ],
    "sg:phone":"+1 504 454 9000",
    "sg:postcode":"70006",
    "sg:province":"LA",
    "sg:tags":[
        "company",
        "broadcasting"
    ],
    "wof:name":"WTIX",
    "wof:placetype":"venue"
},
  "geometry": {"coordinates":[-90.18338,30.001192],"type":"Point"}
}