{
  "type": "Feature",
  "properties": {
    "iso:country":"US",
    "sg:address":"8645 State Rte 182",
    "sg:city":"Franklin",
    "sg:classifiers":[
        {
            "category":"Food & Beverages",
            "subcategory":"Groceries & Convenience Stores",
            "type":"Retail Goods"
        }
    ],
    "sg:phone":"+1 337 836 9700",
    "sg:postcode":"70538",
    "sg:province":"LA",
    "wof:name":"Deli-Mart",
    "wof:placetype":"venue"
},
  "geometry": {"coordinates":[-91.41688000000001,29.759009],"type":"Point"}
}