{
  "type": "Feature",
  "properties": {
    "addr:full":"1600 Dorothy Cir New Iberia LA 70560",
    "addr:housenumber":"1600",
    "addr:postcode":"70560",
    "addr:street":"Dorothy Cir",
    "iso:country":"US",
    "sg:address":"1600 Dorothy Cir",
    "sg:city":"New Iberia",
    "sg:classifiers":[
        {
            "category":"Food & Beverages",
            "subcategory":"Meat & Fish",
            "type":"Retail Goods"
        }
    ],
    "sg:phone":"+1 337 364 6497",
    "sg:postcode":"70560",
    "sg:province":"LA",
    "sg:tags":[
        "seafood"
    ],
    "wof:name":"CNT Seafood Inc",
    "wof:placetype":"venue"
},
  "geometry": {"coordinates":[-91.79568999999999,29.991498],"type":"Point"}
}