{
  "type": "Feature",
  "properties": {
    "iso:country":"US",
    "sg:address":"401 Audubon Blvd",
    "sg:city":"Lafayette",
    "sg:classifiers":[
        {
            "category":"Health Services",
            "subcategory":"Clinic",
            "type":"Services"
        }
    ],
    "sg:phone":"+1 337 291 1988",
    "sg:postcode":"70503",
    "sg:province":"LA",
    "sg:tags":[
        "information",
        "program",
        "referral"
    ],
    "wof:name":"Diabetes Self Management Ctr",
    "wof:placetype":"venue"
},
  "geometry": {"coordinates":[-92.01802000000001,30.206146],"type":"Point"}
}