{
  "type": "Feature",
  "properties": {
    "iso:country":"US",
    "sg:address":"10343 Siegen Ln",
    "sg:city":"Baton Rouge",
    "sg:classifiers":[
        {
            "category":"Real Estate",
            "subcategory":"Architect",
            "type":"Services"
        }
    ],
    "sg:phone":"+1 225 768 7719",
    "sg:postcode":"70810",
    "sg:province":"LA",
    "wof:name":"John J Capdevielle II",
    "wof:placetype":"venue"
},
  "geometry": {"coordinates":[-91.080771,30.355463],"type":"Point"}
}