{
  "type": "Feature",
  "properties": {
    "iso:country":"US",
    "sg:address":"117 Tunica Dr W",
    "sg:city":"Marksville",
    "sg:classifiers":[
        {
            "category":"Restaurant",
            "type":"Food & Drink"
        }
    ],
    "sg:phone":"+1 318 240 8606",
    "sg:postcode":"71351",
    "sg:province":"LA",
    "wof:name":"Southern Cookin",
    "wof:placetype":"venue"
},
  "geometry": {"coordinates":[-92.071337,31.125253],"type":"Point"}
}