{
  "type": "Feature",
  "properties": {
    "iso:country":"US",
    "sg:address":"2934 Johnston St",
    "sg:city":"Lafayette",
    "sg:classifiers":[
        {
            "category":"Professional",
            "subcategory":"Accounting & Tax Preparation",
            "type":"Services"
        }
    ],
    "sg:phone":"+1 337 269 9884",
    "sg:postcode":"70503",
    "sg:province":"LA",
    "sg:tags":[
        "return"
    ],
    "wof:name":"H & R Block",
    "wof:placetype":"venue"
},
  "geometry": {"coordinates":[-92.041127,30.205719],"type":"Point"}
}