{
  "type": "Feature",
  "properties": {
    "addr:full":"520 Hancock St Gretna LA 70053",
    "addr:housenumber":"520",
    "addr:postcode":"70053",
    "addr:street":"Hancock St",
    "iso:country":"US",
    "sg:address":"520 Hancock St",
    "sg:city":"Gretna",
    "sg:classifiers":[
        {
            "category":"Manufacturing",
            "subcategory":"Glass & Minerals",
            "type":"Manufacturing & Wholesale Goods"
        }
    ],
    "sg:phone":"+1 504 363 1577",
    "sg:postcode":"70053",
    "sg:province":"LA",
    "sg:tags":[
        "stone"
    ],
    "wof:name":"Weiser Services",
    "wof:placetype":"venue"
},
  "geometry": {"coordinates":[-90.04862900000001,29.934555],"type":"Point"}
}