{
  "type": "Feature",
  "properties": {
    "iso:country":"US",
    "sg:address":"107 Carrollwood Dr",
    "sg:city":"La Place",
    "sg:classifiers":[
        {
            "category":"Bars & Pubs",
            "type":"Food & Drink"
        }
    ],
    "sg:phone":"+1 985 652 4412",
    "sg:postcode":"70068",
    "sg:province":"LA",
    "sg:tags":[
        "lounge",
        "cocktail"
    ],
    "wof:name":"Plantation Pub",
    "wof:placetype":"venue"
},
  "geometry": {"coordinates":[-90.49630000000001,30.073056],"type":"Point"}
}