{
  "type": "Feature",
  "properties": {
    "iso:country":"US",
    "sg:address":"6635 Complex Dr",
    "sg:city":"Baton Rouge",
    "sg:classifiers":[
        {
            "category":"Retail",
            "subcategory":"Laundry & Dry Cleaning",
            "type":"Services"
        }
    ],
    "sg:phone":"+1 225 752 1333",
    "sg:postcode":"70809",
    "sg:province":"LA",
    "sg:tags":[
        "cleaners",
        "rug",
        "carpet"
    ],
    "sg:website":"www.stanleysteemer.com",
    "wof:name":"Stanley Steemer Carpet Cleaner",
    "wof:placetype":"venue"
},
  "geometry": {"coordinates":[-91.049734,30.382189],"type":"Point"}
}