{
  "type": "Feature",
  "properties": {
    "addr:full":"16955 Kilbourne Hwy Jones LA 71250",
    "addr:housenumber":"16955",
    "addr:postcode":"71250",
    "addr:street":"Kilbourne Hwy Jones La",
    "iso:country":"US",
    "sg:address":"16955 Kilbourne Hwy",
    "sg:city":"Jones",
    "sg:classifiers":[
        {
            "category":"Travel",
            "subcategory":"Campground",
            "type":"Entertainment"
        }
    ],
    "sg:phone":"+1 318 823 4091",
    "sg:postcode":"71250",
    "sg:province":"LA",
    "sg:tags":[
        "camp"
    ],
    "wof:name":"Wayne Ricks Farm",
    "wof:placetype":"venue"
},
  "geometry": {"coordinates":[-91.52942400000001,32.973608],"type":"Point"}
}