{
  "type": "Feature",
  "properties": {
    "iso:country":"US",
    "sg:address":"2308 Meriwether Rd",
    "sg:city":"Shreveport",
    "sg:classifiers":[
        {
            "category":"Utilities",
            "type":"Services"
        }
    ],
    "sg:phone":"+1 318 688 2646",
    "sg:postcode":"71108",
    "sg:province":"LA",
    "sg:tags":[
        "sweeping"
    ],
    "wof:name":"Pollard's Parking Lot Cleaning",
    "wof:placetype":"venue"
},
  "geometry": {"coordinates":[-93.797315,32.42026],"type":"Point"}
}