{
  "type": "Feature",
  "properties": {
    "iso:country":"US",
    "sg:address":"1634 Ryan St",
    "sg:city":"Lake Charles",
    "sg:classifiers":[
        {
            "category":"Insurance",
            "subcategory":"Insurance Agent",
            "type":"Services"
        }
    ],
    "sg:phone":"+1 337 436 3100",
    "sg:postcode":"70601",
    "sg:province":"LA",
    "wof:name":"GMA Agency Inc",
    "wof:placetype":"venue"
},
  "geometry": {"coordinates":[-93.21924799999999,30.217962],"type":"Point"}
}