{
  "type": "Feature",
  "properties": {
    "addr:full":"620 Bolton Ave Alexandria LA 71301",
    "addr:housenumber":"620",
    "addr:postcode":"71301",
    "addr:street":"Bolton Ave",
    "iso:country":"US",
    "sg:address":"620 Bolton Ave",
    "sg:city":"Alexandria",
    "sg:classifiers":[
        {
            "category":"Autos & Motor Vehicles",
            "subcategory":"Auto Supplies",
            "type":"Retail Goods"
        }
    ],
    "sg:phone":"+1 318 448 6246",
    "sg:postcode":"71301",
    "sg:province":"LA",
    "sg:tags":[
        "automobile",
        "parts"
    ],
    "wof:name":"Western Auto",
    "wof:placetype":"venue"
},
  "geometry": {"coordinates":[-92.456103,31.306091],"type":"Point"}
}