{
  "type": "Feature",
  "properties": {
    "iso:country":"US",
    "sg:address":"901 Mudd Ave",
    "sg:city":"Lafayette",
    "sg:classifiers":[
        {
            "category":"Sports & Exercise",
            "subcategory":"Sports Center",
            "type":"Entertainment"
        }
    ],
    "sg:phone":"+1 337 291 5558",
    "sg:postcode":"70501",
    "sg:province":"LA",
    "sg:tags":[
        "amateur",
        "team"
    ],
    "wof:name":"Domingue Center",
    "wof:placetype":"venue"
},
  "geometry": {"coordinates":[-92.007103,30.232201],"type":"Point"}
}