{
  "type": "Feature",
  "properties": {
    "iso:country":"US",
    "sg:address":"629 Chartres St",
    "sg:city":"New Orleans",
    "sg:classifiers":[
        {
            "category":"Shopping",
            "subcategory":"Used Merchandise",
            "type":"Retail Goods"
        }
    ],
    "sg:phone":"+1 504 529 2300",
    "sg:postcode":"70130",
    "sg:province":"LA",
    "sg:tags":[
        "antique"
    ],
    "wof:name":"Bienville Shop & Gallery the",
    "wof:placetype":"venue"
},
  "geometry": {"coordinates":[-90.064003,29.9573],"type":"Point"}
}