{
  "type": "Feature",
  "properties": {
    "iso:country":"US",
    "sg:address":"1636 Toledano St",
    "sg:city":"New Orleans",
    "sg:classifiers":[
        {
            "category":"Government",
            "subcategory":"Office",
            "type":"Public Place"
        }
    ],
    "sg:phone":"+1 504 896 1307",
    "sg:postcode":"70115",
    "sg:province":"LA",
    "wof:name":"Representative Renee Pratt",
    "wof:placetype":"venue"
},
  "geometry": {"coordinates":[-90.090688,29.92931],"type":"Point"}
}