{
  "type": "Feature",
  "properties": {
    "addr:full":"2529 Ames Blvd Marrero LA 70072",
    "addr:housenumber":"2529",
    "addr:postcode":"70072",
    "addr:street":"Ames Blvd Marrero",
    "iso:country":"US",
    "sg:address":"2529 Ames Blvd",
    "sg:city":"Marrero",
    "sg:classifiers":[
        {
            "category":"Personal",
            "subcategory":"Barber",
            "type":"Services"
        }
    ],
    "sg:phone":"+1 504 328 0206",
    "sg:postcode":"70072",
    "sg:province":"LA",
    "wof:name":"Loc's Barber Shop",
    "wof:placetype":"venue"
},
  "geometry": {"coordinates":[-90.110641,29.864734],"type":"Point"}
}