{
  "type": "Feature",
  "properties": {
    "iso:country":"US",
    "sg:address":"9953 State Rte 120",
    "sg:city":"Robeline",
    "sg:classifiers":[
        {
            "category":"Building & Trades",
            "subcategory":"Construction",
            "type":"Services"
        }
    ],
    "sg:phone":"+1 318 472 6478",
    "sg:postcode":"71469",
    "sg:province":"LA",
    "sg:tags":[
        "clearing",
        "land",
        "leveling"
    ],
    "wof:name":"Specialty Contractors",
    "wof:placetype":"venue"
},
  "geometry": {"coordinates":[-93.37302099999999,31.736545],"type":"Point"}
}