{
  "type": "Feature",
  "properties": {
    "addr:full":"302 Dumas Judice Rd New Iberia LA 70563",
    "addr:housenumber":"302",
    "addr:postcode":"70563",
    "addr:street":"Dumas Judice Rd",
    "iso:country":"US",
    "sg:address":"302 Dumas Judice Rd",
    "sg:city":"New Iberia",
    "sg:classifiers":[
        {
            "category":"Professional",
            "subcategory":"Business Services",
            "type":"Services"
        }
    ],
    "sg:phone":"+1 337 229 6859",
    "sg:postcode":"70563",
    "sg:province":"LA",
    "sg:tags":[
        "water",
        "treatment",
        "conditioning"
    ],
    "wof:name":"Steve Thibeaux Water Cond",
    "wof:placetype":"venue"
},
  "geometry": {"coordinates":[-91.779141,30.057055],"type":"Point"}
}