{
  "type": "Feature",
  "properties": {
    "addr:full":"1140 Roma Ave Hammond LA 70403",
    "addr:housenumber":"1140",
    "addr:postcode":"70403",
    "addr:street":"Roma Ave",
    "iso:country":"US",
    "sg:address":"1140 Roma Ave",
    "sg:city":"Hammond",
    "sg:classifiers":[
        {
            "category":"Real Estate",
            "subcategory":"Real Estate Agent",
            "type":"Services"
        }
    ],
    "sg:phone":"+1 985 542 1893",
    "sg:postcode":"70403",
    "sg:province":"LA",
    "sg:website":"www.prudentialgardner.com",
    "wof:name":"Prudential Gardner Realtors",
    "wof:placetype":"venue"
},
  "geometry": {"coordinates":[-90.483068,30.489389],"type":"Point"}
}