{
  "type": "Feature",
  "properties": {
    "iso:country":"US",
    "sg:address":"324 Court St",
    "sg:city":"Baton Rouge",
    "sg:classifiers":[
        {
            "category":"Professional",
            "type":"Services"
        }
    ],
    "sg:phone":"+1 225 769 0758",
    "sg:postcode":"70810",
    "sg:province":"LA",
    "wof:name":"Sealco Inc",
    "wof:placetype":"venue"
},
  "geometry": {"coordinates":[-91.093323,30.357045],"type":"Point"}
}