{
  "type": "Feature",
  "properties": {
    "addr:full":"507 Emmeline St New Iberia LA 70563",
    "addr:housenumber":"507",
    "addr:postcode":"70563",
    "addr:street":"Emmeline St",
    "iso:country":"US",
    "sg:address":"507 Emmeline St",
    "sg:city":"New Iberia",
    "sg:classifiers":[
        {
            "category":"Building & Trades",
            "subcategory":"Electrical",
            "type":"Services"
        }
    ],
    "sg:phone":"+1 337 365 2833",
    "sg:postcode":"70563",
    "sg:province":"LA",
    "sg:tags":[
        "electric",
        "contractor"
    ],
    "wof:name":"Migues Electric",
    "wof:placetype":"venue"
},
  "geometry": {"coordinates":[-91.784451,30.006983],"type":"Point"}
}