{
  "type": "Feature",
  "properties": {
    "iso:country":"US",
    "sg:address":"5500 Prytania St",
    "sg:city":"New Orleans",
    "sg:classifiers":[
        {
            "category":"Manufacturing",
            "subcategory":"Printing",
            "type":"Manufacturing & Wholesale Goods"
        }
    ],
    "sg:phone":"+1 504 269 4050",
    "sg:postcode":"70115",
    "sg:province":"LA",
    "sg:tags":[
        "publisher"
    ],
    "wof:name":"Urban Dog Magazine",
    "wof:placetype":"venue"
},
  "geometry": {"coordinates":[-90.115892,29.925537],"type":"Point"}
}