{
  "type": "Feature",
  "properties": {
    "addr:full":"2132 Oneal Ln Baton Rouge LA 70816",
    "addr:housenumber":"2132",
    "addr:postcode":"70816",
    "addr:street":"Oneal Ln",
    "iso:country":"US",
    "sg:address":"2132 Oneal Ln",
    "sg:city":"Baton Rouge",
    "sg:classifiers":[
        {
            "category":"Restaurant",
            "type":"Food & Drink"
        }
    ],
    "sg:phone":"+1 225 756 7888",
    "sg:postcode":"70816",
    "sg:province":"LA",
    "wof:name":"China King",
    "wof:placetype":"venue"
},
  "geometry": {"coordinates":[-91.007644,30.436213],"type":"Point"}
}