{
  "type": "Feature",
  "properties": {
    "addr:full":"846 Howard Ave New Orleans LA 70113",
    "addr:housenumber":"846",
    "addr:postcode":"70113",
    "addr:street":"Howard Ave",
    "iso:country":"US",
    "sg:address":"846 Howard Ave",
    "sg:city":"New Orleans",
    "sg:classifiers":[
        {
            "category":"Communications",
            "subcategory":"Television Station",
            "type":"Services"
        }
    ],
    "sg:phone":"+1 504 679 0600",
    "sg:postcode":"70113",
    "sg:province":"LA",
    "sg:tags":[
        "broadcasting",
        "co"
    ],
    "sg:website":"www.theneworleanschannel.com",
    "wof:name":"WDSU",
    "wof:placetype":"venue"
},
  "geometry": {"coordinates":[-90.07437299999999,29.944315],"type":"Point"}
}