{
  "type": "Feature",
  "properties": {
    "iso:country":"US",
    "sg:address":"2127 State Rte 30",
    "sg:city":"Gonzales",
    "sg:classifiers":[
        {
            "category":"Retail",
            "subcategory":"Car Wash",
            "type":"Services"
        }
    ],
    "sg:phone":"+1 225 644 5152",
    "sg:postcode":"70737",
    "sg:province":"LA",
    "sg:tags":[
        "truck",
        "cleaning"
    ],
    "wof:name":"Rapid Touchless Truckwash",
    "wof:placetype":"venue"
},
  "geometry": {"coordinates":[-90.945714,30.210687],"type":"Point"}
}