{
  "type": "Feature",
  "properties": {
    "addr:full":"528 Huey P Long Ave Gretna LA 70053",
    "addr:housenumber":"528;p",
    "addr:postcode":"70053",
    "addr:street":"Huey;Long Ave",
    "iso:country":"US",
    "sg:address":"528 Huey P Long Ave",
    "sg:city":"Gretna",
    "sg:classifiers":[
        {
            "category":"Professional",
            "subcategory":"Lawyer & Legal Services",
            "type":"Services"
        }
    ],
    "sg:phone":"+1 504 362 9811",
    "sg:postcode":"70053",
    "sg:province":"LA",
    "wof:name":"Gaudet James K Atty",
    "wof:placetype":"venue"
},
  "geometry": {"coordinates":[-90.064001,29.914488],"type":"Point"}
}