{
  "type": "Feature",
  "properties": {
    "iso:country":"US",
    "sg:address":"605 Warren St",
    "sg:city":"Deridder",
    "sg:classifiers":[
        {
            "category":"Organizations",
            "subcategory":"Religious Organization",
            "type":"Services"
        }
    ],
    "sg:phone":"+1 337 463 2544",
    "sg:postcode":"70634",
    "sg:province":"LA",
    "wof:name":"Deliverance Tabernacle",
    "wof:placetype":"venue"
},
  "geometry": {"coordinates":[-93.287724,30.854576],"type":"Point"}
}