{
  "type": "Feature",
  "properties": {
    "iso:country":"US",
    "sg:address":"740 Milton St",
    "sg:city":"Gretna",
    "sg:classifiers":[
        {
            "category":"Building & Trades",
            "subcategory":"Construction",
            "type":"Services"
        }
    ],
    "sg:phone":"+1 504 227 9099",
    "sg:postcode":"70053",
    "sg:province":"LA",
    "sg:tags":[
        "roofing",
        "contractor"
    ],
    "sg:website":"www.brandtindustries-inc.com",
    "wof:name":"Brandt Industries Inc",
    "wof:placetype":"venue"
},
  "geometry": {"coordinates":[-90.04984399999999,29.920858],"type":"Point"}
}