{
  "type": "Feature",
  "properties": {
    "addr:full":"1102 Hwy 3185 Thibodaux LA 70301",
    "addr:housenumber":"1102",
    "addr:postcode":"3185;70301",
    "addr:street":"Hwy",
    "iso:country":"US",
    "sg:address":"1102 Hwy 3185",
    "sg:city":"Thibodaux",
    "sg:classifiers":[
        {
            "category":"Government",
            "subcategory":"Office",
            "type":"Public Place"
        }
    ],
    "sg:phone":"+1 985 447 0821",
    "sg:postcode":"70301",
    "sg:province":"LA",
    "sg:tags":[
        "state"
    ],
    "wof:name":"Wildlife & Fisheries Dept",
    "wof:placetype":"venue"
},
  "geometry": {"coordinates":[-90.84523,29.77364],"type":"Point"}
}