{
  "type": "Feature",
  "properties": {
    "iso:country":"US",
    "sg:address":"318 S Railroad Ave",
    "sg:city":"Opelousas",
    "sg:classifiers":[
        {
            "category":"Retail",
            "subcategory":"Repair Shop",
            "type":"Services"
        }
    ],
    "sg:phone":"+1 337 948 8248",
    "sg:postcode":"70570",
    "sg:province":"LA",
    "sg:tags":[
        "ironwork"
    ],
    "wof:name":"Cary Iron Works Inc",
    "wof:placetype":"venue"
},
  "geometry": {"coordinates":[-92.088336,30.532489],"type":"Point"}
}