{
  "type": "Feature",
  "properties": {
    "addr:full":"1423 Annunciation St New Orleans LA 70130",
    "addr:housenumber":"1423",
    "addr:postcode":"70130",
    "addr:street":"Annunciation St",
    "iso:country":"US",
    "sg:address":"1423 Annunciation St",
    "sg:city":"New Orleans",
    "sg:classifiers":[
        {
            "category":"Wholesale",
            "subcategory":"Machinery & Supplies",
            "type":"Manufacturing & Wholesale Goods"
        }
    ],
    "sg:phone":"+1 504 522 5553",
    "sg:postcode":"70130",
    "sg:province":"LA",
    "sg:tags":[
        "bearing"
    ],
    "wof:name":"Industrial Bearings Inc",
    "wof:placetype":"venue"
},
  "geometry": {"coordinates":[-90.069605,29.935476],"type":"Point"}
}