{
  "type": "Feature",
  "properties": {
    "addr:full":"5407 Dauphine St New Orleans LA 70117",
    "addr:housenumber":"5407",
    "addr:postcode":"70117",
    "addr:street":"Dauphine St",
    "iso:country":"US",
    "sg:address":"5407 Dauphine St",
    "sg:city":"New Orleans",
    "sg:classifiers":[
        {
            "category":"Social Services",
            "subcategory":"Child Care",
            "type":"Services"
        }
    ],
    "sg:phone":"+1 504 943 6952",
    "sg:postcode":"70117",
    "sg:province":"LA",
    "wof:name":"St Anthony's Head Start Ctr",
    "wof:placetype":"venue"
},
  "geometry": {"coordinates":[-90.017912,29.958354],"type":"Point"}
}