{
  "type": "Feature",
  "properties": {
    "addr:full":"51 Hollycrest Blvd Covington LA 70433",
    "addr:housenumber":"51",
    "addr:postcode":"70433",
    "addr:street":"Hollycrest Blvd",
    "iso:country":"US",
    "sg:address":"51 Hollycrest Blvd",
    "sg:city":"Covington",
    "sg:classifiers":[
        {
            "category":"Health Services",
            "subcategory":"Health Practitioner",
            "type":"Services"
        }
    ],
    "sg:phone":"+1 985 373 7334",
    "sg:postcode":"70433",
    "sg:province":"LA",
    "wof:name":"Gail Chandler Rn",
    "wof:placetype":"venue"
},
  "geometry": {"coordinates":[-90.081153,30.437792],"type":"Point"}
}