{
  "type": "Feature",
  "properties": {
    "addr:full":"4715 E Brookstown Dr Baton Rouge LA 70805",
    "addr:housenumber":"4715",
    "addr:postcode":"70805",
    "addr:street":"E Brookstown Dr",
    "iso:country":"US",
    "sg:address":"4715 E Brookstown Dr",
    "sg:city":"Baton Rouge",
    "sg:classifiers":[
        {
            "category":"Personal",
            "subcategory":"Barber",
            "type":"Services"
        }
    ],
    "sg:phone":"+1 225 355 7855",
    "sg:postcode":"70805",
    "sg:province":"LA",
    "wof:name":"Brookstown Barber Shop",
    "wof:placetype":"venue"
},
  "geometry": {"coordinates":[-91.12843599999999,30.49444],"type":"Point"}
}