{
  "type": "Feature",
  "properties": {
    "addr:full":"2014 W Pinhook Rd Lafayette LA 70508",
    "addr:housenumber":"2014",
    "addr:postcode":"70508",
    "addr:street":"W Pinhook Rd",
    "iso:country":"US",
    "sg:address":"2014 W Pinhook Rd",
    "sg:city":"Lafayette",
    "sg:classifiers":[
        {
            "category":"Insurance",
            "subcategory":"Life Insurance",
            "type":"Services"
        }
    ],
    "sg:phone":"+1 337 237 8555",
    "sg:postcode":"70508",
    "sg:province":"LA",
    "sg:tags":[
        "carrier",
        "carrie"
    ],
    "wof:name":"Humana",
    "wof:placetype":"venue"
},
  "geometry": {"coordinates":[-92.010452,30.185555],"type":"Point"}
}