{
  "type": "Feature",
  "properties": {
    "iso:country":"US",
    "sg:address":"3220 Kaliste Saloom Rd",
    "sg:city":"Lafayette",
    "sg:classifiers":[
        {
            "category":"Health Services",
            "subcategory":"Doctor",
            "type":"Services"
        }
    ],
    "sg:phone":"+1 337 981 8486",
    "sg:postcode":"70508",
    "sg:province":"LA",
    "sg:tags":[
        "physician",
        "surgeon"
    ],
    "wof:name":"Our Lady Of Lourdes Hospital",
    "wof:placetype":"venue"
},
  "geometry": {"coordinates":[-92.056853,30.147453],"type":"Point"}
}