{
  "type": "Feature",
  "properties": {
    "addr:full":"1819 N Macarthur Dr Alexandria LA 71303",
    "addr:housenumber":"1819",
    "addr:postcode":"71303",
    "addr:street":"N Macarthur Dr",
    "iso:country":"US",
    "sg:address":"1819 N Macarthur Dr",
    "sg:city":"Alexandria",
    "sg:classifiers":[
        {
            "category":"Restaurant",
            "type":"Food & Drink"
        }
    ],
    "sg:phone":"+1 318 487 6797",
    "sg:postcode":"71303",
    "sg:province":"LA",
    "wof:name":"Pizza Hut",
    "wof:placetype":"venue"
},
  "geometry": {"coordinates":[-92.470147,31.315342],"type":"Point"}
}