{
  "type": "Feature",
  "properties": {
    "iso:country":"US",
    "sg:address":"161 James Dr W",
    "sg:city":"St Rose",
    "sg:classifiers":[
        {
            "category":"Wholesale",
            "subcategory":"Machinery & Supplies",
            "type":"Manufacturing & Wholesale Goods"
        }
    ],
    "sg:phone":"+1 504 443 0501",
    "sg:postcode":"70047",
    "sg:province":"LA",
    "sg:tags":[
        "equipment",
        "marine"
    ],
    "wof:name":"Z F Industries Marine Div",
    "wof:placetype":"venue"
},
  "geometry": {"coordinates":[-90.346934,29.93953],"type":"Point"}
}