{
  "type": "Feature",
  "properties": {
    "addr:full":"4617 Gary Mikel Ave Metairie LA 70002",
    "addr:housenumber":"4617",
    "addr:postcode":"70002",
    "addr:street":"Gary Mikel Ave",
    "iso:country":"US",
    "sg:address":"4617 Gary Mikel Ave",
    "sg:city":"Metairie",
    "sg:classifiers":[
        {
            "category":"Professional",
            "subcategory":"Business Services",
            "type":"Services"
        }
    ],
    "sg:phone":"+1 504 457 6081",
    "sg:postcode":"70002",
    "sg:province":"LA",
    "sg:tags":[
        "mail",
        "shipping"
    ],
    "wof:name":"Cargo Procurement",
    "wof:placetype":"venue"
},
  "geometry": {"coordinates":[-90.172938,30.017842],"type":"Point"}
}