{
  "type": "Feature",
  "properties": {
    "iso:country":"US",
    "sg:address":"842 Gerard St",
    "sg:city":"Mandeville",
    "sg:classifiers":[
        {
            "category":"Education",
            "subcategory":"Library",
            "type":"Public Place"
        }
    ],
    "sg:phone":"+1 985 626 4293",
    "sg:postcode":"70448",
    "sg:province":"LA",
    "wof:name":"Mandeville Branch Library",
    "wof:placetype":"venue"
},
  "geometry": {"coordinates":[-90.061965,30.362944],"type":"Point"}
}