{
  "type": "Feature",
  "properties": {
    "iso:country":"US",
    "sg:address":"2715 Pargoud Blvd",
    "sg:city":"Monroe",
    "sg:classifiers":[
        {
            "category":"Professional",
            "subcategory":"Business Services",
            "type":"Services"
        }
    ],
    "sg:phone":"+1 318 348 0600",
    "sg:postcode":"71201",
    "sg:province":"LA",
    "wof:name":"Lisa McLaughlin Interiors",
    "wof:placetype":"venue"
},
  "geometry": {"coordinates":[-92.115557,32.551323],"type":"Point"}
}