{
  "type": "Feature",
  "properties": {
    "iso:country":"US",
    "sg:address":"107 N Cherry St",
    "sg:city":"Hammond",
    "sg:classifiers":[
        {
            "category":"Government",
            "subcategory":"Police Station",
            "type":"Public Place"
        }
    ],
    "sg:phone":"+1 985 542 3509",
    "sg:postcode":"70401",
    "sg:province":"LA",
    "sg:tags":[
        "department"
    ],
    "sg:website":"www.hammond.org",
    "wof:name":"Hammond Police Detectives",
    "wof:placetype":"venue"
},
  "geometry": {"coordinates":[-90.45875700000001,30.504945],"type":"Point"}
}