{
  "type": "Feature",
  "properties": {
    "addr:full":"704 Sterlington Hwy Farmerville LA 71241",
    "addr:housenumber":"704",
    "addr:postcode":"71241",
    "addr:street":"Sterlington Hwy",
    "iso:country":"US",
    "sg:address":"704 Sterlington Hwy",
    "sg:city":"Farmerville",
    "sg:classifiers":[
        {
            "category":"Shopping",
            "subcategory":"Tobacco",
            "type":"Retail Goods"
        }
    ],
    "sg:phone":"+1 318 368 1261",
    "sg:postcode":"71241",
    "sg:province":"LA",
    "sg:tags":[
        "product"
    ],
    "wof:name":"Tobacco Barn",
    "wof:placetype":"venue"
},
  "geometry": {"coordinates":[-92.39841300000001,32.772121],"type":"Point"}
}