{
  "type": "Feature",
  "properties": {
    "iso:country":"US",
    "sg:address":"3322 W Pinhook Rd",
    "sg:city":"Lafayette",
    "sg:classifiers":[
        {
            "category":"Shopping",
            "subcategory":"Stationery & Office Supplies",
            "type":"Retail Goods"
        }
    ],
    "sg:phone":"+1 337 234 3566",
    "sg:postcode":"70508",
    "sg:province":"LA",
    "sg:tags":[
        "equipment"
    ],
    "wof:name":"Record Keeper & Supply Inc",
    "wof:placetype":"venue"
},
  "geometry": {"coordinates":[-91.9972,30.1647],"type":"Point"}
}