{
  "type": "Feature",
  "properties": {
    "iso:country":"US",
    "sg:address":"423 State Rte 495",
    "sg:city":"Cloutierville",
    "sg:classifiers":[
        {
            "category":"Organizations",
            "subcategory":"Religious Organization",
            "type":"Services"
        }
    ],
    "sg:phone":"+1 318 379 2231",
    "sg:postcode":"71416",
    "sg:province":"LA",
    "sg:tags":[
        "church"
    ],
    "wof:name":"St John's Catholic Church",
    "wof:placetype":"venue"
},
  "geometry": {"coordinates":[-92.91702100000001,31.54378],"type":"Point"}
}