{
  "type": "Feature",
  "properties": {
    "iso:country":"US",
    "sg:address":"1155 Sligo Rd",
    "sg:city":"Bossier City",
    "sg:classifiers":[
        {
            "category":"Organizations",
            "subcategory":"Religious Organization",
            "type":"Services"
        }
    ],
    "sg:phone":"+1 318 741 5651",
    "sg:postcode":"71112",
    "sg:province":"LA",
    "sg:tags":[
        "church"
    ],
    "wof:name":"South Bossier Baptist Mission",
    "wof:placetype":"venue"
},
  "geometry": {"coordinates":[-93.611422,32.440332],"type":"Point"}
}