{
  "type": "Feature",
  "properties": {
    "iso:country":"US",
    "sg:address":"401 Reynolds Ave",
    "sg:city":"Rayne",
    "sg:classifiers":[
        {
            "category":"Social Services",
            "subcategory":"Child Care",
            "type":"Services"
        }
    ],
    "sg:phone":"+1 337 334 0075",
    "sg:postcode":"70578",
    "sg:province":"LA",
    "wof:name":"Lil Eagles Daycare",
    "wof:placetype":"venue"
},
  "geometry": {"coordinates":[-92.272774,30.240015],"type":"Point"}
}