{
  "type": "Feature",
  "properties": {
    "iso:country":"US",
    "sg:address":"2309 Jefferson Hwy",
    "sg:city":"Jefferson",
    "sg:classifiers":[
        {
            "category":"Retail",
            "subcategory":"Laundry & Dry Cleaning",
            "type":"Services"
        }
    ],
    "sg:phone":"+1 504 833 8532",
    "sg:postcode":"70121",
    "sg:province":"LA",
    "sg:tags":[
        "cleaners"
    ],
    "wof:name":"Rio Vista Cleaners",
    "wof:placetype":"venue"
},
  "geometry": {"coordinates":[-90.151522,29.96312],"type":"Point"}
}