{
  "type": "Feature",
  "properties": {
    "iso:country":"US",
    "sg:address":"2901 E Milton Ave",
    "sg:city":"Youngsville",
    "sg:classifiers":[
        {
            "category":"Education",
            "subcategory":"School",
            "type":"Public Place"
        }
    ],
    "sg:phone":"+1 337 856 1934",
    "sg:postcode":"70592",
    "sg:province":"LA",
    "wof:name":"Ernest Gallet Elementary Schl",
    "wof:placetype":"venue"
},
  "geometry": {"coordinates":[-92.010977,30.109244],"type":"Point"}
}