{
  "type": "Feature",
  "properties": {
    "iso:country":"US",
    "sg:address":"1224 Rapides Ave",
    "sg:city":"Alexandria",
    "sg:classifiers":[
        {
            "category":"Recreation",
            "subcategory":"Arcade",
            "type":"Entertainment"
        }
    ],
    "sg:phone":"+1 318 443 6638",
    "sg:postcode":"71301",
    "sg:province":"LA",
    "sg:tags":[
        "amusement",
        "devices"
    ],
    "wof:name":"Pelican Amusement Co",
    "wof:placetype":"venue"
},
  "geometry": {"coordinates":[-92.457103,31.311928],"type":"Point"}
}