{
  "type": "Feature",
  "properties": {
    "addr:full":"2963 Amazon St New Orleans LA 70114",
    "addr:housenumber":"2963",
    "addr:postcode":"70114",
    "addr:street":"Amazon St",
    "iso:country":"US",
    "sg:address":"2963 Amazon St",
    "sg:city":"New Orleans",
    "sg:classifiers":[
        {
            "category":"Insurance",
            "subcategory":"Insurance Agent",
            "type":"Services"
        }
    ],
    "sg:phone":"+1 504 363 4141",
    "sg:postcode":"70114",
    "sg:province":"LA",
    "sg:tags":[
        "accident"
    ],
    "wof:name":"Frank C Smith III Health Ins",
    "wof:placetype":"venue"
},
  "geometry": {"coordinates":[-90.029073,29.927043],"type":"Point"}
}