{
  "type": "Feature",
  "properties": {
    "iso:country":"US",
    "sg:address":"118 E Bridge St",
    "sg:city":"Breaux Bridge",
    "sg:classifiers":[
        {
            "category":"Wholesale",
            "subcategory":"Jewelry",
            "type":"Manufacturing & Wholesale Goods"
        }
    ],
    "sg:phone":"+1 337 507 3886",
    "sg:postcode":"70517",
    "sg:province":"LA",
    "sg:tags":[
        "clocks"
    ],
    "wof:name":"Clock Shop",
    "wof:placetype":"venue"
},
  "geometry": {"coordinates":[-91.89867599999999,30.274259],"type":"Point"}
}