{
  "type": "Feature",
  "properties": {
    "addr:full":"1700 Winnsboro Rd Monroe LA 71202",
    "addr:housenumber":"1700",
    "addr:postcode":"71202",
    "addr:street":"Winnsboro Rd",
    "iso:country":"US",
    "sg:address":"1700 Winnsboro Rd",
    "sg:city":"Monroe",
    "sg:classifiers":[
        {
            "category":"Autos & Motor Vehicles",
            "subcategory":"Automobile Sales",
            "type":"Retail Goods"
        }
    ],
    "sg:phone":"+1 318 387 3201",
    "sg:postcode":"71202",
    "sg:province":"LA",
    "sg:tags":[
        "car",
        "dealer"
    ],
    "wof:name":"Car Land",
    "wof:placetype":"venue"
},
  "geometry": {"coordinates":[-92.08484199999999,32.483694],"type":"Point"}
}