{
  "type": "Feature",
  "properties": {
    "iso:country":"US",
    "sg:address":"403 Vicky Ln",
    "sg:city":"Alexandria",
    "sg:classifiers":[
        {
            "category":"Building & Trades",
            "subcategory":"Construction",
            "type":"Services"
        }
    ],
    "sg:phone":"+1 318 473 2022",
    "sg:postcode":"71303",
    "sg:province":"LA",
    "sg:tags":[
        "house",
        "family"
    ],
    "wof:name":"Jeff Burns Builder Inc",
    "wof:placetype":"venue"
},
  "geometry": {"coordinates":[-92.505425,31.268417],"type":"Point"}
}