{
  "type": "Feature",
  "properties": {
    "addr:full":"8318 Hickory St New Orleans LA 70118",
    "addr:housenumber":"8318",
    "addr:postcode":"70118",
    "addr:street":"Hickory St",
    "iso:country":"US",
    "sg:address":"8318 Hickory St",
    "sg:city":"New Orleans",
    "sg:classifiers":[
        {
            "category":"Professional",
            "subcategory":"Business Services",
            "type":"Services"
        }
    ],
    "sg:phone":"+1 504 866 3426",
    "sg:postcode":"70118",
    "sg:province":"LA",
    "sg:tags":[
        "recording",
        "studio"
    ],
    "wof:name":"ELM Records",
    "wof:placetype":"venue"
},
  "geometry": {"coordinates":[-90.127734,29.953503],"type":"Point"}
}