{
  "type": "Feature",
  "properties": {
    "addr:full":"1543 Delplaza Dr Baton Rouge LA 70815",
    "addr:housenumber":"1543",
    "addr:postcode":"70815",
    "addr:street":"Delplaza Dr",
    "iso:country":"US",
    "sg:address":"1543 Delplaza Dr",
    "sg:city":"Baton Rouge",
    "sg:classifiers":[
        {
            "category":"Personal",
            "type":"Services"
        }
    ],
    "sg:phone":"+1 225 923 0470",
    "sg:postcode":"70815",
    "sg:province":"LA",
    "sg:tags":[
        "credit",
        "debt",
        "counseling"
    ],
    "wof:name":"Credit Doctor",
    "wof:placetype":"venue"
},
  "geometry": {"coordinates":[-91.08256,30.437923],"type":"Point"}
}