{
  "type": "Feature",
  "properties": {
    "iso:country":"US",
    "sg:address":"104 Secluded Forest Way",
    "sg:city":"Madisonville",
    "sg:classifiers":[
        {
            "category":"Real Estate",
            "subcategory":"Real Estate Services",
            "type":"Services"
        }
    ],
    "sg:phone":"+1 985 898 3408",
    "sg:postcode":"70447",
    "sg:province":"LA",
    "sg:tags":[
        "company",
        "title"
    ],
    "wof:name":"All Professional Title Inc",
    "wof:placetype":"venue"
},
  "geometry": {"coordinates":[-90.20599,30.467424],"type":"Point"}
}