{
  "type": "Feature",
  "properties": {
    "addr:full":"121 Burke St New Iberia LA 70560",
    "addr:housenumber":"121",
    "addr:postcode":"70560",
    "addr:street":"Burke St",
    "iso:country":"US",
    "sg:address":"121 Burke St",
    "sg:city":"New Iberia",
    "sg:classifiers":[
        {
            "category":"Professional",
            "subcategory":"Art Services",
            "type":"Services"
        }
    ],
    "sg:phone":"+1 337 369 7569",
    "sg:postcode":"70560",
    "sg:province":"LA",
    "sg:tags":[
        "commercial",
        "design"
    ],
    "wof:name":"Combined Effort",
    "wof:placetype":"venue"
},
  "geometry": {"coordinates":[-91.816863,30.005295],"type":"Point"}
}