{
  "type": "Feature",
  "properties": {
    "iso:country":"US",
    "sg:address":"11467 N Harrells Ferry Rd",
    "sg:city":"Baton Rouge",
    "sg:classifiers":[
        {
            "category":"Autos & Motor Vehicles",
            "subcategory":"Automobile Sales",
            "type":"Retail Goods"
        }
    ],
    "sg:phone":"+1 225 273 1233",
    "sg:postcode":"70816",
    "sg:province":"LA",
    "sg:tags":[
        "car",
        "dealer"
    ],
    "wof:name":"Hughes'd Cars",
    "wof:placetype":"venue"
},
  "geometry": {"coordinates":[-91.05233800000001,30.432369],"type":"Point"}
}