{
  "type": "Feature",
  "properties": {
    "iso:country":"US",
    "sg:address":"12241 Industriplex Blvd",
    "sg:city":"Baton Rouge",
    "sg:classifiers":[
        {
            "category":"Wholesale",
            "subcategory":"Durable Goods & Equipment",
            "type":"Manufacturing & Wholesale Goods"
        }
    ],
    "sg:phone":"+1 225 756 9876",
    "sg:postcode":"70809",
    "sg:province":"LA",
    "sg:tags":[
        "representative",
        "manufacturer"
    ],
    "wof:name":"Hamilton Sales Inc",
    "wof:placetype":"venue"
},
  "geometry": {"coordinates":[-91.045372,30.383767],"type":"Point"}
}