{
  "type": "Feature",
  "properties": {
    "iso:country":"US",
    "sg:address":"2251 State Rte 487",
    "sg:city":"Marthaville",
    "sg:classifiers":[
        {
            "category":"Professional",
            "subcategory":"Business Services",
            "type":"Services"
        }
    ],
    "sg:phone":"+1 318 472 8072",
    "sg:postcode":"71450",
    "sg:province":"LA",
    "wof:name":"Ajax Beulah Water Assoc Iates",
    "wof:placetype":"venue"
},
  "geometry": {"coordinates":[-93.38096,31.802347],"type":"Point"}
}