{
  "type": "Feature",
  "properties": {
    "iso:country":"US",
    "sg:address":"118 N Rocheblave St",
    "sg:city":"New Orleans",
    "sg:classifiers":[
        {
            "category":"Government",
            "subcategory":"Police Station",
            "type":"Public Place"
        }
    ],
    "sg:phone":"+1 504 826 1410",
    "sg:postcode":"70119",
    "sg:province":"LA",
    "sg:tags":[
        "department"
    ],
    "wof:name":"New Orleans Police Dept",
    "wof:placetype":"venue"
},
  "geometry": {"coordinates":[-90.084118,29.964609],"type":"Point"}
}