{
  "type": "Feature",
  "properties": {
    "addr:full":"1501 N 18th St Monroe LA 71201",
    "addr:housenumber":"1501",
    "addr:postcode":"71201",
    "addr:street":"N 18Th St",
    "iso:country":"US",
    "sg:address":"1501 N 18th St",
    "sg:city":"Monroe",
    "sg:classifiers":[
        {
            "category":"Food & Beverages",
            "subcategory":"Groceries & Convenience Stores",
            "type":"Retail Goods"
        }
    ],
    "sg:phone":"+1 318 325 7111",
    "sg:postcode":"71201",
    "sg:province":"LA",
    "wof:name":"Pantry",
    "wof:placetype":"venue"
},
  "geometry": {"coordinates":[-92.11435,32.525369],"type":"Point"}
}