{
  "type": "Feature",
  "properties": {
    "iso:country":"US",
    "sg:address":"1112 7th St",
    "sg:city":"Morgan City",
    "sg:classifiers":[
        {
            "category":"Professional",
            "type":"Services"
        }
    ],
    "sg:phone":"+1 985 385 0812",
    "sg:postcode":"70380",
    "sg:province":"LA",
    "sg:tags":[
        "establishment"
    ],
    "wof:name":"H & B Young Foundation",
    "wof:placetype":"venue"
},
  "geometry": {"coordinates":[-91.203929,29.70462],"type":"Point"}
}