{
  "type": "Feature",
  "properties": {
    "iso:country":"US",
    "sg:address":"8205 Desiard St",
    "sg:city":"Monroe",
    "sg:classifiers":[
        {
            "category":"Banks & Credit Unions",
            "subcategory":"Bank",
            "type":"Services"
        }
    ],
    "sg:phone":"+1 318 345 5050",
    "sg:postcode":"71203",
    "sg:province":"LA",
    "sg:tags":[
        "financing"
    ],
    "wof:name":"Friendly Finance Svc",
    "wof:placetype":"venue"
},
  "geometry": {"coordinates":[-92.035949,32.528502],"type":"Point"}
}