{
  "type": "Feature",
  "properties": {
    "iso:country":"US",
    "sg:address":"841 S Pine St",
    "sg:city":"Deridder",
    "sg:classifiers":[
        {
            "category":"Freight",
            "type":"Transportation"
        }
    ],
    "sg:phone":"+1 337 462 6601",
    "sg:postcode":"70634",
    "sg:province":"LA",
    "sg:tags":[
        "trucking"
    ],
    "wof:name":"American Roadline Intl",
    "wof:placetype":"venue"
},
  "geometry": {"coordinates":[-93.290744,30.837032],"type":"Point"}
}