{
  "type": "Feature",
  "properties": {
    "addr:full":"326 Gauthier Rd Lafayette LA 70501",
    "addr:housenumber":"326",
    "addr:postcode":"70501",
    "addr:street":"Gauthier Rd",
    "iso:country":"US",
    "sg:address":"326 Gauthier Rd",
    "sg:city":"Lafayette",
    "sg:classifiers":[
        {
            "category":"Education",
            "subcategory":"School",
            "type":"Public Place"
        }
    ],
    "sg:phone":"+1 337 233 2140",
    "sg:postcode":"70501",
    "sg:province":"LA",
    "wof:name":"Vermilion Elementary School",
    "wof:placetype":"venue"
},
  "geometry": {"coordinates":[-92.00146599999999,30.218702],"type":"Point"}
}