{
  "type": "Feature",
  "properties": {
    "addr:full":"1320 Breaux Rd Lafayette LA 70506",
    "addr:housenumber":"1320",
    "addr:postcode":"70506",
    "addr:street":"Breaux Rd",
    "iso:country":"US",
    "sg:address":"1320 Breaux Rd",
    "sg:city":"Lafayette",
    "sg:classifiers":[
        {
            "category":"Mining & Drilling",
            "type":"Manufacturing & Wholesale Goods"
        }
    ],
    "sg:phone":"+1 337 643 1104",
    "sg:postcode":"70506",
    "sg:province":"LA",
    "sg:tags":[
        "oil",
        "gas",
        "producer"
    ],
    "wof:name":"Hilcorp Energy Corp",
    "wof:placetype":"venue"
},
  "geometry": {"coordinates":[-92.112263,30.162437],"type":"Point"}
}