{
  "type": "Feature",
  "properties": {
    "iso:country":"US",
    "sg:address":"1916 Williams Blvd",
    "sg:city":"Kenner",
    "sg:classifiers":[
        {
            "category":"Banks & Credit Unions",
            "subcategory":"Bank",
            "type":"Services"
        }
    ],
    "sg:phone":"+1 504 461 3000",
    "sg:postcode":"70062",
    "sg:province":"LA",
    "sg:tags":[
        "loan"
    ],
    "wof:name":"American Thrift & Finance Plan",
    "wof:placetype":"venue"
},
  "geometry": {"coordinates":[-90.241709,29.990853],"type":"Point"}
}