{
  "type": "Feature",
  "properties": {
    "addr:full":"8451 State Rte 23 Belle Chasse LA 70037",
    "addr:housenumber":"8451",
    "addr:postcode":"70037",
    "addr:street":"State Rte 23",
    "iso:country":"US",
    "sg:address":"8451 State Rte 23",
    "sg:city":"Belle Chasse",
    "sg:classifiers":[
        {
            "category":"Insurance",
            "subcategory":"Insurance Agent",
            "type":"Services"
        }
    ],
    "sg:phone":"+1 504 394 5666",
    "sg:postcode":"70037",
    "sg:province":"LA",
    "wof:name":"Cosse Insurance",
    "wof:placetype":"venue"
},
  "geometry": {"coordinates":[-89.98672500000001,29.852081],"type":"Point"}
}