{
  "type": "Feature",
  "properties": {
    "iso:country":"US",
    "sg:address":"7476 Highland Rd",
    "sg:city":"Baton Rouge",
    "sg:classifiers":[
        {
            "category":"Professional",
            "subcategory":"Business Services",
            "type":"Services"
        }
    ],
    "sg:phone":"+1 225 765 7595",
    "sg:postcode":"70808",
    "sg:province":"LA",
    "sg:tags":[
        "interior",
        "consultant",
        "design",
        "decorator"
    ],
    "wof:name":"By Design Interiors",
    "wof:placetype":"venue"
},
  "geometry": {"coordinates":[-91.136921,30.376833],"type":"Point"}
}