{
  "type": "Feature",
  "properties": {
    "addr:full":"2 Louisville Ave Monroe LA 71201",
    "addr:housenumber":"2",
    "addr:postcode":"71201",
    "addr:street":"Louisville Ave",
    "iso:country":"US",
    "sg:address":"2 Louisville Ave",
    "sg:city":"Monroe",
    "sg:classifiers":[
        {
            "category":"Personal",
            "subcategory":"Tattoo Parlor",
            "type":"Services"
        }
    ],
    "sg:phone":"+1 318 324 2111",
    "sg:postcode":"71201",
    "sg:province":"LA",
    "sg:tags":[
        "tattooing"
    ],
    "wof:name":"Tat 2U",
    "wof:placetype":"venue"
},
  "geometry": {"coordinates":[-92.124606,32.506107],"type":"Point"}
}