{
  "type": "Feature",
  "properties": {
    "addr:full":"116 W Thomas St Hammond LA 70401",
    "addr:housenumber":"116",
    "addr:postcode":"70401",
    "addr:street":"W Thomas St",
    "iso:country":"US",
    "sg:address":"116 W Thomas St",
    "sg:city":"Hammond",
    "sg:classifiers":[
        {
            "category":"Social Services",
            "type":"Services"
        }
    ],
    "sg:phone":"+1 985 542 1959",
    "sg:postcode":"70401",
    "sg:province":"LA",
    "sg:tags":[
        "organization",
        "welfare"
    ],
    "wof:name":"Strawberry Patch",
    "wof:placetype":"venue"
},
  "geometry": {"coordinates":[-90.461558,30.504048],"type":"Point"}
}