{
  "type": "Feature",
  "properties": {
    "addr:full":"6031 Magazine St New Orleans LA 70118",
    "addr:housenumber":"6031",
    "addr:postcode":"70118",
    "addr:street":"Magazine St",
    "iso:country":"US",
    "sg:address":"6031 Magazine St",
    "sg:city":"New Orleans",
    "sg:classifiers":[
        {
            "category":"Professional",
            "subcategory":"Advertising",
            "type":"Services"
        }
    ],
    "sg:phone":"+1 504 891 0020",
    "sg:postcode":"70118",
    "sg:province":"LA",
    "wof:name":"Ad Concepts",
    "wof:placetype":"venue"
},
  "geometry": {"coordinates":[-90.122826,29.922642],"type":"Point"}
}