{
  "type": "Feature",
  "properties": {
    "iso:country":"US",
    "sg:address":"3808 Pontchartrain Dr",
    "sg:city":"Slidell",
    "sg:classifiers":[
        {
            "category":"Retail",
            "subcategory":"Funeral Services",
            "type":"Services"
        }
    ],
    "sg:phone":"+1 985 643 2111",
    "sg:postcode":"70458",
    "sg:province":"LA",
    "sg:tags":[
        "director"
    ],
    "wof:name":"Schoen Funeral Homes",
    "wof:placetype":"venue"
},
  "geometry": {"coordinates":[-89.791314,30.251767],"type":"Point"}
}