{
  "type": "Feature",
  "properties": {
    "iso:country":"US",
    "sg:address":"1501 W Causeway Approach",
    "sg:city":"Mandeville",
    "sg:classifiers":[
        {
            "category":"Organizations",
            "subcategory":"Religious Organization",
            "type":"Services"
        }
    ],
    "sg:phone":"+1 985 626 6977",
    "sg:postcode":"70471",
    "sg:province":"LA",
    "sg:tags":[
        "church"
    ],
    "sg:website":"www.maryqueenofpeace.org",
    "wof:name":"Mary Queen Of Peace Church",
    "wof:placetype":"venue"
},
  "geometry": {"coordinates":[-90.10108099999999,30.392397],"type":"Point"}
}