{
  "type": "Feature",
  "properties": {
    "iso:country":"US",
    "sg:address":"207 Covington St",
    "sg:city":"Madisonville",
    "sg:classifiers":[
        {
            "category":"Food & Beverages",
            "subcategory":"Groceries & Convenience Stores",
            "type":"Retail Goods"
        }
    ],
    "sg:phone":"+1 985 845 7283",
    "sg:postcode":"70447",
    "sg:province":"LA",
    "sg:tags":[
        "grocer"
    ],
    "wof:name":"Madisonville Piggly Wiggly",
    "wof:placetype":"venue"
},
  "geometry": {"coordinates":[-90.16050199999999,30.410867],"type":"Point"}
}