{
  "type": "Feature",
  "properties": {
    "addr:full":"4812 Alphonse Dr Metairie LA 70006",
    "addr:housenumber":"4812",
    "addr:postcode":"70006",
    "addr:street":"Alphonse Dr",
    "iso:country":"US",
    "sg:address":"4812 Alphonse Dr",
    "sg:city":"Metairie",
    "sg:classifiers":[
        {
            "category":"Wholesale",
            "subcategory":"Groceries",
            "type":"Manufacturing & Wholesale Goods"
        }
    ],
    "sg:phone":"+1 504 885 4616",
    "sg:postcode":"70006",
    "sg:province":"LA",
    "sg:tags":[
        "confectionery"
    ],
    "wof:name":"New Orleans Fund Raising",
    "wof:placetype":"venue"
},
  "geometry": {"coordinates":[-90.193853,30.023256],"type":"Point"}
}