{
  "type": "Feature",
  "properties": {
    "addr:full":"4135 State Rte 17 Epps LA 71237",
    "addr:housenumber":"4135",
    "addr:postcode":"71237",
    "addr:street":"State Rte 17 Epps",
    "iso:country":"US",
    "sg:address":"4135 State Rte 17",
    "sg:city":"Epps",
    "sg:classifiers":[
        {
            "category":"Organizations",
            "subcategory":"Religious Organization",
            "type":"Services"
        }
    ],
    "sg:phone":"+1 318 926 3306",
    "sg:postcode":"71237",
    "sg:province":"LA",
    "sg:tags":[
        "church"
    ],
    "wof:name":"Mt Moriah Church",
    "wof:placetype":"venue"
},
  "geometry": {"coordinates":[-91.490081,32.573485],"type":"Point"}
}