{
  "type": "Feature",
  "properties": {
    "iso:country":"US",
    "sg:address":"2226 W Thomas St",
    "sg:city":"Hammond",
    "sg:classifiers":[
        {
            "category":"Banks & Credit Unions",
            "subcategory":"Bank",
            "type":"Services"
        }
    ],
    "sg:phone":"+1 985 345 9150",
    "sg:postcode":"70401",
    "sg:province":"LA",
    "sg:tags":[
        "loan"
    ],
    "wof:name":"Money To Lend Of Louisiana",
    "wof:placetype":"venue"
},
  "geometry": {"coordinates":[-90.483458,30.500983],"type":"Point"}
}