{
  "type": "Feature",
  "properties": {
    "iso:country":"US",
    "sg:address":"2430 Louisiana Ave",
    "sg:city":"Lutcher",
    "sg:classifiers":[
        {
            "category":"Government",
            "subcategory":"Office",
            "type":"Public Place"
        }
    ],
    "sg:phone":"+1 225 869 3643",
    "sg:postcode":"70071",
    "sg:province":"LA",
    "sg:tags":[
        "admin",
        "affairs",
        "state",
        "administrative"
    ],
    "wof:name":"Veterans Affairs La Dept",
    "wof:placetype":"venue"
},
  "geometry": {"coordinates":[-90.697757,30.043572],"type":"Point"}
}