{
  "type": "Feature",
  "properties": {
    "addr:full":"204 S Saratoga St New Orleans LA 70112",
    "addr:housenumber":"204",
    "addr:postcode":"70112",
    "addr:street":"S Saratoga St",
    "iso:country":"US",
    "sg:address":"204 S Saratoga St",
    "sg:city":"New Orleans",
    "sg:classifiers":[
        {
            "category":"Restaurant",
            "type":"Food & Drink"
        }
    ],
    "sg:menulink":"http://www.allmenus.com/la/new-orleans/136684-smoothie-king/menu/",
    "sg:phone":"+1 504 585 1775",
    "sg:postcode":"70112",
    "sg:province":"LA",
    "sg:tags":[
        "smoothy",
        "juice",
        "american"
    ],
    "wof:name":"Smoothie King",
    "wof:placetype":"venue"
},
  "geometry": {"coordinates":[-90.074868,29.955515],"type":"Point"}
}