{
  "type": "Feature",
  "properties": {
    "iso:country":"US",
    "sg:address":"11639 Wardline Rd",
    "sg:city":"Hammond",
    "sg:classifiers":[
        {
            "category":"Organizations",
            "subcategory":"Religious Organization",
            "type":"Services"
        }
    ],
    "sg:phone":"+1 225 567 2033",
    "sg:postcode":"70401",
    "sg:province":"LA",
    "sg:tags":[
        "church"
    ],
    "wof:name":"Wardline Baptist Church",
    "wof:placetype":"venue"
},
  "geometry": {"coordinates":[-90.53456,30.519111],"type":"Point"}
}