{
  "type": "Feature",
  "properties": {
    "iso:country":"US",
    "sg:address":"1204 Irish Bend Rd",
    "sg:city":"Franklin",
    "sg:classifiers":[
        {
            "category":"Wholesale",
            "subcategory":"Auto Parts",
            "type":"Manufacturing & Wholesale Goods"
        }
    ],
    "sg:phone":"+1 337 828 2146",
    "sg:postcode":"70538",
    "sg:province":"LA",
    "sg:tags":[
        "automobile",
        "rebuilt"
    ],
    "wof:name":"Lee Clark Salvage",
    "wof:placetype":"venue"
},
  "geometry": {"coordinates":[-91.480734,29.805449],"type":"Point"}
}