{
  "type": "Feature",
  "properties": {
    "iso:country":"US",
    "sg:address":"3703 Silver Cane Rd",
    "sg:city":"New Iberia",
    "sg:classifiers":[
        {
            "category":"Personal",
            "subcategory":"Beauty Salon",
            "type":"Services"
        }
    ],
    "sg:phone":"+1 337 364 0819",
    "sg:postcode":"70560",
    "sg:province":"LA",
    "sg:tags":[
        "shop"
    ],
    "wof:name":"Barbaras Cuts",
    "wof:placetype":"venue"
},
  "geometry": {"coordinates":[-91.80837,29.94409],"type":"Point"}
}