{
  "type": "Feature",
  "properties": {
    "iso:country":"US",
    "sg:address":"6500 E Old Spanish Trl",
    "sg:city":"Jeanerette",
    "sg:classifiers":[
        {
            "category":"Building & Trades",
            "subcategory":"Construction",
            "type":"Services"
        }
    ],
    "sg:phone":"+1 337 364 5945",
    "sg:postcode":"70544",
    "sg:province":"LA",
    "sg:tags":[
        "general",
        "contractor"
    ],
    "wof:name":"Al Theriot Construction",
    "wof:placetype":"venue"
},
  "geometry": {"coordinates":[-91.721109,29.956677],"type":"Point"}
}