{
  "type": "Feature",
  "properties": {
    "addr:full":"1505 Washington St Franklinton LA 70438",
    "addr:housenumber":"1505",
    "addr:postcode":"70438",
    "addr:street":"Washington St",
    "iso:country":"US",
    "sg:address":"1505 Washington St",
    "sg:city":"Franklinton",
    "sg:classifiers":[
        {
            "category":"Building & Trades",
            "subcategory":"Plumbing",
            "type":"Services"
        }
    ],
    "sg:phone":"+1 985 839 6790",
    "sg:postcode":"70438",
    "sg:province":"LA",
    "sg:tags":[
        "conditioning",
        "air",
        "system",
        "contractor"
    ],
    "wof:name":"Ingram Air Inc",
    "wof:placetype":"venue"
},
  "geometry": {"coordinates":[-90.15136800000001,30.84802],"type":"Point"}
}