{
  "type": "Feature",
  "properties": {
    "iso:country":"US",
    "sg:address":"13944 W Main St",
    "sg:city":"Cut Off",
    "sg:classifiers":[
        {
            "category":"Communications",
            "type":"Services"
        }
    ],
    "sg:phone":"+1 985 693 1234",
    "sg:postcode":"70345",
    "sg:province":"LA",
    "wof:name":"Vision Communications LLC",
    "wof:placetype":"venue"
},
  "geometry": {"coordinates":[-90.355577,29.55932],"type":"Point"}
}