{
  "type": "Feature",
  "properties": {
    "iso:country":"US",
    "sg:address":"713 13th St",
    "sg:city":"Lake Charles",
    "sg:classifiers":[
        {
            "category":"Professional",
            "type":"Services"
        }
    ],
    "sg:phone":"+1 337 436 9717",
    "sg:postcode":"70601",
    "sg:province":"LA",
    "wof:name":"Greater Indian Byou Hnting CLB",
    "wof:placetype":"venue"
},
  "geometry": {"coordinates":[-93.20992099999999,30.211849],"type":"Point"}
}