{
  "type": "Feature",
  "properties": {
    "iso:country":"US",
    "sg:address":"1970 Ormond Blvd",
    "sg:city":"Destrehan",
    "sg:classifiers":[
        {
            "category":"Shopping",
            "type":"Retail Goods"
        }
    ],
    "sg:phone":"+1 985 307 0576",
    "sg:postcode":"70047",
    "sg:province":"LA",
    "sg:tags":[
        "cosmetic",
        "perfume"
    ],
    "wof:name":"Touch Of Love Beauty Supl Hse",
    "wof:placetype":"venue"
},
  "geometry": {"coordinates":[-90.375011,29.969624],"type":"Point"}
}