{
  "type": "Feature",
  "properties": {
    "iso:country":"US",
    "sg:address":"2645 Oneal Ln",
    "sg:city":"Baton Rouge",
    "sg:classifiers":[
        {
            "category":"Health Services",
            "subcategory":"Doctor",
            "type":"Services"
        }
    ],
    "sg:phone":"+1 225 754 7000",
    "sg:postcode":"70816",
    "sg:province":"LA",
    "sg:tags":[
        "physician",
        "surgeon"
    ],
    "wof:name":"Asthma Allergy Immunology Ctr",
    "wof:placetype":"venue"
},
  "geometry": {"coordinates":[-91.007631,30.42726],"type":"Point"}
}