{
  "type": "Feature",
  "properties": {
    "iso:country":"US",
    "sg:address":"125 N 13th St",
    "sg:city":"Baton Rouge",
    "sg:classifiers":[
        {
            "category":"Social Services",
            "subcategory":"Adult Care",
            "type":"Services"
        }
    ],
    "sg:phone":"+1 225 336 5424",
    "sg:postcode":"70802",
    "sg:province":"LA",
    "sg:tags":[
        "home",
        "group"
    ],
    "wof:name":"Tommy Mason Group Home",
    "wof:placetype":"venue"
},
  "geometry": {"coordinates":[-91.176333,30.448356],"type":"Point"}
}