{
  "type": "Feature",
  "properties": {
    "iso:country":"US",
    "sg:address":"916 Carrollwood Dr",
    "sg:city":"La Place",
    "sg:classifiers":[
        {
            "category":"Shopping",
            "subcategory":"Optical Goods",
            "type":"Retail Goods"
        }
    ],
    "sg:phone":"+1 985 652 4097",
    "sg:postcode":"70068",
    "sg:province":"LA",
    "sg:tags":[
        "optician"
    ],
    "wof:name":"Saint Optical",
    "wof:placetype":"venue"
},
  "geometry": {"coordinates":[-90.496155,30.07297],"type":"Point"}
}