{
  "type": "Feature",
  "properties": {
    "iso:country":"US",
    "sg:address":"323 E Interstate Dr",
    "sg:city":"Jennings",
    "sg:classifiers":[
        {
            "category":"Autos & Motor Vehicles",
            "subcategory":"Fuel & Gas Station",
            "type":"Retail Goods"
        }
    ],
    "sg:phone":"+1 337 616 1873",
    "sg:postcode":"70546",
    "sg:province":"LA",
    "sg:tags":[
        "station",
        "gasoline"
    ],
    "wof:name":"Murphy Oil Usa Inc",
    "wof:placetype":"venue"
},
  "geometry": {"coordinates":[-92.658237,30.246222],"type":"Point"}
}