{
  "type": "Feature",
  "properties": {
    "iso:country":"US",
    "sg:address":"335 Jack Crowell Rd",
    "sg:city":"Eros",
    "sg:classifiers":[
        {
            "category":"Building & Trades",
            "subcategory":"Construction",
            "type":"Services"
        }
    ],
    "sg:phone":"+1 318 249 4539",
    "sg:postcode":"71238",
    "sg:province":"LA",
    "sg:tags":[
        "sewer",
        "contractor"
    ],
    "wof:name":"Dale Mckinley Dirt Sewer",
    "wof:placetype":"venue"
},
  "geometry": {"coordinates":[-92.346554,32.393841],"type":"Point"}
}