{
  "type": "Feature",
  "properties": {
    "iso:country":"US",
    "sg:address":"312 Calcasieu Ave",
    "sg:city":"Lake Arthur",
    "sg:classifiers":[
        {
            "category":"Home & Garden",
            "subcategory":"Building Materials",
            "type":"Retail Goods"
        }
    ],
    "sg:phone":"+1 337 824 5703",
    "sg:postcode":"70549",
    "sg:province":"LA",
    "sg:tags":[
        "glass",
        "window",
        "plate"
    ],
    "wof:name":"Acadiana Glass",
    "wof:placetype":"venue"
},
  "geometry": {"coordinates":[-92.67148,30.081166],"type":"Point"}
}