{
  "type": "Feature",
  "properties": {
    "iso:country":"US",
    "sg:address":"3404 Trotter Ct",
    "sg:city":"Houma",
    "sg:classifiers":[
        {
            "category":"Manufacturing",
            "subcategory":"Metals",
            "type":"Manufacturing & Wholesale Goods"
        }
    ],
    "sg:phone":"+1 985 876 5511",
    "sg:postcode":"70363",
    "sg:province":"LA",
    "sg:tags":[
        "sling"
    ],
    "sg:website":"www.herculeswirerope.com",
    "wof:name":"Hercules Wire Rope & Sling Co",
    "wof:placetype":"venue"
},
  "geometry": {"coordinates":[-90.67202899999999,29.580051],"type":"Point"}
}