{
  "type": "Feature",
  "properties": {
    "iso:country":"US",
    "sg:address":"824 Jena St",
    "sg:city":"New Orleans",
    "sg:classifiers":[
        {
            "category":"Building & Trades",
            "subcategory":"Construction",
            "type":"Services"
        }
    ],
    "sg:phone":"+1 504 895 1241",
    "sg:postcode":"70115",
    "sg:province":"LA",
    "sg:tags":[
        "painter"
    ],
    "wof:name":"Daniel T Baird Real Estate Svc",
    "wof:placetype":"venue"
},
  "geometry": {"coordinates":[-90.102763,29.920444],"type":"Point"}
}