{
  "type": "Feature",
  "properties": {
    "iso:country":"US",
    "sg:address":"206 W Harrison Ave",
    "sg:city":"New Orleans",
    "sg:classifiers":[
        {
            "category":"Shopping",
            "subcategory":"Gifts & Souvenirs",
            "type":"Retail Goods"
        }
    ],
    "sg:phone":"+1 504 482 8463",
    "sg:postcode":"70124",
    "sg:province":"LA",
    "sg:tags":[
        "announcement",
        "invitation"
    ],
    "wof:name":"A Paper Affair",
    "wof:placetype":"venue"
},
  "geometry": {"coordinates":[-90.11730300000001,30.00559],"type":"Point"}
}