{
  "type": "Feature",
  "properties": {
    "iso:country":"US",
    "sg:address":"16 Colonial Ln",
    "sg:city":"Harahan",
    "sg:classifiers":[
        {
            "category":"Banks & Credit Unions",
            "subcategory":"Bank",
            "type":"Services"
        }
    ],
    "sg:phone":"+1 504 733 0433",
    "sg:postcode":"70123",
    "sg:province":"LA",
    "sg:tags":[
        "financing"
    ],
    "wof:name":"Alario & Assoc",
    "wof:placetype":"venue"
},
  "geometry": {"coordinates":[-90.20823,29.928756],"type":"Point"}
}