{
  "type": "Feature",
  "properties": {
    "iso:country":"US",
    "sg:address":"1399 Davison Rd",
    "sg:city":"Sulphur",
    "sg:classifiers":[
        {
            "category":"Manufacturing",
            "subcategory":"Petroleum Products",
            "type":"Manufacturing & Wholesale Goods"
        }
    ],
    "sg:phone":"+1 337 583 4642",
    "sg:postcode":"70665",
    "sg:province":"LA",
    "sg:tags":[
        "oil",
        "refiner"
    ],
    "wof:name":"Dynegy Midstream Svc",
    "wof:placetype":"venue"
},
  "geometry": {"coordinates":[-93.344598,30.15809],"type":"Point"}
}