{
  "type": "Feature",
  "properties": {
    "addr:full":"333 Texas St Shreveport LA 71101",
    "addr:housenumber":"333",
    "addr:postcode":"71101",
    "addr:street":"Texas St",
    "iso:country":"US",
    "sg:address":"333 Texas St",
    "sg:city":"Shreveport",
    "sg:classifiers":[
        {
            "category":"Mining & Drilling",
            "type":"Manufacturing & Wholesale Goods"
        }
    ],
    "sg:phone":"+1 318 429 2200",
    "sg:postcode":"71101",
    "sg:province":"LA",
    "sg:tags":[
        "development",
        "gas",
        "oil",
        "exploration"
    ],
    "wof:name":"Christopher Franks",
    "wof:placetype":"venue"
},
  "geometry": {"coordinates":[-93.748413,32.513714],"type":"Point"}
}