{
  "type": "Feature",
  "properties": {
    "iso:country":"US",
    "sg:address":"111 Simpson Rd",
    "sg:city":"Dubach",
    "sg:classifiers":[
        {
            "category":"Building & Trades",
            "subcategory":"Cleaning & Sanitation",
            "type":"Services"
        }
    ],
    "sg:phone":"+1 318 777 9846",
    "sg:postcode":"71235",
    "sg:province":"LA",
    "sg:tags":[
        "maintenance"
    ],
    "wof:name":"Linda F Armstrong",
    "wof:placetype":"venue"
},
  "geometry": {"coordinates":[-92.658055,32.71236],"type":"Point"}
}