{
  "type": "Feature",
  "properties": {
    "iso:country":"US",
    "sg:address":"226 W 70th St",
    "sg:city":"Shreveport",
    "sg:classifiers":[
        {
            "category":"Food & Beverages",
            "subcategory":"Liquor & Beverages",
            "type":"Retail Goods"
        }
    ],
    "sg:phone":"+1 318 869 1226",
    "sg:postcode":"71106",
    "sg:province":"LA",
    "wof:name":"Daiquiari Paradise",
    "wof:placetype":"venue"
},
  "geometry": {"coordinates":[-93.760475,32.442118],"type":"Point"}
}