{
  "type": "Feature",
  "properties": {
    "iso:country":"US",
    "sg:address":"2819 N Rampart St",
    "sg:city":"New Orleans",
    "sg:classifiers":[
        {
            "category":"Retail",
            "subcategory":"Repair Shop",
            "type":"Services"
        }
    ],
    "sg:phone":"+1 504 259 3065",
    "sg:postcode":"70117",
    "sg:province":"LA",
    "sg:tags":[
        "appliance"
    ],
    "wof:name":"Able Appliance Repair",
    "wof:placetype":"venue"
},
  "geometry": {"coordinates":[-90.047669,29.967174],"type":"Point"}
}