{
  "type": "Feature",
  "properties": {
    "addr:full":"201 N Claiborne Ave New Orleans LA 70112",
    "addr:housenumber":"201",
    "addr:postcode":"70112",
    "addr:street":"N Claiborne Ave",
    "iso:country":"US",
    "sg:address":"201 N Claiborne Ave",
    "sg:city":"New Orleans",
    "sg:classifiers":[
        {
            "category":"Taxi",
            "type":"Transportation"
        }
    ],
    "sg:phone":"+1 504 566 9994",
    "sg:postcode":"70112",
    "sg:province":"LA",
    "sg:tags":[
        "taxicab"
    ],
    "wof:name":"Night Hawk",
    "wof:placetype":"venue"
},
  "geometry": {"coordinates":[-90.07648399999999,29.960866],"type":"Point"}
}