{
  "type": "Feature",
  "properties": {
    "iso:country":"US",
    "sg:address":"32315 State Rte 75",
    "sg:city":"Plaquemine",
    "sg:classifiers":[
        {
            "category":"Organizations",
            "subcategory":"Religious Organization",
            "type":"Services"
        }
    ],
    "sg:phone":"+1 225 659 2100",
    "sg:postcode":"70764",
    "sg:province":"LA",
    "sg:tags":[
        "church"
    ],
    "wof:name":"Bayou Sorrel Full Gospel Chr",
    "wof:placetype":"venue"
},
  "geometry": {"coordinates":[-91.33425200000001,30.172973],"type":"Point"}
}