{
  "type": "Feature",
  "properties": {
    "addr:full":"2300 Country Club Rd Lake Charles LA 70605",
    "addr:housenumber":"2300",
    "addr:postcode":"70605",
    "addr:street":"Country Club Rd",
    "iso:country":"US",
    "sg:address":"2300 Country Club Rd",
    "sg:city":"Lake Charles",
    "sg:classifiers":[
        {
            "category":"Real Estate",
            "subcategory":"Developer",
            "type":"Services"
        }
    ],
    "sg:phone":"+1 337 477 5372",
    "sg:postcode":"70605",
    "sg:province":"LA",
    "sg:tags":[
        "cemetery"
    ],
    "wof:name":"Consolata Cemetery",
    "wof:placetype":"venue"
},
  "geometry": {"coordinates":[-93.25542799999999,30.168767],"type":"Point"}
}