{
  "type": "Feature",
  "properties": {
    "addr:full":"702 Roberts St Monroe LA 71202",
    "addr:housenumber":"702",
    "addr:postcode":"71202",
    "addr:street":"Roberts St",
    "iso:country":"US",
    "sg:address":"702 Roberts St",
    "sg:city":"Monroe",
    "sg:classifiers":[
        {
            "category":"Personal",
            "subcategory":"Beauty Salon",
            "type":"Services"
        }
    ],
    "sg:phone":"+1 318 388 1481",
    "sg:postcode":"71202",
    "sg:province":"LA",
    "sg:tags":[
        "shop"
    ],
    "wof:name":"Ariese H Elzie Beauty Shop",
    "wof:placetype":"venue"
},
  "geometry": {"coordinates":[-92.085435,32.47512],"type":"Point"}
}