{
  "type": "Feature",
  "properties": {
    "iso:country":"US",
    "sg:address":"3 Teton St",
    "sg:city":"Kenner",
    "sg:classifiers":[
        {
            "category":"Real Estate",
            "subcategory":"Real Estate Agent",
            "type":"Services"
        }
    ],
    "sg:phone":"+1 504 467 4739",
    "sg:postcode":"70065",
    "sg:province":"LA",
    "wof:name":"Larry Fennel Real Estate Co",
    "wof:placetype":"venue"
},
  "geometry": {"coordinates":[-90.267212,30.046207],"type":"Point"}
}