{
  "type": "Feature",
  "properties": {
    "iso:country":"US",
    "sg:address":"3231 Lake St",
    "sg:city":"Lake Charles",
    "sg:classifiers":[
        {
            "category":"Travel",
            "subcategory":"Hotels & Motels",
            "type":"Entertainment"
        }
    ],
    "sg:phone":"+1 337 477 4230",
    "sg:postcode":"70601",
    "sg:province":"LA",
    "wof:name":"Microtel Inns & Suites",
    "wof:placetype":"venue"
},
  "geometry": {"coordinates":[-93.23227300000001,30.199226],"type":"Point"}
}