{
  "type": "Feature",
  "properties": {
    "addr:full":"3333 Kingman St Metairie LA 70006",
    "addr:housenumber":"3333",
    "addr:postcode":"70006",
    "addr:street":"Kingman St",
    "iso:country":"US",
    "sg:address":"3333 Kingman St",
    "sg:city":"Metairie",
    "sg:classifiers":[
        {
            "category":"Shopping",
            "type":"Retail Goods"
        }
    ],
    "sg:phone":"+1 504 887 3277",
    "sg:postcode":"70006",
    "sg:province":"LA",
    "sg:tags":[
        "hearing",
        "equipment",
        "supply",
        "impaired"
    ],
    "wof:name":"Audiphone Hearing Instruments",
    "wof:placetype":"venue"
},
  "geometry": {"coordinates":[-90.180862,30.006221],"type":"Point"}
}