{
  "type": "Feature",
  "properties": {
    "iso:country":"US",
    "sg:address":"2454 4th St",
    "sg:city":"Ville Platte",
    "sg:classifiers":[
        {
            "category":"Food & Beverages",
            "subcategory":"Bakery",
            "type":"Retail Goods"
        }
    ],
    "sg:phone":"+1 337 363 3533",
    "sg:postcode":"70586",
    "sg:province":"LA",
    "sg:tags":[
        "baker"
    ],
    "wof:name":"Magnolia Bakery",
    "wof:placetype":"venue"
},
  "geometry": {"coordinates":[-92.23964100000001,30.673654],"type":"Point"}
}