{
  "type": "Feature",
  "properties": {
    "iso:country":"US",
    "sg:address":"515 Celeste Ave",
    "sg:city":"New Orleans",
    "sg:classifiers":[
        {
            "category":"Taxi",
            "type":"Transportation"
        }
    ],
    "sg:phone":"+1 504 491 1184",
    "sg:postcode":"70123",
    "sg:province":"LA",
    "sg:tags":[
        "taxicab"
    ],
    "wof:name":"King Cab KC 201",
    "wof:placetype":"venue"
},
  "geometry": {"coordinates":[-90.21427300000001,29.973403],"type":"Point"}
}