{
  "type": "Feature",
  "properties": {
    "addr:full":"1326 Springlake Dr Baton Rouge LA 70810",
    "addr:housenumber":"1326",
    "addr:postcode":"70810",
    "addr:street":"Springlake Dr",
    "iso:country":"US",
    "sg:address":"1326 Springlake Dr",
    "sg:city":"Baton Rouge",
    "sg:classifiers":[
        {
            "category":"Professional",
            "type":"Services"
        }
    ],
    "sg:phone":"+1 225 766 6540",
    "sg:postcode":"70810",
    "sg:province":"LA",
    "wof:name":"Leonard Hardwood Jr",
    "wof:placetype":"venue"
},
  "geometry": {"coordinates":[-91.11444299999999,30.350574],"type":"Point"}
}