{
  "type": "Feature",
  "properties": {
    "iso:country":"US",
    "sg:address":"115 S Main St",
    "sg:city":"Springhill",
    "sg:classifiers":[
        {
            "category":"Travel",
            "subcategory":"Travel Agent",
            "type":"Entertainment"
        }
    ],
    "sg:phone":"+1 318 539 5806",
    "sg:postcode":"71075",
    "sg:province":"LA",
    "sg:tags":[
        "agency",
        "bureau"
    ],
    "wof:name":"Place",
    "wof:placetype":"venue"
},
  "geometry": {"coordinates":[-93.461169,33.002082],"type":"Point"}
}