{
  "type": "Feature",
  "properties": {
    "iso:country":"US",
    "sg:address":"3572 Front St",
    "sg:city":"Winnsboro",
    "sg:classifiers":[
        {
            "category":"Insurance",
            "subcategory":"Insurance Agent",
            "type":"Services"
        }
    ],
    "sg:phone":"+1 318 435 5434",
    "sg:postcode":"71295",
    "sg:province":"LA",
    "wof:name":"Street Insurance",
    "wof:placetype":"venue"
},
  "geometry": {"coordinates":[-91.725247,32.172896],"type":"Point"}
}