{
  "type": "Feature",
  "properties": {
    "addr:full":"2620 Centenary Blvd Shreveport LA 71104",
    "addr:housenumber":"2620",
    "addr:postcode":"71104",
    "addr:street":"Centenary Blvd",
    "iso:country":"US",
    "sg:address":"2620 Centenary Blvd",
    "sg:city":"Shreveport",
    "sg:classifiers":[
        {
            "category":"Professional",
            "subcategory":"Lawyer & Legal Services",
            "type":"Services"
        }
    ],
    "sg:phone":"+1 318 221 8500",
    "sg:postcode":"71104",
    "sg:province":"LA",
    "sg:tags":[
        "attorney"
    ],
    "wof:name":"Baldwin Agency",
    "wof:placetype":"venue"
},
  "geometry": {"coordinates":[-93.733163,32.48602],"type":"Point"}
}