{
  "type": "Feature",
  "properties": {
    "iso:country":"US",
    "sg:address":"8630 Jefferson Hwy",
    "sg:city":"Harahan",
    "sg:classifiers":[
        {
            "category":"Organizations",
            "subcategory":"Religious Organization",
            "type":"Services"
        }
    ],
    "sg:phone":"+1 504 737 7999",
    "sg:postcode":"70123",
    "sg:province":"LA",
    "sg:tags":[
        "church"
    ],
    "wof:name":"Jefferson Congregation",
    "wof:placetype":"venue"
},
  "geometry": {"coordinates":[-90.213104,29.941561],"type":"Point"}
}