{
  "type": "Feature",
  "properties": {
    "iso:country":"US",
    "sg:address":"1108 7th St",
    "sg:city":"Morgan City",
    "sg:classifiers":[
        {
            "category":"Personal",
            "subcategory":"Beauty Salon",
            "type":"Services"
        }
    ],
    "sg:phone":"+1 985 385 1490",
    "sg:postcode":"70380",
    "sg:province":"LA",
    "wof:name":"Serenity Day Spa",
    "wof:placetype":"venue"
},
  "geometry": {"coordinates":[-91.203948,29.704664],"type":"Point"}
}