{
  "type": "Feature",
  "properties": {
    "iso:country":"US",
    "sg:address":"3700 US Hwy 79",
    "sg:city":"Homer",
    "sg:classifiers":[
        {
            "category":"Health Services",
            "subcategory":"Nursing And Care Facility",
            "type":"Services"
        }
    ],
    "sg:phone":"+1 318 927 6133",
    "sg:postcode":"71040",
    "sg:province":"LA",
    "sg:tags":[
        "home",
        "convalescent"
    ],
    "wof:name":"Presbyterian Village Of Homer",
    "wof:placetype":"venue"
},
  "geometry": {"coordinates":[-93.07490199999999,32.764841],"type":"Point"}
}