{
  "type": "Feature",
  "properties": {
    "iso:country":"US",
    "sg:address":"2110 Justice St",
    "sg:city":"Monroe",
    "sg:classifiers":[
        {
            "category":"Health Services",
            "subcategory":"Doctor",
            "type":"Services"
        }
    ],
    "sg:phone":"+1 318 322 8811",
    "sg:postcode":"71201",
    "sg:province":"LA",
    "sg:tags":[
        "physician",
        "surgeon"
    ],
    "wof:name":"Michael E Boykin Medical Corp",
    "wof:placetype":"venue"
},
  "geometry": {"coordinates":[-92.10854399999999,32.535348],"type":"Point"}
}