{
  "type": "Feature",
  "properties": {
    "iso:country":"US",
    "sg:address":"806 Brook Hollow Dr",
    "sg:city":"Shreveport",
    "sg:classifiers":[
        {
            "category":"Mining & Drilling",
            "type":"Manufacturing & Wholesale Goods"
        }
    ],
    "sg:phone":"+1 318 795 0777",
    "sg:postcode":"71105",
    "sg:province":"LA",
    "sg:tags":[
        "development",
        "gas",
        "oil",
        "exploration"
    ],
    "wof:name":"Dzurik Interest Inc",
    "wof:placetype":"venue"
},
  "geometry": {"coordinates":[-93.724503,32.418329],"type":"Point"}
}