{
  "type": "Feature",
  "properties": {
    "addr:full":"861 Ave C Marrero LA 70072",
    "addr:housenumber":"861",
    "addr:postcode":"70072",
    "addr:street":"Ave C Marrero",
    "iso:country":"US",
    "sg:address":"861 Ave C",
    "sg:city":"Marrero",
    "sg:classifiers":[
        {
            "category":"Shopping",
            "subcategory":"Hobbies, Toys, & Games",
            "type":"Retail Goods"
        }
    ],
    "sg:phone":"+1 504 340 3278",
    "sg:postcode":"70072",
    "sg:province":"LA",
    "sg:tags":[
        "darts",
        "boards",
        "dart"
    ],
    "wof:name":"Ton-Eighty",
    "wof:placetype":"venue"
},
  "geometry": {"coordinates":[-90.09487300000001,29.895383],"type":"Point"}
}