{
  "type": "Feature",
  "properties": {
    "addr:full":"4321 Paris Ave New Orleans LA 70122",
    "addr:housenumber":"4321",
    "addr:postcode":"70122",
    "addr:street":"Paris Ave",
    "iso:country":"US",
    "sg:address":"4321 Paris Ave",
    "sg:city":"New Orleans",
    "sg:classifiers":[
        {
            "category":"Food & Beverages",
            "subcategory":"Groceries & Convenience Stores",
            "type":"Retail Goods"
        }
    ],
    "sg:phone":"+1 504 282 8382",
    "sg:postcode":"70122",
    "sg:province":"LA",
    "sg:tags":[
        "grocer"
    ],
    "wof:name":"Easy Pack",
    "wof:placetype":"venue"
},
  "geometry": {"coordinates":[-90.073691,30.000994],"type":"Point"}
}