{
  "type": "Feature",
  "properties": {
    "iso:country":"US",
    "sg:address":"18274 Muddy Creek Rd",
    "sg:city":"Prairieville",
    "sg:classifiers":[
        {
            "category":"Professional",
            "subcategory":"Business Services",
            "type":"Services"
        }
    ],
    "sg:phone":"+1 225 622 0170",
    "sg:postcode":"70769",
    "sg:province":"LA",
    "sg:tags":[
        "embroidery"
    ],
    "wof:name":"Peabody's Promotions",
    "wof:placetype":"venue"
},
  "geometry": {"coordinates":[-90.92004799999999,30.32838],"type":"Point"}
}