{
  "type": "Feature",
  "properties": {
    "addr:full":"109 E 123rd St Galliano LA 70354",
    "addr:housenumber":"109",
    "addr:postcode":"70354",
    "addr:street":"E 123Rd St",
    "iso:country":"US",
    "sg:address":"109 E 123rd St",
    "sg:city":"Galliano",
    "sg:classifiers":[
        {
            "category":"Restaurant",
            "type":"Food & Drink"
        }
    ],
    "sg:phone":"+1 985 632 2444",
    "sg:postcode":"70354",
    "sg:province":"LA",
    "wof:name":"John's Chicken & Grill",
    "wof:placetype":"venue"
},
  "geometry": {"coordinates":[-90.296753,29.434587],"type":"Point"}
}