{
  "type": "Feature",
  "properties": {
    "iso:country":"US",
    "sg:address":"929 Keyser Ave",
    "sg:city":"Natchitoches",
    "sg:classifiers":[
        {
            "category":"Home & Garden",
            "subcategory":"Furniture",
            "type":"Retail Goods"
        }
    ],
    "sg:phone":"+1 318 352 5000",
    "sg:postcode":"71457",
    "sg:province":"LA",
    "sg:tags":[
        "mattress"
    ],
    "wof:name":"America Wholesale Mattress",
    "wof:placetype":"venue"
},
  "geometry": {"coordinates":[-93.067532,31.752617],"type":"Point"}
}