{
  "type": "Feature",
  "properties": {
    "addr:full":"4101 Jumonville St New Orleans LA 70122",
    "addr:housenumber":"4101",
    "addr:postcode":"70122",
    "addr:street":"Jumonville St",
    "iso:country":"US",
    "sg:address":"4101 Jumonville St",
    "sg:city":"New Orleans",
    "sg:classifiers":[
        {
            "category":"Food & Beverages",
            "subcategory":"Groceries & Convenience Stores",
            "type":"Retail Goods"
        }
    ],
    "sg:phone":"+1 504 282 9667",
    "sg:postcode":"70122",
    "sg:province":"LA",
    "sg:tags":[
        "grocer"
    ],
    "wof:name":"Handy's Grocery Store",
    "wof:placetype":"venue"
},
  "geometry": {"coordinates":[-90.078591,29.999829],"type":"Point"}
}