{
  "type": "Feature",
  "properties": {
    "addr:full":"1629 Simon Bolivar Ave New Orleans LA 70113",
    "addr:housenumber":"1629",
    "addr:postcode":"70113",
    "addr:street":"Simon Bolivar Ave",
    "iso:country":"US",
    "sg:address":"1629 Simon Bolivar Ave",
    "sg:city":"New Orleans",
    "sg:classifiers":[
        {
            "category":"Social Services",
            "subcategory":"Child Care",
            "type":"Services"
        }
    ],
    "sg:phone":"+1 504 524 1281",
    "sg:postcode":"70113",
    "sg:province":"LA",
    "wof:name":"Total Community Action Inc",
    "wof:placetype":"venue"
},
  "geometry": {"coordinates":[-90.082773,29.940895],"type":"Point"}
}