{
  "type": "Feature",
  "properties": {
    "iso:country":"US",
    "sg:address":"150 W Prien Lake Rd",
    "sg:city":"Lake Charles",
    "sg:classifiers":[
        {
            "category":"Health Services",
            "subcategory":"Doctor",
            "type":"Services"
        }
    ],
    "sg:phone":"+1 337 478 1700",
    "sg:postcode":"70601",
    "sg:province":"LA",
    "sg:tags":[
        "dentist"
    ],
    "wof:name":"James R Churchman DDS",
    "wof:placetype":"venue"
},
  "geometry": {"coordinates":[-93.222495,30.198179],"type":"Point"}
}