{
  "type": "Feature",
  "properties": {
    "iso:country":"US",
    "sg:address":"445 State Rte 311",
    "sg:city":"Schriever",
    "sg:classifiers":[
        {
            "category":"Education",
            "subcategory":"School",
            "type":"Public Place"
        }
    ],
    "sg:phone":"+1 985 446 0536",
    "sg:postcode":"70395",
    "sg:province":"LA",
    "wof:name":"Caldwell Middle School",
    "wof:placetype":"venue"
},
  "geometry": {"coordinates":[-90.812246,29.719433],"type":"Point"}
}