{
  "type": "Feature",
  "properties": {
    "iso:country":"US",
    "sg:address":"1900 Sam Houston Jones Pkwy",
    "sg:city":"Lake Charles",
    "sg:classifiers":[
        {
            "category":"Food & Beverages",
            "subcategory":"Groceries & Convenience Stores",
            "type":"Retail Goods"
        }
    ],
    "sg:phone":"+1 337 855 4508",
    "sg:postcode":"70611",
    "sg:province":"LA",
    "wof:name":"Five Star Quick Stop",
    "wof:placetype":"venue"
},
  "geometry": {"coordinates":[-93.23303199999999,30.300659],"type":"Point"}
}