{
  "type": "Feature",
  "properties": {
    "addr:full":"37069 Reinninger Rd Denham Springs LA 70706",
    "addr:postcode":"37069;70706",
    "addr:street":"Reinninger Rd",
    "iso:country":"US",
    "sg:address":"37069 Reinninger Rd",
    "sg:city":"Denham Springs",
    "sg:classifiers":[
        {
            "category":"Building & Trades",
            "subcategory":"Plumbing",
            "type":"Services"
        }
    ],
    "sg:phone":"+1 225 665 0306",
    "sg:postcode":"70706",
    "sg:province":"LA",
    "sg:tags":[
        "conditioning",
        "air",
        "system",
        "contractor"
    ],
    "wof:name":"CPR",
    "wof:placetype":"venue"
},
  "geometry": {"coordinates":[-90.88844,30.604329],"type":"Point"}
}