{
  "type": "Feature",
  "properties": {
    "addr:full":"2129 W Willow St Scott LA 70583",
    "addr:housenumber":"2129",
    "addr:postcode":"70583",
    "addr:street":"W Willow St",
    "iso:country":"US",
    "sg:address":"2129 W Willow St",
    "sg:city":"Scott",
    "sg:classifiers":[
        {
            "category":"Professional",
            "subcategory":"Testing Lab",
            "type":"Services"
        }
    ],
    "sg:phone":"+1 337 232 3568",
    "sg:postcode":"70583",
    "sg:province":"LA",
    "sg:tags":[
        "laboratory"
    ],
    "sg:website":"www.sherrylabs.com",
    "wof:name":"Sherry Laboratories",
    "wof:placetype":"venue"
},
  "geometry": {"coordinates":[-92.06304,30.243387],"type":"Point"}
}