{
  "type": "Feature",
  "properties": {
    "iso:country":"US",
    "sg:address":"14502 Hwy 3235",
    "sg:city":"Larose",
    "sg:classifiers":[
        {
            "category":"Autos & Motor Vehicles",
            "subcategory":"Boat Sales",
            "type":"Retail Goods"
        }
    ],
    "sg:phone":"+1 985 693 3646",
    "sg:postcode":"70345",
    "sg:province":"LA",
    "sg:tags":[
        "equipment",
        "marine",
        "supply"
    ],
    "wof:name":"Automatic Power Inc",
    "wof:placetype":"venue"
},
  "geometry": {"coordinates":[-90.31875599999999,29.456902],"type":"Point"}
}