{
  "type": "Feature",
  "properties": {
    "iso:country":"US",
    "sg:address":"29215 State Rte 75",
    "sg:city":"Plaquemine",
    "sg:classifiers":[
        {
            "category":"Organizations",
            "subcategory":"Religious Organization",
            "type":"Services"
        }
    ],
    "sg:phone":"+1 225 659 2344",
    "sg:postcode":"70764",
    "sg:province":"LA",
    "sg:tags":[
        "church"
    ],
    "wof:name":"Bayou Plaquemine Baptist Churc",
    "wof:placetype":"venue"
},
  "geometry": {"coordinates":[-91.31663399999999,30.214767],"type":"Point"}
}