{
  "type": "Feature",
  "properties": {
    "iso:country":"US",
    "sg:address":"4923 Jefferson Hwy",
    "sg:city":"Jefferson",
    "sg:classifiers":[
        {
            "category":"Home & Garden",
            "subcategory":"Building Materials",
            "type":"Retail Goods"
        }
    ],
    "sg:phone":"+1 504 733 2955",
    "sg:postcode":"70121",
    "sg:province":"LA",
    "sg:tags":[
        "lumber"
    ],
    "wof:name":"National Lumber & Demolishing",
    "wof:placetype":"venue"
},
  "geometry": {"coordinates":[-90.177818,29.95553],"type":"Point"}
}