{
  "type": "Feature",
  "properties": {
    "iso:country":"US",
    "sg:address":"292 Ridge Rd",
    "sg:city":"Lafayette",
    "sg:classifiers":[
        {
            "category":"Wholesale",
            "subcategory":"Electrical",
            "type":"Manufacturing & Wholesale Goods"
        }
    ],
    "sg:phone":"+1 337 991 9270",
    "sg:postcode":"70506",
    "sg:province":"LA",
    "sg:tags":[
        "control"
    ],
    "wof:name":"Direct Controls Inc",
    "wof:placetype":"venue"
},
  "geometry": {"coordinates":[-92.078993,30.181404],"type":"Point"}
}