{
  "type": "Feature",
  "properties": {
    "addr:full":"1512 Jefferson Hwy Jefferson LA 70121",
    "addr:housenumber":"1512",
    "addr:postcode":"70121",
    "addr:street":"Jefferson Hwy Jefferson",
    "iso:country":"US",
    "sg:address":"1512 Jefferson Hwy",
    "sg:city":"Jefferson",
    "sg:classifiers":[
        {
            "category":"Travel",
            "subcategory":"Hotels & Motels",
            "type":"Entertainment"
        }
    ],
    "sg:phone":"+1 504 835 5411",
    "sg:postcode":"70121",
    "sg:province":"LA",
    "sg:website":"www.brenthouse.com",
    "wof:name":"Brent House Hotel",
    "wof:placetype":"venue"
},
  "geometry": {"coordinates":[-90.145977,29.962779],"type":"Point"}
}