{
  "type": "Feature",
  "properties": {
    "addr:full":"115 E Mississippi Ave Ruston LA 71270",
    "addr:housenumber":"115",
    "addr:postcode":"71270",
    "addr:street":"E Mississippi Ave",
    "iso:country":"US",
    "sg:address":"115 E Mississippi Ave",
    "sg:city":"Ruston",
    "sg:classifiers":[
        {
            "category":"Insurance",
            "subcategory":"Insurance Agent",
            "type":"Services"
        }
    ],
    "sg:phone":"+1 318 254 1126",
    "sg:postcode":"71270",
    "sg:province":"LA",
    "wof:name":"Central American Life Ins Co",
    "wof:placetype":"venue"
},
  "geometry": {"coordinates":[-92.637061,32.529743],"type":"Point"}
}