{
  "type": "Feature",
  "properties": {
    "iso:country":"US",
    "sg:address":"509 Redbud Ln",
    "sg:city":"Slidell",
    "sg:classifiers":[
        {
            "category":"Building & Trades",
            "subcategory":"Landscaping Services",
            "type":"Services"
        }
    ],
    "sg:phone":"+1 985 847 9560",
    "sg:postcode":"70460",
    "sg:province":"LA",
    "sg:tags":[
        "lawn",
        "maintenance",
        "grounds"
    ],
    "wof:name":"Grass Man LLC",
    "wof:placetype":"venue"
},
  "geometry": {"coordinates":[-89.83515,30.328512],"type":"Point"}
}