{
  "type": "Feature",
  "properties": {
    "addr:full":"2 Rex St Lafayette LA 70503",
    "addr:housenumber":"2",
    "addr:postcode":"70503",
    "addr:street":"Rex St",
    "iso:country":"US",
    "sg:address":"2 Rex St",
    "sg:city":"Lafayette",
    "sg:classifiers":[
        {
            "category":"Professional",
            "subcategory":"Management & Consulting",
            "type":"Services"
        }
    ],
    "sg:phone":"+1 337 482 6334",
    "sg:postcode":"70503",
    "sg:province":"LA",
    "sg:tags":[
        "consultant",
        "training"
    ],
    "wof:name":"Advanced Technology Training",
    "wof:placetype":"venue"
},
  "geometry": {"coordinates":[-92.023212,30.210361],"type":"Point"}
}