{
  "type": "Feature",
  "properties": {
    "addr:full":"7121 N River Rd Port Allen LA 70767",
    "addr:housenumber":"7121",
    "addr:postcode":"70767",
    "addr:street":"N River Rd",
    "iso:country":"US",
    "sg:address":"7121 N River Rd",
    "sg:city":"Port Allen",
    "sg:classifiers":[
        {
            "category":"Real Estate",
            "subcategory":"Real Estate Operator",
            "type":"Services"
        }
    ],
    "sg:phone":"+1 225 383 6279",
    "sg:postcode":"70767",
    "sg:province":"LA",
    "sg:tags":[
        "mobile",
        "home",
        "community"
    ],
    "wof:name":"Belle Vale & Plantation Mobile",
    "wof:placetype":"venue"
},
  "geometry": {"coordinates":[-91.28963899999999,30.503259],"type":"Point"}
}