{
  "type": "Feature",
  "properties": {
    "iso:country":"US",
    "sg:address":"5745 Plauche Ct",
    "sg:city":"New Orleans",
    "sg:classifiers":[
        {
            "category":"Health Services",
            "subcategory":"Doctor",
            "type":"Services"
        }
    ],
    "sg:phone":"+1 504 733 3655",
    "sg:postcode":"70123",
    "sg:province":"LA",
    "sg:tags":[
        "physician",
        "surgeon"
    ],
    "wof:name":"Guardian Medical Group",
    "wof:placetype":"venue"
},
  "geometry": {"coordinates":[-90.186965,29.946303],"type":"Point"}
}