{
  "type": "Feature",
  "properties": {
    "iso:country":"US",
    "sg:address":"8922 Greenwell Springs Rd",
    "sg:city":"Baton Rouge",
    "sg:classifiers":[
        {
            "category":"Freight",
            "type":"Transportation"
        }
    ],
    "sg:phone":"+1 225 927 5102",
    "sg:postcode":"70814",
    "sg:province":"LA",
    "sg:tags":[
        "commercial",
        "storage"
    ],
    "wof:name":"Russell Mini Storage",
    "wof:placetype":"venue"
},
  "geometry": {"coordinates":[-91.089319,30.483644],"type":"Point"}
}