{
  "type": "Feature",
  "properties": {
    "addr:full":"3218 Johnston St Lafayette LA 70503",
    "addr:housenumber":"3218",
    "addr:postcode":"70503",
    "addr:street":"Johnston St",
    "iso:country":"US",
    "sg:address":"3218 Johnston St",
    "sg:city":"Lafayette",
    "sg:classifiers":[
        {
            "category":"Shopping",
            "subcategory":"Bicycles & Sporting Goods",
            "type":"Retail Goods"
        }
    ],
    "sg:phone":"+1 337 981 7686",
    "sg:postcode":"70503",
    "sg:province":"LA",
    "sg:tags":[
        "repair"
    ],
    "wof:name":"Precision Bikes LLC",
    "wof:placetype":"venue"
},
  "geometry": {"coordinates":[-92.049066,30.203462],"type":"Point"}
}