{
  "type": "Feature",
  "properties": {
    "iso:country":"US",
    "sg:address":"655 Main St",
    "sg:city":"Hackberry",
    "sg:classifiers":[
        {
            "category":"Building & Trades",
            "subcategory":"Construction",
            "type":"Services"
        }
    ],
    "sg:phone":"+1 337 762 3992",
    "sg:postcode":"70645",
    "sg:province":"LA",
    "sg:tags":[
        "general",
        "contractor"
    ],
    "wof:name":"Richard E Abshire Inc",
    "wof:placetype":"venue"
},
  "geometry": {"coordinates":[-93.367268,29.980576],"type":"Point"}
}