{
  "type": "Feature",
  "properties": {
    "addr:full":"5749 Susitna Dr New Orleans LA 70123",
    "addr:housenumber":"5749",
    "addr:postcode":"70123",
    "addr:street":"Susitna Dr",
    "iso:country":"US",
    "sg:address":"5749 Susitna Dr",
    "sg:city":"New Orleans",
    "sg:classifiers":[
        {
            "category":"Professional",
            "type":"Services"
        }
    ],
    "sg:phone":"+1 504 733 7529",
    "sg:postcode":"70123",
    "sg:province":"LA",
    "wof:name":"Universal Ogden Svc",
    "wof:placetype":"venue"
},
  "geometry": {"coordinates":[-90.191535,29.947988],"type":"Point"}
}