{
  "type": "Feature",
  "properties": {
    "iso:country":"US",
    "sg:address":"508 Lafayette St",
    "sg:city":"Youngsville",
    "sg:classifiers":[
        {
            "category":"Shopping",
            "subcategory":"Clothing, Apparel, & Fashions",
            "type":"Retail Goods"
        }
    ],
    "sg:phone":"+1 337 856 3443",
    "sg:postcode":"70592",
    "sg:province":"LA",
    "sg:tags":[
        "uniform"
    ],
    "wof:name":"School Time & Athletic Uniform",
    "wof:placetype":"venue"
},
  "geometry": {"coordinates":[-91.99047400000001,30.109245],"type":"Point"}
}