{
  "type": "Feature",
  "properties": {
    "iso:country":"US",
    "sg:address":"235 Soileau Ln",
    "sg:city":"Lake Charles",
    "sg:classifiers":[
        {
            "category":"Building & Trades",
            "subcategory":"Construction",
            "type":"Services"
        }
    ],
    "sg:phone":"+1 337 855 2778",
    "sg:postcode":"70611",
    "sg:province":"LA",
    "sg:tags":[
        "downspouts",
        "house",
        "gutter"
    ],
    "wof:name":"Taylor Aluminum Inc",
    "wof:placetype":"venue"
},
  "geometry": {"coordinates":[-93.207894,30.297964],"type":"Point"}
}