{
  "type": "Feature",
  "properties": {
    "iso:country":"US",
    "sg:address":"5600 Jefferson Hwy",
    "sg:city":"New Orleans",
    "sg:classifiers":[
        {
            "category":"Freight",
            "type":"Transportation"
        }
    ],
    "sg:phone":"+1 504 734 0960",
    "sg:postcode":"70123",
    "sg:province":"LA",
    "sg:tags":[
        "general"
    ],
    "wof:name":"M Aron Corporation",
    "wof:placetype":"venue"
},
  "geometry": {"coordinates":[-90.184997,29.944746],"type":"Point"}
}