{
  "type": "Feature",
  "properties": {
    "iso:country":"US",
    "sg:address":"6434 Greenwell Springs Rd",
    "sg:city":"Baton Rouge",
    "sg:classifiers":[
        {
            "category":"Travel",
            "subcategory":"Hotels & Motels",
            "type":"Entertainment"
        }
    ],
    "sg:phone":"+1 225 924 2455",
    "sg:postcode":"70806",
    "sg:province":"LA",
    "wof:name":"Shed-Dran Motel",
    "wof:placetype":"venue"
},
  "geometry": {"coordinates":[-91.12486199999999,30.470461],"type":"Point"}
}