{
  "type": "Feature",
  "properties": {
    "iso:country":"US",
    "sg:address":"17587 Hard Hat Dr",
    "sg:city":"Covington",
    "sg:classifiers":[
        {
            "category":"Communications",
            "subcategory":"Film & Video Production",
            "type":"Services"
        }
    ],
    "sg:phone":"+1 985 809 8001",
    "sg:postcode":"70435",
    "sg:province":"LA",
    "sg:tags":[
        "consultant",
        "audio"
    ],
    "sg:website":"www.psx-inc.com",
    "wof:name":"PSX Inc",
    "wof:placetype":"venue"
},
  "geometry": {"coordinates":[-90.111881,30.513519],"type":"Point"}
}