{
  "type": "Feature",
  "properties": {
    "iso:country":"US",
    "sg:address":"9262 4th St",
    "sg:city":"New Orleans",
    "sg:classifiers":[
        {
            "category":"Mining & Drilling",
            "type":"Manufacturing & Wholesale Goods"
        }
    ],
    "sg:phone":"+1 504 738 5867",
    "sg:postcode":"70123",
    "sg:province":"LA",
    "sg:tags":[
        "well"
    ],
    "wof:name":"Mark Bickham",
    "wof:placetype":"venue"
},
  "geometry": {"coordinates":[-90.216117,29.948735],"type":"Point"}
}