{
  "type": "Feature",
  "properties": {
    "iso:country":"US",
    "sg:address":"144 Hudson Creek Rd",
    "sg:city":"Colfax",
    "sg:classifiers":[
        {
            "category":"Professional",
            "type":"Services"
        }
    ],
    "sg:phone":"+1 318 640 1080",
    "sg:postcode":"71417",
    "sg:province":"LA",
    "wof:name":"Triple Point Dozier",
    "wof:placetype":"venue"
},
  "geometry": {"coordinates":[-92.534781,31.432644],"type":"Point"}
}