{
  "type": "Feature",
  "properties": {
    "iso:country":"US",
    "sg:address":"106 Amaryllis Dr",
    "sg:city":"Lafayette",
    "sg:classifiers":[
        {
            "category":"Shopping",
            "type":"Retail Goods"
        }
    ],
    "sg:phone":"+1 337 232 0857",
    "sg:postcode":"70503",
    "sg:province":"LA",
    "sg:tags":[
        "merchandise"
    ],
    "wof:name":"Art Jeanelles Studio Inc",
    "wof:placetype":"venue"
},
  "geometry": {"coordinates":[-92.034727,30.205727],"type":"Point"}
}