{
  "type": "Feature",
  "properties": {
    "iso:country":"US",
    "sg:address":"11846 State Rte 23",
    "sg:city":"Belle Chasse",
    "sg:phone":"+1 504 656 2178",
    "sg:postcode":"70037",
    "sg:province":"LA",
    "sg:tags":[
        "farm"
    ],
    "wof:name":"Joseph S Ranatza Jr Inc",
    "wof:placetype":"venue"
},
  "geometry": {"coordinates":[-90.03035300000001,29.768449],"type":"Point"}
}