{
  "type": "Feature",
  "properties": {
    "iso:country":"US",
    "sg:address":"5021 W Monkhouse Dr",
    "sg:city":"Shreveport",
    "sg:classifiers":[
        {
            "category":"Home & Garden",
            "subcategory":"Building Materials",
            "type":"Retail Goods"
        },
        {
            "category":"Building & Trades",
            "subcategory":"Construction",
            "type":"Services"
        },
        {
            "category":"Military Area",
            "subcategory":"Armory",
            "type":"Public Place"
        }
    ],
    "sg:phone":"+1 318 635 4413",
    "sg:postcode":"71109",
    "sg:province":"LA",
    "sg:tags":[
        "repair",
        "fence-sales",
        "fence",
        "contractor"
    ],
    "wof:name":"Edmonds Louisiana Fence",
    "wof:placetype":"venue"
},
  "geometry": {"coordinates":[-93.82974400000001,32.462707],"type":"Point"}
}