{
  "type": "Feature",
  "properties": {
    "iso:country":"US",
    "sg:address":"615 Benton Rd",
    "sg:city":"Bossier City",
    "sg:classifiers":[
        {
            "category":"Home & Garden",
            "subcategory":"Hardware",
            "type":"Retail Goods"
        }
    ],
    "sg:phone":"+1 318 746 0311",
    "sg:postcode":"71111",
    "sg:province":"LA",
    "sg:website":"www.tubbshardware.com",
    "wof:name":"Tubbs Hardware & Rental",
    "wof:placetype":"venue"
},
  "geometry": {"coordinates":[-93.71683899999999,32.523765],"type":"Point"}
}