{
  "type": "Feature",
  "properties": {
    "addr:full":"986 Washington St Franklinton LA 70438",
    "addr:housenumber":"986",
    "addr:postcode":"70438",
    "addr:street":"Washington St",
    "iso:country":"US",
    "sg:address":"986 Washington St",
    "sg:city":"Franklinton",
    "sg:classifiers":[
        {
            "category":"Banks & Credit Unions",
            "subcategory":"Bank",
            "type":"Services"
        }
    ],
    "sg:phone":"+1 985 839 4603",
    "sg:postcode":"70438",
    "sg:province":"LA",
    "sg:tags":[
        "loan",
        "real estate"
    ],
    "wof:name":"First Finance Co",
    "wof:placetype":"venue"
},
  "geometry": {"coordinates":[-90.15558900000001,30.844301],"type":"Point"}
}