{
  "type": "Feature",
  "properties": {
    "iso:country":"US",
    "sg:address":"1107 W Linwood Dr",
    "sg:city":"Opelousas",
    "sg:classifiers":[
        {
            "category":"Government",
            "subcategory":"Office",
            "type":"Public Place"
        }
    ],
    "sg:phone":"+1 337 948 0225",
    "sg:postcode":"70570",
    "sg:province":"LA",
    "wof:name":"Opelousas Community Home",
    "wof:placetype":"venue"
},
  "geometry": {"coordinates":[-92.07796,30.495601],"type":"Point"}
}