{
  "type": "Feature",
  "properties": {
    "iso:country":"US",
    "sg:address":"119 Kimball Dr",
    "sg:city":"Lafayette",
    "sg:classifiers":[
        {
            "category":"Professional",
            "subcategory":"Lawyer & Legal Services",
            "type":"Services"
        }
    ],
    "sg:phone":"+1 337 981 3869",
    "sg:postcode":"70508",
    "sg:province":"LA",
    "wof:name":"Elaine D Abell",
    "wof:placetype":"venue"
},
  "geometry": {"coordinates":[-92.07434499999999,30.13717],"type":"Point"}
}