{
  "type": "Feature",
  "properties": {
    "iso:country":"US",
    "sg:address":"612 N 7th St",
    "sg:city":"West Monroe",
    "sg:classifiers":[
        {
            "category":"Wholesale",
            "subcategory":"Machinery & Supplies",
            "type":"Manufacturing & Wholesale Goods"
        }
    ],
    "sg:phone":"+1 318 388 2660",
    "sg:postcode":"71291",
    "sg:province":"LA",
    "sg:tags":[
        "commercial",
        "fan"
    ],
    "sg:website":"www.gainesequipment.com",
    "wof:name":"Gaines Process-Power Equipment",
    "wof:placetype":"venue"
},
  "geometry": {"coordinates":[-92.134019,32.50108],"type":"Point"}
}