{
  "type": "Feature",
  "properties": {
    "iso:country":"US",
    "sg:address":"763 Philpot Rd",
    "sg:city":"West Monroe",
    "sg:classifiers":[
        {
            "category":"Building & Trades",
            "subcategory":"Construction",
            "type":"Services"
        }
    ],
    "sg:phone":"+1 318 322 1025",
    "sg:postcode":"71292",
    "sg:province":"LA",
    "sg:tags":[
        "heavy"
    ],
    "wof:name":"Porter Roadboring LLC",
    "wof:placetype":"venue"
},
  "geometry": {"coordinates":[-92.1764,32.414262],"type":"Point"}
}