{
  "type": "Feature",
  "properties": {
    "iso:country":"US",
    "sg:address":"620 12th St",
    "sg:city":"Alexandria",
    "sg:classifiers":[
        {
            "category":"Wholesale",
            "subcategory":"Durable Goods & Equipment",
            "type":"Manufacturing & Wholesale Goods"
        }
    ],
    "sg:phone":"+1 318 443 4372",
    "sg:postcode":"71301",
    "sg:province":"LA",
    "sg:tags":[
        "fire",
        "extinguisher"
    ],
    "wof:name":"E L Gremillion & Son Fire",
    "wof:placetype":"venue"
},
  "geometry": {"coordinates":[-92.452179,31.307984],"type":"Point"}
}