{
  "type": "Feature",
  "properties": {
    "iso:country":"US",
    "sg:address":"1200 Sterlington Rd",
    "sg:city":"Monroe",
    "sg:classifiers":[
        {
            "category":"Farming",
            "subcategory":"Farm & Veterinary Services",
            "type":"Manufacturing & Wholesale Goods"
        }
    ],
    "sg:phone":"+1 318 327 1444",
    "sg:postcode":"71203",
    "sg:province":"LA",
    "sg:tags":[
        "cotton",
        "ginning"
    ],
    "wof:name":"Ouachita Gin Inc",
    "wof:placetype":"venue"
},
  "geometry": {"coordinates":[-92.080409,32.530774],"type":"Point"}
}