{
  "type": "Feature",
  "properties": {
    "addr:full":"315 Macon Rd Lafayette LA 70506",
    "addr:housenumber":"315",
    "addr:postcode":"70506",
    "addr:street":"Macon Rd",
    "iso:country":"US",
    "sg:address":"315 Macon Rd",
    "sg:city":"Lafayette",
    "sg:classifiers":[
        {
            "category":"Retail",
            "subcategory":"Repair Shop",
            "type":"Services"
        }
    ],
    "sg:phone":"+1 337 232 6783",
    "sg:postcode":"70506",
    "sg:province":"LA",
    "sg:tags":[
        "water",
        "equipment",
        "softening"
    ],
    "wof:name":"Acadiana Water Conditioning",
    "wof:placetype":"venue"
},
  "geometry": {"coordinates":[-92.049859,30.228483],"type":"Point"}
}