{
  "type": "Feature",
  "properties": {
    "iso:country":"US",
    "sg:address":"307 Robindale Cir",
    "sg:city":"Baton Rouge",
    "sg:classifiers":[
        {
            "category":"Building & Trades",
            "subcategory":"Electrical",
            "type":"Services"
        }
    ],
    "sg:phone":"+1 225 275 9547",
    "sg:postcode":"70815",
    "sg:province":"LA",
    "sg:tags":[
        "electric",
        "contractor"
    ],
    "wof:name":"Andre's Electric Co",
    "wof:placetype":"venue"
},
  "geometry": {"coordinates":[-91.061538,30.454742],"type":"Point"}
}