{
  "type": "Feature",
  "properties": {
    "iso:country":"US",
    "sg:address":"112 Bowers Ln",
    "sg:city":"Buras",
    "sg:classifiers":[
        {
            "category":"Wholesale",
            "subcategory":"Seafood",
            "type":"Manufacturing & Wholesale Goods"
        }
    ],
    "sg:phone":"+1 985 657 5344",
    "sg:postcode":"70050",
    "sg:province":"LA",
    "wof:name":"Roko's Oysters & Seafood Inc",
    "wof:placetype":"venue"
},
  "geometry": {"coordinates":[-89.608806,29.399042],"type":"Point"}
}