{
  "type": "Feature",
  "properties": {
    "iso:country":"US",
    "sg:address":"601 E Pershing St",
    "sg:city":"New Iberia",
    "sg:classifiers":[
        {
            "category":"Freight",
            "type":"Transportation"
        }
    ],
    "sg:phone":"+1 337 364 9600",
    "sg:postcode":"70560",
    "sg:province":"LA",
    "sg:tags":[
        "operator",
        "local",
        "trucking"
    ],
    "wof:name":"M R Bradley Trucking",
    "wof:placetype":"venue"
},
  "geometry": {"coordinates":[-91.815803,29.998578],"type":"Point"}
}