{
  "type": "Feature",
  "properties": {
    "addr:full":"1928 Charity St Abbeville LA 70510",
    "addr:housenumber":"1928",
    "addr:postcode":"70510",
    "addr:street":"Charity St",
    "iso:country":"US",
    "sg:address":"1928 Charity St",
    "sg:city":"Abbeville",
    "sg:classifiers":[
        {
            "category":"Restaurant",
            "type":"Food & Drink"
        }
    ],
    "sg:phone":"+1 337 893 9437",
    "sg:postcode":"70510",
    "sg:province":"LA",
    "sg:tags":[
        "eating"
    ],
    "wof:name":"Cajun Claws",
    "wof:placetype":"venue"
},
  "geometry": {"coordinates":[-92.11453400000001,29.97278],"type":"Point"}
}