{
  "type": "Feature",
  "properties": {
    "addr:full":"10840 Kina Cir Keithville LA 71047",
    "addr:postcode":"10840;71047",
    "addr:street":"Kina Cir",
    "iso:country":"US",
    "sg:address":"10840 Kina Cir",
    "sg:city":"Keithville",
    "sg:classifiers":[
        {
            "category":"Banks & Credit Unions",
            "subcategory":"Investment Brokerage",
            "type":"Services"
        }
    ],
    "sg:phone":"+1 318 925 5112",
    "sg:postcode":"71047",
    "sg:province":"LA",
    "wof:name":"Jusselin Investments LLC",
    "wof:placetype":"venue"
},
  "geometry": {"coordinates":[-93.835311,32.363],"type":"Point"}
}