{
  "type": "Feature",
  "properties": {
    "addr:full":"620 E Bayou Dr Tallulah LA 71282",
    "addr:housenumber":"620",
    "addr:postcode":"71282",
    "addr:street":"E Bayou Dr",
    "iso:country":"US",
    "sg:address":"620 E Bayou Dr",
    "sg:city":"Tallulah",
    "sg:classifiers":[
        {
            "category":"Restaurant",
            "type":"Food & Drink"
        }
    ],
    "sg:phone":"+1 318 574 9090",
    "sg:postcode":"71282",
    "sg:province":"LA",
    "wof:name":"Sonny's Pizza",
    "wof:placetype":"venue"
},
  "geometry": {"coordinates":[-91.18013999999999,32.407717],"type":"Point"}
}