{
  "type": "Feature",
  "properties": {
    "addr:full":"627 Canal Blvd Thibodaux LA 70301",
    "addr:housenumber":"627",
    "addr:postcode":"70301",
    "addr:street":"Canal Blvd",
    "iso:country":"US",
    "sg:address":"627 Canal Blvd",
    "sg:city":"Thibodaux",
    "sg:classifiers":[
        {
            "category":"Restaurant",
            "type":"Food & Drink"
        }
    ],
    "sg:menulink":"http://www.allmenus.com/la/thibodaux/235077-roly-poly-sandwiches/menu/",
    "sg:phone":"+1 985 447 4400",
    "sg:postcode":"70301",
    "sg:province":"LA",
    "sg:tags":[
        "wrap",
        "american",
        "sandwich"
    ],
    "wof:name":"Roly Poly Sandwiches",
    "wof:placetype":"venue"
},
  "geometry": {"coordinates":[-90.81949400000001,29.794758],"type":"Point"}
}