{
  "type": "Feature",
  "properties": {
    "iso:country":"US",
    "sg:address":"600 Brick St",
    "sg:city":"Breaux Bridge",
    "sg:classifiers":[
        {
            "category":"Manufacturing",
            "subcategory":"Printing",
            "type":"Manufacturing & Wholesale Goods"
        }
    ],
    "sg:phone":"+1 337 332 3562",
    "sg:postcode":"70517",
    "sg:province":"LA",
    "sg:tags":[
        "newspaper"
    ],
    "wof:name":"Teche News",
    "wof:placetype":"venue"
},
  "geometry": {"coordinates":[-91.909899,30.274104],"type":"Point"}
}