{
  "type": "Feature",
  "properties": {
    "iso:country":"US",
    "sg:address":"12484 Lake Charles Hwy",
    "sg:city":"Leesville",
    "sg:classifiers":[
        {
            "category":"Shopping",
            "subcategory":"Computers & Home Electronics",
            "type":"Retail Goods"
        }
    ],
    "sg:phone":"+1 337 239 6120",
    "sg:postcode":"71446",
    "sg:province":"LA",
    "sg:tags":[
        "equipment",
        "dealer"
    ],
    "wof:name":"C & G Computers",
    "wof:placetype":"venue"
},
  "geometry": {"coordinates":[-93.27025500000001,31.01868],"type":"Point"}
}