{
  "type": "Feature",
  "properties": {
    "iso:country":"US",
    "sg:address":"4665 Perkins Rd",
    "sg:city":"Baton Rouge",
    "sg:classifiers":[
        {
            "category":"Restaurant",
            "type":"Food & Drink"
        }
    ],
    "sg:phone":"+1 225 924 0324",
    "sg:postcode":"70808",
    "sg:province":"LA",
    "wof:name":"Pizza Hut",
    "wof:placetype":"venue"
},
  "geometry": {"coordinates":[-91.14290200000001,30.416382],"type":"Point"}
}