{
  "type": "Feature",
  "properties": {
    "iso:country":"US",
    "sg:address":"806 King Pl",
    "sg:city":"Shreveport",
    "sg:classifiers":[
        {
            "category":"Home & Garden",
            "subcategory":"Building Materials",
            "type":"Retail Goods"
        }
    ],
    "sg:phone":"+1 318 797 3779",
    "sg:postcode":"71115",
    "sg:province":"LA",
    "sg:tags":[
        "shutter"
    ],
    "wof:name":"L & J Plantation Shutters",
    "wof:placetype":"venue"
},
  "geometry": {"coordinates":[-93.699279,32.405468],"type":"Point"}
}