{
  "type": "Feature",
  "properties": {
    "addr:full":"1980 Hwy 80 Haughton LA 71037",
    "addr:housenumber":"1980",
    "addr:postcode":"71037",
    "addr:street":"Hwy 80",
    "iso:country":"US",
    "sg:address":"1980 Hwy 80",
    "sg:city":"Haughton",
    "sg:classifiers":[
        {
            "category":"Building & Trades",
            "subcategory":"Plumbing",
            "type":"Services"
        }
    ],
    "sg:phone":"+1 318 227 8619",
    "sg:postcode":"71037",
    "sg:province":"LA",
    "sg:tags":[
        "conditioning",
        "air",
        "system",
        "contractor"
    ],
    "wof:name":"Tcs A/C & Heating Inc",
    "wof:placetype":"venue"
},
  "geometry": {"coordinates":[-93.60307,32.555819],"type":"Point"}
}