{
  "type": "Feature",
  "properties": {
    "addr:full":"50 Coronado Ave Kenner LA 70065",
    "addr:housenumber":"50",
    "addr:postcode":"70065",
    "addr:street":"Coronado Ave",
    "iso:country":"US",
    "sg:address":"50 Coronado Ave",
    "sg:city":"Kenner",
    "sg:classifiers":[
        {
            "category":"Wholesale",
            "subcategory":"Electrical",
            "type":"Manufacturing & Wholesale Goods"
        }
    ],
    "sg:phone":"+1 504 443 6511",
    "sg:postcode":"70065",
    "sg:province":"LA",
    "sg:tags":[
        "control",
        "security",
        "system"
    ],
    "wof:name":"Eton Electronics",
    "wof:placetype":"venue"
},
  "geometry": {"coordinates":[-90.234481,30.029253],"type":"Point"}
}