{
  "type": "Feature",
  "properties": {
    "addr:full":"1301 Mills St Scott LA 70583",
    "addr:housenumber":"1301",
    "addr:postcode":"70583",
    "addr:street":"Mills St",
    "iso:country":"US",
    "sg:address":"1301 Mills St",
    "sg:city":"Scott",
    "sg:classifiers":[
        {
            "category":"Building & Trades",
            "subcategory":"Construction",
            "type":"Services"
        }
    ],
    "sg:phone":"+1 337 234 9587",
    "sg:postcode":"70583",
    "sg:province":"LA",
    "sg:tags":[
        "home",
        "improvement"
    ],
    "wof:name":"A New Look Home Improvements",
    "wof:placetype":"venue"
},
  "geometry": {"coordinates":[-92.09107299999999,30.254662],"type":"Point"}
}