{
  "type": "Feature",
  "properties": {
    "iso:country":"US",
    "sg:address":"705 Ormond Blvd",
    "sg:city":"Destrehan",
    "sg:classifiers":[
        {
            "category":"Building & Trades",
            "subcategory":"Construction",
            "type":"Services"
        }
    ],
    "sg:phone":"+1 985 764 9617",
    "sg:postcode":"70047",
    "sg:province":"LA",
    "sg:tags":[
        "housing",
        "family"
    ],
    "wof:name":"J A Ron Inc",
    "wof:placetype":"venue"
},
  "geometry": {"coordinates":[-90.380512,29.963841],"type":"Point"}
}