{
  "type": "Feature",
  "properties": {
    "iso:country":"US",
    "sg:address":"200 Paris Ave",
    "sg:city":"Metairie",
    "sg:classifiers":[
        {
            "category":"Banks & Credit Unions",
            "subcategory":"Bank",
            "type":"Services"
        }
    ],
    "sg:phone":"+1 504 835 3810",
    "sg:postcode":"70005",
    "sg:province":"LA",
    "wof:name":"Barbers & Beauticians Cu",
    "wof:placetype":"venue"
},
  "geometry": {"coordinates":[-90.125877,29.998576],"type":"Point"}
}