{
  "type": "Feature",
  "properties": {
    "iso:country":"US",
    "sg:address":"6600 Morrison Rd",
    "sg:city":"New Orleans",
    "sg:classifiers":[
        {
            "category":"Shopping",
            "type":"Retail Goods"
        }
    ],
    "sg:phone":"+1 504 243 0707",
    "sg:postcode":"70126",
    "sg:province":"LA",
    "sg:tags":[
        "cosmetic",
        "perfume"
    ],
    "wof:name":"Avon Products",
    "wof:placetype":"venue"
},
  "geometry": {"coordinates":[-90.009243,30.030735],"type":"Point"}
}