{
  "type": "Feature",
  "properties": {
    "iso:country":"US",
    "sg:address":"2113 Riviere Ave",
    "sg:city":"Metairie",
    "sg:classifiers":[
        {
            "category":"Professional",
            "subcategory":"Secretarial Services",
            "type":"Services"
        }
    ],
    "sg:phone":"+1 504 454 8327",
    "sg:postcode":"70003",
    "sg:province":"LA",
    "sg:tags":[
        "reporting"
    ],
    "wof:name":"Metro Steno Service",
    "wof:placetype":"venue"
},
  "geometry": {"coordinates":[-90.20929700000001,29.993139],"type":"Point"}
}