{
  "type": "Feature",
  "properties": {
    "addr:full":"6803 W Park Ave Houma LA 70364",
    "addr:housenumber":"6803",
    "addr:postcode":"70364",
    "addr:street":"W Park Ave",
    "iso:country":"US",
    "sg:address":"6803 W Park Ave",
    "sg:city":"Houma",
    "sg:classifiers":[
        {
            "category":"Cafe",
            "type":"Food & Drink"
        }
    ],
    "sg:menulink":"http://www.allmenus.com/la/houma/234213-piccadilly-cafeteria/menu/",
    "sg:phone":"+1 985 879 4222",
    "sg:postcode":"70364",
    "sg:province":"LA",
    "sg:tags":[
        "american",
        "southwestern"
    ],
    "wof:name":"Piccadilly Cafeteria",
    "wof:placetype":"venue"
},
  "geometry": {"coordinates":[-90.74517899999999,29.615081],"type":"Point"}
}