{
  "type": "Feature",
  "properties": {
    "addr:full":"4205 State Rte 75 St Gabriel LA 70776",
    "addr:housenumber":"4205",
    "addr:postcode":"70776",
    "addr:street":"State Rte 75 St Gabriel La",
    "iso:country":"US",
    "sg:address":"4205 State Rte 75",
    "sg:city":"St Gabriel",
    "sg:classifiers":[
        {
            "category":"Wholesale",
            "subcategory":"Chemicals & Plastics",
            "type":"Manufacturing & Wholesale Goods"
        }
    ],
    "sg:phone":"+1 225 642 2900",
    "sg:postcode":"70776",
    "sg:province":"LA",
    "wof:name":"Altiva",
    "wof:placetype":"venue"
},
  "geometry": {"coordinates":[-91.10979,30.240611],"type":"Point"}
}