{
  "type": "Feature",
  "properties": {
    "iso:country":"US",
    "sg:address":"6913 W Port Ave",
    "sg:city":"Shreveport",
    "sg:classifiers":[
        {
            "category":"Professional",
            "type":"Services"
        },
        {
            "category":"Utilities",
            "subcategory":"Fuel Oil & Lpg",
            "type":"Services"
        }
    ],
    "sg:phone":"+1 318 688 9850",
    "sg:postcode":"71129",
    "sg:province":"LA",
    "sg:tags":[
        "field",
        "well",
        "log",
        "library"
    ],
    "sg:website":"http://www.arklatexwireline.com",
    "wof:name":"Arklatex Wireline Services",
    "wof:placetype":"venue"
},
  "geometry": {"coordinates":[-93.865608,32.449162],"type":"Point"}
}