{
  "type": "Feature",
  "properties": {
    "iso:country":"US",
    "sg:address":"503 Cantwell Rd",
    "sg:city":"Jonesville",
    "sg:classifiers":[
        {
            "category":"Farming",
            "subcategory":"Livestock Farm",
            "type":"Manufacturing & Wholesale Goods"
        }
    ],
    "sg:phone":"+1 318 339 8854",
    "sg:postcode":"71343",
    "sg:province":"LA",
    "sg:tags":[
        "beef",
        "feedlot",
        "cattle"
    ],
    "wof:name":"Douglas Rainey",
    "wof:placetype":"venue"
},
  "geometry": {"coordinates":[-91.84904899999999,31.720329],"type":"Point"}
}