{
  "type": "Feature",
  "properties": {
    "addr:full":"802 Main St Pineville LA 71360",
    "addr:housenumber":"802",
    "addr:postcode":"71360",
    "addr:street":"Main St",
    "iso:country":"US",
    "sg:address":"802 Main St",
    "sg:city":"Pineville",
    "sg:classifiers":[
        {
            "category":"Real Estate",
            "subcategory":"Real Estate Agent",
            "type":"Services"
        }
    ],
    "sg:phone":"+1 318 487 1555",
    "sg:postcode":"71360",
    "sg:province":"LA",
    "wof:name":"Roger Mc Coy Realty",
    "wof:placetype":"venue"
},
  "geometry": {"coordinates":[-92.4328,31.323887],"type":"Point"}
}