{
  "type": "Feature",
  "properties": {
    "iso:country":"US",
    "sg:address":"19046 Vignes Lake Ave",
    "sg:city":"Baton Rouge",
    "sg:classifiers":[
        {
            "category":"Real Estate",
            "subcategory":"Real Estate Agent",
            "type":"Services"
        }
    ],
    "sg:phone":"+1 225 756 8434",
    "sg:postcode":"70817",
    "sg:province":"LA",
    "wof:name":"Jay Campagna Realtor",
    "wof:placetype":"venue"
},
  "geometry": {"coordinates":[-90.980082,30.35829],"type":"Point"}
}