{
  "type": "Feature",
  "properties": {
    "addr:full":"8604 Oak Ridge Rd Mer Rouge LA 71261",
    "addr:housenumber":"8604",
    "addr:postcode":"71261",
    "addr:street":"Oak Ridge Rd Mer",
    "iso:country":"US",
    "sg:address":"8604 Oak Ridge Rd",
    "sg:city":"Mer Rouge",
    "sg:classifiers":[
        {
            "category":"Wholesale",
            "subcategory":"Chemicals & Plastics",
            "type":"Manufacturing & Wholesale Goods"
        }
    ],
    "sg:phone":"+1 318 647 5571",
    "sg:postcode":"71261",
    "sg:province":"LA",
    "wof:name":"Helena Chemical Co",
    "wof:placetype":"venue"
},
  "geometry": {"coordinates":[-91.785719,32.751272],"type":"Point"}
}