{
  "type": "Feature",
  "properties": {
    "iso:country":"US",
    "sg:address":"2000 S Morrison Blvd",
    "sg:city":"Hammond",
    "sg:classifiers":[
        {
            "category":"Health Services",
            "subcategory":"Health Practitioner",
            "type":"Services"
        }
    ],
    "sg:phone":"+1 985 419 0459",
    "sg:postcode":"70403",
    "sg:province":"LA",
    "sg:tags":[
        "therapist",
        "physical"
    ],
    "wof:name":"Aquatics Rehab",
    "wof:placetype":"venue"
},
  "geometry": {"coordinates":[-90.48267,30.480484],"type":"Point"}
}