{
  "type": "Feature",
  "properties": {
    "addr:full":"8282 Siegen Ln Baton Rouge LA 70810",
    "addr:housenumber":"8282",
    "addr:postcode":"70810",
    "addr:street":"Siegen Ln",
    "iso:country":"US",
    "sg:address":"8282 Siegen Ln",
    "sg:city":"Baton Rouge",
    "sg:classifiers":[
        {
            "category":"Professional",
            "subcategory":"Business Services",
            "type":"Services"
        }
    ],
    "sg:phone":"+1 225 766 4080",
    "sg:postcode":"70810",
    "sg:province":"LA",
    "sg:tags":[
        "pool",
        "swimming"
    ],
    "sg:website":"www.modernprocess.com",
    "wof:name":"Modern Process Systems Inc",
    "wof:placetype":"venue"
},
  "geometry": {"coordinates":[-91.07056300000001,30.374089],"type":"Point"}
}