{
  "type": "Feature",
  "properties": {
    "iso:country":"US",
    "sg:address":"327 Hall St",
    "sg:city":"Dequincy",
    "sg:classifiers":[
        {
            "category":"Farming",
            "subcategory":"Livestock Farm",
            "type":"Manufacturing & Wholesale Goods"
        }
    ],
    "sg:phone":"+1 337 786 2751",
    "sg:postcode":"70633",
    "sg:province":"LA",
    "sg:tags":[
        "animal",
        "general"
    ],
    "wof:name":"N Flying Ranch Inc",
    "wof:placetype":"venue"
},
  "geometry": {"coordinates":[-93.437107,30.446234],"type":"Point"}
}