{
  "type": "Feature",
  "properties": {
    "addr:full":"7942 Highway 23 Ste B Belle Chasse LA 70037",
    "addr:housenumber":"7942",
    "addr:postcode":"70037",
    "addr:street":"Highway 23 Ste B",
    "iso:country":"US",
    "sg:address":"7942 Highway 23 Ste B",
    "sg:city":"Belle Chasse",
    "sg:classifiers":[
        {
            "category":"Personal",
            "subcategory":"Massage",
            "type":"Services"
        },
        {
            "category":"Personal",
            "subcategory":"Day Spa",
            "type":"Services"
        }
    ],
    "sg:phone":"+1 504 394 3800",
    "sg:postcode":"70037",
    "sg:province":"LA",
    "wof:name":"Renaissance Salon & Spa",
    "wof:placetype":"venue"
},
  "geometry": {"coordinates":[-89.99527,29.861548],"type":"Point"}
}