{
  "type": "Feature",
  "properties": {
    "iso:country":"US",
    "sg:address":"2905 E Simcoe St",
    "sg:city":"Lafayette",
    "sg:classifiers":[
        {
            "category":"Bars & Pubs",
            "type":"Food & Drink"
        }
    ],
    "sg:phone":"+1 337 235 9965",
    "sg:postcode":"70501",
    "sg:province":"LA",
    "wof:name":"Dougout Lounge",
    "wof:placetype":"venue"
},
  "geometry": {"coordinates":[-91.988146,30.221076],"type":"Point"}
}