{
  "type": "Feature",
  "properties": {
    "iso:country":"US",
    "sg:address":"5725 Johnston St",
    "sg:city":"Lafayette",
    "sg:classifiers":[
        {
            "category":"Home & Garden",
            "subcategory":"Furniture",
            "type":"Retail Goods"
        }
    ],
    "sg:phone":"+1 337 993 3010",
    "sg:postcode":"70503",
    "sg:province":"LA",
    "sg:tags":[
        "mattress"
    ],
    "wof:name":"Select Comfort Corp",
    "wof:placetype":"venue"
},
  "geometry": {"coordinates":[-92.077939,30.17453],"type":"Point"}
}