{
  "type": "Feature",
  "properties": {
    "iso:country":"US",
    "sg:address":"500 N Hwy 190",
    "sg:city":"Covington",
    "sg:classifiers":[
        {
            "category":"Professional",
            "type":"Services"
        }
    ],
    "sg:phone":"+1 985 871 0544",
    "sg:postcode":"70433",
    "sg:province":"LA",
    "sg:tags":[
        "establishment"
    ],
    "wof:name":"Fcti",
    "wof:placetype":"venue"
},
  "geometry": {"coordinates":[-90.08310400000001,30.438031],"type":"Point"}
}