{
  "type": "Feature",
  "properties": {
    "addr:full":"7204 Washington Ave New Orleans LA 70125",
    "addr:housenumber":"7204",
    "addr:postcode":"70125",
    "addr:street":"Washington Ave",
    "iso:country":"US",
    "sg:address":"7204 Washington Ave",
    "sg:city":"New Orleans",
    "sg:classifiers":[
        {
            "category":"Building & Trades",
            "subcategory":"Plumbing",
            "type":"Services"
        }
    ],
    "sg:phone":"+1 504 482 7881",
    "sg:postcode":"70125",
    "sg:province":"LA",
    "sg:tags":[
        "plumbing",
        "contractor"
    ],
    "wof:name":"National Economy Plumbers Inc",
    "wof:placetype":"venue"
},
  "geometry": {"coordinates":[-90.10740199999999,29.963027],"type":"Point"}
}