{
  "type": "Feature",
  "properties": {
    "iso:country":"US",
    "sg:address":"2896 US Hwy 171",
    "sg:city":"Lake Charles",
    "sg:classifiers":[
        {
            "category":"Building & Trades",
            "subcategory":"Construction",
            "type":"Services"
        }
    ],
    "sg:phone":"+1 337 855 6300",
    "sg:postcode":"70611",
    "sg:province":"LA",
    "sg:tags":[
        "designer",
        "dealer",
        "pool",
        "swimming"
    ],
    "wof:name":"Lake Area Fiberglass Pools Inc",
    "wof:placetype":"venue"
},
  "geometry": {"coordinates":[-93.200091,30.347432],"type":"Point"}
}