{
  "type": "Feature",
  "properties": {
    "iso:country":"US",
    "sg:address":"1801 Womble St",
    "sg:city":"Winnsboro",
    "sg:classifiers":[
        {
            "category":"Home & Garden",
            "subcategory":"Home Furnishings",
            "type":"Retail Goods"
        }
    ],
    "sg:phone":"+1 318 412 9496",
    "sg:postcode":"71295",
    "sg:province":"LA",
    "sg:tags":[
        "curtain",
        "made",
        "drapery"
    ],
    "wof:name":"Wondas Curtain & Pillows",
    "wof:placetype":"venue"
},
  "geometry": {"coordinates":[-91.730069,32.156763],"type":"Point"}
}