{
  "type": "Feature",
  "properties": {
    "iso:country":"US",
    "sg:address":"21301 South St",
    "sg:city":"Abita Springs",
    "sg:classifiers":[
        {
            "category":"Home & Garden",
            "subcategory":"Building Materials",
            "type":"Retail Goods"
        }
    ],
    "sg:phone":"+1 985 966 1906",
    "sg:postcode":"70420",
    "sg:province":"LA",
    "sg:tags":[
        "door"
    ],
    "wof:name":"Gulfshore Door Co",
    "wof:placetype":"venue"
},
  "geometry": {"coordinates":[-90.047714,30.467246],"type":"Point"}
}