{
  "type": "Feature",
  "properties": {
    "iso:country":"US",
    "sg:address":"1475 Main St",
    "sg:city":"Colfax",
    "sg:classifiers":[
        {
            "category":"Food & Beverages",
            "subcategory":"Groceries & Convenience Stores",
            "type":"Retail Goods"
        }
    ],
    "sg:phone":"+1 318 627 2703",
    "sg:postcode":"71417",
    "sg:province":"LA",
    "sg:tags":[
        "grocer"
    ],
    "wof:name":"O M Grocery",
    "wof:placetype":"venue"
},
  "geometry": {"coordinates":[-92.693027,31.524583],"type":"Point"}
}