{
  "type": "Feature",
  "properties": {
    "iso:country":"US",
    "sg:address":"3100 Ryan St",
    "sg:city":"Lake Charles",
    "sg:classifiers":[
        {
            "category":"Restaurant",
            "type":"Food & Drink"
        }
    ],
    "sg:menulink":"http://www.allmenus.com/la/lake-charles/235072-roly-poly-sandwiches/menu/",
    "sg:phone":"+1 337 433 3130",
    "sg:postcode":"70601",
    "sg:province":"LA",
    "sg:tags":[
        "wrap",
        "american",
        "sandwich"
    ],
    "wof:name":"Roly Poly Sandwiches",
    "wof:placetype":"venue"
},
  "geometry": {"coordinates":[-93.218587,30.200368],"type":"Point"}
}