{
  "type": "Feature",
  "properties": {
    "iso:country":"US",
    "sg:address":"2385 Airline Dr",
    "sg:city":"Bossier City",
    "sg:classifiers":[
        {
            "category":"Education",
            "subcategory":"Dance Studio",
            "type":"Public Place"
        }
    ],
    "sg:phone":"+1 318 741 3547",
    "sg:postcode":"71111",
    "sg:province":"LA",
    "sg:tags":[
        "instruction",
        "dancing"
    ],
    "wof:name":"Bossier City Dance Academy",
    "wof:placetype":"venue"
},
  "geometry": {"coordinates":[-93.707624,32.535758],"type":"Point"}
}