{
  "type": "Feature",
  "properties": {
    "iso:country":"US",
    "sg:address":"15660 Highway 71",
    "sg:city":"Hosston",
    "sg:classifiers":[
        {
            "category":"Autos & Motor Vehicles",
            "subcategory":"Fuel & Gas Station",
            "type":"Retail Goods"
        },
        {
            "category":"Restaurant",
            "type":"Food & Drink"
        }
    ],
    "sg:phone":"+1 318 287 3700",
    "sg:postcode":"71043",
    "sg:province":"LA",
    "sg:tags":[
        "truck",
        "stop"
    ],
    "wof:name":"C J Truck Stop",
    "wof:placetype":"venue"
},
  "geometry": {"coordinates":[-93.878396,32.892093],"type":"Point"}
}