{
  "type": "Feature",
  "properties": {
    "addr:full":"5953 W Park Ave Houma LA 70364",
    "addr:housenumber":"5953",
    "addr:postcode":"70364",
    "addr:street":"W Park Ave",
    "iso:country":"US",
    "sg:address":"5953 W Park Ave",
    "sg:city":"Houma",
    "sg:classifiers":[
        {
            "category":"Food & Beverages",
            "subcategory":"Specialty",
            "type":"Retail Goods"
        }
    ],
    "sg:phone":"+1 985 851 3313",
    "sg:postcode":"70364",
    "sg:province":"LA",
    "sg:tags":[
        "health",
        "diet"
    ],
    "wof:name":"Smoothie King",
    "wof:placetype":"venue"
},
  "geometry": {"coordinates":[-90.76353,29.64989],"type":"Point"}
}