{
  "type": "Feature",
  "properties": {
    "iso:country":"US",
    "sg:address":"615 Veterans Memorial Dr",
    "sg:city":"Abbeville",
    "sg:classifiers":[
        {
            "category":"Government",
            "subcategory":"Office",
            "type":"Public Place"
        }
    ],
    "sg:phone":"+1 337 893 8550",
    "sg:postcode":"70510",
    "sg:province":"LA",
    "sg:tags":[
        "govt",
        "city"
    ],
    "wof:name":"Abbeville Water Treatment Plnt",
    "wof:placetype":"venue"
},
  "geometry": {"coordinates":[-92.14533400000001,29.984794],"type":"Point"}
}