{
  "type": "Feature",
  "properties": {
    "addr:full":"17901 Hwy 330 Abbeville LA 70510",
    "addr:housenumber":"17901",
    "addr:postcode":"70510",
    "addr:street":"Hwy 330",
    "iso:country":"US",
    "sg:address":"17901 Hwy 330",
    "sg:city":"Abbeville",
    "sg:classifiers":[
        {
            "category":"Social Services",
            "subcategory":"Child Care",
            "type":"Services"
        }
    ],
    "sg:phone":"+1 337 893 9978",
    "sg:postcode":"70510",
    "sg:province":"LA",
    "wof:name":"Kids First",
    "wof:placetype":"venue"
},
  "geometry": {"coordinates":[-92.100222,29.895463],"type":"Point"}
}