{
  "type": "Feature",
  "properties": {
    "addr:full":"329 N New Hampshire St Covington LA 70433",
    "addr:housenumber":"329",
    "addr:postcode":"70433",
    "addr:street":"N New Hampshire St",
    "iso:country":"US",
    "sg:address":"329 N New Hampshire St",
    "sg:city":"Covington",
    "sg:classifiers":[
        {
            "category":"Professional",
            "subcategory":"Lawyer & Legal Services",
            "type":"Services"
        }
    ],
    "sg:phone":"+1 985 892 0444",
    "sg:postcode":"70433",
    "sg:province":"LA",
    "wof:name":"Elizabeth Cannon",
    "wof:placetype":"venue"
},
  "geometry": {"coordinates":[-90.09576800000001,30.475767],"type":"Point"}
}