{
  "type": "Feature",
  "properties": {
    "addr:full":"8200 Willow St New Orleans LA 70118",
    "addr:housenumber":"8200",
    "addr:postcode":"70118",
    "addr:street":"Willow St",
    "iso:country":"US",
    "sg:address":"8200 Willow St",
    "sg:city":"New Orleans",
    "sg:classifiers":[
        {
            "category":"Bars & Pubs",
            "type":"Food & Drink"
        }
    ],
    "sg:phone":"+1 504 861 8200",
    "sg:postcode":"70118",
    "sg:province":"LA",
    "sg:tags":[
        "club",
        "night"
    ],
    "wof:name":"Jimmy's Club",
    "wof:placetype":"venue"
},
  "geometry": {"coordinates":[-90.130032,29.950186],"type":"Point"}
}