{
  "type": "Feature",
  "properties": {
    "addr:full":"4721 Loveland St Metairie LA 70006",
    "addr:housenumber":"4721",
    "addr:postcode":"70006",
    "addr:street":"Loveland St",
    "iso:country":"US",
    "sg:address":"4721 Loveland St",
    "sg:city":"Metairie",
    "sg:classifiers":[
        {
            "category":"Social Services",
            "type":"Services"
        }
    ],
    "sg:phone":"+1 504 455 6569",
    "sg:postcode":"70006",
    "sg:province":"LA",
    "sg:tags":[
        "counseling"
    ],
    "wof:name":"Lynn J Friedman",
    "wof:placetype":"venue"
},
  "geometry": {"coordinates":[-90.190956,30.009598],"type":"Point"}
}