{
  "type": "Feature",
  "properties": {
    "iso:country":"US",
    "sg:address":"4600 Cypress St",
    "sg:city":"West Monroe",
    "sg:classifiers":[
        {
            "category":"Wholesale",
            "subcategory":"Toys & Hobbies",
            "type":"Manufacturing & Wholesale Goods"
        }
    ],
    "sg:phone":"+1 318 396 8965",
    "sg:postcode":"71291",
    "sg:province":"LA",
    "sg:tags":[
        "firework"
    ],
    "wof:name":"Little Dixie Fireworks",
    "wof:placetype":"venue"
},
  "geometry": {"coordinates":[-92.176316,32.51407],"type":"Point"}
}