{
  "type": "Feature",
  "properties": {
    "iso:country":"US",
    "sg:address":"5700 Florida Blvd",
    "sg:city":"Baton Rouge",
    "sg:classifiers":[
        {
            "category":"Banks & Credit Unions",
            "subcategory":"Bank",
            "type":"Services"
        }
    ],
    "sg:phone":"+1 225 926 3233",
    "sg:postcode":"70806",
    "sg:province":"LA",
    "sg:tags":[
        "loan",
        "real estate"
    ],
    "wof:name":"All Fund Mortgage",
    "wof:placetype":"venue"
},
  "geometry": {"coordinates":[-91.131362,30.451157],"type":"Point"}
}