{
  "type": "Feature",
  "properties": {
    "iso:country":"US",
    "sg:address":"618 Ave C",
    "sg:city":"Port Allen",
    "sg:classifiers":[
        {
            "category":"Home & Garden",
            "subcategory":"Home Furnishings",
            "type":"Retail Goods"
        }
    ],
    "sg:phone":"+1 225 381 9287",
    "sg:postcode":"70767",
    "sg:province":"LA",
    "sg:tags":[
        "venetian",
        "blind"
    ],
    "wof:name":"ARE Custom Works",
    "wof:placetype":"venue"
},
  "geometry": {"coordinates":[-91.206129,30.449955],"type":"Point"}
}