{
  "type": "Feature",
  "properties": {
    "addr:full":"21341 Parish Line Rd Kinder LA 70648",
    "addr:housenumber":"21341",
    "addr:postcode":"70648",
    "addr:street":"Parish Line Rd",
    "iso:country":"US",
    "sg:address":"21341 Parish Line Rd",
    "sg:city":"Kinder",
    "sg:classifiers":[
        {
            "category":"Wholesale",
            "subcategory":"Construction Materials",
            "type":"Manufacturing & Wholesale Goods"
        }
    ],
    "sg:phone":"+1 337 738 5687",
    "sg:postcode":"70648",
    "sg:province":"LA",
    "sg:tags":[
        "sand",
        "gravel"
    ],
    "wof:name":"Trinity Materials Inc",
    "wof:placetype":"venue"
},
  "geometry": {"coordinates":[-92.97641,30.437836],"type":"Point"}
}