{
  "type": "Feature",
  "properties": {
    "addr:full":"146 Compactor Rd Buras LA 70041",
    "addr:housenumber":"146",
    "addr:postcode":"70041",
    "addr:street":"Compactor Rd",
    "iso:country":"US",
    "sg:address":"146 Compactor Rd",
    "sg:city":"Buras",
    "sg:classifiers":[
        {
            "category":"Manufacturing",
            "subcategory":"Tools & Machinery",
            "type":"Manufacturing & Wholesale Goods"
        }
    ],
    "sg:phone":"+1 985 534 7638",
    "sg:postcode":"70041",
    "sg:province":"LA",
    "sg:tags":[
        "compactors"
    ],
    "wof:name":"Fort Jackson Incinerator",
    "wof:placetype":"venue"
},
  "geometry": {"coordinates":[-89.441952,29.351725],"type":"Point"}
}