{
  "type": "Feature",
  "properties": {
    "iso:country":"US",
    "sg:address":"6412 Hwy 963",
    "sg:city":"Ethel",
    "sg:classifiers":[
        {
            "category":"Retail",
            "subcategory":"Auto Repair",
            "type":"Services"
        }
    ],
    "sg:phone":"+1 225 629 4735",
    "sg:postcode":"70730",
    "sg:province":"LA",
    "sg:tags":[
        "automotive"
    ],
    "wof:name":"McKnight Cylinder",
    "wof:placetype":"venue"
},
  "geometry": {"coordinates":[-91.14208000000001,30.870637],"type":"Point"}
}