{
  "type": "Feature",
  "properties": {
    "iso:country":"US",
    "sg:address":"30049 West Ave",
    "sg:city":"Lacombe",
    "sg:classifiers":[
        {
            "category":"Professional",
            "subcategory":"Computer Services",
            "type":"Services"
        }
    ],
    "sg:phone":"+1 985 882 7563",
    "sg:postcode":"70445",
    "sg:province":"LA",
    "sg:tags":[
        "programing",
        "custom"
    ],
    "wof:name":"Deh Office Software",
    "wof:placetype":"venue"
},
  "geometry": {"coordinates":[-89.902715,30.333387],"type":"Point"}
}