{
  "type": "Feature",
  "properties": {
    "addr:full":"8133 Plank Rd Baton Rouge LA 70811",
    "addr:housenumber":"8133",
    "addr:postcode":"70811",
    "addr:street":"Plank Rd",
    "iso:country":"US",
    "sg:address":"8133 Plank Rd",
    "sg:city":"Baton Rouge",
    "sg:classifiers":[
        {
            "category":"Food & Beverages",
            "subcategory":"Groceries & Convenience Stores",
            "type":"Retail Goods"
        }
    ],
    "sg:phone":"+1 225 357 5006",
    "sg:postcode":"70811",
    "sg:province":"LA",
    "wof:name":"Shell Food Mart",
    "wof:placetype":"venue"
},
  "geometry": {"coordinates":[-91.14498,30.522982],"type":"Point"}
}