{
  "type": "Feature",
  "properties": {
    "addr:full":"1293 N River Rd Denham Springs LA 70726",
    "addr:housenumber":"1293",
    "addr:postcode":"70726",
    "addr:street":"N River Rd",
    "iso:country":"US",
    "sg:address":"1293 N River Rd",
    "sg:city":"Denham Springs",
    "sg:classifiers":[
        {
            "category":"Real Estate",
            "subcategory":"Real Estate Operator",
            "type":"Services"
        }
    ],
    "sg:phone":"+1 225 791 2800",
    "sg:postcode":"70726",
    "sg:province":"LA",
    "sg:tags":[
        "apartment"
    ],
    "wof:name":"Bougainvilla Apartments",
    "wof:placetype":"venue"
},
  "geometry": {"coordinates":[-90.957756,30.501232],"type":"Point"}
}