{
  "type": "Feature",
  "properties": {
    "iso:country":"US",
    "sg:address":"400 SW Main St",
    "sg:city":"Bunkie",
    "sg:classifiers":[
        {
            "category":"Shopping",
            "subcategory":"Florist",
            "type":"Retail Goods"
        }
    ],
    "sg:phone":"+1 318 346 4614",
    "sg:postcode":"71322",
    "sg:province":"LA",
    "wof:name":"Jojo's Flowers",
    "wof:placetype":"venue"
},
  "geometry": {"coordinates":[-92.182481,30.952431],"type":"Point"}
}