{
  "type": "Feature",
  "properties": {
    "iso:country":"US",
    "sg:address":"314 County Line Rd",
    "sg:city":"Deridder",
    "sg:classifiers":[
        {
            "category":"Organizations",
            "subcategory":"Religious Organization",
            "type":"Services"
        }
    ],
    "sg:phone":"+1 337 463 6713",
    "sg:postcode":"70634",
    "sg:province":"LA",
    "wof:name":"Bible Missionary Camp Grounds",
    "wof:placetype":"venue"
},
  "geometry": {"coordinates":[-93.293505,30.885392],"type":"Point"}
}