{
  "type": "Feature",
  "properties": {
    "iso:country":"US",
    "sg:address":"5414 Brittany Dr",
    "sg:city":"Baton Rouge",
    "sg:classifiers":[
        {
            "category":"Health Services",
            "subcategory":"Health Practitioner",
            "type":"Services"
        }
    ],
    "sg:phone":"+1 225 231 3810",
    "sg:postcode":"70808",
    "sg:province":"LA",
    "sg:tags":[
        "therapist",
        "physical"
    ],
    "sg:website":"www.brptlake.com",
    "wof:name":"BRPT Lake",
    "wof:placetype":"venue"
},
  "geometry": {"coordinates":[-91.10897300000001,30.402216],"type":"Point"}
}