{
  "type": "Feature",
  "properties": {
    "addr:full":"3717 Maplewood Dr Sulphur LA 70663",
    "addr:housenumber":"3717",
    "addr:postcode":"70663",
    "addr:street":"Maplewood Dr",
    "iso:country":"US",
    "sg:address":"3717 Maplewood Dr",
    "sg:city":"Sulphur",
    "sg:classifiers":[
        {
            "category":"Freight",
            "type":"Transportation"
        }
    ],
    "sg:phone":"+1 337 626 0757",
    "sg:postcode":"70663",
    "sg:province":"LA",
    "sg:tags":[
        "car",
        "railroad",
        "leasing"
    ],
    "wof:name":"GATX Rail",
    "wof:placetype":"venue"
},
  "geometry": {"coordinates":[-93.333682,30.227489],"type":"Point"}
}