{
  "type": "Feature",
  "properties": {
    "addr:full":"2023 NW Evangeline Trwy Lafayette LA 70501",
    "addr:housenumber":"2023",
    "addr:postcode":"70501",
    "addr:street":"Nw Evangeline",
    "iso:country":"US",
    "sg:address":"2023 NW Evangeline Trwy",
    "sg:city":"Lafayette",
    "sg:classifiers":[
        {
            "category":"Personal",
            "subcategory":"Nail Salon",
            "type":"Services"
        }
    ],
    "sg:phone":"+1 337 233 9392",
    "sg:postcode":"70501",
    "sg:province":"LA",
    "wof:name":"V V Nails",
    "wof:placetype":"venue"
},
  "geometry": {"coordinates":[-92.014,30.251301],"type":"Point"}
}