{
  "type": "Feature",
  "properties": {
    "iso:country":"US",
    "sg:address":"1027 N 6th St",
    "sg:city":"Monroe",
    "sg:classifiers":[
        {
            "category":"Professional",
            "type":"Services"
        }
    ],
    "sg:phone":"+1 318 325 8869",
    "sg:postcode":"71201",
    "sg:province":"LA",
    "sg:tags":[
        "establishment"
    ],
    "wof:name":"Dyess & Assoc",
    "wof:placetype":"venue"
},
  "geometry": {"coordinates":[-92.119806,32.512855],"type":"Point"}
}