{
  "type": "Feature",
  "properties": {
    "addr:full":"14879 W Main St Cut Off LA 70345",
    "addr:housenumber":"14879",
    "addr:postcode":"70345",
    "addr:street":"W Main St Cut Off",
    "iso:country":"US",
    "sg:address":"14879 W Main St",
    "sg:city":"Cut Off",
    "sg:classifiers":[
        {
            "category":"Recreation",
            "type":"Entertainment"
        }
    ],
    "sg:phone":"+1 985 632 6633",
    "sg:postcode":"70345",
    "sg:province":"LA",
    "sg:tags":[
        "charter",
        "boat"
    ],
    "wof:name":"Guilbeau Marine Inc",
    "wof:placetype":"venue"
},
  "geometry": {"coordinates":[-90.335717,29.52645],"type":"Point"}
}