{
  "type": "Feature",
  "properties": {
    "addr:full":"209 W Thomas St Hammond LA 70401",
    "addr:housenumber":"209",
    "addr:postcode":"70401",
    "addr:street":"W Thomas St",
    "iso:country":"US",
    "sg:address":"209 W Thomas St",
    "sg:city":"Hammond",
    "sg:classifiers":[
        {
            "category":"Banks & Credit Unions",
            "subcategory":"Financial Services",
            "type":"Services"
        }
    ],
    "sg:phone":"+1 985 345 0627",
    "sg:postcode":"70401",
    "sg:province":"LA",
    "sg:tags":[
        "investor"
    ],
    "wof:name":"Kropog Investments LLC",
    "wof:placetype":"venue"
},
  "geometry": {"coordinates":[-90.4624,30.503694],"type":"Point"}
}