{
  "type": "Feature",
  "properties": {
    "iso:country":"US",
    "sg:address":"207 Lake Rd",
    "sg:city":"Heflin",
    "sg:classifiers":[
        {
            "category":"Farming",
            "subcategory":"Orchard",
            "type":"Manufacturing & Wholesale Goods"
        }
    ],
    "sg:phone":"+1 318 371 9349",
    "sg:postcode":"71073",
    "sg:province":"LA",
    "sg:tags":[
        "grove",
        "management"
    ],
    "wof:name":"Willamette Seed Orchard",
    "wof:placetype":"venue"
},
  "geometry": {"coordinates":[-93.300071,32.47703],"type":"Point"}
}