{
  "type": "Feature",
  "properties": {
    "iso:country":"US",
    "sg:address":"1200 N Peters St",
    "sg:city":"New Orleans",
    "sg:classifiers":[
        {
            "category":"Shopping",
            "subcategory":"Jewelry",
            "type":"Retail Goods"
        }
    ],
    "sg:phone":"+1 504 523 0647",
    "sg:postcode":"70116",
    "sg:province":"LA",
    "sg:tags":[
        "jeweler"
    ],
    "wof:name":"Hesam Unlimited",
    "wof:placetype":"venue"
},
  "geometry": {"coordinates":[-90.05763899999999,29.960779],"type":"Point"}
}