{
  "type": "Feature",
  "properties": {
    "iso:country":"US",
    "sg:address":"4740 Rye St",
    "sg:city":"Metairie",
    "sg:classifiers":[
        {
            "category":"Bars & Pubs",
            "type":"Food & Drink"
        }
    ],
    "sg:phone":"+1 504 885 6563",
    "sg:postcode":"70006",
    "sg:province":"LA",
    "sg:tags":[
        "lounge",
        "cocktail"
    ],
    "wof:name":"Jabba Jaws Bar & Bites",
    "wof:placetype":"venue"
},
  "geometry": {"coordinates":[-90.188956,30.003222],"type":"Point"}
}