{
  "type": "Feature",
  "properties": {
    "addr:full":"885 Poleman Rd Shreveport LA 71107",
    "addr:housenumber":"885",
    "addr:postcode":"71107",
    "addr:street":"Poleman Rd",
    "iso:country":"US",
    "sg:address":"885 Poleman Rd",
    "sg:city":"Shreveport",
    "sg:classifiers":[
        {
            "category":"Education",
            "subcategory":"School",
            "type":"Public Place"
        }
    ],
    "sg:phone":"+1 318 221 6346",
    "sg:postcode":"71107",
    "sg:province":"LA",
    "sg:tags":[
        "elementary",
        "high"
    ],
    "sg:website":"http://www.northhighlandselementary.com",
    "wof:name":"North Highlands Elementary School",
    "wof:placetype":"venue"
},
  "geometry": {"coordinates":[-93.782669,32.573219],"type":"Point"}
}