{
  "type": "Feature",
  "properties": {
    "iso:country":"US",
    "sg:address":"5620 Johnston St",
    "sg:city":"Lafayette",
    "sg:classifiers":[
        {
            "category":"Government",
            "subcategory":"Police Station",
            "type":"Public Place"
        }
    ],
    "sg:phone":"+1 337 983 0923",
    "sg:postcode":"70503",
    "sg:province":"LA",
    "sg:tags":[
        "department"
    ],
    "wof:name":"Police Sub Station South",
    "wof:placetype":"venue"
},
  "geometry": {"coordinates":[-92.075109,30.177644],"type":"Point"}
}