{
  "type": "Feature",
  "properties": {
    "iso:country":"US",
    "sg:address":"341 Berkshire Pl",
    "sg:city":"Shreveport",
    "sg:classifiers":[
        {
            "category":"Professional",
            "subcategory":"Management & Consulting",
            "type":"Services"
        }
    ],
    "sg:phone":"+1 318 869 2963",
    "sg:postcode":"71106",
    "sg:province":"LA",
    "sg:tags":[
        "business"
    ],
    "wof:name":"Key Consulting",
    "wof:placetype":"venue"
},
  "geometry": {"coordinates":[-93.736133,32.44761],"type":"Point"}
}