{
  "type": "Feature",
  "properties": {
    "iso:country":"US",
    "sg:address":"1906 Johnson St",
    "sg:city":"Jennings",
    "sg:classifiers":[
        {
            "category":"Health Services",
            "subcategory":"Clinic",
            "type":"Services"
        }
    ],
    "sg:phone":"+1 337 824 5353",
    "sg:postcode":"70546",
    "sg:province":"LA",
    "sg:tags":[
        "kidney",
        "dialysis",
        "center"
    ],
    "wof:name":"Jennings Dialysis Center",
    "wof:placetype":"venue"
},
  "geometry": {"coordinates":[-92.66128,30.239129],"type":"Point"}
}