{
  "type": "Feature",
  "properties": {
    "addr:full":"830 Desoto St Alexandria LA 71301",
    "addr:housenumber":"830",
    "addr:postcode":"71301",
    "addr:street":"Desoto St",
    "iso:country":"US",
    "sg:address":"830 Desoto St",
    "sg:city":"Alexandria",
    "sg:classifiers":[
        {
            "category":"Health Services",
            "subcategory":"Hospital",
            "type":"Services"
        }
    ],
    "sg:phone":"+1 318 487 5611",
    "sg:postcode":"71301",
    "sg:province":"LA",
    "sg:tags":[
        "mental"
    ],
    "wof:name":"Alexandria Mental Health Cntr",
    "wof:placetype":"venue"
},
  "geometry": {"coordinates":[-92.44877099999999,31.308922],"type":"Point"}
}