{
  "type": "Feature",
  "properties": {
    "iso:country":"US",
    "sg:address":"1101 Bertrand Dr",
    "sg:city":"Lafayette",
    "sg:classifiers":[
        {
            "category":"Education",
            "subcategory":"Special Training",
            "type":"Public Place"
        }
    ],
    "sg:phone":"+1 337 237 7985",
    "sg:postcode":"70506",
    "sg:province":"LA",
    "sg:tags":[
        "instruction",
        "driving"
    ],
    "wof:name":"Diesel Driving Academy Inc",
    "wof:placetype":"venue"
},
  "geometry": {"coordinates":[-92.049302,30.218289],"type":"Point"}
}