{
  "type": "Feature",
  "properties": {
    "addr:full":"100 Rex Dr New Orleans LA 70123",
    "addr:housenumber":"100",
    "addr:postcode":"70123",
    "addr:street":"Rex Dr",
    "iso:country":"US",
    "sg:address":"100 Rex Dr",
    "sg:city":"New Orleans",
    "sg:classifiers":[
        {
            "category":"Organizations",
            "subcategory":"Religious Organization",
            "type":"Services"
        }
    ],
    "sg:phone":"+1 504 737 2421",
    "sg:postcode":"70123",
    "sg:province":"LA",
    "sg:tags":[
        "church"
    ],
    "sg:website":"www.allsaintsneworleans.org",
    "wof:name":"All Saints Episcopal Church",
    "wof:placetype":"venue"
},
  "geometry": {"coordinates":[-90.21590399999999,29.946013],"type":"Point"}
}