{
  "type": "Feature",
  "properties": {
    "iso:country":"US",
    "sg:address":"1126 Montana St",
    "sg:city":"Sulphur",
    "sg:classifiers":[
        {
            "category":"Wholesale",
            "subcategory":"Machinery & Supplies",
            "type":"Manufacturing & Wholesale Goods"
        }
    ],
    "sg:phone":"+1 337 528 8050",
    "sg:postcode":"70665",
    "sg:province":"LA",
    "sg:tags":[
        "equipment",
        "laundry"
    ],
    "wof:name":"Thomas Winkles Sales & Svc Inc",
    "wof:placetype":"venue"
},
  "geometry": {"coordinates":[-93.366653,30.208143],"type":"Point"}
}