{
  "type": "Feature",
  "properties": {
    "iso:country":"US",
    "sg:address":"1250 Stakes Rd",
    "sg:city":"Crowley",
    "sg:phone":"+1 337 783 4797",
    "sg:postcode":"70526",
    "sg:province":"LA",
    "sg:tags":[
        "farm",
        "rice",
        "soybean"
    ],
    "wof:name":"Dennis Leonards",
    "wof:placetype":"venue"
},
  "geometry": {"coordinates":[-92.427267,30.281628],"type":"Point"}
}