{
  "type": "Feature",
  "properties": {
    "iso:country":"US",
    "sg:address":"151 Martin Luther King Blvd",
    "sg:city":"Ferriday",
    "sg:classifiers":[
        {
            "category":"Education",
            "subcategory":"School",
            "type":"Public Place"
        }
    ],
    "sg:phone":"+1 318 757 3105",
    "sg:postcode":"71334",
    "sg:province":"LA",
    "wof:name":"Ferriday Upper Elementary Schl",
    "wof:placetype":"venue"
},
  "geometry": {"coordinates":[-91.561071,31.622499],"type":"Point"}
}