{
  "type": "Feature",
  "properties": {
    "addr:full":"2011 Centenary Blvd Shreveport LA 71104",
    "addr:housenumber":"2011",
    "addr:postcode":"71104",
    "addr:street":"Centenary Blvd",
    "iso:country":"US",
    "sg:address":"2011 Centenary Blvd",
    "sg:city":"Shreveport",
    "sg:classifiers":[
        {
            "category":"Utilities",
            "subcategory":"Natural Gas",
            "type":"Services"
        }
    ],
    "sg:phone":"+1 318 424 2471",
    "sg:postcode":"71104",
    "sg:province":"LA",
    "wof:name":"Taylor Gas Liquid",
    "wof:placetype":"venue"
},
  "geometry": {"coordinates":[-93.733056,32.491762],"type":"Point"}
}