{
  "type": "Feature",
  "properties": {
    "addr:full":"3735 Blair Dr Shreveport LA 71103",
    "addr:housenumber":"3735",
    "addr:postcode":"71103",
    "addr:street":"Blair Dr",
    "iso:country":"US",
    "sg:address":"3735 Blair Dr",
    "sg:city":"Shreveport",
    "sg:classifiers":[
        {
            "category":"Health Services",
            "subcategory":"Health Practitioner",
            "type":"Services"
        }
    ],
    "sg:phone":"+1 318 632 2015",
    "sg:postcode":"71103",
    "sg:province":"LA",
    "sg:tags":[
        "pathologist",
        "speech"
    ],
    "wof:name":"Mollie E WEBB Speech & Hearing",
    "wof:placetype":"venue"
},
  "geometry": {"coordinates":[-93.76638,32.474926],"type":"Point"}
}