{
  "type": "Feature",
  "properties": {
    "iso:country":"US",
    "sg:address":"2825 SE Evangeline Throughway",
    "sg:city":"Lafayette",
    "sg:classifiers":[
        {
            "category":"Building & Trades",
            "subcategory":"Equipment Rental",
            "type":"Services"
        }
    ],
    "sg:phone":"+1 337 234 7990",
    "sg:postcode":"70508",
    "sg:province":"LA",
    "sg:tags":[
        "oil",
        "well",
        "supply"
    ],
    "sg:website":"www.trendservicesinc.com",
    "wof:name":"Trend Services Inc",
    "wof:placetype":"venue"
},
  "geometry": {"coordinates":[-91.985015,30.17731],"type":"Point"}
}