{
  "type": "Feature",
  "properties": {
    "iso:country":"US",
    "sg:address":"736 Ave D",
    "sg:city":"Marrero",
    "sg:classifiers":[
        {
            "category":"Professional",
            "type":"Services"
        }
    ],
    "sg:phone":"+1 504 347 5079",
    "sg:postcode":"70072",
    "sg:province":"LA",
    "sg:tags":[
        "establishment"
    ],
    "wof:name":"Joseph Cemo Enterprises",
    "wof:placetype":"venue"
},
  "geometry": {"coordinates":[-90.096723,29.897848],"type":"Point"}
}