{
  "type": "Feature",
  "properties": {
    "iso:country":"US",
    "sg:address":"220 Iberia St",
    "sg:city":"New Iberia",
    "sg:classifiers":[
        {
            "category":"Shopping",
            "type":"Retail Goods"
        }
    ],
    "sg:phone":"+1 337 276 5151",
    "sg:postcode":"70560",
    "sg:province":"LA",
    "sg:tags":[
        "monument"
    ],
    "wof:name":"David Marble & Granite",
    "wof:placetype":"venue"
},
  "geometry": {"coordinates":[-91.819902,30.004902],"type":"Point"}
}