{
  "type": "Feature",
  "properties": {
    "addr:full":"603 Prevost St Rayne LA 70578",
    "addr:housenumber":"603",
    "addr:postcode":"70578",
    "addr:street":"Prevost St",
    "iso:country":"US",
    "sg:address":"603 Prevost St",
    "sg:city":"Rayne",
    "sg:classifiers":[
        {
            "category":"Freight",
            "type":"Transportation"
        }
    ],
    "sg:phone":"+1 337 334 5874",
    "sg:postcode":"70578",
    "sg:province":"LA",
    "sg:tags":[
        "building",
        "house",
        "mover"
    ],
    "wof:name":"Wingate House Moving & Levelng",
    "wof:placetype":"venue"
},
  "geometry": {"coordinates":[-92.27328199999999,30.224268],"type":"Point"}
}