{
  "type": "Feature",
  "properties": {
    "addr:full":"701 David Dr Metairie LA 70003",
    "addr:housenumber":"701",
    "addr:postcode":"70003",
    "addr:street":"David Dr",
    "iso:country":"US",
    "sg:address":"701 David Dr",
    "sg:city":"Metairie",
    "sg:classifiers":[
        {
            "category":"Professional",
            "subcategory":"Business Services",
            "type":"Services"
        }
    ],
    "sg:phone":"+1 504 736 0092",
    "sg:postcode":"70003",
    "sg:province":"LA",
    "sg:tags":[
        "embroidery"
    ],
    "wof:name":"One Stop Embroidery Shop",
    "wof:placetype":"venue"
},
  "geometry": {"coordinates":[-90.21219000000001,29.982014],"type":"Point"}
}