{
  "type": "Feature",
  "properties": {
    "addr:full":"400 E School St Lake Charles LA 70605",
    "addr:housenumber":"400",
    "addr:postcode":"70605",
    "addr:street":"E School St",
    "iso:country":"US",
    "sg:address":"400 E School St",
    "sg:city":"Lake Charles",
    "sg:classifiers":[
        {
            "category":"Social Services",
            "subcategory":"Child Care",
            "type":"Services"
        }
    ],
    "sg:phone":"+1 337 477 0674",
    "sg:postcode":"70605",
    "sg:province":"LA",
    "wof:name":"Hart's Child Care",
    "wof:placetype":"venue"
},
  "geometry": {"coordinates":[-93.214229,30.190563],"type":"Point"}
}