{
  "type": "Feature",
  "properties": {
    "addr:full":"1718 Broad St Lake Charles LA 70601",
    "addr:housenumber":"1718",
    "addr:postcode":"70601",
    "addr:street":"Broad St",
    "iso:country":"US",
    "sg:address":"1718 Broad St",
    "sg:city":"Lake Charles",
    "sg:classifiers":[
        {
            "category":"Professional",
            "subcategory":"Business Services",
            "type":"Services"
        }
    ],
    "sg:phone":"+1 337 497 1897",
    "sg:postcode":"70601",
    "sg:province":"LA",
    "sg:tags":[
        "paging",
        "signaling"
    ],
    "wof:name":"Chad's Phone & Pager",
    "wof:placetype":"venue"
},
  "geometry": {"coordinates":[-93.196291,30.227453],"type":"Point"}
}