{
  "type": "Feature",
  "properties": {
    "addr:full":"209 E Alabama Ave Ruston LA 71270",
    "addr:housenumber":"209",
    "addr:postcode":"71270",
    "addr:street":"E Alabama Ave",
    "iso:country":"US",
    "sg:address":"209 E Alabama Ave",
    "sg:city":"Ruston",
    "sg:classifiers":[
        {
            "category":"Professional",
            "subcategory":"Lawyer & Legal Services",
            "type":"Services"
        }
    ],
    "sg:phone":"+1 318 251 0701",
    "sg:postcode":"71270",
    "sg:province":"LA",
    "sg:tags":[
        "attorney"
    ],
    "wof:name":"Culpepper & Carroll",
    "wof:placetype":"venue"
},
  "geometry": {"coordinates":[-92.636652,32.530422],"type":"Point"}
}