{
  "type": "Feature",
  "properties": {
    "addr:full":"255 Sheppard St Minden LA 71055",
    "addr:housenumber":"255",
    "addr:postcode":"71055",
    "addr:street":"Sheppard St",
    "iso:country":"US",
    "sg:address":"255 Sheppard St",
    "sg:city":"Minden",
    "sg:classifiers":[
        {
            "category":"Wholesale",
            "subcategory":"Tobacco Products",
            "type":"Manufacturing & Wholesale Goods"
        }
    ],
    "sg:phone":"+1 318 377 5951",
    "sg:postcode":"71055",
    "sg:province":"LA",
    "sg:tags":[
        "cigarette",
        "cigar",
        "dealer"
    ],
    "wof:name":"Maximum Discount Tobacco",
    "wof:placetype":"venue"
},
  "geometry": {"coordinates":[-93.285887,32.612431],"type":"Point"}
}