{
  "type": "Feature",
  "properties": {
    "iso:country":"US",
    "sg:address":"121 11th St",
    "sg:city":"Morgan City",
    "sg:classifiers":[
        {
            "category":"Communications",
            "subcategory":"Film & Video Production",
            "type":"Services"
        }
    ],
    "sg:phone":"+1 985 385 2862",
    "sg:postcode":"70380",
    "sg:province":"LA",
    "sg:tags":[
        "taping"
    ],
    "wof:name":"Kingdom Of God Productions",
    "wof:placetype":"venue"
},
  "geometry": {"coordinates":[-91.19273099999999,29.694967],"type":"Point"}
}