{
  "type": "Feature",
  "properties": {
    "addr:full":"724 N Thompson St Ville Platte LA 70586",
    "addr:housenumber":"724",
    "addr:postcode":"70586",
    "addr:street":"N Thompson St",
    "iso:country":"US",
    "sg:address":"724 N Thompson St",
    "sg:city":"Ville Platte",
    "sg:classifiers":[
        {
            "category":"Real Estate",
            "subcategory":"Real Estate Agent",
            "type":"Services"
        }
    ],
    "sg:phone":"+1 337 363 2535",
    "sg:postcode":"70586",
    "sg:province":"LA",
    "sg:tags":[
        "authorities",
        "housing"
    ],
    "wof:name":"Ville Platte Housing Authority",
    "wof:placetype":"venue"
},
  "geometry": {"coordinates":[-92.281584,30.69817],"type":"Point"}
}