{
  "type": "Feature",
  "properties": {
    "iso:country":"US",
    "sg:address":"851 Kleber St",
    "sg:city":"Mandeville",
    "sg:classifiers":[
        {
            "category":"Organizations",
            "subcategory":"Religious Organization",
            "type":"Services"
        }
    ],
    "sg:phone":"+1 985 624 5077",
    "sg:postcode":"70448",
    "sg:province":"LA",
    "sg:tags":[
        "church"
    ],
    "wof:name":"Mt Zion Missionary Baptist",
    "wof:placetype":"venue"
},
  "geometry": {"coordinates":[-90.081475,30.372765],"type":"Point"}
}