{
  "type": "Feature",
  "properties": {
    "addr:full":"200 N Main St Springhill LA 71075",
    "addr:housenumber":"200",
    "addr:postcode":"71075",
    "addr:street":"N Main St",
    "iso:country":"US",
    "sg:address":"200 N Main St",
    "sg:city":"Springhill",
    "sg:classifiers":[
        {
            "category":"Shopping",
            "subcategory":"Department Store",
            "type":"Retail Goods"
        },
        {
            "category":"Shopping",
            "subcategory":"Clothing, Apparel, & Fashions",
            "type":"Retail Goods"
        }
    ],
    "sg:phone":"+1 318 539 9713",
    "sg:postcode":"71075",
    "sg:province":"LA",
    "sg:tags":[
        "clothing"
    ],
    "wof:name":"Sharpes Dept Store",
    "wof:placetype":"venue"
},
  "geometry": {"coordinates":[-93.461258,33.003609],"type":"Point"}
}