{
  "type": "Feature",
  "properties": {
    "iso:country":"US",
    "sg:address":"423 Main St",
    "sg:city":"Baton Rouge",
    "sg:classifiers":[
        {
            "category":"Social Services",
            "type":"Services"
        }
    ],
    "sg:phone":"+1 225 343 7364",
    "sg:postcode":"70801",
    "sg:province":"LA",
    "sg:tags":[
        "organization",
        "welfare"
    ],
    "wof:name":"Downtown Christian Outreach",
    "wof:placetype":"venue"
},
  "geometry": {"coordinates":[-91.186201,30.451561],"type":"Point"}
}