{
  "type": "Feature",
  "properties": {
    "iso:country":"US",
    "sg:address":"189 Haddox Rd",
    "sg:city":"Ruston",
    "sg:classifiers":[
        {
            "category":"Wholesale",
            "subcategory":"Construction Materials",
            "type":"Manufacturing & Wholesale Goods"
        }
    ],
    "sg:phone":"+1 318 255 5412",
    "sg:postcode":"71270",
    "sg:province":"LA",
    "sg:tags":[
        "lumber"
    ],
    "sg:website":"www.hoganhardwoods.com",
    "wof:name":"Hogan Hardwoods & Laminate",
    "wof:placetype":"venue"
},
  "geometry": {"coordinates":[-92.603101,32.561885],"type":"Point"}
}