{
  "type": "Feature",
  "properties": {
    "addr:full":"621 Entrance Rd Leesville LA 71446",
    "addr:housenumber":"621",
    "addr:postcode":"71446",
    "addr:street":"Entrance Rd",
    "iso:country":"US",
    "sg:address":"621 Entrance Rd",
    "sg:city":"Leesville",
    "sg:classifiers":[
        {
            "category":"Restaurant",
            "type":"Food & Drink"
        }
    ],
    "sg:menulink":"http://www.allmenus.com/la/rosepine/132092-subway/menu/",
    "sg:phone":"+1 337 537 8100",
    "sg:postcode":"71446",
    "sg:province":"LA",
    "sg:tags":[
        "american",
        "sandwich"
    ],
    "wof:name":"Subway",
    "wof:placetype":"venue"
},
  "geometry": {"coordinates":[-93.264707,31.060809],"type":"Point"}
}