{
  "type": "Feature",
  "properties": {
    "addr:full":"6950 Bundy Rd New Orleans LA 70127",
    "addr:housenumber":"6950",
    "addr:postcode":"70127",
    "addr:street":"Bundy Rd",
    "iso:country":"US",
    "sg:address":"6950 Bundy Rd",
    "sg:city":"New Orleans",
    "sg:classifiers":[
        {
            "category":"Professional",
            "subcategory":"Management & Consulting",
            "type":"Services"
        }
    ],
    "sg:phone":"+1 504 242 9970",
    "sg:postcode":"70127",
    "sg:province":"LA",
    "sg:tags":[
        "party",
        "planning"
    ],
    "wof:name":"Party Plus Characters",
    "wof:placetype":"venue"
},
  "geometry": {"coordinates":[-89.986339,30.034716],"type":"Point"}
}