{
  "type": "Feature",
  "properties": {
    "iso:country":"US",
    "sg:address":"7861 Hooper Rd",
    "sg:city":"Baton Rouge",
    "sg:classifiers":[
        {
            "category":"Shopping",
            "subcategory":"Clothing, Apparel, & Fashions",
            "type":"Retail Goods"
        }
    ],
    "sg:phone":"+1 225 774 2121",
    "sg:postcode":"70811",
    "sg:province":"LA",
    "sg:tags":[
        "alteration"
    ],
    "wof:name":"Silver Needle Tailoring",
    "wof:placetype":"venue"
},
  "geometry": {"coordinates":[-91.108721,30.529255],"type":"Point"}
}