{
  "type": "Feature",
  "properties": {
    "addr:full":"1605 E Airline Hwy La Place LA 70068",
    "addr:housenumber":"1605",
    "addr:postcode":"70068",
    "addr:street":"E Airline Hwy La Place",
    "iso:country":"US",
    "sg:address":"1605 E Airline Hwy",
    "sg:city":"La Place",
    "sg:classifiers":[
        {
            "category":"Autos & Motor Vehicles",
            "subcategory":"Auto Supplies",
            "type":"Retail Goods"
        }
    ],
    "sg:phone":"+1 985 652 6397",
    "sg:postcode":"70068",
    "sg:province":"LA",
    "sg:tags":[
        "tire"
    ],
    "wof:name":"Firestone Tire & Svc Ctr",
    "wof:placetype":"venue"
},
  "geometry": {"coordinates":[-90.442075,30.041506],"type":"Point"}
}