{
  "type": "Feature",
  "properties": {
    "addr:full":"116 Benton Spr Bossier City LA 71111",
    "addr:housenumber":"116",
    "addr:postcode":"71111",
    "addr:street":"Benton Spr",
    "iso:country":"US",
    "sg:address":"116 Benton Spr",
    "sg:city":"Bossier City",
    "sg:classifiers":[
        {
            "category":"Restaurant",
            "type":"Food & Drink"
        }
    ],
    "sg:phone":"+1 318 747 3589",
    "sg:postcode":"71111",
    "sg:province":"LA",
    "wof:name":"Subway Sandwiches & Salads",
    "wof:placetype":"venue"
},
  "geometry": {"coordinates":[-93.715159,32.517871],"type":"Point"}
}