{
  "type": "Feature",
  "properties": {
    "addr:full":"810 State Rte 30 Gonzales LA 70737",
    "addr:housenumber":"810",
    "addr:postcode":"70737",
    "addr:street":"State Rte 30 Gonzales La",
    "iso:country":"US",
    "sg:address":"810 State Rte 30",
    "sg:city":"Gonzales",
    "sg:classifiers":[
        {
            "category":"Utilities",
            "subcategory":"Mobile Phone",
            "type":"Services"
        }
    ],
    "sg:phone":"+1 225 644 8662",
    "sg:postcode":"70737",
    "sg:province":"LA",
    "sg:tags":[
        "telephone",
        "cellular"
    ],
    "wof:name":"Planet Wireless",
    "wof:placetype":"venue"
},
  "geometry": {"coordinates":[-90.927853,30.210939],"type":"Point"}
}