{
  "type": "Feature",
  "properties": {
    "iso:country":"US",
    "sg:address":"7934 Maple St",
    "sg:city":"New Orleans",
    "sg:classifiers":[
        {
            "category":"Real Estate",
            "subcategory":"Real Estate Agent",
            "type":"Services"
        }
    ],
    "sg:phone":"+1 504 861 7575",
    "sg:postcode":"70118",
    "sg:province":"LA",
    "wof:name":"Prudential Gardner Realtors",
    "wof:placetype":"venue"
},
  "geometry": {"coordinates":[-90.13163400000001,29.943504],"type":"Point"}
}