{
  "type": "Feature",
  "properties": {
    "iso:country":"US",
    "sg:address":"8275 Main St",
    "sg:city":"Sorrento",
    "sg:classifiers":[
        {
            "category":"Organizations",
            "subcategory":"Religious Organization",
            "type":"Services"
        }
    ],
    "sg:phone":"+1 225 675 5318",
    "sg:postcode":"70778",
    "sg:province":"LA",
    "sg:tags":[
        "church"
    ],
    "wof:name":"Sorrento Baptist Church",
    "wof:placetype":"venue"
},
  "geometry": {"coordinates":[-90.856219,30.18948],"type":"Point"}
}