{
  "type": "Feature",
  "properties": {
    "iso:country":"US",
    "sg:address":"344 Julia St",
    "sg:city":"Natchitoches",
    "sg:classifiers":[
        {
            "category":"Professional",
            "type":"Services"
        }
    ],
    "sg:phone":"+1 318 239 9967",
    "sg:postcode":"71457",
    "sg:province":"LA",
    "sg:tags":[
        "establishment"
    ],
    "wof:name":"Vernon Parish Landfill",
    "wof:placetype":"venue"
},
  "geometry": {"coordinates":[-93.10463900000001,31.758761],"type":"Point"}
}