{
  "type": "Feature",
  "properties": {
    "iso:country":"US",
    "sg:address":"3221 Mc Connell Dr",
    "sg:city":"Baton Rouge",
    "sg:classifiers":[
        {
            "category":"Building & Trades",
            "subcategory":"Construction",
            "type":"Services"
        }
    ],
    "sg:phone":"+1 225 923 3753",
    "sg:postcode":"70809",
    "sg:province":"LA",
    "sg:tags":[
        "resurfacing",
        "laying",
        "refinishing",
        "floor"
    ],
    "wof:name":"Dirk Burton Floors",
    "wof:placetype":"venue"
},
  "geometry": {"coordinates":[-91.11246,30.423846],"type":"Point"}
}