{
  "type": "Feature",
  "properties": {
    "iso:country":"US",
    "sg:address":"1909 Cooper Lake Rd",
    "sg:city":"Bastrop",
    "sg:classifiers":[
        {
            "category":"Health Services",
            "subcategory":"Health Practitioner",
            "type":"Services"
        }
    ],
    "sg:phone":"+1 318 345 5600",
    "sg:postcode":"71220",
    "sg:province":"LA",
    "sg:tags":[
        "home"
    ],
    "wof:name":"Universal Care Llc & Logo 5 Ha",
    "wof:placetype":"venue"
},
  "geometry": {"coordinates":[-91.869045,32.794224],"type":"Point"}
}