{
  "type": "Feature",
  "properties": {
    "iso:country":"US",
    "sg:address":"2919 Wytchwood Dr",
    "sg:city":"Metairie",
    "sg:classifiers":[
        {
            "category":"Wholesale",
            "subcategory":"Vending Machines",
            "type":"Manufacturing & Wholesale Goods"
        }
    ],
    "sg:phone":"+1 504 887 8133",
    "sg:postcode":"70003",
    "sg:province":"LA",
    "wof:name":"Mire's Vending",
    "wof:placetype":"venue"
},
  "geometry": {"coordinates":[-90.213767,30.003161],"type":"Point"}
}