{
  "type": "Feature",
  "properties": {
    "iso:country":"US",
    "sg:address":"1934 Scenic Hwy",
    "sg:city":"Baton Rouge",
    "sg:classifiers":[
        {
            "category":"Organizations",
            "subcategory":"Religious Organization",
            "type":"Services"
        }
    ],
    "sg:phone":"+1 225 358 4442",
    "sg:postcode":"70802",
    "sg:province":"LA",
    "sg:tags":[
        "church"
    ],
    "wof:name":"Newcreation Word Of Faith",
    "wof:placetype":"venue"
},
  "geometry": {"coordinates":[-91.16784199999999,30.465408],"type":"Point"}
}