{
  "type": "Feature",
  "properties": {
    "iso:country":"US",
    "sg:address":"201 Center St",
    "sg:city":"New Iberia",
    "sg:classifiers":[
        {
            "category":"Wholesale",
            "subcategory":"Chemicals & Plastics",
            "type":"Manufacturing & Wholesale Goods"
        }
    ],
    "sg:phone":"+1 337 364 4191",
    "sg:postcode":"70560",
    "sg:province":"LA",
    "wof:name":"Ther Chem Corp",
    "wof:placetype":"venue"
},
  "geometry": {"coordinates":[-91.81694299999999,30.002584],"type":"Point"}
}