{
  "type": "Feature",
  "properties": {
    "addr:full":"6448 Smithfield Rd Port Allen LA 70767",
    "addr:housenumber":"6448",
    "addr:postcode":"70767",
    "addr:street":"Smithfield Rd",
    "iso:country":"US",
    "sg:address":"6448 Smithfield Rd",
    "sg:city":"Port Allen",
    "sg:classifiers":[
        {
            "category":"Building & Trades",
            "subcategory":"Plumbing",
            "type":"Services"
        }
    ],
    "sg:phone":"+1 225 627 6122",
    "sg:postcode":"70767",
    "sg:province":"LA",
    "sg:tags":[
        "boiler",
        "cleaning"
    ],
    "wof:name":"Boiler Rebuilders & Fbrctrs",
    "wof:placetype":"venue"
},
  "geometry": {"coordinates":[-91.300163,30.546245],"type":"Point"}
}