{
  "type": "Feature",
  "properties": {
    "iso:country":"US",
    "sg:address":"17450 Old Jefferson Hwy",
    "sg:city":"Prairieville",
    "sg:classifiers":[
        {
            "category":"Education",
            "subcategory":"School",
            "type":"Public Place"
        }
    ],
    "sg:phone":"+1 225 622 3924",
    "sg:postcode":"70769",
    "sg:province":"LA",
    "wof:name":"Ascension Christian Academy",
    "wof:placetype":"venue"
},
  "geometry": {"coordinates":[-90.97655399999999,30.32161],"type":"Point"}
}