{
  "type": "Feature",
  "properties": {
    "addr:full":"411 S Vaughan St Brusly LA 70719",
    "addr:housenumber":"411",
    "addr:postcode":"70719",
    "addr:street":"S Vaughan St",
    "iso:country":"US",
    "sg:address":"411 S Vaughan St",
    "sg:city":"Brusly",
    "sg:classifiers":[
        {
            "category":"Restaurant",
            "type":"Food & Drink"
        }
    ],
    "sg:menulink":"http://www.allmenus.com/la/port-allen/221507-louisiana-bayou-bistro/menu/",
    "sg:phone":"+1 225 749 6354",
    "sg:postcode":"70719",
    "sg:province":"LA",
    "sg:tags":[
        "american",
        "creole",
        "cajun"
    ],
    "wof:name":"Louisiana Bayou Bistro",
    "wof:placetype":"venue"
},
  "geometry": {"coordinates":[-91.24461700000001,30.386483],"type":"Point"}
}