{
  "type": "Feature",
  "properties": {
    "addr:full":"310 S Alexander Ave Port Allen LA 70767",
    "addr:housenumber":"310",
    "addr:postcode":"70767",
    "addr:street":"S Alexander Ave",
    "iso:country":"US",
    "sg:address":"310 S Alexander Ave",
    "sg:city":"Port Allen",
    "sg:classifiers":[
        {
            "category":"Restaurant",
            "type":"Food & Drink"
        }
    ],
    "sg:phone":"+1 225 383 2289",
    "sg:postcode":"70767",
    "sg:province":"LA",
    "wof:name":"Pic-A-Pak Fried Chicken",
    "wof:placetype":"venue"
},
  "geometry": {"coordinates":[-91.21006,30.449755],"type":"Point"}
}