{
  "type": "Feature",
  "properties": {
    "addr:full":"450 Benton Rd Bossier City LA 71111",
    "addr:housenumber":"450",
    "addr:postcode":"71111",
    "addr:street":"Benton Rd",
    "iso:country":"US",
    "sg:address":"450 Benton Rd",
    "sg:city":"Bossier City",
    "sg:classifiers":[
        {
            "category":"Insurance",
            "subcategory":"Insurance Agent",
            "type":"Services"
        }
    ],
    "sg:phone":"+1 318 742 3600",
    "sg:postcode":"71111",
    "sg:province":"LA",
    "wof:name":"Geico Insurance",
    "wof:placetype":"venue"
},
  "geometry": {"coordinates":[-93.716121,32.520991],"type":"Point"}
}