{
  "type": "Feature",
  "properties": {
    "iso:country":"US",
    "sg:address":"1250 New Natchitoches Rd",
    "sg:city":"West Monroe",
    "sg:classifiers":[
        {
            "category":"Building & Trades",
            "subcategory":"Construction",
            "type":"Services"
        }
    ],
    "sg:phone":"+1 318 362 9990",
    "sg:postcode":"71292",
    "sg:province":"LA",
    "sg:tags":[
        "builder",
        "deck"
    ],
    "wof:name":"Ready Decks",
    "wof:placetype":"venue"
},
  "geometry": {"coordinates":[-92.180297,32.495396],"type":"Point"}
}