{
  "type": "Feature",
  "properties": {
    "addr:full":"608 W 4th St Thibodaux LA 70301",
    "addr:housenumber":"608",
    "addr:postcode":"70301",
    "addr:street":"W 4Th St",
    "iso:country":"US",
    "sg:address":"608 W 4th St",
    "sg:city":"Thibodaux",
    "sg:classifiers":[
        {
            "category":"Personal",
            "subcategory":"Barber",
            "type":"Services"
        }
    ],
    "sg:phone":"+1 985 446 2222",
    "sg:postcode":"70301",
    "sg:province":"LA",
    "wof:name":"Bilello Barbers & Stylists",
    "wof:placetype":"venue"
},
  "geometry": {"coordinates":[-90.82238599999999,29.796975],"type":"Point"}
}