{
  "type": "Feature",
  "properties": {
    "iso:country":"US",
    "sg:address":"1402 N Causeway Blvd",
    "sg:city":"Mandeville",
    "sg:classifiers":[
        {
            "category":"Organizations",
            "subcategory":"Religious Organization",
            "type":"Services"
        }
    ],
    "sg:phone":"+1 985 624 8763",
    "sg:postcode":"70471",
    "sg:province":"LA",
    "wof:name":"LDS Missionary Church",
    "wof:placetype":"venue"
},
  "geometry": {"coordinates":[-90.08978399999999,30.388327],"type":"Point"}
}