{
  "type": "Feature",
  "properties": {
    "iso:country":"US",
    "sg:address":"302 N Washington Ave",
    "sg:city":"Mansfield",
    "sg:classifiers":[
        {
            "category":"Utilities",
            "subcategory":"Water",
            "type":"Services"
        }
    ],
    "sg:phone":"+1 318 872 0004",
    "sg:postcode":"71052",
    "sg:province":"LA",
    "sg:tags":[
        "company",
        "sewage"
    ],
    "wof:name":"Waterworks District",
    "wof:placetype":"venue"
},
  "geometry": {"coordinates":[-93.71075,32.039279],"type":"Point"}
}