{
  "type": "Feature",
  "properties": {
    "iso:country":"US",
    "sg:address":"3007 Desiard St",
    "sg:city":"Monroe",
    "sg:classifiers":[
        {
            "category":"Retail",
            "subcategory":"Auto Repair",
            "type":"Services"
        }
    ],
    "sg:phone":"+1 318 323 1166",
    "sg:postcode":"71201",
    "sg:province":"LA",
    "sg:tags":[
        "repairing",
        "automobile",
        "radiator"
    ],
    "wof:name":"Brown Radiator & Frame Inc",
    "wof:placetype":"venue"
},
  "geometry": {"coordinates":[-92.08461699999999,32.520713],"type":"Point"}
}