{
  "type": "Feature",
  "properties": {
    "iso:country":"US",
    "sg:address":"1009 Johnson St",
    "sg:city":"Tallulah",
    "sg:classifiers":[
        {
            "category":"Shopping",
            "subcategory":"Pharmacy",
            "type":"Retail Goods"
        }
    ],
    "sg:phone":"+1 318 574 1655",
    "sg:postcode":"71282",
    "sg:province":"LA",
    "wof:name":"Medicine Shoppe Pharmacy",
    "wof:placetype":"venue"
},
  "geometry": {"coordinates":[-91.184854,32.402265],"type":"Point"}
}