{
  "type": "Feature",
  "properties": {
    "iso:country":"US",
    "sg:address":"6047 Mansfield Rd",
    "sg:city":"Shreveport",
    "sg:classifiers":[
        {
            "category":"Insurance",
            "subcategory":"Insurance Agent",
            "type":"Services"
        }
    ],
    "sg:phone":"+1 318 687 6955",
    "sg:postcode":"71103",
    "sg:province":"LA",
    "wof:name":"A-Able Insurance Agency",
    "wof:placetype":"venue"
},
  "geometry": {"coordinates":[-93.77797700000001,32.452078],"type":"Point"}
}