{
  "type": "Feature",
  "properties": {
    "iso:country":"US",
    "sg:address":"4480 General Degaulle Dr",
    "sg:city":"New Orleans",
    "sg:classifiers":[
        {
            "category":"Real Estate",
            "subcategory":"Real Estate Services",
            "type":"Services"
        }
    ],
    "sg:phone":"+1 504 391 1575",
    "sg:postcode":"70131",
    "sg:province":"LA",
    "sg:tags":[
        "company",
        "title"
    ],
    "wof:name":"Riverside Title Agency",
    "wof:placetype":"venue"
},
  "geometry": {"coordinates":[-90.009471,29.918199],"type":"Point"}
}