{
  "type": "Feature",
  "properties": {
    "addr:full":"6820 Westbank Expy Marrero LA 70072",
    "addr:housenumber":"6820",
    "addr:postcode":"70072",
    "addr:street":"Westbank Expy Marrero",
    "iso:country":"US",
    "sg:address":"6820 Westbank Expy",
    "sg:city":"Marrero",
    "sg:classifiers":[
        {
            "category":"Retail",
            "subcategory":"Funeral Services",
            "type":"Services"
        }
    ],
    "sg:phone":"+1 504 348 1896",
    "sg:postcode":"70072",
    "sg:province":"LA",
    "sg:tags":[
        "director"
    ],
    "wof:name":"Davis Mortuary Svc Inc",
    "wof:placetype":"venue"
},
  "geometry": {"coordinates":[-90.122783,29.893989],"type":"Point"}
}