{
  "type": "Feature",
  "properties": {
    "iso:country":"US",
    "sg:address":"11618 Flavie Rd",
    "sg:city":"Kaplan",
    "sg:classifiers":[
        {
            "category":"Professional",
            "subcategory":"Business Services",
            "type":"Services"
        }
    ],
    "sg:phone":"+1 337 643 7550",
    "sg:postcode":"70548",
    "sg:province":"LA",
    "wof:name":"Louisiana Partners",
    "wof:placetype":"venue"
},
  "geometry": {"coordinates":[-92.288055,29.983187],"type":"Point"}
}