{
  "type": "Feature",
  "properties": {
    "iso:country":"US",
    "sg:address":"1504 Center St",
    "sg:city":"New Iberia",
    "sg:classifiers":[
        {
            "category":"Shopping",
            "subcategory":"Used Merchandise",
            "type":"Retail Goods"
        }
    ],
    "sg:phone":"+1 337 364 6573",
    "sg:postcode":"70560",
    "sg:province":"LA",
    "sg:tags":[
        "shop",
        "thrift"
    ],
    "wof:name":"ARC Unlimited",
    "wof:placetype":"venue"
},
  "geometry": {"coordinates":[-91.833017,29.990992],"type":"Point"}
}