{
  "type": "Feature",
  "properties": {
    "addr:full":"1108 S Lake Arthur Ave Jennings LA 70546",
    "addr:housenumber":"1108",
    "addr:postcode":"70546",
    "addr:street":"S Lake Arthur Ave",
    "iso:country":"US",
    "sg:address":"1108 S Lake Arthur Ave",
    "sg:city":"Jennings",
    "sg:classifiers":[
        {
            "category":"Personal",
            "subcategory":"Tanning Parlor",
            "type":"Services"
        }
    ],
    "sg:phone":"+1 337 824 0909",
    "sg:postcode":"70546",
    "sg:province":"LA",
    "sg:tags":[
        "salon"
    ],
    "wof:name":"Island Sun Studio",
    "wof:placetype":"venue"
},
  "geometry": {"coordinates":[-92.663352,30.211919],"type":"Point"}
}