{
  "type": "Feature",
  "properties": {
    "iso:country":"US",
    "sg:address":"125 Methodist Camp Rd",
    "sg:city":"Minden",
    "sg:classifiers":[
        {
            "category":"Professional",
            "subcategory":"Accounting & Tax Preparation",
            "type":"Services"
        }
    ],
    "sg:phone":"+1 318 377 6138",
    "sg:postcode":"71055",
    "sg:province":"LA",
    "sg:tags":[
        "billing"
    ],
    "wof:name":"Data Resources Management",
    "wof:placetype":"venue"
},
  "geometry": {"coordinates":[-93.303687,32.634348],"type":"Point"}
}