{
  "type": "Feature",
  "properties": {
    "iso:country":"US",
    "sg:address":"2 Canal St",
    "sg:city":"New Orleans",
    "sg:classifiers":[
        {
            "category":"Recreation",
            "subcategory":"Dance Hall",
            "type":"Entertainment"
        }
    ],
    "sg:phone":"+1 504 599 9996",
    "sg:postcode":"70130",
    "sg:province":"LA",
    "sg:tags":[
        "club"
    ],
    "sg:website":"www.raysoverneworleans.com",
    "wof:name":"Ray's Over The River",
    "wof:placetype":"venue"
},
  "geometry": {"coordinates":[-90.06309299999999,29.949821],"type":"Point"}
}