{
  "type": "Feature",
  "properties": {
    "addr:full":"347 Evangeline Dr Princeton LA 71051",
    "addr:housenumber":"347",
    "addr:postcode":"71051",
    "addr:street":"Evangeline Dr",
    "iso:country":"US",
    "sg:address":"347 Evangeline Dr",
    "sg:city":"Princeton",
    "sg:classifiers":[
        {
            "category":"Building & Trades",
            "subcategory":"Cleaning & Sanitation",
            "type":"Services"
        }
    ],
    "sg:phone":"+1 318 987 7321",
    "sg:postcode":"71051",
    "sg:province":"LA",
    "sg:tags":[
        "janitor"
    ],
    "wof:name":"Barb's Office Cleaning",
    "wof:placetype":"venue"
},
  "geometry": {"coordinates":[-93.426113,32.348367],"type":"Point"}
}