{
  "type": "Feature",
  "properties": {
    "iso:country":"US",
    "sg:address":"2862 N Foster Dr",
    "sg:city":"Baton Rouge",
    "sg:classifiers":[
        {
            "category":"Social Services",
            "subcategory":"Child Care",
            "type":"Services"
        }
    ],
    "sg:phone":"+1 225 358 9977",
    "sg:postcode":"70805",
    "sg:province":"LA",
    "wof:name":"Queen Jones Christian Daycare",
    "wof:placetype":"venue"
},
  "geometry": {"coordinates":[-91.140259,30.474098],"type":"Point"}
}