{
  "type": "Feature",
  "properties": {
    "addr:full":"69292 Highway 21 Covington LA 70433",
    "addr:housenumber":"69292",
    "addr:postcode":"70433",
    "addr:street":"Highway 21",
    "iso:country":"US",
    "sg:address":"69292 Highway 21",
    "sg:city":"Covington",
    "sg:classifiers":[
        {
            "category":"Restaurant",
            "type":"Food & Drink"
        }
    ],
    "sg:menulink":"http://www.allmenus.com/la/madisonville/89589-moes-southwest-grill/menu/",
    "sg:phone":"+1 985 893 9895",
    "sg:postcode":"70433",
    "sg:province":"LA",
    "sg:tags":[
        "mexican"
    ],
    "wof:name":"Moe's Southwest Grill",
    "wof:placetype":"venue"
},
  "geometry": {"coordinates":[-90.143641,30.442723],"type":"Point"}
}