{
  "type": "Feature",
  "properties": {
    "iso:country":"US",
    "sg:address":"807 W McNeese St",
    "sg:city":"Lake Charles",
    "sg:classifiers":[
        {
            "category":"Insurance",
            "subcategory":"Insurance Agent",
            "type":"Services"
        }
    ],
    "sg:phone":"+1 337 474 4555",
    "sg:postcode":"70605",
    "sg:province":"LA",
    "wof:name":"Demarie Insurance",
    "wof:placetype":"venue"
},
  "geometry": {"coordinates":[-93.23307800000001,30.17606],"type":"Point"}
}