{
  "type": "Feature",
  "properties": {
    "addr:full":"6650 Harbourview Dr New Orleans LA 70126",
    "addr:housenumber":"6650",
    "addr:postcode":"70126",
    "addr:street":"Harbourview Dr",
    "iso:country":"US",
    "sg:address":"6650 Harbourview Dr",
    "sg:city":"New Orleans",
    "sg:classifiers":[
        {
            "category":"Health Services",
            "subcategory":"Clinic",
            "type":"Services"
        }
    ],
    "sg:phone":"+1 504 284 5426",
    "sg:postcode":"70126",
    "sg:province":"LA",
    "wof:name":"S M D & Associates",
    "wof:placetype":"venue"
},
  "geometry": {"coordinates":[-90.012793,30.022107],"type":"Point"}
}