{
  "type": "Feature",
  "properties": {
    "iso:country":"US",
    "sg:address":"6401 4th St",
    "sg:city":"Marrero",
    "sg:classifiers":[
        {
            "category":"Retail",
            "subcategory":"Auto Repair",
            "type":"Services"
        }
    ],
    "sg:phone":"+1 504 328 3780",
    "sg:postcode":"70072",
    "sg:province":"LA",
    "sg:tags":[
        "body",
        "automobile",
        "painting"
    ],
    "wof:name":"Westside Custom Body Shop",
    "wof:placetype":"venue"
},
  "geometry": {"coordinates":[-90.11614899999999,29.900125],"type":"Point"}
}