{
  "type": "Feature",
  "properties": {
    "iso:country":"US",
    "sg:address":"1225 27th St",
    "sg:city":"Kenner",
    "sg:classifiers":[
        {
            "category":"Freight",
            "type":"Transportation"
        }
    ],
    "sg:phone":"+1 504 466 0217",
    "sg:postcode":"70062",
    "sg:province":"LA",
    "sg:tags":[
        "commercial",
        "storage"
    ],
    "wof:name":"Many-Mini Storage",
    "wof:placetype":"venue"
},
  "geometry": {"coordinates":[-90.252326,30.004218],"type":"Point"}
}