{
  "type": "Feature",
  "properties": {
    "addr:full":"7724 E Saint Bernard Hwy Violet LA 70092",
    "addr:housenumber":"7724",
    "addr:postcode":"70092",
    "addr:street":"E Saint Bernard Hwy Violet La",
    "iso:country":"US",
    "sg:address":"7724 E Saint Bernard Hwy",
    "sg:city":"Violet",
    "sg:classifiers":[
        {
            "category":"Organizations",
            "subcategory":"Religious Organization",
            "type":"Services"
        }
    ],
    "sg:phone":"+1 504 272 0785",
    "sg:postcode":"70092",
    "sg:province":"LA",
    "sg:website":"www.thelpc.org",
    "wof:name":"Lighthouse Pentecostal Church",
    "wof:placetype":"venue"
},
  "geometry": {"coordinates":[-89.89559800000001,29.874421],"type":"Point"}
}