{
  "type": "Feature",
  "properties": {
    "iso:country":"US",
    "sg:address":"7942 Picardy Ave",
    "sg:city":"Baton Rouge",
    "sg:classifiers":[
        {
            "category":"Manufacturing",
            "subcategory":"Signs",
            "type":"Manufacturing & Wholesale Goods"
        }
    ],
    "sg:phone":"+1 225 763 6441",
    "sg:postcode":"70809",
    "sg:province":"LA",
    "sg:tags":[
        "advertising",
        "specialty"
    ],
    "wof:name":"Holiday Signs",
    "wof:placetype":"venue"
},
  "geometry": {"coordinates":[-91.10732299999999,30.398498],"type":"Point"}
}