{
  "type": "Feature",
  "properties": {
    "addr:full":"1319 S Dorgenois St New Orleans LA 70125",
    "addr:housenumber":"1319",
    "addr:postcode":"70125",
    "addr:street":"S Dorgenois St",
    "iso:country":"US",
    "sg:address":"1319 S Dorgenois St",
    "sg:city":"New Orleans",
    "sg:classifiers":[
        {
            "category":"Food & Beverages",
            "subcategory":"Groceries & Convenience Stores",
            "type":"Retail Goods"
        }
    ],
    "sg:phone":"+1 504 822 0850",
    "sg:postcode":"70125",
    "sg:province":"LA",
    "sg:tags":[
        "grocer"
    ],
    "wof:name":"Rightway Grocery",
    "wof:placetype":"venue"
},
  "geometry": {"coordinates":[-90.096029,29.952495],"type":"Point"}
}