{
  "type": "Feature",
  "properties": {
    "addr:full":"1253 Florida Blvd Baton Rouge LA 70802",
    "addr:housenumber":"1253",
    "addr:postcode":"70802",
    "addr:street":"Florida Blvd",
    "iso:country":"US",
    "sg:address":"1253 Florida Blvd",
    "sg:city":"Baton Rouge",
    "sg:classifiers":[
        {
            "category":"Local Transit",
            "type":"Transportation"
        }
    ],
    "sg:phone":"+1 225 383 3811",
    "sg:postcode":"70802",
    "sg:province":"LA",
    "sg:tags":[
        "bus",
        "line"
    ],
    "wof:name":"Greyhound Bus Lines",
    "wof:placetype":"venue"
},
  "geometry": {"coordinates":[-91.17700499999999,30.449724],"type":"Point"}
}