{
  "type": "Feature",
  "properties": {
    "iso:country":"US",
    "sg:address":"201 Dellwood Dr",
    "sg:city":"Monroe",
    "sg:classifiers":[
        {
            "category":"Social Services",
            "subcategory":"Child Care",
            "type":"Services"
        }
    ],
    "sg:phone":"+1 318 322 2003",
    "sg:postcode":"71202",
    "sg:province":"LA",
    "wof:name":"Kids Zone",
    "wof:placetype":"venue"
},
  "geometry": {"coordinates":[-92.064892,32.459322],"type":"Point"}
}