{
  "type": "Feature",
  "properties": {
    "iso:country":"US",
    "sg:address":"500 Darby Ln",
    "sg:city":"New Iberia",
    "sg:classifiers":[
        {
            "category":"Recreation",
            "type":"Entertainment"
        }
    ],
    "sg:phone":"+1 337 367 3066",
    "sg:postcode":"70560",
    "sg:province":"LA",
    "wof:name":"Doug Billiard",
    "wof:placetype":"venue"
},
  "geometry": {"coordinates":[-91.837002,30.031328],"type":"Point"}
}