{
  "type": "Feature",
  "properties": {
    "addr:full":"32444 Bowie St White Castle LA 70788",
    "addr:housenumber":"32444",
    "addr:postcode":"70788",
    "addr:street":"Bowie St",
    "iso:country":"US",
    "sg:address":"32444 Bowie St",
    "sg:city":"White Castle",
    "sg:classifiers":[
        {
            "category":"Personal",
            "subcategory":"Beauty Salon",
            "type":"Services"
        }
    ],
    "sg:phone":"+1 225 545 9118",
    "sg:postcode":"70788",
    "sg:province":"LA",
    "sg:tags":[
        "shop"
    ],
    "wof:name":"Hair and Body Shop",
    "wof:placetype":"venue"
},
  "geometry": {"coordinates":[-91.146636,30.170359],"type":"Point"}
}