{
  "type": "Feature",
  "properties": {
    "iso:country":"US",
    "sg:address":"1201 Edwards Ave",
    "sg:city":"New Orleans",
    "sg:classifiers":[
        {
            "category":"Restaurant",
            "type":"Food & Drink"
        }
    ],
    "sg:phone":"+1 504 736 0697",
    "sg:postcode":"70123",
    "sg:province":"LA",
    "sg:tags":[
        "shop",
        "coffee"
    ],
    "wof:name":"Sara Lee Coffee & Tea Fdsrvc",
    "wof:placetype":"venue"
},
  "geometry": {"coordinates":[-90.19354199999999,29.956909],"type":"Point"}
}