{
  "type": "Feature",
  "properties": {
    "addr:full":"10954 Joor Rd Baton Rouge LA 70818",
    "addr:housenumber":"10954",
    "addr:postcode":"70818",
    "addr:street":"Joor Rd",
    "iso:country":"US",
    "sg:address":"10954 Joor Rd",
    "sg:city":"Baton Rouge",
    "sg:classifiers":[
        {
            "category":"Professional",
            "subcategory":"Business Services",
            "type":"Services"
        }
    ],
    "sg:phone":"+1 225 261 6577",
    "sg:postcode":"70818",
    "sg:province":"LA",
    "sg:tags":[
        "notary"
    ],
    "wof:name":"L A Cole Notary Public",
    "wof:placetype":"venue"
},
  "geometry": {"coordinates":[-91.054119,30.54374],"type":"Point"}
}