{
  "type": "Feature",
  "properties": {
    "addr:full":"700 Martin Luther King Blvd Rayne LA 70578",
    "addr:housenumber":"700",
    "addr:postcode":"70578",
    "addr:street":"Martin Luther King Blvd",
    "iso:country":"US",
    "sg:address":"700 Martin Luther King Blvd",
    "sg:city":"Rayne",
    "sg:classifiers":[
        {
            "category":"Education",
            "subcategory":"School",
            "type":"Public Place"
        }
    ],
    "sg:phone":"+1 337 334 3377",
    "sg:postcode":"70578",
    "sg:province":"LA",
    "wof:name":"Armstrong Middle School",
    "wof:placetype":"venue"
},
  "geometry": {"coordinates":[-92.274305,30.245292],"type":"Point"}
}