{
  "type": "Feature",
  "properties": {
    "addr:full":"105 Parkwest Dr West Monroe LA 71291",
    "addr:housenumber":"105",
    "addr:postcode":"71291",
    "addr:street":"Parkwest Dr West",
    "iso:country":"US",
    "sg:address":"105 Parkwest Dr",
    "sg:city":"West Monroe",
    "sg:classifiers":[
        {
            "category":"Professional",
            "subcategory":"Testing Lab",
            "type":"Services"
        }
    ],
    "sg:phone":"+1 318 323 1535",
    "sg:postcode":"71291",
    "sg:province":"LA",
    "sg:tags":[
        "laboratory"
    ],
    "wof:name":"Global Laboratories",
    "wof:placetype":"venue"
},
  "geometry": {"coordinates":[-92.149613,32.512834],"type":"Point"}
}