{
  "type": "Feature",
  "properties": {
    "addr:full":"2171 Tower St Denham Springs LA 70726",
    "addr:housenumber":"2171",
    "addr:postcode":"70726",
    "addr:street":"Tower St",
    "iso:country":"US",
    "sg:address":"2171 Tower St",
    "sg:city":"Denham Springs",
    "sg:classifiers":[
        {
            "category":"Organizations",
            "subcategory":"Religious Organization",
            "type":"Services"
        }
    ],
    "sg:phone":"+1 225 665 1623",
    "sg:postcode":"70726",
    "sg:province":"LA",
    "sg:tags":[
        "church"
    ],
    "wof:name":"St Vincent De Paul",
    "wof:placetype":"venue"
},
  "geometry": {"coordinates":[-90.96963,30.46439],"type":"Point"}
}