{
  "type": "Feature",
  "properties": {
    "iso:country":"US",
    "sg:address":"320 Belle Terre Blvd",
    "sg:city":"La Place",
    "sg:classifiers":[
        {
            "category":"Social Services",
            "subcategory":"Child Care",
            "type":"Services"
        }
    ],
    "sg:phone":"+1 985 652 9655",
    "sg:postcode":"70068",
    "sg:province":"LA",
    "sg:website":"www.kindercare.com",
    "wof:name":"Kinder Care Learning Ctr",
    "wof:placetype":"venue"
},
  "geometry": {"coordinates":[-90.501757,30.081088],"type":"Point"}
}