{
  "type": "Feature",
  "properties": {
    "iso:country":"US",
    "sg:address":"9551 Margaux Dr",
    "sg:city":"Baton Rouge",
    "sg:classifiers":[
        {
            "category":"Professional",
            "subcategory":"Business Services",
            "type":"Services"
        }
    ],
    "sg:phone":"+1 225 288 9551",
    "sg:postcode":"70817",
    "sg:province":"LA",
    "sg:tags":[
        "distributor",
        "broker"
    ],
    "wof:name":"JV Enterprises LLC",
    "wof:placetype":"venue"
},
  "geometry": {"coordinates":[-90.980901,30.363312],"type":"Point"}
}