{
  "type": "Feature",
  "properties": {
    "iso:country":"US",
    "sg:address":"6109 Marshall Foch St",
    "sg:city":"New Orleans",
    "sg:classifiers":[
        {
            "category":"Recreation",
            "type":"Entertainment"
        }
    ],
    "sg:phone":"+1 504 488 7949",
    "sg:postcode":"70124",
    "sg:province":"LA",
    "sg:tags":[
        "club",
        "fishing",
        "hunting"
    ],
    "wof:name":"Migratory Management",
    "wof:placetype":"venue"
},
  "geometry": {"coordinates":[-90.103934,30.0023],"type":"Point"}
}