{
  "type": "Feature",
  "properties": {
    "addr:full":"508 N Airline Hwy Gonzales LA 70737",
    "addr:housenumber":"508",
    "addr:postcode":"70737",
    "addr:street":"N Airline Hwy Gonzales La",
    "iso:country":"US",
    "sg:address":"508 N Airline Hwy",
    "sg:city":"Gonzales",
    "sg:classifiers":[
        {
            "category":"Banks & Credit Unions",
            "subcategory":"Bank",
            "type":"Services"
        }
    ],
    "sg:phone":"+1 225 644 1100",
    "sg:postcode":"70737",
    "sg:province":"LA",
    "wof:name":"Regions",
    "wof:placetype":"venue"
},
  "geometry": {"coordinates":[-90.909165,30.233487],"type":"Point"}
}