{
  "type": "Feature",
  "properties": {
    "iso:country":"US",
    "sg:address":"27600 Hwy 43",
    "sg:city":"Hammond",
    "sg:classifiers":[
        {
            "category":"Wholesale",
            "subcategory":"Auto Parts",
            "type":"Manufacturing & Wholesale Goods"
        }
    ],
    "sg:phone":"+1 225 567 6486",
    "sg:postcode":"70403",
    "sg:province":"LA",
    "sg:tags":[
        "automobile",
        "rebuilt"
    ],
    "wof:name":"Albany Auto Salvage & Sales",
    "wof:placetype":"venue"
},
  "geometry": {"coordinates":[-90.57486900000001,30.46109],"type":"Point"}
}