{
  "type": "Feature",
  "properties": {
    "iso:country":"US",
    "sg:address":"50519 Frank Dillon Rd",
    "sg:city":"Franklinton",
    "sg:classifiers":[
        {
            "category":"Shopping",
            "subcategory":"Used Merchandise",
            "type":"Retail Goods"
        }
    ],
    "sg:phone":"+1 985 848 2143",
    "sg:postcode":"70438",
    "sg:province":"LA",
    "wof:name":"Joyces Sweet Repeats",
    "wof:placetype":"venue"
},
  "geometry": {"coordinates":[-90.052024,30.970641],"type":"Point"}
}