{
  "type": "Feature",
  "properties": {
    "addr:full":"2700 Lake Villa Dr Metairie LA 70002",
    "addr:housenumber":"2700",
    "addr:postcode":"70002",
    "addr:street":"Lake Villa Dr",
    "iso:country":"US",
    "sg:address":"2700 Lake Villa Dr",
    "sg:city":"Metairie",
    "sg:classifiers":[
        {
            "category":"Insurance",
            "subcategory":"Insurance Agent",
            "type":"Services"
        }
    ],
    "sg:phone":"+1 504 779 1675",
    "sg:postcode":"70002",
    "sg:province":"LA",
    "wof:name":"State Farm Insurance",
    "wof:placetype":"venue"
},
  "geometry": {"coordinates":[-90.17604,29.999675],"type":"Point"}
}