{
  "type": "Feature",
  "properties": {
    "iso:country":"US",
    "sg:address":"2605 Johnston St",
    "sg:city":"Lafayette",
    "sg:classifiers":[
        {
            "category":"Shopping",
            "subcategory":"Clothing, Apparel, & Fashions",
            "type":"Retail Goods"
        }
    ],
    "sg:phone":"+1 337 237 7590",
    "sg:postcode":"70503",
    "sg:province":"LA",
    "sg:tags":[
        "infant",
        "wear"
    ],
    "wof:name":"For The Little Ones",
    "wof:placetype":"venue"
},
  "geometry": {"coordinates":[-92.036575,30.208208],"type":"Point"}
}