{
  "type": "Feature",
  "properties": {
    "iso:country":"US",
    "sg:address":"13475 Vera McGowan",
    "sg:city":"Walker",
    "sg:classifiers":[
        {
            "category":"Shopping",
            "subcategory":"Used Merchandise",
            "type":"Retail Goods"
        }
    ],
    "sg:phone":"+1 225 665 3161",
    "sg:postcode":"70785",
    "sg:province":"LA",
    "sg:tags":[
        "antique"
    ],
    "wof:name":"Our House Antiques",
    "wof:placetype":"venue"
},
  "geometry": {"coordinates":[-90.862561,30.47393],"type":"Point"}
}