{
  "type": "Feature",
  "properties": {
    "iso:country":"US",
    "sg:address":"1603 S Gayoso St",
    "sg:city":"New Orleans",
    "sg:classifiers":[
        {
            "category":"Shopping",
            "subcategory":"Gifts & Souvenirs",
            "type":"Retail Goods"
        }
    ],
    "sg:phone":"+1 504 821 7718",
    "sg:postcode":"70125",
    "sg:province":"LA",
    "sg:tags":[
        "party",
        "supply"
    ],
    "wof:name":"Hico Balloons",
    "wof:placetype":"venue"
},
  "geometry": {"coordinates":[-90.102957,29.952544],"type":"Point"}
}