{
  "type": "Feature",
  "properties": {
    "iso:country":"US",
    "sg:address":"103 4th St",
    "sg:city":"Jonesboro",
    "sg:classifiers":[
        {
            "category":"Social Services",
            "type":"Services"
        }
    ],
    "sg:phone":"+1 318 395 9355",
    "sg:postcode":"71251",
    "sg:province":"LA",
    "sg:tags":[
        "organization",
        "welfare"
    ],
    "wof:name":"Greater North Louisiana",
    "wof:placetype":"venue"
},
  "geometry": {"coordinates":[-92.71468299999999,32.241927],"type":"Point"}
}