{
  "type": "Feature",
  "properties": {
    "iso:country":"US",
    "sg:address":"2038 E 70th St",
    "sg:city":"Shreveport",
    "sg:classifiers":[
        {
            "category":"Organizations",
            "subcategory":"Professional Association",
            "type":"Services"
        }
    ],
    "sg:phone":"+1 318 797 8222",
    "sg:postcode":"71105",
    "sg:province":"LA",
    "sg:website":"www.shreveportbossier-hba.org",
    "wof:name":"Home Builders Assn",
    "wof:placetype":"venue"
},
  "geometry": {"coordinates":[-93.707804,32.44433],"type":"Point"}
}