{
  "type": "Feature",
  "properties": {
    "iso:country":"US",
    "sg:address":"5996 Corbina Rd",
    "sg:city":"Lake Charles",
    "sg:classifiers":[
        {
            "category":"Building & Trades",
            "subcategory":"Construction",
            "type":"Services"
        }
    ],
    "sg:phone":"+1 337 474 3999",
    "sg:postcode":"70607",
    "sg:province":"LA",
    "sg:tags":[
        "house"
    ],
    "wof:name":"Stineff Construction",
    "wof:placetype":"venue"
},
  "geometry": {"coordinates":[-93.163056,30.157758],"type":"Point"}
}