{
  "type": "Feature",
  "properties": {
    "iso:country":"US",
    "sg:address":"300 Monroe St",
    "sg:city":"Harrisonburg",
    "sg:classifiers":[
        {
            "category":"Organizations",
            "subcategory":"Religious Organization",
            "type":"Services"
        }
    ],
    "sg:phone":"+1 318 744 1524",
    "sg:postcode":"71340",
    "sg:province":"LA",
    "sg:tags":[
        "church"
    ],
    "wof:name":"Harrisonburg Christian",
    "wof:placetype":"venue"
},
  "geometry": {"coordinates":[-91.825507,31.773715],"type":"Point"}
}