{
  "type": "Feature",
  "properties": {
    "iso:country":"US",
    "sg:address":"2835 Southern Ave",
    "sg:city":"Shreveport",
    "sg:classifiers":[
        {
            "category":"Real Estate",
            "subcategory":"Real Estate Agent",
            "type":"Services"
        }
    ],
    "sg:phone":"+1 318 227 2748",
    "sg:postcode":"71104",
    "sg:province":"LA",
    "sg:tags":[
        "authorities",
        "housing"
    ],
    "wof:name":"Shreveport Housing Authority",
    "wof:placetype":"venue"
},
  "geometry": {"coordinates":[-93.754408,32.482055],"type":"Point"}
}