{
  "type": "Feature",
  "properties": {
    "iso:country":"US",
    "sg:address":"7873 US Hwy 80",
    "sg:city":"Arcadia",
    "sg:classifiers":[
        {
            "category":"Retail",
            "subcategory":"Auto Repair",
            "type":"Services"
        }
    ],
    "sg:phone":"+1 318 263 2744",
    "sg:postcode":"71001",
    "sg:province":"LA",
    "sg:tags":[
        "wrecker"
    ],
    "wof:name":"Paul Davidson's Wrecker & Slvg",
    "wof:placetype":"venue"
},
  "geometry": {"coordinates":[-92.88068800000001,32.542837],"type":"Point"}
}