{
  "type": "Feature",
  "properties": {
    "addr:full":"1635 Court St Port Allen LA 70767",
    "addr:housenumber":"1635",
    "addr:postcode":"70767",
    "addr:street":"Court St",
    "iso:country":"US",
    "sg:address":"1635 Court St",
    "sg:city":"Port Allen",
    "sg:classifiers":[
        {
            "category":"Retail",
            "subcategory":"Veterinary Services",
            "type":"Services"
        }
    ],
    "sg:phone":"+1 225 383 5097",
    "sg:postcode":"70767",
    "sg:province":"LA",
    "sg:tags":[
        "veterinarian"
    ],
    "wof:name":"Westport Animal Clinic",
    "wof:placetype":"venue"
},
  "geometry": {"coordinates":[-91.219067,30.451782],"type":"Point"}
}