{
  "type": "Feature",
  "properties": {
    "iso:country":"US",
    "sg:address":"1042 Hospital Rd",
    "sg:city":"New Roads",
    "sg:classifiers":[
        {
            "category":"Real Estate",
            "subcategory":"Real Estate Operator",
            "type":"Services"
        }
    ],
    "sg:phone":"+1 225 638 3326",
    "sg:postcode":"70760",
    "sg:province":"LA",
    "sg:tags":[
        "apartment"
    ],
    "wof:name":"Acadiana Plaza Apartment",
    "wof:placetype":"venue"
},
  "geometry": {"coordinates":[-91.46462,30.685345],"type":"Point"}
}