{
  "type": "Feature",
  "properties": {
    "iso:country":"US",
    "sg:address":"2620 Centenary Blvd",
    "sg:city":"Shreveport",
    "sg:classifiers":[
        {
            "category":"Organizations",
            "subcategory":"Non-profit Organization",
            "type":"Services"
        }
    ],
    "sg:phone":"+1 318 425 2878",
    "sg:postcode":"71104",
    "sg:province":"LA",
    "wof:name":"American Diabetes Assn",
    "wof:placetype":"venue"
},
  "geometry": {"coordinates":[-93.733163,32.48602],"type":"Point"}
}