{
  "type": "Feature",
  "properties": {
    "addr:full":"1912 S Arkansas St Springhill LA 71075",
    "addr:housenumber":"1912",
    "addr:postcode":"71075",
    "addr:street":"S Arkansas St",
    "iso:country":"US",
    "sg:address":"1912 S Arkansas St",
    "sg:city":"Springhill",
    "sg:classifiers":[
        {
            "category":"Restaurant",
            "type":"Food & Drink"
        }
    ],
    "sg:phone":"+1 318 539 5535",
    "sg:postcode":"71075",
    "sg:province":"LA",
    "wof:name":"Oogie's Restaurant",
    "wof:placetype":"venue"
},
  "geometry": {"coordinates":[-93.459694,32.984955],"type":"Point"}
}