{
  "type": "Feature",
  "properties": {
    "iso:country":"US",
    "sg:address":"2000 Lamy Ln",
    "sg:city":"Monroe",
    "sg:classifiers":[
        {
            "category":"Professional",
            "subcategory":"Lawyer & Legal Services",
            "type":"Services"
        }
    ],
    "sg:phone":"+1 318 323 1980",
    "sg:postcode":"71201",
    "sg:province":"LA",
    "sg:tags":[
        "attorney"
    ],
    "wof:name":"Mc Keithen Law Offices",
    "wof:placetype":"venue"
},
  "geometry": {"coordinates":[-92.09304,32.534639],"type":"Point"}
}