{
  "type": "Feature",
  "properties": {
    "iso:country":"US",
    "sg:address":"929 Kingsway Dr E",
    "sg:city":"Gretna",
    "sg:classifiers":[
        {
            "category":"Freight",
            "type":"Transportation"
        }
    ],
    "sg:phone":"+1 504 433 0569",
    "sg:postcode":"70056",
    "sg:province":"LA",
    "sg:tags":[
        "operator",
        "local",
        "trucking"
    ],
    "wof:name":"D&M Dump Truck Service",
    "wof:placetype":"venue"
},
  "geometry": {"coordinates":[-90.010352,29.891548],"type":"Point"}
}