{
  "type": "Feature",
  "properties": {
    "iso:country":"US",
    "sg:address":"16723 Ticonderoga Ave",
    "sg:city":"Baton Rouge",
    "sg:classifiers":[
        {
            "category":"Professional",
            "subcategory":"Management & Consulting",
            "type":"Services"
        }
    ],
    "sg:phone":"+1 225 753 4302",
    "sg:postcode":"70817",
    "sg:province":"LA",
    "wof:name":"MB Visuals",
    "wof:placetype":"venue"
},
  "geometry": {"coordinates":[-90.997411,30.399612],"type":"Point"}
}