{
  "type": "Feature",
  "properties": {
    "iso:country":"US",
    "sg:address":"1720 State Rte 182",
    "sg:city":"Morgan City",
    "sg:classifiers":[
        {
            "category":"Building & Trades",
            "subcategory":"Construction",
            "type":"Services"
        }
    ],
    "sg:phone":"+1 985 395 6469",
    "sg:postcode":"70380",
    "sg:province":"LA",
    "sg:tags":[
        "roofing",
        "contractor"
    ],
    "wof:name":"Roy's Roofing Co",
    "wof:placetype":"venue"
},
  "geometry": {"coordinates":[-91.27032,29.69173],"type":"Point"}
}