{
  "type": "Feature",
  "properties": {
    "iso:country":"US",
    "sg:address":"8730 Bus Park Dr",
    "sg:city":"Shreveport",
    "sg:classifiers":[
        {
            "category":"Autos & Motor Vehicles",
            "subcategory":"Automobile Sales",
            "type":"Retail Goods"
        }
    ],
    "sg:phone":"+1 318 797 8899",
    "sg:postcode":"71105",
    "sg:province":"LA",
    "sg:tags":[
        "car",
        "dealer"
    ],
    "sg:website":"www.orrauto.com",
    "wof:name":"Orr Infiniti",
    "wof:placetype":"venue"
},
  "geometry": {"coordinates":[-93.723636,32.420561],"type":"Point"}
}