{
  "type": "Feature",
  "properties": {
    "iso:country":"US",
    "sg:address":"1408 Corporate Square Dr",
    "sg:city":"Slidell",
    "sg:classifiers":[
        {
            "category":"Real Estate",
            "subcategory":"Real Estate Agent",
            "type":"Services"
        }
    ],
    "sg:phone":"+1 985 643 5575",
    "sg:postcode":"70458",
    "sg:province":"LA",
    "sg:tags":[
        "appraiser"
    ],
    "wof:name":"David S Olivier & Assoc",
    "wof:placetype":"venue"
},
  "geometry": {"coordinates":[-89.756281,30.283646],"type":"Point"}
}