{
  "type": "Feature",
  "properties": {
    "iso:country":"US",
    "sg:address":"3330 Lake St",
    "sg:city":"Baton Rouge",
    "sg:classifiers":[
        {
            "category":"Professional",
            "subcategory":"Advertising",
            "type":"Services"
        }
    ],
    "sg:phone":"+1 225 343 3667",
    "sg:postcode":"70802",
    "sg:province":"LA",
    "wof:name":"Viacom Sports",
    "wof:placetype":"venue"
},
  "geometry": {"coordinates":[-91.17907599999999,30.417583],"type":"Point"}
}