{
  "type": "Feature",
  "properties": {
    "iso:country":"US",
    "sg:address":"3175 Elgin St",
    "sg:city":"Baton Rouge",
    "sg:classifiers":[
        {
            "category":"Professional",
            "subcategory":"Secretarial Services",
            "type":"Services"
        }
    ],
    "sg:phone":"+1 225 642 1945",
    "sg:postcode":"70805",
    "sg:province":"LA",
    "wof:name":"Mamie Wilson",
    "wof:placetype":"venue"
},
  "geometry": {"coordinates":[-91.12653899999999,30.477491],"type":"Point"}
}