{
  "type": "Feature",
  "properties": {
    "iso:country":"US",
    "sg:address":"23 Holster Ln",
    "sg:city":"St Rose",
    "sg:classifiers":[
        {
            "category":"Local Transit",
            "type":"Transportation"
        }
    ],
    "sg:phone":"+1 504 836 9977",
    "sg:postcode":"70087",
    "sg:province":"LA",
    "sg:tags":[
        "limousine"
    ],
    "sg:website":"www.boogiebususa.com",
    "wof:name":"Boogie Bus",
    "wof:placetype":"venue"
},
  "geometry": {"coordinates":[-90.314198,29.957675],"type":"Point"}
}