{
  "type": "Feature",
  "properties": {
    "addr:full":"1866 Duels St New Orleans LA 70119",
    "addr:housenumber":"1866",
    "addr:postcode":"70119",
    "addr:street":"Duels St",
    "iso:country":"US",
    "sg:address":"1866 Duels St",
    "sg:city":"New Orleans",
    "sg:classifiers":[
        {
            "category":"Social Services",
            "subcategory":"Child Care",
            "type":"Services"
        }
    ],
    "sg:phone":"+1 504 945 6800",
    "sg:postcode":"70119",
    "sg:province":"LA",
    "wof:name":"Yellow Brick Road Day Care Ctr",
    "wof:placetype":"venue"
},
  "geometry": {"coordinates":[-90.06640899999999,29.985284],"type":"Point"}
}