{
  "type": "Feature",
  "properties": {
    "addr:full":"333 E Woodstone Ct Baton Rouge LA 70808",
    "addr:housenumber":"333",
    "addr:postcode":"70808",
    "addr:street":"E Woodstone Ct",
    "iso:country":"US",
    "sg:address":"333 E Woodstone Ct",
    "sg:city":"Baton Rouge",
    "sg:classifiers":[
        {
            "category":"Professional",
            "subcategory":"Research",
            "type":"Services"
        }
    ],
    "sg:phone":"+1 225 766 0856",
    "sg:postcode":"70808",
    "sg:province":"LA",
    "sg:tags":[
        "nonphysical",
        "commercial"
    ],
    "wof:name":"Lawrence S McKenzie III",
    "wof:placetype":"venue"
},
  "geometry": {"coordinates":[-91.146315,30.38719],"type":"Point"}
}