{
  "type": "Feature",
  "properties": {
    "iso:country":"US",
    "sg:address":"400 College Ave",
    "sg:city":"Natchitoches",
    "sg:classifiers":[
        {
            "category":"Professional",
            "type":"Services"
        }
    ],
    "sg:phone":"+1 318 352 6778",
    "sg:postcode":"71457",
    "sg:province":"LA",
    "wof:name":"DBC Inc",
    "wof:placetype":"venue"
},
  "geometry": {"coordinates":[-93.090726,31.751764],"type":"Point"}
}