{
  "type": "Feature",
  "properties": {
    "addr:full":"3453 Hwy 34 West Monroe LA 71292",
    "addr:housenumber":"3453",
    "addr:postcode":"71292",
    "addr:street":"Hwy 34 West",
    "iso:country":"US",
    "sg:address":"3453 Hwy 34",
    "sg:city":"West Monroe",
    "sg:classifiers":[
        {
            "category":"Retail",
            "subcategory":"Repair Shop",
            "type":"Services"
        }
    ],
    "sg:phone":"+1 318 325 5635",
    "sg:postcode":"71292",
    "sg:province":"LA",
    "sg:tags":[
        "upholsterer"
    ],
    "wof:name":"Crain Custom Upholstery",
    "wof:placetype":"venue"
},
  "geometry": {"coordinates":[-92.32222899999999,32.40806],"type":"Point"}
}