{
  "type": "Feature",
  "properties": {
    "iso:country":"US",
    "sg:address":"21789 W J Wicker Rd",
    "sg:city":"Zachary",
    "sg:classifiers":[
        {
            "category":"Home & Garden",
            "subcategory":"Hardware",
            "type":"Retail Goods"
        }
    ],
    "sg:phone":"+1 225 654 4960",
    "sg:postcode":"70791",
    "sg:province":"LA",
    "wof:name":"Gerald R Wicker Jr",
    "wof:placetype":"venue"
},
  "geometry": {"coordinates":[-91.10740199999999,30.67491],"type":"Point"}
}