{
  "type": "Feature",
  "properties": {
    "addr:full":"507 John Stine Rd Westlake LA 70669",
    "addr:housenumber":"507",
    "addr:postcode":"70669",
    "addr:street":"John Stine Rd",
    "iso:country":"US",
    "sg:address":"507 John Stine Rd",
    "sg:city":"Westlake",
    "sg:classifiers":[
        {
            "category":"Organizations",
            "subcategory":"Religious Organization",
            "type":"Services"
        }
    ],
    "sg:phone":"+1 337 433 3179",
    "sg:postcode":"70669",
    "sg:province":"LA",
    "sg:tags":[
        "church"
    ],
    "wof:name":"Bellview Baptist Church",
    "wof:placetype":"venue"
},
  "geometry": {"coordinates":[-93.25282199999999,30.264248],"type":"Point"}
}