{
  "type": "Feature",
  "properties": {
    "iso:country":"US",
    "sg:address":"1304 N Cutting Ave",
    "sg:city":"Jennings",
    "sg:classifiers":[
        {
            "category":"Banks & Credit Unions",
            "subcategory":"Bank",
            "type":"Services"
        }
    ],
    "sg:phone":"+1 337 824 0033",
    "sg:postcode":"70546",
    "sg:province":"LA",
    "wof:name":"Bank",
    "wof:placetype":"venue"
},
  "geometry": {"coordinates":[-92.654904,30.233795],"type":"Point"}
}