{
  "type": "Feature",
  "properties": {
    "addr:full":"2932 Hwy 90 W Westwego LA 70094",
    "addr:housenumber":"2932",
    "addr:postcode":"70094",
    "addr:street":"Hwy 90 W Westwego",
    "iso:country":"US",
    "sg:address":"2932 Hwy 90 W",
    "sg:city":"Westwego",
    "sg:classifiers":[
        {
            "category":"Restaurant",
            "type":"Food & Drink"
        }
    ],
    "sg:phone":"+1 504 436 6988",
    "sg:postcode":"70094",
    "sg:province":"LA",
    "wof:name":"Green Garden Chinese Rstrnt",
    "wof:placetype":"venue"
},
  "geometry": {"coordinates":[-90.203559,29.910027],"type":"Point"}
}