{
  "type": "Feature",
  "properties": {
    "iso:country":"US",
    "sg:address":"301 Turn Row",
    "sg:city":"Lafayette",
    "sg:classifiers":[
        {
            "category":"Professional",
            "subcategory":"Research",
            "type":"Services"
        }
    ],
    "sg:phone":"+1 337 289 5223",
    "sg:postcode":"70508",
    "sg:province":"LA",
    "sg:tags":[
        "environmental",
        "ecological"
    ],
    "wof:name":"Louisiana Environmental Mntrg",
    "wof:placetype":"venue"
},
  "geometry": {"coordinates":[-92.00060999999999,30.167292],"type":"Point"}
}