{
  "type": "Feature",
  "properties": {
    "addr:full":"211 E Interstate Dr Jennings LA 70546",
    "addr:housenumber":"211",
    "addr:postcode":"70546",
    "addr:street":"E Interstate Dr",
    "iso:country":"US",
    "sg:address":"211 E Interstate Dr",
    "sg:city":"Jennings",
    "sg:classifiers":[
        {
            "category":"Autos & Motor Vehicles",
            "subcategory":"Automobile Sales",
            "type":"Retail Goods"
        }
    ],
    "sg:phone":"+1 337 824 1920",
    "sg:postcode":"70546",
    "sg:province":"LA",
    "sg:tags":[
        "car",
        "dealer"
    ],
    "wof:name":"Affordable Used Cars",
    "wof:placetype":"venue"
},
  "geometry": {"coordinates":[-92.65571799999999,30.246053],"type":"Point"}
}