{
  "type": "Feature",
  "properties": {
    "addr:full":"3042 Old Forge Dr Baton Rouge LA 70808",
    "addr:housenumber":"3042",
    "addr:postcode":"70808",
    "addr:street":"Old Forge Dr",
    "iso:country":"US",
    "sg:address":"3042 Old Forge Dr",
    "sg:city":"Baton Rouge",
    "sg:classifiers":[
        {
            "category":"Organizations",
            "subcategory":"Non-profit Organization",
            "type":"Services"
        }
    ],
    "sg:phone":"+1 225 925 9500",
    "sg:postcode":"70808",
    "sg:province":"LA",
    "wof:name":"LATAN State Office",
    "wof:placetype":"venue"
},
  "geometry": {"coordinates":[-91.136762,30.41706],"type":"Point"}
}