{
  "type": "Feature",
  "properties": {
    "addr:full":"241 Washboard Rd Ball LA 71405",
    "addr:housenumber":"241",
    "addr:postcode":"71405",
    "addr:street":"Washboard Rd",
    "iso:country":"US",
    "sg:address":"241 Washboard Rd",
    "sg:city":"Ball",
    "sg:classifiers":[
        {
            "category":"Building & Trades",
            "subcategory":"Construction",
            "type":"Services"
        }
    ],
    "sg:phone":"+1 318 641 9159",
    "sg:postcode":"71405",
    "sg:province":"LA",
    "sg:tags":[
        "excavating",
        "contractor"
    ],
    "wof:name":"B & D Dirt Sand & Gravel",
    "wof:placetype":"venue"
},
  "geometry": {"coordinates":[-92.37341499999999,31.396423],"type":"Point"}
}