{
  "type": "Feature",
  "properties": {
    "addr:full":"5600 Macarthur Blvd New Orleans LA 70131",
    "addr:housenumber":"5600",
    "addr:postcode":"70131",
    "addr:street":"Macarthur Blvd",
    "iso:country":"US",
    "sg:address":"5600 Macarthur Blvd",
    "sg:city":"New Orleans",
    "sg:classifiers":[
        {
            "category":"Professional",
            "subcategory":"Management & Consulting",
            "type":"Services"
        }
    ],
    "sg:phone":"+1 504 393 0990",
    "sg:postcode":"70131",
    "sg:province":"LA",
    "sg:tags":[
        "control",
        "marine",
        "traffic"
    ],
    "wof:name":"Doyle Marine Consultants",
    "wof:placetype":"venue"
},
  "geometry": {"coordinates":[-89.996448,29.921877],"type":"Point"}
}