{
  "type": "Feature",
  "properties": {
    "addr:full":"602 Haifleigh St Franklin LA 70538",
    "addr:housenumber":"602",
    "addr:postcode":"70538",
    "addr:street":"Haifleigh St",
    "iso:country":"US",
    "sg:address":"602 Haifleigh St",
    "sg:city":"Franklin",
    "sg:classifiers":[
        {
            "category":"Health Services",
            "subcategory":"Doctor",
            "type":"Services"
        }
    ],
    "sg:phone":"+1 337 413 8118",
    "sg:postcode":"70538",
    "sg:province":"LA",
    "sg:tags":[
        "physician",
        "surgeon"
    ],
    "wof:name":"Eugene Curzon MD",
    "wof:placetype":"venue"
},
  "geometry": {"coordinates":[-91.498901,29.806007],"type":"Point"}
}