{
  "type": "Feature",
  "properties": {
    "iso:country":"US",
    "sg:address":"6612 Canal Blvd",
    "sg:city":"New Orleans",
    "sg:classifiers":[
        {
            "category":"Organizations",
            "subcategory":"Non-profit Organization",
            "type":"Services"
        }
    ],
    "sg:phone":"+1 504 482 0465",
    "sg:postcode":"70124",
    "sg:province":"LA",
    "wof:name":"Deutsche Seamens' Mission",
    "wof:placetype":"venue"
},
  "geometry": {"coordinates":[-90.1074,30.012031],"type":"Point"}
}