{
  "type": "Feature",
  "properties": {
    "iso:country":"US",
    "sg:address":"6605 Kawanee Ave",
    "sg:city":"Metairie",
    "sg:classifiers":[
        {
            "category":"Shopping",
            "subcategory":"Clothing, Apparel, & Fashions",
            "type":"Retail Goods"
        }
    ],
    "sg:phone":"+1 504 885 4896",
    "sg:postcode":"70003",
    "sg:province":"LA",
    "wof:name":"Jammer Gear",
    "wof:placetype":"venue"
},
  "geometry": {"coordinates":[-90.220111,30.012428],"type":"Point"}
}