{
  "type": "Feature",
  "properties": {
    "addr:full":"832 Jackson St Alexandria LA 71301",
    "addr:housenumber":"832",
    "addr:postcode":"71301",
    "addr:street":"Jackson St",
    "iso:country":"US",
    "sg:address":"832 Jackson St",
    "sg:city":"Alexandria",
    "sg:classifiers":[
        {
            "category":"Government",
            "subcategory":"Office",
            "type":"Public Place"
        }
    ],
    "sg:phone":"+1 318 445 0549",
    "sg:postcode":"71301",
    "sg:province":"LA",
    "sg:tags":[
        "federal",
        "human"
    ],
    "wof:name":"US Social Security Adm",
    "wof:placetype":"venue"
},
  "geometry": {"coordinates":[-92.449371,31.30941],"type":"Point"}
}