{
  "type": "Feature",
  "properties": {
    "iso:country":"US",
    "sg:address":"208 Airline Park Blvd",
    "sg:city":"Metairie",
    "sg:classifiers":[
        {
            "category":"Shopping",
            "subcategory":"Gifts & Souvenirs",
            "type":"Retail Goods"
        }
    ],
    "sg:phone":"+1 504 733 7206",
    "sg:postcode":"70003",
    "sg:province":"LA",
    "wof:name":"Jenny Design & Gift",
    "wof:placetype":"venue"
},
  "geometry": {"coordinates":[-90.20505900000001,29.97857],"type":"Point"}
}