{
  "type": "Feature",
  "properties": {
    "iso:country":"US",
    "sg:address":"207 Marshall Dr",
    "sg:city":"Houma",
    "sg:classifiers":[
        {
            "category":"Wholesale",
            "subcategory":"Durable Goods & Equipment",
            "type":"Manufacturing & Wholesale Goods"
        }
    ],
    "sg:phone":"+1 985 868 2670",
    "sg:postcode":"70360",
    "sg:province":"LA",
    "sg:tags":[
        "exporter"
    ],
    "wof:name":"Cane Tech Inc",
    "wof:placetype":"venue"
},
  "geometry": {"coordinates":[-90.750411,29.583279],"type":"Point"}
}