{
  "type": "Feature",
  "properties": {
    "iso:country":"US",
    "sg:address":"400 N Trenton St",
    "sg:city":"Ruston",
    "sg:classifiers":[
        {
            "category":"Manufacturing",
            "subcategory":"Paper Products",
            "type":"Manufacturing & Wholesale Goods"
        }
    ],
    "sg:phone":"+1 318 255 6258",
    "sg:postcode":"71270",
    "sg:province":"LA",
    "sg:tags":[
        "corrugated",
        "solid",
        "fiber",
        "box"
    ],
    "wof:name":"Weyerhaeuser Co",
    "wof:placetype":"venue"
},
  "geometry": {"coordinates":[-92.639032,32.532468],"type":"Point"}
}