{
  "type": "Feature",
  "properties": {
    "addr:full":"6120 Franklin Ave New Orleans LA 70122",
    "addr:housenumber":"6120",
    "addr:postcode":"70122",
    "addr:street":"Franklin Ave",
    "iso:country":"US",
    "sg:address":"6120 Franklin Ave",
    "sg:city":"New Orleans",
    "sg:classifiers":[
        {
            "category":"Health Services",
            "subcategory":"Dentist",
            "type":"Services"
        }
    ],
    "sg:phone":"+1 504 288 7900",
    "sg:postcode":"70122",
    "sg:province":"LA",
    "sg:website":"www.saloydental.com",
    "wof:name":"Melanie M. Saloy D.D.S.",
    "wof:placetype":"venue"
},
  "geometry": {"coordinates":[-90.052064,30.021644],"type":"Point"}
}