{
  "type": "Feature",
  "properties": {
    "iso:country":"US",
    "sg:address":"163 Leblanc Dr",
    "sg:city":"Lockport",
    "sg:classifiers":[
        {
            "category":"Professional",
            "subcategory":"Detective & Security Services",
            "type":"Services"
        }
    ],
    "sg:phone":"+1 985 532 2983",
    "sg:postcode":"70374",
    "sg:province":"LA",
    "sg:tags":[
        "guard",
        "patrol"
    ],
    "wof:name":"Travirca Security",
    "wof:placetype":"venue"
},
  "geometry": {"coordinates":[-90.49387299999999,29.607981],"type":"Point"}
}