{
  "type": "Feature",
  "properties": {
    "addr:full":"715 Crescent Ave Lockport LA 70374",
    "addr:housenumber":"715",
    "addr:postcode":"70374",
    "addr:street":"Crescent Ave",
    "iso:country":"US",
    "sg:address":"715 Crescent Ave",
    "sg:city":"Lockport",
    "sg:classifiers":[
        {
            "category":"Social Services",
            "subcategory":"Child Care",
            "type":"Services"
        }
    ],
    "sg:phone":"+1 985 532 2300",
    "sg:postcode":"70374",
    "sg:province":"LA",
    "sg:tags":[
        "kindergarten",
        "academic",
        "school"
    ],
    "wof:name":"Learning Cottage Preschool",
    "wof:placetype":"venue"
},
  "geometry": {"coordinates":[-90.541624,29.640787],"type":"Point"}
}