{
  "type": "Feature",
  "properties": {
    "addr:full":"13463 Saint Rd Hammond LA 70403",
    "addr:housenumber":"13463",
    "addr:postcode":"70403",
    "addr:street":"Saint Rd",
    "iso:country":"US",
    "sg:address":"13463 Saint Rd",
    "sg:city":"Hammond",
    "sg:classifiers":[
        {
            "category":"Freight",
            "type":"Transportation"
        }
    ],
    "sg:phone":"+1 985 542 0309",
    "sg:postcode":"70403",
    "sg:province":"LA",
    "sg:tags":[
        "operator",
        "local",
        "trucking"
    ],
    "wof:name":"Dunn Trucking Inc",
    "wof:placetype":"venue"
},
  "geometry": {"coordinates":[-90.50285100000001,30.493017],"type":"Point"}
}