{
  "type": "Feature",
  "properties": {
    "iso:country":"US",
    "sg:address":"12745 State Rte 538",
    "sg:city":"Oil City",
    "sg:classifiers":[
        {
            "category":"Mining & Drilling",
            "type":"Manufacturing & Wholesale Goods"
        }
    ],
    "sg:phone":"+1 318 995 5305",
    "sg:postcode":"71060",
    "sg:province":"LA",
    "sg:tags":[
        "oil",
        "gas",
        "producer"
    ],
    "wof:name":"Petrol Industries Inc",
    "wof:placetype":"venue"
},
  "geometry": {"coordinates":[-93.956639,32.718654],"type":"Point"}
}