{
  "type": "Feature",
  "properties": {
    "iso:country":"US",
    "sg:address":"2101 Banks St",
    "sg:city":"New Orleans",
    "sg:classifiers":[
        {
            "category":"Health Services",
            "subcategory":"Doctor",
            "type":"Services"
        }
    ],
    "sg:phone":"+1 504 523 4357",
    "sg:postcode":"70119",
    "sg:province":"LA",
    "sg:tags":[
        "physician",
        "surgeon"
    ],
    "wof:name":"Childrens Clinic-New Orleans",
    "wof:placetype":"venue"
},
  "geometry": {"coordinates":[-90.08448199999999,29.959425],"type":"Point"}
}