{
  "type": "Feature",
  "properties": {
    "iso:country":"US",
    "sg:address":"804 N Beech St",
    "sg:city":"Tallulah",
    "sg:classifiers":[
        {
            "category":"Health Services",
            "subcategory":"Doctor",
            "type":"Services"
        }
    ],
    "sg:phone":"+1 318 574 1453",
    "sg:postcode":"71282",
    "sg:province":"LA",
    "sg:tags":[
        "clinic"
    ],
    "wof:name":"Outpatient Medical Ctr",
    "wof:placetype":"venue"
},
  "geometry": {"coordinates":[-91.183277,32.408792],"type":"Point"}
}