{
  "type": "Feature",
  "properties": {
    "addr:full":"116 W Vermilion St Lafayette LA 70501",
    "addr:housenumber":"116",
    "addr:postcode":"70501",
    "addr:street":"W Vermilion St",
    "iso:country":"US",
    "sg:address":"116 W Vermilion St",
    "sg:city":"Lafayette",
    "sg:classifiers":[
        {
            "category":"Professional",
            "subcategory":"Lawyer & Legal Services",
            "type":"Services"
        }
    ],
    "sg:phone":"+1 337 593 1350",
    "sg:postcode":"70501",
    "sg:province":"LA",
    "sg:tags":[
        "attorney"
    ],
    "wof:name":"General Title LLC",
    "wof:placetype":"venue"
},
  "geometry": {"coordinates":[-92.019657,30.224],"type":"Point"}
}