{
  "type": "Feature",
  "properties": {
    "iso:country":"US",
    "sg:address":"311 Flournoy Lucas Rd",
    "sg:city":"Shreveport",
    "sg:classifiers":[
        {
            "category":"Building & Trades",
            "subcategory":"Construction",
            "type":"Services"
        }
    ],
    "sg:phone":"+1 318 688 1021",
    "sg:postcode":"71106",
    "sg:province":"LA",
    "sg:tags":[
        "contractor"
    ],
    "wof:name":"Miller Wilburn",
    "wof:placetype":"venue"
},
  "geometry": {"coordinates":[-93.755481,32.390882],"type":"Point"}
}