{
  "type": "Feature",
  "properties": {
    "addr:full":"17163 Lawnside Ave Greenwell Springs LA 70739",
    "addr:housenumber":"17163",
    "addr:postcode":"70739",
    "addr:street":"Lawnside Ave;Springs",
    "iso:country":"US",
    "sg:address":"17163 Lawnside Ave",
    "sg:city":"Greenwell Springs",
    "sg:classifiers":[
        {
            "category":"Professional",
            "subcategory":"Business Services",
            "type":"Services"
        }
    ],
    "sg:phone":"+1 225 262 1531",
    "sg:postcode":"70739",
    "sg:province":"LA",
    "wof:name":"Summers Notary Service",
    "wof:placetype":"venue"
},
  "geometry": {"coordinates":[-90.999281,30.55426],"type":"Point"}
}