{
  "type": "Feature",
  "properties": {
    "iso:country":"US",
    "sg:address":"104 Rue Fountaine",
    "sg:city":"Lafayette",
    "sg:classifiers":[
        {
            "category":"Organizations",
            "subcategory":"Religious Organization",
            "type":"Services"
        }
    ],
    "sg:phone":"+1 337 216 9658",
    "sg:postcode":"70508",
    "sg:province":"LA",
    "sg:tags":[
        "church"
    ],
    "sg:website":"www.acadianalutherans.org",
    "wof:name":"Faith Lutheran Church",
    "wof:placetype":"venue"
},
  "geometry": {"coordinates":[-92.02392399999999,30.169446],"type":"Point"}
}