{
  "type": "Feature",
  "properties": {
    "iso:country":"US",
    "sg:address":"7857 Florida Blvd",
    "sg:city":"Denham Springs",
    "sg:classifiers":[
        {
            "category":"Wholesale",
            "subcategory":"Durable Goods & Equipment",
            "type":"Manufacturing & Wholesale Goods"
        }
    ],
    "sg:phone":"+1 225 665 6642",
    "sg:postcode":"70726",
    "sg:province":"LA",
    "sg:tags":[
        "exporter"
    ],
    "wof:name":"Myrco Enterprises",
    "wof:placetype":"venue"
},
  "geometry": {"coordinates":[-90.937198,30.484208],"type":"Point"}
}