{
  "type": "Feature",
  "properties": {
    "addr:full":"2225 NW Evangeline Trwy Lafayette LA 70501",
    "addr:housenumber":"2225",
    "addr:postcode":"70501",
    "addr:street":"Nw Evangeline",
    "iso:country":"US",
    "sg:address":"2225 NW Evangeline Trwy",
    "sg:city":"Lafayette",
    "sg:classifiers":[
        {
            "category":"Travel",
            "subcategory":"Hotels & Motels",
            "type":"Entertainment"
        }
    ],
    "sg:phone":"+1 337 235 9898",
    "sg:postcode":"70501",
    "sg:province":"LA",
    "wof:name":"Fairfield Inn",
    "wof:placetype":"venue"
},
  "geometry": {"coordinates":[-92.019997,30.2556],"type":"Point"}
}