{
  "type": "Feature",
  "properties": {
    "addr:full":"600 White Oak Ln Natchitoches LA 71457",
    "addr:housenumber":"600",
    "addr:postcode":"71457",
    "addr:street":"White Oak Ln",
    "iso:country":"US",
    "sg:address":"600 White Oak Ln",
    "sg:city":"Natchitoches",
    "sg:classifiers":[
        {
            "category":"Building & Trades",
            "subcategory":"Landscaping Services",
            "type":"Services"
        }
    ],
    "sg:phone":"+1 318 352 0062",
    "sg:postcode":"71457",
    "sg:province":"LA",
    "sg:tags":[
        "sod",
        "sodding"
    ],
    "wof:name":"Louisiana Turf Farm",
    "wof:placetype":"venue"
},
  "geometry": {"coordinates":[-93.126395,31.809991],"type":"Point"}
}