{
  "type": "Feature",
  "properties": {
    "addr:full":"2228 Carey St Slidell LA 70458",
    "addr:housenumber":"2228",
    "addr:postcode":"70458",
    "addr:street":"Carey St",
    "iso:country":"US",
    "sg:address":"2228 Carey St",
    "sg:city":"Slidell",
    "sg:classifiers":[
        {
            "category":"Restaurant",
            "type":"Food & Drink"
        }
    ],
    "sg:phone":"+1 985 643 7881",
    "sg:postcode":"70458",
    "sg:province":"LA",
    "wof:name":"Victorian Tea Room",
    "wof:placetype":"venue"
},
  "geometry": {"coordinates":[-89.783593,30.273709],"type":"Point"}
}