{
  "type": "Feature",
  "properties": {
    "iso:country":"US",
    "sg:address":"1725 N Hearne Ave",
    "sg:city":"Shreveport",
    "sg:classifiers":[
        {
            "category":"Wholesale",
            "subcategory":"Machinery & Supplies",
            "type":"Manufacturing & Wholesale Goods"
        }
    ],
    "sg:phone":"+1 318 678 8420",
    "sg:postcode":"71107",
    "sg:province":"LA",
    "wof:name":"Measurement Assurance Tech",
    "wof:placetype":"venue"
},
  "geometry": {"coordinates":[-93.77101399999999,32.536366],"type":"Point"}
}