{
  "type": "Feature",
  "properties": {
    "iso:country":"US",
    "sg:address":"1300 Franklin Ave",
    "sg:city":"Gretna",
    "sg:classifiers":[
        {
            "category":"Retail",
            "subcategory":"Auto Repair",
            "type":"Services"
        }
    ],
    "sg:phone":"+1 504 366 1467",
    "sg:postcode":"70053",
    "sg:province":"LA",
    "sg:tags":[
        "repairing",
        "automobile"
    ],
    "sg:website":"www.speedometerman.com",
    "wof:name":"Dowell's Speedometer Repair",
    "wof:placetype":"venue"
},
  "geometry": {"coordinates":[-90.049499,29.925371],"type":"Point"}
}