{
  "type": "Feature",
  "properties": {
    "iso:country":"US",
    "sg:address":"9273 State Rte 105",
    "sg:city":"Krotz Springs",
    "sg:classifiers":[
        {
            "category":"Shopping",
            "subcategory":"Florist",
            "type":"Retail Goods"
        }
    ],
    "sg:phone":"+1 337 566 3111",
    "sg:postcode":"71353",
    "sg:province":"LA",
    "wof:name":"Artistic Designs By April LLC",
    "wof:placetype":"venue"
},
  "geometry": {"coordinates":[-91.75276599999999,30.643171],"type":"Point"}
}