{
  "type": "Feature",
  "properties": {
    "iso:country":"US",
    "sg:address":"3000 N Trenton St",
    "sg:city":"Ruston",
    "sg:classifiers":[
        {
            "category":"Organizations",
            "subcategory":"Religious Organization",
            "type":"Services"
        }
    ],
    "sg:phone":"+1 318 251 2389",
    "sg:postcode":"71270",
    "sg:province":"LA",
    "wof:name":"St Paul Lutheran Church",
    "wof:placetype":"venue"
},
  "geometry": {"coordinates":[-92.64204599999999,32.564419],"type":"Point"}
}