{
  "type": "Feature",
  "properties": {
    "iso:country":"US",
    "sg:address":"3657 Lake Aspen Dr W",
    "sg:city":"Gretna",
    "sg:classifiers":[
        {
            "category":"Professional",
            "subcategory":"Lawyer & Legal Services",
            "type":"Services"
        }
    ],
    "sg:phone":"+1 504 392 2086",
    "sg:postcode":"70056",
    "sg:province":"LA",
    "wof:name":"Ripp Melvin Jr Atty",
    "wof:placetype":"venue"
},
  "geometry": {"coordinates":[-90.032898,29.855101],"type":"Point"}
}