{
  "type": "Feature",
  "properties": {
    "addr:full":"4110 General Degaulle Dr New Orleans LA 70131",
    "addr:housenumber":"4110",
    "addr:postcode":"70131",
    "addr:street":"General Degaulle Dr",
    "iso:country":"US",
    "sg:address":"4110 General Degaulle Dr",
    "sg:city":"New Orleans",
    "sg:classifiers":[
        {
            "category":"Retail",
            "subcategory":"Portrait Studio",
            "type":"Services"
        },
        {
            "category":"Shopping",
            "subcategory":"Pharmacy",
            "type":"Retail Goods"
        }
    ],
    "sg:phone":"+1 504 433 3297",
    "sg:postcode":"70131",
    "sg:province":"LA",
    "sg:tags":[
        "photography",
        "drugstore",
        "store"
    ],
    "sg:website":"www.walgreens.com/",
    "wof:name":"Walgreens",
    "wof:placetype":"venue"
},
  "geometry": {"coordinates":[-90.006989,29.916846],"type":"Point"}
}