{
  "type": "Feature",
  "properties": {
    "iso:country":"US",
    "sg:address":"6000 Johnston St",
    "sg:city":"Lafayette",
    "sg:classifiers":[
        {
            "category":"Real Estate",
            "subcategory":"Real Estate Operator",
            "type":"Services"
        }
    ],
    "sg:phone":"+1 337 406 0800",
    "sg:postcode":"70503",
    "sg:province":"LA",
    "sg:tags":[
        "apartment"
    ],
    "wof:name":"Chateau Des Lions",
    "wof:placetype":"venue"
},
  "geometry": {"coordinates":[-92.082489,30.168163],"type":"Point"}
}