{
  "type": "Feature",
  "properties": {
    "iso:country":"US",
    "sg:address":"4490 Moss St",
    "sg:city":"Lafayette",
    "sg:classifiers":[
        {
            "category":"Personal",
            "subcategory":"Beauty Salon",
            "type":"Services"
        }
    ],
    "sg:phone":"+1 337 233 2580",
    "sg:postcode":"70507",
    "sg:province":"LA",
    "wof:name":"Permanent Solution Hair Salon",
    "wof:placetype":"venue"
},
  "geometry": {"coordinates":[-92.006664,30.288527],"type":"Point"}
}