{
  "type": "Feature",
  "properties": {
    "iso:country":"US",
    "sg:address":"645 15th St",
    "sg:city":"Lake Charles",
    "sg:classifiers":[
        {
            "category":"Real Estate",
            "subcategory":"Real Estate Operator",
            "type":"Services"
        }
    ],
    "sg:phone":"+1 337 497 0970",
    "sg:postcode":"70601",
    "sg:province":"LA",
    "sg:tags":[
        "apartment"
    ],
    "wof:name":"Lake Villa",
    "wof:placetype":"venue"
},
  "geometry": {"coordinates":[-93.212784,30.209332],"type":"Point"}
}