{
  "type": "Feature",
  "properties": {
    "addr:full":"511 NW Court Cir Crowley LA 70526",
    "addr:housenumber":"511",
    "addr:postcode":"70526",
    "addr:street":"Nw Court Cir",
    "iso:country":"US",
    "sg:address":"511 NW Court Cir",
    "sg:city":"Crowley",
    "sg:classifiers":[
        {
            "category":"Real Estate",
            "subcategory":"Surveying",
            "type":"Services"
        }
    ],
    "sg:phone":"+1 337 783 7423",
    "sg:postcode":"70526",
    "sg:province":"LA",
    "sg:tags":[
        "surveyor"
    ],
    "wof:name":"A Herbert Land Surveying LLC",
    "wof:placetype":"venue"
},
  "geometry": {"coordinates":[-92.374092,30.214009],"type":"Point"}
}