{
  "type": "Feature",
  "properties": {
    "iso:country":"US",
    "sg:address":"2230 N Main St",
    "sg:city":"Saint Martinville",
    "sg:classifiers":[
        {
            "category":"Bars & Pubs",
            "subcategory":"Nightclub",
            "type":"Food & Drink"
        }
    ],
    "sg:phone":"+1 337 394 5537",
    "sg:postcode":"70582",
    "sg:province":"LA",
    "sg:tags":[
        "nightlife"
    ],
    "wof:name":"Daiquiris and More",
    "wof:placetype":"venue"
},
  "geometry": {"coordinates":[-91.823099,30.144558],"type":"Point"}
}