{
  "type": "Feature",
  "properties": {
    "addr:full":"8125 W 70th St Greenwood LA 71033",
    "addr:housenumber":"8125",
    "addr:postcode":"71033",
    "addr:street":"W 70Th St",
    "iso:country":"US",
    "sg:address":"8125 W 70th St",
    "sg:city":"Greenwood",
    "sg:classifiers":[
        {
            "category":"Freight",
            "type":"Transportation"
        }
    ],
    "sg:phone":"+1 318 938 5396",
    "sg:postcode":"71033",
    "sg:province":"LA",
    "sg:tags":[
        "trucking"
    ],
    "wof:name":"James T Gentry Trucking Co",
    "wof:placetype":"venue"
},
  "geometry": {"coordinates":[-93.947053,32.442684],"type":"Point"}
}