{
  "type": "Feature",
  "properties": {
    "iso:country":"US",
    "sg:address":"1985 Bushville Hwy",
    "sg:city":"Arnaudville",
    "sg:classifiers":[
        {
            "category":"Retail",
            "subcategory":"Auto Repair",
            "type":"Services"
        }
    ],
    "sg:phone":"+1 337 667 8023",
    "sg:postcode":"70512",
    "sg:province":"LA",
    "sg:tags":[
        "repairing",
        "automobile",
        "general"
    ],
    "wof:name":"John's Auto Repair",
    "wof:placetype":"venue"
},
  "geometry": {"coordinates":[-91.86786499999999,30.34963],"type":"Point"}
}