{
  "type": "Feature",
  "properties": {
    "iso:country":"US",
    "sg:address":"625 Garfield St",
    "sg:city":"Lafayette",
    "sg:classifiers":[
        {
            "category":"Home & Garden",
            "subcategory":"Home Furnishings",
            "type":"Retail Goods"
        }
    ],
    "sg:phone":"+1 337 268 4007",
    "sg:postcode":"70501",
    "sg:province":"LA",
    "sg:tags":[
        "pottery"
    ],
    "wof:name":"Odell Pottery",
    "wof:placetype":"venue"
},
  "geometry": {"coordinates":[-92.011965,30.222434],"type":"Point"}
}