{
  "type": "Feature",
  "properties": {
    "addr:full":"5573 Hwy 56 Chauvin LA 70344",
    "addr:housenumber":"5573",
    "addr:postcode":"70344",
    "addr:street":"Hwy 56 Chauvin",
    "iso:country":"US",
    "sg:address":"5573 Hwy 56",
    "sg:city":"Chauvin",
    "sg:classifiers":[
        {
            "category":"Home & Garden",
            "subcategory":"Building Materials",
            "type":"Retail Goods"
        }
    ],
    "sg:phone":"+1 985 594 3311",
    "sg:postcode":"70344",
    "sg:province":"LA",
    "sg:tags":[
        "center"
    ],
    "wof:name":"Chauvin Brothers Inc",
    "wof:placetype":"venue"
},
  "geometry": {"coordinates":[-90.595958,29.435057],"type":"Point"}
}