{
  "type": "Feature",
  "properties": {
    "addr:full":"128 Barataria St Lockport LA 70374",
    "addr:housenumber":"128",
    "addr:postcode":"70374",
    "addr:street":"Barataria St Lockport La",
    "iso:country":"US",
    "sg:address":"128 Barataria St",
    "sg:city":"Lockport",
    "sg:classifiers":[
        {
            "category":"Home & Garden",
            "subcategory":"Hardware",
            "type":"Retail Goods"
        }
    ],
    "sg:phone":"+1 985 532 2640",
    "sg:postcode":"70374",
    "sg:province":"LA",
    "wof:name":"Hardware Store",
    "wof:placetype":"venue"
},
  "geometry": {"coordinates":[-90.538248,29.646643],"type":"Point"}
}