{
  "type": "Feature",
  "properties": {
    "iso:country":"US",
    "sg:address":"6969 Keel Dr",
    "sg:city":"Sulphur",
    "sg:classifiers":[
        {
            "category":"Professional",
            "subcategory":"Business Services",
            "type":"Services"
        }
    ],
    "sg:phone":"+1 337 528 1065",
    "sg:postcode":"70665",
    "sg:province":"LA",
    "wof:name":"Elliot Technical Sales Inc",
    "wof:placetype":"venue"
},
  "geometry": {"coordinates":[-93.352509,30.125376],"type":"Point"}
}