{
  "type": "Feature",
  "properties": {
    "addr:full":"8480 Bluebonnet Blvd Baton Rouge LA 70810",
    "addr:housenumber":"8480",
    "addr:postcode":"70810",
    "addr:street":"Bluebonnet Blvd",
    "iso:country":"US",
    "sg:address":"8480 Bluebonnet Blvd",
    "sg:city":"Baton Rouge",
    "sg:classifiers":[
        {
            "category":"Professional",
            "subcategory":"Lawyer & Legal Services",
            "type":"Services"
        }
    ],
    "sg:phone":"+1 225 768 7803",
    "sg:postcode":"70810",
    "sg:province":"LA",
    "sg:tags":[
        "attorney"
    ],
    "wof:name":"Duncan & Simon",
    "wof:placetype":"venue"
},
  "geometry": {"coordinates":[-91.10092,30.3724],"type":"Point"}
}