{
  "type": "Feature",
  "properties": {
    "iso:country":"US",
    "sg:address":"701 Honduras St",
    "sg:city":"Houma",
    "sg:classifiers":[
        {
            "category":"Building & Trades",
            "subcategory":"Construction",
            "type":"Services"
        }
    ],
    "sg:phone":"+1 985 868 7748",
    "sg:postcode":"70360",
    "sg:province":"LA",
    "sg:tags":[
        "concrete",
        "contractor"
    ],
    "wof:name":"Nelson Best Cement Finishing",
    "wof:placetype":"venue"
},
  "geometry": {"coordinates":[-90.720266,29.590235],"type":"Point"}
}