{
  "type": "Feature",
  "properties": {
    "addr:full":"409 Thomas Rd West Monroe LA 71292",
    "addr:housenumber":"409",
    "addr:postcode":"71292",
    "addr:street":"Thomas Rd West",
    "iso:country":"US",
    "sg:address":"409 Thomas Rd",
    "sg:city":"West Monroe",
    "sg:classifiers":[
        {
            "category":"Restaurant",
            "type":"Food & Drink"
        }
    ],
    "sg:phone":"+1 318 322 8010",
    "sg:postcode":"71292",
    "sg:province":"LA",
    "wof:name":"Martha's Catfish & Seafood",
    "wof:placetype":"venue"
},
  "geometry": {"coordinates":[-92.157268,32.505579],"type":"Point"}
}