{
  "type": "Feature",
  "properties": {
    "addr:full":"6121 Tierra Dr Shreveport LA 71119",
    "addr:housenumber":"6121",
    "addr:postcode":"71119",
    "addr:street":"Tierra Dr",
    "iso:country":"US",
    "sg:address":"6121 Tierra Dr",
    "sg:city":"Shreveport",
    "sg:classifiers":[
        {
            "category":"Real Estate",
            "subcategory":"Real Estate Operator",
            "type":"Services"
        }
    ],
    "sg:phone":"+1 318 635 9914",
    "sg:postcode":"71119",
    "sg:province":"LA",
    "sg:tags":[
        "building",
        "apartment"
    ],
    "wof:name":"LA Tierra Villa Apartments",
    "wof:placetype":"venue"
},
  "geometry": {"coordinates":[-93.866032,32.461463],"type":"Point"}
}