{
  "type": "Feature",
  "properties": {
    "iso:country":"US",
    "sg:address":"7020 Read Blvd",
    "sg:city":"New Orleans",
    "sg:classifiers":[
        {
            "category":"Shopping",
            "subcategory":"Shoes",
            "type":"Retail Goods"
        }
    ],
    "sg:phone":"+1 504 242 1296",
    "sg:postcode":"70127",
    "sg:province":"LA",
    "wof:name":"Payless Shoe Source",
    "wof:placetype":"venue"
},
  "geometry": {"coordinates":[-89.97809599999999,30.039429],"type":"Point"}
}