{
  "type": "Feature",
  "properties": {
    "iso:country":"US",
    "sg:address":"11111 Roy Emerson Dr",
    "sg:city":"Baton Rouge",
    "sg:classifiers":[
        {
            "category":"Education",
            "subcategory":"School",
            "type":"Public Place"
        }
    ],
    "sg:phone":"+1 225 767 7097",
    "sg:postcode":"70810",
    "sg:province":"LA",
    "sg:website":"www.dunhamschool.org",
    "wof:name":"Dunham School",
    "wof:placetype":"venue"
},
  "geometry": {"coordinates":[-91.08645,30.382428],"type":"Point"}
}