{
  "type": "Feature",
  "properties": {
    "addr:full":"1200 N Market St Shreveport LA 71107",
    "addr:housenumber":"1200",
    "addr:postcode":"71107",
    "addr:street":"N Market St",
    "iso:country":"US",
    "sg:address":"1200 N Market St",
    "sg:city":"Shreveport",
    "sg:classifiers":[
        {
            "category":"Insurance",
            "subcategory":"Hazard Insurance",
            "type":"Services"
        }
    ],
    "sg:phone":"+1 318 222 1919",
    "sg:postcode":"71107",
    "sg:province":"LA",
    "sg:tags":[
        "bond"
    ],
    "wof:name":"Buddy Martin-Nez Bail Bonds",
    "wof:placetype":"venue"
},
  "geometry": {"coordinates":[-93.762575,32.529181],"type":"Point"}
}