{
  "type": "Feature",
  "properties": {
    "iso:country":"US",
    "sg:address":"975 Tech Dr",
    "sg:city":"Ruston",
    "sg:classifiers":[
        {
            "category":"Sports & Exercise",
            "subcategory":"Gym",
            "type":"Entertainment"
        }
    ],
    "sg:phone":"+1 318 255 7778",
    "sg:postcode":"71270",
    "sg:province":"LA",
    "sg:tags":[
        "club",
        "health",
        "studio",
        "gymnasium"
    ],
    "wof:name":"Curves For Women",
    "wof:placetype":"venue"
},
  "geometry": {"coordinates":[-92.652126,32.521413],"type":"Point"}
}