{
  "type": "Feature",
  "properties": {
    "addr:full":"1401 W Esplanade Ave Kenner LA 70065",
    "addr:housenumber":"1401",
    "addr:postcode":"70065",
    "addr:street":"W Esplanade Ave",
    "iso:country":"US",
    "sg:address":"1401 W Esplanade Ave",
    "sg:city":"Kenner",
    "sg:classifiers":[
        {
            "category":"Restaurant",
            "type":"Food & Drink"
        }
    ],
    "sg:menulink":"http://www.allmenus.com/la/kenner/180041-chick-fil-a/menu/",
    "sg:phone":"+1 504 469 9845",
    "sg:postcode":"70065",
    "sg:province":"LA",
    "sg:tags":[
        "wrap",
        "soup",
        "american",
        "sandwich",
        "salad"
    ],
    "wof:name":"Chick-fil-A",
    "wof:placetype":"venue"
},
  "geometry": {"coordinates":[-90.24679999999999,30.020121],"type":"Point"}
}