{
  "type": "Feature",
  "properties": {
    "addr:full":"8165 Main St Sorrento LA 70778",
    "addr:housenumber":"8165",
    "addr:postcode":"70778",
    "addr:street":"Main St",
    "iso:country":"US",
    "sg:address":"8165 Main St",
    "sg:city":"Sorrento",
    "sg:classifiers":[
        {
            "category":"Government",
            "subcategory":"Office",
            "type":"Public Place"
        }
    ],
    "sg:phone":"+1 225 675 5851",
    "sg:postcode":"70778",
    "sg:province":"LA",
    "sg:tags":[
        "village"
    ],
    "wof:name":"Sorrento Maintenance Dept",
    "wof:placetype":"venue"
},
  "geometry": {"coordinates":[-90.856208,30.189488],"type":"Point"}
}