{
  "type": "Feature",
  "properties": {
    "addr:full":"4236 Henry St Shreveport LA 71109",
    "addr:housenumber":"4236",
    "addr:postcode":"71109",
    "addr:street":"Henry St",
    "iso:country":"US",
    "sg:address":"4236 Henry St",
    "sg:city":"Shreveport",
    "sg:classifiers":[
        {
            "category":"Organizations",
            "subcategory":"Religious Organization",
            "type":"Services"
        }
    ],
    "sg:phone":"+1 318 631 1664",
    "sg:postcode":"71109",
    "sg:province":"LA",
    "wof:name":"Zion Rest Baptist Church",
    "wof:placetype":"venue"
},
  "geometry": {"coordinates":[-93.812067,32.464474],"type":"Point"}
}