{
  "type": "Feature",
  "properties": {
    "iso:country":"US",
    "sg:address":"58564 Spring Valley Rd",
    "sg:city":"Bogalusa",
    "sg:classifiers":[
        {
            "category":"Organizations",
            "subcategory":"Religious Organization",
            "type":"Services"
        }
    ],
    "sg:phone":"+1 985 732 3487",
    "sg:postcode":"70427",
    "sg:province":"LA",
    "wof:name":"Mt Olive Mssnary Baptst Church",
    "wof:placetype":"venue"
},
  "geometry": {"coordinates":[-89.90915200000001,30.746821],"type":"Point"}
}