{
  "type": "Feature",
  "properties": {
    "iso:country":"US",
    "sg:address":"40201 Hwy 190 E",
    "sg:city":"Slidell",
    "sg:classifiers":[
        {
            "category":"Professional",
            "type":"Services"
        }
    ],
    "sg:phone":"+1 985 649 7252",
    "sg:postcode":"70461",
    "sg:province":"LA",
    "sg:tags":[
        "scientist"
    ],
    "wof:name":"Neptune Sciences Inc",
    "wof:placetype":"venue"
},
  "geometry": {"coordinates":[-89.732432,30.26494],"type":"Point"}
}