{
  "type": "Feature",
  "properties": {
    "iso:country":"US",
    "sg:address":"112 W Genie St",
    "sg:city":"Chalmette",
    "sg:classifiers":[
        {
            "category":"Restaurant",
            "type":"Food & Drink"
        }
    ],
    "sg:phone":"+1 504 276 1172",
    "sg:postcode":"70043",
    "sg:province":"LA",
    "sg:tags":[
        "shop",
        "coffee"
    ],
    "wof:name":"Cappuccinos A Coffee House Inc",
    "wof:placetype":"venue"
},
  "geometry": {"coordinates":[-89.959954,29.952527],"type":"Point"}
}