{
  "type": "Feature",
  "properties": {
    "iso:country":"US",
    "sg:address":"1601 Loree St",
    "sg:city":"Vinton",
    "sg:classifiers":[
        {
            "category":"Banks & Credit Unions",
            "subcategory":"Bank",
            "type":"Services"
        }
    ],
    "sg:phone":"+1 337 589 7406",
    "sg:postcode":"70668",
    "sg:province":"LA",
    "sg:website":"http://www.hibernia.com",
    "wof:name":"Capital One Bank",
    "wof:placetype":"venue"
},
  "geometry": {"coordinates":[-93.58303100000001,30.189079],"type":"Point"}
}