{
  "type": "Feature",
  "properties": {
    "iso:country":"US",
    "sg:address":"400 E William David Pkwy",
    "sg:city":"Metairie",
    "sg:classifiers":[
        {
            "category":"Restaurant",
            "type":"Food & Drink"
        }
    ],
    "sg:phone":"+1 504 833 2120",
    "sg:postcode":"70005",
    "sg:province":"LA",
    "sg:tags":[
        "caterer"
    ],
    "wof:name":"Portobello Catering",
    "wof:placetype":"venue"
},
  "geometry": {"coordinates":[-90.13355199999999,30.001564],"type":"Point"}
}