{
  "type": "Feature",
  "properties": {
    "iso:country":"US",
    "sg:address":"10437 Hwy 3",
    "sg:city":"Plain Dealing",
    "sg:classifiers":[
        {
            "category":"Organizations",
            "subcategory":"Religious Organization",
            "type":"Services"
        }
    ],
    "sg:phone":"+1 318 326 5470",
    "sg:postcode":"71064",
    "sg:province":"LA",
    "sg:tags":[
        "church"
    ],
    "wof:name":"Israelite Baptist Church",
    "wof:placetype":"venue"
},
  "geometry": {"coordinates":[-93.696743,32.946133],"type":"Point"}
}