{
  "type": "Feature",
  "properties": {
    "iso:country":"US",
    "sg:address":"17069 Charlton Rd",
    "sg:city":"Baker",
    "sg:classifiers":[
        {
            "category":"Retail",
            "subcategory":"Repair Shop",
            "type":"Services"
        }
    ],
    "sg:phone":"+1 225 775 1258",
    "sg:postcode":"70714",
    "sg:province":"LA",
    "wof:name":"Horton Enterprize",
    "wof:placetype":"venue"
},
  "geometry": {"coordinates":[-91.105864,30.598885],"type":"Point"}
}