{
  "type": "Feature",
  "properties": {
    "iso:country":"US",
    "sg:address":"201 Tate Cove Rd",
    "sg:city":"Ville Platte",
    "sg:classifiers":[
        {
            "category":"Shopping",
            "subcategory":"Computers & Home Electronics",
            "type":"Retail Goods"
        }
    ],
    "sg:phone":"+1 337 363 6299",
    "sg:postcode":"70586",
    "sg:province":"LA",
    "sg:tags":[
        "equipment",
        "satellite",
        "system"
    ],
    "wof:name":"Satellite Service Inc",
    "wof:placetype":"venue"
},
  "geometry": {"coordinates":[-92.26512,30.686695],"type":"Point"}
}