{
  "type": "Feature",
  "properties": {
    "iso:country":"US",
    "sg:address":"717 Cat Island Rd",
    "sg:city":"Cloutierville",
    "sg:classifiers":[
        {
            "category":"Organizations",
            "subcategory":"Religious Organization",
            "type":"Services"
        }
    ],
    "sg:phone":"+1 318 379 0359",
    "sg:postcode":"71469",
    "sg:province":"LA",
    "sg:tags":[
        "church"
    ],
    "wof:name":"Saint Andrew Baptist Church",
    "wof:placetype":"venue"
},
  "geometry": {"coordinates":[-92.949303,31.551359],"type":"Point"}
}