{
  "type": "Feature",
  "properties": {
    "addr:full":"10001 Lake Forest Blvd New Orleans LA 70127",
    "addr:housenumber":"10001",
    "addr:postcode":"70127",
    "addr:street":"Lake Forest Blvd",
    "iso:country":"US",
    "sg:address":"10001 Lake Forest Blvd",
    "sg:city":"New Orleans",
    "sg:classifiers":[
        {
            "category":"Building & Trades",
            "subcategory":"Construction",
            "type":"Services"
        }
    ],
    "sg:phone":"+1 504 242 1976",
    "sg:postcode":"70127",
    "sg:province":"LA",
    "sg:tags":[
        "designer",
        "marine",
        "contractor"
    ],
    "wof:name":"Durward Dunn Inc",
    "wof:placetype":"venue"
},
  "geometry": {"coordinates":[-89.975769,30.031112],"type":"Point"}
}