{
  "type": "Feature",
  "properties": {
    "iso:country":"US",
    "sg:address":"4207 Cameron St",
    "sg:city":"Lafayette",
    "sg:classifiers":[
        {
            "category":"Home & Garden",
            "subcategory":"Furniture",
            "type":"Retail Goods"
        }
    ],
    "sg:phone":"+1 337 232 2453",
    "sg:postcode":"70506",
    "sg:province":"LA",
    "sg:tags":[
        "store"
    ],
    "wof:name":"Discount Furniture Sales",
    "wof:placetype":"venue"
},
  "geometry": {"coordinates":[-92.0634,30.232201],"type":"Point"}
}