{
  "type": "Feature",
  "properties": {
    "addr:full":"200 Badou Dr Dulac LA 70353",
    "addr:housenumber":"200",
    "addr:postcode":"70353",
    "addr:street":"Badou Dr Dulac",
    "iso:country":"US",
    "sg:address":"200 Badou Dr",
    "sg:city":"Dulac",
    "sg:classifiers":[
        {
            "category":"Education",
            "subcategory":"Library",
            "type":"Public Place"
        }
    ],
    "sg:phone":"+1 985 563 7249",
    "sg:postcode":"70353",
    "sg:province":"LA",
    "wof:name":"Grand Caillou Library",
    "wof:placetype":"venue"
},
  "geometry": {"coordinates":[-90.69955,29.415011],"type":"Point"}
}