{
  "type": "Feature",
  "properties": {
    "addr:full":"5170 Government St Baton Rouge LA 70806",
    "addr:housenumber":"5170",
    "addr:postcode":"70806",
    "addr:street":"Government St",
    "iso:country":"US",
    "sg:address":"5170 Government St",
    "sg:city":"Baton Rouge",
    "sg:classifiers":[
        {
            "category":"Manufacturing",
            "subcategory":"Signs",
            "type":"Manufacturing & Wholesale Goods"
        }
    ],
    "sg:phone":"+1 225 270 4762",
    "sg:postcode":"70806",
    "sg:province":"LA",
    "wof:name":"Express Signs",
    "wof:placetype":"venue"
},
  "geometry": {"coordinates":[-91.137187,30.444456],"type":"Point"}
}