{
  "type": "Feature",
  "properties": {
    "iso:country":"US",
    "sg:address":"1960 Motes Island Cir",
    "sg:city":"Shreveport",
    "sg:classifiers":[
        {
            "category":"Utilities",
            "type":"Services"
        }
    ],
    "sg:phone":"+1 318 222 1456",
    "sg:postcode":"71107",
    "sg:province":"LA",
    "sg:tags":[
        "sweeping"
    ],
    "wof:name":"Clean Sweep Parking Area",
    "wof:placetype":"venue"
},
  "geometry": {"coordinates":[-93.766834,32.547981],"type":"Point"}
}