{
  "type": "Feature",
  "properties": {
    "iso:country":"US",
    "sg:address":"1496 Evergreen Ave",
    "sg:city":"Morgan City",
    "sg:classifiers":[
        {
            "category":"Building & Trades",
            "subcategory":"Construction",
            "type":"Services"
        }
    ],
    "sg:phone":"+1 985 395 4050",
    "sg:postcode":"70380",
    "sg:province":"LA",
    "sg:tags":[
        "general",
        "contractor"
    ],
    "wof:name":"Sampey General Contractors",
    "wof:placetype":"venue"
},
  "geometry": {"coordinates":[-91.26005000000001,29.689497],"type":"Point"}
}