{
  "type": "Feature",
  "properties": {
    "iso:country":"US",
    "sg:address":"207 Church St",
    "sg:city":"Natchitoches",
    "sg:classifiers":[
        {
            "category":"Professional",
            "subcategory":"Management & Consulting",
            "type":"Services"
        }
    ],
    "sg:phone":"+1 318 238 3500",
    "sg:postcode":"71457",
    "sg:province":"LA",
    "sg:tags":[
        "consultant"
    ],
    "wof:name":"Lee Jones Consulting",
    "wof:placetype":"venue"
},
  "geometry": {"coordinates":[-93.088836,31.761166],"type":"Point"}
}