{
  "type": "Feature",
  "properties": {
    "iso:country":"US",
    "sg:address":"110 Gill Hunt Rd",
    "sg:city":"Leesville",
    "sg:classifiers":[
        {
            "category":"Retail",
            "subcategory":"Repair Shop",
            "type":"Services"
        }
    ],
    "sg:phone":"+1 337 239 7649",
    "sg:postcode":"71446",
    "sg:province":"LA",
    "wof:name":"Small Eng & Lawnmower Clinic",
    "wof:placetype":"venue"
},
  "geometry": {"coordinates":[-93.204622,31.229002],"type":"Point"}
}