{
  "type": "Feature",
  "properties": {
    "iso:country":"US",
    "sg:address":"5760 Siegen Ln",
    "sg:city":"Baton Rouge",
    "sg:classifiers":[
        {
            "category":"Shopping",
            "subcategory":"Bicycles & Sporting Goods",
            "type":"Retail Goods"
        }
    ],
    "sg:phone":"+1 225 293 5467",
    "sg:postcode":"70809",
    "sg:province":"LA",
    "sg:website":"www.jimsfirearms.com",
    "wof:name":"Jim's Firearms Inc",
    "wof:placetype":"venue"
},
  "geometry": {"coordinates":[-91.057012,30.397348],"type":"Point"}
}