{
  "type": "Feature",
  "properties": {
    "addr:full":"400 Johnston St New Iberia LA 70560",
    "addr:housenumber":"400",
    "addr:postcode":"70560",
    "addr:street":"Johnston St",
    "iso:country":"US",
    "sg:address":"400 Johnston St",
    "sg:city":"New Iberia",
    "sg:classifiers":[
        {
            "category":"Education",
            "subcategory":"School",
            "type":"Public Place"
        }
    ],
    "sg:phone":"+1 337 369 3560",
    "sg:postcode":"70560",
    "sg:province":"LA",
    "wof:name":"Johnston Street Elem School",
    "wof:placetype":"venue"
},
  "geometry": {"coordinates":[-91.83057599999999,30.004942],"type":"Point"}
}