{
  "type": "Feature",
  "properties": {
    "iso:country":"US",
    "sg:address":"18096 Old Covington Hwy",
    "sg:city":"Hammond",
    "sg:classifiers":[
        {
            "category":"Wholesale",
            "subcategory":"Groceries",
            "type":"Manufacturing & Wholesale Goods"
        }
    ],
    "sg:phone":"+1 985 542 4444",
    "sg:postcode":"70403",
    "sg:province":"LA",
    "sg:tags":[
        "food",
        "broker"
    ],
    "wof:name":"S & W Meats & Provisions Co",
    "wof:placetype":"venue"
},
  "geometry": {"coordinates":[-90.424967,30.493818],"type":"Point"}
}