{
  "type": "Feature",
  "properties": {
    "iso:country":"US",
    "sg:address":"204 Fair Ave",
    "sg:city":"Winnsboro",
    "sg:classifiers":[
        {
            "category":"Insurance",
            "subcategory":"Insurance Agent",
            "type":"Services"
        }
    ],
    "sg:phone":"+1 318 435 8943",
    "sg:postcode":"71295",
    "sg:province":"LA",
    "wof:name":"Benefits Services Inc",
    "wof:placetype":"venue"
},
  "geometry": {"coordinates":[-91.723839,32.175201],"type":"Point"}
}