{
  "type": "Feature",
  "properties": {
    "iso:country":"US",
    "sg:address":"3280 Barataria Blvd",
    "sg:city":"Marrero",
    "sg:classifiers":[
        {
            "category":"Government",
            "subcategory":"Office",
            "type":"Public Place"
        }
    ],
    "sg:phone":"+1 504 349 8893",
    "sg:postcode":"70072",
    "sg:province":"LA",
    "sg:tags":[
        "state"
    ],
    "wof:name":"Elections & Registration Dept",
    "wof:placetype":"venue"
},
  "geometry": {"coordinates":[-90.118968,29.846655],"type":"Point"}
}