{
  "type": "Feature",
  "properties": {
    "iso:country":"US",
    "sg:address":"12289 Florida Blvd",
    "sg:city":"Baton Rouge",
    "sg:classifiers":[
        {
            "category":"Home & Garden",
            "subcategory":"Garden Supply",
            "type":"Retail Goods"
        }
    ],
    "sg:phone":"+1 225 272 9795",
    "sg:postcode":"70815",
    "sg:province":"LA",
    "sg:tags":[
        "nurseryman"
    ],
    "wof:name":"Louisiana Nursery",
    "wof:placetype":"venue"
},
  "geometry": {"coordinates":[-91.045754,30.460936],"type":"Point"}
}