{
  "type": "Feature",
  "properties": {
    "iso:country":"US",
    "sg:address":"100 Westridge Dr",
    "sg:city":"West Monroe",
    "sg:classifiers":[
        {
            "category":"Professional",
            "subcategory":"Research",
            "type":"Services"
        }
    ],
    "sg:phone":"+1 318 397 7778",
    "sg:postcode":"71291",
    "sg:province":"LA",
    "sg:tags":[
        "laboratory"
    ],
    "wof:name":"Synergy Laboratory Svc",
    "wof:placetype":"venue"
},
  "geometry": {"coordinates":[-92.17694899999999,32.515729],"type":"Point"}
}