{
  "type": "Feature",
  "properties": {
    "addr:full":"5600 Jefferson Hwy New Orleans LA 70123",
    "addr:housenumber":"5600",
    "addr:postcode":"70123",
    "addr:street":"Jefferson Hwy",
    "iso:country":"US",
    "sg:address":"5600 Jefferson Hwy",
    "sg:city":"New Orleans",
    "sg:classifiers":[
        {
            "category":"Autos & Motor Vehicles",
            "subcategory":"Boat Sales",
            "type":"Retail Goods"
        }
    ],
    "sg:phone":"+1 504 733 2626",
    "sg:postcode":"70123",
    "sg:province":"LA",
    "sg:tags":[
        "equipment",
        "marine",
        "supply"
    ],
    "wof:name":"Poseidon Marine Wholslr-Nola",
    "wof:placetype":"venue"
},
  "geometry": {"coordinates":[-90.184997,29.944746],"type":"Point"}
}