{
  "type": "Feature",
  "properties": {
    "iso:country":"US",
    "sg:address":"2507 Hulin Rd",
    "sg:city":"New Iberia",
    "sg:classifiers":[
        {
            "category":"Mining & Drilling",
            "type":"Manufacturing & Wholesale Goods"
        }
    ],
    "sg:phone":"+1 337 365 7505",
    "sg:postcode":"70560",
    "sg:province":"LA",
    "sg:tags":[
        "field",
        "oil"
    ],
    "wof:name":"Wood Group Pressure Control",
    "wof:placetype":"venue"
},
  "geometry": {"coordinates":[-91.82606199999999,29.963492],"type":"Point"}
}