{
  "type": "Feature",
  "properties": {
    "addr:full":"401 Booker St Dequincy LA 70633",
    "addr:housenumber":"401",
    "addr:postcode":"70633",
    "addr:street":"Booker St",
    "iso:country":"US",
    "sg:address":"401 Booker St",
    "sg:city":"Dequincy",
    "sg:classifiers":[
        {
            "category":"Retail",
            "subcategory":"Self-service Laundry",
            "type":"Services"
        }
    ],
    "sg:phone":"+1 337 786 3940",
    "sg:postcode":"70633",
    "sg:province":"LA",
    "wof:name":"Fred De Loach Laundry Mat",
    "wof:placetype":"venue"
},
  "geometry": {"coordinates":[-93.42709600000001,30.443006],"type":"Point"}
}