{
  "type": "Feature",
  "properties": {
    "iso:country":"US",
    "sg:address":"3200 4th St",
    "sg:city":"Harvey",
    "sg:classifiers":[
        {
            "category":"Retail",
            "subcategory":"Repair Shop",
            "type":"Services"
        }
    ],
    "sg:phone":"+1 504 340 7200",
    "sg:postcode":"70058",
    "sg:province":"LA",
    "sg:tags":[
        "antique",
        "restoring"
    ],
    "wof:name":"D & L Antique Furniture",
    "wof:placetype":"venue"
},
  "geometry": {"coordinates":[-90.08628,29.907004],"type":"Point"}
}