{
  "type": "Feature",
  "properties": {
    "addr:full":"411 Tate Cove Rd Ville Platte LA 70586",
    "addr:housenumber":"411",
    "addr:postcode":"70586",
    "addr:street":"Tate Cove Rd",
    "iso:country":"US",
    "sg:address":"411 Tate Cove Rd",
    "sg:city":"Ville Platte",
    "sg:classifiers":[
        {
            "category":"Autos & Motor Vehicles",
            "subcategory":"Auto Supplies",
            "type":"Retail Goods"
        }
    ],
    "sg:phone":"+1 337 363 5909",
    "sg:postcode":"70586",
    "sg:province":"LA",
    "wof:name":"OReilly Automotive Inc",
    "wof:placetype":"venue"
},
  "geometry": {"coordinates":[-92.26440700000001,30.688283],"type":"Point"}
}