{
  "type": "Feature",
  "properties": {
    "iso:country":"US",
    "sg:address":"453 John Edwards Rd",
    "sg:city":"Farmerville",
    "sg:classifiers":[
        {
            "category":"Building & Trades",
            "subcategory":"Plumbing",
            "type":"Services"
        }
    ],
    "sg:phone":"+1 318 368 3304",
    "sg:postcode":"71241",
    "sg:province":"LA",
    "sg:tags":[
        "tank",
        "septic"
    ],
    "wof:name":"Williams Backhoe Svc",
    "wof:placetype":"venue"
},
  "geometry": {"coordinates":[-92.33684,32.79596],"type":"Point"}
}