{
  "type": "Feature",
  "properties": {
    "addr:full":"165 Champagne St Lafayette LA 70501",
    "addr:housenumber":"165",
    "addr:postcode":"70501",
    "addr:street":"Champagne St",
    "iso:country":"US",
    "sg:address":"165 Champagne St",
    "sg:city":"Lafayette",
    "sg:classifiers":[
        {
            "category":"Social Services",
            "subcategory":"Child Care",
            "type":"Services"
        }
    ],
    "sg:phone":"+1 337 593 9773",
    "sg:postcode":"70501",
    "sg:province":"LA",
    "wof:name":"Rosa's Infants & Toddlers Care",
    "wof:placetype":"venue"
},
  "geometry": {"coordinates":[-91.99581000000001,30.224732],"type":"Point"}
}