{
  "type": "Feature",
  "properties": {
    "iso:country":"US",
    "sg:address":"410 2nd St",
    "sg:city":"Gueydan",
    "sg:classifiers":[
        {
            "category":"Personal",
            "subcategory":"Beauty Salon",
            "type":"Services"
        }
    ],
    "sg:phone":"+1 337 536 6417",
    "sg:postcode":"70542",
    "sg:province":"LA",
    "wof:name":"Headlines Beauty Shop",
    "wof:placetype":"venue"
},
  "geometry": {"coordinates":[-92.512688,30.025041],"type":"Point"}
}