{
  "type": "Feature",
  "properties": {
    "iso:country":"US",
    "sg:address":"343 Downsville Rd",
    "sg:city":"Downsville",
    "sg:classifiers":[
        {
            "category":"Personal",
            "subcategory":"Beauty Salon",
            "type":"Services"
        },
        {
            "category":"Personal",
            "subcategory":"Barber",
            "type":"Services"
        }
    ],
    "sg:phone":"+1 318 982 7267",
    "sg:postcode":"71234",
    "sg:province":"LA",
    "sg:tags":[
        "shop"
    ],
    "wof:name":"Kay's Hair Shop",
    "wof:placetype":"venue"
},
  "geometry": {"coordinates":[-92.399604,32.644619],"type":"Point"}
}