{
  "type": "Feature",
  "properties": {
    "addr:full":"311 College St Springhill LA 71075",
    "addr:housenumber":"311",
    "addr:postcode":"71075",
    "addr:street":"College St",
    "iso:country":"US",
    "sg:address":"311 College St",
    "sg:city":"Springhill",
    "sg:classifiers":[
        {
            "category":"Personal",
            "subcategory":"Beauty Salon",
            "type":"Services"
        }
    ],
    "sg:phone":"+1 318 539 3032",
    "sg:postcode":"71075",
    "sg:province":"LA",
    "wof:name":"Irie's Beauty Shop",
    "wof:placetype":"venue"
},
  "geometry": {"coordinates":[-93.463058,32.996443],"type":"Point"}
}