{
  "type": "Feature",
  "properties": {
    "iso:country":"US",
    "sg:address":"2228 Arkansas Rd",
    "sg:city":"West Monroe",
    "sg:classifiers":[
        {
            "category":"Building & Trades",
            "subcategory":"Construction",
            "type":"Services"
        }
    ],
    "sg:phone":"+1 318 396 1218",
    "sg:postcode":"71291",
    "sg:province":"LA",
    "sg:tags":[
        "industrial"
    ],
    "wof:name":"JD Pickens Steel Bldg Systems",
    "wof:placetype":"venue"
},
  "geometry": {"coordinates":[-92.185129,32.534719],"type":"Point"}
}