{
  "type": "Feature",
  "properties": {
    "iso:country":"US",
    "sg:address":"3343 Metairie Rd",
    "sg:city":"Metairie",
    "sg:classifiers":[
        {
            "category":"Shopping",
            "type":"Retail Goods"
        },
        {
            "category":"Food & Beverages",
            "subcategory":"Bakery",
            "type":"Retail Goods"
        }
    ],
    "sg:phone":"+1 504 828 1770",
    "sg:postcode":"70001",
    "sg:province":"LA",
    "sg:tags":[
        "shop",
        "coffee",
        "wedding",
        "supply"
    ],
    "wof:name":"Frances' Bakery & Coffee House",
    "wof:placetype":"venue"
},
  "geometry": {"coordinates":[-90.158883,29.975785],"type":"Point"}
}