{
  "type": "Feature",
  "properties": {
    "iso:country":"US",
    "sg:address":"713 Harrell Dr",
    "sg:city":"Lafayette",
    "sg:classifiers":[
        {
            "category":"Building & Trades",
            "subcategory":"Construction",
            "type":"Services"
        }
    ],
    "sg:phone":"+1 337 981 7988",
    "sg:postcode":"70503",
    "sg:province":"LA",
    "sg:tags":[
        "hanging",
        "contractor"
    ],
    "wof:name":"Sensats Wallcovering Service",
    "wof:placetype":"venue"
},
  "geometry": {"coordinates":[-92.058396,30.175797],"type":"Point"}
}