{
  "type": "Feature",
  "properties": {
    "addr:full":"8607 US Hwy 61 St Francisville LA 70775",
    "addr:housenumber":"8607",
    "addr:postcode":"70775",
    "addr:street":"Us Hwy 61 St",
    "iso:country":"US",
    "sg:address":"8607 US Hwy 61",
    "sg:city":"St Francisville",
    "sg:classifiers":[
        {
            "category":"Real Estate",
            "subcategory":"Real Estate Agent",
            "type":"Services"
        }
    ],
    "sg:phone":"+1 225 635 3202",
    "sg:postcode":"70775",
    "sg:province":"LA",
    "wof:name":"Patrick Butler Realtor",
    "wof:placetype":"venue"
},
  "geometry": {"coordinates":[-91.387505,30.818651],"type":"Point"}
}