{
  "type": "Feature",
  "properties": {
    "addr:full":"1400 West St Leesville LA 71446",
    "addr:housenumber":"1400",
    "addr:postcode":"71446",
    "addr:street":"West St",
    "iso:country":"US",
    "sg:address":"1400 West St",
    "sg:city":"Leesville",
    "sg:classifiers":[
        {
            "category":"Wholesale",
            "subcategory":"Groceries",
            "type":"Manufacturing & Wholesale Goods"
        }
    ],
    "sg:phone":"+1 337 392 1924",
    "sg:postcode":"71446",
    "sg:province":"LA",
    "sg:tags":[
        "confectionery"
    ],
    "wof:name":"Ace Distributing",
    "wof:placetype":"venue"
},
  "geometry": {"coordinates":[-93.269001,31.154486],"type":"Point"}
}