{
  "type": "Feature",
  "properties": {
    "iso:country":"US",
    "sg:address":"1620 Belle Chasse Hwy",
    "sg:city":"Terrytown",
    "sg:classifiers":[
        {
            "category":"Shopping",
            "subcategory":"Used Merchandise",
            "type":"Retail Goods"
        }
    ],
    "sg:phone":"+1 504 362 5939",
    "sg:postcode":"70056",
    "sg:province":"LA",
    "sg:tags":[
        "shop",
        "thrift"
    ],
    "wof:name":"Humane Society Thrift Store",
    "wof:placetype":"venue"
},
  "geometry": {"coordinates":[-90.042912,29.897311],"type":"Point"}
}