{
  "type": "Feature",
  "properties": {
    "addr:full":"9470 Mammoth Ave Baton Rouge LA 70814",
    "addr:housenumber":"9470",
    "addr:postcode":"70814",
    "addr:street":"Mammoth Ave",
    "iso:country":"US",
    "sg:address":"9470 Mammoth Ave",
    "sg:city":"Baton Rouge",
    "sg:classifiers":[
        {
            "category":"Building & Trades",
            "subcategory":"Cleaning & Sanitation",
            "type":"Services"
        }
    ],
    "sg:phone":"+1 225 923 0808",
    "sg:postcode":"70814",
    "sg:province":"LA",
    "sg:tags":[
        "janitor"
    ],
    "wof:name":"ICI Building Svc",
    "wof:placetype":"venue"
},
  "geometry": {"coordinates":[-91.080601,30.473875],"type":"Point"}
}