{
  "type": "Feature",
  "properties": {
    "iso:country":"US",
    "sg:address":"3164 N Market St",
    "sg:city":"Shreveport",
    "sg:classifiers":[
        {
            "category":"Shopping",
            "subcategory":"Gifts & Souvenirs",
            "type":"Retail Goods"
        }
    ],
    "sg:phone":"+1 318 221 5281",
    "sg:postcode":"71107",
    "sg:province":"LA",
    "sg:tags":[
        "basket",
        "parcel"
    ],
    "wof:name":"Posy Mart Florist",
    "wof:placetype":"venue"
},
  "geometry": {"coordinates":[-93.78550799999999,32.561951],"type":"Point"}
}