{
  "type": "Feature",
  "properties": {
    "iso:country":"US",
    "sg:address":"2701 Veterans Memorial Blvd",
    "sg:city":"Kenner",
    "sg:classifiers":[
        {
            "category":"Utilities",
            "subcategory":"Mobile Phone",
            "type":"Services"
        }
    ],
    "sg:phone":"+1 504 467 2017",
    "sg:postcode":"70062",
    "sg:province":"LA",
    "sg:tags":[
        "telephone",
        "cellular"
    ],
    "wof:name":"Verizon Wireless",
    "wof:placetype":"venue"
},
  "geometry": {"coordinates":[-90.232163,30.005916],"type":"Point"}
}