{
  "type": "Feature",
  "properties": {
    "addr:full":"23364 Dyson Ln Kentwood LA 70444",
    "addr:postcode":"23364;70444",
    "addr:street":"Dyson Ln",
    "iso:country":"US",
    "sg:address":"23364 Dyson Ln",
    "sg:city":"Kentwood",
    "sg:classifiers":[
        {
            "category":"Building & Trades",
            "subcategory":"Landscaping Services",
            "type":"Services"
        }
    ],
    "sg:phone":"+1 985 229 8272",
    "sg:postcode":"70444",
    "sg:province":"LA",
    "sg:tags":[
        "lawn",
        "maintenance",
        "grounds"
    ],
    "wof:name":"Dyson Lawn & Repair",
    "wof:placetype":"venue"
},
  "geometry": {"coordinates":[-90.333344,30.886844],"type":"Point"}
}