{
  "type": "Feature",
  "properties": {
    "iso:country":"US",
    "sg:address":"1809 Lois Ln",
    "sg:city":"Bossier City",
    "sg:classifiers":[
        {
            "category":"Retail",
            "subcategory":"Auto Repair",
            "type":"Services"
        }
    ],
    "sg:phone":"+1 318 741 3223",
    "sg:postcode":"71111",
    "sg:province":"LA",
    "sg:tags":[
        "repairing",
        "automobile",
        "general"
    ],
    "wof:name":"J D Automotive",
    "wof:placetype":"venue"
},
  "geometry": {"coordinates":[-93.71818500000001,32.536439],"type":"Point"}
}