{
  "type": "Feature",
  "properties": {
    "iso:country":"US",
    "sg:address":"1083 Doty Rd",
    "sg:city":"Ferriday",
    "sg:classifiers":[
        {
            "category":"Farming",
            "subcategory":"Farm",
            "type":"Manufacturing & Wholesale Goods"
        }
    ],
    "sg:phone":"+1 318 757 3485",
    "sg:postcode":"71334",
    "sg:province":"LA",
    "sg:tags":[
        "crop",
        "general"
    ],
    "wof:name":"Bla Farms Inc",
    "wof:placetype":"venue"
},
  "geometry": {"coordinates":[-91.581073,31.652908],"type":"Point"}
}