{
  "type": "Feature",
  "properties": {
    "iso:country":"US",
    "sg:address":"380 Cypremort Rd",
    "sg:city":"Franklin",
    "sg:classifiers":[
        {
            "category":"Retail",
            "subcategory":"Auto Repair",
            "type":"Services"
        }
    ],
    "sg:phone":"+1 337 923 7755",
    "sg:postcode":"70538",
    "sg:province":"LA",
    "sg:tags":[
        "body",
        "automobile",
        "painting"
    ],
    "wof:name":"Kustom Collision Paint & Body",
    "wof:placetype":"venue"
},
  "geometry": {"coordinates":[-91.617047,29.843411],"type":"Point"}
}