{
  "type": "Feature",
  "properties": {
    "addr:full":"14757 S Harrells Ferry Rd Baton Rouge LA 70816",
    "addr:housenumber":"14757",
    "addr:postcode":"70816",
    "addr:street":"S Harrells Ferry Rd",
    "iso:country":"US",
    "sg:address":"14757 S Harrells Ferry Rd",
    "sg:city":"Baton Rouge",
    "sg:classifiers":[
        {
            "category":"Home & Garden",
            "subcategory":"Building Materials",
            "type":"Retail Goods"
        }
    ],
    "sg:phone":"+1 225 756 8997",
    "sg:postcode":"70816",
    "sg:province":"LA",
    "sg:tags":[
        "mixed",
        "concrete"
    ],
    "wof:name":"U-Can-Cart Concrete",
    "wof:placetype":"venue"
},
  "geometry": {"coordinates":[-91.020132,30.428649],"type":"Point"}
}