{
  "type": "Feature",
  "properties": {
    "addr:full":"125 W Forest Dr Slidell LA 70458",
    "addr:housenumber":"125",
    "addr:postcode":"70458",
    "addr:street":"W Forest Dr",
    "iso:country":"US",
    "sg:address":"125 W Forest Dr",
    "sg:city":"Slidell",
    "sg:classifiers":[
        {
            "category":"Professional",
            "type":"Services"
        }
    ],
    "sg:phone":"+1 985 649 6134",
    "sg:postcode":"70458",
    "sg:province":"LA",
    "wof:name":"Angles of Jefferson Inc",
    "wof:placetype":"venue"
},
  "geometry": {"coordinates":[-89.757296,30.311654],"type":"Point"}
}