{
  "type": "Feature",
  "properties": {
    "iso:country":"US",
    "sg:address":"400 Monarch Dr",
    "sg:city":"Houma",
    "sg:classifiers":[
        {
            "category":"Health Services",
            "subcategory":"Nursing And Care Facility",
            "type":"Services"
        }
    ],
    "sg:phone":"+1 985 876 5692",
    "sg:postcode":"70364",
    "sg:province":"LA",
    "sg:tags":[
        "home",
        "convalescent"
    ],
    "wof:name":"Oaks Of Houma",
    "wof:placetype":"venue"
},
  "geometry": {"coordinates":[-90.73401699999999,29.611914],"type":"Point"}
}