{
  "type": "Feature",
  "properties": {
    "addr:full":"710 W McNeese St Lake Charles LA 70605",
    "addr:housenumber":"710",
    "addr:postcode":"70605",
    "addr:street":"W Mcneese St",
    "iso:country":"US",
    "sg:address":"710 W McNeese St",
    "sg:city":"Lake Charles",
    "sg:classifiers":[
        {
            "category":"Real Estate",
            "subcategory":"Real Estate Operator",
            "type":"Services"
        }
    ],
    "sg:phone":"+1 337 477 8886",
    "sg:postcode":"70605",
    "sg:province":"LA",
    "sg:tags":[
        "apartment"
    ],
    "wof:name":"Acadian Oaks Apartments",
    "wof:placetype":"venue"
},
  "geometry": {"coordinates":[-93.231949,30.176216],"type":"Point"}
}