{
  "type": "Feature",
  "properties": {
    "iso:country":"US",
    "sg:address":"22668 Loving Dr",
    "sg:city":"Denham Springs",
    "sg:classifiers":[
        {
            "category":"Shopping",
            "subcategory":"Hobbies, Toys, & Games",
            "type":"Retail Goods"
        }
    ],
    "sg:phone":"+1 225 667 0404",
    "sg:postcode":"70726",
    "sg:province":"LA",
    "sg:tags":[
        "craft"
    ],
    "wof:name":"Yard Crafts To Go",
    "wof:placetype":"venue"
},
  "geometry": {"coordinates":[-90.869957,30.393854],"type":"Point"}
}