{
  "type": "Feature",
  "properties": {
    "iso:country":"US",
    "sg:address":"3647 Veterans Memorial Blvd",
    "sg:city":"Metairie",
    "sg:classifiers":[
        {
            "category":"Coffee & Tea",
            "type":"Food & Drink"
        }
    ],
    "sg:menulink":"http://www.allmenus.com/la/metairie/27224-ccs-coffee-house/menu/",
    "sg:phone":"+1 504 454 1200",
    "sg:postcode":"70002",
    "sg:province":"LA",
    "sg:tags":[
        "american"
    ],
    "wof:name":"CC's Coffee House",
    "wof:placetype":"venue"
},
  "geometry": {"coordinates":[-90.16374,30.003997],"type":"Point"}
}