{
  "type": "Feature",
  "properties": {
    "addr:full":"10512 Springhill Rd Kaplan LA 70548",
    "addr:housenumber":"10512",
    "addr:postcode":"70548",
    "addr:street":"Springhill Rd",
    "iso:country":"US",
    "sg:address":"10512 Springhill Rd",
    "sg:city":"Kaplan",
    "sg:classifiers":[
        {
            "category":"Building & Trades",
            "subcategory":"Plumbing",
            "type":"Services"
        }
    ],
    "sg:phone":"+1 337 643 8884",
    "sg:postcode":"70548",
    "sg:province":"LA",
    "sg:tags":[
        "plumbing",
        "contractor"
    ],
    "wof:name":"Monteaux's Plumbing",
    "wof:placetype":"venue"
},
  "geometry": {"coordinates":[-92.20723099999999,29.998567],"type":"Point"}
}