{
  "type": "Feature",
  "properties": {
    "addr:full":"3225 River Rd Bridge City LA 70094",
    "addr:housenumber":"3225",
    "addr:postcode":"70094",
    "addr:street":"River Rd Bridge",
    "iso:country":"US",
    "sg:address":"3225 River Rd",
    "sg:city":"Bridge City",
    "sg:classifiers":[
        {
            "category":"Government",
            "subcategory":"Jail",
            "type":"Public Place"
        }
    ],
    "sg:phone":"+1 504 436 4253",
    "sg:postcode":"70094",
    "sg:province":"LA",
    "sg:tags":[
        "govt",
        "state",
        "institution"
    ],
    "wof:name":"Bridge City Correctional Ctr",
    "wof:placetype":"venue"
},
  "geometry": {"coordinates":[-90.170385,29.936649],"type":"Point"}
}