{
  "type": "Feature",
  "properties": {
    "iso:country":"US",
    "sg:address":"81179 Section Rd",
    "sg:city":"Covington",
    "sg:classifiers":[
        {
            "category":"Professional",
            "type":"Services"
        }
    ],
    "sg:phone":"+1 985 892 7113",
    "sg:postcode":"70435",
    "sg:province":"LA",
    "wof:name":"Dmg Services",
    "wof:placetype":"venue"
},
  "geometry": {"coordinates":[-90.101333,30.612971],"type":"Point"}
}