{
  "type": "Feature",
  "properties": {
    "iso:country":"US",
    "sg:address":"723 Providence St",
    "sg:city":"New Iberia",
    "sg:classifiers":[
        {
            "category":"Shopping",
            "subcategory":"Gifts & Souvenirs",
            "type":"Retail Goods"
        }
    ],
    "sg:phone":"+1 337 365 9984",
    "sg:postcode":"70560",
    "sg:province":"LA",
    "wof:name":"Inaris U Neek",
    "wof:placetype":"venue"
},
  "geometry": {"coordinates":[-91.825053,30.001924],"type":"Point"}
}