{
  "type": "Feature",
  "properties": {
    "addr:full":"3304 W Landry St Opelousas LA 70570",
    "addr:housenumber":"3304",
    "addr:postcode":"70570",
    "addr:street":"W Landry St",
    "iso:country":"US",
    "sg:address":"3304 W Landry St",
    "sg:city":"Opelousas",
    "sg:classifiers":[
        {
            "category":"Utilities",
            "subcategory":"Natural Gas",
            "type":"Services"
        }
    ],
    "sg:phone":"+1 337 942 2272",
    "sg:postcode":"70570",
    "sg:province":"LA",
    "sg:tags":[
        "company"
    ],
    "wof:name":"Reed Inc",
    "wof:placetype":"venue"
},
  "geometry": {"coordinates":[-92.127869,30.532871],"type":"Point"}
}