{
  "type": "Feature",
  "properties": {
    "addr:full":"12310 State Rte 695 Kaplan LA 70548",
    "addr:housenumber":"12310",
    "addr:postcode":"70548",
    "addr:street":"State Rte 695 Kaplan La",
    "iso:country":"US",
    "sg:address":"12310 State Rte 695",
    "sg:city":"Kaplan",
    "sg:classifiers":[
        {
            "category":"Food & Beverages",
            "subcategory":"Bakery",
            "type":"Retail Goods"
        }
    ],
    "sg:phone":"+1 337 643 3210",
    "sg:postcode":"70548",
    "sg:province":"LA",
    "sg:tags":[
        "baker"
    ],
    "wof:name":"French Market Bread & Pastries",
    "wof:placetype":"venue"
},
  "geometry": {"coordinates":[-92.225065,29.98331],"type":"Point"}
}