{
  "type": "Feature",
  "properties": {
    "addr:full":"4206 Sterlington Rd Monroe LA 71203",
    "addr:housenumber":"4206",
    "addr:postcode":"71203",
    "addr:street":"Sterlington Rd",
    "iso:country":"US",
    "sg:address":"4206 Sterlington Rd",
    "sg:city":"Monroe",
    "sg:classifiers":[
        {
            "category":"Wholesale",
            "subcategory":"Durable Goods & Equipment",
            "type":"Manufacturing & Wholesale Goods"
        }
    ],
    "sg:phone":"+1 318 343 8199",
    "sg:postcode":"71203",
    "sg:province":"LA",
    "sg:tags":[
        "importer"
    ],
    "wof:name":"J C Co",
    "wof:placetype":"venue"
},
  "geometry": {"coordinates":[-92.073887,32.569116],"type":"Point"}
}