{
  "type": "Feature",
  "properties": {
    "iso:country":"US",
    "sg:address":"6119 Hwy 1",
    "sg:city":"Belle Rose",
    "sg:classifiers":[
        {
            "category":"Manufacturing",
            "subcategory":"Watercraft",
            "type":"Manufacturing & Wholesale Goods"
        }
    ],
    "sg:phone":"+1 504 366 3343",
    "sg:postcode":"70341",
    "sg:province":"LA",
    "sg:tags":[
        "shore",
        "marine"
    ],
    "wof:name":"Ocean River International LLC",
    "wof:placetype":"venue"
},
  "geometry": {"coordinates":[-91.056399,29.998224],"type":"Point"}
}