{
  "type": "Feature",
  "properties": {
    "addr:full":"40677 Chinchas Creek Rd Slidell LA 70461",
    "addr:postcode":"40677;70461",
    "addr:street":"Chinchas Creek Rd",
    "iso:country":"US",
    "sg:address":"40677 Chinchas Creek Rd",
    "sg:city":"Slidell",
    "sg:classifiers":[
        {
            "category":"Building & Trades",
            "subcategory":"Pest Control",
            "type":"Services"
        }
    ],
    "sg:phone":"+1 985 641 3480",
    "sg:postcode":"70461",
    "sg:province":"LA",
    "wof:name":"A Bug Kickers Inc",
    "wof:placetype":"venue"
},
  "geometry": {"coordinates":[-89.724085,30.279671],"type":"Point"}
}