{
  "type": "Feature",
  "properties": {
    "addr:full":"315 Candleglow Dr New Iberia LA 70563",
    "addr:housenumber":"315",
    "addr:postcode":"70563",
    "addr:street":"Candleglow Dr",
    "iso:country":"US",
    "sg:address":"315 Candleglow Dr",
    "sg:city":"New Iberia",
    "sg:classifiers":[
        {
            "category":"Banks & Credit Unions",
            "subcategory":"Investment Brokerage",
            "type":"Services"
        }
    ],
    "sg:phone":"+1 337 365 0732",
    "sg:postcode":"70563",
    "sg:province":"LA",
    "sg:tags":[
        "consultant",
        "planning",
        "financial"
    ],
    "wof:name":"Acadiana Land Scrapers",
    "wof:placetype":"venue"
},
  "geometry": {"coordinates":[-91.751808,30.004349],"type":"Point"}
}