{
  "type": "Feature",
  "properties": {
    "iso:country":"US",
    "sg:address":"191 Bellewood Dr",
    "sg:city":"Baton Rouge",
    "sg:classifiers":[
        {
            "category":"Building & Trades",
            "subcategory":"Construction",
            "type":"Services"
        }
    ],
    "sg:phone":"+1 225 216 1528",
    "sg:postcode":"70806",
    "sg:province":"LA",
    "sg:tags":[
        "downspouts",
        "gutter"
    ],
    "wof:name":"Continual House Gutter System",
    "wof:placetype":"venue"
},
  "geometry": {"coordinates":[-91.12173199999999,30.446307],"type":"Point"}
}