{
  "type": "Feature",
  "properties": {
    "addr:full":"437 E Mississippi Ave Ruston LA 71270",
    "addr:housenumber":"437",
    "addr:postcode":"71270",
    "addr:street":"E Mississippi Ave",
    "iso:country":"US",
    "sg:address":"437 E Mississippi Ave",
    "sg:city":"Ruston",
    "sg:classifiers":[
        {
            "category":"Wholesale",
            "subcategory":"Medical Equipment & Supplies",
            "type":"Manufacturing & Wholesale Goods"
        }
    ],
    "sg:phone":"+1 318 255 3077",
    "sg:postcode":"71270",
    "sg:province":"LA",
    "sg:tags":[
        "physician",
        "surgeon"
    ],
    "wof:name":"Respiratory Therapists Eqpt",
    "wof:placetype":"venue"
},
  "geometry": {"coordinates":[-92.63084000000001,32.529325],"type":"Point"}
}