{
  "type": "Feature",
  "properties": {
    "iso:country":"US",
    "sg:address":"318 14th St",
    "sg:city":"Lafayette",
    "sg:classifiers":[
        {
            "category":"Food & Beverages",
            "subcategory":"Groceries & Convenience Stores",
            "type":"Retail Goods"
        }
    ],
    "sg:phone":"+1 337 233 7423",
    "sg:postcode":"70501",
    "sg:province":"LA",
    "sg:tags":[
        "grocer"
    ],
    "wof:name":"Al's Neighborhood Grocery",
    "wof:placetype":"venue"
},
  "geometry": {"coordinates":[-92.005702,30.221446],"type":"Point"}
}