{
  "type": "Feature",
  "properties": {
    "iso:country":"US",
    "sg:address":"15160 Hwy 16",
    "sg:city":"French Settlemnt",
    "sg:classifiers":[
        {
            "category":"Government",
            "subcategory":"Fire Station",
            "type":"Public Place"
        }
    ],
    "sg:phone":"+1 225 698 3510",
    "sg:postcode":"70733",
    "sg:province":"LA",
    "sg:tags":[
        "department"
    ],
    "wof:name":"French Settlement Volunteer",
    "wof:placetype":"venue"
},
  "geometry": {"coordinates":[-90.78474,30.281343],"type":"Point"}
}