{
  "type": "Feature",
  "properties": {
    "addr:full":"50 Cobblestone E Houma LA 70360",
    "addr:housenumber":"50",
    "addr:postcode":"70360",
    "addr:street":"Cobblestone E",
    "iso:country":"US",
    "sg:address":"50 Cobblestone E",
    "sg:city":"Houma",
    "sg:classifiers":[
        {
            "category":"Restaurant",
            "type":"Food & Drink"
        }
    ],
    "sg:phone":"+1 985 851 4492",
    "sg:postcode":"70360",
    "sg:province":"LA",
    "sg:tags":[
        "eating"
    ],
    "wof:name":"Redfish Pizza Co",
    "wof:placetype":"venue"
},
  "geometry": {"coordinates":[-90.740071,29.586788],"type":"Point"}
}