{
  "type": "Feature",
  "properties": {
    "iso:country":"US",
    "sg:address":"10824 Ramblewood Ave",
    "sg:city":"Baton Rouge",
    "sg:classifiers":[
        {
            "category":"Manufacturing",
            "subcategory":"Textiles",
            "type":"Manufacturing & Wholesale Goods"
        }
    ],
    "sg:phone":"+1 225 767 7524",
    "sg:postcode":"70810",
    "sg:province":"LA",
    "sg:tags":[
        "drapery",
        "workroom"
    ],
    "wof:name":"Curtains By Claudia",
    "wof:placetype":"venue"
},
  "geometry": {"coordinates":[-91.09869399999999,30.371001],"type":"Point"}
}