{
  "type": "Feature",
  "properties": {
    "addr:full":"37458 State Rte 621 Prairieville LA 70769",
    "addr:housenumber":"37458",
    "addr:postcode":"70769",
    "addr:street":"State Rte 621",
    "iso:country":"US",
    "sg:address":"37458 State Rte 621",
    "sg:city":"Prairieville",
    "sg:classifiers":[
        {
            "category":"Building & Trades",
            "subcategory":"Landscaping Services",
            "type":"Services"
        }
    ],
    "sg:phone":"+1 225 675 8669",
    "sg:postcode":"70769",
    "sg:province":"LA",
    "sg:tags":[
        "tree"
    ],
    "wof:name":"Affiliated Tree Svc",
    "wof:placetype":"venue"
},
  "geometry": {"coordinates":[-90.973617,30.269613],"type":"Point"}
}