{
  "type": "Feature",
  "properties": {
    "iso:country":"US",
    "sg:address":"8241 US Hwy 84",
    "sg:city":"Ferriday",
    "sg:classifiers":[
        {
            "category":"Personal",
            "subcategory":"Beauty Salon",
            "type":"Services"
        }
    ],
    "sg:phone":"+1 318 757 0173",
    "sg:postcode":"71334",
    "sg:province":"LA",
    "wof:name":"Tangles Hair Salon",
    "wof:placetype":"venue"
},
  "geometry": {"coordinates":[-91.566772,31.630091],"type":"Point"}
}