{
  "type": "Feature",
  "properties": {
    "iso:country":"US",
    "sg:address":"11 Holly Dr",
    "sg:city":"La Place",
    "sg:classifiers":[
        {
            "category":"Professional",
            "subcategory":"Computer Services",
            "type":"Services"
        }
    ],
    "sg:phone":"+1 985 652 7529",
    "sg:postcode":"70068",
    "sg:province":"LA",
    "sg:tags":[
        "internet"
    ],
    "sg:website":"www.communityonline.com",
    "wof:name":"Whitman Internet Svc",
    "wof:placetype":"venue"
},
  "geometry": {"coordinates":[-90.493559,30.068705],"type":"Point"}
}