{
  "type": "Feature",
  "properties": {
    "iso:country":"US",
    "sg:address":"1006 N Reed St",
    "sg:city":"Ville Platte",
    "sg:classifiers":[
        {
            "category":"Health Services",
            "subcategory":"Podiatrist",
            "type":"Services"
        }
    ],
    "sg:phone":"+1 337 363 8552",
    "sg:postcode":"70586",
    "sg:province":"LA",
    "wof:name":"Rosemarie Jack DPM",
    "wof:placetype":"venue"
},
  "geometry": {"coordinates":[-92.27512299999999,30.698038],"type":"Point"}
}