{
  "type": "Feature",
  "properties": {
    "iso:country":"US",
    "sg:address":"11900 Chef Menteur Hwy",
    "sg:city":"New Orleans",
    "sg:classifiers":[
        {
            "category":"Building & Trades",
            "subcategory":"Construction",
            "type":"Services"
        }
    ],
    "sg:phone":"+1 504 246 2410",
    "sg:postcode":"70129",
    "sg:province":"LA",
    "sg:tags":[
        "concrete",
        "contractor"
    ],
    "wof:name":"Lafarge Concrete",
    "wof:placetype":"venue"
},
  "geometry": {"coordinates":[-89.946431,30.024399],"type":"Point"}
}