{
  "type": "Feature",
  "properties": {
    "iso:country":"US",
    "sg:address":"1555 Madison Ave",
    "sg:city":"Baton Rouge",
    "sg:classifiers":[
        {
            "category":"Social Services",
            "type":"Services"
        }
    ],
    "sg:phone":"+1 225 706 0300",
    "sg:postcode":"70802",
    "sg:province":"LA",
    "sg:tags":[
        "counseling"
    ],
    "wof:name":"New Heights Family Health Ctr",
    "wof:placetype":"venue"
},
  "geometry": {"coordinates":[-91.17374,30.467346],"type":"Point"}
}