{
  "type": "Feature",
  "properties": {
    "iso:country":"US",
    "sg:address":"191 Transport Dr",
    "sg:city":"Reserve",
    "sg:classifiers":[
        {
            "category":"Freight",
            "type":"Transportation"
        }
    ],
    "sg:phone":"+1 985 479 3980",
    "sg:postcode":"70084",
    "sg:province":"LA",
    "sg:tags":[
        "operator",
        "trucking"
    ],
    "wof:name":"Oakley Leasing",
    "wof:placetype":"venue"
},
  "geometry": {"coordinates":[-90.58219,30.070185],"type":"Point"}
}