{
  "type": "Feature",
  "properties": {
    "iso:country":"US",
    "sg:address":"105 S Pineville St",
    "sg:city":"Winnfield",
    "sg:classifiers":[
        {
            "category":"Shopping",
            "subcategory":"Gifts & Souvenirs",
            "type":"Retail Goods"
        }
    ],
    "sg:phone":"+1 318 628 1515",
    "sg:postcode":"71483",
    "sg:province":"LA",
    "wof:name":"Pink House",
    "wof:placetype":"venue"
},
  "geometry": {"coordinates":[-92.63224599999999,31.926636],"type":"Point"}
}