{
  "type": "Feature",
  "properties": {
    "iso:country":"US",
    "sg:address":"4933 Janice Ave",
    "sg:city":"Kenner",
    "sg:classifiers":[
        {
            "category":"Wholesale",
            "subcategory":"Electrical",
            "type":"Manufacturing & Wholesale Goods"
        }
    ],
    "sg:phone":"+1 504 888 0135",
    "sg:postcode":"70065",
    "sg:province":"LA",
    "sg:tags":[
        "electric",
        "motor"
    ],
    "wof:name":"Toshiba International Ind Div",
    "wof:placetype":"venue"
},
  "geometry": {"coordinates":[-90.22575500000001,30.023379],"type":"Point"}
}