{
  "type": "Feature",
  "properties": {
    "addr:full":"1836 Hwy 507 Simsboro LA 71275",
    "addr:housenumber":"1836",
    "addr:postcode":"71275",
    "addr:street":"Hwy 507 Simsboro",
    "iso:country":"US",
    "sg:address":"1836 Hwy 507",
    "sg:city":"Simsboro",
    "sg:classifiers":[
        {
            "category":"Shopping",
            "type":"Retail Goods"
        }
    ],
    "sg:phone":"+1 318 247 8155",
    "sg:postcode":"71275",
    "sg:province":"LA",
    "sg:tags":[
        "cosmetic",
        "perfume"
    ],
    "wof:name":"Mary Kay Cosmetics",
    "wof:placetype":"venue"
},
  "geometry": {"coordinates":[-92.80385099999999,32.504603],"type":"Point"}
}