{
  "type": "Feature",
  "properties": {
    "addr:full":"300 Bonita Dr Chalmette LA 70043",
    "addr:housenumber":"300",
    "addr:postcode":"70043",
    "addr:street":"Bonita Dr Chalmette",
    "iso:country":"US",
    "sg:address":"300 Bonita Dr",
    "sg:city":"Chalmette",
    "sg:classifiers":[
        {
            "category":"Wholesale",
            "subcategory":"Groceries",
            "type":"Manufacturing & Wholesale Goods"
        }
    ],
    "sg:phone":"+1 504 270 0361",
    "sg:postcode":"70043",
    "sg:province":"LA",
    "sg:tags":[
        "food",
        "product"
    ],
    "wof:name":"Brother's Foods LLC",
    "wof:placetype":"venue"
},
  "geometry": {"coordinates":[-89.98451799999999,29.936778],"type":"Point"}
}