{
  "type": "Feature",
  "properties": {
    "iso:country":"US",
    "sg:address":"111 N Main St",
    "sg:city":"Breaux Bridge",
    "sg:classifiers":[
        {
            "category":"Professional",
            "subcategory":"Accounting & Tax Preparation",
            "type":"Services"
        }
    ],
    "sg:phone":"+1 337 332 3958",
    "sg:postcode":"70517",
    "sg:province":"LA",
    "sg:tags":[
        "return"
    ],
    "wof:name":"Xpress Tax Inc",
    "wof:placetype":"venue"
},
  "geometry": {"coordinates":[-91.899489,30.273655],"type":"Point"}
}