{
  "type": "Feature",
  "properties": {
    "addr:full":"851 3rd St Kenner LA 70062",
    "addr:housenumber":"851",
    "addr:postcode":"70062",
    "addr:street":"3Rd St",
    "iso:country":"US",
    "sg:address":"851 3rd St",
    "sg:city":"Kenner",
    "sg:classifiers":[
        {
            "category":"Real Estate",
            "subcategory":"Real Estate Operator",
            "type":"Services"
        }
    ],
    "sg:phone":"+1 504 468 1293",
    "sg:postcode":"70062",
    "sg:province":"LA",
    "sg:tags":[
        "apartment"
    ],
    "wof:name":"Malcom Kenner Apartments",
    "wof:placetype":"venue"
},
  "geometry": {"coordinates":[-90.260451,29.976053],"type":"Point"}
}