{
  "type": "Feature",
  "properties": {
    "addr:full":"800 Victor II Blvd Morgan City LA 70380",
    "addr:housenumber":"800",
    "addr:postcode":"70380",
    "addr:street":"Victor Ii Blvd",
    "iso:country":"US",
    "sg:address":"800 Victor II Blvd",
    "sg:city":"Morgan City",
    "sg:classifiers":[
        {
            "category":"Utilities",
            "subcategory":"Cable",
            "type":"Services"
        }
    ],
    "sg:phone":"+1 985 384 8335",
    "sg:postcode":"70380",
    "sg:province":"LA",
    "sg:tags":[
        "television"
    ],
    "wof:name":"Allen's TV Cable Svc Inc",
    "wof:placetype":"venue"
},
  "geometry": {"coordinates":[-91.20041399999999,29.707787],"type":"Point"}
}