{
  "type": "Feature",
  "properties": {
    "addr:full":"230 Monroe St Gretna LA 70053",
    "addr:housenumber":"230",
    "addr:postcode":"70053",
    "addr:street":"Monroe St",
    "iso:country":"US",
    "sg:address":"230 Monroe St",
    "sg:city":"Gretna",
    "sg:classifiers":[
        {
            "category":"Retail",
            "subcategory":"Funeral Services",
            "type":"Services"
        }
    ],
    "sg:phone":"+1 504 361 8649",
    "sg:postcode":"70053",
    "sg:province":"LA",
    "sg:tags":[
        "director",
        "cemetery"
    ],
    "wof:name":"Davis Mortuary Services Inc",
    "wof:placetype":"venue"
},
  "geometry": {"coordinates":[-90.051804,29.9377],"type":"Point"}
}