{
  "type": "Feature",
  "properties": {
    "addr:full":"332 Jefferson St Natchitoches LA 71457",
    "addr:housenumber":"332",
    "addr:postcode":"71457",
    "addr:street":"Jefferson St",
    "iso:country":"US",
    "sg:address":"332 Jefferson St",
    "sg:city":"Natchitoches",
    "sg:classifiers":[
        {
            "category":"Travel",
            "subcategory":"Hotels & Motels",
            "type":"Entertainment"
        }
    ],
    "sg:phone":"+1 318 352 1900",
    "sg:postcode":"71457",
    "sg:province":"LA",
    "sg:tags":[
        "breakfast",
        "accommodation",
        "bed"
    ],
    "wof:name":"Maison Louisiane Historic Bed",
    "wof:placetype":"venue"
},
  "geometry": {"coordinates":[-93.08751599999999,31.756435],"type":"Point"}
}