{
  "type": "Feature",
  "properties": {
    "iso:country":"US",
    "sg:address":"723 Canal St",
    "sg:city":"New Orleans",
    "sg:classifiers":[
        {
            "category":"Shopping",
            "subcategory":"Gifts & Souvenirs",
            "type":"Retail Goods"
        }
    ],
    "sg:phone":"+1 504 524 6161",
    "sg:postcode":"70130",
    "sg:province":"LA",
    "sg:tags":[
        "shop"
    ],
    "wof:name":"Sunshine Sportswear Co",
    "wof:placetype":"venue"
},
  "geometry": {"coordinates":[-90.06965599999999,29.953804],"type":"Point"}
}