{
  "type": "Feature",
  "properties": {
    "iso:country":"US",
    "sg:address":"3240 S Carrollton Ave",
    "sg:city":"New Orleans",
    "sg:classifiers":[
        {
            "category":"Banks & Credit Unions",
            "subcategory":"Bank",
            "type":"Services"
        }
    ],
    "sg:phone":"+1 504 482 9301",
    "sg:postcode":"70118",
    "sg:province":"LA",
    "sg:tags":[
        "cashing",
        "check"
    ],
    "wof:name":"Louisiana Cash Advance",
    "wof:placetype":"venue"
},
  "geometry": {"coordinates":[-90.113947,29.962174],"type":"Point"}
}