{
  "type": "Feature",
  "properties": {
    "addr:full":"128 Kentwood Dr Carencro LA 70520",
    "addr:housenumber":"128",
    "addr:postcode":"70520",
    "addr:street":"Kentwood Dr",
    "iso:country":"US",
    "sg:address":"128 Kentwood Dr",
    "sg:city":"Carencro",
    "sg:classifiers":[
        {
            "category":"Building & Trades",
            "subcategory":"Construction",
            "type":"Services"
        }
    ],
    "sg:phone":"+1 337 896 8647",
    "sg:postcode":"70520",
    "sg:province":"LA",
    "sg:tags":[
        "maker",
        "cabinet"
    ],
    "wof:name":"Stelly's Cabinet Works",
    "wof:placetype":"venue"
},
  "geometry": {"coordinates":[-92.04520599999999,30.302896],"type":"Point"}
}