{
  "type": "Feature",
  "properties": {
    "iso:country":"US",
    "sg:address":"104 Fondale St",
    "sg:city":"Monroe",
    "sg:classifiers":[
        {
            "category":"Organizations",
            "subcategory":"Religious Organization",
            "type":"Services"
        }
    ],
    "sg:phone":"+1 318 398 0930",
    "sg:postcode":"71202",
    "sg:province":"LA",
    "sg:tags":[
        "church"
    ],
    "wof:name":"Mount Arack Baptist Church",
    "wof:placetype":"venue"
},
  "geometry": {"coordinates":[-92.079111,32.483585],"type":"Point"}
}