{
  "type": "Feature",
  "properties": {
    "iso:country":"US",
    "sg:address":"320 Pontchartrain Dr",
    "sg:city":"Slidell",
    "sg:classifiers":[
        {
            "category":"Shopping",
            "type":"Retail Goods"
        }
    ],
    "sg:phone":"+1 985 641 5211",
    "sg:postcode":"70458",
    "sg:province":"LA",
    "sg:tags":[
        "repair",
        "electrical",
        "merchandise"
    ],
    "wof:name":"Beltone Hearing Aid Svc",
    "wof:placetype":"venue"
},
  "geometry": {"coordinates":[-89.78664000000001,30.26655],"type":"Point"}
}