{
  "type": "Feature",
  "properties": {
    "iso:country":"US",
    "sg:address":"11670 Cedar Park Ave",
    "sg:city":"Baton Rouge",
    "sg:classifiers":[
        {
            "category":"Communications",
            "subcategory":"Film & Video Production",
            "type":"Services"
        }
    ],
    "sg:phone":"+1 225 751 3456",
    "sg:postcode":"70809",
    "sg:province":"LA",
    "sg:tags":[
        "taping"
    ],
    "wof:name":"3rd Coast Digital Films",
    "wof:placetype":"venue"
},
  "geometry": {"coordinates":[-91.052747,30.389064],"type":"Point"}
}