{
  "type": "Feature",
  "properties": {
    "iso:country":"US",
    "sg:address":"700 N 4th St",
    "sg:city":"Monroe",
    "sg:classifiers":[
        {
            "category":"Banks & Credit Unions",
            "subcategory":"Bank",
            "type":"Services"
        }
    ],
    "sg:phone":"+1 318 362 4420",
    "sg:postcode":"71201",
    "sg:province":"LA",
    "wof:name":"Bank One",
    "wof:placetype":"venue"
},
  "geometry": {"coordinates":[-92.11954900000001,32.509299],"type":"Point"}
}