{
  "type": "Feature",
  "properties": {
    "addr:full":"125 W Mcneese St Lake Charles LA 70605",
    "addr:housenumber":"125",
    "addr:postcode":"70605",
    "addr:street":"W Mcneese St",
    "iso:country":"US",
    "sg:address":"125 W Mcneese St",
    "sg:city":"Lake Charles",
    "sg:classifiers":[
        {
            "category":"Restaurant",
            "type":"Food & Drink"
        }
    ],
    "sg:menulink":"http://www.allmenus.com/la/lake-charles/132082-subway/menu/",
    "sg:phone":"+1 337 474 1302",
    "sg:postcode":"70605",
    "sg:province":"LA",
    "sg:tags":[
        "american",
        "sandwich"
    ],
    "wof:name":"Subway",
    "wof:placetype":"venue"
},
  "geometry": {"coordinates":[-93.21895600000001,30.176168],"type":"Point"}
}