{
  "type": "Feature",
  "properties": {
    "iso:country":"US",
    "sg:address":"511 N Solomon St",
    "sg:city":"New Orleans",
    "sg:classifiers":[
        {
            "category":"Shopping",
            "subcategory":"Used Merchandise",
            "type":"Retail Goods"
        }
    ],
    "sg:phone":"+1 504 488 5524",
    "sg:postcode":"70119",
    "sg:province":"LA",
    "sg:tags":[
        "antique"
    ],
    "wof:name":"Ricca's Architectural Sales",
    "wof:placetype":"venue"
},
  "geometry": {"coordinates":[-90.09890799999999,29.979517],"type":"Point"}
}