{
  "type": "Feature",
  "properties": {
    "iso:country":"US",
    "sg:address":"2613 Jasmine St",
    "sg:city":"New Orleans",
    "sg:classifiers":[
        {
            "category":"Bars & Pubs",
            "subcategory":"Nightclub",
            "type":"Food & Drink"
        }
    ],
    "sg:phone":"+1 504 945 4588",
    "sg:postcode":"70122",
    "sg:province":"LA",
    "sg:tags":[
        "nightlife"
    ],
    "wof:name":"Jakel's Fourth Edition",
    "wof:placetype":"venue"
},
  "geometry": {"coordinates":[-90.04979400000001,30.000994],"type":"Point"}
}