{
  "type": "Feature",
  "properties": {
    "iso:country":"US",
    "sg:address":"2421 Monterrey Dr",
    "sg:city":"Baton Rouge",
    "sg:classifiers":[
        {
            "category":"Retail",
            "subcategory":"Auto Repair",
            "type":"Services"
        }
    ],
    "sg:phone":"+1 225 924 7098",
    "sg:postcode":"70814",
    "sg:province":"LA",
    "sg:tags":[
        "repairing",
        "engine"
    ],
    "wof:name":"Airline Diesel Svc Inc",
    "wof:placetype":"venue"
},
  "geometry": {"coordinates":[-91.083861,30.473892],"type":"Point"}
}