{
  "type": "Feature",
  "properties": {
    "addr:full":"1855 Ames Blvd Marrero LA 70072",
    "addr:housenumber":"1855",
    "addr:postcode":"70072",
    "addr:street":"Ames Blvd Marrero",
    "iso:country":"US",
    "sg:address":"1855 Ames Blvd",
    "sg:city":"Marrero",
    "sg:classifiers":[
        {
            "category":"Government",
            "subcategory":"Office",
            "type":"Public Place"
        }
    ],
    "sg:phone":"+1 504 349 8802",
    "sg:postcode":"70072",
    "sg:province":"LA",
    "sg:tags":[
        "state",
        "program",
        "health"
    ],
    "wof:name":"Public Health Dept",
    "wof:placetype":"venue"
},
  "geometry": {"coordinates":[-90.114058,29.881258],"type":"Point"}
}