{
  "type": "Feature",
  "properties": {
    "iso:country":"US",
    "sg:address":"914 Julia St",
    "sg:city":"New Orleans",
    "sg:classifiers":[
        {
            "category":"Freight",
            "type":"Transportation"
        }
    ],
    "sg:phone":"+1 504 522 2028",
    "sg:postcode":"70130",
    "sg:province":"LA",
    "sg:tags":[
        "delivery"
    ],
    "wof:name":"Speed Wheels Express",
    "wof:placetype":"venue"
},
  "geometry": {"coordinates":[-90.07523399999999,29.94663],"type":"Point"}
}