{
  "type": "Feature",
  "properties": {
    "addr:full":"1739 N Claiborne Ave New Orleans LA 70116",
    "addr:housenumber":"1739",
    "addr:postcode":"70116",
    "addr:street":"N Claiborne Ave",
    "iso:country":"US",
    "sg:address":"1739 N Claiborne Ave",
    "sg:city":"New Orleans",
    "sg:classifiers":[
        {
            "category":"Organizations",
            "subcategory":"Community Association",
            "type":"Services"
        }
    ],
    "sg:phone":"+1 504 945 1580",
    "sg:postcode":"70116",
    "sg:province":"LA",
    "sg:tags":[
        "club"
    ],
    "wof:name":"Club Malibou",
    "wof:placetype":"venue"
},
  "geometry": {"coordinates":[-90.062798,29.973312],"type":"Point"}
}