{
  "type": "Feature",
  "properties": {
    "addr:full":"1922 Washington St Franklinton LA 70438",
    "addr:housenumber":"1922",
    "addr:postcode":"70438",
    "addr:street":"Washington St",
    "iso:country":"US",
    "sg:address":"1922 Washington St",
    "sg:city":"Franklinton",
    "sg:classifiers":[
        {
            "category":"Insurance",
            "subcategory":"Insurance Agent",
            "type":"Services"
        }
    ],
    "sg:phone":"+1 985 839 6714",
    "sg:postcode":"70438",
    "sg:province":"LA",
    "wof:name":"Arm Insurance Agcy Franklinton",
    "wof:placetype":"venue"
},
  "geometry": {"coordinates":[-90.14019399999999,30.846361],"type":"Point"}
}