{
  "type": "Feature",
  "properties": {
    "iso:country":"US",
    "sg:address":"1904 24th St",
    "sg:city":"Kenner",
    "sg:classifiers":[
        {
            "category":"Government",
            "subcategory":"Office",
            "type":"Public Place"
        }
    ],
    "sg:phone":"+1 504 468 4075",
    "sg:postcode":"70062",
    "sg:province":"LA",
    "sg:tags":[
        "village"
    ],
    "wof:name":"Kenner Brake Tag Station",
    "wof:placetype":"venue"
},
  "geometry": {"coordinates":[-90.241162,29.999756],"type":"Point"}
}