{
  "type": "Feature",
  "properties": {
    "iso:country":"US",
    "sg:address":"1307 Meeks St",
    "sg:city":"Bastrop",
    "sg:classifiers":[
        {
            "category":"Social Services",
            "type":"Services"
        }
    ],
    "sg:phone":"+1 318 283 2078",
    "sg:postcode":"71220",
    "sg:province":"LA",
    "sg:tags":[
        "outreach",
        "center"
    ],
    "wof:name":"Walter Parish Outreach Center",
    "wof:placetype":"venue"
},
  "geometry": {"coordinates":[-91.898563,32.765817],"type":"Point"}
}