{
  "type": "Feature",
  "properties": {
    "addr:full":"1016 Delery St New Orleans LA 70117",
    "addr:housenumber":"1016",
    "addr:postcode":"70117",
    "addr:street":"Delery St",
    "iso:country":"US",
    "sg:address":"1016 Delery St",
    "sg:city":"New Orleans",
    "sg:classifiers":[
        {
            "category":"Organizations",
            "subcategory":"Religious Organization",
            "type":"Services"
        }
    ],
    "sg:phone":"+1 504 271 7889",
    "sg:postcode":"70117",
    "sg:province":"LA",
    "sg:tags":[
        "church"
    ],
    "wof:name":"Holy Bible Baptist Church",
    "wof:placetype":"venue"
},
  "geometry": {"coordinates":[-90.008376,29.958625],"type":"Point"}
}