{
  "type": "Feature",
  "properties": {
    "addr:full":"220 Travis St Shreveport LA 71101",
    "addr:housenumber":"220",
    "addr:postcode":"71101",
    "addr:street":"Travis St",
    "iso:country":"US",
    "sg:address":"220 Travis St",
    "sg:city":"Shreveport",
    "sg:classifiers":[
        {
            "category":"Professional",
            "subcategory":"Accounting & Tax Preparation",
            "type":"Services"
        }
    ],
    "sg:phone":"+1 318 424 6606",
    "sg:postcode":"71101",
    "sg:province":"LA",
    "sg:tags":[
        "billing"
    ],
    "wof:name":"Medinomics",
    "wof:placetype":"venue"
},
  "geometry": {"coordinates":[-93.74847699999999,32.515287],"type":"Point"}
}