{
  "type": "Feature",
  "properties": {
    "iso:country":"US",
    "sg:address":"124 Setter Ln",
    "sg:city":"Pearl River",
    "sg:classifiers":[
        {
            "category":"Professional",
            "type":"Services"
        }
    ],
    "sg:phone":"+1 985 863 9877",
    "sg:postcode":"70452",
    "sg:province":"LA",
    "sg:tags":[
        "establishment"
    ],
    "wof:name":"United Fire Group",
    "wof:placetype":"venue"
},
  "geometry": {"coordinates":[-89.74223499999999,30.329524],"type":"Point"}
}