{
  "type": "Feature",
  "properties": {
    "iso:country":"US",
    "sg:address":"218 Circle Dr",
    "sg:city":"Franklin",
    "sg:classifiers":[
        {
            "category":"Real Estate",
            "subcategory":"Real Estate Agent",
            "type":"Services"
        }
    ],
    "sg:phone":"+1 337 828 1915",
    "sg:postcode":"70538",
    "sg:province":"LA",
    "wof:name":"Little Management LLC",
    "wof:placetype":"venue"
},
  "geometry": {"coordinates":[-91.499028,29.802362],"type":"Point"}
}