{
  "type": "Feature",
  "properties": {
    "iso:country":"US",
    "sg:address":"1801 State Rte 30",
    "sg:city":"Gonzales",
    "sg:classifiers":[
        {
            "category":"Wholesale",
            "subcategory":"Sporting Goods",
            "type":"Manufacturing & Wholesale Goods"
        }
    ],
    "sg:phone":"+1 225 644 3116",
    "sg:postcode":"70737",
    "sg:province":"LA",
    "sg:tags":[
        "broker",
        "boat"
    ],
    "wof:name":"Ronald's Boat Broker",
    "wof:placetype":"venue"
},
  "geometry": {"coordinates":[-90.939317,30.210667],"type":"Point"}
}