{
  "type": "Feature",
  "properties": {
    "iso:country":"US",
    "sg:address":"1408 Manhattan Blvd",
    "sg:city":"Harvey",
    "sg:classifiers":[
        {
            "category":"Museum",
            "type":"Entertainment"
        }
    ],
    "sg:phone":"+1 504 366 9124",
    "sg:postcode":"70058",
    "sg:province":"LA",
    "sg:tags":[
        "organization",
        "arts",
        "information"
    ],
    "wof:name":"Southern Arts Consortium",
    "wof:placetype":"venue"
},
  "geometry": {"coordinates":[-90.059617,29.893483],"type":"Point"}
}