{
  "type": "Feature",
  "properties": {
    "iso:country":"US",
    "sg:address":"3221 Carey St",
    "sg:city":"Slidell",
    "sg:classifiers":[
        {
            "category":"Education",
            "subcategory":"School",
            "type":"Public Place"
        }
    ],
    "sg:phone":"+1 985 646 4920",
    "sg:postcode":"70458",
    "sg:province":"LA",
    "wof:name":"Sainttawny Paris School Board",
    "wof:placetype":"venue"
},
  "geometry": {"coordinates":[-89.78862599999999,30.261225],"type":"Point"}
}