{
  "type": "Feature",
  "properties": {
    "iso:country":"US",
    "sg:address":"800 S Clearview Pkwy",
    "sg:city":"Harahan",
    "sg:classifiers":[
        {
            "category":"Personal",
            "subcategory":"Beauty Salon",
            "type":"Services"
        }
    ],
    "sg:phone":"+1 504 734 7337",
    "sg:postcode":"70123",
    "sg:province":"LA",
    "wof:name":"Supercuts",
    "wof:placetype":"venue"
},
  "geometry": {"coordinates":[-90.18019700000001,29.95355],"type":"Point"}
}