{
  "type": "Feature",
  "properties": {
    "iso:country":"US",
    "sg:address":"2815 Pargoud Blvd",
    "sg:city":"Monroe",
    "sg:classifiers":[
        {
            "category":"Professional",
            "type":"Services"
        }
    ],
    "sg:phone":"+1 318 323 9772",
    "sg:postcode":"71201",
    "sg:province":"LA",
    "wof:name":"Arrowhead Valley Descript",
    "wof:placetype":"venue"
},
  "geometry": {"coordinates":[-92.11409999999999,32.548009],"type":"Point"}
}