{
  "type": "Feature",
  "properties": {
    "iso:country":"US",
    "sg:address":"6715 State Rte 394",
    "sg:city":"Dry Creek",
    "sg:classifiers":[
        {
            "category":"Manufacturing",
            "subcategory":"Tools & Machinery",
            "type":"Manufacturing & Wholesale Goods"
        }
    ],
    "sg:phone":"+1 337 328 8016",
    "sg:postcode":"70634",
    "sg:province":"LA",
    "sg:tags":[
        "machine",
        "shop"
    ],
    "wof:name":"Dale's Machine & Fabrication",
    "wof:placetype":"venue"
},
  "geometry": {"coordinates":[-93.07551100000001,30.690118],"type":"Point"}
}