{
  "type": "Feature",
  "properties": {
    "iso:country":"US",
    "sg:address":"5489 Campus Dr",
    "sg:city":"Shreveport",
    "sg:classifiers":[
        {
            "category":"Manufacturing",
            "subcategory":"Tools & Machinery",
            "type":"Manufacturing & Wholesale Goods"
        }
    ],
    "sg:phone":"+1 318 219 7051",
    "sg:postcode":"71129",
    "sg:province":"LA",
    "sg:tags":[
        "food",
        "mixer"
    ],
    "sg:website":"www.varimixer.com",
    "wof:name":"Varimixer",
    "wof:placetype":"venue"
},
  "geometry": {"coordinates":[-93.84456900000001,32.426921],"type":"Point"}
}