{
  "type": "Feature",
  "properties": {
    "iso:country":"US",
    "sg:address":"8835 Line Ave",
    "sg:city":"Shreveport",
    "sg:classifiers":[
        {
            "category":"Banks & Credit Unions",
            "subcategory":"Bank",
            "type":"Services"
        }
    ],
    "sg:phone":"+1 318 868 2098",
    "sg:postcode":"71106",
    "sg:province":"LA",
    "sg:tags":[
        "loan",
        "real estate"
    ],
    "wof:name":"Wells Fargo Home Mortgage Inc",
    "wof:placetype":"venue"
},
  "geometry": {"coordinates":[-93.736453,32.41812],"type":"Point"}
}