{
  "type": "Feature",
  "properties": {
    "iso:country":"US",
    "sg:address":"729 Canal St",
    "sg:city":"New Orleans",
    "sg:classifiers":[
        {
            "category":"Shopping",
            "subcategory":"Gifts & Souvenirs",
            "type":"Retail Goods"
        }
    ],
    "sg:phone":"+1 504 412 9560",
    "sg:postcode":"70130",
    "sg:province":"LA",
    "sg:tags":[
        "shop"
    ],
    "wof:name":"Zydeco Jambalaya",
    "wof:placetype":"venue"
},
  "geometry": {"coordinates":[-90.06961099999999,29.953769],"type":"Point"}
}