{
  "type": "Feature",
  "properties": {
    "iso:country":"US",
    "sg:address":"40161 Onyx St",
    "sg:city":"Slidell",
    "sg:classifiers":[
        {
            "category":"Building & Trades",
            "subcategory":"Plumbing",
            "type":"Services"
        }
    ],
    "sg:phone":"+1 985 847 9999",
    "sg:postcode":"70461",
    "sg:province":"LA",
    "sg:tags":[
        "conditioning",
        "air",
        "system",
        "contractor"
    ],
    "wof:name":"Air Force Cooling & Heating",
    "wof:placetype":"venue"
},
  "geometry": {"coordinates":[-89.732311,30.295821],"type":"Point"}
}