{
  "type": "Feature",
  "properties": {
    "addr:full":"121 Dino St Pierre Part LA 70339",
    "addr:housenumber":"121",
    "addr:postcode":"70339",
    "addr:street":"Dino St",
    "iso:country":"US",
    "sg:address":"121 Dino St",
    "sg:city":"Pierre Part",
    "sg:classifiers":[
        {
            "category":"Building & Trades",
            "subcategory":"Plumbing",
            "type":"Services"
        }
    ],
    "sg:phone":"+1 985 252 9622",
    "sg:postcode":"70339",
    "sg:province":"LA",
    "sg:tags":[
        "tank",
        "septic"
    ],
    "wof:name":"R & T Sewer Systems",
    "wof:placetype":"venue"
},
  "geometry": {"coordinates":[-91.215046,29.939719],"type":"Point"}
}