{
  "type": "Feature",
  "properties": {
    "iso:country":"US",
    "sg:address":"961 Patrick Rd",
    "sg:city":"Natchitoches",
    "sg:classifiers":[
        {
            "category":"Recreation",
            "type":"Entertainment"
        }
    ],
    "sg:phone":"+1 318 352 4718",
    "sg:postcode":"71457",
    "sg:province":"LA",
    "sg:tags":[
        "club",
        "membership"
    ],
    "wof:name":"Zackery Road Hunting Club",
    "wof:placetype":"venue"
},
  "geometry": {"coordinates":[-93.035363,31.681513],"type":"Point"}
}