{
  "type": "Feature",
  "properties": {
    "iso:country":"US",
    "sg:address":"232 US Hwy 171",
    "sg:city":"Lake Charles",
    "sg:classifiers":[
        {
            "category":"Autos & Motor Vehicles",
            "subcategory":"Automobile Sales",
            "type":"Retail Goods"
        }
    ],
    "sg:phone":"+1 337 855 5133",
    "sg:postcode":"70611",
    "sg:province":"LA",
    "sg:tags":[
        "car",
        "dealer"
    ],
    "wof:name":"Cars Inc",
    "wof:placetype":"venue"
},
  "geometry": {"coordinates":[-93.194901,30.30627],"type":"Point"}
}