{
  "type": "Feature",
  "properties": {
    "iso:country":"US",
    "sg:address":"240 Rees St",
    "sg:city":"Breaux Bridge",
    "sg:classifiers":[
        {
            "category":"Banks & Credit Unions",
            "subcategory":"Bank",
            "type":"Services"
        }
    ],
    "sg:phone":"+1 337 332 4160",
    "sg:postcode":"70517",
    "sg:province":"LA",
    "sg:tags":[
        "loan"
    ],
    "wof:name":"Brenco Finance Inc",
    "wof:placetype":"venue"
},
  "geometry": {"coordinates":[-91.897887,30.277192],"type":"Point"}
}