{
  "type": "Feature",
  "properties": {
    "iso:country":"US",
    "sg:address":"5110 Butter Creek Ln",
    "sg:city":"Baton Rouge",
    "sg:classifiers":[
        {
            "category":"Food & Beverages",
            "subcategory":"Specialty",
            "type":"Retail Goods"
        }
    ],
    "sg:phone":"+1 225 769 4321",
    "sg:postcode":"70809",
    "sg:province":"LA",
    "sg:tags":[
        "herb"
    ],
    "wof:name":"Herbs & Wellness",
    "wof:placetype":"venue"
},
  "geometry": {"coordinates":[-91.099541,30.396896],"type":"Point"}
}