{
  "type": "Feature",
  "properties": {
    "iso:country":"US",
    "sg:address":"127 Vincent Ave",
    "sg:city":"Metairie",
    "sg:classifiers":[
        {
            "category":"Professional",
            "subcategory":"Management & Consulting",
            "type":"Services"
        }
    ],
    "sg:phone":"+1 504 837 8494",
    "sg:postcode":"70005",
    "sg:province":"LA",
    "sg:tags":[
        "consultant",
        "safety"
    ],
    "wof:name":"Synergy Management",
    "wof:placetype":"venue"
},
  "geometry": {"coordinates":[-90.128546,29.981703],"type":"Point"}
}