{
  "type": "Feature",
  "properties": {
    "addr:full":"502 Highland St Winnsboro LA 71295",
    "addr:housenumber":"502",
    "addr:postcode":"71295",
    "addr:street":"Highland St",
    "iso:country":"US",
    "sg:address":"502 Highland St",
    "sg:city":"Winnsboro",
    "sg:classifiers":[
        {
            "category":"Organizations",
            "subcategory":"Religious Organization",
            "type":"Services"
        }
    ],
    "sg:phone":"+1 318 435 4359",
    "sg:postcode":"71295",
    "sg:province":"LA",
    "sg:tags":[
        "church"
    ],
    "wof:name":"First Baptist Church",
    "wof:placetype":"venue"
},
  "geometry": {"coordinates":[-91.718566,32.162241],"type":"Point"}
}