{
  "type": "Feature",
  "properties": {
    "iso:country":"US",
    "sg:address":"13323 US Hwy 90",
    "sg:city":"Boutte",
    "sg:classifiers":[
        {
            "category":"Shopping",
            "type":"Retail Goods"
        }
    ],
    "sg:phone":"+1 985 785 2199",
    "sg:postcode":"70039",
    "sg:province":"LA",
    "sg:tags":[
        "religious"
    ],
    "wof:name":"For Heaven's Sake",
    "wof:placetype":"venue"
},
  "geometry": {"coordinates":[-90.377516,29.904683],"type":"Point"}
}