{
  "type": "Feature",
  "properties": {
    "iso:country":"US",
    "sg:address":"401 N Holtzman Ave",
    "sg:city":"Shreveport",
    "sg:classifiers":[
        {
            "category":"Education",
            "subcategory":"School",
            "type":"Public Place"
        }
    ],
    "sg:phone":"+1 318 222 5606",
    "sg:postcode":"71101",
    "sg:province":"LA",
    "wof:name":"Ingersoll Elementary School",
    "wof:placetype":"venue"
},
  "geometry": {"coordinates":[-93.77169499999999,32.513619],"type":"Point"}
}