{
  "type": "Feature",
  "properties": {
    "iso:country":"US",
    "sg:address":"532 Central Loop",
    "sg:city":"Robeline",
    "sg:classifiers":[
        {
            "category":"Retail",
            "subcategory":"Auto Repair",
            "type":"Services"
        }
    ],
    "sg:phone":"+1 318 472 9585",
    "sg:postcode":"71469",
    "sg:province":"LA",
    "sg:tags":[
        "repairing",
        "automobile"
    ],
    "wof:name":"Roger's Auto Repair",
    "wof:placetype":"venue"
},
  "geometry": {"coordinates":[-93.304717,31.670169],"type":"Point"}
}