{
  "type": "Feature",
  "properties": {
    "iso:country":"US",
    "sg:address":"1013 E Lincoln Rd",
    "sg:city":"Ville Platte",
    "sg:classifiers":[
        {
            "category":"Health Services",
            "subcategory":"Doctor",
            "type":"Services"
        }
    ],
    "sg:phone":"+1 337 363 5658",
    "sg:postcode":"70586",
    "sg:province":"LA",
    "sg:tags":[
        "physician",
        "surgeon"
    ],
    "wof:name":"Francisco C Zarate LTD",
    "wof:placetype":"venue"
},
  "geometry": {"coordinates":[-92.25662800000001,30.692737],"type":"Point"}
}