{
  "type": "Feature",
  "properties": {
    "iso:country":"US",
    "sg:address":"108 Burgess Dr",
    "sg:city":"Broussard",
    "sg:classifiers":[
        {
            "category":"Manufacturing",
            "subcategory":"Tools & Machinery",
            "type":"Manufacturing & Wholesale Goods"
        }
    ],
    "sg:phone":"+1 337 839 0509",
    "sg:postcode":"70518",
    "sg:province":"LA",
    "sg:tags":[
        "machine",
        "shop"
    ],
    "wof:name":"FUSION Plus",
    "wof:placetype":"venue"
},
  "geometry": {"coordinates":[-91.959739,30.154484],"type":"Point"}
}