{
  "type": "Feature",
  "properties": {
    "iso:country":"US",
    "sg:address":"3730 E Texas St",
    "sg:city":"Bossier City",
    "sg:classifiers":[
        {
            "category":"Home & Garden",
            "subcategory":"Mobile Homes",
            "type":"Retail Goods"
        }
    ],
    "sg:phone":"+1 318 752 4663",
    "sg:postcode":"71111",
    "sg:province":"LA",
    "wof:name":"Clayton Homes",
    "wof:placetype":"venue"
},
  "geometry": {"coordinates":[-93.685895,32.529213],"type":"Point"}
}