{
  "type": "Feature",
  "properties": {
    "addr:full":"1140 W Northern Ave Crowley LA 70526",
    "addr:housenumber":"1140",
    "addr:postcode":"70526",
    "addr:street":"W Northern Ave",
    "iso:country":"US",
    "sg:address":"1140 W Northern Ave",
    "sg:city":"Crowley",
    "sg:classifiers":[
        {
            "category":"Personal",
            "subcategory":"Beauty Salon",
            "type":"Services"
        }
    ],
    "sg:phone":"+1 337 783 7846",
    "sg:postcode":"70526",
    "sg:province":"LA",
    "sg:tags":[
        "shop"
    ],
    "wof:name":"Pat's Hair Shop",
    "wof:placetype":"venue"
},
  "geometry": {"coordinates":[-92.39066200000001,30.216802],"type":"Point"}
}