{
  "type": "Feature",
  "properties": {
    "iso:country":"US",
    "sg:address":"400 Highway Dr",
    "sg:city":"Jefferson",
    "sg:classifiers":[
        {
            "category":"Manufacturing",
            "subcategory":"Tools & Machinery",
            "type":"Manufacturing & Wholesale Goods"
        }
    ],
    "sg:phone":"+1 504 833 2279",
    "sg:postcode":"70121",
    "sg:province":"LA",
    "sg:tags":[
        "machine",
        "shop"
    ],
    "wof:name":"Wayne Des Dunes Inc",
    "wof:placetype":"venue"
},
  "geometry": {"coordinates":[-90.170367,29.960382],"type":"Point"}
}