{
  "type": "Feature",
  "properties": {
    "addr:full":"655 E Madison Ave Bastrop LA 71220",
    "addr:housenumber":"655",
    "addr:postcode":"71220",
    "addr:street":"E Madison Ave",
    "iso:country":"US",
    "sg:address":"655 E Madison Ave",
    "sg:city":"Bastrop",
    "sg:classifiers":[
        {
            "category":"Shopping",
            "subcategory":"Used Merchandise",
            "type":"Retail Goods"
        }
    ],
    "sg:phone":"+1 318 283 5755",
    "sg:postcode":"71220",
    "sg:province":"LA",
    "sg:tags":[
        "shop",
        "consignment"
    ],
    "wof:name":"Almost Perfect",
    "wof:placetype":"venue"
},
  "geometry": {"coordinates":[-91.90609000000001,32.778756],"type":"Point"}
}