{
  "type": "Feature",
  "properties": {
    "addr:full":"4520 Clearlake Dr Metairie LA 70006",
    "addr:housenumber":"4520",
    "addr:postcode":"70006",
    "addr:street":"Clearlake Dr",
    "iso:country":"US",
    "sg:address":"4520 Clearlake Dr",
    "sg:city":"Metairie",
    "sg:classifiers":[
        {
            "category":"Shopping",
            "subcategory":"Computers & Home Electronics",
            "type":"Retail Goods"
        }
    ],
    "sg:phone":"+1 504 455 4783",
    "sg:postcode":"70006",
    "sg:province":"LA",
    "sg:tags":[
        "software"
    ],
    "sg:website":"www.gentechsoftware.com",
    "wof:name":"Gen Tech Software Inc",
    "wof:placetype":"venue"
},
  "geometry": {"coordinates":[-90.192283,30.019179],"type":"Point"}
}