{
  "type": "Feature",
  "properties": {
    "iso:country":"US",
    "sg:address":"805 Veterans Dr",
    "sg:city":"Carencro",
    "sg:classifiers":[
        {
            "category":"Banks & Credit Unions",
            "subcategory":"Bank",
            "type":"Services"
        },
        {
            "category":"Banks & Credit Unions",
            "subcategory":"Financial Services",
            "type":"Services"
        }
    ],
    "sg:phone":"+1 337 521 4960",
    "sg:postcode":"70520",
    "sg:province":"LA",
    "sg:tags":[
        "broker",
        "mortgage"
    ],
    "wof:name":"Iberiabank Member Fdic",
    "wof:placetype":"venue"
},
  "geometry": {"coordinates":[-92.04121600000001,30.321868],"type":"Point"}
}