{
  "type": "Feature",
  "properties": {
    "iso:country":"US",
    "sg:address":"1188 Rosenwald Rd",
    "sg:city":"Baton Rouge",
    "sg:classifiers":[
        {
            "category":"Real Estate",
            "subcategory":"Real Estate Operator",
            "type":"Services"
        }
    ],
    "sg:phone":"+1 225 775 9224",
    "sg:postcode":"70807",
    "sg:province":"LA",
    "sg:tags":[
        "apartment"
    ],
    "wof:name":"Ashley Oak Apartments",
    "wof:placetype":"venue"
},
  "geometry": {"coordinates":[-91.182089,30.531309],"type":"Point"}
}