{
  "type": "Feature",
  "properties": {
    "addr:full":"305 Unkle Camp Rd Kinder LA 70648",
    "addr:housenumber":"305",
    "addr:postcode":"70648",
    "addr:street":"Unkle Camp Rd",
    "iso:country":"US",
    "sg:address":"305 Unkle Camp Rd",
    "sg:city":"Kinder",
    "sg:classifiers":[
        {
            "category":"Freight",
            "type":"Transportation"
        },
        {
            "category":"Building & Trades",
            "subcategory":"Construction",
            "type":"Services"
        }
    ],
    "sg:phone":"+1 337 738 2882",
    "sg:postcode":"70648",
    "sg:province":"LA",
    "sg:tags":[
        "operator",
        "trucking",
        "general",
        "local",
        "contractor"
    ],
    "wof:name":"D J Bell Trucking",
    "wof:placetype":"venue"
},
  "geometry": {"coordinates":[-92.918879,30.489536],"type":"Point"}
}