{
  "type": "Feature",
  "properties": {
    "iso:country":"US",
    "sg:address":"1202 N Hwy 190",
    "sg:city":"Covington",
    "sg:classifiers":[
        {
            "category":"Restaurant",
            "type":"Food & Drink"
        }
    ],
    "sg:phone":"+1 985 809 0969",
    "sg:postcode":"70433",
    "sg:province":"LA",
    "sg:website":"www.bouleprimehouse.com",
    "wof:name":"Boule' Prime House",
    "wof:placetype":"venue"
},
  "geometry": {"coordinates":[-90.08196,30.448149],"type":"Point"}
}