{
  "type": "Feature",
  "properties": {
    "iso:country":"US",
    "sg:address":"2603 Millie St",
    "sg:city":"Marrero",
    "sg:classifiers":[
        {
            "category":"Building & Trades",
            "subcategory":"Construction",
            "type":"Services"
        }
    ],
    "sg:phone":"+1 504 347 9130",
    "sg:postcode":"70003",
    "sg:province":"LA",
    "sg:tags":[
        "house"
    ],
    "wof:name":"JBL Homes",
    "wof:placetype":"venue"
},
  "geometry": {"coordinates":[-90.201645,29.999556],"type":"Point"}
}