{
  "type": "Feature",
  "properties": {
    "iso:country":"US",
    "sg:address":"419 Crew Lake Loop",
    "sg:city":"Rayville",
    "sg:classifiers":[
        {
            "category":"Building & Trades",
            "subcategory":"Construction",
            "type":"Services"
        }
    ],
    "sg:phone":"+1 318 728 8963",
    "sg:postcode":"71269",
    "sg:province":"LA",
    "sg:tags":[
        "nonresidential"
    ],
    "wof:name":"C Roy Builders Inc",
    "wof:placetype":"venue"
},
  "geometry": {"coordinates":[-91.862787,32.490944],"type":"Point"}
}