{
  "type": "Feature",
  "properties": {
    "iso:country":"US",
    "sg:address":"2210 Justice St",
    "sg:city":"Monroe",
    "sg:classifiers":[
        {
            "category":"Professional",
            "subcategory":"Research",
            "type":"Services"
        }
    ],
    "sg:phone":"+1 318 387 4628",
    "sg:postcode":"71201",
    "sg:province":"LA",
    "sg:tags":[
        "environmental",
        "ecological"
    ],
    "wof:name":"IETC",
    "wof:placetype":"venue"
},
  "geometry": {"coordinates":[-92.10694700000001,32.537058],"type":"Point"}
}