{
  "type": "Feature",
  "properties": {
    "iso:country":"US",
    "sg:address":"4027 N Claiborne Ave",
    "sg:city":"New Orleans",
    "sg:classifiers":[
        {
            "category":"Personal",
            "subcategory":"Beauty Salon",
            "type":"Services"
        }
    ],
    "sg:phone":"+1 504 948 4225",
    "sg:postcode":"70117",
    "sg:province":"LA",
    "wof:name":"Attitudes Of Beauty",
    "wof:placetype":"venue"
},
  "geometry": {"coordinates":[-90.03312099999999,29.970624],"type":"Point"}
}