{
  "type": "Feature",
  "properties": {
    "addr:full":"100 Sis Ln Carencro LA 70520",
    "addr:housenumber":"100",
    "addr:postcode":"70520",
    "addr:street":"Sis Ln",
    "iso:country":"US",
    "sg:address":"100 Sis Ln",
    "sg:city":"Carencro",
    "sg:classifiers":[
        {
            "category":"Insurance",
            "subcategory":"Insurance Agent",
            "type":"Services"
        }
    ],
    "sg:phone":"+1 337 896 3851",
    "sg:postcode":"70520",
    "sg:province":"LA",
    "sg:website":"www.leeverret.com",
    "wof:name":"State Farm Insurance",
    "wof:placetype":"venue"
},
  "geometry": {"coordinates":[-92.053568,30.308035],"type":"Point"}
}