{
  "type": "Feature",
  "properties": {
    "iso:country":"US",
    "sg:address":"300 Well Rd",
    "sg:city":"West Monroe",
    "sg:classifiers":[
        {
            "category":"Restaurant",
            "type":"Food & Drink"
        }
    ],
    "sg:menulink":"http://www.allmenus.com/la/claiborne/173712-wendys/menu/",
    "sg:phone":"+1 318 322 9200",
    "sg:postcode":"71292",
    "sg:province":"LA",
    "sg:tags":[
        "burger",
        "american",
        "soup"
    ],
    "wof:name":"Wendy's",
    "wof:placetype":"venue"
},
  "geometry": {"coordinates":[-92.191948,32.508242],"type":"Point"}
}