{
  "type": "Feature",
  "properties": {
    "iso:country":"US",
    "sg:address":"113 Production Dr",
    "sg:city":"Slidell",
    "sg:classifiers":[
        {
            "category":"Wholesale",
            "subcategory":"Hardware",
            "type":"Manufacturing & Wholesale Goods"
        }
    ],
    "sg:phone":"+1 985 781 8342",
    "sg:postcode":"70460",
    "sg:province":"LA",
    "sg:tags":[
        "plumbing",
        "fixture",
        "supply"
    ],
    "wof:name":"Tammany Supply LCRM Corp",
    "wof:placetype":"venue"
},
  "geometry": {"coordinates":[-89.774159,30.317449],"type":"Point"}
}