{
  "type": "Feature",
  "properties": {
    "iso:country":"US",
    "sg:address":"301 Sibley Rd",
    "sg:city":"Minden",
    "sg:classifiers":[
        {
            "category":"Home & Garden",
            "subcategory":"Building Materials",
            "type":"Retail Goods"
        }
    ],
    "sg:phone":"+1 318 377 4022",
    "sg:postcode":"71055",
    "sg:province":"LA",
    "sg:tags":[
        "lumber"
    ],
    "wof:name":"Howard Lumber & Supply Co",
    "wof:placetype":"venue"
},
  "geometry": {"coordinates":[-93.28874999999999,32.610357],"type":"Point"}
}