{
  "type": "Feature",
  "properties": {
    "addr:full":"4012 Bissonet Dr Metairie LA 70003",
    "addr:housenumber":"4012",
    "addr:postcode":"70003",
    "addr:street":"Bissonet Dr",
    "iso:country":"US",
    "sg:address":"4012 Bissonet Dr",
    "sg:city":"Metairie",
    "sg:classifiers":[
        {
            "category":"Retail",
            "subcategory":"Repair Shop",
            "type":"Services"
        }
    ],
    "sg:phone":"+1 504 885 7894",
    "sg:postcode":"70003",
    "sg:province":"LA",
    "sg:tags":[
        "plumbing",
        "drain",
        "cleaning",
        "sewer"
    ],
    "wof:name":"Alligator Drain & Sewer Clean",
    "wof:placetype":"venue"
},
  "geometry": {"coordinates":[-90.209368,30.01543],"type":"Point"}
}