{
  "type": "Feature",
  "properties": {
    "addr:full":"85 Whisperwood Blvd Slidell LA 70458",
    "addr:housenumber":"85",
    "addr:postcode":"70458",
    "addr:street":"Whisperwood Blvd",
    "iso:country":"US",
    "sg:address":"85 Whisperwood Blvd",
    "sg:city":"Slidell",
    "sg:classifiers":[
        {
            "category":"Social Services",
            "type":"Services"
        }
    ],
    "sg:phone":"+1 985 661 0560",
    "sg:postcode":"70458",
    "sg:province":"LA",
    "sg:tags":[
        "counselor",
        "marriage",
        "family"
    ],
    "wof:name":"Northshore Family Counseling",
    "wof:placetype":"venue"
},
  "geometry": {"coordinates":[-89.756069,30.311566],"type":"Point"}
}