{
  "type": "Feature",
  "properties": {
    "addr:full":"433 Albert Ave Shreveport LA 71105",
    "addr:housenumber":"433",
    "addr:postcode":"71105",
    "addr:street":"Albert Ave",
    "iso:country":"US",
    "sg:address":"433 Albert Ave",
    "sg:city":"Shreveport",
    "sg:classifiers":[
        {
            "category":"Shopping",
            "subcategory":"Hobbies, Toys, & Games",
            "type":"Retail Goods"
        }
    ],
    "sg:phone":"+1 318 869 4527",
    "sg:postcode":"71105",
    "sg:province":"LA",
    "sg:tags":[
        "glass",
        "stained",
        "instruction",
        "supply"
    ],
    "wof:name":"Window Shopping Stain Glass",
    "wof:placetype":"venue"
},
  "geometry": {"coordinates":[-93.733484,32.465379],"type":"Point"}
}