{
  "type": "Feature",
  "properties": {
    "iso:country":"US",
    "sg:address":"1309 Ruth St",
    "sg:city":"Sulphur",
    "sg:classifiers":[
        {
            "category":"Retail",
            "subcategory":"Auto Repair",
            "type":"Services"
        }
    ],
    "sg:phone":"+1 337 527 6001",
    "sg:postcode":"70663",
    "sg:province":"LA",
    "sg:tags":[
        "automobile",
        "inspection"
    ],
    "wof:name":"Simmons Auto Svc",
    "wof:placetype":"venue"
},
  "geometry": {"coordinates":[-93.376274,30.22718],"type":"Point"}
}