{
  "type": "Feature",
  "properties": {
    "addr:full":"210 W Vermilion St Abbeville LA 70510",
    "addr:housenumber":"210",
    "addr:postcode":"70510",
    "addr:street":"W Vermilion St",
    "iso:country":"US",
    "sg:address":"210 W Vermilion St",
    "sg:city":"Abbeville",
    "sg:classifiers":[
        {
            "category":"Government",
            "subcategory":"Fire Station",
            "type":"Public Place"
        }
    ],
    "sg:phone":"+1 337 898 4258",
    "sg:postcode":"70510",
    "sg:province":"LA",
    "sg:tags":[
        "department"
    ],
    "wof:name":"Abbeville Fire Dept",
    "wof:placetype":"venue"
},
  "geometry": {"coordinates":[-92.136638,29.976661],"type":"Point"}
}