{
  "type": "Feature",
  "properties": {
    "iso:country":"US",
    "sg:address":"107 Garber Rd",
    "sg:city":"Broussard",
    "sg:classifiers":[
        {
            "category":"Retail",
            "subcategory":"Repair Shop",
            "type":"Services"
        }
    ],
    "sg:phone":"+1 337 289 5340",
    "sg:postcode":"70518",
    "sg:province":"LA",
    "sg:tags":[
        "welding"
    ],
    "sg:website":"www.lambservices.com",
    "wof:name":"Lamb Fabrication Ctr",
    "wof:placetype":"venue"
},
  "geometry": {"coordinates":[-91.983633,30.177108],"type":"Point"}
}