{
  "type": "Feature",
  "properties": {
    "addr:full":"611 Louise St Mansfield LA 71052",
    "addr:housenumber":"611",
    "addr:postcode":"71052",
    "addr:street":"Louise St",
    "iso:country":"US",
    "sg:address":"611 Louise St",
    "sg:city":"Mansfield",
    "sg:classifiers":[
        {
            "category":"Personal",
            "subcategory":"Beauty Salon",
            "type":"Services"
        }
    ],
    "sg:phone":"+1 318 872 0914",
    "sg:postcode":"71052",
    "sg:province":"LA",
    "wof:name":"Hair Fashions By Betty & Doris",
    "wof:placetype":"venue"
},
  "geometry": {"coordinates":[-93.691754,32.033243],"type":"Point"}
}