{
  "type": "Feature",
  "properties": {
    "addr:full":"1050 Homer Rd Minden LA 71055",
    "addr:housenumber":"1050",
    "addr:postcode":"71055",
    "addr:street":"Homer Rd",
    "iso:country":"US",
    "sg:address":"1050 Homer Rd",
    "sg:city":"Minden",
    "sg:classifiers":[
        {
            "category":"Restaurant",
            "type":"Food & Drink"
        }
    ],
    "sg:menulink":"http://www.allmenus.com/la/minden/176153-kfc---kentucky-fried-chicken/menu/",
    "sg:phone":"+1 318 377 8828",
    "sg:postcode":"71055",
    "sg:province":"LA",
    "sg:tags":[
        "american",
        "chicken"
    ],
    "wof:name":"KFC - Kentucky Fried Chicken",
    "wof:placetype":"venue"
},
  "geometry": {"coordinates":[-93.25819199999999,32.623429],"type":"Point"}
}