{
  "type": "Feature",
  "properties": {
    "iso:country":"US",
    "sg:address":"760 Goodson Dr",
    "sg:city":"Gretna",
    "sg:classifiers":[
        {
            "category":"Real Estate",
            "subcategory":"Real Estate Agent",
            "type":"Services"
        }
    ],
    "sg:phone":"+1 504 494 2418",
    "sg:postcode":"70056",
    "sg:province":"LA",
    "sg:tags":[
        "inspection"
    ],
    "wof:name":"21st Century Home Inspection",
    "wof:placetype":"venue"
},
  "geometry": {"coordinates":[-90.02366499999999,29.898342],"type":"Point"}
}