{
  "type": "Feature",
  "properties": {
    "addr:full":"432 Yellow Pine Rd Florien LA 71429",
    "addr:housenumber":"432",
    "addr:postcode":"71429",
    "addr:street":"Yellow Pine Rd",
    "iso:country":"US",
    "sg:address":"432 Yellow Pine Rd",
    "sg:city":"Florien",
    "sg:classifiers":[
        {
            "category":"Travel",
            "subcategory":"Hotels & Motels",
            "type":"Entertainment"
        }
    ],
    "sg:phone":"+1 318 377 3600",
    "sg:postcode":"71429",
    "sg:province":"LA",
    "sg:tags":[
        "breakfast",
        "accommodation",
        "bed"
    ],
    "wof:name":"Yellow Pine Inn",
    "wof:placetype":"venue"
},
  "geometry": {"coordinates":[-93.525937,31.459669],"type":"Point"}
}