{
  "type": "Feature",
  "properties": {
    "iso:country":"US",
    "sg:address":"3840 Hwy 22 E",
    "sg:city":"Mandeville",
    "sg:classifiers":[
        {
            "category":"Health Services",
            "subcategory":"Nursing And Care Facility",
            "type":"Services"
        }
    ],
    "sg:phone":"+1 985 626 3623",
    "sg:postcode":"70471",
    "sg:province":"LA",
    "sg:tags":[
        "hospice"
    ],
    "wof:name":"Memorial Hospice Palliative",
    "wof:placetype":"venue"
},
  "geometry": {"coordinates":[-90.140688,30.407211],"type":"Point"}
}