{
  "type": "Feature",
  "properties": {
    "iso:country":"US",
    "sg:address":"130 Santa Inez St",
    "sg:city":"Broussard",
    "sg:classifiers":[
        {
            "category":"Manufacturing",
            "subcategory":"Tools & Machinery",
            "type":"Manufacturing & Wholesale Goods"
        }
    ],
    "sg:phone":"+1 337 837 9263",
    "sg:postcode":"70563",
    "sg:province":"LA",
    "sg:tags":[
        "oil",
        "gas"
    ],
    "wof:name":"FMC Energy Systems",
    "wof:placetype":"venue"
},
  "geometry": {"coordinates":[-91.819272,30.028364],"type":"Point"}
}