{
  "type": "Feature",
  "properties": {
    "iso:country":"US",
    "sg:address":"2537 Rue Jesann",
    "sg:city":"Marrero",
    "sg:classifiers":[
        {
            "category":"Building & Trades",
            "subcategory":"Construction",
            "type":"Services"
        }
    ],
    "sg:phone":"+1 504 494 8816",
    "sg:postcode":"70072",
    "sg:province":"LA",
    "sg:tags":[
        "general",
        "contractor"
    ],
    "wof:name":"H P Construction",
    "wof:placetype":"venue"
},
  "geometry": {"coordinates":[-90.105271,29.839443],"type":"Point"}
}