{
  "type": "Feature",
  "properties": {
    "iso:country":"US",
    "sg:address":"1401 Hudson Ln",
    "sg:city":"Monroe",
    "sg:classifiers":[
        {
            "category":"Professional",
            "subcategory":"Research",
            "type":"Services"
        }
    ],
    "sg:phone":"+1 318 325 7344",
    "sg:postcode":"71201",
    "sg:province":"LA",
    "sg:tags":[
        "environmental",
        "ecological"
    ],
    "wof:name":"Louisiana Environmental Tech",
    "wof:placetype":"venue"
},
  "geometry": {"coordinates":[-92.111818,32.516432],"type":"Point"}
}