{
  "type": "Feature",
  "properties": {
    "iso:country":"US",
    "sg:address":"2405 Cypress Shores Rd",
    "sg:city":"Benton",
    "sg:classifiers":[
        {
            "category":"Home & Garden",
            "subcategory":"Home Furnishings",
            "type":"Retail Goods"
        }
    ],
    "sg:phone":"+1 318 965 1137",
    "sg:postcode":"71006",
    "sg:province":"LA",
    "sg:tags":[
        "beveled",
        "glass",
        "ornamental"
    ],
    "wof:name":"Glass Designs & Graphics",
    "wof:placetype":"venue"
},
  "geometry": {"coordinates":[-93.675482,32.708538],"type":"Point"}
}