{
  "type": "Feature",
  "properties": {
    "addr:full":"5940 Airline Hwy Baton Rouge LA 70805",
    "addr:housenumber":"5940",
    "addr:postcode":"70805",
    "addr:street":"Airline Hwy",
    "iso:country":"US",
    "sg:address":"5940 Airline Hwy",
    "sg:city":"Baton Rouge",
    "sg:classifiers":[
        {
            "category":"Real Estate",
            "subcategory":"Real Estate Operator",
            "type":"Services"
        }
    ],
    "sg:phone":"+1 225 357 8014",
    "sg:postcode":"70805",
    "sg:province":"LA",
    "sg:tags":[
        "mall",
        "shopping",
        "center"
    ],
    "wof:name":"Colonial Plaza Shopping Ctr",
    "wof:placetype":"venue"
},
  "geometry": {"coordinates":[-91.129181,30.499575],"type":"Point"}
}