{
  "type": "Feature",
  "properties": {
    "iso:country":"US",
    "sg:address":"6553 Wales St",
    "sg:city":"New Orleans",
    "sg:classifiers":[
        {
            "category":"Museum",
            "type":"Entertainment"
        }
    ],
    "sg:phone":"+1 504 242 2053",
    "sg:postcode":"70126",
    "sg:province":"LA",
    "sg:tags":[
        "gallery"
    ],
    "wof:name":"Exhibits Unlimited",
    "wof:placetype":"venue"
},
  "geometry": {"coordinates":[-90.018671,30.033488],"type":"Point"}
}