{
  "type": "Feature",
  "properties": {
    "iso:country":"US",
    "sg:address":"2904 N University Ave",
    "sg:city":"Lafayette",
    "sg:classifiers":[
        {
            "category":"Home & Garden",
            "subcategory":"Building Materials",
            "type":"Retail Goods"
        }
    ],
    "sg:phone":"+1 337 896 1333",
    "sg:postcode":"70507",
    "sg:province":"LA",
    "sg:tags":[
        "siding"
    ],
    "wof:name":"Sigue's Wholesale Building",
    "wof:placetype":"venue"
},
  "geometry": {"coordinates":[-92.050309,30.283155],"type":"Point"}
}