{
  "type": "Feature",
  "properties": {
    "iso:country":"US",
    "sg:address":"3827 Hwy 115",
    "sg:city":"Hessmer",
    "sg:classifiers":[
        {
            "category":"Personal",
            "subcategory":"Tanning Parlor",
            "type":"Services"
        }
    ],
    "sg:phone":"+1 318 359 0718",
    "sg:postcode":"71341",
    "sg:province":"LA",
    "sg:tags":[
        "salon"
    ],
    "wof:name":"Dairing Styles",
    "wof:placetype":"venue"
},
  "geometry": {"coordinates":[-92.14985900000001,31.022746],"type":"Point"}
}