{
  "type": "Feature",
  "properties": {
    "iso:country":"US",
    "sg:address":"6602 State Rte 182",
    "sg:city":"Morgan City",
    "sg:classifiers":[
        {
            "category":"Food & Beverages",
            "subcategory":"Groceries & Convenience Stores",
            "type":"Retail Goods"
        }
    ],
    "sg:phone":"+1 985 385 6815",
    "sg:postcode":"70380",
    "sg:province":"LA",
    "wof:name":"Stazione Deli-Market",
    "wof:placetype":"venue"
},
  "geometry": {"coordinates":[-91.194993,29.697013],"type":"Point"}
}