{
  "type": "Feature",
  "properties": {
    "addr:full":"1225 Nashville Ave New Orleans LA 70115",
    "addr:housenumber":"1225",
    "addr:postcode":"70115",
    "addr:street":"Nashville Ave",
    "iso:country":"US",
    "sg:address":"1225 Nashville Ave",
    "sg:city":"New Orleans",
    "sg:classifiers":[
        {
            "category":"Professional",
            "subcategory":"Advertising",
            "type":"Services"
        }
    ],
    "sg:phone":"+1 504 891 8303",
    "sg:postcode":"70115",
    "sg:province":"LA",
    "sg:tags":[
        "agency",
        "public",
        "relations"
    ],
    "wof:name":"Perrien Paulette Advg & Pub RE",
    "wof:placetype":"venue"
},
  "geometry": {"coordinates":[-90.117625,29.925869],"type":"Point"}
}