{
  "type": "Feature",
  "properties": {
    "iso:country":"US",
    "sg:address":"7548 Hwy 120",
    "sg:city":"Zwolle",
    "sg:classifiers":[
        {
            "category":"Wholesale",
            "subcategory":"Machinery & Supplies",
            "type":"Manufacturing & Wholesale Goods"
        }
    ],
    "sg:phone":"+1 318 645 2238",
    "sg:postcode":"71486",
    "sg:province":"LA",
    "sg:tags":[
        "equipment",
        "industrial"
    ],
    "wof:name":"Stacy Veuleman Ind",
    "wof:placetype":"venue"
},
  "geometry": {"coordinates":[-93.550377,31.675736],"type":"Point"}
}