{
  "type": "Feature",
  "properties": {
    "iso:country":"US",
    "sg:address":"547 E 79th St",
    "sg:city":"Shreveport",
    "sg:classifiers":[
        {
            "category":"Government",
            "subcategory":"Police Station",
            "type":"Public Place"
        }
    ],
    "sg:phone":"+1 318 673 7399",
    "sg:postcode":"71106",
    "sg:province":"LA",
    "sg:tags":[
        "department"
    ],
    "wof:name":"Shreveport Police Dept",
    "wof:placetype":"venue"
},
  "geometry": {"coordinates":[-93.746835,32.432757],"type":"Point"}
}