{
  "type": "Feature",
  "properties": {
    "iso:country":"US",
    "sg:address":"1210 Park Dr",
    "sg:city":"Mandeville",
    "sg:classifiers":[
        {
            "category":"Professional",
            "subcategory":"Detective & Security Services",
            "type":"Services"
        }
    ],
    "sg:phone":"+1 985 674 7677",
    "sg:postcode":"70471",
    "sg:province":"LA",
    "sg:tags":[
        "agency"
    ],
    "wof:name":"M A Stringer Assoc",
    "wof:placetype":"venue"
},
  "geometry": {"coordinates":[-90.088964,30.38348],"type":"Point"}
}