{
  "type": "Feature",
  "properties": {
    "iso:country":"US",
    "sg:address":"111 S Texas St",
    "sg:city":"Deridder",
    "sg:classifiers":[
        {
            "category":"Shopping",
            "type":"Retail Goods"
        }
    ],
    "sg:phone":"+1 337 462 2283",
    "sg:postcode":"70634",
    "sg:province":"LA",
    "sg:tags":[
        "equipment",
        "care",
        "health",
        "home"
    ],
    "wof:name":"Family Respitory Svc",
    "wof:placetype":"venue"
},
  "geometry": {"coordinates":[-93.2974,30.84647],"type":"Point"}
}