{
  "type": "Feature",
  "properties": {
    "iso:country":"US",
    "sg:address":"6025 Greenwell St",
    "sg:city":"Baton Rouge",
    "sg:classifiers":[
        {
            "category":"Restaurant",
            "type":"Food & Drink"
        }
    ],
    "sg:phone":"+1 225 357 3539",
    "sg:postcode":"70812",
    "sg:province":"LA",
    "wof:name":"Tom's Seafood",
    "wof:placetype":"venue"
},
  "geometry": {"coordinates":[-91.130762,30.502495],"type":"Point"}
}