{
  "type": "Feature",
  "properties": {
    "addr:full":"701 Pride Dr Hammond LA 70401",
    "addr:housenumber":"701",
    "addr:postcode":"70401",
    "addr:street":"Pride Dr",
    "iso:country":"US",
    "sg:address":"701 Pride Dr",
    "sg:city":"Hammond",
    "sg:classifiers":[
        {
            "category":"Manufacturing",
            "subcategory":"Tools & Machinery",
            "type":"Manufacturing & Wholesale Goods"
        }
    ],
    "sg:phone":"+1 985 549 1660",
    "sg:postcode":"70401",
    "sg:province":"LA",
    "sg:tags":[
        "physician",
        "surgeon"
    ],
    "wof:name":"Cardinal Health",
    "wof:placetype":"venue"
},
  "geometry": {"coordinates":[-90.423709,30.518964],"type":"Point"}
}