{
  "type": "Feature",
  "properties": {
    "addr:full":"1106 Cocoville Rd Mansura LA 71350",
    "addr:housenumber":"1106",
    "addr:postcode":"71350",
    "addr:street":"Cocoville Rd",
    "iso:country":"US",
    "sg:address":"1106 Cocoville Rd",
    "sg:city":"Mansura",
    "sg:classifiers":[
        {
            "category":"Utilities",
            "subcategory":"Water",
            "type":"Services"
        }
    ],
    "sg:phone":"+1 318 253 8715",
    "sg:postcode":"71350",
    "sg:province":"LA",
    "sg:tags":[
        "system",
        "supply"
    ],
    "wof:name":"Wards Three Avoyelles Water",
    "wof:placetype":"venue"
},
  "geometry": {"coordinates":[-92.059513,31.097153],"type":"Point"}
}