{
  "type": "Feature",
  "properties": {
    "iso:country":"US",
    "sg:address":"1408 N Roosevelt St",
    "sg:city":"Bogalusa",
    "sg:classifiers":[
        {
            "category":"Organizations",
            "subcategory":"Religious Organization",
            "type":"Services"
        }
    ],
    "sg:phone":"+1 985 735 6859",
    "sg:postcode":"70427",
    "sg:province":"LA",
    "sg:tags":[
        "church"
    ],
    "wof:name":"Sweet Beluah Baptist Church",
    "wof:placetype":"venue"
},
  "geometry": {"coordinates":[-89.853979,30.801378],"type":"Point"}
}