{
  "type": "Feature",
  "properties": {
    "addr:full":"147 W Bayou Ln Port Sulphur LA 70083",
    "addr:housenumber":"147",
    "addr:postcode":"70083",
    "addr:street":"W Bayou Ln",
    "iso:country":"US",
    "sg:address":"147 W Bayou Ln",
    "sg:city":"Port Sulphur",
    "sg:classifiers":[
        {
            "category":"Building & Trades",
            "subcategory":"Plumbing",
            "type":"Services"
        }
    ],
    "sg:phone":"+1 504 656 7200",
    "sg:postcode":"70083",
    "sg:province":"LA",
    "sg:tags":[
        "product",
        "management",
        "energy",
        "system"
    ],
    "wof:name":"Stone Energy Corp",
    "wof:placetype":"venue"
},
  "geometry": {"coordinates":[-89.886348,29.558196],"type":"Point"}
}