{
  "type": "Feature",
  "properties": {
    "iso:country":"US",
    "sg:address":"806 Pine St",
    "sg:city":"Madisonville",
    "sg:classifiers":[
        {
            "category":"Organizations",
            "subcategory":"Religious Organization",
            "type":"Services"
        }
    ],
    "sg:phone":"+1 985 845 3317",
    "sg:postcode":"70447",
    "sg:province":"LA",
    "sg:tags":[
        "church"
    ],
    "wof:name":"Hopewell Baptist Church",
    "wof:placetype":"venue"
},
  "geometry": {"coordinates":[-90.158079,30.404334],"type":"Point"}
}