{
  "type": "Feature",
  "properties": {
    "iso:country":"US",
    "sg:address":"134 S Broad St",
    "sg:city":"New Orleans",
    "sg:classifiers":[
        {
            "category":"Shopping",
            "subcategory":"Clothing, Apparel, & Fashions",
            "type":"Retail Goods"
        }
    ],
    "sg:phone":"+1 504 821 4164",
    "sg:postcode":"70119",
    "sg:province":"LA",
    "wof:name":"Icesis",
    "wof:placetype":"venue"
},
  "geometry": {"coordinates":[-90.08759000000001,29.965092],"type":"Point"}
}