{
  "type": "Feature",
  "properties": {
    "iso:country":"US",
    "sg:address":"715 Bourbon St",
    "sg:city":"New Orleans",
    "sg:classifiers":[
        {
            "category":"Shopping",
            "subcategory":"Gifts & Souvenirs",
            "type":"Retail Goods"
        }
    ],
    "sg:phone":"+1 504 524 5989",
    "sg:postcode":"70116",
    "sg:province":"LA",
    "sg:tags":[
        "shop"
    ],
    "wof:name":"Bourbon Boutique",
    "wof:placetype":"venue"
},
  "geometry": {"coordinates":[-90.065594,29.95873],"type":"Point"}
}