{
  "type": "Feature",
  "properties": {
    "addr:full":"4355 Prescott Rd Baton Rouge LA 70805",
    "addr:housenumber":"4355",
    "addr:postcode":"70805",
    "addr:street":"Prescott Rd",
    "iso:country":"US",
    "sg:address":"4355 Prescott Rd",
    "sg:city":"Baton Rouge",
    "sg:classifiers":[
        {
            "category":"Wholesale",
            "subcategory":"Machinery & Supplies",
            "type":"Manufacturing & Wholesale Goods"
        }
    ],
    "sg:phone":"+1 225 356 3220",
    "sg:postcode":"70805",
    "sg:province":"LA",
    "sg:tags":[
        "equipment",
        "establishment"
    ],
    "wof:name":"Freeman Ephrim III",
    "wof:placetype":"venue"
},
  "geometry": {"coordinates":[-91.14890699999999,30.487422],"type":"Point"}
}