{
  "type": "Feature",
  "properties": {
    "iso:country":"US",
    "sg:address":"1120 Coolidge St",
    "sg:city":"Lafayette",
    "sg:classifiers":[
        {
            "category":"Shopping",
            "subcategory":"Jewelry",
            "type":"Retail Goods"
        }
    ],
    "sg:phone":"+1 337 234 3890",
    "sg:postcode":"70503",
    "sg:province":"LA",
    "sg:tags":[
        "jeweler"
    ],
    "sg:website":"www.ronstevensjeweller.com",
    "wof:name":"Ron Stevens Jeweler",
    "wof:placetype":"venue"
},
  "geometry": {"coordinates":[-92.018029,30.203232],"type":"Point"}
}