{
  "type": "Feature",
  "properties": {
    "addr:full":"4931 W Esplanade Ave Metairie LA 70006",
    "addr:housenumber":"4931",
    "addr:postcode":"70006",
    "addr:street":"W Esplanade Ave",
    "iso:country":"US",
    "sg:address":"4931 W Esplanade Ave",
    "sg:city":"Metairie",
    "sg:classifiers":[
        {
            "category":"Real Estate",
            "subcategory":"Real Estate Agent",
            "type":"Services"
        }
    ],
    "sg:phone":"+1 504 455 5500",
    "sg:postcode":"70006",
    "sg:province":"LA",
    "sg:website":"www.prudentialgardner.com",
    "wof:name":"Prudential Gardner Realtors",
    "wof:placetype":"venue"
},
  "geometry": {"coordinates":[-90.196819,30.017239],"type":"Point"}
}