{
  "type": "Feature",
  "properties": {
    "addr:full":"1451 Annunciation St New Orleans LA 70130",
    "addr:housenumber":"1451",
    "addr:postcode":"70130",
    "addr:street":"Annunciation St",
    "iso:country":"US",
    "sg:address":"1451 Annunciation St",
    "sg:city":"New Orleans",
    "sg:classifiers":[
        {
            "category":"Real Estate",
            "subcategory":"Developer",
            "type":"Services"
        }
    ],
    "sg:phone":"+1 504 523 6021",
    "sg:postcode":"70130",
    "sg:province":"LA",
    "wof:name":"Watson Developments",
    "wof:placetype":"venue"
},
  "geometry": {"coordinates":[-90.070014,29.934097],"type":"Point"}
}