{
  "type": "Feature",
  "properties": {
    "addr:full":"3800 Grandlake Blvd Kenner LA 70065",
    "addr:housenumber":"3800",
    "addr:postcode":"70065",
    "addr:street":"Grandlake Blvd",
    "iso:country":"US",
    "sg:address":"3800 Grandlake Blvd",
    "sg:city":"Kenner",
    "sg:classifiers":[
        {
            "category":"Professional",
            "subcategory":"Business Services",
            "type":"Services"
        }
    ],
    "sg:phone":"+1 504 467 7533",
    "sg:postcode":"70065",
    "sg:province":"LA",
    "wof:name":"Weber Ventures LLC",
    "wof:placetype":"venue"
},
  "geometry": {"coordinates":[-90.27714400000001,30.034547],"type":"Point"}
}