{
  "type": "Feature",
  "properties": {
    "iso:country":"US",
    "sg:address":"880 E Mount Pleasant Rd",
    "sg:city":"Zachary",
    "sg:classifiers":[
        {
            "category":"Social Services",
            "subcategory":"Child Care",
            "type":"Services"
        }
    ],
    "sg:phone":"+1 225 658 0040",
    "sg:postcode":"70791",
    "sg:province":"LA",
    "wof:name":"Mrs Robinson's Child Care Ctr",
    "wof:placetype":"venue"
},
  "geometry": {"coordinates":[-91.219729,30.649614],"type":"Point"}
}