{
  "type": "Feature",
  "properties": {
    "addr:full":"100 N Land Ave Oil City LA 71061",
    "addr:housenumber":"100",
    "addr:postcode":"71061",
    "addr:street":"N Land Ave",
    "iso:country":"US",
    "sg:address":"100 N Land Ave",
    "sg:city":"Oil City",
    "sg:classifiers":[
        {
            "category":"Mining & Drilling",
            "type":"Manufacturing & Wholesale Goods"
        }
    ],
    "sg:phone":"+1 318 995 0404",
    "sg:postcode":"71061",
    "sg:province":"LA",
    "sg:tags":[
        "oil",
        "gas",
        "producer"
    ],
    "wof:name":"Wooldridge Productions",
    "wof:placetype":"venue"
},
  "geometry": {"coordinates":[-93.97165,32.743879],"type":"Point"}
}