{
  "type": "Feature",
  "properties": {
    "iso:country":"US",
    "sg:address":"701 McMillan Rd",
    "sg:city":"West Monroe",
    "sg:classifiers":[
        {
            "category":"Insurance",
            "subcategory":"Insurance Agent",
            "type":"Services"
        }
    ],
    "sg:phone":"+1 318 322 5344",
    "sg:postcode":"71291",
    "sg:province":"LA",
    "wof:name":"White & Roberts Insurance",
    "wof:placetype":"venue"
},
  "geometry": {"coordinates":[-92.15531,32.513419],"type":"Point"}
}