{
  "type": "Feature",
  "properties": {
    "iso:country":"US",
    "sg:address":"14100 Airline Hwy",
    "sg:city":"Baton Rouge",
    "sg:classifiers":[
        {
            "category":"Banks & Credit Unions",
            "subcategory":"Financial Services",
            "type":"Services"
        }
    ],
    "sg:phone":"+1 225 753 1244",
    "sg:postcode":"70817",
    "sg:province":"LA",
    "sg:tags":[
        "company",
        "holding"
    ],
    "wof:name":"L R K LLC",
    "wof:placetype":"venue"
},
  "geometry": {"coordinates":[-91.02379999999999,30.365007],"type":"Point"}
}