{
  "type": "Feature",
  "properties": {
    "iso:country":"US",
    "sg:address":"5815 E Judge Perez Dr",
    "sg:city":"Violet",
    "sg:classifiers":[
        {
            "category":"Food & Beverages",
            "subcategory":"Groceries & Convenience Stores",
            "type":"Retail Goods"
        }
    ],
    "sg:phone":"+1 504 682 4990",
    "sg:postcode":"70092",
    "sg:province":"LA",
    "wof:name":"Quick Check Inc",
    "wof:placetype":"venue"
},
  "geometry": {"coordinates":[-89.88980100000001,29.899401],"type":"Point"}
}