{
  "type": "Feature",
  "properties": {
    "iso:country":"US",
    "sg:address":"3316 Florida Ave",
    "sg:city":"Kenner",
    "sg:classifiers":[
        {
            "category":"Professional",
            "subcategory":"Engineering",
            "type":"Services"
        }
    ],
    "sg:phone":"+1 504 466 6366",
    "sg:postcode":"70065",
    "sg:province":"LA",
    "sg:tags":[
        "engineer"
    ],
    "wof:name":"All South Cnsltng Engr LLC",
    "wof:placetype":"venue"
},
  "geometry": {"coordinates":[-90.240531,30.017563],"type":"Point"}
}