{
  "type": "Feature",
  "properties": {
    "addr:full":"3001 Barrow St Houma LA 70360",
    "addr:housenumber":"3001",
    "addr:postcode":"70360",
    "addr:street":"Barrow St",
    "iso:country":"US",
    "sg:address":"3001 Barrow St",
    "sg:city":"Houma",
    "sg:classifiers":[
        {
            "category":"Restaurant",
            "type":"Food & Drink"
        }
    ],
    "sg:menulink":"http://www.allmenus.com/la/houma/188332-mcdonalds/menu/",
    "sg:postcode":"70360",
    "sg:province":"LA",
    "sg:tags":[
        "burger",
        "american"
    ],
    "wof:name":"McDonald's",
    "wof:placetype":"venue"
},
  "geometry": {"coordinates":[-90.722815,29.570062],"type":"Point"}
}