{
  "type": "Feature",
  "properties": {
    "iso:country":"US",
    "sg:address":"410 N Canal Blvd",
    "sg:city":"Thibodaux",
    "sg:classifiers":[
        {
            "category":"Personal",
            "subcategory":"Beauty Salon",
            "type":"Services"
        }
    ],
    "sg:phone":"+1 985 493 8121",
    "sg:postcode":"70301",
    "sg:province":"LA",
    "wof:name":"Smart Style Family Hair Salon",
    "wof:placetype":"venue"
},
  "geometry": {"coordinates":[-90.81631,29.80572],"type":"Point"}
}