{
  "type": "Feature",
  "properties": {
    "iso:country":"US",
    "sg:address":"7427 Highway 23",
    "sg:city":"Belle Chasse",
    "sg:classifiers":[
        {
            "category":"Sports & Exercise",
            "subcategory":"Golf",
            "type":"Entertainment"
        }
    ],
    "sg:phone":"+1 504 394 9500",
    "sg:postcode":"70037",
    "sg:province":"LA",
    "wof:name":"Bayou Barriere Golf Club",
    "wof:placetype":"venue"
},
  "geometry": {"coordinates":[-90.006104,29.870001],"type":"Point"}
}