{
  "type": "Feature",
  "properties": {
    "addr:full":"6583 Main St Winnsboro LA 71295",
    "addr:housenumber":"6583",
    "addr:postcode":"71295",
    "addr:street":"Main St",
    "iso:country":"US",
    "sg:address":"6583 Main St",
    "sg:city":"Winnsboro",
    "sg:classifiers":[
        {
            "category":"Real Estate",
            "subcategory":"Architect",
            "type":"Services"
        }
    ],
    "sg:phone":"+1 318 435 6180",
    "sg:postcode":"71295",
    "sg:province":"LA",
    "sg:tags":[
        "architectural"
    ],
    "wof:name":"John T Womble",
    "wof:placetype":"venue"
},
  "geometry": {"coordinates":[-91.71487500000001,32.165271],"type":"Point"}
}