{
  "type": "Feature",
  "properties": {
    "iso:country":"US",
    "sg:address":"1414 W 58th St",
    "sg:city":"Shreveport",
    "sg:classifiers":[
        {
            "category":"Restaurant",
            "type":"Food & Drink"
        }
    ],
    "sg:phone":"+1 318 865 6034",
    "sg:postcode":"71108",
    "sg:province":"LA",
    "sg:tags":[
        "caterer"
    ],
    "wof:name":"Charles Catering",
    "wof:placetype":"venue"
},
  "geometry": {"coordinates":[-93.760779,32.455686],"type":"Point"}
}