{
  "type": "Feature",
  "properties": {
    "addr:full":"218 Audalia Ave Sulphur LA 70663",
    "addr:housenumber":"218",
    "addr:postcode":"70663",
    "addr:street":"Audalia Ave",
    "iso:country":"US",
    "sg:address":"218 Audalia Ave",
    "sg:city":"Sulphur",
    "sg:classifiers":[
        {
            "category":"Building & Trades",
            "subcategory":"Construction",
            "type":"Services"
        }
    ],
    "sg:phone":"+1 337 802 8059",
    "sg:postcode":"70663",
    "sg:province":"LA",
    "sg:tags":[
        "house"
    ],
    "wof:name":"B O S Remodeling",
    "wof:placetype":"venue"
},
  "geometry": {"coordinates":[-93.32193700000001,30.231636],"type":"Point"}
}