{
  "type": "Feature",
  "properties": {
    "addr:full":"1993 Motes Island Cir Shreveport LA 71107",
    "addr:housenumber":"1993",
    "addr:postcode":"la 71107",
    "addr:street":"Motes Island Cir",
    "iso:country":"US",
    "sg:address":"1993 Motes Island Cir",
    "sg:city":"Shreveport",
    "sg:classifiers":[
        {
            "category":"Manufacturing",
            "subcategory":"Rubber & Plastics",
            "type":"Manufacturing & Wholesale Goods"
        }
    ],
    "sg:phone":"+1 318 227 1011",
    "sg:postcode":"71107",
    "sg:province":"LA",
    "sg:tags":[
        "sealing",
        "devices",
        "gasket"
    ],
    "wof:name":"Triplex Inc Shreveport Branch",
    "wof:placetype":"venue"
},
  "geometry": {"coordinates":[-93.766947,32.549292],"type":"Point"}
}