{
  "type": "Feature",
  "properties": {
    "addr:full":"615 Destrehan Ave Harvey LA 70058",
    "addr:housenumber":"615",
    "addr:postcode":"70058",
    "addr:street":"Destrehan Ave",
    "iso:country":"US",
    "sg:address":"615 Destrehan Ave",
    "sg:city":"Harvey",
    "sg:classifiers":[
        {
            "category":"Manufacturing",
            "subcategory":"Watercraft",
            "type":"Manufacturing & Wholesale Goods"
        }
    ],
    "sg:phone":"+1 504 340 0621",
    "sg:postcode":"70058",
    "sg:province":"LA",
    "sg:tags":[
        "builder",
        "ship",
        "repairer"
    ],
    "sg:website":"www.bollingershipyards.com",
    "wof:name":"Bollinger Quick Repair Inc",
    "wof:placetype":"venue"
},
  "geometry": {"coordinates":[-90.08351,29.905092],"type":"Point"}
}