{
  "type": "Feature",
  "properties": {
    "iso:country":"US",
    "sg:address":"9310 Riva Ridge Dr",
    "sg:city":"Shreveport",
    "sg:classifiers":[
        {
            "category":"Professional",
            "type":"Services"
        }
    ],
    "sg:phone":"+1 318 795 8118",
    "sg:postcode":"71115",
    "sg:province":"LA",
    "sg:tags":[
        "establishment"
    ],
    "wof:name":"Waterscapes",
    "wof:placetype":"venue"
},
  "geometry": {"coordinates":[-93.714766,32.421494],"type":"Point"}
}