{
  "type": "Feature",
  "properties": {
    "iso:country":"US",
    "sg:address":"9241 Wallace Lake Rd",
    "sg:city":"Shreveport",
    "sg:classifiers":[
        {
            "category":"Insurance",
            "subcategory":"Insurance Agent",
            "type":"Services"
        }
    ],
    "sg:phone":"+1 318 686 7700",
    "sg:postcode":"71106",
    "sg:province":"LA",
    "wof:name":"Hudson-Silver Agency",
    "wof:placetype":"venue"
},
  "geometry": {"coordinates":[-93.738483,32.398397],"type":"Point"}
}