{
  "type": "Feature",
  "properties": {
    "iso:country":"US",
    "sg:address":"1010 W Raymond St",
    "sg:city":"Gonzales",
    "sg:classifiers":[
        {
            "category":"Wholesale",
            "subcategory":"Hardware",
            "type":"Manufacturing & Wholesale Goods"
        }
    ],
    "sg:phone":"+1 225 644 6601",
    "sg:postcode":"70737",
    "sg:province":"LA",
    "sg:tags":[
        "nut",
        "bolt"
    ],
    "wof:name":"Spindletop Bolt & Gasket Inc",
    "wof:placetype":"venue"
},
  "geometry": {"coordinates":[-90.929975,30.219435],"type":"Point"}
}