{
  "type": "Feature",
  "properties": {
    "iso:country":"US",
    "sg:address":"401 N Meadow St",
    "sg:city":"Metairie",
    "sg:classifiers":[
        {
            "category":"Building & Trades",
            "subcategory":"Construction",
            "type":"Services"
        }
    ],
    "sg:phone":"+1 504 738 1204",
    "sg:postcode":"70003",
    "sg:province":"LA",
    "sg:tags":[
        "maker",
        "cabinet"
    ],
    "wof:name":"Jon Mar Cabinetry",
    "wof:placetype":"venue"
},
  "geometry": {"coordinates":[-90.21422,29.978923],"type":"Point"}
}