{
  "type": "Feature",
  "properties": {
    "addr:full":"2208 Robert E Lee Blvd New Orleans LA 70122",
    "addr:housenumber":"2208",
    "addr:postcode":"70122",
    "addr:street":"Robert E Lee Blvd",
    "iso:country":"US",
    "sg:address":"2208 Robert E Lee Blvd",
    "sg:city":"New Orleans",
    "sg:classifiers":[
        {
            "category":"Bars & Pubs",
            "type":"Food & Drink"
        }
    ],
    "sg:phone":"+1 504 282 9488",
    "sg:postcode":"70122",
    "sg:province":"LA",
    "sg:tags":[
        "lounge",
        "nightlife",
        "cocktail"
    ],
    "wof:name":"Checkmate Lounge",
    "wof:placetype":"venue"
},
  "geometry": {"coordinates":[-90.060501,30.0219],"type":"Point"}
}