{
  "type": "Feature",
  "properties": {
    "addr:full":"1200 S Clearview Pkwy New Orleans LA 70123",
    "addr:housenumber":"1200",
    "addr:postcode":"70123",
    "addr:street":"S Clearview Pkwy",
    "iso:country":"US",
    "sg:address":"1200 S Clearview Pkwy",
    "sg:city":"New Orleans",
    "sg:classifiers":[
        {
            "category":"Shopping",
            "subcategory":"Clothing, Apparel, & Fashions",
            "type":"Retail Goods"
        }
    ],
    "sg:phone":"+1 504 733 6660",
    "sg:postcode":"70123",
    "sg:province":"LA",
    "sg:tags":[
        "infant",
        "wear"
    ],
    "sg:website":"www.rainbowshops.com",
    "wof:name":"Rainbow",
    "wof:placetype":"venue"
},
  "geometry": {"coordinates":[-90.18474000000001,29.962441],"type":"Point"}
}