{
  "type": "Feature",
  "properties": {
    "iso:country":"US",
    "sg:address":"313 Center St",
    "sg:city":"Marksville",
    "sg:classifiers":[
        {
            "category":"Health Services",
            "subcategory":"Doctor",
            "type":"Services"
        }
    ],
    "sg:phone":"+1 318 253 8655",
    "sg:postcode":"71351",
    "sg:province":"LA",
    "sg:tags":[
        "physician",
        "surgeon"
    ],
    "wof:name":"Predrag M Gagic Inc",
    "wof:placetype":"venue"
},
  "geometry": {"coordinates":[-92.073936,31.125338],"type":"Point"}
}