{
  "type": "Feature",
  "properties": {
    "addr:full":"1048 Brown Dr Breaux Bridge LA 70517",
    "addr:housenumber":"1048",
    "addr:postcode":"la 70517",
    "addr:street":"Brown Dr",
    "iso:country":"US",
    "sg:address":"1048 Brown Dr",
    "sg:city":"Breaux Bridge",
    "sg:classifiers":[
        {
            "category":"Shopping",
            "subcategory":"Hobbies, Toys, & Games",
            "type":"Retail Goods"
        }
    ],
    "sg:phone":"+1 337 667 7589",
    "sg:postcode":"70517",
    "sg:province":"LA",
    "sg:tags":[
        "doll"
    ],
    "wof:name":"Dolls Of House",
    "wof:placetype":"venue"
},
  "geometry": {"coordinates":[-91.85568499999999,30.330582],"type":"Point"}
}