{
  "type": "Feature",
  "properties": {
    "iso:country":"US",
    "sg:address":"455 Pavie St",
    "sg:city":"Natchitoches",
    "sg:classifiers":[
        {
            "category":"Organizations",
            "subcategory":"Religious Organization",
            "type":"Services"
        }
    ],
    "sg:phone":"+1 318 352 5961",
    "sg:postcode":"71457",
    "sg:province":"LA",
    "wof:name":"We Care Ministries",
    "wof:placetype":"venue"
},
  "geometry": {"coordinates":[-93.090592,31.76525],"type":"Point"}
}