{
  "type": "Feature",
  "properties": {
    "iso:country":"US",
    "sg:address":"1828 N Ave G",
    "sg:city":"Crowley",
    "sg:classifiers":[
        {
            "category":"Autos & Motor Vehicles",
            "subcategory":"Auto Supplies",
            "type":"Retail Goods"
        }
    ],
    "sg:phone":"+1 337 788 2361",
    "sg:postcode":"70526",
    "sg:province":"LA",
    "sg:tags":[
        "automobile",
        "parts"
    ],
    "wof:name":"O'Reilly Auto Parts",
    "wof:placetype":"venue"
},
  "geometry": {"coordinates":[-92.37871699999999,30.226217],"type":"Point"}
}