{
  "type": "Feature",
  "properties": {
    "iso:country":"US",
    "sg:address":"1028 Manhattan Blvd",
    "sg:city":"Harvey",
    "sg:classifiers":[
        {
            "category":"Professional",
            "subcategory":"Accounting & Tax Preparation",
            "type":"Services"
        }
    ],
    "sg:phone":"+1 504 368 2216",
    "sg:postcode":"70058",
    "sg:province":"LA",
    "sg:tags":[
        "return",
        "filing"
    ],
    "wof:name":"Liberty Tax Svc",
    "wof:placetype":"venue"
},
  "geometry": {"coordinates":[-90.062873,29.898372],"type":"Point"}
}