{
  "type": "Feature",
  "properties": {
    "addr:full":"517 S Chataignier St Ville Platte LA 70586",
    "addr:housenumber":"517",
    "addr:postcode":"70586",
    "addr:street":"S Chataignier St",
    "iso:country":"US",
    "sg:address":"517 S Chataignier St",
    "sg:city":"Ville Platte",
    "sg:classifiers":[
        {
            "category":"Shopping",
            "type":"Retail Goods"
        }
    ],
    "sg:phone":"+1 337 363 5300",
    "sg:postcode":"70586",
    "sg:province":"LA",
    "sg:tags":[
        "trophy",
        "medal",
        "award"
    ],
    "wof:name":"Trophy Creations",
    "wof:placetype":"venue"
},
  "geometry": {"coordinates":[-92.273916,30.68348],"type":"Point"}
}