{
  "type": "Feature",
  "properties": {
    "iso:country":"US",
    "sg:address":"6760 State Rte 31",
    "sg:city":"Opelousas",
    "sg:classifiers":[
        {
            "category":"Retail",
            "subcategory":"Auto Repair",
            "type":"Services"
        }
    ],
    "sg:phone":"+1 337 942 8148",
    "sg:postcode":"70570",
    "sg:province":"LA",
    "sg:tags":[
        "repairing",
        "automobile",
        "general"
    ],
    "wof:name":"Mack's Repair & Alignment",
    "wof:placetype":"venue"
},
  "geometry": {"coordinates":[-92.045986,30.489538],"type":"Point"}
}