{
  "type": "Feature",
  "properties": {
    "iso:country":"US",
    "sg:address":"5023 Magazine St",
    "sg:city":"New Orleans",
    "sg:classifiers":[
        {
            "category":"Autos & Motor Vehicles",
            "subcategory":"Fuel & Gas Station",
            "type":"Retail Goods"
        }
    ],
    "sg:phone":"+1 504 899 7211",
    "sg:postcode":"70115",
    "sg:province":"LA",
    "sg:tags":[
        "oil"
    ],
    "wof:name":"Kollin Service Station",
    "wof:placetype":"venue"
},
  "geometry": {"coordinates":[-90.10983299999999,29.920427],"type":"Point"}
}