{
  "type": "Feature",
  "properties": {
    "addr:full":"8910 Tilford Rd New Orleans LA 70127",
    "addr:housenumber":"8910",
    "addr:postcode":"70127",
    "addr:street":"Tilford Rd",
    "iso:country":"US",
    "sg:address":"8910 Tilford Rd",
    "sg:city":"New Orleans",
    "sg:classifiers":[
        {
            "category":"Building & Trades",
            "subcategory":"Construction",
            "type":"Services"
        }
    ],
    "sg:phone":"+1 504 246 1362",
    "sg:postcode":"70127",
    "sg:province":"LA",
    "sg:tags":[
        "house"
    ],
    "wof:name":"BAN Remodeling",
    "wof:placetype":"venue"
},
  "geometry": {"coordinates":[-89.982192,30.02554],"type":"Point"}
}