{
  "type": "Feature",
  "properties": {
    "iso:country":"US",
    "sg:address":"123 Industrial Dr",
    "sg:city":"Rayne",
    "sg:classifiers":[
        {
            "category":"Freight",
            "type":"Transportation"
        }
    ],
    "sg:phone":"+1 337 334 1799",
    "sg:postcode":"70578",
    "sg:province":"LA",
    "sg:tags":[
        "dry",
        "bulk",
        "trucking"
    ],
    "wof:name":"Hercules Transport",
    "wof:placetype":"venue"
},
  "geometry": {"coordinates":[-92.30559700000001,30.232858],"type":"Point"}
}