{
  "type": "Feature",
  "properties": {
    "iso:country":"US",
    "sg:address":"105 N Pat St",
    "sg:city":"Scott",
    "sg:classifiers":[
        {
            "category":"Building & Trades",
            "subcategory":"Construction",
            "type":"Services"
        }
    ],
    "sg:phone":"+1 337 268 9551",
    "sg:postcode":"70583",
    "sg:province":"LA",
    "sg:tags":[
        "contractor"
    ],
    "wof:name":"Lrj Lebeouf Llc",
    "wof:placetype":"venue"
},
  "geometry": {"coordinates":[-92.05802,30.240351],"type":"Point"}
}