{
  "type": "Feature",
  "properties": {
    "iso:country":"US",
    "sg:address":"110 Oakridge St",
    "sg:city":"Lafayette",
    "sg:classifiers":[
        {
            "category":"Building & Trades",
            "subcategory":"Pest Control",
            "type":"Services"
        }
    ],
    "sg:phone":"+1 337 269 9672",
    "sg:postcode":"70506",
    "sg:province":"LA",
    "wof:name":"Precise Pest Control",
    "wof:placetype":"venue"
},
  "geometry": {"coordinates":[-92.03756,30.221594],"type":"Point"}
}