{
  "type": "Feature",
  "properties": {
    "iso:country":"US",
    "sg:address":"10822 W Robin Hood Dr",
    "sg:city":"Baton Rouge",
    "sg:classifiers":[
        {
            "category":"Real Estate",
            "subcategory":"Real Estate Agent",
            "type":"Services"
        }
    ],
    "sg:phone":"+1 225 272 9415",
    "sg:postcode":"70815",
    "sg:province":"LA",
    "wof:name":"Kay's Realty",
    "wof:placetype":"venue"
},
  "geometry": {"coordinates":[-91.06285800000001,30.455575],"type":"Point"}
}