{
  "type": "Feature",
  "properties": {
    "iso:country":"US",
    "sg:address":"6709 Pines Rd",
    "sg:city":"Shreveport",
    "sg:classifiers":[
        {
            "category":"Banks & Credit Unions",
            "subcategory":"Bank",
            "type":"Services"
        }
    ],
    "sg:phone":"+1 318 688 9030",
    "sg:postcode":"71129",
    "sg:province":"LA",
    "sg:tags":[
        "loan"
    ],
    "wof:name":"Mr Thrifty Express Loans",
    "wof:placetype":"venue"
},
  "geometry": {"coordinates":[-93.865154,32.448175],"type":"Point"}
}