{
  "type": "Feature",
  "properties": {
    "iso:country":"US",
    "sg:address":"8202 Maurice Ave",
    "sg:city":"Maurice",
    "sg:classifiers":[
        {
            "category":"Restaurant",
            "type":"Food & Drink"
        }
    ],
    "sg:menulink":"http://www.allmenus.com/la/maurice/80247-dominos-pizza/menu/",
    "sg:phone":"+1 337 893 4334",
    "sg:postcode":"70555",
    "sg:province":"LA",
    "sg:tags":[
        "american",
        "wing",
        "pizza"
    ],
    "wof:name":"Domino's Pizza",
    "wof:placetype":"venue"
},
  "geometry": {"coordinates":[-92.124287,30.061484],"type":"Point"}
}