{
  "type": "Feature",
  "properties": {
    "iso:country":"US",
    "sg:address":"7391 Read Blvd",
    "sg:city":"New Orleans",
    "sg:classifiers":[
        {
            "category":"Insurance",
            "subcategory":"Insurance Agent",
            "type":"Services"
        }
    ],
    "sg:phone":"+1 504 241 7286",
    "sg:postcode":"70127",
    "sg:province":"LA",
    "wof:name":"Allstate Insurance",
    "wof:placetype":"venue"
},
  "geometry": {"coordinates":[-89.97917700000001,30.041554],"type":"Point"}
}