{
  "type": "Feature",
  "properties": {
    "addr:full":"9087 State Rte 941 Gonzales LA 70737",
    "addr:housenumber":"9087",
    "addr:postcode":"70737",
    "addr:street":"State Rte 941 Gonzales La",
    "iso:country":"US",
    "sg:address":"9087 State Rte 941",
    "sg:city":"Gonzales",
    "sg:classifiers":[
        {
            "category":"Retail",
            "subcategory":"Auto Repair",
            "type":"Services"
        }
    ],
    "sg:phone":"+1 225 675 8075",
    "sg:postcode":"70737",
    "sg:province":"LA",
    "sg:tags":[
        "wrecker"
    ],
    "wof:name":"Gonzales Towing & Repair Inc",
    "wof:placetype":"venue"
},
  "geometry": {"coordinates":[-90.886588,30.197493],"type":"Point"}
}