{
  "type": "Feature",
  "properties": {
    "addr:full":"5743 S Pollard Pkwy Baton Rouge LA 70808",
    "addr:housenumber":"5743",
    "addr:postcode":"70808",
    "addr:street":"S Pollard Pkwy",
    "iso:country":"US",
    "sg:address":"5743 S Pollard Pkwy",
    "sg:city":"Baton Rouge",
    "sg:classifiers":[
        {
            "category":"Professional",
            "type":"Services"
        }
    ],
    "sg:phone":"+1 225 767 2240",
    "sg:postcode":"70808",
    "sg:province":"LA",
    "wof:name":"Charles G Smith",
    "wof:placetype":"venue"
},
  "geometry": {"coordinates":[-91.13431300000001,30.400266],"type":"Point"}
}