{
  "type": "Feature",
  "properties": {
    "iso:country":"US",
    "sg:address":"627 Old Spanish Trl",
    "sg:city":"Slidell",
    "sg:classifiers":[
        {
            "category":"Autos & Motor Vehicles",
            "subcategory":"Auto Supplies",
            "type":"Retail Goods"
        }
    ],
    "sg:phone":"+1 985 643 7092",
    "sg:postcode":"70458",
    "sg:province":"LA",
    "sg:tags":[
        "tire"
    ],
    "wof:name":"Tire Town Stores",
    "wof:placetype":"venue"
},
  "geometry": {"coordinates":[-89.7825,30.263494],"type":"Point"}
}