{
  "type": "Feature",
  "properties": {
    "addr:full":"131 Huey P Long Ave Gretna LA 70053",
    "addr:housenumber":"131;p",
    "addr:postcode":"70053",
    "addr:street":"Huey;Long Ave",
    "iso:country":"US",
    "sg:address":"131 Huey P Long Ave",
    "sg:city":"Gretna",
    "sg:classifiers":[
        {
            "category":"Restaurant",
            "type":"Food & Drink"
        }
    ],
    "sg:phone":"+1 504 368 8678",
    "sg:postcode":"70053",
    "sg:province":"LA",
    "sg:tags":[
        "banquet",
        "room"
    ],
    "wof:name":"Mothers Restaurant",
    "wof:placetype":"venue"
},
  "geometry": {"coordinates":[-90.06590300000001,29.9175],"type":"Point"}
}