{
  "type": "Feature",
  "properties": {
    "iso:country":"US",
    "sg:address":"9445 Lindale Ave",
    "sg:city":"Baton Rouge",
    "sg:classifiers":[
        {
            "category":"Wholesale",
            "subcategory":"Construction Materials",
            "type":"Manufacturing & Wholesale Goods"
        }
    ],
    "sg:phone":"+1 225 927 8376",
    "sg:postcode":"70815",
    "sg:province":"LA",
    "sg:tags":[
        "building"
    ],
    "wof:name":"Werco Building Specialties",
    "wof:placetype":"venue"
},
  "geometry": {"coordinates":[-91.085019,30.439112],"type":"Point"}
}