{
  "type": "Feature",
  "properties": {
    "addr:full":"107 Magnolia Ridge Rd Boutte LA 70039",
    "addr:housenumber":"107",
    "addr:postcode":"70039",
    "addr:street":"Magnolia Ridge Rd",
    "iso:country":"US",
    "sg:address":"107 Magnolia Ridge Rd",
    "sg:city":"Boutte",
    "sg:classifiers":[
        {
            "category":"Organizations",
            "subcategory":"Religious Organization",
            "type":"Services"
        }
    ],
    "sg:phone":"+1 985 785 8395",
    "sg:postcode":"70039",
    "sg:province":"LA",
    "sg:tags":[
        "church"
    ],
    "wof:name":"Mt Zion Baptist Church",
    "wof:placetype":"venue"
},
  "geometry": {"coordinates":[-90.38546599999999,29.896663],"type":"Point"}
}