{
  "type": "Feature",
  "properties": {
    "iso:country":"US",
    "sg:address":"9986 Bayou Des Glaises St",
    "sg:city":"Moreauville",
    "sg:classifiers":[
        {
            "category":"Organizations",
            "subcategory":"Religious Organization",
            "type":"Services"
        }
    ],
    "sg:phone":"+1 318 985 2774",
    "sg:postcode":"71355",
    "sg:province":"LA",
    "sg:tags":[
        "church"
    ],
    "wof:name":"Sacred Heart Catholic Church",
    "wof:placetype":"venue"
},
  "geometry": {"coordinates":[-91.977479,31.037804],"type":"Point"}
}