{
  "type": "Feature",
  "properties": {
    "iso:country":"US",
    "sg:address":"4770 Southern Ave",
    "sg:city":"Shreveport",
    "sg:classifiers":[
        {
            "category":"Wholesale",
            "subcategory":"Home Furnishings",
            "type":"Manufacturing & Wholesale Goods"
        }
    ],
    "sg:phone":"+1 318 221 5900",
    "sg:postcode":"71106",
    "sg:province":"LA",
    "sg:tags":[
        "mat",
        "matting"
    ],
    "wof:name":"American Dust Control Inc",
    "wof:placetype":"venue"
},
  "geometry": {"coordinates":[-93.754778,32.456692],"type":"Point"}
}