{
  "type": "Feature",
  "properties": {
    "addr:full":"1547 Munal Dr Baton Rouge LA 70816",
    "addr:housenumber":"1547",
    "addr:postcode":"70816",
    "addr:street":"Munal Dr",
    "iso:country":"US",
    "sg:address":"1547 Munal Dr",
    "sg:city":"Baton Rouge",
    "sg:classifiers":[
        {
            "category":"Professional",
            "subcategory":"Business Services",
            "type":"Services"
        }
    ],
    "sg:phone":"+1 225 274 8224",
    "sg:postcode":"70816",
    "sg:province":"LA",
    "sg:tags":[
        "process",
        "server"
    ],
    "wof:name":"AAA Process Servers",
    "wof:placetype":"venue"
},
  "geometry": {"coordinates":[-91.01963499999999,30.446126],"type":"Point"}
}