{
  "type": "Feature",
  "properties": {
    "addr:full":"4911 Hot Wells Rd Boyce LA 71409",
    "addr:housenumber":"4911",
    "addr:postcode":"71409",
    "addr:street":"Hot Wells Rd",
    "iso:country":"US",
    "sg:address":"4911 Hot Wells Rd",
    "sg:city":"Boyce",
    "sg:classifiers":[
        {
            "category":"Organizations",
            "subcategory":"Religious Organization",
            "type":"Services"
        }
    ],
    "sg:phone":"+1 318 793 2043",
    "sg:postcode":"71409",
    "sg:province":"LA",
    "wof:name":"Second Evning Star Bptst Chrch",
    "wof:placetype":"venue"
},
  "geometry": {"coordinates":[-92.616236,31.311675],"type":"Point"}
}