{
  "type": "Feature",
  "properties": {
    "iso:country":"US",
    "sg:address":"902 N Beech St",
    "sg:city":"Tallulah",
    "sg:classifiers":[
        {
            "category":"Real Estate",
            "subcategory":"Real Estate Operator",
            "type":"Services"
        }
    ],
    "sg:phone":"+1 318 574 2304",
    "sg:postcode":"71282",
    "sg:province":"LA",
    "sg:tags":[
        "apartment"
    ],
    "wof:name":"Madison Place Apartments",
    "wof:placetype":"venue"
},
  "geometry": {"coordinates":[-91.18231,32.408972],"type":"Point"}
}