{
  "type": "Feature",
  "properties": {
    "iso:country":"US",
    "sg:address":"400 N Enterprise Blvd",
    "sg:city":"Lake Charles",
    "sg:classifiers":[
        {
            "category":"Social Services",
            "subcategory":"Child Care",
            "type":"Services"
        }
    ],
    "sg:phone":"+1 337 437 8258",
    "sg:postcode":"70601",
    "sg:province":"LA",
    "wof:name":"Annette's Developmental & Lrng",
    "wof:placetype":"venue"
},
  "geometry": {"coordinates":[-93.20442799999999,30.242744],"type":"Point"}
}