{
  "type": "Feature",
  "properties": {
    "iso:country":"US",
    "sg:address":"380 Bernice Hwy",
    "sg:city":"Farmerville",
    "sg:classifiers":[
        {
            "category":"Restaurant",
            "type":"Food & Drink"
        }
    ],
    "sg:phone":"+1 318 368 0600",
    "sg:postcode":"71241",
    "sg:province":"LA",
    "wof:name":"K & D's Bar-B-Que",
    "wof:placetype":"venue"
},
  "geometry": {"coordinates":[-92.40937700000001,32.781274],"type":"Point"}
}