{
  "type": "Feature",
  "properties": {
    "addr:full":"2240 Texas Eastern Rd Ragley LA 70657",
    "addr:housenumber":"2240",
    "addr:postcode":"70657",
    "addr:street":"Texas Eastern Rd",
    "iso:country":"US",
    "sg:address":"2240 Texas Eastern Rd",
    "sg:city":"Ragley",
    "sg:classifiers":[
        {
            "category":"Building & Trades",
            "subcategory":"Construction",
            "type":"Services"
        }
    ],
    "sg:phone":"+1 337 725 3621",
    "sg:postcode":"70657",
    "sg:province":"LA",
    "sg:tags":[
        "pipe",
        "line",
        "contractor"
    ],
    "wof:name":"Texas Eastern Transmission",
    "wof:placetype":"venue"
},
  "geometry": {"coordinates":[-93.14760200000001,30.43216],"type":"Point"}
}