{
  "type": "Feature",
  "properties": {
    "iso:country":"US",
    "sg:address":"4640 Ambassador Caffery Pkwy",
    "sg:city":"Lafayette",
    "sg:classifiers":[
        {
            "category":"Health Services",
            "subcategory":"Doctor",
            "type":"Services"
        }
    ],
    "sg:phone":"+1 337 984 1050",
    "sg:postcode":"70508",
    "sg:province":"LA",
    "sg:tags":[
        "physician",
        "surgeon"
    ],
    "sg:website":"www.acadianawomen.com",
    "wof:name":"Acadiana Womens Health Group",
    "wof:placetype":"venue"
},
  "geometry": {"coordinates":[-92.042548,30.151854],"type":"Point"}
}