{
  "type": "Feature",
  "properties": {
    "addr:full":"159 W State St Baton Rouge LA 70802",
    "addr:housenumber":"159",
    "addr:postcode":"70802",
    "addr:street":"W State St",
    "iso:country":"US",
    "sg:address":"159 W State St",
    "sg:city":"Baton Rouge",
    "sg:classifiers":[
        {
            "category":"Manufacturing",
            "subcategory":"Printing",
            "type":"Manufacturing & Wholesale Goods"
        }
    ],
    "sg:phone":"+1 225 344 7296",
    "sg:postcode":"70802",
    "sg:province":"LA",
    "sg:tags":[
        "printer"
    ],
    "sg:website":"www.kinkos.com",
    "wof:name":"Fed Ex Kinko's Ofc & Print Ctr",
    "wof:placetype":"venue"
},
  "geometry": {"coordinates":[-91.178246,30.418122],"type":"Point"}
}