{
  "type": "Feature",
  "properties": {
    "iso:country":"US",
    "sg:address":"1775 Grand Caillou Rd",
    "sg:city":"Houma",
    "sg:classifiers":[
        {
            "category":"Professional",
            "subcategory":"Accounting & Tax Preparation",
            "type":"Services"
        }
    ],
    "sg:phone":"+1 985 879 3459",
    "sg:postcode":"70363",
    "sg:province":"LA",
    "sg:tags":[
        "accountant"
    ],
    "wof:name":"Edward W Hay CPA",
    "wof:placetype":"venue"
},
  "geometry": {"coordinates":[-90.682142,29.566979],"type":"Point"}
}