{
  "type": "Feature",
  "properties": {
    "addr:full":"908 Broadway St Delhi LA 71232",
    "addr:housenumber":"908",
    "addr:postcode":"71232",
    "addr:street":"Broadway St",
    "iso:country":"US",
    "sg:address":"908 Broadway St",
    "sg:city":"Delhi",
    "sg:classifiers":[
        {
            "category":"Shopping",
            "subcategory":"Department Store",
            "type":"Retail Goods"
        }
    ],
    "sg:phone":"+1 318 878 9993",
    "sg:postcode":"71232",
    "sg:province":"LA",
    "sg:tags":[
        "shop"
    ],
    "wof:name":"Fred's Store",
    "wof:placetype":"venue"
},
  "geometry": {"coordinates":[-91.49291599999999,32.448098],"type":"Point"}
}