{
  "type": "Feature",
  "properties": {
    "iso:country":"US",
    "sg:address":"4240 Williams Blvd",
    "sg:city":"Kenner",
    "sg:classifiers":[
        {
            "category":"Banks & Credit Unions",
            "subcategory":"Bank",
            "type":"Services"
        }
    ],
    "sg:phone":"+1 504 467 8500",
    "sg:postcode":"70065",
    "sg:province":"LA",
    "sg:tags":[
        "financing"
    ],
    "wof:name":"General Finance",
    "wof:placetype":"venue"
},
  "geometry": {"coordinates":[-90.23802999999999,30.033328],"type":"Point"}
}