{
  "type": "Feature",
  "properties": {
    "iso:country":"US",
    "sg:address":"18445 Red Oak Dr",
    "sg:city":"Prairieville",
    "sg:classifiers":[
        {
            "category":"Food & Beverages",
            "subcategory":"Candy",
            "type":"Retail Goods"
        }
    ],
    "sg:phone":"+1 225 673 6546",
    "sg:postcode":"70769",
    "sg:province":"LA",
    "wof:name":"Brendas Candy Fur You",
    "wof:placetype":"venue"
},
  "geometry": {"coordinates":[-90.990247,30.332794],"type":"Point"}
}