{
  "type": "Feature",
  "properties": {
    "iso:country":"US",
    "sg:address":"211 Westport Dr",
    "sg:city":"Houma",
    "sg:classifiers":[
        {
            "category":"Manufacturing",
            "subcategory":"Printing",
            "type":"Manufacturing & Wholesale Goods"
        }
    ],
    "sg:phone":"+1 985 868 3374",
    "sg:postcode":"70360",
    "sg:province":"LA",
    "sg:tags":[
        "book"
    ],
    "wof:name":"Daddybond Books Publishing Co",
    "wof:placetype":"venue"
},
  "geometry": {"coordinates":[-90.749734,29.59229],"type":"Point"}
}