{
  "type": "Feature",
  "properties": {
    "addr:full":"1300 Mandeville St New Orleans LA 70117",
    "addr:housenumber":"1300",
    "addr:postcode":"70117",
    "addr:street":"Mandeville St",
    "iso:country":"US",
    "sg:address":"1300 Mandeville St",
    "sg:city":"New Orleans",
    "sg:classifiers":[
        {
            "category":"Food & Beverages",
            "subcategory":"Groceries & Convenience Stores",
            "type":"Retail Goods"
        }
    ],
    "sg:phone":"+1 504 944 1249",
    "sg:postcode":"70117",
    "sg:province":"LA",
    "sg:tags":[
        "grocer"
    ],
    "wof:name":"Pilet Self Svc Food Store",
    "wof:placetype":"venue"
},
  "geometry": {"coordinates":[-90.05461200000001,29.971735],"type":"Point"}
}