{
  "type": "Feature",
  "properties": {
    "iso:country":"US",
    "sg:address":"1925 SW Railroad Ave",
    "sg:city":"Hammond",
    "sg:classifiers":[
        {
            "category":"Restaurant",
            "type":"Food & Drink"
        }
    ],
    "sg:menulink":"http://www.allmenus.com/la/hammond/72987-pizza-hut/menu/",
    "sg:phone":"+1 985 542 8596",
    "sg:postcode":"70403",
    "sg:province":"LA",
    "sg:tags":[
        "american",
        "pizza"
    ],
    "wof:name":"Pizza Hut",
    "wof:placetype":"venue"
},
  "geometry": {"coordinates":[-90.45682600000001,30.483389],"type":"Point"}
}