{
  "type": "Feature",
  "properties": {
    "iso:country":"US",
    "sg:address":"4905 Bissonet Dr",
    "sg:city":"Metairie",
    "sg:classifiers":[
        {
            "category":"Professional",
            "type":"Services"
        }
    ],
    "sg:phone":"+1 504 885 9400",
    "sg:postcode":"70003",
    "sg:province":"LA",
    "wof:name":"Emanon Services Inc",
    "wof:placetype":"venue"
},
  "geometry": {"coordinates":[-90.212217,30.023459],"type":"Point"}
}