{
  "type": "Feature",
  "properties": {
    "addr:full":"13711 Coursey Blvd Baton Rouge LA 70817",
    "addr:housenumber":"13711",
    "addr:postcode":"70817",
    "addr:street":"Coursey Blvd",
    "iso:country":"US",
    "sg:address":"13711 Coursey Blvd",
    "sg:city":"Baton Rouge",
    "sg:classifiers":[
        {
            "category":"Restaurant",
            "type":"Food & Drink"
        }
    ],
    "sg:menulink":"http://www.allmenus.com/la/baton-rouge/236441-tropical-smoothie/menu/",
    "sg:phone":"+1 225 755 1511",
    "sg:postcode":"70817",
    "sg:province":"LA",
    "sg:tags":[
        "smoothy",
        "juice",
        "american"
    ],
    "wof:name":"Tropical Smoothie",
    "wof:placetype":"venue"
},
  "geometry": {"coordinates":[-91.02638,30.408196],"type":"Point"}
}