{
  "type": "Feature",
  "properties": {
    "addr:full":"10859 Perkins Rd Baton Rouge LA 70810",
    "addr:housenumber":"10859",
    "addr:postcode":"70810",
    "addr:street":"Perkins Rd",
    "iso:country":"US",
    "sg:address":"10859 Perkins Rd",
    "sg:city":"Baton Rouge",
    "sg:classifiers":[
        {
            "category":"Retail",
            "subcategory":"Laundry & Dry Cleaning",
            "type":"Services"
        }
    ],
    "sg:phone":"+1 225 769 6062",
    "sg:postcode":"70810",
    "sg:province":"LA",
    "sg:tags":[
        "cleaners"
    ],
    "wof:name":"Peerless Cleaners",
    "wof:placetype":"venue"
},
  "geometry": {"coordinates":[-91.08995899999999,30.374681],"type":"Point"}
}