{
  "type": "Feature",
  "properties": {
    "addr:full":"3825 Gilbert Dr Bossier City LA 71104",
    "addr:housenumber":"3825",
    "addr:postcode":"71104",
    "addr:street":"Gilbert Dr",
    "iso:country":"US",
    "sg:address":"3825 Gilbert Dr",
    "sg:city":"Bossier City",
    "sg:classifiers":[
        {
            "category":"Wholesale",
            "subcategory":"Electrical",
            "type":"Manufacturing & Wholesale Goods"
        }
    ],
    "sg:phone":"+1 318 861 5954",
    "sg:postcode":"71104",
    "sg:province":"LA",
    "sg:tags":[
        "electronic",
        "merchandise"
    ],
    "wof:name":"Motorola",
    "wof:placetype":"venue"
},
  "geometry": {"coordinates":[-93.737241,32.47153],"type":"Point"}
}