{
  "type": "Feature",
  "properties": {
    "iso:country":"US",
    "sg:address":"108 Leah St",
    "sg:city":"Ball",
    "sg:classifiers":[
        {
            "category":"Professional",
            "subcategory":"Business Services",
            "type":"Services"
        }
    ],
    "sg:phone":"+1 318 640 9264",
    "sg:postcode":"71405",
    "sg:province":"LA",
    "wof:name":"Stanley P Crane",
    "wof:placetype":"venue"
},
  "geometry": {"coordinates":[-92.408396,31.406097],"type":"Point"}
}