{
  "type": "Feature",
  "properties": {
    "addr:full":"176 Rebel Ave New Orleans LA 70123",
    "addr:housenumber":"176",
    "addr:postcode":"70123",
    "addr:street":"Rebel Ave",
    "iso:country":"US",
    "sg:address":"176 Rebel Ave",
    "sg:city":"New Orleans",
    "sg:classifiers":[
        {
            "category":"Professional",
            "subcategory":"Business Services",
            "type":"Services"
        }
    ],
    "sg:phone":"+1 504 738 2906",
    "sg:postcode":"70123",
    "sg:province":"LA",
    "sg:tags":[
        "plant",
        "design",
        "maintenance"
    ],
    "wof:name":"Tropical Interior Plant Svc",
    "wof:placetype":"venue"
},
  "geometry": {"coordinates":[-90.223083,29.963093],"type":"Point"}
}