{
  "type": "Feature",
  "properties": {
    "iso:country":"US",
    "sg:address":"2604 Choctaw St",
    "sg:city":"New Orleans",
    "sg:classifiers":[
        {
            "category":"Wholesale",
            "subcategory":"Durable Goods & Equipment",
            "type":"Manufacturing & Wholesale Goods"
        }
    ],
    "sg:phone":"+1 504 943 8801",
    "sg:postcode":"70117",
    "sg:province":"LA",
    "sg:tags":[
        "exporter"
    ],
    "wof:name":"Just For Kids Daycare & Prschl",
    "wof:placetype":"venue"
},
  "geometry": {"coordinates":[-90.01246399999999,29.978029],"type":"Point"}
}