{
  "type": "Feature",
  "properties": {
    "addr:full":"311 Market St Hammond LA 70401",
    "addr:housenumber":"311",
    "addr:postcode":"70401",
    "addr:street":"Market St",
    "iso:country":"US",
    "sg:address":"311 Market St",
    "sg:city":"Hammond",
    "sg:classifiers":[
        {
            "category":"Autos & Motor Vehicles",
            "subcategory":"Auto Supplies",
            "type":"Retail Goods"
        }
    ],
    "sg:phone":"+1 985 543 0016",
    "sg:postcode":"70401",
    "sg:province":"LA",
    "sg:tags":[
        "alternator",
        "generator"
    ],
    "wof:name":"Daniel's Starter & Alternator",
    "wof:placetype":"venue"
},
  "geometry": {"coordinates":[-90.48934300000001,30.502681],"type":"Point"}
}