{
  "type": "Feature",
  "properties": {
    "iso:country":"US",
    "sg:address":"1333 Coates Bluff Dr",
    "sg:city":"Shreveport",
    "sg:classifiers":[
        {
            "category":"Professional",
            "subcategory":"Accounting & Tax Preparation",
            "type":"Services"
        }
    ],
    "sg:phone":"+1 318 219 2312",
    "sg:postcode":"71112",
    "sg:province":"LA",
    "sg:tags":[
        "return",
        "filing"
    ],
    "wof:name":"MLS Accounting & Tax Svc",
    "wof:placetype":"venue"
},
  "geometry": {"coordinates":[-93.708449,32.49308],"type":"Point"}
}