{
  "type": "Feature",
  "properties": {
    "iso:country":"US",
    "sg:address":"3920 Wells St",
    "sg:city":"Shreveport",
    "sg:classifiers":[
        {
            "category":"Building & Trades",
            "subcategory":"Construction",
            "type":"Services"
        }
    ],
    "sg:phone":"+1 318 686 5966",
    "sg:postcode":"71103",
    "sg:province":"LA",
    "sg:tags":[
        "concrete",
        "pumping"
    ],
    "wof:name":"Hi-Tower Concrete Pumpers",
    "wof:placetype":"venue"
},
  "geometry": {"coordinates":[-93.76934300000001,32.474755],"type":"Point"}
}