{
  "type": "Feature",
  "properties": {
    "addr:full":"2824 Hwy 114 Hessmer LA 71341",
    "addr:housenumber":"2824",
    "addr:postcode":"71341",
    "addr:street":"Hwy 114 Hessmer",
    "iso:country":"US",
    "sg:address":"2824 Hwy 114",
    "sg:city":"Hessmer",
    "sg:classifiers":[
        {
            "category":"Food & Beverages",
            "subcategory":"Groceries & Convenience Stores",
            "type":"Retail Goods"
        }
    ],
    "sg:phone":"+1 318 563 4795",
    "sg:postcode":"71341",
    "sg:province":"LA",
    "sg:tags":[
        "grocer"
    ],
    "wof:name":"Country Store",
    "wof:placetype":"venue"
},
  "geometry": {"coordinates":[-92.16051,31.060299],"type":"Point"}
}