{
  "type": "Feature",
  "properties": {
    "iso:country":"US",
    "sg:address":"2837 Barataria Blvd",
    "sg:city":"Marrero",
    "sg:classifiers":[
        {
            "category":"Restaurant",
            "type":"Food & Drink"
        }
    ],
    "sg:phone":"+1 504 349 3444",
    "sg:postcode":"70072",
    "sg:province":"LA",
    "sg:tags":[
        "parlor",
        "ice",
        "cream"
    ],
    "wof:name":"Cold Spot",
    "wof:placetype":"venue"
},
  "geometry": {"coordinates":[-90.11269,29.8509],"type":"Point"}
}