{
  "type": "Feature",
  "properties": {
    "iso:country":"US",
    "sg:address":"632 Pine Hill Rd",
    "sg:city":"Shreveport",
    "sg:classifiers":[
        {
            "category":"Autos & Motor Vehicles",
            "subcategory":"Fuel & Gas Station",
            "type":"Retail Goods"
        }
    ],
    "sg:phone":"+1 318 929 7454",
    "sg:postcode":"71107",
    "sg:province":"LA",
    "sg:tags":[
        "oil"
    ],
    "wof:name":"Blanchard '66'",
    "wof:placetype":"venue"
},
  "geometry": {"coordinates":[-93.78912200000001,32.580367],"type":"Point"}
}