{
  "type": "Feature",
  "properties": {
    "iso:country":"US",
    "sg:address":"7234 Plank Rd",
    "sg:city":"Baton Rouge",
    "sg:classifiers":[
        {
            "category":"Organizations",
            "subcategory":"Religious Organization",
            "type":"Services"
        }
    ],
    "sg:phone":"+1 225 358 7772",
    "sg:postcode":"70811",
    "sg:province":"LA",
    "sg:tags":[
        "church"
    ],
    "sg:website":"www.promisedla.tripod.com",
    "wof:name":"Promise Land Baptist Church",
    "wof:placetype":"venue"
},
  "geometry": {"coordinates":[-91.147254,30.516003],"type":"Point"}
}