{
  "type": "Feature",
  "properties": {
    "iso:country":"US",
    "sg:address":"1206 Martin L King S",
    "sg:city":"Bastrop",
    "sg:classifiers":[
        {
            "category":"Retail",
            "subcategory":"Car Wash",
            "type":"Services"
        }
    ],
    "sg:phone":"+1 318 281 7982",
    "sg:postcode":"71220",
    "sg:province":"LA",
    "sg:tags":[
        "polishing",
        "washing"
    ],
    "wof:name":"Gay's Car Wash",
    "wof:placetype":"venue"
},
  "geometry": {"coordinates":[-91.92502,32.765689],"type":"Point"}
}