{
  "type": "Feature",
  "properties": {
    "iso:country":"US",
    "sg:address":"1935 Race Track Bayou Rd",
    "sg:city":"Bossier City",
    "sg:classifiers":[
        {
            "category":"Recreation",
            "type":"Entertainment"
        }
    ],
    "sg:phone":"+1 318 742 3022",
    "sg:postcode":"71111",
    "sg:province":"LA",
    "sg:tags":[
        "course",
        "golf"
    ],
    "wof:name":"Stonebridge Golf Maintenance",
    "wof:placetype":"venue"
},
  "geometry": {"coordinates":[-93.66752099999999,32.56441],"type":"Point"}
}