{
  "type": "Feature",
  "properties": {
    "iso:country":"US",
    "sg:address":"405 N Cushing Ave",
    "sg:city":"Kaplan",
    "sg:classifiers":[
        {
            "category":"Museum",
            "type":"Entertainment"
        }
    ],
    "sg:phone":"+1 337 643 1528",
    "sg:postcode":"70548",
    "sg:province":"LA",
    "wof:name":"Kaplan Museum",
    "wof:placetype":"venue"
},
  "geometry": {"coordinates":[-92.284003,30.00163],"type":"Point"}
}