{
  "type": "Feature",
  "properties": {
    "iso:country":"US",
    "sg:address":"8709 24th St",
    "sg:city":"Metairie",
    "sg:classifiers":[
        {
            "category":"Building & Trades",
            "subcategory":"Cleaning & Sanitation",
            "type":"Services"
        }
    ],
    "sg:phone":"+1 504 305 3104",
    "sg:postcode":"70003",
    "sg:province":"LA",
    "sg:tags":[
        "house"
    ],
    "wof:name":"On The Spot Maid Svc Inc",
    "wof:placetype":"venue"
},
  "geometry": {"coordinates":[-90.226339,29.998895],"type":"Point"}
}