{
  "type": "Feature",
  "properties": {
    "iso:country":"US",
    "sg:address":"2618 Buffon St",
    "sg:city":"Chalmette",
    "sg:classifiers":[
        {
            "category":"Retail",
            "subcategory":"Auto Repair",
            "type":"Services"
        }
    ],
    "sg:phone":"+1 504 278 4901",
    "sg:postcode":"70043",
    "sg:province":"LA",
    "sg:tags":[
        "body",
        "automobile",
        "painting"
    ],
    "wof:name":"Precision Collision",
    "wof:placetype":"venue"
},
  "geometry": {"coordinates":[-89.962217,29.942881],"type":"Point"}
}