{
  "type": "Feature",
  "properties": {
    "iso:country":"US",
    "sg:address":"1129 S Clearview Pkwy",
    "sg:city":"New Orleans",
    "sg:classifiers":[
        {
            "category":"Restaurant",
            "type":"Food & Drink"
        }
    ],
    "sg:menulink":"http://www.allmenus.com/la/bridge-city/173624-wendys/menu/",
    "sg:phone":"+1 504 733 8255",
    "sg:postcode":"70121",
    "sg:province":"LA",
    "sg:tags":[
        "burger",
        "american",
        "soup"
    ],
    "wof:name":"Wendy's",
    "wof:placetype":"venue"
},
  "geometry": {"coordinates":[-90.183429,29.960713],"type":"Point"}
}