{
  "type": "Feature",
  "properties": {
    "iso:country":"US",
    "sg:address":"7825 Forshey St",
    "sg:city":"New Orleans",
    "sg:classifiers":[
        {
            "category":"Organizations",
            "subcategory":"Religious Organization",
            "type":"Services"
        }
    ],
    "sg:phone":"+1 504 488 4212",
    "sg:postcode":"70125",
    "sg:province":"LA",
    "sg:tags":[
        "church"
    ],
    "wof:name":"Cornerstone Ministries",
    "wof:placetype":"venue"
},
  "geometry": {"coordinates":[-90.111024,29.960407],"type":"Point"}
}