{
  "type": "Feature",
  "properties": {
    "iso:country":"US",
    "sg:address":"1701 Broad St",
    "sg:city":"Lake Charles",
    "sg:classifiers":[
        {
            "category":"Professional",
            "subcategory":"Accounting & Tax Preparation",
            "type":"Services"
        }
    ],
    "sg:phone":"+1 337 436 2535",
    "sg:postcode":"70601",
    "sg:province":"LA",
    "sg:tags":[
        "return",
        "filing"
    ],
    "wof:name":"K & T Rapid Tax Svc",
    "wof:placetype":"venue"
},
  "geometry": {"coordinates":[-93.19611999999999,30.227528],"type":"Point"}
}