{
  "type": "Feature",
  "properties": {
    "iso:country":"US",
    "sg:address":"1723 Willow St",
    "sg:city":"Franklin",
    "sg:classifiers":[
        {
            "category":"Organizations",
            "subcategory":"Religious Organization",
            "type":"Services"
        }
    ],
    "sg:phone":"+1 337 828 4892",
    "sg:postcode":"70538",
    "sg:province":"LA",
    "wof:name":"Triune Church Of God In Christ",
    "wof:placetype":"venue"
},
  "geometry": {"coordinates":[-91.522369,29.784842],"type":"Point"}
}