{
  "type": "Feature",
  "properties": {
    "iso:country":"US",
    "sg:address":"72305 Military Rd",
    "sg:city":"Covington",
    "sg:classifiers":[
        {
            "category":"Building & Trades",
            "subcategory":"Pest Control",
            "type":"Services"
        }
    ],
    "sg:phone":"+1 985 893 8099",
    "sg:postcode":"70435",
    "sg:province":"LA",
    "wof:name":"Jerry Miller Exterminating Co",
    "wof:placetype":"venue"
},
  "geometry": {"coordinates":[-90.08208500000001,30.481693],"type":"Point"}
}