{
  "type": "Feature",
  "properties": {
    "iso:country":"US",
    "sg:address":"6221 S Claiborne Ave",
    "sg:city":"New Orleans",
    "sg:classifiers":[
        {
            "category":"Arts & Performance",
            "subcategory":"Theater",
            "type":"Entertainment"
        }
    ],
    "sg:phone":"+1 504 821 5062",
    "sg:postcode":"70125",
    "sg:province":"LA",
    "sg:tags":[
        "theatrical"
    ],
    "wof:name":"PO Boy Productions LLC",
    "wof:placetype":"venue"
},
  "geometry": {"coordinates":[-90.113212,29.945185],"type":"Point"}
}