{
  "type": "Feature",
  "properties": {
    "iso:country":"US",
    "sg:address":"1105 S College Rd",
    "sg:city":"Lafayette",
    "sg:classifiers":[
        {
            "category":"Health Services",
            "subcategory":"Doctor",
            "type":"Services"
        }
    ],
    "sg:phone":"+1 337 232 0060",
    "sg:postcode":"70503",
    "sg:province":"LA",
    "sg:tags":[
        "medical"
    ],
    "wof:name":"David J Rees MD",
    "wof:placetype":"venue"
},
  "geometry": {"coordinates":[-92.026596,30.199231],"type":"Point"}
}