{
  "type": "Feature",
  "properties": {
    "addr:full":"4025 S Saratoga St New Orleans LA 70115",
    "addr:housenumber":"4025",
    "addr:postcode":"70115",
    "addr:street":"S Saratoga St",
    "iso:country":"US",
    "sg:address":"4025 S Saratoga St",
    "sg:city":"New Orleans",
    "sg:classifiers":[
        {
            "category":"Recreation",
            "type":"Entertainment"
        }
    ],
    "sg:phone":"+1 504 896 4747",
    "sg:postcode":"70115",
    "sg:province":"LA",
    "sg:tags":[
        "tennis",
        "court"
    ],
    "wof:name":"New Orleans Nord Tennis Ctr",
    "wof:placetype":"venue"
},
  "geometry": {"coordinates":[-90.098302,29.931829],"type":"Point"}
}