{
  "type": "Feature",
  "properties": {
    "addr:full":"201 Rue Iberville Lafayette LA 70508",
    "addr:housenumber":"201",
    "addr:postcode":"70508",
    "addr:street":"Rue Iberville",
    "iso:country":"US",
    "sg:address":"201 Rue Iberville",
    "sg:city":"Lafayette",
    "sg:classifiers":[
        {
            "category":"Mining & Drilling",
            "type":"Manufacturing & Wholesale Goods"
        }
    ],
    "sg:phone":"+1 337 237 0419",
    "sg:postcode":"70508",
    "sg:province":"LA",
    "sg:tags":[
        "development",
        "gas",
        "oil",
        "exploration"
    ],
    "wof:name":"Tolar Energy LLC",
    "wof:placetype":"venue"
},
  "geometry": {"coordinates":[-92.007637,30.191758],"type":"Point"}
}