{
  "type": "Feature",
  "properties": {
    "iso:country":"US",
    "sg:address":"1602 W Pinhook Rd",
    "sg:city":"Lafayette",
    "sg:classifiers":[
        {
            "category":"Professional",
            "subcategory":"Computer Services",
            "type":"Services"
        }
    ],
    "sg:phone":"+1 337 234 5767",
    "sg:postcode":"70508",
    "sg:province":"LA",
    "wof:name":"Synergy Information Tech Group",
    "wof:placetype":"venue"
},
  "geometry": {"coordinates":[-92.01621,30.194826],"type":"Point"}
}