{
  "type": "Feature",
  "properties": {
    "addr:full":"920 Tchoupitoulas St New Orleans LA 70130",
    "addr:housenumber":"920",
    "addr:postcode":"70130",
    "addr:street":"Tchoupitoulas St",
    "iso:country":"US",
    "sg:address":"920 Tchoupitoulas St",
    "sg:city":"New Orleans",
    "sg:classifiers":[
        {
            "category":"Building & Trades",
            "subcategory":"Construction",
            "type":"Services"
        }
    ],
    "sg:phone":"+1 504 524 9930",
    "sg:postcode":"70130",
    "sg:province":"LA",
    "sg:tags":[
        "general",
        "contractor"
    ],
    "wof:name":"Design Build Group LLC",
    "wof:placetype":"venue"
},
  "geometry": {"coordinates":[-90.067353,29.942229],"type":"Point"}
}