{
  "type": "Feature",
  "properties": {
    "addr:full":"3870 Hwy 121 Boyce LA 71409",
    "addr:housenumber":"3870",
    "addr:postcode":"71409",
    "addr:street":"Hwy 121",
    "iso:country":"US",
    "sg:address":"3870 Hwy 121",
    "sg:city":"Boyce",
    "sg:classifiers":[
        {
            "category":"Building & Trades",
            "subcategory":"Plumbing",
            "type":"Services"
        }
    ],
    "sg:phone":"+1 318 793 5698",
    "sg:postcode":"71409",
    "sg:province":"LA",
    "sg:tags":[
        "plumbing",
        "contractor"
    ],
    "wof:name":"Andrews' Plumbing Repair Svc",
    "wof:placetype":"venue"
},
  "geometry": {"coordinates":[-92.670435,31.292222],"type":"Point"}
}