{
  "type": "Feature",
  "properties": {
    "iso:country":"US",
    "sg:address":"740 Stonewall-Frierson Rd",
    "sg:city":"Frierson",
    "sg:classifiers":[
        {
            "category":"Building & Trades",
            "subcategory":"Construction",
            "type":"Services"
        }
    ],
    "sg:phone":"+1 318 798 6615",
    "sg:postcode":"71027",
    "sg:province":"LA",
    "sg:tags":[
        "roofing",
        "contractor"
    ],
    "wof:name":"Whitfield Construction",
    "wof:placetype":"venue"
},
  "geometry": {"coordinates":[-93.70021199999999,32.281854],"type":"Point"}
}