{
  "type": "Feature",
  "properties": {
    "addr:full":"109 Candy Ln Thibodaux LA 70301",
    "addr:housenumber":"109",
    "addr:postcode":"70301",
    "addr:street":"Candy Ln",
    "iso:country":"US",
    "sg:address":"109 Candy Ln",
    "sg:city":"Thibodaux",
    "sg:classifiers":[
        {
            "category":"Manufacturing",
            "subcategory":"Food",
            "type":"Manufacturing & Wholesale Goods"
        }
    ],
    "sg:phone":"+1 985 446 1354",
    "sg:postcode":"70301",
    "sg:province":"LA",
    "sg:tags":[
        "confectionery",
        "candy"
    ],
    "sg:website":"www.necco.com",
    "wof:name":"Stark Candy Co",
    "wof:placetype":"venue"
},
  "geometry": {"coordinates":[-90.83039599999999,29.786395],"type":"Point"}
}