{
  "type": "Feature",
  "properties": {
    "iso:country":"US",
    "sg:address":"1330 Doctor Beatrous Rd",
    "sg:city":"Theriot",
    "sg:classifiers":[
        {
            "category":"Government",
            "subcategory":"Office",
            "type":"Public Place"
        }
    ],
    "sg:phone":"+1 985 879 4340",
    "sg:postcode":"70397",
    "sg:province":"LA",
    "wof:name":"Dularge Center",
    "wof:placetype":"venue"
},
  "geometry": {"coordinates":[-90.752965,29.460037],"type":"Point"}
}