{
  "type": "Feature",
  "properties": {
    "iso:country":"US",
    "sg:address":"52 Davenport St",
    "sg:city":"Westwego",
    "sg:classifiers":[
        {
            "category":"Health Services",
            "subcategory":"Clinic",
            "type":"Services"
        }
    ],
    "sg:phone":"+1 504 431 4518",
    "sg:postcode":"70094",
    "sg:province":"LA",
    "sg:tags":[
        "home"
    ],
    "wof:name":"Quality Home Care",
    "wof:placetype":"venue"
},
  "geometry": {"coordinates":[-90.241185,29.952037],"type":"Point"}
}