{
  "type": "Feature",
  "properties": {
    "addr:full":"200 Syrup Mill Rd Minden LA 71055",
    "addr:housenumber":"200",
    "addr:postcode":"71055",
    "addr:street":"Syrup Mill Rd",
    "iso:country":"US",
    "sg:address":"200 Syrup Mill Rd",
    "sg:city":"Minden",
    "sg:classifiers":[
        {
            "category":"Retail",
            "subcategory":"Repair Shop",
            "type":"Services"
        }
    ],
    "sg:phone":"+1 318 377 0634",
    "sg:postcode":"71055",
    "sg:province":"LA",
    "wof:name":"Franklin Upholstery",
    "wof:placetype":"venue"
},
  "geometry": {"coordinates":[-93.41104199999999,32.585449],"type":"Point"}
}