{
  "type": "Feature",
  "properties": {
    "addr:full":"131 Harbor Rd Ferriday LA 71334",
    "addr:housenumber":"131",
    "addr:postcode":"71334",
    "addr:street":"Harbor Rd",
    "iso:country":"US",
    "sg:address":"131 Harbor Rd",
    "sg:city":"Ferriday",
    "sg:classifiers":[
        {
            "category":"Organizations",
            "subcategory":"Religious Organization",
            "type":"Services"
        }
    ],
    "sg:phone":"+1 318 757 2619",
    "sg:postcode":"71334",
    "sg:province":"LA",
    "sg:tags":[
        "church"
    ],
    "wof:name":"House Of Prayer",
    "wof:placetype":"venue"
},
  "geometry": {"coordinates":[-91.566485,31.639905],"type":"Point"}
}