{
  "type": "Feature",
  "properties": {
    "iso:country":"US",
    "sg:address":"6650 Joor Rd",
    "sg:city":"Baton Rouge",
    "sg:classifiers":[
        {
            "category":"Building & Trades",
            "subcategory":"Construction",
            "type":"Services"
        }
    ],
    "sg:phone":"+1 225 927 5181",
    "sg:postcode":"70811",
    "sg:province":"LA",
    "sg:tags":[
        "painter"
    ],
    "wof:name":"Southern Fine Finishes",
    "wof:placetype":"venue"
},
  "geometry": {"coordinates":[-91.075374,30.512932],"type":"Point"}
}