{
  "type": "Feature",
  "properties": {
    "iso:country":"US",
    "sg:address":"1501 Basin St",
    "sg:city":"New Orleans",
    "sg:classifiers":[
        {
            "category":"Bars & Pubs",
            "type":"Food & Drink"
        }
    ],
    "sg:phone":"+1 504 593 9777",
    "sg:postcode":"70116",
    "sg:province":"LA",
    "sg:tags":[
        "club",
        "night"
    ],
    "wof:name":"Bertha's Place",
    "wof:placetype":"venue"
},
  "geometry": {"coordinates":[-90.072166,29.963724],"type":"Point"}
}