{
  "type": "Feature",
  "properties": {
    "iso:country":"US",
    "sg:address":"3288 State Rte 143",
    "sg:city":"Marion",
    "sg:classifiers":[
        {
            "category":"Food & Beverages",
            "subcategory":"Groceries & Convenience Stores",
            "type":"Retail Goods"
        }
    ],
    "sg:phone":"+1 318 292 5149",
    "sg:postcode":"71260",
    "sg:province":"LA",
    "wof:name":"Haile Grocery",
    "wof:placetype":"venue"
},
  "geometry": {"coordinates":[-92.147063,32.832919],"type":"Point"}
}