{
  "type": "Feature",
  "properties": {
    "iso:country":"US",
    "sg:address":"1530 4th St",
    "sg:city":"Jonesville",
    "sg:classifiers":[
        {
            "category":"Restaurant",
            "type":"Food & Drink"
        }
    ],
    "sg:phone":"+1 318 339 4304",
    "sg:postcode":"71343",
    "sg:province":"LA",
    "sg:tags":[
        "out"
    ],
    "wof:name":"Jackie's Riverside Steak",
    "wof:placetype":"venue"
},
  "geometry": {"coordinates":[-91.827764,31.629496],"type":"Point"}
}