{
  "type": "Feature",
  "properties": {
    "addr:full":"3800 Johnston St Lafayette LA 70503",
    "addr:housenumber":"3800",
    "addr:postcode":"70503",
    "addr:street":"Johnston St",
    "iso:country":"US",
    "sg:address":"3800 Johnston St",
    "sg:city":"Lafayette",
    "sg:classifiers":[
        {
            "category":"Home & Garden",
            "subcategory":"Building Materials",
            "type":"Retail Goods"
        }
    ],
    "sg:phone":"+1 337 988 0481",
    "sg:postcode":"70503",
    "sg:province":"LA",
    "sg:tags":[
        "glass",
        "window",
        "plate"
    ],
    "wof:name":"Cornerstone's Glass",
    "wof:placetype":"venue"
},
  "geometry": {"coordinates":[-92.05502799999999,30.200173],"type":"Point"}
}