{
  "type": "Feature",
  "properties": {
    "iso:country":"US",
    "sg:address":"3544 W Esplanade Ave N",
    "sg:city":"Metairie",
    "sg:classifiers":[
        {
            "category":"Shopping",
            "subcategory":"Hobbies, Toys, & Games",
            "type":"Retail Goods"
        }
    ],
    "sg:phone":"+1 504 885 4263",
    "sg:postcode":"70002",
    "sg:province":"LA",
    "sg:tags":[
        "model",
        "supply"
    ],
    "wof:name":"Galactic Games Emporium Inc",
    "wof:placetype":"venue"
},
  "geometry": {"coordinates":[-90.161019,30.014811],"type":"Point"}
}