{
  "type": "Feature",
  "properties": {
    "iso:country":"US",
    "sg:address":"421 Sonnier Rd",
    "sg:city":"Carencro",
    "sg:classifiers":[
        {
            "category":"Building & Trades",
            "subcategory":"Construction",
            "type":"Services"
        }
    ],
    "sg:phone":"+1 337 896 3900",
    "sg:postcode":"70520",
    "sg:province":"LA",
    "sg:tags":[
        "contractor"
    ],
    "wof:name":"Mann's Construction",
    "wof:placetype":"venue"
},
  "geometry": {"coordinates":[-92.019013,30.315956],"type":"Point"}
}