{
  "type": "Feature",
  "properties": {
    "addr:full":"531 Girod St New Orleans LA 70130",
    "addr:housenumber":"531",
    "addr:postcode":"70130",
    "addr:street":"Girod St",
    "iso:country":"US",
    "sg:address":"531 Girod St",
    "sg:city":"New Orleans",
    "sg:classifiers":[
        {
            "category":"Personal",
            "subcategory":"Barber",
            "type":"Services"
        }
    ],
    "sg:phone":"+1 504 524 1503",
    "sg:postcode":"70130",
    "sg:province":"LA",
    "wof:name":"Brown's Hair Design",
    "wof:placetype":"venue"
},
  "geometry": {"coordinates":[-90.069661,29.947022],"type":"Point"}
}