{
  "type": "Feature",
  "properties": {
    "iso:country":"US",
    "sg:address":"734 State Rte 485",
    "sg:city":"Natchitoches",
    "sg:classifiers":[
        {
            "category":"Organizations",
            "subcategory":"Religious Organization",
            "type":"Services"
        }
    ],
    "sg:phone":"+1 318 352 9856",
    "sg:postcode":"71457",
    "sg:province":"LA",
    "sg:tags":[
        "church"
    ],
    "wof:name":"North Star Baptist Church",
    "wof:placetype":"venue"
},
  "geometry": {"coordinates":[-93.20462999999999,31.851923],"type":"Point"}
}