{
  "type": "Feature",
  "properties": {
    "addr:full":"104 Judson Walsh Dr Opelousas LA 70570",
    "addr:housenumber":"104",
    "addr:postcode":"70570",
    "addr:street":"Judson Walsh Dr",
    "iso:country":"US",
    "sg:address":"104 Judson Walsh Dr",
    "sg:city":"Opelousas",
    "sg:classifiers":[
        {
            "category":"Retail",
            "subcategory":"Auto Repair",
            "type":"Services"
        }
    ],
    "sg:phone":"+1 337 948 9832",
    "sg:postcode":"70570",
    "sg:province":"LA",
    "sg:tags":[
        "repairing",
        "automobile"
    ],
    "wof:name":"Pitre's Automotive Svc Inc",
    "wof:placetype":"venue"
},
  "geometry": {"coordinates":[-92.088032,30.498335],"type":"Point"}
}