{
  "type": "Feature",
  "properties": {
    "addr:full":"2170 Gause Blvd W Slidell LA 70460",
    "addr:housenumber":"2170",
    "addr:postcode":"70460",
    "addr:street":"Gause Blvd W",
    "iso:country":"US",
    "sg:address":"2170 Gause Blvd W",
    "sg:city":"Slidell",
    "sg:classifiers":[
        {
            "category":"Cafe",
            "type":"Food & Drink"
        }
    ],
    "sg:menulink":"http://www.allmenus.com/la/bonfouca/155744-wow-cafe--wingery/menu/",
    "sg:phone":"+1 985 661 9692",
    "sg:postcode":"70460",
    "sg:province":"LA",
    "sg:tags":[
        "american"
    ],
    "wof:name":"Wow Cafe & Wingery",
    "wof:placetype":"venue"
},
  "geometry": {"coordinates":[-89.831937,30.301884],"type":"Point"}
}