{
  "type": "Feature",
  "properties": {
    "iso:country":"US",
    "sg:address":"324 Albert Hart Dr",
    "sg:city":"Baton Rouge",
    "sg:classifiers":[
        {
            "category":"Personal",
            "subcategory":"Beauty Salon",
            "type":"Services"
        }
    ],
    "sg:phone":"+1 225 445 1353",
    "sg:postcode":"70808",
    "sg:province":"LA",
    "wof:name":"Salon Laura",
    "wof:placetype":"venue"
},
  "geometry": {"coordinates":[-91.127205,30.379288],"type":"Point"}
}