{
  "type": "Feature",
  "properties": {
    "iso:country":"US",
    "sg:address":"7273 Greenwell Springs Rd",
    "sg:city":"Baton Rouge",
    "sg:classifiers":[
        {
            "category":"Retail",
            "subcategory":"Auto Repair",
            "type":"Services"
        }
    ],
    "sg:phone":"+1 225 928 1396",
    "sg:postcode":"70805",
    "sg:province":"LA",
    "sg:tags":[
        "general"
    ],
    "wof:name":"Davis Auto Shop Inc",
    "wof:placetype":"venue"
},
  "geometry": {"coordinates":[-91.11693099999999,30.474962],"type":"Point"}
}