{
  "type": "Feature",
  "properties": {
    "addr:full":"1272 Lafourche St Donaldsonville LA 70346",
    "addr:housenumber":"1272",
    "addr:postcode":"70346",
    "addr:street":"Lafourche St",
    "iso:country":"US",
    "sg:address":"1272 Lafourche St",
    "sg:city":"Donaldsonville",
    "sg:phone":"+1 225 473 7662",
    "sg:postcode":"70346",
    "sg:province":"LA",
    "sg:tags":[
        "oil"
    ],
    "wof:name":"Bouchereau Oil Co Inc",
    "wof:placetype":"venue"
},
  "geometry": {"coordinates":[-90.99472299999999,30.097417],"type":"Point"}
}