{
  "type": "Feature",
  "properties": {
    "addr:full":"4709 Pecanland Mall Dr Monroe LA 71203",
    "addr:housenumber":"4709",
    "addr:postcode":"71203",
    "addr:street":"Pecanland Mall Dr",
    "iso:country":"US",
    "sg:address":"4709 Pecanland Mall Dr",
    "sg:city":"Monroe",
    "sg:classifiers":[
        {
            "category":"Shopping",
            "type":"Retail Goods"
        }
    ],
    "sg:phone":"+1 318 388 0460",
    "sg:postcode":"71203",
    "sg:province":"LA",
    "sg:tags":[
        "church",
        "supply"
    ],
    "sg:website":"www.familychristian.com",
    "wof:name":"Family Christian Book Store",
    "wof:placetype":"venue"
},
  "geometry": {"coordinates":[-92.06112,32.495849],"type":"Point"}
}