{
  "type": "Feature",
  "properties": {
    "addr:full":"5159 Hwy 361 Morrow LA 71356",
    "addr:housenumber":"5159",
    "addr:postcode":"71356",
    "addr:street":"Hwy 361",
    "iso:country":"US",
    "sg:address":"5159 Hwy 361",
    "sg:city":"Morrow",
    "sg:classifiers":[
        {
            "category":"Government",
            "subcategory":"Office",
            "type":"Public Place"
        }
    ],
    "sg:phone":"+1 318 939 2292",
    "sg:postcode":"71356",
    "sg:province":"LA",
    "sg:tags":[
        "village"
    ],
    "wof:name":"Village Of Plaucheville",
    "wof:placetype":"venue"
},
  "geometry": {"coordinates":[-92.00536,30.855613],"type":"Point"}
}