{
  "type": "Feature",
  "properties": {
    "iso:country":"US",
    "sg:address":"13823 Achord Ln",
    "sg:city":"Walker",
    "sg:classifiers":[
        {
            "category":"Real Estate",
            "subcategory":"Real Estate Operator",
            "type":"Services"
        }
    ],
    "sg:phone":"+1 225 665 7416",
    "sg:postcode":"70785",
    "sg:province":"LA",
    "sg:tags":[
        "apartment"
    ],
    "wof:name":"High Point Apartments",
    "wof:placetype":"venue"
},
  "geometry": {"coordinates":[-90.85633,30.487333],"type":"Point"}
}