{
  "type": "Feature",
  "properties": {
    "iso:country":"US",
    "sg:address":"755 Larry St",
    "sg:city":"Zwolle",
    "sg:classifiers":[
        {
            "category":"Wholesale",
            "subcategory":"Farm Supplies",
            "type":"Manufacturing & Wholesale Goods"
        }
    ],
    "sg:phone":"+1 318 645 6927",
    "sg:postcode":"71462",
    "sg:province":"LA",
    "wof:name":"All American Trmt & Pest Ctrl",
    "wof:placetype":"venue"
},
  "geometry": {"coordinates":[-93.64370599999999,31.646685],"type":"Point"}
}