{
  "type": "Feature",
  "properties": {
    "iso:country":"US",
    "sg:address":"221 Sunset Dr",
    "sg:city":"Alexandria",
    "sg:classifiers":[
        {
            "category":"Real Estate",
            "subcategory":"Real Estate Operator",
            "type":"Services"
        }
    ],
    "sg:phone":"+1 318 473 2148",
    "sg:postcode":"71301",
    "sg:province":"LA",
    "sg:tags":[
        "apartment"
    ],
    "wof:name":"Alexandria Housing Authority",
    "wof:placetype":"venue"
},
  "geometry": {"coordinates":[-92.471999,31.301615],"type":"Point"}
}