{
  "type": "Feature",
  "properties": {
    "iso:country":"US",
    "sg:address":"901 Bank Ave",
    "sg:city":"New Iberia",
    "sg:classifiers":[
        {
            "category":"Food & Beverages",
            "subcategory":"Groceries & Convenience Stores",
            "type":"Retail Goods"
        }
    ],
    "sg:phone":"+1 337 369 9321",
    "sg:postcode":"70560",
    "sg:province":"LA",
    "sg:tags":[
        "grocer"
    ],
    "wof:name":"Menard Brothers",
    "wof:placetype":"venue"
},
  "geometry": {"coordinates":[-91.823097,29.994946],"type":"Point"}
}