{
  "type": "Feature",
  "properties": {
    "addr:full":"1130 Mobile St Lake Charles LA 70605",
    "addr:housenumber":"1130",
    "addr:postcode":"70605",
    "addr:street":"Mobile St",
    "iso:country":"US",
    "sg:address":"1130 Mobile St",
    "sg:city":"Lake Charles",
    "sg:classifiers":[
        {
            "category":"Shopping",
            "subcategory":"Clothing, Apparel, & Fashions",
            "type":"Retail Goods"
        }
    ],
    "sg:phone":"+1 337 439 1724",
    "sg:postcode":"70605",
    "sg:province":"LA",
    "sg:tags":[
        "infant",
        "wear"
    ],
    "wof:name":"Emily's Children Store",
    "wof:placetype":"venue"
},
  "geometry": {"coordinates":[-93.239214,30.182117],"type":"Point"}
}