{
  "type": "Feature",
  "properties": {
    "iso:country":"US",
    "sg:address":"4201 E Judge Perez Dr",
    "sg:city":"Meraux",
    "sg:classifiers":[
        {
            "category":"Education",
            "subcategory":"School",
            "type":"Public Place"
        }
    ],
    "sg:phone":"+1 504 271 0443",
    "sg:postcode":"70075",
    "sg:province":"LA",
    "wof:name":"One In Christ Academy",
    "wof:placetype":"venue"
},
  "geometry": {"coordinates":[-89.919601,29.9342],"type":"Point"}
}