{
  "type": "Feature",
  "properties": {
    "iso:country":"US",
    "sg:address":"710 N 32nd St",
    "sg:city":"Monroe",
    "sg:classifiers":[
        {
            "category":"Recreation",
            "type":"Entertainment"
        }
    ],
    "sg:phone":"+1 318 330 9300",
    "sg:postcode":"71201",
    "sg:province":"LA",
    "sg:tags":[
        "instruction",
        "gymnastic"
    ],
    "wof:name":"River City Gymnastics",
    "wof:placetype":"venue"
},
  "geometry": {"coordinates":[-92.087835,32.529687],"type":"Point"}
}