{
  "type": "Feature",
  "properties": {
    "iso:country":"US",
    "sg:address":"145 Robert E Lee Blvd",
    "sg:city":"New Orleans",
    "sg:classifiers":[
        {
            "category":"Personal",
            "subcategory":"Beauty Salon",
            "type":"Services"
        }
    ],
    "sg:phone":"+1 504 283 7002",
    "sg:postcode":"70124",
    "sg:province":"LA",
    "sg:tags":[
        "treatment",
        "skin"
    ],
    "wof:name":"Right Face",
    "wof:placetype":"venue"
},
  "geometry": {"coordinates":[-90.11192200000001,30.020179],"type":"Point"}
}