{
  "type": "Feature",
  "properties": {
    "addr:full":"602 Alex St Houma LA 70360",
    "addr:housenumber":"602",
    "addr:postcode":"70360",
    "addr:street":"Alex St",
    "iso:country":"US",
    "sg:address":"602 Alex St",
    "sg:city":"Houma",
    "sg:classifiers":[
        {
            "category":"Education",
            "subcategory":"Special Training",
            "type":"Public Place"
        }
    ],
    "sg:phone":"+1 985 868 0613",
    "sg:postcode":"70360",
    "sg:province":"LA",
    "wof:name":"Model World",
    "wof:placetype":"venue"
},
  "geometry": {"coordinates":[-90.754025,29.569539],"type":"Point"}
}