{
  "type": "Feature",
  "properties": {
    "iso:country":"US",
    "sg:address":"117 W Landry St",
    "sg:city":"Opelousas",
    "sg:classifiers":[
        {
            "category":"Professional",
            "subcategory":"Lawyer & Legal Services",
            "type":"Services"
        }
    ],
    "sg:phone":"+1 337 594 8200",
    "sg:postcode":"70570",
    "sg:province":"LA",
    "sg:tags":[
        "attorney"
    ],
    "wof:name":"D Patrick Keating Law Firm",
    "wof:placetype":"venue"
},
  "geometry": {"coordinates":[-92.08401499999999,30.533141],"type":"Point"}
}