{
  "type": "Feature",
  "properties": {
    "iso:country":"US",
    "sg:address":"2200 Westbank Expy",
    "sg:city":"Harvey",
    "sg:classifiers":[
        {
            "category":"Travel",
            "subcategory":"Hotels & Motels",
            "type":"Entertainment"
        }
    ],
    "sg:phone":"+1 504 366 5311",
    "sg:postcode":"70058",
    "sg:province":"LA",
    "sg:website":"www.neworleanstravelodge.com",
    "wof:name":"Travelodge",
    "wof:placetype":"venue"
},
  "geometry": {"coordinates":[-90.071489,29.90108],"type":"Point"}
}