{
  "type": "Feature",
  "properties": {
    "iso:country":"US",
    "sg:address":"1254 Oden St",
    "sg:city":"Shreveport",
    "sg:classifiers":[
        {
            "category":"Education",
            "subcategory":"School",
            "type":"Public Place"
        }
    ],
    "sg:phone":"+1 318 868 7108",
    "sg:postcode":"71104",
    "sg:province":"LA",
    "wof:name":"Star Point Inc",
    "wof:placetype":"venue"
},
  "geometry": {"coordinates":[-93.709112,32.490507],"type":"Point"}
}