{
  "type": "Feature",
  "properties": {
    "iso:country":"US",
    "sg:address":"666 Travis St",
    "sg:city":"Shreveport",
    "sg:classifiers":[
        {
            "category":"Professional",
            "subcategory":"Accounting & Tax Preparation",
            "type":"Services"
        }
    ],
    "sg:phone":"+1 318 424 3185",
    "sg:postcode":"71101",
    "sg:province":"LA",
    "sg:tags":[
        "accountant"
    ],
    "sg:website":"www.ybcpa.net",
    "wof:name":"Young & Bell",
    "wof:placetype":"venue"
},
  "geometry": {"coordinates":[-93.75196200000001,32.512838],"type":"Point"}
}