{
  "type": "Feature",
  "properties": {
    "iso:country":"US",
    "sg:address":"109 Commission Blvd",
    "sg:city":"Lafayette",
    "sg:classifiers":[
        {
            "category":"Professional",
            "subcategory":"Lawyer & Legal Services",
            "type":"Services"
        }
    ],
    "sg:phone":"+1 800 463 3339",
    "sg:postcode":"70508",
    "sg:province":"LA",
    "sg:tags":[
        "notary"
    ],
    "sg:website":"www.kinkos.com",
    "wof:name":"Fedex Express Ship Center",
    "wof:placetype":"venue"
},
  "geometry": {"coordinates":[-91.98554799999999,30.172196],"type":"Point"}
}