{
  "type": "Feature",
  "properties": {
    "iso:country":"US",
    "sg:address":"709 Ryan St",
    "sg:city":"Lake Charles",
    "sg:classifiers":[
        {
            "category":"Personal",
            "subcategory":"Massage",
            "type":"Services"
        }
    ],
    "sg:phone":"+1 337 437 8300",
    "sg:postcode":"70601",
    "sg:province":"LA",
    "wof:name":"Mani Toccare Therapeutic",
    "wof:placetype":"venue"
},
  "geometry": {"coordinates":[-93.21697,30.229496],"type":"Point"}
}