{
  "type": "Feature",
  "properties": {
    "iso:country":"US",
    "sg:address":"2055 McCall St",
    "sg:city":"Bossier City",
    "sg:classifiers":[
        {
            "category":"Building & Trades",
            "subcategory":"Construction",
            "type":"Services"
        }
    ],
    "sg:phone":"+1 318 742 3922",
    "sg:postcode":"71111",
    "sg:province":"LA",
    "sg:tags":[
        "demolition",
        "contractor"
    ],
    "wof:name":"H & W Demolition Inc",
    "wof:placetype":"venue"
},
  "geometry": {"coordinates":[-93.723429,32.528884],"type":"Point"}
}