{
  "type": "Feature",
  "properties": {
    "addr:full":"1799 Stumpf Blvd Gretna LA 70056",
    "addr:housenumber":"1799",
    "addr:postcode":"70056",
    "addr:street":"Stumpf Blvd",
    "iso:country":"US",
    "sg:address":"1799 Stumpf Blvd",
    "sg:city":"Gretna",
    "sg:classifiers":[
        {
            "category":"Health Services",
            "subcategory":"Nursing And Care Facility",
            "type":"Services"
        },
        {
            "category":"Social Services",
            "type":"Services"
        }
    ],
    "sg:phone":"+1 504 368 4535",
    "sg:postcode":"70056",
    "sg:province":"LA",
    "sg:tags":[
        "info",
        "program",
        "referral"
    ],
    "wof:name":"Authentic Community Living Inc",
    "wof:placetype":"venue"
},
  "geometry": {"coordinates":[-90.037826,29.911631],"type":"Point"}
}