{
  "type": "Feature",
  "properties": {
    "addr:full":"4510 Michoud Blvd New Orleans LA 70129",
    "addr:housenumber":"4510",
    "addr:postcode":"70129",
    "addr:street":"Michoud Blvd",
    "iso:country":"US",
    "sg:address":"4510 Michoud Blvd",
    "sg:city":"New Orleans",
    "sg:classifiers":[
        {
            "category":"Restaurant",
            "type":"Food & Drink"
        },
        {
            "category":"Food & Beverages",
            "subcategory":"Bakery",
            "type":"Retail Goods"
        }
    ],
    "sg:phone":"+1 504 254 5246",
    "sg:postcode":"70129",
    "sg:province":"LA",
    "sg:tags":[
        "sandwich",
        "cajun/creole"
    ],
    "wof:name":"Vucinovich's Restaurant",
    "wof:placetype":"venue"
},
  "geometry": {"coordinates":[-89.927299,30.0291],"type":"Point"}
}