{
  "type": "Feature",
  "properties": {
    "addr:full":"165 SW Railroad Ave Ponchatoula LA 70454",
    "addr:housenumber":"165",
    "addr:postcode":"70454",
    "addr:street":"Sw Railroad Ave",
    "iso:country":"US",
    "sg:address":"165 SW Railroad Ave",
    "sg:city":"Ponchatoula",
    "sg:classifiers":[
        {
            "category":"Autos & Motor Vehicles",
            "subcategory":"Auto Supplies",
            "type":"Retail Goods"
        }
    ],
    "sg:phone":"+1 985 386 4303",
    "sg:postcode":"70454",
    "sg:province":"LA",
    "sg:tags":[
        "tire"
    ],
    "wof:name":"Womack Tire Store",
    "wof:placetype":"venue"
},
  "geometry": {"coordinates":[-90.441294,30.437869],"type":"Point"}
}