{
  "type": "Feature",
  "properties": {
    "iso:country":"US",
    "sg:address":"179 Belle Terre Blvd",
    "sg:city":"La Place",
    "sg:classifiers":[
        {
            "category":"Health Services",
            "subcategory":"Doctor",
            "type":"Services"
        }
    ],
    "sg:phone":"+1 985 652 2425",
    "sg:postcode":"70068",
    "sg:province":"LA",
    "sg:tags":[
        "dentist"
    ],
    "wof:name":"Jack P Newell Jr DDS",
    "wof:placetype":"venue"
},
  "geometry": {"coordinates":[-90.50207,30.078613],"type":"Point"}
}