{
  "type": "Feature",
  "properties": {
    "iso:country":"US",
    "sg:address":"1651 Abbeville Hwy",
    "sg:city":"Rayne",
    "sg:classifiers":[
        {
            "category":"Wholesale",
            "subcategory":"Machinery & Supplies",
            "type":"Manufacturing & Wholesale Goods"
        }
    ],
    "sg:phone":"+1 337 334 5235",
    "sg:postcode":"70578",
    "sg:province":"LA",
    "sg:tags":[
        "equipment",
        "irrigation",
        "system"
    ],
    "wof:name":"Aucoin's Trucking & Backhoe",
    "wof:placetype":"venue"
},
  "geometry": {"coordinates":[-92.26914600000001,30.219981],"type":"Point"}
}