{
  "type": "Feature",
  "properties": {
    "addr:full":"1760 South Ln Mandeville LA 70471",
    "addr:housenumber":"1760",
    "addr:postcode":"70471",
    "addr:street":"South Ln",
    "iso:country":"US",
    "sg:address":"1760 South Ln",
    "sg:city":"Mandeville",
    "sg:classifiers":[
        {
            "category":"Manufacturing",
            "subcategory":"Retail Goods",
            "type":"Manufacturing & Wholesale Goods"
        }
    ],
    "sg:phone":"+1 985 893 9340",
    "sg:postcode":"70471",
    "sg:province":"LA",
    "sg:tags":[
        "casket"
    ],
    "sg:website":"www.orleanscasket.com",
    "wof:name":"Orleans Casket Co",
    "wof:placetype":"venue"
},
  "geometry": {"coordinates":[-90.035202,30.427069],"type":"Point"}
}