{
  "type": "Feature",
  "properties": {
    "iso:country":"US",
    "sg:address":"2200 N Morrison Blvd",
    "sg:city":"Hammond",
    "sg:classifiers":[
        {
            "category":"Real Estate",
            "subcategory":"Real Estate Operator",
            "type":"Services"
        }
    ],
    "sg:phone":"+1 985 345 1605",
    "sg:postcode":"70401",
    "sg:province":"LA",
    "sg:tags":[
        "apartment"
    ],
    "wof:name":"College Town Apartments",
    "wof:placetype":"venue"
},
  "geometry": {"coordinates":[-90.482713,30.519249],"type":"Point"}
}