{
  "type": "Feature",
  "properties": {
    "iso:country":"US",
    "sg:address":"255 W 177th St",
    "sg:city":"Galliano",
    "sg:classifiers":[
        {
            "category":"Farming",
            "subcategory":"Fish & Marine Products",
            "type":"Manufacturing & Wholesale Goods"
        }
    ],
    "sg:phone":"+1 985 632 7462",
    "sg:postcode":"70354",
    "sg:province":"LA",
    "sg:tags":[
        "shellfish",
        "fishing"
    ],
    "wof:name":"Noland Lasseigne",
    "wof:placetype":"venue"
},
  "geometry": {"coordinates":[-90.301913,29.429951],"type":"Point"}
}