{
  "type": "Feature",
  "properties": {
    "iso:country":"US",
    "sg:address":"905 Aberdeen Dr",
    "sg:city":"Lake Charles",
    "sg:classifiers":[
        {
            "category":"Building & Trades",
            "subcategory":"Construction",
            "type":"Services"
        }
    ],
    "sg:phone":"+1 337 562 1083",
    "sg:postcode":"70605",
    "sg:province":"LA",
    "sg:tags":[
        "hanging",
        "contractor"
    ],
    "wof:name":"Face Lift Painting LLC",
    "wof:placetype":"venue"
},
  "geometry": {"coordinates":[-93.226973,30.150766],"type":"Point"}
}