{
  "type": "Feature",
  "properties": {
    "iso:country":"US",
    "sg:address":"9667 Mesa Verde Ave",
    "sg:city":"Baton Rouge",
    "sg:classifiers":[
        {
            "category":"Real Estate",
            "subcategory":"Real Estate Agent",
            "type":"Services"
        }
    ],
    "sg:phone":"+1 225 216 3075",
    "sg:postcode":"70814",
    "sg:province":"LA",
    "wof:name":"Rainbow Community Realty",
    "wof:placetype":"venue"
},
  "geometry": {"coordinates":[-91.08153799999999,30.477244],"type":"Point"}
}