{
  "type": "Feature",
  "properties": {
    "iso:country":"US",
    "sg:address":"3844 W Loyola Dr",
    "sg:city":"Kenner",
    "sg:classifiers":[
        {
            "category":"Building & Trades",
            "subcategory":"Plumbing",
            "type":"Services"
        }
    ],
    "sg:phone":"+1 504 466 3201",
    "sg:postcode":"70065",
    "sg:province":"LA",
    "sg:tags":[
        "plumbing",
        "contractor"
    ],
    "wof:name":"A-1 Pro Plumbing & Gas Svc",
    "wof:placetype":"venue"
},
  "geometry": {"coordinates":[-90.27247699999999,30.034018],"type":"Point"}
}