{
  "type": "Feature",
  "properties": {
    "iso:country":"US",
    "sg:address":"4206 Eldridge St",
    "sg:city":"New Iberia",
    "sg:classifiers":[
        {
            "category":"Insurance",
            "subcategory":"Hazard Insurance",
            "type":"Services"
        }
    ],
    "sg:phone":"+1 337 369 9993",
    "sg:postcode":"70563",
    "sg:province":"LA",
    "sg:tags":[
        "bond"
    ],
    "wof:name":"AAA Bonding Agency",
    "wof:placetype":"venue"
},
  "geometry": {"coordinates":[-91.772564,29.993106],"type":"Point"}
}