{
  "type": "Feature",
  "properties": {
    "addr:full":"3718 Southdown Mandalay Rd Houma LA 70360",
    "addr:housenumber":"3718",
    "addr:postcode":"70360",
    "addr:street":"Southdown Mandalay Rd",
    "iso:country":"US",
    "sg:address":"3718 Southdown Mandalay Rd",
    "sg:city":"Houma",
    "sg:classifiers":[
        {
            "category":"Recreation",
            "type":"Entertainment"
        }
    ],
    "sg:phone":"+1 985 868 4758",
    "sg:postcode":"70360",
    "sg:province":"LA",
    "wof:name":"Annie Miller Tours",
    "wof:placetype":"venue"
},
  "geometry": {"coordinates":[-90.796431,29.564346],"type":"Point"}
}