{
  "type": "Feature",
  "properties": {
    "iso:country":"US",
    "sg:address":"5433 Crowder Blvd",
    "sg:city":"New Orleans",
    "sg:classifiers":[
        {
            "category":"Shopping",
            "subcategory":"Bicycles & Sporting Goods",
            "type":"Retail Goods"
        }
    ],
    "sg:phone":"+1 504 241 3239",
    "sg:postcode":"70127",
    "sg:province":"LA",
    "wof:name":"Triangle Bicycle & Lawnmower",
    "wof:placetype":"venue"
},
  "geometry": {"coordinates":[-89.990858,30.026701],"type":"Point"}
}