{
  "type": "Feature",
  "properties": {
    "iso:country":"US",
    "sg:address":"3030 Hwy 90 W",
    "sg:city":"Avondale",
    "sg:classifiers":[
        {
            "category":"Food & Beverages",
            "subcategory":"Groceries & Convenience Stores",
            "type":"Retail Goods"
        }
    ],
    "sg:phone":"+1 504 436 3968",
    "sg:postcode":"70094",
    "sg:province":"LA",
    "wof:name":"Circle K",
    "wof:placetype":"venue"
},
  "geometry": {"coordinates":[-90.205539,29.910222],"type":"Point"}
}