{
  "type": "Feature",
  "properties": {
    "addr:full":"1003 Lafourche St Donaldsonville LA 70346",
    "addr:housenumber":"1003",
    "addr:postcode":"70346",
    "addr:street":"Lafourche St",
    "iso:country":"US",
    "sg:address":"1003 Lafourche St",
    "sg:city":"Donaldsonville",
    "sg:classifiers":[
        {
            "category":"Building & Trades",
            "subcategory":"Construction",
            "type":"Services"
        }
    ],
    "sg:phone":"+1 225 473 8322",
    "sg:postcode":"70346",
    "sg:province":"LA",
    "sg:tags":[
        "contractor"
    ],
    "wof:name":"Calvin Ishmael Co",
    "wof:placetype":"venue"
},
  "geometry": {"coordinates":[-90.99472299999999,30.097417],"type":"Point"}
}