{
  "type": "Feature",
  "properties": {
    "iso:country":"US",
    "sg:address":"2300 Garrett Rd",
    "sg:city":"Monroe",
    "sg:classifiers":[
        {
            "category":"Real Estate",
            "subcategory":"Real Estate Operator",
            "type":"Services"
        }
    ],
    "sg:phone":"+1 318 343 4850",
    "sg:postcode":"71202",
    "sg:province":"LA",
    "sg:tags":[
        "mobile",
        "home",
        "community"
    ],
    "wof:name":"Pecanland Estates & Rv Park",
    "wof:placetype":"venue"
},
  "geometry": {"coordinates":[-92.05530899999999,32.48114],"type":"Point"}
}