{
  "type": "Feature",
  "properties": {
    "iso:country":"US",
    "sg:address":"7064 Siegen Ln",
    "sg:city":"Baton Rouge",
    "sg:classifiers":[
        {
            "category":"Utilities",
            "subcategory":"Mobile Phone",
            "type":"Services"
        }
    ],
    "sg:phone":"+1 225 292 7970",
    "sg:postcode":"70809",
    "sg:province":"LA",
    "sg:tags":[
        "telephone",
        "cellular"
    ],
    "wof:name":"Radio Shack",
    "wof:placetype":"venue"
},
  "geometry": {"coordinates":[-91.063982,30.385901],"type":"Point"}
}