{
  "type": "Feature",
  "properties": {
    "addr:full":"20860 Lee Rd Franklinton LA 70438",
    "addr:housenumber":"20860",
    "addr:postcode":"70438",
    "addr:street":"Lee Rd",
    "iso:country":"US",
    "sg:address":"20860 Lee Rd",
    "sg:city":"Franklinton",
    "sg:classifiers":[
        {
            "category":"Retail",
            "subcategory":"Auto Repair",
            "type":"Services"
        }
    ],
    "sg:phone":"+1 985 848 5155",
    "sg:postcode":"70438",
    "sg:province":"LA",
    "sg:tags":[
        "truck"
    ],
    "wof:name":"Bennett Trucking & Truck Rpr",
    "wof:placetype":"venue"
},
  "geometry": {"coordinates":[-90.009491,30.823337],"type":"Point"}
}