{
  "type": "Feature",
  "properties": {
    "iso:country":"US",
    "sg:address":"8149 Baudoin Rd",
    "sg:city":"Maurice",
    "sg:classifiers":[
        {
            "category":"Retail",
            "subcategory":"Auto Repair",
            "type":"Services"
        }
    ],
    "sg:phone":"+1 337 893 4333",
    "sg:postcode":"70555",
    "sg:province":"LA",
    "sg:tags":[
        "repairing",
        "automobile"
    ],
    "wof:name":"Elite Automotive Svc",
    "wof:placetype":"venue"
},
  "geometry": {"coordinates":[-92.10742399999999,30.119499],"type":"Point"}
}