{
  "type": "Feature",
  "properties": {
    "iso:country":"US",
    "sg:address":"721 State Rte 1",
    "sg:city":"Oil City",
    "sg:classifiers":[
        {
            "category":"Wholesale",
            "subcategory":"Machinery & Supplies",
            "type":"Manufacturing & Wholesale Goods"
        }
    ],
    "sg:phone":"+1 318 995 6825",
    "sg:postcode":"71061",
    "sg:province":"LA",
    "sg:tags":[
        "field",
        "oil",
        "equipment"
    ],
    "wof:name":"Bobcat Pipe & Supply",
    "wof:placetype":"venue"
},
  "geometry": {"coordinates":[-93.974684,32.737378],"type":"Point"}
}