{
  "type": "Feature",
  "properties": {
    "iso:country":"US",
    "sg:address":"763 North Blvd",
    "sg:city":"Baton Rouge",
    "sg:classifiers":[
        {
            "category":"Social Services",
            "type":"Services"
        }
    ],
    "sg:phone":"+1 225 387 2287",
    "sg:postcode":"70802",
    "sg:province":"LA",
    "sg:tags":[
        "professional",
        "counselor"
    ],
    "sg:website":"www.brchristiancounseling.com",
    "wof:name":"Baton Rouge Christian Cnslng",
    "wof:placetype":"venue"
},
  "geometry": {"coordinates":[-91.18338799999999,30.447417],"type":"Point"}
}