{
  "type": "Feature",
  "properties": {
    "addr:full":"317 Kirkman St Lake Charles LA 70601",
    "addr:housenumber":"317",
    "addr:postcode":"70601",
    "addr:street":"Kirkman St",
    "iso:country":"US",
    "sg:address":"317 Kirkman St",
    "sg:city":"Lake Charles",
    "sg:classifiers":[
        {
            "category":"Building & Trades",
            "subcategory":"Construction",
            "type":"Services"
        }
    ],
    "sg:phone":"+1 337 436 5147",
    "sg:postcode":"70601",
    "sg:province":"LA",
    "sg:tags":[
        "contractor"
    ],
    "wof:name":"Miracle Demolition",
    "wof:placetype":"venue"
},
  "geometry": {"coordinates":[-93.209794,30.234395],"type":"Point"}
}