{
  "type": "Feature",
  "properties": {
    "iso:country":"US",
    "sg:address":"2901 Pershing Blvd",
    "sg:city":"Shreveport",
    "sg:classifiers":[
        {
            "category":"Recreation",
            "type":"Entertainment"
        }
    ],
    "sg:phone":"+1 318 636 5555",
    "sg:postcode":"71109",
    "sg:province":"LA",
    "sg:tags":[
        "club",
        "baseball"
    ],
    "sg:website":"www.shreveportsports.com",
    "wof:name":"Shreveport Sports",
    "wof:placetype":"venue"
},
  "geometry": {"coordinates":[-93.786361,32.478738],"type":"Point"}
}