{
  "type": "Feature",
  "properties": {
    "iso:country":"US",
    "sg:address":"8700 Lake Forest Blvd",
    "sg:city":"New Orleans",
    "sg:classifiers":[
        {
            "category":"Insurance",
            "subcategory":"Insurance Agent",
            "type":"Services"
        }
    ],
    "sg:phone":"+1 504 244 9987",
    "sg:postcode":"70127",
    "sg:province":"LA",
    "wof:name":"Securall Insurance Agency",
    "wof:placetype":"venue"
},
  "geometry": {"coordinates":[-89.98870599999999,30.027913],"type":"Point"}
}