{
  "type": "Feature",
  "properties": {
    "iso:country":"US",
    "sg:address":"321 N Vermont St",
    "sg:city":"Covington",
    "sg:classifiers":[
        {
            "category":"Professional",
            "subcategory":"Lawyer & Legal Services",
            "type":"Services"
        }
    ],
    "sg:phone":"+1 985 893 7047",
    "sg:postcode":"70433",
    "sg:province":"LA",
    "wof:name":"Sanders Kimberly J LLC",
    "wof:placetype":"venue"
},
  "geometry": {"coordinates":[-90.097055,30.475627],"type":"Point"}
}