{
  "type": "Feature",
  "properties": {
    "iso:country":"US",
    "sg:address":"5246 Brittany Dr",
    "sg:city":"Baton Rouge",
    "sg:classifiers":[
        {
            "category":"Professional",
            "type":"Services"
        }
    ],
    "sg:phone":"+1 225 768 7536",
    "sg:postcode":"70808",
    "sg:province":"LA",
    "sg:tags":[
        "establishment"
    ],
    "wof:name":"Surgi Center",
    "wof:placetype":"venue"
},
  "geometry": {"coordinates":[-91.109731,30.400806],"type":"Point"}
}