{
  "type": "Feature",
  "properties": {
    "addr:full":"505 Conti St New Orleans LA 70130",
    "addr:housenumber":"505",
    "addr:postcode":"70130",
    "addr:street":"Conti St",
    "iso:country":"US",
    "sg:address":"505 Conti St",
    "sg:city":"New Orleans",
    "sg:classifiers":[
        {
            "category":"Shopping",
            "subcategory":"Florist",
            "type":"Retail Goods"
        }
    ],
    "sg:phone":"+1 504 636 3225",
    "sg:postcode":"70130",
    "sg:province":"LA",
    "wof:name":"Studio 3 Antiques & Florists",
    "wof:placetype":"venue"
},
  "geometry": {"coordinates":[-90.065855,29.955091],"type":"Point"}
}