{
  "type": "Feature",
  "properties": {
    "iso:country":"US",
    "sg:address":"1160 Ted's Ln",
    "sg:city":"Port Allen",
    "sg:classifiers":[
        {
            "category":"Professional",
            "type":"Services"
        }
    ],
    "sg:phone":"+1 225 343 2559",
    "sg:postcode":"70767",
    "sg:province":"LA",
    "wof:name":"Yaw Brothers Enterprises Inc",
    "wof:placetype":"venue"
},
  "geometry": {"coordinates":[-91.253612,30.483772],"type":"Point"}
}