{
  "type": "Feature",
  "properties": {
    "iso:country":"US",
    "sg:address":"260 Grider Rd",
    "sg:city":"Minden",
    "sg:classifiers":[
        {
            "category":"Personal",
            "subcategory":"Beauty Salon",
            "type":"Services"
        }
    ],
    "sg:phone":"+1 318 382 1688",
    "sg:postcode":"71055",
    "sg:province":"LA",
    "wof:name":"Polly's Beauty Shop",
    "wof:placetype":"venue"
},
  "geometry": {"coordinates":[-93.209703,32.661791],"type":"Point"}
}