{
  "type": "Feature",
  "properties": {
    "addr:full":"1387 Garland Gin Rd Downsville LA 71234",
    "addr:housenumber":"1387",
    "addr:postcode":"71234",
    "addr:street":"Garland Gin Rd",
    "iso:country":"US",
    "sg:address":"1387 Garland Gin Rd",
    "sg:city":"Downsville",
    "sg:classifiers":[
        {
            "category":"Manufacturing",
            "subcategory":"Signs",
            "type":"Manufacturing & Wholesale Goods"
        }
    ],
    "sg:phone":"+1 318 644 5890",
    "sg:postcode":"71234",
    "sg:province":"LA",
    "wof:name":"A-1 Sign Svc",
    "wof:placetype":"venue"
},
  "geometry": {"coordinates":[-92.32766599999999,32.583057],"type":"Point"}
}