{
  "type": "Feature",
  "properties": {
    "iso:country":"US",
    "sg:address":"3053 Hwy 1192",
    "sg:city":"Marksville",
    "sg:classifiers":[
        {
            "category":"Utilities",
            "subcategory":"Water",
            "type":"Services"
        }
    ],
    "sg:phone":"+1 318 253 8670",
    "sg:postcode":"71351",
    "sg:province":"LA",
    "sg:tags":[
        "company",
        "sewage"
    ],
    "wof:name":"Brouilette Water Systems",
    "wof:placetype":"venue"
},
  "geometry": {"coordinates":[-92.068995,31.182645],"type":"Point"}
}