{
  "type": "Feature",
  "properties": {
    "addr:full":"200 Huey P Long Ave Gretna LA 70053",
    "addr:housenumber":"200;p",
    "addr:postcode":"70053",
    "addr:street":"Huey;Long Ave",
    "iso:country":"US",
    "sg:address":"200 Huey P Long Ave",
    "sg:city":"Gretna",
    "sg:classifiers":[
        {
            "category":"Government",
            "subcategory":"Office",
            "type":"Public Place"
        }
    ],
    "sg:phone":"+1 504 364 3481",
    "sg:postcode":"70053",
    "sg:province":"LA",
    "wof:name":"Jefferson Parish Home Incarcer",
    "wof:placetype":"venue"
},
  "geometry": {"coordinates":[-90.065383,29.916307],"type":"Point"}
}