{
  "type": "Feature",
  "properties": {
    "iso:country":"US",
    "sg:address":"319 Crail St",
    "sg:city":"Jennings",
    "sg:classifiers":[
        {
            "category":"Education",
            "subcategory":"Special Training",
            "type":"Public Place"
        }
    ],
    "sg:phone":"+1 337 824 0948",
    "sg:postcode":"70546",
    "sg:province":"LA",
    "wof:name":"Ruths",
    "wof:placetype":"venue"
},
  "geometry": {"coordinates":[-92.642039,30.226186],"type":"Point"}
}