{
  "type": "Feature",
  "properties": {
    "iso:country":"US",
    "sg:address":"4031 Division St",
    "sg:city":"Metairie",
    "sg:classifiers":[
        {
            "category":"Professional",
            "type":"Services"
        }
    ],
    "sg:phone":"+1 504 883 5763",
    "sg:postcode":"70002",
    "sg:province":"LA",
    "wof:name":"All Things Beautiful",
    "wof:placetype":"venue"
},
  "geometry": {"coordinates":[-90.164529,30.010287],"type":"Point"}
}