{
  "type": "Feature",
  "properties": {
    "iso:country":"US",
    "sg:address":"201 Bayou Rd",
    "sg:city":"Saint Bernard",
    "sg:classifiers":[
        {
            "category":"Food & Beverages",
            "subcategory":"Groceries & Convenience Stores",
            "type":"Retail Goods"
        }
    ],
    "sg:phone":"+1 504 682 0264",
    "sg:postcode":"70085",
    "sg:province":"LA",
    "wof:name":"King Bird Food Store",
    "wof:placetype":"venue"
},
  "geometry": {"coordinates":[-89.886597,29.868099],"type":"Point"}
}