{
  "type": "Feature",
  "properties": {
    "iso:country":"US",
    "sg:address":"125 Ridgeview Dr Ofc",
    "sg:city":"Broussard",
    "sg:classifiers":[
        {
            "category":"Real Estate",
            "subcategory":"Real Estate Operator",
            "type":"Services"
        }
    ],
    "sg:phone":"+1 337 837 9356",
    "sg:postcode":"70518",
    "sg:province":"LA",
    "sg:tags":[
        "apartment"
    ],
    "wof:name":"Ridgeview Apartments",
    "wof:placetype":"venue"
},
  "geometry": {"coordinates":[-91.947403,30.133101],"type":"Point"}
}