{
  "type": "Feature",
  "properties": {
    "iso:country":"US",
    "sg:address":"2621 Calhoun St",
    "sg:city":"New Orleans",
    "sg:classifiers":[
        {
            "category":"Restaurant",
            "type":"Food & Drink"
        }
    ],
    "sg:phone":"+1 504 524 7992",
    "sg:postcode":"70118",
    "sg:province":"LA",
    "sg:tags":[
        "eating"
    ],
    "wof:name":"Ice Breakers Inc",
    "wof:placetype":"venue"
},
  "geometry": {"coordinates":[-90.11575499999999,29.942356],"type":"Point"}
}