{
  "type": "Feature",
  "properties": {
    "iso:country":"US",
    "sg:address":"2601 Petroleum Dr",
    "sg:city":"Houma",
    "sg:classifiers":[
        {
            "category":"Freight",
            "type":"Transportation"
        }
    ],
    "sg:phone":"+1 985 879 1244",
    "sg:postcode":"70363",
    "sg:province":"LA",
    "sg:tags":[
        "field",
        "oil",
        "hauling"
    ],
    "sg:website":"www.dyntrans.com",
    "wof:name":"Dynasty Transportation",
    "wof:placetype":"venue"
},
  "geometry": {"coordinates":[-90.68117599999999,29.574014],"type":"Point"}
}