{
  "type": "Feature",
  "properties": {
    "addr:full":"38 English Turn Dr New Orleans LA 70131",
    "addr:housenumber":"38",
    "addr:postcode":"70131",
    "addr:street":"English Turn Dr",
    "iso:country":"US",
    "sg:address":"38 English Turn Dr",
    "sg:city":"New Orleans",
    "sg:classifiers":[
        {
            "category":"Health Services",
            "subcategory":"Dentist",
            "type":"Services"
        }
    ],
    "sg:phone":"+1 504 393 7414",
    "sg:postcode":"70131",
    "sg:province":"LA",
    "wof:name":"Hogue Charles B Dr Dntst",
    "wof:placetype":"venue"
},
  "geometry": {"coordinates":[-89.952797,29.9097],"type":"Point"}
}