{
  "type": "Feature",
  "properties": {
    "iso:country":"US",
    "sg:address":"1015 Brashear Ave",
    "sg:city":"Morgan City",
    "sg:classifiers":[
        {
            "category":"Banks & Credit Unions",
            "subcategory":"Bank",
            "type":"Services"
        }
    ],
    "sg:phone":"+1 985 385 6500",
    "sg:postcode":"70380",
    "sg:province":"LA",
    "wof:name":"Mid South Bank",
    "wof:placetype":"venue"
},
  "geometry": {"coordinates":[-91.201072,29.702174],"type":"Point"}
}