{
  "type": "Feature",
  "properties": {
    "iso:country":"US",
    "sg:address":"1415 Metairie Rd",
    "sg:city":"Metairie",
    "sg:classifiers":[
        {
            "category":"Banks & Credit Unions",
            "subcategory":"Bank",
            "type":"Services"
        }
    ],
    "sg:phone":"+1 504 552 2550",
    "sg:postcode":"70005",
    "sg:province":"LA",
    "wof:name":"Bank One",
    "wof:placetype":"venue"
},
  "geometry": {"coordinates":[-90.138679,29.987593],"type":"Point"}
}