{
  "type": "Feature",
  "properties": {
    "addr:full":"1033 Audubon St New Orleans LA 70118",
    "addr:housenumber":"1033",
    "addr:postcode":"70118",
    "addr:street":"Audubon St",
    "iso:country":"US",
    "sg:address":"1033 Audubon St",
    "sg:city":"New Orleans",
    "sg:classifiers":[
        {
            "category":"Organizations",
            "subcategory":"Community Association",
            "type":"Services"
        }
    ],
    "sg:phone":"+1 504 866 7523",
    "sg:postcode":"70118",
    "sg:province":"LA",
    "sg:tags":[
        "sorority",
        "fraternity"
    ],
    "wof:name":"Kappa Kappa Gamma Sorority",
    "wof:placetype":"venue"
},
  "geometry": {"coordinates":[-90.12267900000001,29.940857],"type":"Point"}
}