{
  "type": "Feature",
  "properties": {
    "iso:country":"US",
    "sg:address":"4423 Pine Park Dr",
    "sg:city":"Baton Rouge",
    "sg:classifiers":[
        {
            "category":"Health Services",
            "subcategory":"Doctor",
            "type":"Services"
        }
    ],
    "sg:phone":"+1 225 924 4488",
    "sg:postcode":"70809",
    "sg:province":"LA",
    "sg:tags":[
        "physician",
        "surgeon"
    ],
    "wof:name":"Malton J Bullock Jr MD",
    "wof:placetype":"venue"
},
  "geometry": {"coordinates":[-91.086369,30.405602],"type":"Point"}
}