{
  "type": "Feature",
  "properties": {
    "iso:country":"US",
    "sg:address":"2880 N Westport Dr",
    "sg:city":"Port Allen",
    "sg:classifiers":[
        {
            "category":"Travel",
            "subcategory":"Hotels & Motels",
            "type":"Entertainment"
        }
    ],
    "sg:phone":"+1 225 343 4300",
    "sg:postcode":"70767",
    "sg:province":"LA",
    "wof:name":"Comfort Suites",
    "wof:placetype":"venue"
},
  "geometry": {"coordinates":[-91.24289899999999,30.448407],"type":"Point"}
}