{
  "type": "Feature",
  "properties": {
    "addr:full":"1503 Gause Blvd Slidell LA 70458",
    "addr:housenumber":"1503",
    "addr:postcode":"70458",
    "addr:street":"Gause Blvd",
    "iso:country":"US",
    "sg:address":"1503 Gause Blvd",
    "sg:city":"Slidell",
    "sg:classifiers":[
        {
            "category":"Professional",
            "subcategory":"Management & Consulting",
            "type":"Services"
        }
    ],
    "sg:phone":"+1 985 646 1700",
    "sg:postcode":"70458",
    "sg:province":"LA",
    "sg:tags":[
        "selling",
        "establishment",
        "direct"
    ],
    "wof:name":"People's Lifestyle Inc",
    "wof:placetype":"venue"
},
  "geometry": {"coordinates":[-89.757465,30.28464],"type":"Point"}
}