{
  "type": "Feature",
  "properties": {
    "iso:country":"US",
    "sg:address":"209 Choctaw Dr",
    "sg:city":"Houma",
    "sg:classifiers":[
        {
            "category":"Professional",
            "subcategory":"Detective & Security Services",
            "type":"Services"
        }
    ],
    "sg:phone":"+1 985 868 1414",
    "sg:postcode":"70360",
    "sg:province":"LA",
    "sg:tags":[
        "fingerprinting"
    ],
    "wof:name":"I D Plus-Identification System",
    "wof:placetype":"venue"
},
  "geometry": {"coordinates":[-90.729304,29.57772],"type":"Point"}
}