{
  "type": "Feature",
  "properties": {
    "iso:country":"US",
    "sg:address":"20148 Adolphus Rd",
    "sg:city":"Covington",
    "sg:classifiers":[
        {
            "category":"Building & Trades",
            "subcategory":"Construction",
            "type":"Services"
        }
    ],
    "sg:phone":"+1 985 892 7513",
    "sg:postcode":"70435",
    "sg:province":"LA",
    "sg:tags":[
        "builder",
        "patio",
        "deck"
    ],
    "wof:name":"Mc Lains Deck & Patio",
    "wof:placetype":"venue"
},
  "geometry": {"coordinates":[-90.07168900000001,30.618743],"type":"Point"}
}