{
  "type": "Feature",
  "properties": {
    "addr:full":"147 N Lacarpe Cir Houma LA 70360",
    "addr:housenumber":"147",
    "addr:postcode":"70360",
    "addr:street":"N Lacarpe Cir",
    "iso:country":"US",
    "sg:address":"147 N Lacarpe Cir",
    "sg:city":"Houma",
    "sg:classifiers":[
        {
            "category":"Building & Trades",
            "subcategory":"Construction",
            "type":"Services"
        }
    ],
    "sg:phone":"+1 985 876 3032",
    "sg:postcode":"70360",
    "sg:province":"LA",
    "sg:tags":[
        "contractor"
    ],
    "wof:name":"V J Caro Dump Truck & Equip",
    "wof:placetype":"venue"
},
  "geometry": {"coordinates":[-90.750927,29.596256],"type":"Point"}
}