{
  "type": "Feature",
  "properties": {
    "addr:full":"2029 S Philippe Ave Gonzales LA 70737",
    "addr:housenumber":"2029",
    "addr:postcode":"70737",
    "addr:street":"S Philippe Ave",
    "iso:country":"US",
    "sg:address":"2029 S Philippe Ave",
    "sg:city":"Gonzales",
    "sg:classifiers":[
        {
            "category":"Manufacturing",
            "subcategory":"Tools & Machinery",
            "type":"Manufacturing & Wholesale Goods"
        }
    ],
    "sg:phone":"+1 225 647 5551",
    "sg:postcode":"70737",
    "sg:province":"LA",
    "sg:tags":[
        "filter"
    ],
    "wof:name":"Eggelhof Inc",
    "wof:placetype":"venue"
},
  "geometry": {"coordinates":[-90.92957,30.216909],"type":"Point"}
}