{
  "type": "Feature",
  "properties": {
    "addr:full":"112 N Adams Ave Rayne LA 70578",
    "addr:housenumber":"112",
    "addr:postcode":"70578",
    "addr:street":"N Adams Ave",
    "iso:country":"US",
    "sg:address":"112 N Adams Ave",
    "sg:city":"Rayne",
    "sg:classifiers":[
        {
            "category":"Retail",
            "subcategory":"Laundry & Dry Cleaning",
            "type":"Services"
        }
    ],
    "sg:phone":"+1 337 334 9371",
    "sg:postcode":"70578",
    "sg:province":"LA",
    "sg:tags":[
        "cleaners"
    ],
    "wof:name":"J & J Sunshine Cleaners",
    "wof:placetype":"venue"
},
  "geometry": {"coordinates":[-92.26873999999999,30.236744],"type":"Point"}
}