{
  "type": "Feature",
  "properties": {
    "iso:country":"US",
    "sg:address":"1940 Airline Dr",
    "sg:city":"Bossier City",
    "sg:classifiers":[
        {
            "category":"Autos & Motor Vehicles",
            "subcategory":"Automobile Sales",
            "type":"Retail Goods"
        }
    ],
    "sg:phone":"+1 318 747 9725",
    "sg:postcode":"71112",
    "sg:province":"LA",
    "sg:tags":[
        "car",
        "dealer"
    ],
    "sg:website":"www.redriverchevy.com",
    "wof:name":"Used Cars On Airline",
    "wof:placetype":"venue"
},
  "geometry": {"coordinates":[-93.697846,32.523685],"type":"Point"}
}