{
  "type": "Feature",
  "properties": {
    "addr:full":"2821 Kingman St Metairie LA 70006",
    "addr:housenumber":"2821",
    "addr:postcode":"70006",
    "addr:street":"Kingman St",
    "iso:country":"US",
    "sg:address":"2821 Kingman St",
    "sg:city":"Metairie",
    "sg:classifiers":[
        {
            "category":"Insurance",
            "subcategory":"Insurance Agent",
            "type":"Services"
        }
    ],
    "sg:phone":"+1 504 779 1675",
    "sg:postcode":"70006",
    "sg:province":"LA",
    "wof:name":"State Farm Insurance",
    "wof:placetype":"venue"
},
  "geometry": {"coordinates":[-90.179548,29.999281],"type":"Point"}
}