{
  "type": "Feature",
  "properties": {
    "iso:country":"US",
    "sg:address":"14311 Sweetbay Rd",
    "sg:city":"Abbeville",
    "sg:classifiers":[
        {
            "category":"Farming",
            "subcategory":"Farm",
            "type":"Manufacturing & Wholesale Goods"
        }
    ],
    "sg:phone":"+1 337 898 0066",
    "sg:postcode":"70510",
    "sg:province":"LA",
    "sg:tags":[
        "crop",
        "general"
    ],
    "wof:name":"Kenneth J Dehart",
    "wof:placetype":"venue"
},
  "geometry": {"coordinates":[-92.191058,29.930391],"type":"Point"}
}