{
  "type": "Feature",
  "properties": {
    "addr:full":"1015 Hashim Dr Opelousas LA 70570",
    "addr:housenumber":"1015",
    "addr:postcode":"70570",
    "addr:street":"Hashim Dr",
    "iso:country":"US",
    "sg:address":"1015 Hashim Dr",
    "sg:city":"Opelousas",
    "sg:classifiers":[
        {
            "category":"Real Estate",
            "subcategory":"Real Estate Services",
            "type":"Services"
        }
    ],
    "sg:phone":"+1 337 948 9763",
    "sg:postcode":"70570",
    "sg:province":"LA",
    "sg:tags":[
        "abstract",
        "title"
    ],
    "wof:name":"Dorio Abstracting Inc",
    "wof:placetype":"venue"
},
  "geometry": {"coordinates":[-92.076376,30.509077],"type":"Point"}
}