{
  "type": "Feature",
  "properties": {
    "addr:full":"3510 Ryan St Lake Charles LA 70605",
    "addr:housenumber":"3510",
    "addr:postcode":"70605",
    "addr:street":"Ryan St",
    "iso:country":"US",
    "sg:address":"3510 Ryan St",
    "sg:city":"Lake Charles",
    "sg:classifiers":[
        {
            "category":"Shopping",
            "subcategory":"Clothing, Apparel, & Fashions",
            "type":"Retail Goods"
        }
    ],
    "sg:phone":"+1 337 562 9990",
    "sg:postcode":"70605",
    "sg:province":"LA",
    "sg:tags":[
        "uniform"
    ],
    "wof:name":"Uniformly Fit",
    "wof:placetype":"venue"
},
  "geometry": {"coordinates":[-93.218693,30.193284],"type":"Point"}
}