{
  "type": "Feature",
  "properties": {
    "iso:country":"US",
    "sg:address":"528 Robertson St",
    "sg:city":"New Iberia",
    "sg:classifiers":[
        {
            "category":"Personal",
            "subcategory":"Beauty Salon",
            "type":"Services"
        }
    ],
    "sg:phone":"+1 337 367 2564",
    "sg:postcode":"70560",
    "sg:province":"LA",
    "sg:tags":[
        "barber"
    ],
    "wof:name":"Bill's Hair Fashions",
    "wof:placetype":"venue"
},
  "geometry": {"coordinates":[-91.827904,30.007401],"type":"Point"}
}