{
  "type": "Feature",
  "properties": {
    "addr:full":"102 E Church St Church Point LA 70525",
    "addr:housenumber":"102",
    "addr:postcode":"70525",
    "addr:street":"E Church St",
    "iso:country":"US",
    "sg:address":"102 E Church St",
    "sg:city":"Church Point",
    "sg:classifiers":[
        {
            "category":"Government",
            "subcategory":"Office",
            "type":"Public Place"
        }
    ],
    "sg:phone":"+1 337 684 5543",
    "sg:postcode":"70525",
    "sg:province":"LA",
    "sg:tags":[
        "village"
    ],
    "wof:name":"Sewer Plant",
    "wof:placetype":"venue"
},
  "geometry": {"coordinates":[-92.21479600000001,30.407092],"type":"Point"}
}