{
  "type": "Feature",
  "properties": {
    "addr:full":"300 Williams Lake Rd Pineville LA 71360",
    "addr:housenumber":"300",
    "addr:postcode":"71360",
    "addr:street":"Williams Lake Rd",
    "iso:country":"US",
    "sg:address":"300 Williams Lake Rd",
    "sg:city":"Pineville",
    "sg:classifiers":[
        {
            "category":"Manufacturing",
            "subcategory":"Paper Products",
            "type":"Manufacturing & Wholesale Goods"
        }
    ],
    "sg:phone":"+1 318 441 4100",
    "sg:postcode":"71360",
    "sg:province":"LA",
    "wof:name":"International Paper Co",
    "wof:placetype":"venue"
},
  "geometry": {"coordinates":[-92.347983,31.296193],"type":"Point"}
}