{
  "type": "Feature",
  "properties": {
    "addr:full":"620 E Madison Ave Bastrop LA 71220",
    "addr:housenumber":"620",
    "addr:postcode":"71220",
    "addr:street":"E Madison Ave",
    "iso:country":"US",
    "sg:address":"620 E Madison Ave",
    "sg:city":"Bastrop",
    "sg:classifiers":[
        {
            "category":"Organizations",
            "subcategory":"Religious Organization",
            "type":"Services"
        }
    ],
    "sg:phone":"+1 318 281 6885",
    "sg:postcode":"71220",
    "sg:province":"LA",
    "sg:tags":[
        "church"
    ],
    "sg:website":"www.firstbaptistbastrop.org",
    "wof:name":"First Baptist Church",
    "wof:placetype":"venue"
},
  "geometry": {"coordinates":[-91.905867,32.77871],"type":"Point"}
}