{
  "type": "Feature",
  "properties": {
    "iso:country":"US",
    "sg:address":"1760 Swan Lake Rd",
    "sg:city":"Bossier City",
    "sg:classifiers":[
        {
            "category":"Home & Garden",
            "subcategory":"Household Appliances",
            "type":"Retail Goods"
        }
    ],
    "sg:phone":"+1 318 746 3332",
    "sg:postcode":"71111",
    "sg:province":"LA",
    "wof:name":"Barrett Appliance & Home Prod",
    "wof:placetype":"venue"
},
  "geometry": {"coordinates":[-93.67595300000001,32.552168],"type":"Point"}
}