{
  "type": "Feature",
  "properties": {
    "iso:country":"US",
    "sg:address":"410 Fincher Rd",
    "sg:city":"Minden",
    "sg:classifiers":[
        {
            "category":"Organizations",
            "subcategory":"Religious Organization",
            "type":"Services"
        }
    ],
    "sg:phone":"+1 318 377 5364",
    "sg:postcode":"71055",
    "sg:province":"LA",
    "sg:tags":[
        "church"
    ],
    "wof:name":"St Paul Catholic Church",
    "wof:placetype":"venue"
},
  "geometry": {"coordinates":[-93.26871300000001,32.61913],"type":"Point"}
}