{
  "type": "Feature",
  "properties": {
    "addr:full":"64207 Hwy 41 Pearl River LA 70452",
    "addr:housenumber":"64207",
    "addr:postcode":"70452",
    "addr:street":"Hwy 41",
    "iso:country":"US",
    "sg:address":"64207 Hwy 41",
    "sg:city":"Pearl River",
    "sg:classifiers":[
        {
            "category":"Food & Beverages",
            "subcategory":"Meat & Fish",
            "type":"Retail Goods"
        }
    ],
    "sg:phone":"+1 985 863 0906",
    "sg:postcode":"70452",
    "sg:province":"LA",
    "sg:tags":[
        "seafood"
    ],
    "wof:name":"Bayou Boys Seafood & Produce",
    "wof:placetype":"venue"
},
  "geometry": {"coordinates":[-89.754696,30.36311],"type":"Point"}
}