{
  "type": "Feature",
  "properties": {
    "iso:country":"US",
    "sg:address":"206 S Chestnut St",
    "sg:city":"Tallulah",
    "sg:classifiers":[
        {
            "category":"Cinema",
            "subcategory":"Movie Rental",
            "type":"Entertainment"
        }
    ],
    "sg:phone":"+1 318 574 1016",
    "sg:postcode":"71282",
    "sg:province":"LA",
    "sg:tags":[
        "leasing",
        "video",
        "disc",
        "tape"
    ],
    "wof:name":"Movie Gallery",
    "wof:placetype":"venue"
},
  "geometry": {"coordinates":[-91.188704,32.407187],"type":"Point"}
}