{
  "type": "Feature",
  "properties": {
    "addr:full":"1101 Huey P Long Ave Gretna LA 70053",
    "addr:housenumber":"1101;p",
    "addr:postcode":"70053",
    "addr:street":"Huey;Long Ave",
    "iso:country":"US",
    "sg:address":"1101 Huey P Long Ave",
    "sg:city":"Gretna",
    "sg:classifiers":[
        {
            "category":"Professional",
            "subcategory":"Business Services",
            "type":"Services"
        }
    ],
    "sg:phone":"+1 504 365 0846",
    "sg:postcode":"70053",
    "sg:province":"LA",
    "sg:tags":[
        "convention",
        "meeting",
        "facility"
    ],
    "wof:name":"Coastal International Inc",
    "wof:placetype":"venue"
},
  "geometry": {"coordinates":[-90.05961499999999,29.9095],"type":"Point"}
}