{
  "type": "Feature",
  "properties": {
    "addr:full":"1136 Homer Rd Minden LA 71055",
    "addr:housenumber":"1136",
    "addr:postcode":"71055",
    "addr:street":"Homer Rd",
    "iso:country":"US",
    "sg:address":"1136 Homer Rd",
    "sg:city":"Minden",
    "sg:classifiers":[
        {
            "category":"Personal",
            "subcategory":"Beauty Salon",
            "type":"Services"
        }
    ],
    "sg:phone":"+1 318 377 5999",
    "sg:postcode":"71055",
    "sg:province":"LA",
    "sg:tags":[
        "manicuring"
    ],
    "wof:name":"Natural Nails",
    "wof:placetype":"venue"
},
  "geometry": {"coordinates":[-93.25347600000001,32.624541],"type":"Point"}
}