{
  "type": "Feature",
  "properties": {
    "addr:full":"2400 Danbury Dr New Orleans LA 70131",
    "addr:housenumber":"2400",
    "addr:postcode":"70131",
    "addr:street":"Danbury Dr",
    "iso:country":"US",
    "sg:address":"2400 Danbury Dr",
    "sg:city":"New Orleans",
    "sg:classifiers":[
        {
            "category":"Mining & Drilling",
            "type":"Manufacturing & Wholesale Goods"
        }
    ],
    "sg:phone":"+1 504 394 9595",
    "sg:postcode":"70131",
    "sg:province":"LA",
    "sg:tags":[
        "field",
        "oil"
    ],
    "wof:name":"Pinnacle Energy Solutions",
    "wof:placetype":"venue"
},
  "geometry": {"coordinates":[-89.99838099999999,29.927283],"type":"Point"}
}