{
  "type": "Feature",
  "properties": {
    "addr:full":"15833 Antietam Ave Baton Rouge LA 70817",
    "addr:housenumber":"15833",
    "addr:postcode":"70817",
    "addr:street":"Antietam Ave",
    "iso:country":"US",
    "sg:address":"15833 Antietam Ave",
    "sg:city":"Baton Rouge",
    "sg:classifiers":[
        {
            "category":"Building & Trades",
            "subcategory":"Construction",
            "type":"Services"
        }
    ],
    "sg:phone":"+1 225 753 3028",
    "sg:postcode":"70817",
    "sg:province":"LA",
    "sg:tags":[
        "siding",
        "contractor"
    ],
    "wof:name":"Todor Development Corp",
    "wof:placetype":"venue"
},
  "geometry": {"coordinates":[-91.010589,30.397215],"type":"Point"}
}