{
  "type": "Feature",
  "properties": {
    "iso:country":"US",
    "sg:address":"371 Powell Rd",
    "sg:city":"Otis",
    "sg:classifiers":[
        {
            "category":"Building & Trades",
            "subcategory":"Construction",
            "type":"Services"
        }
    ],
    "sg:phone":"+1 318 793 5259",
    "sg:postcode":"71466",
    "sg:province":"LA",
    "sg:tags":[
        "siding",
        "contractor"
    ],
    "wof:name":"Exteriors Inc",
    "wof:placetype":"venue"
},
  "geometry": {"coordinates":[-92.750973,31.210145],"type":"Point"}
}