{
  "type": "Feature",
  "properties": {
    "iso:country":"US",
    "sg:address":"215 Macarthur Dr",
    "sg:city":"Alexandria",
    "sg:classifiers":[
        {
            "category":"Autos & Motor Vehicles",
            "subcategory":"Auto Supplies",
            "type":"Retail Goods"
        }
    ],
    "sg:phone":"+1 318 445 9881",
    "sg:postcode":"71303",
    "sg:province":"LA",
    "sg:tags":[
        "automobile",
        "parts"
    ],
    "sg:website":"www.autozone.com",
    "wof:name":"Autozone",
    "wof:placetype":"venue"
},
  "geometry": {"coordinates":[-92.478995,31.29769],"type":"Point"}
}