{
  "type": "Feature",
  "properties": {
    "iso:country":"US",
    "sg:address":"909 N Gladys St",
    "sg:city":"Leesville",
    "sg:classifiers":[
        {
            "category":"Organizations",
            "subcategory":"Religious Organization",
            "type":"Services"
        }
    ],
    "sg:phone":"+1 337 239 2374",
    "sg:postcode":"71446",
    "sg:province":"LA",
    "wof:name":"Greater Bethel AME Church",
    "wof:placetype":"venue"
},
  "geometry": {"coordinates":[-93.27059800000001,31.151171],"type":"Point"}
}