{
  "type": "Feature",
  "properties": {
    "iso:country":"US",
    "sg:address":"105 W Louisiana Ave",
    "sg:city":"Vivian",
    "sg:classifiers":[
        {
            "category":"Food & Beverages",
            "subcategory":"Candy",
            "type":"Retail Goods"
        }
    ],
    "sg:phone":"+1 318 375 2238",
    "sg:postcode":"71082",
    "sg:province":"TX",
    "sg:tags":[
        "confectionery"
    ],
    "wof:name":"Candy Lane",
    "wof:placetype":"venue"
},
  "geometry": {"coordinates":[-93.987674,32.872833],"type":"Point"}
}