{
  "type": "Feature",
  "properties": {
    "addr:full":"2222 Simon Bolivar Ave New Orleans LA 70113",
    "addr:housenumber":"2222",
    "addr:postcode":"70113",
    "addr:street":"Simon Bolivar Ave",
    "iso:country":"US",
    "sg:address":"2222 Simon Bolivar Ave",
    "sg:city":"New Orleans",
    "sg:classifiers":[
        {
            "category":"Social Services",
            "type":"Services"
        }
    ],
    "sg:phone":"+1 504 569 4690",
    "sg:postcode":"70113",
    "sg:province":"LA",
    "sg:tags":[
        "professional",
        "counselor"
    ],
    "wof:name":"Healthy Beginnings",
    "wof:placetype":"venue"
},
  "geometry": {"coordinates":[-90.08481500000001,29.939014],"type":"Point"}
}