{
  "type": "Feature",
  "properties": {
    "addr:full":"9740 Florida Blvd Baton Rouge LA 70815",
    "addr:housenumber":"9740",
    "addr:postcode":"70815",
    "addr:street":"Florida Blvd",
    "iso:country":"US",
    "sg:address":"9740 Florida Blvd",
    "sg:city":"Baton Rouge",
    "sg:classifiers":[
        {
            "category":"Banks & Credit Unions",
            "subcategory":"Bank",
            "type":"Services"
        }
    ],
    "sg:phone":"+1 225 925 1510",
    "sg:postcode":"70815",
    "sg:province":"LA",
    "sg:tags":[
        "cashing",
        "check"
    ],
    "wof:name":"Advance America",
    "wof:placetype":"venue"
},
  "geometry": {"coordinates":[-91.080252,30.455325],"type":"Point"}
}