{
  "type": "Feature",
  "properties": {
    "addr:full":"5267 Plank Rd Baton Rouge LA 70805",
    "addr:housenumber":"5267",
    "addr:postcode":"70805",
    "addr:street":"Plank Rd",
    "iso:country":"US",
    "sg:address":"5267 Plank Rd",
    "sg:city":"Baton Rouge",
    "sg:classifiers":[
        {
            "category":"Banks & Credit Unions",
            "subcategory":"Financial Services",
            "type":"Services"
        }
    ],
    "sg:phone":"+1 225 355 2127",
    "sg:postcode":"70805",
    "sg:province":"LA",
    "sg:tags":[
        "company",
        "investment"
    ],
    "wof:name":"Pizzolato Investments",
    "wof:placetype":"venue"
},
  "geometry": {"coordinates":[-91.153856,30.497597],"type":"Point"}
}