{
  "type": "Feature",
  "properties": {
    "addr:full":"2185 N Lexington Ave Gretna LA 70056",
    "addr:housenumber":"2185",
    "addr:postcode":"70056",
    "addr:street":"N Lexington Ave",
    "iso:country":"US",
    "sg:address":"2185 N Lexington Ave",
    "sg:city":"Gretna",
    "sg:classifiers":[
        {
            "category":"Professional",
            "subcategory":"Engineering",
            "type":"Services"
        }
    ],
    "sg:phone":"+1 504 392 9432",
    "sg:postcode":"70056",
    "sg:province":"LA",
    "wof:name":"V E S Inc",
    "wof:placetype":"venue"
},
  "geometry": {"coordinates":[-90.024823,29.894615],"type":"Point"}
}