{
  "type": "Feature",
  "properties": {
    "addr:full":"13495 Vera McGowan Walker LA 70785",
    "addr:housenumber":"13495",
    "addr:postcode":"70785",
    "addr:street":"Vera Mcgowan",
    "iso:country":"US",
    "sg:address":"13495 Vera McGowan",
    "sg:city":"Walker",
    "sg:classifiers":[
        {
            "category":"Personal",
            "subcategory":"Beauty Salon",
            "type":"Services"
        }
    ],
    "sg:phone":"+1 225 665 0067",
    "sg:postcode":"70785",
    "sg:province":"LA",
    "wof:name":"Zaxx Cuts & Styles",
    "wof:placetype":"venue"
},
  "geometry": {"coordinates":[-90.86309199999999,30.473926],"type":"Point"}
}