{
  "type": "Feature",
  "properties": {
    "iso:country":"US",
    "sg:address":"291 A J Estay Rd",
    "sg:city":"Golden Meadow",
    "sg:classifiers":[
        {
            "category":"Mining & Drilling",
            "type":"Manufacturing & Wholesale Goods"
        }
    ],
    "sg:phone":"+1 985 396 2377",
    "sg:postcode":"70357",
    "sg:province":"LA",
    "sg:tags":[
        "field",
        "oil"
    ],
    "sg:website":"www.bakerhughes.com",
    "wof:name":"Baker Hughes Inteq",
    "wof:placetype":"venue"
},
  "geometry": {"coordinates":[-90.19902399999999,29.115916],"type":"Point"}
}