{
  "type": "Feature",
  "properties": {
    "addr:full":"1105 Van Ave Bastrop LA 71220",
    "addr:housenumber":"1105",
    "addr:postcode":"71220",
    "addr:street":"Van Ave",
    "iso:country":"US",
    "sg:address":"1105 Van Ave",
    "sg:city":"Bastrop",
    "sg:classifiers":[
        {
            "category":"Organizations",
            "subcategory":"Religious Organization",
            "type":"Services"
        }
    ],
    "sg:phone":"+1 318 283 1514",
    "sg:postcode":"71220",
    "sg:province":"LA",
    "sg:tags":[
        "church"
    ],
    "wof:name":"New Lights Baptist Church",
    "wof:placetype":"venue"
},
  "geometry": {"coordinates":[-91.92658,32.784834],"type":"Point"}
}