{
  "type": "Feature",
  "properties": {
    "iso:country":"US",
    "sg:address":"9811 Elm Pl",
    "sg:city":"New Orleans",
    "sg:classifiers":[
        {
            "category":"Real Estate",
            "subcategory":"Real Estate Agent",
            "type":"Services"
        }
    ],
    "sg:phone":"+1 504 737 1471",
    "sg:postcode":"70123",
    "sg:province":"LA",
    "wof:name":"Bennett Real Estate",
    "wof:placetype":"venue"
},
  "geometry": {"coordinates":[-90.2149,29.965733],"type":"Point"}
}