{
  "type": "Feature",
  "properties": {
    "addr:full":"2469 Winnfield Hwy Jonesboro LA 71251",
    "addr:housenumber":"2469",
    "addr:postcode":"71251",
    "addr:street":"Winnfield Hwy",
    "iso:country":"US",
    "sg:address":"2469 Winnfield Hwy",
    "sg:city":"Jonesboro",
    "sg:classifiers":[
        {
            "category":"Organizations",
            "subcategory":"Religious Organization",
            "type":"Services"
        }
    ],
    "sg:phone":"+1 318 259 7144",
    "sg:postcode":"71251",
    "sg:province":"LA",
    "sg:tags":[
        "church"
    ],
    "wof:name":"Kingdom Hall-Jehovah's Witness",
    "wof:placetype":"venue"
},
  "geometry": {"coordinates":[-92.707767,32.20046],"type":"Point"}
}