{
  "type": "Feature",
  "properties": {
    "addr:full":"13710 W Ave A Cut Off LA 70345",
    "addr:housenumber":"13710",
    "addr:postcode":"70345",
    "addr:street":"W Ave A Cut Off",
    "iso:country":"US",
    "sg:address":"13710 W Ave A",
    "sg:city":"Cut Off",
    "sg:classifiers":[
        {
            "category":"Building & Trades",
            "subcategory":"Construction",
            "type":"Services"
        }
    ],
    "sg:phone":"+1 985 632 6445",
    "sg:postcode":"70345",
    "sg:province":"LA",
    "sg:tags":[
        "house"
    ],
    "wof:name":"Felarise Builders",
    "wof:placetype":"venue"
},
  "geometry": {"coordinates":[-90.30730699999999,29.453831],"type":"Point"}
}