{
  "type": "Feature",
  "properties": {
    "iso:country":"US",
    "sg:address":"3162 Pontchartrain Dr",
    "sg:city":"Slidell",
    "sg:classifiers":[
        {
            "category":"Food & Beverages",
            "subcategory":"Bakery",
            "type":"Retail Goods"
        }
    ],
    "sg:phone":"+1 985 643 3968",
    "sg:postcode":"70458",
    "sg:province":"LA",
    "sg:tags":[
        "doughnut"
    ],
    "wof:name":"Not Just Donuts",
    "wof:placetype":"venue"
},
  "geometry": {"coordinates":[-89.785369,30.26201],"type":"Point"}
}