{
  "type": "Feature",
  "properties": {
    "iso:country":"US",
    "sg:address":"9001 Cortana Pl",
    "sg:city":"Baton Rouge",
    "sg:classifiers":[
        {
            "category":"Professional",
            "subcategory":"Business Services",
            "type":"Services"
        }
    ],
    "sg:phone":"+1 225 927 6408",
    "sg:postcode":"70815",
    "sg:province":"LA",
    "sg:tags":[
        "notary"
    ],
    "sg:website":"www.applenotaries.com",
    "wof:name":"Apple Notaries Inc",
    "wof:placetype":"venue"
},
  "geometry": {"coordinates":[-91.08994300000001,30.45568],"type":"Point"}
}