{
  "type": "Feature",
  "properties": {
    "addr:full":"2400 Delachaise St New Orleans LA 70115",
    "addr:housenumber":"2400",
    "addr:postcode":"70115",
    "addr:street":"Delachaise St",
    "iso:country":"US",
    "sg:address":"2400 Delachaise St",
    "sg:city":"New Orleans",
    "sg:classifiers":[
        {
            "category":"Organizations",
            "subcategory":"Religious Organization",
            "type":"Services"
        }
    ],
    "sg:phone":"+1 504 891 5963",
    "sg:postcode":"70115",
    "sg:province":"LA",
    "sg:tags":[
        "church"
    ],
    "wof:name":"Ephesus Seventh Day Adventist",
    "wof:placetype":"venue"
},
  "geometry": {"coordinates":[-90.09651599999999,29.935979],"type":"Point"}
}