{
  "type": "Feature",
  "properties": {
    "iso:country":"US",
    "sg:address":"2007 Florida St",
    "sg:city":"Mandeville",
    "sg:classifiers":[
        {
            "category":"Personal",
            "subcategory":"Barber",
            "type":"Services"
        }
    ],
    "sg:phone":"+1 985 727 1230",
    "sg:postcode":"70448",
    "sg:province":"LA",
    "wof:name":"Olde Tyme Tonsorial Parlor",
    "wof:placetype":"venue"
},
  "geometry": {"coordinates":[-90.06197,30.363766],"type":"Point"}
}