{
  "type": "Feature",
  "properties": {
    "addr:full":"8330 Scenic Hwy Baton Rouge LA 70807",
    "addr:housenumber":"8330",
    "addr:postcode":"70807",
    "addr:street":"Scenic Hwy",
    "iso:country":"US",
    "sg:address":"8330 Scenic Hwy",
    "sg:city":"Baton Rouge",
    "sg:classifiers":[
        {
            "category":"Restaurant",
            "type":"Food & Drink"
        }
    ],
    "sg:phone":"+1 225 775 9696",
    "sg:postcode":"70807",
    "sg:province":"LA",
    "wof:name":"Panda House",
    "wof:placetype":"venue"
},
  "geometry": {"coordinates":[-91.180661,30.523174],"type":"Point"}
}