{
  "type": "Feature",
  "properties": {
    "iso:country":"US",
    "sg:address":"401 Whitney Ave",
    "sg:city":"Gretna",
    "sg:classifiers":[
        {
            "category":"Banks & Credit Unions",
            "subcategory":"Bank",
            "type":"Services"
        }
    ],
    "sg:phone":"+1 504 364 0786",
    "sg:postcode":"70056",
    "sg:province":"LA",
    "sg:tags":[
        "mortgage",
        "loan",
        "broker",
        "real estate"
    ],
    "sg:website":"www.sunmortgagefunding.com",
    "wof:name":"Sun Mortgage Funding",
    "wof:placetype":"venue"
},
  "geometry": {"coordinates":[-90.042297,29.919901],"type":"Point"}
}