{
  "type": "Feature",
  "properties": {
    "iso:country":"US",
    "sg:address":"1711 Nashville Ave",
    "sg:city":"Hammond",
    "sg:classifiers":[
        {
            "category":"Government",
            "subcategory":"Office",
            "type":"Public Place"
        }
    ],
    "sg:phone":"+1 985 543 4966",
    "sg:postcode":"70401",
    "sg:province":"LA",
    "sg:tags":[
        "state",
        "inspection"
    ],
    "sg:website":"www.laworks.net",
    "wof:name":"Labor Dept",
    "wof:placetype":"venue"
},
  "geometry": {"coordinates":[-90.480794,30.519099],"type":"Point"}
}