{
  "type": "Feature",
  "properties": {
    "iso:country":"US",
    "sg:address":"8009 Jefferson Hwy",
    "sg:city":"Baton Rouge",
    "sg:classifiers":[
        {
            "category":"Banks & Credit Unions",
            "subcategory":"Bank",
            "type":"Services"
        }
    ],
    "sg:phone":"+1 225 381 2049",
    "sg:postcode":"70809",
    "sg:province":"LA",
    "wof:name":"Hibernia National Bank",
    "wof:placetype":"venue"
},
  "geometry": {"coordinates":[-91.10436799999999,30.424343],"type":"Point"}
}