{
  "type": "Feature",
  "properties": {
    "iso:country":"US",
    "sg:address":"526 McCulla St",
    "sg:city":"Thibodaux",
    "sg:classifiers":[
        {
            "category":"Health Services",
            "subcategory":"Doctor",
            "type":"Services"
        }
    ],
    "sg:phone":"+1 985 448 3700",
    "sg:postcode":"70301",
    "sg:province":"LA",
    "sg:tags":[
        "physician",
        "surgeon"
    ],
    "wof:name":"Center For Pediatric & Adlscnt",
    "wof:placetype":"venue"
},
  "geometry": {"coordinates":[-90.815628,29.795],"type":"Point"}
}