{
  "type": "Feature",
  "properties": {
    "iso:country":"US",
    "sg:address":"22 Madera Ct",
    "sg:city":"Kenner",
    "sg:classifiers":[
        {
            "category":"Organizations",
            "subcategory":"Religious Organization",
            "type":"Services"
        }
    ],
    "sg:phone":"+1 504 443 3052",
    "sg:postcode":"70065",
    "sg:province":"LA",
    "wof:name":"St Matthews United Methodist",
    "wof:placetype":"venue"
},
  "geometry": {"coordinates":[-90.232078,30.029103],"type":"Point"}
}