{
  "type": "Feature",
  "properties": {
    "iso:country":"US",
    "sg:address":"2055 McCall St",
    "sg:city":"Bossier City",
    "sg:classifiers":[
        {
            "category":"Freight",
            "type":"Transportation"
        }
    ],
    "sg:phone":"+1 318 221 1610",
    "sg:postcode":"71111",
    "sg:province":"LA",
    "sg:tags":[
        "mover"
    ],
    "wof:name":"Chandler House Movers",
    "wof:placetype":"venue"
},
  "geometry": {"coordinates":[-93.723429,32.528884],"type":"Point"}
}