{
  "type": "Feature",
  "properties": {
    "addr:full":"533 Jefferson St Lafayette LA 70501",
    "addr:housenumber":"533",
    "addr:postcode":"70501",
    "addr:street":"Jefferson St",
    "iso:country":"US",
    "sg:address":"533 Jefferson St",
    "sg:city":"Lafayette",
    "sg:classifiers":[
        {
            "category":"Bars & Pubs",
            "type":"Food & Drink"
        }
    ],
    "sg:phone":"+1 337 264 8000",
    "sg:postcode":"70501",
    "sg:province":"LA",
    "sg:tags":[
        "club",
        "night"
    ],
    "sg:website":"www.julesdowntown.com",
    "wof:name":"Jules Downtown",
    "wof:placetype":"venue"
},
  "geometry": {"coordinates":[-92.018709,30.224651],"type":"Point"}
}