{
  "type": "Feature",
  "properties": {
    "iso:country":"US",
    "sg:address":"1414 Moss St",
    "sg:city":"Lafayette",
    "sg:classifiers":[
        {
            "category":"Food & Beverages",
            "subcategory":"Meat & Fish",
            "type":"Retail Goods"
        }
    ],
    "sg:phone":"+1 337 234 0300",
    "sg:postcode":"70501",
    "sg:province":"LA",
    "sg:tags":[
        "seafood",
        "market"
    ],
    "wof:name":"L A Seafood",
    "wof:placetype":"venue"
},
  "geometry": {"coordinates":[-92.006401,30.244499],"type":"Point"}
}