{
  "type": "Feature",
  "properties": {
    "iso:country":"US",
    "sg:address":"103 E Church St",
    "sg:city":"Delcambre",
    "sg:classifiers":[
        {
            "category":"Restaurant",
            "type":"Food & Drink"
        }
    ],
    "sg:phone":"+1 337 685 4891",
    "sg:postcode":"70528",
    "sg:province":"LA",
    "wof:name":"Lil Sandwiche Shoppe",
    "wof:placetype":"venue"
},
  "geometry": {"coordinates":[-91.98753600000001,29.949223],"type":"Point"}
}