{
  "type": "Feature",
  "properties": {
    "addr:full":"3742 Hollywood Ave Shreveport LA 71109",
    "addr:housenumber":"3742",
    "addr:postcode":"71109",
    "addr:street":"Hollywood Ave",
    "iso:country":"US",
    "sg:address":"3742 Hollywood Ave",
    "sg:city":"Shreveport",
    "sg:classifiers":[
        {
            "category":"Health Services",
            "subcategory":"Nursing And Care Facility",
            "type":"Services"
        }
    ],
    "sg:phone":"+1 318 636 6110",
    "sg:postcode":"71109",
    "sg:province":"LA",
    "sg:tags":[
        "hospice"
    ],
    "wof:name":"EPC Hospice Of Shreveport",
    "wof:placetype":"venue"
},
  "geometry": {"coordinates":[-93.799452,32.456597],"type":"Point"}
}