{
  "type": "Feature",
  "properties": {
    "iso:country":"US",
    "sg:address":"314 Brockton Dr",
    "sg:city":"Carencro",
    "sg:classifiers":[
        {
            "category":"Personal",
            "subcategory":"Beauty Salon",
            "type":"Services"
        }
    ],
    "sg:phone":"+1 337 896 7053",
    "sg:postcode":"70520",
    "sg:province":"LA",
    "sg:tags":[
        "shop"
    ],
    "wof:name":"Gails Hair Creation",
    "wof:placetype":"venue"
},
  "geometry": {"coordinates":[-92.061572,30.317429],"type":"Point"}
}