{
  "type": "Feature",
  "properties": {
    "iso:country":"US",
    "sg:address":"130 Moreau St",
    "sg:city":"Natchitoches",
    "sg:classifiers":[
        {
            "category":"Government",
            "subcategory":"Office",
            "type":"Public Place"
        }
    ],
    "sg:phone":"+1 318 357 3101",
    "sg:postcode":"71457",
    "sg:province":"LA",
    "wof:name":"Fort St Jean Commemorative",
    "wof:placetype":"venue"
},
  "geometry": {"coordinates":[-92.78107199999999,31.540388],"type":"Point"}
}