{
  "type": "Feature",
  "properties": {
    "iso:country":"US",
    "sg:address":"1056 Wemple Rd",
    "sg:city":"Bossier City",
    "sg:classifiers":[
        {
            "category":"Professional",
            "subcategory":"Business Services",
            "type":"Services"
        }
    ],
    "sg:phone":"+1 318 549 0868",
    "sg:postcode":"71111",
    "sg:province":"LA",
    "wof:name":"Dorothy Delanie",
    "wof:placetype":"venue"
},
  "geometry": {"coordinates":[-93.701525,32.594771],"type":"Point"}
}