{
  "type": "Feature",
  "properties": {
    "iso:country":"US",
    "sg:address":"2420 Pritchard Rd",
    "sg:city":"Marrero",
    "sg:classifiers":[
        {
            "category":"Building & Trades",
            "subcategory":"Landscaping Services",
            "type":"Services"
        }
    ],
    "sg:phone":"+1 504 340 6006",
    "sg:postcode":"70072",
    "sg:province":"LA",
    "wof:name":"Anthonys Complete Lawn Care",
    "wof:placetype":"venue"
},
  "geometry": {"coordinates":[-90.104078,29.847464],"type":"Point"}
}