{
  "type": "Feature",
  "properties": {
    "addr:full":"202 Benton Rd Bossier City LA 71111",
    "addr:housenumber":"202",
    "addr:postcode":"71111",
    "addr:street":"Benton Rd",
    "iso:country":"US",
    "sg:address":"202 Benton Rd",
    "sg:city":"Bossier City",
    "sg:classifiers":[
        {
            "category":"Shopping",
            "subcategory":"Department Store",
            "type":"Retail Goods"
        }
    ],
    "sg:phone":"+1 318 741 9195",
    "sg:postcode":"71111",
    "sg:province":"LA",
    "sg:tags":[
        "shop"
    ],
    "wof:name":"Dollar General",
    "wof:placetype":"venue"
},
  "geometry": {"coordinates":[-93.716509,32.518791],"type":"Point"}
}