{
  "type": "Feature",
  "properties": {
    "addr:full":"38903 State Rte 23 Buras LA 70041",
    "addr:housenumber":"38903",
    "addr:postcode":"70041",
    "addr:street":"State Rte 23 Buras",
    "iso:country":"US",
    "sg:address":"38903 State Rte 23",
    "sg:city":"Buras",
    "sg:classifiers":[
        {
            "category":"Utilities",
            "subcategory":"Water",
            "type":"Services"
        }
    ],
    "sg:phone":"+1 985 534 2233",
    "sg:postcode":"70041",
    "sg:province":"LA",
    "sg:tags":[
        "company",
        "sewage"
    ],
    "wof:name":"Severn Trent Svc Inc",
    "wof:placetype":"venue"
},
  "geometry": {"coordinates":[-89.440406,29.35222],"type":"Point"}
}