{
  "type": "Feature",
  "properties": {
    "addr:full":"1105 S John M Hardy Dr Abbeville LA 70510",
    "addr:housenumber":"1105",
    "addr:postcode":"70510",
    "addr:street":"S John M Hardy Dr",
    "iso:country":"US",
    "sg:address":"1105 S John M Hardy Dr",
    "sg:city":"Abbeville",
    "sg:classifiers":[
        {
            "category":"Professional",
            "subcategory":"Business Services",
            "type":"Services"
        }
    ],
    "sg:phone":"+1 337 893 6722",
    "sg:postcode":"70510",
    "sg:province":"LA",
    "sg:tags":[
        "personal",
        "bureau",
        "broker",
        "agent"
    ],
    "wof:name":"Skate Zone",
    "wof:placetype":"venue"
},
  "geometry": {"coordinates":[-92.116553,29.958085],"type":"Point"}
}