{
  "type": "Feature",
  "properties": {
    "iso:country":"US",
    "sg:address":"327 Patrick Dr",
    "sg:city":"Schriever",
    "sg:classifiers":[
        {
            "category":"Freight",
            "type":"Transportation"
        }
    ],
    "sg:phone":"+1 985 447 0074",
    "sg:postcode":"70395",
    "sg:province":"LA",
    "sg:tags":[
        "trucking"
    ],
    "wof:name":"Brians Trucking LLC",
    "wof:placetype":"venue"
},
  "geometry": {"coordinates":[-90.83396,29.737412],"type":"Point"}
}