{
  "type": "Feature",
  "properties": {
    "addr:full":"4605 N Laurel Creek Ct Baton Rouge LA 70817",
    "addr:housenumber":"4605",
    "addr:postcode":"70817",
    "addr:street":"N Laurel Creek Ct",
    "iso:country":"US",
    "sg:address":"4605 N Laurel Creek Ct",
    "sg:city":"Baton Rouge",
    "sg:classifiers":[
        {
            "category":"Professional",
            "subcategory":"Business Services",
            "type":"Services"
        }
    ],
    "sg:phone":"+1 225 755 1911",
    "sg:postcode":"70817",
    "sg:province":"LA",
    "wof:name":"KMC Enterprises LLC",
    "wof:placetype":"venue"
},
  "geometry": {"coordinates":[-91.031009,30.407072],"type":"Point"}
}