{
  "type": "Feature",
  "properties": {
    "iso:country":"US",
    "sg:address":"2446 Ged Rd",
    "sg:city":"Vinton",
    "sg:classifiers":[
        {
            "category":"Mining & Drilling",
            "type":"Manufacturing & Wholesale Goods"
        }
    ],
    "sg:phone":"+1 337 589 3766",
    "sg:postcode":"70668",
    "sg:province":"LA",
    "sg:tags":[
        "oil",
        "gas",
        "producer"
    ],
    "wof:name":"Aminex USA",
    "wof:placetype":"venue"
},
  "geometry": {"coordinates":[-93.591453,30.152916],"type":"Point"}
}