{
  "type": "Feature",
  "properties": {
    "iso:country":"US",
    "sg:address":"714 1st St",
    "sg:city":"Gretna",
    "sg:classifiers":[
        {
            "category":"Restaurant",
            "type":"Food & Drink"
        }
    ],
    "sg:phone":"+1 504 366 5555",
    "sg:postcode":"70053",
    "sg:province":"LA",
    "wof:name":"Lion's Share Restaurant",
    "wof:placetype":"venue"
},
  "geometry": {"coordinates":[-90.066281,29.917985],"type":"Point"}
}