{
  "type": "Feature",
  "properties": {
    "iso:country":"US",
    "sg:address":"1900 N Market St",
    "sg:city":"Shreveport",
    "sg:classifiers":[
        {
            "category":"Autos & Motor Vehicles",
            "subcategory":"Fuel & Gas Station",
            "type":"Retail Goods"
        }
    ],
    "sg:phone":"+1 318 221 4990",
    "sg:postcode":"71107",
    "sg:province":"LA",
    "sg:tags":[
        "oil"
    ],
    "wof:name":"Texaco Night & Day",
    "wof:placetype":"venue"
},
  "geometry": {"coordinates":[-93.778837,32.549427],"type":"Point"}
}