{
  "type": "Feature",
  "properties": {
    "iso:country":"US",
    "sg:address":"407 S Broad St",
    "sg:city":"New Orleans",
    "sg:classifiers":[
        {
            "category":"Professional",
            "subcategory":"Lawyer & Legal Services",
            "type":"Services"
        }
    ],
    "sg:phone":"+1 504 822 3930",
    "sg:postcode":"70119",
    "sg:province":"LA",
    "sg:tags":[
        "attorney"
    ],
    "wof:name":"Capasso & Brancato",
    "wof:placetype":"venue"
},
  "geometry": {"coordinates":[-90.09024100000001,29.962527],"type":"Point"}
}