{
  "type": "Feature",
  "properties": {
    "iso:country":"US",
    "sg:address":"10652 Alco Ave",
    "sg:city":"Baton Rouge",
    "sg:classifiers":[
        {
            "category":"Wholesale",
            "subcategory":"Seafood",
            "type":"Manufacturing & Wholesale Goods"
        }
    ],
    "sg:phone":"+1 225 368 8633",
    "sg:postcode":"70816",
    "sg:province":"LA",
    "wof:name":"Todd Co",
    "wof:placetype":"venue"
},
  "geometry": {"coordinates":[-91.06289700000001,30.409554],"type":"Point"}
}