{
  "type": "Feature",
  "properties": {
    "iso:country":"US",
    "sg:address":"13279 Village Trace Dr",
    "sg:city":"Folsom",
    "sg:classifiers":[
        {
            "category":"Building & Trades",
            "subcategory":"Construction",
            "type":"Services"
        }
    ],
    "sg:phone":"+1 985 796 8351",
    "sg:postcode":"70437",
    "sg:province":"LA",
    "sg:tags":[
        "roofing",
        "contractor"
    ],
    "wof:name":"Gulf Shore Construction Rfng",
    "wof:placetype":"venue"
},
  "geometry": {"coordinates":[-90.19070000000001,30.633503],"type":"Point"}
}