{
  "type": "Feature",
  "properties": {
    "addr:full":"131 Oak St Dubach LA 71235",
    "addr:housenumber":"131",
    "addr:postcode":"71235",
    "addr:street":"Oak St",
    "iso:country":"US",
    "sg:address":"131 Oak St",
    "sg:city":"Dubach",
    "sg:classifiers":[
        {
            "category":"Organizations",
            "subcategory":"Religious Organization",
            "type":"Services"
        }
    ],
    "sg:phone":"+1 318 777 3988",
    "sg:postcode":"71235",
    "sg:province":"LA",
    "sg:tags":[
        "church"
    ],
    "wof:name":"United Pentecostal Church",
    "wof:placetype":"venue"
},
  "geometry": {"coordinates":[-92.657989,32.690678],"type":"Point"}
}