{
  "type": "Feature",
  "properties": {
    "iso:country":"US",
    "sg:address":"5207 Magazine St",
    "sg:city":"New Orleans",
    "sg:classifiers":[
        {
            "category":"Shopping",
            "type":"Retail Goods"
        }
    ],
    "sg:phone":"+1 504 897 5330",
    "sg:postcode":"70115",
    "sg:province":"LA",
    "sg:tags":[
        "art",
        "gallery",
        "dealer"
    ],
    "wof:name":"Magazine Street Gallery",
    "wof:placetype":"venue"
},
  "geometry": {"coordinates":[-90.11188300000001,29.920525],"type":"Point"}
}