{
  "type": "Feature",
  "properties": {
    "iso:country":"US",
    "sg:address":"2241 Kansas Ave",
    "sg:city":"Kenner",
    "sg:classifiers":[
        {
            "category":"Professional",
            "subcategory":"Credit Reporting & Collection",
            "type":"Services"
        }
    ],
    "sg:phone":"+1 504 467 2525",
    "sg:postcode":"70062",
    "sg:province":"LA",
    "sg:tags":[
        "agency"
    ],
    "wof:name":"Thomas Gottschalk & Olton Svc",
    "wof:placetype":"venue"
},
  "geometry": {"coordinates":[-90.23548700000001,29.996541],"type":"Point"}
}