{
  "type": "Feature",
  "properties": {
    "iso:country":"US",
    "sg:address":"19448 Tice Rd",
    "sg:city":"Covington",
    "sg:classifiers":[
        {
            "category":"Professional",
            "subcategory":"Computer Services",
            "type":"Services"
        }
    ],
    "sg:phone":"+1 985 892 6490",
    "sg:postcode":"70435",
    "sg:province":"LA",
    "wof:name":"S G Lane Enterprises Inc",
    "wof:placetype":"venue"
},
  "geometry": {"coordinates":[-90.074912,30.530541],"type":"Point"}
}