{
  "type": "Feature",
  "properties": {
    "addr:full":"4709 Bluebonnet Rd Baton Rouge LA 70809",
    "addr:housenumber":"4709",
    "addr:postcode":"70809",
    "addr:street":"Bluebonnet Rd",
    "iso:country":"US",
    "sg:address":"4709 Bluebonnet Rd",
    "sg:city":"Baton Rouge",
    "sg:classifiers":[
        {
            "category":"Banks & Credit Unions",
            "subcategory":"Bank",
            "type":"Services"
        }
    ],
    "sg:phone":"+1 225 291 2695",
    "sg:postcode":"70809",
    "sg:province":"LA",
    "sg:tags":[
        "financing"
    ],
    "wof:name":"Southwest Funding",
    "wof:placetype":"venue"
},
  "geometry": {"coordinates":[-91.081249,30.410054],"type":"Point"}
}