{
  "type": "Feature",
  "properties": {
    "iso:country":"US",
    "sg:address":"1300 Saint Jude Ave",
    "sg:city":"New Iberia",
    "sg:classifiers":[
        {
            "category":"Food & Beverages",
            "subcategory":"Groceries & Convenience Stores",
            "type":"Retail Goods"
        }
    ],
    "sg:phone":"+1 337 367 2849",
    "sg:postcode":"70560",
    "sg:province":"LA",
    "wof:name":"T & B Grocery",
    "wof:placetype":"venue"
},
  "geometry": {"coordinates":[-91.834801,30.0021],"type":"Point"}
}