{
  "type": "Feature",
  "properties": {
    "iso:country":"US",
    "sg:address":"5930 Goodwood Ave",
    "sg:city":"Baton Rouge",
    "sg:classifiers":[
        {
            "category":"Professional",
            "subcategory":"Lawyer & Legal Services",
            "type":"Services"
        }
    ],
    "sg:phone":"+1 225 926 3913",
    "sg:postcode":"70806",
    "sg:province":"LA",
    "wof:name":"Pedaegis LLC",
    "wof:placetype":"venue"
},
  "geometry": {"coordinates":[-91.12749599999999,30.441555],"type":"Point"}
}