{
  "type": "Feature",
  "properties": {
    "addr:full":"1117 Forsythe Ave Monroe LA 71201",
    "addr:housenumber":"1117",
    "addr:postcode":"71201",
    "addr:street":"Forsythe Ave",
    "iso:country":"US",
    "sg:address":"1117 Forsythe Ave",
    "sg:city":"Monroe",
    "sg:classifiers":[
        {
            "category":"Shopping",
            "subcategory":"Clothing, Apparel, & Fashions",
            "type":"Retail Goods"
        }
    ],
    "sg:phone":"+1 318 388 0180",
    "sg:postcode":"71201",
    "sg:province":"LA",
    "sg:tags":[
        "uniform"
    ],
    "wof:name":"Uniforms & More",
    "wof:placetype":"venue"
},
  "geometry": {"coordinates":[-92.122207,32.525855],"type":"Point"}
}