{
  "type": "Feature",
  "properties": {
    "iso:country":"US",
    "sg:address":"463 Pea Ridge Rd",
    "sg:city":"Dubach",
    "sg:classifiers":[
        {
            "category":"Health Services",
            "subcategory":"Nursing And Care Facility",
            "type":"Services"
        }
    ],
    "sg:phone":"+1 318 255 2033",
    "sg:postcode":"71235",
    "sg:province":"LA",
    "sg:tags":[
        "hospice"
    ],
    "wof:name":"Hospice Of Caring Hearts",
    "wof:placetype":"venue"
},
  "geometry": {"coordinates":[-92.588497,32.631457],"type":"Point"}
}