{
  "type": "Feature",
  "properties": {
    "iso:country":"US",
    "sg:address":"101 2nd St",
    "sg:city":"Franklin",
    "sg:classifiers":[
        {
            "category":"Education",
            "subcategory":"School",
            "type":"Public Place"
        }
    ],
    "sg:phone":"+1 337 828 1905",
    "sg:postcode":"70538",
    "sg:province":"LA",
    "wof:name":"Foster W Prescott Elementary",
    "wof:placetype":"venue"
},
  "geometry": {"coordinates":[-91.49996400000001,29.785213],"type":"Point"}
}