{
  "type": "Feature",
  "properties": {
    "iso:country":"US",
    "sg:address":"1104 Hwy 71 S",
    "sg:city":"Lecompte",
    "sg:classifiers":[
        {
            "category":"Freight",
            "type":"Transportation"
        }
    ],
    "sg:phone":"+1 318 776 0700",
    "sg:postcode":"71346",
    "sg:province":"LA",
    "sg:tags":[
        "commercial",
        "storage"
    ],
    "wof:name":"Lecompte Mini Storage",
    "wof:placetype":"venue"
},
  "geometry": {"coordinates":[-92.40192999999999,31.10385],"type":"Point"}
}