{
  "type": "Feature",
  "properties": {
    "iso:country":"US",
    "sg:address":"14389 Chef Menteur Hwy",
    "sg:city":"New Orleans",
    "sg:classifiers":[
        {
            "category":"Personal",
            "subcategory":"Beauty Salon",
            "type":"Services"
        }
    ],
    "sg:phone":"+1 504 254 1976",
    "sg:postcode":"70129",
    "sg:province":"LA",
    "wof:name":"Kim Thoa Beauty Salon",
    "wof:placetype":"venue"
},
  "geometry": {"coordinates":[-89.91172899999999,30.036457],"type":"Point"}
}