{
  "type": "Feature",
  "properties": {
    "iso:country":"US",
    "sg:address":"501 N Range Ave",
    "sg:city":"Denham Springs",
    "sg:classifiers":[
        {
            "category":"Retail",
            "subcategory":"Auto Repair",
            "type":"Services"
        }
    ],
    "sg:phone":"+1 225 667 0072",
    "sg:postcode":"70726",
    "sg:province":"LA",
    "sg:tags":[
        "automobile",
        "lubrication"
    ],
    "wof:name":"Gene's Quick Lube",
    "wof:placetype":"venue"
},
  "geometry": {"coordinates":[-90.95629599999999,30.489423],"type":"Point"}
}