{
  "type": "Feature",
  "properties": {
    "addr:full":"1106 Hatchell Ln Denham Springs LA 70726",
    "addr:housenumber":"1106",
    "addr:postcode":"70726",
    "addr:street":"Hatchell Ln",
    "iso:country":"US",
    "sg:address":"1106 Hatchell Ln",
    "sg:city":"Denham Springs",
    "sg:classifiers":[
        {
            "category":"Government",
            "subcategory":"Fire Station",
            "type":"Public Place"
        }
    ],
    "sg:phone":"+1 225 667 8370",
    "sg:postcode":"70726",
    "sg:province":"LA",
    "sg:tags":[
        "department"
    ],
    "wof:name":"Denham Springs Fire Dept",
    "wof:placetype":"venue"
},
  "geometry": {"coordinates":[-90.943442,30.49922],"type":"Point"}
}