{
  "type": "Feature",
  "properties": {
    "addr:full":"101 S State St Abbeville LA 70510",
    "addr:housenumber":"101",
    "addr:postcode":"70510",
    "addr:street":"S State St",
    "iso:country":"US",
    "sg:address":"101 S State St",
    "sg:city":"Abbeville",
    "sg:classifiers":[
        {
            "category":"Government",
            "subcategory":"Police Station",
            "type":"Public Place"
        }
    ],
    "sg:phone":"+1 337 898 4417",
    "sg:postcode":"70510",
    "sg:province":"LA",
    "sg:tags":[
        "sheriff"
    ],
    "wof:name":"County Sheriff-Purchasing",
    "wof:placetype":"venue"
},
  "geometry": {"coordinates":[-92.135651,29.974014],"type":"Point"}
}