{
  "type": "Feature",
  "properties": {
    "iso:country":"US",
    "sg:address":"1120 Creswell Ave",
    "sg:city":"Shreveport",
    "sg:classifiers":[
        {
            "category":"Organizations",
            "subcategory":"Religious Organization",
            "type":"Services"
        }
    ],
    "sg:phone":"+1 318 227 9532",
    "sg:postcode":"71101",
    "sg:province":"LA",
    "sg:tags":[
        "church"
    ],
    "wof:name":"Christian Development Center",
    "wof:placetype":"venue"
},
  "geometry": {"coordinates":[-93.74168899999999,32.500873],"type":"Point"}
}