{
  "type": "Feature",
  "properties": {
    "addr:full":"1129 Mustang Dr Arnaudville LA 70582",
    "addr:housenumber":"1129",
    "addr:postcode":"70582",
    "addr:street":"Mustang Dr Arnaudville",
    "iso:country":"US",
    "sg:address":"1129 Mustang Dr",
    "sg:city":"Arnaudville",
    "sg:classifiers":[
        {
            "category":"Wholesale",
            "subcategory":"Chemicals & Plastics",
            "type":"Manufacturing & Wholesale Goods"
        }
    ],
    "sg:phone":"+1 337 394 4801",
    "sg:postcode":"70582",
    "sg:province":"LA",
    "wof:name":"3-D Chemicals Inc",
    "wof:placetype":"venue"
},
  "geometry": {"coordinates":[-91.85119299999999,30.084428],"type":"Point"}
}