{
  "type": "Feature",
  "properties": {
    "addr:full":"5765 Hwy 107 S Plaucheville LA 71362",
    "addr:housenumber":"5765",
    "addr:postcode":"71362",
    "addr:street":"Hwy 107 S Plaucheville",
    "iso:country":"US",
    "sg:address":"5765 Hwy 107 S",
    "sg:city":"Plaucheville",
    "sg:classifiers":[
        {
            "category":"Organizations",
            "subcategory":"Religious Organization",
            "type":"Services"
        }
    ],
    "sg:phone":"+1 318 922 3243",
    "sg:postcode":"71362",
    "sg:province":"LA",
    "sg:tags":[
        "church"
    ],
    "wof:name":"Immaculate Conception Catholic",
    "wof:placetype":"venue"
},
  "geometry": {"coordinates":[-91.945902,30.927619],"type":"Point"}
}