{
  "type": "Feature",
  "properties": {
    "addr:full":"1852 Russell Rd Shreveport LA 71107",
    "addr:housenumber":"1852",
    "addr:postcode":"71107",
    "addr:street":"Russell Rd",
    "iso:country":"US",
    "sg:address":"1852 Russell Rd",
    "sg:city":"Shreveport",
    "sg:classifiers":[
        {
            "category":"Organizations",
            "subcategory":"Religious Organization",
            "type":"Services"
        }
    ],
    "sg:phone":"+1 318 221 8120",
    "sg:postcode":"71107",
    "sg:province":"LA",
    "sg:tags":[
        "church"
    ],
    "sg:website":"www.cocrr.org",
    "wof:name":"Church Of Christ",
    "wof:placetype":"venue"
},
  "geometry": {"coordinates":[-93.802768,32.540739],"type":"Point"}
}