{
  "type": "Feature",
  "properties": {
    "iso:country":"US",
    "sg:address":"1808 US Hwy 190",
    "sg:city":"Deridder",
    "sg:classifiers":[
        {
            "category":"Professional",
            "subcategory":"Art Services",
            "type":"Services"
        }
    ],
    "sg:phone":"+1 337 462 3908",
    "sg:postcode":"70634",
    "sg:province":"LA",
    "sg:tags":[
        "graphic",
        "designer"
    ],
    "wof:name":"Dental Graphics",
    "wof:placetype":"venue"
},
  "geometry": {"coordinates":[-93.254755,30.844197],"type":"Point"}
}