{
  "type": "Feature",
  "properties": {
    "iso:country":"US",
    "sg:address":"3521 Lake Des Allemanos Dr",
    "sg:city":"Harvey",
    "sg:classifiers":[
        {
            "category":"Professional",
            "subcategory":"Management & Consulting",
            "type":"Services"
        }
    ],
    "sg:phone":"+1 504 361 5233",
    "sg:postcode":"70058",
    "sg:province":"LA",
    "sg:tags":[
        "consultant",
        "business"
    ],
    "wof:name":"Jemison & Partners Inc",
    "wof:placetype":"venue"
},
  "geometry": {"coordinates":[-90.044459,29.858031],"type":"Point"}
}