{
  "type": "Feature",
  "properties": {
    "iso:country":"US",
    "sg:address":"625 N 4th St",
    "sg:city":"Baton Rouge",
    "sg:classifiers":[
        {
            "category":"Government",
            "subcategory":"Office",
            "type":"Public Place"
        }
    ],
    "sg:phone":"+1 225 389 0405",
    "sg:postcode":"70802",
    "sg:province":"LA",
    "sg:tags":[
        "federal",
        "safety",
        "order"
    ],
    "wof:name":"US Emergency Mgmt State & Lcl",
    "wof:placetype":"venue"
},
  "geometry": {"coordinates":[-91.187285,30.453282],"type":"Point"}
}