{
  "type": "Feature",
  "properties": {
    "iso:country":"US",
    "sg:address":"421 Mississippi St",
    "sg:city":"Donaldsonville",
    "sg:classifiers":[
        {
            "category":"Professional",
            "subcategory":"Computer Services",
            "type":"Services"
        }
    ],
    "sg:phone":"+1 225 473 3286",
    "sg:postcode":"70346",
    "sg:province":"LA",
    "sg:tags":[
        "consultant",
        "designer"
    ],
    "wof:name":"General Computer Svc",
    "wof:placetype":"venue"
},
  "geometry": {"coordinates":[-90.98679199999999,30.10623],"type":"Point"}
}