{
  "type": "Feature",
  "properties": {
    "addr:full":"630 Mandeville St New Orleans LA 70117",
    "addr:housenumber":"630",
    "addr:postcode":"70117",
    "addr:street":"Mandeville St",
    "iso:country":"US",
    "sg:address":"630 Mandeville St",
    "sg:city":"New Orleans",
    "sg:classifiers":[
        {
            "category":"Restaurant",
            "type":"Food & Drink"
        }
    ],
    "sg:phone":"+1 504 947 4558",
    "sg:postcode":"70117",
    "sg:province":"LA",
    "wof:name":"Praline Connection the",
    "wof:placetype":"venue"
},
  "geometry": {"coordinates":[-90.05390199999999,29.9646],"type":"Point"}
}