{
  "type": "Feature",
  "properties": {
    "addr:full":"4040 Berkley St Slidell LA 70458",
    "addr:housenumber":"4040",
    "addr:postcode":"70458",
    "addr:street":"Berkley St",
    "iso:country":"US",
    "sg:address":"4040 Berkley St",
    "sg:city":"Slidell",
    "sg:classifiers":[
        {
            "category":"Education",
            "subcategory":"School",
            "type":"Public Place"
        }
    ],
    "sg:phone":"+1 985 643 7359",
    "sg:postcode":"70458",
    "sg:province":"LA",
    "wof:name":"Salmen High School",
    "wof:placetype":"venue"
},
  "geometry": {"coordinates":[-89.79185,30.247329],"type":"Point"}
}