{
  "type": "Feature",
  "properties": {
    "iso:country":"US",
    "sg:address":"3021 Ursulines Ave",
    "sg:city":"New Orleans",
    "sg:classifiers":[
        {
            "category":"Professional",
            "type":"Services"
        }
    ],
    "sg:phone":"+1 504 484 6476",
    "sg:postcode":"70119",
    "sg:province":"LA",
    "wof:name":"Hung Fine Art Framing & Svcs",
    "wof:placetype":"venue"
},
  "geometry": {"coordinates":[-90.084492,29.977016],"type":"Point"}
}