{
  "type": "Feature",
  "properties": {
    "addr:full":"8318 Mickens Rd Baton Rouge LA 70811",
    "addr:housenumber":"8318",
    "addr:postcode":"70811",
    "addr:street":"Mickens Rd",
    "iso:country":"US",
    "sg:address":"8318 Mickens Rd",
    "sg:city":"Baton Rouge",
    "sg:classifiers":[
        {
            "category":"Home & Garden",
            "subcategory":"Garden Supply",
            "type":"Retail Goods"
        }
    ],
    "sg:phone":"+1 225 356 3356",
    "sg:postcode":"70811",
    "sg:province":"LA",
    "sg:tags":[
        "nurseryman"
    ],
    "wof:name":"Burris's Nursery & Greenhouses",
    "wof:placetype":"venue"
},
  "geometry": {"coordinates":[-91.10517299999999,30.511899],"type":"Point"}
}