{
  "type": "Feature",
  "properties": {
    "addr:full":"3421 Tulane Dr Kenner LA 70065",
    "addr:housenumber":"3421",
    "addr:postcode":"70065",
    "addr:street":"Tulane Dr",
    "iso:country":"US",
    "sg:address":"3421 Tulane Dr",
    "sg:city":"Kenner",
    "sg:classifiers":[
        {
            "category":"Shopping",
            "subcategory":"Books",
            "type":"Retail Goods"
        }
    ],
    "sg:phone":"+1 504 466 1780",
    "sg:postcode":"70065",
    "sg:province":"LA",
    "wof:name":"Kangaroo Pouch Cover To Cover",
    "wof:placetype":"venue"
},
  "geometry": {"coordinates":[-90.27562399999999,30.022795],"type":"Point"}
}