{
  "type": "Feature",
  "properties": {
    "addr:full":"1751 Gentilly Blvd New Orleans LA 70119",
    "addr:housenumber":"1751",
    "addr:postcode":"70119",
    "addr:street":"Gentilly Blvd",
    "iso:country":"US",
    "sg:address":"1751 Gentilly Blvd",
    "sg:city":"New Orleans",
    "sg:classifiers":[
        {
            "category":"Professional",
            "type":"Services"
        }
    ],
    "sg:phone":"+1 504 945 0511",
    "sg:postcode":"70119",
    "sg:province":"LA",
    "sg:tags":[
        "establishment"
    ],
    "wof:name":"Express Tees Inc Jazzfest",
    "wof:placetype":"venue"
},
  "geometry": {"coordinates":[-90.07672599999999,29.984267],"type":"Point"}
}