{
  "type": "Feature",
  "properties": {
    "iso:country":"US",
    "sg:address":"557 11th St NE",
    "sg:city":"Springhill",
    "sg:classifiers":[
        {
            "category":"Building & Trades",
            "subcategory":"Electrical",
            "type":"Services"
        }
    ],
    "sg:phone":"+1 318 539 3762",
    "sg:postcode":"71075",
    "sg:province":"LA",
    "sg:tags":[
        "electric",
        "contractor"
    ],
    "wof:name":"Ernest Edwards Electric",
    "wof:placetype":"venue"
},
  "geometry": {"coordinates":[-93.445627,33.0157],"type":"Point"}
}