{
  "type": "Feature",
  "properties": {
    "iso:country":"US",
    "sg:address":"923 Bourbon St",
    "sg:city":"New Orleans",
    "sg:classifiers":[
        {
            "category":"Professional",
            "subcategory":"Lawyer & Legal Services",
            "type":"Services"
        }
    ],
    "sg:phone":"+1 504 522 7421",
    "sg:postcode":"70116",
    "sg:province":"LA",
    "wof:name":"M L Talbott A Prof Law Corp",
    "wof:placetype":"venue"
},
  "geometry": {"coordinates":[-90.06365099999999,29.960937],"type":"Point"}
}