{
  "type": "Feature",
  "properties": {
    "iso:country":"US",
    "sg:address":"5463 Main St",
    "sg:city":"Zachary",
    "sg:classifiers":[
        {
            "category":"Health Services",
            "subcategory":"Clinic",
            "type":"Services"
        }
    ],
    "sg:phone":"+1 225 658 0608",
    "sg:postcode":"70791",
    "sg:province":"LA",
    "wof:name":"Health Alliance",
    "wof:placetype":"venue"
},
  "geometry": {"coordinates":[-91.146704,30.647489],"type":"Point"}
}