{
  "type": "Feature",
  "properties": {
    "iso:country":"US",
    "sg:address":"1018 Victory Dr",
    "sg:city":"Westwego",
    "sg:classifiers":[
        {
            "category":"Building & Trades",
            "subcategory":"Construction",
            "type":"Services"
        }
    ],
    "sg:phone":"+1 504 328 3510",
    "sg:postcode":"70094",
    "sg:province":"LA",
    "sg:tags":[
        "contractor"
    ],
    "wof:name":"Pierce Foundation",
    "wof:placetype":"venue"
},
  "geometry": {"coordinates":[-90.137086,29.887314],"type":"Point"}
}