{
  "type": "Feature",
  "properties": {
    "addr:full":"6117 Magazine St New Orleans LA 70118",
    "addr:housenumber":"6117",
    "addr:postcode":"70118",
    "addr:street":"Magazine St",
    "iso:country":"US",
    "sg:address":"6117 Magazine St",
    "sg:city":"New Orleans",
    "sg:classifiers":[
        {
            "category":"Retail",
            "subcategory":"Animal Services",
            "type":"Services"
        }
    ],
    "sg:phone":"+1 504 895 9617",
    "sg:postcode":"70118",
    "sg:province":"LA",
    "sg:tags":[
        "pet",
        "grooming",
        "washing"
    ],
    "wof:name":"Audubon Grooming & Boarding",
    "wof:placetype":"venue"
},
  "geometry": {"coordinates":[-90.124197,29.923181],"type":"Point"}
}