{
  "type": "Feature",
  "properties": {
    "iso:country":"US",
    "sg:address":"3154 NE Evangeline Trwy",
    "sg:city":"Lafayette",
    "sg:classifiers":[
        {
            "category":"Home & Garden",
            "subcategory":"Garden Supply",
            "type":"Retail Goods"
        }
    ],
    "sg:phone":"+1 337 237 4795",
    "sg:postcode":"70507",
    "sg:province":"LA",
    "sg:tags":[
        "nursery",
        "gardening"
    ],
    "wof:name":"A B C Orchids",
    "wof:placetype":"venue"
},
  "geometry": {"coordinates":[-92.022697,30.2897],"type":"Point"}
}