{
  "type": "Feature",
  "properties": {
    "addr:full":"4104 Jackson St Exd Alexandria LA 71303",
    "addr:housenumber":"4104",
    "addr:postcode":"71303",
    "addr:street":"Jackson St Exd",
    "iso:country":"US",
    "sg:address":"4104 Jackson St Exd",
    "sg:city":"Alexandria",
    "sg:classifiers":[
        {
            "category":"Restaurant",
            "type":"Food & Drink"
        }
    ],
    "sg:phone":"+1 318 443 0440",
    "sg:postcode":"71303",
    "sg:province":"LA",
    "wof:name":"A LA Mode",
    "wof:placetype":"venue"
},
  "geometry": {"coordinates":[-92.47882,31.280732],"type":"Point"}
}