{
  "type": "Feature",
  "properties": {
    "iso:country":"US",
    "sg:address":"11534 Cloverland Ave",
    "sg:city":"Baton Rouge",
    "sg:classifiers":[
        {
            "category":"Wholesale",
            "subcategory":"Machinery & Supplies",
            "type":"Manufacturing & Wholesale Goods"
        }
    ],
    "sg:phone":"+1 225 755 1992",
    "sg:postcode":"70809",
    "sg:province":"LA",
    "sg:tags":[
        "valve"
    ],
    "sg:website":"www.vscinc.com",
    "wof:name":"Valve Systems & Controls",
    "wof:placetype":"venue"
},
  "geometry": {"coordinates":[-91.053417,30.391901],"type":"Point"}
}