{
  "type": "Feature",
  "properties": {
    "iso:country":"US",
    "sg:address":"1029 Clarkson St",
    "sg:city":"Coushatta",
    "sg:phone":"+1 318 932 5834",
    "sg:postcode":"71019",
    "sg:province":"LA",
    "sg:tags":[
        "farm",
        "soybean"
    ],
    "wof:name":"Stuart John",
    "wof:placetype":"venue"
},
  "geometry": {"coordinates":[-93.332835,32.014172],"type":"Point"}
}