{
  "type": "Feature",
  "properties": {
    "iso:country":"US",
    "sg:address":"28478 Blair Ln",
    "sg:city":"Angie",
    "sg:classifiers":[
        {
            "category":"Freight",
            "type":"Transportation"
        }
    ],
    "sg:phone":"+1 985 848 2291",
    "sg:postcode":"70426",
    "sg:province":"LA",
    "sg:tags":[
        "operator",
        "trucking"
    ],
    "wof:name":"Blair Transport",
    "wof:placetype":"venue"
},
  "geometry": {"coordinates":[-89.93176200000001,30.942761],"type":"Point"}
}