{
  "type": "Feature",
  "properties": {
    "iso:country":"US",
    "sg:address":"1200 Sterlington Rd",
    "sg:city":"Monroe",
    "sg:classifiers":[
        {
            "category":"Banks & Credit Unions",
            "subcategory":"Bank",
            "type":"Services"
        }
    ],
    "sg:phone":"+1 318 345 8450",
    "sg:postcode":"71203",
    "sg:province":"LA",
    "wof:name":"Bank One",
    "wof:placetype":"venue"
},
  "geometry": {"coordinates":[-92.080409,32.530774],"type":"Point"}
}