{
  "type": "Feature",
  "properties": {
    "iso:country":"US",
    "sg:address":"101 E 2nd St",
    "sg:city":"Broussard",
    "sg:classifiers":[
        {
            "category":"Restaurant",
            "type":"Food & Drink"
        }
    ],
    "sg:phone":"+1 337 839 9333",
    "sg:postcode":"70518",
    "sg:province":"LA",
    "sg:website":"www.nashs-restaurant.com",
    "wof:name":"Nash's Restaurant",
    "wof:placetype":"venue"
},
  "geometry": {"coordinates":[-91.9618,30.151699],"type":"Point"}
}