{
  "type": "Feature",
  "properties": {
    "addr:full":"225 Four Park Rd Lafayette LA 70507",
    "addr:housenumber":"225",
    "addr:postcode":"70507",
    "addr:street":"Four Park Rd",
    "iso:country":"US",
    "sg:address":"225 Four Park Rd",
    "sg:city":"Lafayette",
    "sg:classifiers":[
        {
            "category":"Building & Trades",
            "subcategory":"Plumbing",
            "type":"Services"
        }
    ],
    "sg:phone":"+1 337 886 4710",
    "sg:postcode":"70507",
    "sg:province":"LA",
    "sg:tags":[
        "sheet",
        "work",
        "metal",
        "contractor"
    ],
    "wof:name":"Specialty Sheet Metal Inc",
    "wof:placetype":"venue"
},
  "geometry": {"coordinates":[-92.031346,30.296243],"type":"Point"}
}