{
  "type": "Feature",
  "properties": {
    "iso:country":"US",
    "sg:address":"1117 Broad St",
    "sg:city":"Lake Charles",
    "sg:classifiers":[
        {
            "category":"Professional",
            "subcategory":"Management & Consulting",
            "type":"Services"
        }
    ],
    "sg:phone":"+1 337 439 1139",
    "sg:postcode":"70601",
    "sg:province":"LA",
    "sg:tags":[
        "marketing",
        "consultant"
    ],
    "wof:name":"Advantage Plus Marketing",
    "wof:placetype":"venue"
},
  "geometry": {"coordinates":[-93.204448,30.227567],"type":"Point"}
}