{
  "type": "Feature",
  "properties": {
    "addr:full":"3835 Iberville St New Orleans LA 70119",
    "addr:housenumber":"3835",
    "addr:postcode":"70119",
    "addr:street":"Iberville St",
    "iso:country":"US",
    "sg:address":"3835 Iberville St",
    "sg:city":"New Orleans",
    "sg:classifiers":[
        {
            "category":"Restaurant",
            "type":"Food & Drink"
        }
    ],
    "sg:phone":"+1 504 482 4924",
    "sg:postcode":"70119",
    "sg:province":"LA",
    "wof:name":"Christian's Restaurant",
    "wof:placetype":"venue"
},
  "geometry": {"coordinates":[-90.096845,29.973561],"type":"Point"}
}