{
  "type": "Feature",
  "properties": {
    "addr:full":"11770 S Harrells Ferry Rd Baton Rouge LA 70816",
    "addr:housenumber":"11770",
    "addr:postcode":"70816",
    "addr:street":"S Harrells Ferry Rd",
    "iso:country":"US",
    "sg:address":"11770 S Harrells Ferry Rd",
    "sg:city":"Baton Rouge",
    "sg:classifiers":[
        {
            "category":"Insurance",
            "subcategory":"Insurance Agent",
            "type":"Services"
        }
    ],
    "sg:phone":"+1 225 295 1519",
    "sg:postcode":"70816",
    "sg:province":"LA",
    "wof:name":"Bill Smith Assoc",
    "wof:placetype":"venue"
},
  "geometry": {"coordinates":[-91.051061,30.431057],"type":"Point"}
}