{
  "type": "Feature",
  "properties": {
    "iso:country":"US",
    "sg:address":"12065 Cotton Patch Ln",
    "sg:city":"Gonzales",
    "sg:classifiers":[
        {
            "category":"Professional",
            "subcategory":"Lawyer & Legal Services",
            "type":"Services"
        }
    ],
    "sg:phone":"+1 225 673 3403",
    "sg:postcode":"70737",
    "sg:province":"LA",
    "sg:tags":[
        "attorney"
    ],
    "wof:name":"Rachele K Diez",
    "wof:placetype":"venue"
},
  "geometry": {"coordinates":[-90.96419899999999,30.2401],"type":"Point"}
}