{
  "type": "Feature",
  "properties": {
    "iso:country":"US",
    "sg:address":"3500 N Hullen St",
    "sg:city":"Metairie",
    "sg:classifiers":[
        {
            "category":"Professional",
            "subcategory":"Lawyer & Legal Services",
            "type":"Services"
        }
    ],
    "sg:phone":"+1 504 586 8600",
    "sg:postcode":"70002",
    "sg:province":"LA",
    "sg:tags":[
        "attorney"
    ],
    "wof:name":"Gauither Downing Labarre Besle",
    "wof:placetype":"venue"
},
  "geometry": {"coordinates":[-90.157775,30.013828],"type":"Point"}
}