{
  "type": "Feature",
  "properties": {
    "iso:country":"US",
    "sg:address":"2302 Fasske St",
    "sg:city":"Sulphur",
    "sg:classifiers":[
        {
            "category":"Building & Trades",
            "subcategory":"Plumbing",
            "type":"Services"
        }
    ],
    "sg:phone":"+1 337 625 9617",
    "sg:postcode":"70663",
    "sg:province":"LA",
    "sg:tags":[
        "plumbing",
        "contractor"
    ],
    "wof:name":"R Bergeron Plumbing Inc",
    "wof:placetype":"venue"
},
  "geometry": {"coordinates":[-93.348675,30.233028],"type":"Point"}
}