{
  "type": "Feature",
  "properties": {
    "iso:country":"US",
    "sg:address":"1905 Veterans Memorial Dr",
    "sg:city":"Abbeville",
    "sg:classifiers":[
        {
            "category":"Government",
            "subcategory":"Office",
            "type":"Public Place"
        }
    ],
    "sg:phone":"+1 337 898 4264",
    "sg:postcode":"70510",
    "sg:province":"LA",
    "sg:tags":[
        "village"
    ],
    "wof:name":"Abbeville Tourist Information",
    "wof:placetype":"venue"
},
  "geometry": {"coordinates":[-92.149829,29.984856],"type":"Point"}
}