{
  "type": "Feature",
  "properties": {
    "addr:full":"3104 Charity St Abbeville LA 70510",
    "addr:housenumber":"3104",
    "addr:postcode":"70510",
    "addr:street":"Charity St",
    "iso:country":"US",
    "sg:address":"3104 Charity St",
    "sg:city":"Abbeville",
    "sg:classifiers":[
        {
            "category":"Autos & Motor Vehicles",
            "subcategory":"Automobile Sales",
            "type":"Retail Goods"
        }
    ],
    "sg:phone":"+1 337 893 7745",
    "sg:postcode":"70510",
    "sg:province":"LA",
    "sg:tags":[
        "car",
        "dealer"
    ],
    "wof:name":"Coastal Sales",
    "wof:placetype":"venue"
},
  "geometry": {"coordinates":[-92.093234,29.969811],"type":"Point"}
}