{
  "type": "Feature",
  "properties": {
    "addr:full":"301 Sandra Dr Berwick LA 70342",
    "addr:housenumber":"301",
    "addr:postcode":"70342",
    "addr:street":"Sandra Dr",
    "iso:country":"US",
    "sg:address":"301 Sandra Dr",
    "sg:city":"Berwick",
    "sg:classifiers":[
        {
            "category":"Professional",
            "type":"Services"
        }
    ],
    "sg:phone":"+1 985 380 2300",
    "sg:postcode":"70342",
    "sg:province":"LA",
    "sg:tags":[
        "establishment"
    ],
    "wof:name":"BST",
    "wof:placetype":"venue"
},
  "geometry": {"coordinates":[-91.22310400000001,29.694148],"type":"Point"}
}