{
  "type": "Feature",
  "properties": {
    "addr:full":"380 E Pine St Ponchatoula LA 70454",
    "addr:housenumber":"380",
    "addr:postcode":"70454",
    "addr:street":"E Pine St",
    "iso:country":"US",
    "sg:address":"380 E Pine St",
    "sg:city":"Ponchatoula",
    "sg:classifiers":[
        {
            "category":"Sports & Exercise",
            "subcategory":"Gym",
            "type":"Entertainment"
        }
    ],
    "sg:phone":"+1 985 370 0041",
    "sg:postcode":"70454",
    "sg:province":"LA",
    "sg:tags":[
        "club",
        "health",
        "studio",
        "gymnasium"
    ],
    "wof:name":"Body Shop",
    "wof:placetype":"venue"
},
  "geometry": {"coordinates":[-90.437765,30.439658],"type":"Point"}
}