{
  "type": "Feature",
  "properties": {
    "iso:country":"US",
    "sg:address":"73279 Allen Rd",
    "sg:city":"Abita Springs",
    "sg:classifiers":[
        {
            "category":"Real Estate",
            "subcategory":"Architect",
            "type":"Services"
        }
    ],
    "sg:phone":"+1 985 867 9509",
    "sg:postcode":"70420",
    "sg:province":"LA",
    "sg:tags":[
        "architectural"
    ],
    "wof:name":"A Professional Architectural",
    "wof:placetype":"venue"
},
  "geometry": {"coordinates":[-90.014574,30.498246],"type":"Point"}
}