{
  "type": "Feature",
  "properties": {
    "addr:full":"1242 Bistineau Line Rd Heflin LA 71039",
    "addr:housenumber":"1242",
    "addr:postcode":"71039",
    "addr:street":"Bistineau Line Rd",
    "iso:country":"US",
    "sg:address":"1242 Bistineau Line Rd",
    "sg:city":"Heflin",
    "sg:classifiers":[
        {
            "category":"Building & Trades",
            "subcategory":"Construction",
            "type":"Services"
        }
    ],
    "sg:phone":"+1 318 377 1647",
    "sg:postcode":"71039",
    "sg:province":"LA",
    "sg:tags":[
        "contractor"
    ],
    "wof:name":"Southern Drywall",
    "wof:placetype":"venue"
},
  "geometry": {"coordinates":[-93.240651,32.409641],"type":"Point"}
}