{
  "type": "Feature",
  "properties": {
    "addr:full":"1318 Lee St Minden LA 71055",
    "addr:housenumber":"1318",
    "addr:postcode":"71055",
    "addr:street":"Lee St",
    "iso:country":"US",
    "sg:address":"1318 Lee St",
    "sg:city":"Minden",
    "sg:classifiers":[
        {
            "category":"Travel",
            "subcategory":"Hotels & Motels",
            "type":"Entertainment"
        }
    ],
    "sg:phone":"+1 318 371 2880",
    "sg:postcode":"71055",
    "sg:province":"LA",
    "wof:name":"Southern Inn",
    "wof:placetype":"venue"
},
  "geometry": {"coordinates":[-93.287549,32.597741],"type":"Point"}
}