{
  "type": "Feature",
  "properties": {
    "addr:full":"581 Fairview Dr Berwick LA 70342",
    "addr:housenumber":"581",
    "addr:postcode":"70342",
    "addr:street":"Fairview Dr",
    "iso:country":"US",
    "sg:address":"581 Fairview Dr",
    "sg:city":"Berwick",
    "sg:classifiers":[
        {
            "category":"Organizations",
            "subcategory":"Community Association",
            "type":"Services"
        }
    ],
    "sg:phone":"+1 985 384 8500",
    "sg:postcode":"70342",
    "sg:province":"LA",
    "sg:tags":[
        "club"
    ],
    "wof:name":"St Mary Golf & Country Club",
    "wof:placetype":"venue"
},
  "geometry": {"coordinates":[-91.24015799999999,29.722396],"type":"Point"}
}