{
  "type": "Feature",
  "properties": {
    "iso:country":"US",
    "sg:address":"3899 Roy Rd",
    "sg:city":"Shreveport",
    "sg:classifiers":[
        {
            "category":"Building & Trades",
            "subcategory":"Landscaping Services",
            "type":"Services"
        }
    ],
    "sg:phone":"+1 318 426 1690",
    "sg:postcode":"71107",
    "sg:province":"LA",
    "sg:tags":[
        "tree"
    ],
    "wof:name":"Tullis Tree Care & Removal",
    "wof:placetype":"venue"
},
  "geometry": {"coordinates":[-93.84568,32.582584],"type":"Point"}
}