{
  "type": "Feature",
  "properties": {
    "iso:country":"US",
    "sg:address":"103 Journey Ln",
    "sg:city":"Lafayette",
    "sg:classifiers":[
        {
            "category":"Professional",
            "type":"Services"
        }
    ],
    "sg:phone":"+1 337 981 2030",
    "sg:postcode":"70506",
    "sg:province":"LA",
    "sg:tags":[
        "establishment"
    ],
    "wof:name":"Linda B Desormeaux Ms Ccc Slp",
    "wof:placetype":"venue"
},
  "geometry": {"coordinates":[-92.08919400000001,30.194672],"type":"Point"}
}