{
  "type": "Feature",
  "properties": {
    "iso:country":"US",
    "sg:address":"200 Polk St",
    "sg:city":"Lafayette",
    "sg:classifiers":[
        {
            "category":"Recreation",
            "type":"Entertainment"
        }
    ],
    "sg:phone":"+1 337 278 9933",
    "sg:postcode":"70501",
    "sg:province":"LA",
    "sg:tags":[
        "instruction",
        "yoga"
    ],
    "wof:name":"Radiant Health Yoga Ctr",
    "wof:placetype":"venue"
},
  "geometry": {"coordinates":[-92.01774899999999,30.224076],"type":"Point"}
}