{
  "type": "Feature",
  "properties": {
    "iso:country":"US",
    "sg:address":"1133 Hickory Ave",
    "sg:city":"Harahan",
    "sg:classifiers":[
        {
            "category":"Organizations",
            "subcategory":"Non-profit Organization",
            "type":"Services"
        }
    ],
    "sg:phone":"+1 504 737 3446",
    "sg:postcode":"70123",
    "sg:province":"LA",
    "wof:name":"Veterans Of Foreign Wars",
    "wof:placetype":"venue"
},
  "geometry": {"coordinates":[-90.202956,29.956608],"type":"Point"}
}