{
  "type": "Feature",
  "properties": {
    "addr:full":"532 E Rutland St Covington LA 70433",
    "addr:housenumber":"532",
    "addr:postcode":"70433",
    "addr:street":"E Rutland St",
    "iso:country":"US",
    "sg:address":"532 E Rutland St",
    "sg:city":"Covington",
    "sg:classifiers":[
        {
            "category":"Personal",
            "subcategory":"Barber",
            "type":"Services"
        }
    ],
    "sg:phone":"+1 985 892 4034",
    "sg:postcode":"70433",
    "sg:province":"LA",
    "wof:name":"Town & Country Barber Shop",
    "wof:placetype":"venue"
},
  "geometry": {"coordinates":[-90.09576800000001,30.474412],"type":"Point"}
}