{
  "type": "Feature",
  "properties": {
    "iso:country":"US",
    "sg:address":"1599 Eaton Dr",
    "sg:city":"Abbeville",
    "sg:classifiers":[
        {
            "category":"Organizations",
            "subcategory":"Professional Association",
            "type":"Services"
        }
    ],
    "sg:phone":"+1 337 893 6143",
    "sg:postcode":"70510",
    "sg:province":"LA",
    "wof:name":"Vermilion Boat Club",
    "wof:placetype":"venue"
},
  "geometry": {"coordinates":[-92.148466,29.960735],"type":"Point"}
}