{
  "type": "Feature",
  "properties": {
    "addr:full":"538 Madison Ave New Orleans LA 70116",
    "addr:housenumber":"538",
    "addr:postcode":"70116",
    "addr:street":"Madison Ave",
    "iso:country":"US",
    "sg:address":"538 Madison Ave",
    "sg:city":"New Orleans",
    "sg:classifiers":[
        {
            "category":"Wholesale",
            "subcategory":"Durable Goods & Equipment",
            "type":"Manufacturing & Wholesale Goods"
        }
    ],
    "sg:phone":"+1 504 410 2254",
    "sg:postcode":"70116",
    "sg:province":"LA",
    "sg:tags":[
        "importer"
    ],
    "wof:name":"Private Connection",
    "wof:placetype":"venue"
},
  "geometry": {"coordinates":[-90.062377,29.958333],"type":"Point"}
}