{
  "type": "Feature",
  "properties": {
    "addr:full":"330 Camp St New Orleans LA 70130",
    "addr:housenumber":"330",
    "addr:postcode":"70130",
    "addr:street":"Camp St",
    "iso:country":"US",
    "sg:address":"330 Camp St",
    "sg:city":"New Orleans",
    "sg:classifiers":[
        {
            "category":"Banks & Credit Unions",
            "subcategory":"Bank",
            "type":"Services"
        }
    ],
    "sg:phone":"+1 504 524 6172",
    "sg:postcode":"70130",
    "sg:province":"LA",
    "sg:tags":[
        "financing"
    ],
    "sg:website":"www.rlcsbidco.com",
    "wof:name":"Regional Loan Corp",
    "wof:placetype":"venue"
},
  "geometry": {"coordinates":[-90.06902700000001,29.950251],"type":"Point"}
}