{
  "type": "Feature",
  "properties": {
    "iso:country":"US",
    "sg:address":"2075 3rd St",
    "sg:city":"Mandeville",
    "sg:classifiers":[
        {
            "category":"Professional",
            "subcategory":"Business Services",
            "type":"Services"
        }
    ],
    "sg:phone":"+1 985 626 3283",
    "sg:postcode":"70471",
    "sg:province":"LA",
    "sg:tags":[
        "interior",
        "consultant",
        "design",
        "decorator"
    ],
    "wof:name":"Fabrics & Then Some",
    "wof:placetype":"venue"
},
  "geometry": {"coordinates":[-90.083529,30.396593],"type":"Point"}
}