{
  "type": "Feature",
  "properties": {
    "iso:country":"US",
    "sg:address":"7515 Florida Blvd",
    "sg:city":"Baton Rouge",
    "sg:classifiers":[
        {
            "category":"Professional",
            "subcategory":"Employment Agencies",
            "type":"Services"
        }
    ],
    "sg:phone":"+1 225 926 5477",
    "sg:postcode":"70806",
    "sg:province":"LA",
    "sg:tags":[
        "opportunity"
    ],
    "sg:website":"www.laborready.com",
    "wof:name":"Labor Ready Inc",
    "wof:placetype":"venue"
},
  "geometry": {"coordinates":[-91.109978,30.451944],"type":"Point"}
}