{
  "type": "Feature",
  "properties": {
    "addr:full":"12555 Shelby Dr Bastrop LA 71220",
    "addr:housenumber":"12555",
    "addr:postcode":"71220",
    "addr:street":"Shelby Dr",
    "iso:country":"US",
    "sg:address":"12555 Shelby Dr",
    "sg:city":"Bastrop",
    "sg:classifiers":[
        {
            "category":"Manufacturing",
            "subcategory":"Signs",
            "type":"Manufacturing & Wholesale Goods"
        }
    ],
    "sg:phone":"+1 318 281 5230",
    "sg:postcode":"71220",
    "sg:province":"LA",
    "wof:name":"Carter Sign Co",
    "wof:placetype":"venue"
},
  "geometry": {"coordinates":[-91.854647,32.853617],"type":"Point"}
}