{
  "type": "Feature",
  "properties": {
    "addr:full":"1914 E 70th St Shreveport LA 71105",
    "addr:housenumber":"1914",
    "addr:postcode":"71105",
    "addr:street":"E 70Th St",
    "iso:country":"US",
    "sg:address":"1914 E 70th St",
    "sg:city":"Shreveport",
    "sg:classifiers":[
        {
            "category":"Health Services",
            "subcategory":"Doctor",
            "type":"Services"
        }
    ],
    "sg:phone":"+1 318 797 8833",
    "sg:postcode":"71105",
    "sg:province":"LA",
    "sg:tags":[
        "dentist"
    ],
    "wof:name":"Benjamin E Foster DDS",
    "wof:placetype":"venue"
},
  "geometry": {"coordinates":[-93.710679,32.443328],"type":"Point"}
}