{
  "type": "Feature",
  "properties": {
    "iso:country":"US",
    "sg:address":"2271 Military Rd",
    "sg:city":"Ringgold",
    "sg:classifiers":[
        {
            "category":"Health Services",
            "subcategory":"Optometrist",
            "type":"Services"
        }
    ],
    "sg:phone":"+1 318 894 4466",
    "sg:postcode":"71068",
    "sg:province":"LA",
    "wof:name":"Thomas Eye Clinic",
    "wof:placetype":"venue"
},
  "geometry": {"coordinates":[-93.280021,32.32302],"type":"Point"}
}