{
  "type": "Feature",
  "properties": {
    "iso:country":"US",
    "sg:address":"2752 Canal St",
    "sg:city":"New Orleans",
    "sg:classifiers":[
        {
            "category":"Professional",
            "subcategory":"Lawyer & Legal Services",
            "type":"Services"
        }
    ],
    "sg:phone":"+1 504 304 6150",
    "sg:postcode":"70119",
    "sg:province":"LA",
    "sg:tags":[
        "attorney"
    ],
    "wof:name":"Gisele Benson Rose Law Office",
    "wof:placetype":"venue"
},
  "geometry": {"coordinates":[-90.08772500000001,29.965537],"type":"Point"}
}