{
  "type": "Feature",
  "properties": {
    "iso:country":"US",
    "sg:address":"1603 N Morrison Blvd",
    "sg:city":"Hammond",
    "sg:classifiers":[
        {
            "category":"Restaurant",
            "type":"Food & Drink"
        }
    ],
    "sg:menulink":"http://www.allmenus.com/la/hammond/66340-pizza-inn/menu/",
    "sg:phone":"+1 985 345 4817",
    "sg:postcode":"70401",
    "sg:province":"LA",
    "sg:tags":[
        "american",
        "pizza"
    ],
    "wof:name":"Pizza Inn",
    "wof:placetype":"venue"
},
  "geometry": {"coordinates":[-90.482739,30.515252],"type":"Point"}
}