{
  "type": "Feature",
  "properties": {
    "iso:country":"US",
    "sg:address":"4167 Hillias Rd",
    "sg:city":"Jennings",
    "sg:classifiers":[
        {
            "category":"Shopping",
            "type":"Retail Goods"
        }
    ],
    "sg:phone":"+1 337 616 3900",
    "sg:postcode":"70546",
    "sg:province":"LA",
    "sg:tags":[
        "wedding",
        "supply"
    ],
    "wof:name":"Uniquely Yours",
    "wof:placetype":"venue"
},
  "geometry": {"coordinates":[-92.685196,30.158972],"type":"Point"}
}