{
  "type": "Feature",
  "properties": {
    "addr:full":"147 Melvin Ct Houma LA 70363",
    "addr:housenumber":"147",
    "addr:postcode":"70363",
    "addr:street":"Melvin Ct",
    "iso:country":"US",
    "sg:address":"147 Melvin Ct",
    "sg:city":"Houma",
    "sg:classifiers":[
        {
            "category":"Health Services",
            "subcategory":"Hospital",
            "type":"Services"
        }
    ],
    "sg:phone":"+1 985 876 7587",
    "sg:postcode":"70363",
    "sg:province":"LA",
    "sg:tags":[
        "general"
    ],
    "wof:name":"Cmjt Medical Services Inc",
    "wof:placetype":"venue"
},
  "geometry": {"coordinates":[-90.735536,29.536016],"type":"Point"}
}