{
  "type": "Feature",
  "properties": {
    "iso:country":"US",
    "sg:address":"2500 Sycamore St",
    "sg:city":"Monroe",
    "sg:classifiers":[
        {
            "category":"Sports & Exercise",
            "subcategory":"Golf",
            "type":"Entertainment"
        }
    ],
    "sg:phone":"+1 318 329 2457",
    "sg:postcode":"71201",
    "sg:province":"LA",
    "sg:tags":[
        "course"
    ],
    "wof:name":"Monroe Municipal Golf Course",
    "wof:placetype":"venue"
},
  "geometry": {"coordinates":[-92.130561,32.523567],"type":"Point"}
}