{
  "type": "Feature",
  "properties": {
    "iso:country":"US",
    "sg:address":"2747 Arkansas Rd",
    "sg:city":"West Monroe",
    "sg:classifiers":[
        {
            "category":"Autos & Motor Vehicles",
            "subcategory":"Automobile Sales",
            "type":"Retail Goods"
        }
    ],
    "sg:phone":"+1 318 397 7325",
    "sg:postcode":"71291",
    "sg:province":"LA",
    "sg:tags":[
        "car",
        "dealer"
    ],
    "wof:name":"BRB Auto Sales",
    "wof:placetype":"venue"
},
  "geometry": {"coordinates":[-92.19756700000001,32.535941],"type":"Point"}
}