{
  "type": "Feature",
  "properties": {
    "addr:full":"2661 North Blvd Baton Rouge LA 70806",
    "addr:housenumber":"2661",
    "addr:postcode":"70806",
    "addr:street":"North Blvd",
    "iso:country":"US",
    "sg:address":"2661 North Blvd",
    "sg:city":"Baton Rouge",
    "sg:classifiers":[
        {
            "category":"Health Services",
            "subcategory":"Doctor",
            "type":"Services"
        }
    ],
    "sg:phone":"+1 225 387 5777",
    "sg:postcode":"70806",
    "sg:province":"LA",
    "sg:tags":[
        "clinic"
    ],
    "wof:name":"FMSNA Dialysis Ctr",
    "wof:placetype":"venue"
},
  "geometry": {"coordinates":[-91.161046,30.448106],"type":"Point"}
}