{
  "type": "Feature",
  "properties": {
    "iso:country":"US",
    "sg:address":"66 Fontainebleau Dr",
    "sg:city":"New Orleans",
    "sg:classifiers":[
        {
            "category":"Organizations",
            "subcategory":"Religious Organization",
            "type":"Services"
        }
    ],
    "sg:phone":"+1 504 866 9335",
    "sg:postcode":"70125",
    "sg:province":"LA",
    "sg:tags":[
        "monastery",
        "convent"
    ],
    "wof:name":"Dominican Sisters",
    "wof:placetype":"venue"
},
  "geometry": {"coordinates":[-90.115162,29.954343],"type":"Point"}
}