{
  "type": "Feature",
  "properties": {
    "iso:country":"US",
    "sg:address":"5765 Hwy 56",
    "sg:city":"Chauvin",
    "sg:classifiers":[
        {
            "category":"Home & Garden",
            "subcategory":"Hardware",
            "type":"Retail Goods"
        }
    ],
    "sg:phone":"+1 985 594 8155",
    "sg:postcode":"70344",
    "sg:province":"LA",
    "wof:name":"Barre Hardware & Marine Supply",
    "wof:placetype":"venue"
},
  "geometry": {"coordinates":[-90.602643,29.421516],"type":"Point"}
}