{
  "type": "Feature",
  "properties": {
    "iso:country":"US",
    "sg:address":"616 T W Barker Dr",
    "sg:city":"Franklinton",
    "sg:classifiers":[
        {
            "category":"Education",
            "subcategory":"School",
            "type":"Public Place"
        }
    ],
    "sg:phone":"+1 985 839 6218",
    "sg:postcode":"70438",
    "sg:province":"LA",
    "wof:name":"Franklinton Vocational Ed Ctr",
    "wof:placetype":"venue"
},
  "geometry": {"coordinates":[-90.14546,30.855008],"type":"Point"}
}