{
  "type": "Feature",
  "properties": {
    "iso:country":"US",
    "sg:address":"207 N Broad St",
    "sg:city":"New Orleans",
    "sg:classifiers":[
        {
            "category":"Personal",
            "type":"Services"
        }
    ],
    "sg:phone":"+1 504 821 1006",
    "sg:postcode":"70119",
    "sg:province":"LA",
    "wof:name":"J & L Formal Wear",
    "wof:placetype":"venue"
},
  "geometry": {"coordinates":[-90.08602999999999,29.96733],"type":"Point"}
}