{
  "type": "Feature",
  "properties": {
    "iso:country":"US",
    "sg:address":"660 San Antonio Ave",
    "sg:city":"Many",
    "sg:classifiers":[
        {
            "category":"Shopping",
            "subcategory":"Clothing, Apparel, & Fashions",
            "type":"Retail Goods"
        }
    ],
    "sg:phone":"+1 318 256 3838",
    "sg:postcode":"71449",
    "sg:province":"LA",
    "wof:name":"J B's Tots Teens & Ladies",
    "wof:placetype":"venue"
},
  "geometry": {"coordinates":[-93.48456299999999,31.568275],"type":"Point"}
}