{
  "type": "Feature",
  "properties": {
    "iso:country":"US",
    "sg:address":"4244 Hwy 22 E",
    "sg:city":"Mandeville",
    "sg:classifiers":[
        {
            "category":"Shopping",
            "subcategory":"Department Store",
            "type":"Retail Goods"
        }
    ],
    "sg:phone":"+1 985 674 9778",
    "sg:postcode":"70471",
    "sg:province":"LA",
    "sg:tags":[
        "shop"
    ],
    "wof:name":"Dollar Stop",
    "wof:placetype":"venue"
},
  "geometry": {"coordinates":[-90.140688,30.407211],"type":"Point"}
}