{
  "type": "Feature",
  "properties": {
    "iso:country":"US",
    "sg:address":"4408 S Carrollton Ave",
    "sg:city":"New Orleans",
    "sg:classifiers":[
        {
            "category":"Social Services",
            "type":"Services"
        }
    ],
    "sg:phone":"+1 504 484 6810",
    "sg:postcode":"70119",
    "sg:province":"LA",
    "sg:tags":[
        "organization",
        "welfare"
    ],
    "wof:name":"Carrollton Community Home",
    "wof:placetype":"venue"
},
  "geometry": {"coordinates":[-90.103195,29.971882],"type":"Point"}
}