{
  "type": "Feature",
  "properties": {
    "iso:country":"US",
    "sg:address":"630 W 1st St",
    "sg:city":"Delhi",
    "sg:classifiers":[
        {
            "category":"Health Services",
            "subcategory":"Clinic",
            "type":"Services"
        }
    ],
    "sg:phone":"+1 318 878 4510",
    "sg:postcode":"71232",
    "sg:province":"LA",
    "sg:tags":[
        "home"
    ],
    "wof:name":"All About You",
    "wof:placetype":"venue"
},
  "geometry": {"coordinates":[-91.49855599999999,32.457529],"type":"Point"}
}