{
  "type": "Feature",
  "properties": {
    "iso:country":"US",
    "sg:address":"13340 Florida Blvd",
    "sg:city":"Livingston",
    "sg:classifiers":[
        {
            "category":"Banks & Credit Unions",
            "subcategory":"Financial Services",
            "type":"Services"
        }
    ],
    "sg:phone":"+1 225 686 2252",
    "sg:postcode":"70785",
    "sg:province":"LA",
    "sg:tags":[
        "company",
        "holding"
    ],
    "wof:name":"Jah Enterprises Inc",
    "wof:placetype":"venue"
},
  "geometry": {"coordinates":[-90.86223,30.4881],"type":"Point"}
}