{
  "type": "Feature",
  "properties": {
    "iso:country":"US",
    "sg:address":"2909 Cameron St",
    "sg:city":"Monroe",
    "sg:classifiers":[
        {
            "category":"Wholesale",
            "subcategory":"Stationery",
            "type":"Manufacturing & Wholesale Goods"
        }
    ],
    "sg:phone":"+1 318 388 0666",
    "sg:postcode":"71201",
    "sg:province":"LA",
    "sg:tags":[
        "mill",
        "paper",
        "broker",
        "representative"
    ],
    "wof:name":"Box Board Supply Inc",
    "wof:placetype":"venue"
},
  "geometry": {"coordinates":[-92.09061800000001,32.53204],"type":"Point"}
}