{
  "type": "Feature",
  "properties": {
    "iso:country":"US",
    "sg:address":"5104 Freret St",
    "sg:city":"New Orleans",
    "sg:classifiers":[
        {
            "category":"Home & Garden",
            "subcategory":"Building Materials",
            "type":"Retail Goods"
        }
    ],
    "sg:phone":"+1 504 894 0400",
    "sg:postcode":"70115",
    "sg:province":"LA",
    "sg:tags":[
        "paint"
    ],
    "wof:name":"Freret Paint Inc",
    "wof:placetype":"venue"
},
  "geometry": {"coordinates":[-90.110179,29.934925],"type":"Point"}
}