{
  "type": "Feature",
  "properties": {
    "iso:country":"US",
    "sg:address":"5633 Government St",
    "sg:city":"Baton Rouge",
    "sg:classifiers":[
        {
            "category":"Professional",
            "type":"Services"
        }
    ],
    "sg:phone":"+1 225 923 3300",
    "sg:postcode":"70806",
    "sg:province":"LA",
    "sg:tags":[
        "parliamentarian"
    ],
    "wof:name":"C Alan Jennings",
    "wof:placetype":"venue"
},
  "geometry": {"coordinates":[-91.132334,30.444726],"type":"Point"}
}