{
  "type": "Feature",
  "properties": {
    "iso:country":"US",
    "sg:address":"6901 Memphis St",
    "sg:city":"New Orleans",
    "sg:classifiers":[
        {
            "category":"Health Services",
            "subcategory":"Clinic",
            "type":"Services"
        }
    ],
    "sg:phone":"+1 504 282 8369",
    "sg:postcode":"70124",
    "sg:province":"LA",
    "wof:name":"Certified Healthcare",
    "wof:placetype":"venue"
},
  "geometry": {"coordinates":[-90.10427199999999,30.017455],"type":"Point"}
}