{
  "type": "Feature",
  "properties": {
    "iso:country":"US",
    "sg:address":"227 Lee Ln",
    "sg:city":"Covington",
    "sg:classifiers":[
        {
            "category":"Shopping",
            "subcategory":"Clothing, Apparel, & Fashions",
            "type":"Retail Goods"
        }
    ],
    "sg:phone":"+1 985 893 1013",
    "sg:postcode":"70433",
    "sg:province":"LA",
    "wof:name":"Vie Paysanne",
    "wof:placetype":"venue"
},
  "geometry": {"coordinates":[-90.091802,30.475945],"type":"Point"}
}