{
  "type": "Feature",
  "properties": {
    "iso:country":"US",
    "sg:address":"2222 Saint Claude Ave",
    "sg:city":"New Orleans",
    "sg:classifiers":[
        {
            "category":"Food & Beverages",
            "subcategory":"Groceries & Convenience Stores",
            "type":"Retail Goods"
        }
    ],
    "sg:phone":"+1 504 943 8891",
    "sg:postcode":"70117",
    "sg:province":"LA",
    "wof:name":"Robert Fresh Market",
    "wof:placetype":"venue"
},
  "geometry": {"coordinates":[-90.056099,29.9685],"type":"Point"}
}