{
  "type": "Feature",
  "properties": {
    "addr:full":"191 Mes Amis Ln Chauvin LA 70344",
    "addr:housenumber":"191",
    "addr:postcode":"70344",
    "addr:street":"Mes Amis Ln Chauvin",
    "iso:country":"US",
    "sg:address":"191 Mes Amis Ln",
    "sg:city":"Chauvin",
    "sg:classifiers":[
        {
            "category":"Building & Trades",
            "subcategory":"Construction",
            "type":"Services"
        }
    ],
    "sg:phone":"+1 985 594 6052",
    "sg:postcode":"70344",
    "sg:province":"LA",
    "sg:tags":[
        "sandblasting"
    ],
    "wof:name":"Jubilee Enterprises Inc",
    "wof:placetype":"venue"
},
  "geometry": {"coordinates":[-90.595221,29.516281],"type":"Point"}
}