{
  "type": "Feature",
  "properties": {
    "iso:country":"US",
    "sg:address":"403 Bolton Ave",
    "sg:city":"Alexandria",
    "sg:classifiers":[
        {
            "category":"Local Transit",
            "type":"Transportation"
        }
    ],
    "sg:phone":"+1 318 445 4524",
    "sg:postcode":"71301",
    "sg:province":"LA",
    "sg:tags":[
        "bus",
        "line"
    ],
    "wof:name":"Continental Bus Ctr",
    "wof:placetype":"venue"
},
  "geometry": {"coordinates":[-92.456159,31.306323],"type":"Point"}
}