{
  "type": "Feature",
  "properties": {
    "iso:country":"US",
    "sg:address":"697 State Rte 182",
    "sg:city":"Sunset",
    "sg:classifiers":[
        {
            "category":"Wholesale",
            "subcategory":"Motor Vehicles",
            "type":"Manufacturing & Wholesale Goods"
        }
    ],
    "sg:phone":"+1 337 662 2242",
    "sg:postcode":"70584",
    "sg:province":"LA",
    "sg:tags":[
        "automobile",
        "truck",
        "broker"
    ],
    "wof:name":"Coble Enterprises",
    "wof:placetype":"venue"
},
  "geometry": {"coordinates":[-92.03645299999999,30.390561],"type":"Point"}
}