{
  "type": "Feature",
  "properties": {
    "iso:country":"US",
    "sg:address":"14281 Chef Menteur Hwy",
    "sg:city":"New Orleans",
    "sg:classifiers":[
        {
            "category":"Health Services",
            "subcategory":"Chiropractor",
            "type":"Services"
        }
    ],
    "sg:phone":"+1 504 254 0911",
    "sg:postcode":"70129",
    "sg:province":"LA",
    "wof:name":"Spinal Health Clinic",
    "wof:placetype":"venue"
},
  "geometry": {"coordinates":[-89.91343500000001,30.035822],"type":"Point"}
}