{
  "type": "Feature",
  "properties": {
    "iso:country":"US",
    "sg:address":"409 Faircloth St",
    "sg:city":"Colfax",
    "sg:classifiers":[
        {
            "category":"Organizations",
            "subcategory":"Religious Organization",
            "type":"Services"
        }
    ],
    "sg:phone":"+1 318 627 3297",
    "sg:postcode":"71417",
    "sg:province":"LA",
    "sg:tags":[
        "church"
    ],
    "wof:name":"Colfax Baptist Church",
    "wof:placetype":"venue"
},
  "geometry": {"coordinates":[-92.711806,31.519778],"type":"Point"}
}