{
  "type": "Feature",
  "properties": {
    "iso:country":"US",
    "sg:address":"108 Sonnier Rd",
    "sg:city":"Carencro",
    "sg:classifiers":[
        {
            "category":"Autos & Motor Vehicles",
            "subcategory":"Motorcycle Sales",
            "type":"Retail Goods"
        }
    ],
    "sg:phone":"+1 337 896 3411",
    "sg:postcode":"70520",
    "sg:province":"LA",
    "sg:tags":[
        "car",
        "golf",
        "cart"
    ],
    "wof:name":"Cajun Carts",
    "wof:placetype":"venue"
},
  "geometry": {"coordinates":[-92.016177,30.32067],"type":"Point"}
}