{
  "type": "Feature",
  "properties": {
    "addr:full":"1305 W Causeway Approach Mandeville LA 70471",
    "addr:housenumber":"1305",
    "addr:postcode":"70471",
    "addr:street":"W Causeway Approach",
    "iso:country":"US",
    "sg:address":"1305 W Causeway Approach",
    "sg:city":"Mandeville",
    "sg:classifiers":[
        {
            "category":"Health Services",
            "subcategory":"Nursing And Care Facility",
            "type":"Services"
        }
    ],
    "sg:phone":"+1 985 892 2252",
    "sg:postcode":"70471",
    "sg:province":"LA",
    "sg:tags":[
        "home",
        "retirement",
        "community"
    ],
    "wof:name":"Beau L'Age",
    "wof:placetype":"venue"
},
  "geometry": {"coordinates":[-90.100678,30.391645],"type":"Point"}
}