{
  "type": "Feature",
  "properties": {
    "addr:full":"2833 Crater Lake Dr Baton Rouge LA 70814",
    "addr:housenumber":"2833",
    "addr:postcode":"70814",
    "addr:street":"Crater Lake Dr",
    "iso:country":"US",
    "sg:address":"2833 Crater Lake Dr",
    "sg:city":"Baton Rouge",
    "sg:classifiers":[
        {
            "category":"Building & Trades",
            "subcategory":"Construction",
            "type":"Services"
        }
    ],
    "sg:phone":"+1 225 216 3466",
    "sg:postcode":"70814",
    "sg:province":"LA",
    "sg:tags":[
        "fire",
        "restoration",
        "damage"
    ],
    "wof:name":"Professional Restoration Contr",
    "wof:placetype":"venue"
},
  "geometry": {"coordinates":[-91.087492,30.475751],"type":"Point"}
}