{
  "type": "Feature",
  "properties": {
    "iso:country":"US",
    "sg:address":"510 Guilbeau Rd",
    "sg:city":"Lafayette",
    "sg:classifiers":[
        {
            "category":"Professional",
            "subcategory":"Computer Services",
            "type":"Services"
        }
    ],
    "sg:phone":"+1 337 993 0437",
    "sg:postcode":"70506",
    "sg:province":"LA",
    "sg:tags":[
        "website",
        "design"
    ],
    "wof:name":"Efficient Technologies",
    "wof:placetype":"venue"
},
  "geometry": {"coordinates":[-92.069394,30.197854],"type":"Point"}
}