{
  "type": "Feature",
  "properties": {
    "iso:country":"US",
    "sg:address":"9751 Buttercup Dr",
    "sg:city":"Baton Rouge",
    "sg:classifiers":[
        {
            "category":"Professional",
            "type":"Services"
        }
    ],
    "sg:phone":"+1 225 292 5456",
    "sg:postcode":"70809",
    "sg:province":"LA",
    "wof:name":"Frank Schroeder",
    "wof:placetype":"venue"
},
  "geometry": {"coordinates":[-91.07438,30.383066],"type":"Point"}
}