{
  "type": "Feature",
  "properties": {
    "iso:country":"US",
    "sg:address":"10 Chateau Trianon Dr",
    "sg:city":"Kenner",
    "sg:classifiers":[
        {
            "category":"Insurance",
            "subcategory":"Insurance Agent",
            "type":"Services"
        }
    ],
    "sg:phone":"+1 504 468 8997",
    "sg:postcode":"70065",
    "sg:province":"LA",
    "wof:name":"Fringe Benefit Planners",
    "wof:placetype":"venue"
},
  "geometry": {"coordinates":[-90.248454,30.028937],"type":"Point"}
}