{
  "type": "Feature",
  "properties": {
    "iso:country":"US",
    "sg:address":"21563 Katina Ln",
    "sg:city":"Ponchatoula",
    "sg:classifiers":[
        {
            "category":"Retail",
            "subcategory":"Repair Shop",
            "type":"Services"
        }
    ],
    "sg:phone":"+1 985 386 0931",
    "sg:postcode":"70454",
    "sg:province":"LA",
    "sg:tags":[
        "welding"
    ],
    "wof:name":"Klein Fabricators",
    "wof:placetype":"venue"
},
  "geometry": {"coordinates":[-90.370239,30.45323],"type":"Point"}
}