{
  "type": "Feature",
  "properties": {
    "iso:country":"US",
    "sg:address":"2766 Belle Chasse Hwy",
    "sg:city":"Terrytown",
    "sg:classifiers":[
        {
            "category":"Restaurant",
            "type":"Food & Drink"
        }
    ],
    "sg:phone":"+1 504 393 7766",
    "sg:postcode":"70056",
    "sg:province":"LA",
    "wof:name":"Cucos Mexican Cafe",
    "wof:placetype":"venue"
},
  "geometry": {"coordinates":[-90.04749,29.901249],"type":"Point"}
}