{
  "type": "Feature",
  "properties": {
    "iso:country":"US",
    "sg:address":"5907 King St",
    "sg:city":"Shreveport",
    "sg:classifiers":[
        {
            "category":"Organizations",
            "subcategory":"Religious Organization",
            "type":"Services"
        }
    ],
    "sg:phone":"+1 318 686 0507",
    "sg:postcode":"71129",
    "sg:province":"LA",
    "sg:tags":[
        "church"
    ],
    "wof:name":"Fellowship Assembly Of Christ",
    "wof:placetype":"venue"
},
  "geometry": {"coordinates":[-93.857258,32.412432],"type":"Point"}
}