{
  "type": "Feature",
  "properties": {
    "addr:full":"717 21st St Gretna LA 70053",
    "addr:housenumber":"717",
    "addr:postcode":"70053",
    "addr:street":"21St St",
    "iso:country":"US",
    "sg:address":"717 21st St",
    "sg:city":"Gretna",
    "sg:classifiers":[
        {
            "category":"Personal",
            "subcategory":"Beauty Salon",
            "type":"Services"
        }
    ],
    "sg:phone":"+1 504 263 0399",
    "sg:postcode":"70053",
    "sg:province":"LA",
    "sg:tags":[
        "hair"
    ],
    "wof:name":"Blessed Barber Shop",
    "wof:placetype":"venue"
},
  "geometry": {"coordinates":[-90.053658,29.902998],"type":"Point"}
}