{
  "type": "Feature",
  "properties": {
    "addr:full":"651 Old Spanish Trl Slidell LA 70458",
    "addr:housenumber":"651",
    "addr:postcode":"70458",
    "addr:street":"Old Spanish Trl",
    "iso:country":"US",
    "sg:address":"651 Old Spanish Trl",
    "sg:city":"Slidell",
    "sg:classifiers":[
        {
            "category":"Retail",
            "subcategory":"Repair Shop",
            "type":"Services"
        }
    ],
    "sg:phone":"+1 985 726 0001",
    "sg:postcode":"70458",
    "sg:province":"LA",
    "sg:tags":[
        "repairing",
        "aids",
        "hearing"
    ],
    "wof:name":"Lifetime Hearing Aid Svc",
    "wof:placetype":"venue"
},
  "geometry": {"coordinates":[-89.781847,30.263083],"type":"Point"}
}