{
  "type": "Feature",
  "properties": {
    "iso:country":"US",
    "sg:address":"4882 Hwy 1",
    "sg:city":"Mathews",
    "sg:classifiers":[
        {
            "category":"Utilities",
            "subcategory":"Mobile Phone",
            "type":"Services"
        }
    ],
    "sg:phone":"+1 985 532 0000",
    "sg:postcode":"70390",
    "sg:province":"LA",
    "sg:tags":[
        "telephone",
        "cellular"
    ],
    "wof:name":"Allied Communications",
    "wof:placetype":"venue"
},
  "geometry": {"coordinates":[-91.028655,29.945442],"type":"Point"}
}