{
  "type": "Feature",
  "properties": {
    "iso:country":"US",
    "sg:address":"3613 Bayou Black Dr",
    "sg:city":"Houma",
    "sg:classifiers":[
        {
            "category":"Recreation",
            "type":"Entertainment"
        }
    ],
    "sg:phone":"+1 985 879 1087",
    "sg:postcode":"70360",
    "sg:province":"LA",
    "sg:tags":[
        "stable"
    ],
    "wof:name":"Diamond J Farms Inc",
    "wof:placetype":"venue"
},
  "geometry": {"coordinates":[-90.77824,29.561128],"type":"Point"}
}