{
  "type": "Feature",
  "properties": {
    "iso:country":"US",
    "sg:address":"3403 S Macarthur Dr",
    "sg:city":"Alexandria",
    "sg:classifiers":[
        {
            "category":"Shopping",
            "type":"Retail Goods"
        }
    ],
    "sg:phone":"+1 318 308 4689",
    "sg:postcode":"71302",
    "sg:province":"LA",
    "sg:tags":[
        "dry",
        "ice"
    ],
    "wof:name":"B's Dry Ice",
    "wof:placetype":"venue"
},
  "geometry": {"coordinates":[-92.452663,31.264725],"type":"Point"}
}