{
  "type": "Feature",
  "properties": {
    "addr:full":"134 Angelina Ln Garyville LA 70051",
    "addr:housenumber":"134",
    "addr:postcode":"70051",
    "addr:street":"Angelina Ln",
    "iso:country":"US",
    "sg:address":"134 Angelina Ln",
    "sg:city":"Garyville",
    "sg:classifiers":[
        {
            "category":"Freight",
            "type":"Transportation"
        }
    ],
    "sg:phone":"+1 985 535 1121",
    "sg:postcode":"70051",
    "sg:province":"LA",
    "sg:tags":[
        "trucking"
    ],
    "wof:name":"Davenport Trucking",
    "wof:placetype":"venue"
},
  "geometry": {"coordinates":[-90.627214,30.07658],"type":"Point"}
}