{
  "type": "Feature",
  "properties": {
    "iso:country":"US",
    "sg:address":"6550 Sevenoaks Ave",
    "sg:city":"Baton Rouge",
    "sg:classifiers":[
        {
            "category":"Education",
            "subcategory":"School",
            "type":"Public Place"
        }
    ],
    "sg:phone":"+1 225 929 8600",
    "sg:postcode":"70806",
    "sg:province":"LA",
    "sg:tags":[
        "academic",
        "special"
    ],
    "sg:website":"www.ebrschools.org",
    "wof:name":"Ebr Parish Pupil Appraisal",
    "wof:placetype":"venue"
},
  "geometry": {"coordinates":[-91.122433,30.438808],"type":"Point"}
}