{
  "type": "Feature",
  "properties": {
    "iso:country":"US",
    "sg:address":"601 Terry Pkwy",
    "sg:city":"Gretna",
    "sg:classifiers":[
        {
            "category":"Restaurant",
            "type":"Food & Drink"
        }
    ],
    "sg:menulink":"http://www.allmenus.com/la/golden-meadow/131989-subway/menu/",
    "sg:phone":"+1 504 366 3777",
    "sg:postcode":"70056",
    "sg:province":"LA",
    "sg:tags":[
        "american",
        "sandwich"
    ],
    "wof:name":"Subway",
    "wof:placetype":"venue"
},
  "geometry": {"coordinates":[-90.029889,29.903359],"type":"Point"}
}