{
  "type": "Feature",
  "properties": {
    "iso:country":"US",
    "sg:address":"5930 Frontage Rd",
    "sg:city":"Monroe",
    "sg:classifiers":[
        {
            "category":"Manufacturing",
            "subcategory":"Metals",
            "type":"Manufacturing & Wholesale Goods"
        }
    ],
    "sg:phone":"+1 318 343 3900",
    "sg:postcode":"71202",
    "sg:province":"LA",
    "wof:name":"Metal Mart",
    "wof:placetype":"venue"
},
  "geometry": {"coordinates":[-92.047095,32.493387],"type":"Point"}
}