{
  "type": "Feature",
  "properties": {
    "addr:full":"1856 Jackson St Alexandria LA 71301",
    "addr:housenumber":"1856",
    "addr:postcode":"71301",
    "addr:street":"Jackson St",
    "iso:country":"US",
    "sg:address":"1856 Jackson St",
    "sg:city":"Alexandria",
    "sg:classifiers":[
        {
            "category":"Organizations",
            "subcategory":"Religious Organization",
            "type":"Services"
        }
    ],
    "sg:phone":"+1 318 442 3047",
    "sg:postcode":"71301",
    "sg:province":"LA",
    "sg:tags":[
        "church"
    ],
    "wof:name":"Church Of Christ",
    "wof:placetype":"venue"
},
  "geometry": {"coordinates":[-92.45707400000001,31.302493],"type":"Point"}
}