{
  "type": "Feature",
  "properties": {
    "iso:country":"US",
    "sg:address":"3436 Mills St",
    "sg:city":"Carencro",
    "sg:classifiers":[
        {
            "category":"Retail",
            "subcategory":"Auto Repair",
            "type":"Services"
        }
    ],
    "sg:phone":"+1 337 896 6619",
    "sg:postcode":"70520",
    "sg:province":"LA",
    "sg:tags":[
        "repairing",
        "automobile"
    ],
    "wof:name":"Thibodeaux Automotive & Small",
    "wof:placetype":"venue"
},
  "geometry": {"coordinates":[-92.09215,30.302268],"type":"Point"}
}