{
  "type": "Feature",
  "properties": {
    "iso:country":"US",
    "sg:address":"2538 Fournerat Rd",
    "sg:city":"Eunice",
    "sg:classifiers":[
        {
            "category":"Retail",
            "subcategory":"Auto Repair",
            "type":"Services"
        }
    ],
    "sg:phone":"+1 337 457 5532",
    "sg:postcode":"70535",
    "sg:province":"LA",
    "sg:tags":[
        "engine",
        "truck"
    ],
    "wof:name":"Moreaus Repair Service Inc",
    "wof:placetype":"venue"
},
  "geometry": {"coordinates":[-92.49900599999999,30.465948],"type":"Point"}
}