{
  "type": "Feature",
  "properties": {
    "addr:full":"814 Jordan St Shreveport LA 71101",
    "addr:housenumber":"814",
    "addr:postcode":"71101",
    "addr:street":"Jordan St",
    "iso:country":"US",
    "sg:address":"814 Jordan St",
    "sg:city":"Shreveport",
    "sg:classifiers":[
        {
            "category":"Banks & Credit Unions",
            "subcategory":"Bank",
            "type":"Services"
        }
    ],
    "sg:phone":"+1 318 674 2523",
    "sg:postcode":"71101",
    "sg:province":"LA",
    "wof:name":"Hibernia National Bank",
    "wof:placetype":"venue"
},
  "geometry": {"coordinates":[-93.746517,32.498227],"type":"Point"}
}