{
  "type": "Feature",
  "properties": {
    "addr:full":"2134 E Texas St Bossier City LA 71111",
    "addr:housenumber":"2134",
    "addr:postcode":"71111",
    "addr:street":"E Texas St",
    "iso:country":"US",
    "sg:address":"2134 E Texas St",
    "sg:city":"Bossier City",
    "sg:classifiers":[
        {
            "category":"Retail",
            "subcategory":"Auto Repair",
            "type":"Services"
        }
    ],
    "sg:phone":"+1 318 742 7754",
    "sg:postcode":"71111",
    "sg:province":"LA",
    "sg:tags":[
        "repairing",
        "automobile"
    ],
    "sg:website":"www.transmissioncenter.net",
    "wof:name":"Performance Automotive Ctr",
    "wof:placetype":"venue"
},
  "geometry": {"coordinates":[-93.71933300000001,32.528141],"type":"Point"}
}