{
  "type": "Feature",
  "properties": {
    "addr:full":"440 Newton St New Orleans LA 70114",
    "addr:housenumber":"440",
    "addr:postcode":"70114",
    "addr:street":"Newton St",
    "iso:country":"US",
    "sg:address":"440 Newton St",
    "sg:city":"New Orleans",
    "sg:classifiers":[
        {
            "category":"Restaurant",
            "type":"Food & Drink"
        }
    ],
    "sg:phone":"+1 504 361 4007",
    "sg:postcode":"70114",
    "sg:province":"LA",
    "wof:name":"Rita's Bar & Soul Food",
    "wof:placetype":"venue"
},
  "geometry": {"coordinates":[-90.051412,29.945563],"type":"Point"}
}