{
  "type": "Feature",
  "properties": {
    "iso:country":"US",
    "sg:address":"5035 Airline Hwy",
    "sg:city":"Baton Rouge",
    "sg:classifiers":[
        {
            "category":"Shopping",
            "subcategory":"Bicycles & Sporting Goods",
            "type":"Retail Goods"
        }
    ],
    "sg:phone":"+1 225 355 9807",
    "sg:postcode":"70805",
    "sg:province":"LA",
    "sg:tags":[
        "bait",
        "fishing"
    ],
    "wof:name":"Sportsman's Haven",
    "wof:placetype":"venue"
},
  "geometry": {"coordinates":[-91.13984000000001,30.508463],"type":"Point"}
}