{
  "type": "Feature",
  "properties": {
    "addr:full":"4927 Bloomfield St Jefferson LA 70121",
    "addr:housenumber":"4927",
    "addr:postcode":"70121",
    "addr:street":"Bloomfield St",
    "iso:country":"US",
    "sg:address":"4927 Bloomfield St",
    "sg:city":"Jefferson",
    "sg:classifiers":[
        {
            "category":"Wholesale",
            "subcategory":"Wine & Distilled Alcoholic Beverages",
            "type":"Manufacturing & Wholesale Goods"
        }
    ],
    "sg:phone":"+1 504 736 9577",
    "sg:postcode":"70121",
    "sg:province":"LA",
    "sg:website":"www.bigasswines.com",
    "wof:name":"International Wine & Spirits",
    "wof:placetype":"venue"
},
  "geometry": {"coordinates":[-90.178889,29.960235],"type":"Point"}
}