{
  "type": "Feature",
  "properties": {
    "iso:country":"US",
    "sg:address":"301 Burgundy St",
    "sg:city":"New Orleans",
    "sg:classifiers":[
        {
            "category":"Professional",
            "subcategory":"Employment Agencies",
            "type":"Services"
        }
    ],
    "sg:phone":"+1 504 586 9313",
    "sg:postcode":"70112",
    "sg:province":"LA",
    "sg:tags":[
        "help",
        "contractor"
    ],
    "wof:name":"Black Tie Svc",
    "wof:placetype":"venue"
},
  "geometry": {"coordinates":[-90.06952699999999,29.957493],"type":"Point"}
}