{
  "type": "Feature",
  "properties": {
    "iso:country":"US",
    "sg:address":"1015 Jefferson Hwy",
    "sg:city":"Jefferson",
    "sg:classifiers":[
        {
            "category":"Shopping",
            "type":"Retail Goods"
        }
    ],
    "sg:phone":"+1 504 833 4582",
    "sg:postcode":"70121",
    "sg:province":"LA",
    "sg:tags":[
        "enforcement",
        "law",
        "supply"
    ],
    "wof:name":"Belsco Inc",
    "wof:placetype":"venue"
},
  "geometry": {"coordinates":[-90.139989,29.962732],"type":"Point"}
}