{
  "type": "Feature",
  "properties": {
    "iso:country":"US",
    "sg:address":"201 McKnight Ln",
    "sg:city":"Amite",
    "sg:classifiers":[
        {
            "category":"Farming",
            "subcategory":"Farm",
            "type":"Manufacturing & Wholesale Goods"
        }
    ],
    "sg:phone":"+1 985 748 9192",
    "sg:postcode":"70422",
    "sg:province":"LA",
    "wof:name":"Louisiana Farm Bur Appraiser",
    "wof:placetype":"venue"
},
  "geometry": {"coordinates":[-90.51657299999999,30.725071],"type":"Point"}
}