{
  "type": "Feature",
  "properties": {
    "addr:full":"7700 Earhart Blvd New Orleans LA 70125",
    "addr:housenumber":"7700",
    "addr:postcode":"70125",
    "addr:street":"Earhart Blvd",
    "iso:country":"US",
    "sg:address":"7700 Earhart Blvd",
    "sg:city":"New Orleans",
    "sg:classifiers":[
        {
            "category":"Wholesale",
            "subcategory":"Durable Goods & Equipment",
            "type":"Manufacturing & Wholesale Goods"
        }
    ],
    "sg:phone":"+1 504 861 1373",
    "sg:postcode":"70125",
    "sg:province":"LA",
    "sg:tags":[
        "environmental",
        "product"
    ],
    "wof:name":"T H Agriculture & Nutrition Co",
    "wof:placetype":"venue"
},
  "geometry": {"coordinates":[-90.11127500000001,29.958996],"type":"Point"}
}