{
  "type": "Feature",
  "properties": {
    "iso:country":"US",
    "sg:address":"6757 Brutus St",
    "sg:city":"New Orleans",
    "sg:classifiers":[
        {
            "category":"Organizations",
            "subcategory":"Religious Organization",
            "type":"Services"
        }
    ],
    "sg:phone":"+1 504 245 3838",
    "sg:postcode":"70126",
    "sg:province":"LA",
    "wof:name":"Rosedale Missionary Baptist Church",
    "wof:placetype":"venue"
},
  "geometry": {"coordinates":[-90.0093,30.010599],"type":"Point"}
}