{
  "type": "Feature",
  "properties": {
    "addr:full":"122 W Bayou Pkwy Lafayette LA 70503",
    "addr:housenumber":"122",
    "addr:postcode":"70503",
    "addr:street":"W Bayou Pkwy",
    "iso:country":"US",
    "sg:address":"122 W Bayou Pkwy",
    "sg:city":"Lafayette",
    "sg:classifiers":[
        {
            "category":"Real Estate",
            "subcategory":"Real Estate Agent",
            "type":"Services"
        }
    ],
    "sg:phone":"+1 337 291 9222",
    "sg:postcode":"70503",
    "sg:province":"LA",
    "wof:name":"Teal Realty",
    "wof:placetype":"venue"
},
  "geometry": {"coordinates":[-92.02556,30.196003],"type":"Point"}
}