{
  "type": "Feature",
  "properties": {
    "iso:country":"US",
    "sg:address":"1029 Bourbon St",
    "sg:city":"New Orleans",
    "sg:classifiers":[
        {
            "category":"Real Estate",
            "subcategory":"Real Estate Agent",
            "type":"Services"
        }
    ],
    "sg:phone":"+1 504 523 4277",
    "sg:postcode":"70116",
    "sg:province":"LA",
    "wof:name":"Gurry Brothers Supply Corp",
    "wof:placetype":"venue"
},
  "geometry": {"coordinates":[-90.062995,29.961677],"type":"Point"}
}