{
  "type": "Feature",
  "properties": {
    "addr:full":"4108 Highway 90 E Broussard LA 70518",
    "addr:housenumber":"4108",
    "addr:postcode":"70518",
    "addr:street":"Highway 90 E",
    "iso:country":"US",
    "sg:address":"4108 Highway 90 E",
    "sg:city":"Broussard",
    "sg:classifiers":[
        {
            "category":"Food & Beverages",
            "subcategory":"Groceries & Convenience Stores",
            "type":"Retail Goods"
        }
    ],
    "sg:phone":"+1 337 837 4013",
    "sg:postcode":"70518",
    "sg:province":"LA",
    "wof:name":"Shop Rite Grocery Inc Number 48",
    "wof:placetype":"venue"
},
  "geometry": {"coordinates":[-91.949699,30.1495],"type":"Point"}
}