{
  "type": "Feature",
  "properties": {
    "iso:country":"US",
    "sg:address":"3715 Youree Dr",
    "sg:city":"Shreveport",
    "sg:classifiers":[
        {
            "category":"Organizations",
            "subcategory":"Religious Organization",
            "type":"Services"
        }
    ],
    "sg:phone":"+1 318 861 0586",
    "sg:postcode":"71105",
    "sg:province":"LA",
    "sg:tags":[
        "church"
    ],
    "sg:website":"www.broadmoorumc.org",
    "wof:name":"Broadmoor United Methodist Chr",
    "wof:placetype":"venue"
},
  "geometry": {"coordinates":[-93.722025,32.470424],"type":"Point"}
}