{
  "type": "Feature",
  "properties": {
    "addr:full":"5023 Windfall Ct Baton Rouge LA 70812",
    "addr:housenumber":"5023",
    "addr:postcode":"70812",
    "addr:street":"Windfall Ct",
    "iso:country":"US",
    "sg:address":"5023 Windfall Ct",
    "sg:city":"Baton Rouge",
    "sg:classifiers":[
        {
            "category":"Building & Trades",
            "subcategory":"Construction",
            "type":"Services"
        }
    ],
    "sg:phone":"+1 225 355 8012",
    "sg:postcode":"70812",
    "sg:province":"LA",
    "sg:tags":[
        "contractor"
    ],
    "wof:name":"Carey Woods Jr Masonry",
    "wof:placetype":"venue"
},
  "geometry": {"coordinates":[-91.112272,30.49711],"type":"Point"}
}