{
  "type": "Feature",
  "properties": {
    "iso:country":"US",
    "sg:address":"28832 Mary Kinchen Rd",
    "sg:city":"Albany",
    "sg:classifiers":[
        {
            "category":"Social Services",
            "type":"Services"
        }
    ],
    "sg:phone":"+1 225 209 1003",
    "sg:postcode":"70711",
    "sg:province":"LA",
    "sg:tags":[
        "organization",
        "welfare"
    ],
    "wof:name":"Tri-Parish Childcare Assn-LA",
    "wof:placetype":"venue"
},
  "geometry": {"coordinates":[-90.601848,30.566324],"type":"Point"}
}