{
  "type": "Feature",
  "properties": {
    "addr:full":"10689 Perkins Rd Baton Rouge LA 70810",
    "addr:housenumber":"10689",
    "addr:postcode":"70810",
    "addr:street":"Perkins Rd",
    "iso:country":"US",
    "sg:address":"10689 Perkins Rd",
    "sg:city":"Baton Rouge",
    "sg:classifiers":[
        {
            "category":"Manufacturing",
            "subcategory":"Jewelry",
            "type":"Manufacturing & Wholesale Goods"
        }
    ],
    "sg:phone":"+1 225 766 4988",
    "sg:postcode":"70810",
    "sg:province":"LA",
    "wof:name":"Gilded Lily",
    "wof:placetype":"venue"
},
  "geometry": {"coordinates":[-91.09141200000001,30.375932],"type":"Point"}
}