{
  "type": "Feature",
  "properties": {
    "iso:country":"US",
    "sg:address":"2012 N Harco Dr",
    "sg:city":"Baton Rouge",
    "sg:classifiers":[
        {
            "category":"Organizations",
            "subcategory":"Religious Organization",
            "type":"Services"
        }
    ],
    "sg:phone":"+1 225 275 3661",
    "sg:postcode":"70815",
    "sg:province":"LA",
    "sg:tags":[
        "church"
    ],
    "wof:name":"Jesus The Light World",
    "wof:placetype":"venue"
},
  "geometry": {"coordinates":[-91.04248,30.4717],"type":"Point"}
}