{
  "type": "Feature",
  "properties": {
    "addr:full":"5139 Dixie Garden Dr Shreveport LA 71105",
    "addr:housenumber":"5139",
    "addr:postcode":"71105",
    "addr:street":"Dixie Garden Dr",
    "iso:country":"US",
    "sg:address":"5139 Dixie Garden Dr",
    "sg:city":"Shreveport",
    "sg:classifiers":[
        {
            "category":"Building & Trades",
            "subcategory":"Landscaping Services",
            "type":"Services"
        }
    ],
    "sg:phone":"+1 318 861 2626",
    "sg:postcode":"71105",
    "sg:province":"LA",
    "sg:tags":[
        "landscape",
        "contractor"
    ],
    "wof:name":"Curtis Farms Inc",
    "wof:placetype":"venue"
},
  "geometry": {"coordinates":[-93.697365,32.453035],"type":"Point"}
}