{
  "type": "Feature",
  "properties": {
    "iso:country":"US",
    "sg:address":"100 Mariners Blvd",
    "sg:city":"Mandeville",
    "sg:classifiers":[
        {
            "category":"Real Estate",
            "subcategory":"Real Estate Agent",
            "type":"Services"
        }
    ],
    "sg:phone":"+1 985 727 1727",
    "sg:postcode":"70448",
    "sg:province":"LA",
    "wof:name":"Showcase Properties",
    "wof:placetype":"venue"
},
  "geometry": {"coordinates":[-90.089157,30.367725],"type":"Point"}
}