{
  "type": "Feature",
  "properties": {
    "addr:full":"18128 River Rd La Place LA 70068",
    "addr:housenumber":"18128",
    "addr:postcode":"70068",
    "addr:street":"River Rd;Place",
    "iso:country":"US",
    "sg:address":"18128 River Rd",
    "sg:city":"La Place",
    "sg:classifiers":[
        {
            "category":"Professional",
            "subcategory":"Engineering",
            "type":"Services"
        }
    ],
    "sg:phone":"+1 504 455 2237",
    "sg:postcode":"70068",
    "sg:province":"LA",
    "sg:tags":[
        "architect",
        "naval"
    ],
    "wof:name":"Definitive Marine Svc",
    "wof:placetype":"venue"
},
  "geometry": {"coordinates":[-90.467977,30.013847],"type":"Point"}
}