{
  "type": "Feature",
  "properties": {
    "addr:full":"400 Millaudon St New Orleans LA 70118",
    "addr:housenumber":"400",
    "addr:postcode":"70118",
    "addr:street":"Millaudon St",
    "iso:country":"US",
    "sg:address":"400 Millaudon St",
    "sg:city":"New Orleans",
    "sg:classifiers":[
        {
            "category":"Professional",
            "subcategory":"Computer Services",
            "type":"Services"
        }
    ],
    "sg:phone":"+1 504 301 4452",
    "sg:postcode":"70118",
    "sg:province":"LA",
    "sg:tags":[
        "internet"
    ],
    "wof:name":"Web Lab",
    "wof:placetype":"venue"
},
  "geometry": {"coordinates":[-90.12932000000001,29.937918],"type":"Point"}
}