{
  "type": "Feature",
  "properties": {
    "iso:country":"US",
    "sg:address":"315 E Kirkland St",
    "sg:city":"Covington",
    "sg:classifiers":[
        {
            "category":"Professional",
            "subcategory":"Secretarial Services",
            "type":"Services"
        }
    ],
    "sg:phone":"+1 985 893 2500",
    "sg:postcode":"70433",
    "sg:province":"LA",
    "sg:tags":[
        "convention",
        "court",
        "reporter"
    ],
    "wof:name":"Consolidated Reporters Inc",
    "wof:placetype":"venue"
},
  "geometry": {"coordinates":[-90.094015,30.479206],"type":"Point"}
}