{
  "type": "Feature",
  "properties": {
    "iso:country":"US",
    "sg:address":"101 Production Dr",
    "sg:city":"Slidell",
    "sg:classifiers":[
        {
            "category":"Manufacturing",
            "subcategory":"Tools & Machinery",
            "type":"Manufacturing & Wholesale Goods"
        }
    ],
    "sg:phone":"+1 985 645 0704",
    "sg:postcode":"70460",
    "sg:province":"LA",
    "sg:tags":[
        "machine",
        "shop"
    ],
    "wof:name":"Marshall Industries LLC",
    "wof:placetype":"venue"
},
  "geometry": {"coordinates":[-89.77408800000001,30.317926],"type":"Point"}
}