{
  "type": "Feature",
  "properties": {
    "iso:country":"US",
    "sg:address":"2608 Main St",
    "sg:city":"Baker",
    "sg:classifiers":[
        {
            "category":"Building & Trades",
            "subcategory":"Construction",
            "type":"Services"
        }
    ],
    "sg:phone":"+1 225 775 7604",
    "sg:postcode":"70714",
    "sg:province":"LA",
    "wof:name":"TNT Metal Building Component",
    "wof:placetype":"venue"
},
  "geometry": {"coordinates":[-91.164587,30.604842],"type":"Point"}
}