{
  "type": "Feature",
  "properties": {
    "addr:full":"2626 Felicity St New Orleans LA 70113",
    "addr:housenumber":"2626",
    "addr:postcode":"70113",
    "addr:street":"Felicity St",
    "iso:country":"US",
    "sg:address":"2626 Felicity St",
    "sg:city":"New Orleans",
    "sg:classifiers":[
        {
            "category":"Organizations",
            "subcategory":"Religious Organization",
            "type":"Services"
        }
    ],
    "sg:phone":"+1 504 523 2927",
    "sg:postcode":"70113",
    "sg:province":"LA",
    "sg:tags":[
        "church"
    ],
    "wof:name":"Greater Full Gospel Church",
    "wof:placetype":"venue"
},
  "geometry": {"coordinates":[-90.08701499999999,29.944579],"type":"Point"}
}