{
  "type": "Feature",
  "properties": {
    "iso:country":"US",
    "sg:address":"526 Pine St",
    "sg:city":"Minden",
    "sg:classifiers":[
        {
            "category":"Building & Trades",
            "subcategory":"Electrical",
            "type":"Services"
        }
    ],
    "sg:phone":"+1 318 377 0758",
    "sg:postcode":"71055",
    "sg:province":"LA",
    "sg:tags":[
        "electric",
        "contractor"
    ],
    "wof:name":"Samuel Electric Inc",
    "wof:placetype":"venue"
},
  "geometry": {"coordinates":[-93.29615099999999,32.622301],"type":"Point"}
}