{
  "type": "Feature",
  "properties": {
    "addr:full":"3767 General Degaulle Dr # A New Orleans LA 70114",
    "addr:housenumber":"3767",
    "addr:postcode":"70114",
    "addr:street":"General Degaulle Dr # A",
    "iso:country":"US",
    "sg:address":"3767 General Degaulle Dr # A",
    "sg:city":"New Orleans",
    "sg:classifiers":[
        {
            "category":"Shopping",
            "subcategory":"Clothing, Apparel, & Fashions",
            "type":"Retail Goods"
        },
        {
            "category":"Shopping",
            "subcategory":"Beauty & Cosmetics",
            "type":"Retail Goods"
        }
    ],
    "sg:phone":"+1 504 362 6330",
    "sg:postcode":"70114",
    "sg:province":"LA",
    "sg:tags":[
        "women's",
        "accessory",
        "clothing",
        "supply"
    ],
    "wof:name":"Beauty Fashions",
    "wof:placetype":"venue"
},
  "geometry": {"coordinates":[-90.01799800000001,29.922701],"type":"Point"}
}