{
  "type": "Feature",
  "properties": {
    "iso:country":"US",
    "sg:address":"319 Bellot St",
    "sg:city":"Lafayette",
    "sg:classifiers":[
        {
            "category":"Personal",
            "subcategory":"Tattoo Parlor",
            "type":"Services"
        }
    ],
    "sg:phone":"+1 337 593 9009",
    "sg:postcode":"70501",
    "sg:province":"LA",
    "sg:tags":[
        "tattooing"
    ],
    "sg:website":"www.twistedinktattoo.com",
    "wof:name":"Twisted Ink",
    "wof:placetype":"venue"
},
  "geometry": {"coordinates":[-92.012497,30.236401],"type":"Point"}
}