{
  "type": "Feature",
  "properties": {
    "addr:full":"334 Stonehill Rd Folsom LA 70437",
    "addr:housenumber":"334",
    "addr:postcode":"70437",
    "addr:street":"Stonehill Rd",
    "iso:country":"US",
    "sg:address":"334 Stonehill Rd",
    "sg:city":"Folsom",
    "sg:classifiers":[
        {
            "category":"Building & Trades",
            "subcategory":"Landscaping Services",
            "type":"Services"
        }
    ],
    "sg:phone":"+1 985 796 9090",
    "sg:postcode":"70437",
    "sg:province":"LA",
    "wof:name":"Lawn Maintenance Plus Inc",
    "wof:placetype":"venue"
},
  "geometry": {"coordinates":[-90.229046,30.657758],"type":"Point"}
}