{
  "type": "Feature",
  "properties": {
    "iso:country":"US",
    "sg:address":"222 Louise St",
    "sg:city":"Baton Rouge",
    "sg:classifiers":[
        {
            "category":"Government",
            "subcategory":"Office",
            "type":"Public Place"
        }
    ],
    "sg:phone":"+1 225 389 3284",
    "sg:postcode":"70802",
    "sg:province":"LA",
    "sg:tags":[
        "city",
        "taxation"
    ],
    "wof:name":"Baton Rouge Treasurer",
    "wof:placetype":"venue"
},
  "geometry": {"coordinates":[-91.182574,30.433972],"type":"Point"}
}