{
  "type": "Feature",
  "properties": {
    "addr:full":"1112 E Ascension Complex Blvd Gonzales LA 70737",
    "addr:housenumber":"1112",
    "addr:postcode":"70737",
    "addr:street":"E;Complex Blvd Gonzales La",
    "iso:country":"US",
    "sg:address":"1112 E Ascension Complex Blvd",
    "sg:city":"Gonzales",
    "sg:classifiers":[
        {
            "category":"Health Services",
            "subcategory":"Doctor",
            "type":"Services"
        }
    ],
    "sg:phone":"+1 225 644 8687",
    "sg:postcode":"70737",
    "sg:province":"LA",
    "sg:tags":[
        "physician",
        "surgeon"
    ],
    "wof:name":"Karen Stone MD",
    "wof:placetype":"venue"
},
  "geometry": {"coordinates":[-90.91329,30.224669],"type":"Point"}
}