{
  "type": "Feature",
  "properties": {
    "iso:country":"US",
    "sg:address":"150 Olive St",
    "sg:city":"Shreveport",
    "sg:classifiers":[
        {
            "category":"Shopping",
            "subcategory":"Shoes",
            "type":"Retail Goods"
        }
    ],
    "sg:phone":"+1 318 673 1904",
    "sg:postcode":"71104",
    "sg:province":"LA",
    "wof:name":"Steppin In Style",
    "wof:placetype":"venue"
},
  "geometry": {"coordinates":[-93.73211499999999,32.492725],"type":"Point"}
}