{
  "type": "Feature",
  "properties": {
    "addr:full":"412 Travis St Lafayette LA 70503",
    "addr:housenumber":"412",
    "addr:postcode":"70503",
    "addr:street":"Travis St",
    "iso:country":"US",
    "sg:address":"412 Travis St",
    "sg:city":"Lafayette",
    "sg:classifiers":[
        {
            "category":"Professional",
            "subcategory":"Detective & Security Services",
            "type":"Services"
        }
    ],
    "sg:phone":"+1 337 237 4444",
    "sg:postcode":"70503",
    "sg:province":"LA",
    "wof:name":"Aar & Assoc Inc",
    "wof:placetype":"venue"
},
  "geometry": {"coordinates":[-92.01646599999999,30.206546],"type":"Point"}
}