{
  "type": "Feature",
  "properties": {
    "addr:full":"806 E Main St Broussard LA 70518",
    "addr:housenumber":"806",
    "addr:postcode":"70518",
    "addr:street":"E Main St",
    "iso:country":"US",
    "sg:address":"806 E Main St",
    "sg:city":"Broussard",
    "sg:classifiers":[
        {
            "category":"Home & Garden",
            "subcategory":"Building Materials",
            "type":"Retail Goods"
        }
    ],
    "sg:phone":"+1 337 839 9351",
    "sg:postcode":"70518",
    "sg:province":"LA",
    "sg:tags":[
        "paint"
    ],
    "wof:name":"Recon Coatings",
    "wof:placetype":"venue"
},
  "geometry": {"coordinates":[-91.950755,30.144563],"type":"Point"}
}