{
  "type": "Feature",
  "properties": {
    "addr:full":"2106 Loop Rd Winnsboro LA 71295",
    "addr:housenumber":"2106",
    "addr:postcode":"71295",
    "addr:street":"Loop Rd",
    "iso:country":"US",
    "sg:address":"2106 Loop Rd",
    "sg:city":"Winnsboro",
    "sg:classifiers":[
        {
            "category":"Health Services",
            "subcategory":"Hospital",
            "type":"Services"
        }
    ],
    "sg:phone":"+1 318 435 9411",
    "sg:postcode":"71295",
    "sg:province":"LA",
    "wof:name":"Franklin Medical Ctr",
    "wof:placetype":"venue"
},
  "geometry": {"coordinates":[-91.705174,32.158215],"type":"Point"}
}