{
  "type": "Feature",
  "properties": {
    "iso:country":"US",
    "sg:address":"798 E I- 10 Svc Rd",
    "sg:city":"Slidell",
    "sg:classifiers":[
        {
            "category":"Travel",
            "subcategory":"Hotels & Motels",
            "type":"Entertainment"
        }
    ],
    "sg:phone":"+1 985 643 2010",
    "sg:postcode":"70461",
    "sg:province":"LA",
    "wof:name":"Guest Lodge Motel",
    "wof:placetype":"venue"
},
  "geometry": {"coordinates":[-89.748864,30.284041],"type":"Point"}
}