{
  "type": "Feature",
  "properties": {
    "addr:full":"136 Hwy 167 N Ville Platte LA 70586",
    "addr:housenumber":"136",
    "addr:postcode":"70586",
    "addr:street":"Hwy 167 N Ville Platte",
    "iso:country":"US",
    "sg:address":"136 Hwy 167 N",
    "sg:city":"Ville Platte",
    "sg:classifiers":[
        {
            "category":"Building & Trades",
            "subcategory":"Plumbing",
            "type":"Services"
        }
    ],
    "sg:phone":"+1 337 363 8283",
    "sg:postcode":"70586",
    "sg:province":"LA",
    "sg:tags":[
        "septic"
    ],
    "wof:name":"Tate's Septic Svc",
    "wof:placetype":"venue"
},
  "geometry": {"coordinates":[-92.311323,30.700563],"type":"Point"}
}