{
  "type": "Feature",
  "properties": {
    "addr:full":"110 River Birch Dr Lafayette LA 70508",
    "addr:housenumber":"110",
    "addr:postcode":"70508",
    "addr:street":"River Birch Dr",
    "iso:country":"US",
    "sg:address":"110 River Birch Dr",
    "sg:city":"Lafayette",
    "sg:classifiers":[
        {
            "category":"Shopping",
            "subcategory":"Computers & Home Electronics",
            "type":"Retail Goods"
        }
    ],
    "sg:phone":"+1 337 857 1430",
    "sg:postcode":"70508",
    "sg:province":"LA",
    "sg:tags":[
        "system"
    ],
    "wof:name":"That's Entertainment",
    "wof:placetype":"venue"
},
  "geometry": {"coordinates":[-92.06501,30.121495],"type":"Point"}
}