{
  "type": "Feature",
  "properties": {
    "addr:full":"1501 Ambassador Caffery Pkwy Lafayette LA 70506",
    "addr:housenumber":"1501",
    "addr:postcode":"70506",
    "addr:street":"Ambassador Caffery Pkwy",
    "iso:country":"US",
    "sg:address":"1501 Ambassador Caffery Pkwy",
    "sg:city":"Lafayette",
    "sg:classifiers":[
        {
            "category":"Manufacturing",
            "subcategory":"Tools & Machinery",
            "type":"Manufacturing & Wholesale Goods"
        }
    ],
    "sg:phone":"+1 337 988 7140",
    "sg:postcode":"70506",
    "sg:province":"LA",
    "sg:tags":[
        "turbine"
    ],
    "wof:name":"Solar Turbines Inc",
    "wof:placetype":"venue"
},
  "geometry": {"coordinates":[-92.07559000000001,30.220157],"type":"Point"}
}