{
  "type": "Feature",
  "properties": {
    "addr:full":"6719 Perkins Rd Baton Rouge LA 70808",
    "addr:housenumber":"6719",
    "addr:postcode":"70808",
    "addr:street":"Perkins Rd",
    "iso:country":"US",
    "sg:address":"6719 Perkins Rd",
    "sg:city":"Baton Rouge",
    "sg:classifiers":[
        {
            "category":"Professional",
            "subcategory":"Advertising",
            "type":"Services"
        }
    ],
    "sg:phone":"+1 225 767 8600",
    "sg:postcode":"70808",
    "sg:province":"LA",
    "sg:tags":[
        "counselor"
    ],
    "sg:website":"www.braymedia.com",
    "wof:name":"Bray Media",
    "wof:placetype":"venue"
},
  "geometry": {"coordinates":[-91.119383,30.402033],"type":"Point"}
}