{
  "type": "Feature",
  "properties": {
    "iso:country":"US",
    "sg:address":"940 Parkview Dr",
    "sg:city":"New Iberia",
    "sg:classifiers":[
        {
            "category":"Banks & Credit Unions",
            "subcategory":"Bank",
            "type":"Services"
        }
    ],
    "sg:phone":"+1 337 560 5496",
    "sg:postcode":"70563",
    "sg:province":"LA",
    "wof:name":"Capital City",
    "wof:placetype":"venue"
},
  "geometry": {"coordinates":[-91.804168,30.003367],"type":"Point"}
}