{
  "type": "Feature",
  "properties": {
    "addr:full":"203 N 16th St Oakdale LA 71463",
    "addr:housenumber":"203",
    "addr:postcode":"71463",
    "addr:street":"N 16Th St",
    "iso:country":"US",
    "sg:address":"203 N 16th St",
    "sg:city":"Oakdale",
    "sg:classifiers":[
        {
            "category":"Wholesale",
            "subcategory":"Medical Equipment & Supplies",
            "type":"Manufacturing & Wholesale Goods"
        }
    ],
    "sg:phone":"+1 318 335 3329",
    "sg:postcode":"71463",
    "sg:province":"LA",
    "sg:tags":[
        "hospital"
    ],
    "wof:name":"Medical Shop",
    "wof:placetype":"venue"
},
  "geometry": {"coordinates":[-92.651098,30.818159],"type":"Point"}
}