{
  "type": "Feature",
  "properties": {
    "addr:full":"7354 Alberta Dr Baton Rouge LA 70808",
    "addr:housenumber":"7354",
    "addr:postcode":"70808",
    "addr:street":"Alberta Dr",
    "iso:country":"US",
    "sg:address":"7354 Alberta Dr",
    "sg:city":"Baton Rouge",
    "sg:classifiers":[
        {
            "category":"Professional",
            "subcategory":"Computer Services",
            "type":"Services"
        }
    ],
    "sg:phone":"+1 225 303 0035",
    "sg:postcode":"70808",
    "sg:province":"LA",
    "wof:name":"Southern Technology Svc Inc",
    "wof:placetype":"venue"
},
  "geometry": {"coordinates":[-91.11062,30.39314],"type":"Point"}
}