{
  "type": "Feature",
  "properties": {
    "addr:full":"8220 Goodwood Blvd Baton Rouge LA 70806",
    "addr:housenumber":"8220",
    "addr:postcode":"70806",
    "addr:street":"Goodwood Blvd",
    "iso:country":"US",
    "sg:address":"8220 Goodwood Blvd",
    "sg:city":"Baton Rouge",
    "sg:classifiers":[
        {
            "category":"Health Services",
            "subcategory":"Doctor",
            "type":"Services"
        }
    ],
    "sg:phone":"+1 225 927 9659",
    "sg:postcode":"70806",
    "sg:province":"LA",
    "sg:tags":[
        "dentist"
    ],
    "wof:name":"James E Pope Inc",
    "wof:placetype":"venue"
},
  "geometry": {"coordinates":[-91.100247,30.442545],"type":"Point"}
}