{
  "type": "Feature",
  "properties": {
    "iso:country":"US",
    "sg:address":"480 US Hwy 171",
    "sg:city":"Lake Charles",
    "sg:classifiers":[
        {
            "category":"Autos & Motor Vehicles",
            "subcategory":"Automobile Sales",
            "type":"Retail Goods"
        }
    ],
    "sg:phone":"+1 337 855 7400",
    "sg:postcode":"70611",
    "sg:province":"LA",
    "sg:tags":[
        "car",
        "used",
        "dealer"
    ],
    "wof:name":"Bobby Lafleur Auto Sales",
    "wof:placetype":"venue"
},
  "geometry": {"coordinates":[-93.195053,30.303306],"type":"Point"}
}