{
  "type": "Feature",
  "properties": {
    "iso:country":"US",
    "sg:address":"31 Loop Rd",
    "sg:city":"Delhi",
    "sg:classifiers":[
        {
            "category":"Personal",
            "subcategory":"Barber",
            "type":"Services"
        }
    ],
    "sg:phone":"+1 318 878 3301",
    "sg:postcode":"71232",
    "sg:province":"LA",
    "wof:name":"Shear-KUT",
    "wof:placetype":"venue"
},
  "geometry": {"coordinates":[-91.489841,32.472297],"type":"Point"}
}