{
  "type": "Feature",
  "properties": {
    "addr:full":"1656 E Texas St Bossier City LA 71111",
    "addr:housenumber":"1656",
    "addr:postcode":"71111",
    "addr:street":"E Texas St",
    "iso:country":"US",
    "sg:address":"1656 E Texas St",
    "sg:city":"Bossier City",
    "sg:classifiers":[
        {
            "category":"Food & Beverages",
            "subcategory":"Groceries & Convenience Stores",
            "type":"Retail Goods"
        }
    ],
    "sg:phone":"+1 318 746 9688",
    "sg:postcode":"71111",
    "sg:province":"LA",
    "wof:name":"Texas Liquor Shop",
    "wof:placetype":"venue"
},
  "geometry": {"coordinates":[-93.73007800000001,32.52624],"type":"Point"}
}