{
  "type": "Feature",
  "properties": {
    "addr:full":"8945 Cortana Pl Baton Rouge LA 70815",
    "addr:housenumber":"8945",
    "addr:postcode":"70815",
    "addr:street":"Cortana Pl",
    "iso:country":"US",
    "sg:address":"8945 Cortana Pl",
    "sg:city":"Baton Rouge",
    "sg:classifiers":[
        {
            "category":"Shopping",
            "subcategory":"Optical Goods",
            "type":"Retail Goods"
        }
    ],
    "sg:phone":"+1 225 929 7994",
    "sg:postcode":"70815",
    "sg:province":"LA",
    "wof:name":"Lens Crafters",
    "wof:placetype":"venue"
},
  "geometry": {"coordinates":[-91.088983,30.456141],"type":"Point"}
}