{
  "type": "Feature",
  "properties": {
    "iso:country":"US",
    "sg:address":"1215 E Main St",
    "sg:city":"New Iberia",
    "sg:classifiers":[
        {
            "category":"Autos & Motor Vehicles",
            "subcategory":"Auto Supplies",
            "type":"Retail Goods"
        }
    ],
    "sg:phone":"+1 337 369 3781",
    "sg:postcode":"70560",
    "sg:province":"LA",
    "sg:tags":[
        "automobile",
        "parts"
    ],
    "wof:name":"Himel Motor Supply",
    "wof:placetype":"venue"
},
  "geometry": {"coordinates":[-91.802547,29.997286],"type":"Point"}
}