{
  "type": "Feature",
  "properties": {
    "addr:full":"2410 N Causeway Blvd Mandeville LA 70471",
    "addr:housenumber":"2410",
    "addr:postcode":"70471",
    "addr:street":"N Causeway Blvd",
    "iso:country":"US",
    "sg:address":"2410 N Causeway Blvd",
    "sg:city":"Mandeville",
    "sg:classifiers":[
        {
            "category":"Banks & Credit Unions",
            "subcategory":"Bank",
            "type":"Services"
        }
    ],
    "sg:phone":"+1 504 609 1000",
    "sg:postcode":"70471",
    "sg:province":"LA",
    "sg:tags":[
        "loan",
        "real estate"
    ],
    "wof:name":"Home Buyers Choice",
    "wof:placetype":"venue"
},
  "geometry": {"coordinates":[-90.088987,30.393021],"type":"Point"}
}