{
  "type": "Feature",
  "properties": {
    "addr:full":"5207 Monkhouse Dr Shreveport LA 71109",
    "addr:housenumber":"5207",
    "addr:postcode":"71109",
    "addr:street":"Monkhouse Dr",
    "iso:country":"US",
    "sg:address":"5207 Monkhouse Dr",
    "sg:city":"Shreveport",
    "sg:classifiers":[
        {
            "category":"Retail",
            "subcategory":"Auto Rental",
            "type":"Services"
        }
    ],
    "sg:phone":"+1 318 631 1839",
    "sg:postcode":"71109",
    "sg:province":"LA",
    "sg:tags":[
        "renting",
        "automobile"
    ],
    "wof:name":"Airline Car Rental Inc",
    "wof:placetype":"venue"
},
  "geometry": {"coordinates":[-93.827,32.458323],"type":"Point"}
}