{
  "type": "Feature",
  "properties": {
    "iso:country":"US",
    "sg:address":"4561 Lennox Blvd",
    "sg:city":"New Orleans",
    "sg:classifiers":[
        {
            "category":"Travel",
            "subcategory":"Travel Agent",
            "type":"Entertainment"
        }
    ],
    "sg:phone":"+1 504 393 1226",
    "sg:postcode":"70131",
    "sg:province":"LA",
    "sg:tags":[
        "agency",
        "bureau"
    ],
    "wof:name":"Dream Destinations",
    "wof:placetype":"venue"
},
  "geometry": {"coordinates":[-90.00778699999999,29.904372],"type":"Point"}
}