{
  "type": "Feature",
  "properties": {
    "addr:full":"15255 Jefferson Hwy Baton Rouge LA 70817",
    "addr:housenumber":"15255",
    "addr:postcode":"70817",
    "addr:street":"Jefferson Hwy",
    "iso:country":"US",
    "sg:address":"15255 Jefferson Hwy",
    "sg:city":"Baton Rouge",
    "sg:classifiers":[
        {
            "category":"Organizations",
            "subcategory":"Religious Organization",
            "type":"Services"
        }
    ],
    "sg:phone":"+1 225 755 3043",
    "sg:postcode":"70817",
    "sg:province":"LA",
    "sg:tags":[
        "church"
    ],
    "wof:name":"Unity Church Of Christianity",
    "wof:placetype":"venue"
},
  "geometry": {"coordinates":[-91.020617,30.37799],"type":"Point"}
}