{
  "type": "Feature",
  "properties": {
    "addr:full":"2570 Florida Blvd SW Denham Springs LA 70726",
    "addr:housenumber":"2570",
    "addr:postcode":"70726",
    "addr:street":"Florida Blvd Sw Denham Springs",
    "iso:country":"US",
    "sg:address":"2570 Florida Blvd SW",
    "sg:city":"Denham Springs",
    "sg:classifiers":[
        {
            "category":"Personal",
            "subcategory":"Beauty Salon",
            "type":"Services"
        }
    ],
    "sg:phone":"+1 225 665 5672",
    "sg:postcode":"70726",
    "sg:province":"LA",
    "wof:name":"New Look For Hair",
    "wof:placetype":"venue"
},
  "geometry": {"coordinates":[-90.986344,30.4632],"type":"Point"}
}