{
  "type": "Feature",
  "properties": {
    "iso:country":"US",
    "sg:address":"145 17th St",
    "sg:city":"Golden Meadow",
    "sg:classifiers":[
        {
            "category":"Professional",
            "subcategory":"Research",
            "type":"Services"
        }
    ],
    "sg:phone":"+1 985 396 2804",
    "sg:postcode":"70357",
    "sg:province":"LA",
    "sg:tags":[
        "environmental",
        "ecological"
    ],
    "wof:name":"Newpark Environmental Svc",
    "wof:placetype":"venue"
},
  "geometry": {"coordinates":[-90.20460799999999,29.119004],"type":"Point"}
}