{
  "type": "Feature",
  "properties": {
    "iso:country":"US",
    "sg:address":"9345 Springfield Rd",
    "sg:city":"Denham Springs",
    "sg:classifiers":[
        {
            "category":"Shopping",
            "type":"Retail Goods"
        }
    ],
    "sg:phone":"+1 225 667 7645",
    "sg:postcode":"70706",
    "sg:province":"LA",
    "sg:tags":[
        "cosmetic",
        "perfume"
    ],
    "wof:name":"Parlor",
    "wof:placetype":"venue"
},
  "geometry": {"coordinates":[-90.933252,30.580728],"type":"Point"}
}