{
  "type": "Feature",
  "properties": {
    "addr:full":"10166 Jefferson Hwy Harahan LA 70123",
    "addr:housenumber":"10166",
    "addr:postcode":"70123",
    "addr:street":"Jefferson Hwy Harahan",
    "iso:country":"US",
    "sg:address":"10166 Jefferson Hwy",
    "sg:city":"Harahan",
    "sg:classifiers":[
        {
            "category":"Shopping",
            "type":"Retail Goods"
        }
    ],
    "sg:phone":"+1 504 737 4658",
    "sg:postcode":"70123",
    "sg:province":"LA",
    "sg:tags":[
        "wedding",
        "supply"
    ],
    "wof:name":"Alamo Cleaners",
    "wof:placetype":"venue"
},
  "geometry": {"coordinates":[-90.22238,29.962541],"type":"Point"}
}