{
  "type": "Feature",
  "properties": {
    "iso:country":"US",
    "sg:address":"105 Lee Ct",
    "sg:city":"New Orleans",
    "sg:classifiers":[
        {
            "category":"Building & Trades",
            "subcategory":"Construction",
            "type":"Services"
        }
    ],
    "sg:phone":"+1 504 737 9552",
    "sg:postcode":"70123",
    "sg:province":"LA",
    "sg:tags":[
        "house"
    ],
    "wof:name":"Maynard Construction",
    "wof:placetype":"venue"
},
  "geometry": {"coordinates":[-90.21347299999999,29.94484],"type":"Point"}
}