{
  "type": "Feature",
  "properties": {
    "iso:country":"US",
    "sg:address":"2403 Hulin Rd",
    "sg:city":"New Iberia",
    "sg:classifiers":[
        {
            "category":"Manufacturing",
            "subcategory":"Glass & Minerals",
            "type":"Manufacturing & Wholesale Goods"
        }
    ],
    "sg:phone":"+1 337 365 1394",
    "sg:postcode":"70560",
    "sg:province":"LA",
    "sg:tags":[
        "ready"
    ],
    "wof:name":"Baldwin Redi-Mix",
    "wof:placetype":"venue"
},
  "geometry": {"coordinates":[-91.827647,29.963174],"type":"Point"}
}