{
  "type": "Feature",
  "properties": {
    "addr:full":"1301 S Polk St Covington LA 70433",
    "addr:housenumber":"1301",
    "addr:postcode":"70433",
    "addr:street":"S Polk St",
    "iso:country":"US",
    "sg:address":"1301 S Polk St",
    "sg:city":"Covington",
    "sg:classifiers":[
        {
            "category":"Education",
            "subcategory":"Dance Studio",
            "type":"Public Place"
        }
    ],
    "sg:phone":"+1 985 893 1143",
    "sg:postcode":"70433",
    "sg:province":"LA",
    "sg:tags":[
        "instruction",
        "dancing"
    ],
    "wof:name":"Northshore Academy Of Dance",
    "wof:placetype":"venue"
},
  "geometry": {"coordinates":[-90.11551900000001,30.46864],"type":"Point"}
}