{
  "type": "Feature",
  "properties": {
    "iso:country":"US",
    "sg:address":"8760 Greenwell Springs Rd",
    "sg:city":"Baton Rouge",
    "sg:classifiers":[
        {
            "category":"Wholesale",
            "subcategory":"Groceries",
            "type":"Manufacturing & Wholesale Goods"
        }
    ],
    "sg:phone":"+1 225 928 3311",
    "sg:postcode":"70814",
    "sg:province":"LA",
    "sg:tags":[
        "grocer"
    ],
    "wof:name":"General Goods Of LA",
    "wof:placetype":"venue"
},
  "geometry": {"coordinates":[-91.095964,30.481839],"type":"Point"}
}