{
  "type": "Feature",
  "properties": {
    "iso:country":"US",
    "sg:address":"1007 Gould Dr",
    "sg:city":"Bossier City",
    "sg:classifiers":[
        {
            "category":"Professional",
            "subcategory":"Computer Services",
            "type":"Services"
        }
    ],
    "sg:phone":"+1 318 742 1065",
    "sg:postcode":"71111",
    "sg:province":"LA",
    "sg:tags":[
        "consultant",
        "designer"
    ],
    "wof:name":"Roger P Ley",
    "wof:placetype":"venue"
},
  "geometry": {"coordinates":[-93.707115,32.522101],"type":"Point"}
}