{
  "type": "Feature",
  "properties": {
    "iso:country":"US",
    "sg:address":"2601 Centenary Blvd",
    "sg:city":"Shreveport",
    "sg:classifiers":[
        {
            "category":"Mining & Drilling",
            "type":"Manufacturing & Wholesale Goods"
        }
    ],
    "sg:phone":"+1 318 226 1773",
    "sg:postcode":"71104",
    "sg:province":"LA",
    "sg:tags":[
        "operator",
        "oil"
    ],
    "wof:name":"Gemini Explorations Inc",
    "wof:placetype":"venue"
},
  "geometry": {"coordinates":[-93.73308900000001,32.485836],"type":"Point"}
}