{
  "type": "Feature",
  "properties": {
    "iso:country":"US",
    "sg:address":"424 S Roadway St",
    "sg:city":"New Orleans",
    "sg:classifiers":[
        {
            "category":"Wholesale",
            "subcategory":"Durable Goods & Equipment",
            "type":"Manufacturing & Wholesale Goods"
        }
    ],
    "sg:phone":"+1 504 284 3442",
    "sg:postcode":"70124",
    "sg:province":"LA",
    "sg:tags":[
        "representative",
        "manufacturer"
    ],
    "wof:name":"Associated Manufactures Agents",
    "wof:placetype":"venue"
},
  "geometry": {"coordinates":[-90.119328,30.023681],"type":"Point"}
}