{
  "type": "Feature",
  "properties": {
    "addr:full":"8687 United Plaza Blvd Baton Rouge LA 70809",
    "addr:housenumber":"8687",
    "addr:postcode":"70809",
    "addr:street":"United Plaza Blvd",
    "iso:country":"US",
    "sg:address":"8687 United Plaza Blvd",
    "sg:city":"Baton Rouge",
    "sg:classifiers":[
        {
            "category":"Insurance",
            "subcategory":"Health Insurance",
            "type":"Services"
        }
    ],
    "sg:phone":"+1 225 927 3490",
    "sg:postcode":"70809",
    "sg:province":"LA",
    "sg:tags":[
        "plan"
    ],
    "sg:website":"www.momedicare.com",
    "wof:name":"Blue Cross & Blue Shield",
    "wof:placetype":"venue"
},
  "geometry": {"coordinates":[-91.10033199999999,30.410195],"type":"Point"}
}