{
  "type": "Feature",
  "properties": {
    "addr:full":"1000 Royal St New Orleans LA 70116",
    "addr:housenumber":"1000",
    "addr:postcode":"70116",
    "addr:street":"Royal St",
    "iso:country":"US",
    "sg:address":"1000 Royal St",
    "sg:city":"New Orleans",
    "sg:classifiers":[
        {
            "category":"Food & Beverages",
            "subcategory":"Groceries & Convenience Stores",
            "type":"Retail Goods"
        }
    ],
    "sg:phone":"+1 504 552 2700",
    "sg:postcode":"70116",
    "sg:province":"LA",
    "wof:name":"New Orleans Grocery & Deli",
    "wof:placetype":"venue"
},
  "geometry": {"coordinates":[-90.06240099999999,29.960501],"type":"Point"}
}