{
  "type": "Feature",
  "properties": {
    "addr:full":"114 Cedar St Houma LA 70364",
    "addr:housenumber":"114",
    "addr:postcode":"70364",
    "addr:street":"Cedar St",
    "iso:country":"US",
    "sg:address":"114 Cedar St",
    "sg:city":"Houma",
    "sg:classifiers":[
        {
            "category":"Utilities",
            "subcategory":"Telephone",
            "type":"Services"
        }
    ],
    "sg:phone":"+1 985 876 6612",
    "sg:postcode":"70364",
    "sg:province":"LA",
    "sg:tags":[
        "telecommunication"
    ],
    "wof:name":"Lightning Communications Inc",
    "wof:placetype":"venue"
},
  "geometry": {"coordinates":[-90.724969,29.599236],"type":"Point"}
}