{
  "type": "Feature",
  "properties": {
    "addr:full":"3535 Bienville St New Orleans LA 70119",
    "addr:housenumber":"3535",
    "addr:postcode":"70119",
    "addr:street":"Bienville St",
    "iso:country":"US",
    "sg:address":"3535 Bienville St",
    "sg:city":"New Orleans",
    "sg:classifiers":[
        {
            "category":"Health Services",
            "subcategory":"Doctor",
            "type":"Services"
        }
    ],
    "sg:phone":"+1 504 486 7415",
    "sg:postcode":"70119",
    "sg:province":"LA",
    "sg:tags":[
        "physician",
        "surgeon"
    ],
    "wof:name":"Cerise Adinolfi Mc Ginness",
    "wof:placetype":"venue"
},
  "geometry": {"coordinates":[-90.09414099999999,29.972934],"type":"Point"}
}