{
  "type": "Feature",
  "properties": {
    "addr:full":"235 Barbara Ln Farmerville LA 71241",
    "addr:housenumber":"235",
    "addr:postcode":"71241",
    "addr:street":"Barbara Ln",
    "iso:country":"US",
    "sg:address":"235 Barbara Ln",
    "sg:city":"Farmerville",
    "sg:classifiers":[
        {
            "category":"Farming",
            "subcategory":"Farm",
            "type":"Manufacturing & Wholesale Goods"
        }
    ],
    "sg:phone":"+1 318 368 9576",
    "sg:postcode":"71241",
    "sg:province":"LA",
    "sg:tags":[
        "crop",
        "general"
    ],
    "wof:name":"Weir Farms",
    "wof:placetype":"venue"
},
  "geometry": {"coordinates":[-92.38405899999999,32.801588],"type":"Point"}
}