{
  "type": "Feature",
  "properties": {
    "addr:full":"13938 Hwy 165 Kinder LA 70648",
    "addr:housenumber":"13938",
    "addr:postcode":"70648",
    "addr:street":"Hwy 165 Kinder",
    "iso:country":"US",
    "sg:address":"13938 Hwy 165",
    "sg:city":"Kinder",
    "sg:classifiers":[
        {
            "category":"Health Services",
            "subcategory":"Nursing And Care Facility",
            "type":"Services"
        }
    ],
    "sg:phone":"+1 337 738 5671",
    "sg:postcode":"70648",
    "sg:province":"LA",
    "sg:tags":[
        "home",
        "convalescent"
    ],
    "wof:name":"Kinder Retirement & Rehab Ctr",
    "wof:placetype":"venue"
},
  "geometry": {"coordinates":[-92.91210100000001,30.374781],"type":"Point"}
}