{
  "type": "Feature",
  "properties": {
    "addr:full":"2915 Perdido St New Orleans LA 70119",
    "addr:housenumber":"2915",
    "addr:postcode":"70119",
    "addr:street":"Perdido St",
    "iso:country":"US",
    "sg:address":"2915 Perdido St",
    "sg:city":"New Orleans",
    "sg:classifiers":[
        {
            "category":"Insurance",
            "subcategory":"Hazard Insurance",
            "type":"Services"
        }
    ],
    "sg:phone":"+1 504 827 0614",
    "sg:postcode":"70119",
    "sg:province":"LA",
    "sg:tags":[
        "fidelity",
        "carrier",
        "surety",
        "bond"
    ],
    "wof:name":"Mike's Surety",
    "wof:placetype":"venue"
},
  "geometry": {"coordinates":[-90.09607800000001,29.961259],"type":"Point"}
}