{
  "type": "Feature",
  "properties": {
    "addr:full":"24456 US Hwy 371 Sarepta LA 71071",
    "addr:housenumber":"24456",
    "addr:postcode":"71071",
    "addr:street":"Us Hwy 371 Sarepta",
    "iso:country":"US",
    "sg:address":"24456 US Hwy 371",
    "sg:city":"Sarepta",
    "sg:classifiers":[
        {
            "category":"Autos & Motor Vehicles",
            "subcategory":"Fuel & Gas Station",
            "type":"Retail Goods"
        }
    ],
    "sg:phone":"+1 318 847 4910",
    "sg:postcode":"71071",
    "sg:province":"LA",
    "sg:tags":[
        "oil"
    ],
    "wof:name":"Sparc Station",
    "wof:placetype":"venue"
},
  "geometry": {"coordinates":[-93.450855,32.899736],"type":"Point"}
}