{
  "type": "Feature",
  "properties": {
    "addr:full":"6981 Gulf Beach Hwy Cameron LA 70631",
    "addr:housenumber":"6981",
    "addr:postcode":"70631",
    "addr:street":"Gulf Beach Hwy Cameron",
    "iso:country":"US",
    "sg:address":"6981 Gulf Beach Hwy",
    "sg:city":"Cameron",
    "sg:classifiers":[
        {
            "category":"Government",
            "subcategory":"Office",
            "type":"Public Place"
        }
    ],
    "sg:phone":"+1 337 569 2567",
    "sg:postcode":"70631",
    "sg:province":"LA",
    "sg:tags":[
        "county",
        "program"
    ],
    "wof:name":"Solid Waste Collection",
    "wof:placetype":"venue"
},
  "geometry": {"coordinates":[-93.73437699999999,29.763512],"type":"Point"}
}