{
  "type": "Feature",
  "properties": {
    "iso:country":"US",
    "sg:address":"1723 Woodring St",
    "sg:city":"Lake Charles",
    "sg:classifiers":[
        {
            "category":"Organizations",
            "subcategory":"Community Association",
            "type":"Services"
        }
    ],
    "sg:phone":"+1 337 436 8909",
    "sg:postcode":"70601",
    "sg:province":"LA",
    "wof:name":"Huff & Thomas Prepetual Care",
    "wof:placetype":"venue"
},
  "geometry": {"coordinates":[-93.195719,30.255091],"type":"Point"}
}