{
  "type": "Feature",
  "properties": {
    "iso:country":"US",
    "sg:address":"146 Banks Ave",
    "sg:city":"Lafayette",
    "sg:classifiers":[
        {
            "category":"Shopping",
            "subcategory":"Crafts & Fabrics",
            "type":"Retail Goods"
        }
    ],
    "sg:phone":"+1 337 235 5875",
    "sg:postcode":"70506",
    "sg:province":"LA",
    "sg:tags":[
        "sewing"
    ],
    "wof:name":"Lafayette Costume Supply",
    "wof:placetype":"venue"
},
  "geometry": {"coordinates":[-92.06073499999999,30.22712],"type":"Point"}
}