{
  "type": "Feature",
  "properties": {
    "iso:country":"US",
    "sg:address":"1010 Canal St",
    "sg:city":"New Orleans",
    "sg:classifiers":[
        {
            "category":"Shopping",
            "subcategory":"Clothing, Apparel, & Fashions",
            "type":"Retail Goods"
        }
    ],
    "sg:phone":"+1 504 680 8411",
    "sg:postcode":"70112",
    "sg:province":"LA",
    "sg:tags":[
        "furnishing"
    ],
    "wof:name":"Motif",
    "wof:placetype":"venue"
},
  "geometry": {"coordinates":[-90.072723,29.95542],"type":"Point"}
}