{
  "type": "Feature",
  "properties": {
    "iso:country":"US",
    "sg:address":"1701 Winnsboro Rd",
    "sg:city":"Monroe",
    "sg:classifiers":[
        {
            "category":"Professional",
            "subcategory":"Business Services",
            "type":"Services"
        }
    ],
    "sg:phone":"+1 318 651 0904",
    "sg:postcode":"71202",
    "sg:province":"LA",
    "wof:name":"Legalized Records",
    "wof:placetype":"venue"
},
  "geometry": {"coordinates":[-92.08474200000001,32.483805],"type":"Point"}
}