{
  "type": "Feature",
  "properties": {
    "iso:country":"US",
    "sg:address":"1234 Decatur St",
    "sg:city":"New Orleans",
    "sg:classifiers":[
        {
            "category":"Shopping",
            "subcategory":"Used Merchandise",
            "type":"Retail Goods"
        }
    ],
    "sg:phone":"+1 504 522 6639",
    "sg:postcode":"70116",
    "sg:province":"LA",
    "sg:tags":[
        "antique"
    ],
    "wof:name":"Le Garage Antiques and Clothing",
    "wof:placetype":"venue"
},
  "geometry": {"coordinates":[-90.058998,29.960899],"type":"Point"}
}