{
  "type": "Feature",
  "properties": {
    "addr:full":"2730 Saint Claude Ave New Orleans LA 70117",
    "addr:housenumber":"2730",
    "addr:postcode":"70117",
    "addr:street":"Saint Claude Ave",
    "iso:country":"US",
    "sg:address":"2730 Saint Claude Ave",
    "sg:city":"New Orleans",
    "sg:classifiers":[
        {
            "category":"Personal",
            "subcategory":"Barber",
            "type":"Services"
        }
    ],
    "sg:phone":"+1 504 947 1181",
    "sg:postcode":"70117",
    "sg:province":"LA",
    "wof:name":"Ace Barber Shop",
    "wof:placetype":"venue"
},
  "geometry": {"coordinates":[-90.048401,29.968399],"type":"Point"}
}