{
  "type": "Feature",
  "properties": {
    "iso:country":"US",
    "sg:address":"149 Trunzler Rd",
    "sg:city":"Jonesville",
    "sg:classifiers":[
        {
            "category":"Professional",
            "subcategory":"Detective & Security Services",
            "type":"Services"
        }
    ],
    "sg:phone":"+1 318 339 9947",
    "sg:postcode":"71343",
    "sg:province":"LA",
    "sg:tags":[
        "guard"
    ],
    "wof:name":"Joe Trunzler",
    "wof:placetype":"venue"
},
  "geometry": {"coordinates":[-91.864531,31.607666],"type":"Point"}
}