{
  "type": "Feature",
  "properties": {
    "addr:full":"4908 Main St Zachary LA 70791",
    "addr:housenumber":"4908",
    "addr:postcode":"70791",
    "addr:street":"Main St",
    "iso:country":"US",
    "sg:address":"4908 Main St",
    "sg:city":"Zachary",
    "sg:classifiers":[
        {
            "category":"Shopping",
            "subcategory":"Stationery & Office Supplies",
            "type":"Retail Goods"
        }
    ],
    "sg:phone":"+1 225 654 2420",
    "sg:postcode":"70791",
    "sg:province":"LA",
    "sg:tags":[
        "album",
        "scrapbook"
    ],
    "wof:name":"Twopeas In A Pod",
    "wof:placetype":"venue"
},
  "geometry": {"coordinates":[-91.153516,30.64811],"type":"Point"}
}