{
  "type": "Feature",
  "properties": {
    "addr:full":"7808 Jewella Ave Shreveport LA 71108",
    "addr:housenumber":"7808",
    "addr:postcode":"71108",
    "addr:street":"Jewella Ave",
    "iso:country":"US",
    "sg:address":"7808 Jewella Ave",
    "sg:city":"Shreveport",
    "sg:classifiers":[
        {
            "category":"Professional",
            "type":"Services"
        }
    ],
    "sg:phone":"+1 318 688 9565",
    "sg:postcode":"71108",
    "sg:province":"LA",
    "sg:tags":[
        "establishment"
    ],
    "wof:name":"Mary Godrey Creative Prod",
    "wof:placetype":"venue"
},
  "geometry": {"coordinates":[-93.797501,32.429733],"type":"Point"}
}