{
  "type": "Feature",
  "properties": {
    "iso:country":"US",
    "sg:address":"413 Clearview Pkwy",
    "sg:city":"Metairie",
    "sg:classifiers":[
        {
            "category":"Building & Trades",
            "subcategory":"Pest Control",
            "type":"Services"
        }
    ],
    "sg:phone":"+1 504 456 2664",
    "sg:postcode":"70001",
    "sg:province":"LA",
    "wof:name":"Dr Bug Exterminating Co Inc",
    "wof:placetype":"venue"
},
  "geometry": {"coordinates":[-90.17867,29.978372],"type":"Point"}
}