{
  "type": "Feature",
  "properties": {
    "iso:country":"US",
    "sg:address":"401 W Jefferson Ave",
    "sg:city":"Bastrop",
    "sg:classifiers":[
        {
            "category":"Insurance",
            "subcategory":"Hazard Insurance",
            "type":"Services"
        }
    ],
    "sg:phone":"+1 318 281 2039",
    "sg:postcode":"71220",
    "sg:province":"LA",
    "sg:tags":[
        "bond"
    ],
    "wof:name":"Bear's Bail Bonding Svc",
    "wof:placetype":"venue"
},
  "geometry": {"coordinates":[-91.92108399999999,32.776672],"type":"Point"}
}