{
  "type": "Feature",
  "properties": {
    "addr:full":"1205 Gould Blvd Lake Providence LA 71254",
    "addr:housenumber":"1205",
    "addr:postcode":"71254",
    "addr:street":"Gould Blvd",
    "iso:country":"US",
    "sg:address":"1205 Gould Blvd",
    "sg:city":"Lake Providence",
    "sg:classifiers":[
        {
            "category":"Education",
            "subcategory":"School",
            "type":"Public Place"
        }
    ],
    "sg:phone":"+1 318 559 5804",
    "sg:postcode":"71254",
    "sg:province":"LA",
    "wof:name":"East Carroll Parish Altrntv",
    "wof:placetype":"venue"
},
  "geometry": {"coordinates":[-91.18440699999999,32.79681],"type":"Point"}
}