{
  "type": "Feature",
  "properties": {
    "iso:country":"US",
    "sg:address":"308 Johnson St",
    "sg:city":"Mansfield",
    "sg:classifiers":[
        {
            "category":"Farming",
            "subcategory":"Livestock Farm",
            "type":"Manufacturing & Wholesale Goods"
        }
    ],
    "sg:phone":"+1 318 872 4050",
    "sg:postcode":"71052",
    "sg:province":"LA",
    "sg:tags":[
        "beef",
        "feedlot",
        "cattle"
    ],
    "wof:name":"Woolridge Larnceen",
    "wof:placetype":"venue"
},
  "geometry": {"coordinates":[-93.70011100000001,32.034427],"type":"Point"}
}