{
  "type": "Feature",
  "properties": {
    "iso:country":"US",
    "sg:address":"3338 Hwy 70",
    "sg:city":"Pierre Part",
    "sg:classifiers":[
        {
            "category":"Autos & Motor Vehicles",
            "subcategory":"Fuel & Gas Station",
            "type":"Retail Goods"
        }
    ],
    "sg:phone":"+1 985 252 6382",
    "sg:postcode":"70339",
    "sg:province":"LA",
    "sg:tags":[
        "station",
        "gasoline"
    ],
    "wof:name":"Chevron",
    "wof:placetype":"venue"
},
  "geometry": {"coordinates":[-91.212945,29.960667],"type":"Point"}
}