{
  "type": "Feature",
  "properties": {
    "iso:country":"US",
    "sg:address":"505 Gretna Blvd",
    "sg:city":"Gretna",
    "sg:classifiers":[
        {
            "category":"Professional",
            "subcategory":"Lawyer & Legal Services",
            "type":"Services"
        }
    ],
    "sg:phone":"+1 504 361 9904",
    "sg:postcode":"70053",
    "sg:province":"LA",
    "sg:tags":[
        "attorney"
    ],
    "wof:name":"Smith-Rubin & Assoc Inc",
    "wof:placetype":"venue"
},
  "geometry": {"coordinates":[-90.046277,29.898466],"type":"Point"}
}