{
  "type": "Feature",
  "properties": {
    "addr:full":"2828 Lakeshore Dr Shreveport LA 71109",
    "addr:housenumber":"2828",
    "addr:postcode":"71109",
    "addr:street":"Lakeshore Dr",
    "iso:country":"US",
    "sg:address":"2828 Lakeshore Dr",
    "sg:city":"Shreveport",
    "sg:classifiers":[
        {
            "category":"Communications",
            "subcategory":"Film & Video Production",
            "type":"Services"
        }
    ],
    "sg:phone":"+1 318 425 9522",
    "sg:postcode":"71109",
    "sg:province":"LA",
    "sg:tags":[
        "motion"
    ],
    "wof:name":"MO Fun Productions Inc",
    "wof:placetype":"venue"
},
  "geometry": {"coordinates":[-93.783502,32.492782],"type":"Point"}
}