{
  "type": "Feature",
  "properties": {
    "iso:country":"US",
    "sg:address":"322 W K-Jon Rd",
    "sg:city":"Grand Cane",
    "sg:classifiers":[
        {
            "category":"Building & Trades",
            "subcategory":"Plumbing",
            "type":"Services"
        }
    ],
    "sg:phone":"+1 318 858 6637",
    "sg:postcode":"71032",
    "sg:province":"LA",
    "sg:tags":[
        "sheet",
        "work",
        "metal",
        "contractor"
    ],
    "wof:name":"Flip's Sheet Metal",
    "wof:placetype":"venue"
},
  "geometry": {"coordinates":[-93.797217,32.095243],"type":"Point"}
}