{
  "type": "Feature",
  "properties": {
    "iso:country":"US",
    "sg:address":"53409 W Fontana Rd",
    "sg:city":"Independence",
    "sg:classifiers":[
        {
            "category":"Recreation",
            "type":"Entertainment"
        }
    ],
    "sg:phone":"+1 985 878 0044",
    "sg:postcode":"70443",
    "sg:province":"LA",
    "sg:tags":[
        "parks"
    ],
    "wof:name":"Independence Recreation Park",
    "wof:placetype":"venue"
},
  "geometry": {"coordinates":[-90.530241,30.624778],"type":"Point"}
}