{
  "type": "Feature",
  "properties": {
    "iso:country":"US",
    "sg:address":"108 Old Bastrop Rd",
    "sg:city":"Monroe",
    "sg:classifiers":[
        {
            "category":"Retail",
            "subcategory":"Auto Repair",
            "type":"Services"
        }
    ],
    "sg:phone":"+1 318 343 1900",
    "sg:postcode":"71203",
    "sg:province":"LA",
    "sg:tags":[
        "transmission"
    ],
    "wof:name":"All Automatic Trans Co",
    "wof:placetype":"venue"
},
  "geometry": {"coordinates":[-92.032456,32.530312],"type":"Point"}
}