{
  "type": "Feature",
  "properties": {
    "addr:full":"1104 Jackson St Lake Charles LA 70601",
    "addr:housenumber":"1104",
    "addr:postcode":"70601",
    "addr:street":"Jackson St",
    "iso:country":"US",
    "sg:address":"1104 Jackson St",
    "sg:city":"Lake Charles",
    "sg:classifiers":[
        {
            "category":"Organizations",
            "subcategory":"Religious Organization",
            "type":"Services"
        }
    ],
    "sg:phone":"+1 337 433 2415",
    "sg:postcode":"70601",
    "sg:province":"LA",
    "sg:tags":[
        "church"
    ],
    "wof:name":"St Paul African Methodist Chr",
    "wof:placetype":"venue"
},
  "geometry": {"coordinates":[-93.204337,30.23969],"type":"Point"}
}