{
  "type": "Feature",
  "properties": {
    "iso:country":"US",
    "sg:address":"220 N Alexander Ave",
    "sg:city":"Port Allen",
    "sg:classifiers":[
        {
            "category":"Food & Beverages",
            "subcategory":"Groceries & Convenience Stores",
            "type":"Retail Goods"
        }
    ],
    "sg:phone":"+1 225 344 4265",
    "sg:postcode":"70767",
    "sg:province":"LA",
    "sg:tags":[
        "grocer"
    ],
    "wof:name":"Port Allen Supermarket Pharm",
    "wof:placetype":"venue"
},
  "geometry": {"coordinates":[-91.21029,30.454053],"type":"Point"}
}