{
  "type": "Feature",
  "properties": {
    "addr:full":"1403 W Esplanade Ave Kenner LA 70065",
    "addr:housenumber":"1403",
    "addr:postcode":"70065",
    "addr:street":"W Esplanade Ave",
    "iso:country":"US",
    "sg:address":"1403 W Esplanade Ave",
    "sg:city":"Kenner",
    "sg:classifiers":[
        {
            "category":"Professional",
            "subcategory":"Lawyer & Legal Services",
            "type":"Services"
        }
    ],
    "sg:phone":"+1 504 464 7000",
    "sg:postcode":"70065",
    "sg:province":"LA",
    "sg:tags":[
        "attorney"
    ],
    "wof:name":"Montgomery Law Ctr",
    "wof:placetype":"venue"
},
  "geometry": {"coordinates":[-90.245262,30.019903],"type":"Point"}
}