{
  "type": "Feature",
  "properties": {
    "iso:country":"US",
    "sg:address":"4238 Magazine St",
    "sg:city":"New Orleans",
    "sg:classifiers":[
        {
            "category":"Restaurant",
            "type":"Food & Drink"
        },
        {
            "category":"Food & Beverages",
            "subcategory":"Groceries & Convenience Stores",
            "type":"Retail Goods"
        }
    ],
    "sg:menulink":"http://www.allmenus.com/la/new-orleans/274236-la-petite-grocery/menu/",
    "sg:phone":"+1 504 891 3377",
    "sg:postcode":"70115",
    "sg:province":"LA",
    "sg:tags":[
        "french"
    ],
    "wof:name":"La Petite Grocery",
    "wof:placetype":"venue"
},
  "geometry": {"coordinates":[-90.099553,29.920797],"type":"Point"}
}