{
  "type": "Feature",
  "properties": {
    "iso:country":"US",
    "sg:address":"6700 Florida Blvd",
    "sg:city":"Baton Rouge",
    "sg:classifiers":[
        {
            "category":"Retail",
            "subcategory":"Funeral Services",
            "type":"Services"
        }
    ],
    "sg:phone":"+1 225 924 7241",
    "sg:postcode":"70806",
    "sg:province":"LA",
    "sg:tags":[
        "director"
    ],
    "wof:name":"Welsh Funeral Home",
    "wof:placetype":"venue"
},
  "geometry": {"coordinates":[-91.12104600000001,30.451535],"type":"Point"}
}