{
  "type": "Feature",
  "properties": {
    "iso:country":"US",
    "sg:address":"2901 Kirkman St",
    "sg:city":"Lake Charles",
    "sg:classifiers":[
        {
            "category":"Autos & Motor Vehicles",
            "subcategory":"Automobile Sales",
            "type":"Retail Goods"
        }
    ],
    "sg:phone":"+1 337 437 3933",
    "sg:postcode":"70601",
    "sg:province":"LA",
    "sg:tags":[
        "car",
        "dealer"
    ],
    "wof:name":"National Auto Mart",
    "wof:placetype":"venue"
},
  "geometry": {"coordinates":[-93.209789,30.202545],"type":"Point"}
}