{
  "type": "Feature",
  "properties": {
    "iso:country":"US",
    "sg:address":"204 Scotchpine Dr",
    "sg:city":"Mandeville",
    "sg:classifiers":[
        {
            "category":"Building & Trades",
            "subcategory":"Construction",
            "type":"Services"
        }
    ],
    "sg:phone":"+1 985 845 4501",
    "sg:postcode":"70471",
    "sg:province":"LA",
    "sg:tags":[
        "general",
        "contractor"
    ],
    "wof:name":"Parker Lehman Construction Co",
    "wof:placetype":"venue"
},
  "geometry": {"coordinates":[-90.128631,30.402975],"type":"Point"}
}