{
  "type": "Feature",
  "properties": {
    "addr:full":"11022 Gibbens Rd Baton Rouge LA 70807",
    "addr:housenumber":"11022",
    "addr:postcode":"70807",
    "addr:street":"Gibbens Rd",
    "iso:country":"US",
    "sg:address":"11022 Gibbens Rd",
    "sg:city":"Baton Rouge",
    "sg:classifiers":[
        {
            "category":"Organizations",
            "subcategory":"Religious Organization",
            "type":"Services"
        }
    ],
    "sg:phone":"+1 225 775 3304",
    "sg:postcode":"70807",
    "sg:province":"LA",
    "sg:tags":[
        "church"
    ],
    "wof:name":"Mt Peliour Church Of God",
    "wof:placetype":"venue"
},
  "geometry": {"coordinates":[-91.156145,30.550449],"type":"Point"}
}