{
  "type": "Feature",
  "properties": {
    "iso:country":"US",
    "sg:address":"951 Mott St",
    "sg:city":"Franklinton",
    "sg:classifiers":[
        {
            "category":"Banks & Credit Unions",
            "subcategory":"Bank",
            "type":"Services"
        }
    ],
    "sg:phone":"+1 985 839 2777",
    "sg:postcode":"70438",
    "sg:province":"LA",
    "sg:tags":[
        "loan"
    ],
    "wof:name":"Advantage Financial Svc",
    "wof:placetype":"venue"
},
  "geometry": {"coordinates":[-90.152411,30.845727],"type":"Point"}
}