{
  "type": "Feature",
  "properties": {
    "iso:country":"US",
    "sg:address":"806 Holt St",
    "sg:city":"Tallulah",
    "sg:classifiers":[
        {
            "category":"Restaurant",
            "type":"Food & Drink"
        }
    ],
    "sg:phone":"+1 318 574 9230",
    "sg:postcode":"71282",
    "sg:province":"LA",
    "sg:tags":[
        "caterer"
    ],
    "wof:name":"Hall's Catering",
    "wof:placetype":"venue"
},
  "geometry": {"coordinates":[-91.178257,32.414107],"type":"Point"}
}