{
  "type": "Feature",
  "properties": {
    "addr:full":"304 South St Natchitoches LA 71457",
    "addr:housenumber":"304",
    "addr:postcode":"71457",
    "addr:street":"South St",
    "iso:country":"US",
    "sg:address":"304 South St",
    "sg:city":"Natchitoches",
    "sg:classifiers":[
        {
            "category":"Insurance",
            "subcategory":"Insurance Agent",
            "type":"Services"
        }
    ],
    "sg:phone":"+1 318 352 8361",
    "sg:postcode":"71457",
    "sg:province":"LA",
    "wof:name":"State Farm Insurance",
    "wof:placetype":"venue"
},
  "geometry": {"coordinates":[-93.092265,31.756781],"type":"Point"}
}