{
  "type": "Feature",
  "properties": {
    "iso:country":"US",
    "sg:address":"440 Chartres St",
    "sg:city":"New Orleans",
    "sg:classifiers":[
        {
            "category":"Restaurant",
            "type":"Food & Drink"
        }
    ],
    "sg:phone":"+1 504 524 8990",
    "sg:postcode":"70130",
    "sg:province":"LA",
    "sg:tags":[
        "cajun/creole"
    ],
    "sg:website":"www.pierremasperosrestaurant.com/",
    "wof:name":"The Original Pierre Maspero's",
    "wof:placetype":"venue"
},
  "geometry": {"coordinates":[-90.065201,29.955601],"type":"Point"}
}