{
  "type": "Feature",
  "properties": {
    "addr:full":"8412 State Rte 585 Oak Grove LA 71263",
    "addr:housenumber":"8412",
    "addr:postcode":"71263",
    "addr:street":"State Rte 585;Grove",
    "iso:country":"US",
    "sg:address":"8412 State Rte 585",
    "sg:city":"Oak Grove",
    "sg:classifiers":[
        {
            "category":"Home & Garden",
            "subcategory":"Building Materials",
            "type":"Retail Goods"
        }
    ],
    "sg:phone":"+1 318 428 4116",
    "sg:postcode":"71263",
    "sg:province":"LA",
    "wof:name":"Boyd Willie Dirt & Gravel",
    "wof:placetype":"venue"
},
  "geometry": {"coordinates":[-91.53593499999999,32.857205],"type":"Point"}
}