{
  "type": "Feature",
  "properties": {
    "iso:country":"US",
    "sg:address":"3645 Delta Dr",
    "sg:city":"St Gabriel",
    "sg:classifiers":[
        {
            "category":"Freight",
            "type":"Transportation"
        }
    ],
    "sg:phone":"+1 225 642 5338",
    "sg:postcode":"70776",
    "sg:province":"LA",
    "sg:tags":[
        "dry",
        "bulk",
        "trucking"
    ],
    "sg:website":"www.mckenzietanklines.com",
    "wof:name":"Mc Kenzie Tank Lines",
    "wof:placetype":"venue"
},
  "geometry": {"coordinates":[-91.072209,30.256014],"type":"Point"}
}