{
  "type": "Feature",
  "properties": {
    "iso:country":"US",
    "sg:address":"1117 Jeane Chapel Rd",
    "sg:city":"Leesville",
    "sg:classifiers":[
        {
            "category":"Freight",
            "type":"Transportation"
        }
    ],
    "sg:phone":"+1 337 535 1024",
    "sg:postcode":"71446",
    "sg:province":"LA",
    "sg:tags":[
        "mobile",
        "home"
    ],
    "wof:name":"Leesville Mobile Home",
    "wof:placetype":"venue"
},
  "geometry": {"coordinates":[-93.253899,31.068785],"type":"Point"}
}