{
  "type": "Feature",
  "properties": {
    "iso:country":"US",
    "sg:address":"7026 Airline Hwy",
    "sg:city":"Baton Rouge",
    "sg:classifiers":[
        {
            "category":"Retail",
            "subcategory":"Auto Repair",
            "type":"Services"
        }
    ],
    "sg:phone":"+1 225 355 8480",
    "sg:postcode":"70805",
    "sg:province":"LA",
    "sg:tags":[
        "repairing",
        "automobile"
    ],
    "wof:name":"Shorty's Radiator Svc",
    "wof:placetype":"venue"
},
  "geometry": {"coordinates":[-91.12074800000001,30.487813],"type":"Point"}
}