{
  "type": "Feature",
  "properties": {
    "iso:country":"US",
    "sg:address":"1401 S Harvard St",
    "sg:city":"Alexandria",
    "sg:classifiers":[
        {
            "category":"Organizations",
            "subcategory":"Religious Organization",
            "type":"Services"
        }
    ],
    "sg:phone":"+1 318 443 0857",
    "sg:postcode":"71301",
    "sg:province":"LA",
    "wof:name":"Mount Pisgah Baptist Church",
    "wof:placetype":"venue"
},
  "geometry": {"coordinates":[-92.45026799999999,31.287619],"type":"Point"}
}