{
  "type": "Feature",
  "properties": {
    "iso:country":"US",
    "sg:address":"13780 Jefferson Hwy",
    "sg:city":"Baton Rouge",
    "sg:classifiers":[
        {
            "category":"Building & Trades",
            "subcategory":"Construction",
            "type":"Services"
        }
    ],
    "sg:phone":"+1 225 756 5449",
    "sg:postcode":"70817",
    "sg:province":"LA",
    "sg:tags":[
        "roofing",
        "contractor"
    ],
    "wof:name":"Roofmaster/Mastercare Roofing",
    "wof:placetype":"venue"
},
  "geometry": {"coordinates":[-91.03193,30.387062],"type":"Point"}
}