{
  "type": "Feature",
  "properties": {
    "iso:country":"US",
    "sg:address":"2916 N Bolton Ave",
    "sg:city":"Alexandria",
    "sg:classifiers":[
        {
            "category":"Retail",
            "subcategory":"Auto Repair",
            "type":"Services"
        }
    ],
    "sg:phone":"+1 318 487 6622",
    "sg:postcode":"71303",
    "sg:province":"LA",
    "sg:tags":[
        "body",
        "automobile",
        "painting"
    ],
    "wof:name":"Thomasee Paint & Body",
    "wof:placetype":"venue"
},
  "geometry": {"coordinates":[-92.48032600000001,31.325856],"type":"Point"}
}