{
  "type": "Feature",
  "properties": {
    "addr:full":"4921 Pentland Dr New Orleans LA 70128",
    "addr:housenumber":"4921",
    "addr:postcode":"70128",
    "addr:street":"Pentland Dr",
    "iso:country":"US",
    "sg:address":"4921 Pentland Dr",
    "sg:city":"New Orleans",
    "sg:classifiers":[
        {
            "category":"Real Estate",
            "subcategory":"Real Estate Agent",
            "type":"Services"
        }
    ],
    "sg:phone":"+1 504 245 8125",
    "sg:postcode":"70128",
    "sg:province":"LA",
    "wof:name":"G Adrain Harris Properties Inc",
    "wof:placetype":"venue"
},
  "geometry": {"coordinates":[-89.949624,30.027894],"type":"Point"}
}