{
  "type": "Feature",
  "properties": {
    "iso:country":"US",
    "sg:address":"3900 Carlyss Dr",
    "sg:city":"Sulphur",
    "sg:classifiers":[
        {
            "category":"Wholesale",
            "subcategory":"Machinery & Supplies",
            "type":"Manufacturing & Wholesale Goods"
        }
    ],
    "sg:phone":"+1 337 583 4403",
    "sg:postcode":"70665",
    "sg:province":"LA",
    "sg:tags":[
        "burial",
        "vault"
    ],
    "wof:name":"Richard's Vault & Monument",
    "wof:placetype":"venue"
},
  "geometry": {"coordinates":[-93.384618,30.19252],"type":"Point"}
}