{
  "type": "Feature",
  "properties": {
    "addr:full":"1100 Jackson Ave New Orleans LA 70130",
    "addr:housenumber":"1100",
    "addr:postcode":"70130",
    "addr:street":"Jackson Ave",
    "iso:country":"US",
    "sg:address":"1100 Jackson Ave",
    "sg:city":"New Orleans",
    "sg:classifiers":[
        {
            "category":"Real Estate",
            "subcategory":"Architect",
            "type":"Services"
        }
    ],
    "sg:phone":"+1 504 581 7023",
    "sg:postcode":"70130",
    "sg:province":"LA",
    "wof:name":"Koch & Wilson",
    "wof:placetype":"venue"
},
  "geometry": {"coordinates":[-90.07749099999999,29.930398],"type":"Point"}
}