{
  "type": "Feature",
  "properties": {
    "iso:country":"US",
    "sg:address":"704 N Range Ave",
    "sg:city":"Denham Springs",
    "sg:classifiers":[
        {
            "category":"Social Services",
            "subcategory":"Child Care",
            "type":"Services"
        }
    ],
    "sg:phone":"+1 225 665 0620",
    "sg:postcode":"70726",
    "sg:province":"LA",
    "wof:name":"Little Saints Learning Ctr",
    "wof:placetype":"venue"
},
  "geometry": {"coordinates":[-90.95623500000001,30.491231],"type":"Point"}
}