{
  "type": "Feature",
  "properties": {
    "iso:country":"US",
    "sg:address":"407 Main St",
    "sg:city":"Colfax",
    "sg:classifiers":[
        {
            "category":"Organizations",
            "subcategory":"Religious Organization",
            "type":"Services"
        }
    ],
    "sg:phone":"+1 318 627 3603",
    "sg:postcode":"71417",
    "sg:province":"LA",
    "sg:tags":[
        "church"
    ],
    "wof:name":"Colfax United Methodist",
    "wof:placetype":"venue"
},
  "geometry": {"coordinates":[-92.71060199999999,31.517589],"type":"Point"}
}