{
  "type": "Feature",
  "properties": {
    "addr:full":"4810 Lake St Lake Charles LA 70605",
    "addr:housenumber":"4810",
    "addr:postcode":"70605",
    "addr:street":"Lake St",
    "iso:country":"US",
    "sg:address":"4810 Lake St",
    "sg:city":"Lake Charles",
    "sg:classifiers":[
        {
            "category":"Health Services",
            "subcategory":"Doctor",
            "type":"Services"
        }
    ],
    "sg:phone":"+1 337 474 4193",
    "sg:postcode":"70605",
    "sg:province":"LA",
    "sg:tags":[
        "dentist"
    ],
    "wof:name":"Charles E Guth DDS",
    "wof:placetype":"venue"
},
  "geometry": {"coordinates":[-93.232409,30.17078],"type":"Point"}
}