{
  "type": "Feature",
  "properties": {
    "addr:full":"1702 Main St Baker LA 70714",
    "addr:housenumber":"1702",
    "addr:postcode":"70714",
    "addr:street":"Main St",
    "iso:country":"US",
    "sg:address":"1702 Main St",
    "sg:city":"Baker",
    "sg:classifiers":[
        {
            "category":"Banks & Credit Unions",
            "subcategory":"Bank",
            "type":"Services"
        }
    ],
    "sg:phone":"+1 225 332 4310",
    "sg:postcode":"70714",
    "sg:province":"LA",
    "wof:name":"Bank One",
    "wof:placetype":"venue"
},
  "geometry": {"coordinates":[-91.16712800000001,30.593014],"type":"Point"}
}