{
  "type": "Feature",
  "properties": {
    "iso:country":"US",
    "sg:address":"23085 State Rte 1",
    "sg:city":"Plaquemine",
    "sg:classifiers":[
        {
            "category":"Autos & Motor Vehicles",
            "subcategory":"Automobile Sales",
            "type":"Retail Goods"
        }
    ],
    "sg:phone":"+1 225 687 9244",
    "sg:postcode":"70764",
    "sg:province":"LA",
    "sg:tags":[
        "car",
        "dealer"
    ],
    "wof:name":"Iberville Motors Inc",
    "wof:placetype":"venue"
},
  "geometry": {"coordinates":[-91.240741,30.297082],"type":"Point"}
}