{
  "type": "Feature",
  "properties": {
    "iso:country":"US",
    "sg:address":"10323 Ginger Place Dr",
    "sg:city":"Baton Rouge",
    "sg:classifiers":[
        {
            "category":"Professional",
            "type":"Services"
        }
    ],
    "sg:phone":"+1 225 752 0354",
    "sg:postcode":"70817",
    "sg:province":"LA",
    "wof:name":"Emergency Training Service",
    "wof:placetype":"venue"
},
  "geometry": {"coordinates":[-90.975635,30.355406],"type":"Point"}
}