{
  "type": "Feature",
  "properties": {
    "addr:full":"14849 Old Hammond Hwy Baton Rouge LA 70816",
    "addr:housenumber":"14849",
    "addr:postcode":"70816",
    "addr:street":"Old Hammond Hwy",
    "iso:country":"US",
    "sg:address":"14849 Old Hammond Hwy",
    "sg:city":"Baton Rouge",
    "sg:classifiers":[
        {
            "category":"Building & Trades",
            "subcategory":"Construction",
            "type":"Services"
        }
    ],
    "sg:phone":"+1 225 275 3712",
    "sg:postcode":"70816",
    "sg:province":"LA",
    "sg:tags":[
        "home",
        "improvement"
    ],
    "wof:name":"Great Scot Home Maintenance",
    "wof:placetype":"venue"
},
  "geometry": {"coordinates":[-91.021218,30.453531],"type":"Point"}
}