{
  "type": "Feature",
  "properties": {
    "addr:full":"301 Seattle St New Orleans LA 70124",
    "addr:housenumber":"301",
    "addr:postcode":"70124",
    "addr:street":"Seattle St",
    "iso:country":"US",
    "sg:address":"301 Seattle St",
    "sg:city":"New Orleans",
    "sg:classifiers":[
        {
            "category":"Restaurant",
            "type":"Food & Drink"
        }
    ],
    "sg:phone":"+1 504 486 8157",
    "sg:postcode":"70124",
    "sg:province":"LA",
    "sg:tags":[
        "caterer"
    ],
    "wof:name":"Fleur De Lis Catering",
    "wof:placetype":"venue"
},
  "geometry": {"coordinates":[-90.119607,30.012762],"type":"Point"}
}