{
  "type": "Feature",
  "properties": {
    "iso:country":"US",
    "sg:address":"718 Broadway St",
    "sg:city":"Delhi",
    "sg:classifiers":[
        {
            "category":"Restaurant",
            "type":"Food & Drink"
        }
    ],
    "sg:phone":"+1 318 878 9090",
    "sg:postcode":"71232",
    "sg:province":"LA",
    "wof:name":"Chicken Basket",
    "wof:placetype":"venue"
},
  "geometry": {"coordinates":[-91.49299600000001,32.451406],"type":"Point"}
}