{
  "type": "Feature",
  "properties": {
    "iso:country":"US",
    "sg:address":"1281 Hwy 3072",
    "sg:city":"Ruston",
    "sg:classifiers":[
        {
            "category":"Insurance",
            "subcategory":"Insurance Agent",
            "type":"Services"
        }
    ],
    "sg:phone":"+1 318 255 8234",
    "sg:postcode":"71270",
    "sg:province":"LA",
    "wof:name":"American Modern Home Insurance",
    "wof:placetype":"venue"
},
  "geometry": {"coordinates":[-92.60467800000001,32.598213],"type":"Point"}
}