{
  "type": "Feature",
  "properties": {
    "addr:full":"400 Wilmuth St Monroe LA 71201",
    "addr:housenumber":"400",
    "addr:postcode":"71201",
    "addr:street":"Wilmuth St",
    "iso:country":"US",
    "sg:address":"400 Wilmuth St",
    "sg:city":"Monroe",
    "sg:classifiers":[
        {
            "category":"Personal",
            "subcategory":"Beauty Salon",
            "type":"Services"
        }
    ],
    "sg:phone":"+1 318 361 0029",
    "sg:postcode":"71201",
    "sg:province":"LA",
    "wof:name":"Mardis's Hair Salon",
    "wof:placetype":"venue"
},
  "geometry": {"coordinates":[-92.109781,32.541849],"type":"Point"}
}