{
  "type": "Feature",
  "properties": {
    "addr:full":"3300 W Esplanade Ave S Metairie LA 70002",
    "addr:housenumber":"3300",
    "addr:postcode":"70002",
    "addr:street":"W Esplanade Ave S Metairie",
    "iso:country":"US",
    "sg:address":"3300 W Esplanade Ave S",
    "sg:city":"Metairie",
    "sg:classifiers":[
        {
            "category":"Professional",
            "subcategory":"Detective & Security Services",
            "type":"Services"
        }
    ],
    "sg:phone":"+1 504 831 3048",
    "sg:postcode":"70002",
    "sg:province":"LA",
    "sg:tags":[
        "guard",
        "patrol"
    ],
    "wof:name":"Securitas Security Svc USA",
    "wof:placetype":"venue"
},
  "geometry": {"coordinates":[-90.157844,30.014066],"type":"Point"}
}