{
  "type": "Feature",
  "properties": {
    "iso:country":"US",
    "sg:address":"207 Park St",
    "sg:city":"Patterson",
    "sg:classifiers":[
        {
            "category":"Health Services",
            "subcategory":"Doctor",
            "type":"Services"
        }
    ],
    "sg:phone":"+1 985 399 0649",
    "sg:postcode":"70392",
    "sg:province":"LA",
    "sg:tags":[
        "physician",
        "surgeon"
    ],
    "wof:name":"Russo Clinic",
    "wof:placetype":"venue"
},
  "geometry": {"coordinates":[-91.304542,29.696203],"type":"Point"}
}