{
  "type": "Feature",
  "properties": {
    "addr:full":"819 River Rd Shreveport LA 71105",
    "addr:housenumber":"819",
    "addr:postcode":"71105",
    "addr:street":"River Rd",
    "iso:country":"US",
    "sg:address":"819 River Rd",
    "sg:city":"Shreveport",
    "sg:classifiers":[
        {
            "category":"Building & Trades",
            "subcategory":"Construction",
            "type":"Services"
        }
    ],
    "sg:phone":"+1 318 865 7494",
    "sg:postcode":"71105",
    "sg:province":"LA",
    "sg:tags":[
        "contractor"
    ],
    "wof:name":"Steve Cassard Builders",
    "wof:placetype":"venue"
},
  "geometry": {"coordinates":[-93.71153700000001,32.47461],"type":"Point"}
}