{
  "type": "Feature",
  "properties": {
    "addr:full":"5441 Church Point Hwy Rayne LA 70578",
    "addr:housenumber":"5441",
    "addr:postcode":"70578",
    "addr:street":"Church Point Hwy",
    "iso:country":"US",
    "sg:address":"5441 Church Point Hwy",
    "sg:city":"Rayne",
    "sg:classifiers":[
        {
            "category":"Building & Trades",
            "subcategory":"Plumbing",
            "type":"Services"
        }
    ],
    "sg:phone":"+1 337 334 2203",
    "sg:postcode":"70578",
    "sg:province":"LA",
    "sg:tags":[
        "plumbing",
        "contractor"
    ],
    "wof:name":"Mike Castille Plumbing",
    "wof:placetype":"venue"
},
  "geometry": {"coordinates":[-92.26309500000001,30.287029],"type":"Point"}
}