{
  "type": "Feature",
  "properties": {
    "iso:country":"US",
    "sg:address":"1226 Saint Mary Rd",
    "sg:city":"Eunice",
    "sg:classifiers":[
        {
            "category":"Building & Trades",
            "subcategory":"Plumbing",
            "type":"Services"
        }
    ],
    "sg:phone":"+1 337 457 4234",
    "sg:postcode":"70535",
    "sg:province":"LA",
    "sg:tags":[
        "plumbing",
        "contractor"
    ],
    "wof:name":"Charles Guillory Inc",
    "wof:placetype":"venue"
},
  "geometry": {"coordinates":[-92.38925399999999,30.517236],"type":"Point"}
}