{
  "type": "Feature",
  "properties": {
    "iso:country":"US",
    "sg:address":"624 Pine Hill Rd",
    "sg:city":"Shreveport",
    "sg:classifiers":[
        {
            "category":"Wholesale",
            "subcategory":"Hardware",
            "type":"Manufacturing & Wholesale Goods"
        }
    ],
    "sg:phone":"+1 318 929 3711",
    "sg:postcode":"71107",
    "sg:province":"LA",
    "sg:tags":[
        "equipment",
        "soda",
        "fountain",
        "refrigeration"
    ],
    "sg:website":"www.melsclassicsodas.com",
    "wof:name":"Mel's Classic Soda Machines",
    "wof:placetype":"venue"
},
  "geometry": {"coordinates":[-93.789165,32.580367],"type":"Point"}
}