{
  "type": "Feature",
  "properties": {
    "addr:full":"214 Reagan St West Monroe LA 71292",
    "addr:housenumber":"214",
    "addr:postcode":"71292",
    "addr:street":"Reagan St West",
    "iso:country":"US",
    "sg:address":"214 Reagan St",
    "sg:city":"West Monroe",
    "sg:classifiers":[
        {
            "category":"Organizations",
            "subcategory":"Religious Organization",
            "type":"Services"
        }
    ],
    "sg:phone":"+1 318 325 8271",
    "sg:postcode":"71292",
    "sg:province":"LA",
    "sg:tags":[
        "church"
    ],
    "wof:name":"Trinity Baptist Church",
    "wof:placetype":"venue"
},
  "geometry": {"coordinates":[-92.142976,32.489981],"type":"Point"}
}