{
  "type": "Feature",
  "properties": {
    "iso:country":"US",
    "sg:address":"1411 Lindberg Dr",
    "sg:city":"Slidell",
    "sg:classifiers":[
        {
            "category":"Retail",
            "subcategory":"Portrait Studio",
            "type":"Services"
        }
    ],
    "sg:phone":"+1 985 649 3234",
    "sg:postcode":"70458",
    "sg:province":"LA",
    "sg:tags":[
        "photographer"
    ],
    "wof:name":"O' Connell Photography",
    "wof:placetype":"venue"
},
  "geometry": {"coordinates":[-89.75398,30.282359],"type":"Point"}
}