{
  "type": "Feature",
  "properties": {
    "iso:country":"US",
    "sg:address":"3129 Edenborn Ave",
    "sg:city":"Metairie",
    "sg:classifiers":[
        {
            "category":"Real Estate",
            "subcategory":"Architect",
            "type":"Services"
        }
    ],
    "sg:phone":"+1 504 454 3112",
    "sg:postcode":"70002",
    "sg:province":"LA",
    "sg:website":"www.clsarchitects.com",
    "wof:name":"Charles L Silbernagel & Assoc",
    "wof:placetype":"venue"
},
  "geometry": {"coordinates":[-90.161906,30.007008],"type":"Point"}
}