{
  "type": "Feature",
  "properties": {
    "iso:country":"US",
    "sg:address":"712 Harrison Ave",
    "sg:city":"Metairie",
    "sg:classifiers":[
        {
            "category":"Insurance",
            "subcategory":"Insurance Agent",
            "type":"Services"
        }
    ],
    "sg:phone":"+1 504 835 0718",
    "sg:postcode":"70005",
    "sg:province":"LA",
    "sg:tags":[
        "general"
    ],
    "wof:name":"Kullman Insurance Agency Inc",
    "wof:placetype":"venue"
},
  "geometry": {"coordinates":[-90.129722,30.006829],"type":"Point"}
}