{
  "type": "Feature",
  "properties": {
    "iso:country":"US",
    "sg:address":"315 Westbank Expy",
    "sg:city":"Gretna",
    "sg:classifiers":[
        {
            "category":"Shopping",
            "subcategory":"Pharmacy",
            "type":"Retail Goods"
        }
    ],
    "sg:phone":"+1 504 365 8614",
    "sg:postcode":"70053",
    "sg:province":"LA",
    "wof:name":"First Dose Pharmacy",
    "wof:placetype":"venue"
},
  "geometry": {"coordinates":[-90.05486000000001,29.910084],"type":"Point"}
}