{
  "type": "Feature",
  "properties": {
    "iso:country":"US",
    "sg:address":"720 Daspit St",
    "sg:city":"Alexandria",
    "sg:classifiers":[
        {
            "category":"Recreation",
            "type":"Entertainment"
        }
    ],
    "sg:phone":"+1 318 442 4596",
    "sg:postcode":"71302",
    "sg:province":"LA",
    "sg:tags":[
        "club",
        "membership"
    ],
    "wof:name":"Little League Baseball",
    "wof:placetype":"venue"
},
  "geometry": {"coordinates":[-92.418621,31.287264],"type":"Point"}
}