{
  "type": "Feature",
  "properties": {
    "addr:full":"161 Pleasant Rd Ringgold LA 71068",
    "addr:housenumber":"161",
    "addr:postcode":"71068",
    "addr:street":"Pleasant Rd",
    "iso:country":"US",
    "sg:address":"161 Pleasant Rd",
    "sg:city":"Ringgold",
    "sg:phone":"+1 318 894 4433",
    "sg:postcode":"71068",
    "sg:province":"LA",
    "sg:tags":[
        "farm"
    ],
    "wof:name":"Woodard Villa Inc",
    "wof:placetype":"venue"
},
  "geometry": {"coordinates":[-93.255166,32.272406],"type":"Point"}
}