{
  "type": "Feature",
  "properties": {
    "iso:country":"US",
    "sg:address":"136 Carroll St",
    "sg:city":"Shreveport",
    "sg:classifiers":[
        {
            "category":"Shopping",
            "subcategory":"Used Merchandise",
            "type":"Retail Goods"
        }
    ],
    "sg:phone":"+1 318 865 5222",
    "sg:postcode":"71105",
    "sg:province":"LA",
    "wof:name":"Carl Belcher",
    "wof:placetype":"venue"
},
  "geometry": {"coordinates":[-93.713723,32.453838],"type":"Point"}
}