{
  "type": "Feature",
  "properties": {
    "iso:country":"US",
    "sg:address":"2911 State Rte 966",
    "sg:city":"St Francisville",
    "sg:classifiers":[
        {
            "category":"Travel",
            "subcategory":"Travel Agent",
            "type":"Entertainment"
        }
    ],
    "sg:phone":"+1 225 635 3582",
    "sg:postcode":"70775",
    "sg:province":"LA",
    "sg:tags":[
        "tours",
        "promoter"
    ],
    "wof:name":"Southern Hospitality Tours Inc",
    "wof:placetype":"venue"
},
  "geometry": {"coordinates":[-91.30689599999999,30.770045],"type":"Point"}
}