{
  "type": "Feature",
  "properties": {
    "addr:full":"603 Natchez Blvd Opelousas LA 70570",
    "addr:housenumber":"603",
    "addr:postcode":"70570",
    "addr:street":"Natchez Blvd",
    "iso:country":"US",
    "sg:address":"603 Natchez Blvd",
    "sg:city":"Opelousas",
    "sg:classifiers":[
        {
            "category":"Shopping",
            "type":"Retail Goods"
        }
    ],
    "sg:phone":"+1 337 594 1825",
    "sg:postcode":"70570",
    "sg:province":"LA",
    "sg:tags":[
        "chemical"
    ],
    "wof:name":"Janes Industrial Products",
    "wof:placetype":"venue"
},
  "geometry": {"coordinates":[-92.075592,30.545804],"type":"Point"}
}