{
  "type": "Feature",
  "properties": {
    "iso:country":"US",
    "sg:address":"70417 8th St",
    "sg:city":"Covington",
    "sg:classifiers":[
        {
            "category":"Freight",
            "type":"Transportation"
        }
    ],
    "sg:phone":"+1 985 875 7979",
    "sg:postcode":"70433",
    "sg:province":"LA",
    "sg:tags":[
        "mover"
    ],
    "wof:name":"Calvary Movers",
    "wof:placetype":"venue"
},
  "geometry": {"coordinates":[-90.06054899999999,30.457675],"type":"Point"}
}