{
  "type": "Feature",
  "properties": {
    "iso:country":"US",
    "sg:address":"314 W Main St",
    "sg:city":"New Iberia",
    "sg:classifiers":[
        {
            "category":"Health Services",
            "subcategory":"Dentist",
            "type":"Services"
        }
    ],
    "sg:phone":"+1 337 364 0000",
    "sg:postcode":"70560",
    "sg:province":"LA",
    "wof:name":"Guilbeau L C Dr",
    "wof:placetype":"venue"
},
  "geometry": {"coordinates":[-91.821616,30.009719],"type":"Point"}
}