{
  "type": "Feature",
  "properties": {
    "addr:full":"4523 Plank Rd Baton Rouge LA 70805",
    "addr:housenumber":"4523",
    "addr:postcode":"70805",
    "addr:street":"Plank Rd",
    "iso:country":"US",
    "sg:address":"4523 Plank Rd",
    "sg:city":"Baton Rouge",
    "sg:classifiers":[
        {
            "category":"Government",
            "subcategory":"Office",
            "type":"Public Place"
        }
    ],
    "sg:phone":"+1 225 358 4583",
    "sg:postcode":"70805",
    "sg:province":"LA",
    "sg:tags":[
        "village"
    ],
    "wof:name":"Baton Rouge Human Development",
    "wof:placetype":"venue"
},
  "geometry": {"coordinates":[-91.156043,30.491513],"type":"Point"}
}