{
  "type": "Feature",
  "properties": {
    "addr:full":"4151 Viking Dr Bossier City LA 71111",
    "addr:housenumber":"4151",
    "addr:postcode":"71111",
    "addr:street":"Viking Dr",
    "iso:country":"US",
    "sg:address":"4151 Viking Dr",
    "sg:city":"Bossier City",
    "sg:classifiers":[
        {
            "category":"Wholesale",
            "subcategory":"Groceries",
            "type":"Manufacturing & Wholesale Goods"
        }
    ],
    "sg:phone":"+1 318 747 3168",
    "sg:postcode":"71111",
    "sg:province":"LA",
    "sg:tags":[
        "baker"
    ],
    "wof:name":"Interstate Brands Corp",
    "wof:placetype":"venue"
},
  "geometry": {"coordinates":[-93.68731200000001,32.550843],"type":"Point"}
}