{
  "type": "Feature",
  "properties": {
    "iso:country":"US",
    "sg:address":"7837 Youree Dr",
    "sg:city":"Shreveport",
    "sg:classifiers":[
        {
            "category":"Health Services",
            "subcategory":"Doctor",
            "type":"Services"
        }
    ],
    "sg:phone":"+1 318 798 2030",
    "sg:postcode":"71105",
    "sg:province":"LA",
    "sg:tags":[
        "physician",
        "surgeon"
    ],
    "wof:name":"Thomas J Worgul MD",
    "wof:placetype":"venue"
},
  "geometry": {"coordinates":[-93.712445,32.432967],"type":"Point"}
}