{
  "type": "Feature",
  "properties": {
    "iso:country":"US",
    "sg:address":"2000 Old Spanish Trl",
    "sg:city":"Slidell",
    "sg:classifiers":[
        {
            "category":"Insurance",
            "subcategory":"Insurance Agent",
            "type":"Services"
        }
    ],
    "sg:phone":"+1 985 726 5001",
    "sg:postcode":"70458",
    "sg:province":"LA",
    "wof:name":"Allstate Insurance",
    "wof:placetype":"venue"
},
  "geometry": {"coordinates":[-89.76647,30.251055],"type":"Point"}
}