{
  "type": "Feature",
  "properties": {
    "addr:full":"756 Old Spanish Trl Slidell LA 70458",
    "addr:housenumber":"756",
    "addr:postcode":"70458",
    "addr:street":"Old Spanish Trl",
    "iso:country":"US",
    "sg:address":"756 Old Spanish Trl",
    "sg:city":"Slidell",
    "sg:classifiers":[
        {
            "category":"Building & Trades",
            "subcategory":"Construction",
            "type":"Services"
        }
    ],
    "sg:phone":"+1 985 643 3307",
    "sg:postcode":"70458",
    "sg:province":"LA",
    "sg:tags":[
        "contractor"
    ],
    "wof:name":"Schuler's Home Svc",
    "wof:placetype":"venue"
},
  "geometry": {"coordinates":[-89.77887800000001,30.261403],"type":"Point"}
}