{
  "type": "Feature",
  "properties": {
    "iso:country":"US",
    "sg:address":"1501 Utah Beach Dr",
    "sg:city":"Bridge City",
    "sg:classifiers":[
        {
            "category":"Organizations",
            "subcategory":"Religious Organization",
            "type":"Services"
        }
    ],
    "sg:phone":"+1 504 342 1900",
    "sg:postcode":"70094",
    "sg:province":"LA",
    "sg:tags":[
        "church"
    ],
    "wof:name":"Good Samaritan Svc",
    "wof:placetype":"venue"
},
  "geometry": {"coordinates":[-90.163348,29.929112],"type":"Point"}
}