{
  "type": "Feature",
  "properties": {
    "addr:full":"403 S Laurel St Amite LA 70422",
    "addr:housenumber":"403",
    "addr:postcode":"70422",
    "addr:street":"S Laurel St",
    "iso:country":"US",
    "sg:address":"403 S Laurel St",
    "sg:city":"Amite",
    "sg:classifiers":[
        {
            "category":"Education",
            "subcategory":"School",
            "type":"Public Place"
        }
    ],
    "sg:phone":"+1 985 748 9301",
    "sg:postcode":"70422",
    "sg:province":"LA",
    "wof:name":"Amite High School",
    "wof:placetype":"venue"
},
  "geometry": {"coordinates":[-90.506663,30.722524],"type":"Point"}
}