{
  "type": "Feature",
  "properties": {
    "iso:country":"US",
    "sg:address":"514 Oak Manor Dr",
    "sg:city":"New Iberia",
    "sg:classifiers":[
        {
            "category":"Retail",
            "subcategory":"Repair Shop",
            "type":"Services"
        }
    ],
    "sg:phone":"+1 337 364 3352",
    "sg:postcode":"70563",
    "sg:province":"LA",
    "wof:name":"Minuteman Furn Restoration",
    "wof:placetype":"venue"
},
  "geometry": {"coordinates":[-91.78321,30.006667],"type":"Point"}
}