{
  "type": "Feature",
  "properties": {
    "iso:country":"US",
    "sg:address":"599 Hwy 1194",
    "sg:city":"Marksville",
    "sg:classifiers":[
        {
            "category":"Retail",
            "subcategory":"Auto Repair",
            "type":"Services"
        }
    ],
    "sg:phone":"+1 318 253 5427",
    "sg:postcode":"71351",
    "sg:province":"LA",
    "sg:tags":[
        "transmission"
    ],
    "wof:name":"Avoyelles Transmission",
    "wof:placetype":"venue"
},
  "geometry": {"coordinates":[-92.17187,31.119216],"type":"Point"}
}