{
  "type": "Feature",
  "properties": {
    "iso:country":"US",
    "sg:address":"2030 Constance St",
    "sg:city":"New Orleans",
    "sg:classifiers":[
        {
            "category":"Organizations",
            "subcategory":"Religious Organization",
            "type":"Services"
        }
    ],
    "sg:phone":"+1 504 525 2495",
    "sg:postcode":"70130",
    "sg:province":"LA",
    "sg:tags":[
        "shrine"
    ],
    "sg:website":"www.seelos.org",
    "wof:name":"Blessed Francis Seelos Shire",
    "wof:placetype":"venue"
},
  "geometry": {"coordinates":[-90.07464,29.929603],"type":"Point"}
}