{
  "type": "Feature",
  "properties": {
    "addr:city":"New Orleans",
    "addr:full":"2030 Constance St New Orleans, La 70130",
    "addr:house_number":"2030",
    "addr:housenumber":"2030",
    "addr:phone":"+1 504-525-2495",
    "addr:postcode":"70130",
    "addr:road":"Constance St",
    "addr:state":"LA",
    "addr:street":"Constance St",
    "iso:country":"US",
    "sg:address":"2030 Constance St",
    "sg:city":"New Orleans",
    "sg:classifiers":[
        {
            "category":"Organizations",
            "subcategory":"Religious Organization",
            "type":"Services"
        }
    ],
    "sg:phone":"+1 504 525 2495",
    "sg:postcode":"70130",
    "sg:province":"LA",
    "sg:tags":[
        "shrine"
    ],
    "sg:website":"www.seelos.org",
    "wof:airports":[
        102530009,
        102530037,
        102525981
    ],
    "wof:name":"Blessed Francis Seelos Shrine",
    "wof:placetype":"venue"
},
  "geometry": {"coordinates":[-90.07446,29.92967],"type":"Point"}
}