{
  "type": "Feature",
  "properties": {
    "iso:country":"US",
    "sg:address":"1437 Pauger St",
    "sg:city":"New Orleans",
    "sg:classifiers":[
        {
            "category":"Travel",
            "subcategory":"Hotels & Motels",
            "type":"Entertainment"
        }
    ],
    "sg:phone":"+1 504 943 3019",
    "sg:postcode":"70116",
    "sg:province":"LA",
    "sg:tags":[
        "breakfast",
        "accommodation",
        "bed"
    ],
    "sg:website":"www.mentonebandb.com",
    "wof:name":"Mentone Bed and Breakfast",
    "wof:placetype":"venue"
},
  "geometry": {"coordinates":[-90.060303,29.965],"type":"Point"}
}