{
  "type": "Feature",
  "properties": {
    "iso:country":"US",
    "sg:address":"2042 Manhattan Blvd",
    "sg:city":"Harvey",
    "sg:classifiers":[
        {
            "category":"Organizations",
            "subcategory":"Religious Organization",
            "type":"Services"
        }
    ],
    "sg:phone":"+1 504 309 3268",
    "sg:postcode":"70058",
    "sg:province":"LA",
    "sg:tags":[
        "church"
    ],
    "wof:name":"Manhattan Church-God & Christ",
    "wof:placetype":"venue"
},
  "geometry": {"coordinates":[-90.054784,29.885688],"type":"Point"}
}