{
  "type": "Feature",
  "properties": {
    "iso:country":"US",
    "sg:address":"300 S 1st St",
    "sg:city":"Leesville",
    "sg:classifiers":[
        {
            "category":"Professional",
            "subcategory":"Lawyer & Legal Services",
            "type":"Services"
        }
    ],
    "sg:phone":"+1 337 238 3558",
    "sg:postcode":"71446",
    "sg:province":"LA",
    "sg:tags":[
        "attorney"
    ],
    "wof:name":"Guy R Smith Law Office",
    "wof:placetype":"venue"
},
  "geometry": {"coordinates":[-93.25961599999999,31.142001],"type":"Point"}
}