{
  "type": "Feature",
  "properties": {
    "iso:country":"US",
    "sg:address":"705 W Pinhook Rd",
    "sg:city":"Lafayette",
    "sg:classifiers":[
        {
            "category":"Mining & Drilling",
            "type":"Manufacturing & Wholesale Goods"
        }
    ],
    "sg:phone":"+1 337 233 2102",
    "sg:postcode":"70503",
    "sg:province":"LA",
    "sg:tags":[
        "field",
        "oil"
    ],
    "wof:name":"Oil Country Tubular Corp",
    "wof:placetype":"venue"
},
  "geometry": {"coordinates":[-92.012085,30.20643],"type":"Point"}
}