{
  "type": "Feature",
  "properties": {
    "iso:country":"US",
    "sg:address":"1902 Carter St",
    "sg:city":"Vidalia",
    "sg:classifiers":[
        {
            "category":"Personal",
            "subcategory":"Beauty Salon",
            "type":"Services"
        }
    ],
    "sg:phone":"+1 318 336 5163",
    "sg:postcode":"71373",
    "sg:province":"LA",
    "wof:name":"Just Hair",
    "wof:placetype":"venue"
},
  "geometry": {"coordinates":[-91.454376,31.573329],"type":"Point"}
}