{
  "type": "Feature",
  "properties": {
    "addr:full":"3806 Ambassador Caffery Pkwy Lafayette LA 70503",
    "addr:housenumber":"3806",
    "addr:postcode":"70503",
    "addr:street":"Ambassador Caffery Pkwy",
    "iso:country":"US",
    "sg:address":"3806 Ambassador Caffery Pkwy",
    "sg:city":"Lafayette",
    "sg:classifiers":[
        {
            "category":"Food & Beverages",
            "subcategory":"Groceries & Convenience Stores",
            "type":"Retail Goods"
        }
    ],
    "sg:phone":"+1 337 988 2311",
    "sg:postcode":"70503",
    "sg:province":"LA",
    "wof:name":"Circle K",
    "wof:placetype":"venue"
},
  "geometry": {"coordinates":[-92.06613299999999,30.171155],"type":"Point"}
}