{
  "type": "Feature",
  "properties": {
    "iso:country":"US",
    "sg:address":"125 S 14th St",
    "sg:city":"Baton Rouge",
    "sg:classifiers":[
        {
            "category":"Freight",
            "type":"Transportation"
        }
    ],
    "sg:phone":"+1 225 336 1140",
    "sg:postcode":"70802",
    "sg:province":"LA",
    "sg:tags":[
        "warehouse",
        "merchandise"
    ],
    "wof:name":"Ace Storage Inc",
    "wof:placetype":"venue"
},
  "geometry": {"coordinates":[-91.174528,30.443915],"type":"Point"}
}