{
  "type": "Feature",
  "properties": {
    "iso:country":"US",
    "sg:address":"11781 State Rte 23",
    "sg:city":"Belle Chasse",
    "sg:classifiers":[
        {
            "category":"Professional",
            "subcategory":"Engineering",
            "type":"Services"
        }
    ],
    "sg:phone":"+1 504 656 7270",
    "sg:postcode":"70037",
    "sg:province":"LA",
    "sg:tags":[
        "engineer"
    ],
    "wof:name":"Sharon Branan",
    "wof:placetype":"venue"
},
  "geometry": {"coordinates":[-90.03001500000001,29.770501],"type":"Point"}
}