{
  "type": "Feature",
  "properties": {
    "iso:country":"US",
    "sg:address":"1317 E Holly Hill Cir",
    "sg:city":"Westlake",
    "sg:classifiers":[
        {
            "category":"Travel",
            "subcategory":"Travel Agent",
            "type":"Entertainment"
        }
    ],
    "sg:phone":"+1 337 493 1010",
    "sg:postcode":"70669",
    "sg:province":"LA",
    "sg:tags":[
        "agency",
        "bureau"
    ],
    "wof:name":"Network 2 Travel",
    "wof:placetype":"venue"
},
  "geometry": {"coordinates":[-93.250169,30.251091],"type":"Point"}
}