{
  "type": "Feature",
  "properties": {
    "iso:country":"US",
    "sg:address":"6371 Canal Blvd",
    "sg:city":"New Orleans",
    "sg:classifiers":[
        {
            "category":"Organizations",
            "subcategory":"Religious Organization",
            "type":"Services"
        }
    ],
    "sg:phone":"+1 504 486 0989",
    "sg:postcode":"70124",
    "sg:province":"LA",
    "sg:tags":[
        "monastery",
        "convent"
    ],
    "wof:name":"Marianites Of Holy Cross",
    "wof:placetype":"venue"
},
  "geometry": {"coordinates":[-90.107643,30.005388],"type":"Point"}
}