{
  "type": "Feature",
  "properties": {
    "addr:full":"1115 State Rte 529 Sarepta LA 71064",
    "addr:housenumber":"1115",
    "addr:postcode":"71064",
    "addr:street":"State Rte 529 Sarepta",
    "iso:country":"US",
    "sg:address":"1115 State Rte 529",
    "sg:city":"Sarepta",
    "sg:classifiers":[
        {
            "category":"Building & Trades",
            "subcategory":"Plumbing",
            "type":"Services"
        }
    ],
    "sg:phone":"+1 318 326 4539",
    "sg:postcode":"71064",
    "sg:province":"LA",
    "sg:tags":[
        "product",
        "management",
        "energy",
        "system"
    ],
    "wof:name":"KERR-Mc Gee Corp",
    "wof:placetype":"venue"
},
  "geometry": {"coordinates":[-93.498358,32.880734],"type":"Point"}
}