{
  "type": "Feature",
  "properties": {
    "iso:country":"US",
    "sg:address":"724 Papworth Ave",
    "sg:city":"Metairie",
    "sg:classifiers":[
        {
            "category":"Shopping",
            "type":"Retail Goods"
        }
    ],
    "sg:phone":"+1 504 831 8439",
    "sg:postcode":"70005",
    "sg:province":"LA",
    "sg:tags":[
        "equipment",
        "telephone",
        "supply"
    ],
    "sg:website":"www.guywire.com",
    "wof:name":"Guywire Communicaitons Inc",
    "wof:placetype":"venue"
},
  "geometry": {"coordinates":[-90.126949,29.996924],"type":"Point"}
}