{
  "type": "Feature",
  "properties": {
    "addr:full":"429 Germaine St Rayne LA 70578",
    "addr:housenumber":"429",
    "addr:postcode":"70578",
    "addr:street":"Germaine St",
    "iso:country":"US",
    "sg:address":"429 Germaine St",
    "sg:city":"Rayne",
    "sg:classifiers":[
        {
            "category":"Retail",
            "subcategory":"Repair Shop",
            "type":"Services"
        }
    ],
    "sg:phone":"+1 337 334 5660",
    "sg:postcode":"70578",
    "sg:province":"LA",
    "sg:tags":[
        "related"
    ],
    "wof:name":"Juno's Repair Shop",
    "wof:placetype":"venue"
},
  "geometry": {"coordinates":[-92.22766,30.299902],"type":"Point"}
}