{
  "type": "Feature",
  "properties": {
    "iso:country":"US",
    "sg:address":"30 Muirfield Dr",
    "sg:city":"La Place",
    "sg:classifiers":[
        {
            "category":"Health Services",
            "subcategory":"Clinic",
            "type":"Services"
        }
    ],
    "sg:phone":"+1 985 651 4625",
    "sg:postcode":"70068",
    "sg:province":"LA",
    "sg:tags":[
        "specialty",
        "outpatient"
    ],
    "wof:name":"Janis K Ducote",
    "wof:placetype":"venue"
},
  "geometry": {"coordinates":[-90.500063,30.095853],"type":"Point"}
}