{
  "type": "Feature",
  "properties": {
    "addr:full":"32129 S Poitevent Rd Slidell LA 70460",
    "addr:housenumber":"32129",
    "addr:postcode":"70460",
    "addr:street":"S Poitevent Rd",
    "iso:country":"US",
    "sg:address":"32129 S Poitevent Rd",
    "sg:city":"Slidell",
    "sg:classifiers":[
        {
            "category":"Building & Trades",
            "subcategory":"Plumbing",
            "type":"Services"
        }
    ],
    "sg:phone":"+1 985 649 3839",
    "sg:postcode":"70460",
    "sg:province":"LA",
    "sg:tags":[
        "septic"
    ],
    "wof:name":"Parker's Septic Tank & Clng",
    "wof:placetype":"venue"
},
  "geometry": {"coordinates":[-89.86694199999999,30.314675],"type":"Point"}
}