{
  "type": "Feature",
  "properties": {
    "addr:full":"410 N Acadian Throughway Baton Rouge LA 70806",
    "addr:housenumber":"410",
    "addr:postcode":"70806",
    "addr:street":"N Acadian",
    "iso:country":"US",
    "sg:address":"410 N Acadian Throughway",
    "sg:city":"Baton Rouge",
    "sg:classifiers":[
        {
            "category":"Shopping",
            "subcategory":"Music",
            "type":"Retail Goods"
        }
    ],
    "sg:phone":"+1 225 383 4637",
    "sg:postcode":"70806",
    "sg:province":"LA",
    "sg:tags":[
        "compact",
        "record",
        "disc",
        "tape"
    ],
    "wof:name":"Music Treasure Chest",
    "wof:placetype":"venue"
},
  "geometry": {"coordinates":[-91.154657,30.452323],"type":"Point"}
}