{
  "type": "Feature",
  "properties": {
    "addr:full":"1500 Spencer Ave Monroe LA 71201",
    "addr:housenumber":"1500",
    "addr:postcode":"71201",
    "addr:street":"Spencer Ave",
    "iso:country":"US",
    "sg:address":"1500 Spencer Ave",
    "sg:city":"Monroe",
    "sg:classifiers":[
        {
            "category":"Organizations",
            "subcategory":"Religious Organization",
            "type":"Services"
        }
    ],
    "sg:phone":"+1 318 388 8695",
    "sg:postcode":"71201",
    "sg:province":"LA",
    "wof:name":"Windsong Ministries",
    "wof:placetype":"venue"
},
  "geometry": {"coordinates":[-92.119632,32.528641],"type":"Point"}
}