{
  "type": "Feature",
  "properties": {
    "addr:full":"4606 Jones Creek Rd Baton Rouge LA 70817",
    "addr:housenumber":"4606",
    "addr:postcode":"70817",
    "addr:street":"Jones Creek Rd",
    "iso:country":"US",
    "sg:address":"4606 Jones Creek Rd",
    "sg:city":"Baton Rouge",
    "sg:classifiers":[
        {
            "category":"Professional",
            "subcategory":"Computer Services",
            "type":"Services"
        }
    ],
    "sg:phone":"+1 225 753 0301",
    "sg:postcode":"70817",
    "sg:province":"LA",
    "sg:tags":[
        "scanning"
    ],
    "wof:name":"Renaissance Imaging",
    "wof:placetype":"venue"
},
  "geometry": {"coordinates":[-91.01546500000001,30.412064],"type":"Point"}
}