{
  "type": "Feature",
  "properties": {
    "iso:country":"US",
    "sg:address":"3617 Williams Blvd",
    "sg:city":"Kenner",
    "sg:classifiers":[
        {
            "category":"Bars & Pubs",
            "type":"Food & Drink"
        }
    ],
    "sg:phone":"+1 504 443 1137",
    "sg:postcode":"70065",
    "sg:province":"LA",
    "sg:tags":[
        "club",
        "night"
    ],
    "wof:name":"Rhythms Night Club",
    "wof:placetype":"venue"
},
  "geometry": {"coordinates":[-90.239249,30.02283],"type":"Point"}
}