{
  "type": "Feature",
  "properties": {
    "addr:full":"3870 Old Sterlington Rd Monroe LA 71203",
    "addr:housenumber":"3870",
    "addr:postcode":"71203",
    "addr:street":"Old Sterlington Rd",
    "iso:country":"US",
    "sg:address":"3870 Old Sterlington Rd",
    "sg:city":"Monroe",
    "sg:classifiers":[
        {
            "category":"Organizations",
            "subcategory":"Religious Organization",
            "type":"Services"
        }
    ],
    "sg:phone":"+1 318 343 6242",
    "sg:postcode":"71203",
    "sg:province":"LA",
    "wof:name":"Gateway Baptist Church",
    "wof:placetype":"venue"
},
  "geometry": {"coordinates":[-92.066423,32.56334],"type":"Point"}
}