{
  "type": "Feature",
  "properties": {
    "iso:country":"US",
    "sg:address":"9000 Chef Menteur Hwy",
    "sg:city":"New Orleans",
    "sg:classifiers":[
        {
            "category":"Personal",
            "subcategory":"Massage",
            "type":"Services"
        },
        {
            "category":"Personal",
            "type":"Services"
        }
    ],
    "sg:phone":"+1 504 242 4070",
    "sg:postcode":"70127",
    "sg:province":"LA",
    "wof:name":"Hong Kong Spa",
    "wof:placetype":"venue"
},
  "geometry": {"coordinates":[-89.98165299999999,30.015225],"type":"Point"}
}