{
  "type": "Feature",
  "properties": {
    "iso:country":"US",
    "sg:address":"283 Sanders Loop",
    "sg:city":"Sugartown",
    "sg:classifiers":[
        {
            "category":"Professional",
            "subcategory":"Computer Services",
            "type":"Services"
        }
    ],
    "sg:phone":"+1 337 328 7691",
    "sg:postcode":"70662",
    "sg:province":"LA",
    "sg:tags":[
        "datum"
    ],
    "wof:name":"Web Direct Enterprises",
    "wof:placetype":"venue"
},
  "geometry": {"coordinates":[-93.01655599999999,30.781958],"type":"Point"}
}