{
  "type": "Feature",
  "properties": {
    "addr:full":"9490 Airline Hwy Baton Rouge LA 70815",
    "addr:housenumber":"9490",
    "addr:postcode":"70815",
    "addr:street":"Airline Hwy",
    "iso:country":"US",
    "sg:address":"9490 Airline Hwy",
    "sg:city":"Baton Rouge",
    "sg:classifiers":[
        {
            "category":"Insurance",
            "subcategory":"Insurance Agent",
            "type":"Services"
        }
    ],
    "sg:phone":"+1 225 923 2222",
    "sg:postcode":"70815",
    "sg:province":"LA",
    "wof:name":"Direct General Ins Agency",
    "wof:placetype":"venue"
},
  "geometry": {"coordinates":[-91.084236,30.43663],"type":"Point"}
}