{
  "type": "Feature",
  "properties": {
    "iso:country":"US",
    "sg:address":"1400 Opelousas St",
    "sg:city":"Lake Charles",
    "sg:classifiers":[
        {
            "category":"Education",
            "subcategory":"School",
            "type":"Public Place"
        }
    ],
    "sg:phone":"+1 337 436 7103",
    "sg:postcode":"70601",
    "sg:province":"LA",
    "wof:name":"Ralph W Wilson Elementary Schl",
    "wof:placetype":"venue"
},
  "geometry": {"coordinates":[-93.200093,30.2422],"type":"Point"}
}