{
  "type": "Feature",
  "properties": {
    "iso:country":"US",
    "sg:address":"708 E Madison Ave",
    "sg:city":"Bastrop",
    "sg:classifiers":[
        {
            "category":"Banks & Credit Unions",
            "subcategory":"Bank",
            "type":"Services"
        }
    ],
    "sg:phone":"+1 318 283 9900",
    "sg:postcode":"71220",
    "sg:province":"LA",
    "sg:tags":[
        "loan"
    ],
    "wof:name":"World Finance Corp",
    "wof:placetype":"venue"
},
  "geometry": {"coordinates":[-91.904878,32.779141],"type":"Point"}
}