{
  "type": "Feature",
  "properties": {
    "iso:country":"US",
    "sg:address":"3747 Moss St",
    "sg:city":"Lafayette",
    "sg:classifiers":[
        {
            "category":"Shopping",
            "subcategory":"Pharmacy",
            "type":"Retail Goods"
        }
    ],
    "sg:phone":"+1 337 291 1808",
    "sg:postcode":"70507",
    "sg:province":"LA",
    "sg:tags":[
        "drugstore"
    ],
    "sg:website":"www.walgreens.com",
    "wof:name":"Walgreen Drug Stores",
    "wof:placetype":"venue"
},
  "geometry": {"coordinates":[-92.008102,30.275499],"type":"Point"}
}