{
  "type": "Feature",
  "properties": {
    "addr:full":"306 S Buchanan St Lafayette LA 70501",
    "addr:housenumber":"306",
    "addr:postcode":"70501",
    "addr:street":"S Buchanan St",
    "iso:country":"US",
    "sg:address":"306 S Buchanan St",
    "sg:city":"Lafayette",
    "sg:classifiers":[
        {
            "category":"Utilities",
            "subcategory":"Telephone",
            "type":"Services"
        }
    ],
    "sg:phone":"+1 337 265 3000",
    "sg:postcode":"70501",
    "sg:province":"LA",
    "sg:tags":[
        "telecommunication"
    ],
    "wof:name":"A & M 24 Hour Answering Svc",
    "wof:placetype":"venue"
},
  "geometry": {"coordinates":[-92.017371,30.227794],"type":"Point"}
}