{
  "type": "Feature",
  "properties": {
    "iso:country":"US",
    "sg:address":"3323 Ambassador Caffery Pkwy",
    "sg:city":"Lafayette",
    "sg:classifiers":[
        {
            "category":"Restaurant",
            "type":"Food & Drink"
        }
    ],
    "sg:menulink":"http://www.allmenus.com/la/carencro/99507-logans-roadhouse/menu/",
    "sg:phone":"+1 337 991 9150",
    "sg:postcode":"70506",
    "sg:province":"LA",
    "sg:tags":[
        "american"
    ],
    "wof:name":"Logan's Roadhouse",
    "wof:placetype":"venue"
},
  "geometry": {"coordinates":[-92.074985,30.179441],"type":"Point"}
}