{
  "type": "Feature",
  "properties": {
    "iso:country":"US",
    "sg:address":"230 Carroll St",
    "sg:city":"Shreveport",
    "sg:classifiers":[
        {
            "category":"Health Services",
            "subcategory":"Doctor",
            "type":"Services"
        }
    ],
    "sg:phone":"+1 318 869 2593",
    "sg:postcode":"71105",
    "sg:province":"LA",
    "sg:tags":[
        "dentist"
    ],
    "wof:name":"Jeffrey B Jeter DDS",
    "wof:placetype":"venue"
},
  "geometry": {"coordinates":[-93.722042,32.453082],"type":"Point"}
}