{
  "type": "Feature",
  "properties": {
    "addr:full":"2300 S Claiborne Ave New Orleans LA 70125",
    "addr:housenumber":"2300",
    "addr:postcode":"70125",
    "addr:street":"S Claiborne Ave",
    "iso:country":"US",
    "sg:address":"2300 S Claiborne Ave",
    "sg:city":"New Orleans",
    "sg:classifiers":[
        {
            "category":"Utilities",
            "subcategory":"Mobile Phone",
            "type":"Services"
        }
    ],
    "sg:phone":"+1 504 581 2337",
    "sg:postcode":"70125",
    "sg:province":"LA",
    "sg:tags":[
        "repair",
        "beeper"
    ],
    "wof:name":"USA Beepers",
    "wof:placetype":"venue"
},
  "geometry": {"coordinates":[-90.09116899999999,29.944201],"type":"Point"}
}