{
  "type": "Feature",
  "properties": {
    "iso:country":"US",
    "sg:address":"777 Florida St",
    "sg:city":"Baton Rouge",
    "sg:classifiers":[
        {
            "category":"Government",
            "subcategory":"Office",
            "type":"Public Place"
        }
    ],
    "sg:phone":"+1 225 389 0735",
    "sg:postcode":"70801",
    "sg:province":"LA",
    "sg:tags":[
        "federal",
        "govt",
        "program"
    ],
    "wof:name":"Us Env Protection Agency",
    "wof:placetype":"venue"
},
  "geometry": {"coordinates":[-91.1827,30.449552],"type":"Point"}
}