{
  "type": "Feature",
  "properties": {
    "addr:full":"10550 Airline Hwy Baton Rouge LA 70816",
    "addr:housenumber":"10550",
    "addr:postcode":"70816",
    "addr:street":"Airline Hwy",
    "iso:country":"US",
    "sg:address":"10550 Airline Hwy",
    "sg:city":"Baton Rouge",
    "sg:classifiers":[
        {
            "category":"Professional",
            "subcategory":"Engineering",
            "type":"Services"
        }
    ],
    "sg:phone":"+1 225 293 6600",
    "sg:postcode":"70816",
    "sg:province":"LA",
    "sg:tags":[
        "engineer"
    ],
    "sg:website":"www.urscorp.com",
    "wof:name":"URS Corp",
    "wof:placetype":"venue"
},
  "geometry": {"coordinates":[-91.06411300000001,30.410172],"type":"Point"}
}