{
  "type": "Feature",
  "properties": {
    "addr:full":"11450 Coursey Blvd Baton Rouge LA 70816",
    "addr:housenumber":"11450",
    "addr:postcode":"70816",
    "addr:street":"Coursey Blvd",
    "iso:country":"US",
    "sg:address":"11450 Coursey Blvd",
    "sg:city":"Baton Rouge",
    "sg:classifiers":[
        {
            "category":"Utilities",
            "subcategory":"Mobile Phone",
            "type":"Services"
        }
    ],
    "sg:phone":"+1 225 769 6500",
    "sg:postcode":"70816",
    "sg:province":"LA",
    "sg:tags":[
        "telephone",
        "cellular"
    ],
    "sg:website":"www.nexcomla.com",
    "wof:name":"Nex Com",
    "wof:placetype":"venue"
},
  "geometry": {"coordinates":[-91.058201,30.414888],"type":"Point"}
}