{
  "type": "Feature",
  "properties": {
    "addr:full":"312 E Main St Jonesboro LA 71251",
    "addr:housenumber":"312",
    "addr:postcode":"71251",
    "addr:street":"E Main St",
    "iso:country":"US",
    "sg:address":"312 E Main St",
    "sg:city":"Jonesboro",
    "sg:classifiers":[
        {
            "category":"Retail",
            "subcategory":"Self-service Laundry",
            "type":"Services"
        }
    ],
    "sg:phone":"+1 318 259 7989",
    "sg:postcode":"71251",
    "sg:province":"LA",
    "wof:name":"Wash World",
    "wof:placetype":"venue"
},
  "geometry": {"coordinates":[-92.709709,32.240951],"type":"Point"}
}