{
  "type": "Feature",
  "properties": {
    "iso:country":"US",
    "sg:address":"1100 W Port St",
    "sg:city":"Abbeville",
    "sg:classifiers":[
        {
            "category":"Personal",
            "subcategory":"Beauty Salon",
            "type":"Services"
        }
    ],
    "sg:phone":"+1 337 893 6608",
    "sg:postcode":"70510",
    "sg:province":"LA",
    "wof:name":"Lee Anna's Beauty Salon",
    "wof:placetype":"venue"
},
  "geometry": {"coordinates":[-92.146317,29.976304],"type":"Point"}
}