{
  "type": "Feature",
  "properties": {
    "iso:country":"US",
    "sg:address":"113 Parkway Dr",
    "sg:city":"Lafayette",
    "sg:classifiers":[
        {
            "category":"Government",
            "subcategory":"Office",
            "type":"Public Place"
        }
    ],
    "sg:phone":"+1 337 236 8977",
    "sg:postcode":"70508",
    "sg:province":"LA",
    "sg:tags":[
        "management"
    ],
    "wof:name":"Shaw Environmental  Inc",
    "wof:placetype":"venue"
},
  "geometry": {"coordinates":[-92.05893399999999,30.150161],"type":"Point"}
}