{
  "type": "Feature",
  "properties": {
    "addr:full":"403 Thomas Rd West Monroe LA 71292",
    "addr:housenumber":"403",
    "addr:postcode":"71292",
    "addr:street":"Thomas Rd West",
    "iso:country":"US",
    "sg:address":"403 Thomas Rd",
    "sg:city":"West Monroe",
    "sg:classifiers":[
        {
            "category":"Shopping",
            "subcategory":"Florist",
            "type":"Retail Goods"
        }
    ],
    "sg:phone":"+1 318 322 4899",
    "sg:postcode":"71292",
    "sg:province":"LA",
    "wof:name":"Flowerama",
    "wof:placetype":"venue"
},
  "geometry": {"coordinates":[-92.157273,32.505716],"type":"Point"}
}