{
  "type": "Feature",
  "properties": {
    "addr:full":"17473 Lake Iris Ave Baton Rouge LA 70817",
    "addr:housenumber":"17473",
    "addr:postcode":"70817",
    "addr:street":"Lake Iris Ave",
    "iso:country":"US",
    "sg:address":"17473 Lake Iris Ave",
    "sg:city":"Baton Rouge",
    "sg:classifiers":[
        {
            "category":"Sports & Exercise",
            "subcategory":"Gym",
            "type":"Entertainment"
        }
    ],
    "sg:phone":"+1 225 753 6302",
    "sg:postcode":"70817",
    "sg:province":"LA",
    "sg:tags":[
        "fitness",
        "physical",
        "facility"
    ],
    "wof:name":"Kirk P Simmons",
    "wof:placetype":"venue"
},
  "geometry": {"coordinates":[-90.984185,30.350291],"type":"Point"}
}