{
  "type": "Feature",
  "properties": {
    "addr:full":"69 Lisa Ave Kenner LA 70065",
    "addr:housenumber":"69",
    "addr:postcode":"70065",
    "addr:street":"Lisa Ave",
    "iso:country":"US",
    "sg:address":"69 Lisa Ave",
    "sg:city":"Kenner",
    "sg:classifiers":[
        {
            "category":"Insurance",
            "subcategory":"Insurance Agent",
            "type":"Services"
        }
    ],
    "sg:phone":"+1 504 443 6624",
    "sg:postcode":"70065",
    "sg:province":"LA",
    "wof:name":"Lewis Burney Assoc Inc",
    "wof:placetype":"venue"
},
  "geometry": {"coordinates":[-90.23048,30.024544],"type":"Point"}
}