{
  "type": "Feature",
  "properties": {
    "addr:full":"616 Jefferson Hts Ave New Orleans LA 70121",
    "addr:housenumber":"616",
    "addr:postcode":"70121",
    "addr:street":"Jefferson Hts Ave",
    "iso:country":"US",
    "sg:address":"616 Jefferson Hts Ave",
    "sg:city":"New Orleans",
    "sg:classifiers":[
        {
            "category":"Retail",
            "subcategory":"Veterinary Services",
            "type":"Services"
        }
    ],
    "sg:phone":"+1 504 734 7946",
    "sg:postcode":"70121",
    "sg:province":"LA",
    "sg:tags":[
        "specialty"
    ],
    "wof:name":"Home Vetenary Service",
    "wof:placetype":"venue"
},
  "geometry": {"coordinates":[-90.177176,29.961662],"type":"Point"}
}