{
  "type": "Feature",
  "properties": {
    "iso:country":"US",
    "sg:address":"8805 Line Ave",
    "sg:city":"Shreveport",
    "sg:classifiers":[
        {
            "category":"Professional",
            "subcategory":"Lawyer & Legal Services",
            "type":"Services"
        }
    ],
    "sg:phone":"+1 318 865 6688",
    "sg:postcode":"71106",
    "sg:province":"LA",
    "sg:tags":[
        "attorney"
    ],
    "wof:name":"Kenneth C Thomas",
    "wof:placetype":"venue"
},
  "geometry": {"coordinates":[-93.736141,32.419004],"type":"Point"}
}