{
  "type": "Feature",
  "properties": {
    "iso:country":"US",
    "sg:address":"1512 Royal Ave",
    "sg:city":"Monroe",
    "sg:classifiers":[
        {
            "category":"Health Services",
            "subcategory":"Doctor",
            "type":"Services"
        }
    ],
    "sg:phone":"+1 318 387 5400",
    "sg:postcode":"71201",
    "sg:province":"LA",
    "sg:tags":[
        "dentist"
    ],
    "wof:name":"Gregg C Tidwell DDS",
    "wof:placetype":"venue"
},
  "geometry": {"coordinates":[-92.111041,32.519451],"type":"Point"}
}