{
  "type": "Feature",
  "properties": {
    "iso:country":"US",
    "sg:address":"4200 S Vienna St",
    "sg:city":"Ruston",
    "sg:classifiers":[
        {
            "category":"Retail",
            "subcategory":"Auto Repair",
            "type":"Services"
        }
    ],
    "sg:phone":"+1 318 251 2237",
    "sg:postcode":"71270",
    "sg:province":"LA",
    "sg:tags":[
        "repairing",
        "automobile"
    ],
    "wof:name":"Ace Automotive",
    "wof:placetype":"venue"
},
  "geometry": {"coordinates":[-92.64289599999999,32.484747],"type":"Point"}
}