{
  "type": "Feature",
  "properties": {
    "addr:full":"2506 N Magnolia Dr Baker LA 70714",
    "addr:housenumber":"2506",
    "addr:postcode":"70714",
    "addr:street":"N Magnolia Dr",
    "iso:country":"US",
    "sg:address":"2506 N Magnolia Dr",
    "sg:city":"Baker",
    "sg:classifiers":[
        {
            "category":"Building & Trades",
            "subcategory":"Landscaping Services",
            "type":"Services"
        }
    ],
    "sg:phone":"+1 225 774 7075",
    "sg:postcode":"70714",
    "sg:province":"LA",
    "sg:tags":[
        "landscape"
    ],
    "wof:name":"Overhultz Landscape Manag",
    "wof:placetype":"venue"
},
  "geometry": {"coordinates":[-91.175937,30.585673],"type":"Point"}
}