{
  "type": "Feature",
  "properties": {
    "addr:full":"9701 Hammond St New Orleans LA 70127",
    "addr:housenumber":"9701",
    "addr:postcode":"70127",
    "addr:street":"Hammond St",
    "iso:country":"US",
    "sg:address":"9701 Hammond St",
    "sg:city":"New Orleans",
    "sg:classifiers":[
        {
            "category":"Organizations",
            "subcategory":"Religious Organization",
            "type":"Services"
        }
    ],
    "sg:phone":"+1 504 242 8669",
    "sg:postcode":"70127",
    "sg:province":"LA",
    "sg:tags":[
        "church"
    ],
    "wof:name":"Resurrection of Our Lord Church",
    "wof:placetype":"venue"
},
  "geometry": {"coordinates":[-89.973297,30.022699],"type":"Point"}
}