{
  "type": "Feature",
  "properties": {
    "addr:full":"5700 Westbank Expy Marrero LA 70072",
    "addr:housenumber":"5700",
    "addr:postcode":"70072",
    "addr:street":"Westbank Expy Marrero",
    "iso:country":"US",
    "sg:address":"5700 Westbank Expy",
    "sg:city":"Marrero",
    "sg:classifiers":[
        {
            "category":"Personal",
            "subcategory":"Barber",
            "type":"Services"
        }
    ],
    "sg:phone":"+1 504 347 8618",
    "sg:postcode":"70072",
    "sg:province":"LA",
    "sg:tags":[
        "shop"
    ],
    "wof:name":"Daggs Barber Shop",
    "wof:placetype":"venue"
},
  "geometry": {"coordinates":[-90.108329,29.894295],"type":"Point"}
}