{
  "type": "Feature",
  "properties": {
    "addr:full":"211 Irby Rd Lafayette LA 70507",
    "addr:housenumber":"211",
    "addr:postcode":"70507",
    "addr:street":"Irby Rd",
    "iso:country":"US",
    "sg:address":"211 Irby Rd",
    "sg:city":"Lafayette",
    "sg:classifiers":[
        {
            "category":"Retail",
            "subcategory":"Repair Shop",
            "type":"Services"
        }
    ],
    "sg:phone":"+1 337 269 0862",
    "sg:postcode":"70507",
    "sg:province":"LA",
    "wof:name":"Fiberworks",
    "wof:placetype":"venue"
},
  "geometry": {"coordinates":[-91.99038899999999,30.296817],"type":"Point"}
}