{
  "type": "Feature",
  "properties": {
    "iso:country":"US",
    "sg:address":"3978 Downman Rd",
    "sg:city":"New Orleans",
    "sg:classifiers":[
        {
            "category":"Retail",
            "subcategory":"Repair Shop",
            "type":"Services"
        }
    ],
    "sg:phone":"+1 504 241 2722",
    "sg:postcode":"70126",
    "sg:province":"LA",
    "sg:tags":[
        "repairing",
        "lawn",
        "mower"
    ],
    "wof:name":"Gentilly Lawnmower Sales & Svc",
    "wof:placetype":"venue"
},
  "geometry": {"coordinates":[-90.02101500000001,30.010421],"type":"Point"}
}