{
  "type": "Feature",
  "properties": {
    "iso:country":"US",
    "sg:address":"329 Lawrence St",
    "sg:city":"Lake Charles",
    "sg:classifiers":[
        {
            "category":"Restaurant",
            "type":"Food & Drink"
        }
    ],
    "sg:phone":"+1 337 436 4344",
    "sg:postcode":"70601",
    "sg:province":"LA",
    "wof:name":"Sylvia's Cafe Royale",
    "wof:placetype":"venue"
},
  "geometry": {"coordinates":[-93.215796,30.234252],"type":"Point"}
}