{
  "type": "Feature",
  "properties": {
    "iso:country":"US",
    "sg:address":"6621 Saint Claude Ave",
    "sg:city":"Arabi",
    "sg:classifiers":[
        {
            "category":"Shopping",
            "subcategory":"Pawn Shop",
            "type":"Retail Goods"
        }
    ],
    "sg:phone":"+1 504 304 3905",
    "sg:postcode":"70032",
    "sg:province":"LA",
    "wof:name":"Riverside Pawn & Jewelry Inc",
    "wof:placetype":"venue"
},
  "geometry": {"coordinates":[-90.00536200000001,29.958051],"type":"Point"}
}