{
  "type": "Feature",
  "properties": {
    "iso:country":"US",
    "sg:address":"147 Dan St",
    "sg:city":"Cameron",
    "sg:classifiers":[
        {
            "category":"Building & Trades",
            "subcategory":"Plumbing",
            "type":"Services"
        }
    ],
    "sg:phone":"+1 337 775 5385",
    "sg:postcode":"70631",
    "sg:province":"LA",
    "sg:tags":[
        "conditioning",
        "air",
        "system",
        "contractor"
    ],
    "wof:name":"Duhon Refrigeration",
    "wof:placetype":"venue"
},
  "geometry": {"coordinates":[-93.319383,29.796287],"type":"Point"}
}