{
  "type": "Feature",
  "properties": {
    "addr:full":"304 Pine St Monroe LA 71201",
    "addr:housenumber":"304",
    "addr:postcode":"71201",
    "addr:street":"Pine St",
    "iso:country":"US",
    "sg:address":"304 Pine St",
    "sg:city":"Monroe",
    "sg:classifiers":[
        {
            "category":"Professional",
            "subcategory":"Art Services",
            "type":"Services"
        }
    ],
    "sg:phone":"+1 318 322 4821",
    "sg:postcode":"71201",
    "sg:province":"LA",
    "sg:tags":[
        "photographer"
    ],
    "wof:name":"Jack Tarver Photography",
    "wof:placetype":"venue"
},
  "geometry": {"coordinates":[-92.11832800000001,32.507674],"type":"Point"}
}