{
  "type": "Feature",
  "properties": {
    "iso:country":"US",
    "sg:address":"116 Cox Ferry Rd",
    "sg:city":"Farmerville",
    "sg:classifiers":[
        {
            "category":"Recreation",
            "type":"Entertainment"
        }
    ],
    "sg:phone":"+1 318 368 6165",
    "sg:postcode":"71241",
    "sg:province":"LA",
    "sg:tags":[
        "center"
    ],
    "wof:name":"Farmerville Recreation Ctr",
    "wof:placetype":"venue"
},
  "geometry": {"coordinates":[-92.402956,32.762247],"type":"Point"}
}