{
  "type": "Feature",
  "properties": {
    "iso:country":"US",
    "sg:address":"13980 W Main St",
    "sg:city":"Cut Off",
    "sg:classifiers":[
        {
            "category":"Food & Beverages",
            "subcategory":"Groceries & Convenience Stores",
            "type":"Retail Goods"
        }
    ],
    "sg:phone":"+1 985 693 4858",
    "sg:postcode":"70345",
    "sg:province":"LA",
    "sg:tags":[
        "grocer"
    ],
    "wof:name":"Rouse's Supermarket",
    "wof:placetype":"venue"
},
  "geometry": {"coordinates":[-90.355577,29.55932],"type":"Point"}
}