{
  "type": "Feature",
  "properties": {
    "iso:country":"US",
    "sg:address":"1500 S Jefferson Davis Pkwy",
    "sg:city":"New Orleans",
    "sg:classifiers":[
        {
            "category":"Organizations",
            "subcategory":"Professional Association",
            "type":"Services"
        }
    ],
    "sg:phone":"+1 504 827 1570",
    "sg:postcode":"70125",
    "sg:province":"LA",
    "wof:name":"Louisiana Associated Contrs",
    "wof:placetype":"venue"
},
  "geometry": {"coordinates":[-90.105941,29.955147],"type":"Point"}
}