{
  "type": "Feature",
  "properties": {
    "iso:country":"US",
    "sg:address":"4715 Jasper Rd",
    "sg:city":"New Iberia",
    "sg:classifiers":[
        {
            "category":"Manufacturing",
            "subcategory":"Tools & Machinery",
            "type":"Manufacturing & Wholesale Goods"
        }
    ],
    "sg:phone":"+1 337 364 9753",
    "sg:postcode":"70560",
    "sg:province":"LA",
    "sg:tags":[
        "industrial",
        "mfg"
    ],
    "wof:name":"Reeds Accuracy & Machining",
    "wof:placetype":"venue"
},
  "geometry": {"coordinates":[-91.887309,29.981798],"type":"Point"}
}