{
  "type": "Feature",
  "properties": {
    "iso:country":"US",
    "sg:address":"310 N Cedar St",
    "sg:city":"Lockport",
    "sg:classifiers":[
        {
            "category":"Shopping",
            "subcategory":"Gifts & Souvenirs",
            "type":"Retail Goods"
        }
    ],
    "sg:phone":"+1 985 532 8303",
    "sg:postcode":"70374",
    "sg:province":"LA",
    "sg:tags":[
        "party",
        "supply"
    ],
    "wof:name":"Jerry's Fun-Time Rentals",
    "wof:placetype":"venue"
},
  "geometry": {"coordinates":[-90.546481,29.649157],"type":"Point"}
}