{
  "type": "Feature",
  "properties": {
    "iso:country":"US",
    "sg:address":"2006 Perry St",
    "sg:city":"Vinton",
    "sg:classifiers":[
        {
            "category":"Restaurant",
            "type":"Food & Drink"
        }
    ],
    "sg:menulink":"http://www.allmenus.com/la/sulphur/132094-subway/menu/",
    "sg:phone":"+1 337 589 0032",
    "sg:postcode":"70668",
    "sg:province":"LA",
    "sg:tags":[
        "american",
        "sandwich"
    ],
    "wof:name":"Subway",
    "wof:placetype":"venue"
},
  "geometry": {"coordinates":[-93.588784,30.183606],"type":"Point"}
}