{
  "type": "Feature",
  "properties": {
    "iso:country":"US",
    "sg:address":"4282 Pro St",
    "sg:city":"Shreveport",
    "sg:classifiers":[
        {
            "category":"Home & Garden",
            "subcategory":"Building Materials",
            "type":"Retail Goods"
        },
        {
            "category":"Building & Trades",
            "subcategory":"Construction",
            "type":"Services"
        },
        {
            "category":"Military Area",
            "subcategory":"Armory",
            "type":"Public Place"
        }
    ],
    "sg:phone":"+1 318 635 7094",
    "sg:postcode":"71109",
    "sg:province":"LA",
    "sg:tags":[
        "repair",
        "fence-sales",
        "fence",
        "contractor"
    ],
    "wof:name":"Shreve Fence Co",
    "wof:placetype":"venue"
},
  "geometry": {"coordinates":[-93.813503,32.469296],"type":"Point"}
}