{
  "type": "Feature",
  "properties": {
    "iso:country":"US",
    "sg:address":"229 Saint de Porres St",
    "sg:city":"Broussard",
    "sg:classifiers":[
        {
            "category":"Social Services",
            "subcategory":"Child Care",
            "type":"Services"
        }
    ],
    "sg:phone":"+1 337 837 4457",
    "sg:postcode":"70518",
    "sg:province":"LA",
    "wof:name":"Rosa's Child Development",
    "wof:placetype":"venue"
},
  "geometry": {"coordinates":[-91.95798499999999,30.142488],"type":"Point"}
}