{
  "type": "Feature",
  "properties": {
    "addr:full":"1625 Centenary Blvd Shreveport LA 71101",
    "addr:housenumber":"1625",
    "addr:postcode":"71101",
    "addr:street":"Centenary Blvd",
    "iso:country":"US",
    "sg:address":"1625 Centenary Blvd",
    "sg:city":"Shreveport",
    "sg:classifiers":[
        {
            "category":"Real Estate",
            "subcategory":"Real Estate Operator",
            "type":"Services"
        }
    ],
    "sg:phone":"+1 318 226 1371",
    "sg:postcode":"71101",
    "sg:province":"LA",
    "sg:tags":[
        "apartment"
    ],
    "wof:name":"Centenary Gardens Apartments",
    "wof:placetype":"venue"
},
  "geometry": {"coordinates":[-93.733124,32.495733],"type":"Point"}
}