{
  "type": "Feature",
  "properties": {
    "addr:full":"10132 Oakline Dr Baton Rouge LA 70809",
    "addr:housenumber":"10132",
    "addr:postcode":"70809",
    "addr:street":"Oakline Dr",
    "iso:country":"US",
    "sg:address":"10132 Oakline Dr",
    "sg:city":"Baton Rouge",
    "sg:classifiers":[
        {
            "category":"Personal",
            "type":"Services"
        }
    ],
    "sg:phone":"+1 225 368 8463",
    "sg:postcode":"70809",
    "sg:province":"LA",
    "sg:tags":[
        "miscellaneous",
        "errand"
    ],
    "wof:name":"Professional Assistant",
    "wof:placetype":"venue"
},
  "geometry": {"coordinates":[-91.06698900000001,30.398139],"type":"Point"}
}