{
  "type": "Feature",
  "properties": {
    "iso:country":"US",
    "sg:address":"11562 Cedar Park Ave",
    "sg:city":"Baton Rouge",
    "sg:classifiers":[
        {
            "category":"Building & Trades",
            "subcategory":"Construction",
            "type":"Services"
        }
    ],
    "sg:phone":"+1 225 754 5700",
    "sg:postcode":"70809",
    "sg:province":"LA",
    "sg:tags":[
        "painter"
    ],
    "wof:name":"Faux Scapes",
    "wof:placetype":"venue"
},
  "geometry": {"coordinates":[-91.05408,30.389231],"type":"Point"}
}