{
  "type": "Feature",
  "properties": {
    "addr:full":"843 Robert Blvd Slidell LA 70458",
    "addr:housenumber":"843",
    "addr:postcode":"70458",
    "addr:street":"Robert Blvd",
    "iso:country":"US",
    "sg:address":"843 Robert Blvd",
    "sg:city":"Slidell",
    "sg:classifiers":[
        {
            "category":"Shopping",
            "subcategory":"Used Merchandise",
            "type":"Retail Goods"
        }
    ],
    "sg:phone":"+1 985 641 1100",
    "sg:postcode":"70458",
    "sg:province":"LA",
    "sg:tags":[
        "shop",
        "consignment"
    ],
    "wof:name":"Real Resale & Closeout",
    "wof:placetype":"venue"
},
  "geometry": {"coordinates":[-89.766423,30.29385],"type":"Point"}
}