{
  "type": "Feature",
  "properties": {
    "iso:country":"US",
    "sg:address":"1405 W Pinhook Rd",
    "sg:city":"Lafayette",
    "sg:classifiers":[
        {
            "category":"Professional",
            "subcategory":"Lawyer & Legal Services",
            "type":"Services"
        }
    ],
    "sg:phone":"+1 337 234 0099",
    "sg:postcode":"70503",
    "sg:province":"LA",
    "sg:tags":[
        "attorney"
    ],
    "wof:name":"Stan Gauthier II",
    "wof:placetype":"venue"
},
  "geometry": {"coordinates":[-92.016396,30.198402],"type":"Point"}
}