{
  "type": "Feature",
  "properties": {
    "addr:full":"4611 Reynes St New Orleans LA 70126",
    "addr:housenumber":"4611",
    "addr:postcode":"70126",
    "addr:street":"Reynes St",
    "iso:country":"US",
    "sg:address":"4611 Reynes St",
    "sg:city":"New Orleans",
    "sg:classifiers":[
        {
            "category":"Building & Trades",
            "subcategory":"Landscaping Services",
            "type":"Services"
        }
    ],
    "sg:phone":"+1 504 246 8247",
    "sg:postcode":"70126",
    "sg:province":"LA",
    "sg:tags":[
        "lawn",
        "maintenance",
        "grounds"
    ],
    "wof:name":"Cloud Lawn Svc",
    "wof:placetype":"venue"
},
  "geometry": {"coordinates":[-90.011329,30.018444],"type":"Point"}
}