{
  "type": "Feature",
  "properties": {
    "iso:country":"US",
    "sg:address":"1308 Woodcliff Dr",
    "sg:city":"Baton Rouge",
    "sg:classifiers":[
        {
            "category":"Organizations",
            "subcategory":"Community Association",
            "type":"Services"
        }
    ],
    "sg:phone":"+1 225 275 7912",
    "sg:postcode":"70815",
    "sg:province":"LA",
    "wof:name":"Redstick Kiwanis",
    "wof:placetype":"venue"
},
  "geometry": {"coordinates":[-91.039258,30.444605],"type":"Point"}
}