{
  "type": "Feature",
  "properties": {
    "iso:country":"US",
    "sg:address":"730 North Blvd",
    "sg:city":"Baton Rouge",
    "sg:classifiers":[
        {
            "category":"Travel",
            "subcategory":"Travel Agent",
            "type":"Entertainment"
        }
    ],
    "sg:phone":"+1 225 383 1825",
    "sg:postcode":"70802",
    "sg:province":"LA",
    "sg:tags":[
        "information",
        "tourist"
    ],
    "sg:website":"www.visitbatonrouge.com",
    "wof:name":"Baton Rouge Area Convention",
    "wof:placetype":"venue"
},
  "geometry": {"coordinates":[-91.183036,30.447007],"type":"Point"}
}