{
  "type": "Feature",
  "properties": {
    "addr:full":"69173 Hwy 59 Mandeville LA 70471",
    "addr:housenumber":"69173",
    "addr:postcode":"70471",
    "addr:street":"Hwy 59",
    "iso:country":"US",
    "sg:address":"69173 Hwy 59",
    "sg:city":"Mandeville",
    "sg:classifiers":[
        {
            "category":"Professional",
            "type":"Services"
        }
    ],
    "sg:phone":"+1 985 893 9221",
    "sg:postcode":"70471",
    "sg:province":"LA",
    "sg:tags":[
        "establishment"
    ],
    "wof:name":"Sonarwire Inc",
    "wof:placetype":"venue"
},
  "geometry": {"coordinates":[-90.041681,30.437976],"type":"Point"}
}