{
  "type": "Feature",
  "properties": {
    "addr:full":"1325 E Prien Lake Rd Lake Charles LA 70601",
    "addr:housenumber":"1325",
    "addr:postcode":"70601",
    "addr:street":"E Prien Lake Rd",
    "iso:country":"US",
    "sg:address":"1325 E Prien Lake Rd",
    "sg:city":"Lake Charles",
    "sg:classifiers":[
        {
            "category":"Retail",
            "subcategory":"Auto Repair",
            "type":"Services"
        }
    ],
    "sg:phone":"+1 337 478 0744",
    "sg:postcode":"70601",
    "sg:province":"LA",
    "sg:tags":[
        "van",
        "conversion",
        "truck",
        "accessory"
    ],
    "wof:name":"Access Vans-Louisiana Lake",
    "wof:placetype":"venue"
},
  "geometry": {"coordinates":[-93.201795,30.198327],"type":"Point"}
}