{
  "type": "Feature",
  "properties": {
    "addr:full":"648 Ave G Westwego LA 70094",
    "addr:housenumber":"648",
    "addr:postcode":"70094",
    "addr:street":"Ave G Westwego",
    "iso:country":"US",
    "sg:address":"648 Ave G",
    "sg:city":"Westwego",
    "sg:classifiers":[
        {
            "category":"Food & Beverages",
            "subcategory":"Bakery",
            "type":"Retail Goods"
        }
    ],
    "sg:phone":"+1 504 348 4614",
    "sg:postcode":"70094",
    "sg:province":"LA",
    "wof:name":"Special Cakes By Olite",
    "wof:placetype":"venue"
},
  "geometry": {"coordinates":[-90.141649,29.904246],"type":"Point"}
}